{
  "identify": "ILD-99-訴緝-9-20100512-1",
  "court": {
    "name": "臺灣宜蘭地方法院",
    "code": "ILD"
  },
  "division": {
    "name": "刑事",
    "code": "M"
  },
  "year": 99,
  "word": "訴緝",
  "number": "9",
  "jcheck": "1",
  "reason": "偽造文書等",
  "content": "臺灣宜蘭地方法院刑事判決               99年度訴緝字第9號\n公  訴  人  臺灣宜蘭地方法院檢察署檢察官\n被      告  甲○○\n上列被告因偽造文書等案件，經檢察官提起公訴（97年度偵字第\n3908號、98年度偵字第138號）及追加起訴（98年度偵字第3081\n號），本院判決如下：\n    主  文\n甲○○共同犯毀越門扇竊盜罪，累犯，處有期徒刑柒月；又共同\n犯踰越門扇夜間侵入住宅竊盜罪，累犯，處有期徒刑柒月；又共\n同犯踰越門扇竊盜罪，累犯，處有期徒刑柒月；又犯結夥踰越門\n扇竊盜罪，累犯，處有期徒刑柒月；又共同犯侵入住宅罪，累犯\n，處有期徒刑月；又共同犯行使偽造私文書罪，累犯，處有期\n徒刑陸月。應執行有期徒刑貳年肆月。\n其餘被訴侵入林莉情、林敬人住宅部分公訴不受理。\n    事  實\n一、甲○○前因竊盜及違反槍砲彈藥刀械管制條例案件，經臺灣\n    高等法院於民國94年6月27日，以94年度上訴字第846號刑事\n    判決分別判處有期徒刑3年4月、4月確定；另因毒品案件，\n    經本院於94年2月14日，以94年度宜簡字第7號刑事判決判處\n    有期徒刑4月確定；再因竊盜案件，經臺灣臺北地方法院於\n    95年3月27日，以94年度易字第878號刑事判決判處有期徒刑\n    1年6月確定，上開有期徒刑嗣經臺灣臺北地方法院以96年度\n    聲減字第2716號裁定減刑後定應執行刑有期徒刑3年11月，\n    於97年2月5日假釋出監，於97年5月6日假釋期滿，以已執行\n    論。詎甲○○猶不知悔改，先後與張耀宗（業經本院以98年\n    度訴字第308號、98年度易字第397號刑事案件審結）基於意\n    圖為自己不法所有之犯意聯絡，而為下列行為：\n  (一)於97年6月27日日間某時，共同至宜蘭縣五結鄉○○路○段12\n    7號林莉情住處，敲破林莉情住處窗戶後，踰越窗戶侵入林\n    莉情住宅內，竊取林莉情所有或其管領之金飾、金手鍊共價\n    值約新台幣（下同）2萬多元及集郵冊1本、郵局存摺、林莉\n    情之子林冠嶧之普通小型車駕照、重型機車駕照、普通重型\n    機車駕照、健保卡、身分證、技術士證各1張。\n  (二)於97年7月13日晚間7時許起至同日晚間9時10分止之夜間某\n    時，共同至宜蘭縣五結鄉○○路○段139巷6號常琪住處，踰\n    越2樓陽台氣窗侵入常琪住處後，竊取常琪所有或其管領之\n    金戒指6只、金項鍊6條、金手鐲1對、滿月金飾3盒、綠色皮\n    製皮包1個，皮包內之現金2,200元，合作金庫存摺4本、臺\n    灣土地銀行存摺1本、中國信託商業銀行存摺1本、蘇澳郵局\n    存摺1本、房屋地契證明書。\n  (三)於97年7月23日上午8時40分許至同日下午3時許間某時，共\n    同至宜蘭縣宜蘭市○○路○段166巷13號簡大程住處，將1樓\n    廁所窗戶拆下，踰越窗戶侵入住宅竊取簡大程所有電腦2組\n    （含液晶螢幕）、華南商業銀行、中國信託商業銀行、永豐\n    銀行（帳號00000000000000號）、第一商業銀行存摺各1本\n    、郵局存摺2本、富邦信用卡1張、身分證1張、印章2枚（其\n    中1枚為永豐銀行印鑑章）、銀質藍寶石項鍊1條、藍寶石耳\n    環1對、數量不詳之外幣鈔票、硬幣等。於得手後，甲○○\n    、張耀宗見簡大程前開永豐銀行帳戶內尚有131,389元，復\n    共同意圖為自己不法之所有，並基於偽造私文書之犯意聯絡\n    ，共同至宜蘭縣宜蘭市○○路○段33號永豐銀行，先由張耀\n    宗進入銀行拿取銀行取款憑條，再返回交由停放於銀行外自\n    用小客車內等候之甲○○，由甲○○在該取款憑條填載簡大\n    程前開永豐銀行帳戶帳號、取款日期為97年7月27日、取款\n    金額為13萬元、並在存戶簽章欄上蓋用其等所竊取之簡大程\n    印章，用以偽造簡大程向永豐銀行取款之私文書。於97年7\n    月23日上午11時25分許，由張耀宗持該偽造之取款憑條，向\n    不知情之永豐銀行行員行使，致使不知情之永豐銀行行員陷\n    於錯誤，而支付13萬元予張耀宗，足以生損害於簡大程及永\n    豐銀行。\n  (四)張耀宗、甲○○再與陳俊成（所涉竊盜犯行部分，由臺灣桃\n    園地方法院檢察署檢察官以98年度偵緝字第866號案件提起\n    公訴，現由臺灣桃園地方法院以98年度審易字1429號案件審\n    理；另冒用李孟融名義應訊涉犯偽造文書犯行部分，業經臺\n    灣桃園地方法院檢察署檢察官以98年度偵緝字第393號提起\n    公訴，及由臺灣桃園地方法院檢察署檢察官以98年度偵字第\n    9319號移請臺灣桃園地方法院併案審理）共同基於意圖為自\n    己不法所有之犯意聯絡，於97年8月21日下午5時許前日間某\n    時，至宜蘭縣宜蘭市○○○路347巷15號林敬人住處，踰越\n    林敬人住處後門上方窗戶，進入住宅竊取林敬人所有或管領\n    之集郵冊10本、郵局、銀行存摺共6本、古董鋼筆60多支、\n    鋼質萬用刀1把（上刻有林敬人）、打火機3只、林敬人之妻\n    印章3枚及金飾價值約3千多元。\n二、查獲情形：\n  (一)於犯罪事實一(二)後，嗣經警到場，在常琪住處2樓陽台氣窗\n    採獲數枚指紋經送鑑驗比對，與刑事警察局檔存張耀宗指紋\n    卡之右中指、右食指、右環指指紋相符。\n  (二)於犯罪事實一(三)後，為警在簡大程住處廁所門框、氣窗及後\n    陽台鋁窗上採取指紋送鑑定，其中編號1至5採取之指紋送檢\n    驗比對確認結果，與刑事警察局檔存張耀宗指紋卡之左中指\n    、左環指、左食指、右食指指紋相符；另自前開偽造之取款\n    憑條上採取之指紋1枚，經送鑑定比對，確認結果，與刑事\n    警察局檔存甲○○指紋卡之左食指指紋相符而查獲。\n  (三)於97年9月3日晚間6時40分許，甲○○駕駛車牌號碼9338-RF\n    自用小客車載陳俊成、張耀宗行經桃園縣楊梅鎮○○路○段\n    107巷77弄37號前為警攔檢9338-RF自用小客車時，經甲○○\n    同意搜索，於甲○○之手提包內起出林敬人所有遭竊之刻有\n    林敬人名字之鋼質萬用刀1把；另於97年9月4日凌晨12時5分\n    許，為警帶同張耀宗至其臺北縣中和市○○路177巷5號6樓\n    住處，經張耀宗同意執行搜索，當場起出林冠嶧所有之普通\n    小型車駕照、重型機車駕照、普通重型機車駕照、健保卡、\n    身分證、技術士證共6張。\n三、案經臺北縣政府警察局汐止分局、宜蘭縣政府警察局宜蘭分\n    局、宜蘭縣政府警察局羅東分局報請臺灣宜蘭地方法院檢察\n    署檢察官偵查起訴。\n    理  由\n甲、有罪部分：\n一、訊據被告於本院審理中，對於前開犯罪事實一之竊盜、侵入\n    住宅、行使偽造私文書、詐欺取財犯行均坦承不諱。經查：\n  (一)就前開犯罪事實一(一)部分，業據被害人林莉情於警訊中指述\n    其住處遭竊之情形（參見97年度偵字第3908號卷第9、10頁\n    97年9月10日警訊筆錄）。再臺北縣政府警察局汐止分局員\n    警於97年9月4日凌晨12時5分許，在同案共犯張耀宗位於臺\n    北縣中和市○○路177巷5號6樓住處搜索，扣得林莉情之子\n    林冠嶧之普通小型車駕照、重型機車駕照、普通重型機車駕\n    照、健保卡、身分證、技術士證等物，有臺北縣政府警察局\n    汐止分局搜索扣押筆錄、扣押物品目錄表、被害人林莉情出\n    具之贓物認領保管單，及林冠嶧證件影本等件在卷可佐（97\n    年度偵字第3908號卷第37頁、第51至53頁、第55頁）。\n  (二)就前開犯罪事實一(二)部分，同案共犯張耀宗於本院審理中自\n    承在卷，並據被害人常琪於警訊中指述其住處遭竊之情形（\n    警羅偵字第00983100040號卷第1、2頁97年7月13日警訊筆錄\n    ），復有現場照片10幀在卷可佐（警羅偵字第00983100040\n    號卷第7至11頁）。再員警於被害人常琪住處2樓陽台氣窗採\n    獲數枚指紋送鑑定之結果，核與同案共犯張耀宗之右中指、\n    右食指、右環指指紋相符，有內政部警政署97年8月1日刑紋\n    字第0970111740號鑑驗書1份附卷可證（警羅偵字第0098310\n    0040號卷第5、6頁）。\n  (三)就前開犯罪事實一(三)部分，同案共犯張耀宗於本院審理中自\n    承在卷，並據被害人簡大程於警、偵訊中證述在卷（參見警\n    蘭偵字第0972104864號卷第1至3頁97年7月23日警訊筆錄、9\n    7年7月29日警訊筆錄、98年度偵字第138號卷第28、29頁98\n    年5月20日偵訊筆錄），並有現場照片4幀在卷可佐（警蘭偵\n    字第0972104864號卷第26、27頁）。而員警在被害人簡大程\n    住處廁所門框、氣窗及後陽台鋁窗上採取指紋送鑑定之結果\n    ，其中編號1至5採取之指紋輸入指紋電腦比對確認結果，與\n    同案共犯張耀宗之左中指、左環指、左食指、右食指指紋相\n    符，有內政部警政署刑事警察局97年8月1日刑紋字第097011\n    1438號鑑驗書1份附卷可證（警蘭偵字第0972104864號卷第8\n    、9頁）。而同案共犯張耀宗於97年7月23日上午11時25分許\n    ，持蓋用被害人簡大程印章之取款憑條，至永豐銀行冒充被\n    害人簡大程提款，致使銀行行員陷於錯誤，而交付13萬元，\n    亦有永豐銀行監視器錄影畫面翻拍照片2幀，及取款憑條照\n    片2幀附卷可佐（警蘭偵字第0972104864號卷第28、29頁）\n    。而上開取款憑條上採取之指紋1枚經送鑑定，與被告指紋\n    卡之左食指指紋相符，有內政部警政署刑事警察局97年8月5\n    日刑紋字第0970114803號鑑驗書1份附卷可證（警蘭偵字第\n    0972104864號卷第10、11頁）。\n  (四)就前開犯罪事實一(四)部分，同案共犯張耀宗於審理中自承在\n    卷，並據被害人林敬人就其住處遭竊情節，於警訊中指述在\n    卷（參見97年度偵字第3908號卷第11、12頁97年9月15日警\n    訊筆錄），且同案共犯陳俊成於偵查中，亦自承與被告及同\n    案共犯張耀宗共同行竊之犯行（參見97年度偵字第3908號卷\n    第312至314頁98年5月12日偵訊筆錄）。再於97年9月3日下\n    午6時40分許，被告駕駛車牌號碼9338-RF自用小客車行經桃\n    園縣楊梅鎮○○路○段107巷77弄37號前為警攔檢，自其手提\n    包內起出林敬人所有遭竊之刻有林敬人名字之鋼質萬用刀1\n    把，有臺北縣政府警察局汐止分局搜索扣押筆錄、扣押物品\n    目錄表（97年度偵字第3908號卷第43至49頁），及被害人林\n    敬人出具之贓物認領保管單1紙（97年度偵字第3908號卷第\n    39頁）附卷可佐。\n  (五)綜上所述，本件事證明確，被告前開竊盜、侵入住宅、行使\n    偽造私文書、詐欺取財犯行堪以認定，應依法論科。\n二、核被告關於犯罪事實一(一)所為，係犯刑法第321條第1項第2\n    款毀越門扇竊盜罪；關於犯罪事實一(二)所為，係犯刑法第\n    321條第1項第1款、第2款於夜間踰越門扇侵入住宅竊盜罪；\n    關於犯罪事實一(三)所為，係犯刑法第321條第1項第2款踰越\n    門扇竊盜罪、第306條第1項侵入住宅罪、第216條、第210條\n    行使偽造私文書罪、第339條第1項詐欺取財罪；關於犯罪事\n    實一(四)所為，係犯刑法第321條第1項第2款、第4款結夥三人\n    以上踰越門扇竊盜罪。被告就前開犯罪事實一(三)中，冒用被\n    害人簡大程名義行使偽造之取款憑條，以此詐騙手法致使銀\n    行行員陷於錯誤，因而交付財物，係以一詐騙行為而觸犯上\n    開行使偽造私文書、詐欺取財2罪，為想像競合犯，應從一\n    重依行使偽造私文書罪處斷。被告就犯罪事實一(一)、(二)、(三)\n    之竊盜、侵入住宅、行使偽造私文書犯行，與張耀宗有犯意\n    之聯絡及行為之分擔，另關於犯罪事實一(四)之竊盜犯行，與\n    張耀宗、陳俊成有犯意之聯絡及行為之分擔，為共同正犯。\n    被告所犯上開竊盜罪4罪、侵入住宅罪1罪、行使偽造私文書\n    罪1罪，犯意各別，行為互殊，應予分論併罰。查被告前因\n    竊盜及違反槍砲彈藥刀械管制條例案件，經臺灣高等法院以\n    94年度上訴字第846號刑事判決分別判處有期徒刑3年4月、4\n    月確定，另因毒品案件，經本院以94年度宜簡字第7號刑事\n    判決判處有期徒刑4月確定，再因竊盜案件，經臺灣臺北地\n    方法院以94年度易字第878號刑事判決判處有期徒刑1年6月\n    確定，上開有期徒刑嗣經臺灣臺北地方法院以96年度聲減字\n    第2716號裁定減刑後定應執行刑有期徒刑3年11月，於97年2\n    月5日假釋出監，於97年5月6日假釋期滿，有卷附臺灣高等\n    法院被告前案紀錄表可按，其受有期徒刑之執行完畢，5年\n    內再犯法定刑有期徒刑以上之上開6罪，為累犯，均依法加\n    重其刑。爰審酌被告不思正途獲取報酬，竟多次竊取侵入他\n    人住處竊取財物，復冒用他人身分至銀行提款，依其犯罪之\n    動機、目的、手段、被害人所受之損失，及被告犯後坦承犯\n    行等一切情狀，就其所犯上開各罪分別量處如主文所示之刑\n    ，並定其應執行刑。\n乙、不受理部分：\n一、公訴意旨另以：(一)被告與同案共犯張耀宗於97年6月27日日\n    間某時，至宜蘭縣五結鄉○○路○段127號被害人林莉情住處\n    ，敲破被害人林莉情住處窗戶後，踰越窗戶侵入被害人林莉\n    情住宅內行竊；(二)被告與同案共犯張耀宗、陳俊成於97年8\n    月21日下午5時許前日間某時，至宜蘭縣宜蘭市○○○路347\n    巷15號被害人林敬人住處，踰越被害人林敬人住處後門上方\n    窗戶，進入住宅竊取被害人林敬人之財物。因認被告此部分\n    另涉有刑法第306條第1項侵入住宅罪嫌。\n二、按「案件有下列情形之一者，應諭知不受理之判決：三、告\n    訴或請求乃論之罪，未經告訴、請求或其告訴、請求經撤回\n    或已逾告訴期間者。」，刑事訴訟法第303條第3款定有明文\n    。檢察官認被告涉犯刑法第306條第1項侵入住宅罪，依同法\n    第308條第1項規定，須告訴乃論。查本件被害人林莉情、林\n    敬人前於警訊中，僅就被告竊盜犯行提起告訴（參見97年度\n    偵字第3908號卷第10頁97年9月10日警訊筆錄、同卷第12頁\n    97年9月15日警訊筆錄），未併就侵入住宅提起告訴，有警\n    訊筆錄在卷可參。檢察官就被告此部分侵入住宅犯行提起公\n    訴，自有未洽，依前開規定，此部分應為不受理判決之諭知\n    。\n據上論斷，應依刑事訴訟法第299條第1項前段、第303條第3款，\n刑法第28條、第216條、第210條、第306條第1項、第321條第1項\n第1款、第2款、第4款、第339條第1項、第55條、第47條第1項、\n第51條第5款，刑法施行法第1條之1第1項、第2項前段，判決如\n主文。\n本案經檢察官陳嘉瑜到庭執行職務\n中    華    民    國    99    年    5     月    12    日\n                  刑事第四庭審判長法  官  林楨森\n                                  法  官  陳雪玉\n                                  法  官  辜漢忠\n以上正本證明與原本無異。\n如不服本判決應於收受送達後十日內向本院提出上訴書狀，並應\n敘述具體理由；其未敘述上述理由者，應於上訴期間屆滿後二十\n日內向本院補提理由書(均須按他造當事人之人數附繕本)「切勿\n逕送上級法院」。\n                                  書記官  林詩綺\n中    華    民    國    99    年    5     月    13    日\n附錄本案論罪科刑法條：\n刑法第210條\n偽造、變造私文書，足以生損害於公眾或他人者，處5年以下有\n期徒刑。\n刑法第216條\n行使第210條至第215條之文書者，依偽造、變造文書或登載不實\n事項或使登載不實事項之規定處斷。\n刑法第306條第1項\n無故侵入他人住宅、建築物或附連圍繞之土地或船艦者，處1年\n以下有期徒刑、拘役或3百元以下罰金。\n刑法第321條第1項\n犯竊盜罪而有左列情形之一者，處6月以上、5年以下有期徒刑：\n一、於夜間侵入住宅或有人居住之建築物、船艦或隱匿其內而犯\n    之者。\n二、毀越門扇、牆垣或其他安全設備而犯之者。\n三、攜帶兇器而犯之者。\n四、結夥三人以上而犯之者。\n五、乘火災、水災或其他災害之際而犯之者。\n六、在車站或埠頭而犯之者。\n刑法第339條第1項\n意圖為自己或第三人不法之所有，以詐術使人將本人或第三人之\n物交付者，處5年以下有期徒刑、拘役或科或併科1千元以下罰金\n。",
  "structure": {
    "main": "甲○○共同犯毀越門扇竊盜罪，累犯，處有期徒刑柒月；又共同\n犯踰越門扇夜間侵入住宅竊盜罪，累犯，處有期徒刑柒月；又共\n同犯踰越門扇竊盜罪，累犯，處有期徒刑柒月；又犯結夥踰越門\n扇竊盜罪，累犯，處有期徒刑柒月；又共同犯侵入住宅罪，累犯\n，處有期徒刑月；又共同犯行使偽造私文書罪，累犯，處有期\n徒刑陸月。應執行有期徒刑貳年肆月。\n其餘被訴侵入林莉情、林敬人住宅部分公訴不受理。",
    "fact": "一、甲○○前因竊盜及違反槍砲彈藥刀械管制條例案件，經臺灣\n    高等法院於民國94年6月27日，以94年度上訴字第846號刑事\n    判決分別判處有期徒刑3年4月、4月確定；另因毒品案件，\n    經本院於94年2月14日，以94年度宜簡字第7號刑事判決判處\n    有期徒刑4月確定；再因竊盜案件，經臺灣臺北地方法院於\n    95年3月27日，以94年度易字第878號刑事判決判處有期徒刑\n    1年6月確定，上開有期徒刑嗣經臺灣臺北地方法院以96年度\n    聲減字第2716號裁定減刑後定應執行刑有期徒刑3年11月，\n    於97年2月5日假釋出監，於97年5月6日假釋期滿，以已執行\n    論。詎甲○○猶不知悔改，先後與張耀宗（業經本院以98年\n    度訴字第308號、98年度易字第397號刑事案件審結）基於意\n    圖為自己不法所有之犯意聯絡，而為下列行為：\n  (一)於97年6月27日日間某時，共同至宜蘭縣五結鄉○○路○段12\n    7號林莉情住處，敲破林莉情住處窗戶後，踰越窗戶侵入林\n    莉情住宅內，竊取林莉情所有或其管領之金飾、金手鍊共價\n    值約新台幣（下同）2萬多元及集郵冊1本、郵局存摺、林莉\n    情之子林冠嶧之普通小型車駕照、重型機車駕照、普通重型\n    機車駕照、健保卡、身分證、技術士證各1張。\n  (二)於97年7月13日晚間7時許起至同日晚間9時10分止之夜間某\n    時，共同至宜蘭縣五結鄉○○路○段139巷6號常琪住處，踰\n    越2樓陽台氣窗侵入常琪住處後，竊取常琪所有或其管領之\n    金戒指6只、金項鍊6條、金手鐲1對、滿月金飾3盒、綠色皮\n    製皮包1個，皮包內之現金2,200元，合作金庫存摺4本、臺\n    灣土地銀行存摺1本、中國信託商業銀行存摺1本、蘇澳郵局\n    存摺1本、房屋地契證明書。\n  (三)於97年7月23日上午8時40分許至同日下午3時許間某時，共\n    同至宜蘭縣宜蘭市○○路○段166巷13號簡大程住處，將1樓\n    廁所窗戶拆下，踰越窗戶侵入住宅竊取簡大程所有電腦2組\n    （含液晶螢幕）、華南商業銀行、中國信託商業銀行、永豐\n    銀行（帳號00000000000000號）、第一商業銀行存摺各1本\n    、郵局存摺2本、富邦信用卡1張、身分證1張、印章2枚（其\n    中1枚為永豐銀行印鑑章）、銀質藍寶石項鍊1條、藍寶石耳\n    環1對、數量不詳之外幣鈔票、硬幣等。於得手後，甲○○\n    、張耀宗見簡大程前開永豐銀行帳戶內尚有131,389元，復\n    共同意圖為自己不法之所有，並基於偽造私文書之犯意聯絡\n    ，共同至宜蘭縣宜蘭市○○路○段33號永豐銀行，先由張耀\n    宗進入銀行拿取銀行取款憑條，再返回交由停放於銀行外自\n    用小客車內等候之甲○○，由甲○○在該取款憑條填載簡大\n    程前開永豐銀行帳戶帳號、取款日期為97年7月27日、取款\n    金額為13萬元、並在存戶簽章欄上蓋用其等所竊取之簡大程\n    印章，用以偽造簡大程向永豐銀行取款之私文書。於97年7\n    月23日上午11時25分許，由張耀宗持該偽造之取款憑條，向\n    不知情之永豐銀行行員行使，致使不知情之永豐銀行行員陷\n    於錯誤，而支付13萬元予張耀宗，足以生損害於簡大程及永\n    豐銀行。\n  (四)張耀宗、甲○○再與陳俊成（所涉竊盜犯行部分，由臺灣桃\n    園地方法院檢察署檢察官以98年度偵緝字第866號案件提起\n    公訴，現由臺灣桃園地方法院以98年度審易字1429號案件審\n    理；另冒用李孟融名義應訊涉犯偽造文書犯行部分，業經臺\n    灣桃園地方法院檢察署檢察官以98年度偵緝字第393號提起\n    公訴，及由臺灣桃園地方法院檢察署檢察官以98年度偵字第\n    9319號移請臺灣桃園地方法院併案審理）共同基於意圖為自\n    己不法所有之犯意聯絡，於97年8月21日下午5時許前日間某\n    時，至宜蘭縣宜蘭市○○○路347巷15號林敬人住處，踰越\n    林敬人住處後門上方窗戶，進入住宅竊取林敬人所有或管領\n    之集郵冊10本、郵局、銀行存摺共6本、古董鋼筆60多支、\n    鋼質萬用刀1把（上刻有林敬人）、打火機3只、林敬人之妻\n    印章3枚及金飾價值約3千多元。\n二、查獲情形：\n  (一)於犯罪事實一(二)後，嗣經警到場，在常琪住處2樓陽台氣窗\n    採獲數枚指紋經送鑑驗比對，與刑事警察局檔存張耀宗指紋\n    卡之右中指、右食指、右環指指紋相符。\n  (二)於犯罪事實一(三)後，為警在簡大程住處廁所門框、氣窗及後\n    陽台鋁窗上採取指紋送鑑定，其中編號1至5採取之指紋送檢\n    驗比對確認結果，與刑事警察局檔存張耀宗指紋卡之左中指\n    、左環指、左食指、右食指指紋相符；另自前開偽造之取款\n    憑條上採取之指紋1枚，經送鑑定比對，確認結果，與刑事\n    警察局檔存甲○○指紋卡之左食指指紋相符而查獲。\n  (三)於97年9月3日晚間6時40分許，甲○○駕駛車牌號碼9338-RF\n    自用小客車載陳俊成、張耀宗行經桃園縣楊梅鎮○○路○段\n    107巷77弄37號前為警攔檢9338-RF自用小客車時，經甲○○\n    同意搜索，於甲○○之手提包內起出林敬人所有遭竊之刻有\n    林敬人名字之鋼質萬用刀1把；另於97年9月4日凌晨12時5分\n    許，為警帶同張耀宗至其臺北縣中和市○○路177巷5號6樓\n    住處，經張耀宗同意執行搜索，當場起出林冠嶧所有之普通\n    小型車駕照、重型機車駕照、普通重型機車駕照、健保卡、\n    身分證、技術士證共6張。\n三、案經臺北縣政府警察局汐止分局、宜蘭縣政府警察局宜蘭分\n    局、宜蘭縣政府警察局羅東分局報請臺灣宜蘭地方法院檢察\n    署檢察官偵查起訴。",
    "reason": "甲、有罪部分：\n一、訊據被告於本院審理中，對於前開犯罪事實一之竊盜、侵入\n    住宅、行使偽造私文書、詐欺取財犯行均坦承不諱。經查：\n  (一)就前開犯罪事實一(一)部分，業據被害人林莉情於警訊中指述\n    其住處遭竊之情形（參見97年度偵字第3908號卷第9、10頁\n    97年9月10日警訊筆錄）。再臺北縣政府警察局汐止分局員\n    警於97年9月4日凌晨12時5分許，在同案共犯張耀宗位於臺\n    北縣中和市○○路177巷5號6樓住處搜索，扣得林莉情之子\n    林冠嶧之普通小型車駕照、重型機車駕照、普通重型機車駕\n    照、健保卡、身分證、技術士證等物，有臺北縣政府警察局\n    汐止分局搜索扣押筆錄、扣押物品目錄表、被害人林莉情出\n    具之贓物認領保管單，及林冠嶧證件影本等件在卷可佐（97\n    年度偵字第3908號卷第37頁、第51至53頁、第55頁）。\n  (二)就前開犯罪事實一(二)部分，同案共犯張耀宗於本院審理中自\n    承在卷，並據被害人常琪於警訊中指述其住處遭竊之情形（\n    警羅偵字第00983100040號卷第1、2頁97年7月13日警訊筆錄\n    ），復有現場照片10幀在卷可佐（警羅偵字第00983100040\n    號卷第7至11頁）。再員警於被害人常琪住處2樓陽台氣窗採\n    獲數枚指紋送鑑定之結果，核與同案共犯張耀宗之右中指、\n    右食指、右環指指紋相符，有內政部警政署97年8月1日刑紋\n    字第0970111740號鑑驗書1份附卷可證（警羅偵字第0098310\n    0040號卷第5、6頁）。\n  (三)就前開犯罪事實一(三)部分，同案共犯張耀宗於本院審理中自\n    承在卷，並據被害人簡大程於警、偵訊中證述在卷（參見警\n    蘭偵字第0972104864號卷第1至3頁97年7月23日警訊筆錄、9\n    7年7月29日警訊筆錄、98年度偵字第138號卷第28、29頁98\n    年5月20日偵訊筆錄），並有現場照片4幀在卷可佐（警蘭偵\n    字第0972104864號卷第26、27頁）。而員警在被害人簡大程\n    住處廁所門框、氣窗及後陽台鋁窗上採取指紋送鑑定之結果\n    ，其中編號1至5採取之指紋輸入指紋電腦比對確認結果，與\n    同案共犯張耀宗之左中指、左環指、左食指、右食指指紋相\n    符，有內政部警政署刑事警察局97年8月1日刑紋字第097011\n    1438號鑑驗書1份附卷可證（警蘭偵字第0972104864號卷第8\n    、9頁）。而同案共犯張耀宗於97年7月23日上午11時25分許\n    ，持蓋用被害人簡大程印章之取款憑條，至永豐銀行冒充被\n    害人簡大程提款，致使銀行行員陷於錯誤，而交付13萬元，\n    亦有永豐銀行監視器錄影畫面翻拍照片2幀，及取款憑條照\n    片2幀附卷可佐（警蘭偵字第0972104864號卷第28、29頁）\n    。而上開取款憑條上採取之指紋1枚經送鑑定，與被告指紋\n    卡之左食指指紋相符，有內政部警政署刑事警察局97年8月5\n    日刑紋字第0970114803號鑑驗書1份附卷可證（警蘭偵字第\n    0972104864號卷第10、11頁）。\n  (四)就前開犯罪事實一(四)部分，同案共犯張耀宗於審理中自承在\n    卷，並據被害人林敬人就其住處遭竊情節，於警訊中指述在\n    卷（參見97年度偵字第3908號卷第11、12頁97年9月15日警\n    訊筆錄），且同案共犯陳俊成於偵查中，亦自承與被告及同\n    案共犯張耀宗共同行竊之犯行（參見97年度偵字第3908號卷\n    第312至314頁98年5月12日偵訊筆錄）。再於97年9月3日下\n    午6時40分許，被告駕駛車牌號碼9338-RF自用小客車行經桃\n    園縣楊梅鎮○○路○段107巷77弄37號前為警攔檢，自其手提\n    包內起出林敬人所有遭竊之刻有林敬人名字之鋼質萬用刀1\n    把，有臺北縣政府警察局汐止分局搜索扣押筆錄、扣押物品\n    目錄表（97年度偵字第3908號卷第43至49頁），及被害人林\n    敬人出具之贓物認領保管單1紙（97年度偵字第3908號卷第\n    39頁）附卷可佐。\n  (五)綜上所述，本件事證明確，被告前開竊盜、侵入住宅、行使\n    偽造私文書、詐欺取財犯行堪以認定，應依法論科。\n二、核被告關於犯罪事實一(一)所為，係犯刑法第321條第1項第2\n    款毀越門扇竊盜罪；關於犯罪事實一(二)所為，係犯刑法第\n    321條第1項第1款、第2款於夜間踰越門扇侵入住宅竊盜罪；\n    關於犯罪事實一(三)所為，係犯刑法第321條第1項第2款踰越\n    門扇竊盜罪、第306條第1項侵入住宅罪、第216條、第210條\n    行使偽造私文書罪、第339條第1項詐欺取財罪；關於犯罪事\n    實一(四)所為，係犯刑法第321條第1項第2款、第4款結夥三人\n    以上踰越門扇竊盜罪。被告就前開犯罪事實一(三)中，冒用被\n    害人簡大程名義行使偽造之取款憑條，以此詐騙手法致使銀\n    行行員陷於錯誤，因而交付財物，係以一詐騙行為而觸犯上\n    開行使偽造私文書、詐欺取財2罪，為想像競合犯，應從一\n    重依行使偽造私文書罪處斷。被告就犯罪事實一(一)、(二)、(三)\n    之竊盜、侵入住宅、行使偽造私文書犯行，與張耀宗有犯意\n    之聯絡及行為之分擔，另關於犯罪事實一(四)之竊盜犯行，與\n    張耀宗、陳俊成有犯意之聯絡及行為之分擔，為共同正犯。\n    被告所犯上開竊盜罪4罪、侵入住宅罪1罪、行使偽造私文書\n    罪1罪，犯意各別，行為互殊，應予分論併罰。查被告前因\n    竊盜及違反槍砲彈藥刀械管制條例案件，經臺灣高等法院以\n    94年度上訴字第846號刑事判決分別判處有期徒刑3年4月、4\n    月確定，另因毒品案件，經本院以94年度宜簡字第7號刑事\n    判決判處有期徒刑4月確定，再因竊盜案件，經臺灣臺北地\n    方法院以94年度易字第878號刑事判決判處有期徒刑1年6月\n    確定，上開有期徒刑嗣經臺灣臺北地方法院以96年度聲減字\n    第2716號裁定減刑後定應執行刑有期徒刑3年11月，於97年2\n    月5日假釋出監，於97年5月6日假釋期滿，有卷附臺灣高等\n    法院被告前案紀錄表可按，其受有期徒刑之執行完畢，5年\n    內再犯法定刑有期徒刑以上之上開6罪，為累犯，均依法加\n    重其刑。爰審酌被告不思正途獲取報酬，竟多次竊取侵入他\n    人住處竊取財物，復冒用他人身分至銀行提款，依其犯罪之\n    動機、目的、手段、被害人所受之損失，及被告犯後坦承犯\n    行等一切情狀，就其所犯上開各罪分別量處如主文所示之刑\n    ，並定其應執行刑。\n乙、不受理部分：\n一、公訴意旨另以：(一)被告與同案共犯張耀宗於97年6月27日日\n    間某時，至宜蘭縣五結鄉○○路○段127號被害人林莉情住處\n    ，敲破被害人林莉情住處窗戶後，踰越窗戶侵入被害人林莉\n    情住宅內行竊；(二)被告與同案共犯張耀宗、陳俊成於97年8\n    月21日下午5時許前日間某時，至宜蘭縣宜蘭市○○○路347\n    巷15號被害人林敬人住處，踰越被害人林敬人住處後門上方\n    窗戶，進入住宅竊取被害人林敬人之財物。因認被告此部分\n    另涉有刑法第306條第1項侵入住宅罪嫌。\n二、按「案件有下列情形之一者，應諭知不受理之判決：三、告\n    訴或請求乃論之罪，未經告訴、請求或其告訴、請求經撤回\n    或已逾告訴期間者。」，刑事訴訟法第303條第3款定有明文\n    。檢察官認被告涉犯刑法第306條第1項侵入住宅罪，依同法\n    第308條第1項規定，須告訴乃論。查本件被害人林莉情、林\n    敬人前於警訊中，僅就被告竊盜犯行提起告訴（參見97年度\n    偵字第3908號卷第10頁97年9月10日警訊筆錄、同卷第12頁\n    97年9月15日警訊筆錄），未併就侵入住宅提起告訴，有警\n    訊筆錄在卷可參。檢察官就被告此部分侵入住宅犯行提起公\n    訴，自有未洽，依前開規定，此部分應為不受理判決之諭知\n    。\n據上論斷，應依刑事訴訟法第299條第1項前段、第303條第3款，\n刑法第28條、第216條、第210條、第306條第1項、第321條第1項\n第1款、第2款、第4款、第339條第1項、第55條、第47條第1項、\n第51條第5款，刑法施行法第1條之1第1項、第2項前段，判決如\n主文。\n本案經檢察官陳嘉瑜到庭執行職務\n中    華    民    國    99    年    5     月    12    日\n                  刑事第四庭審判長法  官  林楨森\n                                  法  官  陳雪玉\n                                  法  官  辜漢忠\n以上正本證明與原本無異。\n如不服本判決應於收受送達後十日內向本院提出上訴書狀，並應\n敘述具體理由；其未敘述上述理由者，應於上訴期間屆滿後二十\n日內向本院補提理由書(均須按他造當事人之人數附繕本)「切勿\n逕送上級法院」。\n                                  書記官  林詩綺"
  },
  "characters": {
    "judges": [
      "林楨森",
      "陳雪玉",
      "辜漢忠"
    ],
    "prosecutors": [
      "陳嘉瑜"
    ],
    "lawyers": [

    ],
    "clerks": [
      "林詩綺"
    ],
    "plaintiffs": [

    ],
    "defendants": [
      "甲○○"
    ],
    "prosecutor_office": [
      "臺灣宜蘭地方法院檢察署檢察官"
    ],
    "creditors": [

    ],
    "debtors": [

    ],
    "judicial_associate_officer": [

    ]
  },
  "adjudged_at": "2010-05-12",
  "created_at": "2016-01-05 12:30:22",
  "updated_at": "2016-01-05 12:30:22"
}