{
  "identify": "ILD-99-聲-256-20100512-1",
  "court": {
    "name": "臺灣宜蘭地方法院",
    "code": "ILD"
  },
  "division": {
    "name": "刑事",
    "code": "M"
  },
  "year": 99,
  "word": "聲",
  "number": "256",
  "jcheck": "1",
  "reason": "定應執行刑",
  "content": "臺灣宜蘭地方法院刑事裁定               99年度聲字第256號\n聲  請  人  臺灣宜蘭地方法院檢察署檢察官\n受  刑  人  甲○○\n上列聲請人因對受刑人數罪併罰有二裁判以上，聲請定其應執行\n之刑（99年度執聲字第199號），本院裁定如下：\n    主  文\n甲○○所犯如附表所示各罪所處之刑，應執行有期徒刑拾陸年捌\n月，併科罰金新臺幣伍萬貳仟元，罰金如易服勞役，以新臺幣壹\n仟元折算壹日。\n    理  由\n一、查受刑人甲○○因犯偽造文書等案件，先後經判決確定如附\n    表，爰依刑法第53條、第51條第5、7款及刑事訴訟法第477\n    條第1項規定，聲請定應執行刑等語。\n二、經核聲請人之聲請並無不合，應予准許。爰依刑事訴訟法第\n    477條第1項，刑法第53條、第51條第5款、第7款、第42條第\n    3項前段，裁定如主文。\n中    華    民    國    99    年    5     月    12    日\n                  刑事第三庭  法  官  陳映佐\n以上正本證明與原本無異。\n如不服本裁定，應於裁定送達後5日內向本院提出抗告狀（應附\n繕本）「切勿逕送上級法院」。\n                              書記官  翁靜儀\n中    華    民    國    99    年    5     月    13    日",
  "structure": {
    "main": "甲○○所犯如附表所示各罪所處之刑，應執行有期徒刑拾陸年捌\n月，併科罰金新臺幣伍萬貳仟元，罰金如易服勞役，以新臺幣壹\n仟元折算壹日。",
    "reason": "一、查受刑人甲○○因犯偽造文書等案件，先後經判決確定如附\n    表，爰依刑法第53條、第51條第5、7款及刑事訴訟法第477\n    條第1項規定，聲請定應執行刑等語。\n二、經核聲請人之聲請並無不合，應予准許。爰依刑事訴訟法第\n    477條第1項，刑法第53條、第51條第5款、第7款、第42條第\n    3項前段，裁定如主文。"
  },
  "characters": {
    "judges": [
      "陳映佐"
    ],
    "prosecutors": [

    ],
    "lawyers": [

    ],
    "clerks": [
      "翁靜儀"
    ],
    "plaintiffs": [

    ],
    "defendants": [

    ],
    "prosecutor_office": [
      "臺灣宜蘭地方法院檢察署檢察官"
    ],
    "creditors": [

    ],
    "debtors": [

    ],
    "judicial_associate_officer": [

    ]
  },
  "adjudged_at": "2010-05-12",
  "created_at": "2016-01-05 12:30:15",
  "updated_at": "2016-01-05 12:30:15"
}