{
  "identify": "ILD-98-訴-427-20100512-1",
  "court": {
    "name": "臺灣宜蘭地方法院",
    "code": "ILD"
  },
  "division": {
    "name": "刑事",
    "code": "M"
  },
  "year": 98,
  "word": "訴",
  "number": "427",
  "jcheck": "1",
  "reason": "毒品危害防制條例",
  "content": "臺灣宜蘭地方法院刑事判決               98年度訴字第427號\n公  訴  人  臺灣宜蘭地方法院檢察署檢察官\n被      告  丙○○\n選任辯護人  曾文杞律師\n上列被告因違反毒品危害防制條例案件，經檢察官提起公訴（98\n年度偵字第499號），本院判決如下：\n    主  文\n丙○○無罪。\n    理  由\n一、公訴意旨略以：被告丙○○基於販賣第一級毒品海洛因及第\n    二級毒品安非他命之犯意，以其所使用行動電話門號000000\n    0000號為聯絡工具，自民國98年1月間某日起至98年4月間某\n    日止，在附表所示之時間、地點，每次以新臺幣（下同）1,\n    000元、2,000元或4,000元代價販賣海洛因或安非他命予戊\n    ○○等4人。並於98年1月19日晚上10時許，在位於宜蘭縣蘇\n    澳鎮之北濱公園停車場為警查獲，並扣得海洛因7小包（檢\n    驗餘重1.4028公克）及分裝袋17只，因認被告所為，係涉犯\n    毒品危害防制條例第4條第1項、第2項之販賣第一級、第二\n    級毒品罪嫌。\n二、按犯罪事實應依證據認定之，無證據不得認定犯罪事實；又\n    不能證明被告犯罪者，法院應諭知無罪之判決，刑事訴訟法\n    第154條第2項、第301條第1項分別定有明文。次按認定不利\n    於被告之事實，須依積極證據，茍積極證據不足為不利於被\n    告事實之認定時，即應為有利於被告之認定，更不必任何有\n    利之證據；又刑事訴訟法上所謂認定犯罪事實之積極證據，\n    係指適合於被告犯罪事實認定之積極證據而言，雖不以直接\n    證據為限，間接證據亦包括在內，然而無論直接或間接證據\n    ，其為訴訟上之證明，須於通常一般之人均不致有所懷疑，\n    而得確信其為真實之程度者，始得據為有罪之認定，倘其證\n    明尚未達到此一程度，而有合理之懷疑存在而無從使事實審\n    法院得有罪之確信時，即應由法院為諭知被告無罪之判決（\n    最高法院40年台上字第86號、30年上字第816號、29年上字\n    第3105號、76年台上字第4986號判例意旨參照）。再按，施\n    用毒品者，其所稱來源為某人之供述，須補強證據以擔保其\n    供述之真實性，良以施用毒品者其供述之憑信性本不及於一\n    般人，況施用毒品者其供出來源，因而破獲者，法律復規定\n    得減輕其刑，其有為偵查機關誘導、或為邀輕典而為不實之\n    陳述之可能，其供述之真實性自有合理之懷疑，是施用毒品\n    者關於其向某人購買毒品或毒品受讓自某人之供述，必須補\n    強證據佐證，以擔保其供述之真實性，俾貫徹刑事訴訟無罪\n    推定及嚴格證明之基本原則。而茲所謂補強證據，指其他有\n    關證明施用毒品者之關於毒品交易或來源之供述真實性之相\n    關證據而言，必須與施用毒品者關於毒品提供者之供述，具\n    有相當程度之關連性，而足使一般人對施用毒品者關於毒品\n    交易或來源之供述，並無合理之懷疑存在，而得確信其為真\n    實，始足當之（最高法院94年度台上字第2033號裁判要旨可\n    為參照）。\n三、公訴人認被告涉犯販賣海洛因、安非他命之罪嫌，無非以證\n    人戊○○、甲○○、丁○○、乙○○、羅正道於警詢及偵查\n    中之證述及通聯紀錄及扣案之海洛因7包（驗畢餘重1.4028\n    公克）等為其論據。訊據被告堅決否認有何公訴人所指之上\n    述犯行，辯稱：伊不曾販賣海洛因、安非他命予戊○○、甲\n    ○○、丁○○、乙○○等人，前開通聯紀錄均與本案無關等\n    語。\n四、經查：\n（一）按被告以外之人於審判外之言詞或書面陳述，除法律有規\n      定者外，不得作為證據，刑事訴訟法第159條第1項定有明\n      文。故關於證人戊○○、甲○○、丁○○、乙○○於警訊\n      中之證述，均係被告以外之人於審判外之言詞陳述，且被\n      告之辯護人就上開供述之證據能力於本院準備及審理程序\n      中均提出爭執，復查無刑事訴訟法第159條之2至第159條\n      之5例外得為證據之情形，應認無證據能力，不得採為認\n      定被告有罪之證據。至證人羅正道於警詢之供述，雖屬被\n      告以外之人於審判外之陳述，惟被告及辯護人於本院調查\n      證據時，已知有同法第159條第1項不得為證據之情形，而\n      未於言詞辯論終結前聲明異議，依同法第159條之5第2項\n      之規定，視為有同條第1項之同意，本院審酌上開證人之\n      言詞陳述作成時之情況，認為適當，爰依同法第159條之5\n      第1項之規定認有證據能力，合先敘明。\n（二）證人戊○○於本院經傳喚、拘提均不到，而其雖於檢察官\n      偵查時證述：98年1月第1次向丙○○購買毒品，撥打他00\n      00000000號行動電話聯絡，以1千元的價格購買1包海洛因\n      ，最後1次他過來我蘇澳鎮○○路的住處，以1千元代價購\n      買1包海洛因等語在卷（見偵查卷第46-47頁筆錄），然依\n      證人戊○○所述，其並未指出先後向被告購買2次毒品之\n      確切時間，且證人戊○○於本院審理時未到庭，無法予被\n      告反對詰問之機會，以擔保其證詞之憑信性，故證人戊○\n      ○於偵查中所述是否足採，已有可疑。且公訴人雖提出證\n      人戊○○與被告之通聯紀錄為補強證據，然雖被告自承該\n      通聯紀錄為其使用0000000000號行動電話而與證人戊○○\n      聯絡之紀錄無訛，然該通聯紀錄僅得證明被告與證人戊○\n      ○間確有於該時間以電話聯繫一情，並無通話內容，與證\n      人戊○○指稱被告有販賣海洛因之供述之間，並無相當程\n      度之關連性，揆諸上開說明，上開通聯記錄自不得資為證\n      人戊○○指證被告有販賣海洛因予戊○○之補強證據。至\n      扣案之海洛因7小包（驗畢餘重1.4028公克）及分裝袋17\n      個，雖為被告為警查獲時扣得之物，然被告否認為供販賣\n      毒品之用，而參之該扣得之海洛因及分裝袋數量非鉅，是\n      否供販賣所用，已有可疑，況依被告當日為警查獲採尿之\n      結果，確有施用海洛因之毒品反應，且經本院以98年度訴\n      字第292號判決在案，故上開扣得之第一級毒品海洛因7包\n      ，亦不足為被告有販賣海洛因予戊○○之補強證據，從而\n      ，公訴意旨所指被告販賣海洛因予戊○○之犯行，除證人\n      戊○○上開單一指證外，別無其他證據足以佐認證人戊○\n      ○之陳述如何與事實相符，尚有合理懷疑之存在，無從使\n      本院形成被告有罪之確信，故公訴人僅憑證人戊○○之片\n      面指證，遽認被告有販賣海洛因予證人戊○○之情事，其\n      舉證尚有未足，無從認定為真實。\n（三）證人甲○○於本院審理時拒絕證言，而其於偵查中雖證述\n      ：98年1月，他事先用電話問我要不要買安非他命，我說\n      好，他就過來我文化路住處附近，我以1千元代價買1包安\n      非他命，最後1次是98年2月，他事先打電話給我，他過來\n      我文化路住處附近，我以1千元代價買1包安非他命等語在\n      卷（見偵查卷第47頁筆錄），然依證人甲○○所述，其並\n      未指出先後向被告購買2次毒品之確切時間，且證人甲○\n      ○於本院審理時拒絕作證，無法予被告反對詰問之機會，\n      而擔保其證詞之可憑信性，故證人甲○○於偵查中所述是\n      否足採，已有可疑。且公訴人雖提出證人甲○○與被告之\n      通聯紀錄為補強證據，然雖被告自承該通聯紀錄為其使用\n      0000000000號行動電話而與證人甲○○聯絡之紀錄無訛，\n      然該通聯紀錄僅得證明被告與證人甲○○間確有於該時間\n      以電話聯繫一情，並無通話內容，與證人甲○○指稱被告\n      有販賣安非他命之供述之間，並無相當程度之關連性，況\n      依通聯紀錄所示，亦僅有98年1月18日晚間被告與證人甲\n      ○○之通聯紀錄，亦無從證明該日之通聯紀錄即為證人甲\n      ○○前於偵查中所證述之「98年1月」購買安非他命之時\n      間，故揆諸上開說明，上開通聯記錄自不得資為證人甲○\n      ○指證被告有販賣安非他命予甲○○之補強證據。至扣案\n      之海洛因7小包及分裝袋17個，雖為被告為警查獲時扣得\n      之物，更與被告是否販賣安非他命無涉，亦不足為被告有\n      販賣安非他命予甲○○之補強證據，從而，公訴意旨所指\n      被告販賣安非他命予甲○○之犯行，除證人甲○○上開單\n      一指證外，別無其他證據足以佐認證人甲○○之陳述如何\n      與事實相符，尚有合理懷疑之存在，無從使本院形成被告\n      有罪之確信，故公訴人僅憑證人甲○○之片面指證，遽認\n      被告有販賣安非他命予證人甲○○之情事，其舉證尚有未\n      足，無從認定為真實。\n（三）證人丁○○雖於偵查中證述：第1次於98年2月初，被告直\n      接來我南安路住處問我是否要買安非他命，我以4千元代\n      價買1包安非他命，約1克重，最後1次是98年2月底，被告\n      也是到我南安路的住處問我是否要買，我以4千元代價買1\n      包，約1克重，另1次也是在98年2月，被告也是到我南安\n      路住處，我以4千元代價買1包安非他命約1克重等語在卷\n      （見偵查卷第46頁筆錄），然證人丁○○於本院審理時則\n      證稱並未向被告購買安非他命等語在卷（見本院卷第47-5\n      0頁筆錄），則以證人丁○○於偵查及本院審理時所為證\n      述內容已有不符，其於偵查中所為證述是否足採，已有可\n      疑，況依證人丁○○前於警詢中證述：係從97年7、8月開\n      始，向被告購買6、7次安非他命，最後1次是20幾天前（\n      製作筆錄日期為98年4月10日，前20幾日即為98年3月間）\n      等語（見警卷第11-12頁筆錄），亦核與其於偵查中所為\n      證述向被告購買安非他命之時間、次數均有差異，故證人\n      丁○○於偵查中之證述，尚難遽採為真實，則公訴意旨所\n      指被告販賣安非他命予丁○○之犯行，除證人丁○○上開\n      單一指證外，別無其他證據足以佐認證人丁○○之陳述如\n      何與事實相符，尚有合理懷疑之存在，無從形成被告有罪\n      之確信，從而公訴人僅憑證人丁○○之片面指證，遽認被\n      告有販賣安非他命予證人丁○○之情事，其舉證尚有未足\n      ，無從認定為真實。\n（四）證人乙○○雖於偵查中證述：第1次是98年1月，我在蘇澳\n      鎮榮民醫院外面的馬路上，以2千元代價買1包安非他命，\n      最後1次是98年4月在蘇澳鎮○○○道前面，以1千元代價\n      買1包安非他命，前後至少向被告買過4次等語在卷（見偵\n      查卷第48-49頁筆錄），然依證人乙○○所述，其並未指\n      出先後向被告購買4次毒品之確切時間、金額，且證人乙\n      ○○於本院審理時則證述並未向被告購買安非他命等語（\n      見本院卷第頁筆錄），更與其於偵查中所為之證述相違，\n      故證人乙○○於偵查中所述是否足採，已有可疑。且公訴\n      人雖提出證人乙○○與被告之通聯紀錄為補強證據，而雖\n      被告自承該通聯紀錄為其使用0000000000號行動電話而與\n      證人乙○○聯絡之紀錄無訛，然該通聯紀錄僅得證明被告\n      與證人乙○○間確有於該時間以電話聯繫一情，並無通話\n      內容，與證人乙○○指稱被告有販賣安非他命之供述之間\n      ，並無相當程度之關連性，況依通聯紀錄所示，亦僅有98\n      年1月11日之通聯紀錄，亦無從證明該日之通聯紀錄即為\n      證人乙○○前於偵查中所證述之「98年1月」購買安非他\n      命之時間，且復查無證人乙○○所稱向被告購買4次安非\n      他命之通聯紀錄，故揆諸上開說明，上開通聯記錄自不得\n      資為證人乙○○指證被告有販賣安非他命之補強證據。至\n      扣案之海洛因7小包及分裝袋17個，雖為被告為警查獲時\n      扣得之物，更與被告是否販賣安非他命無涉，亦不足為被\n      告有販賣安非他命予乙○○之補強證據，從而，公訴意旨\n      所指被告販賣安非他命予乙○○之犯行，除證人乙○○上\n      開單一指證外，別無其他證據足以佐認證人乙○○之陳述\n      如何與事實相符，尚有合理懷疑之存在，無從使本院形成\n      被告有罪之確信，故公訴人僅憑證人乙○○之片面指證，\n      遽認被告有販賣安非他命予證人乙○○之情事，其舉證尚\n      有未足，無從認定為真實。\n五、綜上所述，本件依公訴人所舉之證據，均無法使本院形成被\n    告有罪之心證而證明被告確有販賣海洛因及安非他命予附表\n    所示之人之犯行，此外，復查無其他積極證據足以證明被告\n    有公訴意旨所指之犯行，不能證明被告犯罪，依前述說明，\n    自應為被告無罪之諭知。\n六、又本案既未能證明被告有販賣海洛因之犯行，則扣案之毒品\n    海洛因、分裝袋自與本案無涉，依主從不可分原則，本案既\n    無主刑，從刑亦無所附麗，自無從於本案併予宣告沒收，應\n    由檢察官另行處理。\n據上論斷，應依刑事訴訟法第301條第1項前段，判決如主文。\n本案經檢察官張立言到庭執行職務\n中    華    民    國    99    年     5    月    12     日\n                  刑事第三庭審判長  法  官  黃永勝\n                                    法  官  陳映佐\n                                    法  官  鄭貽馨\n以上正本證明與原本無異。\n如不服本判決應於收受送達後十日內向本院提出上訴書狀，並應\n敘述具體理由；其未敘述上述理由者，應於上訴期間屆滿後二十\n日內向本院補提理由書(均須按他造當事人之人數附繕本)「切勿\n逕送上級法院」。\n                                    書記官  高雪琴\n中    華    民    國    99    年    5     月    12    日\n附表\n┌──┬────────┬───────┬────┬────┬────┬────┬──────────┐\n│編號│時           間 │地          點│價    格│販賣毒品│販賣對象│販賣次數│聯    絡    方    式│\n├──┼────────┼───────┼────┼────┼────┼────┼──────────┤\n│ 1  │98年1月初某日及 │宜蘭縣蘇澳鎮民│1,000元 │海洛因  │戊○○  │2次     │被告使用0000000000號│\n│    │98年1月19日。   │生路10號。    │        │        │        │        │行動電話與戊○○所使│\n│    │                │              │        │        │        │        │用0000000000號行動電│\n│    │                │              │        │        │        │        │話聯絡。            │\n├──┼────────┼───────┼────┼────┼────┼────┼──────────┤\n│ 2  │98年1月18日及98 │宜蘭縣蘇澳鎮文│1,000元 │安非他命│甲○○  │2次     │被告使用0000000000號│\n│    │年2月間某日。   │化巷98號附近。│        │        │        │        │行動電話與甲○○所使│\n│    │                │              │        │        │        │        │用之0000000000號行動│\n│    │                │              │        │        │        │        │電話聯絡。          │\n├──┼────────┼───────┼────┼────┼────┼────┼──────────┤\n│ 3  │98年2月初某日起 │宜蘭縣蘇澳鎮南│4,000元 │安非他命│丁○○  │3次     │被告直接至丁○○位於│\n│    │至98年2月底某日 │安路193號2樓。│        │        │        │        │宜蘭縣蘇澳鎮○○路19│\n│    │止。            │              │        │        │        │        │3號2樓住處，販賣安非│\n│    │                │              │        │        │        │        │他命予丁○○。      │\n├──┼────────┼───────┼────┼────┼────┼────┼──────────┤\n│ 4  │98年1月11日起至 │宜蘭縣蘇澳鎮榮│1,000元 │安非他命│乙○○  │4次     │被告使用0000000000號│\n│    │98年4月間某日。 │民醫院附近、宜│或2,000 │        │        │        │行動電話與乙○○所使│\n│    │                │蘭縣蘇澳鎮蘭陽│元      │        │        │        │用之0000000000號行動│\n│    │                │隧道前。      │        │        │        │        │電話聯絡。          │\n└──┴────────┴───────┴────┴────┴────┴────┴──────────┘",
  "structure": {
    "main": "丙○○無罪。",
    "reason": "一、公訴意旨略以：被告丙○○基於販賣第一級毒品海洛因及第\n    二級毒品安非他命之犯意，以其所使用行動電話門號000000\n    0000號為聯絡工具，自民國98年1月間某日起至98年4月間某\n    日止，在附表所示之時間、地點，每次以新臺幣（下同）1,\n    000元、2,000元或4,000元代價販賣海洛因或安非他命予戊\n    ○○等4人。並於98年1月19日晚上10時許，在位於宜蘭縣蘇\n    澳鎮之北濱公園停車場為警查獲，並扣得海洛因7小包（檢\n    驗餘重1.4028公克）及分裝袋17只，因認被告所為，係涉犯\n    毒品危害防制條例第4條第1項、第2項之販賣第一級、第二\n    級毒品罪嫌。\n二、按犯罪事實應依證據認定之，無證據不得認定犯罪事實；又\n    不能證明被告犯罪者，法院應諭知無罪之判決，刑事訴訟法\n    第154條第2項、第301條第1項分別定有明文。次按認定不利\n    於被告之事實，須依積極證據，茍積極證據不足為不利於被\n    告事實之認定時，即應為有利於被告之認定，更不必任何有\n    利之證據；又刑事訴訟法上所謂認定犯罪事實之積極證據，\n    係指適合於被告犯罪事實認定之積極證據而言，雖不以直接\n    證據為限，間接證據亦包括在內，然而無論直接或間接證據\n    ，其為訴訟上之證明，須於通常一般之人均不致有所懷疑，\n    而得確信其為真實之程度者，始得據為有罪之認定，倘其證\n    明尚未達到此一程度，而有合理之懷疑存在而無從使事實審\n    法院得有罪之確信時，即應由法院為諭知被告無罪之判決（\n    最高法院40年台上字第86號、30年上字第816號、29年上字\n    第3105號、76年台上字第4986號判例意旨參照）。再按，施\n    用毒品者，其所稱來源為某人之供述，須補強證據以擔保其\n    供述之真實性，良以施用毒品者其供述之憑信性本不及於一\n    般人，況施用毒品者其供出來源，因而破獲者，法律復規定\n    得減輕其刑，其有為偵查機關誘導、或為邀輕典而為不實之\n    陳述之可能，其供述之真實性自有合理之懷疑，是施用毒品\n    者關於其向某人購買毒品或毒品受讓自某人之供述，必須補\n    強證據佐證，以擔保其供述之真實性，俾貫徹刑事訴訟無罪\n    推定及嚴格證明之基本原則。而茲所謂補強證據，指其他有\n    關證明施用毒品者之關於毒品交易或來源之供述真實性之相\n    關證據而言，必須與施用毒品者關於毒品提供者之供述，具\n    有相當程度之關連性，而足使一般人對施用毒品者關於毒品\n    交易或來源之供述，並無合理之懷疑存在，而得確信其為真\n    實，始足當之（最高法院94年度台上字第2033號裁判要旨可\n    為參照）。\n三、公訴人認被告涉犯販賣海洛因、安非他命之罪嫌，無非以證\n    人戊○○、甲○○、丁○○、乙○○、羅正道於警詢及偵查\n    中之證述及通聯紀錄及扣案之海洛因7包（驗畢餘重1.4028\n    公克）等為其論據。訊據被告堅決否認有何公訴人所指之上\n    述犯行，辯稱：伊不曾販賣海洛因、安非他命予戊○○、甲\n    ○○、丁○○、乙○○等人，前開通聯紀錄均與本案無關等\n    語。\n四、經查：\n（一）按被告以外之人於審判外之言詞或書面陳述，除法律有規\n      定者外，不得作為證據，刑事訴訟法第159條第1項定有明\n      文。故關於證人戊○○、甲○○、丁○○、乙○○於警訊\n      中之證述，均係被告以外之人於審判外之言詞陳述，且被\n      告之辯護人就上開供述之證據能力於本院準備及審理程序\n      中均提出爭執，復查無刑事訴訟法第159條之2至第159條\n      之5例外得為證據之情形，應認無證據能力，不得採為認\n      定被告有罪之證據。至證人羅正道於警詢之供述，雖屬被\n      告以外之人於審判外之陳述，惟被告及辯護人於本院調查\n      證據時，已知有同法第159條第1項不得為證據之情形，而\n      未於言詞辯論終結前聲明異議，依同法第159條之5第2項\n      之規定，視為有同條第1項之同意，本院審酌上開證人之\n      言詞陳述作成時之情況，認為適當，爰依同法第159條之5\n      第1項之規定認有證據能力，合先敘明。\n（二）證人戊○○於本院經傳喚、拘提均不到，而其雖於檢察官\n      偵查時證述：98年1月第1次向丙○○購買毒品，撥打他00\n      00000000號行動電話聯絡，以1千元的價格購買1包海洛因\n      ，最後1次他過來我蘇澳鎮○○路的住處，以1千元代價購\n      買1包海洛因等語在卷（見偵查卷第46-47頁筆錄），然依\n      證人戊○○所述，其並未指出先後向被告購買2次毒品之\n      確切時間，且證人戊○○於本院審理時未到庭，無法予被\n      告反對詰問之機會，以擔保其證詞之憑信性，故證人戊○\n      ○於偵查中所述是否足採，已有可疑。且公訴人雖提出證\n      人戊○○與被告之通聯紀錄為補強證據，然雖被告自承該\n      通聯紀錄為其使用0000000000號行動電話而與證人戊○○\n      聯絡之紀錄無訛，然該通聯紀錄僅得證明被告與證人戊○\n      ○間確有於該時間以電話聯繫一情，並無通話內容，與證\n      人戊○○指稱被告有販賣海洛因之供述之間，並無相當程\n      度之關連性，揆諸上開說明，上開通聯記錄自不得資為證\n      人戊○○指證被告有販賣海洛因予戊○○之補強證據。至\n      扣案之海洛因7小包（驗畢餘重1.4028公克）及分裝袋17\n      個，雖為被告為警查獲時扣得之物，然被告否認為供販賣\n      毒品之用，而參之該扣得之海洛因及分裝袋數量非鉅，是\n      否供販賣所用，已有可疑，況依被告當日為警查獲採尿之\n      結果，確有施用海洛因之毒品反應，且經本院以98年度訴\n      字第292號判決在案，故上開扣得之第一級毒品海洛因7包\n      ，亦不足為被告有販賣海洛因予戊○○之補強證據，從而\n      ，公訴意旨所指被告販賣海洛因予戊○○之犯行，除證人\n      戊○○上開單一指證外，別無其他證據足以佐認證人戊○\n      ○之陳述如何與事實相符，尚有合理懷疑之存在，無從使\n      本院形成被告有罪之確信，故公訴人僅憑證人戊○○之片\n      面指證，遽認被告有販賣海洛因予證人戊○○之情事，其\n      舉證尚有未足，無從認定為真實。\n（三）證人甲○○於本院審理時拒絕證言，而其於偵查中雖證述\n      ：98年1月，他事先用電話問我要不要買安非他命，我說\n      好，他就過來我文化路住處附近，我以1千元代價買1包安\n      非他命，最後1次是98年2月，他事先打電話給我，他過來\n      我文化路住處附近，我以1千元代價買1包安非他命等語在\n      卷（見偵查卷第47頁筆錄），然依證人甲○○所述，其並\n      未指出先後向被告購買2次毒品之確切時間，且證人甲○\n      ○於本院審理時拒絕作證，無法予被告反對詰問之機會，\n      而擔保其證詞之可憑信性，故證人甲○○於偵查中所述是\n      否足採，已有可疑。且公訴人雖提出證人甲○○與被告之\n      通聯紀錄為補強證據，然雖被告自承該通聯紀錄為其使用\n      0000000000號行動電話而與證人甲○○聯絡之紀錄無訛，\n      然該通聯紀錄僅得證明被告與證人甲○○間確有於該時間\n      以電話聯繫一情，並無通話內容，與證人甲○○指稱被告\n      有販賣安非他命之供述之間，並無相當程度之關連性，況\n      依通聯紀錄所示，亦僅有98年1月18日晚間被告與證人甲\n      ○○之通聯紀錄，亦無從證明該日之通聯紀錄即為證人甲\n      ○○前於偵查中所證述之「98年1月」購買安非他命之時\n      間，故揆諸上開說明，上開通聯記錄自不得資為證人甲○\n      ○指證被告有販賣安非他命予甲○○之補強證據。至扣案\n      之海洛因7小包及分裝袋17個，雖為被告為警查獲時扣得\n      之物，更與被告是否販賣安非他命無涉，亦不足為被告有\n      販賣安非他命予甲○○之補強證據，從而，公訴意旨所指\n      被告販賣安非他命予甲○○之犯行，除證人甲○○上開單\n      一指證外，別無其他證據足以佐認證人甲○○之陳述如何\n      與事實相符，尚有合理懷疑之存在，無從使本院形成被告\n      有罪之確信，故公訴人僅憑證人甲○○之片面指證，遽認\n      被告有販賣安非他命予證人甲○○之情事，其舉證尚有未\n      足，無從認定為真實。\n（三）證人丁○○雖於偵查中證述：第1次於98年2月初，被告直\n      接來我南安路住處問我是否要買安非他命，我以4千元代\n      價買1包安非他命，約1克重，最後1次是98年2月底，被告\n      也是到我南安路的住處問我是否要買，我以4千元代價買1\n      包，約1克重，另1次也是在98年2月，被告也是到我南安\n      路住處，我以4千元代價買1包安非他命約1克重等語在卷\n      （見偵查卷第46頁筆錄），然證人丁○○於本院審理時則\n      證稱並未向被告購買安非他命等語在卷（見本院卷第47-5\n      0頁筆錄），則以證人丁○○於偵查及本院審理時所為證\n      述內容已有不符，其於偵查中所為證述是否足採，已有可\n      疑，況依證人丁○○前於警詢中證述：係從97年7、8月開\n      始，向被告購買6、7次安非他命，最後1次是20幾天前（\n      製作筆錄日期為98年4月10日，前20幾日即為98年3月間）\n      等語（見警卷第11-12頁筆錄），亦核與其於偵查中所為\n      證述向被告購買安非他命之時間、次數均有差異，故證人\n      丁○○於偵查中之證述，尚難遽採為真實，則公訴意旨所\n      指被告販賣安非他命予丁○○之犯行，除證人丁○○上開\n      單一指證外，別無其他證據足以佐認證人丁○○之陳述如\n      何與事實相符，尚有合理懷疑之存在，無從形成被告有罪\n      之確信，從而公訴人僅憑證人丁○○之片面指證，遽認被\n      告有販賣安非他命予證人丁○○之情事，其舉證尚有未足\n      ，無從認定為真實。\n（四）證人乙○○雖於偵查中證述：第1次是98年1月，我在蘇澳\n      鎮榮民醫院外面的馬路上，以2千元代價買1包安非他命，\n      最後1次是98年4月在蘇澳鎮○○○道前面，以1千元代價\n      買1包安非他命，前後至少向被告買過4次等語在卷（見偵\n      查卷第48-49頁筆錄），然依證人乙○○所述，其並未指\n      出先後向被告購買4次毒品之確切時間、金額，且證人乙\n      ○○於本院審理時則證述並未向被告購買安非他命等語（\n      見本院卷第頁筆錄），更與其於偵查中所為之證述相違，\n      故證人乙○○於偵查中所述是否足採，已有可疑。且公訴\n      人雖提出證人乙○○與被告之通聯紀錄為補強證據，而雖\n      被告自承該通聯紀錄為其使用0000000000號行動電話而與\n      證人乙○○聯絡之紀錄無訛，然該通聯紀錄僅得證明被告\n      與證人乙○○間確有於該時間以電話聯繫一情，並無通話\n      內容，與證人乙○○指稱被告有販賣安非他命之供述之間\n      ，並無相當程度之關連性，況依通聯紀錄所示，亦僅有98\n      年1月11日之通聯紀錄，亦無從證明該日之通聯紀錄即為\n      證人乙○○前於偵查中所證述之「98年1月」購買安非他\n      命之時間，且復查無證人乙○○所稱向被告購買4次安非\n      他命之通聯紀錄，故揆諸上開說明，上開通聯記錄自不得\n      資為證人乙○○指證被告有販賣安非他命之補強證據。至\n      扣案之海洛因7小包及分裝袋17個，雖為被告為警查獲時\n      扣得之物，更與被告是否販賣安非他命無涉，亦不足為被\n      告有販賣安非他命予乙○○之補強證據，從而，公訴意旨\n      所指被告販賣安非他命予乙○○之犯行，除證人乙○○上\n      開單一指證外，別無其他證據足以佐認證人乙○○之陳述\n      如何與事實相符，尚有合理懷疑之存在，無從使本院形成\n      被告有罪之確信，故公訴人僅憑證人乙○○之片面指證，\n      遽認被告有販賣安非他命予證人乙○○之情事，其舉證尚\n      有未足，無從認定為真實。\n五、綜上所述，本件依公訴人所舉之證據，均無法使本院形成被\n    告有罪之心證而證明被告確有販賣海洛因及安非他命予附表\n    所示之人之犯行，此外，復查無其他積極證據足以證明被告\n    有公訴意旨所指之犯行，不能證明被告犯罪，依前述說明，\n    自應為被告無罪之諭知。\n六、又本案既未能證明被告有販賣海洛因之犯行，則扣案之毒品\n    海洛因、分裝袋自與本案無涉，依主從不可分原則，本案既\n    無主刑，從刑亦無所附麗，自無從於本案併予宣告沒收，應\n    由檢察官另行處理。\n據上論斷，應依刑事訴訟法第301條第1項前段，判決如主文。\n本案經檢察官張立言到庭執行職務"
  },
  "characters": {
    "judges": [
      "黃永勝",
      "陳映佐",
      "鄭貽馨"
    ],
    "prosecutors": [
      "張立言"
    ],
    "lawyers": [
      "曾文杞"
    ],
    "clerks": [
      "高雪琴"
    ],
    "plaintiffs": [

    ],
    "defendants": [
      "丙○○"
    ],
    "prosecutor_office": [
      "臺灣宜蘭地方法院檢察署檢察官"
    ],
    "creditors": [

    ],
    "debtors": [

    ],
    "judicial_associate_officer": [

    ]
  },
  "adjudged_at": "2010-05-12",
  "created_at": "2016-01-05 12:29:51",
  "updated_at": "2016-01-05 12:29:51"
}