{
  "identify": "IPC-98-行專訴-112-20100105-2",
  "court": {
    "name": "智慧財產法院",
    "code": "IPC"
  },
  "division": {
    "name": "行政",
    "code": "A"
  },
  "year": 98,
  "word": "行專訴",
  "number": "112",
  "jcheck": "2",
  "reason": "新型專利異議",
  "content": "智慧財產法院行政裁定\n                                   98年度行專訴字第112號\n原      告  李見忠      \n送達代收人  吳木如      \n被      告  經濟部智慧財產局\n代  表  人  王美花（局長）住同上\n參  加  人  三陽工業股份有限公司\n代  表  人  黃世惠       \n上列原告與被告間因新型專利異議事件，應命參加人參加訴訟，\n本院裁定如下：\n    主  文\n三陽工業股份有限公司應獨立參加本件被告之訴訟。\n    理  由\n一、按行政法院認為撤銷訴訟之結果，第三人之權利或法律上利\n    益將受損害者，得依職權命其獨立參加訴訟，並得因該第三\n    人之聲請，裁定允許其參加，智慧財產案件審理法第1 條、\n    行政訴訟法第42條第1 項定有明文。\n二、原告前於民國91年12月5 日以「引擎汽門組之改良」向被告\n    申請新型專利，經該局編為第91219884號審查，准予專利（\n    下稱系爭專利），公告期間，三陽工業股份有限公司（下稱\n    三陽公司）以系爭專利有違核准審定時專利法第98條第1 項\n    第1 款及第2 項規定，對之提起異議。案經被告審查，核認\n    系爭專利並未違反前揭規定，於94年7 月29日以（94）智專\n    三(三)05051 字第09420695080 號專利異議審定書為「異議不\n    成立」之處分。三陽公司不服，訴經經濟部95年6 月12日經\n    訴字第09506169910 號訴願決定，以異議證據一、二可證明\n    該專利不具新穎性，且不具功效增進而撤銷前揭處分，責由\n    被告另為適法之處分。被告乃依前揭經濟部訴願決定意旨重\n    行審查，並於95年11月2 日以（95）智專三(三)05051 字第09\n    520917150 號專利異議審定書為「異議成立，應不予專利」\n    之處分。原告不服，訴經經濟部96年3 月15日經訴字第0960\n    6063780 號訴願決定駁回其訴願後，遞向臺北高等行政法院\n    提起行政訴訟。案經該院以97年3 月6 日96年度訴字第1629\n    號判決核認異議證據一及二皆無法證明該專利不具新穎性，\n    而撤銷前揭處分及經濟部訴願決定。被告乃再重行審查，並\n    核認證據一及補充證據一仍可證明該專利不具進步性，於98\n    年5 月6 日以（98）智專三(三)05051 字第09820263040 號專\n    利異議審定書重為本件「異議成立，應不予專利」之處分。\n    原告不服，提起訴願，經經濟部98年8 月27日經訴字第0980\n    6116710 號訴願決定書，為「訴願駁回」在案，原告不服，\n    提起行政訴訟。本院認本件判決之結果，將影響三陽公司之\n    權利或法律上之利益，依職權命三陽公司獨立參加本件訴訟\n    ，爰為裁定如主文。\n中    華    民    國    99    年    1     月    5     日\n                  智慧財產法院第二庭\n                              審判長法  官  陳國成\n                                    法  官  熊誦梅\n                                    法  官  曾啟謀\n以上正本係照原本作成。\n不得抗告。\n中    華    民    國    99    年    1     月    5     日\n                                    書記官  王月伶",
  "structure": {
    "main": "三陽工業股份有限公司應獨立參加本件被告之訴訟。",
    "reason": "一、按行政法院認為撤銷訴訟之結果，第三人之權利或法律上利\n    益將受損害者，得依職權命其獨立參加訴訟，並得因該第三\n    人之聲請，裁定允許其參加，智慧財產案件審理法第1 條、\n    行政訴訟法第42條第1 項定有明文。\n二、原告前於民國91年12月5 日以「引擎汽門組之改良」向被告\n    申請新型專利，經該局編為第91219884號審查，准予專利（\n    下稱系爭專利），公告期間，三陽工業股份有限公司（下稱\n    三陽公司）以系爭專利有違核准審定時專利法第98條第1 項\n    第1 款及第2 項規定，對之提起異議。案經被告審查，核認\n    系爭專利並未違反前揭規定，於94年7 月29日以（94）智專\n    三(三)05051 字第09420695080 號專利異議審定書為「異議不\n    成立」之處分。三陽公司不服，訴經經濟部95年6 月12日經\n    訴字第09506169910 號訴願決定，以異議證據一、二可證明\n    該專利不具新穎性，且不具功效增進而撤銷前揭處分，責由\n    被告另為適法之處分。被告乃依前揭經濟部訴願決定意旨重\n    行審查，並於95年11月2 日以（95）智專三(三)05051 字第09\n    520917150 號專利異議審定書為「異議成立，應不予專利」\n    之處分。原告不服，訴經經濟部96年3 月15日經訴字第0960\n    6063780 號訴願決定駁回其訴願後，遞向臺北高等行政法院\n    提起行政訴訟。案經該院以97年3 月6 日96年度訴字第1629\n    號判決核認異議證據一及二皆無法證明該專利不具新穎性，\n    而撤銷前揭處分及經濟部訴願決定。被告乃再重行審查，並\n    核認證據一及補充證據一仍可證明該專利不具進步性，於98\n    年5 月6 日以（98）智專三(三)05051 字第09820263040 號專\n    利異議審定書重為本件「異議成立，應不予專利」之處分。\n    原告不服，提起訴願，經經濟部98年8 月27日經訴字第0980\n    6116710 號訴願決定書，為「訴願駁回」在案，原告不服，\n    提起行政訴訟。本院認本件判決之結果，將影響三陽公司之\n    權利或法律上之利益，依職權命三陽公司獨立參加本件訴訟\n    ，爰為裁定如主文。"
  },
  "characters": {
    "judges": [
      "陳國成",
      "熊誦梅",
      "曾啟謀"
    ],
    "prosecutors": [

    ],
    "lawyers": [

    ],
    "clerks": [

    ],
    "plaintiffs": [
      "李見忠"
    ],
    "defendants": [
      "經濟部智慧財產局",
      "代  表  人  王美花（局長）住同上",
      "參  加  人  三陽工業股份有限公司",
      "代  表  人  黃世惠"
    ],
    "prosecutor_office": [

    ],
    "creditors": [

    ],
    "debtors": [

    ],
    "judicial_associate_officer": [

    ]
  },
  "adjudged_at": "2010-01-05",
  "created_at": "2016-01-05 15:06:22",
  "updated_at": "2016-01-05 15:06:22"
}