{
  "identify": "IPC-98-民著訴-28-20100105-1",
  "court": {
    "name": "智慧財產法院",
    "code": "IPC"
  },
  "division": {
    "name": "民事",
    "code": "V"
  },
  "year": 98,
  "word": "民著訴",
  "number": "28",
  "jcheck": "1",
  "reason": "侵害著作權有關財產權爭議",
  "content": "智慧財產法院民事判決\n                                    98年度民著訴字第28號\n原      告\n即委 任 人  社團法人日本音樂著作權協（JASRAC）\n法定代理人  甲○○\n訴訟代理人  社團法人中華音樂著作權協會\n法定代理人  丁○○\n複 代 理人  戊○○\n            丙○○\n被      告  音圓國際股份有限公司\n兼\n法定代理人  乙○○\n上二人共同\n訴訟代理人  羅明通律師\n            陳世偉律師\n            劉曉萍律師\n上列當事人間侵害著作權有關財產權爭議事件，本院於民國98年\n12月15日言詞辯論終結，判決如下：\n    主  文\n被告應給付原告新臺幣貳佰肆拾萬元，及自民國九十八年七月二\n十三日起至清償日止，按週年利率百分之五計算之利息。\n原告其餘之訴駁回。\n訴訟費用由被告負擔十分之七，餘由原告負擔。\n本判決第一項於原告以新臺幣捌拾萬元為被告供擔保後，得假執\n行。但被告於假執行程序實施前，以新台幣貳佰肆拾萬元為原告\n供擔保後，得免為假執行。\n原告其餘假執行之聲請駁回。\n    事實及理由\n壹、程序方面：\n一、依智慧財產案件審理法第7 條規定，智慧財產法院組織法第\n    3 條第1 款、第4 款所定之民事事件，由智慧財產法院管轄\n    。本案既屬因著作權法所保護之智慧財產權益所生之第一審\n    民事案件，符合智慧財產法院組織法第3 條第1 款規定，本\n    院依法自有管轄權，合先敘明。\n二、按訴狀送達後，原告不得將原訴變更或追加他訴，但請求之\n    基礎事實同一或擴張者或減縮應受判決事項之聲明者，不在\n    此限，民事訴訟法第255 條第1 項第2 款、第3 款定有明文\n    。本件原告起訴請求：(一)就侵權行為損害賠償部分，被告音\n    圓國際股份有限公司（下稱音圓公司）及乙○○應連帶給付\n    原告新臺幣（下同）100 萬元，就音樂著作重製之使用報酬\n    部分，被告音圓公司及乙○○應連帶給付原告245 萬元，及\n    自起訴狀繕本送達翌日起至清償日止，按週年利率5%計算之\n    利息。(二)訴訟費用由被告負擔。(三)原告願供擔保，請准宣告\n    假執行。嗣於民國98年9 月18日具狀變更第1 項聲明為：(一)\n    就侵權行為損害賠償部分，被告音圓公司及乙○○應連帶給\n    付原告100 萬元，就音樂著作重製之使用報酬部分，被告音\n    圓公司應給付原告245 萬元，及自起訴狀繕本送達翌日起至\n    清償日止，按週年利率5%計算之利息。復於98年11月4 日具\n    狀變更第1 項聲明為：(一)就侵權行為損害賠償部分，被告音\n    圓公司及乙○○應連帶給付原告100 萬元，就音樂著作重製\n    之使用報酬部分，被告音圓公司應給付原告240 萬元，及自\n    起訴狀繕本送達翌日起至清償日止，按週年利率5%計算之利\n    息。經核原告上開所為訴之聲明變更，係屬減縮應受判決事\n    項之聲明，且基於主張被告侵害其著作權之同一基礎事實，\n    是其訴之變更合於首揭規定，應予准許。\n貳、實體方面：\n一、原告主張：\n  (一)原告社團法人日本音樂著作權協（Japanese Society for\n    Rights of Authors, Composers and Publishers ，即JASR\n    AC）係依日本著作權等管理事業法設立，於日本國內經營音\n    樂著作權集中管理事業之社團法人。原告係受音樂（樂曲、\n    歌詞）著作之作詞者、作曲者及音樂出版業者等將其著作財\n    產權信託，對於音樂利用人進行使用授權、使用報酬之收受\n    及權利金之分配等業務之法人。原告之受任人社團法人中華\n    音樂著作權協會（下稱中華音樂著作權協會）係依據我國之\n    「著作權仲介團體條例」籌組，經主管機關許可成立，依法\n    辦理法人登記之音樂著作權仲介團體，乃具有法人格之組織\n    ，其受原告授權委託，管理原告音樂著作在我國（台澎金馬\n    ）之重製權，故其就被告未經原告授權而重製如附表一所示\n    之曲目，既已受原告之授權及委託，自得採取民事、刑事及\n    其他之保護權利之訴訟行為，此有授權契約及授權聲明為憑\n    。\n  (二)次按我國自91年1月1日加入世界貿易組織（下稱WTO）後，\n    與WTO現有全體會員體建立著作權互惠保護關係。而日本亦\n    為WTO會員體之一，依著作權法第4條第2款規定，日本人之\n    著作亦受我國著作權法保護，是於我國加入WTO後，利用日\n    本人之音樂著作（包括詞、曲），除有合理使用之情形外，\n    應取得授權。又依經濟部智慧財產局96年9月5日智著字第09\n    600075430號函釋意旨，我國加入WTO前，即將日本人之詞曲\n    音樂著作（日曲日詞）製成MIDI音樂之行為，歌詞部分，若\n    是以重現日文原文之方式利用日本歌詞，乃涉及重製該歌詞\n    之行為，依著作權法第106條之2第1項及第2項規定，利用人\n    自91年1月1日起至92年12月31日得繼續利用（包括重製及銷\n    售等），過渡期間屆滿後之利用，則須另行獲得著作財產權\n    人之授權，始得為之，如有違反，即有涉及侵害著作權民、\n    刑事責任之虞。復依經濟部智慧財產局96年9月5日智著字第\n    09600075430號函釋意旨，歌曲可能是著作權法第106條之2\n    第4項所規定之利用受保護之著作另行創作，亦可能為同法\n    第106條之3第1項及第2項所規定之衍生著作，惟其法律效果\n    均係利用人應對被利用著作之著作財產權人支付該著作一般\n    經自由磋商所應支付合理之使用報酬。故在我國加入WTO 之\n    前即已存在之將日本人之歌曲製成MIDI音樂之行為，我國利\n    用人原則上僅需向原來之權利人支付使用報酬即可繼續使用\n    （包括繼續重製、出租、公開演出、播送等），而不需再向\n    日本歌曲著作財產權人或音樂著作權仲介團體取得授權，亦\n    不須負侵害著作權之民、刑事責任。權利人或原權利人加入\n    音樂仲介團體時，對仲介團體而言，就此類MIDI音樂僅有民\n    事上之報酬請求權，並無刑事告訴權利。是原告除得請求侵\n    害重製權之侵權行為賠償金外，亦得就歌曲部分請求報酬。\n  (三)被告音圓公司為國內知名之電腦伴唱機製造商，係從事電腦\n    伴唱機製造、銷售及服務等業務，其於生產製造過程，使用\n    到音樂著作之行為核屬著作權法第3條第5款規定之重製行為\n    。而被告音圓公司明知如附表所示之歌曲係原告所管理之音\n    樂著作，未經原告之同意或授權，竟擅自重製於其生產製造\n    之電腦伴唱機中，顯已侵害原告所管理之音樂著作財產權。\n    原告之受任人中華音樂著作權協會於96年3月13日函請被告\n    音圓公司與受任人聯絡以取得合法授權未獲果，原告乃於96\n    年6月5日會同調查局嘉義調查站查扣其所製造之電腦伴唱機\n    、伴唱光碟、硬碟片及磁片。原告就被告音圓公司未經授權\n    擅自重製如附表所示之音樂著作，爰依著作權法第88條第1\n    項規定，請求其負損害賠償責任，並依著作權法第88條第3\n    項規定，請求100萬元之損害賠償。至被告乙○○為被告音\n    圓公司之負責人，依公司法第28條規定，應與被告音圓公司\n    負連帶損害賠償責任，爰請求如訴之聲明第1項前段所示。\n    另就歌曲之使用報酬及預付重製版稅部分，每首分別為3萬\n    元及2萬元，則每首著作以5萬元計算，而被告音圓公司重製\n    如附表所示之48首歌曲，應給付原告240萬元之音樂著作重\n    製使用報酬，爰請求如訴之聲明第1項後段所示。\n  (四)原告自西元1939年成立之著作權協會，管理日本音樂市場超\n    過90% 之音樂著作，並於網站上建立完善之檢索作品系統，\n    一般民眾皆已習慣依此系統查詢音樂著作，而日本文化廳之\n    查詢登錄系統，係建立於原告所提供之檢索作品系統之後，\n    且此套系統係特別針對未加入著作權管理團體之獨立音樂著\n    作財產權人而設計，方便一般民眾對於未有著作權管理團體\n    所管理之音樂著作，查詢真正權利人為何者，而另外向其取\n    得授權等。又日本著作權法第77條第1 款規定之立法目的係\n    為保障著作財產權移轉、處分時之交易安全，其所謂不得對\n    抗第三人，係指爭執真正權利人時得行使抗辯之主體，而非\n    指侵害著作財產權之人。被告既已知悉原告所屬網站有提供\n    查詢曲目之系統，卻未於該網站查詢本案系爭歌曲，僅以其\n    查詢日本文化廳之登錄情形，遽認原告主張重製權並無根據\n    ，其主張實不足採。並聲明：1.就侵權行為損害賠償部分，\n    被告音圓公司及乙○○應連帶給付原告100 萬元，就音樂著\n    作重製之使用報酬部分，被告音圓公司應給付原告240 萬元\n    ，及自起訴狀繕本送達翌日起至清償日止，按週年利率5%計\n    算之利息。2.訴訟費用由被告負擔。3.原告願供擔保，請准\n    宣告假執行。\n二、被告則以：\n  (一)中華音樂著作權協會既受原告委任提起本件訴訟，依最高法\n    院64年度第5 次民庭庭推總會議決定意旨，應列中華音樂著\n    作權協會之代表人丁○○為訴訟代理人，詎原告竟列非自然\n    人之中華音樂著作權協會為訴訟代理人，自與民事訴訟法第\n    68條規定有違，是原告之起訴不合法。又如附表編號34及44\n    所示之音樂著作既屬公共財，且編號34之曲及編號44之詞亦\n    無信託或授權予原告管理，原告自不得主張享有該音樂著作\n    之重製權，亦即原告無權向被告請求使用報酬。再者，被告\n    電腦伴唱機內之系爭歌曲「日曲日詞」係以MIDI電腦程式依\n    個人風格及國人演唱習慣改作並整合成另一獨立之音樂著作\n    ，自屬「衍生著作」，依著作權法第106 條之3 第1 項、第\n    2 項、第106 條之2 第3 項、第4 項規定及智慧財產局相關\n    函釋意旨，利用人與著作人，或利用人與著作權仲介團體間\n    之關係，僅生支付使用報酬之一般債權債務關係，與侵害著\n    作權民、刑事責任無涉。原告主張被告重製如附表所示之音\n    樂著作「日曲日詞」部分構成侵害著作權之行為，故應負損\n    害賠償責任，自不足採。又被告音圓公司對原告既不負侵權\n    行為損害賠償責任，其負責人即被告乙○○自無須依民法第\n    28條規定，與被告音圓公司連帶負損害賠償責任。\n  (二)中華音樂著作權協會於96年3 月13日（被告誤繕為96年3 月\n    3 日）代表原告發函被告音圓公司要求處理被告音圓公司電\n    腦伴唱機內之日文歌曲「重製權」之授權及支付使用報酬事\n    宜，被告音圓公司旋於96年3 月22日發函中華音樂著作權協\n    會表達願意配合辦理，並未拒絕支付使用報酬予原告。詎中\n    華音樂著作權協會僅要求被告音圓公司配合辦理「重製權」\n    之授權事宜，且拒不告知原告所管理之日文歌曲為何，被告\n    音圓公司仍盡力確認原告管理之日文歌曲範圍，自非不支付\n    使用報酬予原告。\n  (三)原告主張就歌曲之使用報酬及預付重製版稅部分，每首分別\n    為3 萬元及2 萬元，則每首著作以5 萬元計算，故被告音圓\n    公司應給付原告240 萬元之音樂著作重製使用報酬。然據中\n    華音樂著作權協會提出之台北市音樂著作權代理人協會MPA\n    有關電腦伴唱機重製授權之報價表，其中固就授權範圍包含\n    營業用及家用MIDI卡拉OK，建議授權費用為52,500元，惟被\n    告音圓公司之電腦伴唱機係家用型MIDI卡拉OK並非營業型，\n    縱依該報價表亦僅適用家用MIDI卡拉OK之31,500元，而非適\n    用營業用加家用MIDI卡拉OK之52,500元。況據原告所提出之\n    使用同意書第2 條第1 款約定，可知其係包括音樂著作及視\n    聽著作之重製授權契約，而非單純音樂著作之重製授權契約\n    ，故被告音圓公司僅須取得音樂著作重製之授權，不包括影\n    像部分（即視聽著作）重製之授權，原告自難援引作為請求\n    系爭音樂著作每首重製授權費為5 萬元之依據。並答辯聲明\n    ：1.原告之訴及假執行之聲明均駁回。2.訴訟費用由原告負\n    擔。3.如受不利判決，被告願供擔保，請准免為假執行。\n三、兩造不爭執之事實：\n  (一)被告提出如被證三、被證四及被證五所示之由經濟部智慧財\n    產局所作出之解釋函令，係就我國加入WTO 前已存在之「日\n    曲台詞」歌曲，我國利用人與著作權人，利用人與音樂著作\n    仲介團體間僅生支付使用報酬義務之債權債務關係，不生著\n    作權侵害民、刑事責任問題。\n  (二)原告與中華音樂著作權協會於2005年5 月1 日簽訂如原證三\n    所示之「CONTRACT OF UNILATERAL REPRESENTATION MECHAN\n    ICAL RIGHTS（單邊代表機械灌錄權合約）」，原告委託中\n    華音樂著作權協會管理其音樂著作在我國之「重製權」、中\n    華音樂著作權協會所在地區錄製或機械灌錄原告之曲目，並\n    在任何地點以任何形式發售錄製品與複製品，但圖像重製不\n    在此限。\n  (三)原告就告訴狀附表所示音樂著作有重製權之管理權限。\n四、本件兩造之主要爭點：\n  (一)本件起訴是否符合程式？\n  (二)被告伴唱機內所錄製之「日曲日詞」歌曲部分，是否屬於「\n    衍生著作」，屬獨立創作而無民事侵權責任？\n  (三)被告使用原告會員歌曲部分其報酬應如何計算？\n五、得心證之理由：\n  (一)查本件原告乃依日本著作權等管理事業法設立，於日本國內\n    經營音樂著作權集中管理事業之社團法人，而本件原告之受\n    任人社團法人中華音樂著作權協會（下稱中華音樂著作權協\n    會）係依據我國之「著作權仲介團體條例」籌組，經主管機\n    關許可成立，依法辦理法人登記之音樂著作權仲介團體，乃\n    具有法人格之組織，此部分事實亦有著作權仲介團體許可證\n    明書在卷可稽（參原證二）。又本件原告係受日本國內音樂\n    （樂曲、歌詞）著作之作詞者、作曲者及音樂出版業者等將\n    其著作財產權信託，對於音樂利用人進行使用授權、使用報\n    酬之收受及權利金之分配等業務之法人，本件請求中其受會\n    員信託之著作部分，有著作權信託契約書、著作權信託證書\n    、信託證書等影本附卷可考（參陳證二，即本院卷第228 頁\n    至第373 頁）。本件原告主張其會員之上開著作權遭被告侵\n    害，乃委任中華音樂著作權協會代為處理原告全部會員所信\n    託之音樂著作在我國（台澎金馬）之重製權（參原證三），\n    又原告與其受任人之間除簽訂上開契約書之外，就被告之侵\n    權行為，亦授權受任人即中華音樂著作權協會提起訴訟（參\n    原證四），而中華音樂著作權協會經受委任後，復轉而委任\n    其員工戊○○、丙○○為訴訟代理人，依代理之法律關係（\n    參民法第103 條），本件可認為原告係委任戊○○、丙○○\n    為訴訟代理人，是本件原告提起本件訴訟，於法尚無違誤，\n    合先敘明。\n  (二)本件原告就附表所示音樂著作有重製權之管理權限，此部分\n    事實業據原告提出信託文件影本在卷可稽，被告對此亦不爭\n    執（參本院卷第422 頁），堪信此部分事實為真正。而被告\n    對於其所生產銷售之伴唱機內確有附表所示之歌曲一情亦不\n    否認，惟辯稱其中「日曲日詞」歌曲部分乃屬於「衍生著作\n    」，屬獨立創作而無民事侵權責任云云。查被告就其上開辯\n    詞所提出之證據資料乃被證2 、3 、4 、5 、6 等智慧局所\n    為之函釋，惟查，智慧局上開函釋中，被證2 、3 、4 、5\n    均係就「日曲台詞」歌曲所為之解釋，與本件單純「日曲日\n    詞」之情形不同，而被證6 之函釋（即96年9 月5 日智著字\n    第號函，參本院卷第70頁），其中就歌詞部分是否構成「重\n    製」問題並無不同看法（參該函說明欄第二、(二)段），認為\n    仍屬文字之重製行為。至歌曲部分，智慧局之意見乃認為此\n    種MIDI歌曲「可能」是著作權法第106 條之2 第4 項所規定\n    之「利用受保護之著作另行創作」，「也可能」是同法第10\n    6 條之3 第1 、2 項所規定之「衍生著作」，故對於此種在\n    我國加入WTO 之前即已存在之將日本人之歌曲製成MIDI音樂\n    之行為，我國利用人原則上只要向原來之權利人支付使用報\n    酬即可繼續使用（包括繼續重製、出租、公開演出、播送等\n    ），而不需再向日本歌曲著作財產權人或音樂著作權仲介團\n    體取得授權，亦不需負侵害著作權之民、刑事責任等語（參\n    同上）。按所謂MIDI者，乃指Musical Instrument Digital\n    Interface 而言，係將聲音轉換為一種電子儀器或設備（例\n    如鍵盤或音效卡）可以讀取之資訊，MIDI為此種轉換行為提\n    供轉換之協定（protocol），使上開不同介面之數位儀器設\n    備均可讀取或了解此種訊號之意義，並進而將其呈現。此種\n    數位資料，雖然不是傳送聲音，而是傳送音調或是聲音信號\n    強弱程度之資料，惟此種將他人所創作之曲調檔案轉換成為\n    數位資料，乃係將原檔案以不同型態之格式儲存，透過可解\n    讀此種訊息之儀器或設備，例如電腦與音效卡，仍可將此種\n    訊號以人類五官可感受之旋律或聲音傳達出來。然因將他人\n    所創作之樂曲旋律，轉換成不同格式之訊號資料，性質上確\n    有將原著作之型態加以改變之情形，依著作權法第3 條第1\n    項第11款及第6 條規定意旨，此種經改變型態後之資料乃原\n    著作之改作，屬另一獨立著作，原告就此部分性質亦不爭執\n    ，僅主張被告應就此部分支付使用費。惟就歌詞部分，由於\n    此種文字之輸入必須以攝影、掃描、打字或其他方式書入，\n    因其就文字之內容並無任何型態上之改變，性質上乃重製行\n    為，被告就「日詞」之語文著作（文字著作）部分既未獲得\n    原告之授權，其擅自將原告會員之語文著作重製於其所製造\n    銷售之伴唱機內，自構成對原告會員歌詞部分之重製權之侵\n    害，殆無疑義。\n  (三)承上所述，本件被告就原告所提如附表所示其會員之音樂著\n    作，其中歌曲部分縱係屬於衍生著作，亦應依法支付使用報\n    酬予原告，惟其迄今均未支付任何款項予原告，原告本於著\n    作權法第106 條之2 規定就此部分訴請被告給付使用報酬，\n    自屬有據。而依據原告授權中華音樂著作權協會與其他伴唱\n    機產銷業者所簽訂之使用同意書顯示，其授權其他業者使用\n    音樂著作之計價標準，在影音同步之權利金部分為每首30,0\n    00元，重製費為每首20,000元（參陳證三，本院卷第375 頁\n    ），此一計價標準在其對外報價均屬相同（參陳證四，本院\n    卷第381 頁），被告既係從事伴唱機生產銷售之業者，其使\n    用原告系爭著作之情形與其他業者均類似，復無任何事由足\n    認其有應獲特別待遇之條件，就市場公平競爭之角度以觀，\n    原告請求被告就其使用如附表所示之音樂著作依上開標準支\n    付使用報酬，應屬有據，本件被告使用之歌曲合計為48首，\n    以每首之重製及使用費合計50,000元計算，被告就此部分應\n    給付原告之金額為240 萬元，原告就此部分之請求自有理由\n    。\n  (四)另就被告未獲得原告同意或授權之情形下即擅自重製其會員\n    歌詞之重製權部分，原告主張被告此部分之行為屬侵權行為\n    ，應賠償100 萬元云云。按損害賠償之制度在於賠償權利人\n    財產因侵權行為之發生所受之減損，是其制度在於彌補損害\n    ，而非在於彌補損害之外另外增加權利人之收益。至權利人\n    所受損害之程度，亦即權利人所得請求彌補之損失範圍，著\n    作權法第88條已設有計算之規定，考其規定內容，均在於彌\n    補權利人應得而未得之差額，尚無在應得而未得之財產損失\n    之外另外加給利益之情形，而除非權利人能證明侵害人之侵\n    權行為係故意且情節重大者，否則亦無同法條第3 項加倍賠\n    償規定之適用。本件原告因被告之侵權行為，其所受之損害\n    乃應收取之相關費用未能收取，此即其所受損害之範圍，而\n    原告對於其他同類業者之報價及收費，就重製部分均係以每\n    首歌20,000萬元計算，其中每首歌之定義係包括曲、詞二者\n    （參原告所提陳證三「使用同意書」第一條，本院卷第374\n    頁），顯然對原告而言，詞、曲二者之重製費為每首20,000\n    元，至於詞、曲二部分究竟如何分配上開收益，則未明文，\n    是以，不論究係對詞或曲所為之重製行為，其應收取之費用\n    最高均不超過20,000元，始為的論。本件原告因被告之侵權\n    行為，應收而未收之重製費每首20,000元即為其所受之損害\n    ，倘此一損害得以獲得彌補，即應認為原告之損失業已回復\n    ，其損失已不復存在，不應就已經填補而不存在之「損害」\n    再度請求「填補」，此為當然之理。本件原告對於被告未經\n    許可擅自重製及使用其會員歌曲之行為，業已請求被告支付\n    每首50,000元之價金，上開50,000元價金中包含詞曲之重製\n    費20,000元，換言之，原告所受之損害，業已因請求被告支\n    付上開價金而獲得填補，自無在於獲得填補之後，額外請求\n    被告就每首「詞」之部分再度支付侵害重製權之損害賠償，\n    否則依原告之請求，被告在支付每首詞、曲之重製費20,000\n    元後，尚需支付每首詞部分之重製費20,833元（損害賠償金\n    100 萬元除以48首歌詞），則顯然被告就此部分支付之金額\n    遠高於其他同業，而原告就此部分之損害於獲得填補後，另\n    額外獲得高於其向其他業者收取之費用收益，此顯非損害賠\n    償制度設計之目的。而原告就被告之行為是否屬「故意且情\n    節重大」之情形而有著作權法第88條第3 項規定之適用，既\n    未提出其他證據資料供本院佐參，則其在上開金額之外另外\n    請求被告應連帶賠償100 萬元，自無理由，應予駁回。\n  (五)綜上所述，本件被告未經原告之同意即擅自重製及使用原告\n    會員之著作，因此造成原告之損害，自應對此負損害賠償責\n    任。而本件原告因被告之侵權行為，其所受之損害乃應收取\n    之使用及重製費未能收取，是原告主張依其對被告同業收取\n    之費用標準請求被告支付每首歌曲50,000元，48首歌合計24\n    0 萬元，及自起訴狀繕本送達翌日即98年7 月23日起至清償\n    日止，按週年利率百分之五計算之利息，即有理由，應予准\n    許。至原告請求被告給付損害賠償金100 萬元部分，因屬重\n    複請求，自屬無據，應予駁回。\n六、假執行部分：\n    本件兩造均陳明願供擔保，請准宣告假執行或免為假執行，\n    於原告上開勝訴範圍內，經核均無不合，爰酌定相當擔保金\n    額分別准許之。至原告敗訴部分，其願供擔保為假執行之聲\n    請即失所附麗，應併予駁回，附此敘明。\n七、本件事證已臻明確，兩造其餘主張陳述及所提之證據，均毋\n    庸再予審酌，附此敘明。\n八、據上論結，本件原告之訴為一部有理由，一部無理由，依智\n    慧財產案件審理法第1 條、民事訴訟法第79條、第392 條，\n    判決如主文。\n中    華    民    國    99    年    1    月     5     日\n                    智慧財產法院第一庭\n                        法  官  汪漢卿\n以上正本係照原本作成\n如不服本判決，應於送達後20日內，向本院提出上訴狀並表明上\n訴理由，如於本判決宣示後送達前提起上訴者，應於判決送達後\n20日內補提上訴理由書（須按他造人數附繕本）。\n中    華    民    國    99    年    1    月     5     日\n                        書記官  邱于婷\n",
  "structure": {
    "main": "被告應給付原告新臺幣貳佰肆拾萬元，及自民國九十八年七月二\n十三日起至清償日止，按週年利率百分之五計算之利息。\n原告其餘之訴駁回。\n訴訟費用由被告負擔十分之七，餘由原告負擔。\n本判決第一項於原告以新臺幣捌拾萬元為被告供擔保後，得假執\n行。但被告於假執行程序實施前，以新台幣貳佰肆拾萬元為原告\n供擔保後，得免為假執行。\n原告其餘假執行之聲請駁回。",
    "fact": "壹、程序方面：\n一、依智慧財產案件審理法第7 條規定，智慧財產法院組織法第\n    3 條第1 款、第4 款所定之民事事件，由智慧財產法院管轄\n    。本案既屬因著作權法所保護之智慧財產權益所生之第一審\n    民事案件，符合智慧財產法院組織法第3 條第1 款規定，本\n    院依法自有管轄權，合先敘明。\n二、按訴狀送達後，原告不得將原訴變更或追加他訴，但請求之\n    基礎事實同一或擴張者或減縮應受判決事項之聲明者，不在\n    此限，民事訴訟法第255 條第1 項第2 款、第3 款定有明文\n    。本件原告起訴請求：(一)就侵權行為損害賠償部分，被告音\n    圓國際股份有限公司（下稱音圓公司）及乙○○應連帶給付\n    原告新臺幣（下同）100 萬元，就音樂著作重製之使用報酬\n    部分，被告音圓公司及乙○○應連帶給付原告245 萬元，及\n    自起訴狀繕本送達翌日起至清償日止，按週年利率5%計算之\n    利息。(二)訴訟費用由被告負擔。(三)原告願供擔保，請准宣告\n    假執行。嗣於民國98年9 月18日具狀變更第1 項聲明為：(一)\n    就侵權行為損害賠償部分，被告音圓公司及乙○○應連帶給\n    付原告100 萬元，就音樂著作重製之使用報酬部分，被告音\n    圓公司應給付原告245 萬元，及自起訴狀繕本送達翌日起至\n    清償日止，按週年利率5%計算之利息。復於98年11月4 日具\n    狀變更第1 項聲明為：(一)就侵權行為損害賠償部分，被告音\n    圓公司及乙○○應連帶給付原告100 萬元，就音樂著作重製\n    之使用報酬部分，被告音圓公司應給付原告240 萬元，及自\n    起訴狀繕本送達翌日起至清償日止，按週年利率5%計算之利\n    息。經核原告上開所為訴之聲明變更，係屬減縮應受判決事\n    項之聲明，且基於主張被告侵害其著作權之同一基礎事實，\n    是其訴之變更合於首揭規定，應予准許。\n貳、實體方面：\n一、原告主張：\n  (一)原告社團法人日本音樂著作權協（Japanese Society for\n    Rights of Authors, Composers and Publishers ，即JASR\n    AC）係依日本著作權等管理事業法設立，於日本國內經營音\n    樂著作權集中管理事業之社團法人。原告係受音樂（樂曲、\n    歌詞）著作之作詞者、作曲者及音樂出版業者等將其著作財\n    產權信託，對於音樂利用人進行使用授權、使用報酬之收受\n    及權利金之分配等業務之法人。原告之受任人社團法人中華\n    音樂著作權協會（下稱中華音樂著作權協會）係依據我國之\n    「著作權仲介團體條例」籌組，經主管機關許可成立，依法\n    辦理法人登記之音樂著作權仲介團體，乃具有法人格之組織\n    ，其受原告授權委託，管理原告音樂著作在我國（台澎金馬\n    ）之重製權，故其就被告未經原告授權而重製如附表一所示\n    之曲目，既已受原告之授權及委託，自得採取民事、刑事及\n    其他之保護權利之訴訟行為，此有授權契約及授權聲明為憑\n    。\n  (二)次按我國自91年1月1日加入世界貿易組織（下稱WTO）後，\n    與WTO現有全體會員體建立著作權互惠保護關係。而日本亦\n    為WTO會員體之一，依著作權法第4條第2款規定，日本人之\n    著作亦受我國著作權法保護，是於我國加入WTO後，利用日\n    本人之音樂著作（包括詞、曲），除有合理使用之情形外，\n    應取得授權。又依經濟部智慧財產局96年9月5日智著字第09\n    600075430號函釋意旨，我國加入WTO前，即將日本人之詞曲\n    音樂著作（日曲日詞）製成MIDI音樂之行為，歌詞部分，若\n    是以重現日文原文之方式利用日本歌詞，乃涉及重製該歌詞\n    之行為，依著作權法第106條之2第1項及第2項規定，利用人\n    自91年1月1日起至92年12月31日得繼續利用（包括重製及銷\n    售等），過渡期間屆滿後之利用，則須另行獲得著作財產權\n    人之授權，始得為之，如有違反，即有涉及侵害著作權民、\n    刑事責任之虞。復依經濟部智慧財產局96年9月5日智著字第\n    09600075430號函釋意旨，歌曲可能是著作權法第106條之2\n    第4項所規定之利用受保護之著作另行創作，亦可能為同法\n    第106條之3第1項及第2項所規定之衍生著作，惟其法律效果\n    均係利用人應對被利用著作之著作財產權人支付該著作一般\n    經自由磋商所應支付合理之使用報酬。故在我國加入WTO 之\n    前即已存在之將日本人之歌曲製成MIDI音樂之行為，我國利\n    用人原則上僅需向原來之權利人支付使用報酬即可繼續使用\n    （包括繼續重製、出租、公開演出、播送等），而不需再向\n    日本歌曲著作財產權人或音樂著作權仲介團體取得授權，亦\n    不須負侵害著作權之民、刑事責任。權利人或原權利人加入\n    音樂仲介團體時，對仲介團體而言，就此類MIDI音樂僅有民\n    事上之報酬請求權，並無刑事告訴權利。是原告除得請求侵\n    害重製權之侵權行為賠償金外，亦得就歌曲部分請求報酬。\n  (三)被告音圓公司為國內知名之電腦伴唱機製造商，係從事電腦\n    伴唱機製造、銷售及服務等業務，其於生產製造過程，使用\n    到音樂著作之行為核屬著作權法第3條第5款規定之重製行為\n    。而被告音圓公司明知如附表所示之歌曲係原告所管理之音\n    樂著作，未經原告之同意或授權，竟擅自重製於其生產製造\n    之電腦伴唱機中，顯已侵害原告所管理之音樂著作財產權。\n    原告之受任人中華音樂著作權協會於96年3月13日函請被告\n    音圓公司與受任人聯絡以取得合法授權未獲果，原告乃於96\n    年6月5日會同調查局嘉義調查站查扣其所製造之電腦伴唱機\n    、伴唱光碟、硬碟片及磁片。原告就被告音圓公司未經授權\n    擅自重製如附表所示之音樂著作，爰依著作權法第88條第1\n    項規定，請求其負損害賠償責任，並依著作權法第88條第3\n    項規定，請求100萬元之損害賠償。至被告乙○○為被告音\n    圓公司之負責人，依公司法第28條規定，應與被告音圓公司\n    負連帶損害賠償責任，爰請求如訴之聲明第1項前段所示。\n    另就歌曲之使用報酬及預付重製版稅部分，每首分別為3萬\n    元及2萬元，則每首著作以5萬元計算，而被告音圓公司重製\n    如附表所示之48首歌曲，應給付原告240萬元之音樂著作重\n    製使用報酬，爰請求如訴之聲明第1項後段所示。\n  (四)原告自西元1939年成立之著作權協會，管理日本音樂市場超\n    過90% 之音樂著作，並於網站上建立完善之檢索作品系統，\n    一般民眾皆已習慣依此系統查詢音樂著作，而日本文化廳之\n    查詢登錄系統，係建立於原告所提供之檢索作品系統之後，\n    且此套系統係特別針對未加入著作權管理團體之獨立音樂著\n    作財產權人而設計，方便一般民眾對於未有著作權管理團體\n    所管理之音樂著作，查詢真正權利人為何者，而另外向其取\n    得授權等。又日本著作權法第77條第1 款規定之立法目的係\n    為保障著作財產權移轉、處分時之交易安全，其所謂不得對\n    抗第三人，係指爭執真正權利人時得行使抗辯之主體，而非\n    指侵害著作財產權之人。被告既已知悉原告所屬網站有提供\n    查詢曲目之系統，卻未於該網站查詢本案系爭歌曲，僅以其\n    查詢日本文化廳之登錄情形，遽認原告主張重製權並無根據\n    ，其主張實不足採。並聲明：1.就侵權行為損害賠償部分，\n    被告音圓公司及乙○○應連帶給付原告100 萬元，就音樂著\n    作重製之使用報酬部分，被告音圓公司應給付原告240 萬元\n    ，及自起訴狀繕本送達翌日起至清償日止，按週年利率5%計\n    算之利息。2.訴訟費用由被告負擔。3.原告願供擔保，請准\n    宣告假執行。\n二、被告則以：\n  (一)中華音樂著作權協會既受原告委任提起本件訴訟，依最高法\n    院64年度第5 次民庭庭推總會議決定意旨，應列中華音樂著\n    作權協會之代表人丁○○為訴訟代理人，詎原告竟列非自然\n    人之中華音樂著作權協會為訴訟代理人，自與民事訴訟法第\n    68條規定有違，是原告之起訴不合法。又如附表編號34及44\n    所示之音樂著作既屬公共財，且編號34之曲及編號44之詞亦\n    無信託或授權予原告管理，原告自不得主張享有該音樂著作\n    之重製權，亦即原告無權向被告請求使用報酬。再者，被告\n    電腦伴唱機內之系爭歌曲「日曲日詞」係以MIDI電腦程式依\n    個人風格及國人演唱習慣改作並整合成另一獨立之音樂著作\n    ，自屬「衍生著作」，依著作權法第106 條之3 第1 項、第\n    2 項、第106 條之2 第3 項、第4 項規定及智慧財產局相關\n    函釋意旨，利用人與著作人，或利用人與著作權仲介團體間\n    之關係，僅生支付使用報酬之一般債權債務關係，與侵害著\n    作權民、刑事責任無涉。原告主張被告重製如附表所示之音\n    樂著作「日曲日詞」部分構成侵害著作權之行為，故應負損\n    害賠償責任，自不足採。又被告音圓公司對原告既不負侵權\n    行為損害賠償責任，其負責人即被告乙○○自無須依民法第\n    28條規定，與被告音圓公司連帶負損害賠償責任。\n  (二)中華音樂著作權協會於96年3 月13日（被告誤繕為96年3 月\n    3 日）代表原告發函被告音圓公司要求處理被告音圓公司電\n    腦伴唱機內之日文歌曲「重製權」之授權及支付使用報酬事\n    宜，被告音圓公司旋於96年3 月22日發函中華音樂著作權協\n    會表達願意配合辦理，並未拒絕支付使用報酬予原告。詎中\n    華音樂著作權協會僅要求被告音圓公司配合辦理「重製權」\n    之授權事宜，且拒不告知原告所管理之日文歌曲為何，被告\n    音圓公司仍盡力確認原告管理之日文歌曲範圍，自非不支付\n    使用報酬予原告。\n  (三)原告主張就歌曲之使用報酬及預付重製版稅部分，每首分別\n    為3 萬元及2 萬元，則每首著作以5 萬元計算，故被告音圓\n    公司應給付原告240 萬元之音樂著作重製使用報酬。然據中\n    華音樂著作權協會提出之台北市音樂著作權代理人協會MPA\n    有關電腦伴唱機重製授權之報價表，其中固就授權範圍包含\n    營業用及家用MIDI卡拉OK，建議授權費用為52,500元，惟被\n    告音圓公司之電腦伴唱機係家用型MIDI卡拉OK並非營業型，\n    縱依該報價表亦僅適用家用MIDI卡拉OK之31,500元，而非適\n    用營業用加家用MIDI卡拉OK之52,500元。況據原告所提出之\n    使用同意書第2 條第1 款約定，可知其係包括音樂著作及視\n    聽著作之重製授權契約，而非單純音樂著作之重製授權契約\n    ，故被告音圓公司僅須取得音樂著作重製之授權，不包括影\n    像部分（即視聽著作）重製之授權，原告自難援引作為請求\n    系爭音樂著作每首重製授權費為5 萬元之依據。並答辯聲明\n    ：1.原告之訴及假執行之聲明均駁回。2.訴訟費用由原告負\n    擔。3.如受不利判決，被告願供擔保，請准免為假執行。\n三、兩造不爭執之事實：\n  (一)被告提出如被證三、被證四及被證五所示之由經濟部智慧財\n    產局所作出之解釋函令，係就我國加入WTO 前已存在之「日\n    曲台詞」歌曲，我國利用人與著作權人，利用人與音樂著作\n    仲介團體間僅生支付使用報酬義務之債權債務關係，不生著\n    作權侵害民、刑事責任問題。\n  (二)原告與中華音樂著作權協會於2005年5 月1 日簽訂如原證三\n    所示之「CONTRACT OF UNILATERAL REPRESENTATION MECHAN\n    ICAL RIGHTS（單邊代表機械灌錄權合約）」，原告委託中\n    華音樂著作權協會管理其音樂著作在我國之「重製權」、中\n    華音樂著作權協會所在地區錄製或機械灌錄原告之曲目，並\n    在任何地點以任何形式發售錄製品與複製品，但圖像重製不\n    在此限。\n  (三)原告就告訴狀附表所示音樂著作有重製權之管理權限。\n四、本件兩造之主要爭點：\n  (一)本件起訴是否符合程式？\n  (二)被告伴唱機內所錄製之「日曲日詞」歌曲部分，是否屬於「\n    衍生著作」，屬獨立創作而無民事侵權責任？\n  (三)被告使用原告會員歌曲部分其報酬應如何計算？\n五、得心證之理由：\n  (一)查本件原告乃依日本著作權等管理事業法設立，於日本國內\n    經營音樂著作權集中管理事業之社團法人，而本件原告之受\n    任人社團法人中華音樂著作權協會（下稱中華音樂著作權協\n    會）係依據我國之「著作權仲介團體條例」籌組，經主管機\n    關許可成立，依法辦理法人登記之音樂著作權仲介團體，乃\n    具有法人格之組織，此部分事實亦有著作權仲介團體許可證\n    明書在卷可稽（參原證二）。又本件原告係受日本國內音樂\n    （樂曲、歌詞）著作之作詞者、作曲者及音樂出版業者等將\n    其著作財產權信託，對於音樂利用人進行使用授權、使用報\n    酬之收受及權利金之分配等業務之法人，本件請求中其受會\n    員信託之著作部分，有著作權信託契約書、著作權信託證書\n    、信託證書等影本附卷可考（參陳證二，即本院卷第228 頁\n    至第373 頁）。本件原告主張其會員之上開著作權遭被告侵\n    害，乃委任中華音樂著作權協會代為處理原告全部會員所信\n    託之音樂著作在我國（台澎金馬）之重製權（參原證三），\n    又原告與其受任人之間除簽訂上開契約書之外，就被告之侵\n    權行為，亦授權受任人即中華音樂著作權協會提起訴訟（參\n    原證四），而中華音樂著作權協會經受委任後，復轉而委任\n    其員工戊○○、丙○○為訴訟代理人，依代理之法律關係（\n    參民法第103 條），本件可認為原告係委任戊○○、丙○○\n    為訴訟代理人，是本件原告提起本件訴訟，於法尚無違誤，\n    合先敘明。\n  (二)本件原告就附表所示音樂著作有重製權之管理權限，此部分\n    事實業據原告提出信託文件影本在卷可稽，被告對此亦不爭\n    執（參本院卷第422 頁），堪信此部分事實為真正。而被告\n    對於其所生產銷售之伴唱機內確有附表所示之歌曲一情亦不\n    否認，惟辯稱其中「日曲日詞」歌曲部分乃屬於「衍生著作\n    」，屬獨立創作而無民事侵權責任云云。查被告就其上開辯\n    詞所提出之證據資料乃被證2 、3 、4 、5 、6 等智慧局所\n    為之函釋，惟查，智慧局上開函釋中，被證2 、3 、4 、5\n    均係就「日曲台詞」歌曲所為之解釋，與本件單純「日曲日\n    詞」之情形不同，而被證6 之函釋（即96年9 月5 日智著字\n    第號函，參本院卷第70頁），其中就歌詞部分是否構成「重\n    製」問題並無不同看法（參該函說明欄第二、(二)段），認為\n    仍屬文字之重製行為。至歌曲部分，智慧局之意見乃認為此\n    種MIDI歌曲「可能」是著作權法第106 條之2 第4 項所規定\n    之「利用受保護之著作另行創作」，「也可能」是同法第10\n    6 條之3 第1 、2 項所規定之「衍生著作」，故對於此種在\n    我國加入WTO 之前即已存在之將日本人之歌曲製成MIDI音樂\n    之行為，我國利用人原則上只要向原來之權利人支付使用報\n    酬即可繼續使用（包括繼續重製、出租、公開演出、播送等\n    ），而不需再向日本歌曲著作財產權人或音樂著作權仲介團\n    體取得授權，亦不需負侵害著作權之民、刑事責任等語（參\n    同上）。按所謂MIDI者，乃指Musical Instrument Digital\n    Interface 而言，係將聲音轉換為一種電子儀器或設備（例\n    如鍵盤或音效卡）可以讀取之資訊，MIDI為此種轉換行為提\n    供轉換之協定（protocol），使上開不同介面之數位儀器設\n    備均可讀取或了解此種訊號之意義，並進而將其呈現。此種\n    數位資料，雖然不是傳送聲音，而是傳送音調或是聲音信號\n    強弱程度之資料，惟此種將他人所創作之曲調檔案轉換成為\n    數位資料，乃係將原檔案以不同型態之格式儲存，透過可解\n    讀此種訊息之儀器或設備，例如電腦與音效卡，仍可將此種\n    訊號以人類五官可感受之旋律或聲音傳達出來。然因將他人\n    所創作之樂曲旋律，轉換成不同格式之訊號資料，性質上確\n    有將原著作之型態加以改變之情形，依著作權法第3 條第1\n    項第11款及第6 條規定意旨，此種經改變型態後之資料乃原\n    著作之改作，屬另一獨立著作，原告就此部分性質亦不爭執\n    ，僅主張被告應就此部分支付使用費。惟就歌詞部分，由於\n    此種文字之輸入必須以攝影、掃描、打字或其他方式書入，\n    因其就文字之內容並無任何型態上之改變，性質上乃重製行\n    為，被告就「日詞」之語文著作（文字著作）部分既未獲得\n    原告之授權，其擅自將原告會員之語文著作重製於其所製造\n    銷售之伴唱機內，自構成對原告會員歌詞部分之重製權之侵\n    害，殆無疑義。\n  (三)承上所述，本件被告就原告所提如附表所示其會員之音樂著\n    作，其中歌曲部分縱係屬於衍生著作，亦應依法支付使用報\n    酬予原告，惟其迄今均未支付任何款項予原告，原告本於著\n    作權法第106 條之2 規定就此部分訴請被告給付使用報酬，\n    自屬有據。而依據原告授權中華音樂著作權協會與其他伴唱\n    機產銷業者所簽訂之使用同意書顯示，其授權其他業者使用\n    音樂著作之計價標準，在影音同步之權利金部分為每首30,0\n    00元，重製費為每首20,000元（參陳證三，本院卷第375 頁\n    ），此一計價標準在其對外報價均屬相同（參陳證四，本院\n    卷第381 頁），被告既係從事伴唱機生產銷售之業者，其使\n    用原告系爭著作之情形與其他業者均類似，復無任何事由足\n    認其有應獲特別待遇之條件，就市場公平競爭之角度以觀，\n    原告請求被告就其使用如附表所示之音樂著作依上開標準支\n    付使用報酬，應屬有據，本件被告使用之歌曲合計為48首，\n    以每首之重製及使用費合計50,000元計算，被告就此部分應\n    給付原告之金額為240 萬元，原告就此部分之請求自有理由\n    。\n  (四)另就被告未獲得原告同意或授權之情形下即擅自重製其會員\n    歌詞之重製權部分，原告主張被告此部分之行為屬侵權行為\n    ，應賠償100 萬元云云。按損害賠償之制度在於賠償權利人\n    財產因侵權行為之發生所受之減損，是其制度在於彌補損害\n    ，而非在於彌補損害之外另外增加權利人之收益。至權利人\n    所受損害之程度，亦即權利人所得請求彌補之損失範圍，著\n    作權法第88條已設有計算之規定，考其規定內容，均在於彌\n    補權利人應得而未得之差額，尚無在應得而未得之財產損失\n    之外另外加給利益之情形，而除非權利人能證明侵害人之侵\n    權行為係故意且情節重大者，否則亦無同法條第3 項加倍賠\n    償規定之適用。本件原告因被告之侵權行為，其所受之損害\n    乃應收取之相關費用未能收取，此即其所受損害之範圍，而\n    原告對於其他同類業者之報價及收費，就重製部分均係以每\n    首歌20,000萬元計算，其中每首歌之定義係包括曲、詞二者\n    （參原告所提陳證三「使用同意書」第一條，本院卷第374\n    頁），顯然對原告而言，詞、曲二者之重製費為每首20,000\n    元，至於詞、曲二部分究竟如何分配上開收益，則未明文，\n    是以，不論究係對詞或曲所為之重製行為，其應收取之費用\n    最高均不超過20,000元，始為的論。本件原告因被告之侵權\n    行為，應收而未收之重製費每首20,000元即為其所受之損害\n    ，倘此一損害得以獲得彌補，即應認為原告之損失業已回復\n    ，其損失已不復存在，不應就已經填補而不存在之「損害」\n    再度請求「填補」，此為當然之理。本件原告對於被告未經\n    許可擅自重製及使用其會員歌曲之行為，業已請求被告支付\n    每首50,000元之價金，上開50,000元價金中包含詞曲之重製\n    費20,000元，換言之，原告所受之損害，業已因請求被告支\n    付上開價金而獲得填補，自無在於獲得填補之後，額外請求\n    被告就每首「詞」之部分再度支付侵害重製權之損害賠償，\n    否則依原告之請求，被告在支付每首詞、曲之重製費20,000\n    元後，尚需支付每首詞部分之重製費20,833元（損害賠償金\n    100 萬元除以48首歌詞），則顯然被告就此部分支付之金額\n    遠高於其他同業，而原告就此部分之損害於獲得填補後，另\n    額外獲得高於其向其他業者收取之費用收益，此顯非損害賠\n    償制度設計之目的。而原告就被告之行為是否屬「故意且情\n    節重大」之情形而有著作權法第88條第3 項規定之適用，既\n    未提出其他證據資料供本院佐參，則其在上開金額之外另外\n    請求被告應連帶賠償100 萬元，自無理由，應予駁回。\n  (五)綜上所述，本件被告未經原告之同意即擅自重製及使用原告\n    會員之著作，因此造成原告之損害，自應對此負損害賠償責\n    任。而本件原告因被告之侵權行為，其所受之損害乃應收取\n    之使用及重製費未能收取，是原告主張依其對被告同業收取\n    之費用標準請求被告支付每首歌曲50,000元，48首歌合計24\n    0 萬元，及自起訴狀繕本送達翌日即98年7 月23日起至清償\n    日止，按週年利率百分之五計算之利息，即有理由，應予准\n    許。至原告請求被告給付損害賠償金100 萬元部分，因屬重\n    複請求，自屬無據，應予駁回。\n六、假執行部分：\n    本件兩造均陳明願供擔保，請准宣告假執行或免為假執行，\n    於原告上開勝訴範圍內，經核均無不合，爰酌定相當擔保金\n    額分別准許之。至原告敗訴部分，其願供擔保為假執行之聲\n    請即失所附麗，應併予駁回，附此敘明。\n七、本件事證已臻明確，兩造其餘主張陳述及所提之證據，均毋\n    庸再予審酌，附此敘明。\n八、據上論結，本件原告之訴為一部有理由，一部無理由，依智\n    慧財產案件審理法第1 條、民事訴訟法第79條、第392 條，\n    判決如主文。",
    "reason": "壹、程序方面：\n一、依智慧財產案件審理法第7 條規定，智慧財產法院組織法第\n    3 條第1 款、第4 款所定之民事事件，由智慧財產法院管轄\n    。本案既屬因著作權法所保護之智慧財產權益所生之第一審\n    民事案件，符合智慧財產法院組織法第3 條第1 款規定，本\n    院依法自有管轄權，合先敘明。\n二、按訴狀送達後，原告不得將原訴變更或追加他訴，但請求之\n    基礎事實同一或擴張者或減縮應受判決事項之聲明者，不在\n    此限，民事訴訟法第255 條第1 項第2 款、第3 款定有明文\n    。本件原告起訴請求：(一)就侵權行為損害賠償部分，被告音\n    圓國際股份有限公司（下稱音圓公司）及乙○○應連帶給付\n    原告新臺幣（下同）100 萬元，就音樂著作重製之使用報酬\n    部分，被告音圓公司及乙○○應連帶給付原告245 萬元，及\n    自起訴狀繕本送達翌日起至清償日止，按週年利率5%計算之\n    利息。(二)訴訟費用由被告負擔。(三)原告願供擔保，請准宣告\n    假執行。嗣於民國98年9 月18日具狀變更第1 項聲明為：(一)\n    就侵權行為損害賠償部分，被告音圓公司及乙○○應連帶給\n    付原告100 萬元，就音樂著作重製之使用報酬部分，被告音\n    圓公司應給付原告245 萬元，及自起訴狀繕本送達翌日起至\n    清償日止，按週年利率5%計算之利息。復於98年11月4 日具\n    狀變更第1 項聲明為：(一)就侵權行為損害賠償部分，被告音\n    圓公司及乙○○應連帶給付原告100 萬元，就音樂著作重製\n    之使用報酬部分，被告音圓公司應給付原告240 萬元，及自\n    起訴狀繕本送達翌日起至清償日止，按週年利率5%計算之利\n    息。經核原告上開所為訴之聲明變更，係屬減縮應受判決事\n    項之聲明，且基於主張被告侵害其著作權之同一基礎事實，\n    是其訴之變更合於首揭規定，應予准許。\n貳、實體方面：\n一、原告主張：\n  (一)原告社團法人日本音樂著作權協（Japanese Society for\n    Rights of Authors, Composers and Publishers ，即JASR\n    AC）係依日本著作權等管理事業法設立，於日本國內經營音\n    樂著作權集中管理事業之社團法人。原告係受音樂（樂曲、\n    歌詞）著作之作詞者、作曲者及音樂出版業者等將其著作財\n    產權信託，對於音樂利用人進行使用授權、使用報酬之收受\n    及權利金之分配等業務之法人。原告之受任人社團法人中華\n    音樂著作權協會（下稱中華音樂著作權協會）係依據我國之\n    「著作權仲介團體條例」籌組，經主管機關許可成立，依法\n    辦理法人登記之音樂著作權仲介團體，乃具有法人格之組織\n    ，其受原告授權委託，管理原告音樂著作在我國（台澎金馬\n    ）之重製權，故其就被告未經原告授權而重製如附表一所示\n    之曲目，既已受原告之授權及委託，自得採取民事、刑事及\n    其他之保護權利之訴訟行為，此有授權契約及授權聲明為憑\n    。\n  (二)次按我國自91年1月1日加入世界貿易組織（下稱WTO）後，\n    與WTO現有全體會員體建立著作權互惠保護關係。而日本亦\n    為WTO會員體之一，依著作權法第4條第2款規定，日本人之\n    著作亦受我國著作權法保護，是於我國加入WTO後，利用日\n    本人之音樂著作（包括詞、曲），除有合理使用之情形外，\n    應取得授權。又依經濟部智慧財產局96年9月5日智著字第09\n    600075430號函釋意旨，我國加入WTO前，即將日本人之詞曲\n    音樂著作（日曲日詞）製成MIDI音樂之行為，歌詞部分，若\n    是以重現日文原文之方式利用日本歌詞，乃涉及重製該歌詞\n    之行為，依著作權法第106條之2第1項及第2項規定，利用人\n    自91年1月1日起至92年12月31日得繼續利用（包括重製及銷\n    售等），過渡期間屆滿後之利用，則須另行獲得著作財產權\n    人之授權，始得為之，如有違反，即有涉及侵害著作權民、\n    刑事責任之虞。復依經濟部智慧財產局96年9月5日智著字第\n    09600075430號函釋意旨，歌曲可能是著作權法第106條之2\n    第4項所規定之利用受保護之著作另行創作，亦可能為同法\n    第106條之3第1項及第2項所規定之衍生著作，惟其法律效果\n    均係利用人應對被利用著作之著作財產權人支付該著作一般\n    經自由磋商所應支付合理之使用報酬。故在我國加入WTO 之\n    前即已存在之將日本人之歌曲製成MIDI音樂之行為，我國利\n    用人原則上僅需向原來之權利人支付使用報酬即可繼續使用\n    （包括繼續重製、出租、公開演出、播送等），而不需再向\n    日本歌曲著作財產權人或音樂著作權仲介團體取得授權，亦\n    不須負侵害著作權之民、刑事責任。權利人或原權利人加入\n    音樂仲介團體時，對仲介團體而言，就此類MIDI音樂僅有民\n    事上之報酬請求權，並無刑事告訴權利。是原告除得請求侵\n    害重製權之侵權行為賠償金外，亦得就歌曲部分請求報酬。\n  (三)被告音圓公司為國內知名之電腦伴唱機製造商，係從事電腦\n    伴唱機製造、銷售及服務等業務，其於生產製造過程，使用\n    到音樂著作之行為核屬著作權法第3條第5款規定之重製行為\n    。而被告音圓公司明知如附表所示之歌曲係原告所管理之音\n    樂著作，未經原告之同意或授權，竟擅自重製於其生產製造\n    之電腦伴唱機中，顯已侵害原告所管理之音樂著作財產權。\n    原告之受任人中華音樂著作權協會於96年3月13日函請被告\n    音圓公司與受任人聯絡以取得合法授權未獲果，原告乃於96\n    年6月5日會同調查局嘉義調查站查扣其所製造之電腦伴唱機\n    、伴唱光碟、硬碟片及磁片。原告就被告音圓公司未經授權\n    擅自重製如附表所示之音樂著作，爰依著作權法第88條第1\n    項規定，請求其負損害賠償責任，並依著作權法第88條第3\n    項規定，請求100萬元之損害賠償。至被告乙○○為被告音\n    圓公司之負責人，依公司法第28條規定，應與被告音圓公司\n    負連帶損害賠償責任，爰請求如訴之聲明第1項前段所示。\n    另就歌曲之使用報酬及預付重製版稅部分，每首分別為3萬\n    元及2萬元，則每首著作以5萬元計算，而被告音圓公司重製\n    如附表所示之48首歌曲，應給付原告240萬元之音樂著作重\n    製使用報酬，爰請求如訴之聲明第1項後段所示。\n  (四)原告自西元1939年成立之著作權協會，管理日本音樂市場超\n    過90% 之音樂著作，並於網站上建立完善之檢索作品系統，\n    一般民眾皆已習慣依此系統查詢音樂著作，而日本文化廳之\n    查詢登錄系統，係建立於原告所提供之檢索作品系統之後，\n    且此套系統係特別針對未加入著作權管理團體之獨立音樂著\n    作財產權人而設計，方便一般民眾對於未有著作權管理團體\n    所管理之音樂著作，查詢真正權利人為何者，而另外向其取\n    得授權等。又日本著作權法第77條第1 款規定之立法目的係\n    為保障著作財產權移轉、處分時之交易安全，其所謂不得對\n    抗第三人，係指爭執真正權利人時得行使抗辯之主體，而非\n    指侵害著作財產權之人。被告既已知悉原告所屬網站有提供\n    查詢曲目之系統，卻未於該網站查詢本案系爭歌曲，僅以其\n    查詢日本文化廳之登錄情形，遽認原告主張重製權並無根據\n    ，其主張實不足採。並聲明：1.就侵權行為損害賠償部分，\n    被告音圓公司及乙○○應連帶給付原告100 萬元，就音樂著\n    作重製之使用報酬部分，被告音圓公司應給付原告240 萬元\n    ，及自起訴狀繕本送達翌日起至清償日止，按週年利率5%計\n    算之利息。2.訴訟費用由被告負擔。3.原告願供擔保，請准\n    宣告假執行。\n二、被告則以：\n  (一)中華音樂著作權協會既受原告委任提起本件訴訟，依最高法\n    院64年度第5 次民庭庭推總會議決定意旨，應列中華音樂著\n    作權協會之代表人丁○○為訴訟代理人，詎原告竟列非自然\n    人之中華音樂著作權協會為訴訟代理人，自與民事訴訟法第\n    68條規定有違，是原告之起訴不合法。又如附表編號34及44\n    所示之音樂著作既屬公共財，且編號34之曲及編號44之詞亦\n    無信託或授權予原告管理，原告自不得主張享有該音樂著作\n    之重製權，亦即原告無權向被告請求使用報酬。再者，被告\n    電腦伴唱機內之系爭歌曲「日曲日詞」係以MIDI電腦程式依\n    個人風格及國人演唱習慣改作並整合成另一獨立之音樂著作\n    ，自屬「衍生著作」，依著作權法第106 條之3 第1 項、第\n    2 項、第106 條之2 第3 項、第4 項規定及智慧財產局相關\n    函釋意旨，利用人與著作人，或利用人與著作權仲介團體間\n    之關係，僅生支付使用報酬之一般債權債務關係，與侵害著\n    作權民、刑事責任無涉。原告主張被告重製如附表所示之音\n    樂著作「日曲日詞」部分構成侵害著作權之行為，故應負損\n    害賠償責任，自不足採。又被告音圓公司對原告既不負侵權\n    行為損害賠償責任，其負責人即被告乙○○自無須依民法第\n    28條規定，與被告音圓公司連帶負損害賠償責任。\n  (二)中華音樂著作權協會於96年3 月13日（被告誤繕為96年3 月\n    3 日）代表原告發函被告音圓公司要求處理被告音圓公司電\n    腦伴唱機內之日文歌曲「重製權」之授權及支付使用報酬事\n    宜，被告音圓公司旋於96年3 月22日發函中華音樂著作權協\n    會表達願意配合辦理，並未拒絕支付使用報酬予原告。詎中\n    華音樂著作權協會僅要求被告音圓公司配合辦理「重製權」\n    之授權事宜，且拒不告知原告所管理之日文歌曲為何，被告\n    音圓公司仍盡力確認原告管理之日文歌曲範圍，自非不支付\n    使用報酬予原告。\n  (三)原告主張就歌曲之使用報酬及預付重製版稅部分，每首分別\n    為3 萬元及2 萬元，則每首著作以5 萬元計算，故被告音圓\n    公司應給付原告240 萬元之音樂著作重製使用報酬。然據中\n    華音樂著作權協會提出之台北市音樂著作權代理人協會MPA\n    有關電腦伴唱機重製授權之報價表，其中固就授權範圍包含\n    營業用及家用MIDI卡拉OK，建議授權費用為52,500元，惟被\n    告音圓公司之電腦伴唱機係家用型MIDI卡拉OK並非營業型，\n    縱依該報價表亦僅適用家用MIDI卡拉OK之31,500元，而非適\n    用營業用加家用MIDI卡拉OK之52,500元。況據原告所提出之\n    使用同意書第2 條第1 款約定，可知其係包括音樂著作及視\n    聽著作之重製授權契約，而非單純音樂著作之重製授權契約\n    ，故被告音圓公司僅須取得音樂著作重製之授權，不包括影\n    像部分（即視聽著作）重製之授權，原告自難援引作為請求\n    系爭音樂著作每首重製授權費為5 萬元之依據。並答辯聲明\n    ：1.原告之訴及假執行之聲明均駁回。2.訴訟費用由原告負\n    擔。3.如受不利判決，被告願供擔保，請准免為假執行。\n三、兩造不爭執之事實：\n  (一)被告提出如被證三、被證四及被證五所示之由經濟部智慧財\n    產局所作出之解釋函令，係就我國加入WTO 前已存在之「日\n    曲台詞」歌曲，我國利用人與著作權人，利用人與音樂著作\n    仲介團體間僅生支付使用報酬義務之債權債務關係，不生著\n    作權侵害民、刑事責任問題。\n  (二)原告與中華音樂著作權協會於2005年5 月1 日簽訂如原證三\n    所示之「CONTRACT OF UNILATERAL REPRESENTATION MECHAN\n    ICAL RIGHTS（單邊代表機械灌錄權合約）」，原告委託中\n    華音樂著作權協會管理其音樂著作在我國之「重製權」、中\n    華音樂著作權協會所在地區錄製或機械灌錄原告之曲目，並\n    在任何地點以任何形式發售錄製品與複製品，但圖像重製不\n    在此限。\n  (三)原告就告訴狀附表所示音樂著作有重製權之管理權限。\n四、本件兩造之主要爭點：\n  (一)本件起訴是否符合程式？\n  (二)被告伴唱機內所錄製之「日曲日詞」歌曲部分，是否屬於「\n    衍生著作」，屬獨立創作而無民事侵權責任？\n  (三)被告使用原告會員歌曲部分其報酬應如何計算？\n五、得心證之理由：\n  (一)查本件原告乃依日本著作權等管理事業法設立，於日本國內\n    經營音樂著作權集中管理事業之社團法人，而本件原告之受\n    任人社團法人中華音樂著作權協會（下稱中華音樂著作權協\n    會）係依據我國之「著作權仲介團體條例」籌組，經主管機\n    關許可成立，依法辦理法人登記之音樂著作權仲介團體，乃\n    具有法人格之組織，此部分事實亦有著作權仲介團體許可證\n    明書在卷可稽（參原證二）。又本件原告係受日本國內音樂\n    （樂曲、歌詞）著作之作詞者、作曲者及音樂出版業者等將\n    其著作財產權信託，對於音樂利用人進行使用授權、使用報\n    酬之收受及權利金之分配等業務之法人，本件請求中其受會\n    員信託之著作部分，有著作權信託契約書、著作權信託證書\n    、信託證書等影本附卷可考（參陳證二，即本院卷第228 頁\n    至第373 頁）。本件原告主張其會員之上開著作權遭被告侵\n    害，乃委任中華音樂著作權協會代為處理原告全部會員所信\n    託之音樂著作在我國（台澎金馬）之重製權（參原證三），\n    又原告與其受任人之間除簽訂上開契約書之外，就被告之侵\n    權行為，亦授權受任人即中華音樂著作權協會提起訴訟（參\n    原證四），而中華音樂著作權協會經受委任後，復轉而委任\n    其員工戊○○、丙○○為訴訟代理人，依代理之法律關係（\n    參民法第103 條），本件可認為原告係委任戊○○、丙○○\n    為訴訟代理人，是本件原告提起本件訴訟，於法尚無違誤，\n    合先敘明。\n  (二)本件原告就附表所示音樂著作有重製權之管理權限，此部分\n    事實業據原告提出信託文件影本在卷可稽，被告對此亦不爭\n    執（參本院卷第422 頁），堪信此部分事實為真正。而被告\n    對於其所生產銷售之伴唱機內確有附表所示之歌曲一情亦不\n    否認，惟辯稱其中「日曲日詞」歌曲部分乃屬於「衍生著作\n    」，屬獨立創作而無民事侵權責任云云。查被告就其上開辯\n    詞所提出之證據資料乃被證2 、3 、4 、5 、6 等智慧局所\n    為之函釋，惟查，智慧局上開函釋中，被證2 、3 、4 、5\n    均係就「日曲台詞」歌曲所為之解釋，與本件單純「日曲日\n    詞」之情形不同，而被證6 之函釋（即96年9 月5 日智著字\n    第號函，參本院卷第70頁），其中就歌詞部分是否構成「重\n    製」問題並無不同看法（參該函說明欄第二、(二)段），認為\n    仍屬文字之重製行為。至歌曲部分，智慧局之意見乃認為此\n    種MIDI歌曲「可能」是著作權法第106 條之2 第4 項所規定\n    之「利用受保護之著作另行創作」，「也可能」是同法第10\n    6 條之3 第1 、2 項所規定之「衍生著作」，故對於此種在\n    我國加入WTO 之前即已存在之將日本人之歌曲製成MIDI音樂\n    之行為，我國利用人原則上只要向原來之權利人支付使用報\n    酬即可繼續使用（包括繼續重製、出租、公開演出、播送等\n    ），而不需再向日本歌曲著作財產權人或音樂著作權仲介團\n    體取得授權，亦不需負侵害著作權之民、刑事責任等語（參\n    同上）。按所謂MIDI者，乃指Musical Instrument Digital\n    Interface 而言，係將聲音轉換為一種電子儀器或設備（例\n    如鍵盤或音效卡）可以讀取之資訊，MIDI為此種轉換行為提\n    供轉換之協定（protocol），使上開不同介面之數位儀器設\n    備均可讀取或了解此種訊號之意義，並進而將其呈現。此種\n    數位資料，雖然不是傳送聲音，而是傳送音調或是聲音信號\n    強弱程度之資料，惟此種將他人所創作之曲調檔案轉換成為\n    數位資料，乃係將原檔案以不同型態之格式儲存，透過可解\n    讀此種訊息之儀器或設備，例如電腦與音效卡，仍可將此種\n    訊號以人類五官可感受之旋律或聲音傳達出來。然因將他人\n    所創作之樂曲旋律，轉換成不同格式之訊號資料，性質上確\n    有將原著作之型態加以改變之情形，依著作權法第3 條第1\n    項第11款及第6 條規定意旨，此種經改變型態後之資料乃原\n    著作之改作，屬另一獨立著作，原告就此部分性質亦不爭執\n    ，僅主張被告應就此部分支付使用費。惟就歌詞部分，由於\n    此種文字之輸入必須以攝影、掃描、打字或其他方式書入，\n    因其就文字之內容並無任何型態上之改變，性質上乃重製行\n    為，被告就「日詞」之語文著作（文字著作）部分既未獲得\n    原告之授權，其擅自將原告會員之語文著作重製於其所製造\n    銷售之伴唱機內，自構成對原告會員歌詞部分之重製權之侵\n    害，殆無疑義。\n  (三)承上所述，本件被告就原告所提如附表所示其會員之音樂著\n    作，其中歌曲部分縱係屬於衍生著作，亦應依法支付使用報\n    酬予原告，惟其迄今均未支付任何款項予原告，原告本於著\n    作權法第106 條之2 規定就此部分訴請被告給付使用報酬，\n    自屬有據。而依據原告授權中華音樂著作權協會與其他伴唱\n    機產銷業者所簽訂之使用同意書顯示，其授權其他業者使用\n    音樂著作之計價標準，在影音同步之權利金部分為每首30,0\n    00元，重製費為每首20,000元（參陳證三，本院卷第375 頁\n    ），此一計價標準在其對外報價均屬相同（參陳證四，本院\n    卷第381 頁），被告既係從事伴唱機生產銷售之業者，其使\n    用原告系爭著作之情形與其他業者均類似，復無任何事由足\n    認其有應獲特別待遇之條件，就市場公平競爭之角度以觀，\n    原告請求被告就其使用如附表所示之音樂著作依上開標準支\n    付使用報酬，應屬有據，本件被告使用之歌曲合計為48首，\n    以每首之重製及使用費合計50,000元計算，被告就此部分應\n    給付原告之金額為240 萬元，原告就此部分之請求自有理由\n    。\n  (四)另就被告未獲得原告同意或授權之情形下即擅自重製其會員\n    歌詞之重製權部分，原告主張被告此部分之行為屬侵權行為\n    ，應賠償100 萬元云云。按損害賠償之制度在於賠償權利人\n    財產因侵權行為之發生所受之減損，是其制度在於彌補損害\n    ，而非在於彌補損害之外另外增加權利人之收益。至權利人\n    所受損害之程度，亦即權利人所得請求彌補之損失範圍，著\n    作權法第88條已設有計算之規定，考其規定內容，均在於彌\n    補權利人應得而未得之差額，尚無在應得而未得之財產損失\n    之外另外加給利益之情形，而除非權利人能證明侵害人之侵\n    權行為係故意且情節重大者，否則亦無同法條第3 項加倍賠\n    償規定之適用。本件原告因被告之侵權行為，其所受之損害\n    乃應收取之相關費用未能收取，此即其所受損害之範圍，而\n    原告對於其他同類業者之報價及收費，就重製部分均係以每\n    首歌20,000萬元計算，其中每首歌之定義係包括曲、詞二者\n    （參原告所提陳證三「使用同意書」第一條，本院卷第374\n    頁），顯然對原告而言，詞、曲二者之重製費為每首20,000\n    元，至於詞、曲二部分究竟如何分配上開收益，則未明文，\n    是以，不論究係對詞或曲所為之重製行為，其應收取之費用\n    最高均不超過20,000元，始為的論。本件原告因被告之侵權\n    行為，應收而未收之重製費每首20,000元即為其所受之損害\n    ，倘此一損害得以獲得彌補，即應認為原告之損失業已回復\n    ，其損失已不復存在，不應就已經填補而不存在之「損害」\n    再度請求「填補」，此為當然之理。本件原告對於被告未經\n    許可擅自重製及使用其會員歌曲之行為，業已請求被告支付\n    每首50,000元之價金，上開50,000元價金中包含詞曲之重製\n    費20,000元，換言之，原告所受之損害，業已因請求被告支\n    付上開價金而獲得填補，自無在於獲得填補之後，額外請求\n    被告就每首「詞」之部分再度支付侵害重製權之損害賠償，\n    否則依原告之請求，被告在支付每首詞、曲之重製費20,000\n    元後，尚需支付每首詞部分之重製費20,833元（損害賠償金\n    100 萬元除以48首歌詞），則顯然被告就此部分支付之金額\n    遠高於其他同業，而原告就此部分之損害於獲得填補後，另\n    額外獲得高於其向其他業者收取之費用收益，此顯非損害賠\n    償制度設計之目的。而原告就被告之行為是否屬「故意且情\n    節重大」之情形而有著作權法第88條第3 項規定之適用，既\n    未提出其他證據資料供本院佐參，則其在上開金額之外另外\n    請求被告應連帶賠償100 萬元，自無理由，應予駁回。\n  (五)綜上所述，本件被告未經原告之同意即擅自重製及使用原告\n    會員之著作，因此造成原告之損害，自應對此負損害賠償責\n    任。而本件原告因被告之侵權行為，其所受之損害乃應收取\n    之使用及重製費未能收取，是原告主張依其對被告同業收取\n    之費用標準請求被告支付每首歌曲50,000元，48首歌合計24\n    0 萬元，及自起訴狀繕本送達翌日即98年7 月23日起至清償\n    日止，按週年利率百分之五計算之利息，即有理由，應予准\n    許。至原告請求被告給付損害賠償金100 萬元部分，因屬重\n    複請求，自屬無據，應予駁回。\n六、假執行部分：\n    本件兩造均陳明願供擔保，請准宣告假執行或免為假執行，\n    於原告上開勝訴範圍內，經核均無不合，爰酌定相當擔保金\n    額分別准許之。至原告敗訴部分，其願供擔保為假執行之聲\n    請即失所附麗，應併予駁回，附此敘明。\n七、本件事證已臻明確，兩造其餘主張陳述及所提之證據，均毋\n    庸再予審酌，附此敘明。\n八、據上論結，本件原告之訴為一部有理由，一部無理由，依智\n    慧財產案件審理法第1 條、民事訴訟法第79條、第392 條，\n    判決如主文。"
  },
  "characters": {
    "judges": [
      "汪漢卿"
    ],
    "prosecutors": [

    ],
    "lawyers": [
      "羅明通",
      "陳世偉",
      "劉曉萍"
    ],
    "clerks": [
      "邱于婷"
    ],
    "plaintiffs": [
      "即委"
    ],
    "defendants": [
      "音圓國際股份有限公司",
      "兼"
    ],
    "prosecutor_office": [

    ],
    "creditors": [

    ],
    "debtors": [

    ],
    "judicial_associate_officer": [

    ]
  },
  "adjudged_at": "2010-01-05",
  "created_at": "2016-01-05 15:06:17",
  "updated_at": "2016-01-05 15:06:17"
}