{
  "identify": "IPC-98-行商訴-210-20100105-1",
  "court": {
    "name": "智慧財產法院",
    "code": "IPC"
  },
  "division": {
    "name": "行政",
    "code": "A"
  },
  "year": 98,
  "word": "行商訴",
  "number": "210",
  "jcheck": "1",
  "reason": "商標異議",
  "content": "智慧財產法院行政裁定\n                                   98年度行商訴字第210號\n原      告  麗曦有限公司\n代  表  人  丁華龍      \n送達代收人  王良正      \n被      告  經濟部智慧財產局\n代  表  人  王美花（局長）住同上\n參  加  人  法商香奈兒股份有限公司\n                            斯街135號\n                            （135,avenue Charles de Gau\n                              lle,92200 Neuilly-sur\n                              Suine,France）\n代  表  人  凱瑟琳．克魯斯（Catherine CRUSE）\n送達代收人  陳長文律師\n上列原告與被告間因商標異議事件，應命參加人參加訴訟，本院\n裁定如下：\n    主  文\n法商香奈兒股份有限公司應獨立參加本件被告之訴訟。\n    理  由\n一、按行政法院認為撤銷訴訟之結果，第三人之權利或法律上利\n    益將受損害者，得依職權命其獨立參加訴訟，並得因該第三\n    人之聲請，裁定允許其參加，智慧財產案件審理法第1 條、\n    行政訴訟法第42條第1 項定有明文。\n二、原告前於民國94年6 月3 日以「晶朵CRISTAL 及圖」商標，\n    指定使用於商標法施行細則第13條所定商品及服務分類表第\n    3 類之「化妝品」商品及第21類之「化妝用具、粉盒、香水\n    噴霧器」商品，向原處分機關智慧財產局申請註冊，經該局\n    審查，核准列為註冊第1233538 號商標（下稱系爭商標）。\n    嗣法商香奈兒股份有限公司以該註冊商標有違商標法第23條\n    第1 項第12及13款之規定，對之提起異議，案經被告審查，\n    認系爭商標之註冊有違商標法第23條第1 項第13款之規定，\n    以96年10月15日中台異字第960066號商標異議審定書為系爭\n    商標之註冊應予撤銷之處分。原告不服，提起訴願，經經濟\n    部98年8 月26日經訴字第09806116970 號決定駁回，遂向本\n    院提起行政訴訟，聲明被告上開處分及訴願決定均應撤銷。\n三、查本件撤銷訴訟之結果，法商香奈兒股份有限公司之權利或\n    法律上利益將受損害，故法商香奈兒股份有限公司有參加本\n    件訴訟之必要，爰依前揭規定，裁定如主文。\n中    華    民    國    99    年    1     月    5     日\n                    智慧財產法院第二庭\n                        審判長法  官  陳國成\n                              法  官  熊誦梅\n                              法  官  曾啟謀\n以上正本係照原本作成。\n不得抗告。\n中    華    民    國    99    年    1     月    5     日\n                              書記官  王月伶",
  "structure": {
    "main": "法商香奈兒股份有限公司應獨立參加本件被告之訴訟。",
    "reason": "一、按行政法院認為撤銷訴訟之結果，第三人之權利或法律上利\n    益將受損害者，得依職權命其獨立參加訴訟，並得因該第三\n    人之聲請，裁定允許其參加，智慧財產案件審理法第1 條、\n    行政訴訟法第42條第1 項定有明文。\n二、原告前於民國94年6 月3 日以「晶朵CRISTAL 及圖」商標，\n    指定使用於商標法施行細則第13條所定商品及服務分類表第\n    3 類之「化妝品」商品及第21類之「化妝用具、粉盒、香水\n    噴霧器」商品，向原處分機關智慧財產局申請註冊，經該局\n    審查，核准列為註冊第1233538 號商標（下稱系爭商標）。\n    嗣法商香奈兒股份有限公司以該註冊商標有違商標法第23條\n    第1 項第12及13款之規定，對之提起異議，案經被告審查，\n    認系爭商標之註冊有違商標法第23條第1 項第13款之規定，\n    以96年10月15日中台異字第960066號商標異議審定書為系爭\n    商標之註冊應予撤銷之處分。原告不服，提起訴願，經經濟\n    部98年8 月26日經訴字第09806116970 號決定駁回，遂向本\n    院提起行政訴訟，聲明被告上開處分及訴願決定均應撤銷。\n三、查本件撤銷訴訟之結果，法商香奈兒股份有限公司之權利或\n    法律上利益將受損害，故法商香奈兒股份有限公司有參加本\n    件訴訟之必要，爰依前揭規定，裁定如主文。"
  },
  "characters": {
    "judges": [
      "陳國成",
      "熊誦梅",
      "曾啟謀"
    ],
    "prosecutors": [

    ],
    "lawyers": [
      "陳長文"
    ],
    "clerks": [

    ],
    "plaintiffs": [
      "麗曦有限公司"
    ],
    "defendants": [
      "經濟部智慧財產局",
      "代  表  人  王美花（局長）住同上",
      "參  加  人  法商香奈兒股份有限公司"
    ],
    "prosecutor_office": [

    ],
    "creditors": [

    ],
    "debtors": [

    ],
    "judicial_associate_officer": [

    ]
  },
  "adjudged_at": "2010-01-05",
  "created_at": "2016-01-05 15:06:27",
  "updated_at": "2016-01-05 15:06:27"
}