{
  "identify": "IPC-98-民專訴-143-20100512-2",
  "court": {
    "name": "智慧財產法院",
    "code": "IPC"
  },
  "division": {
    "name": "民事",
    "code": "V"
  },
  "year": 98,
  "word": "民專訴",
  "number": "143",
  "jcheck": "2",
  "reason": "排除侵害專利權",
  "content": "智慧財產法院民事判決\n                                   98年度民專訴字第143號\n原      告  坴賦佳金屬有限公司\n法定代理人  甲○○\n訴訟代理人  周佳弘律師\n被      告  立匠鋼品工業有限公司\n兼      上\n法定代理人  乙○○\n上二人共同\n訴訟代理人  林耀泉 律師\n            連雲呈 律師\n上列當事人間排除侵害專利權事件，本院於99年4月21日言詞辯\n論終結，判決如下：\n    主  文\n原告之訴駁回。\n訴訟費用由原告負擔。\n    事實及理由\n甲、程序方面：\n一、按訴狀送達後，原告不得將原訴變更或追加他訴，但被告同\n    意、不甚礙被告之防禦及訴訟之終結者，不在此限。被告於\n    訴之變更或追加無異議，而為本案之言詞辯論者，視為同意\n    變更或追加。民事訴訟法第255條第1項第1款、第7款、第2\n    項分別定有明文。本件原告於民國98年10月2日起訴時其訴\n    之聲明第1項係請求「被告等不得實施『內授營建管字第095\n    0807834號內政部建築新技術、新工法、新設備及新材料認\n    可通知書』及『內授營建管字第0960807640號內政部建築新\n    技術、新工法、新設備及新材料認可通知書』之內容」，嗣\n    於98年12月2日具狀擴張第1項聲明為「被告等不得實施『內\n    授營建管字第0950807834號內政部建築新技術、新工法、新\n    設備及新材料認可通知書』（見原證3）、『內授營建管字\n    第0960807640號內政部建築新技術、新工法、新設備及新材\n    料認可通知書』（見原證4）、『內授營建管字第097080602\n    3號內政部建築新技術、新工法、新設備及新材料認可通知\n    書』（見原證5 ）及『內授營建管字第0970807377號內政部\n    建築新技術、新工法、新設備及新材料認可通知書』（下稱\n    見原證6 ）之內容」（見本院卷第94頁），復於99年1 月29\n    日具狀追加聲明第2 項為「被告等應賠償原告新臺幣（下同\n    ）155 萬元整，及自起訴狀送達被告之日起按百分之5 計算\n    之利息」（見本院卷第172 頁），被告雖不同意原告於98年\n    12月2日 所為訴之追加（見本院卷第154 頁），惟原告係於\n    本院98 年1月13日第1 次行準備程序前即已具狀擴張第1 項\n    訴之聲明，且經原告於98年12月2 日具狀擴張聲明後，被告\n    係以系爭專利不具進步性，且原證4 、5 、6 認可書所載施\n    工方法之自攻螺絲固定方式均係隱藏於屋面板固定座內，與\n    系爭專利均將螺栓開放式拴緊之設計相異，故無侵害原告專\n    利權等語資為抗辯（見本院卷第154-157 頁），足見原告雖\n    擴張第1 項聲明而及於原證5 、6 之認可書，惟不甚礙於被\n    告之防禦及本件訴訟之終結，至原告於99年1 月29日另具狀\n    追加聲明第2 項後，被告並無異議而為本案之言詞辯論（見\n    本院卷第190 、243 、287 頁），依法應視為同意上開訴之\n    變更，是原告所為訴之變更及追加，核與首揭規定相符，應\n    予准許，合先敘明。\n乙、實體方面：\n一、原告方面：\n  (一)原告起訴主張：原告係發明專利第I240777 號「防火金屬鋼\n    板結構(一)」（下稱系爭專利）之專利權人，被告等明知原告\n    擁有系爭專利權，竟未經原告同意，而以侵害系爭專利之申\n    請專利範圍之施工法，並依據建築技術規則第74條第2款之\n    規定取得「建築物防火屋頂板」之認可書，且被告於95年12\n    月22日向內政部營建署申請取得「內授營建管字第09508078\n    34號內政部建築新技術、新工法、新設備及新材料認可通知\n    書」，並於96年11月29日向內政部營建署申請取得「內授營\n    建管字第0960807640號內政部建築新技術、新工法、新設備\n    及新材料認可通知書」，又於97年8月4日取得「內授營建管\n    字第0970806023號建築新技術、新工法、新設備及新材料認\n    可通知書」，再於97年9月10日取得「內授營建管字第09708\n    07377號建築新技術、新工法、新設備及新材料認可通知書\n    」，被告實施上開4認可書及對外招攬之行為，已侵害系爭\n    專利權，為此爰依專利法第84條第1項後段請求排除被告等\n    之侵害，並依專利法第85條第1項第2款、公司法第23條、民\n    法第28條規定請求被告立匠鋼品工業有限公司（下稱立匠公\n    司）及其法定代理人即被告乙○○賠償所受損害。並聲明：\n    1.被告等不得實施「內授營建管字第0950807834號內政部建\n      築新技術、新工法、新設備及新材料認可通知書」、「內\n      授營建管字第0960807640號內政部建築新技術、新工法、\n      新設備及新材料認可通知書」、「內授營建管字第097080\n      6023號內政部建築新技術、新工法、新設備及新材料認可\n      通知書」及「內授營建管字第0970807377號內政部建築新\n      技術、新工法、新設備及新材料認可通知書」之內容；2.\n      被告等應賠償原告155 萬元整及自起訴狀送達被告之日起\n      按百分之5 計算之利息。\n  (二)對被告抗辯之陳述：\n  1.被證1 無法證明系爭專利之申請專利範圍欠缺新穎性與進步\n    性：\n    (1)此可由被證1之「申請案件資料」之「主要材料或構件」\n      係由「第一層烤漆鋼板、第二層矽酸鈣板、第三層岩棉、\n      第四層矽酸鈣板、雙併C型立柱與C型槽鐵小樑」組成可\n      知，且由被證1第14頁之「橫向剖透示意圖」亦可知悉，\n      於雙併C型立柱與C型槽鐵小樑之間設「第四層矽酸鈣板」\n      ，被證1亦僅設「第一層烤漆鋼板」，並無如系爭專利設\n      「上、下層鋼板」，且被證1之「雙併C型立柱與C型槽鐵\n      小樑為垂直設置」與系爭專利之上下層鋼架為同向設置不\n      同，且被證1並無法經由「雙併C型立柱拉引C型槽鐵小樑\n      ，以達到防止C型槽鐵小樑塌陷之防火效果」，而與系爭\n      專利藉由「上層鋼架拉引下層鋼架，以達到防止下層鋼架\n      塌陷之效果」結構特徵不同，自無從由被證1證明系爭專\n      利之申請專利範圍第1項及第8項欠缺新穎性或進步性。\n    (2)被證1之雙併C型立柱，雖然與C型鋼互相以自攻螺絲栓設\n      ，但由該雙併C型立柱係設於矽酸鈣板上方觀察，並因為\n      被證1之C型鋼需再藉由被覆防火被覆材（俗稱防火漆），\n      顯見，被證1之雙併C型立柱無法提供C型鋼產生任何拉引\n      力量，無法藉由雙併C型立柱以防止C型鋼受到火場高溫而\n      變形迅速塌陷之危險，而與系爭專利申請專利範圍第1項\n      之上層鋼架或下層鋼架結構特徵完全不同。被證1之「自\n      攻螺絲（c、d），係自雙併C型立柱（B）穿過矽酸鈣板（\n      E）與C型鋼栓設。」，系爭專利申請專利範圍第1項之連\n      結元件，由說明書第3圖至第9圖有各種結構之變化，但是\n      被證1僅係利用自攻螺絲將雙併C型立柱與C型鋼栓設，被\n      證1之自攻螺絲並無法提供拉引作用，以延長C型鋼受到火\n      場高溫而急速塌陷之問題，系爭專利申請專利範圍第1項\n      之連結元件3與被證1之自攻螺絲之特徵完全不同。被證1\n      之烤漆鋼板（A）設於最上層，於該烤漆鋼板與雙併C型立\n      柱（B）之間再設置有矽酸鈣板（F），系爭專利申請專利\n      範圍第1項之上層鋼板4下方就是上層鋼架，亦即上層鋼板\n      4係直接設置於上層鋼架上方，並與防火層形成防火區隔\n      區，惟依據設置之位置，被證1之烤漆鋼板並不等於系爭\n      專利申請專利範圍第1項之上層鋼板。系爭專利申請專利\n      範圍第1 項之下層鋼板5 為浪形、或琉璃瓦形、或平板形\n      狀、或隱藏狀，且係設於下層鋼架2 上方，並由上層鋼架\n      以為支撐與施工，形成防火層6 之舖設空間，被證1 並無\n      如系爭專利所設之下層鋼板，僅有矽酸鈣板（E ）與（F\n      ），但矽酸鈣板並不等於系爭專利之下層鋼板5 ，充其量\n      ，被證1 之矽酸鈣板（E ）、（F ）與岩棉（D ）僅等於\n      系爭專利申請專利範圍第1 項之防火層6 。系爭專利申請\n      專利範圍第1 項之防火層6 係設於上層鋼板4 與下層鋼板\n      5 之間，且形成防火區隔區7 ，防火層6 可以單一防火材\n      料或以複合材料為之，複合材料如防火材加防水毯或再加\n      入防火岩棉或矽酸鈣板或陶瓷棉等，被證1 之防火層，係\n      由矽酸鈣板（E ）、（F ）與岩棉（D ）組成，設置於C\n      型鋼上方與雙併C 型立柱上方，二者防火層之設置結構不\n      相同，且被證1 僅是將防火層設置多層狀態，但該矽酸鈣\n      板遇到高溫即會脆化，根本無法經由拉引雙併C 型立柱拉\n      引C 型鋼。被證1 僅是利用傳統隔間牆之結構，作為屋頂\n      板之結構，需藉由被覆防火漆，才能達成所要達成之目的\n      ，無法真正提昇建築物之防火效果。被證1 施工時，需被\n      覆防火層，再逐層舖設複數之厚重之矽酸鈣板，結果並無\n      法較系爭專利之更具防火效果。綜上，被證1 欠缺系爭專\n      利申請專利範圍第1 項之下層鋼板，且由被證1 之結構所\n      揭示之「矽酸鈣板（E ）、（F ）與岩棉（D ）」之設置\n      僅與請求項1 之防火層6 相當，但系爭專利申請專利範圍\n      第1 項又較被證1 之結構簡易，但防火時效仍然優於被證\n      1 ，因為由被證1 之自攻螺絲並無法提供雙併C 型立柱拉\n      引C 型鋼之力量，無法藉由雙併C 型立柱拉引C 型鋼，產\n      生防止C 型鋼快速塌陷之問題。因此，由被證1 並無法證\n      明請求項1 欠缺進步性。\n    (3)系爭專利設防火區隔區7係由防火層6與上層鋼板4所形成\n      者，具有讓熱氣被順利排出，而延長上層鋼板4與上層鋼\n      架1之受到火場高溫而變形之時間，具有提高防火時效之\n      優點，但被證1於雙併C型立柱與烤漆鋼板之間再設置有矽\n      酸鈣板（E），如此，將形成另一隔熱層，無法適時將火\n      場中之熱氣排出，反而會將高溫熱氣封閉於屋內，如果發\n      生火警，勢必加快C型鋼之變形塌陷之時間，顯見系爭專\n      利之防火效果絕對較被證1更為增進與精進，兩者結構不\n      同。\n  2.被告等應負推定過失責任，系爭專利係於94年10月1日公告\n    於經濟部智慧財產局（下稱智慧局）之專利公報中，專利公\n    報並包含「紙本公報、光碟公告與網站內容」等，而智慧局\n    除了位於台北市之公務機關所在地之外，更於高雄、台南、\n    台中與新竹均設有辦事處，接受並提供本國人民隨時查閱並\n    利用各項智慧財產資訊之方法，且系爭專利申請之後，原告\n    亦取得「內授營建管字第0950800048號內政部建築新技術、\n    新工法、新設備及新材料認可通知書」，且於94年1 月31日\n    公告於財團法人中華建築中心之網站，而財團法人中華建築\n    中心之網站乃被告最常利用並作為被告施工或監工完成之建\n    築物開立防火證明進行登錄之網站，且由財團法人中華建築\n    中心之網站中，被告更得以輕易取得系爭專利之相關防火認\n    證資訊，而被告對於他人取得之具備進步性之防火認證直接\n    加以援用，實應負推定過失責任。\n二、被告則抗辯以：\n  (一)依系爭專利所附圖說可知，所謂上層鋼架及下層鋼架可以為\n    C形鋼、H形鋼抑或是其他形狀鋼架為之，經比較被證1與系\n    爭專利申請專利範圍第1項，可知被證1之雙併C型鋼編號B（\n    即等同系爭專利之上層鋼架）、C型鋼編號C（即等同系爭專\n    利之下層鋼架）、上層矽酸鈣板編號F（即等同系爭專利之\n    上層鋼板）、下層矽酸鈣板編號E（即等同系爭專利之下層\n    鋼板）、雙併C型鋼B與C間藉自攻螺絲編號b、c（即等同系\n    爭專利連結元件）相連結、雙併C型鋼B與C間設岩棉編號D（\n    即等同系爭專利之防火層）等之技術設計功能皆相同，並確\n    實早於系爭專利申請前已揭露系爭專利申請專利範圍第1項\n    所述必要元件與元件間之相對關係。至被證1上層矽酸鈣板\n    （編號F）上方設置烤漆鋼板（編號A），此雖與系爭專利上\n    層鋼架上方及上層鋼架與下層鋼架間分別固定上層鋼板及下\n    層鋼板相異。惟被證1早已揭露於雙併C型鋼（編號B）上方\n    及雙併C型鋼（編號B）與C型鋼（編號C）間分別設有上層矽\n    酸鈣板（編號F）、下層矽酸鈣板（編號E），將此矽酸鈣板\n    F、E置換為鋼板，為所屬技術領域中具有通常知識者所能輕\n    易完成。此觀系爭專利申請前，第三人玉逢工程有限公司所\n    申請內政部建築新技術、新工法、新設備及新材料認可通知\n    書中之系統概述記載「兩面覆蓋單層烤漆鋼板，其中填充岩\n    棉複合板之防火屋頂板…」可知，故於系爭專利申請前，即\n    有所屬技術領域中具有通常知識者，輕易完成換置矽酸鈣板\n    為鋼板之技術，原告卻執此主張為其專利申請範圍，顯不具\n    進步性。\n  (二)系爭專利申請專利範圍第8項界定一種「防火金屬鋼板結構\n    (一)」，其包含：「連結元件，連結元件係設於上層鋼架與下\n    層鋼架之間，…之結構剛性」，然系爭專利申請專利範圍第\n    8 項並未提及所謂連結元件係指何種材料，是否凡各式螺栓\n    均屬其所指之連結元件範圍，亦不可知，被證1所揭露之自\n    攻螺絲b、c與系爭專利所謂之連結元件或螺栓之功用均為螺\n    鎖連結二鋼材，是故被證1明顯給予系爭專利申請專利範圍\n    第8項產生教示作用，系爭專利所謂連結元件及螺栓之設計\n    僅是就被證1技術特徵之簡單置換，顯不具進步性。\n  (三)被告並無侵害原告專利之情事：\n  1.系爭專利之申請專利範圍第1、8項僅為施工法與完成品，並\n    不含其中之材料與零件，故被告依照上開認可通知書販賣主\n    要材料與構件，並無侵害系爭專利之虞。\n  2.縱原告之專利為有效，然依原證3之標準施工圖之短項剖面\n    圖均可得知，該項通知書之施工方法包含以12#X3.5\"六角自\n    攻螺絲，間距380mm貫穿整個防火屋頂板結構以及12#1.5\"六\n    角自攻螺絲，間距380mm以上下拴緊鋼板等二種方式固定，\n    顯與系爭專利僅用螺栓上下拴緊之施工方式迥異，原證4（\n    亦採用原證3固定法）、5、6部分，自攻螺絲均採用隱藏式\n    設計。易言之，即Z型連結元件先以自攻螺絲固定於屋頂板\n    固定座後，再將上層鋼板從外面包覆屋頂板固定座，並夾緊\n    固定，使外觀觀之無法察覺六角自攻螺絲固定之處，以減少\n    六角自攻螺絲因風雨侵蝕而加速氧化，是故原證4、5、6部\n    分之自攻螺絲固定方式均隱藏於屋面板固定座內，與系爭專\n    利均將螺栓開放式拴緊之設計相異，此由原證4、5、6之長\n    向、短向剖面圖說可證，且原證4、5、6之施工步驟7.8.亦\n    說明「將上層烤漆鋼板固定於固定座上方，安裝第二片烤漆\n    鋼板時，將第二片烤漆鋼板之左側扣合於第一片鋼板右側之\n    上方，再以六角自攻螺絲鎖固」、「將屋面板固定座以自攻\n    螺絲固定於Z 型鍍鋅隔件之上方，將上層烤漆板固定於屋面\n    板固定座上，安裝第二片烤漆鋼板時，於第二片烤漆鋼板之\n    左側扣合第一片鋼板右側之上方，以鉸合器於鋼板接合處將\n    兩鋼板鉸合。」，職是被告原證3 、4 、5 、6 通知書所施\n    工之工法與材料均與系爭專利迥異。又被告4 項認可書之結\n    構主要與系爭專利之不同點在於，被告此四項認可書施做方\n    式僅有在最下層架設一C 型鋼並以自攻螺絲固定下層鋼板於\n    C 型鋼並鋪設岩棉後，即鋪設鍍鋅隔件或Z 型隔件，且從該\n    四項認可通知書之構成材料規格上可知，鍍鋅隔件僅為\n    0.47mm 、Z型隔件僅為1.5mm ，且鍍鋅隔件或Z 型隔件質地\n    偏軟，並無上下層鋼架之剛性，故並無法與鋼架有相同之功\n    用，以自攻螺絲由上而下貫穿後，並未有如系爭專利以兩個\n    C 型鋼之組合以連結元件連結而產生上下拉引之力量。\n  3.被告係信賴內政部所頒發之認可通知書而為使用，並非故意\n    侵害原告之專利權。再者，原證2之存證信函係於原告專利\n    申請4 年多後向多數業者發出，然其專利範圍、受函者所販\n    賣之內容何種型號有侵害系爭專利之虞等事項均無明述。原\n    告如此通知，實難謂被告明知其專利範圍而仍販售侵害系爭\n    專利之成品，而請求排除侵害。況被告就原證4 之材料認可\n    通知書所示材料與構件，早已於原告以存證信函通知2 年前\n    停止施作及販賣，原證3 之內容於原證2 存證信函通知後已\n    無施作，僅零星販賣零件，故無侵害原告專利權之虞。\n  (四)並聲明：1.原告之訴駁回；2.訴訟費用由原告負擔。\n三、本件兩造不爭執之事實（見本院卷第161、162頁）：\n  (一)原告於93年7 月29日向經濟部智慧財產局申請「防火金屬鋼\n    板結構(一)」發明專利，經該局審查核准專利後，發給第I240\n    777號專利證書，專利權期間自94年10月1日起至113年7月28\n    日止。\n  (二)被告確有向內政部營建署申請取得下列認可書：\n  1.95年12月22日內授營建管字第0950807834號建築新技術、新\n    工法、新設備及新材料認可通知書。\n  2.96年11月29日內授營建管字第0960807640號建築新技術、新\n    工法、新設備及新材料認可通知書。\n  3.97年8月4日內授營建管字第0970806023號建築新技術、新工\n    法、新設備及新材料認可通知書。\n  4.97年9月10日內授營建管字第0970807377號建築新技術、新\n    工法、新設備及新材料認可通知書。\n四、本件經本院與兩造整理並協定簡化之爭點如下（見本院卷第\n    162頁）：\n  (一)被證1是否足以證明系爭專利申請專利範圍第1、8項不具進\n    步性（被證2之主張業經被告於99年3月24日捨棄，見本院卷\n    第246頁）？\n  (二)上開認可書所載之鋼板施工結構是否落入系爭專利申請專利\n    範圍第1、8項？原告得否依專利法第84條第1項請求排除、\n    防止侵害或損害賠償？\n五、本院之判斷如下：\n  (一)被證1足以證明系爭專利申請專利範圍第1、8項不具進步性\n    ：\n  1.按解釋專利權範圍應以申請專利範圍之記載為準，不得將發\n    明說明或圖式有揭露但未載於申請專利範圍之技術特徵讀入\n    ，而縮小專利權範圍，是以專利是否具有新穎性或進步性，\n    應以申請專利範圍之記載為判斷標的，倘某項技術特徵僅揭\n    露於發明說明或圖式卻未載於申請專利範圍，則專利權人不\n    得藉由該技術特徵減縮其申請專利範圍，俾使其專利得以符\n    合新穎性或進步性之要件，至於用以證明該專利不具新穎性\n    或進步性之先前技術倘係專利文獻，則以該專利文獻所揭露\n    之全部內容為先前技術。此外，發明說明應記載實施方式，\n    俾以符合明確且充份揭露達成發明目的所採用解決問題之技\n    術手段，而使具有通常知識者在無須過度實驗之情況下，即\n    能瞭解申請專利之發明內容，並可據以實施，是以解釋專利\n    權範圍時應涵括但不限於說明書所載之實施方式或實施例。\n  2.查系爭專利申請專利範圍共8項，其中第1、8項為獨立項，\n    其餘第2項至第7項為附屬項，第1項之內容為：「一種防火\n    金屬鋼板結構(一)，包含：鋼架，鋼架設上層鋼架及下層鋼架\n    ，於上層鋼架與下層鋼架之間並設有連結元件，利用連結元\n    件以將上、下層鋼架連結，以使上層鋼架對下層鋼架產生拉\n    引力量；鋼板，鋼板設上層鋼板及下層鋼板，分別固定於上\n    層鋼架上方及上層鋼架與下層鋼架之間；防火層，該防火層\n    設於上層鋼板與下層鋼板之間，以組成本發明之防火金屬鋼\n    板。」，第8項之內容為：「一種防火金屬鋼板結構(一)，包\n    含：連結元件，連結元件係設於上層鋼架與下層鋼架之間，\n    以使下層鋼架藉由上層鋼架產生拉引力量，強化整體防火金\n    屬鋼板之結構剛性。」，雖系爭專利說明書之發明內容記載\n    ：「本發明之特點有：1.本發明之防火金屬鋼板結構(一)，利\n    用連結元件連結上、下層鋼架，以使上層鋼架對下層鋼架產\n    生拉引力量，確保下層鋼架可承受火警高溫，不易變形，避\n    免建築物塌陷造成危害。2.本發明之防火金屬鋼板結構(一)設\n    鋼板，鋼板設上層鋼板及下層鋼板，分別固定於上層鋼架上\n    方及上層鋼架與下層鋼架之間，再於上層鋼板與下層鋼板之\n    間設防火層，且形成防火區隔區，利用防火層之防火功能，\n    及於前述防火區隔區形成部份之空氣空間，更增加防火效果\n    ，以符合國家標準之防火時效。」，惟系爭專利申請專利範\n    圍第1項並未揭露防火層與上層鋼板間設有「防火區隔區」\n    ，而防火層之舖設於系爭專利申請專利範圍第1項中僅界定\n    「設於上層鋼板與下層鋼板之間」，是以「防火區隔區」即\n    無從作為判斷系爭專利申請專利範圍第1項是否具有進步性\n    之技術特徵。\n  3.被證1為內政部營建署於92年8月7日對弘耀實業有限公司生\n    產之「弘耀F-18防火屋頂」所核發之認可通知書，其產品種\n    類為「建築物防火屋頂版」，被證1之防火屋頂板結構，係\n    將C型槽鋼噴覆防火被覆材作為小梁，固定於H型鋼大梁上，\n    在C 型鋼上利用自攻螺絲及雙併C 型鋼固定，由上而下順序\n    為：第一層烤漆鋼板、第二層矽酸鈣板、雙併C 型鋼、第三\n    層填充岩棉、第四層矽酸鈣板所組成的合板屋頂結構。依系\n    爭專利說明書「發明說明」記載：「鋼架設上層鋼架1 及下\n    層鋼架2 ，鋼架由C 形鋼；或H 形鋼；或其他形狀之鋼架為\n    之皆可以，本發明以C 形鋼以解說明本發明之特性。再於上\n    層鋼架1 與下層鋼架2 之間並設有連結元件3 ，該連結元件\n    3 可以為複數，端視鋼架之長度而定。」、「連結元件3 ，\n    可以由任意配件為之」、「防火層6 可以單一防火料或以複\n    合材料為之，複合材料如防火材加防水毯或再加入防火岩棉\n    」（見說明書第9 頁），是以系爭專利之上下層鋼架即包括\n    C 形鋼，防火層即包括防火岩棉，至於連結元件只須能達成\n    連結鋼架之功效即包含之，依被證1 之記載其防火屋頂板之\n    結構為「以雙併C 型鋼（間隔915mm ），加上自攻螺絲固定\n    由外層烤漆鋼板（0.5mm ）貼上矽酸鈣板（6mm ），中間填\n    實密度80公斤/ 立方米之岩棉（50mm），再加上矽酸鈣板（\n    10mm）之屋頂板結構，固定在C 型鋼槽上（間隔915mm ）」\n    （詳如附圖，見本院卷第60頁），就被證1 與系爭專利之申\n    請專利範圍第1 項所界定之技術特徵比對，系爭專利申請專\n    利範圍第1 項所記載之上層鋼板、上層鋼架、防火層、連結\n    元件、下層鋼架等構件，已分別對應揭露於被證1 之烤漆鋼\n    板、雙併C 型鋼、岩棉、六角自攻螺絲、C 型鋼，且兩案之\n    構件組構關係係屬相同，其不同處在於被證1 與下層鋼架連\n    結者為矽酸鈣板，而系爭專利則為下層鋼板，是以二者均具\n    有下層板構件，僅該構件之材質不同。\n  4.依系爭專利說明書第8頁記載：「發明目的乃於上層鋼架與\n    下層鋼架之間設有連結元件，利用連結元件以將上、下層鋼\n    架連結，以使上層鋼架對下層鋼架產生拉引力量，下層鋼架\n    可承受火場高溫，不易變形，建築物不易塌陷，造成危害，\n    以符合國家標準之防火時效。」，因此與下層鋼架連結者是\n    否使用鋼板並非本案之發明目的或特點，且被證1之下層使\n    用矽酸鈣板係屬耐燃之防火建材，系爭專利與被證1雖於下\n    層板部分有鋼板與矽酸鈣板之不同，然由於鋼板、矽酸鈣板\n    皆屬系爭專利申請時防火屋頂習用之建材，此由被證5內政\n    部營建署於93年2月4日以內授營建管字第0930082097號建築\n    新技術、新工法、新設備及新材料認可通知書可資佐證（見\n    本院卷第264頁），而原告又未能證明將矽酸鈣板置換為先\n    前技術之鋼板，其材質之不同有何無法預期之功效，則原告\n    以具有相同功能的已知材料置換已知物品中相對應之材料，\n    應認定該發明能輕易完成，不具進步性，故被證1足以證明\n    系爭專利申請專利範圍第1項不具進步性。\n  5.原告雖主張系爭專利可藉由連結元件以使上層鋼架對下層鋼\n    架產生拉引力量，下層鋼架可承受火場高溫，不易變形，而\n    被證1之C型鋼必須再被覆防火被覆材，顯見被證1之C型鋼無\n    法藉由雙併C型立柱產生任何拉引力量，且系爭專利之上下\n    層鋼架為同向設置等語。惟查，系爭專利申請專利範圍第1\n    項僅記載其連結元件可使上層鋼架對下層鋼架產生拉引力量\n    ，惟其僅為功能的敘述，而於系爭專利申請專利範圍第1項\n    中並未對連結元件或下層鋼架之構造有所限定，系爭專利說\n    明書「發明說明」僅記載：「鋼架設上層鋼架1及下層鋼架2\n    ，鋼架由C形鋼；或H型鋼；或其他形狀之鋼架為之皆可以，\n    本發明以C形鋼以解說明本發明之特性。再於上層鋼架1與下\n    層鋼架2之間並設有連結元件3，該連結元件3可以為複數，\n    端視鋼架之長度而定。」、「連結元件3，可以由任意配件\n    為之」，業如前述，系爭專利申請專利範圍第1項亦未界定\n    其鋼架及連結元件是否為防火材料或被覆防火漆，則原告主\n    張被證1之C型鋼必須再被覆防火被覆材，而無法藉由雙併C\n    型立柱產生任何拉引力量，即非可採。\n  6.另就被證1與系爭專利申請專利範圍第8項所界定之技術特徵\n    比對，系爭專利所記載設於上層鋼架與下層鋼架間之連結元\n    件已為被證1之六角自攻螺絲所揭露，由於被證1之六角自攻\n    螺絲亦設於上層鋼架與下層鋼架間，而其是否可使下層鋼架\n    藉由上層鋼架產生拉引力量以強化整體防火金屬鋼板之結構\n    剛性，已如前所述，故被證1亦可證明系爭專利申請專利範\n    圍第8項不具進步性。\n  (二)原證3、4、5、6認可書所載之鋼板施工結構落入系爭專利申\n    請專利範圍第1項：\n  1.原證3認可書之侵害分析:\n    (1)經解析系爭專利申請專利範圍第1項，其技術特徵可拆解\n      為5個要件，分別為編號1要件「一種防火金屬鋼板結構(一)\n      ，包含：」，編號2要件「鋼架，鋼架設上層鋼架及下層\n      鋼架，」，編號3要件「於上層鋼架與下層鋼架之間並設\n      有連結元件，利用連結元件以將上、下層鋼架連結，以使\n      上層鋼架對下層鋼架產生拉引力量；」，編號4要件「鋼\n      板，鋼板設上層鋼板及下層鋼板，分別固定於上層鋼架上\n      方及上層鋼架與下層鋼架之間；」，編號5要件「防火層\n      ，該防火層設於上層鋼板與下層鋼板之間，以組成本發明\n      之防火金屬鋼板。」。\n    (2)原證3之認可書為一種建築物防火屋頂板，其設有上、下\n      層鋼板，板厚度0.42mm，上、下層鋼板間以C型鋼固定，\n      利用12#×3.5\"六角頭自攻螺絲連結上（C型鋼）、下層鋼\n      架，上下層鋼板間填充陶瓷棉。原證3之認可書對應於系\n      爭專利申請專利範圍第1項各技術特徵可解析為5個要件，\n      原證3為一種防火金屬鋼板結構，編號1要件已文義讀取，\n      原證3設有上、下層C型鋼架，編號2要件已文義讀取，原\n      證3於上下層鋼架間設有六角頭自攻螺絲之連結元件，利\n      用連結元件以將上、下層鋼架連結，以使上層鋼架對下層\n      鋼架產生拉引力量，編號3要件已文義讀取，原證3設有厚\n      度0.42 mm之上、下層烤漆鋼板，編號4要件已文義讀取，\n      原證3亦於上下層鋼板間填充有陶瓷棉之防火層，編號5要\n      件已文義讀取，故原證3認可書之技術內容分別為系爭專\n      利申請專利範圍第1項編號1至5要件之文義所讀取，是以\n      原證3認可書落入系爭專利申請專利範圍第1項之文義範圍\n      。\n    (3)至於被告辯稱原證3之認可書施工法包含以12#×3.5\"六角\n      頭自攻螺絲，間距380mm貫穿整個防火屋頂板結構以及12#\n      1.5\"六角自攻螺絲，間距380mm以上下拴緊鋼板等二種方\n      式固定，顯與系爭專利僅用螺栓上下拴緊之施工方式迥異\n      等語。惟查，系爭專利申請專利範圍第1項係界定：「於\n      上層鋼架與下層鋼架之間並設有連結元件，利用連結元件\n      以將上、下層鋼架連結，以使上層鋼架對下層鋼架產生拉\n      引力量」，系爭專利說明書之發明說明雖係以螺栓作為連\n      結元件之實施例，惟解釋申請專利範圍時僅能就申請專利\n      範圍所載之技術特徵予以解釋，尚不得將說明書所揭露之\n      實施例讀入申請專利範圍，而限縮申請專利範圍，被告所\n      稱系爭專利僅用螺栓上下拴緊之施工方法及連結元件之結\n      構並未載於系爭專利申請專利範圍第1項，而原證3認可書\n      之施工法亦係於上層鋼架與下層鋼架之間設有連結元件（\n      六角頭自攻螺絲）將上、下層鋼架連結，以該連結使上層\n      鋼架對下層鋼架產生拉引力量，原證3之該項技術內容自\n      應為系爭專利申請專利範圍第1項編號3要件之文義所讀取\n      ，被告所辯尚非可採。\n  2.原證4認可書之侵害分析：\n    (1)原證4之認可書為一種建築物複層式防火屋頂板，其設有\n      厚度0.52mm上層鋼板、厚度0.42mm下層鋼板，上、下層鋼\n      板間以熱浸鍍鋅鋼材之固定座固定，利用12#×3.5\"六角\n      頭自攻螺絲連結上、下層鋼架（C型鋼125×50×20×2.3m\n      m），上、下層鋼板間填充陶瓷棉。\n    (2)原證4之認可書對應於系爭專利申請專利範圍第1項各技術\n      特徵可解析為5個要件，原證4為一種防火金屬鋼板結構，\n      編號1要件已文義讀取，原證4設有上層熱浸鍍鋅鋼材鋼架\n      、下層C型鋼架，編號2要件已文義讀取，原證4於上、下\n      層鋼架間設有六角頭自攻螺絲之連結元件，利用連結元件\n      以將上、下層鋼架連結，以使上層鋼架對下層鋼架產生拉\n      引力量，編號3要件已文義讀取，原證4設有厚度0.52mm上\n      層鋼板、厚度0.42mm下層鋼板，編號4要件已文義讀取，\n      原證4亦於上下層鋼板間填充有陶瓷棉之防火層，編號5要\n      件已文義讀取，故原證4認可書之技術內容分別為系爭專\n      利申請專利範圍第1項編號1至5要件之文義所讀取，是以\n      原證4認可書落入系爭專利申請專利範圍第1項之文義範圍\n      。\n  3.原證5認可書之侵害分析：\n    (1)原證5之認可書為一種建築物複層式防火金屬鋼板屋頂，\n      其設有厚度0.476mm上層鋼板、厚度0.42mm下層鋼板，上\n      、下層鋼板間固定有鍍鋅鋼材之鍍鋅隔件50×50×50 ×1\n      .5 ×1.5 （t ）mm，間距1000mm，利用六角頭自攻螺絲\n      連結上、下層鋼架（C 型鋼125 ×50×20×2.3 （t ）mm\n      ），上、下層鋼板間填充岩棉及陶瓷棉。\n    (2)原證5之認可書對應於系爭專利申請專利範圍第1項各技術\n      特徵可解析為5個要件，原證5為一種防火金屬鋼板結構，\n      編號1要件已文義讀取，原證5設有上層鍍鋅鋼材（鍍鋅隔\n      件）鋼架、下層C型鋼架，編號2要件已文義讀取，原證5\n      於上、下層鋼架間設有六角頭自攻螺絲之連結元件，利用\n      連結元件以將上、下層鋼架連結，以使上層鋼架對下層鋼\n      架產生拉引力量，編號3要件已文義讀取，原證5設有厚度\n      0.476mm上層鋼板、厚度0.42mm下層鋼板，編號4要件已文\n      義讀取，原證5亦於上下層鋼板間填充有岩棉及陶瓷棉之\n      防火層，編號5要件已文義讀取，故原證5認可書之技術內\n      容分別為系爭專利申請專利範圍第1項編號1至5要件之文\n      義所讀取，是以原證5認可書落入系爭專利申請專利範圍\n      第1項之文義範圍。\n  4.原證6認可書之侵害分析：\n    (1)原證6之認可書為一種建築物複層式防火金屬鋼板屋頂，\n      其設有厚度0.476mm上層烤漆鋼板、厚度0.42mm下層烤漆\n      鋼板，上、下層鋼板間固定有鍍鋅鋼材之Z型鍍鋅隔件（5\n      0×50×50×1.5（t）mm），利用六角頭自攻螺絲連結上\n      、下層鋼架（C型鋼125×50×20×2.3（t）mm），上、下\n      層鋼板間填充岩棉及陶瓷棉。\n    (2)原證6之認可書對應於系爭專利申請專利範圍第1項各技術\n      特徵可解析為5個要件，原證6為一種防火金屬鋼板結構，\n      編號1要件已文義讀取，原證6設有上層鍍鋅鋼材（Z型鍍\n      鋅隔件）鋼架、下層C型鋼架，編號2要件已文義讀取，原\n      證6於上、下層鋼架間設有六角頭自攻螺絲之連結元件，\n      利用連結元件以將上、下層鋼架連結，以使上層鋼架對下\n      層鋼架產生拉引力量，編號3要件已文義讀取，原證6設有\n      厚度0.476mm上層鋼板、厚度0.42mm下層鋼板，編號4要件\n      已文義讀取，原證6亦於上下層鋼板間填充有岩棉及陶瓷\n      棉之防火層，編號5要件已文義讀取，故原證6認可書之編\n      號1至5要件皆為系爭專利申請專利範圍第1項編號1至5要\n      件文義所讀取，是以原證6認可書落入系爭專利申請專利\n      範圍第1項之文義範圍。\n  5.至於被告辯稱原證4、5、6之認可書施工法之自攻螺絲固定\n    方式均隱藏於屋面板固定座內，與系爭專利均將螺栓開放式\n    拴緊之設計相異等語，惟查，系爭專利申請專利範圍第1項\n    並未限定連結元件螺栓為開放式或隱藏式拴緊，亦不得將說\n    明書所揭露之實施例讀入申請專利範圍，而限縮系爭專利申\n    請專利範圍第1項，則原證4、5、6認可書之施工法係於上層\n    鋼架與下層鋼架之間設有連結元件（六角頭自攻螺絲）將上\n    、下層鋼架連結，以該連結使上層鋼架對下層鋼架產生拉引\n    力量，原證4、5、6之該項技術內容亦為系爭專利申請專利\n    範圍第1項編號3要件文義所讀取。\n  6.另被告辯稱原證3、4、5、6認可書之構成材料規格上可知，\n    鍍鋅隔件僅為0.47mm、Z型隔件僅為1.5mm，且鍍鋅隔件或Z\n    型隔件質地偏軟，並無上下層鋼架之剛性，故並無法與鋼架\n    有相同之功用，以自攻螺絲由上而下貫穿後，並未有如系爭\n    專利以兩個C型鋼之組合以連結元件連結而產生上下拉引之\n    力量等語。經查，縱原證3、4、5、6認可書鍍鋅隔件僅為0.\n    47mm、Z型隔件僅為1.5mm，然其上下層烤漆鋼板厚度亦僅為\n    0.476mm或0.42mm，相對該上下層鋼板厚度，尚難稱0.47mm\n    之鍍鋅隔件、0.42mm之Z型隔件不具有結構之剛性支撐作用\n    。況且系爭專利申請專利範圍第1項中亦未界定相關構件之\n    形狀及厚度，原證3、4、5、6既揭示於上、下層鋼架間設有\n    連結元件，實無法僅由其所稱之厚度即可推知其未能產生拉\n    引力量，被告所辯均不足採。\n  (三)原證3、4、5、6認可書所載之鋼板施工結構落入系爭專利申請\n    專利範圍第8項：\n  1.經解析系爭專利申請專利範圍第8項，其技術特徵可拆解為2\n    個要件，分別為編號1要件「一種防火金屬鋼板結構(一)，包\n    含：」，編號2要件「連結元件，連結元件係設於上層鋼架\n    與下層鋼架之間，以使下層鋼架藉由上層鋼架產生拉引力量\n    ，強化整體防火金屬鋼板之結構剛性。」。\n  2.原證3之認可書對應於系爭專利申請專利範圍第8項各技術特\n    徵可解析為2個要件，原證3為一種防火金屬鋼板結構，編號\n    1要件已文義讀取，原證3於上下層鋼架間設有六角頭自攻螺\n    絲之連結元件，利用連結元件以將上、下層鋼架連結，以使\n    上層鋼架對下層鋼架產生拉引力量，編號2要件已文義讀取\n    ，故原證3認可書之編號1、2要件皆為系爭專利申請專利範\n    圍第8 項編號1 、2 要件文義所讀取，是以原證3 認可書落\n    入系爭專利申請專利範圍第8 項之文義範圍。\n  3.原證4之認可書對應於系爭專利申請專利範圍第8項各技術特\n    徵可解析為2個要件，原證4為一種防火金屬鋼板結構，編號\n    1要件已文義讀取，原證4於上下層鋼架間設有六角頭自攻螺\n    絲之連結元件，利用連結元件以將上、下層鋼架連結，以使\n    上層鋼架對下層鋼架產生拉引力量，編號2要件已文義讀取\n    ，故原證4認可書之編號1、2要件皆為系爭專利申請專利範\n    圍第8 項編號1 、2 要件文義所讀取，是以原證3 認可書落\n    入系爭專利申請專利範圍第8 項之文義範圍。\n  4.原證5之認可書對應於系爭專利申請專利範圍第8項各技術特\n    徵可解析為2個要件，原證5為一種防火金屬鋼板結構，編號\n    1要件已文義讀取，原證5於上下層鋼架間設有六角頭自攻螺\n    絲之連結元件，利用連結元件以將上、下層鋼架連結，以使\n    上層鋼架對下層鋼架產生拉引力量，編號2要件已文義讀取\n    ，故原證5認可書之編號1、2要件皆為系爭專利申請專利範\n    圍第8 項編號1 、2 要件文義所讀取，是以原證5 認可書落\n    入系爭專利申請專利範圍第8 項之文義範圍。\n  5.原證6之認可書對應於系爭專利申請專利範圍第8項各技術特\n    徵可解析為2個要件，原證6為一種防火金屬鋼板結構，編號\n    1要件已文義讀取，原證6於上下層鋼架間設有六角頭自攻螺\n    絲之連結元件，利用連結元件以將上、下層鋼架連結，以使\n    上層鋼架對下層鋼架產生拉引力量，編號2要件已文義讀取\n    ，故原證6認可書之編號1、2要件皆為系爭專利申請專利範\n    圍第8 項編號1 、2 要件文義所讀取，是以原證6 認可書落\n    入系爭專利申請專利範圍第8 項之文義範圍。\n六、綜上所述，原證3、4、5、6認可書所載之鋼板施工結構均落\n    入系爭專利申請專利範圍第1、8項之文義範圍，惟被告所提\n    出之被證1足以證明系爭專利申請專利範圍第1、8項均不具\n    進步性，而有專利法第22條第4項之撤銷原因，則依智慧財\n    產案件審理法第16條第2項規定，原告於本件民事訴訟中自\n    不得以系爭專利申請專利範圍第1、8項對於被告主張權利。\n    從而，原告依專利法第84條第1項、第85條第1項第2款、公\n    司法第23條及民法第28條規定為如訴之聲明所示之請求，均\n    無理由，應予駁回。\n七、本件事證已臻明確，兩造其餘主張陳述及所提之證據，經本\n    院斟酌後，認與判決結果不生影響，均毋庸再予論述，附此\n    敘明。\n八、訴訟費用負擔之依據：民事訴訟法第78條。\n中    華    民    國    99    年     5    月   12     日\n                    智慧財產法院第一庭\n                                法  官  林欣蓉\n以上正本係照原本作成。\n如對本判決上訴，須於判決送達後20日內向本院提出上訴狀。\n中    華    民    國    99    年     5    月   12     日\n                                書記官  周其祥\n",
  "structure": {
    "main": "原告之訴駁回。\n訴訟費用由原告負擔。",
    "fact": "甲、程序方面：\n一、按訴狀送達後，原告不得將原訴變更或追加他訴，但被告同\n    意、不甚礙被告之防禦及訴訟之終結者，不在此限。被告於\n    訴之變更或追加無異議，而為本案之言詞辯論者，視為同意\n    變更或追加。民事訴訟法第255條第1項第1款、第7款、第2\n    項分別定有明文。本件原告於民國98年10月2日起訴時其訴\n    之聲明第1項係請求「被告等不得實施『內授營建管字第095\n    0807834號內政部建築新技術、新工法、新設備及新材料認\n    可通知書』及『內授營建管字第0960807640號內政部建築新\n    技術、新工法、新設備及新材料認可通知書』之內容」，嗣\n    於98年12月2日具狀擴張第1項聲明為「被告等不得實施『內\n    授營建管字第0950807834號內政部建築新技術、新工法、新\n    設備及新材料認可通知書』（見原證3）、『內授營建管字\n    第0960807640號內政部建築新技術、新工法、新設備及新材\n    料認可通知書』（見原證4）、『內授營建管字第097080602\n    3號內政部建築新技術、新工法、新設備及新材料認可通知\n    書』（見原證5 ）及『內授營建管字第0970807377號內政部\n    建築新技術、新工法、新設備及新材料認可通知書』（下稱\n    見原證6 ）之內容」（見本院卷第94頁），復於99年1 月29\n    日具狀追加聲明第2 項為「被告等應賠償原告新臺幣（下同\n    ）155 萬元整，及自起訴狀送達被告之日起按百分之5 計算\n    之利息」（見本院卷第172 頁），被告雖不同意原告於98年\n    12月2日 所為訴之追加（見本院卷第154 頁），惟原告係於\n    本院98 年1月13日第1 次行準備程序前即已具狀擴張第1 項\n    訴之聲明，且經原告於98年12月2 日具狀擴張聲明後，被告\n    係以系爭專利不具進步性，且原證4 、5 、6 認可書所載施\n    工方法之自攻螺絲固定方式均係隱藏於屋面板固定座內，與\n    系爭專利均將螺栓開放式拴緊之設計相異，故無侵害原告專\n    利權等語資為抗辯（見本院卷第154-157 頁），足見原告雖\n    擴張第1 項聲明而及於原證5 、6 之認可書，惟不甚礙於被\n    告之防禦及本件訴訟之終結，至原告於99年1 月29日另具狀\n    追加聲明第2 項後，被告並無異議而為本案之言詞辯論（見\n    本院卷第190 、243 、287 頁），依法應視為同意上開訴之\n    變更，是原告所為訴之變更及追加，核與首揭規定相符，應\n    予准許，合先敘明。\n乙、實體方面：\n一、原告方面：\n  (一)原告起訴主張：原告係發明專利第I240777 號「防火金屬鋼\n    板結構(一)」（下稱系爭專利）之專利權人，被告等明知原告\n    擁有系爭專利權，竟未經原告同意，而以侵害系爭專利之申\n    請專利範圍之施工法，並依據建築技術規則第74條第2款之\n    規定取得「建築物防火屋頂板」之認可書，且被告於95年12\n    月22日向內政部營建署申請取得「內授營建管字第09508078\n    34號內政部建築新技術、新工法、新設備及新材料認可通知\n    書」，並於96年11月29日向內政部營建署申請取得「內授營\n    建管字第0960807640號內政部建築新技術、新工法、新設備\n    及新材料認可通知書」，又於97年8月4日取得「內授營建管\n    字第0970806023號建築新技術、新工法、新設備及新材料認\n    可通知書」，再於97年9月10日取得「內授營建管字第09708\n    07377號建築新技術、新工法、新設備及新材料認可通知書\n    」，被告實施上開4認可書及對外招攬之行為，已侵害系爭\n    專利權，為此爰依專利法第84條第1項後段請求排除被告等\n    之侵害，並依專利法第85條第1項第2款、公司法第23條、民\n    法第28條規定請求被告立匠鋼品工業有限公司（下稱立匠公\n    司）及其法定代理人即被告乙○○賠償所受損害。並聲明：\n    1.被告等不得實施「內授營建管字第0950807834號內政部建\n      築新技術、新工法、新設備及新材料認可通知書」、「內\n      授營建管字第0960807640號內政部建築新技術、新工法、\n      新設備及新材料認可通知書」、「內授營建管字第097080\n      6023號內政部建築新技術、新工法、新設備及新材料認可\n      通知書」及「內授營建管字第0970807377號內政部建築新\n      技術、新工法、新設備及新材料認可通知書」之內容；2.\n      被告等應賠償原告155 萬元整及自起訴狀送達被告之日起\n      按百分之5 計算之利息。\n  (二)對被告抗辯之陳述：\n  1.被證1 無法證明系爭專利之申請專利範圍欠缺新穎性與進步\n    性：\n    (1)此可由被證1之「申請案件資料」之「主要材料或構件」\n      係由「第一層烤漆鋼板、第二層矽酸鈣板、第三層岩棉、\n      第四層矽酸鈣板、雙併C型立柱與C型槽鐵小樑」組成可\n      知，且由被證1第14頁之「橫向剖透示意圖」亦可知悉，\n      於雙併C型立柱與C型槽鐵小樑之間設「第四層矽酸鈣板」\n      ，被證1亦僅設「第一層烤漆鋼板」，並無如系爭專利設\n      「上、下層鋼板」，且被證1之「雙併C型立柱與C型槽鐵\n      小樑為垂直設置」與系爭專利之上下層鋼架為同向設置不\n      同，且被證1並無法經由「雙併C型立柱拉引C型槽鐵小樑\n      ，以達到防止C型槽鐵小樑塌陷之防火效果」，而與系爭\n      專利藉由「上層鋼架拉引下層鋼架，以達到防止下層鋼架\n      塌陷之效果」結構特徵不同，自無從由被證1證明系爭專\n      利之申請專利範圍第1項及第8項欠缺新穎性或進步性。\n    (2)被證1之雙併C型立柱，雖然與C型鋼互相以自攻螺絲栓設\n      ，但由該雙併C型立柱係設於矽酸鈣板上方觀察，並因為\n      被證1之C型鋼需再藉由被覆防火被覆材（俗稱防火漆），\n      顯見，被證1之雙併C型立柱無法提供C型鋼產生任何拉引\n      力量，無法藉由雙併C型立柱以防止C型鋼受到火場高溫而\n      變形迅速塌陷之危險，而與系爭專利申請專利範圍第1項\n      之上層鋼架或下層鋼架結構特徵完全不同。被證1之「自\n      攻螺絲（c、d），係自雙併C型立柱（B）穿過矽酸鈣板（\n      E）與C型鋼栓設。」，系爭專利申請專利範圍第1項之連\n      結元件，由說明書第3圖至第9圖有各種結構之變化，但是\n      被證1僅係利用自攻螺絲將雙併C型立柱與C型鋼栓設，被\n      證1之自攻螺絲並無法提供拉引作用，以延長C型鋼受到火\n      場高溫而急速塌陷之問題，系爭專利申請專利範圍第1項\n      之連結元件3與被證1之自攻螺絲之特徵完全不同。被證1\n      之烤漆鋼板（A）設於最上層，於該烤漆鋼板與雙併C型立\n      柱（B）之間再設置有矽酸鈣板（F），系爭專利申請專利\n      範圍第1項之上層鋼板4下方就是上層鋼架，亦即上層鋼板\n      4係直接設置於上層鋼架上方，並與防火層形成防火區隔\n      區，惟依據設置之位置，被證1之烤漆鋼板並不等於系爭\n      專利申請專利範圍第1項之上層鋼板。系爭專利申請專利\n      範圍第1 項之下層鋼板5 為浪形、或琉璃瓦形、或平板形\n      狀、或隱藏狀，且係設於下層鋼架2 上方，並由上層鋼架\n      以為支撐與施工，形成防火層6 之舖設空間，被證1 並無\n      如系爭專利所設之下層鋼板，僅有矽酸鈣板（E ）與（F\n      ），但矽酸鈣板並不等於系爭專利之下層鋼板5 ，充其量\n      ，被證1 之矽酸鈣板（E ）、（F ）與岩棉（D ）僅等於\n      系爭專利申請專利範圍第1 項之防火層6 。系爭專利申請\n      專利範圍第1 項之防火層6 係設於上層鋼板4 與下層鋼板\n      5 之間，且形成防火區隔區7 ，防火層6 可以單一防火材\n      料或以複合材料為之，複合材料如防火材加防水毯或再加\n      入防火岩棉或矽酸鈣板或陶瓷棉等，被證1 之防火層，係\n      由矽酸鈣板（E ）、（F ）與岩棉（D ）組成，設置於C\n      型鋼上方與雙併C 型立柱上方，二者防火層之設置結構不\n      相同，且被證1 僅是將防火層設置多層狀態，但該矽酸鈣\n      板遇到高溫即會脆化，根本無法經由拉引雙併C 型立柱拉\n      引C 型鋼。被證1 僅是利用傳統隔間牆之結構，作為屋頂\n      板之結構，需藉由被覆防火漆，才能達成所要達成之目的\n      ，無法真正提昇建築物之防火效果。被證1 施工時，需被\n      覆防火層，再逐層舖設複數之厚重之矽酸鈣板，結果並無\n      法較系爭專利之更具防火效果。綜上，被證1 欠缺系爭專\n      利申請專利範圍第1 項之下層鋼板，且由被證1 之結構所\n      揭示之「矽酸鈣板（E ）、（F ）與岩棉（D ）」之設置\n      僅與請求項1 之防火層6 相當，但系爭專利申請專利範圍\n      第1 項又較被證1 之結構簡易，但防火時效仍然優於被證\n      1 ，因為由被證1 之自攻螺絲並無法提供雙併C 型立柱拉\n      引C 型鋼之力量，無法藉由雙併C 型立柱拉引C 型鋼，產\n      生防止C 型鋼快速塌陷之問題。因此，由被證1 並無法證\n      明請求項1 欠缺進步性。\n    (3)系爭專利設防火區隔區7係由防火層6與上層鋼板4所形成\n      者，具有讓熱氣被順利排出，而延長上層鋼板4與上層鋼\n      架1之受到火場高溫而變形之時間，具有提高防火時效之\n      優點，但被證1於雙併C型立柱與烤漆鋼板之間再設置有矽\n      酸鈣板（E），如此，將形成另一隔熱層，無法適時將火\n      場中之熱氣排出，反而會將高溫熱氣封閉於屋內，如果發\n      生火警，勢必加快C型鋼之變形塌陷之時間，顯見系爭專\n      利之防火效果絕對較被證1更為增進與精進，兩者結構不\n      同。\n  2.被告等應負推定過失責任，系爭專利係於94年10月1日公告\n    於經濟部智慧財產局（下稱智慧局）之專利公報中，專利公\n    報並包含「紙本公報、光碟公告與網站內容」等，而智慧局\n    除了位於台北市之公務機關所在地之外，更於高雄、台南、\n    台中與新竹均設有辦事處，接受並提供本國人民隨時查閱並\n    利用各項智慧財產資訊之方法，且系爭專利申請之後，原告\n    亦取得「內授營建管字第0950800048號內政部建築新技術、\n    新工法、新設備及新材料認可通知書」，且於94年1 月31日\n    公告於財團法人中華建築中心之網站，而財團法人中華建築\n    中心之網站乃被告最常利用並作為被告施工或監工完成之建\n    築物開立防火證明進行登錄之網站，且由財團法人中華建築\n    中心之網站中，被告更得以輕易取得系爭專利之相關防火認\n    證資訊，而被告對於他人取得之具備進步性之防火認證直接\n    加以援用，實應負推定過失責任。\n二、被告則抗辯以：\n  (一)依系爭專利所附圖說可知，所謂上層鋼架及下層鋼架可以為\n    C形鋼、H形鋼抑或是其他形狀鋼架為之，經比較被證1與系\n    爭專利申請專利範圍第1項，可知被證1之雙併C型鋼編號B（\n    即等同系爭專利之上層鋼架）、C型鋼編號C（即等同系爭專\n    利之下層鋼架）、上層矽酸鈣板編號F（即等同系爭專利之\n    上層鋼板）、下層矽酸鈣板編號E（即等同系爭專利之下層\n    鋼板）、雙併C型鋼B與C間藉自攻螺絲編號b、c（即等同系\n    爭專利連結元件）相連結、雙併C型鋼B與C間設岩棉編號D（\n    即等同系爭專利之防火層）等之技術設計功能皆相同，並確\n    實早於系爭專利申請前已揭露系爭專利申請專利範圍第1項\n    所述必要元件與元件間之相對關係。至被證1上層矽酸鈣板\n    （編號F）上方設置烤漆鋼板（編號A），此雖與系爭專利上\n    層鋼架上方及上層鋼架與下層鋼架間分別固定上層鋼板及下\n    層鋼板相異。惟被證1早已揭露於雙併C型鋼（編號B）上方\n    及雙併C型鋼（編號B）與C型鋼（編號C）間分別設有上層矽\n    酸鈣板（編號F）、下層矽酸鈣板（編號E），將此矽酸鈣板\n    F、E置換為鋼板，為所屬技術領域中具有通常知識者所能輕\n    易完成。此觀系爭專利申請前，第三人玉逢工程有限公司所\n    申請內政部建築新技術、新工法、新設備及新材料認可通知\n    書中之系統概述記載「兩面覆蓋單層烤漆鋼板，其中填充岩\n    棉複合板之防火屋頂板…」可知，故於系爭專利申請前，即\n    有所屬技術領域中具有通常知識者，輕易完成換置矽酸鈣板\n    為鋼板之技術，原告卻執此主張為其專利申請範圍，顯不具\n    進步性。\n  (二)系爭專利申請專利範圍第8項界定一種「防火金屬鋼板結構\n    (一)」，其包含：「連結元件，連結元件係設於上層鋼架與下\n    層鋼架之間，…之結構剛性」，然系爭專利申請專利範圍第\n    8 項並未提及所謂連結元件係指何種材料，是否凡各式螺栓\n    均屬其所指之連結元件範圍，亦不可知，被證1所揭露之自\n    攻螺絲b、c與系爭專利所謂之連結元件或螺栓之功用均為螺\n    鎖連結二鋼材，是故被證1明顯給予系爭專利申請專利範圍\n    第8項產生教示作用，系爭專利所謂連結元件及螺栓之設計\n    僅是就被證1技術特徵之簡單置換，顯不具進步性。\n  (三)被告並無侵害原告專利之情事：\n  1.系爭專利之申請專利範圍第1、8項僅為施工法與完成品，並\n    不含其中之材料與零件，故被告依照上開認可通知書販賣主\n    要材料與構件，並無侵害系爭專利之虞。\n  2.縱原告之專利為有效，然依原證3之標準施工圖之短項剖面\n    圖均可得知，該項通知書之施工方法包含以12#X3.5\"六角自\n    攻螺絲，間距380mm貫穿整個防火屋頂板結構以及12#1.5\"六\n    角自攻螺絲，間距380mm以上下拴緊鋼板等二種方式固定，\n    顯與系爭專利僅用螺栓上下拴緊之施工方式迥異，原證4（\n    亦採用原證3固定法）、5、6部分，自攻螺絲均採用隱藏式\n    設計。易言之，即Z型連結元件先以自攻螺絲固定於屋頂板\n    固定座後，再將上層鋼板從外面包覆屋頂板固定座，並夾緊\n    固定，使外觀觀之無法察覺六角自攻螺絲固定之處，以減少\n    六角自攻螺絲因風雨侵蝕而加速氧化，是故原證4、5、6部\n    分之自攻螺絲固定方式均隱藏於屋面板固定座內，與系爭專\n    利均將螺栓開放式拴緊之設計相異，此由原證4、5、6之長\n    向、短向剖面圖說可證，且原證4、5、6之施工步驟7.8.亦\n    說明「將上層烤漆鋼板固定於固定座上方，安裝第二片烤漆\n    鋼板時，將第二片烤漆鋼板之左側扣合於第一片鋼板右側之\n    上方，再以六角自攻螺絲鎖固」、「將屋面板固定座以自攻\n    螺絲固定於Z 型鍍鋅隔件之上方，將上層烤漆板固定於屋面\n    板固定座上，安裝第二片烤漆鋼板時，於第二片烤漆鋼板之\n    左側扣合第一片鋼板右側之上方，以鉸合器於鋼板接合處將\n    兩鋼板鉸合。」，職是被告原證3 、4 、5 、6 通知書所施\n    工之工法與材料均與系爭專利迥異。又被告4 項認可書之結\n    構主要與系爭專利之不同點在於，被告此四項認可書施做方\n    式僅有在最下層架設一C 型鋼並以自攻螺絲固定下層鋼板於\n    C 型鋼並鋪設岩棉後，即鋪設鍍鋅隔件或Z 型隔件，且從該\n    四項認可通知書之構成材料規格上可知，鍍鋅隔件僅為\n    0.47mm 、Z型隔件僅為1.5mm ，且鍍鋅隔件或Z 型隔件質地\n    偏軟，並無上下層鋼架之剛性，故並無法與鋼架有相同之功\n    用，以自攻螺絲由上而下貫穿後，並未有如系爭專利以兩個\n    C 型鋼之組合以連結元件連結而產生上下拉引之力量。\n  3.被告係信賴內政部所頒發之認可通知書而為使用，並非故意\n    侵害原告之專利權。再者，原證2之存證信函係於原告專利\n    申請4 年多後向多數業者發出，然其專利範圍、受函者所販\n    賣之內容何種型號有侵害系爭專利之虞等事項均無明述。原\n    告如此通知，實難謂被告明知其專利範圍而仍販售侵害系爭\n    專利之成品，而請求排除侵害。況被告就原證4 之材料認可\n    通知書所示材料與構件，早已於原告以存證信函通知2 年前\n    停止施作及販賣，原證3 之內容於原證2 存證信函通知後已\n    無施作，僅零星販賣零件，故無侵害原告專利權之虞。\n  (四)並聲明：1.原告之訴駁回；2.訴訟費用由原告負擔。\n三、本件兩造不爭執之事實（見本院卷第161、162頁）：\n  (一)原告於93年7 月29日向經濟部智慧財產局申請「防火金屬鋼\n    板結構(一)」發明專利，經該局審查核准專利後，發給第I240\n    777號專利證書，專利權期間自94年10月1日起至113年7月28\n    日止。\n  (二)被告確有向內政部營建署申請取得下列認可書：\n  1.95年12月22日內授營建管字第0950807834號建築新技術、新\n    工法、新設備及新材料認可通知書。\n  2.96年11月29日內授營建管字第0960807640號建築新技術、新\n    工法、新設備及新材料認可通知書。\n  3.97年8月4日內授營建管字第0970806023號建築新技術、新工\n    法、新設備及新材料認可通知書。\n  4.97年9月10日內授營建管字第0970807377號建築新技術、新\n    工法、新設備及新材料認可通知書。\n四、本件經本院與兩造整理並協定簡化之爭點如下（見本院卷第\n    162頁）：\n  (一)被證1是否足以證明系爭專利申請專利範圍第1、8項不具進\n    步性（被證2之主張業經被告於99年3月24日捨棄，見本院卷\n    第246頁）？\n  (二)上開認可書所載之鋼板施工結構是否落入系爭專利申請專利\n    範圍第1、8項？原告得否依專利法第84條第1項請求排除、\n    防止侵害或損害賠償？\n五、本院之判斷如下：\n  (一)被證1足以證明系爭專利申請專利範圍第1、8項不具進步性\n    ：\n  1.按解釋專利權範圍應以申請專利範圍之記載為準，不得將發\n    明說明或圖式有揭露但未載於申請專利範圍之技術特徵讀入\n    ，而縮小專利權範圍，是以專利是否具有新穎性或進步性，\n    應以申請專利範圍之記載為判斷標的，倘某項技術特徵僅揭\n    露於發明說明或圖式卻未載於申請專利範圍，則專利權人不\n    得藉由該技術特徵減縮其申請專利範圍，俾使其專利得以符\n    合新穎性或進步性之要件，至於用以證明該專利不具新穎性\n    或進步性之先前技術倘係專利文獻，則以該專利文獻所揭露\n    之全部內容為先前技術。此外，發明說明應記載實施方式，\n    俾以符合明確且充份揭露達成發明目的所採用解決問題之技\n    術手段，而使具有通常知識者在無須過度實驗之情況下，即\n    能瞭解申請專利之發明內容，並可據以實施，是以解釋專利\n    權範圍時應涵括但不限於說明書所載之實施方式或實施例。\n  2.查系爭專利申請專利範圍共8項，其中第1、8項為獨立項，\n    其餘第2項至第7項為附屬項，第1項之內容為：「一種防火\n    金屬鋼板結構(一)，包含：鋼架，鋼架設上層鋼架及下層鋼架\n    ，於上層鋼架與下層鋼架之間並設有連結元件，利用連結元\n    件以將上、下層鋼架連結，以使上層鋼架對下層鋼架產生拉\n    引力量；鋼板，鋼板設上層鋼板及下層鋼板，分別固定於上\n    層鋼架上方及上層鋼架與下層鋼架之間；防火層，該防火層\n    設於上層鋼板與下層鋼板之間，以組成本發明之防火金屬鋼\n    板。」，第8項之內容為：「一種防火金屬鋼板結構(一)，包\n    含：連結元件，連結元件係設於上層鋼架與下層鋼架之間，\n    以使下層鋼架藉由上層鋼架產生拉引力量，強化整體防火金\n    屬鋼板之結構剛性。」，雖系爭專利說明書之發明內容記載\n    ：「本發明之特點有：1.本發明之防火金屬鋼板結構(一)，利\n    用連結元件連結上、下層鋼架，以使上層鋼架對下層鋼架產\n    生拉引力量，確保下層鋼架可承受火警高溫，不易變形，避\n    免建築物塌陷造成危害。2.本發明之防火金屬鋼板結構(一)設\n    鋼板，鋼板設上層鋼板及下層鋼板，分別固定於上層鋼架上\n    方及上層鋼架與下層鋼架之間，再於上層鋼板與下層鋼板之\n    間設防火層，且形成防火區隔區，利用防火層之防火功能，\n    及於前述防火區隔區形成部份之空氣空間，更增加防火效果\n    ，以符合國家標準之防火時效。」，惟系爭專利申請專利範\n    圍第1項並未揭露防火層與上層鋼板間設有「防火區隔區」\n    ，而防火層之舖設於系爭專利申請專利範圍第1項中僅界定\n    「設於上層鋼板與下層鋼板之間」，是以「防火區隔區」即\n    無從作為判斷系爭專利申請專利範圍第1項是否具有進步性\n    之技術特徵。\n  3.被證1為內政部營建署於92年8月7日對弘耀實業有限公司生\n    產之「弘耀F-18防火屋頂」所核發之認可通知書，其產品種\n    類為「建築物防火屋頂版」，被證1之防火屋頂板結構，係\n    將C型槽鋼噴覆防火被覆材作為小梁，固定於H型鋼大梁上，\n    在C 型鋼上利用自攻螺絲及雙併C 型鋼固定，由上而下順序\n    為：第一層烤漆鋼板、第二層矽酸鈣板、雙併C 型鋼、第三\n    層填充岩棉、第四層矽酸鈣板所組成的合板屋頂結構。依系\n    爭專利說明書「發明說明」記載：「鋼架設上層鋼架1 及下\n    層鋼架2 ，鋼架由C 形鋼；或H 形鋼；或其他形狀之鋼架為\n    之皆可以，本發明以C 形鋼以解說明本發明之特性。再於上\n    層鋼架1 與下層鋼架2 之間並設有連結元件3 ，該連結元件\n    3 可以為複數，端視鋼架之長度而定。」、「連結元件3 ，\n    可以由任意配件為之」、「防火層6 可以單一防火料或以複\n    合材料為之，複合材料如防火材加防水毯或再加入防火岩棉\n    」（見說明書第9 頁），是以系爭專利之上下層鋼架即包括\n    C 形鋼，防火層即包括防火岩棉，至於連結元件只須能達成\n    連結鋼架之功效即包含之，依被證1 之記載其防火屋頂板之\n    結構為「以雙併C 型鋼（間隔915mm ），加上自攻螺絲固定\n    由外層烤漆鋼板（0.5mm ）貼上矽酸鈣板（6mm ），中間填\n    實密度80公斤/ 立方米之岩棉（50mm），再加上矽酸鈣板（\n    10mm）之屋頂板結構，固定在C 型鋼槽上（間隔915mm ）」\n    （詳如附圖，見本院卷第60頁），就被證1 與系爭專利之申\n    請專利範圍第1 項所界定之技術特徵比對，系爭專利申請專\n    利範圍第1 項所記載之上層鋼板、上層鋼架、防火層、連結\n    元件、下層鋼架等構件，已分別對應揭露於被證1 之烤漆鋼\n    板、雙併C 型鋼、岩棉、六角自攻螺絲、C 型鋼，且兩案之\n    構件組構關係係屬相同，其不同處在於被證1 與下層鋼架連\n    結者為矽酸鈣板，而系爭專利則為下層鋼板，是以二者均具\n    有下層板構件，僅該構件之材質不同。\n  4.依系爭專利說明書第8頁記載：「發明目的乃於上層鋼架與\n    下層鋼架之間設有連結元件，利用連結元件以將上、下層鋼\n    架連結，以使上層鋼架對下層鋼架產生拉引力量，下層鋼架\n    可承受火場高溫，不易變形，建築物不易塌陷，造成危害，\n    以符合國家標準之防火時效。」，因此與下層鋼架連結者是\n    否使用鋼板並非本案之發明目的或特點，且被證1之下層使\n    用矽酸鈣板係屬耐燃之防火建材，系爭專利與被證1雖於下\n    層板部分有鋼板與矽酸鈣板之不同，然由於鋼板、矽酸鈣板\n    皆屬系爭專利申請時防火屋頂習用之建材，此由被證5內政\n    部營建署於93年2月4日以內授營建管字第0930082097號建築\n    新技術、新工法、新設備及新材料認可通知書可資佐證（見\n    本院卷第264頁），而原告又未能證明將矽酸鈣板置換為先\n    前技術之鋼板，其材質之不同有何無法預期之功效，則原告\n    以具有相同功能的已知材料置換已知物品中相對應之材料，\n    應認定該發明能輕易完成，不具進步性，故被證1足以證明\n    系爭專利申請專利範圍第1項不具進步性。\n  5.原告雖主張系爭專利可藉由連結元件以使上層鋼架對下層鋼\n    架產生拉引力量，下層鋼架可承受火場高溫，不易變形，而\n    被證1之C型鋼必須再被覆防火被覆材，顯見被證1之C型鋼無\n    法藉由雙併C型立柱產生任何拉引力量，且系爭專利之上下\n    層鋼架為同向設置等語。惟查，系爭專利申請專利範圍第1\n    項僅記載其連結元件可使上層鋼架對下層鋼架產生拉引力量\n    ，惟其僅為功能的敘述，而於系爭專利申請專利範圍第1項\n    中並未對連結元件或下層鋼架之構造有所限定，系爭專利說\n    明書「發明說明」僅記載：「鋼架設上層鋼架1及下層鋼架2\n    ，鋼架由C形鋼；或H型鋼；或其他形狀之鋼架為之皆可以，\n    本發明以C形鋼以解說明本發明之特性。再於上層鋼架1與下\n    層鋼架2之間並設有連結元件3，該連結元件3可以為複數，\n    端視鋼架之長度而定。」、「連結元件3，可以由任意配件\n    為之」，業如前述，系爭專利申請專利範圍第1項亦未界定\n    其鋼架及連結元件是否為防火材料或被覆防火漆，則原告主\n    張被證1之C型鋼必須再被覆防火被覆材，而無法藉由雙併C\n    型立柱產生任何拉引力量，即非可採。\n  6.另就被證1與系爭專利申請專利範圍第8項所界定之技術特徵\n    比對，系爭專利所記載設於上層鋼架與下層鋼架間之連結元\n    件已為被證1之六角自攻螺絲所揭露，由於被證1之六角自攻\n    螺絲亦設於上層鋼架與下層鋼架間，而其是否可使下層鋼架\n    藉由上層鋼架產生拉引力量以強化整體防火金屬鋼板之結構\n    剛性，已如前所述，故被證1亦可證明系爭專利申請專利範\n    圍第8項不具進步性。\n  (二)原證3、4、5、6認可書所載之鋼板施工結構落入系爭專利申\n    請專利範圍第1項：\n  1.原證3認可書之侵害分析:\n    (1)經解析系爭專利申請專利範圍第1項，其技術特徵可拆解\n      為5個要件，分別為編號1要件「一種防火金屬鋼板結構(一)\n      ，包含：」，編號2要件「鋼架，鋼架設上層鋼架及下層\n      鋼架，」，編號3要件「於上層鋼架與下層鋼架之間並設\n      有連結元件，利用連結元件以將上、下層鋼架連結，以使\n      上層鋼架對下層鋼架產生拉引力量；」，編號4要件「鋼\n      板，鋼板設上層鋼板及下層鋼板，分別固定於上層鋼架上\n      方及上層鋼架與下層鋼架之間；」，編號5要件「防火層\n      ，該防火層設於上層鋼板與下層鋼板之間，以組成本發明\n      之防火金屬鋼板。」。\n    (2)原證3之認可書為一種建築物防火屋頂板，其設有上、下\n      層鋼板，板厚度0.42mm，上、下層鋼板間以C型鋼固定，\n      利用12#×3.5\"六角頭自攻螺絲連結上（C型鋼）、下層鋼\n      架，上下層鋼板間填充陶瓷棉。原證3之認可書對應於系\n      爭專利申請專利範圍第1項各技術特徵可解析為5個要件，\n      原證3為一種防火金屬鋼板結構，編號1要件已文義讀取，\n      原證3設有上、下層C型鋼架，編號2要件已文義讀取，原\n      證3於上下層鋼架間設有六角頭自攻螺絲之連結元件，利\n      用連結元件以將上、下層鋼架連結，以使上層鋼架對下層\n      鋼架產生拉引力量，編號3要件已文義讀取，原證3設有厚\n      度0.42 mm之上、下層烤漆鋼板，編號4要件已文義讀取，\n      原證3亦於上下層鋼板間填充有陶瓷棉之防火層，編號5要\n      件已文義讀取，故原證3認可書之技術內容分別為系爭專\n      利申請專利範圍第1項編號1至5要件之文義所讀取，是以\n      原證3認可書落入系爭專利申請專利範圍第1項之文義範圍\n      。\n    (3)至於被告辯稱原證3之認可書施工法包含以12#×3.5\"六角\n      頭自攻螺絲，間距380mm貫穿整個防火屋頂板結構以及12#\n      1.5\"六角自攻螺絲，間距380mm以上下拴緊鋼板等二種方\n      式固定，顯與系爭專利僅用螺栓上下拴緊之施工方式迥異\n      等語。惟查，系爭專利申請專利範圍第1項係界定：「於\n      上層鋼架與下層鋼架之間並設有連結元件，利用連結元件\n      以將上、下層鋼架連結，以使上層鋼架對下層鋼架產生拉\n      引力量」，系爭專利說明書之發明說明雖係以螺栓作為連\n      結元件之實施例，惟解釋申請專利範圍時僅能就申請專利\n      範圍所載之技術特徵予以解釋，尚不得將說明書所揭露之\n      實施例讀入申請專利範圍，而限縮申請專利範圍，被告所\n      稱系爭專利僅用螺栓上下拴緊之施工方法及連結元件之結\n      構並未載於系爭專利申請專利範圍第1項，而原證3認可書\n      之施工法亦係於上層鋼架與下層鋼架之間設有連結元件（\n      六角頭自攻螺絲）將上、下層鋼架連結，以該連結使上層\n      鋼架對下層鋼架產生拉引力量，原證3之該項技術內容自\n      應為系爭專利申請專利範圍第1項編號3要件之文義所讀取\n      ，被告所辯尚非可採。\n  2.原證4認可書之侵害分析：\n    (1)原證4之認可書為一種建築物複層式防火屋頂板，其設有\n      厚度0.52mm上層鋼板、厚度0.42mm下層鋼板，上、下層鋼\n      板間以熱浸鍍鋅鋼材之固定座固定，利用12#×3.5\"六角\n      頭自攻螺絲連結上、下層鋼架（C型鋼125×50×20×2.3m\n      m），上、下層鋼板間填充陶瓷棉。\n    (2)原證4之認可書對應於系爭專利申請專利範圍第1項各技術\n      特徵可解析為5個要件，原證4為一種防火金屬鋼板結構，\n      編號1要件已文義讀取，原證4設有上層熱浸鍍鋅鋼材鋼架\n      、下層C型鋼架，編號2要件已文義讀取，原證4於上、下\n      層鋼架間設有六角頭自攻螺絲之連結元件，利用連結元件\n      以將上、下層鋼架連結，以使上層鋼架對下層鋼架產生拉\n      引力量，編號3要件已文義讀取，原證4設有厚度0.52mm上\n      層鋼板、厚度0.42mm下層鋼板，編號4要件已文義讀取，\n      原證4亦於上下層鋼板間填充有陶瓷棉之防火層，編號5要\n      件已文義讀取，故原證4認可書之技術內容分別為系爭專\n      利申請專利範圍第1項編號1至5要件之文義所讀取，是以\n      原證4認可書落入系爭專利申請專利範圍第1項之文義範圍\n      。\n  3.原證5認可書之侵害分析：\n    (1)原證5之認可書為一種建築物複層式防火金屬鋼板屋頂，\n      其設有厚度0.476mm上層鋼板、厚度0.42mm下層鋼板，上\n      、下層鋼板間固定有鍍鋅鋼材之鍍鋅隔件50×50×50 ×1\n      .5 ×1.5 （t ）mm，間距1000mm，利用六角頭自攻螺絲\n      連結上、下層鋼架（C 型鋼125 ×50×20×2.3 （t ）mm\n      ），上、下層鋼板間填充岩棉及陶瓷棉。\n    (2)原證5之認可書對應於系爭專利申請專利範圍第1項各技術\n      特徵可解析為5個要件，原證5為一種防火金屬鋼板結構，\n      編號1要件已文義讀取，原證5設有上層鍍鋅鋼材（鍍鋅隔\n      件）鋼架、下層C型鋼架，編號2要件已文義讀取，原證5\n      於上、下層鋼架間設有六角頭自攻螺絲之連結元件，利用\n      連結元件以將上、下層鋼架連結，以使上層鋼架對下層鋼\n      架產生拉引力量，編號3要件已文義讀取，原證5設有厚度\n      0.476mm上層鋼板、厚度0.42mm下層鋼板，編號4要件已文\n      義讀取，原證5亦於上下層鋼板間填充有岩棉及陶瓷棉之\n      防火層，編號5要件已文義讀取，故原證5認可書之技術內\n      容分別為系爭專利申請專利範圍第1項編號1至5要件之文\n      義所讀取，是以原證5認可書落入系爭專利申請專利範圍\n      第1項之文義範圍。\n  4.原證6認可書之侵害分析：\n    (1)原證6之認可書為一種建築物複層式防火金屬鋼板屋頂，\n      其設有厚度0.476mm上層烤漆鋼板、厚度0.42mm下層烤漆\n      鋼板，上、下層鋼板間固定有鍍鋅鋼材之Z型鍍鋅隔件（5\n      0×50×50×1.5（t）mm），利用六角頭自攻螺絲連結上\n      、下層鋼架（C型鋼125×50×20×2.3（t）mm），上、下\n      層鋼板間填充岩棉及陶瓷棉。\n    (2)原證6之認可書對應於系爭專利申請專利範圍第1項各技術\n      特徵可解析為5個要件，原證6為一種防火金屬鋼板結構，\n      編號1要件已文義讀取，原證6設有上層鍍鋅鋼材（Z型鍍\n      鋅隔件）鋼架、下層C型鋼架，編號2要件已文義讀取，原\n      證6於上、下層鋼架間設有六角頭自攻螺絲之連結元件，\n      利用連結元件以將上、下層鋼架連結，以使上層鋼架對下\n      層鋼架產生拉引力量，編號3要件已文義讀取，原證6設有\n      厚度0.476mm上層鋼板、厚度0.42mm下層鋼板，編號4要件\n      已文義讀取，原證6亦於上下層鋼板間填充有岩棉及陶瓷\n      棉之防火層，編號5要件已文義讀取，故原證6認可書之編\n      號1至5要件皆為系爭專利申請專利範圍第1項編號1至5要\n      件文義所讀取，是以原證6認可書落入系爭專利申請專利\n      範圍第1項之文義範圍。\n  5.至於被告辯稱原證4、5、6之認可書施工法之自攻螺絲固定\n    方式均隱藏於屋面板固定座內，與系爭專利均將螺栓開放式\n    拴緊之設計相異等語，惟查，系爭專利申請專利範圍第1項\n    並未限定連結元件螺栓為開放式或隱藏式拴緊，亦不得將說\n    明書所揭露之實施例讀入申請專利範圍，而限縮系爭專利申\n    請專利範圍第1項，則原證4、5、6認可書之施工法係於上層\n    鋼架與下層鋼架之間設有連結元件（六角頭自攻螺絲）將上\n    、下層鋼架連結，以該連結使上層鋼架對下層鋼架產生拉引\n    力量，原證4、5、6之該項技術內容亦為系爭專利申請專利\n    範圍第1項編號3要件文義所讀取。\n  6.另被告辯稱原證3、4、5、6認可書之構成材料規格上可知，\n    鍍鋅隔件僅為0.47mm、Z型隔件僅為1.5mm，且鍍鋅隔件或Z\n    型隔件質地偏軟，並無上下層鋼架之剛性，故並無法與鋼架\n    有相同之功用，以自攻螺絲由上而下貫穿後，並未有如系爭\n    專利以兩個C型鋼之組合以連結元件連結而產生上下拉引之\n    力量等語。經查，縱原證3、4、5、6認可書鍍鋅隔件僅為0.\n    47mm、Z型隔件僅為1.5mm，然其上下層烤漆鋼板厚度亦僅為\n    0.476mm或0.42mm，相對該上下層鋼板厚度，尚難稱0.47mm\n    之鍍鋅隔件、0.42mm之Z型隔件不具有結構之剛性支撐作用\n    。況且系爭專利申請專利範圍第1項中亦未界定相關構件之\n    形狀及厚度，原證3、4、5、6既揭示於上、下層鋼架間設有\n    連結元件，實無法僅由其所稱之厚度即可推知其未能產生拉\n    引力量，被告所辯均不足採。\n  (三)原證3、4、5、6認可書所載之鋼板施工結構落入系爭專利申請\n    專利範圍第8項：\n  1.經解析系爭專利申請專利範圍第8項，其技術特徵可拆解為2\n    個要件，分別為編號1要件「一種防火金屬鋼板結構(一)，包\n    含：」，編號2要件「連結元件，連結元件係設於上層鋼架\n    與下層鋼架之間，以使下層鋼架藉由上層鋼架產生拉引力量\n    ，強化整體防火金屬鋼板之結構剛性。」。\n  2.原證3之認可書對應於系爭專利申請專利範圍第8項各技術特\n    徵可解析為2個要件，原證3為一種防火金屬鋼板結構，編號\n    1要件已文義讀取，原證3於上下層鋼架間設有六角頭自攻螺\n    絲之連結元件，利用連結元件以將上、下層鋼架連結，以使\n    上層鋼架對下層鋼架產生拉引力量，編號2要件已文義讀取\n    ，故原證3認可書之編號1、2要件皆為系爭專利申請專利範\n    圍第8 項編號1 、2 要件文義所讀取，是以原證3 認可書落\n    入系爭專利申請專利範圍第8 項之文義範圍。\n  3.原證4之認可書對應於系爭專利申請專利範圍第8項各技術特\n    徵可解析為2個要件，原證4為一種防火金屬鋼板結構，編號\n    1要件已文義讀取，原證4於上下層鋼架間設有六角頭自攻螺\n    絲之連結元件，利用連結元件以將上、下層鋼架連結，以使\n    上層鋼架對下層鋼架產生拉引力量，編號2要件已文義讀取\n    ，故原證4認可書之編號1、2要件皆為系爭專利申請專利範\n    圍第8 項編號1 、2 要件文義所讀取，是以原證3 認可書落\n    入系爭專利申請專利範圍第8 項之文義範圍。\n  4.原證5之認可書對應於系爭專利申請專利範圍第8項各技術特\n    徵可解析為2個要件，原證5為一種防火金屬鋼板結構，編號\n    1要件已文義讀取，原證5於上下層鋼架間設有六角頭自攻螺\n    絲之連結元件，利用連結元件以將上、下層鋼架連結，以使\n    上層鋼架對下層鋼架產生拉引力量，編號2要件已文義讀取\n    ，故原證5認可書之編號1、2要件皆為系爭專利申請專利範\n    圍第8 項編號1 、2 要件文義所讀取，是以原證5 認可書落\n    入系爭專利申請專利範圍第8 項之文義範圍。\n  5.原證6之認可書對應於系爭專利申請專利範圍第8項各技術特\n    徵可解析為2個要件，原證6為一種防火金屬鋼板結構，編號\n    1要件已文義讀取，原證6於上下層鋼架間設有六角頭自攻螺\n    絲之連結元件，利用連結元件以將上、下層鋼架連結，以使\n    上層鋼架對下層鋼架產生拉引力量，編號2要件已文義讀取\n    ，故原證6認可書之編號1、2要件皆為系爭專利申請專利範\n    圍第8 項編號1 、2 要件文義所讀取，是以原證6 認可書落\n    入系爭專利申請專利範圍第8 項之文義範圍。\n六、綜上所述，原證3、4、5、6認可書所載之鋼板施工結構均落\n    入系爭專利申請專利範圍第1、8項之文義範圍，惟被告所提\n    出之被證1足以證明系爭專利申請專利範圍第1、8項均不具\n    進步性，而有專利法第22條第4項之撤銷原因，則依智慧財\n    產案件審理法第16條第2項規定，原告於本件民事訴訟中自\n    不得以系爭專利申請專利範圍第1、8項對於被告主張權利。\n    從而，原告依專利法第84條第1項、第85條第1項第2款、公\n    司法第23條及民法第28條規定為如訴之聲明所示之請求，均\n    無理由，應予駁回。\n七、本件事證已臻明確，兩造其餘主張陳述及所提之證據，經本\n    院斟酌後，認與判決結果不生影響，均毋庸再予論述，附此\n    敘明。\n八、訴訟費用負擔之依據：民事訴訟法第78條。",
    "reason": "甲、程序方面：\n一、按訴狀送達後，原告不得將原訴變更或追加他訴，但被告同\n    意、不甚礙被告之防禦及訴訟之終結者，不在此限。被告於\n    訴之變更或追加無異議，而為本案之言詞辯論者，視為同意\n    變更或追加。民事訴訟法第255條第1項第1款、第7款、第2\n    項分別定有明文。本件原告於民國98年10月2日起訴時其訴\n    之聲明第1項係請求「被告等不得實施『內授營建管字第095\n    0807834號內政部建築新技術、新工法、新設備及新材料認\n    可通知書』及『內授營建管字第0960807640號內政部建築新\n    技術、新工法、新設備及新材料認可通知書』之內容」，嗣\n    於98年12月2日具狀擴張第1項聲明為「被告等不得實施『內\n    授營建管字第0950807834號內政部建築新技術、新工法、新\n    設備及新材料認可通知書』（見原證3）、『內授營建管字\n    第0960807640號內政部建築新技術、新工法、新設備及新材\n    料認可通知書』（見原證4）、『內授營建管字第097080602\n    3號內政部建築新技術、新工法、新設備及新材料認可通知\n    書』（見原證5 ）及『內授營建管字第0970807377號內政部\n    建築新技術、新工法、新設備及新材料認可通知書』（下稱\n    見原證6 ）之內容」（見本院卷第94頁），復於99年1 月29\n    日具狀追加聲明第2 項為「被告等應賠償原告新臺幣（下同\n    ）155 萬元整，及自起訴狀送達被告之日起按百分之5 計算\n    之利息」（見本院卷第172 頁），被告雖不同意原告於98年\n    12月2日 所為訴之追加（見本院卷第154 頁），惟原告係於\n    本院98 年1月13日第1 次行準備程序前即已具狀擴張第1 項\n    訴之聲明，且經原告於98年12月2 日具狀擴張聲明後，被告\n    係以系爭專利不具進步性，且原證4 、5 、6 認可書所載施\n    工方法之自攻螺絲固定方式均係隱藏於屋面板固定座內，與\n    系爭專利均將螺栓開放式拴緊之設計相異，故無侵害原告專\n    利權等語資為抗辯（見本院卷第154-157 頁），足見原告雖\n    擴張第1 項聲明而及於原證5 、6 之認可書，惟不甚礙於被\n    告之防禦及本件訴訟之終結，至原告於99年1 月29日另具狀\n    追加聲明第2 項後，被告並無異議而為本案之言詞辯論（見\n    本院卷第190 、243 、287 頁），依法應視為同意上開訴之\n    變更，是原告所為訴之變更及追加，核與首揭規定相符，應\n    予准許，合先敘明。\n乙、實體方面：\n一、原告方面：\n  (一)原告起訴主張：原告係發明專利第I240777 號「防火金屬鋼\n    板結構(一)」（下稱系爭專利）之專利權人，被告等明知原告\n    擁有系爭專利權，竟未經原告同意，而以侵害系爭專利之申\n    請專利範圍之施工法，並依據建築技術規則第74條第2款之\n    規定取得「建築物防火屋頂板」之認可書，且被告於95年12\n    月22日向內政部營建署申請取得「內授營建管字第09508078\n    34號內政部建築新技術、新工法、新設備及新材料認可通知\n    書」，並於96年11月29日向內政部營建署申請取得「內授營\n    建管字第0960807640號內政部建築新技術、新工法、新設備\n    及新材料認可通知書」，又於97年8月4日取得「內授營建管\n    字第0970806023號建築新技術、新工法、新設備及新材料認\n    可通知書」，再於97年9月10日取得「內授營建管字第09708\n    07377號建築新技術、新工法、新設備及新材料認可通知書\n    」，被告實施上開4認可書及對外招攬之行為，已侵害系爭\n    專利權，為此爰依專利法第84條第1項後段請求排除被告等\n    之侵害，並依專利法第85條第1項第2款、公司法第23條、民\n    法第28條規定請求被告立匠鋼品工業有限公司（下稱立匠公\n    司）及其法定代理人即被告乙○○賠償所受損害。並聲明：\n    1.被告等不得實施「內授營建管字第0950807834號內政部建\n      築新技術、新工法、新設備及新材料認可通知書」、「內\n      授營建管字第0960807640號內政部建築新技術、新工法、\n      新設備及新材料認可通知書」、「內授營建管字第097080\n      6023號內政部建築新技術、新工法、新設備及新材料認可\n      通知書」及「內授營建管字第0970807377號內政部建築新\n      技術、新工法、新設備及新材料認可通知書」之內容；2.\n      被告等應賠償原告155 萬元整及自起訴狀送達被告之日起\n      按百分之5 計算之利息。\n  (二)對被告抗辯之陳述：\n  1.被證1 無法證明系爭專利之申請專利範圍欠缺新穎性與進步\n    性：\n    (1)此可由被證1之「申請案件資料」之「主要材料或構件」\n      係由「第一層烤漆鋼板、第二層矽酸鈣板、第三層岩棉、\n      第四層矽酸鈣板、雙併C型立柱與C型槽鐵小樑」組成可\n      知，且由被證1第14頁之「橫向剖透示意圖」亦可知悉，\n      於雙併C型立柱與C型槽鐵小樑之間設「第四層矽酸鈣板」\n      ，被證1亦僅設「第一層烤漆鋼板」，並無如系爭專利設\n      「上、下層鋼板」，且被證1之「雙併C型立柱與C型槽鐵\n      小樑為垂直設置」與系爭專利之上下層鋼架為同向設置不\n      同，且被證1並無法經由「雙併C型立柱拉引C型槽鐵小樑\n      ，以達到防止C型槽鐵小樑塌陷之防火效果」，而與系爭\n      專利藉由「上層鋼架拉引下層鋼架，以達到防止下層鋼架\n      塌陷之效果」結構特徵不同，自無從由被證1證明系爭專\n      利之申請專利範圍第1項及第8項欠缺新穎性或進步性。\n    (2)被證1之雙併C型立柱，雖然與C型鋼互相以自攻螺絲栓設\n      ，但由該雙併C型立柱係設於矽酸鈣板上方觀察，並因為\n      被證1之C型鋼需再藉由被覆防火被覆材（俗稱防火漆），\n      顯見，被證1之雙併C型立柱無法提供C型鋼產生任何拉引\n      力量，無法藉由雙併C型立柱以防止C型鋼受到火場高溫而\n      變形迅速塌陷之危險，而與系爭專利申請專利範圍第1項\n      之上層鋼架或下層鋼架結構特徵完全不同。被證1之「自\n      攻螺絲（c、d），係自雙併C型立柱（B）穿過矽酸鈣板（\n      E）與C型鋼栓設。」，系爭專利申請專利範圍第1項之連\n      結元件，由說明書第3圖至第9圖有各種結構之變化，但是\n      被證1僅係利用自攻螺絲將雙併C型立柱與C型鋼栓設，被\n      證1之自攻螺絲並無法提供拉引作用，以延長C型鋼受到火\n      場高溫而急速塌陷之問題，系爭專利申請專利範圍第1項\n      之連結元件3與被證1之自攻螺絲之特徵完全不同。被證1\n      之烤漆鋼板（A）設於最上層，於該烤漆鋼板與雙併C型立\n      柱（B）之間再設置有矽酸鈣板（F），系爭專利申請專利\n      範圍第1項之上層鋼板4下方就是上層鋼架，亦即上層鋼板\n      4係直接設置於上層鋼架上方，並與防火層形成防火區隔\n      區，惟依據設置之位置，被證1之烤漆鋼板並不等於系爭\n      專利申請專利範圍第1項之上層鋼板。系爭專利申請專利\n      範圍第1 項之下層鋼板5 為浪形、或琉璃瓦形、或平板形\n      狀、或隱藏狀，且係設於下層鋼架2 上方，並由上層鋼架\n      以為支撐與施工，形成防火層6 之舖設空間，被證1 並無\n      如系爭專利所設之下層鋼板，僅有矽酸鈣板（E ）與（F\n      ），但矽酸鈣板並不等於系爭專利之下層鋼板5 ，充其量\n      ，被證1 之矽酸鈣板（E ）、（F ）與岩棉（D ）僅等於\n      系爭專利申請專利範圍第1 項之防火層6 。系爭專利申請\n      專利範圍第1 項之防火層6 係設於上層鋼板4 與下層鋼板\n      5 之間，且形成防火區隔區7 ，防火層6 可以單一防火材\n      料或以複合材料為之，複合材料如防火材加防水毯或再加\n      入防火岩棉或矽酸鈣板或陶瓷棉等，被證1 之防火層，係\n      由矽酸鈣板（E ）、（F ）與岩棉（D ）組成，設置於C\n      型鋼上方與雙併C 型立柱上方，二者防火層之設置結構不\n      相同，且被證1 僅是將防火層設置多層狀態，但該矽酸鈣\n      板遇到高溫即會脆化，根本無法經由拉引雙併C 型立柱拉\n      引C 型鋼。被證1 僅是利用傳統隔間牆之結構，作為屋頂\n      板之結構，需藉由被覆防火漆，才能達成所要達成之目的\n      ，無法真正提昇建築物之防火效果。被證1 施工時，需被\n      覆防火層，再逐層舖設複數之厚重之矽酸鈣板，結果並無\n      法較系爭專利之更具防火效果。綜上，被證1 欠缺系爭專\n      利申請專利範圍第1 項之下層鋼板，且由被證1 之結構所\n      揭示之「矽酸鈣板（E ）、（F ）與岩棉（D ）」之設置\n      僅與請求項1 之防火層6 相當，但系爭專利申請專利範圍\n      第1 項又較被證1 之結構簡易，但防火時效仍然優於被證\n      1 ，因為由被證1 之自攻螺絲並無法提供雙併C 型立柱拉\n      引C 型鋼之力量，無法藉由雙併C 型立柱拉引C 型鋼，產\n      生防止C 型鋼快速塌陷之問題。因此，由被證1 並無法證\n      明請求項1 欠缺進步性。\n    (3)系爭專利設防火區隔區7係由防火層6與上層鋼板4所形成\n      者，具有讓熱氣被順利排出，而延長上層鋼板4與上層鋼\n      架1之受到火場高溫而變形之時間，具有提高防火時效之\n      優點，但被證1於雙併C型立柱與烤漆鋼板之間再設置有矽\n      酸鈣板（E），如此，將形成另一隔熱層，無法適時將火\n      場中之熱氣排出，反而會將高溫熱氣封閉於屋內，如果發\n      生火警，勢必加快C型鋼之變形塌陷之時間，顯見系爭專\n      利之防火效果絕對較被證1更為增進與精進，兩者結構不\n      同。\n  2.被告等應負推定過失責任，系爭專利係於94年10月1日公告\n    於經濟部智慧財產局（下稱智慧局）之專利公報中，專利公\n    報並包含「紙本公報、光碟公告與網站內容」等，而智慧局\n    除了位於台北市之公務機關所在地之外，更於高雄、台南、\n    台中與新竹均設有辦事處，接受並提供本國人民隨時查閱並\n    利用各項智慧財產資訊之方法，且系爭專利申請之後，原告\n    亦取得「內授營建管字第0950800048號內政部建築新技術、\n    新工法、新設備及新材料認可通知書」，且於94年1 月31日\n    公告於財團法人中華建築中心之網站，而財團法人中華建築\n    中心之網站乃被告最常利用並作為被告施工或監工完成之建\n    築物開立防火證明進行登錄之網站，且由財團法人中華建築\n    中心之網站中，被告更得以輕易取得系爭專利之相關防火認\n    證資訊，而被告對於他人取得之具備進步性之防火認證直接\n    加以援用，實應負推定過失責任。\n二、被告則抗辯以：\n  (一)依系爭專利所附圖說可知，所謂上層鋼架及下層鋼架可以為\n    C形鋼、H形鋼抑或是其他形狀鋼架為之，經比較被證1與系\n    爭專利申請專利範圍第1項，可知被證1之雙併C型鋼編號B（\n    即等同系爭專利之上層鋼架）、C型鋼編號C（即等同系爭專\n    利之下層鋼架）、上層矽酸鈣板編號F（即等同系爭專利之\n    上層鋼板）、下層矽酸鈣板編號E（即等同系爭專利之下層\n    鋼板）、雙併C型鋼B與C間藉自攻螺絲編號b、c（即等同系\n    爭專利連結元件）相連結、雙併C型鋼B與C間設岩棉編號D（\n    即等同系爭專利之防火層）等之技術設計功能皆相同，並確\n    實早於系爭專利申請前已揭露系爭專利申請專利範圍第1項\n    所述必要元件與元件間之相對關係。至被證1上層矽酸鈣板\n    （編號F）上方設置烤漆鋼板（編號A），此雖與系爭專利上\n    層鋼架上方及上層鋼架與下層鋼架間分別固定上層鋼板及下\n    層鋼板相異。惟被證1早已揭露於雙併C型鋼（編號B）上方\n    及雙併C型鋼（編號B）與C型鋼（編號C）間分別設有上層矽\n    酸鈣板（編號F）、下層矽酸鈣板（編號E），將此矽酸鈣板\n    F、E置換為鋼板，為所屬技術領域中具有通常知識者所能輕\n    易完成。此觀系爭專利申請前，第三人玉逢工程有限公司所\n    申請內政部建築新技術、新工法、新設備及新材料認可通知\n    書中之系統概述記載「兩面覆蓋單層烤漆鋼板，其中填充岩\n    棉複合板之防火屋頂板…」可知，故於系爭專利申請前，即\n    有所屬技術領域中具有通常知識者，輕易完成換置矽酸鈣板\n    為鋼板之技術，原告卻執此主張為其專利申請範圍，顯不具\n    進步性。\n  (二)系爭專利申請專利範圍第8項界定一種「防火金屬鋼板結構\n    (一)」，其包含：「連結元件，連結元件係設於上層鋼架與下\n    層鋼架之間，…之結構剛性」，然系爭專利申請專利範圍第\n    8 項並未提及所謂連結元件係指何種材料，是否凡各式螺栓\n    均屬其所指之連結元件範圍，亦不可知，被證1所揭露之自\n    攻螺絲b、c與系爭專利所謂之連結元件或螺栓之功用均為螺\n    鎖連結二鋼材，是故被證1明顯給予系爭專利申請專利範圍\n    第8項產生教示作用，系爭專利所謂連結元件及螺栓之設計\n    僅是就被證1技術特徵之簡單置換，顯不具進步性。\n  (三)被告並無侵害原告專利之情事：\n  1.系爭專利之申請專利範圍第1、8項僅為施工法與完成品，並\n    不含其中之材料與零件，故被告依照上開認可通知書販賣主\n    要材料與構件，並無侵害系爭專利之虞。\n  2.縱原告之專利為有效，然依原證3之標準施工圖之短項剖面\n    圖均可得知，該項通知書之施工方法包含以12#X3.5\"六角自\n    攻螺絲，間距380mm貫穿整個防火屋頂板結構以及12#1.5\"六\n    角自攻螺絲，間距380mm以上下拴緊鋼板等二種方式固定，\n    顯與系爭專利僅用螺栓上下拴緊之施工方式迥異，原證4（\n    亦採用原證3固定法）、5、6部分，自攻螺絲均採用隱藏式\n    設計。易言之，即Z型連結元件先以自攻螺絲固定於屋頂板\n    固定座後，再將上層鋼板從外面包覆屋頂板固定座，並夾緊\n    固定，使外觀觀之無法察覺六角自攻螺絲固定之處，以減少\n    六角自攻螺絲因風雨侵蝕而加速氧化，是故原證4、5、6部\n    分之自攻螺絲固定方式均隱藏於屋面板固定座內，與系爭專\n    利均將螺栓開放式拴緊之設計相異，此由原證4、5、6之長\n    向、短向剖面圖說可證，且原證4、5、6之施工步驟7.8.亦\n    說明「將上層烤漆鋼板固定於固定座上方，安裝第二片烤漆\n    鋼板時，將第二片烤漆鋼板之左側扣合於第一片鋼板右側之\n    上方，再以六角自攻螺絲鎖固」、「將屋面板固定座以自攻\n    螺絲固定於Z 型鍍鋅隔件之上方，將上層烤漆板固定於屋面\n    板固定座上，安裝第二片烤漆鋼板時，於第二片烤漆鋼板之\n    左側扣合第一片鋼板右側之上方，以鉸合器於鋼板接合處將\n    兩鋼板鉸合。」，職是被告原證3 、4 、5 、6 通知書所施\n    工之工法與材料均與系爭專利迥異。又被告4 項認可書之結\n    構主要與系爭專利之不同點在於，被告此四項認可書施做方\n    式僅有在最下層架設一C 型鋼並以自攻螺絲固定下層鋼板於\n    C 型鋼並鋪設岩棉後，即鋪設鍍鋅隔件或Z 型隔件，且從該\n    四項認可通知書之構成材料規格上可知，鍍鋅隔件僅為\n    0.47mm 、Z型隔件僅為1.5mm ，且鍍鋅隔件或Z 型隔件質地\n    偏軟，並無上下層鋼架之剛性，故並無法與鋼架有相同之功\n    用，以自攻螺絲由上而下貫穿後，並未有如系爭專利以兩個\n    C 型鋼之組合以連結元件連結而產生上下拉引之力量。\n  3.被告係信賴內政部所頒發之認可通知書而為使用，並非故意\n    侵害原告之專利權。再者，原證2之存證信函係於原告專利\n    申請4 年多後向多數業者發出，然其專利範圍、受函者所販\n    賣之內容何種型號有侵害系爭專利之虞等事項均無明述。原\n    告如此通知，實難謂被告明知其專利範圍而仍販售侵害系爭\n    專利之成品，而請求排除侵害。況被告就原證4 之材料認可\n    通知書所示材料與構件，早已於原告以存證信函通知2 年前\n    停止施作及販賣，原證3 之內容於原證2 存證信函通知後已\n    無施作，僅零星販賣零件，故無侵害原告專利權之虞。\n  (四)並聲明：1.原告之訴駁回；2.訴訟費用由原告負擔。\n三、本件兩造不爭執之事實（見本院卷第161、162頁）：\n  (一)原告於93年7 月29日向經濟部智慧財產局申請「防火金屬鋼\n    板結構(一)」發明專利，經該局審查核准專利後，發給第I240\n    777號專利證書，專利權期間自94年10月1日起至113年7月28\n    日止。\n  (二)被告確有向內政部營建署申請取得下列認可書：\n  1.95年12月22日內授營建管字第0950807834號建築新技術、新\n    工法、新設備及新材料認可通知書。\n  2.96年11月29日內授營建管字第0960807640號建築新技術、新\n    工法、新設備及新材料認可通知書。\n  3.97年8月4日內授營建管字第0970806023號建築新技術、新工\n    法、新設備及新材料認可通知書。\n  4.97年9月10日內授營建管字第0970807377號建築新技術、新\n    工法、新設備及新材料認可通知書。\n四、本件經本院與兩造整理並協定簡化之爭點如下（見本院卷第\n    162頁）：\n  (一)被證1是否足以證明系爭專利申請專利範圍第1、8項不具進\n    步性（被證2之主張業經被告於99年3月24日捨棄，見本院卷\n    第246頁）？\n  (二)上開認可書所載之鋼板施工結構是否落入系爭專利申請專利\n    範圍第1、8項？原告得否依專利法第84條第1項請求排除、\n    防止侵害或損害賠償？\n五、本院之判斷如下：\n  (一)被證1足以證明系爭專利申請專利範圍第1、8項不具進步性\n    ：\n  1.按解釋專利權範圍應以申請專利範圍之記載為準，不得將發\n    明說明或圖式有揭露但未載於申請專利範圍之技術特徵讀入\n    ，而縮小專利權範圍，是以專利是否具有新穎性或進步性，\n    應以申請專利範圍之記載為判斷標的，倘某項技術特徵僅揭\n    露於發明說明或圖式卻未載於申請專利範圍，則專利權人不\n    得藉由該技術特徵減縮其申請專利範圍，俾使其專利得以符\n    合新穎性或進步性之要件，至於用以證明該專利不具新穎性\n    或進步性之先前技術倘係專利文獻，則以該專利文獻所揭露\n    之全部內容為先前技術。此外，發明說明應記載實施方式，\n    俾以符合明確且充份揭露達成發明目的所採用解決問題之技\n    術手段，而使具有通常知識者在無須過度實驗之情況下，即\n    能瞭解申請專利之發明內容，並可據以實施，是以解釋專利\n    權範圍時應涵括但不限於說明書所載之實施方式或實施例。\n  2.查系爭專利申請專利範圍共8項，其中第1、8項為獨立項，\n    其餘第2項至第7項為附屬項，第1項之內容為：「一種防火\n    金屬鋼板結構(一)，包含：鋼架，鋼架設上層鋼架及下層鋼架\n    ，於上層鋼架與下層鋼架之間並設有連結元件，利用連結元\n    件以將上、下層鋼架連結，以使上層鋼架對下層鋼架產生拉\n    引力量；鋼板，鋼板設上層鋼板及下層鋼板，分別固定於上\n    層鋼架上方及上層鋼架與下層鋼架之間；防火層，該防火層\n    設於上層鋼板與下層鋼板之間，以組成本發明之防火金屬鋼\n    板。」，第8項之內容為：「一種防火金屬鋼板結構(一)，包\n    含：連結元件，連結元件係設於上層鋼架與下層鋼架之間，\n    以使下層鋼架藉由上層鋼架產生拉引力量，強化整體防火金\n    屬鋼板之結構剛性。」，雖系爭專利說明書之發明內容記載\n    ：「本發明之特點有：1.本發明之防火金屬鋼板結構(一)，利\n    用連結元件連結上、下層鋼架，以使上層鋼架對下層鋼架產\n    生拉引力量，確保下層鋼架可承受火警高溫，不易變形，避\n    免建築物塌陷造成危害。2.本發明之防火金屬鋼板結構(一)設\n    鋼板，鋼板設上層鋼板及下層鋼板，分別固定於上層鋼架上\n    方及上層鋼架與下層鋼架之間，再於上層鋼板與下層鋼板之\n    間設防火層，且形成防火區隔區，利用防火層之防火功能，\n    及於前述防火區隔區形成部份之空氣空間，更增加防火效果\n    ，以符合國家標準之防火時效。」，惟系爭專利申請專利範\n    圍第1項並未揭露防火層與上層鋼板間設有「防火區隔區」\n    ，而防火層之舖設於系爭專利申請專利範圍第1項中僅界定\n    「設於上層鋼板與下層鋼板之間」，是以「防火區隔區」即\n    無從作為判斷系爭專利申請專利範圍第1項是否具有進步性\n    之技術特徵。\n  3.被證1為內政部營建署於92年8月7日對弘耀實業有限公司生\n    產之「弘耀F-18防火屋頂」所核發之認可通知書，其產品種\n    類為「建築物防火屋頂版」，被證1之防火屋頂板結構，係\n    將C型槽鋼噴覆防火被覆材作為小梁，固定於H型鋼大梁上，\n    在C 型鋼上利用自攻螺絲及雙併C 型鋼固定，由上而下順序\n    為：第一層烤漆鋼板、第二層矽酸鈣板、雙併C 型鋼、第三\n    層填充岩棉、第四層矽酸鈣板所組成的合板屋頂結構。依系\n    爭專利說明書「發明說明」記載：「鋼架設上層鋼架1 及下\n    層鋼架2 ，鋼架由C 形鋼；或H 形鋼；或其他形狀之鋼架為\n    之皆可以，本發明以C 形鋼以解說明本發明之特性。再於上\n    層鋼架1 與下層鋼架2 之間並設有連結元件3 ，該連結元件\n    3 可以為複數，端視鋼架之長度而定。」、「連結元件3 ，\n    可以由任意配件為之」、「防火層6 可以單一防火料或以複\n    合材料為之，複合材料如防火材加防水毯或再加入防火岩棉\n    」（見說明書第9 頁），是以系爭專利之上下層鋼架即包括\n    C 形鋼，防火層即包括防火岩棉，至於連結元件只須能達成\n    連結鋼架之功效即包含之，依被證1 之記載其防火屋頂板之\n    結構為「以雙併C 型鋼（間隔915mm ），加上自攻螺絲固定\n    由外層烤漆鋼板（0.5mm ）貼上矽酸鈣板（6mm ），中間填\n    實密度80公斤/ 立方米之岩棉（50mm），再加上矽酸鈣板（\n    10mm）之屋頂板結構，固定在C 型鋼槽上（間隔915mm ）」\n    （詳如附圖，見本院卷第60頁），就被證1 與系爭專利之申\n    請專利範圍第1 項所界定之技術特徵比對，系爭專利申請專\n    利範圍第1 項所記載之上層鋼板、上層鋼架、防火層、連結\n    元件、下層鋼架等構件，已分別對應揭露於被證1 之烤漆鋼\n    板、雙併C 型鋼、岩棉、六角自攻螺絲、C 型鋼，且兩案之\n    構件組構關係係屬相同，其不同處在於被證1 與下層鋼架連\n    結者為矽酸鈣板，而系爭專利則為下層鋼板，是以二者均具\n    有下層板構件，僅該構件之材質不同。\n  4.依系爭專利說明書第8頁記載：「發明目的乃於上層鋼架與\n    下層鋼架之間設有連結元件，利用連結元件以將上、下層鋼\n    架連結，以使上層鋼架對下層鋼架產生拉引力量，下層鋼架\n    可承受火場高溫，不易變形，建築物不易塌陷，造成危害，\n    以符合國家標準之防火時效。」，因此與下層鋼架連結者是\n    否使用鋼板並非本案之發明目的或特點，且被證1之下層使\n    用矽酸鈣板係屬耐燃之防火建材，系爭專利與被證1雖於下\n    層板部分有鋼板與矽酸鈣板之不同，然由於鋼板、矽酸鈣板\n    皆屬系爭專利申請時防火屋頂習用之建材，此由被證5內政\n    部營建署於93年2月4日以內授營建管字第0930082097號建築\n    新技術、新工法、新設備及新材料認可通知書可資佐證（見\n    本院卷第264頁），而原告又未能證明將矽酸鈣板置換為先\n    前技術之鋼板，其材質之不同有何無法預期之功效，則原告\n    以具有相同功能的已知材料置換已知物品中相對應之材料，\n    應認定該發明能輕易完成，不具進步性，故被證1足以證明\n    系爭專利申請專利範圍第1項不具進步性。\n  5.原告雖主張系爭專利可藉由連結元件以使上層鋼架對下層鋼\n    架產生拉引力量，下層鋼架可承受火場高溫，不易變形，而\n    被證1之C型鋼必須再被覆防火被覆材，顯見被證1之C型鋼無\n    法藉由雙併C型立柱產生任何拉引力量，且系爭專利之上下\n    層鋼架為同向設置等語。惟查，系爭專利申請專利範圍第1\n    項僅記載其連結元件可使上層鋼架對下層鋼架產生拉引力量\n    ，惟其僅為功能的敘述，而於系爭專利申請專利範圍第1項\n    中並未對連結元件或下層鋼架之構造有所限定，系爭專利說\n    明書「發明說明」僅記載：「鋼架設上層鋼架1及下層鋼架2\n    ，鋼架由C形鋼；或H型鋼；或其他形狀之鋼架為之皆可以，\n    本發明以C形鋼以解說明本發明之特性。再於上層鋼架1與下\n    層鋼架2之間並設有連結元件3，該連結元件3可以為複數，\n    端視鋼架之長度而定。」、「連結元件3，可以由任意配件\n    為之」，業如前述，系爭專利申請專利範圍第1項亦未界定\n    其鋼架及連結元件是否為防火材料或被覆防火漆，則原告主\n    張被證1之C型鋼必須再被覆防火被覆材，而無法藉由雙併C\n    型立柱產生任何拉引力量，即非可採。\n  6.另就被證1與系爭專利申請專利範圍第8項所界定之技術特徵\n    比對，系爭專利所記載設於上層鋼架與下層鋼架間之連結元\n    件已為被證1之六角自攻螺絲所揭露，由於被證1之六角自攻\n    螺絲亦設於上層鋼架與下層鋼架間，而其是否可使下層鋼架\n    藉由上層鋼架產生拉引力量以強化整體防火金屬鋼板之結構\n    剛性，已如前所述，故被證1亦可證明系爭專利申請專利範\n    圍第8項不具進步性。\n  (二)原證3、4、5、6認可書所載之鋼板施工結構落入系爭專利申\n    請專利範圍第1項：\n  1.原證3認可書之侵害分析:\n    (1)經解析系爭專利申請專利範圍第1項，其技術特徵可拆解\n      為5個要件，分別為編號1要件「一種防火金屬鋼板結構(一)\n      ，包含：」，編號2要件「鋼架，鋼架設上層鋼架及下層\n      鋼架，」，編號3要件「於上層鋼架與下層鋼架之間並設\n      有連結元件，利用連結元件以將上、下層鋼架連結，以使\n      上層鋼架對下層鋼架產生拉引力量；」，編號4要件「鋼\n      板，鋼板設上層鋼板及下層鋼板，分別固定於上層鋼架上\n      方及上層鋼架與下層鋼架之間；」，編號5要件「防火層\n      ，該防火層設於上層鋼板與下層鋼板之間，以組成本發明\n      之防火金屬鋼板。」。\n    (2)原證3之認可書為一種建築物防火屋頂板，其設有上、下\n      層鋼板，板厚度0.42mm，上、下層鋼板間以C型鋼固定，\n      利用12#×3.5\"六角頭自攻螺絲連結上（C型鋼）、下層鋼\n      架，上下層鋼板間填充陶瓷棉。原證3之認可書對應於系\n      爭專利申請專利範圍第1項各技術特徵可解析為5個要件，\n      原證3為一種防火金屬鋼板結構，編號1要件已文義讀取，\n      原證3設有上、下層C型鋼架，編號2要件已文義讀取，原\n      證3於上下層鋼架間設有六角頭自攻螺絲之連結元件，利\n      用連結元件以將上、下層鋼架連結，以使上層鋼架對下層\n      鋼架產生拉引力量，編號3要件已文義讀取，原證3設有厚\n      度0.42 mm之上、下層烤漆鋼板，編號4要件已文義讀取，\n      原證3亦於上下層鋼板間填充有陶瓷棉之防火層，編號5要\n      件已文義讀取，故原證3認可書之技術內容分別為系爭專\n      利申請專利範圍第1項編號1至5要件之文義所讀取，是以\n      原證3認可書落入系爭專利申請專利範圍第1項之文義範圍\n      。\n    (3)至於被告辯稱原證3之認可書施工法包含以12#×3.5\"六角\n      頭自攻螺絲，間距380mm貫穿整個防火屋頂板結構以及12#\n      1.5\"六角自攻螺絲，間距380mm以上下拴緊鋼板等二種方\n      式固定，顯與系爭專利僅用螺栓上下拴緊之施工方式迥異\n      等語。惟查，系爭專利申請專利範圍第1項係界定：「於\n      上層鋼架與下層鋼架之間並設有連結元件，利用連結元件\n      以將上、下層鋼架連結，以使上層鋼架對下層鋼架產生拉\n      引力量」，系爭專利說明書之發明說明雖係以螺栓作為連\n      結元件之實施例，惟解釋申請專利範圍時僅能就申請專利\n      範圍所載之技術特徵予以解釋，尚不得將說明書所揭露之\n      實施例讀入申請專利範圍，而限縮申請專利範圍，被告所\n      稱系爭專利僅用螺栓上下拴緊之施工方法及連結元件之結\n      構並未載於系爭專利申請專利範圍第1項，而原證3認可書\n      之施工法亦係於上層鋼架與下層鋼架之間設有連結元件（\n      六角頭自攻螺絲）將上、下層鋼架連結，以該連結使上層\n      鋼架對下層鋼架產生拉引力量，原證3之該項技術內容自\n      應為系爭專利申請專利範圍第1項編號3要件之文義所讀取\n      ，被告所辯尚非可採。\n  2.原證4認可書之侵害分析：\n    (1)原證4之認可書為一種建築物複層式防火屋頂板，其設有\n      厚度0.52mm上層鋼板、厚度0.42mm下層鋼板，上、下層鋼\n      板間以熱浸鍍鋅鋼材之固定座固定，利用12#×3.5\"六角\n      頭自攻螺絲連結上、下層鋼架（C型鋼125×50×20×2.3m\n      m），上、下層鋼板間填充陶瓷棉。\n    (2)原證4之認可書對應於系爭專利申請專利範圍第1項各技術\n      特徵可解析為5個要件，原證4為一種防火金屬鋼板結構，\n      編號1要件已文義讀取，原證4設有上層熱浸鍍鋅鋼材鋼架\n      、下層C型鋼架，編號2要件已文義讀取，原證4於上、下\n      層鋼架間設有六角頭自攻螺絲之連結元件，利用連結元件\n      以將上、下層鋼架連結，以使上層鋼架對下層鋼架產生拉\n      引力量，編號3要件已文義讀取，原證4設有厚度0.52mm上\n      層鋼板、厚度0.42mm下層鋼板，編號4要件已文義讀取，\n      原證4亦於上下層鋼板間填充有陶瓷棉之防火層，編號5要\n      件已文義讀取，故原證4認可書之技術內容分別為系爭專\n      利申請專利範圍第1項編號1至5要件之文義所讀取，是以\n      原證4認可書落入系爭專利申請專利範圍第1項之文義範圍\n      。\n  3.原證5認可書之侵害分析：\n    (1)原證5之認可書為一種建築物複層式防火金屬鋼板屋頂，\n      其設有厚度0.476mm上層鋼板、厚度0.42mm下層鋼板，上\n      、下層鋼板間固定有鍍鋅鋼材之鍍鋅隔件50×50×50 ×1\n      .5 ×1.5 （t ）mm，間距1000mm，利用六角頭自攻螺絲\n      連結上、下層鋼架（C 型鋼125 ×50×20×2.3 （t ）mm\n      ），上、下層鋼板間填充岩棉及陶瓷棉。\n    (2)原證5之認可書對應於系爭專利申請專利範圍第1項各技術\n      特徵可解析為5個要件，原證5為一種防火金屬鋼板結構，\n      編號1要件已文義讀取，原證5設有上層鍍鋅鋼材（鍍鋅隔\n      件）鋼架、下層C型鋼架，編號2要件已文義讀取，原證5\n      於上、下層鋼架間設有六角頭自攻螺絲之連結元件，利用\n      連結元件以將上、下層鋼架連結，以使上層鋼架對下層鋼\n      架產生拉引力量，編號3要件已文義讀取，原證5設有厚度\n      0.476mm上層鋼板、厚度0.42mm下層鋼板，編號4要件已文\n      義讀取，原證5亦於上下層鋼板間填充有岩棉及陶瓷棉之\n      防火層，編號5要件已文義讀取，故原證5認可書之技術內\n      容分別為系爭專利申請專利範圍第1項編號1至5要件之文\n      義所讀取，是以原證5認可書落入系爭專利申請專利範圍\n      第1項之文義範圍。\n  4.原證6認可書之侵害分析：\n    (1)原證6之認可書為一種建築物複層式防火金屬鋼板屋頂，\n      其設有厚度0.476mm上層烤漆鋼板、厚度0.42mm下層烤漆\n      鋼板，上、下層鋼板間固定有鍍鋅鋼材之Z型鍍鋅隔件（5\n      0×50×50×1.5（t）mm），利用六角頭自攻螺絲連結上\n      、下層鋼架（C型鋼125×50×20×2.3（t）mm），上、下\n      層鋼板間填充岩棉及陶瓷棉。\n    (2)原證6之認可書對應於系爭專利申請專利範圍第1項各技術\n      特徵可解析為5個要件，原證6為一種防火金屬鋼板結構，\n      編號1要件已文義讀取，原證6設有上層鍍鋅鋼材（Z型鍍\n      鋅隔件）鋼架、下層C型鋼架，編號2要件已文義讀取，原\n      證6於上、下層鋼架間設有六角頭自攻螺絲之連結元件，\n      利用連結元件以將上、下層鋼架連結，以使上層鋼架對下\n      層鋼架產生拉引力量，編號3要件已文義讀取，原證6設有\n      厚度0.476mm上層鋼板、厚度0.42mm下層鋼板，編號4要件\n      已文義讀取，原證6亦於上下層鋼板間填充有岩棉及陶瓷\n      棉之防火層，編號5要件已文義讀取，故原證6認可書之編\n      號1至5要件皆為系爭專利申請專利範圍第1項編號1至5要\n      件文義所讀取，是以原證6認可書落入系爭專利申請專利\n      範圍第1項之文義範圍。\n  5.至於被告辯稱原證4、5、6之認可書施工法之自攻螺絲固定\n    方式均隱藏於屋面板固定座內，與系爭專利均將螺栓開放式\n    拴緊之設計相異等語，惟查，系爭專利申請專利範圍第1項\n    並未限定連結元件螺栓為開放式或隱藏式拴緊，亦不得將說\n    明書所揭露之實施例讀入申請專利範圍，而限縮系爭專利申\n    請專利範圍第1項，則原證4、5、6認可書之施工法係於上層\n    鋼架與下層鋼架之間設有連結元件（六角頭自攻螺絲）將上\n    、下層鋼架連結，以該連結使上層鋼架對下層鋼架產生拉引\n    力量，原證4、5、6之該項技術內容亦為系爭專利申請專利\n    範圍第1項編號3要件文義所讀取。\n  6.另被告辯稱原證3、4、5、6認可書之構成材料規格上可知，\n    鍍鋅隔件僅為0.47mm、Z型隔件僅為1.5mm，且鍍鋅隔件或Z\n    型隔件質地偏軟，並無上下層鋼架之剛性，故並無法與鋼架\n    有相同之功用，以自攻螺絲由上而下貫穿後，並未有如系爭\n    專利以兩個C型鋼之組合以連結元件連結而產生上下拉引之\n    力量等語。經查，縱原證3、4、5、6認可書鍍鋅隔件僅為0.\n    47mm、Z型隔件僅為1.5mm，然其上下層烤漆鋼板厚度亦僅為\n    0.476mm或0.42mm，相對該上下層鋼板厚度，尚難稱0.47mm\n    之鍍鋅隔件、0.42mm之Z型隔件不具有結構之剛性支撐作用\n    。況且系爭專利申請專利範圍第1項中亦未界定相關構件之\n    形狀及厚度，原證3、4、5、6既揭示於上、下層鋼架間設有\n    連結元件，實無法僅由其所稱之厚度即可推知其未能產生拉\n    引力量，被告所辯均不足採。\n  (三)原證3、4、5、6認可書所載之鋼板施工結構落入系爭專利申請\n    專利範圍第8項：\n  1.經解析系爭專利申請專利範圍第8項，其技術特徵可拆解為2\n    個要件，分別為編號1要件「一種防火金屬鋼板結構(一)，包\n    含：」，編號2要件「連結元件，連結元件係設於上層鋼架\n    與下層鋼架之間，以使下層鋼架藉由上層鋼架產生拉引力量\n    ，強化整體防火金屬鋼板之結構剛性。」。\n  2.原證3之認可書對應於系爭專利申請專利範圍第8項各技術特\n    徵可解析為2個要件，原證3為一種防火金屬鋼板結構，編號\n    1要件已文義讀取，原證3於上下層鋼架間設有六角頭自攻螺\n    絲之連結元件，利用連結元件以將上、下層鋼架連結，以使\n    上層鋼架對下層鋼架產生拉引力量，編號2要件已文義讀取\n    ，故原證3認可書之編號1、2要件皆為系爭專利申請專利範\n    圍第8 項編號1 、2 要件文義所讀取，是以原證3 認可書落\n    入系爭專利申請專利範圍第8 項之文義範圍。\n  3.原證4之認可書對應於系爭專利申請專利範圍第8項各技術特\n    徵可解析為2個要件，原證4為一種防火金屬鋼板結構，編號\n    1要件已文義讀取，原證4於上下層鋼架間設有六角頭自攻螺\n    絲之連結元件，利用連結元件以將上、下層鋼架連結，以使\n    上層鋼架對下層鋼架產生拉引力量，編號2要件已文義讀取\n    ，故原證4認可書之編號1、2要件皆為系爭專利申請專利範\n    圍第8 項編號1 、2 要件文義所讀取，是以原證3 認可書落\n    入系爭專利申請專利範圍第8 項之文義範圍。\n  4.原證5之認可書對應於系爭專利申請專利範圍第8項各技術特\n    徵可解析為2個要件，原證5為一種防火金屬鋼板結構，編號\n    1要件已文義讀取，原證5於上下層鋼架間設有六角頭自攻螺\n    絲之連結元件，利用連結元件以將上、下層鋼架連結，以使\n    上層鋼架對下層鋼架產生拉引力量，編號2要件已文義讀取\n    ，故原證5認可書之編號1、2要件皆為系爭專利申請專利範\n    圍第8 項編號1 、2 要件文義所讀取，是以原證5 認可書落\n    入系爭專利申請專利範圍第8 項之文義範圍。\n  5.原證6之認可書對應於系爭專利申請專利範圍第8項各技術特\n    徵可解析為2個要件，原證6為一種防火金屬鋼板結構，編號\n    1要件已文義讀取，原證6於上下層鋼架間設有六角頭自攻螺\n    絲之連結元件，利用連結元件以將上、下層鋼架連結，以使\n    上層鋼架對下層鋼架產生拉引力量，編號2要件已文義讀取\n    ，故原證6認可書之編號1、2要件皆為系爭專利申請專利範\n    圍第8 項編號1 、2 要件文義所讀取，是以原證6 認可書落\n    入系爭專利申請專利範圍第8 項之文義範圍。\n六、綜上所述，原證3、4、5、6認可書所載之鋼板施工結構均落\n    入系爭專利申請專利範圍第1、8項之文義範圍，惟被告所提\n    出之被證1足以證明系爭專利申請專利範圍第1、8項均不具\n    進步性，而有專利法第22條第4項之撤銷原因，則依智慧財\n    產案件審理法第16條第2項規定，原告於本件民事訴訟中自\n    不得以系爭專利申請專利範圍第1、8項對於被告主張權利。\n    從而，原告依專利法第84條第1項、第85條第1項第2款、公\n    司法第23條及民法第28條規定為如訴之聲明所示之請求，均\n    無理由，應予駁回。\n七、本件事證已臻明確，兩造其餘主張陳述及所提之證據，經本\n    院斟酌後，認與判決結果不生影響，均毋庸再予論述，附此\n    敘明。\n八、訴訟費用負擔之依據：民事訴訟法第78條。"
  },
  "characters": {
    "judges": [
      "林欣蓉"
    ],
    "prosecutors": [

    ],
    "lawyers": [
      "周佳弘"
    ],
    "clerks": [
      "周其祥"
    ],
    "plaintiffs": [
      "坴賦佳金屬有限公司"
    ],
    "defendants": [
      "立匠鋼品工業有限公司",
      "兼      上"
    ],
    "prosecutor_office": [

    ],
    "creditors": [

    ],
    "debtors": [

    ],
    "judicial_associate_officer": [

    ]
  },
  "adjudged_at": "2010-05-12",
  "created_at": "2016-01-05 11:59:09",
  "updated_at": "2016-01-05 11:59:09"
}