{
  "identify": "IPC-98-行商訴-212-20100105-1",
  "court": {
    "name": "智慧財產法院",
    "code": "IPC"
  },
  "division": {
    "name": "行政",
    "code": "A"
  },
  "year": 98,
  "word": "行商訴",
  "number": "212",
  "jcheck": "1",
  "reason": "商標異議",
  "content": "智慧財產法院行政裁定\n                                   98年度行商訴字第212號\n原      告  瑞士商殼牌國際股份有限公司\n            （Shell Brands International AG）\n代  表  人  喬琪娜‧伊凡絲（Georgina Evans）\n送達代收人  蔡瑞森律師\n被      告  經濟部智慧財產局\n代  表  人  王美花（局長）住同上\n參  加  人  興國橡膠廠股份有限公司\n代  表  人  陳誠斌       \n上列原告與被告間因商標異議事件，應命參加人參加訴訟，本院\n裁定如下：\n    主  文\n興國橡膠廠股份有限公司獨立參加本件被告之訴訟。\n    理  由\n一、按行政法院認為撤銷訴訟之結果，第三人之權利或法律上利\n    益將受損害者，得依職權命其獨立參加訴訟，並得因該第三\n    人之聲請，裁定允許其參加。行政訴訟法第42條第1 項定有\n    明文。\n二、興國橡膠廠股份有限公司於民國96年6 月15日以「V POWER\n    」商標，指定使用於商標法施行細則第13條所定商品及服務\n    分類表第12類之「車輛用平面膠帶、車輛用輸送膠帶、車輛\n    用三角傳動膠帶、車輛用扁平傳動膠帶、車輛用V 形傳動膠\n    帶、車輛用圓狀傳動膠帶、車輛用輸送皮帶、車輛用傳動皮\n    帶、車輛用傳動膠帶、車輪軸部用皮帶」等商品，向被告申\n    請註冊，經該局審查，核准列為註冊第1297540 號商標（下\n    稱系爭商標）。嗣原告於97年4 月15日以該註冊商標有違商\n    標法第23條第1 項第12款、第13款及第14款之規定，對之提\n    起異議，經被告審查，以98年4 月16日中台異字第970434號\n    商標異議審定書為「主張註冊第01297540號『V POWER 』商\n    標違反商標法第23條第1 項第12款之部分，異議不成立；主\n    張違反商標法第23條第1 項第13、14款之部分，申請駁回」\n    之處分。原告不服，提起訴願，經經濟部98年2 月25日經訴\n    字第09806107400 號訴願決定駁回，原告仍不服，遂向本院\n    提起行政訴訟。本院認本件判決之結果，將影響興國橡膠廠\n    股份有限公司之權利或法律上之利益，依職權命興國橡膠廠\n    股份有限公司獨立參加本件訴訟，爰為裁定如主文。\n中    華    民    國    99    年    1     月    5     日\n                  智慧財產法院第二庭\n                              審判長法  官  陳國成\n                                    法  官  熊誦梅\n                                    法  官  曾啟謀\n以上正本係照原本作成。\n不得抗告。\n中    華    民    國    99    年    1     月    5     日\n                                    書記官  王月伶",
  "structure": {
    "main": "興國橡膠廠股份有限公司獨立參加本件被告之訴訟。",
    "reason": "一、按行政法院認為撤銷訴訟之結果，第三人之權利或法律上利\n    益將受損害者，得依職權命其獨立參加訴訟，並得因該第三\n    人之聲請，裁定允許其參加。行政訴訟法第42條第1 項定有\n    明文。\n二、興國橡膠廠股份有限公司於民國96年6 月15日以「V POWER\n    」商標，指定使用於商標法施行細則第13條所定商品及服務\n    分類表第12類之「車輛用平面膠帶、車輛用輸送膠帶、車輛\n    用三角傳動膠帶、車輛用扁平傳動膠帶、車輛用V 形傳動膠\n    帶、車輛用圓狀傳動膠帶、車輛用輸送皮帶、車輛用傳動皮\n    帶、車輛用傳動膠帶、車輪軸部用皮帶」等商品，向被告申\n    請註冊，經該局審查，核准列為註冊第1297540 號商標（下\n    稱系爭商標）。嗣原告於97年4 月15日以該註冊商標有違商\n    標法第23條第1 項第12款、第13款及第14款之規定，對之提\n    起異議，經被告審查，以98年4 月16日中台異字第970434號\n    商標異議審定書為「主張註冊第01297540號『V POWER 』商\n    標違反商標法第23條第1 項第12款之部分，異議不成立；主\n    張違反商標法第23條第1 項第13、14款之部分，申請駁回」\n    之處分。原告不服，提起訴願，經經濟部98年2 月25日經訴\n    字第09806107400 號訴願決定駁回，原告仍不服，遂向本院\n    提起行政訴訟。本院認本件判決之結果，將影響興國橡膠廠\n    股份有限公司之權利或法律上之利益，依職權命興國橡膠廠\n    股份有限公司獨立參加本件訴訟，爰為裁定如主文。"
  },
  "characters": {
    "judges": [
      "陳國成",
      "熊誦梅",
      "曾啟謀"
    ],
    "prosecutors": [

    ],
    "lawyers": [
      "蔡瑞森"
    ],
    "clerks": [

    ],
    "plaintiffs": [
      "瑞士商殼牌國際股份有限公司"
    ],
    "defendants": [
      "經濟部智慧財產局",
      "代  表  人  王美花（局長）住同上",
      "參  加  人  興國橡膠廠股份有限公司",
      "代  表  人  陳誠斌"
    ],
    "prosecutor_office": [

    ],
    "creditors": [

    ],
    "debtors": [

    ],
    "judicial_associate_officer": [

    ]
  },
  "adjudged_at": "2010-01-05",
  "created_at": "2016-01-05 15:06:28",
  "updated_at": "2016-01-05 15:06:28"
}