{
  "identify": "IPC-98-行商訴-222-20100105-1",
  "court": {
    "name": "智慧財產法院",
    "code": "IPC"
  },
  "division": {
    "name": "行政",
    "code": "A"
  },
  "year": 98,
  "word": "行商訴",
  "number": "222",
  "jcheck": "1",
  "reason": "商標異議",
  "content": "智慧財產法院行政裁定\n                                   98年度行商訴字第222號\n原      告  國際語言學習服務有限公司\n代  表  人  王志偉         \n訴訟代理人  李逸文律師\n被      告  經濟部智慧財產局\n代  表  人  王美花（局長） \n參  加  人  英國劍橋大學   \n代  表  人  賽門大衛雷巴斯 \n送達代收人  林坤賢         \n上列原告與被告間因商標異議事件，應命參加人參加訴訟，本院\n裁定如下：\n    主  文\n英國劍橋大學應獨立參加本件被告之訴訟。\n    理  由\n一、按行政法院認為撤銷訴訟之結果，第三人之權利或法律上利\n    益將受損害者，得依職權命其獨立參加訴訟，並得因該第三\n    人之聲請，裁定允許其參加。行政訴訟法第42條第1 項定有\n    明文。\n二、原告前於民國93年6 月23日以「ELTS英美語言訓練測驗中心\n    English Learning Testing Service及圖」商標，指定使用\n    於商標法施行細則第13條所定商品及服務分類表第9 類之「\n    電腦程式、電腦軟體、錄有電腦程式之磁碟片、錄有電腦程\n    式之光碟、電子書、語言學習機、錄影帶及其整理盒、唱片\n    及其整理盒、錄音帶及其整理盒、影碟及其整理盒、音碟及\n    其整理盒」商品；第16類之「書籍、指導手冊、講義、教材\n    、印刷出版品、印刷刊物」商品；第41類之「職業訓練、空\n    服人員、地勤人員培訓、語言訓練、語言測驗及檢定、電子\n    書籍出版發行、書籍出版發行、書刊雜誌之翻譯、電腦補習\n    班、技藝訓練班、補習班、語文補習班、函授課程、專門學\n    校（教育）」服務；及第42類之「電腦程式設計、電腦資料\n    處理」服務，向被告申請註冊，經該局審查，核准列為註冊\n    第1160035 號商標（下稱系爭商標）。嗣英國劍橋大學以該\n    註冊商標有違商標法第23條第1 項第12款、第13款及第14款\n    之規定，對之提起異議。案經被告審認系爭商標與據以異議\n    之註冊第1176426 號及實際使用之「IELTS 」等商標不構成\n    近似，以96年2 月15日中台異字第941095號商標異議審定書\n    為「異議不成立」之處分。英國劍橋大學不服，提起訴願，\n    經經濟部以兩造商標構成近似為由，以96年8 月7 日經訴字\n    第09606072030 號訴願決定書撤銷原處分。嗣原告提起行政\n    訴訟，經臺北高等行政法院以96年度訴字第03409 號判決，\n    維持經濟部訴願決定見解，而駁回原告之訴確定。被告旋依\n    據經濟部訴願決定意旨，核認系爭商標有商標法第23條第1\n    項第13款規定之適用，以98年4 月21日中台異字第970883號\n    商標異議審定書為系爭商標之註冊應予撤銷之處分。原告不\n    服，提起訴願，經經濟部98年8 月12日經訴字第0980611644\n    0 號訴願決定駁回，原告仍不服，遂向本院提起行政訴訟。\n    本院認本件判決之結果，將影響英國劍橋大學之權利或法律\n    上之利益，依職權命英國劍橋大學獨立參加本件訴訟，爰為\n    裁定如主文。\n中    華    民    國    99    年    1     月    5     日\n                  智慧財產法院第二庭\n                              審判長法  官  陳國成\n                                    法  官  熊誦梅\n                                    法  官  曾啟謀\n以上正本係照原本作成。\n不得抗告。\n中    華    民    國    99    年    1     月    5     日\n                                    書記官  王月伶",
  "structure": {
    "main": "英國劍橋大學應獨立參加本件被告之訴訟。",
    "reason": "一、按行政法院認為撤銷訴訟之結果，第三人之權利或法律上利\n    益將受損害者，得依職權命其獨立參加訴訟，並得因該第三\n    人之聲請，裁定允許其參加。行政訴訟法第42條第1 項定有\n    明文。\n二、原告前於民國93年6 月23日以「ELTS英美語言訓練測驗中心\n    English Learning Testing Service及圖」商標，指定使用\n    於商標法施行細則第13條所定商品及服務分類表第9 類之「\n    電腦程式、電腦軟體、錄有電腦程式之磁碟片、錄有電腦程\n    式之光碟、電子書、語言學習機、錄影帶及其整理盒、唱片\n    及其整理盒、錄音帶及其整理盒、影碟及其整理盒、音碟及\n    其整理盒」商品；第16類之「書籍、指導手冊、講義、教材\n    、印刷出版品、印刷刊物」商品；第41類之「職業訓練、空\n    服人員、地勤人員培訓、語言訓練、語言測驗及檢定、電子\n    書籍出版發行、書籍出版發行、書刊雜誌之翻譯、電腦補習\n    班、技藝訓練班、補習班、語文補習班、函授課程、專門學\n    校（教育）」服務；及第42類之「電腦程式設計、電腦資料\n    處理」服務，向被告申請註冊，經該局審查，核准列為註冊\n    第1160035 號商標（下稱系爭商標）。嗣英國劍橋大學以該\n    註冊商標有違商標法第23條第1 項第12款、第13款及第14款\n    之規定，對之提起異議。案經被告審認系爭商標與據以異議\n    之註冊第1176426 號及實際使用之「IELTS 」等商標不構成\n    近似，以96年2 月15日中台異字第941095號商標異議審定書\n    為「異議不成立」之處分。英國劍橋大學不服，提起訴願，\n    經經濟部以兩造商標構成近似為由，以96年8 月7 日經訴字\n    第09606072030 號訴願決定書撤銷原處分。嗣原告提起行政\n    訴訟，經臺北高等行政法院以96年度訴字第03409 號判決，\n    維持經濟部訴願決定見解，而駁回原告之訴確定。被告旋依\n    據經濟部訴願決定意旨，核認系爭商標有商標法第23條第1\n    項第13款規定之適用，以98年4 月21日中台異字第970883號\n    商標異議審定書為系爭商標之註冊應予撤銷之處分。原告不\n    服，提起訴願，經經濟部98年8 月12日經訴字第0980611644\n    0 號訴願決定駁回，原告仍不服，遂向本院提起行政訴訟。\n    本院認本件判決之結果，將影響英國劍橋大學之權利或法律\n    上之利益，依職權命英國劍橋大學獨立參加本件訴訟，爰為\n    裁定如主文。"
  },
  "characters": {
    "judges": [
      "陳國成",
      "熊誦梅",
      "曾啟謀"
    ],
    "prosecutors": [

    ],
    "lawyers": [
      "李逸文"
    ],
    "clerks": [

    ],
    "plaintiffs": [
      "國際語言學習服務有限公司"
    ],
    "defendants": [
      "經濟部智慧財產局",
      "代  表  人  王美花（局長）",
      "參  加  人  英國劍橋大學",
      "代  表  人  賽門大衛雷巴斯",
      "送達代收人  林坤賢"
    ],
    "prosecutor_office": [

    ],
    "creditors": [

    ],
    "debtors": [

    ],
    "judicial_associate_officer": [

    ]
  },
  "adjudged_at": "2010-01-05",
  "created_at": "2016-01-05 15:06:24",
  "updated_at": "2016-01-05 15:06:24"
}