{
  "identify": "KLD-99-聲-499-20100512-1",
  "court": {
    "name": "臺灣基隆地方法院",
    "code": "KLD"
  },
  "division": {
    "name": "刑事",
    "code": "M"
  },
  "year": 99,
  "word": "聲",
  "number": "499",
  "jcheck": "1",
  "reason": "宣告沒收",
  "content": "臺灣基隆地方法院刑事裁定               99年度聲字第499號\n聲  請  人  臺灣基隆地方法院檢察署檢察官\n被      告  甲○○\n聲請人因上列被告違反毒品危害防制條例案件，聲請單獨宣告沒\n收（99年度執聲字第342 號），本院裁定如下：\n    主  文\n扣案之第一級毒品海洛因壹包（驗餘後淨重零點捌柒公克），沒\n收銷燬之。\n    理  由\n一、聲請意旨略以：緣被告甲○○違反毒品危害防制條例乙案，\n    業經檢察官以其所為，係犯毒品危害防制條例第十條第一項\n    、第二項之罪，核屬法定本刑為死刑、無期徒刑或三年以上\n    有期徒刑以外之案件，經參酌被告坦承犯行而表悔悟之犯後\n    態度，尤以自願參加毒品減害計畫以戒除毒癮，而認以緩起\n    訴處分為適當等情詞，依刑事訴訟法第二百五十三條之一第\n    一項規定，以96年度毒偵字第3237號為緩起訴處分確定（確\n    定日期：民國97年3 月7 日），並於99年3 月6 日期間屆滿\n    ，而查無刑事訴訟法第二百五十三條之三第一項各款所列得\n    撤銷緩起訴處分之事由。茲因扣案之白色粉末1 包，係被告\n    供犯罪之所用，且為被告所有，為此，乃依刑事訴訟法第二\n    百五十九條之一規定，聲請單獨宣告沒收等語。\n二、按檢察官依刑事訴訟法第二百五十三條或第二百五十三條之\n    一為不起訴或緩起訴之處分者，對供犯罪所用、供犯罪預備\n    或因犯罪所得之物，以屬於被告者為限，得單獨宣告沒收，\n    刑事訴訟法第二百五十九條之一定有明文。又此項規定除係\n    明文擴張法院得單獨宣告沒收之範圍，而核屬「主從刑不可\n    分原則」之例外；並為刑法第四十條第二項違禁物得單獨宣\n    告沒收之特別規定，依「特別法優於普通法原則」，即應排\n    除刑法第四十條第二項規定之適用。再按毒品危害防制條例\n    第二條第二項第一款、第二款規定，海洛因、安非他命類為\n    第一級、第二級毒品，依同條例第十八條第一項前段之規定\n    ，查獲之第一、二級毒品及專供製造或施用第一、二級毒品\n    之器具，應沒收銷燬之。\n三、經查：被告違反毒品危害防制條例乙案，業經檢察官依刑事\n    訴訟法第二百五十三條之一第一項規定，以96年度毒偵字第\n    3237號為緩起訴處分確定；期間自97年3 月7 日起，並已於\n    99年3 月6 日屆滿，復查無刑事訴訟法第二百五十三條之三\n    第一項各款所列得撤銷緩起訴處分之事由等情，業據本院職\n    權核閱臺灣基隆地方法院檢察署97年度緩字第269 號緩起訴\n    執行卷宗無訛，並有上開偵查卷附緩起訴處分書暨緩起訴執\n    行卷附緩起訴處分命令通知書可稽。至被告違反毒品危害防\n    制條例乙案所查扣之白色粉末1 包（驗餘後淨重0.87公克）\n    ，核屬毒品危害防制條例第二條第二項第一款所明定列管之\n    第一級毒品海洛因，此亦有法務部調查局97年1 月1 日調科\n    壹字第09623085680 號鑑定書1 紙在卷可稽（96年度毒偵字\n    第3237號偵查卷宗第36頁）；兼以併為被告所有供犯罪之所\n    用，此亦經被告敘明在卷。從而，聲請人聲請單獨宣告沒收\n    ，核與首開規定相符，應予准許。\n四、依毒品危害防制條例第十八條第一項前段，刑事訴訟法第二\n    百五十九條之一，裁定如主文。\n中    華    民    國    99    年    5     月    12    日\n                  刑事第四庭法  官  王慧惠\n以上正本證明與原本無異。\n對於本件裁定如有不服，應於收受送達後5 日內，向本院提出抗\n告書狀，敘述抗告之理由，抗告於臺灣高等法院。\n中    華    民    國    99    年    5     月    12    日\n                            書記官  王一芳",
  "structure": {
    "main": "扣案之第一級毒品海洛因壹包（驗餘後淨重零點捌柒公克），沒\n收銷燬之。",
    "reason": "一、聲請意旨略以：緣被告甲○○違反毒品危害防制條例乙案，\n    業經檢察官以其所為，係犯毒品危害防制條例第十條第一項\n    、第二項之罪，核屬法定本刑為死刑、無期徒刑或三年以上\n    有期徒刑以外之案件，經參酌被告坦承犯行而表悔悟之犯後\n    態度，尤以自願參加毒品減害計畫以戒除毒癮，而認以緩起\n    訴處分為適當等情詞，依刑事訴訟法第二百五十三條之一第\n    一項規定，以96年度毒偵字第3237號為緩起訴處分確定（確\n    定日期：民國97年3 月7 日），並於99年3 月6 日期間屆滿\n    ，而查無刑事訴訟法第二百五十三條之三第一項各款所列得\n    撤銷緩起訴處分之事由。茲因扣案之白色粉末1 包，係被告\n    供犯罪之所用，且為被告所有，為此，乃依刑事訴訟法第二\n    百五十九條之一規定，聲請單獨宣告沒收等語。\n二、按檢察官依刑事訴訟法第二百五十三條或第二百五十三條之\n    一為不起訴或緩起訴之處分者，對供犯罪所用、供犯罪預備\n    或因犯罪所得之物，以屬於被告者為限，得單獨宣告沒收，\n    刑事訴訟法第二百五十九條之一定有明文。又此項規定除係\n    明文擴張法院得單獨宣告沒收之範圍，而核屬「主從刑不可\n    分原則」之例外；並為刑法第四十條第二項違禁物得單獨宣\n    告沒收之特別規定，依「特別法優於普通法原則」，即應排\n    除刑法第四十條第二項規定之適用。再按毒品危害防制條例\n    第二條第二項第一款、第二款規定，海洛因、安非他命類為\n    第一級、第二級毒品，依同條例第十八條第一項前段之規定\n    ，查獲之第一、二級毒品及專供製造或施用第一、二級毒品\n    之器具，應沒收銷燬之。\n三、經查：被告違反毒品危害防制條例乙案，業經檢察官依刑事\n    訴訟法第二百五十三條之一第一項規定，以96年度毒偵字第\n    3237號為緩起訴處分確定；期間自97年3 月7 日起，並已於\n    99年3 月6 日屆滿，復查無刑事訴訟法第二百五十三條之三\n    第一項各款所列得撤銷緩起訴處分之事由等情，業據本院職\n    權核閱臺灣基隆地方法院檢察署97年度緩字第269 號緩起訴\n    執行卷宗無訛，並有上開偵查卷附緩起訴處分書暨緩起訴執\n    行卷附緩起訴處分命令通知書可稽。至被告違反毒品危害防\n    制條例乙案所查扣之白色粉末1 包（驗餘後淨重0.87公克）\n    ，核屬毒品危害防制條例第二條第二項第一款所明定列管之\n    第一級毒品海洛因，此亦有法務部調查局97年1 月1 日調科\n    壹字第09623085680 號鑑定書1 紙在卷可稽（96年度毒偵字\n    第3237號偵查卷宗第36頁）；兼以併為被告所有供犯罪之所\n    用，此亦經被告敘明在卷。從而，聲請人聲請單獨宣告沒收\n    ，核與首開規定相符，應予准許。\n四、依毒品危害防制條例第十八條第一項前段，刑事訴訟法第二\n    百五十九條之一，裁定如主文。"
  },
  "characters": {
    "judges": [
      "王慧惠"
    ],
    "prosecutors": [

    ],
    "lawyers": [

    ],
    "clerks": [

    ],
    "plaintiffs": [

    ],
    "defendants": [
      "甲○○",
      "聲請人因上列被告違反毒品危害防制條例案件，聲請單獨宣告沒",
      "收（99年度執聲字第342 號），本院裁定如下："
    ],
    "prosecutor_office": [
      "臺灣基隆地方法院檢察署檢察官"
    ],
    "creditors": [

    ],
    "debtors": [

    ],
    "judicial_associate_officer": [

    ]
  },
  "adjudged_at": "2010-05-12",
  "created_at": "2016-01-05 12:34:00",
  "updated_at": "2016-01-05 12:34:00"
}