{
  "identify": "KLD-99-聲-479-20100512-1",
  "court": {
    "name": "臺灣基隆地方法院",
    "code": "KLD"
  },
  "division": {
    "name": "刑事",
    "code": "M"
  },
  "year": 99,
  "word": "聲",
  "number": "479",
  "jcheck": "1",
  "reason": "定應執行刑",
  "content": "臺灣基隆地方法院刑事裁定               99年度聲字第479號\n聲  請  人  臺灣基隆地方法院檢察署檢察官\n受  刑  人  甲○○\n上列聲請人因受刑人數罪併罰有二裁判以上，聲請定其應執行之\n刑（99年度執聲字第350號），本院裁定如下：\n    主  文\n甲○○犯如附表所示之罪，各處如附表所示之刑，應執行有期徒\n刑陸月，如易科罰金，以新台幣壹仟元折算壹日。\n    理  由\n一、本件受刑人甲○○因犯偽造文書等案件，經本院分別判處如\n    附表所示之刑，均經分別確定在案。茲聲請人依刑事訴訟法\n    第477 條第1 項之規定，以犯罪事實最後判決之法院之檢察\n    官，聲請定其應執行之刑，本院審核認聲請為正當，裁定其\n    應執行之刑如主文所示。\n二、依刑事訴訟法第477 條第1 項，刑法第53條、第51條第5 款\n    ，裁定如主文。\n中    華    民    國    99    年    5     月    12    日\n                  刑事第四庭法  官  周霙蘭\n以上正本證明與原本無異。\n對於本件裁定如有不服，應於收受送達後5 日內，向本院提出抗\n告書狀，敘述抗告之理由，抗告於臺灣高等法院。\n中    華    民    國    99    年    5     月    12    日\n                            書記官  莊智凱\n附表：\n臺灣基隆地方法院檢察署受刑人甲○○定應執行刑案件一覽表\n┌────────┬────────┬────────┬────────┐\n│ 編          號 │      1         │      2         │                │\n├────────┼────────┼────────┼────────┤\n│ 罪          名 │偽造文書        │妨害風化        │                │\n├────────┼────────┼────────┼────────┤\n│ 宣    告    刑 │有期徒刑3月     │有期徒刑4月     │                │\n├────────┼────────┼────────┼────────┤\n│ 犯  罪  日  期 │97年12月8日     │97年4月間至98年 │                │\n│                │                │10月16日        │                │\n├────────┼────────┼────────┼────────┤\n│ 偵查(自訴)機關 │基隆地檢98年度偵│基隆地檢98年度偵│                │\n│ 年  度  案  號 │字第646、2481號 │字第4682、4863號│                │\n├───┬────┼────────┼────────┼────────┤\n│      │法    院│    基隆地院    │    基隆地院    │                │\n│最  後├────┼────────┼────────┼────────┤\n│      │案    號│98年度訴字第887 │99年度訴字第25號│                │\n│      │        │號              │                │                │\n│事實審├────┼────────┼────────┼────────┤\n│      │判決日期│98年12月31日    │99年1月29日     │                │\n├───┼────┼────────┼────────┼────────┤\n│      │法    院│    基隆地院    │    基隆地院    │                │\n│      ├────┼────────┼────────┼────────┤\n│確  定│案    號│98年度訴字第887 │99年度訴字第25號│                │\n│      │        │號              │                │                │\n│      ├────┼────────┼────────┼────────┤\n│      │判    決│99年3月29日     │99年3月8日      │                │\n│      │確定日期│                │                │                │\n├───┴────┼────────┼────────┼────────┤\n│備            註│基隆地檢99年度執│基隆地檢99年度執│                │\n│                │字第791號       │字第981號       │                │\n└────────┴────────┴────────┴────────┘",
  "structure": {
    "main": "甲○○犯如附表所示之罪，各處如附表所示之刑，應執行有期徒\n刑陸月，如易科罰金，以新台幣壹仟元折算壹日。",
    "reason": "一、本件受刑人甲○○因犯偽造文書等案件，經本院分別判處如\n    附表所示之刑，均經分別確定在案。茲聲請人依刑事訴訟法\n    第477 條第1 項之規定，以犯罪事實最後判決之法院之檢察\n    官，聲請定其應執行之刑，本院審核認聲請為正當，裁定其\n    應執行之刑如主文所示。\n二、依刑事訴訟法第477 條第1 項，刑法第53條、第51條第5 款\n    ，裁定如主文。"
  },
  "characters": {
    "judges": [
      "周霙蘭"
    ],
    "prosecutors": [

    ],
    "lawyers": [

    ],
    "clerks": [
      "莊智凱"
    ],
    "plaintiffs": [

    ],
    "defendants": [

    ],
    "prosecutor_office": [
      "臺灣基隆地方法院檢察署檢察官"
    ],
    "creditors": [

    ],
    "debtors": [

    ],
    "judicial_associate_officer": [

    ]
  },
  "adjudged_at": "2010-05-12",
  "created_at": "2016-01-05 12:33:55",
  "updated_at": "2016-01-05 12:33:55"
}