{
  "identify": "KLD-99-簡上-80-20100512-1",
  "court": {
    "name": "臺灣基隆地方法院",
    "code": "KLD"
  },
  "division": {
    "name": "刑事",
    "code": "M"
  },
  "year": 99,
  "word": "簡上",
  "number": "80",
  "jcheck": "1",
  "reason": "兒童及少年性交易防制條例",
  "content": "臺灣基隆地方法院刑事判決              99年度簡上字第80號\n公  訴  人  臺灣基隆地方法院檢察署檢察官\n上  訴  人\n即  被  告  乙○○\n上列上訴人即被告因兒童及少年性交易防制條例案件，不服本院\n基隆簡易庭中華民國99年3月17日99年度基簡字第254號第一審刑\n事簡易判決（檢察官聲請簡易判決處刑案號：99年度偵字第153\n號），提起上訴，本院管轄之第二審合議庭判決如下：\n    主  文\n上訴駁回。\n乙○○緩刑貳年，並應向公庫支付新臺幣貳萬元。\n    事實及理由\n一、本案經本院審理結果，認第一審以上訴人即被告乙○○係犯\n    兒童及少年性交易防制條例第29條之電腦網路刊登足以引誘\n    暗示促使人為性交易之訊息罪，並依刑事訴訟法第449條第1\n    項前段、第454條第2項，兒童及少年性交易防制條例第29條\n    、刑法第11條前段、第41條第1項前段，判處被告有期徒刑2\n    月，如易科罰金，以新臺幣（下同）1,000元折算1日，其認\n    事用法並無不當，量刑亦稱妥適，應予維持，除補引「被告\n    乙○○於本院審理時之自白」為證據外，餘均引用第一審判\n    決書及檢察官聲請簡易判決處刑書記載之事實、證據、理由\n    及應適用之法條（詳如附件）。上訴人即被告於偵訊時原否\n    認犯行，惟其於本院審理時已認罪，是其上訴即核無理由，\n    應予以駁回。\n二、末查被告前未曾受有期徒刑以上刑之宣告，有本院卷附臺灣\n    高等法院被告前案紀錄表1份在卷可參，而被告前已因相似\n    之違反兒童及少年性交易防制條例案件，經檢察官於98年12\n    月22日為緩起訴處分確定，現尚在緩起訴處分間，本不應為\n    緩刑之宣告，惟本件被告在網路上刊登足以引誘及暗示人為\n    性交易之訊息，係在前案之前，因未予刪除而再犯本案，且\n    考量被告年輕識淺，犯後於本院審理時已坦承犯行，知所悔\n    悟，經此偵審教訓，當知所警惕，信無再犯之虞，因認對其\n    宣告之刑以暫不執行為適當，爰併予宣告緩刑2年，以啟自\n    新。惟為使被告能確實記取本案教訓，避免再犯，爰依刑法\n    第74條第2項第4款，命被告應向公庫支付2萬元之金額，以\n    為懲儆。\n據上論斷，應依刑事訴訟法第455條之1 第1項、第3項、第368條\n、第373條，刑法第74條第1項第1款、第2項第4款，判決如主文\n。\n本案經檢察官甲○○到庭執行職務。\n中    華    民    國    99    年    5    月    12     日\n                  刑事第一庭審判長法  官  王福康\n                                  法  官  劉桂金\n                                  法  官  王美婷\n以上正本證明與原本無異。\n本判決不得上訴。\n中    華    民    國    99    年    5    月    12     日\n                                  書記官  明祖斌\n附錄論罪法條\n兒童及少年性交易防制條例第29條\n以廣告物、出版品、廣播、電視、電子訊號、電腦網路或其他媒\n體，散布、播送或刊登足以引誘、媒介、暗示或其他促使人為性\n交易之訊息者，處5 年以下有期徒刑，得併科新台幣 1 百萬元\n以下罰金。\n附件：\n臺灣基隆地方法院刑事簡易判決         99年度基簡字第254號\n聲  請  人  臺灣基隆地方法院檢察署檢察官\n被      告  乙○○  女  19歲（民國○○年○月○○日生）\n                        身分證統一編號：Ｚ000000000號\n                        住基隆市○○區○○路325巷5之1號\n上列被告因違反兒童及少年性交易防制條例案件，經檢察官聲請\n簡易判決處刑（99年度偵字第513 號），判決如下：\n    主  文\n乙○○以電腦網路刊登足以引誘及暗示人為性交易之訊息，處有\n期徒刑貳月，如易科罰金，以新臺幣壹仟元折算壹日。\n    事實及理由\n一、本件犯罪事實、證據及應適用之法條，均引用如附件檢察官\n    聲請簡易判決處刑書之記載。\n二、刑之酌科：\n    爰審酌被告所刊登之網路訊息內容對社會善良風俗之危害、\n    犯罪手段、智識程度暨其犯後態度等一切情狀，量處如主文\n    所示之刑，並諭知易科罰金之折算標準。\n三、依刑事訴訟法第449 條第1 項前段、第454 條第2 項，兒童\n    及少年性交易防制條例第29條，刑法第11條前段、第41條第\n    1 項前段，逕以簡易判決處刑如主文。\n四、如不服本判決，得於判決送達後10日內，向本院提出上訴書\n    狀，上訴於本院第二審合議庭。\n中    華    民    國    99    年    3     月    17    日\n                  基隆簡易庭法  官  黃永定\n以上正本證明與原本無異。\n如不服本判決，應於判決送達後10日內，向本院提出上訴書狀，\n上訴於本院合議庭，並按他造當事人之人數附具繕本。\n中    華    民    國    99    年    3     月    17    日\n                            書記官  劉珍珍\n附錄論罪法條：\n兒童及少年性交易防制條例第29條\n以廣告物、出版品、廣播、電視、電子訊號、電腦網路或其他媒\n體，散布、播送或刊登足以引誘、媒介、暗示或其他促使人為性\n交易之訊息者，處5年以下有期徒刑，得併科新台幣1百萬元以下\n附件： \n臺灣基隆地方法院檢察署檢察官聲請簡易判決處刑書\n                                       99年度偵字第513號\n    被      告  乙○○  女  19歲（民國○○年○月○○日生）\n                        住基隆市○○區○○路325巷5之1號\n                        身分證統一編號：Ｚ000000000號\n上列被告因違反兒童及少年性交易防制條例案件，業經偵查終結\n，認為宜聲請以簡易判決處刑，茲將犯罪事實及證據並所犯法條\n分敘如下：\n        犯罪事實\n一、乙○○基於刊登足以引誘、暗示人為性交易訊息之犯意，於\n    民國98年8月21日，在基隆市○○路56號網咖店，以網際網\n    路連線至「UTHOME聊天室」網站之「男同志聊天室」，以「\n    點燈泡約→800」為暱稱，登入該聊天室後，刊登「人在基\n    隆廟口24小時營業約一次800無論時間次數可內設口交爆不\n    剛交不三P不野外不車床只限基隆要ㄉ打0000000000我35D不\n    要依直密要就直接打來」等足以引誘、暗示促使網路上不特\n    定人與之從事性交易之訊息，並留下其於無名網站上帳號「\n    angel0000000」以供聯絡。嗣經警於99年1月12日於網路巡\n    邏時發現，並與乙○○使用之「angel0000000」帳號交談確\n    認其確有性交易之意思後，相約於99年1月13日下午1時30分\n    許，在基隆市○○區○○路57號前性交易時當場查獲。\n二、案經臺北市政府警察局大同分局報告偵辦。\n        證據並所犯法條\n一、訊據被告乙○○固承認有於前揭時、地上述揭暱稱刊登上開\n    訊息一情，惟矢口否認有何犯行，辯稱：伊不知道員警與伊\n    網路對談之意思為何，伊就如網頁內容回答他云云。經查，\n    被告承認於前揭時、地刊登上開訊息，且以「angel0000000\n    」帳號與員警對談等情，且有警員之職務報告書、電腦網路\n    列印資料附卷可證，足認被告確曾於網路上以上開暱稱刊登\n    上開訊息。又被告在網路聊天室使用之「點燈泡約→800」\n    一詞，性質上雖屬網路使用者之暱稱，然此暱稱既已顯現於\n    該聊天室之公開交談版面上，而為不特定人所得瀏覽，自屬\n    在電腦網路刊登訊息之行為；而所謂「點燈泡約→800」，\n    依一般社會通念，係指尋找願付其新臺幣（下同）800元之\n    代價為性交易者，故一般社會大眾對於「點燈泡約→800」\n    之客觀文義，均能認知係在從事性交易；且被告又刊登「人\n    再基隆廟口24小時營業約一次800無論時間次數可內設口交\n    爆不剛交不三P不野外不車床只限基隆要ㄉ打0000000000我\n    35D不要依直密要就直接打來」等語，從客觀文義來看，亦\n    指尋找願付800元與之性交易者，是以上開暱稱及訊息，客\n    觀上均已足使社會一般人望文即生性交易之聯想或揣測，顯\n    有引誘、暗示一般人為性交易之效果。況員警巡邏網路後，\n    發現被告之上開訊息，進而以「q331942」帳號與被告使用\n    之「angel0000000」帳號交談、相約性交易，益證被告刊登\n    上開訊息實有性交易之意，足認被告有刊登足以引誘、暗示\n    人為性交易之訊息，是其犯嫌已堪認定。\n二、核被告所為，係違反兒童及少年性交易防制條例第29條之以\n    電腦網路刊登足以引誘暗示促使人為性交易之訊息罪嫌。\n三、依刑事訴訟法第451條第1項聲請逕以簡易判決處刑。\n    此  致\n臺灣基隆地方法院基隆簡易庭\n中    華    民    國    99    年     2    月    28    日\n                              檢察官  李  元  銘\n本件正本證明與原本無異\n中    華    民    國    99    年    3     月    4     日\n                              書記官\n附錄所犯法條：\n兒童及少年性交易防制條例第29條\n（罰則）\n以廣告物、出版品、廣播、電視、電子訊號、電腦網路或其他媒\n體，散佈、播送或刊登足以引誘、媒介、暗示或其他促使人為性\n交易之訊息者，處5 年以下有期徒刑，得併科新台幣 1 百萬元\n以下罰金。\n\n附記事項：本件係依刑事訴訟法簡易程式辦理，法院簡易庭得不\n傳喚被告、輔佐人、告訴人、告發人等出庭即以簡易判決處刑；\n被告、被害人、告訴人等對告訴乃論案件如已達成民事和解而要\n撤回告訴或對非告訴乃論案件認有受傳喚到庭陳述意見之必要時\n，請即另以書狀向簡易法庭陳述或請求傳訊。",
  "structure": {
    "main": "上訴駁回。\n乙○○緩刑貳年，並應向公庫支付新臺幣貳萬元。\n    事實及理由\n一、本案經本院審理結果，認第一審以上訴人即被告乙○○係犯\n    兒童及少年性交易防制條例第29條之電腦網路刊登足以引誘\n    暗示促使人為性交易之訊息罪，並依刑事訴訟法第449條第1\n    項前段、第454條第2項，兒童及少年性交易防制條例第29條\n    、刑法第11條前段、第41條第1項前段，判處被告有期徒刑2\n    月，如易科罰金，以新臺幣（下同）1,000元折算1日，其認\n    事用法並無不當，量刑亦稱妥適，應予維持，除補引「被告\n    乙○○於本院審理時之自白」為證據外，餘均引用第一審判\n    決書及檢察官聲請簡易判決處刑書記載之事實、證據、理由\n    及應適用之法條（詳如附件）。上訴人即被告於偵訊時原否\n    認犯行，惟其於本院審理時已認罪，是其上訴即核無理由，\n    應予以駁回。\n二、末查被告前未曾受有期徒刑以上刑之宣告，有本院卷附臺灣\n    高等法院被告前案紀錄表1份在卷可參，而被告前已因相似\n    之違反兒童及少年性交易防制條例案件，經檢察官於98年12\n    月22日為緩起訴處分確定，現尚在緩起訴處分間，本不應為\n    緩刑之宣告，惟本件被告在網路上刊登足以引誘及暗示人為\n    性交易之訊息，係在前案之前，因未予刪除而再犯本案，且\n    考量被告年輕識淺，犯後於本院審理時已坦承犯行，知所悔\n    悟，經此偵審教訓，當知所警惕，信無再犯之虞，因認對其\n    宣告之刑以暫不執行為適當，爰併予宣告緩刑2年，以啟自\n    新。惟為使被告能確實記取本案教訓，避免再犯，爰依刑法\n    第74條第2項第4款，命被告應向公庫支付2萬元之金額，以\n    為懲儆。\n據上論斷，應依刑事訴訟法第455條之1 第1項、第3項、第368條\n、第373條，刑法第74條第1項第1款、第2項第4款，判決如主文\n。\n本案經檢察官甲○○到庭執行職務。\n中    華    民    國    99    年    5    月    12     日\n                  刑事第一庭審判長法  官  王福康\n                                  法  官  劉桂金\n                                  法  官  王美婷\n以上正本證明與原本無異。\n本判決不得上訴。\n中    華    民    國    99    年    5    月    12     日\n                                  書記官  明祖斌\n附錄論罪法條\n兒童及少年性交易防制條例第29條\n以廣告物、出版品、廣播、電視、電子訊號、電腦網路或其他媒\n體，散布、播送或刊登足以引誘、媒介、暗示或其他促使人為性\n交易之訊息者，處5 年以下有期徒刑，得併科新台幣 1 百萬元\n以下罰金。\n附件：\n臺灣基隆地方法院刑事簡易判決         99年度基簡字第254號\n聲  請  人  臺灣基隆地方法院檢察署檢察官\n被      告  乙○○  女  19歲（民國○○年○月○○日生）\n                        身分證統一編號：Ｚ000000000號\n                        住基隆市○○區○○路325巷5之1號\n上列被告因違反兒童及少年性交易防制條例案件，經檢察官聲請\n簡易判決處刑（99年度偵字第513 號），判決如下：\n    主  文\n乙○○以電腦網路刊登足以引誘及暗示人為性交易之訊息，處有\n期徒刑貳月，如易科罰金，以新臺幣壹仟元折算壹日。",
    "fact": "一、本案經本院審理結果，認第一審以上訴人即被告乙○○係犯\n    兒童及少年性交易防制條例第29條之電腦網路刊登足以引誘\n    暗示促使人為性交易之訊息罪，並依刑事訴訟法第449條第1\n    項前段、第454條第2項，兒童及少年性交易防制條例第29條\n    、刑法第11條前段、第41條第1項前段，判處被告有期徒刑2\n    月，如易科罰金，以新臺幣（下同）1,000元折算1日，其認\n    事用法並無不當，量刑亦稱妥適，應予維持，除補引「被告\n    乙○○於本院審理時之自白」為證據外，餘均引用第一審判\n    決書及檢察官聲請簡易判決處刑書記載之事實、證據、理由\n    及應適用之法條（詳如附件）。上訴人即被告於偵訊時原否\n    認犯行，惟其於本院審理時已認罪，是其上訴即核無理由，\n    應予以駁回。\n二、末查被告前未曾受有期徒刑以上刑之宣告，有本院卷附臺灣\n    高等法院被告前案紀錄表1份在卷可參，而被告前已因相似\n    之違反兒童及少年性交易防制條例案件，經檢察官於98年12\n    月22日為緩起訴處分確定，現尚在緩起訴處分間，本不應為\n    緩刑之宣告，惟本件被告在網路上刊登足以引誘及暗示人為\n    性交易之訊息，係在前案之前，因未予刪除而再犯本案，且\n    考量被告年輕識淺，犯後於本院審理時已坦承犯行，知所悔\n    悟，經此偵審教訓，當知所警惕，信無再犯之虞，因認對其\n    宣告之刑以暫不執行為適當，爰併予宣告緩刑2年，以啟自\n    新。惟為使被告能確實記取本案教訓，避免再犯，爰依刑法\n    第74條第2項第4款，命被告應向公庫支付2萬元之金額，以\n    為懲儆。\n據上論斷，應依刑事訴訟法第455條之1 第1項、第3項、第368條\n、第373條，刑法第74條第1項第1款、第2項第4款，判決如主文\n。\n本案經檢察官甲○○到庭執行職務。",
    "reason": "一、本案經本院審理結果，認第一審以上訴人即被告乙○○係犯\n    兒童及少年性交易防制條例第29條之電腦網路刊登足以引誘\n    暗示促使人為性交易之訊息罪，並依刑事訴訟法第449條第1\n    項前段、第454條第2項，兒童及少年性交易防制條例第29條\n    、刑法第11條前段、第41條第1項前段，判處被告有期徒刑2\n    月，如易科罰金，以新臺幣（下同）1,000元折算1日，其認\n    事用法並無不當，量刑亦稱妥適，應予維持，除補引「被告\n    乙○○於本院審理時之自白」為證據外，餘均引用第一審判\n    決書及檢察官聲請簡易判決處刑書記載之事實、證據、理由\n    及應適用之法條（詳如附件）。上訴人即被告於偵訊時原否\n    認犯行，惟其於本院審理時已認罪，是其上訴即核無理由，\n    應予以駁回。\n二、末查被告前未曾受有期徒刑以上刑之宣告，有本院卷附臺灣\n    高等法院被告前案紀錄表1份在卷可參，而被告前已因相似\n    之違反兒童及少年性交易防制條例案件，經檢察官於98年12\n    月22日為緩起訴處分確定，現尚在緩起訴處分間，本不應為\n    緩刑之宣告，惟本件被告在網路上刊登足以引誘及暗示人為\n    性交易之訊息，係在前案之前，因未予刪除而再犯本案，且\n    考量被告年輕識淺，犯後於本院審理時已坦承犯行，知所悔\n    悟，經此偵審教訓，當知所警惕，信無再犯之虞，因認對其\n    宣告之刑以暫不執行為適當，爰併予宣告緩刑2年，以啟自\n    新。惟為使被告能確實記取本案教訓，避免再犯，爰依刑法\n    第74條第2項第4款，命被告應向公庫支付2萬元之金額，以\n    為懲儆。\n據上論斷，應依刑事訴訟法第455條之1 第1項、第3項、第368條\n、第373條，刑法第74條第1項第1款、第2項第4款，判決如主文\n。\n本案經檢察官甲○○到庭執行職務。"
  },
  "characters": {
    "judges": [
      "王福康",
      "劉桂金",
      "王美婷",
      "黃永定"
    ],
    "prosecutors": [

    ],
    "lawyers": [

    ],
    "clerks": [
      "明祖斌",
      "劉珍珍",
      "附錄所犯法條："
    ],
    "plaintiffs": [

    ],
    "defendants": [
      "乙○○  女  19歲（民國○○年○月○○日生）"
    ],
    "prosecutor_office": [
      "臺灣基隆地方法院檢察署檢察官"
    ],
    "creditors": [

    ],
    "debtors": [

    ],
    "judicial_associate_officer": [

    ]
  },
  "adjudged_at": "2010-05-12",
  "created_at": "2016-01-05 12:34:30",
  "updated_at": "2016-01-05 12:34:30"
}