{
  "identify": "KLD-99-易-126-20100512-1",
  "court": {
    "name": "臺灣基隆地方法院",
    "code": "KLD"
  },
  "division": {
    "name": "刑事",
    "code": "M"
  },
  "year": 99,
  "word": "易",
  "number": "126",
  "jcheck": "1",
  "reason": "毒品危害防制條例",
  "content": "臺灣基隆地方法院刑事判決               99年度易字第126號\n公  訴  人  臺灣基隆地方法院檢察署檢察官\n被      告  乙○○\n上列被告因違反毒品危害防制條例案件，經檢察官提起公訴（99\n年度毒偵字第303、320 號），被告並於準備程序進行中為有罪\n之陳述，本院乃裁定以簡式審判程序進行審理，並判決如下：\n    主  文\n乙○○施用第二級毒品，累犯，處有期徒刑月，如易科罰金，\n以新臺幣壹仟元折算壹日；又施用第二級毒品，累犯，處有期徒\n刑月，如易科罰金，以新臺幣壹仟元折算壹日。應執行有期徒\n刑伍月，如易科罰金，以新臺幣壹仟元折算壹日。\n    事  實\n一、前案紀錄：\n  (一)乙○○前因初犯施用毒品案件，經觀察、勒戒後，認無繼續\n    施用毒品之傾向，於民國96年4 月19日經釋放出所，並由臺\n    灣基隆地方法院檢察署檢察官於96年4 月18日，以95年度毒\n    偵字第2252號為不起訴處分確定。\n  (二)其後，又於前揭(一)所述之觀察、勒戒執行完畢經釋放出所以\n    後之五年以內，再犯施用毒品案件（二犯施用毒品案件，施\n    用毒品時間：97年11月15日），由臺灣基隆地方法院檢察署\n    檢察官聲請以簡易判決處刑，經本院於98年1 月13日，以98\n    年度基簡字第52號判決有期徒刑四月確定，98年3 月23日易\n    科罰金執行完畢（構成累犯）。\n  (三)繼而復分別因(甲)三犯施用毒品案件，由臺灣基隆地方法院檢\n    察署檢察官聲請以簡易判決處刑，經本院於98年12月8 日，\n    以98年度基簡字第1507號判決有期徒刑四月確定而未執畢；\n    (乙)四犯施用毒品案件，由臺灣基隆地方法院檢察署檢察官聲\n    請以簡易判決處刑，經本院於98年12月24日，以98年度基簡\n    字第1619號判決有期徒刑四月確定而未執畢（以上，則不構\n    成累犯）。\n二、本案事實：\n    乙○○猶不思戒除毒癮，復基於施用第二級毒品安非他命類\n    （安非他命暨甲基安非他命）之個別犯意，分別於下列時、\n    地，藉由下述方式，先、後施用第二級毒品安非他命類2 次\n    ，乃為警依法查獲各如下述：\n  (一)於99年1 月14日晚間10時，在基隆市暖暖區碇內公園之公共\n    廁所內，將安非他命類置入玻璃球吸食器燒烤使生霧化白煙\n    再以口鼻吸食，藉以施用第二級毒品安非他命類1 次。乃為\n    警於99年1 月15日晚間10時14分通知到場採尿送驗，結果呈\n    安非他命暨甲基安非他命陽性反應。\n  (二)於99年1 月26日上午9 時，在基隆市暖暖區碇內公園之公共\n    廁所內，將安非他命類置入玻璃球吸食器燒烤使生霧化白煙\n    再以口鼻吸食，藉以施用第二級毒品安非他命類1 次。乃為\n    警於99年1 月29日上午11時45分，在乙○○住處即基隆市○\n    ○區○○路275 之8 號因案（竊盜另案）拘獲，嗣經採其尿\n    液送驗，結果仍呈安非他命暨甲基安非他命陽性反應。\n三、案經基隆市警察局第一分局移送臺灣基隆地方法院檢察署檢\n    察官偵查起訴。\n    理  由\n壹、程序事項\n一、查刑事訴訟法第二百八十四條之一：「除簡式審判程序、簡\n    易程序及第三百七十六條第一款、第二款所列之罪之案件外\n    ，第一審應行合議審判。」業於本案繫屬以前經公布施行。\n    兼以本案起訴罪名，核與刑事訴訟法第三百七十六條第一款\n    、第二款之規定相符，是其當有首開規定之適用，即其法院\n    組織應為獨任審判無誤。\n二、次查，本案被告乙○○所犯者，非為死刑、無期徒刑、最輕\n    本刑為三年以上有期徒刑之罪或高等法院管轄之第一審案件\n    ；兼以被告業於準備程序進行中，就被訴事實為有罪之陳述\n    ，本院乃告知其簡式審判程序之旨，並於聽取公訴人及被告\n    之意見後，依刑事訴訟法第二百七十三條之一第一項規定，\n    裁定改行簡式審判程序。準此，本案當亦有刑事訴訟法第一\n    百五十九條第二項前段，「不受傳聞證據法則拘束」之例外\n    性規定之適用。\n貳、實體事項\n一、前揭事實業據被告乙○○於本院審理時坦承在卷；且被告如\n    本判決事實欄二所載，為警先、後採集之尿液檢體，經分別\n    送請臺灣檢驗科技股份有限公司以氣相層析質譜儀法為確認\n    檢驗之結果，均呈安非他命暨甲基安非他命陽性反應。此亦\n    有臺灣檢驗科技股份有限公司99年2 月1 日UL/2010/10611\n    號、99年2 月12日UL/2010/20063 號濫用藥物尿液檢驗報告\n    各1 份，暨足與上開檢驗報告相對應之尿液檢體對照表各1\n    件在卷可憑；參之以酵素免疫分析或薄層定性分析等方式為\n    初步篩檢者，檢驗結果雖有相當程度偽陽性之可能，然以氣\n    （液）相層析、質譜分析之儀器為交叉確認者，檢驗結果出\n    現偽陽性之機率則極低，因而具有公信力，核足為對涉嫌人\n    不利之認定；尤以「毒品施用後於尿液、血液中可檢出之最\n    大時限，與施用劑量、施用頻率、施用方式、施用者飲水量\n    之多寡、個人體質、代謝情況、檢體收集時間點及所用檢測\n    方法之靈敏度等因素有關，因個案而異。依據Clarke's Iso\n    lation Identification of Drugs第二版記載，血液中藥物\n    之半衰期（濃度減半所需時間）分別為古柯鹼0.7-1.5 小時\n    、海洛因3 分鐘（其代謝物為嗎啡2-3 小時）、嗎啡2-3 小\n    時、大麻20-36 小時、安非他命12小時（當尿液偏酸性時，\n    為4-8 小時）、甲基安非他命9 小時、Ketamine2-4 小時，\n    而MDMA約8.49小時。一般於尿液中可檢出之最大時限，古柯\n    鹼為施用後1-4 天、海洛因2-4 天、嗎啡2-4 天、大麻1-10\n    天、安非他命1-4 天、甲基安非他命1-5 天、MDMA1-4 天、\n    MDA 1-4 天、Ketamine2-4 天。」此復曾經行政院衛生署藥\n    物食品檢驗局以92年7 月23日管檢字第0920005609號函釋在\n    案。勾稽以觀，足見被告於本院審理時之任意性自白，與事\n    實相符，堪可採信。再者，被告查有如本判決事實欄一所載\n    施用毒品之前案紀錄。觀諸卷附臺灣高等法院被告前案紀錄\n    表所載內容即明。從而，本案事證明確，參照最高法院97年\n    9 月9 日97年度第5 次刑事庭會議二決議意旨、97年度臺非\n    字第540、585號暨98年度臺非字第127、211號判決意旨，被\n    告於初犯施用毒品案件之五年以內，再犯施用毒品之犯行，\n    堪可認定，應依法論科。\n二、論罪科刑：\n  (一)查海洛因、安非他命類分別係毒品危害防制條例所列管之第\n    一級、第二級毒品，此為該條例第二條第二項第一款、第二\n    款所明定。按犯毒品危害防制條例第十條之罪（施用毒品罪\n    ）者，檢察官應聲請法院裁定，令被告入勒戒處所觀察、勒\n    戒，經勒戒處所陳報，認受觀察、勒戒人無繼續施用毒品傾\n    向者，應即釋放，並為不起訴之處分；認有繼續施用毒品傾\n    向者，即應聲請法院裁定令入戒治處所強制戒治，俟強制戒\n    治期滿釋放，再為不起訴之處分。惟依上揭規定觀察勒戒或\n    強制戒治執行完畢釋放後，五年內再犯毒品危害防制條例第\n    十條之罪（施用毒品罪）者，檢察官即應依法追訴，毒品危\n    害防制條例第二十條第一項、第二項、第二十三條第二項分\n    別定有明文。\n  (二)核被告於初犯施用毒品案件以後之五年以內，再犯施用第二\n    級毒品安非他命類（安非他命、甲基安非他命）之行為如本\n    判決事實欄二之所載，均係犯毒品危害防制條例第十條第二\n    項之施用第二級毒品罪。被告施用毒品前、後持有第二級毒\n    品安非他命類（安非他命、甲基安非他命）之低度行為，各\n    應為其施用第二級毒品之高度行為所吸收，均不另論罪。\n  (三)查起訴書雖誤繕被告施用毒品之時間、地點，然此業據蒞庭\n    檢察官於未變動其社會基本事實同一性之前提下，當庭更正\n    如本判決事實欄之所載，此有本院審判筆錄在卷可稽；核此\n    更正範圍，亦無礙於原起訴所特定之事實。本於檢察一體之\n    原則，本院當以蒞庭檢察官所到庭更正者，為起訴所指之犯\n    罪時、地。\n  (四)被告所犯上開二罪，犯意各別，行為互殊，應予分論併罰。\n  (五)被告查有如本判決事實欄一(二)所載之犯罪科刑及刑之執行情\n    形，此有臺灣高等法院被告前案紀錄表在卷可考。乃於前案\n    有期徒刑執行完畢後，五年以內，故意再犯本起最重本刑有\n    期徒刑以上之罪，為累犯，應依刑法第四十七條第一項規定\n    ，就其所犯各罪分別加重其刑。\n  (六)本院審酌被告犯罪之動機、吸食頻率、曾有施用毒品之前科\n    仍不知戒除，兼以被告犯後坦承犯行而表悛悔之犯後態度，\n    及其本案所為雖對己身健康戕害甚鉅，然其究非可與侵害他\n    人法益之犯罪行為等量齊觀，尤以之於此類「施用毒品」之\n    行為人而言，毒品危害防制條例之立法目的亦非重在嚴懲，\n    而係重在彼等「病患性」行為之矯治等一切情狀，分別量處\n    如主文所示之刑，併均諭知易科罰金之折算標準，暨定其應\n    執行之刑。\n據上論斷，應依刑事訴訟法第二百八十四條之一、第二百七十三\n條之一第一項、第二百九十九條第一項前段，毒品危害防制條例\n第二十三條第二項、第十條第二項，刑法第十一條前段、第四十\n七條第一項、第四十一條第一項前段、第五十一條第五款，判決\n如主文。\n本案經檢察官甲○○到庭執行職務。\n中    華    民    國    99    年    5     月    12    日\n                  刑事第四庭法  官  王慧惠\n以上正本證明與原本無異。\n如不服本判決應於收受送達後10日內向本院提出上訴書狀，並應\n敘述具體理由；其未敘述上訴理由者，應於上訴期間屆滿後20日\n內向本院補提理由書(均須按他造當事人之人數附繕本)「切勿逕\n送上級法院」。\n中    華    民    國    99    年    5     月    12    日\n                            書記官  王一芳\n附錄論罪法條：\n毒品危害防制條例第10條第2 項\n施用第二級毒品者，處3 年以下有期徒刑。",
  "structure": {
    "main": "乙○○施用第二級毒品，累犯，處有期徒刑月，如易科罰金，\n以新臺幣壹仟元折算壹日；又施用第二級毒品，累犯，處有期徒\n刑月，如易科罰金，以新臺幣壹仟元折算壹日。應執行有期徒\n刑伍月，如易科罰金，以新臺幣壹仟元折算壹日。",
    "fact": "一、前案紀錄：\n  (一)乙○○前因初犯施用毒品案件，經觀察、勒戒後，認無繼續\n    施用毒品之傾向，於民國96年4 月19日經釋放出所，並由臺\n    灣基隆地方法院檢察署檢察官於96年4 月18日，以95年度毒\n    偵字第2252號為不起訴處分確定。\n  (二)其後，又於前揭(一)所述之觀察、勒戒執行完畢經釋放出所以\n    後之五年以內，再犯施用毒品案件（二犯施用毒品案件，施\n    用毒品時間：97年11月15日），由臺灣基隆地方法院檢察署\n    檢察官聲請以簡易判決處刑，經本院於98年1 月13日，以98\n    年度基簡字第52號判決有期徒刑四月確定，98年3 月23日易\n    科罰金執行完畢（構成累犯）。\n  (三)繼而復分別因(甲)三犯施用毒品案件，由臺灣基隆地方法院檢\n    察署檢察官聲請以簡易判決處刑，經本院於98年12月8 日，\n    以98年度基簡字第1507號判決有期徒刑四月確定而未執畢；\n    (乙)四犯施用毒品案件，由臺灣基隆地方法院檢察署檢察官聲\n    請以簡易判決處刑，經本院於98年12月24日，以98年度基簡\n    字第1619號判決有期徒刑四月確定而未執畢（以上，則不構\n    成累犯）。\n二、本案事實：\n    乙○○猶不思戒除毒癮，復基於施用第二級毒品安非他命類\n    （安非他命暨甲基安非他命）之個別犯意，分別於下列時、\n    地，藉由下述方式，先、後施用第二級毒品安非他命類2 次\n    ，乃為警依法查獲各如下述：\n  (一)於99年1 月14日晚間10時，在基隆市暖暖區碇內公園之公共\n    廁所內，將安非他命類置入玻璃球吸食器燒烤使生霧化白煙\n    再以口鼻吸食，藉以施用第二級毒品安非他命類1 次。乃為\n    警於99年1 月15日晚間10時14分通知到場採尿送驗，結果呈\n    安非他命暨甲基安非他命陽性反應。\n  (二)於99年1 月26日上午9 時，在基隆市暖暖區碇內公園之公共\n    廁所內，將安非他命類置入玻璃球吸食器燒烤使生霧化白煙\n    再以口鼻吸食，藉以施用第二級毒品安非他命類1 次。乃為\n    警於99年1 月29日上午11時45分，在乙○○住處即基隆市○\n    ○區○○路275 之8 號因案（竊盜另案）拘獲，嗣經採其尿\n    液送驗，結果仍呈安非他命暨甲基安非他命陽性反應。\n三、案經基隆市警察局第一分局移送臺灣基隆地方法院檢察署檢\n    察官偵查起訴。",
    "reason": "壹、程序事項\n一、查刑事訴訟法第二百八十四條之一：「除簡式審判程序、簡\n    易程序及第三百七十六條第一款、第二款所列之罪之案件外\n    ，第一審應行合議審判。」業於本案繫屬以前經公布施行。\n    兼以本案起訴罪名，核與刑事訴訟法第三百七十六條第一款\n    、第二款之規定相符，是其當有首開規定之適用，即其法院\n    組織應為獨任審判無誤。\n二、次查，本案被告乙○○所犯者，非為死刑、無期徒刑、最輕\n    本刑為三年以上有期徒刑之罪或高等法院管轄之第一審案件\n    ；兼以被告業於準備程序進行中，就被訴事實為有罪之陳述\n    ，本院乃告知其簡式審判程序之旨，並於聽取公訴人及被告\n    之意見後，依刑事訴訟法第二百七十三條之一第一項規定，\n    裁定改行簡式審判程序。準此，本案當亦有刑事訴訟法第一\n    百五十九條第二項前段，「不受傳聞證據法則拘束」之例外\n    性規定之適用。\n貳、實體事項\n一、前揭事實業據被告乙○○於本院審理時坦承在卷；且被告如\n    本判決事實欄二所載，為警先、後採集之尿液檢體，經分別\n    送請臺灣檢驗科技股份有限公司以氣相層析質譜儀法為確認\n    檢驗之結果，均呈安非他命暨甲基安非他命陽性反應。此亦\n    有臺灣檢驗科技股份有限公司99年2 月1 日UL/2010/10611\n    號、99年2 月12日UL/2010/20063 號濫用藥物尿液檢驗報告\n    各1 份，暨足與上開檢驗報告相對應之尿液檢體對照表各1\n    件在卷可憑；參之以酵素免疫分析或薄層定性分析等方式為\n    初步篩檢者，檢驗結果雖有相當程度偽陽性之可能，然以氣\n    （液）相層析、質譜分析之儀器為交叉確認者，檢驗結果出\n    現偽陽性之機率則極低，因而具有公信力，核足為對涉嫌人\n    不利之認定；尤以「毒品施用後於尿液、血液中可檢出之最\n    大時限，與施用劑量、施用頻率、施用方式、施用者飲水量\n    之多寡、個人體質、代謝情況、檢體收集時間點及所用檢測\n    方法之靈敏度等因素有關，因個案而異。依據Clarke's Iso\n    lation Identification of Drugs第二版記載，血液中藥物\n    之半衰期（濃度減半所需時間）分別為古柯鹼0.7-1.5 小時\n    、海洛因3 分鐘（其代謝物為嗎啡2-3 小時）、嗎啡2-3 小\n    時、大麻20-36 小時、安非他命12小時（當尿液偏酸性時，\n    為4-8 小時）、甲基安非他命9 小時、Ketamine2-4 小時，\n    而MDMA約8.49小時。一般於尿液中可檢出之最大時限，古柯\n    鹼為施用後1-4 天、海洛因2-4 天、嗎啡2-4 天、大麻1-10\n    天、安非他命1-4 天、甲基安非他命1-5 天、MDMA1-4 天、\n    MDA 1-4 天、Ketamine2-4 天。」此復曾經行政院衛生署藥\n    物食品檢驗局以92年7 月23日管檢字第0920005609號函釋在\n    案。勾稽以觀，足見被告於本院審理時之任意性自白，與事\n    實相符，堪可採信。再者，被告查有如本判決事實欄一所載\n    施用毒品之前案紀錄。觀諸卷附臺灣高等法院被告前案紀錄\n    表所載內容即明。從而，本案事證明確，參照最高法院97年\n    9 月9 日97年度第5 次刑事庭會議二決議意旨、97年度臺非\n    字第540、585號暨98年度臺非字第127、211號判決意旨，被\n    告於初犯施用毒品案件之五年以內，再犯施用毒品之犯行，\n    堪可認定，應依法論科。\n二、論罪科刑：\n  (一)查海洛因、安非他命類分別係毒品危害防制條例所列管之第\n    一級、第二級毒品，此為該條例第二條第二項第一款、第二\n    款所明定。按犯毒品危害防制條例第十條之罪（施用毒品罪\n    ）者，檢察官應聲請法院裁定，令被告入勒戒處所觀察、勒\n    戒，經勒戒處所陳報，認受觀察、勒戒人無繼續施用毒品傾\n    向者，應即釋放，並為不起訴之處分；認有繼續施用毒品傾\n    向者，即應聲請法院裁定令入戒治處所強制戒治，俟強制戒\n    治期滿釋放，再為不起訴之處分。惟依上揭規定觀察勒戒或\n    強制戒治執行完畢釋放後，五年內再犯毒品危害防制條例第\n    十條之罪（施用毒品罪）者，檢察官即應依法追訴，毒品危\n    害防制條例第二十條第一項、第二項、第二十三條第二項分\n    別定有明文。\n  (二)核被告於初犯施用毒品案件以後之五年以內，再犯施用第二\n    級毒品安非他命類（安非他命、甲基安非他命）之行為如本\n    判決事實欄二之所載，均係犯毒品危害防制條例第十條第二\n    項之施用第二級毒品罪。被告施用毒品前、後持有第二級毒\n    品安非他命類（安非他命、甲基安非他命）之低度行為，各\n    應為其施用第二級毒品之高度行為所吸收，均不另論罪。\n  (三)查起訴書雖誤繕被告施用毒品之時間、地點，然此業據蒞庭\n    檢察官於未變動其社會基本事實同一性之前提下，當庭更正\n    如本判決事實欄之所載，此有本院審判筆錄在卷可稽；核此\n    更正範圍，亦無礙於原起訴所特定之事實。本於檢察一體之\n    原則，本院當以蒞庭檢察官所到庭更正者，為起訴所指之犯\n    罪時、地。\n  (四)被告所犯上開二罪，犯意各別，行為互殊，應予分論併罰。\n  (五)被告查有如本判決事實欄一(二)所載之犯罪科刑及刑之執行情\n    形，此有臺灣高等法院被告前案紀錄表在卷可考。乃於前案\n    有期徒刑執行完畢後，五年以內，故意再犯本起最重本刑有\n    期徒刑以上之罪，為累犯，應依刑法第四十七條第一項規定\n    ，就其所犯各罪分別加重其刑。\n  (六)本院審酌被告犯罪之動機、吸食頻率、曾有施用毒品之前科\n    仍不知戒除，兼以被告犯後坦承犯行而表悛悔之犯後態度，\n    及其本案所為雖對己身健康戕害甚鉅，然其究非可與侵害他\n    人法益之犯罪行為等量齊觀，尤以之於此類「施用毒品」之\n    行為人而言，毒品危害防制條例之立法目的亦非重在嚴懲，\n    而係重在彼等「病患性」行為之矯治等一切情狀，分別量處\n    如主文所示之刑，併均諭知易科罰金之折算標準，暨定其應\n    執行之刑。\n據上論斷，應依刑事訴訟法第二百八十四條之一、第二百七十三\n條之一第一項、第二百九十九條第一項前段，毒品危害防制條例\n第二十三條第二項、第十條第二項，刑法第十一條前段、第四十\n七條第一項、第四十一條第一項前段、第五十一條第五款，判決\n如主文。\n本案經檢察官甲○○到庭執行職務。\n中    華    民    國    99    年    5     月    12    日\n                  刑事第四庭法  官  王慧惠\n以上正本證明與原本無異。\n如不服本判決應於收受送達後10日內向本院提出上訴書狀，並應\n敘述具體理由；其未敘述上訴理由者，應於上訴期間屆滿後20日\n內向本院補提理由書(均須按他造當事人之人數附繕本)「切勿逕\n送上級法院」。"
  },
  "characters": {
    "judges": [
      "王慧惠"
    ],
    "prosecutors": [

    ],
    "lawyers": [

    ],
    "clerks": [
      "王一芳"
    ],
    "plaintiffs": [

    ],
    "defendants": [
      "乙○○"
    ],
    "prosecutor_office": [
      "臺灣基隆地方法院檢察署檢察官"
    ],
    "creditors": [

    ],
    "debtors": [

    ],
    "judicial_associate_officer": [

    ]
  },
  "adjudged_at": "2010-05-12",
  "created_at": "2016-01-05 12:33:50",
  "updated_at": "2016-01-05 12:33:50"
}