{
  "identify": "KLD-99-易-92-20100512-1",
  "court": {
    "name": "臺灣基隆地方法院",
    "code": "KLD"
  },
  "division": {
    "name": "刑事",
    "code": "M"
  },
  "year": 99,
  "word": "易",
  "number": "92",
  "jcheck": "1",
  "reason": "竊盜等",
  "content": "臺灣基隆地方法院刑事判決                99年度易字第92號\n公  訴  人  臺灣基隆地方法院檢察署檢察官\n被      告  甲○○\n上列被告因竊盜案件，經檢察官提起公訴（98年度偵字第5036號\n），本院判決如下：\n    主  文\n甲○○無故侵入他人建築物，累犯，處有期徒刑月；又竊盜，\n累犯，處有期徒刑伍月；又無故侵入他人建築物，累犯，處有期\n徒刑月；又攜帶兇器，毀損門扇竊盜，累犯，處有期徒刑拾月\n。應執行有期徒刑壹年陸月。\n    事  實\n一、前案紀錄：\n    甲○○前分別因(甲)犯竊盜案件，經本院於民國93年9 月29日\n    ，以93年度訴字第250 號判決有期徒刑十月確定；(乙)違反毒\n    品危害防制條例案件，經本院於94年1 月12日，以94年度基\n    簡字第26號判決有期徒刑四月確定。所犯(甲)(乙)二案，則經合\n    併定刑為有期徒刑一年（94年度聲字第467 號裁定），94年\n    1 月13日發監執行、95年1 月12日執行完畢（惟甲○○因自\n    95年1 月13日起，接續執行另案拘役，故而遲至95年1 月19\n    日始經釋放）。其後，又再犯竊盜案件，經本院於96年7 月\n    6 日，以96年度易字第347 號判決應執行有期徒刑一年，暨\n    於96年7 月30日，以96年度聲減字第35號裁定減為有期徒刑\n    六月確定，97年4 月15日發監執行、97年10月14日執行完畢\n    （以上，均構成累犯）。\n二、本案事實：\n    甲○○前曾租賃暫居於基隆市○○區○○路57號9 樓，並因\n    而探知該棟大樓之內部概況，遂萌生為自己不法所有之意圖\n    暨竊盜他人財物之犯意，進而利用該棟大樓1 樓樓梯間大門\n    長年未經關攏且無人看守而可隨意進出之機會，分別於下列\n    時、地，著手實施下列2 起竊盜犯行；嗣則因下址所有人乙\n    ○○及其使用人丁○○報警查辦，方為警調閱裝設於該棟大\n    樓內部之監視錄影畫面而循線查獲：\n  (一)甲○○於98年9 月23日上午6 時，逕由上揭大樓洞開之1 樓\n    樓梯間大門登堂而入，繼而利用「基隆市○○區○○路57號\n    5 樓」（以下簡稱「系爭建築物」）之大門門鎖（喇叭鎖）\n    鬆動而未能關攏之機會，無故侵入乙○○所有而由丁○○承\n    租充當倉庫使用之「系爭建築物」內部，徒手將丁○○所有\n    之七星牌香菸、峰牌香菸各5 包及可樂5 罐，置於自己實力\n    支配之下，藉以侵入他人建築物而後竊盜他人財物得逞，其\n    後，復即攜同上揭香菸、可樂離開現場而取用一空。\n  (二)茲因丁○○查悉「系爭建築物」屢遭不明竊賊侵入行竊，遂\n    囑由原屋主即出租人乙○○於98年9 月27日，為其更換大門\n    俾其得以閉門上鎖。乃甲○○查悉上情以後，非特未曾稍改\n    其侵入行竊之本意，猶於98年10月12日上午7 時，自備客觀\n    上足以對人之生命、身體安全構成威脅、危害之「鐵鎚」1\n    支，先由上揭大樓洞開之1 樓樓梯間大門登堂而入，再以自\n    備之上揭「鐵鎚」敲擊「系爭建築物」大門鑲嵌之喇叭鎖（\n    該喇叭鎖因屬門板之一部而無從與之分離），致該喇叭鎖內\n    部機件斷裂，使「系爭建築物」之大門喪失其原有之防閑效\n    用，隨即啟門而無故侵入，逕將丁○○所有之七星牌香菸、\n    峰牌香菸各2 包及御茶園飲料6 罐，置於自己實力支配之下\n    ，藉以侵入他人建築物暨攜帶兇器、毀損門扇竊盜他人財物\n    得手，其後，復即攜同上揭香菸、御茶園飲料離開現場而取\n    用一空；至上揭「鐵鎚」1 支，則因甲○○於其後隨手棄置\n    而告滅失。\n三、案經基隆市警察局第一分局移送臺灣基隆地方法院檢察署檢\n    察官偵查起訴。\n    理  由\n一、證據能力\n  (一)供述證據─即「被告以外之人於審判外之言詞或書面陳述」\n    （被告就關此「證據能力」俱表「不予爭執」）：\n    按「被告以外之人於審判外之陳述，雖不符前四條之規定，\n    而經當事人於審判程序同意作為證據，法院審酌該言詞陳述\n    或書面陳述作成時之情況，認為適當者，亦得為證據。「當\n    事人、代理人或辯護人於法院調查證據時，知有第一百五十\n    九條第一項不得為證據之情形，而未於言詞辯論終結前聲明\n    異議者，視為有前項之同意。」刑事訴訟法第一百五十九條\n    之五第一項、第二項定有明文。查本案相關證人即乙○○、\n    丁○○、莊榮臻、張君豪於「審判外之言詞陳述」，或未經\n    被告於本院審理中就其證據能力而為明示爭執，或未經被告\n    於本院言詞辯論終結前就其證據能力而為聲明異議；兼以本\n    院自形式上察其作成、取得當時之外部情況，亦俱無「任意\n    性」或「信用性」違反而顯然不適當之情形，而均與刑事訴\n    訟法第一百五十九條之五第二項之規定相符。因認關此證人\n    於「審判外言詞陳述」，之於本案而言，均有證據能力。\n  (二)非供述證據\n    其餘業經本院援用如後所述之非供述證據，非特核無公務員\n    違法採證之情形，尤以均曾經本院於審判期日，依刑事訴訟\n    法第一百六十四條規定，踐行證據調查之法定程式，提示被\n    告及辯護人而使其辨認，則其證據能力之具備，當亦毋待贅\n    言。\n二、事實認定\n    上開事實業據被告甲○○於本院審理時坦承不諱（見本院審\n    判筆錄第2 頁至第5 頁、第7 頁至第8 頁），並經證人乙○\n    ○（即系爭建築物之所有人）、丁○○（即系爭建築物之使\n    用人）、莊榮臻（即查獲員警）、張君豪（即查獲員警）證\n    述無誤，且有系爭建築物「大門」更換之98年9 月27日報價\n    單影本1 紙、現場照片5 張、監視錄影翻拍照片16張及檢察\n    官勘驗筆錄在卷可佐。綜上，堪認被告於本院審理時之任意\n    性自白，與事實相符，可以採信。從而，本案事證明確，被\n    告如本判決事實欄所載之侵入住宅、竊盜等犯行，堪可認定\n    ，應依法論科。\n三、論罪科刑\n  (一)按刑法第三百二十一條第一項第二款所稱之「其他安全設備\n    」，固係指門扇、牆垣以外，依社會通常觀念，足認為防盜\n    之一切設備；惟如本判決事實欄二(二)所指，鑲嵌於系爭建築\n    物大門之喇叭鎖，既已嵌入其門板而無從與之分離，即其顯\n    已構成門板之一部。準此，本案被告以「鐵鎚」敲擊上開喇\n    叭鎖，致該喇叭鎖之內部機件斷裂，無異已使該大門喪失其\n    原有之防閑效用；即其毀損上開喇叭鎖以入室行竊，自應論\n    以本條之毀損門扇加重竊盜罪。又毀（毀損）越（踰越）門\n    扇而入室行竊，其毀損行為即屬毀棄、損壞他人之物，已結\n    合於所犯加重竊盜之罪質中，並無更行構成毀損罪名之餘地\n    （最高法院92年度臺非字第6 號判決意旨參照）。\n  (二)次按刑法第三百二十一條第一項第三款之攜帶兇器竊盜罪，\n    係以行為人攜帶兇器為其加重要件，此所謂兇器，其種類並\n    無限制，凡客觀上足以對人之生命、身體安全構成威脅，具\n    有危險性之兇器均屬之，且祇須行竊時攜帶此種具危險性之\n    兇器為已足，並不以攜帶之初有行兇之意圖為必要（最高法\n    院79年臺上字第5253號判例意旨參照），亦不以將該兇器自\n    他地攜往行竊地為必要（最高法院62年臺上字第2489號判例\n    意旨參照），是不問該兇器係行為人自行攜往行竊現場，或\n    在竊盜現場臨時持以行竊，均應論行為人以攜帶兇器竊盜罪\n    。茲就本案情節而論，如本判決事實欄二(二)所載之「鐵鎚」\n    1 支，雖經被告於犯案後棄置滅失而未經扣案，然其既足以\n    敲毀喇叭鎖而使該喇叭鎖之內部機件斷裂，則自客觀以言，\n    當亦足以對人之生命、身體構成威脅，是被告攜同上揭「鐵\n    鎚」而藉由本判決事實欄二(二)所載方式竊盜他人財物之所為\n    ，當亦悉與刑法第三百二十一條第一項第三款攜帶兇器加重\n    竊盜罪之構成要件相符。\n  (三)再者，「系爭建築物」因係丁○○向乙○○承租而充當倉庫\n    使用，致其固非刑法所稱「供人日常生活起居」之住宅可比\n    ；惟其既定著於土地，上有屋面，周有四壁而足以蔽風雨、\n    通出入，則其當仍屬刑法所指之建築物無疑。據此，被告未\n    得丁○○、乙○○允許而隨意進入「系爭建築物」如本判決\n    事實欄二(一)(二)之所示，自亦分別該當刑法第三百零六條第一\n    項之無故侵入他人建築物罪。\n  (四)是核被告如本判決事實欄二(一)之所為，係犯刑法第三百零六\n    條第一項之無故侵入他人建築物罪及同法第三百二十條第一\n    項之普通竊盜罪；至被告如本判決事實欄二(二)之所為，則係\n    犯刑法第三百零六條第一項之無故侵入他人建築物罪及同法\n    第三百二十一條第一項第二款、第三款之攜帶兇器，毀損門\n    扇竊盜罪。\n  (五)被告查有如本判決事實欄一所載之犯罪科刑及執行情形，此\n    有臺灣高等法院被告前案紀錄表在卷可稽；乃於前案有期徒\n    刑執行完畢後，五年以內，故意再犯最重本刑有期徒刑以上\n    之罪，為累犯，應依刑法第四十七條第一項規定，就其所犯\n    各罪分別加重其刑。\n  (六)被告前、後2 起侵入他人建築物犯行及其前、後2 起竊盜犯\n    行，犯意各別、行為互殊，應予分論併罰。\n  (七)本院審酌被告不思努力工作以賺取所需，妄想藉由侵入建築\n    物而後竊盜之方式不勞而獲，嚴重缺乏尊重他人財產權之觀\n    念，併衡量被告侵入建築物而後竊盜之手法，對於整體社會\n    治安所造成之危害，兼考量被告屢有相類於本案竊盜之前科\n    素行（詳如本判決事實欄一之所載，卷附臺灣高等法院被告\n    前案紀錄表參見），乃一犯再犯而未見改悔，暨審酌被害人\n    法益侵害之程度，及被告生活狀況、智識程度、雖一度於偵\n    查中飾詞推諉，然於本院審理時則終知坦承而表悛悔之犯後\n    態度等一切情狀，分別量處如主文所示之刑，併定其應執行\n    之刑。\n據上論斷，應依刑事訴訟法第二百八十四條之一、第二百九十九\n條第一項前段，刑法第三百零六條第一項、第三百二十條第一項\n、第三百二十一條第一項第二款、第三款、第四十七條第一項、\n第五十一條第五款，刑法施行法第一條之一，判決如主文。\n本案經檢察官丙○○到庭執行職務。\n中    華    民    國    99    年    5     月    12    日\n                  刑事第四庭法  官  王慧惠\n以上正本證明與原本無異。\n如不服本判決應於收受送達後10日內向本院提出上訴書狀，並應\n敘述具體理由；其未敘述上訴理由者，應於上訴期間屆滿後20日\n內向本院補提理由書(均須按他造當事人之人數附繕本)「切勿逕\n送上級法院」。\n中    華    民    國    99    年    5     月    12    日\n                            書記官  王一芳\n附錄論罪法條：\n刑法第306 條第1 項\n無故侵入他人住宅、建築物或附連圍繞之土地或船艦者，處1 年\n以下有期徒刑、拘役或3 百元以下罰金。\n刑法第320 條第1 項\n（普通竊盜罪、竊佔罪）\n意圖為自己或第三人不法之所有，而竊取他人之動產者，為竊盜\n罪，處5 年以下有期徒刑、拘役或5 百元以下罰金。\n刑法第321 條第1 項第2 款、第3 款\n犯竊盜罪而有左列情形之一者，處6 月以上、5 年以下有期徒刑\n：\n一、於夜間侵入住宅或有人居住之建築物、船艦或隱匿其內而犯\n    之者。\n二、毀越門扇、牆垣或其他安全設備而犯之者。\n三、攜帶兇器而犯之者。\n四、結夥三人以上而犯之者。\n五、乘火災、水災或其他災害之際而犯之者。\n六、在車站或埠頭而犯之者。",
  "structure": {
    "main": "甲○○無故侵入他人建築物，累犯，處有期徒刑月；又竊盜，\n累犯，處有期徒刑伍月；又無故侵入他人建築物，累犯，處有期\n徒刑月；又攜帶兇器，毀損門扇竊盜，累犯，處有期徒刑拾月\n。應執行有期徒刑壹年陸月。",
    "fact": "一、前案紀錄：\n    甲○○前分別因(甲)犯竊盜案件，經本院於民國93年9 月29日\n    ，以93年度訴字第250 號判決有期徒刑十月確定；(乙)違反毒\n    品危害防制條例案件，經本院於94年1 月12日，以94年度基\n    簡字第26號判決有期徒刑四月確定。所犯(甲)(乙)二案，則經合\n    併定刑為有期徒刑一年（94年度聲字第467 號裁定），94年\n    1 月13日發監執行、95年1 月12日執行完畢（惟甲○○因自\n    95年1 月13日起，接續執行另案拘役，故而遲至95年1 月19\n    日始經釋放）。其後，又再犯竊盜案件，經本院於96年7 月\n    6 日，以96年度易字第347 號判決應執行有期徒刑一年，暨\n    於96年7 月30日，以96年度聲減字第35號裁定減為有期徒刑\n    六月確定，97年4 月15日發監執行、97年10月14日執行完畢\n    （以上，均構成累犯）。\n二、本案事實：\n    甲○○前曾租賃暫居於基隆市○○區○○路57號9 樓，並因\n    而探知該棟大樓之內部概況，遂萌生為自己不法所有之意圖\n    暨竊盜他人財物之犯意，進而利用該棟大樓1 樓樓梯間大門\n    長年未經關攏且無人看守而可隨意進出之機會，分別於下列\n    時、地，著手實施下列2 起竊盜犯行；嗣則因下址所有人乙\n    ○○及其使用人丁○○報警查辦，方為警調閱裝設於該棟大\n    樓內部之監視錄影畫面而循線查獲：\n  (一)甲○○於98年9 月23日上午6 時，逕由上揭大樓洞開之1 樓\n    樓梯間大門登堂而入，繼而利用「基隆市○○區○○路57號\n    5 樓」（以下簡稱「系爭建築物」）之大門門鎖（喇叭鎖）\n    鬆動而未能關攏之機會，無故侵入乙○○所有而由丁○○承\n    租充當倉庫使用之「系爭建築物」內部，徒手將丁○○所有\n    之七星牌香菸、峰牌香菸各5 包及可樂5 罐，置於自己實力\n    支配之下，藉以侵入他人建築物而後竊盜他人財物得逞，其\n    後，復即攜同上揭香菸、可樂離開現場而取用一空。\n  (二)茲因丁○○查悉「系爭建築物」屢遭不明竊賊侵入行竊，遂\n    囑由原屋主即出租人乙○○於98年9 月27日，為其更換大門\n    俾其得以閉門上鎖。乃甲○○查悉上情以後，非特未曾稍改\n    其侵入行竊之本意，猶於98年10月12日上午7 時，自備客觀\n    上足以對人之生命、身體安全構成威脅、危害之「鐵鎚」1\n    支，先由上揭大樓洞開之1 樓樓梯間大門登堂而入，再以自\n    備之上揭「鐵鎚」敲擊「系爭建築物」大門鑲嵌之喇叭鎖（\n    該喇叭鎖因屬門板之一部而無從與之分離），致該喇叭鎖內\n    部機件斷裂，使「系爭建築物」之大門喪失其原有之防閑效\n    用，隨即啟門而無故侵入，逕將丁○○所有之七星牌香菸、\n    峰牌香菸各2 包及御茶園飲料6 罐，置於自己實力支配之下\n    ，藉以侵入他人建築物暨攜帶兇器、毀損門扇竊盜他人財物\n    得手，其後，復即攜同上揭香菸、御茶園飲料離開現場而取\n    用一空；至上揭「鐵鎚」1 支，則因甲○○於其後隨手棄置\n    而告滅失。\n三、案經基隆市警察局第一分局移送臺灣基隆地方法院檢察署檢\n    察官偵查起訴。",
    "reason": "一、證據能力\n  (一)供述證據─即「被告以外之人於審判外之言詞或書面陳述」\n    （被告就關此「證據能力」俱表「不予爭執」）：\n    按「被告以外之人於審判外之陳述，雖不符前四條之規定，\n    而經當事人於審判程序同意作為證據，法院審酌該言詞陳述\n    或書面陳述作成時之情況，認為適當者，亦得為證據。「當\n    事人、代理人或辯護人於法院調查證據時，知有第一百五十\n    九條第一項不得為證據之情形，而未於言詞辯論終結前聲明\n    異議者，視為有前項之同意。」刑事訴訟法第一百五十九條\n    之五第一項、第二項定有明文。查本案相關證人即乙○○、\n    丁○○、莊榮臻、張君豪於「審判外之言詞陳述」，或未經\n    被告於本院審理中就其證據能力而為明示爭執，或未經被告\n    於本院言詞辯論終結前就其證據能力而為聲明異議；兼以本\n    院自形式上察其作成、取得當時之外部情況，亦俱無「任意\n    性」或「信用性」違反而顯然不適當之情形，而均與刑事訴\n    訟法第一百五十九條之五第二項之規定相符。因認關此證人\n    於「審判外言詞陳述」，之於本案而言，均有證據能力。\n  (二)非供述證據\n    其餘業經本院援用如後所述之非供述證據，非特核無公務員\n    違法採證之情形，尤以均曾經本院於審判期日，依刑事訴訟\n    法第一百六十四條規定，踐行證據調查之法定程式，提示被\n    告及辯護人而使其辨認，則其證據能力之具備，當亦毋待贅\n    言。\n二、事實認定\n    上開事實業據被告甲○○於本院審理時坦承不諱（見本院審\n    判筆錄第2 頁至第5 頁、第7 頁至第8 頁），並經證人乙○\n    ○（即系爭建築物之所有人）、丁○○（即系爭建築物之使\n    用人）、莊榮臻（即查獲員警）、張君豪（即查獲員警）證\n    述無誤，且有系爭建築物「大門」更換之98年9 月27日報價\n    單影本1 紙、現場照片5 張、監視錄影翻拍照片16張及檢察\n    官勘驗筆錄在卷可佐。綜上，堪認被告於本院審理時之任意\n    性自白，與事實相符，可以採信。從而，本案事證明確，被\n    告如本判決事實欄所載之侵入住宅、竊盜等犯行，堪可認定\n    ，應依法論科。\n三、論罪科刑\n  (一)按刑法第三百二十一條第一項第二款所稱之「其他安全設備\n    」，固係指門扇、牆垣以外，依社會通常觀念，足認為防盜\n    之一切設備；惟如本判決事實欄二(二)所指，鑲嵌於系爭建築\n    物大門之喇叭鎖，既已嵌入其門板而無從與之分離，即其顯\n    已構成門板之一部。準此，本案被告以「鐵鎚」敲擊上開喇\n    叭鎖，致該喇叭鎖之內部機件斷裂，無異已使該大門喪失其\n    原有之防閑效用；即其毀損上開喇叭鎖以入室行竊，自應論\n    以本條之毀損門扇加重竊盜罪。又毀（毀損）越（踰越）門\n    扇而入室行竊，其毀損行為即屬毀棄、損壞他人之物，已結\n    合於所犯加重竊盜之罪質中，並無更行構成毀損罪名之餘地\n    （最高法院92年度臺非字第6 號判決意旨參照）。\n  (二)次按刑法第三百二十一條第一項第三款之攜帶兇器竊盜罪，\n    係以行為人攜帶兇器為其加重要件，此所謂兇器，其種類並\n    無限制，凡客觀上足以對人之生命、身體安全構成威脅，具\n    有危險性之兇器均屬之，且祇須行竊時攜帶此種具危險性之\n    兇器為已足，並不以攜帶之初有行兇之意圖為必要（最高法\n    院79年臺上字第5253號判例意旨參照），亦不以將該兇器自\n    他地攜往行竊地為必要（最高法院62年臺上字第2489號判例\n    意旨參照），是不問該兇器係行為人自行攜往行竊現場，或\n    在竊盜現場臨時持以行竊，均應論行為人以攜帶兇器竊盜罪\n    。茲就本案情節而論，如本判決事實欄二(二)所載之「鐵鎚」\n    1 支，雖經被告於犯案後棄置滅失而未經扣案，然其既足以\n    敲毀喇叭鎖而使該喇叭鎖之內部機件斷裂，則自客觀以言，\n    當亦足以對人之生命、身體構成威脅，是被告攜同上揭「鐵\n    鎚」而藉由本判決事實欄二(二)所載方式竊盜他人財物之所為\n    ，當亦悉與刑法第三百二十一條第一項第三款攜帶兇器加重\n    竊盜罪之構成要件相符。\n  (三)再者，「系爭建築物」因係丁○○向乙○○承租而充當倉庫\n    使用，致其固非刑法所稱「供人日常生活起居」之住宅可比\n    ；惟其既定著於土地，上有屋面，周有四壁而足以蔽風雨、\n    通出入，則其當仍屬刑法所指之建築物無疑。據此，被告未\n    得丁○○、乙○○允許而隨意進入「系爭建築物」如本判決\n    事實欄二(一)(二)之所示，自亦分別該當刑法第三百零六條第一\n    項之無故侵入他人建築物罪。\n  (四)是核被告如本判決事實欄二(一)之所為，係犯刑法第三百零六\n    條第一項之無故侵入他人建築物罪及同法第三百二十條第一\n    項之普通竊盜罪；至被告如本判決事實欄二(二)之所為，則係\n    犯刑法第三百零六條第一項之無故侵入他人建築物罪及同法\n    第三百二十一條第一項第二款、第三款之攜帶兇器，毀損門\n    扇竊盜罪。\n  (五)被告查有如本判決事實欄一所載之犯罪科刑及執行情形，此\n    有臺灣高等法院被告前案紀錄表在卷可稽；乃於前案有期徒\n    刑執行完畢後，五年以內，故意再犯最重本刑有期徒刑以上\n    之罪，為累犯，應依刑法第四十七條第一項規定，就其所犯\n    各罪分別加重其刑。\n  (六)被告前、後2 起侵入他人建築物犯行及其前、後2 起竊盜犯\n    行，犯意各別、行為互殊，應予分論併罰。\n  (七)本院審酌被告不思努力工作以賺取所需，妄想藉由侵入建築\n    物而後竊盜之方式不勞而獲，嚴重缺乏尊重他人財產權之觀\n    念，併衡量被告侵入建築物而後竊盜之手法，對於整體社會\n    治安所造成之危害，兼考量被告屢有相類於本案竊盜之前科\n    素行（詳如本判決事實欄一之所載，卷附臺灣高等法院被告\n    前案紀錄表參見），乃一犯再犯而未見改悔，暨審酌被害人\n    法益侵害之程度，及被告生活狀況、智識程度、雖一度於偵\n    查中飾詞推諉，然於本院審理時則終知坦承而表悛悔之犯後\n    態度等一切情狀，分別量處如主文所示之刑，併定其應執行\n    之刑。\n據上論斷，應依刑事訴訟法第二百八十四條之一、第二百九十九\n條第一項前段，刑法第三百零六條第一項、第三百二十條第一項\n、第三百二十一條第一項第二款、第三款、第四十七條第一項、\n第五十一條第五款，刑法施行法第一條之一，判決如主文。\n本案經檢察官丙○○到庭執行職務。\n中    華    民    國    99    年    5     月    12    日\n                  刑事第四庭法  官  王慧惠\n以上正本證明與原本無異。\n如不服本判決應於收受送達後10日內向本院提出上訴書狀，並應\n敘述具體理由；其未敘述上訴理由者，應於上訴期間屆滿後20日\n內向本院補提理由書(均須按他造當事人之人數附繕本)「切勿逕\n送上級法院」。"
  },
  "characters": {
    "judges": [
      "王慧惠"
    ],
    "prosecutors": [

    ],
    "lawyers": [

    ],
    "clerks": [
      "王一芳"
    ],
    "plaintiffs": [

    ],
    "defendants": [
      "甲○○"
    ],
    "prosecutor_office": [
      "臺灣基隆地方法院檢察署檢察官"
    ],
    "creditors": [

    ],
    "debtors": [

    ],
    "judicial_associate_officer": [

    ]
  },
  "adjudged_at": "2010-05-12",
  "created_at": "2016-01-05 12:34:19",
  "updated_at": "2016-01-05 12:34:19"
}