{
  "identify": "KLD-99-訴-257-20100512-2",
  "court": {
    "name": "臺灣基隆地方法院",
    "code": "KLD"
  },
  "division": {
    "name": "刑事",
    "code": "M"
  },
  "year": 99,
  "word": "訴",
  "number": "257",
  "jcheck": "2",
  "reason": "毒品危害防制條例",
  "content": "臺灣基隆地方法院刑事判決               99年度訴字第257號\n公  訴  人  臺灣基隆地方法院檢察署檢察官\n被      告  甲○○\n上列被告因違反毒品危害防制條例案件，經檢察官提起公訴（99\n年度毒偵字第259 號），被告並為有罪陳述，本院合議庭乃裁定\n由受命法官獨任以簡式審判程序進行審理，並判決如下：\n    主  文\n甲○○施用第二級毒品，累犯，處有期徒刑月；又施用第一級\n毒品，累犯，處有期徒刑柒月。應執行有期徒刑玖月。\n    事  實\n一、前案紀錄：\n  (一)甲○○前因初犯施用毒品案件，經觀察、勒戒後，認無繼續\n    施用毒品之傾向，於民國93年9 月17日經釋放出所，並由臺\n    灣基隆地方法院檢察署檢察官於93年9 月14日，以93年度毒\n    偵字第905 、930 、1359、1504號為不起訴處分確定。\n  (二)其後，又於前揭(一)所述之觀察、勒戒執行完畢經釋放出所以\n    後之五年以內，再犯施用毒品案件（二犯施用毒品案件，施\n    用毒品時間：自93年11月間某日起，至93年12月21日止），\n    由臺灣基隆地方法院檢察署檢察官提起公訴，經本院於94年\n    2 月18日，以94年度訴字第59號判決有期徒刑八月、四月，\n    應執行有期徒刑十月確定，94年5 月5 日發監執行、95年6\n    月3 日執行完畢（構成累犯）。\n  (三)再三犯施用毒品案件（施用毒品時間：自95年12月底某日起\n    ，至96年2 月14日止），由臺灣基隆地方法院檢察署檢察官\n    提起公訴，經本院於96年4 月25日，以96年度訴字第250 號\n    判決有期徒刑十月確定；嗣中華民國九十六年罪犯減刑條例\n    於96年7 月16日公布施行，前開案件乃經依法減刑（本院96\n    年度聲減字第1100號裁定），再由檢察官指揮發監暨於96年\n    12月23日赦免餘刑，而已於96年12月23日經釋放出獄（構成\n    累犯）。\n  (四)繼而復四犯施用毒品案件（施用毒品時間：97年3 月31日）\n    ，由臺灣基隆地方法院檢察署檢察官提起公訴，經本院於97\n    年7 月25日，以97年度訴字第980 號判決有期徒刑七月確定\n    ，97年9 月8 日發監執行、98年4 月7 日執行完畢（構成累\n    犯；惟甲○○因自98年4 月8 日起，接續執行另案拘役五十\n    日，故而遲至98年5 月28日始經釋放出監）。\n二、本案事實：\n    甲○○猶不思戒除毒癮，復基於施用第二級毒品安非他命類\n    （安非他命暨甲基安非他命）之犯意，於99年1 月16日晚間\n    9 時，在基隆市○○區○○路131 巷14號住處，將安非他命\n    類置入玻璃球吸食器內燒烤使生霧化白煙再以口鼻吸食，藉\n    以施用第二級毒品安非他命類1 次。其後，復萌生施用第一\n    級毒品海洛因之犯意，於99年1 月17日上午10時，在上址，\n    將稀釋後之海洛因置入注射針筒再持以施打，藉以施用第一\n    級毒品海洛因1 次。乃為警於99年1 月18日中午12時30分，\n    在基隆市仁愛區○○○○○路口盤檢查獲，經採其尿液送驗\n    ，結果呈嗎啡（海洛因代謝後尿液檢出成份）、安非他命暨\n    甲基安非他命陽性反應。\n三、案經基隆市警察局第一分局移送臺灣基隆地方法院檢察署檢\n    察官偵查起訴。\n    理  由\n壹、程序事項\n    本案被告甲○○所犯者非為死刑、無期徒刑、最輕本刑為三\n    年以上有期徒刑之罪或高等法院管轄之第一審案件，其於準\n    備程序進行中，先就被訴事實為有罪之陳述，經告知其簡式\n    審判程序之旨，並聽取公訴人、被告之意見後，本院業已依\n    刑事訴訟法第二百七十三條之一第一項規定，裁定由受命法\n    官獨任以簡式審判程序進行本案之審理。\n貳、實體事項\n一、前揭事實業據被告甲○○於本院審理時坦承在卷；且被告為\n    警查獲而採集之尿液檢體，經送請臺灣尖端先進生技醫藥股\n    份有限公司以氣相層析質譜儀法為確認檢驗之結果，呈嗎啡\n    （海洛因代謝後尿液檢出成份）、安非他命暨甲基安非他命\n    陽性反應，此亦有臺灣尖端先進生技醫藥股份有限公司99年\n    2 月5 日濫用藥物檢驗報告1 份，暨足與上開檢驗報告相對\n    應之尿液檢體對照表1 件在卷可憑；參之以酵素免疫分析或\n    薄層定性分析等方式為初步篩檢者，檢驗結果雖有相當程度\n    偽陽性之可能，然以氣（液）相層析、質譜分析之儀器為交\n    叉確認者，檢驗結果出現偽陽性之機率則極低，因而具有公\n    信力，核足為對涉嫌人不利之認定；尤以「毒品施用後於尿\n    液、血液中可檢出之最大時限，與施用劑量、施用頻率、施\n    用方式、施用者飲水量之多寡、個人體質、代謝情況、檢體\n    收集時間點及所用檢測方法之靈敏度等因素有關，因個案而\n    異。依據Clarke's Isolation Identification of Drugs第\n    二版記載，血液中藥物之半衰期（濃度減半所需時間）分別\n    為古柯鹼0.7-1.5 小時、海洛因3 分鐘（其代謝物為嗎啡2-\n    3 小時）、嗎啡2-3 小時、大麻20-36 小時、安非他命12小\n    時（當尿液偏酸性時，為4-8 小時）、甲基安非他命9 小時\n    、Ketamine 2-4小時，而MDMA約8.49小時。一般於尿液中可\n    檢出之最大時限，古柯鹼為施用後1-4 天、海洛因2-4 天、\n    嗎啡2-4 天、大麻1-10天、安非他命1-4 天、甲基安非他命\n    1-5 天、MDMA1-4 天、MDA 1-4 天、Ketamine2-4 天。」此\n    復曾經行政院衛生署藥物食品檢驗局以92年7 月23日管檢字\n    第0920005609號函釋在案。勾稽以觀，足見被告於本院審理\n    時之任意性自白，與事實相符，堪可採信。再者，被告查有\n    如本判決事實欄一所載施用毒品之前案紀錄。觀諸卷附臺灣\n    高等法院被告前案紀錄表所載內容即明。從而，本案事證明\n    確，參照最高法院97年9 月9 日97年度第5 次刑事庭會議二\n    決議意旨、97年度臺非字第540、585號暨98年度臺非字第12\n    7、211號判決意旨，被告於初犯施用毒品案件之五年以內，\n    再犯施用毒品之犯行，堪可認定，應依法論科。\n二、論罪科刑：\n  (一)查海洛因、安非他命類分別係毒品危害防制條例所列管之第\n    一級、第二級毒品，此為該條例第二條第二項第一款、第二\n    款所明定。按犯毒品危害防制條例第十條之罪（施用毒品罪\n    ）者，檢察官應聲請法院裁定，令被告入勒戒處所觀察、勒\n    戒，經勒戒處所陳報，認受觀察、勒戒人無繼續施用毒品傾\n    向者，應即釋放，並為不起訴之處分；認有繼續施用毒品傾\n    向者，即應聲請法院裁定令入戒治處所強制戒治，俟強制戒\n    治期滿釋放，再為不起訴之處分。惟依上揭規定觀察勒戒或\n    強制戒治執行完畢釋放後，五年內再犯毒品危害防制條例第\n    十條之罪（施用毒品罪）者，檢察官即應依法追訴，毒品危\n    害防制條例第二十條第一項、第二項、第二十三條第二項分\n    別定有明文。\n  (二)核被告於初犯施用毒品案件以後之五年以內，再犯施用第一\n    級毒品海洛因、第二級毒品安非他命類（安非他命、甲基安\n    非他命）之行為如本判決事實欄二之所載，各係犯毒品危害\n    防制條例第十條第一項之施用第一級毒品罪及同條第二項之\n    施用第二級毒品罪。被告施用毒品先、後持有第一級毒品海\n    洛因、第二級毒品安非他命類（安非他命、甲基安非他命）\n    之低度行為，各應分別為施用第一級、第二級毒品之高度行\n    為所吸收，均不另論罪。\n  (三)被告所犯上開二罪，犯意各別，行為互殊，應予分論併罰。\n  (四)被告查有如本判決事實欄一(二)(三)(四)所載之犯罪科刑及刑之執\n    行情形，此有臺灣高等法院被告前案紀錄表在卷可考。乃於\n    前案有期徒刑執行完畢或受一部之執行而赦免後，五年以內\n    ，故意再犯本起最重本刑有期徒刑以上之罪，為累犯，應依\n    刑法第四十七條第一項規定，就其所犯各罪分別加重其刑。\n  (五)本院審酌被告犯罪之動機、吸食頻率、曾有施用毒品之前科\n    仍不知戒除，兼以被告犯後坦承犯行而表悛悔之犯後態度，\n    及其本案所為雖對己身健康戕害甚鉅，然其究非可與侵害他\n    人法益之犯罪行為等量齊觀，尤以之於此類「施用毒品」之\n    行為人而言，毒品危害防制條例之立法目的亦非重在嚴懲，\n    而係重在彼等「病患性」行為之矯治等一切情狀，分別量處\n    如主文所示之刑，併定其應執行之刑。\n據上論斷，應依刑事訴訟法第二百七十三條之一第一項、第二百\n九十九條第一項前段，毒品危害防制條例第二十三條第二項、第\n十條第一項、第二項，刑法第十一條前段、第四十七條第一項、\n第五十一條第五款，判決如主文。\n本案經檢察官乙○○到庭執行職務。\n中    華    民    國    99    年    5     月    12    日\n                  刑事第四庭法  官  王慧惠\n以上正本證明與原本無異。\n如不服本判決應於收受送達後10日內向本院提出上訴書狀，並應\n敘述具體理由；其未敘述上訴理由者，應於上訴期間屆滿後20日\n內向本院補提理由書(均須按他造當事人之人數附繕本)「切勿逕\n送上級法院」。\n中    華    民    國    99    年    5     月    12    日\n                            書記官  王一芳\n附錄論罪法條：\n毒品危害防制條例第10條第1 項、第2 項\n施用第一級毒品者，處6 月以上5 年以下有期徒刑。\n施用第二級毒品者，處3 年以下有期徒刑。",
  "structure": {
    "main": "甲○○施用第二級毒品，累犯，處有期徒刑月；又施用第一級\n毒品，累犯，處有期徒刑柒月。應執行有期徒刑玖月。",
    "fact": "一、前案紀錄：\n  (一)甲○○前因初犯施用毒品案件，經觀察、勒戒後，認無繼續\n    施用毒品之傾向，於民國93年9 月17日經釋放出所，並由臺\n    灣基隆地方法院檢察署檢察官於93年9 月14日，以93年度毒\n    偵字第905 、930 、1359、1504號為不起訴處分確定。\n  (二)其後，又於前揭(一)所述之觀察、勒戒執行完畢經釋放出所以\n    後之五年以內，再犯施用毒品案件（二犯施用毒品案件，施\n    用毒品時間：自93年11月間某日起，至93年12月21日止），\n    由臺灣基隆地方法院檢察署檢察官提起公訴，經本院於94年\n    2 月18日，以94年度訴字第59號判決有期徒刑八月、四月，\n    應執行有期徒刑十月確定，94年5 月5 日發監執行、95年6\n    月3 日執行完畢（構成累犯）。\n  (三)再三犯施用毒品案件（施用毒品時間：自95年12月底某日起\n    ，至96年2 月14日止），由臺灣基隆地方法院檢察署檢察官\n    提起公訴，經本院於96年4 月25日，以96年度訴字第250 號\n    判決有期徒刑十月確定；嗣中華民國九十六年罪犯減刑條例\n    於96年7 月16日公布施行，前開案件乃經依法減刑（本院96\n    年度聲減字第1100號裁定），再由檢察官指揮發監暨於96年\n    12月23日赦免餘刑，而已於96年12月23日經釋放出獄（構成\n    累犯）。\n  (四)繼而復四犯施用毒品案件（施用毒品時間：97年3 月31日）\n    ，由臺灣基隆地方法院檢察署檢察官提起公訴，經本院於97\n    年7 月25日，以97年度訴字第980 號判決有期徒刑七月確定\n    ，97年9 月8 日發監執行、98年4 月7 日執行完畢（構成累\n    犯；惟甲○○因自98年4 月8 日起，接續執行另案拘役五十\n    日，故而遲至98年5 月28日始經釋放出監）。\n二、本案事實：\n    甲○○猶不思戒除毒癮，復基於施用第二級毒品安非他命類\n    （安非他命暨甲基安非他命）之犯意，於99年1 月16日晚間\n    9 時，在基隆市○○區○○路131 巷14號住處，將安非他命\n    類置入玻璃球吸食器內燒烤使生霧化白煙再以口鼻吸食，藉\n    以施用第二級毒品安非他命類1 次。其後，復萌生施用第一\n    級毒品海洛因之犯意，於99年1 月17日上午10時，在上址，\n    將稀釋後之海洛因置入注射針筒再持以施打，藉以施用第一\n    級毒品海洛因1 次。乃為警於99年1 月18日中午12時30分，\n    在基隆市仁愛區○○○○○路口盤檢查獲，經採其尿液送驗\n    ，結果呈嗎啡（海洛因代謝後尿液檢出成份）、安非他命暨\n    甲基安非他命陽性反應。\n三、案經基隆市警察局第一分局移送臺灣基隆地方法院檢察署檢\n    察官偵查起訴。",
    "reason": "壹、程序事項\n    本案被告甲○○所犯者非為死刑、無期徒刑、最輕本刑為三\n    年以上有期徒刑之罪或高等法院管轄之第一審案件，其於準\n    備程序進行中，先就被訴事實為有罪之陳述，經告知其簡式\n    審判程序之旨，並聽取公訴人、被告之意見後，本院業已依\n    刑事訴訟法第二百七十三條之一第一項規定，裁定由受命法\n    官獨任以簡式審判程序進行本案之審理。\n貳、實體事項\n一、前揭事實業據被告甲○○於本院審理時坦承在卷；且被告為\n    警查獲而採集之尿液檢體，經送請臺灣尖端先進生技醫藥股\n    份有限公司以氣相層析質譜儀法為確認檢驗之結果，呈嗎啡\n    （海洛因代謝後尿液檢出成份）、安非他命暨甲基安非他命\n    陽性反應，此亦有臺灣尖端先進生技醫藥股份有限公司99年\n    2 月5 日濫用藥物檢驗報告1 份，暨足與上開檢驗報告相對\n    應之尿液檢體對照表1 件在卷可憑；參之以酵素免疫分析或\n    薄層定性分析等方式為初步篩檢者，檢驗結果雖有相當程度\n    偽陽性之可能，然以氣（液）相層析、質譜分析之儀器為交\n    叉確認者，檢驗結果出現偽陽性之機率則極低，因而具有公\n    信力，核足為對涉嫌人不利之認定；尤以「毒品施用後於尿\n    液、血液中可檢出之最大時限，與施用劑量、施用頻率、施\n    用方式、施用者飲水量之多寡、個人體質、代謝情況、檢體\n    收集時間點及所用檢測方法之靈敏度等因素有關，因個案而\n    異。依據Clarke's Isolation Identification of Drugs第\n    二版記載，血液中藥物之半衰期（濃度減半所需時間）分別\n    為古柯鹼0.7-1.5 小時、海洛因3 分鐘（其代謝物為嗎啡2-\n    3 小時）、嗎啡2-3 小時、大麻20-36 小時、安非他命12小\n    時（當尿液偏酸性時，為4-8 小時）、甲基安非他命9 小時\n    、Ketamine 2-4小時，而MDMA約8.49小時。一般於尿液中可\n    檢出之最大時限，古柯鹼為施用後1-4 天、海洛因2-4 天、\n    嗎啡2-4 天、大麻1-10天、安非他命1-4 天、甲基安非他命\n    1-5 天、MDMA1-4 天、MDA 1-4 天、Ketamine2-4 天。」此\n    復曾經行政院衛生署藥物食品檢驗局以92年7 月23日管檢字\n    第0920005609號函釋在案。勾稽以觀，足見被告於本院審理\n    時之任意性自白，與事實相符，堪可採信。再者，被告查有\n    如本判決事實欄一所載施用毒品之前案紀錄。觀諸卷附臺灣\n    高等法院被告前案紀錄表所載內容即明。從而，本案事證明\n    確，參照最高法院97年9 月9 日97年度第5 次刑事庭會議二\n    決議意旨、97年度臺非字第540、585號暨98年度臺非字第12\n    7、211號判決意旨，被告於初犯施用毒品案件之五年以內，\n    再犯施用毒品之犯行，堪可認定，應依法論科。\n二、論罪科刑：\n  (一)查海洛因、安非他命類分別係毒品危害防制條例所列管之第\n    一級、第二級毒品，此為該條例第二條第二項第一款、第二\n    款所明定。按犯毒品危害防制條例第十條之罪（施用毒品罪\n    ）者，檢察官應聲請法院裁定，令被告入勒戒處所觀察、勒\n    戒，經勒戒處所陳報，認受觀察、勒戒人無繼續施用毒品傾\n    向者，應即釋放，並為不起訴之處分；認有繼續施用毒品傾\n    向者，即應聲請法院裁定令入戒治處所強制戒治，俟強制戒\n    治期滿釋放，再為不起訴之處分。惟依上揭規定觀察勒戒或\n    強制戒治執行完畢釋放後，五年內再犯毒品危害防制條例第\n    十條之罪（施用毒品罪）者，檢察官即應依法追訴，毒品危\n    害防制條例第二十條第一項、第二項、第二十三條第二項分\n    別定有明文。\n  (二)核被告於初犯施用毒品案件以後之五年以內，再犯施用第一\n    級毒品海洛因、第二級毒品安非他命類（安非他命、甲基安\n    非他命）之行為如本判決事實欄二之所載，各係犯毒品危害\n    防制條例第十條第一項之施用第一級毒品罪及同條第二項之\n    施用第二級毒品罪。被告施用毒品先、後持有第一級毒品海\n    洛因、第二級毒品安非他命類（安非他命、甲基安非他命）\n    之低度行為，各應分別為施用第一級、第二級毒品之高度行\n    為所吸收，均不另論罪。\n  (三)被告所犯上開二罪，犯意各別，行為互殊，應予分論併罰。\n  (四)被告查有如本判決事實欄一(二)(三)(四)所載之犯罪科刑及刑之執\n    行情形，此有臺灣高等法院被告前案紀錄表在卷可考。乃於\n    前案有期徒刑執行完畢或受一部之執行而赦免後，五年以內\n    ，故意再犯本起最重本刑有期徒刑以上之罪，為累犯，應依\n    刑法第四十七條第一項規定，就其所犯各罪分別加重其刑。\n  (五)本院審酌被告犯罪之動機、吸食頻率、曾有施用毒品之前科\n    仍不知戒除，兼以被告犯後坦承犯行而表悛悔之犯後態度，\n    及其本案所為雖對己身健康戕害甚鉅，然其究非可與侵害他\n    人法益之犯罪行為等量齊觀，尤以之於此類「施用毒品」之\n    行為人而言，毒品危害防制條例之立法目的亦非重在嚴懲，\n    而係重在彼等「病患性」行為之矯治等一切情狀，分別量處\n    如主文所示之刑，併定其應執行之刑。\n據上論斷，應依刑事訴訟法第二百七十三條之一第一項、第二百\n九十九條第一項前段，毒品危害防制條例第二十三條第二項、第\n十條第一項、第二項，刑法第十一條前段、第四十七條第一項、\n第五十一條第五款，判決如主文。\n本案經檢察官乙○○到庭執行職務。\n中    華    民    國    99    年    5     月    12    日\n                  刑事第四庭法  官  王慧惠\n以上正本證明與原本無異。\n如不服本判決應於收受送達後10日內向本院提出上訴書狀，並應\n敘述具體理由；其未敘述上訴理由者，應於上訴期間屆滿後20日\n內向本院補提理由書(均須按他造當事人之人數附繕本)「切勿逕\n送上級法院」。"
  },
  "characters": {
    "judges": [
      "王慧惠"
    ],
    "prosecutors": [

    ],
    "lawyers": [

    ],
    "clerks": [
      "王一芳"
    ],
    "plaintiffs": [

    ],
    "defendants": [
      "甲○○"
    ],
    "prosecutor_office": [
      "臺灣基隆地方法院檢察署檢察官"
    ],
    "creditors": [

    ],
    "debtors": [

    ],
    "judicial_associate_officer": [

    ]
  },
  "adjudged_at": "2010-05-12",
  "created_at": "2016-01-05 12:33:53",
  "updated_at": "2016-01-05 12:33:53"
}