{
  "identify": "KLD-99-基交簡-240-20100512-1",
  "court": {
    "name": "臺灣基隆地方法院",
    "code": "KLD"
  },
  "division": {
    "name": "刑事",
    "code": "M"
  },
  "year": 99,
  "word": "基交簡",
  "number": "240",
  "jcheck": "1",
  "reason": "公共危險",
  "content": "臺灣基隆地方法院刑事簡易判決       99年度基交簡字第240號\n聲  請  人  臺灣基隆地方法院檢察署檢察官\n被      告  乙○○\n上列被告因公共危險案件，經檢察官聲請以簡易判決處刑（99年\n度偵字第1414號），本院判決如下：\n    主      文\n乙○○服用酒類，不能安全駕駛動力交通工具而駕駛，處拘役\n拾日，如易科罰金，以新臺幣壹仟元折算壹日。緩刑貳年。\n    事實及理由\n一、本件犯罪事實、證據及應適用之法條，均引用檢察官聲請簡\n    易判決處刑書（以下簡稱「聲請書」）之記載（詳如附件）\n    ，並補充如下：\n    按一般人飲酒後之呼氣酒精濃度值倘逾越0.55mg/L標準，即\n    明顯可見其人平衡感、注意力、反應力、操控力、穩定性、\n    感知能力及駕駛能力之衰減或降低；乃被告為警查獲後，經\n    警施以酒精濃度測試結果，其呼氣酒精濃度值竟達0.56mg/L\n    （即每公升0.56毫克），觀諸卷附酒精測定值表（即酒精濃\n    度檢測單）所載內容自明；兼以被告或查有「駛入對向車道\n    」等異常駕駛行為，或命其施作汽機車駕駛人酒後生理平衡\n    檢測而不能完成「閉雙眼，30秒內朗誦阿拉伯數字，由1001\n    到1030」等施測項目。此亦有測試觀察紀錄表、汽機車駕駛\n    人酒後生理協調平衡檢測紀錄表各1 件在卷足考。互核上情\n    以觀，堪認被告飲用酒類以後，確已處於不能安全駕駛之狀\n    態無訛。\n二、本院審酌被告乙○○明知酒後駕車在道路上行駛，對一般往\n    來之公眾及駕駛人自身具有高度危險性，仍執意酒後駕車，\n    既漠視自身安危，更枉顧公眾安全；並考量被告為警依法施\n    測所得之酒精濃度值達0.56mg/L，本次幸未肇致車禍實害，\n    兼衡量被告核無酒後不能安全駕駛而經法院判處罪刑確定之\n    相類素行（參見卷附臺灣高等法院被告前案紀錄表），暨其\n    坦承己過而表悛悔之犯後態度等一切情狀，量處如主文所示\n    之刑，併諭知易科罰金之折算標準。\n三、末查，被告前未曾因故意犯罪受有期徒刑以上刑之宣告，有\n    臺灣高等法院被告前案紀錄表在卷可參，本次僅因一時失慮\n    ，致罹刑典，犯後並已深表悔悟，經此科刑教訓，信當知所\n    警惕，而無再犯之虞，因認所受刑之宣告，以暫不執行為適\n    當，爰依刑法第七十四條第一項第一款規定，併宣告緩刑二\n    年，用啟自新，以勵來茲。\n四、依刑事訴訟法第四百四十九條第一項前段、第四百五十四條\n    第二項，刑法第一百八十五條之三、第四十一條第一項前段\n    、第七十四條第一項第一款，刑法施行法第一條之一，逕以\n    簡易判決處刑如主文。\n如不服本判決，得自收受送達之日起10日內，向本院提起上訴。\n中    華    民    國    99    年    5     月    12    日\n                  基隆簡易庭法  官  王慧惠\n以上正本證明與原本無異。\n如不服本判決，應於判決送達後10日內，向本院提出上訴書狀，\n敘述上訴理由，上訴於本院合議庭，並按他造當事人之人數附具\n繕本。\n中    華    民    國    99    年    5     月    12    日\n                            書記官  王一芳\n附錄論罪法條：\n刑法第185 條之3\n服用毒品、麻醉藥品、酒類或其他相類之物，不能安全駕駛動力\n交通工具而駕駛者，處1 年以下有期徒刑、拘役或科或併科15萬\n元以下罰金。\n附件：\n臺灣基隆地方法院檢察署檢察官聲請簡易判決處刑書\n                                      99年度偵字第1414號\n    被      告  乙○○  男  41歲（民國○○年○月○○日生）\n                        住臺北縣汐止市○○路35巷15弄8號2\n                        樓\n                        國民身分證統一編號：Ｚ000000000號\n上列被告因公共危險案件，業經偵查終結，認為宜聲請以簡易判\n決處刑，茲將犯罪事實及證據並所犯法條分敘如下：\n      犯罪事實\n一、乙○○明知服用酒類過量會導致反應遲鈍、注意力減低之結\n    果，此時若駕駛動力交通工具行駛於道路上，肇事之機率及\n    危險性均遠較正常人為高，仍於民國99年3月2日15時許，在\n    基隆市○○路友人家中飲用高梁酒2杯，其後已達反應遲緩\n    、注意能力減低，而不能安全駕駛動力交通工具之程度，猶\n    駕駛車牌號碼276-CWJ號機車上路欲返家。嗣於同日16時45\n    分許途經基隆市○○街與精一路口時，因逆向行駛為警攔查\n    ，經測試乙○○呼氣中酒精含量為每公升0.56毫克。\n二、案經基隆市警察局第一分局報告偵辦。\n          證據並所犯法條\n一、證據：（一）被告乙○○之自白，（二）酒精呼氣測試紀錄\n    1紙，（三）刑法第185條之3案件測試觀察紀錄表，（四）\n    汽機車駕駛人酒後生理協調平衡檢測紀錄表。\n二、所犯法條：刑法第185條之3公共危險罪嫌。\n三、依刑事訴訟法第451條第1項聲請逕以簡易判決處刑。\n    此    致\n臺灣基隆地方法院基隆簡易庭\n中    華    民    國    99    年    5     月    5     日\n                          檢  察  官    甲  ○  ○\n上正本證明與原本無異\n中    華    民    國    99    年    5     月    7     日\n                          書  記  官    魏  書  崧\n參考法條：\n中華民國刑法第185條之3\n服用毒品、麻醉藥品、酒類或其他相類之物，不能安全駕駛動力\n交通工具而駕駛者，處1年以下有期徒刑、拘役或科或併科15萬\n元以下罰金。\n附記事項：\n本件係依刑事訴訟法簡易程式辦理，法院簡易庭得不傳喚被告、\n輔佐人、告訴人、告發人等出庭即以簡易判決處刑；被告、被害\n人、告訴人等對告訴乃論案件如已達成民事和解而要撤回告訴或\n對非告訴乃論案件認有受傳喚到庭陳述意見之必要時，請即另以\n書狀向簡易法庭陳述或請求傳訊。",
  "structure": {
    "main": "乙○○服用酒類，不能安全駕駛動力交通工具而駕駛，處拘役\n拾日，如易科罰金，以新臺幣壹仟元折算壹日。緩刑貳年。",
    "fact": "一、本件犯罪事實、證據及應適用之法條，均引用檢察官聲請簡\n    易判決處刑書（以下簡稱「聲請書」）之記載（詳如附件）\n    ，並補充如下：\n    按一般人飲酒後之呼氣酒精濃度值倘逾越0.55mg/L標準，即\n    明顯可見其人平衡感、注意力、反應力、操控力、穩定性、\n    感知能力及駕駛能力之衰減或降低；乃被告為警查獲後，經\n    警施以酒精濃度測試結果，其呼氣酒精濃度值竟達0.56mg/L\n    （即每公升0.56毫克），觀諸卷附酒精測定值表（即酒精濃\n    度檢測單）所載內容自明；兼以被告或查有「駛入對向車道\n    」等異常駕駛行為，或命其施作汽機車駕駛人酒後生理平衡\n    檢測而不能完成「閉雙眼，30秒內朗誦阿拉伯數字，由1001\n    到1030」等施測項目。此亦有測試觀察紀錄表、汽機車駕駛\n    人酒後生理協調平衡檢測紀錄表各1 件在卷足考。互核上情\n    以觀，堪認被告飲用酒類以後，確已處於不能安全駕駛之狀\n    態無訛。\n二、本院審酌被告乙○○明知酒後駕車在道路上行駛，對一般往\n    來之公眾及駕駛人自身具有高度危險性，仍執意酒後駕車，\n    既漠視自身安危，更枉顧公眾安全；並考量被告為警依法施\n    測所得之酒精濃度值達0.56mg/L，本次幸未肇致車禍實害，\n    兼衡量被告核無酒後不能安全駕駛而經法院判處罪刑確定之\n    相類素行（參見卷附臺灣高等法院被告前案紀錄表），暨其\n    坦承己過而表悛悔之犯後態度等一切情狀，量處如主文所示\n    之刑，併諭知易科罰金之折算標準。\n三、末查，被告前未曾因故意犯罪受有期徒刑以上刑之宣告，有\n    臺灣高等法院被告前案紀錄表在卷可參，本次僅因一時失慮\n    ，致罹刑典，犯後並已深表悔悟，經此科刑教訓，信當知所\n    警惕，而無再犯之虞，因認所受刑之宣告，以暫不執行為適\n    當，爰依刑法第七十四條第一項第一款規定，併宣告緩刑二\n    年，用啟自新，以勵來茲。\n四、依刑事訴訟法第四百四十九條第一項前段、第四百五十四條\n    第二項，刑法第一百八十五條之三、第四十一條第一項前段\n    、第七十四條第一項第一款，刑法施行法第一條之一，逕以\n    簡易判決處刑如主文。\n如不服本判決，得自收受送達之日起10日內，向本院提起上訴。",
    "reason": "一、本件犯罪事實、證據及應適用之法條，均引用檢察官聲請簡\n    易判決處刑書（以下簡稱「聲請書」）之記載（詳如附件）\n    ，並補充如下：\n    按一般人飲酒後之呼氣酒精濃度值倘逾越0.55mg/L標準，即\n    明顯可見其人平衡感、注意力、反應力、操控力、穩定性、\n    感知能力及駕駛能力之衰減或降低；乃被告為警查獲後，經\n    警施以酒精濃度測試結果，其呼氣酒精濃度值竟達0.56mg/L\n    （即每公升0.56毫克），觀諸卷附酒精測定值表（即酒精濃\n    度檢測單）所載內容自明；兼以被告或查有「駛入對向車道\n    」等異常駕駛行為，或命其施作汽機車駕駛人酒後生理平衡\n    檢測而不能完成「閉雙眼，30秒內朗誦阿拉伯數字，由1001\n    到1030」等施測項目。此亦有測試觀察紀錄表、汽機車駕駛\n    人酒後生理協調平衡檢測紀錄表各1 件在卷足考。互核上情\n    以觀，堪認被告飲用酒類以後，確已處於不能安全駕駛之狀\n    態無訛。\n二、本院審酌被告乙○○明知酒後駕車在道路上行駛，對一般往\n    來之公眾及駕駛人自身具有高度危險性，仍執意酒後駕車，\n    既漠視自身安危，更枉顧公眾安全；並考量被告為警依法施\n    測所得之酒精濃度值達0.56mg/L，本次幸未肇致車禍實害，\n    兼衡量被告核無酒後不能安全駕駛而經法院判處罪刑確定之\n    相類素行（參見卷附臺灣高等法院被告前案紀錄表），暨其\n    坦承己過而表悛悔之犯後態度等一切情狀，量處如主文所示\n    之刑，併諭知易科罰金之折算標準。\n三、末查，被告前未曾因故意犯罪受有期徒刑以上刑之宣告，有\n    臺灣高等法院被告前案紀錄表在卷可參，本次僅因一時失慮\n    ，致罹刑典，犯後並已深表悔悟，經此科刑教訓，信當知所\n    警惕，而無再犯之虞，因認所受刑之宣告，以暫不執行為適\n    當，爰依刑法第七十四條第一項第一款規定，併宣告緩刑二\n    年，用啟自新，以勵來茲。\n四、依刑事訴訟法第四百四十九條第一項前段、第四百五十四條\n    第二項，刑法第一百八十五條之三、第四十一條第一項前段\n    、第七十四條第一項第一款，刑法施行法第一條之一，逕以\n    簡易判決處刑如主文。\n如不服本判決，得自收受送達之日起10日內，向本院提起上訴。"
  },
  "characters": {
    "judges": [
      "王慧惠"
    ],
    "prosecutors": [

    ],
    "lawyers": [

    ],
    "clerks": [
      "王一芳"
    ],
    "plaintiffs": [

    ],
    "defendants": [
      "乙○○",
      "乙○○  男  41歲（民國○○年○月○○日生）"
    ],
    "prosecutor_office": [
      "臺灣基隆地方法院檢察署檢察官"
    ],
    "creditors": [

    ],
    "debtors": [

    ],
    "judicial_associate_officer": [

    ]
  },
  "adjudged_at": "2010-05-12",
  "created_at": "2016-01-05 12:34:27",
  "updated_at": "2016-01-05 12:34:27"
}