{
  "identify": "KSH-98-上重訴-23-20100105-1",
  "court": {
    "name": "臺灣高等法院",
    "code": "KSH"
  },
  "division": {
    "name": "刑事",
    "code": "M"
  },
  "year": 98,
  "word": "上重訴",
  "number": "23",
  "jcheck": "1",
  "reason": "常業詐欺",
  "content": "臺灣高等法院高雄分院刑事判決        98年度上重訴字第23號\n上  訴  人  臺灣高雄地方法院檢察署檢察官\n被      告  戊○○\n            甲ｕ○\n            甲ｄ○\n            乙ｆ○\n            甲辛○\n            乙ｈ○\n            申○○\n            乙Ｘ○\n            未○○\n            甲ｆ○\n上開被告六人\n共同選任辯護人  歐陽珮律師\n                張清富律師\n被      告  甲ｗ○\n            午○○\n            甲ｖ○\n            Ｉ○○\n                      樓之1\n            甲ｂ○\n            乙黃○\n            Ｘ○○\n上開被告七人\n共同選任辯護人  邱明政律師\n被      告  ｈ○○\n上開  被告\n選任辯護人      郭家祺律師\n被      告  乙丙○\n            乙Ｆ○\n            乙地○\n            Ｐ○○\n            甲Ｂ○\n            乙Ｒ○\n            甲ｓ○\n            乙Ｉ○\n            Ｌ○○\n            乙ｋ○\n            甲Ｉ○\n            甲Ｊ○\n            ｍ○○\n            Ｊ○○\n            乙子○\n            甲子○\n            Ｃ○○\n            乙Ｇ○\n            Ｍ○○\n            乙Ｃ○\n                      之1\n            甲Ｒ○\n            甲ｍ○\n            甲Ｐ○\n            Ｎ○○\n            ａ○○\n            乙Ｄ○○\n上列上訴人因被告等常業詐欺案件，不服臺灣高雄地方法院95年\n度重訴字第57號中華民國98年7 月30日第一審判決（起訴案號：\n臺灣高雄地方法院檢察署94年度偵字第13441 、14546 、15270\n、19560 、23929 號、95年度偵緝字第368 號），提起上訴，本\n院判決如下：\n    主  文\n上訴駁回。\n    理  由\n一、公訴意旨略以：\n(一)、被告戊○○係海閣林休閒渡假酒店股份有限公司（下稱海閣\n    林公司）之董事長，該公司前身為翻天創新國際股份有限公\n    司（下稱翻天創新公司），被告甲ｕ○係戊○○之秘書、顏\n    廉埕（原名顏銘震）、甲ｄ○係該公司之總經理、甲辛○、\n    乙ｈ○、乙地○係該公司之協理、申○○、乙Ｆ○係該公司\n    之經理、乙丙○係該公司之董事長特助（負責財務）、Ｐ○\n    ○（原名吳俊德）、甲Ｂ○係該公司之業務主任、乙Ｒ○係\n    該公司之襄理、甲ｗ○、午○○（原名史雅茜）、甲ｓ○、\n    蔡幸（原名蔡宜庭）、Ｌ○○、乙ｋ○、甲Ｉ○、甲Ｊ○\n    、林宥吟（原名林詩怡）、乙Ｘ○、Ｊ○○、乙子○（原名\n    黃彩惠）、甲ｖ○（原名馮志群）、未○○（原名史恆華）\n    、甲子○、Ｉ○○、Ｃ○○、ｈ○○、乙Ｇ○、乙Ｄ○○、\n    甲ｆ○、乙Ｃ○、甲ｂ○、甲Ｒ○、乙黃○、甲ｍ○、甲Ｐ\n    ○、Ｎ○○、Ｘ○○、ａ○○（原名李裙鳳）、Ｍ○○，均\n    係該公司之各級業務員（對外名稱為「專員」或「主任」，\n    下稱戊○○等44人）。\n(二)、被告戊○○等44人以海閣林公司名義，先動用少數資金在臺\n    東縣綠島鄉（下稱「綠島」）購得依法不得建造旅館之土地\n    ，共計建地3 筆、農地（應係「旱地」，詳後述）8 筆，再\n    以集合住宅的名義申請建造執照，隨即以在綠島投資興建五\n    星級休閒渡假大飯店為幌子，而渠等均明知海閣林公司僅取\n    得集合住宅建造執照，自始至終無法取得臺東縣政府所核發\n    之合法旅館使用執照，竟仍共同基於意圖為自己不法所有之\n    常業詐欺犯意聯絡，由戊○○總管公司業務，甲ｕ○擔任秘\n    書幫忙管理，乙丙○負責財務，顏銘震、甲ｄ○、甲辛○、\n    乙ｈ○、乙地○、申○○、乙Ｆ○負責公司內部各級幹部之\n    訓練、考核與管理，並安排業務員至婚友社或上網交友，吳\n    俊德、甲Ｂ○、乙Ｒ○負責對客戶說明，自民國91年4 月間\n    起，由各級業務員至婚友社或上網交友，以想要和對方交往\n    為藉口，隱瞞沒有合法旅館建築執照之事實，不斷遊說，而\n    向不知情之投資人誘騙投資海閣林休閒渡假酒店，每一投資\n    單位為新臺幣（下同）13萬5 千元，業務員（沒有底薪）每\n    賣出1 單位可抽取獎金（專員為9 千至1 萬元不等，主任為\n    1 萬3 千元），另總經理、協理、經理，依階級可分別抽取\n    3 千元至2 萬3 千元不等之獎金，所收入之款項均未經過合\n    格之會計師依實際收支情形確實作帳，除扣掉管銷以及上開\n    業務獎金之外，均流入戊○○私人帳戶內，且海閣林公司位\n    於高雄市新興區○○○路251 號12樓之1 的辦公處所等大批\n    房地產均登記在戊○○私人名下。嗣因該所謂五星級休閒渡\n    假大飯店之營業一直遙遙無期，且待投資被害人繳完款項後\n    ，業務員隨即失聯，投資之被害人始知受騙，截至94年6 月\n    8 日經檢察官指揮警方查獲為止，共有被害人1,336 人投資\n    3,654 個單位，詐得金額總計4 億9329萬元，已查出被害人\n    有ｒ○○等196 人（被害人姓名、投資單位數、被詐騙金額\n    ，詳如附表一、二所示）。\n(三)、嗣於94年6 月8 日經檢察官指揮內政部警政署刑事警察局偵\n    八隊二組與高雄縣政府警察局刑事警察大隊，至海閣林休閒\n    渡假酒店股份有限公司位於高雄市新興區○○○路251 號12\n    樓之1 、高雄市前金區○○○路235 號8 樓之4 等處所實施\n    搜索，扣得附表三「證據索引」甲、乙所示之物證及書證，\n    因認被告戊○○等人共同涉犯修正前刑法第340 條之常業詐\n    欺罪嫌。\n二、按犯罪事實，應依證據認定之，無證據不得認定犯罪事實；\n    又不能證明被告犯罪者，應諭知無罪之判決；刑事訴訟法第\n    154 條第2 項、第301 條第1 項各有明文。次按認定不利於\n    被告之證據須依積極證據，苟積極證據不足為不利於被告事\n    實之認定，即應為有利被告之認定，更不必有何有利之證據\n    ；又犯罪事實之認定，應憑證據，如無相當之證據，或證據\n    不足以證明，自不得以推測或擬制之方法，以為裁判之基礎\n    （最高法院30年上字第816 號、40年台上字第86號判例意旨\n    可參）；另按刑事訴訟法第161 條規定：檢察官就被告犯罪\n    事實，應負舉證責任，並指出證明之方法。因此，檢察官對\n    於起訴之犯罪事實，應負提出證據及說服之實質舉證責任。\n    倘其所提出之證據，不足為被告有罪之積極證明，或其闡明\n    之證明方法，無從說服法官以形成被告有罪之心證，基於無\n    罪推定之原則，自應為被告無罪判決之諭知（最高法院92年\n    台上字第128 號判例要旨足佐）。另按刑法第339 條第1 項\n    詐欺罪之成立，須行為人於主觀上有為自己或第三人不法所\n    有之意圖，客觀上有施用詐術，使對方陷於錯誤致為財產上\n    之處分行為，始足當之；若其所用方法，不能認為詐術，亦\n    不致使人陷於錯誤，即不構成該罪（最高法院46年台上字第\n    260 號判例參照）。至於民事關係當事人間，債務人於債之\n    關係成立後，如有未依債之本旨履行民事債務之情形，在一\n    般社會生活經驗上可能之原因甚多，而刑事被告依法不負自\n    證無罪之義務，若別無足以證明被告自始意圖不法所有之積\n    極證據，亦僅能認係民事債權債務糾紛，不得僅憑被告事後\n    不履行債務之客觀事態，而推定被告自始具有不法所有之詐\n    欺意圖。\n三、證據能力：\n(一)、後述證人等各警詢陳述，其性質雖屬傳聞證據，惟檢察官、\n    被告、辯護人已於本院審理調查上開筆錄予以提示並告以要\n    旨時，由檢察官、被告、辯護人表示意見，當事人或辯護人\n    已知上述筆錄乃傳聞證據，而就此證據能力均表示無意見，\n    即同意作為證據，且本院審酌上開筆錄作成時，較無人情施\n    壓或干擾，亦無不當取供之情形，認為以之作為本案之證據\n    亦屬適當，依刑事訴訟法第159 條之5 第1 項規定，自得為\n    證據。\n(二)、後述證人等各於偵查中經具結之陳述，並未曾提及檢察官在\n    偵查時有不法取供之情形，且亦無證據足以證明證人上開陳\n    述有顯不可信之情況，被告或其辯護人於本院復未再聲請詰\n    問何證人，而部分證人各於原審復已到庭接受詰問，足可認\n    定業已保障被告詰問權，依刑事訴訟法第159 條之1 第2 項\n    規定，自得為證據。\n(三)、後述引用之其他卷附書證，而屬於書面之傳聞證據部分，因\n    檢察官、被告、辯護人於本院審理調查上開書證予以提示並\n    告以要旨時，由檢察官、被告、辯護人表示意見，當事人、\n    辯護人已知此等書證乃傳聞證據，而就此證據能力均表示無\n    意見，亦未聲明異議，即視為同意作為證據，且本院審酌該\n    書證作成時之客觀情狀，並無證據證明此等書證有何遭變造\n    或偽造情事，認為以之作為本件論証之證據，均與待證事實\n    具有關聯性，作為本案之證據亦屬適當，依刑事訴訟法第15\n    9 條之5 第1 項規定，均認得為證據。\n四、公訴意旨認被告戊○○等44人共同涉犯常業詐欺罪嫌，係以\n    如附表三「證據索引」所示之「物證」、「書證」、「人證\n    」及「被告之供述」等情為據，然被告戊○○等44人於原審\n    均否認上開被訴犯行，辯詞各略如下：\n1 、戊○○：\n    我是海閣林休閒渡假酒店負責人，目前海閣林公司已經結案\n    ，現在公司改為風緻開發，負責人為顏銘震。內勤人員底薪\n    1 萬8 千元，全勤再加2 千元，每月內勤薪水約45萬元，業\n    務專員招攬投資獎金每筆1 萬元，主任每筆獎金1 萬3 千元\n    ，襄理每筆獎金1 萬5 千元，副理每筆獎金1 萬8 千元，經\n    理每筆獎金2 萬元，協理每筆獎金2 萬5 千元，副理每筆獎\n    金3 萬5 千元，董事長每筆獎金5 萬元。我沒有底薪，獎金\n    5 萬元還要扣掉間差，實際合夥人每投資1 單位13萬5 千元\n    ，只有8 萬5 千元存入公司帳戶。公司以海閣林休閒渡假酒\n    店在綠島興建五星級休閒渡假酒店對外招商，總共是6 千個\n    單位，實際招商約3 千6 百個單位左右，每單位13萬5 千元\n    ，募得投資金額大概4 億8 千多萬。一開始有申請旅館建照\n    ，因旅館未緊鄰八米道路等因素，被台東縣政府核退多次，\n    最後因時間緊迫，公司為把飯店蓋好，不得已先申請集合住\n    宅之建照，並動工興建目的是為了給合夥人一個交代，公司\n    有把握能變更成旅館用途並取得合法之使用執照。業務員招\n    攬投資的錢以現金交給公司會計或匯入公司帳戶，所募得4\n    億8 千多萬之款項用於黃復杰侵占公司7200萬元；被勒贖65\n    0 萬元；工程與投資約2 億元；購買公司資產約2 千萬元；\n    業務獎金已發放1 億8 千萬元；內勤職員薪資約1 千5 百萬\n    元；水電、租金開銷約3 千5 百萬元；購買綠島之土地約36\n    50萬元，總計約4 億8 千萬元。海閣林有陳列以一棟地上5\n    層地下1 層的樣品屋。我們計畫在綠島開設旅館，因資金不\n    足，所以對外募集資金我們有宣導，也跟業務員講一定要讓\n    客戶知道公司建築飯店的執照還沒發放下來，也很努力聲請\n    換發旅館執照。婚友中心只是客源其中之一的管道，也有從\n    親友、網路上找來，公司業務員大部分是未婚女生，所以從\n    婚友中心的客戶比例較高，只要客戶有錢、有意願我們會解\n    釋的很清楚。當時買農地沒辦法登記在公司名下，因公司要\n    有農業相關業務才能登記，所以我想先登記我名下，待房地\n    蓋好後再移轉登記公司名下。和被害人和解人數大概33人，\n    和解金額以投資款3 成為基準。公司財務乙丙○負責，顏銘\n    震是台中地區代理商，甲ｄ○是公司高階主管。現在進度與\n    3 年前一樣，旅館的使用執照已經核發，內部還沒開始裝潢\n    ，只做天花板、防火設備、門窗等，迄今仍無法營運還是因\n    資金不足，陸續與人和解，且綠島天氣不好，颱風後很多設\n    備要維修，沒有多餘的錢繼續蓋飯店。若不發放業務獎金，\n    對於業務的推展勢必無法推展，當初就是不足所以一定要先\n    發放獎金，才會再有資金進來，工程才能繼續進行等語（出\n    處：警卷(一)，P1-P9 、P11-P13 、偵五卷，P16 、P187-P18\n    9 、P231、偵七卷，P32-P34 、偵九卷，P11 -P12、偵十三\n    卷，P17-P18 、偵十九卷，P102-P114 、偵二十卷，P184、\n    P269-P2 73聲一卷，P4-P9 、P11-P1 3、抗一卷，P18-P21\n    、原審一卷，P280、P321、原審二卷，P277-P278 、原審四\n    卷，P193-P195 、P208反面）。\n2 、童微庭：\n    海閣林休閒渡假酒店股份有限公司負責人是戊○○，我們是\n    男女朋友，92年初進入海閣林公司擔任業務助理，當時已推\n    出綠島的業務，現擔任公司秘書，負責接待訪客、訂飲料或\n    便當及幫董事長處理一些雜務。公司有向政府登記營業執照\n    ，資本額應該是600 萬元，不清楚公司帳戶內之資金與戊○\n    ○私人帳戶內金錢之流通情形，我作秘書只有年終獎金，沒\n    辦法分紅利，業務員分多少紅利我也不清楚。知道公司在綠\n    島有蓋休閒渡假酒店，92年3 、4 月間公司開始以開發綠島\n    休閒渡假酒店為名對外募資，共募得2400個單位，每單位13\n    萬5 千元，約3 億2 千4 百萬元資金，資金應是存入公司帳\n    戶，由財務部徐淑瑩專責管理。公司在綠島購得土地約8筆\n    或11筆，海閣林休閒渡假酒店股份有限公司以戊○○的集合\n    住宅名義申請建照，但它是以休閒飯店的模式下去設計的。\n    業務員的銷售手法我不清楚。在公司我沒參與資金往來，也\n    沒遊說客戶投資。據我所知海閣林財務由董事長和會計人員\n    全權處理，財務是乙丙○等語（出處：警卷(一)，P35-P41 、\n    P43-P44 、偵四卷，P4-P5 、原審一卷，P321-P322 、原審\n    四卷，P195反面-P196 ）。\n3 、甲ｄ○：\n    海閣林休閒渡假酒店股份有限公司負責人是戊○○，我於92\n    年9 月至93年12月擔任高雄總公司副總經理，執掌人事考核\n    、協助新進人員應徵及參加公司會議，我管業務，負責一些\n    業務及與客戶間溝通事宜。92年1 月初進入公司時已推綠島\n    酒店。公司獎金制度我去推銷的1 筆（1 股）13萬5 千元，\n    我抽7 千元的獎金，我的組員推銷成交的我抽5 千元獎金，\n    襄理、協理抽的獎金我不知道，專員即最基層的員工1 筆抽\n    1 萬，但我所收入的獎金也提供公司24％之管銷費用，員工\n    沒有薪水，都靠業務招募合夥人的獎金；我是公司股東，也\n    有買1 筆公司的股份，我沒有薪水，沒有分紅，都靠業務招\n    募合夥人的獎金。海閣林休閒渡假酒店是在綠島蓋飯店以旅\n    館名義申請建照，公司92年間就開始對外募資，我們都把募\n    得資金交給財務部的會計徐淑瑩，資金何人管理我不清處。\n    戊○○告訴我們工程已經要完成了，一定會通過建照，我們\n    深信會通過，當時沒通過建照申請，所以對外招募以五星級\n    觀光大飯店名義招募。我們以要在綠島蓋一間五星級觀光酒\n    店名義，告知合夥人飯店前景看好，有很好的投資前景去對\n    外招募，公司沒幫合夥人辦貸款。我任職期間約完成10筆，\n    含我自己1 筆，我進公司時是1 筆13萬元，共招募2 人，一\n    為甲戌○買5 筆，另一為男性網友買4 筆，共領取7 萬元業\n    務獎金，進公司期間92年約領5 、60萬元獎金，93年約領3\n    、40萬元獎金。1 個單位13萬5 千元先全部繳回公司，我跟\n    下面業務員依階級一起分3 萬5 千元。在海閣林公司應該有\n    領到2 、3 百萬元業務獎金金額。大家都是20幾歲到海閣林\n    公司上班，入公司時公司有給我們很好的藍圖及前景，我自\n    己也有投資，公司給我們的訊息是工程有進行，我所知也是\n    正在興建中的飯店，若我知道是詐欺我有不可能會投資，我\n    認為公司給我們的是指日可待的藍圖等語（出處：警卷(一)，\n    P48-P52 、偵四卷，P6-P7 、原審一卷，P322、原審四卷，\n    P196反面、P208反面）。\n4 、乙ｆ○（原名顏銘震）：\n    我當初在海閣林公司是任職副總經理職務，負責台中辦事處\n    的業務，台中辦事處已在94年4 月結束。公司集資進來的錢\n    先進戊○○的帳戶，再匯進公司的帳戶。公司基層專員都是\n    領業績獎金，每招攬1 單位13萬5 千元的投資，可領1萬 元\n    的業績獎金，主任可抽3 千元，襄理抽2 千元，經理抽3 千\n    元，協理抽5 千元，副總抽1 萬2 千元，我和戊○○固定每\n    單位領1 萬2 千元，每筆13萬5 千元實際上進入公司的帳戶\n    內只有8 萬5 千元。業務員都透過網路交友和婚友社方式對\n    外尋找投資目標。高雄總公司及台中辦公室的租金、水電由\n    公司負責，業務部的管銷由戊○○負責，但台中辦事處人員\n    的薪水由我支付。海閣林在綠島購得之土地共11筆，金額共\n    約3 、4 千萬元以上。海閣林休閒渡假酒店是以戊○○名義\n    申請集合式住宅建照，一開始真的要申請旅館建照，但申請\n    不過，後來也是因工程款的問題才繼續對外以投資建造五星\n    級渡假酒店名義繼續招募投資。海閣林公司總共集資4 億多\n    元，我沒出資投資綠島開發案，綠島興建酒店大約共花超過\n    2 億元，投資客每年可分紅，92年底迄今我分得5 百至8 百\n    萬元。我在台中擔任朕聖企業公司的總經理，是間代銷公司\n    ，我們公司代銷海閣林公司綠島投資案，在台中、高雄運作\n    ，甲辛○、潘春枚、乙地○、Ｐ○○、乙Ｒ○、甲Ｂ○、黃\n    世杰、劉家沛、乙Ｉ○、Ｌ○○、甲Ｉ○、甲Ｊ○、ｍ○○\n    、黃彩惠、甲ｖ○、Ｃ○○、乙Ｄ○○、甲ｆ○、乙Ｃ○、\n    甲ｍ○、甲Ｐ○、Ｎ○○、Ｘ○○、Ｍ○○都是朕聖公司員\n    工。我與戊○○是好友，當時我知道他買了土地，飯店也在\n    興建中，才與公司員工一起代銷，朕聖企業沒有詐欺的意思\n    等語（出處：警卷(一)，P57-P60、偵四卷，P2-P3、原審一卷\n    ，P322、原審四卷，P196、P208反面-P209）。\n5 、甲辛○：\n    92年中戊○○叫我到海閣林休閒渡假酒店擔任業務主管，我\n    擔任經理，後擔任協理，工作內容為業務人員之管理和業務\n    推廣，沒底薪只有獎金，我大約招募300 多個單位。我手下\n    的業務每招攬投資1 單位，我可領2 萬3 千元，但要再扣掉\n    給業務及其他主管的錢，所以我實領5 千元（偵訊時改稱8\n    千元），任職期間領1 、2 百萬元。公司以要在綠島建照五\n    星級休閒渡假酒店名義對外招攬投資，投資1 筆13萬5 千元\n    ，對外招商3600單位。公司會安排女業務到婚友社拓展人脈\n    ，至於女業務在婚友社認識朋友後如何向他們介紹投資，我\n    不清楚。女業務招攬投資完款後，會將客戶投資的錢分別以\n    現金或匯款方式給乙丙○處理。海閣林在綠島總共買11筆土\n    地，海閣林休閒渡假酒店公司以集合住宅名義申請建照。戊\n    ○○解釋要先以集合住宅的名義，先把房子蓋起來，以便對\n    股東有交代，戊○○也說到時一定可變更成旅館用途，我們\n    才一直相信戊○○，才向合夥人說到時一定可變更成休閒旅\n    館。當時跟客戶介紹時有明確跟客戶告知，沒隱瞞，沒詐欺\n    客戶等語（出處：警卷(一)，P63-P67 、偵二十卷，P55-P56\n    、原審一卷，P322、原審四卷，P196反面-P197 、P209）。\n6 、乙ｈ○：\n    91年中進入公司當業務員，後升協理，現任董事長助理，執\n    行董事長交代的各項工作，沒出資投資海閣林休閒渡假酒店\n    ，沒底薪，介紹募集每單位13萬5 千元之合夥人，我可抽4\n    千元佣金，每月約可領5 萬元我經手招募的約30人左右，海\n    閣林休閒渡假酒店以蓋飯店為名，向合夥人募資。海閣林在\n    綠島有11筆土地，是以戊○○名義申請建照。業務員每單位\n    可抽1 萬元，我抽4 千元。不知道公司的休閒旅館沒有執照\n    。一開始我們即沒有要詐欺客戶，公司給我們的訊息是一個\n    很好的投資案才介紹給客戶等語（出處：警卷(一)，P77-P83\n    、偵二十卷，P56-P57 、原審一卷，P322、原審四卷，P209\n    ）。\n7 、申○○：\n    92年底戊○○叫我到海閣林休閒渡假酒店擔任董事，在公司\n    擔任業務經理，94年4 月離職，離職時我的團隊剩下4 個女\n    業務ｈ○○、Ｉ○○、張雅婷及李文倩。沒固定薪水，視每\n    月業績而定，每筆我可抽3 千元業績獎金，我旗下女業務也\n    大約抽佣3 千元。公司以要在綠島興建五星級休閒渡假酒店\n    為由對外招攬投資，對外招商3600單位。公司有時會安排女\n    業務到婚友社拓展人脈，女業務在婚友社認識朋友後如何向\n    他們介紹投資我不清楚。女業務招攬投資完款後，會將客戶\n    的錢以現金或匯款的方式給我，我再將錢匯到戊○○或公司\n    的帳戶，或以現金拿給財務部經理乙丙○。公司在綠島共購\n    買11筆土地，公司跟我們說有申請過建照，我們不知道通過\n    的是集合住宅的建照，不知道公司的休閒旅館沒有執照。公\n    司給我們的案子，我認為很好才去推銷，也認為工作還不錯\n    ，沒有詐欺等語（出處：警卷(一)，P69-P72、偵二十卷，P5\n    6 、原審一卷，P322、原審四卷，P209）。\n8 、乙丙○：\n    我擔任戊○○特別助理，負責載送戊○○外出，以前是擔任\n    會計，我月薪3 萬。業務員沒支領底薪，拉到客戶買股份後\n    才有獎金，1 股份為1 單位13萬5 千元，業務員可分1 萬元\n    ，13萬5 千元中8 萬5 千元交回公司，入戊○○或公司帳戶\n    ，業務分3 萬5 千元，1 萬5 千元給戊○○，海閣林公司經\n    營是以業務員招攬販賣不知情之客戶投資公司股份蓋五星級\n    大飯店為業務方式。幹部均教導業務員，利用打電話機會宣\n    導朋友或參加婚友社約會的男生，告訴他們海閣林要在綠島\n    蓋休閒渡假酒店，蓋完觀光大飯店，如公司有賺錢，股東就\n    可以分紅。91年中旬開始招募，92年購買10多筆土地約3600\n    萬元。戊○○告訴我綠島建地有一部分是農地，不能蓋房子\n    ，要變更才能取得觀光飯店之建照。戊○○以將來會興建五\n    星級渡假大酒店告訴我們，大家才會以此名義對外召攬集資\n    。我全部都是按照公司及老闆指示去辦理等語（出處：警卷\n    (一)，P19-P31 、偵四卷，P3-P4 、偵七卷，P33 反面-P34、\n    原審一卷，P322、原審四卷，P197反面-P198 、P209）。\n9 、乙Ｆ○：\n    92年底在海閣林台中辦事處擔任經理，是教育訓練的講師，\n    我不負責對外推銷業務，是向公司業務員上一些有關公司的\n    專業知識及加強員工信心的課程，不是業務訓練。我沒向任\n    何人推銷過海閣林公司的股份，我的業務員每成交1 單位我\n    可抽2 萬元業績獎金，但須支付公司的水電費。我知道海閣\n    林休閒渡假酒店在綠島興建的飯店以戊○○私人名義去申請\n    集合式住宅的建照，公司是說將來一定可以變更過，但這部\n    分我們不瞭解，所以公司怎麼說我們就怎麼對客戶說等語（\n    出處：警卷(一)，P112-P113、偵二十卷，P62-P63、原審一卷\n    ，P322、原審四卷，197反面、P209）。\n10、乙地○：\n    91年開始在海閣林任職協理，負責管理業務員，知道海閣林\n    公司實際上沒有旅館執照，業務員都知道，有告訴客戶是集\n    合住宅，薪水是1 個單位抽8 千或9 千元，沒有底薪。我是\n    在乙ｆ○（顏銘震）公司上班，當時我有一個產品代銷即將\n    結束，認為觀光休閒是個不錯的產業，才轉換跑道代銷此商\n    品，我們都依照公司的工程進行去做，不知道犯罪等語（出\n    處：偵二十卷，P165-P 166、原審一卷，P322、原審四卷，\n    P209 ）。\n11、Ｐ○○（原名吳俊德）：\n    我在公司擔任業務主任，看主管要我做什麼，就做什麼，他\n    們都是我的主管。我是代銷公司的員工，入行不久，我得到\n    的訊息是工程有在進行，不曉得觸法。通常我們會算報酬率\n    給客戶看，客戶認為合理才簽約等語（出處：原審一卷，P3\n    22、原審四卷，P209、P212）。\n12、乙Ｒ○：\n    92年開始在海閣林公司擔任專員，後升職主任、襄理，94年\n    離職，剛開始公司叫翻天創新公司，後才改名海閣林。工作\n    性質主要是針對女業務所帶回來的客戶，我要向他們介紹公\n    司所投資的產業、性質或工程進度等有關投資案相關事情，\n    資訊都從公司處得知，由公司提供資料、建照影本等相關資\n    料，然後再由女業務向他們介紹投資海閣林公司的股份，解\n    說時不一定會進公司，但簽約時一定會帶到公司。解說投資\n    期間客戶每年可獲利多少有講大概的數字，營運後1 年才可\n    分紅，還本要看客戶自己計算，如投資10萬元，每年可分1\n    萬即10年可還本。簽約時我只依照合夥協議書內容陳列之項\n    目解釋，沒告知支付業務員獎金及幹部報酬部分。我的主管\n    是甲辛○。專員的業績獎金是1 萬元，主任獎金是1 萬3 千\n    元，襄理獎金是1 萬5 千元，我底薪1 個月3 萬元，我解說\n    的部分1 單位可領到2 千元。我知道海閣林公司是以戊○○\n    私人名義申請集合式住宅建照去蓋的，公司有跟我們說未申\n    請過合格的旅館建照，為了趕快把建物蓋好，公司才先申請\n    集合式住宅來蓋，將來一定可變更為旅館的建築執照。有跟\n    客戶說明集合住宅的執照，沒有飯店、酒店的執照，建照在\n    變更當中。我認為公司有用心經營，客戶也都是成年人，應\n    該有判斷能力，我們是依照公司藍圖跟客戶解釋，若詐欺客\n    戶就不會買地、開工等語（出處：警卷(一)，P183-P185 、偵\n    二十卷，P72 、原審一卷，P322、原審四卷，P198、P209、\n    P211-P212）。\n13 、甲Ｂ○：\n    93年中在海閣林公司擔任專員，後當主任，薪水每月大約2\n    萬多，知道海閣林公司沒有飯店執照，有對客戶講是集合住\n    宅的執照，會申請變更。我也是代銷公司員工，職務內容與\n    乙Ｒ○同等語（出處：偵二十卷，原審四卷，P209反面、P2\n    12）。\n14、甲ｗ○：\n    93年在海閣林公司上班擔任業務專員，94年就被乙Ｒ○換到\n    風緻開發公司上班，期間約支領10萬元薪水。我在海閣林公\n    司沒有底薪，要談CASE才有薪水，不知道談CASE收入有多少\n    ，我在海閣林均只幫人介紹資料，我沒錢吃飯都跟甲辛○拿\n    。海閣林公司經營股份投資買賣。上級要我以綠島飯店開發\n    案去尋找客戶，以後會賺錢，我有對外賣出10個單位，1 單\n    位13萬5 千元可抽8 千元到1 萬元佣金，有賣給ｙ○○、甲\n    Ｅ○，當時有跟她們說是集合住宅的執照，之後會變更為飯\n    店，還有拿文件給他們看。我是代銷公司員工，我只是業務\n    員要賺錢，不知道是詐欺等語（出處：警卷(一)，P195-P199\n    、偵二十卷，P183-P184 、原審二卷，P115、原審四卷，P2\n    09反面）。\n15、午○○（原名史雅茜）：\n    92年在海閣林公司當專員，後升到主任，沒有底薪，是獎金\n    制，專員是1 單位1 萬元，主任是1 萬3 千元，前後領到的\n    獎金約幾10萬。申○○、未○○是我堂兄妹。不知道海閣林\n    沒有飯店執照，只知道有集合住宅建造執照，有對客戶說有\n    建照，公司跟客戶說明時有講是集合住宅的執照，會申請變\n    更，公司當時拿土地等投資案相關資料給我，我才去找客戶\n    ，有告知客戶相關訊息，客戶有到公司看過後，才決定投資\n    ，我有到綠島看過現場。有賣ｗ○○、乙ｒ○、乙Ｕ○、甲\n    ｐ○、Ｙ○○、黃○○、ｐ○○、甲ｉ○、乙Ｌ○、Ｒ○○\n    、Ｕ○○，當時我以朋友立場推薦給朋友，沒說要結婚，只\n    說要當朋友，沒說不買東西就不能交朋友等語（出處：偵二\n    十卷，P156、原審二卷，P74、P276-P277、原審四卷，P199\n    、P209反面）。\n16、甲ｓ○：\n    92年底進入海閣林公司擔任專員，薪水是獎金，1 單位9 千\n    元，知道海閣林公司沒有飯店的執照，但有集合住宅的執照\n    ，共約賣出50幾個單位，有向客戶說明是集合住宅的執照。\n    有賣丁○○、甲Ｆ○。老闆怎麼說就怎麼做，我沒有詐欺意\n    圖等語（出處；偵二十卷，P94-P95 、原審四卷，P209反面\n    ）。\n17、乙Ｉ○（原名蔡宜庭）：\n    92年底開始在海閣林公司當專員，沒有底薪，是獎金制，專\n    員1 個單位9 千元，知道海閣林公司沒有飯店執照，有對客\n    戶講是集合住宅的執照，會申請變更，共賣約40幾個單位，\n    有賣給ｌ○○、許見智、Ａ○○等大概4 個客戶，有拿到佣\n    金。沒有詐欺意圖，公司推出此投資案時，在綠島有蓋旅館\n    ，我有詳細跟客戶解說，也提到會變更建照等語（出處：偵\n    二十卷，P158、P184、原審二卷，P63 、原審四卷，P209反\n    面）。\n18、Ｌ○○：\n    93年初在海閣林公司擔任業務專員，薪水是獎金，1 單位9\n    千元，知道海閣林公司沒有飯店的執照，共賣出約5 、60個\n    單位，有向客戶說明是集合住宅的執照，有賣給乙酉○、甲\n    Ｎ○、乙亥○、甲Ｇ○、甲天○。我有請客人到公司瞭解狀\n    況。Ｍ○○是我姊姊等語（出處：偵十六卷，P6-P57、偵十\n    八卷，P5-P6 、P16-P17 、P22 、P29-P30 、偵二十卷，P9\n    3、P272、原審二卷，P62 、原審四卷，P209反面）。\n19、乙ｋ○：\n    91年底在海閣林公司擔任專員，後升到主任，當時公司名稱\n    是翻天，薪水是獎金，1 個單位9 千元，主任是1 萬3 千元\n    ，我大概可以抽9 千元，不知道海閣林公司沒有飯店的執照\n    ，當時公司正在買地，有向客戶說明執照的情形，共賣不到\n    10個單位，有賣乙Ｏ○。如公司所說，執照、什麼東西都有\n    ，簽約時都有看得到等語（出處：偵二十卷，P94、原審二\n    卷，P62-P63、原審四卷，P209反面）。\n20、甲Ｉ○：\n    當初在海閣林公司擔任業務，1 個單位13萬5 千元，佣金約\n    8 千至1 萬元。知道海閣林公司沒有飯店執照，有對客戶說\n    明是集合住宅的執照，共賣1 、20個單位，有賣給宇○○。\n    公司說什麼我們就做什麼等語（出處：偵二十卷，P157-P15\n    8 、原審二卷，P118、原審四卷，P209反面）。\n21、甲Ｊ○：\n    93年在海閣林公司擔任專員，薪水是獎金，1 個單位9 千元\n    ，知道海閣林公司沒有飯店的執照，但有集合住宅的執照並\n    有向客戶說明，共賣出約2 、30個單位，有賣辛○○、乙宙\n    ○、甲Ｑ○、乙ｏ○。我們是一般代銷公司，公司叫我們做\n    什麼就做什麼等語（出處：偵二十卷，P87-P88 、原審二卷\n    ，P63 、原審四卷，P209反面）。\n22、ｍ○○（原名林詩怡）：\n    92年間在海閣林公司擔任業務助理，我領底薪，每月1 萬5\n    、6 千元，沒有在賣單位，也沒有賣甲Ｃ○單位，當時甲Ｃ\n    ○是我負責開發，但產品介紹不是我，我有帶甲Ｃ○到公司\n    交由公司人員介紹。我在代銷公司上班，不知道飯店是否有\n    蓋好，沒有以結婚為前提認識客戶等語（出處：偵二十卷，\n     P93-P94、原審二卷，P74 ）。\n23、乙Ｘ○：\n    91年在海閣林公司擔任業務助理，當時公司是翻天，薪水是\n    獎金，1 單位1 萬元，當時公司已買完地在搭建，只知道有\n    執照，不知何執照。不知道綠島有無辦理登記，主管有跟我\n    們講，但我們沒直接去綠島瞭解，那時剛出社會，認為公司\n    提供訊息飯店有在興建，不知道要看執照，認為當時有在營\n    運，不是詐欺，約2 個半月我就離職，我負責綠島開發案及\n    跟客戶推銷，1 個單位約12、3 萬元，抽取8 、9 千元等語\n    （出處：偵二十卷，P96、原審二卷，P63、原審四卷，P210\n    ）。\n24、Ｊ○○：\n    91年在海閣林公司當任專員，後升到主任，沒底薪是獎金制\n    ，專員1 單位1 萬元，主任1 萬3 千元，不知道海閣林公司\n    沒飯店執照，沒帶客戶到公司，不記得賣多少單位，有賣給\n    亥○○、巳○○。沒拿到佣金。我沒詐欺，我到離開公司時\n    都認為是真的等語（出處：偵二十卷，P159、原審二卷，P6\n    3 、原審四卷，P210）。\n25、黃睦芸（原名黃彩惠）：\n    92年底進去海閣林公司擔任專員，薪水是獎金，1 單位9 千\n    元，知道海閣林公司沒飯店執照，共賣出約2 、30個單位，\n    有向他們說明是集合住宅的執照，有賣乙ａ○、乙Ａ○，有\n    領到佣金，我把客戶帶到公司後即由公司職員介紹。當時剛\n    進公司認為公司前景很好，是代銷公司等語（出處：偵二十\n    院，P95 、原審二卷，P63 、原審四卷，P210）。\n26、甲ｖ○（原名馮志群）：\n    92年進去海閣林公司擔任專員，後升到主任，薪水是獎金，\n    1 個單位1 萬元，主任1 萬3 千元，知道海閣林公司沒有飯\n    店的執照，但有集合式住宅的執照，共賣出約1 百個單位，\n    有向客戶說明是集合住宅的執照，是我帶客戶到公司，乙Ｒ\n    ○、吳俊德、甲Ｂ○向他們說明的。有賣給甲丙○、乙丑○\n    、丙○○、甲酉、甲庚○、甲ｅ○、甲Ｗ○、甲未○、甲Ｌ\n    ○，客戶大部分用貸款方式購買公司產品，由公司辦信用貸\n    款，我純粹負責推銷，以朋友心態與其聯繫，但客人若以交\n    女友心態問我，我會直接講明。我是代銷公司員工，有看到\n    建築執照、買地證件等，公司有跟我說日後建照會變更，我\n    沒威脅客戶不成交就不交往，董事長有帶我們到綠島看基地\n    等語（出處：偵二十卷，P88 、原審二卷，P74 、原審四卷\n    ，P210）。\n27、未○○（原名史恆華）：\n    92年我哥哥申○○介紹我進去海閣林公司擔任專員，後升到\n    主任、襄理，沒底薪，是領獎金，我的工作就是要推銷海閣\n    林公司的股份，大約推銷20人左右，我從參加婚友社著手開\n    發，專員的獎金是1 萬元，主任獎金是1 萬3 千元，襄理獎\n    金是1 萬5 千元，副理獎金是1 萬8 千元，經理獎金是2 萬\n    元。公司有拿1 張公文和很多資料給我們看，給我們看集合\n    住宅的執照，說已經申請過合法的建照，我們對這部分也是\n    一知半解，公司如何教育我們，我們就怎麼對客戶說。戊○\n    ○開會有說要以他名義申請建照比較好通過，他保證會將整\n    個飯店的產權都變更回公司名下。有賣過ｔ○○、吳宣昌、\n    甲Ｖ○、Ｏ○○、宙○○。我對客戶均稱公司在綠島興建飯\n    店，綠島目前無飯店，投資1 個單位13萬5 千元，將來應可\n    獲利，客戶有些是貸款購買，我沒幫其辦貸款，我帶客戶到\n    中正路公司由公司人員介紹，客戶有些是同事或朋友介紹，\n    我與客人沒牽過手。公司每個工程進度都會跟我們講，我會\n    告知客戶此訊息等語（出處：警卷(一)，P125-P128 、偵二十\n    卷，P63- P64、原審二卷，P74 、原審四卷，P199反面-P20\n    0 、P210）。\n28、甲子○：\n    92年在海閣林當兼職業務員，只負責在外接客戶推銷海閣林\n    公司的股份，成功時向公司拿我該得的獎金即1 萬元。我利\n    用想和對方交往的方法，誘導少數投資人投資海閣林，我沒\n    說過要結婚，有極力推銷，以公司給我們的訊息去做推銷。\n    。剛開始我不知道海閣林公司以何名義申請建照，但後來因\n    客戶在問，公司才跟我說是以戊○○名義去申請集合住宅的\n    建築執照，公司說到時再申請變更，這樣比較不會耽誤到正\n    式營運的時間。我都是將客戶帶到公司，由乙ｈ○向客戶介\n    紹，公司男客戶扮演女業務的親戚或乾哥，我都會跟客戶說\n    乙ｈ○是在公司擔任特助，由他向客戶介紹比較直接且較深\n    入。有賣過乙ｐ○、許福元、Ｖ○○。當時公司有帶我們到\n    綠島看動工，工程進度陸續在走，公司有跟我們回報，都是\n    聽從公司指示在走等語（出處：警卷(一)，P176-P178 、偵二\n    十卷，P71-P72 、原審二卷，P75 、原審四卷，P210）。\n29、Ｉ○○：\n    92年開始在海閣林公司擔任業務專員，後升到主任沒有底薪\n    ，薪水是獎金，業務員獎金是1 萬元，主任是1 萬3 千元。\n    我去婚友社認識新朋友，跟對方介紹投資海閣林的投資方案\n    ，主要希望對方能因投資海閣林而獲利。共向約20人推銷過\n    ，賣過5 、60個單位，總計完款60至70筆。我不知道建照方\n    面的事情，最近才知道公司在綠島蓋飯店是以戊○○私人名\n    義申請過集合式住宅建照，公司說將來一定可變更成功。公\n    司有拿集合住宅的執照給我們看，有跟客戶說有建照，沒說\n    是什麼建照，有賣過甲辰○、地○○、ｉ○○、甲宇○，我\n    是以朋友立場去推銷，公司有帶我們到綠島看動土典禮等語\n    （出處：警卷(一)，P158-P160、偵二十卷，P70-P71、原審二\n    卷，P75、原審四卷，P210）。\n30、Ｃ○○：\n    92年進去海閣林擔任專員，薪水是獎金，1 單位1 萬元，知\n    道海閣林公司沒有飯店的執照，但有集合住宅的執照，共賣\n    出約100 個單位，有向客戶說明是集合住宅的執照，日後會\n    變更，有賣甲申○、甲ｈ○等3 個客戶單位。客戶均在交友\n    中心認識，客人先衡量自己資力購買，甲申○當時經濟能力\n    佳所以購買9 或10單位，沒說要購買產品我才要與其作朋友\n    。我進公司後，瞭解公司有買地，飯店也有蓋，客戶到公司\n    有告知建照會變更，現以集合住宅興建等語（出處：偵二十\n    卷，P86 、原審二卷，P75 、原審四卷，P210）。\n31、ｈ○○：\n    擔任海閣林公司專員，販賣、推銷海閣林公司股份給不特定\n    人，1 單位13萬5 千元，可分配到1 萬元。前後大約招攬30\n    人投資，完款30筆，領取30萬左右業務獎金。有賣過卯○○\n    、乙Ｍ○、簡國恒、ｃ○○、乙Ｅ○、乙ｑ○、甲ｃ○、乙\n    寅○、Ｈ○○、甲Ｘ○單位。其中乙ｑ○是工人，因信貸不\n    足，只付部分款項，剩下由我墊付。有到綠島看建築等語（\n    出處：警卷(一)，P208-P213、偵二十卷，P77-P78、原審二卷\n    ，P75、原審四卷，P210反面）。\n32、乙Ｇ○：\n    91年在翻天創新國際股份有限公司任職，92年離職時公司改\n    名為海閣林公司，擔任會計兼業務，在海閣林有推銷公司的\n    股份，約推銷4 、5 人，賣5 、6 個單位，薪水是會計1 個\n    月2 萬3 千元加獎金即成交1 單位8 千元。我離職時公司尚\n    未購地，但有計畫在接洽購地事宜，已簽下建地，興建集合\n    住宅我不清楚。有賣過甲壬○等語（出處：警卷(一)，P223-P\n    225 、偵二十卷，P78-P79 、原審二卷，P75 、原審四卷，\n    P210反面）。\n33、陳佩琦：\n    93年在海閣林公司當專員，後升到主任，沒底薪是獎金制，\n    專員1 單位1 萬元，主任是1 萬3 千元。知道海閣林公司沒\n    有飯店執照，跟客戶說明時有講是集合住宅的執照，共賣20\n    幾個單位左右，有賣給乙申○、乙Ｐ○、乙ｃ○。我沒說要\n    先購買產品才可交友。我屬代銷公司，知道當時是以集合住\n    宅興建，但會變更用途，我有到綠島，有看到基地在興建飯\n    店，認為是真的投資等語（出處：偵二十卷，P160、原審二\n    卷，P75、原審四卷，P210反面）。\n34、乙Ｃ○：\n    93年在海閣林公司但任業務專員，後升到主任，沒有底薪，\n    是領獎金，業務員是1 個單位1 萬元，主任是1 萬3 千元，\n    94年覺得公司怪怪的就離職。大概向20個客戶推銷成功過海\n    閣林公司的股份，完款20筆左右，每單位專員的獎金是1 萬\n    元。我知道海閣林休閒渡假酒店是以戊○○私人名義去申請\n    集合式住宅建築執照，公司說將來一定可以變更過，公司怎\n    麼對我們說，我們就怎麼對客戶說。有賣過Ｓ○○，有帶他\n    到綠島看過。我認為我也被騙。當初都認為公司給我們的訊\n    息是真的等語（出處：警卷(一)，P189-P191 、偵二十卷，P\n    72- P73 、原審二卷，P75 、原審四卷，P210反面）。\n35、甲ｂ○：\n    93年在海閣林擔任業務專員，沒有底薪，是領獎金，1 個單\n    位1 萬元，大概向7 、8 個客戶推銷成功過，完款10幾筆左\n    右。不知道海閣林公司沒有酒店飯店執照，但知道海閣林休\n    閒度假酒店是以戊○○私人名義申請集合式住宅，公司說要\n    先把建物蓋起來，將來再去變更。有賣過ｋ○○、Ｂ○○、\n    ｊ○○、乙癸○，而乙癸○錢沒付完。入公司只是為了1 份\n    工作，主管叫我們做什麼就做什麼，沒有要欺騙客人，客戶\n    需要瞭解什麼就帶入公司由主管講解等語（出處：警卷(一)，\n    P148 - P150 、偵二十卷，P65 、原審二卷，P76 、原審四\n    卷，P210反面）。\n36、甲Ｒ○：\n    91年至92年在海閣林擔任專員，後來是襄理，沒有薪水，但\n    賣出單位有獎金，專員是1 單位8-9 千元，襄理是1 萬元，\n    共賣出10幾個單位，知道海閣林公司是集合住宅執照，有跟\n    買的客戶說明是集合住宅執照，說像民宿，有賣給甲Ｘ○、\n    甲丑○、乙Ｓ○單位。我以朋友立場告訴客人這是不錯的產\n    品可以投資，分享給客人等語（出處：偵十三卷，P17-P18\n    、偵十四卷，P22、原審二卷，P76、原審四卷，210反面）\n    。\n37、乙黃○：\n    劉珈妤也是我本人。92年間在海閣林公司擔任業務專員，後\n    升到主任，沒有底薪，是領獎金，業務員是1 個單位1 萬元\n    ，主任是1 萬3 千元，不知道海閣林沒有飯店執照，任職期\n    間大概向20個客戶推銷成功過，完款約4 、50個單位。領過\n    約10幾萬元業務獎金。沒帶過客戶到綠島。當時工程都有在\n    進行，不認為詐欺等語（出處：警卷(一)，P137-P138 、偵七\n    卷，P32 、偵二十卷，P64 、原審二卷，P76 、原審四卷，\n    P198 反面-P199 、P210反面）。\n38、甲ｍ○：\n    92年在海閣林公司任職，公司是在台中的辦事處，進去是業\n    務員，後升到主任，沒有底薪，是領獎金，業務員是1 單位\n    9 千元，主任是1 萬2 千元。我都從網路上認識朋友，跟他\n    們說海閣林的投資方案很好可賺大錢，看他們要不要投資，\n    如他們有意願，就帶他們到公司進一步瞭解，想投資的人沒\n    錢，我會介紹他們去貸款。知道海閣林公司沒有酒店飯店執\n    照，有跟客戶說是集合住宅執照，有賣給乙戌○、玄○○、\n    林豊田、甲丁○、子○○、乙ｔ○、乙丁○、乙Ｔ○、甲宙\n    ○。沒跟客戶說沒有購買不能當朋友，公司有帶我們到綠島\n    看工程，的確有動工、興建，公司當時也沒說執照沒核發。\n    我只是代銷海閣林產品，乙ｆ○叫我們做什麼我們就做，確\n    實沒以結婚為前提介紹投資等語（出處：警卷(一)，P142-P14\n    3 、偵二十卷，P64-P65 、原審二卷，P76 、原審四卷，P2\n    11）\n39、甲Ｐ○：\n    92年在台中朕聖公司擔任兼職業務員，主管叫我去推銷海閣\n    林公司的投資案，要在綠島蓋五星級大飯店，銷售海閣林飯\n    店股權，以股權銷售方式，每單位13萬5 千元，我只推銷給\n    庚○○4 個單位，說有很大商機，會有很大獲利，沒說獲利\n    多少，每單位我可抽1 萬元業績獎金，不知道海閣林沒有酒\n    店飯店執照，客戶有到公司現場，有看到執照。我沒去綠島\n    看過，但有委託朋友去綠島時幫我看，我朋友去問當地人，\n    當地人說沒聽過海閣林休閒渡假酒店，我覺得怪怪就不再推\n    銷海閣林的投資案。沒推銷給ｎ○○、乙ｄ○、乙ｙ○，我\n    依照公司的訊息介紹，沒跟客戶說以結婚為前提作為投資的\n    方向等語（出處：警卷(一)，P170-P171、偵二十卷，P71、原\n    審一卷，P251反面、原審四卷，P211）。\n40、Ｎ○○：\n    我在朕聖公司任職，不是在海閣林公司，沒有賣給甲ｔ○、\n    甲寅○、乙Ｑ○，當時我沒有介紹客戶，也沒到外面推銷，\n    只有在公司接電話，那是別人介紹的。記得當時很多客戶到\n    公司由負責解說的人解說，公司如何跟其解說我不清楚等語\n    （出處：偵二十卷，P86-P87 、原審二卷，P115、原審四卷\n    ，P211）。\n41、Ｘ○○：\n    92年在海閣林公司擔任業務員，主管要我從事海閣林投資案\n    股權推銷，要在綠島蓋五星級飯店，以股權銷售方式，每單\n    位13萬5 千元。薪水是獎金，1 個單位1 萬元，知道海閣林\n    公司沒有飯店的執照，有向客戶說明是集合住宅的執照，甲\n    ａ○問我說他想要賺錢，所以我向其推銷海閣林股權，我賣\n    他5 單位；甲ｇ○我推銷他14個單位188 萬元，乙天○我推\n    銷他6 個單位，他用信用貸款方式繳錢，有介紹他們產品，\n    沒說獲利多少等語（出處：偵二十卷，P87 、原審一卷，P2\n    51 反面、原審四卷，P211）\n42、ａ○○（原名李裙鳳）：\n    91年任職海閣林公司擔任業務員，後升到主任，主管要我從\n    事海閣林投資案股權推銷，要在綠島蓋五星級飯店，是以股\n    權銷售方式，每單位13萬5 千元，我只推銷給乙Ｂ○4 單位\n    ，說公司將綠島蓋五星級飯店，看其有無意願投資，沒有說\n    利潤多少，只說綠島現在沒有飯店，只有民宿，蓋飯店投資\n    報酬率會好，我有帶客戶到公司瞭解狀況，是客戶本身想投\n    資，沒有強迫其投資等語（出處：偵二十卷，P160、原審一\n    卷，P252、原審四卷，P211）。\n43、Ｍ○○：\n    92年在朕勝公司擔任業務員，主管要我推銷海閣林投資案股\n    權，要在綠島蓋五星級飯店，是以股權銷售方式，每單位13\n    萬5 千元。我沒有薪水，是獎金制，1 個單位9 千元，知道\n    海閣林公司沒有飯店執照，但有對客戶說明有集合住宅執照\n    ，會申請變更，共賣出3 、40個單位，有賣給癸○○、乙ｌ\n    ○、乙庚○、乙甲○，我跟他們推銷公司將在綠島蓋五星級\n    飯店，看其有無意願投資，有說利潤不錯，沒有明確講說利\n    潤有多少等語（出處：偵二十卷，P156-P157 、原審一卷，\n    P251 反面-P252 、原審四卷，P211）。\n44、乙Ｄ○○\n    我於91年間在翻天創新國際有限公司任職，後來公司改名海\n    閣林休閒渡假酒店公司，在海閣林擔任專員、主任、襄理，\n    對外開發業績，在公司內介紹客戶產品，以綠島開發案為主\n    ，有時業務會跟客戶說，親戚在海閣林公司上班，目的是將\n    客戶帶到公司，讓主管幫我們向客戶推銷，推銷成功約50筆\n    左右，專員的獎金是1 萬元，主任獎金是1 萬3 千元，襄理\n    獎金是1 萬5 千元，離職前公司就對我們說海閣林休閒渡假\n    酒店有申請過合法旅館的建築執照，是合法建照，我也都是\n    這樣跟客戶推銷，有賣給甲巳○、ｂ○○、乙Ｖ○、甲卯○\n    如起訴所載之投資單位，沒有要他們投資海閣林，才去婚友\n    社，是因為朋友關係，覺得真的會賺錢才跟客戶分享，我去\n    過綠島2 次，第1 次去現場在整理地基，第2 次去時已有建\n    築物存在，沒帶過4 位客戶去過綠島，但他們參加投資後好\n    像有去綠島看過等語（見警A 卷，P163-P166 、偵四卷，P2\n    1 反、偵二十卷，P166、原審二卷，P118、原審四卷，P311\n    -P312、P314）。\n五、經查：\n(一)、公訴意旨雖認被告戊○○等人以海閣林公司名義，先以少數\n    之資金在綠島地區購得依法不得建造旅館之土地（建地3 筆\n    、農地8 筆），且購得土地，均登記在被告戊○○名下，再\n    以集合住宅的名義申請建造執照，佯稱在綠島投資興建五星\n    級休閒渡假大飯店，且明知海閣林公司自始至終無法取得臺\n    東縣政府所核發之合法旅館建築執照，而向被害人詐騙投資\n    款等情。惟：\n 1、緣於91年4 、5 月間，另案被告黃復杰以在綠島投資購地建\n    造「海閣林休閒渡假酒店」為由，邀被告戊○○合夥，共同\n    籌劃設立翻天創新公司（址設高雄市前金區○○○路235 號\n    8 樓之5 ），黃復杰負責公司出資及總攬公司財政等營運事\n    項，戊○○則擔任招募公司股東、籌措資金及其餘公司事務\n    ，並由戊○○擔任翻天創新公司之登記負責人，該公司於91\n    年5 月7 日完成設立登記，2 人即擬定「合夥預定契約書」\n    （下稱「舊合夥預定契約書」），以購地興建「海閣林渡假\n    大酒店」名義，對外招募股東籌措資金；詎黃復杰與戊○○\n    ，自91年6 月24日起至92年3 月5 日間止，於綠島進行購地\n    之際，竟將部分募得資金，由戊○○連續轉帳共計72,094,2\n    00元之投資款項至黃復杰所指定之帳戶內，供黃復杰提領使\n    用，黃復杰得款上開7 千2 百萬餘元，即避不見面，2 人共\n    同連續業務侵占部分，黃復杰前經原審法院以92年度易字第\n    2253號判決判處有期徒刑4 年，並經本院94年度上易字第58\n    9 號判決駁回上訴確定；戊○○另經原審法院以98年度易字\n    第75號判處有期徒刑2 年，亦經本院98年度上易字第762 號\n    判決駁回上訴確定，合先敘明。\n 2、被告戊○○於92年4 月間，將翻天創新公司改籌組海閣林公\n    司，由戊○○擔任海閣林公司董事長，並增修「舊合夥預定\n    契約書」內容，重新擬定「合夥預定契約書」（下稱「新合\n    夥預定契約書」），以海閣林公司名義繼續招募股東及籌措\n    資金，並透過臺東市市民代表陳貞賢之介紹，委託臺東縣綠\n    島鄉公所秘書鄭文仁居中簽線，經多次協調土地買賣事宜，\n    由海閣林公司出資2,117 萬3 千元，向地主韓春麟購買坐落\n    臺東縣綠島鄉○○○段第1176、1178、1179、1180、1180-1\n    、1183、1183之1 、1185地號之土地（上開土地皆係「旱地\n    」，起訴書誤載為「農地」），並於92年5 、6 月間，將購\n    地款項匯入鄭文仁開設之合作金庫臺東分行帳戶；嗣戊○○\n    發現土地面積仍不足興建海閣林休閒渡假酒店，希望再購買\n    週邊其它建地，以擴大使用面積，復透過陳貞賢介紹，委託\n    鄭文仁居中簽線，經多次接洽，以1,389 萬之代價，向地主\n    鄭盛隆購買坐落臺東縣綠島鄉○○○段1152、1152-1、1152\n    -2地號之土地（3 筆土地皆為「建地」），並於92年8 月間\n    ，並將購地款項匯入鄭盛隆指定友人謝志忠之郵局帳戶等情\n    ；此據證人鄭文仁、韓春麟於警詢時證述甚詳（警(一)卷第25\n    2 至254 、265 、266 、309 、310 頁），復有海閣林公司\n    登記資料、股東名簿、股東繳納股款明細表、不動產買賣契\n    約書、鄭文仁之合作金庫銀行活期存款存摺影本、謝志忠之\n    郵政存簿儲金簿影本、土地所有權人土地資料謄本、地籍圖\n    影本，及土地異動索引資料各1 份在卷可稽（警卷(四)第1600\n    、1601、1740至1772頁，警卷(四)第256 至263 、267 至271\n    頁）。足證被告戊○○自92年4 月間起至同年8 月間止，確\n    有將海閣林公司募得之資金共計3 千5 百多萬元，在綠島地\n    區取得上開土地，並作為興建海閣林休閒渡假酒店之用途。\n 3、被告戊○○於92年8 月間在綠島購得上開土地後，因部分土\n    地地目係屬「旱地」，無法登記公司所有，而暫將土地登記\n    於戊○○名下；隨即委請蔡國勇建築師在上開地號1152、11\n    52-1、1152-2、1178、1180、1183等6 筆土地，規劃設計全\n    棟地上5 層、地下1 層共計49戶之「海閣林休閒渡假酒店」\n    （下稱「全案工程」、基地面積共計1571.64 平方公尺、法\n    定空地面積共計599.87平方公尺、總樓地板面積共計3124.4\n    2 平方公尺），並向臺東縣政府申請旅館執照，然因旁邊臨\n    時道路問題，尚未解決，縣府僅准核發集合住宅用途之建造\n    執照（93年3 月25日府城建字第000000000 號），戊○○支\n    付蔡國勇建築師約130 萬元之規劃設計費用，並取得建造執\n    照後，自93年4 月19日起，復將全案工程交由銘泉營造有限\n    公司（下稱銘泉營造公司），並按蔡國勇建築師之上開設計\n    規劃施工，全案工程於94年12月20日完工，工程款（含追加\n    工程款）總計9, 608萬，嗣於95年2 月10日取得臺東縣政府\n    核發之集合住宅使用執照（府城建字第Ｚ0000000000 號）等\n    情，業據證人即建築師蔡國勇於偵查中具結，及證人即銘泉\n    營造公司股東賴振東於警詢陳明在卷（偵七卷第32、33頁蔡\n    國勇筆錄、警卷(一)第272 至274 賴振東筆錄），並有綠島海\n    閣林旅館新建工程申請建築執照流程說明及相關資料（偵五\n    卷第192 至195 頁）、銘泉營造公司臺中商業銀行活期性存\n    款存摺影本、銘泉營造公司開立之發票影本（發票上面買受\n    人均記載「海閣林休閒渡假酒店」）、銘泉營造公司營造業\n    登記證書影本（警卷(一)第276 至291 頁）、臺東縣政府93年\n    3 月25日府城建字第000000000 號建造執照及95年2 月10日\n    府城建字第Ｚ0000000000 號使用執照（警卷(四)第1733頁，原\n    審卷(一)第262 至265 頁）在卷可稽；復有綠島海閣林施工程\n    藍圖、工程合約書、水電工程配置圖、鋼構配置圖、施工圖\n    本、平面配置圖、工程照片、綠島海閣林遊樂業整合性管理\n    系統建議書及餐飲管理系統建議書可佐。是被告戊○○自92\n    年8 月間起至95年2 月10日止，確將海閣林公司募得之資金\n    約9 千7 百多萬元，用以興建「海閣林休閒渡假酒店」，作\n    為綠島地區休閒遊樂渡假場所之事實無誤。\n 4、證人蔡國勇建築師於偵查中亦具結證稱：海閣林公司請我設\n    計時，說是要蓋飯店，我起初以旅館名義申請，但縣府說不\n    合法令，我建議用集合住宅名義申請，但蓋的標準，還是用\n    旅館方式去興建，以後再變更申請；當時因為旁邊臨時道路\n    的問題，沒有辦法解決，預計興建的旅館旁邊，雖有一條既\n    成道路，但要用捐贈道路土地，或收購隔壁民房的方式，當\n    作道路土地，才能解決臨時道路的問題等語（偵七卷第33頁\n    ），是被告戊○○委請蔡國勇建築師設計之初，原先即以旅\n    館規模之建造設計；且因臨時道路問題無法克服，才先以集\n    合住宅名義申請建造執照之事實亦明。又上開建築工程於95\n    年2 月10日取得上開集合住宅使用執照後，海閣林公司於95\n    年11月14日提出申請，經臺東縣政府審查符合旅館消防安全\n    設備，同意海閣林公司籌設旅館，並於一年內依建築法、都\n    市計畫法等相關法規辦理後，再申請旅館登記等情，有臺東\n    縣政府95年12月4 日府旅管字第0953038052號函及臺東縣消\n    防局95年12月28日消預審字第0950000119號函在卷可稽（原\n    審卷(一)第218 、219 頁），嗣被告戊○○於96年7 月17日再\n    提出申請，臺東縣政府於96年7 月26日爰准將上開集合住宅\n    （地上5 層、地下1 層、1 棟共計49戶）變更為「旅館用途\n    」之事實，亦有臺東縣政府96年7 月26日府城建字第Ｚ00000\n    00000 號（第01次變更）使用執照影本1 份附卷可查（原審\n    卷(一)第266 至269 頁），足徵上開集合住宅共計49戶確已合\n    法變更「旅館用途」。\n 5、據上各節，被告戊○○在綠島之購地資金，已投入約3,500\n    萬元，另興建「海閣林休閒渡假酒店」之設計及工程費用，\n    亦達約9,700 萬元。此外，臺東縣政府確於96年7 月26日准\n    將上開集合住宅49戶變更為「旅館用途」等情，均如前述。\n    是公訴人起訴所執「被告戊○○等人以少數資金購地，且明\n    知無法取得合法旅館建築執照，而向被害人詐騙投資款」等\n    情，尚有未洽。\n(二)、公訴意旨另認被告戊○○等人，自91年4 月間起，由海閣林\n    公司各級業務員至婚友社或上網交友，以與被害人交往為藉\n    口，隱瞞沒有合法旅館使用執照之事實，誘騙被害人投資海\n    閣林休閒渡假酒店，且被害人不知業務員有抽取高額獎金，\n    並於被害人繳完款項後，業務員隨即失聯，以此方式詐騙被\n    害人投資款等情。惟：\n 1、依卷附合夥預定契約書觀之，本件黃復杰及戊○○於91年5\n    月間擬定之「舊合夥預定契約書」（以翻天創新公司名義對\n    外簽約），及戊○○於92年4 月擬定之「新合夥預定契約書\n    」（以「海閣林」公司名義簽約，但部分契約書第1 行誤繕\n    「翻天創新」公司，嗣經更正為「海閣林」公司），均載明\n    投資人與翻天創新公司（或海閣林公司），雙方係針對共同\n    開發海閣林休閒渡假酒店之合夥出資事宜之相關權益事項而\n    簽訂契約；而新合夥預定契約書第1 條之1 載明「海閣林休\n    閒渡假酒店預定座落於臺東縣綠島鄉○○○段1152、1152-1\n    、1152-2、1176、1178、1179、1180、1180-1、1183、1183\n    之1 、11  85地號土地上」等語；而被告戊○○自92年4 月\n    間起至同年8 月間止，確將募得之資金約3 千5 百多萬元，\n    購得上開契約書所載明之土地，另於92年8 月間起至95年2\n    月10日止，亦將募得之資金約9 千7 百多萬元，用以興建「\n    海閣林休閒渡假酒店」，又本件臺東縣政府業於96年7 月26\n    日已將上開集合住宅49戶變更為「旅館用途」等情，皆如前\n    述，是被告戊○○確實已依上開合夥契約內容，在綠島購地\n    並完成上開渡假酒店之興建。則公訴人起訴指稱被告等人，\n    隱瞞無法在綠島取得合法旅館使用執照，而向被害人誘騙投\n    資海閣林休閒渡假酒店一節，亦難採認。\n 2、就下列被害人證述觀之，上開海閣林公司業務員於行銷過程\n    中，並未特別以結婚或交往為藉口，而誘騙投資人參加投資\n    事宜，且投資之前，亦未受業務人員姿色誘惑之影響；另就\n    扣案之海閣林公司所有之會議記錄、人事資料、員工教育手\n    冊及客戶電話資料內容觀之，查扣之書面資料，主要皆是傳\n    授業務員招攬客戶之技巧，並未提及如何使用詐術欺騙投資\n    人，亦未刻意安排業務員至婚友社或上網尋覓投資對象；縱\n    部分業務員曾向某被害人表示參與投資後，始願意與被害人\n    結婚或繼續交往等語，然此屬業務員為求績效所為之個人行\n    為，僅係吸引異性客戶之行銷手段，難認被告等人即有以業\n    務員欲與客戶結婚或交往為藉口，而誘騙投資人參加投資之\n    情：\n (1)證人ｒ○○證稱：未○○向我推銷海閣林公司在綠島的投資\n    案，她希望我認購愈多愈好，但我衡量能力，只能購買2 個\n    單位27萬元，我把身分證、薪轉存摺、印鑑都交給她去向高\n    雄二信銀行辦理信用貸款，共貸款80萬元，扣除後投資款後\n    ，約剩50幾萬元在戶頭裡，未○○要我多貸些，用剩餘的錢\n    來扣本息，我自己也有動用過部分款項，當時未○○沒有說\n    要與我交往等語（警卷(一)第317 至319 頁、原審二卷第155\n    至162 頁）。\n (2)證人甲ｊ○證稱：91年9 月在溫馨婚友社認識史恆華，她對\n    我推銷海閣林公司的股份，說她哥哥是海閣林公司的主管，\n    她邀我去高雄市○○路的海閣林公司瞭解營運狀況，還播放\n    DVD 簡介要把綠島變成觀光勝地，她說如生活想要好一點，\n    就要有良好的投資理財觀念，我沒想要追求她，她當時也沒\n    說要與我交往，也沒有說不投資就不跟我交朋友，從她介紹\n    投資案到我決定投資的過程間隔大概3 、4 個月，經過評估\n    後，我才決定要投資3 單位共40萬5 千元，因我身上現金不\n    夠，一部分資金是向銀行貸款等語（警卷(一)第323 至325 頁\n    、原審二卷第163 至169 頁）。\n (3)證人ｔ○○證稱：94年2 、3 月時，去「合緣婚友社」認識\n    未○○，她介紹我投資海閣林公司綠島飯店開發案，跟我說\n    如將來要在一起，要有良好的投資理財觀，我自己決定投資\n    10單位共135 萬元，資金是未○○幫我貸款，未○○有告訴\n    我將於94年7 月試賣，10月正式營運，我於投資後有與朋友\n    到綠島看過工地，當時正在施工當中等語（警卷(一)第328 至\n    330 頁、原審二卷第170 至180 頁）。\n (4)證人吳永成（原名吳宣昌）證稱：92年12月在「溫馨婚友社\n    」認識未○○，她鼓吹我投資海閣林公司綠島飯店開發案，\n    她沒有承諾會跟我結婚或進一步的發展，最後是我與她一起\n    決定投資金額，共投資10單位合計135 萬元，並由她幫我處\n    理貸款事項，我有將存摺、印章交給她處理等語（警卷(一)第\n    341 至343 頁、原審二卷第189 至197 頁）。\n (5)證人Ｏ○○證稱：92年11月在「溫馨婚友社」認識未○○，\n    她鼓吹我投資海閣林公司的綠島飯店開發案，告訴我綠島開\n    發案將是綠島第一家五星級大飯店，前景看好，一定可賺錢\n    ，有多少股份就有多少紅利，沒告訴我可能會賠錢，當時投\n    資2 單位共27萬元，資金來源是貸款，當時有說開發案尚未\n    取得台東縣政府核准，但要先建設，我於投資前有先去海閣\n    林公司看過模型，之後有去綠島看工地，第1 次去現場看時\n    是空地，大概隔1 年後，第2 次再去看時，已經是蓋到5 樓\n    的空屋，就我當時的認知，投資風險是一定有的，現在的投\n    資又不是一定會賺錢等語（警卷(一)第348 至350 頁、原審二\n    卷第180 至189 頁）。\n (6)證人ｗ○○證稱：92年1 月時，經朋友介紹認識陳怡文跟午\n    ○○（原名史雅茜），不斷向我遊說公司的投資方案，但他\n    們沒有跟我說不投資海閣林公司就不跟我作朋友，他們跟我\n    介紹投資案約1 個月後，我決定投資4 個單位共計54萬元，\n    就我認知中，沒有何種投資是百分之百會賺錢，而沒有風險\n    ，認為被騙是那時電視和新聞都有報導等語（警卷(一)第359\n    至361 頁、原審二卷第227 至232 頁）。\n (7)證人乙ｒ○證稱：92年在交友中心認識史雅茜，她對我推銷\n    海閣林公司綠島飯店開發案，我拿錢投資是因我想追求她，\n    也想做投資多賺點錢，她沒說如果我不投資，就不跟我做朋\n    友，她有向我解說投資內容，我用貸款作為投資的資金來源\n    ，我買2 個單位共27萬元，當時史雅茜有跟我說明投資金額\n    的紅利算法，於飯店營利後賺錢的情況下會發紅利，我是後\n    來看到報紙才覺得被騙，但我的認知裡，沒有投資是百分之\n    百會賺錢而絕無風險等語（警卷(一)第368 至370 頁、原審二\n    卷第233 至240 頁）。\n (8)證人黃○○證稱：93年在合欣婚友社認識史雅茜，她沒有要\n    求我投資，當時她要去海閣林公司簽約要我陪她去，幫她看\n    契約內容，之後閒聊時，她問我是否要投資，我當時想賺多\n    一點錢，所以投資3 單位共40萬5 千元，並以貸款取得投資\n    的資金，史雅茜有說飯店已經動工，並說公司有網站，上面\n    有資料及工程進度，我上網查看有一些主體結構正在蓋，我\n    認為沒有哪種投資是完全零風險，但她也沒說這件投資案是\n    有風險的，報紙刊登後，資料傳到我營區，長官說我非法投\n    資，我才認定本件投資案是場騙局（警卷(一)第383 至385 頁\n    、原審二卷第245 至251 頁）。\n (9)證人乙Ｌ○證稱：93年間在「和信婚友社」認識史雅茜，她\n    跟我說投資海閣林公司綠島開發案，如飯店正常營運有賺錢\n    時，每個單位可獲利8 千元左右，當時想賺錢，投資15單位\n    共計202 萬5 千元，我以貸款取得投資的資金，我決定投資\n    15個單位，是史雅茜跟我說能貸到多少錢就投資多少單位，\n    她沒說我不投資就不再與我聯絡等語（警卷(一)第393 至397\n    頁、原審二卷第256 至260 頁）。\n(10)證人甲申○證稱：93年在「溫馨婚友社」認識Ｃ○○，說將\n    來要在一起，我要有良好的投資理財觀念，她介紹海閣林在\n    綠島蓋度假飯店讓我知悉，我本來不想投資，她表現出不高\n    興的態度，我與她溝通後，決定投資9 個單位，後來投資10\n    單位135 萬元，最後1 個單位是跟劉佩妤買的，劉佩妤也是\n    在「溫馨婚友社」認識的，他們都沒有說不投資就不跟我往\n    來，投資的金額，部分是貸款、部分是現金，Ｃ○○陪我到\n    海閣林公司簽約前，有有仔細看過合約內容，她有跟我講投\n    資後如何分紅、何時開始獲利回收，但沒說明投資案可能會\n    賠錢，也沒分析投資案的風險，只說是不錯的投資案，投資\n    後每年可分到蠻多紅利，從Ｃ○○介紹投資到我正式簽約，\n    前後約2 、3 個月，我當時的認知沒有何種投資是完全是零\n    風險的，是新聞報導後，我才感覺被騙等語（警卷(一)第430\n    至432 頁、原審三卷第75至87頁）。\n(11)證人甲ｈ○證稱：92年在「蕙萊婚友社」認識Ｃ○○，她在\n    海閣林公司上班，說他親戚有在海閣林公司上班或投資，她\n    要我投資海閣林公司，說該投資案是溫泉休閒中心，有高獲\n    利，1 個單位13萬5 千元，我購買7 個單位合計94萬5 千元\n    ，她帶我去公司，有拿出綠島建設藍圖給我看，當時我是看\n    設計圖判斷才決定投資，我拿扣繳憑單等資料給Ｃ○○向萬\n    泰等3 家銀行辦貸款，貸款金額合計166 萬元，辦好後她帶\n    我到銀行開戶領錢，交付投資款後，我還是能順利聯絡到Ｃ\n    ○○，本件我看蘋果日報才知道這是詐騙集團，我不知道海\n    閣林公司在綠島的開發案，已經取得旅館的使用執照等語（\n    警卷(一)第435 至437 頁、原審三卷第88至94頁）。\n(12)證人乙ｉ○證稱：93年在「欣緣婚友社」認識Ｃ○○，當時\n    投資理財是想讓家人過得更好一點，所以投資海閣林公司的\n    綠島飯店開發案，我以現金投資1 單位13萬5 千元，我忘記\n    Ｃ○○或海閣林公司有無跟我說明投資案有可能會賠錢或獲\n    利不低，海閣林公司好像有跟我和解，本件我不追究了等語\n    （警卷(一)第452 至454 頁、原審三卷第94至96頁）。\n 3、海閣林公司業務員於行銷過程中，縱未向投資人告知每賣出\n    1 單位（13萬5 千元），業務員（沒有底薪）可抽取獎金（\n    專員為9 千至1 萬元不等，主任為1 萬3 千元），另上開公\n    司總經理、協理、經理，依階級可分別抽取3 千元至2 萬3\n    千元不等獎金之情，惟本件被告等人是否成立被訴常業詐欺\n    犯行，係以投資人於海閣林公司（或翻天創新公司）簽訂上\n    開合夥預定契約書時，被告等人有無施用詐術為判斷基準，\n    至於行銷獎金如何分配抽取及業務員與公司間薪資酬勞之內\n    部關係，以客觀社會常情，一般業務員在外推銷公司產品（\n    例如房屋、汽車、保險、信用卡、美容商品等），亦少有向\n    客戶說明業務員如何抽佣，分配獎金等情，無從僅以業務員\n    抽取獎金偏高，遽認被告等人即有不法詐欺之犯意與犯行，\n    且如上開被害人之證述，被害人訂約投資時，均已考量相關\n    之投資因素（如自身經濟能力、決定貸款額度、或曾到綠島\n    查看工程進度、或知悉本件仍有投資風險存在等），足徵被\n    害人均係出於自由意志而決定投資購買，並非陷於錯誤所致\n    。\n(三)、公訴意旨另以海閣林休閒渡假酒店，至今仍未營運，而認投\n    資之被害人確屬受騙等情。然上開新（舊）合夥預定契約書\n    第6 條固載上開酒店須於93年底公告正式營運等情，惟被告\n    戊○○於92年8 月間在綠島購得上開土地後，即委請蔡國勇\n    建築師規劃設計，於93年4 月19日由銘泉營造公司施工，並\n    於94年12月20日完工等情（如上所述），又上開工程略有遲\n    誤之原因，亦據證人即銘泉營造公司股東賴振東於警詢陳明\n    ：本件營造工程包括結構工程、裝修工程及水電工程等3 項\n    ，原本預計在94年8 月底以前完工，因離島天氣不穩定、運\n    輸補給不方便，且綠島工人不容易掌握等因素，才造成本件\n    工程遲誤（警卷(一)第273 頁），且於95年2 月10日取得上開\n    集合住宅使用執照，並據臺東縣政府於96年7 月26日准將上\n    開集合住宅變更為旅館用途等情（如上所述），復參以上開\n    酒店施工期間（93年4 月19日施工起至94年12月20日完工）\n    ，因海閣林公司於94年6 月8 日遭警搜索，並偵辦被告等人\n    及約談投資人，經媒體報導後致使原投資人紛紛退股，其他\n    民眾亦不敢冒然進行投資，造成海閣林公司資金不足，無法\n    繼續進行上開酒店裝潢及其他準備營運事項，導致無從營運\n    之情。是此部分亦難僅以上開酒店遲未營運一節，遽認被告\n    等人即有詐騙意圖。\n(四)、公訴意旨復以截至94年6 月8 日經警查獲，被害人1,336 人\n    投資3,654 個單位，查出被害人共計196 人，詐得總金額總\n    計4 億9329萬元；又投資人繳交款項未依實際收支情形確實\n    作帳，除扣掉管銷及上開業務獎金之外，餘均流入被告戊○\n    ○私人帳戶內，且海閣林公司辦公處所之房地產亦登記被告\n    戊○○名下，而認有詐騙情事。惟：\n 1、本件尚有1 千餘名投資人均未出面向檢、警機關提出告訴，\n    或以證人身分說明本件被騙之經過情形為何？起訴意旨僅憑\n    扣得之合夥預定契約書，遽認受騙被害人高達1,336 人，尚\n    乏依據。又被告戊○○等人如於收受投資款時，即自始有意\n    詐騙，何於偵、審期間仍持續進行上開酒店之興建事宜，至\n    終取得旅館之使用執照。另海閣林公司於案發後，亦與被害\n    人吳宣昌等33人陸續達成和解，並同意被害人退夥等情，有\n    卷附和解名單、刑事撤回告訴狀及和解退夥切結書在卷可參\n    （原審一卷第184 至202 頁、原審四卷第293 至297 頁）。\n    益證被告等人確有與投資人辦理退夥之誠意。\n 2、被告戊○○雖承募得投資金額計約4 億8 千多萬，然於91年\n    6 月24日起至92年3 月5 日間止，即將募得投資款項7, 200\n    多萬元匯至黃復杰所指定之帳戶內，供黃復杰提領使用（即\n    上開另案共同業務侵占部分），又購地資金亦投入約3,500\n    萬元，另興建上開酒店之設計及工程費用，亦支出達約9,70\n    0 萬元；而依海閣林公司抽取獎金之計算，發放業務獎金約\n    計1 億8 千萬元；另依卷附海閣林公司提出該公司歷年之會\n    計科目明細表、總分類帳、損益表觀之，購買公司資產約花\n    費2,000 萬元、公司內勤職員薪資已發放約1,500 萬元、公\n    司水電及租金等開銷約3,500 萬元；又戊○○前於92年3 月\n    間遭歹徒強押，而由海閣林公司支付650 萬贖款等情，亦有\n    臺灣高雄地方法院檢察署92年度偵字15924 號起訴書及原審\n    法院93年度重訴字第121 號判決書在卷可參。則被告戊○○\n    所為上開支付款項總額已達4 億6 千多萬元。此外，衡諸客\n    觀常情，於上開酒店購地、興建、申請相關執照等數年過程\n    中，定尚有其他支出而無單據或發票證明等相關之公關、交\n    際費用等，是公訴人起訴指稱本件投資人繳交款項後，扣除\n    管銷及上開業務獎金之外，均流入被告戊○○私人帳戶等情\n    ，尚與上開事證未合。至於公訴意旨所稱「投資人繳交款項\n    未經合格之會計師依實際收支情形確實作帳；海閣林公司辦\n    公處所之房地產亦登記被告戊○○名下」等情，係屬被告戊\n    ○○於收受投資款後所為之帳務管理是否確實，有無挪用海\n    閣林公司款項，而與本件起訴意旨所指之常業詐欺取財犯行\n    無涉。且亦尚乏其他積極證據佐認被告戊○○是否涉及未經\n    起訴之其他罪嫌部分，更無從以此等情狀，據以推論被告等\n    人於向本件被害人收受投資款之初，即有何基於詐欺取財之\n    不法犯意。\n六、綜上所述，本件在偏遠離島地區（綠島）投資合夥經營上開\n    酒店，其投資態樣本具有不確定性或交易風險，例如覓尋土\n    地困難、核發建照不易、施工進度遲誤、旅館執照延宕等因\n    素，而被告等人招攬投資之上開酒店，固未能依約如期營運\n    ，然此屬民事投資合夥關係衍生之債權債務糾紛，不能僅以\n    事後上開酒店未能營運，推論被告等44人自始即具有常業詐\n    欺之犯罪意圖。公訴人起訴所舉上開證據，均不足採為認定\n    被告等44人有修正前刑法第340 條常業詐欺犯行之積極證明\n    。此外，復查無其他積極證據足資證明被告等44人有何被訴\n    常業詐欺犯行，被告等44人被訴此罪，均屬不能證明，原審\n    因而為被告等44人均無罪之諭知，核無違誤。\n七、原審公訴人所提上訴意旨，猶執起訴所據各節，指摘原判決\n    不當，為無理由（如下所述），應予駁回。\n(一)、上訴理由略以：\n 1、原審法院判決理由一方面認定「被害人均係合夥投資關係」\n    ，另一方面又認定「業務員於行銷過程中，每賣出1 單位（\n    13萬5 千元），業務員（沒有底薪）可抽取獎金（專員為9\n    千至1 萬元不等，主任為1 萬3 千元），另上開公司總經理\n    、協理、經理，依階級可分別抽取3 千元至2 萬3 千元不等\n    獎金之情事」之理由，試想豈有公司「合夥」人出資金額先\n    由公司各層級主管、業務員層層抽成的道理？且發放給業務\n    員獎金竟至少高達新台幣（下同）1 億8 千萬元以上，顯見\n    本案渠等被告係以簽訂「投資契約書」之脫法方式，用以「\n    詐欺」廣大投資人使之「陷於錯誤」而將大筆金錢付出，供\n    被告戊○○等44人分層瓜分高達1 億8 千餘萬元之吸金款項\n    。渠等無異係以「多層次傳銷」變種手法「收受投資」，「\n    使加入股東或其他名義」「向多數人或不特定人收受款項或\n    吸收資金」，而與民法「合夥」關係顯然不同。原審未予查\n    明，混淆「合夥」與「詐欺吸金」之界限，判決所載理由顯\n    然矛盾，且與社會通念嚴重不符，難稱妥當！況被告等人以\n    「高額紅利」及「迅速還本」為號召之吸收資金行為，顯係\n    「約定與本金顯不相當之紅利、利息、股息或其他報酬」情\n    形，尚有違反銀行法第125 條、第29條、第29條之1 可能，\n    亦經原審法院審理時當庭諭知上開罪名，詎原審判決理由中\n    未見說明有關被告等人違反前揭銀行法罪名部分，判決所載\n    理由顯有疏漏！\n 2、原審判決將本件募得投資金額共計4 億8 千多萬用途予以切\n    割，顯然混淆一般公司「合理」支出款項，及「吸金公司」\n    支付予吸金業務員獎金之界限。蓋一般「渡假飯店開發公司\n    」主要業務係在於「開發土地」「興建飯店」，公司職員之\n    聘請主要工作亦應著眼於此。詎本案海閣林公司之員工至少\n    高達43人以上之主要工作內容，卻是「向多數人或不特定人\n    收受款項或吸收資金」且「從中分層抽取獎金」，所謂「內\n    勤職員」主要工作亦在管理「業務員」吸收資金事項，共支\n    出高達1 億9 千5 百萬餘元款項，佔被害人受詐騙之4 億8\n    千萬元款項至少5 分之2 ，與公司「合夥」通念顯然不同！\n    況「購買公司資產約花費2,000 萬元」，海閣林公司位於高\n    雄市之房地產均登記在被告戊○○名下；「綠島購得土地，\n    部分土地登記在戊○○名下」，均與合法經營公司登記資產\n    方式有違。\n 3、本案於95年5 月24日經本署起訴，被告等人為脫免刑責，只\n    得謀求「取得旅館使用執照」以求解套，與「積極營運酒店\n    情形」顯屬有間，原審法院未親自至綠島地區實地勘驗酒店\n    之建築規格、設計、內部裝潢是否具備五星級飯店等級規格\n    ，實際有無經營五星級飯店可能，徒以被告夥同之建築師所\n    提出文件，逕認「戊○○顯有積極營運上開酒店企圖」，罔\n    顧戊○○以興建旅館代替五星級飯店之情形，論理稍嫌速斷\n    ！況被告戊○○為脫免刑責，僅願意以被害人受詐騙投資款\n    項一成至三成予以和解，在被害人1,336 人中亦僅與被害人\n    吳宣昌等33人達成和解，和解金額僅1 千餘萬元，與被害人\n    總受詐騙金額4 億8 千餘萬元相比，無異杯水車薪，原審法\n    院據之認為「被告等人顯有進行退夥誠意」，亦難稱妥當。\n 4、況據被告戊○○當庭供承：「顏銘震他是台中地區的代理商\n    ；甲ｄ○算是公司的高階主管。」「公司協理、經理、主任\n    或襄理、專員或業務員只有一個共同身分即業務員，因為經\n    理也要做業務，他們只是職稱不同，但都要做業務」「當時\n    海閣林公司負責財務的人是乙丙○」等語，參以被告乙ｆ○\n    等人另案（臺灣高雄地方法院97年度重訴字第76號）涉及「\n    全方位停車場」詐欺吸金案件，益徵渠等為常業詐欺慣犯，\n    經常變換詐欺手法用以吸金，而海閣林公司大部分幹部、職\n    員主要工作內容即為「吸金」，甚至在高雄、台中地區亦設\n    立分公司用以吸金，原審法院均未審酌及此，遽為無罪諭知\n    ，顯然難稱妥當。又被告甲辛○當庭供承：「公司有提供很\n    多方式讓業務選擇去找客戶」「包含婚友社、陌生開發或朋\n    友之間等」等語，參以被告乙黃○供承：「公司叫我們去婚\n    友社找客戶」等語；被告午○○供承：「到婚友社找客戶是\n    公司建議的方案」等情，均足徵海閣林公司訓練大批員工到\n    婚友社招攬客戶，藉口交友為幌子，以高額紅利及迅速還本\n    為號召，並隱瞞「旅館未取得建築執照及使用執照」之現況\n    ，大量吸收現、退役軍人資金，甚至積極主動要求被害人向\n    銀行信用貸款高額款項以「吸收資金」。原審法院以「被害\n    人訂約參與投資，均係充分考量並盤算相關條件，非陷於錯\n    誤所致」「查扣之書面資料，主要皆是傳授業務員招攬客戶\n    之技巧，並未提及如何使用詐術欺騙投資人，亦未刻意安排\n    業務員至婚友社或上網尋覓投資對象」為由，諭知被告等人\n    均無罪，除與被告供承明顯不符合外，更嚴重違背社會對於\n    正常投資之通念，混淆「吸金」與「投資」界限。\n 5、據證人ｒ○○證述：「當時未○○與海閣林公司的人並無告\n    知我，該投資飯店的案件在台東縣政府當時並未經核可」「\n    她只說當時只缺資金」「海閣林公司相關人並無完全告知我\n    該投資案的風險及內容」等語；證人甲ｊ○證稱：「當時未\n    ○○跟海閣林公司相關人推銷綠島投資案時，完全沒有告知\n    海閣林公司當時尚未取得台東縣政府核准設立旅館」「若當\n    時知道海閣林公司並未取得台東縣政府的核准，我不願意拿\n    錢出來投資」「未○○在投資時沒有說本件投資他可以抽佣\n    」「當初未○○邀請我投資時說飯店兩、三年後蓋好，可以\n    分得錢」「每年紅利可以分」等語；證人ｔ○○證稱：「當\n    時未○○與我交往虛虛實實」「當時未○○跟我說如將來要\n    在一起要有好的投資觀，所以才要求我投資綠島開發案」「\n    （貸款）錢核撥後未○○就不跟我聯絡」「當時未○○及海\n    閣林公司人員並無跟我說明本案綠島開發案尚未經台東縣政\n    府核准」「若當時知悉本情狀我不可能還願意投資」「就女\n    朋友的定義，當時未○○算是在交往中」「我有明確跟她說\n    我喜歡她」「她有說過如果不投資大家就不用往來了」「是\n    因為她這樣講我才投資」「純粹都是貸款」「未○○鼓吹投\n    資時，並無跟我說本投資案她可以抽佣」「未○○說負責人\n    是她親戚」等語，並當庭指認在庭被告戊○○說未○○曾說\n    那是她哥哥；證人Ｏ○○證稱：「未○○態度很明顯，如果\n    我不投資本開發案就不往來」「她說很穩，但賺多賺少不一\n    定」等語；證人吳永成（原名吳宣昌）證稱：「當時未○○\n    幫我處理貸款事項」「我覺得被騙」「海閣林公司人員好像\n    說一股可以分多少，但沒具體說明，當時說一股可分得近萬\n    元。」「有說過一定賺，不會賠錢，蓋好後還可以轉賣」「\n    貸款是我與未○○一起決定」「講到這個是說為了我們以後\n    ，所以我才尊重她」等語，均足徵被告未○○有透過婚友社\n    管道，陸續認識7名被害人，並「以交往為藉口，隱瞞海閣\n    林公司真實狀況，以高額紅利為號召」誘騙被害人以吸收資\n    金之情形。\n 6、據證人ｗ○○證述：「我拿錢出來投資後陳怡文和午○○就\n    不和我聯絡」「若知道該投資案沒有經過政府許可，我不願\n    意投資」「當時被告等人沒有跟我說該飯店投資案有賠錢可\n    能」「沒有跟我分析該投資案的風險」等語；證人乙ｒ○證\n    稱：「當時想追求她，也做投資多賺點錢，才拿錢跟被告史\n    雅茜投資海閣林公司的綠島開發案」「資金來源係貸款」「\n    當時史雅茜或海閣林公司的人有跟我說明投資錢的紅利之算\n    法」「如果我知道當時海閣林公司的綠島開發案沒有經過政\n    府的許可，我不願意拿錢出來投資」等語；證人Ｙ○○證稱\n    ：「貸款是史雅茜提議」「拿錢出來投資後史雅茜就不和我\n    聯絡」「當時史雅茜及海閣林公司的人只有說明當年度就可\n    以建造完畢就可以營運可以發紅利」等語；證人黃○○證稱\n    ：「當時不知道史雅茜在我的投資案內可以抽成，是後來本\n    件事情有風聲出來時，我有去問，該婚友社告訴我史雅茜有\n    跟會員推銷東西，我以為是公司在亂講話有向她求證，她跟\n    我說沒有。」「當初說要蓋五星級飯店，現在只蓋一般飯店\n    」等語；證人乙Ｕ○證稱：「若我知道投資當時海閣林公司\n    尚未取得綠島開發案正式許可，我不會願意投資」「是史雅\n    茜找我投資」等語；證人乙Ｌ○證稱：「史雅茜跟我說投資\n    海閣林公司綠島開發案後每個單位都可以獲利八千元左右」\n    等語；證人Ｒ○○證稱：「當時史雅茜及海閣林公司人員鼓\n    吹我投資綠島開發案，標榜是綠島第一家五星級酒店」「是\n    史雅茜提議向銀行貸款來投資」等語；證人Ｕ○○證稱：「\n    她當時好像叫史雅玲（音譯）」「當時在交友社認識她，她\n    說要跟我交往，她說為了爾後的生活或退休後的生活要投資\n    」「史雅玲就是在場之午○○」「說投資13.5萬元，時間到\n    時公司會以50萬元買回股權」「她說會賺錢」等語；證人乙\n    己○證稱：「史雅茜鼓吹我去投資本件投資案」「和我接觸\n    時是用假名史雅玲」「她說如果我與你交往，未來做何打算\n    」「當時午○○是說不投資就不往來」「因為她這樣講我才\n    投資」「94年8 月間開始不接我的電話」「午○○或海閣林\n    公司的人有跟我說投資一定會分紅」等語；證人甲申○證稱\n    ：「我當時職業為軍人」「Ｃ○○有跟我說將來在一起，要\n    有良好的投資理財觀念」「本來我不想投資，她表現出不是\n    很高興的態度，我與她溝通幾次後，就先投資兩個單位，錢\n    是貸款取得後投資，陸陸續續在其身上投資9 個單位，一個\n    單位13.5萬元」「Ｃ○○好像有說她的親戚在海閣林公司上\n    班」「當時Ｃ○○跟海閣林公司人員，沒有跟我說綠島開發\n    案沒有經過台東縣政府核發執照」「Ｃ○○當時沒有無跟我\n    明白說明該投資案有可能賠錢」「印象中，Ｃ○○跟我說紅\n    利的年息蠻高的」「Ｃ○○說這個投資還不錯的投資案，我\n    投資後，每年可以分到蠻多紅利」「她沒有明講可抽成，她\n    說她不是公司的人，只介紹朋友去。」「如果我知道Ｃ○○\n    跟很多婚友社會員鼓吹投資的話，我應該不會去投資」「後\n    來我得知軍中學長也是Ｃ○○介紹去投資，也是在溫馨婚友\n    社認識，是軍中政三監察官約談後得知」「不知道本件投資\n    案劉佩妤可以抽成」「在決定投資之前，我沒有無仔細評估\n    過本投資案」「斷斷續續買到九個單位後，約Ｃ○○就比較\n    約不出來，打電話給她不是沒有接電話，就是口氣不好」等\n    語；證人甲ｈ○證稱：「當時不知道本件投資案，Ｃ○○可\n    以中從抽成」「我拿扣繳憑單、身分證正本、還有印章等交\n    給Ｃ○○，她拿去辦理貸款，辦好後，她帶我到銀行開戶領\n    錢」「被告Ｃ○○跟海閣林公司人員，有跟我說該投資案有\n    高獲利」「剛開始說我買七個單位第一年可能有幾十萬元獲\n    利，一個單位一年只有幾萬元收入」「她說一定獲利」「如\n    果沒有這樣的獲利情形，我不會投資」「都是Ｃ○○講，如\n    果我投資的話會有額外收入，生活會過得比較好」「Ｃ○○\n    有跟我說如果不投資就不跟我聯絡了」等語；證人乙ｉ○證\n    稱：「我是職業軍人」「是Ｃ○○介紹我投資該開發案」等\n    語；證人乙ｕ○證稱：「詐騙我的人名字叫林麗雯，當時她\n    是我女友，後來離開了，林芷萱不是她的真實姓名，騙我時\n    叫林麗雯，進海閣林公司工作後才改名林芷萱」等語；證人\n    乙Ｙ○證稱：「如果我知道當時海閣林公司就綠島投資興建\n    五星級休閒渡假大飯店尚未取得台東縣政府核發，我不會還\n    願意拿94.5萬元出來投資」等語；證人甲己○證稱：「過了\n    一年後我打電話到公司，才發現公司不見了，始知被騙」「\n    若我知道當時海閣林公司當時尚未取得旅館建築執照，我不\n    會會投資」等語；證人乙ｗ○證稱：「貸款核發下來後海閣\n    林公司有兩個業務員自行將款項提領出來」「當時在陽信銀\n    行辦理貸款完畢後，存摺、印章他們取走」等語，均足徵海\n    閣林公司所屬「辣妹兵團成員」利用婚友社機會認識現、退\n    役軍人用以吸金，或以假名交往，或刻意隱匿海閣林公司綠\n    島投資案之真實狀況，或藉口高額紅利吸引投資，並非單純\n    「業務員為求績效所為之個人行為」，亦非「充其量僅係吸\n    引異性客戶之行銷手段」，而係海閣林公司用以吸金之普遍\n    手段，光是在婚友社之受害人即高達數百人。\n 7、被告戊○○為公司首腦；被告乙丙○為該公司財務；被告甲\n    ｕ○、顏銘震、甲ｄ○、甲辛○、乙ｈ○、乙地○、申○○\n    、乙Ｆ○、吳俊德、甲Ｂ○、乙Ｒ○為該公司之核心幹部；\n    另外被告未○○詐騙人數7 人、午○○詐騙人數12 人 、Ｃ\n    ○○詐騙人數3 人、Ｉ○○詐騙人數6 人、Ｊ○○詐騙人數\n    4 人、Ｌ○○詐騙人數6 人、Ｍ○○詐騙人數5人 、Ｎ○○\n    詐騙人數3 人、Ｘ○○詐騙人數5 人、李瓊鳳詐騙人數1 人\n    、ｈ○○詐騙人數10人、林詩怡詐騙人數1人 、甲子○詐騙\n    人數5 人、甲Ｉ○詐騙人數1 人、甲Ｊ○詐騙人數4 人、甲\n    Ｐ○詐騙人數4 人、甲ｆ○詐騙人數3人 、甲Ｒ○詐騙人數\n    3 人、甲ｂ○詐騙人數4 人、甲ｄ○詐騙人數1 人、甲ｍ○\n    詐騙人數9 人、甲ｓ○詐騙人數2人 、甲ｖ○詐騙人數9 人\n    、甲ｗ○詐騙人數2 人、黃彩惠詐騙人數2 人、乙Ｃ○詐騙\n    人數1 人、乙黃○詐騙人數7人 、乙Ｄ○○詐騙人數4 人，\n    乙Ｇ○詐騙人數1 人、蔡幸（）（原名蔡宜庭）詐騙人數\n    4 人、乙Ｘ○詐騙人數1 人、乙ｋ○詐騙人數2 人，均惡性\n    非輕。且被告及其辯護人均對被害人於警詢中之證述不爭執\n    證據能力，詎原審法院對被害人於警詢指證予以忽略。\n(二)、經查：\n 1、本件上訴理由第1 、2 項雖以「豈有公司合夥人出資金額先\n    由公司各層級主管、業務員層層抽成的道理？且發放給業務\n    員獎金竟高達1 億8 千萬元以上」、「將本件募得投資金額\n    共計4 億8 千多萬用途予以切割」，而認被告等人係以簽訂\n    「投資契約書」之脫法方式，詐欺投資人使之陷於錯誤而付\n    出金錢，被告等人係以「多層次傳銷」變種手法「收受投資\n    」，而與民法「合夥」關係顯然不同。又原判決亦混淆一般\n    公司「合理」支出款項，及「吸金公司」支付予吸金業務員\n    獎金之界限云云，然：\n (1)投資合夥經營事業本須有一定之業務支出或人事成本等開銷\n    ，而業務獎金抽成多寡，繫於投資人與公司間之契約或協議\n    內容，本件被告等人係被訴常業詐欺罪嫌，亦即被告等人成\n    罪與否，自應審究投資人（即公訴人所指之被害人）與海閣\n    林公司簽訂上開合夥預定契約書時，被告等人有無施用詐術\n    之舉，而非純以該公司發放業務獎金多寡或如何分配使用投\n    資款項等情為斷。至於投資人倘對被告等人執行合夥關係之\n    履約情形有所疑義，亦屬雙方如何循民事程序予以處理，原\n    審公訴人提起上訴據此主張被告等人於向投資人收受投資款\n    時，即有詐欺之不法意圖等語，尚難成立。\n (2)本件投資人所簽訂之投資契約書，係屬經合格律師製作之契\n    約書（如下所述），亦難認被告等人有何以簽訂「投資契約\n    書」之脫法方式，詐欺投資人使之陷於錯誤而付出金錢之事\n    實。何況，海閣林公司之登記股東5 人，除被告戊○○外，\n    則為被告甲ｄ○、甲辛○、申○○、乙ｈ○等4 人，而被告\n    戊○○係屬最大股東（佔9 成以上），此有卷附之海閣林公\n    司股東繳款明細表、股東名簿足佐（見警卷(四)第1601、1602\n    頁），復參以被告戊○○所供「公司協理、經理或業務員，\n    只有一個共同身分即業務員」等情，則身兼股東之被告甲ｄ\n    ○、甲辛○、申○○、乙ｈ○等4 人雖屬公司之協理、經理\n    身分，但仍與其他共同被告等人之業務員身分無異，是除被\n    告戊○○外之其餘共同被告43人，均屬本於海閣林公司之業\n    務內容及被告戊○○之指示，以經合格律師製作之契約書從\n    事招攬投資人，亦難認本件除被告戊○○外之其餘共同被告\n    43人有何被訴共同常業詐欺之犯意存在。\n 2、本件上訴理由第1 、2 項另主張「被告等人以高額紅利及迅\n    速還本為號召之吸收資金行為，顯係約定與本金顯不相當之\n    紅利、利息、股息或其他報酬，有違反銀行法第125 條、第\n    29條、第29條之1 可能」、「海閣林公司位於高雄市之房地\n    產均登記在被告戊○○名下；綠島購得土地，部分土地登記\n    在戊○○名下，均與合法經營公司登記資產方式有違」等情\n    ，然本件投資人與海閣林公司（或翻天創新公司）簽訂上開\n    合夥預定契約書或收據之內容，並無約定有何「高額紅利」\n    及「迅速還本」等情，且無其他證據足以證明被告等人與投\n    資人如何約定相當利率之紅利或報酬之事實，自難證明被告\n    等人有何觸犯上開銀行法罪嫌之情；又上開契約書係由律師\n    草擬一節，已據證人即契約見證律師單文程於偵查中具結證\n    實在卷（見偵七卷第33頁），則被告等人以經合格律師製作\n    之上開契約書與投資人簽訂而收受投資款，亦難認被告等人\n    有何違反銀行法之犯意。至於上開公司房產、綠島土地如何\n    登記等情，亦屬被告等人執行合夥關係之履約糾葛，應由雙\n    方循民事程序確認解決。原審公訴人提起上訴執此主張，亦\n    非可採。\n 3、本件上訴理由第3 項固陳「被告等人經起訴後為脫免刑責，\n    只得謀求取得旅館使用執照以求解套」、「原審法院未親自\n    至綠島地區實地勘驗酒店之建築規格、設計、內部裝潢是否\n    具備五星級飯店等級規格，實際有無經營五星級飯店可能」\n    、「被告戊○○為脫免刑責，僅以投資款項一至三成與33名\n    被害人和解」等情，惟被告戊○○等人於綠島購地、興建旅\n    館欲經營上開酒店之事實，業經原審認定如上，經核與卷證\n    資料並無相違，則被告等人按照工程進度，依序申辦取得旅\n    館使用執照等過程，應合於常情事理，無從僅以被告等人曾\n    遭起訴上開罪嫌，遽以推論臆測即屬「脫免刑責以求解套」\n    。又上開酒店之興建規模，已有卷附之上開酒店新建工程申\n    請建築執照流程說明相關資料、建造執照、施工程藍圖、工\n    程合約書、水電工程配置圖、鋼構配置圖、施工圖本、平面\n    配置圖、工程照片、綠島海閣林遊樂業整合性管理系統建議\n    書及餐飲管理系統建議書、使用執照可佐，此部分待證事實\n    已明，則原審未親赴綠島履勘，自無不當。至於該酒店之內\n    部裝潢是否具備五星級飯店等級規格，實際有無經營五星級\n    飯店可能等情，均有賴日後之內部設計、規劃、裝潢及管理\n    ，而此部分營運之延宕因素，業據原審敘明如上，衡諸常情\n    ，並無不合。此外，和解成立與否在於雙方對於退夥金額之\n    認知是否合致，自無必然需以若干成數即能達成和解之情形\n    ，則被告戊○○以投資款項一至三成與33名被害人和解之情\n    ，即屬上開部分投資人對於和解條件之主觀認知，亦難據此\n    而認此屬被告戊○○之「脫免刑責」，從而，此部分上訴主\n    張均無可採。\n 4、本件上訴理由第4 、5 項雖以被告戊○○、甲辛○、午○○\n    等人供詞，及參以被告乙ｆ○等人另案（臺灣高雄地方法院\n    97年度重訴字第76號）涉及「全方位停車場」詐欺吸金案件\n    ，而認被告等人為常業詐欺慣犯，海閣林公司大部分幹部、\n    職員主要工作內容即為「吸金」，且訓練大批員工到婚友社\n    招攬客戶，藉口交友為幌子，吸收現、退役軍人資金等情，\n    然被告乙ｆ○另涉他案部分，係屬其個人另案情形，公訴人\n    起訴既未包含此部分，自難以此另案情形，推論本件其他共\n    同被告之被訴犯行；又被告等人經營上開酒店之合夥事業，\n    於招募合夥資金期間，自然業務主力在於招攬投資人，而擴\n    充行銷人脈以利招攬業務，更屬社會常見之商業推銷，而推\n    銷招攬僅係民事契約要約行為之一部分，至於投資人之承諾\n    成交即簽約與否，則屬投資人之自我判斷範圍，以此部分上\n    訴理由所載之上開被告供詞內容，無從逕認被告等人即屬「\n    詐欺吸金」而非「投資入夥」。\n 5、本件上訴理由第5 、6 項雖以「證人ｒ○○、甲ｊ○、ｔ○\n    ○、Ｏ○○、吳永成（原名吳宣昌）」等人證詞，而認被告\n    未○○有透過婚友社管道，陸續認識上開被害人，並以「交\n    往為藉口，隱瞞海閣林公司真實狀況，以高額紅利為號召誘\n    騙被害人以吸收資金等情，及以「證人ｗ○○、乙ｒ○、Ｙ\n    ○○、黃○○、乙Ｕ○、乙Ｌ○、Ｒ○○、Ｕ○○、乙己○\n    、甲申○、甲ｈ○、乙ｉ○、乙ｕ○、乙Ｙ○、甲己○、乙\n    ｗ○」等人證詞，並認海閣林公司所屬「辣妹兵團成員」利\n    用婚友社機會認識現、退役軍人用以吸金，或以假名交往，\n    或刻意隱匿海閣林公司綠島投資案之真實狀況，或藉口高額\n    紅利吸引投資，係海閣林公司用以吸金之普遍手段，光是在\n    婚友社之受害人即高達數百人等情，然原判決就此部分，業\n    已敘明「被告戊○○確實已依上開合夥契約內容，在綠島購\n    地並完成上開渡假酒店之興建；海閣林公司業務員於行銷過\n    程中，並未特別以結婚或交往為藉口，而誘騙投資人參加投\n    資事宜，且投資人於交款前，亦未受業務人員姿色誘惑之影\n    響，縱部分業務員曾向某被害人表示參與投資後，始願意與\n    被害人結婚或繼續交往等語，然此屬業務員為求績效所為之\n    個人行為，僅係吸引異性客戶之行銷手段，難認被告等人即\n    有以業務員欲與客戶結婚或交往為藉口，而誘騙投資人參加\n    投資」等情（如上所述），又上訴意旨所載被害人指稱之業\n    務員即被告未○○、午○○（原名史雅茜）、吳佳潁等人固\n    承其等有透過婚友社管道開發客戶一節，但均否認有以「與\n    被害人交往」為條件誘騙被害人投資，而依上開被害人及卷\n    附之其他投資人之陳述，部分投資人雖有提及公司業務員曾\n    對渠等表示「將來在一起」、「與其交往」、「不投資就不\n    來往」、「投資是為了以後」等語，惟參以當前社會男女交\n    往之情形，雙方對於所謂「交往」、「為以後」等情之認定\n    ，常因個人主觀情感之因素而有異，且是否繼續交往或僅係\n    維持普通朋友之誼，所受影響之因素復屬多元，更何況，被\n    害人於投資時均屬成年且有相當學識、經歷之人，實難僅以\n    公司女業務員於推銷投資時之部分言語，遽認投資人即有因\n    業務員欲與其結婚或交往，而陷於錯誤而遭誘騙投資之情。\n    至於被害人所指之「高額紅利」部分，亦屬投資人得循民事\n    契約關係求償之範疇，無從以此遽認被告等人違法吸金。\n 6、本件上訴理由第7 項雖以本件被害人等均於警詢指證歷歷，\n    且有扣案物證即合夥預定契約書所載事實，自可認被害人數\n    高達1336人等情，然卷附如附表三證據索引「丙」項之人證\n    關於被害人之警、偵陳述部分，均屬渠等如何投資交款等情\n    ，而關於部分被害人指訴有遭業務員以結婚或交往為藉口而\n    遭誘騙投資部分，尚難構成刑法詐欺犯行之要件，業已論述\n    如上，至於扣案物證即合夥預定契約書所載事實，亦僅可認\n    定有此部分契約所載之投資金額，不能據此逕認全屬受騙之\n    被害人數，是此部分上訴主張，亦非可採。\n八、被告午○○（原名史雅茜）、乙Ｉ○（原名蔡宜庭），均經\n    合法傳喚，無正當理由，未於98年12月22日本院審判期日到\n    庭（見本院二卷第99、127 、128 、220 頁之送達證書、刑\n    事報到單），依據刑事訴訟法第371 條規定，不待其陳述，\n    逕行判決。\n據上論斷，應依刑事訴訟法第368 條、第371 條，判決如主文。\n本案經檢察官許美女到庭執行職務。\n中    華    民    國    99    年    1     月    5     日\n                    刑事第三庭  審判長法  官  莊崑山\n                                      法  官  唐照明\n                                      法  官  張意聰\n以上正本證明與原本無異。\n檢察官如不服本判決應於收受本判決後10日內向本院提出上訴書\n狀，其未敘述上訴理由者，並得於提起上訴後10日內向本院補提\n理由書狀（均須按他造當事人之人數附繕本）「切勿逕送上級法\n院」。\n中    華    民    國    99    年    1     月    5     日\n                                      書記官  陳金\n附表一：被害人姓名、投資單位數、金額及參與業務員\n        ┌───┬─────┬─────────┬────────┐\n        │被害人│投資單位數│被詐騙總金額（元）│業務員          │\n        ├───┼─────┼─────────┼────────┤\n        │ｒ○○│   2      │   27萬           │未○○          │\n        ├───┼─────┼─────────┼────────┤\n        │甲ｊ○│   3      │   40.5萬         │未○○          │\n        ├───┼─────┼─────────┼────────┤\n        │ｔ○○│   10     │   135萬          │未○○          │\n        ├───┼─────┼─────────┼────────┤\n        │吳宣昌│   10     │   135萬          │未○○          │\n        ├───┼─────┼─────────┼────────┤\n        │甲Ｖ○│   4      │   54萬           │未○○          │\n        ├───┼─────┼─────────┼────────┤\n        │Ｏ○○│   2      │   27萬           │未○○          │\n        ├───┼─────┼─────────┼────────┤\n        │宙○○│   4      │   54萬           │未○○          │\n        ├───┼─────┼─────────┼────────┤\n        │ｗ○○│   4      │   54萬           │午○○          │\n        ├───┼─────┼─────────┼────────┤\n        │乙ｒ○│   2      │   27萬           │午○○          │\n        ├───┼─────┼─────────┼────────┤\n        │乙Ｕ○│   2      │   27萬           │午○○          │\n        ├───┼─────┼─────────┼────────┤\n        │甲ｐ○│   6      │   81萬           │午○○          │\n        ├───┼─────┼─────────┼────────┤\n        │Ｙ○○│   7      │   97萬           │午○○          │\n        ├───┼─────┼─────────┼────────┤\n        │黃○○│   3      │   40.5萬         │午○○          │\n        ├───┼─────┼─────────┼────────┤\n        │ｐ○○│   5      │   67.5萬         │午○○          │\n        ├───┼─────┼─────────┼────────┤\n        │甲ｉ○│   6      │   81萬           │午○○          │\n        ├───┼─────┼─────────┼────────┤\n        │乙Ｌ○│   15     │   202.5萬        │午○○          │\n        ├───┼─────┼─────────┼────────┤\n        │Ｒ○○│   3      │   40.5萬         │午○○          │\n        ├───┼─────┼─────────┼────────┤\n        │Ｕ○○│   6      │   81萬           │午○○          │\n        ├───┼─────┼─────────┼────────┤\n        │乙己○│   10     │   135萬          │午○○          │\n        ├───┼─────┼─────────┼────────┤\n        │甲申○│   10     │   135萬          │Ｃ○○          │\n        ├───┼─────┼─────────┼────────┤\n        │甲ｈ○│   7      │   94.5萬         │Ｃ○○          │\n        ├───┼─────┼─────────┼────────┤\n        │乙ｉ○│   1      │   13.5萬         │Ｃ○○          │\n        ├───┼─────┼─────────┼────────┤\n        │甲黃○│   2      │   27萬           │Ｉ○○          │\n        ├───┼─────┼─────────┼────────┤\n        │甲宇○│   9      │   121萬          │Ｉ○○          │\n        ├───┼─────┼─────────┼────────┤\n        │甲辰○│   3      │   40.5萬         │Ｉ○○          │\n        ├───┼─────┼─────────┼────────┤\n        │地○○│   3      │   40.5萬         │Ｉ○○          │\n        ├───┼─────┼─────────┼────────┤\n        │ｉ○○│   10     │   40.5萬         │Ｉ○○          │\n        ├───┼─────┼─────────┼────────┤\n        │甲ｑ○│   2      │   27萬           │Ｉ○○          │\n        ├───┼─────┼─────────┼────────┤\n        │亥○○│   2      │   27萬           │Ｊ○○          │\n        ├───┼─────┼─────────┼────────┤\n        │巳○○│   3      │   40.5萬         │Ｊ○○          │\n        ├───┼─────┼─────────┼────────┤\n        │Ｗ○○│   3      │   40.5萬         │Ｊ○○          │\n        ├───┼─────┼─────────┼────────┤\n        │乙午○│   10     │   135萬          │Ｊ○○          │\n        ├───┼─────┼─────────┼────────┤\n        │乙酉○│   4      │   54萬           │Ｌ○○          │\n        ├───┼─────┼─────────┼────────┤\n        │甲Ｎ○│   6      │   81萬           │Ｌ○○          │\n        ├───┼─────┼─────────┼────────┤\n        │乙亥○│   8      │   108萬          │Ｌ○○          │\n        ├───┼─────┼─────────┼────────┤\n        │甲Ｇ○│   2      │   27萬           │Ｌ○○          │\n        ├───┼─────┼─────────┼────────┤\n        │甲天○│   2      │   27萬           │Ｌ○○          │\n        ├───┼─────┼─────────┼────────┤\n        │甲○○│   5      │   67.5萬         │Ｌ○○          │\n        ├───┼─────┼─────────┼────────┤\n        │王志  │   4      │   54萬           │Ｍ○○          │\n        ├───┼─────┼─────────┼────────┤\n        │乙ｌ○│   3      │   40.5萬         │Ｍ○○          │\n        ├───┼─────┼─────────┼────────┤\n        │乙庚○│   6      │   81萬           │Ｍ○○          │\n        ├───┼─────┼─────────┼────────┤\n        │乙甲○│   2      │   27萬           │Ｍ○○          │\n        ├───┼─────┼─────────┼────────┤\n        │甲Ｕ○│   5      │   67.5萬         │Ｍ○○          │\n        ├───┼─────┼─────────┼────────┤\n        │甲ｔ○│   2      │   27萬           │Ｎ○○          │\n        ├───┼─────┼─────────┼────────┤\n        │甲寅○│   7      │   94.5萬         │Ｎ○○          │\n        ├───┼─────┼─────────┼────────┤\n        │乙Ｑ○│   6      │   81萬           │Ｎ○○          │\n        ├───┼─────┼─────────┼────────┤\n        │乙Ｗ○│   13     │175 萬5 千元（起訴│甲ｖ○（起訴書誤│\n        │      │          │書誤載176萬）     │載Ｘ○○）      │\n        ├───┼─────┼─────────┼────────┤\n        │甲ｎ○│   3      │   40.5萬         │Ｘ○○          │\n        ├───┼─────┼─────────┼────────┤\n        │甲ｇ○│   14     │   188萬          │Ｘ○○          │\n        ├───┼─────┼─────────┼────────┤\n        │甲ａ○│   5      │   67.5萬         │Ｘ○○          │\n        ├───┼─────┼─────────┼────────┤\n        │乙天○│   6      │   81萬           │Ｘ○○          │\n        ├───┼─────┼─────────┼────────┤\n        │乙Ｂ○│   6      │   81萬           │李群鳳          │\n        ├───┼─────┼─────────┼────────┤\n        │卯○○│   9      │   121萬          │ｈ○○          │\n        ├───┼─────┼─────────┼────────┤\n        │乙Ｍ○│   6      │   81萬           │ｈ○○          │\n        ├───┼─────┼─────────┼────────┤\n        │乙ｂ○│   5      │   67.5萬         │ｈ○○          │\n        ├───┼─────┼─────────┼────────┤\n        │ｃ○○│   5      │   67.5萬         │ｈ○○          │\n        ├───┼─────┼─────────┼────────┤\n        │乙Ｅ○│   7      │   94.5萬         │ｈ○○          │\n        ├───┼─────┼─────────┼────────┤\n        │乙ｑ○│   1      │   13.5萬         │ｈ○○          │\n        ├───┼─────┼─────────┼────────┤\n        │甲ｃ○│   3      │   40.5萬         │ｈ○○          │\n        ├───┼─────┼─────────┼────────┤\n        │乙寅○│   5      │   67.5萬         │ｈ○○          │\n        ├───┼─────┼─────────┼────────┤\n        │Ｈ○○│   4      │   54萬           │ｈ○○          │\n        ├───┼─────┼─────────┼────────┤\n        │甲Ｘ○│   9      │   121.5萬        │ｈ○○          │\n        ├───┼─────┼─────────┼────────┤\n        │甲Ｃ○│   2      │   27萬           │林詩怡          │\n        ├───┼─────┼─────────┼────────┤\n        │甲Ｋ○│   8      │   108萬          │甲子○          │\n        ├───┼─────┼─────────┼────────┤\n        │林寶生│   8      │   108萬          │甲子○          │\n        ├───┼─────┼─────────┼────────┤\n        │乙ｐ○│   15     │   202.5萬        │甲子○          │\n        ├───┼─────┼─────────┼────────┤\n        │天○○│   3      │   40.5萬         │甲子○          │\n        ├───┼─────┼─────────┼────────┤\n        │Ｖ○○│   7      │   94.5萬         │甲子○          │\n        ├───┼─────┼─────────┼────────┤\n        │江建  │   4      │   54萬           │甲Ｉ○          │\n        ├───┼─────┼─────────┼────────┤\n        │辛○○│   5      │   67.5萬         │甲Ｊ○          │\n        ├───┼─────┼─────────┼────────┤\n        │乙宙○│   9      │   121.5萬        │甲Ｊ○          │\n        ├───┼─────┼─────────┼────────┤\n        │甲Ｑ○│   5      │   67.5萬         │甲Ｊ○          │\n        ├───┼─────┼─────────┼────────┤\n        │乙ｏ○│   8      │   108萬          │甲Ｊ○          │\n        ├───┼─────┼─────────┼────────┤\n        │庚○○│   3      │   40.5萬         │甲Ｐ○          │\n        ├───┼─────┼─────────┼────────┤\n        │ｎ○○│   4      │   54萬           │甲Ｐ○、甲ｂ○（│\n        │      │          │                  │起訴漏載）      │\n        ├───┼─────┼─────────┼────────┤\n        │乙ｙ○│   2      │   27萬           │甲Ｐ○          │\n        ├───┼─────┼─────────┼────────┤\n        │乙ｄ○│   6      │   81萬           │甲Ｐ○          │\n        ├───┼─────┼─────────┼────────┤\n        │酁孟昇│   3      │   40.5萬         │甲ｆ○          │\n        ├───┼─────┼─────────┼────────┤\n        │乙Ｐ○│   5      │   67.5萬         │甲ｆ○          │\n        ├───┼─────┼─────────┼────────┤\n        │乙ｃ○│   3      │   40.5萬         │甲ｆ○          │\n        ├───┼─────┼─────────┼────────┤\n        │甲Ｙ○│   4      │   54萬           │甲Ｒ○          │\n        ├───┼─────┼─────────┼────────┤\n        │甲丑○│   1      │   13.5萬         │甲Ｒ○          │\n        ├───┼─────┼─────────┼────────┤\n        │乙Ｓ○│   3      │   40.5萬         │甲Ｒ○          │\n        ├───┼─────┼─────────┼────────┤\n        │ｋ○○│   8      │   108萬          │甲ｂ○          │\n        ├───┼─────┼─────────┼────────┤\n        │Ｂ○○│   2      │   27萬           │甲ｂ○          │\n        ├───┼─────┼─────────┼────────┤\n        │乙癸○│   1      │   13.5萬         │甲ｂ○          │\n        ├───┼─────┼─────────┼────────┤\n        │ｊ○○│   3      │   40.5萬         │甲ｂ○          │\n        ├───┼─────┼─────────┼────────┤\n        │甲戌○│   9      │   121.5萬        │甲ｄ○          │\n        ├───┼─────┼─────────┼────────┤\n        │乙戌○│   7      │   94.5萬         │甲ｍ○          │\n        ├───┼─────┼─────────┼────────┤\n        │玄○○│   2      │   27萬           │甲ｍ○          │\n        ├───┼─────┼─────────┼────────┤\n        │ｘ○○│   3      │   40.5萬         │甲ｍ○          │\n        ├───┼─────┼─────────┼────────┤\n        │甲丁○│   3      │   40.5萬         │甲ｍ○          │\n        ├───┼─────┼─────────┼────────┤\n        │子○○│   7      │   94.5萬         │甲ｍ○          │\n        ├───┼─────┼─────────┼────────┤\n        │乙ｔ○│   4      │   54萬           │甲ｍ○          │\n        ├───┼─────┼─────────┼────────┤\n        │乙丁○│   1      │   13.5萬         │甲ｍ○          │\n        ├───┼─────┼─────────┼────────┤\n        │乙Ｔ○│   7      │   94.5萬         │甲ｍ○          │\n        ├───┼─────┼─────────┼────────┤\n        │甲宙○│   4      │   54萬           │甲ｍ○          │\n        ├───┼─────┼─────────┼────────┤\n        │丁○○│   8      │   108萬          │甲ｓ○          │\n        ├───┼─────┼─────────┼────────┤\n        │甲Ｆ○│   7      │   94.5萬         │甲ｓ○          │\n        ├───┼─────┼─────────┼────────┤\n        │乙丑○│   5      │   67.5萬         │甲ｖ○          │\n        ├───┼─────┼─────────┼────────┤\n        │丙○○│   7      │   94.5萬         │甲ｖ○          │\n        ├───┼─────┼─────────┼────────┤\n        │甲酉  │   3      │   40.5萬         │甲ｖ○          │\n        ├───┼─────┼─────────┼────────┤\n        │甲庚○│   9      │   121.5萬        │甲ｖ○          │\n        ├───┼─────┼─────────┼────────┤\n        │甲ｅ○│   2      │   27萬           │甲ｖ○          │\n        ├───┼─────┼─────────┼────────┤\n        │甲Ｗ○│   21     │   283.5萬        │甲ｖ○          │\n        ├───┼─────┼─────────┼────────┤\n        │甲未○│   2      │   27萬           │甲ｖ○          │\n        ├───┼─────┼─────────┼────────┤\n        │甲Ｌ○│   13     │   175萬          │甲ｖ○          │\n        ├───┼─────┼─────────┼────────┤\n        │甲丙○│   1      │   13.5萬         │甲ｖ○          │\n        ├───┼─────┼─────────┼────────┤\n        │ｙ○○│   9      │   121萬          │甲ｗ○          │\n        ├───┼─────┼─────────┼────────┤\n        │甲Ｅ○│   7      │   94.5萬         │甲ｗ○          │\n        ├───┼─────┼─────────┼────────┤\n        │乙ａ○│   3      │   40.5萬         │黃彩惠          │\n        ├───┼─────┼─────────┼────────┤\n        │乙Ａ○│   2      │   27萬           │黃彩惠          │\n        ├───┼─────┼─────────┼────────┤\n        │Ｓ○○│   3      │   40.5萬         │乙Ｃ○          │\n        ├───┼─────┼─────────┼────────┤\n        │乙辰○│   10     │   135萬          │乙黃○          │\n        ├───┼─────┼─────────┼────────┤\n        │甲甲○│   1      │   13.5萬         │乙黃○          │\n        ├───┼─────┼─────────┼────────┤\n        │甲Ｔ○│   3      │   40.5萬         │乙黃○          │\n        ├───┼─────┼─────────┼────────┤\n        │Ｋ○○│   6      │   81萬           │乙黃○          │\n        ├───┼─────┼─────────┼────────┤\n        │黃健清│   3      │   40.5萬         │乙黃○          │\n        ├───┼─────┼─────────┼────────┤\n        │乙卯○│   4      │   54萬           │乙黃○          │\n        ├───┼─────┼─────────┼────────┤\n        │甲ｏ○│   1      │   13.5萬         │乙黃○          │\n        ├───┼─────┼─────────┼────────┤\n        │甲巳○│   5      │   67.5萬         │乙Ｄ○○        │\n        ├───┼─────┼─────────┼────────┤\n        │ｂ○○│   2      │   27萬           │乙Ｄ○○        │\n        ├───┼─────┼─────────┼────────┤\n        │乙Ｖ○│   5      │   67.5萬         │乙Ｄ○○        │\n        ├───┼─────┼─────────┼────────┤\n        │甲卯○│   4      │   54萬           │乙Ｄ○○        │\n        ├───┼─────┼─────────┼────────┤\n        │甲壬○│   1      │   13.5萬         │乙Ｇ○          │\n        ├───┼─────┼─────────┼────────┤\n        │ｌ○○│   6      │   81萬           │蔡幸          │\n        ├───┼─────┼─────────┼────────┤\n        │甲Ｈ○│   2      │   27萬           │蔡幸          │\n        ├───┼─────┼─────────┼────────┤\n        │Ａ○○│   4      │   54萬           │蔡幸          │\n        ├───┼─────┼─────────┼────────┤\n        │Ｆ○○│   6      │   81萬           │蔡幸          │\n        ├───┼─────┼─────────┼────────┤\n        │甲ｙ○│   2      │   27萬           │乙Ｘ○          │\n        ├───┼─────┼─────────┼────────┤\n        │乙Ｏ○│   3      │   40.5萬         │乙ｋ○          │\n        ├───┼─────┼─────────┼────────┤\n        │乙宇○│   4      │   54萬           │乙ｋ○          │\n        ├───┼─────┼─────────┼────────┤\n        │甲亥○│   10     │   135萬          │「方慧令」      │\n        ├───┼─────┼─────────┼────────┤\n        │林佑賢│   4      │   54萬           │「江家秀」      │\n        ├───┼─────┼─────────┼────────┤\n        │乙ｎ○│   3      │   40.5萬         │「何依驊」      │\n        ├───┼─────┼─────────┼────────┤\n        │甲癸○│   3      │   40.5萬         │「吳家佩」      │\n        ├───┼─────┼─────────┼────────┤\n        │乙○○│   11     │   148.5萬        │「吳雅惠」      │\n        ├───┼─────┼─────────┼────────┤\n        │乙Ｋ○│   4      │   54萬           │「吳雅惠」      │\n        ├───┼─────┼─────────┼────────┤\n        │乙Ｎ○│   1      │   13.5萬         │「吳蜜茹」      │\n        ├───┼─────┼─────────┼────────┤\n        │甲Ｕ○│   5      │   67.5萬         │「吳親蓉」      │\n        ├───┼─────┼─────────┼────────┤\n        │乙ｖ○│   5      │   67.5萬         │「吳靜雅」      │\n        ├───┼─────┼─────────┼────────┤\n        │甲ｋ○│   2      │   27萬           │「吳謹如」      │\n        ├───┼─────┼─────────┼────────┤\n        │ｅ○○│   4      │   54萬           │「李倩儀」      │\n        ├───┼─────┼─────────┼────────┤\n        │酉○○│   1      │   13.5萬         │「李喬芳」      │\n        ├───┼─────┼─────────┼────────┤\n        │甲Ｓ○│   1      │   13.5萬         │「李瑞芳」      │\n        ├───┼─────┼─────────┼────────┤\n        │甲乙○│   5      │   67.5萬         │「李瑞芳」      │\n        ├───┼─────┼─────────┼────────┤\n        │ｄ○○│   11     │   148.5萬        │「李瑞芳」      │\n        ├───┼─────┼─────────┼────────┤\n        │乙巳○│   1      │   13.5萬         │「林芷萱」      │\n        ├───┼─────┼─────────┼────────┤\n        │鍾建福│   1      │   13.5萬         │「林芷萱」      │\n        ├───┼─────┼─────────┼────────┤\n        │乙未○│   2      │   27萬           │「林美真」      │\n        ├───┼─────┼─────────┼────────┤\n        │甲Ｚ○│   10     │   135萬          │「洪幸惠」      │\n        ├───┼─────┼─────────┼────────┤\n        │甲ｒ○│   2      │   27萬           │「洪幸惠」      │\n        ├───┼─────┼─────────┼────────┤\n        │甲Ｍ○│   4      │   54萬           │「洪欣惠」      │\n        ├───┼─────┼─────────┼────────┤\n        │甲戊○│   6      │   81萬           │「洪薇雯」      │\n        ├───┼─────┼─────────┼────────┤\n        │ｖ○○│   4      │   54萬           │「洪薇雯」      │\n        ├───┼─────┼─────────┼────────┤\n        │乙ｅ○│   1      │   13.5萬         │「胡若羚」      │\n        ├───┼─────┼─────────┼────────┤\n        │壬○○│   11     │   148.5萬        │「徐慧玲」      │\n        ├───┼─────┼─────────┼────────┤\n        │甲Ｄ○│   4      │   54萬           │「張娟綾」      │\n        ├───┼─────┼─────────┼────────┤\n        │Ｔ○○│   6      │   81萬           │「張娟綾」      │\n        ├───┼─────┼─────────┼────────┤\n        │甲地○│   8      │   108萬          │「張容楨」      │\n        ├───┼─────┼─────────┼────────┤\n        │ｏ○○│   1      │   13.5萬         │「張雅雯」      │\n        ├───┼─────┼─────────┼────────┤\n        │乙ｍ○│   6      │   81萬           │「張雅雯」      │\n        ├───┼─────┼─────────┼────────┤\n        │甲ｚ○│   2      │   27萬           │「張雅雯」      │\n        ├───┼─────┼─────────┼────────┤\n        │ｕ○○│   10     │   135萬          │「張雅雯」      │\n        ├───┼─────┼─────────┼────────┤\n        │乙戊○│   3      │   40.5萬         │「張雅雯」      │\n        ├───┼─────┼─────────┼────────┤\n        │乙壬○│   7      │   94.5萬         │「許姿玲」      │\n        ├───┼─────┼─────────┼────────┤\n        │ｚ○○│   7      │   94.5萬         │「郭靜蓉」      │\n        ├───┼─────┼─────────┼────────┤\n        │Ｄ○○│   2      │   27萬           │「陳喬安」      │\n        ├───┼─────┼─────────┼────────┤\n        │ｇ○○│   3      │   40.5萬         │「陳喬安」      │\n        ├───┼─────┼─────────┼────────┤\n        │寅○○│   3      │   40.5萬         │「陳靜雅」      │\n        ├───┼─────┼─────────┼────────┤\n        │黃勝輝│   6      │   81萬           │「黃美真」      │\n        ├───┼─────┼─────────┼────────┤\n        │乙ｊ○│   4      │   54萬           │「黃詩婷」      │\n        ├───┼─────┼─────────┼────────┤\n        │ｑ○○│   13     │   175.5萬        │「黃詩婷」      │\n        ├───┼─────┼─────────┼────────┤\n        │甲午○│   3      │   40.5萬         │「黃詩婷」      │\n        ├───┼─────┼─────────┼────────┤\n        │乙ｘ○│   10     │   135萬          │「黃詩瑾」      │\n        ├───┼─────┼─────────┼────────┤\n        │戌○○│   11     │   148.5萬        │「黃詩謹」      │\n        ├───┼─────┼─────────┼────────┤\n        │甲ｌ○│   3      │   40.5萬         │「潘唯心」      │\n        ├───┼─────┼─────────┼────────┤\n        │丑○○│   19     │   256.5 萬       │「蔡羽庭」      │\n        ├───┼─────┼─────────┼────────┤\n        │辰○○│   4      │   54萬           │「蔡佳玲」      │\n        ├───┼─────┼─────────┼────────┤\n        │甲Ｏ○│   2      │   27萬           │「蔡佳玲」      │\n        ├───┼─────┼─────────┼────────┤\n        │蔡祖恩│   3      │   40.5萬         │「鄭靜茹」      │\n        ├───┼─────┼─────────┼────────┤\n        │乙Ｚ○│   2      │   27萬           │「蕭玄鈴」      │\n        ├───┼─────┼─────────┼────────┤\n        │Ｚ○○│   25     │   337.5萬        │「賴雅玲」      │\n        ├───┼─────┼─────────┼────────┤\n        │甲Ａ○│   4      │   54萬           │「蘇佳音」      │\n        ├───┼─────┼─────────┼────────┤\n        │乙Ｙ○│   6      │   81萬           │「李嘉倩」      │\n        ├───┼─────┼─────────┼────────┤\n        │乙Ｊ○│   2      │   27萬           │  不詳          │\n        ├───┼─────┼─────────┼────────┤\n        │乙ｇ○│   4      │   54萬           │  不詳          │\n        ├───┼─────┼─────────┼────────┤\n        │甲己○│   1      │   13.5萬         │  不詳          │\n        ├───┼─────┼─────────┼────────┤\n        │王志中│   2      │   27萬           │  不詳          │\n        ├───┼─────┼─────────┼────────┤\n        │乙玄○│   3      │   40.5萬         │  不詳          │\n        ├───┼─────┼─────────┼────────┤\n        │Ｑ○○│   5      │   67.5萬         │  不詳          │\n        ├───┼─────┼─────────┼────────┤\n        │甲ｘ○│   3      │   40.5萬         │  不詳          │\n        ├───┼─────┼─────────┼────────┤\n        │Ｅ○○│   4      │   54萬           │  不詳          │\n        ├───┼─────┼─────────┼────────┤\n        │甲玄○│   3      │   40.5萬         │  不詳          │\n        ├───┼─────┼─────────┼────────┤\n        │乙ｗ○│   6      │   81萬           │  不詳          │\n        ├───┼─────┼─────────┼────────┤\n        │乙ｓ○│   1      │   13.5萬         │  不詳          │\n        └───┴─────┴─────────┴────────┘\n附表二、被害人供述：\n1、ｒ○○\n   未○○向我推銷海閣林公司在綠島的投資案，她有改名過，\n   原名是史恆華。她對我遊說投資方案有多好，說如將來想生\n   活好一點，就要有良好的投資理財觀念，說她表哥是海閣林\n   公司內部高級幹部是經理，告訴我這是一個非常好的投資機\n   會，說她有相當大的把握一定要我加入她們的合夥。我在91\n   年11月在公司外跟她簽約，當下她當然希望我認購愈多愈好\n   ，但我衡量我的能力只購買2 單位27萬元，我把身分證、薪\n   轉存摺、印鑑都交給她去向高雄二信銀行辦信用貸款，共貸\n   款80萬元，扣除後約剩50幾萬元在戶頭裡，未○○要我多貸\n   些，用剩餘的錢來扣本息，我自己也有動用過部分款項，當\n   時辦理貸款後，銀行的存摺、印章她們有交還給我。當時未\n   ○○與海閣林公司的人無告知我該投資飯店的案件在台東縣\n   政府當時並未經核可，她當時只說缺資金，祇要一有資金所\n   有事情都可順利解決。當時未○○無說要與我交往。目前我\n   不清楚海閣林公司在綠島蓋的飯店已經取得旅館的使用執照\n   。是否每個投資都有賺錢的問題沒有一定的答案，有無哪種\n   投資是沒有風險，這也是沒有一定答案。（出處：警( 一)\n   卷，P317- P319、原審二卷，P155-P162 ）\n2、甲ｊ○\n   91年9 月在溫馨婚友社認識史恆華，她對我推銷海閣林公司\n   的股份，說她哥哥是海閣林公司的主管，她邀我跟她去高雄\n   市○○路的海閣林公司瞭解營運狀況，還播放DVD 簡介要把\n   綠島變成觀光勝地，她說如生活想要好一點就要有良好的投\n   資理財觀念，我沒想要追求她，她當時也沒說要與我交往或\n   我不投資就不跟我交朋友，從她跟我介紹投資案到我決定投\n   資的過程間隔大概3 、4 個月，經過評估後才決定要投資3\n   單位共40萬5 千元，因我身上現金不夠，一部分資金是向銀\n   行貸款。未○○跟海閣林公司相關人員向我推銷綠島飯店投\n   資案時，完全沒向我告知海閣林公司當時並未取得台東縣政\n   府核准設立飯店，未○○當時沒告知我綠島開發案進行程度\n   ，我投資當時是92年間，當時只有初步計畫，不知道迄今海\n   閣林公司已取得台東縣政府核准的旅館使用執照。（出處：\n   警(一)卷，P323-P325 、原審二卷，P163-P169 ）\n3、ｔ○○\n   94年2 、3 月時，去「合緣婚友社」認識未○○，她介紹我\n   投資海閣林公司綠島飯店開發案，跟我說如將來要在一起，\n   要有良好的投資理財觀，我自己決定投資10單位共135 萬元\n   ，資金是未○○幫我貸款，我將銀行存摺、印章都交由她保\n   管，但沒授權她把錢領走，她跟我說核貸貸款的錢下來了，\n   要領走去投資。未○○及海閣林公司人員沒跟我說綠島飯店\n   開發案尚未經台東縣政府核准，未○○有告訴我將於94年7\n   月試賣，10月正式營運，投資後我有與朋友到綠島看過工地\n   ，當時正在施工當中，看到時無覺得海閣林公司是個騙局。\n   （出處：警(一) 卷，P328-P330 、原審二卷，P170-P180）\n4、吳永成（原名吳宣昌）\n   92年12月在「溫馨婚友社」認識未○○，她鼓吹我投資海閣\n   林公司綠島飯店開發案，說為了我們以後，沒承諾我投資多\n   久後會跟我結婚或進一步的發展，投資金額看能貸款多少再\n   決定要投資多少，最後我與她一起決定投資金額，共投資10\n   單位合計135 萬元，並由她幫我處理貸款事項，我將存摺、\n   印章交給她處理。海閣林公司人員好像說一股可以分得近萬\n   元，但沒具體講明，有說過一定賺，不會賠錢，蓋好後還可\n   轉賣，當時未○○或海閣林公司人員無跟我說綠島飯店開發\n   案尚未經過台東縣政府核准，那時有說飯店不知何時會蓋好\n   ，不知道已經核發使用執照。如沒經過核准的，表示案子是\n   騙人的，我當時就不會投資。（出處：警(一)卷，P341-P343\n   、原審二卷，P189-P197 ）\n5、甲Ｖ○\n   93年11月經朋友介紹認識未○○，她向我推銷「海閣林公司\n   」的股份，遊說投資方案有多好，她哥哥申○○在海閣林當\n   主管，未○○說如果將來想生活好一點，就要有良好的投資\n   理財觀念，我以貸款投資4 單位共54萬元，拿錢投資後，未\n   ○○就不和我聯絡。（出處：警(一) 卷，P344-P346）\n6、Ｏ○○\n   92年11月在「溫馨婚友社」認識未○○，她鼓吹我投資海閣\n   林公司的綠島飯店開發案，告訴我綠島開發案將是綠島第一\n   家五星級大飯店，前景看好，一定可賺錢，有多少股份就有\n   多少紅利，沒告訴我可能會賠錢，當時投資2 單位共27萬元\n   ，資金來源是貸款。當時有說開發案尚未取得台東縣政府核\n   准，但要先建設。投資前有先去海閣林公司看過模型，之後\n   有去綠島看，第一次去看現場是空地，大概隔1 年，第二次\n   去時看到蓋了5 樓的空屋。就我當時認知，投資風險是一定\n   有的，現在的投資又不是一定會賺錢。（出處：警(一) 卷，\n   P348-P350 、原審二卷，P180-P189）\n7、宙○○\n   93年6 月在「欣緣婚友社」認識使未○○，她向我推銷海閣\n   林公司的股份，遊說海閣林公司發展前景看好，說她哥哥是\n   海閣林公司主管。我跟她去高雄營運處瞭解營運狀況，放DV\n   D 瞭解以後正式營運內容，她說她有投資4 單位並拿合約書\n   給我看，我就投資4 單位共計54萬元，簽約後，未○○就不\n   和我聯絡。投資前，公司主管說公司已取得政府執照可蓋五\n   星級休閒渡假酒店，但未說王丁以慶集合式住宅名義申請建\n   照，在網路上公布戊○○是以集合式住宅申請建照，如知道\n   是集合式住宅我就不投資了。（出處：警( 一) 卷，P354-P\n   356）\n8、ｗ○○\n   92年1 月時，經朋友介紹認識陳怡文跟午○○（原名史雅茜\n   ），不斷向我遊說公司的投資方案，午○○、陳怡文和海閣\n   林公司的人沒有跟我說綠島飯店的投資案沒經過台東縣政府\n   的許可。午○○、陳怡文沒跟我說不投資海閣林公司就不跟\n   我作朋友，他們跟我介紹投資案後到我決定投資約1 個月，\n   我投資4 單位共計54萬元，她們說按我投資金額年利率40％\n   來計算，等公司營運正常時，可開始回收，就我認知中沒有\n   何種投資是百分之百賺錢無風險，認為被騙是那時電視和新\n   聞都有報導。不知道海閣林公司在綠島蓋的飯店目前已經取\n   得台東縣政府核發飯店使用執照。（出處：警( 一) 卷，\n   P359- P361、原審二卷，P227-P232 ）\n9、乙ｒ○\n   92年在交友中心認識史雅茜，她對我推銷海閣林公司綠島飯\n   店開發案，我拿錢投資是因我想追求她，也想做投資多賺點\n   錢，她沒說如果我不投資就不跟我做朋友，她有向我解說投\n   資內容，我貸款作為投資的資金來源，我買2 個單位共27萬\n   元，當時史雅茜有跟我說明投資金額的紅利算法，於飯店營\n   利後賺錢的情況下會發紅利，不記得當時有無跟我說綠島飯\n   店開發案有無可能賠錢，我是到後來看到報紙才覺得被騙，\n   但我的認知裡無何種投資是百分擺賺錢絕無風險。當初未看\n   到報紙之前有懷疑海閣林是一家詐騙公司，有向史雅茜提出\n   懷疑，後來她跟我解答，我相信她。（出處：警( 一) 卷，\n   P368 -P370、原審二卷，P233-P240 ）\n10、乙Ｕ○\n    93年時在「溫馨婚友社」認識史雅茜，說她姊姊在在海閣林\n    公司上班，有件綠島飯店投資案，收益很大，要求我投資，\n    沒說我不投資就不跟我做朋友，她們有放影片說已蓋好基地\n    。從第1 次邀我投資到我決定投資簽立合約約1 、2 個星期\n    ，我投資2 單位共27萬元，從警方公佈時，我開始覺得這是\n    場騙局，如知道投資當時海閣林公司在綠島蓋的飯店只取得\n    一般住宅許可而非飯店許可，我不會投資，我不曉得海閣林\n    公司在綠島開發案已經取得台東縣政府核發的飯店許可。\n    （出處：原審二卷，P252-P255）\n11、甲ｐ○\n    92年認識史雅茜，她對我推銷海閣林公司的股份，向我遊說\n    投資方案有多好，負責人是她乾爸，說如果將來想生活好一\n    點就要有良好的投資理財觀念，我投資6 單位共81萬元，並\n    向高雄二信銀行貸款120 萬元來投資。（出處：警( 一) 卷\n    ，P376-P378 ）\n12、Ｙ○○\n    93年6 月在婚友社認識史雅茜，她向我鼓吹海閣林公司的綠\n    島飯店開發案，說她堂哥在海閣林公司擔任高級幹部，公司\n    剛好開放機會給好朋認股，說在該年度飯店就可建造完畢開\n    始營運，而後會有紅利可發放，沒說投資案會賠錢，如我知\n    道海閣林公司在的綠島飯店開發案未取得政府的核准許可，\n    就不會投資了，投資前有去過海閣林公司，公司的人有說投\n    資案的飯店蓋在哪裡，一些附屬設備有哪些，我問過他們投\n    資獲利金額為何，他們沒說明，從史雅茜向我介紹投資案到\n    我決定投資7 單位共97萬元大約2 、3 個星期，我以貸款取\n    得投資的資金。不清楚海閣林公司在綠島蓋的飯店已經取得\n    台東縣政府核發的旅館使用執照。（出處：警( 一) 卷，\n    P380- P382、原審二卷，P240-P245 ）\n13、黃○○\n    93年在合欣婚友社認識史雅茜，她沒有要求我投資，當時她\n    要去海閣林公司簽約要我陪她去，幫她看契約內容，之後閒\n    聊時，她問我是否要投資，當時想賺多一點錢，所以投資3\n    單位共40萬5 千元，並以貸款取得投資的資金。史雅茜及海\n    閣林公司的人沒跟我說明綠島飯店開發案的投資風險及可能\n    會賠錢，但有跟我說到時可分得紅利，合約上有寫百分比的\n    紅利，是以飯店每月營收按投資比例來分，投資時公司的人\n    沒跟我說尚未取得政府的飯店開發許可，若當時知道尚未取\n    得許得我不會願意投資。當初史雅茜有說飯店已經動工，並\n    說公司有網站，上面有資料及工程進度可上網看，我有上網\n    查看，有一些主體結構正在蓋。沒有哪種投資是完全零風險\n    ，但她也沒說這件投資案是有風險的。報紙刊登後，資料傳\n    到我營區，長官說我非法投資我才認定本投資案是廠騙局。\n    （出處：警( 一) 卷，P 、原審二卷，P245-P251 ）\n14、ｐ○○\n    93年間在「溫馨婚友社」認識史雅茜，她一直對我推銷海閣\n    林公司的股份，遊說投資方案有多好，她表哥在公司裡面當\n    主管，說如果將來想生活好一點，就要有良好的投資理財觀\n    念，我就投資5 單位共67萬5 千元，並以貸款取得投資的資\n    金。（出處：警(一) 卷，P388-P390）\n15、甲ｉ○\n    93年間在「和信婚友社」認識史雅茜，她一直對我推銷海閣\n    林公司的股份，說投資方案有多好，她表哥在公司裡面當主\n    管，說如果將來想生活好一點，就要有良好的投資理財觀念\n    ，我就投資6 單位共81萬元，並以貸款取得投資的資金。\n    （出處：警(一) 卷，P393-P395）\n16、乙Ｌ○\n    93年間在「和信婚友社」認識史雅茜，她跟我說投資海閣林\n    公司綠島開發案如飯店正常營運有賺錢時，每個單位可獲利\n    8 千元左右，當時想賺錢，投資15單位共計202 萬5 千元，\n    我以貸款取得投資的資金，決定15個單位是史雅茜當時跟我\n    說看能貸到多少錢就投資多少單位。投資時如知道綠島飯店\n    開發案僅取得一般住宅開發許可而未取得飯店的開發許可，\n    就不願意投資。史雅茜或海閣林公司的人沒跟我說明開發案\n    的風險或有可能賠錢，史雅茜沒說如我不投資就不與我聯絡\n    。不曉得海閣林公司在綠島的飯店已經取得台東縣政府核發\n    的使用執照。從93年底我聯絡不上史雅茜開始覺得本投資案\n    是場騙局。基本上如不是詐騙案的話，我仍然會去投資。\n    （出處：警(一) 卷，P393-P3 97、原審二卷，P256-P260）\n17、Ｒ○○\n    93年在「溫馨婚友社」認識史雅茜，她及海閣林公司人員鼓\n    吹我投資綠島飯店開發案時，有標榜是綠島第一家五星級休\n    閒渡假酒店，希望我投資，我衡量自己沒什麼錢，所以只買\n    3 單位，投資的資金是向銀行貸款，共貸了70餘萬元。後來\n    才知道我投資當時海閣林公司興建的飯店，只是取得一般住\n    宅興建執照，未取得政府核准之飯店開發執照，如當時知道\n    這個情況，應該不會拿錢出來投資，當時沒跟我講得很清楚\n    如何分紅，只說何時興建完成。投資當時我有去過海閣林公\n    司，有人向我說明投資案的內容，及要我上網去看在綠島蓋\n    飯店的進度。不曉得海閣林公司在綠島蓋的飯店已經取得台\n    東縣政府核發的飯店使用執照。投資後有段時間她都沒與我\n    聯絡，我就知道本件投資案是場騙局。我是在看到新聞報導\n    後去警局報案的。（出處：警(一)卷，P400-P402 、原審二卷\n    ，P261-P265 ）\n18、Ｕ○○\n    92年認識叫史雅玲（音譯）女子，就是當庭之午○○，她對\n    我推銷海閣林公司的股份，提議我貸款投資本案，我當時貸\n    款130 萬元，本來只買3 單位，後史雅玲跟一個自稱她姊姊\n    的人來找我，我又加買3 單位，所以投資6 單位共81萬元，\n    剩餘款項一部分作為償還銀行利息，另借12萬元給她。當初\n    投資是她說要跟我交往，說為了我們爾後的生活或退休的計\n    畫所以要我投資，我考慮了1 天決定投資，她說如投資13萬\n    5 千元，公司屆期會以每單位50萬元向我買回股權，並只說\n    這會賺錢，她有說如我不投資的話就不用往來了，而當時不\n    知道海閣林公司只取得一般住宅的興建執照，而尚未取得興\n    建飯店的建築執照，如知道是這樣情形，就不會貸款去投資\n    。投資過程中我有到過海閣林公司，史雅玲不與我聯絡後，\n    93年間我有打電話要求海閣林公司退費。（出處：警( 一)\n    卷，P405-P407 、原審二卷，P266-P270 ）\n19、乙己○\n    93年在婚友社認識史雅茜（即午○○、史雅玲），她叫我投\n    資海閣林休閒渡假酒店，因當時我以結婚為前提在交往，但\n    她口頭上與我交往，有說如果我不投資就不跟我往來了，所\n    以我用信用貸款140 多萬元，然後她幫我決定投資10單位13\n    5 萬元，投資時不知道海閣林公司當時未取得政府許可的綠\n    島飯店開發核准，如當時知道這情況，不會拿錢出來投資。\n    她沒跟我說這投資案百分之百賺錢，完全零風險，有跟我說\n    投資一定會分紅，分紅的金額以飯店當月的利潤按百分比來\n    計算，多少比例忘了。94年8 月間她不接我電話時，開始覺\n    得這是場騙局，覺得自己受騙。就我認知沒有何種投資會百\n    分之百賺錢無任何風險，但午○○跟我講說百分之百賺錢，\n    我就相信她了。（出處：警( 四) 卷，P1486-P1489 、原審\n    二卷，P271 -P276）\n20、甲申○\n    93年在「溫馨婚友社」認識Ｃ○○，說將來在一起，我要有\n    良好的投資理財觀念，她介紹海閣林在綠島蓋度假飯店讓我\n    知悉，我本來不想投資，她表現出不高興的態度，我與她溝\n    通後，投資9 個單位，我共投資10單位135 萬元，最後1 個\n    單位是跟劉佩妤買的，她也是在「溫馨婚友社」認識的，她\n    們都沒說不投資就不跟我往來。投資金額部分貸款部分現金\n    ，Ｃ○○陪我到海閣林公司簽約，簽約前有仔細看過合約內\n    容，她有跟我講投資後如何分紅、何時開始獲利回收，但沒\n    說明投資案可能會賠錢，也沒分析投資案的風險，是說還不\n    錯的投資案，投資後每年可分到蠻多紅利。當時Ｃ○○及海\n    閣林公司人員無跟我說綠島開發案沒經過台東縣政府核發執\n    照，事發後看報紙才知道，如知道沒經過縣政府許可，我就\n    不會投資了。從Ｃ○○跟我介紹投資到正式簽約投資，約2\n    、3 個月，我當時的認知是沒有何種投資是完全零風險一定\n    可賺錢。不知道海閣林公司綠島開發案已經取的旅館的執照\n    。是新聞報導後才感覺被騙。（出處：警( 一) 卷，P430-P\n    432 、原審三卷，P75-P87 ）\n21、甲ｈ○\n    92年在「蕙萊婚友社」認識Ｃ○○，她在海閣林公司上班，\n    有說他親戚在海閣林公司上班或投資，她要我投資海閣林公\n    司，說該投資案有高獲利，說海閣林公司是溫泉休閒中心，\n    剛開始要看營業額，一單位13萬5 千元，以購買單位依整年\n    度營業額來計算獲利，我購買7 個單位合計94萬5 千元，說\n    我買7 個單位第1 年可能有幾10萬元獲利，1 單位1 年只有\n    幾萬元收入，她帶我去公司拿出綠島建設藍圖給我看，說公\n    司需要多少資金，第1 年營業額可能不是很多，但依其營業\n    額可分算分得紅利，如沒這樣的獲利，我不會投資，當時我\n    是看設計圖判斷的。我拿扣繳憑單等資料給Ｃ○○向萬泰等\n    3 家銀行辦貸款貸款金額合計166 萬元，辦好後她帶我到銀\n    行開戶領錢，交付後能順利聯絡Ｃ○○。我看蘋果日報才知\n    道這是詐騙集團。不知道海閣林公司在綠島的開發案已經取\n    得旅館的使用執照。（出處：警( 一) 卷，P435-P437 、原\n    審三卷，P88-P9 4）\n22、乙ｉ○\n    93年在「欣緣婚友社」認識Ｃ○○，當時為了要投資理財想\n    讓家人過得更好一點，所以投資海閣林公司的綠島飯店開發\n    案，當時以現金投資1 單位13萬5 千元，忘記Ｃ○○或海閣\n    林公司有無跟我說明投資案有可能會賠錢或獲利不低，海閣\n    林公司好像有跟我和解，我不追究了。（出處：警(一) 卷，\n    P452- P454、原審三卷，P94-P96）\n23、甲黃○\n    93年在「合緣婚友社」認識Ｉ○○，她對我推銷海閣林公司\n    的股份，向我遊說公司的投資方案有多好，說她媽媽也有投\n    資，說她如果將來和我在一起，也希望我有良好的投資理財\n    觀念，我就拿現金27萬元投資2 單位。（出處：警(一) 卷，\n    P447- P449）\n24、甲宇○\n    93年間朋友介紹認識Ｉ○○，她對我推銷海閣林公司的股份\n    ，向我遊說投資方案有多好，她學姐李嘉倩也在那裡上班，\n    李嘉倩說她如果將來和我在一起，希望我有良好的投資理財\n    觀念，我就拿現金45萬元加貸款70萬元投資了9 單位共121\n    萬5 千元。（出處：警(一) 卷，P456-P458）\n25、甲辰○\n    93年間在「合緣婚友社」認識Ｉ○○，她對我推銷海閣林公\n    司的股份，說她伯父在那裡當主管，說如果將來想生活好一\n    點，就要有良好的投資理財觀念，我就投資3 單位共40萬5\n    千元，並以貸款取得投資之資金來源。（出處：警(一) 卷，\n    P463-P465）\n26、地○○\n    93年間在「合緣婚友社」認識Ｉ○○，她對我推銷海閣林公\n    司的股份，向我遊說投資方案有多好，她堂姐在那裡當主管\n    ，說如果將來想生活好一點就要有良好的投資理財觀念，我\n    就投資3 單位共40萬5 千元，並以辦貸款方式取得投資資金\n    來源。（出處：警(一) 卷，P470-P472）\n27、ｉ○○\n    93年間在「溫馨婚友社」認識Ｉ○○，她對我推銷海閣林公\n    司的股份，向我遊說投資方案有多好，她乾哥在那裡當經理\n    ，我投資10單位共135 萬元，並以貸款取得投資資金來源。\n    （出處：警(一) 卷，P477-P479）\n28、甲ｑ○\n    92年間在「溫馨婚友社」認識Ｉ○○，說她想換到海閣林公\n    司上班，跟我介紹公司的投資方案有多好，她親戚也在裡面\n    上班，說她如果將來和我在一起，希望我能有良好的投資理\n    財觀念，我就投資2 單位27萬元，並以貸款取得投資的資金\n    。（出處：警(四) 卷，P1497-P1499）\n29、亥○○\n    91年間認識Ｊ○○，她對我推銷海閣林公司的股份，向我遊\n    說投資方案有多好，說她哥哥在那裡上班，說她如果將還和\n    我在一起，希望我能有良好的投資理財觀念，我就投資2 單\n    位共27萬元並以貸款取得投資的資金。（出處：警(一) 卷，\n    P482-P484）\n30、巳○○\n    91年年間在婚友社認識Ｊ○○，向我遊說投資方案有多好，\n    說她表哥在那裡上班，說她如果將還和我在一起，希望我能\n    有良好的投資理財觀念，我就投資3 單位共40萬5 千元並以\n    貸款取得投資的資金。（出處：警(一)卷，P490-P492）\n31、Ｗ○○\n    91年間在「和信婚友社」認識Ｊ○○，她向我慫恿海閣林公\n    司在綠島有一個投資獲利不錯，並提供書面給我參考，並找\n    來一位自稱她「阿伯」的中年男子讓我認識，2 人一直慫恿\n    我投資海閣林公司，說獲利很好，我共買3 單位40萬5 千元\n    ，並貸款取得投資的資金。（出處：警(一)卷，P496-P49 8）\n32、乙午○\n    93年間在「欣緣婚友社」認識Ｉ○○，說有親戚在海閣林公\n    司上班，對我介紹投資海閣林公司推出的綠島海閣林休閒渡\n    假酒店方案，說她如果將來和我在一起，希望我能有良好的\n    投資理財觀念，並帶我到綠島看海閣林休閒渡假酒店施工的\n    情形，我有看到工人在施工，就投資10單位135 萬，我將證\n    件交給代辦公司共向2 家銀行貸款185 萬元用以支付投資款\n    項。（出處：警(三) 卷，P1355-P1357）\n33、乙酉○\n    93年間在網路上認識Ｌ○○，她說投資海閣林公司的股份將\n    來一定會賺很多錢，如投資每單位是13萬5 千元，將來每單\n    位價值會增值，向我遊說公司的投資方案有多好，且她大哥\n    在那裡上班，我就投資4 單位共計54萬元，並以貸款取得投\n    資的資金。（出處：警(一) 卷，P507-P509）\n34、甲Ｎ○\n    93年在網路上認識Ｌ○○，她對我推銷海閣林公司的股份，\n    向我遊說投資方案有多好，她表哥也在裡面當主任，說她如\n    果將來和我在一起，希望我能有良好的投資理財觀念，我就\n    投資6 單位共81萬元，並將16萬元現金給Ｌ○○，其餘投資\n    款項以貸款方式取得。他說投資海閣林穩賺不賠，幫我爭取\n    2 個單位，後又追加到6 個單位，不斷打電話給我，叫我再\n    買。她當時叫我幫她看這個投資好不好，之後進一步叫我買\n    ，她說公司陸續有在蓋，現以超過契約上預計完工的時間。\n    當初被告戊○○是說要把酒店蓋在綠島，我們是一直到新聞\n    爆發「辣妹吸金五億」才知道被騙。（出處：警(一)卷，P517\n    - P519、偵九卷，P12 、偵十八卷，P9-P10、P21 、P30）\n35、乙亥○\n    93年間經朋友介紹認識Ｌ○○，她對我推銷海閣林公司的股\n    份，向我遊說投資方案有多好，她哥哥有在那裡當主管，說\n    她如果將來和我在一起，希望我能有良好的投資理財觀念，\n    我就投資8 單位共計108 萬元，並以貸款方式取得投資的資\n    金。（出處：警(一) 卷，P511-P513）\n36、甲Ｇ○\n    93年間認識Ｌ○○，她對我推銷海閣林公司的股份，說政府\n    要在94年在綠島開放賭博條款，公司取得政府簽約可成立休\n    閒渡假酒店的投資方案，海閣林公司發展前景看好，她哥哥\n    是公司主管，事後叫我跟她去台中營業處瞭解公司營運狀況\n    ，說等公司正式營運時，只要投資，每單位都匯獲利3 到4\n    成左右，最後因我只有現金17萬元，貸款僅貸得10萬元，故\n    我僅投資2 單位共27萬元。我買2 個單位都是Ｌ○○介紹的\n    ，她說投資海閣林穩賺不賠，開始她先叫我幫她看投資好不\n    好，之後就叫我買，買之後就不理我。後我發覺她在那邊工\n    作，就覺得她是在騙我。（出處：警( 一) 卷，P522-P524\n    、偵十八卷，P10-P11 、P30 ）\n37、甲天○\n    92年經朋友介紹認識Ｌ○○，她對我推銷海閣林公司的股份\n    ，說她哥哥是公司主管，叫我跟她去台中的公司，讓我瞭解\n    營運狀況，她說她有投資，如錯過這個機會以後就沒有了，\n    我就投資2 單位共27萬元，並以貸款取得投資的資金。當時\n    以海閣林五星級休閒渡假酒店向我們推銷，說她乾父有投資\n    這個事業，只有員工才能買，她透過內部關係買了4 個，願\n    2 個給我投資。我合約是她帶我到她們公司簽的，見證律師\n    是事先蓋好的，當時僅我們2 人在場，沒看到辦公室，只有\n    1 魏櫃檯小姐，是在會客室內簽約。Ｌ○○說投資海閣林酒\n    店獲利很高，但根本沒那間酒店，電視有報導，那是私人住\n    宅。發現受騙是因電視報導違法吸金。我有打電話給公司，\n    公司說沒辦法退費。她謊稱她乾爸有特權，可買海閣林酒店\n    4 個單位，她把2 單位讓我給，共27萬元，她們是非法吸金\n    。93年6 月份她說她乾爹是內政部退休的官員，海閣林的金\n    主，可以買。（出處：警( 一) 卷，P527-P529 、偵十六卷\n    ，P4 -P5、P48-P49 、P57 、偵十八卷，P5、P16-P17 、P2\n    9- P30、偵二十卷，P271）\n38、義龍\n    93年間透過朋友介紹認識Ｌ○○，她向我介紹投資海閣林公\n    司有多好，希望我能有良好的投資理財觀念，好好把握海閣\n    林公司那麼好的投資機會，之後我和她去台新銀行西台中分\n    行開戶，我在該行貸款88萬4 千3 百元，入帳後她就從我戶\n    頭匯出67萬4 千30元（30元為匯費），錢匯出後她才帶我到\n    海閣林公司台中辦公室簽約，我投資5 單位67萬5 千元（1\n    千元定金已先付）簽約前Ｌ○○有帶我去海閣林公司台中辦\n    公室，有人跟我介紹在綠島的開發案相關內容，當時有跟我\n    說該飯店一定會在今年暑假正式營運，到時公司有獲利，股\n    東就可以分紅。（出處：警( 四) 卷，P1516-P1518 ）\n39、癸○○92年間在網路上認識Ｍ○○，她對我推銷海閣林公司\n    的股份，向我遊說投資方案有多好，她表哥在裡面當主任，\n    說她如果將來和我在一起，希望我能有良好的投資理財觀念\n    ，我就投資4 單位共54萬元。（出處：警(一)卷，P532-P534)\n40、乙ｌ○\n    93年間經朋友介紹認識Ｍ○○，她對我推銷海閣林公司的股\n    份，遊說公司的投資方案有多好，說她乾哥在當主任，說她\n    如果將來想生活好一點就要有良好的投資理財觀念，94年間\n    我就投資3 單位共40萬5 千元，並以貸款取得投資的資金。\n    我們是一直到新聞爆發「辣妹吸金五億」才知道被騙。（出\n    處：警( 一) 卷，P537-P539 、偵九卷，P21 、偵十九卷，\n    P27- P28）\n41、乙庚○\n    92年間在台中青年生活館婚友社認識Ｍ○○，她對我推銷海\n    閣林公司的股份，遊說公司的投資方案有多好，說她媽有投\n    資，公司負責人是她舅舅，等渡假飯店完工才會申請國際觀\n    光賭場，說她如果將來想生活好一點，就要有良好的投資理\n    財觀念，我就以現金投資6 單位共81萬，6 個單位是Ｍ○○\n    陪我去買的，我不知道海閣林酒店是何種執照，他們說在申\n    請中，沒告訴我是集合住宅執照。（出處：警( 一) 卷，\n    P540- P542、偵二卷，P269-P270 ）\n42、乙甲○\n    94年在網路聊天室認識Ｍ○○，她約我去台中的海閣林公司\n    ，告訴我她乾爸在海閣林公司擔任總經理，說海閣林在7 月\n    就會正式營運，現在正是投資的好機會，明（95）年股份就\n    可轉換成股票就會賺錢，拿出綠島的施工照片及有關公司獲\n    利分析圖片慫恿我投資，強調會拜託她乾爸替我向公司爭取\n    股份讓我投資，我就貸款投資了2 單位共27萬元。（出處：\n    警( 二) 卷，P546-P548 ）\n43、甲Ｕ○\n    93年間認識Ｍ○○，說她哥哥在海閣林公司擔任主任，說她\n    全家都有投資海閣林公司，海閣林公司有在綠島興建五星級\n    的休閒渡假酒店，希望我也一起投資，對我說海閣林公司將\n    來是綠島第一家五星級大飯店，前景看好一定會賺大錢，我\n    投資5 單位67萬5 千元，我向萬泰銀行貸款70萬元投資。投\n    資時Ｍ○○有對我說公司正在申請旅館執照，且她說她去過\n    綠島看過工程進度，把綠島海閣林大飯店說的很豪華，讓我\n    相信海閣林公司真的要蓋五星級大飯店，因合約內容這麼寫\n    ，我才投資。（出處：警(二) 卷，P604-P606）\n44、甲ｔ○\n    93年間在網路上認識Ｎ○○，跟我說她是海閣林公司的業務\n    員，叫我為了自己的將來著想，一定要有經濟基礎，她乾哥\n    在高雄「翻天創新公司」上班，來台中時約我見面，他們一\n    直跟我說投資綠島海閣林五星級休閒渡假大酒店，將來營運\n    會賺大錢，如投資每單位13萬5 千元的話，將來每單位價值\n    會增值，每年每股會約5 萬3 千元的利潤，我就投資2 單位\n    共27萬元。（出處：警(二) 卷，P553-P555）\n45、甲寅○\n    93年間在台中認識Ｎ○○，她對我推銷海閣林公司的股份，\n    遊說說公司的投資方案有多好，說希望我能有良好的投資理\n    財觀念，我就投資7 單位共94萬5 千元。（出處：警( 二)\n    卷，P557-P559 ）\n46、乙Ｑ○\n    94年在台中認識Ｎ○○，她說她乾哥在台中的海閣林公司當\n    經理，海閣林公司在綠島興建一間五星級的觀光休閒大酒店\n    ，將來營運會大賺錢，說現在每單位是13萬5 千元，將來每\n    單位的價值保證會增值，公司只給她6 個單位，她自己有投\n    資6 個單位，後我投資了3 單位共40萬5 千元。（出處：警\n    (二) 卷，P564-P567）\n47、乙Ｗ○\n    93年間在「和信婚友社」認識馮志群、Ｘ○○，她們對我推\n    銷海閣林公司的股份，向我遊說公司的投資方案有多好，她\n    表姊在那裡面工作，說如果將來和我在一起，希望我能有良\n    好的投資理財觀念，我投資13單位共175 萬5 千元，我當時\n    向4 家銀行貸款225 萬元投資。（出處：警(二) 卷，P623-\n    P625）\n48、甲ｎ○\n    91年間在網路婚友社認識李美菁，她一直對我推銷海閣林公\n    司的股份，向我遊說公司的投資方案有多好，她乾爹在海閣\n    林公司投資，說如果將來想生活好一點，就要有良好的投資\n    理財觀念，我投資3 單位共40萬5 千元，我以貸款取得投資\n    的資金。（出處：警(二) 卷，P627-P629）\n49、甲ｇ○\n    93年間經朋友介紹認識Ｘ○○，她對我推銷海閣林公司的股\n    份，向我遊說投資方案有多好，她姊姊在那裡面當副總，說\n    如果將來想生活好一點，就要有良好的投資理財觀念，我投\n    資14單位共188 萬元，我以貸款取得投資的資金。（出處：\n    警(二) 卷，P630-P632）\n50、甲ａ○\n    93年間在「和信婚友社」認識Ｘ○○，帶我到海閣林公司介\n    紹她乾哥給我認識，他提到海閣林公司在綠島有一個海閣林\n    休閒渡假酒店的的投資案獲利不錯，並讓我看介紹綠島觀光\n    景點的影片，Ｘ○○慫恿我投資海閣林公司，每單位13萬5\n    千元，投資後獲利很好，說我們將來會過的比較好，我前後\n    共投資5 單位共67萬5 千元並以貸款取得投資的資金。（出\n    處：警( 二) 卷，P638-P640 ）\n51、乙天○\n    93年間透過「欣緣婚友社」認識Ｘ○○，說她兄長姓薛在海\n    閣林公司當副總，公司計畫在綠島投資開發一五星級渡假觀\n    光飯店，94年可完工開始營業，95年可開始分紅，每股投資\n    額為13萬5 千元，一年約獲利20萬元，因我缺資金，薛副總\n    表示可先簽約，若簽約後不想投資他會接收我的股份，我前\n    後去海閣林公司4 、5 次，後我心動，決定先簽約5 單位81\n    萬元，簽約後我向2 家銀行信用貸款共100 萬元，其中81萬\n    元Ｘ○○以我提款卡逐次提領支付投資款項。（出處：警J\n    卷，P54-P55 ）\n52、乙Ｂ○\n    91年間在「合信婚友社」認識李群鳳，說她表哥在海閣林公\n    司當經理，海閣林公司在綠島投資興建五星級的休閒渡假酒\n    店，投資1 單位13萬5 千元，將來海閣林公司的股份一定會\n    增值到每單位50萬元，每單位就可以淨賺36萬5 千元，我投\n    資6 單位共81萬元。（出處：警( 二) 卷，P674-P676 ）\n53、卯○○\n    93年間經朋友介紹認識ｈ○○，她對我推銷海閣林公司的股\n    份，向我遊說公司的投資方案有多好，她哥哥在那裡面上班\n    ，說她如果將來和我在一起，希望我能有良好的投資理財觀\n    念，我就投資9 單位共121 萬5 千元，並以貸款方式取得投\n    資資金。（出處：警( 二) 卷，P693-P695 ）\n54、乙Ｍ○\n    93年間在「合信婚友社」認識ｈ○○，她對我推銷海閣林公\n    司的股份，向我遊說公司的投資方案有多好，說她乾哥在裡\n    面上班，說她如果將來和我在一起，希望我能有良好的投資\n    理財觀念，那麼好的投資機會一定要好好把握，我就投資6\n    單位共81萬元，並以貸款取得投資的資金。（出處：警( 二\n    ) 卷，P696-P698 ）\n55、乙ｂ○\n    93年間在「溫馨婚友社」認識ｈ○○，她對我推銷海閣林公\n    司的股份，不斷向我遊說公司的投資方案有多好，她乾哥也\n    在那裡面上班，說她如果將來和我在一起，希望我能有良好\n    的投資理財觀念，向海閣林那麼好的投資機會一定要好好把\n    握，我就投資5 單位共67萬5 千元，並以貸款方式取得投資\n    的資金。（出處：警( 二) 卷，P701-P703 ）\n56、ｃ○○\n    93年間在「溫馨婚友社」認識ｈ○○，認識沒多久她就約1\n    位自稱海閣林公司的助理工程師乙ｈ○，由他介紹海閣林公\n    司在綠島有投資1 個海閣林休閒渡假酒店案，宣稱投資1 單\n    位是13萬5 千元，每月可有8 千元的獲利，沒現金的話可幫\n    我辦貸款，之後我陸續投資5 單位共67萬5 千元，均以貸款\n    方式支付投資金額。（出處：警( 二) 卷，P708-P710 ）\n57、乙Ｅ○\n    93年間在「溫馨婚友社」認識ｈ○○，她對我推銷海閣林公\n    司的股份，向我遊說公司的投資方案有多好，說她表哥在海\n    閣林公司當主管，說如果將來想生活好一點就要有良好的投\n    資理財觀念，我就投資7 單位共94萬5 千元，並以貸款方式\n    取得投資金額。（出處：警( 二) 卷，P715-P717 ）\n58、乙ｑ○\n    92年間在「溫馨婚友社」認識ｈ○○，她對我推銷海閣林公\n    司的股份，向我遊說公司的投資方案有多好，她表哥是海閣\n    林公司主管，說如果將來想生活好一點就要有良好的投資理\n    財觀念，我就投資1 單位共13萬5 千元，並以貸款方式取得\n    投資資金。\n59、甲ｃ○\n    93年間在婚友社認識ｈ○○，她對我推銷海閣林公司的股份\n    ，向我遊說公司的投資方案有多好，叫我去愛河邊，介紹投\n    資海閣林渡假酒店就等於是跟中部的日月潭涵碧樓一樣，說\n    她爸是涵碧樓的股東，現她要介紹我這間海閣林渡假酒店跟\n    涵碧樓的前景一樣看好，海閣林公司的主管是她乾哥，叫我\n    跟她去公司瞭解營運狀況，播放DVD 簡介要把綠島變成觀光\n    勝地一般，說如果將來想生活好一點，就要有良好的投資理\n    財觀念。我就投資3 單位共40萬5 千元，並以貸款方式取得\n    投資資金。（出處：警( 二) 卷，P724-P726 ）\n60、乙寅○\n    93年間在「和信婚友社」認識ｈ○○，她說她表哥在海閣林\n    公司任職，海閣林公司有在綠島投資興建五星級的休閒渡假\n    酒店，希望我投資，她說海閣林將來是綠島第一家五星級大\n    飯店，前景看好一定會賺大錢，我就投資5 單位共67萬5 千\n    元，並以貸款取得投資資金。（出處：警( 二) 卷，P730-P\n    732 ）\n61、Ｈ○○\n    92間在「溫馨婚友社」認識ｈ○○，一個月後她介紹她一位\n    張姓學姐，說是任職海閣林公司，那學姐向我說她們公司在\n    綠島有一個海閣林休閒渡假酒店的投資案，每單位13萬5 千\n    元，稱投資該渡假酒店獲利不錯，之後帶我到她們公司又有\n    好幾位過來慫恿我投資，我前後共投資4 單位共108 萬，並\n    以貸款及現金支付投資款項。（出處：警( 二) 卷，P738-P\n    740 ）\n62、甲Ｘ○\n    93年間認識ｈ○○，說她表哥在海閣林公司有投資，海閣林\n    公司有在綠島投資興建五星級的休閒渡假酒店，希望我一起\n    投資，對我說海閣林將來是綠島第一家五星級大飯店，前景\n    看好且一定會賺大錢，希望我能投資理財以保障將來的生活\n    ，我投資9 單位共121 萬5 千元，並以貸款取得投資的資金\n    來源。（出處：警(二) 卷，P745-P747）\n63、甲Ｃ○\n    92年間在台中「非常男女婚友社」認識林詩怡，她向我說她\n    表舅在海閣林公司擔任很高的職務，海閣林公司在綠島投資\n    興建五星級的休閒渡假酒店，希望我投資，說海閣林將來是\n    綠島第一家五星級大飯店，前景看好一定會賺大錢，我投資\n    2 單位27萬元，並向台新銀行西台中分行貸款40萬用以支付\n    投資款項。（出處：警(二) 卷，P755-P757）\n64、甲Ｋ○\n    94年間透過朋友認識甲子○，她告訴我他乾爹和乾媽都在海\n    閣林擔任企劃人員，公司在綠島進行一項開發案，如我投資\n    入股，年底就可分紅，帶我到公司看介紹綠島新建工程的影\n    片，之後我貸款投資8 單位共108 萬元。（出處：警J 卷，\n    P3-P4 、警(二) 卷，P790-P792）\n65、ｆ○○（起訴書誤載為林寶生）\n    92年在婚友社認識洪琦霞，她親戚也在海閣林公司上班，對\n    我推銷投資海閣林，一直對我推銷海閣林公司所推出的綠島\n    海閣林休閒渡假酒店，說她如果將來和我在一起，也希望我\n    能有良好的投資理財觀念，像海閣林公司那麼好的投資機會\n    希望我能好好把握，我以現金投資8 單位共108 萬元。\n    （出處：警(二) 卷，P780-P782）\n66、蘇志雄\n    93年間在「溫馨婚友社」認識洪琦霞，說她乾爸在海閣林公\n    司擔任顧問，說她全家都有投資海閣林公司，海閣林公司在\n    綠島投資興建五星級的休閒渡假酒店，對我說海閣林將來是\n    綠島第一家五星級大飯店，前景看好且一定會賺大錢，我投\n    資15單位共202 萬5 千元，並以貸款取得投資的資金。\n    （出處：警(二) 卷，P785-P787）\n67、天○○\n    92年間在婚友社認識洪琦霞，她跟我介紹投資海閣林公司有\n    多好，希望我能有良好的投資理財觀念，將來賺的錢也能當\n    作結婚基金，我投資3 單位40萬5 千元，並將證件交給她去\n    向萬泰銀行貸款40萬，因金額不夠，她叫我刷卡5 萬，可我\n    只刷1 萬多，共被騙41萬多，核貸後她直接將錢領走。\n    （出處：警(四) 卷，P1506-P1508）\n68、Ｖ○○\n    93年間在「合緣婚友社」認識甲子○，她對我推銷海閣林公\n    司的股份，說她乾爸是海閣林公司的主管，叫我跟她去公司\n    瞭解營運狀況，說等公司正式營運後就會賺錢，說她有投資\n    8 單位，錯過機會以後就沒有，當時她還跟她小阿姨跟我說\n    公司是如何的好，說他們有投資過日月潭的大飯店有賺到錢\n    ，我就貸款投資7 單位共94萬5 千元。（出處：警(二) 卷，\n    P794- P796）\n69、宇○○\n    94年在網路上認識許惠鈴，告訴我她舅舅最近有個投資案賺\n    很多錢，問我要不要參加，當時我想瞭解一下詳情，她帶我\n    到台中的海閣林公司，說94年7 、8 月間將正式對外營業，\n    我以貸款投資4 單位共54萬元。（出處：警( 二) 卷，P876\n    - P879）\n70、辛○○\n    94年間在網路上認識甲Ｊ○，她對我推銷海閣林公司的股份\n    ，向我遊說公司的投資方案有多好，她舅舅在裡面當主管，\n    說她如果將來和我在一起，希望我能有良好的投資理財觀念\n    ，我就以貸款投資5 單位共67萬5 千元。（出處：警( 二)\n    卷，P882-P884 ）\n71、乙宙○\n    94年間經朋友介紹認識甲Ｊ○，說她舅舅在海閣林公司任職\n    ，她有投資她舅舅的公司且賺了不少錢，海閣林在綠島投資\n    興建五星級的休閒渡假酒店，希望我一起投資，她和她舅舅\n    不斷對我說海閣林將來是綠島第一家五星級大飯店，前景看\n    好一定賺大錢，我就以貸款投資9 單位共121 萬5 千元。\n    （出處：警(二) 卷，P887-P889）\n72、劉延銓\n    93年間經朋友介紹認識甲Ｊ○，她說她爸爸的乾兒子在海閣\n    林公司任職，說她想投資海閣林公司，海閣林公司有在綠島\n    投資興建五星級的休閒渡假酒店，希望我一起投資，對我說\n    海閣林將來是綠島第一家五星級大飯店，前景看好一定會賺\n    大錢，我就貸款投資5 單位共67萬5 千元。（出處：警( 二\n    ) 卷，P891-P893 ）\n73、乙ｏ○\n    93年間經朋友介紹認識甲Ｊ○，說她大哥在海閣林台中辦事\n    處任職，她有投資海閣林公司在綠島投資興建的五星級休閒\n    渡假酒店，希望我一起投資，她介紹投資方案時，不斷吹噓\n    海閣林的前景非常非常看好，投資的資金回收很快，不久就\n    可回本並開始獲利，我就貸款投資8 單位共108 萬元。\n    （出處：警(二) 卷，P896-P898）\n74、庚○○\n    92年間在台中「非常男女婚友社」經甲Ｐ○介紹認識吳瓊峰\n    ，後甲Ｐ○稱她媽媽要投資海閣林公司在綠島的休閒渡假酒\n    店，希望我跟她一起投資，投資1 單位要13萬5 千元，當天\n    我即匯款13萬5 千元，後又以貸款投資3 單位共40萬5 千元\n    ，前後共投資4 單位54萬元。（出處：警(二)卷，P904-P907)\n75、ｎ○○\n    92年間在「欣緣婚友社」認識陳怡文，她對我推銷海閣林公\n    司的股份，向我遊說公司的投資方案有多好，她父親在那裡\n    面上班，說她如果將來和我在一起，希望我能有良好的投資\n    理財觀念，我就貸款投資4 單位共54萬元。（出處：警( 二\n    ) 卷，P924-P926 ）\n76、乙ｙ○\n    92年間在「和信婚友社」認識陳怡文，她對我推銷海閣林公\n    司的股份，不斷向我遊說公司的投資方案有多好，她表哥在\n    裡面工作，說她如果將來和我在一起，希望我能有良好的投\n    資理財觀念，我就貸款投資2 單位共27萬元。（出處：警(\n    二) 卷，P927-P929 ）\n77、乙ｄ○\n    92年間在婚友社認識陳怡文，她對我推銷海閣林公司的股份\n    ，向我遊說公司的投資方案有多好，說她爸爸跟海閣林主管\n    很好，說如果將來想生活好一點就要有良好的投資理財觀念\n    ，我就貸款投資6 單位共81萬元。（出處：警( 二) 卷，P9\n    33-P935 ）\n78、乙申○\n    93年間在「溫馨婚友社」認識甲ｆ○，她對我推銷海閣林公\n    司的股份，向我遊說公司的投資方案有多好，她伯伯在海閣\n    林公司當主管，說如果將來想生活好一點，就要有良好的投\n    資理財觀念，我就貸款投資3 單位共40萬5 千元。（出處：\n    警( 二) 卷，P911-P913 ）\n79、乙Ｐ○\n    94年間在「溫馨婚友社」認識甲ｆ○，她對我推銷海閣林公\n    司的股份，向我遊說公司的投資方案有多好，告訴我海閣林\n    休閒渡假酒店會像墾丁凱撒飯店發展前景看好，叫我跟他去\n    公司瞭解營運狀況，播放DVD 簡介要把綠島變成觀光勝地一\n    般，說如果將來想生活好一點就要有良好的投資理財觀念，\n    我就貸款投資5 單位共67萬5 千元。（出處：警( 二) 卷，\n    P915 - P917 ）。\n80、乙ｃ○\n    93年間在「欣緣婚友社」認識甲ｆ○，她說她哥在海閣林公\n    司任職，她有投資海閣林公司，海閣林公司在綠島投資興建\n    五星級的休閒渡假酒店，希望我一起投資，說海閣林公司將\n    來是綠島第一家五星級大飯店，前景看好一定賺大錢，希望\n    我能投資理財保障將來的生活，我貸款投資3 單位共40萬5\n    千元。（出處：警(二) 卷，P919-P921）\n81、甲Ｙ○\n    92年間在「溫馨婚友社」認識甲Ｒ○，她對我推銷海閣林公\n    司的股份，向我遊說公司的投資方案有多好，她哥哥在那裡\n    面上班，說她如果將來和我在一起，希望我能有有良好的投\n    資理財觀念，我就貸款投資4 單位共54萬元。（出處：警(\n    二) 卷，P938-P940 ）\n82、甲丑○\n    92年間在「溫馨婚友社」認識甲Ｒ○，說她表姊在海閣林公\n    司任職，海閣林公司在綠島投資興建五星級的休閒渡假酒店\n    ，希望我跟她一起投資，說如果將來2 個人有在一起的話，\n    要有經濟基礎，海閣林在綠島所蓋的休閒渡假大酒店有王夢\n    麟做保證，她乾爹也有投資，那麼好的投資機會一定要好好\n    把握，我就投資1 單位13萬5 千元。（出處：警( 二) 卷，\n    P944 -P946）\n83、乙Ｓ○\n    91年間在「溫馨婚友社」認識甲Ｒ○，她對我推銷海閣林公\n    司的股份，向我遊說公司的投資方案有多好，說她乾爹是海\n    閣林公司的股東，說她希望我能有良好的投資理財觀念，我\n    就以貸款和辦理現金卡的方式取得資金並投資3 單位共40萬\n    5 千元。（出處：警( 二) 卷，P950-P952 ）\n84、ｋ○○\n    93年間在「合緣婚友社」認識甲ｂ○，她對我推銷海閣林公\n    司的股份，向我遊說公司的投資方案有多好，說她如果將來\n    和我在一起，希望我能有良好的投資理財觀念，我就貸款投\n    資8 單位共108 萬元。（出處：警( 二) 卷，P956-P958 ）\n85、Ｂ○○\n    93年間在「欣緣婚友社」認識甲ｂ○與Ｘ○○，先由Ｘ○○\n    向我慫恿海閣林公司在綠島有一個投資案獲利不錯，帶我到\n    公司看綠島興建工程的影片，慫恿我投資海閣林公司，說以\n    後獲利很好，我就投資1 單位，之後甲ｂ○向我鼓吹，我又\n    投資2 單位，我前後共投資3 單位，並以現金支付投資金額\n    40萬5 千元。（出處：警( 二) 卷，P960-P962 ）\n86、乙癸○\n    93年間在「欣緣婚友社」認識甲ｂ○，她向我慫恿海閣林公\n    司在綠島有一個海閣林休閒渡假酒店的投資案，稱該投資案\n    獲利不錯，為將來著想，要有投資才有保障，我就允諾買1\n    單位，後她主管幫我辦理現金卡用以支付5 萬3 千元現金，\n    餘款8 萬5 千元我未再補繳。（出處：警(二)卷，P964-P 966\n    ）\n87、ｊ○○\n    94年間在「慧萊婚友社」認識甲ｂ○，她說她哥哥在海閣林\n    公司任職，她有投資海閣林公司，海閣林公司在綠島投資興\n    建五星級的休閒度假酒店，希望我一起投資，不斷對我說海\n    閣林將來是綠島第一家五星級大飯店，前景看好一定會賺大\n    錢，說如果將還和我交往的話，希望我能投資理財以保障將\n    來的生活，我就貸款投資3 單位共40萬5 千元。（出處：警\n     (二) 卷，P968-P970 ）\n88、甲戌○\n    91年間經朋友介紹認識甲ｄ○，她告訴我她舅舅最近有個投\n    資案很賺錢，問我要不要參加，我想說瞭解一下詳情，她就\n    帶我到公司，且說94年即將正式對外營業，我就以貸款投資\n    9 單位共121 萬5 千元。（出處：警(二) 卷，P972-P975 ）\n89、乙戌○\n    93年間在網路上認識甲ｍ○，她對我推銷海閣林公司的股份\n    ，向我遊說公司的投資方案有多好，她表哥在裡面當主任，\n    說她如果將來和我在一起，希望我能有良好的投資理財觀念\n    ，我就貸款投資7 單位共94萬5 千元。（出處：警( 二) 卷\n    ，P996- P998）\n90、玄○○\n    93年間在網路上認識甲ｍ○，她對我推銷海閣林公司的股份\n    ，向我遊說公司的投資方案有多好，她表哥在裡面當主任，\n    說她如果將來和我在一起，希望我能有良好的投資理財觀念\n    ，我就拿現金6 萬元及以貸款投資2 單位共27萬元。（出處\n    ：警( 二) 卷，P1001-P1003 ）\n91、林豊田\n    94年間在網路上認識甲ｍ○，說如要長期交往的話，為將來\n    著想，一定要有經濟基礎，她乾哥在海閣林公司上班，有透\n    過關係從公司拿出幾仟股的股份，要我也投資，說她也有投\n    資綠島海閣林五星級休閒渡假大酒店，該投資案將來營運會\n    大賺錢，如投資每單位13萬5 千元，將來每單位將會增值，\n    我就貸款投資3 單位共40萬5 千元。（出處：警( 二) 卷，\n    P1001-P1003 ）\n92、甲丁○\n    93年間在網路聊天室尋夢園跟甲ｍ○聊天，之後她稱有親戚\n    在做投資，且對投資方面很厲害，說她要跟他們一起去綠島\n    玩，回來後就說她們親戚有認識海閣林公司的人，接著向我\n    推銷3 單位，每單位13萬5 千元，她說她有買，我就當場先\n    下定金6 萬元而其餘款項以貸款金額支付，並於銀行核貸後\n    ，由她陪我去提領，並將錢匯給戊○○帳戶，後又將我定存\n    解約匯款27萬元至戊○○帳戶，前後共投資5 單位67萬5 千\n    元。（出處：警( 三) 卷，P1010-P1012 ）\n93、子○○\n    93年間在台中經朋友介紹認識甲ｍ○，她對我推銷投資海閣\n    林公司的股份，遊說公司的投資方案有多好，說她表姊也在\n    海閣林公司擔任幹部，海閣林的投資案只有員工和家屬本身\n    可投資，我原本要投資2 單位，但甲ｍ○未經我同意擅自以\n    我名義投資7 單位，並將核貸後的錢94萬5 千元匯至海閣林\n    公司戶頭。（出處：警(三) 卷，P1016-P1018 、P1010）\n94、乙ｔ○\n    93年間在網路上認識甲ｍ○，說她有個乾哥在台中海閣林公\n    司當經理，海閣林公司正在綠島興建一間五星級的觀光休閒\n    大酒店，將來營運會賺大錢，說如果將來要一起組織家庭的\n    話，有需要有經濟基礎，希望我能好好把握海閣林這個投資\n    機會，說現每單位13萬5 千元，將來每單位的價值保證會增\n    值，公司只給她6 單位，她投資4 單位，另2 單位希望我投\n    資，我就以現金投資2 單位共27萬元。（出處：警( 三) 卷\n    ，P1030- P1032）\n95、乙丁○\n    93年間在台中茶藝館認識甲ｍ○，她對我推銷海閣林公司的\n    股份，向我遊說公司的投資方案有多好，以後會像日月潭的\n    涵碧樓飯店發展前景看好，她舅舅是海閣林公司的主管，事\n    後叫我跟她去台中的海閣林公司，他們在公司有放樣品屋，\n    讓我瞭解營運狀況，說等公司正式營運時，只要投資每單位\n    都會獲利5 萬元左右，說她已經投資2 單位，如果將來想生\n    活好一點就要有良好的投資理財觀念，我就辦貸款投資1 單\n    位13萬5 千元。（出處：警( 三) 卷，P1036-P1038 ）\n96、乙Ｔ○\n    93年間在台中認識甲ｍ○，她說她哥哥在海閣林公司任職經\n    理，她想投資海閣林公司，而海閣林公司有在綠島投資興建\n    五星級的休閒渡假酒店，希望我一起投資，對我說海閣林將\n    來是綠島第一家五星級大飯店，前景看好且一定會賺大錢，\n    我就投資7 單位共94萬5 千元，並向台新、中國信託及新竹\n    商業銀行貸款共128 萬元，其中94萬5 千元投資海閣林，代\n    辦費用也繳了3 萬多元。（出處：警(三) 卷，P1040-P1042）\n97、甲宙○\n    93年間透過同事介紹認識甲ｍ○，她又介紹我認識她哥哥徐\n    毓良，說任職於海閣林公司，並帶我到台中大隆路，她和她\n    哥哥向我慫恿投資她們公司在綠島有一個海閣林休閒渡假酒\n    的投資案，每單位13萬5 千元，稱投資該渡假酒店獲利不錯\n    ，本來我只想投資2 單位，但她向我說公司還剩下4 單位，\n    看我要不要買足4 單位，投資多就回收的愈快，銀行貸款會\n    比較快還清，一年一個單位九可賺15萬元等，後我就投資4\n    單位共54萬元，並向3 家銀行共貸款75萬元，核貸後甲ｍ○\n    帶我去提領，並將54萬元到公司交給徐毓良簽約。（出處：\n    警(三) 卷，P1045-P1047）\n98、丁○○\n    93年間在朋友介紹下認識甲ｓ○，她對我推銷海閣林公司的\n    股份，向我遊說公司的投資方案有多好，她大哥也在裡面工\n    作當負責人，說如果將來想生活好一點就要有良好的投資理\n    財觀念，我就投資8 單位108 萬元，並向4 家銀行共貸款15\n    8 萬元，核貸後她就把我的錢領走去投資，剩下的錢讓銀行\n    扣除。（出處：警( 三) 卷，P1049-P1051 ）\n99、甲Ｆ○\n    93年間經朋友介紹認識甲ｓ○，她對我推銷海閣林公司的股\n    份，說她大哥是海閣林休閒渡假酒店公司的主管，叫我跟她\n    去台中的公司，讓我瞭解公司營運狀況，等公司正式營運時\n    ，只要投資，每個月1 單位都會獲利1 萬多元左右，她說她\n    有投資5 單位，如錯過機會以後就沒有了，我買7 單位94萬\n    5 千元，她幫我辦貸款80萬元。（出處：警( 三) 卷，P105\n    6- P1058）\n100、乙丑○\n     93年間在「欣緣婚友社」認識馮志群（已更名甲ｖ○），\n     她對我推銷海閣林公司的股份，向我遊說公司的投資方案\n     有多好，說她如果將來想和我在一起，希望我能有良好的\n     投資理財觀念，我就投資5 單位67萬5 千元，並向2 家共\n     貸款120 萬元，核貸後她直接將錢領走。（出處：警( 三)\n     卷，P1060- P1062）\n101、丙○○\n     93年間在「欣緣婚友社」認識馮志群（已更名甲ｖ○），\n     她對我推銷海閣林公司的股份，向我遊說公司的投資方案\n     有多好，她大哥在裡面當副總，說如果將來想生活好一點\n     ，就要有良好的投資理財觀念，我就投資7 單位94萬5 千\n     元，並向2 家共貸款120 萬元，核貸後她直接將錢領走。\n     （出處：警(三) 卷，P1060-P1062）\n102、甲酉\n     93年間經朋友介紹認識馮志群（已更名甲ｖ○），她對我\n     推銷海閣林公司的股份，向我遊說公司的投資方案有多好\n     ，她哥哥在海閣林公司當主管，跟我說如果將來想生活好\n     一點就要有良好的投資理財觀念，我就投資3 單位40萬5\n     千元，我向3 家銀行貸款62萬元，核貸後她將錢領有去投\n     資，剩下的錢留在銀行代扣。（出處：警( 三) 卷，P106\n     7- P1069 ）\n103、甲庚○\n     93年間在「合信婚友社」認識馮志群（已更名甲ｖ○），\n     她對我推銷海閣林公司的股份，遊說公司的投資方案有多\n     好，她表哥在裡面上班，我貸款197 萬投資9 單位共121\n     萬元，核貸後她將我的錢提領交給她表哥乙ｈ○處理。\n     （出處：警(三) 卷，P1072-P1074）\n104、甲ｅ○\n     93年間在「和信婚友社」認識馮志群（已更名甲ｖ○），\n     她對我推銷海閣林公司的股份，說她乾哥是主管，叫我跟\n     她去高雄的公司，讓我瞭解公司的營運狀況，等公司正是\n     營運的時候就會賺大錢，說她有投資，如錯過機會以後就\n     沒有了，我就向2 家銀行共貸款48萬元投資3 單位40萬5\n     千元。（出處：警( 三) 卷，P1076-P1078 ）\n105、甲Ｗ○\n     93年間在「欣緣婚友社」認識甲ｖ○，告訴我她爸爸在海\n     閣林公司擔任環境污水處理的技師，知道該公司在94年7\n     、8 月間即將正式營運，現是投資的好時機，明年就可回\n     收獲利，並拿出很多有關綠島地區旅遊分析的圖表及投資\n     獲利分析圖表慫恿我投資，說公司股份都已額滿，會特別\n     拜託她媽媽徐郁華向公司爭取股份讓我投資，我就答應投\n     資21單位共283 萬5 千元，並向6 家銀行共貸款350 萬元\n     ，手續費被扣25萬元，扣除投資金額剩30幾萬元我都拿來\n     償還貸款。（出處：警( 三) 卷，P1080-P1082 ）\n106、甲未○\n     93間參加高中同學會，高中同學即前女友馮志群（已更名\n     甲ｖ○）在同學會後常約我，後向我說她是在海閣林公司\n     上班，向我慫恿海閣林公司在綠島有一個海閣林休閒渡假\n     酒店的投資案，每單位13萬5 千元，該投資案獲利不錯，\n     我即允諾購買1 單位，並於1 禮拜後交付現金13萬5 千元\n     給她，嗣我又購買1 單位，並再交付她13萬5 千元現金，\n     前後共購買2 單位27萬元。（出處：警( 三) 卷，P1087-\n     P1089）\n107、甲Ｌ○\n     93年間透過朋友認識馮志群（已更名甲ｖ○），她向我說\n     她一位鄭姓大哥任職海閣林公司擔任主管，她向我宣稱她\n     要投資海閣林公司，之後向我慫恿海閣林公司在綠島有一\n     個海閣林休閒渡假酒店的投資案，每單位13萬5 千元，投\n     資該酒店獲利不錯，後帶我到公司認識鄭大哥，並看一些\n     介紹綠島興建工程的模型，後她約我到綠島實地看工地後\n     ，她要我用貸款方式購買10單位，共向銀行貸款200 萬元\n     ，但扣除手續費後僅拿到180 萬元，該筆款項即由貸款公\n     司直接匯給戊○○的中國信託銀行帳戶，後又購買3 單位\n     ，款項亦由代辦公司匯入戊○○帳戶，前後共購買13單位\n     175 萬5 千元，投資完後我曾找她想要回投資款項，因她\n     沒經我同意將核貸後的錢全部投入購買海閣林公司的投資\n     案，但她一再哭訴，我未再追究逼討。（出處：警( 三)\n     卷，P1095-P1097 ）\n108、甲丙○\n     93年間在「欣喜婚友社」認識甲ｖ○，她對我推銷海閣林\n     公司的股份，說她朋友是海閣林休閒渡假酒店公司的主管\n     ，事後叫我跟她去高雄的公司，讓我瞭解公司的營運狀況\n     ，等公司正式營運時，只要投資每個月1 單位都會獲利1\n     萬多元，她說有投資1 單位，如錯過機會以後就沒有了，\n     我就買1 單位13萬5 千元，並找2 家銀行共貸款40萬元，\n     手續費7 萬多。（出處：警(三) 卷，P1100-P1102）\n109、ｙ○○\n     93年間在網路上認識甲ｗ○，他為我推銷海閣林公司的股\n     份，說他家中發生財務問題，跟我調現金13萬5 千元，事\n     後他拿1 張海閣林公司的合約書給我當作是還我的錢，向\n     我遊說公司的投資方案有多好，說吳俊德在公司當副總，\n     希望我能有良好的投資理財觀念，我就投資9 單位121 萬\n     5 千元，並向銀行貸款172 元，核貸後他將錢直接領走，\n     剩下的錢放在銀行。（出處：警(三)卷，P1105-P1107）\n110、甲Ｅ○\n     93年間在奇摩交友站認識甲ｗ○，他跟我說他是在海閣林\n     公司上班，他以生涯規劃及替未來作打算等語，對我推銷\n     海閣林公司的股份，向我說明公司的投資方案有多好，告\n     訴我海閣林公司會把綠島變成觀光勝地的為一五星級大飯\n     店，我說沒錢不想投資，他說沒錢可利用貸款方式投資理\n     財，我就投資7 單位94萬5 千元，然後向3 家銀行貸款共\n     144 萬元，甲ｗ○拿走100 萬元投資，其中5 萬5 千元說\n     是給銀行抽成佣金，剩餘44萬元扣除貸款利息。（出處：\n     警(三) 卷，P1109-P1111）\n111、乙ａ○\n     94年間在網路上認識黃彩惠（已更名乙子○），她對我推\n     銷海閣林公司的股份，向我遊說公司的投資方案有多好，\n     她舅舅在裡面當主任，說她如果將來和我在一起，希望我\n     能有良好的投資理財觀念，我就投資3 單位40萬5 千元，\n     並將證件交給她去向台新銀行辦貸款67萬元，核貸後她直\n     接將錢領走去投資，剩下的錢先還清，其餘都讓銀行去扣\n     除。（出處：警(三) 卷，P1120-P1122）\n112、乙Ａ○\n     92年間經同學介紹認識黃彩惠（已更名乙子○），她說她\n     舅舅在台中海閣林公司當經理，海閣林公司在綠島興建一\n     間五星級的觀光休閒大酒店，將來營運會賺大錢，每單位\n     13萬5 千元，將來每單位價值保證會增值，我投資2 單位\n     27萬元，並將證件交給她辦貸款，核貸後她就將錢匯出去\n     。（出處：警(三)卷，P1124-P1126）\n113、Ｓ○○\n     94年間在「蕙萊婚友社」認識乙Ｃ○，她向我慫恿說海閣\n     林公司在綠島有一個投資按獲利不錯，帶我到高雄的公司\n     由她及一張特助給我看一些介紹綠島新建工程的影片及建\n     築模型，慫恿我投資海閣林，說以後獲利很好，我就投資\n     3 單位40萬5 千元，並將款項匯入戊○○中國信託銀行帳\n     戶內。（出處：警(三) 卷，P1158-P1160）\n114、乙辰○\n     93年間在網路上認識劉珈妤，她對我推銷海閣林公司的股\n     份，說她哥哥是海閣林休閒渡假酒店公司的主管，叫我跟\n     她去高雄的公司瞭解營運狀況，等公司正式營運時會賺錢\n     ，說她有投資10單位，錯過機會就沒有了，我投資10單位\n     135 萬元，她幫我辦貸款150 元，手續費拿15萬多，說在\n     94年1 月就可賣出且會獲利，93年12月有到公司說股權要\n     轉讓的事，公司的人說要自己找買主。（出處：警( 三)\n     卷，P1162- P1164）\n115、甲甲○\n     93年間在婚友社認識劉珈妤，她說她乾姐在海閣林公司當\n     副理，海閣林公司在綠島有投資興建五星級的休閒渡假酒\n     店，希望我跟她一起投資，如將來2 人有在一起，需要有\n     經濟基礎，她父母也是投資致富，那麼好的投資機會要好\n     好把握，她本身也有投資，1 單位13萬5 千元將來股份一\n     定會增值，我投資2 單位27萬元。（出處：警(三) 卷，\n     P1165-P1167）\n116、甲Ｔ○\n     92年間在「溫馨婚友社」認識劉珈妤，她說她在翻天建築\n     做業務，她對我推銷海閣林公司的股份，向我遊說公司的\n     投資方案有多好，告訴我海閣林休閒渡假酒店公司以後會\n     向墾丁的凱撒飯店發展前景看好，說她哥哥是股東，叫我\n     跟她去高雄的公司瞭解營運狀況，說如果將來想生活好一\n     點就要有良好的投資理財觀念，我投資3 單位40萬5 千元\n     ，並向台新銀行貸款45萬元，抽成2 萬多，她把錢直接匯\n     到海閣林公司的帳戶內。（出處：警( 三) 卷，P1171-\n     P1173 ）\n117、Ｋ○○\n     93年間經同事介紹認識劉珈妤，她說她乾哥在海閣林公司\n     任職，她本身也有投資，海閣林公司在綠島投資興建五星\n     級的休閒渡假酒店，希望我一起投資，對我說海閣林將來\n     是綠島第一家五星級大飯店，前景看好一定會賺大錢，如\n     投資入股，有很高利潤可圖，完工後約1 個月至少可拿到\n     1 萬元紅利，希望我能投資理財保障將來的生活，我投資\n     6 單位共81萬元，並將證件交給她去幫我向4 家銀行辦貸\n     款，共貸得91萬元，核貸後我將存摺及印章交給她直接提\n     領81萬元投資海閣林，代辦費用4 萬元。（出處：警（三\n     ）卷，P1177-P 1179、警J 卷，P36-P37 ）\n118、黃健清\n     93年間在網路上認識劉家宜，她一直對我推銷海閣林公司\n     的股份，向我遊說公司的投資方案有多好，她表哥在裡面\n     當主任，說她如果將來和我在一起，希望我能有良好的投\n     資理財觀念，我投資3 單位40萬5 千元，並拿證件給她幫\n     我向萬泰銀行貸款60萬元，核貸後她直接把錢領走去投資\n     ，剩下的錢讓銀行扣除。（出處：警( 三) 卷，P1186-P1\n     18 6-1 ）\n119、乙卯○\n     93年間在「溫馨婚友社」認識乙黃○，說她想改名「珈妤\n     」，要我叫她「珈妤」，她說她乾哥在海閣林公司當經理\n     ，海閣林公司正在綠島興建一間五星級的觀光休閒大酒店\n     ，將來營運會大賺錢，她一直跟我介紹海閣林公司的股份\n     ，說如果將來還有在一起的話，有經濟基礎的話比較有保\n     障，每單位是13萬5 千元，將來每單位的價值會增值，我\n     投資4 單位54萬元，並向銀行辦理貸款，核貸後我將錢領\n     出來，她再陪我去公司繳錢。（出處：警( 三) 卷，\n     P1188- P1190）\n120、甲ｏ○\n     91年間被朋友慫恿購買海閣林的股份1 單位，當時不是被\n     他們公司的辣妹所騙。當時是公司業務員幫我辦貸款，我\n     再把現金領出來交給業務員。（出處：警( 三) 卷，P119\n     2- P1194 ）\n121、甲巳○\n     93年間在「溫馨婚友社」認識乙Ｄ○○，有次藉口要帶我\n     去她表哥戊○○的海閣林公司辦公室找他，當天由戊○○\n     向我介紹他們公司正積極推展有關綠島海閣林休閒渡假酒\n     店的投資案，每單位13萬5 千元，我答應購買，並由乙Ｄ\n     ○○幫我辦信用貸款80萬元，後由她直接在我帳戶提款，\n     但我到公司與戊○○簽約，嗣乙Ｄ○○以朋友反悔不購買\n     要我購買為由，我共投資5 單位67萬5 千元。（警( 三)\n     卷，P1198-P1200 ）\n122、ｂ○○\n     91年間在「雙惠婚友社」認識乙Ｄ○○，她對我推銷海閣\n     林公司的股份，遊說公司的投資方案有多好，她爸爸也有\n     投資，說她如果將來和我在一起，希望我能有良好的投資\n     理財觀念，我就拿現金給她投資2 單位27萬元。（出處：\n     警(三) 卷，P1203-P1205）\n123、乙Ｖ○\n     92年間經朋友介紹認識乙Ｄ○○，她告訴我她表哥最近有\n     個投資案賺很多錢，問我要不要參加，我想說瞭解一下詳\n     情，她就帶我到高雄的公司，後有位經理說這個投資會很\n     賺錢，並以涵碧樓為例子，我就向2 家銀行貸款85萬元投\n     資5 單位67萬5 千元。（出處：警(三)卷，P1206-P1208 ）\n124、甲卯○\n     92年間在「合信婚友社」認識乙Ｄ○○，她說她表哥在海\n     閣林公司任職，海閣林在綠島投資興建五星級的休閒渡假\n     酒店，希望我投資，說海閣林將來是綠島第一家五星級大\n     飯店，前景看好一定賺大錢，投資前我有向公司詢問，公\n     司拿了一堆設計圖和綠島土地的資料給我看，我投資4 單\n     位54萬元，我將證件交給她，她帶我去辦貸款，共向2 家\n     銀行貸款60萬元。（出處：警(三) 卷，P1214-P1216）\n125、甲壬○\n     90年間在「美群婚友社」認識乙Ｇ○，她對我推銷海閣林\n     公司的股份，向我遊說公司的投資方案有多好，說戊○○\n     是她舅舅，在海閣林公司當主管，說如果將來想生活好一\n     點就要有良好的投資理財觀念，我就拿現金交給乙Ｇ○投\n     資1 單位13萬5 千元。（出處：警（三）卷，P1127-P112\n     9）\n126、ｌ○○\n     93年間在網路上認識蔡宜庭，她對我推銷海閣林公司的股\n     份，向我遊說公司的投資方案有多好，她哥哥在那裡面當\n     主任，說她如果將來想和我在一起，希望我能有良好的投\n     資理財觀念，我投資6 單位81萬元，並拿證件給她幫我向\n     3 家銀行貸款共100 萬元，核貸後她直接把錢領走去投資\n     ，剩下的錢由銀行扣除。（出處：警(三)卷，P1255-P1257)\n127、甲Ｈ○\n     93年間經朋友介紹認識蔡宜庭，她對我推銷海閣林公司的\n     股份，向我遊說公司的投資方案有多好，她哥哥在那裡面\n     當主任，說她如果將來想和我在一起，希望我能有良好的\n     投資理財觀念，我拿現金投資2 單位27萬元。（出處：警\n     (三)卷，P1259-P1261）\n128、Ａ○○\n     93年間在網路上認識蔡宜庭，說她表哥在海閣林公司任職\n     ，她有投資海閣林公司且賺了不少錢，海閣林公司在綠島\n     投資興建五星級的休閒渡假酒店，希望我投資，她表哥說\n     海閣林將來是綠島第一家五星級大飯店，前景看好一定會\n     賺大錢，我投資4 單位54萬元，並以貸款取得投資的資金\n     。（出處：警(三) 卷，P1263-P1265）\n129、Ｆ○○\n     要告的是庭上的蔡宜庭，共買6 個單位，她沒有對我說是\n     集合住宅，沒說適合執照，只說要開酒店。（出處：偵二\n     十卷，P184）\n130、甲ｙ○\n     91年間在「友馨婚友社」認識乙Ｘ○，她說她有個哥哥在\n     海閣林公司上班，海閣林公司和王夢麟有合作，正在綠島\n     興建一間五星級的觀光休閒大酒店，將來營運會大賺錢，\n     一直跟我介紹投資海閣林公司的股份，投資每單位13萬5\n     千元，將來每單位的價值會增值，我就投資2 單位27萬元\n     ，並將證件交給她向4 家銀行貸款共30萬元，核貸後她把\n     我戶頭內的錢匯給她哥哥。（出處：警( 三) 卷，P1287-\n     P1289 ）\n131、乙Ｏ○\n     91年間在網路上認識乙ｋ○，她對我推銷海閣林公司的股\n     份，向我遊說公司的投資方案有多好，她朋友在裡面工作\n     ，說她如果將來和我在一起，希望我能有良好的投資理財\n     觀念，我拿現金投資3 單位40萬5 千元。（出處：警（三\n     ）卷，P1292-P1294 ）\n132、乙宇○\n     91年間經朋友介紹認識羅姿桂，她告訴我她表哥最近有個\n     投資案賺很多錢，問我要不要投資，我當時想說瞭解一下\n     詳情，她就帶我到海閣林公司附近，後有位自稱她哥的男\n     子過來說這個投資案會很賺錢，我向二信貸款90萬元，投\n     資4 單位54萬元，而手續費扣8 萬多。（出處：警( 三)\n     卷，P1297-P1300 ）\n133、甲亥○\n     93年年間認識方慧令，她說她有一個大哥在台中海閣林公\n     司當經理，海閣林公司正在綠島興建一間五星級的觀光休\n     閒大酒店，將來營運會大賺錢，說如果將來我們要一起組\n     織家庭的話，也需要有經濟基礎，希望我能好好把握海閣\n     林這個投資機會，將來每單位價值保證會增值，公司只給\n     他10單位，她自己有投資5 單位，我就向2 家銀行貸款共\n     80萬元，而我投資5 單位67萬5 千元，並於核貸後才將投\n     資的錢轉匯給她。時隔已久忘記本案銷售交易小姐或到公\n     司簽約時在場之公司男性職員為何人，（出處：警( 一)\n     卷，P311-P313 、原審三卷，P213-P214 ）\n134、ｓ○○\n     91年間在「和信婚友社」認識江家秀，她告訴我她乾爹戊\n     ○○有個投資案很賺錢，問我要不要參加，帶我到海閣林\n     公司，有位經理說這個投資會很賺錢，以涵碧樓為例子，\n     後又有江家秀表姊「雅惠」加入遊說行列，我投資4 單位\n     52萬5 千元，投資資金來源8 萬元是用現金卡支付，另向\n     高雄區中小企業銀行貸款50萬元，手續費被扣3 萬多，其\n     中44萬5 千元支付投資款項。時隔已久忘記本案銷售交易\n     之小姐或到公司簽約時在場之公司男性職員為何人。（出\n     處：警(一) 卷，P412-P414 、原審三卷，P213-P214）\n135、乙ｎ○\n     93年間在「和信婚友社」認識何依驊，她說她叔叔在海閣\n     林公司任職，說她本身有投資海閣林公司，海閣林公司有\n     在綠島投資興建五星級的休閒渡假酒店，希望我一起投資\n     ，不斷對我說海閣林將來是綠島第一家五星級大飯店，前\n     景看好且一定會賺大錢，希望我能以投資理財以保障將來\n     的生活，我向台東企銀辦理信用貸款50萬元，而投資3 單\n     位40萬5 千元。（出處：警(一) 卷，P419-P421）\n136、甲癸○\n     93年間朋友介紹認識吳佳佩，她說她是行政助理，認識後\n     一直推銷海閣林公司的股份，說她乾哥是海閣林休閒渡假\n     酒店的主管，叫我跟她去台中的公司，讓我瞭解營運狀況\n     ，等公司正式營運時會賺錢，說她有投資3 個單位，如錯\n     過這個機會以後就沒有了，跟她乾哥一同說該公司的好，\n     我投資3 單位40萬5 千元，並向2 家銀行貸款共45萬元，\n     手續費花了3 萬多元。（出處：警(一) 卷，P426-P428）\n137、乙○○\n     92年間朋友介紹認識吳雅惠，她對我推銷海閣林公司的股\n     份，向我遊說投資方案有郭好，說如果將來想生活好一點\n     ，就要有良好的投資理財觀念，我就投資11單位，共148\n     萬元。因時隔已久，只見2 、3 次面，現已忘記當時銷售\n     小姐或到公司簽約時之在場男性職員為何人，有認為被騙\n     。（出處：警(二)卷，P570-P572 、原審三卷，P213-P214)\n138、乙Ｋ○\n     92年間在婚友社認識吳雅惠、劉依驊、李嘉蒨3 名女子，\n     她們陸續告訴我海閣林公司將在94年初建好五星級大酒店\n     並正式營運，現在是投資的好時機，如投資後馬上可回收\n     獲利，並拿出有關的投資與獲利分析資料慫恿我投資，我\n     就投資4 單位，共54萬元。因時隔已久，只見2 、3 次面\n     ，現已忘記當時銷售小姐或到公司簽約時之在場男性職員\n     為何人。（出處：警( 二) 卷，P577-P580 、原審三卷，\n     P213- P215）\n139、乙Ｎ○\n     92年間經朋友介紹認識吳蜜茹，她對我推銷海閣林公司的\n     股份，向我遊說投資方案有多好，說她朋友的舅舅在海閣\n     林公司當主管，說如果將來想生活好一點，就要有良好的\n     投資理財觀念，我就投資1 單位13萬5 千元。因時隔已久\n     ，只見2 、3 次面，現已忘記當時銷售小姐或到公司簽約\n     時之在場男性職員為何人。（出處：警卷，P598-P600 、\n     原審三卷，P213-P215）\n140、甲Ｕ○\n     93年間在台中認識Ｍ○○，說她哥哥在海閣林公司擔任主\n     任，說她全家都有投資海閣林公司，海閣林在綠島興建五\n     星級的休閒渡假酒店，希望我一起投資，說海閣林將來是\n     綠島第一家五星級大飯店，前景看好一定賺大錢，我投資\n     5 單位共67萬5 千元。（出處：警(二) 卷，P604-P606）\n141、乙ｖ○\n     92年間在「溫馨婚友社」認識吳靜雅，她對我推銷海閣林\n     公司的股份，向我遊說投資方案有多好，她表姊在海閣林\n     公司當主管，說如果將來想生活好一點，就要有良好的投\n     資理財觀念，我就投資5 單位共67萬5 千元。事隔已久已\n     忘記當時銷售小姐或到公司簽約時之在場男性職員為何人\n     。（出處：警(二)卷，P612-P614 、原審三卷，P216-P217)\n142、甲ｋ○\n     92年在「和信婚友社」認識吳謹如，她說海閣林公司在綠\n     島有一個投資按獲利不錯，帶我到海閣林公司看介紹綠島\n     興建工程的影片，然後陸續邀我出去見面，慫恿我投資，\n     說以後獲利很好，我分別以現金及貸款投資2 單位共27萬\n     元。（出處：警(二) 卷，P617-P619）\n143、ｅ○○\n     91年間在婚友社認識李倩儀，她是海閣林公司的助理，一\n     直對我推銷海閣林公司的股份，向我遊說投資方案有多好\n     ，說如果將來想生活好一點，就要有良好的投資理財觀念\n     ，我投4 單位共54萬元，我以貸款取得投資的資金來源。\n     因事隔已久，忘記本案銷售交易之小姐或到公司簽約時在\n     場之男性職員為何人，有認為被騙。（出處：警(二) 卷，\n     P635 -P637、原審三卷，P216-P217）\n144、酉○○\n     92年間在「和信婚友社」認識李喬芳，她告訴我她鄰居在\n     海閣林公司上班，劉姓經理告訴我公司將在93年間夏季正\n     式營運，現在是投資的好時機，馬上可回收獲利，拿出很\n     多有關投資與獲利分析的資料慫恿我投資，我投資1 單位\n     13萬5 千元，並以貸款取得投資的資金來源。忘記本案銷\n     售交易之小姐或到公司簽約時在場之男性職員為何人，有\n     認為被騙。（出處：警( 二) 卷，P642-P644 、原審三卷\n     ，P216-P217 ）\n145、甲Ｓ○\n     91年間在「溫馨婚友社」認識李瑞芳，她對我推銷海閣林\n     公司的股份，遊說公司的投資方案有多好，說她如果將來\n     和我在一起，希望我能有良好的投資理財觀念，我投資1\n     單位即13萬5 千元，並以貸款取得投資的資金來源。忘記\n     本案銷售交易之小姐或到公司簽約時在場之男性職員為何\n     人，有認為被騙。當時海閣林公司員工內無人勸說我投資\n     ，有拿回6 千餘元。（出處：警( 二) 卷，P653-P655 、\n     原審三卷，P216 -P219）\n146、甲乙○\n     91年間先認識李瑞芳，再認識「王大姐」、李嘉蒨、「小\n     棋」等3 名女子，王大姐說她在海閣林公司上班，向我慫\n     恿投資海閣林公司在綠島有一個海閣林休閒渡假酒店的投\n     資案，每單位13萬5 千元，之後打電話稱投資該渡假酒店\n     獲利不錯，約我出來看介紹綠島風景的簡介，我先投資4\n     單位，後李嘉蒨慫恿我用現金卡購買，我又投資1 單位，\n     前後共投資5 單位計67萬5 千元。我以貸款及辦理現金卡\n     支付投資的款項。無法指認本案銷售交易之小姐或到公司\n     簽約時在場之公司男性職員為何人，有認為本件投資被騙\n     。（出處：警( 二) 卷，P658-P660 、原審三卷，P218-\n     P219）\n147、ｄ○○\n     92年間在「和信婚友社」認識李瑞芳，我對我推銷海閣林\n     公司的股份，遊說公司的投資方案有多好，說如果將來想\n     生活好一點，就要有良好的投資理財觀念，我投資11單位\n     共148 萬5 千元，並以貸款取得投資的資金來源。無法指\n     認本案銷售交易之小姐或到公司簽約時在場之公司男性職\n     員為何人，有認為本件投資被騙。（出處：警( 二) 卷，\n     P668 -P670、原審三卷，P218-P219 ）\n148、乙巳○\n     92年間在網路上認識林芷萱，她對我推銷海閣林公司的股\n     份，向我遊說公司的投資方案有多好，她朋友的表姊在海\n     閣林公司當主管，說如果將來想生活好一點就要有良好的\n     投資理財觀念，我向萬泰銀行辦貸款20萬元投資1 單位13\n     萬5 千元，核貸後她直接把錢領走去投資，剩下的錢由銀\n     行代扣。無法指認本案銷售交易之小姐或到公司簽約時在\n     場之男性職員為何人，認為本件投資被騙。（出處：警(\n     二) 卷，P681-P683 、原審三卷，P218-P219 ）\n149、鍾建福\n     92年間因我女友林麗雯進入海閣林公司工作，跟我說她要\n     衝業績，我基於她是我女友才會接受她推銷海閣林公司的\n     股份，她不斷向我鼓舞遊說公司的投資方案有多好，叫我\n     跟她去公司，經由公司資料瞭解如何將綠島變成觀光勝地\n     一般，說如果將來想生活好過一點就要有良好的投資理財\n     觀念，我投資1 單位13萬5 千元，並貸款取得投資資金。\n     林麗雯進入海閣林工作後改名林芷萱。（出處：警( 二)\n     卷，P685-P687 、原審三卷，P220-P221 ）\n150、乙未○\n     93年間在網路上認識林美真，她跟我說她哥哥在海閣林公\n     司任職，說她本身也有投資海閣林公司，海閣林公司有在\n     綠島投資興建五星級的休閒渡假酒店，希望我一起投資，\n     且不斷對我說海閣林將來是綠島第一家五星級大飯店，前\n     景看好且每年可以回收大約5 萬元，我共投資2 單位共27\n     萬元。在庭之女子並非台中地區銷售交易之小姐。（出處\n     ：警( 二) 卷，P751-P753 ）\n151、甲Ｚ○\n     91年間經朋友介紹認識洪幸蕙，她對我推銷海閣林公司的\n     股份，向我遊說投資方案有多好，她舅舅跟老闆合資在當\n     主管，說如果將來想生活好一點就要有良好的投資理財觀\n     念，我投資10單位135 萬元，並以貸款方式取得資金來源\n     。看不出來洪幸蕙女子有無在場。認為受騙（出處：警(\n     二) 卷，P759-P761 、原審三卷，P220-P222 ）\n152、甲ｒ○\n     91及93年間在「溫馨婚友設」分別認識洪幸蕙及ｈ○○，\n     她們都說有親戚、朋友在海閣林公司任職，海閣林公司在\n     綠島投資興建五星級的休閒渡假酒店，她們本身都有投資\n     ，希望我一起投資，說海閣林將來是綠島第一家五星級大\n     飯店，前景看好一定會賺大錢，ｈ○○騙我說將來會跟我\n     在一起，所以要有投資觀念生活才有保障，我以現金投資\n     2 單位27萬元。沒有見到本案銷售交易之小姐或到公司簽\n     約時在場之公司男性職員，洪幸蕙、ｈ○○沒有在庭，時\n     隔已久無法指認海閣林公司對我遊說之人員。（出處：警\n     (二) 卷，P765-P767 、原審三卷，P220-P222）\n153、甲Ｍ○\n     91年間在婚友社認識洪欣惠，她對我推銷海閣林公司的股\n     份，向我遊說公司的投資方案有多好，說如果將來想生活\n     好一點，就要有良好的投資理財觀念，我就投資4 單位共\n     54萬元，並貸款取得投資金額。（出處：警( 二) 卷，P7\n     74- P776 ）\n154、甲戊○\n     93年間在台中認識洪薇雯，對我推銷海閣林公司的股份，\n     不斷向我鼓吹公司的投資方案有多好，說她乾哥在海閣林\n     公司工作，能透過他投資海閣林公司，那麼好的投資機會\n     希望我能好好把握，我以貸款投資6 單位共81萬元。認不\n     出來本案銷售交易之小姐或到公司簽約時在場之男性職員\n     為何人，因時隔已久，看不出來洪薇雯有無在庭，有認為\n     本件投資被騙。（出處：警( 二) 卷，P800-P802 、原審\n     三卷，P223- P224）\n155、ｖ○○\n     94年經朋友介紹認識洪薇雯，她對我推銷海閣林公司的股\n     份，說她乾爸的助手是海閣林公司的主管，叫我跟她去台\n     中的公司讓我瞭解營運狀況，等公司正是營運的時候會賺\n     錢，說她有投資6 單位，如錯過這個機會以後就沒有了，\n     說如果將來有機會在一起，一定要有良好的投資理財計畫\n     ，我就貸款投資4 單位共54萬元。一直到新聞爆發「辣妹\n     吸金五億」才知道被騙。任不出來本案銷售交易之小姐或\n     到公司簽約時在場之男性職員，認為被騙。（出處：警(二)\n     卷，P800-P802 、偵九卷，P12 、原審三卷，P223-P224)\n156、乙ｅ○\n     92年間在婚友社認識胡若羚，說她朋友在海閣林公司任職\n     ，海閣林公私有在綠島投資興建五星級的休閒渡假酒店，\n     希望我投資，說海閣林將來是綠島第一家五星級大飯店，\n     前景看好，一定賺大錢，我投資1 單位13萬5 千元。認不\n     出來本案銷售交易之小姐或到公司簽約時在場之男性職員\n     ，本件投資行為被騙。（出處：警( 二) 卷，P813-P815\n     、原審三卷，P223-P224 ）\n157、壬○○\n     93年間透過同事認識徐慧玲，之後她向我稱她跟一位朋友\n     要去綠島2 天，回來後便主動向我說她朋友袋她去綠島看\n     海閣林休閒渡假酒店建造工程，她朋友的乾爸是大股東、\n     有位大哥在裡面擔任幹部，工程大概會在94年7 月完工營\n     運，這個投資獲利案不錯，我後來共買了11單位148 萬5\n     千元，並以貸款取得投資的資金。不記得本案銷售交易之\n     小姐或到公司簽約時在場之男性職員，投資本案認為受騙\n     。（出處：警( 二) 卷，P819-P821 、原審三卷，\n     P225-P226 ）\n158、甲Ｄ○\n     93年間透過朋友認識張娟綾，她說她有位乾哥在翻天公司\n     上班，介紹我與他認識，她乾哥說他們公司在綠島有一個\n     海閣林休閒渡假的投資案，每單位13萬5 千元，後張娟綾\n     打電話給我稱投資該渡假酒店獲利不錯，並約我在台中辦\n     事處看一些介紹綠島投資案的興建模型及簡介，我即購買\n     4 單位共54萬元。不記得本案銷售交易之小姐或到公司簽\n     約之男性職員，投資本案有認為被騙。（出處：警( 二)\n     卷，P819-P821 、原審三卷，P225-P226 ）\n159、Ｔ○○\n     94年間認識張娟綾，說她舅舅在海閣林公司任職，她媽媽\n     有投資海閣林公司，海閣林公司有在綠島投資興建五星級\n     的休閒渡假酒店，希望我一起投資，說海閣林將來是綠島\n     第一家五星級大飯店，前景看好且一定會賺大錢，希望我\n     能投資理財以保障將來的生活，我投資6 單位共81萬元。\n     不記得本案銷售交易之小姐或到公司簽約時在場之男性職\n     員。投資本案有認為被騙，一直到新聞爆發辣妹吸金五億\n     才知道被騙。（出處：警( 二) 卷，P832-P834 、偵九卷\n     ，P12 、原審三卷，P225-P226 ）\n160、甲地○\n     92年在「溫馨婚友社」認識張容楨，說她親戚在海閣林公\n     司任職，她也有投資海閣林公司，海閣林公司有在綠島投\n     資興建五星級的休閒渡假酒店，希望我也一起投資，不斷\n     對我說海閣林將來是綠島第一家五星級大飯店，前景看好\n     一定會賺大錢，我投資8 單位共108 萬元。（出處：警(\n     二) 卷，P840-P842 ）\n161、ｏ○○\n     92年間在「溫馨婚友社」認識張雅雯，她對我推銷海閣林\n     公司的股份，向我遊說投資方案有多好，她舅媽也在那裡\n     面當主管，說如果將來想生活好一點，就要有良好的投資\n     理財觀念，我就投資1 單位13萬5 千元，並以貸款取得投\n     資資金。投資本案認為受騙。不記得本案銷售交易之小姐\n     或到公司簽約時在場之公司男性職員，認不出來張雅雯有\n     無在庭，我在網路上看到散佈訊息收購股權，所以將股權\n     以6 千元賣給對方做為和解。（出處：警(二) 卷，P847-\n     P849、原審三卷，P225-P226）\n162、乙ｍ○\n     92間在網路上的婚友社認識張雅雯，她對我推銷海閣林公\n     司的股份，向我遊說公司的投資方案有多好，她表哥在公\n     司當主管，說如果將來想生活好一點，就要有良好的投資\n     理財觀念，我就投資6 單位81萬元，並以貸款取得投資金\n     額。本案銷售交易之小姐或到公司簽約時在場之男性職員\n     不在現場，認為本件投資案有受騙。（出處：警( 二) 卷\n     ，P851 -P853、原審三卷，P227-P228 ）\n163、甲ｚ○\n     93年間在「溫馨婚友社」認識張雅雯，她對我推銷海閣林\n     公司的故份，遊說公司的投資方案有多好，說海閣林休閒\n     渡假酒店以後會向墾丁得凱撒飯店發展前景看好，她哥哥\n     是海閣林的股東，叫我跟她去公司瞭解營運狀況，還播放\n     DVD 簡介，說如果將來想生活好一點，就要有良好的投資\n     理財觀念，我貸款投資2 單位共27萬元。看不出來本案銷\n     售交易之小姐或到公司簽約時在場之男性職員。（出處：\n     警( 二) 卷，P857-P859 、原審三卷，P227-P229 ）\n164、ｕ○○\n     92年間在「溫馨婚友社」認識張雅雯，說她大伯的兒子在\n     海閣林公司擔任高級幹部，那位大伯的兒子向我遊說海閣\n     林公司在綠島有一個海閣林休閒渡假酒店的投資案，每單\n     位13萬5 千元，帶我到公司讓我看介紹綠島觀光景點的影\n     片，說擁有11個地主的權狀，並拿給我看，還拿寶成建設\n     公司的設計圖及休閒酒店的模型給我看，我前後投資10單\n     位135 萬。本案銷售交易之小姐或到公司簽約時在場之男\n     性職員沒有在場，對我詐騙之人沒有在場，和解金額為三\n     分之一即37-38 萬元左右，金額有存入銀行存摺。（出處\n     ：警(二) 卷，P862-P863 、原審三卷，230-P232）\n165、乙戊○\n     92年間在婚友社認識張雅雯，她對我推銷海閣林公司的股\n     份，向我遊說公司的投資方案有多好，她乾哥也在海閣林\n     工作，說她要我有良好的理財觀念，希望要好好把握，我\n     就貸款投資3 單位共40萬5 千元。時隔已久看不出來詐騙\n     我進行投資的張雅雯有無在庭，本件投資案有認為受騙。\n     （出處：警(二)卷，P867-P869、原審三卷，P228）\n166、乙壬○\n     91年間在婚友社認識許姿玲，她對我推銷海閣林公司的股\n     份，向我遊說公司的投資方案有多好，她媽有投資，公司\n     負責人是她舅舅，說如果將來想生活好一點，就要有良好\n     得投資理財觀念，我以貸款投資7 單位共97萬元。本案銷\n     售交易之小姐或到公司簽約時在場之男性職員不在庭，本\n     件投資案有認為受騙。（出處：警( 二) 卷，P873-P875\n     、原審三卷，P233-P234 ）\n167、ｚ○○\n     92年間在「合信婚友社」認識郭靜蓉，她對我推銷海閣林\n     公司的股份，向我遊說公司的投資方案有多好，她乾哥在\n     裡面上班，說她如果將來和我在一起，希望我能有良好的\n     投資理財穿念，那麼好的投資機會一定要好好把握，我貸\n     款投資7 單位共94萬5 千元。看不出來本案銷售交易之小\n     姐或到公司簽約時在場之公司男性職員為何人，本件投資\n     案認為受騙。（出處：警( 二) 卷，P900-P902 、原審三\n     卷，P227-P228 ）\n168、Ｄ○○\n     92年間認識陳蕎安，她對我推銷海閣林公司的股份，向我\n     遊說公司的投資方案有多好，她一楊哥哥也有投資，說她\n     希望我能有良好的投資理財觀念，那麼好的投資機會要好\n     好把握，我就投資2 單位共27萬元。本案銷售交易之小姐\n     或到公司簽約時在場之公司男性職員沒有在場，有受騙。\n     （出處：警(二)卷，P980-P982 、原審三卷，P230-P23 1 ）\n169、ｇ○○\n     91年10月在「合勝婚友社」認識陳蕎安，她說她大哥在海\n     閣林公司任職，海閣林公司有在綠島投資興建五星級的休\n     閒渡假酒店，希望我投資，說海閣林將來是綠島第一家五\n     星級大飯店，前景看好且一定會賺大錢，我就貸款投資3\n     單位40萬5 千元。本案銷售交易之小姐或到公司簽約時在\n     場之公司男性職員沒有在場，有受騙。（出處：警( 二)\n     卷，P984-P986 、原審三卷，P230-P231 ）\n170、寅○○\n     92年間在「成威婚友社」認識陳靜雅與Ｘ○○，先由陳靜\n     雅向我慫恿海閣林公司在綠島有一個投資案獲利不錯，帶\n     我到公司看介紹綠島興建工程的模型，慫恿我投資海閣林\n     ，我就買1 單位，後Ｘ○○也慫恿我投資海閣林公司，經\n     她鼓吹，我再投資2 單位，我前後共投資3 單位共40萬5\n     千元，並以貸款取得投資的資金。本案銷售交易之小姐或\n     到公司簽約時在場之公司男性職員沒有在場，有受騙。（\n     出處：警(二)卷，P991-P993 、原審三卷，P230-P231）\n171、乙辛○\n     93年間經朋友介紹認識黃美真，她對我推銷海閣林公司的\n     股份，向我遊說公司的投資方案有多好，她哥哥在那裡上\n     班，說她如果將來想和我在一起，希望我能有良好的投資\n     理財觀念，我就投資6 單位80萬元，由黃美真幫我向3 家\n     銀行貸款共100 萬元，核貸後她直接將拿領走。本案銷售\n     交易之小姐或到公司簽約時在場之男性職員不在庭上，95\n     年間被騙，該女子自稱黃美真，忘記她如何向我遊說，忘\n     記購買幾單位，購買金額約15萬元，對方沒說1 個單位13\n     萬5 千元，就到精明一街的公司簽約，貸款金額除投資外\n     ，其餘繳納利息，我投資80幾萬元。（出處：警( 三) 卷\n     ，P1115-P1117 、原審三卷，P233-P235 ）\n172、乙ｊ○\n     92年間在網路上認識黃詩婷，她對我推銷海閣林公司的股\n     份，向我遊說公司的投資方案有多好，她表哥在那裡面工\n     作當主任，說她如果將來和我在一起，希望我能有良好的\n     投資理財觀念，我就投資4 單位54萬元，並將證件交給她\n     幫我向台新銀行貸款60萬元，本來我要投資2 單位，但核\n     貸後她幫我多加1 個單位，又叫我借她13萬5 千元投資，\n     等她領錢再還我，後稱4 單位都是我買的，剩下的錢都是\n     讓銀行扣除。時隔已久不記得本案銷售交易之小姐或到公\n     司簽約時在場之男性職員為何人，本件投資有認為受騙。\n     （出處：警(三)卷，P1130-P1132 、原審三卷，P232-P234)\n173、ｑ○○\n     93年間在台中認識黃詩婷，她為我推銷海閣林公司的股份\n     ，向我遊說公司投資方案有多好，她自己也有投資，她哥\n     哥在海閣林公司上班，投資案只有員工的家屬和員工本身\n     可以投資而已，她因本身也要投資可是資金不夠，希望我\n     能幫她的忙一起投資海閣林公司，她有說要和我交往，我\n     就投資13單位共175 萬5 千元，我以存款50萬及向3 家銀\n     行貸款126 萬元，她未經我同意匯81萬元至戊○○戶頭。\n     不記得本案銷售交易之小姐或到公司簽約時在場之男性職\n     員為何人，本件投資案認為受騙。（出處：警( 三) 卷，\n     P1134-P1136、原審三卷，P232-P234 ）\n174、甲午○\n     93年間在網路上認識黃詩婷，她對我推銷海閣林公司的股\n     份，向我遊說公司的投資方案有多好，她表哥在海閣林公\n     司當主管，說如果將來想生活好一點就要有良好的投資理\n     財觀念，我就投資3 單位40萬5 千元，並將我證件給她去\n     向台新銀行辦貸款51萬元，核貸後她直接將錢領走去投資\n     ，剩下的錢留在銀行代扣。（出處：警(三) 卷，P1141-\n     P1143）\n175、乙ｘ○\n     93年間在台中認識黃詩瑾及Ｌ○○，黃詩瑾說她有一個乾\n     哥在海閣林公司上班，海閣林公司正在綠島興建一間五星\n     級的觀光休閒大酒店，將來營運會賺大錢，她一直跟我介\n     紹投資海閣林公司的股份，如投資每單位13萬5 千元，將\n     來每單位價值會增值1 到3 倍，我就投資10單位135 萬元\n     ，我拿我證件給她向3 家銀行貸款110 萬元，核貸後我把\n     現金領出來交給她。時隔已久忘記本案銷售交易之小姐或\n     到公司簽約時在場之公司男性職員為何人，本件頭資案有\n     認為受騙。（出處：警( 三) 卷，P1145-P1147 、原審三\n     卷，P236-P237 ）\n176、戌○○\n     93年間經同事介紹認識黃詩瑾，她對我推銷海閣林公司的\n     股份，向我遊說公司的投資方案有多好，她表哥在海閣林\n     公司當主管，說如果將來想生活好一點就要有良好的投資\n     理財觀念，我就投資11單位148 萬5 千元，並將證件交給\n     她幫我向2 家銀行辦貸款共120 萬元，我出現金28萬5 千\n     元，核貸後她與我一同前往提款，我將錢交給她去投資。\n     他沒說海閣林公司沒有酒店執照，不知道海閣林是集合式\n     住宅執照，她有拿過一張執照給我看，但我沒注意看，只\n     看一下就拿回去，也沒解釋執照內容。認不出來本案銷售\n     交易之小姐或到公司簽約時在場之公司男性職員為何人，\n     本件頭資案有認為受騙（出處：警( 三) 卷，P1150-P115\n     2、偵二十卷，P272-P273 、原審三卷，P236-P237 ）\n177、甲ｌ○\n     91年間在網路上認識潘唯心，她對我推銷海閣林公司的股\n     份，向我遊說公司的投資方案有多好，她哥哥在海閣林公\n     司當主管，跟我說如果想生活好一點就要有良好的投資理\n     財觀念，我就投資3 單位40萬5 千元，並將我證件交給她\n     幫我向高雄第二信用合作社貸款80萬元，核貸後她直接把\n     錢領走去投資，剩下的錢留在銀行代扣。認不出來本案銷\n     售交易之小姐或到公司簽約時在場之男性職員，本件投資\n     認為受騙，受騙金額80萬元左右，被告以2 萬多元與我和\n     解，認為受騙80萬元是因簽和解書之金額，時隔已久既不\n     清楚購買單位多少錢，記得購買3 單位。潘唯心領走3 單\n     位的錢。（出處：警( 三) 卷，P1233-P1235 、原審三卷\n     ，P236 -P238）\n178、丑○○\n     92年間經朋友介紹認識蔡羽庭，她對我推銷海閣林公司的\n     股份，向我遊說公司的投資方案有多好，說如果將來想生\n     活好一點就要有良好的投資理財觀念，我拿我證件給她幫\n     我向臺灣中小企銀貸款100 萬元，核貸後她直接把錢領走\n     去投資，我又拿100 多萬元現金給她，共購買19單位256\n     萬5 千元。時隔已久認不出來本案銷售交易之小姐或到公\n     司簽約時在場之男性職員，本件投資有認為受騙。（出處\n     ：警(三) 卷，P1239-P1241 、原審三卷，P236-P237）\n179、辰○○\n     93年間在台中認識蔡佳玲，她對我推銷海閣林公司的股份\n     ，不斷向我遊說公司的投資方案有多好，她乾哥哥在那裡\n     面上班，說希望我能有良好的投資理財觀念，向海閣林那\n     麼好的投資機會要好好把握，我投資4 單位，並將證件交\n     給她去幫我向2 家銀行辦貸款，共貸得70萬元，核貸後我\n     領54萬元給她完款投資。一直到新聞爆發辣妹吸金五億才\n     知道被騙。認不出來本案銷售交易之小姐或到公司簽約時\n     在場之男性職員為何人。本件投資認為受騙。（出處：警\n     (三)卷，P1245- P1247、偵九卷，P12 、原審三卷，P239 ）\n180、甲Ｏ○\n     91年間認識「小珊」、「喬藝」，她們對我推銷海閣林公\n     司的股份，向我遊說公司的投資方案有多好，說希望我能\n     有良好的投資理財觀念，向海閣林那麼好的投資機會一定\n     要好好把握，我就投資2 單位27萬元。本案銷售交易之小\n     姐或到公司簽約時在場之男性職員不在場。本件投資認為\n     受騙。（出處：警(三)卷，P1250-P1252 、原審三卷，P239\n     ）\n181、乙Ｈ○（原名蔡祖恩）\n     92年間在「欣緣婚友社」認識鄭靜茹，她對我推銷海閣林\n     公司的股份，向我遊說公司的投資方案有多好，她媽媽也\n     在裡面投資，說她如果將來和我在一起，希望我能有良好\n     的投資理財觀念，我將證件交給她去向安泰銀行辦理貸款\n     45萬元，我投資3 單位40萬5 千元，核貸後她直接將錢領\n     走。認不出來本案銷售交易之小姐或到公司簽約時在場之\n     男性職員為何人，本件投資有認為受騙。（出處：警( 三)\n     卷，P1269-P1271 、原審三卷，P239）\n182、乙Ｚ○\n     91年間因朋友蕭玄鈴在海閣林公司上班，她業績不好，我\n     為給她做業績才投資海閣林公司在綠島的投資案，我投資\n     2 單位，我朋友不是以詐騙手段叫我投資。認不出來本案\n     銷售交易之小姐或到公司簽約時在場之男性職員為何人，\n     本件投資行為有認為受騙。（出處：警( 三) 卷，P1277-\n     P1278 、原審三卷，P239）\n183、Ｚ○○\n     91年間在「和信婚友社」認識賴雅玲，她告訴我她舅舅最\n     近有個投資按賺很多錢，問我要不要投資，我當時只是想\n     瞭解一下詳情，她就帶我到高雄的公司，以涵碧樓的例子\n     ，說94年即將正式對外營業，我投資25單位337 萬5 千元\n     ，我拿現金250 萬元及向交通銀行貸款100 萬元投資。\n     （出處：警(三) 卷，P1280-P1283）\n184、甲Ａ○\n     92年間在「欣緣婚友社」認識Ｘ○○、蘇佳音，她們對我\n     推銷海閣林公司的股份，向我遊說公司的投資方案有多好\n     ，叔叔在裡面工作，說如果將來和我在一起，希望我能有\n     良好的投資理財觀念，我投資4 單位54萬元，並將證件交\n     給她們向4 家銀行貸款125 萬元，核貸後她們直接將錢領\n     走。（出處：警(三)卷，P1304-P1306）\n185、乙Ｙ○\n     不認識戊○○，李嘉倩應該是業務員，不能確定本名，詐\n     騙發生在92年、93年間。本案銷售交易之小姐或到公司簽\n     約時在場之男性職員沒有在庭，在交友中心認識李嘉倩，\n     她說她伯父在綠島飯店，要我貸款投資，我投資海閣林綠\n     島開發案94萬5 千元，認為被騙是因之後李嘉倩就消失無\n     蹤，當時李嘉倩有說要與我交往，拿錢給李嘉倩進行綠島\n     投資案是因當時相信她講的投資前景很不錯，要在綠島蓋\n     五星級飯店，忘記當時李嘉倩或海閣林公司人員有無跟我\n     說當時他們還未取得綠島開發案的執照，如果當時知道未\n     取得台東縣政府核發之執照，不會投資。我有到過公司，\n     當時認識李嘉倩約3 個月左右。（出處：偵二十卷，P269\n     、原審三卷，P241-P245）\n186、乙Ｊ○\n     91年間朋友乙ｋ○帶其他人一起介紹翻天創新公司戊○○\n     看準綠島無觀光飯店，想找人投資，鼓吹我購買該公司股\n     份，1 單位13萬5 千元，說前景看好，後我動心購買2 單\n     位，後來看到報紙才知道被騙。（出處：偵十卷，P3）\n187、乙ｇ○\n     92年間經朋友介紹認識靜宜，她對我推銷海閣林公司的股\n     份，向我遊說公司的投資方案有多好，她在裡面上班，是\n     很好的投資機會介紹給我，說如果將來和我在一起，希望\n     我能有良好的投資理財觀念，我投資4 單位54萬元，並將\n     證件交給她去向高企銀行貸款70萬元，核貸後她直接將錢\n     領走。（出處：警(三) 卷，P1311-P1313）\n188、甲己○\n     92年間陪我表妹去海閣林公司應徵工讀生，海閣林公司派\n     一位自稱「楊先生」的人出來向我表妹介紹工作性質，並\n     趁機跟我介紹海閣林公司的投資性質，不斷對我說公司的\n     股份未來將會從每單位13萬5 千元上漲到每單位20萬元，\n     投資報酬率非常高，叫我趕快投資，不然就來不及了，因\n     我表妹被錄用，海閣林公司就要我表妹來向我遊說投資，\n     我就投資1 單位13萬5 千元，並辦理貸款繳交投資款項。\n     楊先生之人無在庭，一開始不認為受騙，我曾打電話到公\n     司，也到綠島看飯店有在經營，但過1 年後我打電話到公\n     司，才發現公司不見了。楊先生及海閣林公司之人員沒有\n     跟我說明投資之風險及當時尚未取得台東縣政府核發旅館\n     建築執照，若當時知道未取得執照就不會投資。對方以6\n     千元與我和解。（出處：警( 三) 卷，P1318-P1320 、原\n     審三卷，P241-P244 ）\n189、己○○（起訴書記載王志中）\n     92年間透過婚友社認識李嘉倩，她向我介紹她乾爹有投資\n     海閣林公司有多好，希望我能有良好的投資理財觀念，好\n     好把握海閣林公司那麼好的投資機會，我在萬泰銀行貸款\n     80萬元，後她帶我去辦公司簽約，我投資2 單位27萬元，\n     並分2 次提領現金交給李嘉倩。簽約前李嘉倩有帶我去高\n     雄的公司，在那有人跟我介紹海閣林公司在綠島的開發案\n     相關內容，說在93年12月以前完全營運，事後說要延後94\n     年完工，到時公司有獲利，股東就可分紅。簽約時他們有\n     逐條向我解釋合約書的內容，但我是在還沒簽約時就把錢\n     匯給公司。（出處：警(四) 卷，P1527-P1529）\n190、乙玄○\n     92年間在網路上認識一女子，名字忘記，她對我推銷海閣\n     林公司的股份，不斷向我遊說公司的投資方案有多好，她\n     表哥也在裡面工作，說她如果想要和我在一起，希望我能\n     有良好的投資理財觀念，我投資3 單位40萬5 千元，她拿\n     我的證件去高雄商業銀行貸款100 萬元，核貸後她直接將\n     錢領走去投資，剩下的錢讓銀行扣除。本案銷售交易之小\n     姐或到公司簽約時在場之男性職員沒有在場，本件投資認\n     為被騙。（出處：警( 三) 卷，P1323- P1325、原審三卷\n     ，P241 、P243 ）\n191、Ｑ○○\n     92年間在「欣緣婚友社」認識吳靜雅，她說她乾爹有投資\n     海閣林公司，該公司在綠島投資興建海閣林休閒渡假酒店\n     ，向我介紹將來酒店營運後會非常賺錢，我投資5 單位67\n     萬5 千元，她替我向交通銀行貸款60萬左右，我拿我郵局\n     提款卡給吳靜雅，由她將我的所要投資的錢匯出去。認不\n     出來本案銷售交易之小姐或到公司簽約時在場之男性職員\n     ，有認為受騙，有和解，和解金額為15萬-17 萬間。（出\n     處：警(四)卷，P1538-P1540 、原審三卷，P241-P244）\n192、甲ｘ○\n     91年間在婚友社認識一女業務員，名字忘記，她說以後如\n     要長期交往的話，一定要有經濟基礎，她父母都投資綠島\n     一間五星級的觀光休閒大酒店的投資事業，將來營運會大\n     賺錢，王夢麟也是股東之一，應不會騙人，如投資每單位\n     是13萬5 千元的話，將來每單位的價值將會增值1 到3 倍\n     ，我投資3 單位40萬5 千元，她說她媽媽已經幫我支付投\n     資款項，所以我將錢匯入她媽媽的戶頭。（出處：警( 三)\n     卷，P1327- P1329）\n193、Ｅ○○\n     91年間在網路上認識「YOKO」女子，她介紹蕭先生給我認\n     識，然後蕭先生對我推銷海閣林公司的股份，向我遊說公\n     司的投資方案有多好，說希望我要趁年輕的時候，有良好\n     的投資理財觀念，向海閣林公司那麼好的投資機會一定要\n     好好把握，我向高雄二信貸款80萬元投資4 單位54萬元，\n     當時先給蕭先生3 萬元定金，核貸後我領51萬元匯給他。\n     本案銷售交易之小姐或到公司簽約時在場之男性職員不在\n     場，騙我的人是女的，當時匯款51萬元給蕭先生存摺上有\n     紀錄，蕭先生是「YOKO」介紹的，認為受騙。（出處：警\n     (三) 卷，P1333-P1335 、原審三卷，P246-P249）\n194、甲玄○\n     91年間認識一女子，名字忘記，她對我推銷海閣林公司的\n     股份，說她在海閣林休閒渡假酒店擔任會計，叫我跟她去\n     公司，讓我瞭解公司營運狀況，說等公司正式營運會賺錢\n     ，她說她有投資，拿合約給我看，說如果錯過機會就沒有\n     了，我買3 單位36萬元，並貸款40萬元用以支付投資金額\n     ，貸款手續費5 千多元。時隔已久忘記本案銷售交易之小\n     姐或到公司簽約時在場之男性職員為何人，本件投資行為\n     認為受騙。（出處：警( 三) 卷，P1338-P1340 、原審三\n     卷，P246-P249 ）\n195、乙ｗ○\n     91年間在「和信婚友社」認識一女子，名字忘記，綽號「\n     小琪」，她是海閣林公司員工，她舅舅也在海閣林公司任\n     職，說她本身有投資海閣林公司，海閣林公司有在綠島投\n     資興建五星級的休閒渡假酒店，希望我一起投資，表示將\n     來如果和我交往的話，希望我能有投資理財觀念，我投資\n     6 單位81萬元，海閣林公司2 個業務員帶我到陽信銀行貸\n     款60萬元，核貸後她們將款項提領出來，不足21萬元部分\n     我以現金繳款完成投資。時隔已久忘記本案銷售交易之小\n     姐或到公司簽約時在場之男性職員及業務員為何人，認為\n     本件投資受騙。（出處：警( 三) 卷，P1343-P1345 、原\n     審三卷，P246- P249）\n196、乙ｓ○\n     90年間在婚友社認識一女子，她告訴我她表哥最近有個投\n     資案賺很多錢，問我要不要參加，我當時想說瞭解一下詳\n     情，她帶我到高雄的公司，隨後有位自稱她哥的男子過來\n     說這個投資會很賺錢，說93年即將正式對外營業，我投資\n     1 單位10萬元，並向台新銀行貸款10萬元作為投資的資金\n     。（出處：警( 三) 卷，P1349-P1353 ）\n附表三、證據索引：\n        （甲、物證；乙、書證；丙、人證；丁、被告供述）\n甲、物證：\n 1、印鑑4枚（甲ｕ○）【警(一)卷，P46】\n 2、客戶印鑑卡冊21本、會記憑證3 箱、銀行帳戶存摺21本、印\n    章4 枚、海閣林建築資料1 箱、客戶簽約契約書1348份、電\n    腦主機2 台（會計、經理各1 台）、董事長保險箱1 個、會\n    計報表及薪資1 份、海閣林會議記錄1 冊、海閣林人事資料\n    1 冊、海閣林員工教育手冊1 冊、海閣林介紹公司( 三)(四\n    )5片【扣押物品清單，警( 三) 卷，P1365-P1366 （陳欣怡\n    、乙丙○）】\n 3、人員進出管制表1 冊、客戶電話資料1 袋、員工請假單1 疊\n    、員工名冊相關資料1 疊、筆記本2 本、客戶資料1 袋【扣\n    押物品清單，警( 三) 卷，P1372 （邱育欽）】\n 4、照片8張【警(四)卷，P1773-P1780】\n 5、印鑑4枚【扣押物品清單，偵五卷，P239】\n乙、書證：\n 1、不動產買賣契約書影本1份【警(一)卷，P256-P263】\n 2、鄭文仁合作金庫銀行帳號0000000000000 號活期存款存摺影\n    本1 份【警( 一) 卷，P267-P268 】\n 3、謝志忠郵政存簿儲金簿帳號00000000000000號影本1 份【警\n     (一) 卷，P269-P271 】\n 4、銘泉營造公司台中商業銀行帳號000-00-0000000號活期性存\n    款存摺影本1 份【警(一) 卷，P276-P284 】\n 5、銘泉營造公司發票影本11張【警(一)卷，P286-P290】\n 6、銘泉營造公司營造業登記證書影本1紙【警(一)卷，P291】\n 7、中國信託商業銀行94年6月17日中信銀高字第94003720015號\n    函1紙【警(一)卷，P292】\n 8、不動產買賣契約書影本、土地買賣所有權移轉契約書影本各\n    1份【警(一)卷，P301-P308】\n 9、合夥預定契約書1份（甲亥○）【警(一)卷，P314-P316】\n10、合夥預定契約書1份（ｒ○○）【警(一)卷，P320-P322】\n11、合夥預定契約書1份（甲ｊ○）【警(一)卷，P326-P327】\n12、合夥預定契約書1份（ｔ○○）【警(一)卷，P331-P340】\n13、收據影本2紙（甲Ｖ○）【警(一)卷，P347】\n14、合夥預定契約書1份（Ｏ○○）【警(一)卷，P351-P353】\n15、合夥預定契約書1份（宙○○）【警(一)卷，P357-P358】\n16、合夥預定契約書1份（ｗ○○）【警(一)卷，P362-P367】\n17、收據2紙（乙ｒ○）【警(一)卷，P371】\n18、收據1紙（乙Ｕ○）【警(一)卷，P375】\n19、收據2紙（甲ｐ○）【警(一)卷，P379】\n20、合夥預定契約書1份（黃○○）【警(一)卷，P386-P387】\n21、收據2紙（ｐ○○）【警(一)卷，P391】\n22、合夥預定契約書1份（乙Ｌ○）【警(一)卷，P398-P399】\n23、合夥預定契約書1份（Ｒ○○）【警(一)卷，P403-P404】\n24、合夥預定契約書1份（Ｕ○○）【警(一)卷，P408-P411】\n25、合夥預定契約書1份（ｓ○○）【警(一)卷，P416-P417】\n26、ｓ○○帳戶存款明細影本1紙【警(一)卷，P418】\n27、合夥預定契約書1份（乙ｎ○）【警(一)卷，P422-P424】\n28、定金收據及收據各1紙（甲癸○）【警(一)卷，P429】\n29、收據4紙（甲申○）【警(一)卷，P433-P434】\n30、收據3 紙及合夥預定契約書1 份（甲ｈ○）【警( 一) 卷，\n    P438- P446】\n31、收據3紙（甲黃○）【警(一)卷，P450-P451】\n32、收據1紙（乙ｉ○）【警(一)卷，P455】\n33、合夥預定契約書1份（甲宇○）【警(一)卷，P459-P462】\n34、合夥預定契約書2份（甲辰○）【警(一)卷，P466-P469】\n35、合夥預定契約書2份（地○○）【警(一)卷，P473-P476】\n36、合夥預定契約書1份（ｉ○○）【警(一)卷，P480-P481】\n37、合夥預定契約書1份（亥○○）【警(一)卷，P485-P489】\n38、合夥預定契約書1份（巳○○）【警(一)卷，P493-P495】\n39、李建良存款明細影本及合夥預定契約書影本各1 份【警( 一\n     ) 卷，P499-P506】\n40、定金收據影本4只及收據影本2紙（乙亥○）【警(一)卷，\n    P514-P516 】\n41、收據影本3 紙及合夥預定契約書1 份（甲Ｎ○）警詢【警(\n    一) 卷，P520-P521 、偵十七卷，P5-P9 】\n42、合夥預定契約書1份（甲Ｇ○）【警(一)卷，P525-P526】\n43、收據、定金收據各2紙及合夥預定契約書1份（甲天○）【警\n    (一) 卷，P530-P531、偵十六卷，P38-P42】\n44、彰化銀行92.10.24匯款回條聯及收據各1紙（癸○○）【警\n    (一)卷，P535】\n45、合夥預定契約書1份（乙庚○）【警(一)卷，P543-P545】\n46、合夥預定契約書及收據各1 份（乙甲○）【警( 二) 卷，\n    P550-P55 1】\n47、定金收據及收據各1 紙及合夥預定契約書1 份（甲ｔ○）【\n    警(二)卷，P556、偵十七卷，P14-P15】\n48、合夥預定契約書1份（甲寅○）【警(二)卷，P560-P561】\n49、甲寅○新竹國際商業銀行帳號00000000000 號及國泰世華銀\n    行帳號000-00-000000-0 號存款明細資料影本各1 份【警(\n    二) 卷，P562-P563 】\n50、收據、現金支出傳票各1 紙及合夥預定契約書1 份（乙Ｑ○\n    ）【警( 二) 卷，P568-P569 、偵十七卷，P33-P34 】\n51、合夥預定契約書1份（乙○○）【警(二)卷，P573-P576】\n52、合夥預定契約書4 份及收據2 份（乙Ｋ○）【警( 二) 卷，\n    P581 -P5 97 】\n53、合夥預定契約書1份（乙○○）【警(二)卷，P601-P603】\n54、合夥預定契約書1份及收據2紙（甲Ｕ○）【警(二)卷，\n     P607-P6 10】\n55、合夥預定契約書1份（乙ｖ○）【警(二)卷，P615-P616】\n56、合夥預定契約書1份（甲ｋ○）【警(二)卷，P620-P622】\n57、收據2紙（乙Ｗ○）【警(二)卷，P626】\n58、收據3紙（甲ｇ○）【警(二)卷，P633-P634】\n59、收據1紙（甲ａ○）【警(二)卷，P641】\n60、合夥預定契約書1份（酉○○）【警(二)卷，P645-P652】\n61、合夥預定契約書1份（甲Ｓ○）【警(二)卷，P656-P657】\n62、合夥預定契約書1份（甲乙○）【警(二)卷，P661-P667】\n63、合夥預定契約書1份（ｄ○○）【警(二)卷，P671-P673】\n64、合夥預定契約書1份（乙Ｂ○）【警(二)卷，P677-P679】\n65、收據1紙（乙巳○）【警(二)卷，P684】\n66、合夥預定契約書1份（乙ｕ○）【警(二)卷，P688-P692】\n67、合夥預定契約書1份（乙Ｍ○）【警(二)卷，P699-P700】\n68、合夥預定契約書2份（乙ｂ○）【警(二)卷，P704-P707】\n69、收據3紙（ｃ○○）【警(二)卷，P712-P714】\n70、合夥預定契約書1份（乙Ｅ○）【警(二)卷，P718-P719】\n71、收據1紙（乙ｑ○）【警(二)卷，P723】\n72、合夥預定契約書及收據各1 份（甲ｃ○）【警( 二) 卷，\n    P727- P729】\n73、合夥預定契約書1份（乙寅○）【警(二)卷，P735-P737】\n74、收據4紙（Ｈ○○）【警(二)卷，P742-P744】\n75、合夥預定契約書1份（甲Ｘ○）【警(二)卷，P749-P750】\n76、收據1紙（乙未○）【警(二)卷，P754】\n77、收據2紙（甲Ｃ○）【警(二)卷，P758】\n78、合夥預定契約書1份（甲Ｚ○）【警(二)卷，P762-P764】\n79、合夥預定契約書2份（甲ｒ○）【警(二)卷，P768-P773】\n80、合夥預定契約書1份（甲Ｍ○）【警(二)卷，P777-P779】\n81、收據2紙（ｆ○○）【警(二)卷，P783正反面】\n82、收據2紙（乙ｐ○）【警(二)卷，P788】\n83、收據1紙（甲Ｋ○）【警(二)卷，P793】\n84、合夥預定契約書2份（Ｖ○○）【警(二)卷，P797-P799】\n85、合夥預定契約書1份及收據3紙（甲戊○）【警(二)卷，\n    P803-P807】\n86、收據2紙、定金收據1紙及合夥預定契約書2份（ｖ○○）【\n    警(二)卷，P811-P812、偵十七卷，P39-P43】\n87、合夥預定契約書1份（乙ｅ○）【警(二)卷，P816-P818】\n88、定金收據3 紙及收據4 紙（壬○○）【警( 二) 卷，\n    P822-P825-1 】\n89、收據1 紙及定金收據2 紙（甲Ｄ○）【警( 二) 卷，P830-P\n    831 】\n90、收據2 紙及合夥預定契約書1 份（Ｔ○○）【警( 二) 卷，\n    P835- P838】\n91、合夥預定契約書1份（甲地○）【警(二)卷，P844-P845】\n92、收據1紙（ｏ○○）【警(二)卷，P850】\n93、合夥預定契約書1份（乙ｍ○）【警(二)卷，P854-P856】\n94、收據1紙（甲ｚ○）【警(二)卷，P860】\n95、收據4紙（ｕ○○）【警(二)卷，P864-P865】\n96、合夥預定契約書及收據各1份（乙戊○）【警(二)卷，P870-\n    P872】\n97、合夥預定契約書1份（宇○○）【警(二)卷，P880-P881】\n98、收據3 紙及定金收據1 紙（辛○○）【警( 二) 卷，\n    P885-P886 】\n99、合夥預定契約書1份（甲Ｑ○）【警(二)卷，P894-P895】\n100、股份轉讓同意書1份（乙ｏ○）【警(二)卷，P899】\n101、合夥預定契約書1份（庚○○）【警(二)卷，P908-P910】\n102、收據1紙（乙申○）【警(二)卷，P914】\n103、收據2紙（乙ｃ○）【警(二)卷，P922】\n104、合夥預定契約書1份（乙ｙ○）【警(二)卷，P930-P932】\n105、合夥預定契約書1份（乙ｄ○）【警(二)卷，P936-P937】\n106、合夥預定契約書1份（甲Ｙ○）【警(二)卷，P941-P943】\n107、合夥預定契約書1份（甲丑○）【警(二)卷，P947-P949】\n108、合夥預定契約書1份（乙Ｓ○）【警(二)卷，P954-P955】\n109、收據2紙（ｋ○○）【警(二)卷，P959】\n110、收據1紙及合夥預定契約書2份（Ｂ○○）【警(二)卷，P963、\n    警J卷，P16-P22、P30-P35】\n111、定金收據1紙（乙癸○）【警(二)卷，P967 】\n112、合夥預定契約書2份（甲戌○）【警(二)卷，P976-P979】\n113、收據1紙（Ｄ○○）【警(二)卷，P983】\n114、合夥預定契約書及收據各1份（ｇ○○）【警(二)卷，P9\n     87-P990】\n115、收據3紙（寅○○）【警(二)卷，P994-P995】\n116、收據3紙（乙戌○）【警(二)卷，P999-P1000】\n117、收據1紙及定金收據2紙（余雲傑）【警(二)卷，P1004-P1005\n    】\n118、收據1紙（林豊田）【警(二)卷，P1009】\n119、收據3紙及郵政跨行93.11.29匯款申請書及新竹國際商業銀\n     行93.11.23匯款副通知書各1紙、合夥預定契約書1份（甲\n     丁○）【警(三)卷，P1013-P1015、偵十七卷，P35-P36】\n120、收據2紙及合夥預定契約書1份（子○○）【警(三)卷，P1020-\n     P1028】\n121、收據及定金收據各2紙（乙ｔ○）【警(三)卷，P1033-P1035】\n122、收據1紙（乙丁○）【警(三)卷，P1039】\n123、合夥預定契約書1份（乙Ｔ○）【警(三)卷，P1043-P1044】\n124、收據及定金收據各1紙（甲宙○）【警(三)卷，P1048】\n125、收據6紙（丁○○）【警(三)卷，P1052-P1054】\n126、收據3紙（甲Ｆ○）【警(三)卷，P1058-P1059】\n127、收據1紙（丙○○）【警(三)卷，P1066】\n128、合夥預定契約書1份（甲酉）【警(三)卷，P1070-P1071】\n129、收據2紙（甲庚○）【警(三)卷，P1075】\n130、收據1紙（甲ｅ○）【警(三)卷，P1079】\n131、收據1紙及合夥預定契約書1份（甲Ｗ○）【警(三)卷，P1083-\n     P1085】\n132、合夥預定契約書2份及收據1紙（甲未○）【警(三)卷，P1090-\n     P1071】\n133、收據2紙（甲Ｌ○）【警(三)卷，P1098-P1099】\n134、合夥預定契約書1份（甲丙○）【警(三)卷，P1103-P1104】\n135、收據2紙（ｙ○○）【警(三)卷，P1108】\n136、復華商業銀行貸款資料、中國信託業銀行94.3.15存入憑證\n     及甲Ｅ○第一商業銀行北台南分行帳號000-00-000000號活\n     期儲蓄存款存摺資料各1份【警(三)卷，P1112-P1114】\n137、收據1紙（乙ａ○）【警(三)卷，P1123】\n138、定金收據及收據各1紙（乙Ａ○）【警(三)卷，P1128】\n139、收據2紙（乙ｊ○）【警(三)卷，P1133】\n140、合夥預定契約書1份及台新國際商業銀行93.12.8國內匯款\n     回條、定金收據3紙及收據6張（ｑ○○）【警(三)卷，P1138-\n     P1140、偵十七卷，P27-P32】\n140-1、收據、定金收據及合夥預定契約書各1份（甲午○）【警\n       (三) 卷，P1144】\n141、合夥預定契約書1份（乙ｘ○）【警(三) 卷，P1148-P1149】\n142、收據5紙、合夥預定契約書1份及定金收據6紙（戌○○）【\n     警(三)卷，P1153- P1157、偵二十卷，P191-P202】\n143、收據1紙及合夥預定契約書1份（乙辰○）【警(三)卷，P1164-\n     1、偵六卷，P5-P12】\n144、合夥預定契約書1份（甲甲○）【警(三)卷，P1168-P1170】\n145、合夥預定契約書1份（甲Ｔ○）【警(三)卷，P1174-P1176】\n146、合夥預定契約書3份、收據2紙（Ｋ○○）【警(三)卷，P1181-\n     P1185、警J卷，P38-P39】\n147、合夥預定契約書及收據各1 份（乙乙○）【警( 三) 卷，\n     P1187-P 1187-1】\n148、收據1紙（乙卯○）【警(三)卷，P1191】\n149、合夥預定契約書1份（甲ｏ○）【警(三)卷，P1195-P1197】\n150、收據3紙（甲巳○）【警(三)卷，P1201-P1202】\n151、乙Ｖ○存款明細影本、萬泰商業銀行自動櫃員機交易明細\n     表影本4紙及收據2紙【警(三)卷，P1210-P1213】\n152、合夥預定契約書1份（甲卯○）【警(三)卷，P1219-P1226】\n153、合夥預定契約書1份（甲壬○）【警(三)卷，P1231-P1232】\n154、合夥預定契約書1份（甲ｌ○）【警(三)卷，P1236-P1238】\n155、合夥預定契約書1份（丑○○）【警(三)卷，P1242-P1244】\n156、合夥預定契約書1份及收據2紙（辰○○）【警(三)卷，\n     P1248-P1249、偵十七卷，P49 】\n157、合夥預定契約書1份（甲Ｏ○）【警(三)卷，P1253-P1254】\n158、收據2紙（ｌ○○）【警(三)卷，P1258】\n159、收據1紙（甲Ｈ○）【警(三)卷，P1262】\n160、合夥預定契約書1份（Ａ○○）【警(三)卷，P1266-P1268】\n161、合夥預定契約書1份（蔡祖恩）【警(三)卷，P1272-P1275】\n162、合夥預定契約書1份（乙Ｚ○）【警(三)卷，P1277-P1279】\n163、合夥預定契約書1份（Ｚ○○）【警(三)卷，P1284-P1286】\n164、合夥預定契約書1份（甲ｙ○）【警(三)卷，P1290-P1291】\n165、合夥預定契約書1份（乙Ｏ○）【警(三)卷，P1295-P1296】\n166、合夥預定契約書1份（乙宇○）【警(三)卷，P1301-P1303】\n167、合夥預定契約書2份（甲Ａ○）【警(三)卷，P1307-P1310】\n168、合夥預定契約書1份（乙ｇ○）【警(三)卷，P1314-P1317】\n169、合夥預定契約書1份（甲己○）【警(三)卷，P1321-P1322】\n170、合夥預定契約書1份（甲ｘ○）【警(三)卷，P1330-P1332】\n171、合夥預定契約書1份（Ｅ○○）【警(三)卷，P1336-P1337】\n172、合夥預定契約書1份（甲玄○）【警(三)卷，P1341-P1342】\n173、合夥預定契約書1份（乙ｗ○）【警(三)卷，P1346-P1348】\n174、合夥預定契約書1份（乙ｓ○）【警(三)卷，P1352-P1354】\n175、94.6.8搜索扣押筆錄1份（陳欣怡）【警(三)卷，P1361-P1366\n     】\n176、94.6.8搜索扣押筆錄1份（邱育欽）【警(三)卷，P1368-P1372\n     】\n177、94.6.8搜索筆錄1份（陳淑萍）【警(三)卷，P1374-P1376】\n178、合夥預定契約書1份（乙己○）【警(四)卷，P1490-P1396】\n179、合夥預定契約書1份（甲ｑ○）【警(四)卷，P1500-P1504】\n180、指認照片1張（甲ｑ○-Ｉ○○）【警(四)卷，P1505】\n181、合夥預定契約書1份（天○○）【警(四)卷，P1509-P1515】\n182、合夥預定契約書及收據各1份（涂義隆）【警(四)卷，P1522\n     -P1526】\n183、合夥預定契約書1份（己○○）【警(四)卷，P1530-P1537】\n184、合夥預定契約書1份（呂文傑）【警(四)卷，P1541-P1544】\n185、海閣林休閒渡假酒店股份有限公司增資日前後銀行存款明\n     細表1份【警(四)卷，P1600】\n186、海閣林休閒渡假酒店股份有限公司股東繳納股款明細表1份\n    【警(四)卷，P1601】\n187、海閣林休閒渡假酒店股份有限公司股東名簿【警(四)卷，P160\n     2】\n188、94.1.19海閣林公司董事會議事錄1份【警(四)卷，P1603-P160\n     5】\n189、台東縣政府94年4月21日府城建字第0940030261號函及綠島\n     鄉○○○段1152、1152-1、1152-2、1178、1180、1183等6\n     地號經台東縣政府核發府城建字第000000000號建造執照等\n     相關資料【警(四)卷，P1732-P1734】\n190、海閣林飯店簡介影本1份【警(四)卷，P1735-P1739】\n191、土地登記第二類謄本11張（地號綠島鄉○○○段1152、115\n     2-1、1152-2、1178、1180、1183、1176、1179、1180-1、\n     1183-1、1185）【警(四)卷，P1740-P1750】\n192、台東縣台東地政事務所民政閱覽異動索引資料【警(四)卷，P1\n     751-P1771】\n193、地籍圖影本1份（綠島鄉○○○段1152地號等11筆）【警(四)卷\n     ，P1772】\n194、收據3紙及合夥預定契約書1份（乙天○）【警J卷，P23-P2\n     9、P64-P66】\n195、台東縣政府94年4月6日府地籍字第0943010565號函及海閣\n     林申請建照等相關資料【警J卷，P69-P124】\n196、海閣林休閒渡假酒店股份有限公司設立及歷次變更登記表\n     、歷次股東匯集董事會、最近1次章程等資料【警J卷，P12\n     5-P162】\n197、戊○○君綠島海閣林旅館新建工程申請建築執照流程說明\n     及相關資料【偵五卷，P192-P195】\n198、財團法人金融聯合徵信中心-海閣林休閒渡假酒店股份有限\n     公司資料【偵五卷，P196-P197、P199-P201】\n199、客戶印鑑卡1箱【扣押物品清單，偵五卷，P235】\n200、92.1.1-93.12.31會計憑證1箱【扣押物品清單，偵五卷，\n     P235】\n201、海閣林94.1-94.5.31及翻天公司91.9.1-93.12.31會計憑證\n     1箱【扣押物品清單，偵五卷，P235】\n202、海閣林公司92年度總分類帳1箱【扣押物品清單，偵五卷，\n     P235】\n203、海閣林公司92年度總分類帳1箱【扣押物品清單，偵五卷，\n     P235】\n204、中國信託存摺5本（000000000000）【扣押物品清單，偵五\n     卷，P235】\n205、永昌證券存摺1本（0000000）【扣押物品清單，偵五卷，\n     P235】\n206、金華信銀證券存摺1本（00000000000）【扣押物品清單，\n     偵五卷，P235】\n207、金鼎證券存摺1本（582J0000000）【扣押物品清單，偵五\n     卷，P235】\n208、國泰世華銀行存摺1本（000000000000）【扣押物品清單，\n     偵五卷，P235】\n209、世華聯合銀行存摺1本（000000000000）【扣押物品清單，\n     偵五卷，P235】\n210、世華銀行存摺2本（000000000000、000000000000）【扣押\n     物品清單，偵五卷，P236】\n211、上海商業儲蓄銀行存摺2本（00000000000000）【扣押物品\n     清單，偵五卷，P236】\n212、台新銀行存摺1本（00000000000）【扣押物品清單，偵五\n     卷，P236】\n213、郵局存摺1本（0000000-0000000）【扣押物品清單，偵五\n     卷，P236】\n214、安泰銀行存摺1本（00000000000000）【扣押物品清單，偵\n     五卷，P236】\n215、大眾商業銀行存摺1本（000000000000）【扣押物品清單，\n     偵五卷，P236】\n216、華信銀行存摺1本（00000000000000）【扣押物品清單，偵\n     五卷，P236】\n217、彰化銀行存摺1本（曾俊霖-00000000000000）【扣押物品\n     清單，偵五卷，P236】\n218、聯邦銀行存摺（顏銘震-000000000000）【扣押物品清單，\n     偵五卷，P236】\n219、綠島海閣林施工藍圖2本【扣押物品清單，偵五卷，P237】\n220、綠島海閣林工程合約書1本【扣押物品清單，偵五卷，P237\n     】\n221、綠島海閣林集合住宅建築執5張（000000000）【扣押物品\n     清單，偵五卷，P237】\n222、綠島海閣林地籍圖2本【扣押物品清單，偵五卷，P237】\n223、綠島海閣林水電工程配置圖1本【扣押物品清單，偵五卷，\n     P237】\n224、綠島海閣林鋼構配置圖1本【扣押物品清單，偵五卷，P237\n     】\n225、蔡國勇建築師施工圖3本【扣押物品清單，偵五卷，P237】\n226、綠島海閣林平面配置圖6本【扣押物品清單，偵五卷，P237】\n227、台東縣政府函5張【扣押物品清單，偵五卷，P237】\n228、綠島海閣林工程照片1本【扣押物品清單，偵五卷，P237】\n229、綠島海閣林遊樂業整合性管理系統建議書1本【扣押物品清\n     單，偵五卷，P238】\n230、綠島海閣林餐飲管理系統建議書1本【扣押物品清單，偵五\n     卷，P238】\n231、存證信函1本【扣押物品清單，偵五卷，P238】\n232、投資人合夥契約書1346本【扣押物品清單，偵五卷，P238\n     】\n233、電腦主機1台（經理室，開機密碼00000000）【扣押物品清\n     單，偵五卷，P238】\n234、匯款單9張（乙丙○匯給鄭文仁、陳麗華匯給鄭文仁、乙丙\n     ○匯給謝志忠）【扣押物品清單，偵五卷，P238-P239】\n235、戊○○土地權狀10筆【扣押物品清單，偵五卷，P239、偵\n     十九卷，P76-P85】\n236、綠島土地買賣契約書2份【扣押物品清單，偵五卷，P239】\n237、海閣林公司土地權狀1筆【扣押物品清單，偵五卷，P239】\n238 、海閣林公司建物權狀1 筆【扣押物品清單，偵五卷，P239\n     】\n239、海閣林公司中正四路235號8樓之4、8樓之5使用權狀2張【\n     扣押物品清單，偵五卷，P239】\n240、安泰銀行支票簿（00000000000000）1本【扣押物品清單，\n     偵五卷，P239】\n241、中國信託支票存簿（000000000000）3本【扣押物品清單，\n     偵五卷，P239】\n242、會計報表（海閣林公司資產負債表）【扣押物品清單，偵\n     五卷，P239】\n243、會議記錄、不動產買賣契約書等1本【扣押物品清單，偵五\n     卷，P240】\n244、海閣林公司人事資料1本【扣押物品清單，偵五卷，P240】\n245、海閣林公司員工教育手冊1本【扣押物品清單，偵五卷，\n     P240】\n246、海閣林公司簡介(三)(四)5片【扣押物品清單，偵五卷，P240】\n247、海閣林公司人員進出管制冊1本【扣押物品清單，偵五卷，\n     P241】\n248、海閣林公司業務員筆記本10本【扣押物品清單，偵五卷，\n     P241】\n249、海閣林公司員工請假單1本【扣押物品清單，偵五卷，P241\n     】\n250、海閣林公司員工名冊相關資料1本【扣押物品清單，偵五卷\n     ，P241】\n251、海閣林公司客戶資料1本【扣押物品清單，偵五卷，P241】\n252、合夥預定契約書1份、收據2紙及定金收據各1紙（Ｆ○○）\n    【偵十二卷，P2-P9、P21-P23】\n253、合夥預定契約書1份及收據1紙（乙ｌ○）【偵十七卷，P22\n     -P24】\n254、財團法人金融聯合徵信中心-翻天創新公司相關資料【偵二\n     十卷，P278-P279】\n255、中國信託商業銀行帳號0000-00-00000-0-0存款系統歷史交\n     易查詢報表及對帳單各1份【偵二十卷，P282-P311】\n256、中國信託商業銀行帳號0000-00-00000-0-0存款系統歷史交\n     易查詢報表及對帳單各1份【偵二十卷，P312-P333】\n257、合夥預定契約書及收據各1份（李長隆）【偵二十卷，P4-P\n     8】\n丙、人證：\n 1、陳淑萍（海閣林員工）\n（1）94.6.9警詢【警(一)卷，P87-P93】\n（2）94.9.14偵訊【偵二十卷，P57】\n 2、陳欣怡（不起訴處份-海閣林員工）\n（1）94.6.9警詢【偵四卷，P6】\n（2）94.6.9偵訊\n（2）94.9.14偵訊【偵二十卷，P57】\n 3、黃姵菁（海閣林員工）\n（1）94.6.9警詢【警(一)卷，P107-P111】\n（2）94.9.14偵訊【偵二十卷，P57】\n 4、李文倩（海閣林員工）\n（1）94.6.28警詢【警(一)卷，P117-P120】\n（2）94.9.14偵訊【偵二十卷，P63】\n 5、莊馥蔓（海閣林員工）\n（1）94.6.30警詢【警(一)卷，P132-P133】\n（2）94.12.15偵訊【偵二十卷，P183】\n 6、王紹名（海閣林員工）\n（1）94.6.11警詢【警(一)卷，P202-P205】\n（2）94.9.14偵訊【偵二十卷，P77】\n 7、江妍慧（海閣林員工）\n（1）94.6.11警詢【警(一)卷，P216-P220】\n（2）94.9.14偵訊【偵二十卷，P78】\n 8、許力偉（海閣林員工）\n（1）94.6.10警詢【警(一)卷，P229-P231】\n 9、邱育欽（海閣林員工）\n（1）94.6.9警詢【警(一)卷，P235-P236】\n（2）94.9.15偵訊（有具結）【偵七卷，P33反面】\n 10、方淑美（會計師）\n（1）94.6.29警詢【警(一)卷，P241】\n（2）94.9.15偵訊（方淑美）【偵七卷，P32反面】\n 11、徐淑瑩（海閣林會計）\n（1）94.6.22警詢【警(一)卷，P246-P250】\n 12、鄭文仁（綠島鄉公所秘書）\n（1）94.7.12警詢【警(一)卷，P252-P24】\n（2）97.7.13警詢【警(一)卷，P265-P266】\n 13、賴振東（銘泉營造公司股東）\n（1）97.7.20警詢【警(一)卷，P272-P274】\n 14、金鑫（金東和-海閣林公司顧問）\n（1）94.7.6警詢【警(一)卷，P294-P295】\n 15、婁美莉（戊○○購地之原登記名義人）\n（1）94.7.6警詢【警(一)卷，P298-P299】\n 16、韓春麟（土地出賣人）\n（1）94.7.12警詢【警(一)卷，P309-P310】\n 17、甲亥○（被害人）\n（1）94.6.20警詢【警(一)卷，P311-P313】\n（2）98.3.12審訊（審判）（有具結）【原審三卷，P213-P214】\n 18、ｒ○○（被害人）\n（1）94.6.17警詢【警(一)卷，P317-P319】\n（2）97.10.23審訊（審判）（有具結）【原審二卷，P155-P163】\n 19、甲ｊ○（被害人）\n（1）94.6.24警詢【警(一)卷，P323-P325】\n（2）97.10.23審訊（審判）（有具結）【原審二卷，P163-P170】\n 20、ｔ○○（被害人）\n（1）94.6.9警詢【警(一)卷，P328-P330】\n（2）97.10.23審訊（審判）（有具結）【原審二卷，P170-P180】\n 21、Ｇ○○（原名吳宣昌，被害人）\n（1）94.6.10警詢【警(一)卷，P341-P343】\n（2）97.10.23審訊（審判）（有具結）【原審二卷，P189-P197】\n 22、甲Ｖ○（被害人）\n（1）94.6.14警詢【警(一)卷，P344-P346】\n 23、Ｏ○○（被害人）\n（1）94.6.23警詢【警(一)卷，P348-P350】\n（2）97.10.23審訊（審判）（有具結）【原審二卷，P180-P189】\n 24、宙○○（被害人）\n（1）94.6.28警詢【警(一)卷，P354-P355】\n 25、ｗ○○（被害人）\n（1）94.6.9警詢【警(一)卷，P359-P361】\n（2）97.11.20審訊（審判）（有具結）【原審二卷，P227-P232】\n 26、乙ｒ○（被害人）\n（1）94.6.10警詢【警(一)卷，P368-P370】\n（2）97.11.20審訊（審判）（有具結）【原審二卷，P233-P240】\n 27、乙Ｕ○（被害人）\n（1）94.6.11警詢【警(一)卷，P372-P374】\n（2）97.11.20審訊（審判）（有具結）【原審二卷，P252-P255】\n 28、甲ｐ○（被害人）\n（1）94.6.11警詢【警(一)卷，P376-P378】\n 29、Ｙ○○（被害人）\n（1）94.6.13警詢【警(一)卷，P380-P382】\n（2）97.11.20審訊（審判）（有具結）【原審二卷，P240-P245】\n 30、黃○○（被害人）\n（1）94.6.15警詢【警(一)卷，P383-P385】\n（2）97.11.20審訊（審判）（有具結）【原審二卷，P245-P251】\n 31、ｐ○○（被害人）\n（1）94.6.15警詢【警(一)卷，P388-P390】\n 32、甲ｉ○（被害人）\n（1）94.6.16警詢【警(一)卷，P392-P395】\n 33、乙Ｌ○（被害人）\n（1）94.6.24警詢【警(一)卷，P393-P397】\n（2）97.11.20審訊（審判）（有具結）【原審二卷，P256-P260】\n 34、Ｒ○○（被害人）\n（1）94.6.27警詢【警(一)卷，P400-P402】\n（2）97.11.20審訊（審判）（有具結）【原審二卷，P261-P265】\n 35、Ｕ○○（被害人）\n（1）94.6.17警詢【警(一)卷，P405-P407】\n（2）97.11.20審訊（審判）（有具結）【原審二卷，P266-P270】\n 36、ｓ○○（被害人）\n（1）94.7.1警詢【警(一)卷，P412-P414】\n（2）98.3.12審訊（審判）（有具結）【原審三卷，P213-P214】\n 37、乙ｎ○（被害人）\n（1）94.7.1警詢【警(一)卷，P419-P421】\n 38、甲癸○（被害人）\n（1）94.6.27警詢【警(一)卷，P426-P428】\n 39、甲申○（被害人）\n（1）94.6.19警詢【警(一)卷，P430-P432】\n（2）98.1.22審訊（審判）（有具結）【原審三卷，P75-P87】\n 40、甲ｈ○（被害人）\n（1）94.6.29警詢【警(一)卷，P435-P437】\n（2）98.1.22審訊（審判）（有具結）【原審三卷，P88-P94】\n 41、甲黃○（被害人）\n（1）94.6.10警詢【警(一)卷，P447-P449】\n 42、乙ｉ○（被害人）\n（1）94.6.11警詢【警(一)卷，P452-P454】\n（2）98.1.22審訊（審判）（有具結）【原審三卷，P94-P96】\n 43、甲宇○（被害人）\n（1）94.6.9警詢【警(一)卷，P456-P458】\n 44、甲辰○（被害人）\n（1）94.6.13警詢【警(一)卷，P463-P465】\n 45、地○○（被害人）\n（1）94.6.15警詢【警(一)卷，P470-P472】\n 46、ｉ○○（被害人）\n（1）94.6.19警詢【警(一)卷，P477-P479】\n 47、亥○○（被害人）\n（1）94.6.9警詢【警(一)卷，P482-P484】\n 48、巳○○（被害人）\n（1）94.6.16警詢【警(一)卷，P490-P492】\n 49、Ｗ○○（被害人）\n（1）94.6.21警詢【警(一)卷，P496-P498】\n 50、乙酉○（被害人）\n（1）94.6.11警詢【警(一)卷，P507-P509】\n 51、乙亥○（被害人）\n（1）94.6.11警詢【警(一)卷，P511-P513】\n 52、甲Ｎ○（被害人）\n（1）94.6.11警詢【警(一)卷，P517-P519】\n（2）94.9.2偵訊【偵九卷，P12】\n（3）94.12.26偵訊（有具結）【偵十八卷，P10】\n（4）95.3.14偵訊【偵十八卷，P21】\n（5）95.4.28偵訊【偵十八卷，P30】\n 53、甲Ｇ○（被害人）\n（1）94.6.24警詢【警(一)卷，P522-P524】\n（2）94.12.26偵訊（有具結）【偵十八卷，P10-P11】\n（3）95.4.28偵訊【偵十八卷，P30】\n 54、甲天○（被害人）\n（1）94.6.28警詢【警(一)卷，P527-P529】\n（2）94.9.21偵訊【偵十六卷，P4-P5】\n（3）94.10.6偵訊【偵十六卷，P48-P49】\n（4）94.10.28偵詢【偵十六卷，P57】\n（5）94.12.15偵訊【偵十八卷，P5】\n（6）94.12.26偵訊【偵十八卷，P9、P11】\n（7）95.1.10偵訊【偵二十卷，P271】\n（8）95.1.23偵訊【偵十八卷，P16-P17】\n（9）95.4.28偵訊【偵十八卷，P29-P30】\n 55、癸○○（被害人）\n（1）94.6.13警詢【警(一)卷，P532-P534】\n 56、乙ｌ○（被害人）\n（1）94.5.11警詢【偵十九卷，P27-P28】\n（2）94.6.13警詢【警(一)卷，P537-P539】\n（3）94.9.22偵訊【偵九卷，P12】\n 57、乙庚○（被害人）\n（1）94.6.14警詢【警(一)卷，P540-P542】\n（2）95.1.10偵訊【偵二十卷，P270】\n 58、乙甲○（被害人）\n（1）94.6.29警詢【警(二)卷，P546-P548】\n 59、甲ｔ○（被害人）\n（1）94.6.11警詢【警(二)卷，P553-P555】\n 60、甲寅○（被害人）\n（1）94.6.15警詢【警(二)卷，P557-P559】\n 61、乙Ｑ○（被害人）\n（1）94.6.21警詢【警(二)卷，P564-P567】\n（2）94.9.22偵訊【偵九卷，P12】\n 62、乙○○（被害人）\n（1）94.6.19警詢【警(二)卷，P570-P572】\n（2）98.3.12審訊（審判）（有具結）【原審三卷，P213-P214】\n 63、乙Ｋ○（被害人）\n（1）94.7.15警詢【警(二)卷，P577-P580】\n（2）98.3.12審訊（審判）（有具結）【原審三卷，P213-P215】\n 64、乙Ｎ○（被害人）\n（1）94.6.13警詢【警(二)卷，P598-P600】\n（2）98.3.12審訊（審判）（有具結）【原審三卷，P213-P215】\n 65、甲Ｕ○（被害人）\n（1）94.6.24警詢【警(二)卷，P604-P606】\n 66、乙ｖ○（被害人）\n（1）94.6.16警詢【警(二)卷，P612-P614】\n（2）98.3.12審訊（審判）（有具結）【原審三卷，P216-P217】\n 67、甲ｋ○（被害人）\n（1）94.6.11警詢【警(二)卷，P617-P619】\n 68、乙Ｗ○（被害人）\n（1）94.6.11警詢【警(二)卷，P623-P625】\n 69、甲ｎ○（被害人）\n（1）94.6.13警詢【警(二)卷，P627-P629】\n 70、甲ｇ○（被害人）\n（1）94.6.11警詢【警(二)卷，P630-P632】\n 71、ｅ○○（被害人）\n（1）94.6.13警詢【警(二)卷，P635-P637】\n（2）98.3.12審訊（審判）（有具結）【原審三卷，P216-P217】\n 72、甲ａ○（被害人）\n（1）94.6.27警詢【警(二)卷，P638-P640】\n 73、酉○○（被害人）\n（1）94.6.28警詢【警(二)卷，P642-P644】\n（2）98.3.12審訊（審判）（有具結）【原審三卷，P216-P217】\n 74、甲Ｓ○（被害人）\n（1）94.6.10警詢【警(二)卷，P653-P655】\n（2）98.3.12審訊（審判）（有具結）【原審三卷，P216-P217、\n     P218-P219 】\n 75、甲乙○（被害人）\n（1）94.6.15警詢【警(二)卷，P658-P660】\n（2）98.3.12審訊（審判）（有具結）【原審三卷，P218-P219】\n 76、ｄ○○（被害人）\n（1）94.6.19警詢【警(二)卷，P668-P670】\n（2）98.3.12審訊（審判）（有具結）【原審三卷，P218-P219】\n 77、乙Ｂ○（被害人）\n（1）94.6.21警詢【警(二)卷，P674-P676】\n 78、乙巳○（被害人）\n（1）94.6.13警詢【警(二)卷，P681-P683】\n（2）98.3.12審訊（審判）（有具結）【原審三卷，P218-P219】\n 79、乙ｕ○（被害人）\n（1）94.6.30警詢【警(二)卷，P685-P687】\n（2）98.3.12審訊（審判）（有具結）【原審三卷，P220-P222】\n 80、卯○○（被害人）\n（1）94.6.9警詢【警(二)卷，P693-P695】\n 81、乙Ｍ○（被害人）\n（1）94.6.13警詢【警(二)卷，P696-P698】\n 82、乙ｂ○（被害人）\n（1）94.6.14警詢【警(二)卷，P701-P703】\n 83、ｃ○○（被害人）\n（1）94.6.16警詢【警(二)卷，P708-P710】\n 84、乙Ｅ○（被害人）\n（1）94.6.19警詢【警(二)卷，P715-P717】\n 85、乙ｑ○（被害人）\n（1）94.6.19警詢【警(二)卷，P720-P722】\n 86、甲ｃ○（被害人）\n（1）94.6.20警詢【警(二)卷，P724-P726】\n 87、乙寅○（被害人）\n（1）94.6.23警詢【警(二)卷，P730-P732】\n 88、Ｈ○○（被害人）\n（1）94.6.30警詢【警(二)卷，P738-P740】\n 89、甲Ｘ○（被害人）\n（1）94.7.4警詢【警(二)卷，P745-P747】\n 90、乙未○（被害人）\n（1）94.7.1警詢【警(二)卷，P751-P753】\n（2）98.3.12審訊（審判）（有具結）【原審三卷，P220、P222】\n 91、甲Ｃ○（被害人）\n（1）94.6.23警詢【警(二)卷，P755-P757】\n 92、甲Ｚ○（被害人）\n（1）94.6.19警詢【警(二)卷，P759-P761】\n（2）98.3.12審訊（審判）（有具結）【原審三卷，P220-P222】\n 93、甲ｒ○（被害人）\n（1）94.6.29警詢【警(二)卷，P765-P767】\n（2）98.3.12審訊（審判）（有具結）【原審三卷，P220-P222】\n 94、甲Ｍ○（被害人）\n（1）94.6.14警詢【警(二)卷，P774-P776】\n 95、ｆ○○（被害人）\n（1）94.6.9警詢【警(二)卷，P780-P782】\n 96、乙ｐ○（被害人）\n（1）94.6.24警詢【警(二)卷，P784-P787】\n 97、甲Ｋ○（被害人）\n（1）94.4.18警詢【警J卷，P3-P4】\n（2）94.6.11警詢【警(二)卷，P790-P792】\n 98、Ｖ○○（被害人）\n（1）94.6.27警詢【警(二)卷，P794-P796】\n 99、甲戊○（被害人）\n（1）94.6.22警詢【警(二)卷，P800-P802】\n（2）98.3.12審訊（審判）（有具結）【原審三卷，P223-P224】\n 100、ｖ○○（被害人）\n（1）94.7.1警詢【警(二)卷，P8081-P810】\n（2）94.9.22偵訊【偵九卷，P12】\n（3）98.3.12審訊（審判）（有具結）【原審三卷，P223-P224】\n 101、乙ｅ○（被害人）\n（1）94.6.23警詢【警(二)卷，P813-P815】\n（2）98.3.12審訊（審判）（有具結）【原審三卷，P223-P224】\n 102、壬○○（被害人）\n（1）94.6.23警詢【警(二)卷，P819-P821】\n（2）98.3.12審訊（審判）（有具結）【原審三卷，P225-P226】\n 103、甲Ｄ○（被害人）\n（1）94.6.30警詢【警(二)卷，P826-P828】\n（2）98.3.12審訊（審判）（有具結）【原審三卷，P225-P226】\n 104、Ｔ○○（被害人）\n（1）94.7.1警詢【警(二)卷，P832-P834】\n（2）94.9.22偵訊【偵九卷，，P12】\n（3）98.3.12審訊（審判）（有具結）【原審三卷，P225-P226】\n 105、甲地○（被害人）\n（1）94.6.24警詢【警(二)卷，P840-P842】\n 106、ｏ○○（被害人）\n（1）94.6.11警詢【警(二)卷，P847-P849】\n（2）98.3.12審訊（審判）（有具結）【原審三卷，P225-P226】\n 107、乙ｍ○（被害人）\n（1）94.6.17警詢【警(二)卷，P851-P853】\n（2）98.3.12審訊（審判）（有具結）【原審三卷，P228】\n 108、甲ｚ○（被害人）\n（1）94.6.20警詢【警(二)卷，P857-P859】\n（2）98.3.12審訊（審判）（有具結）【原審三卷，P228-P229】\n 109、ｕ○○（被害人）\n（1）94.6.27警詢【警(二)卷，P861-P863】\n（2）98.3.12審訊（審判）（有具結）【原審三卷，P230-P232】\n 110、乙戊○（被害人）\n（1）94.6.30警詢【警(二)卷，P867-P869】\n（2）98.3.12審訊（審判）（有具結）【原審三卷，P228】\n 111、乙壬○（被害人）\n（1）94.6.13警詢【警(二)卷，P873-P875】\n（2）98.3.12審訊（審判）（有具結）【原審三卷，P233-P234】\n 112、宇○○（被害人）\n（1）94.7.22警詢【警(二)卷，P876-P879】\n 113、辛○○（被害人）\n（1）94.6.11警詢【警(二)卷，P882-P884】\n 114、乙宙○（被害人）\n（1）94.6.24警詢【警(二)卷，P887-P889】\n 115、甲Ｑ○（被害人）\n（1）94.6.24警詢【警(二)卷，P891-P893】\n 116、乙ｏ○（被害人）\n（1）94.7.14警詢【警(二)卷，P896-P898】\n 117、ｚ○○（被害人）\n（1）94.6.11警詢【警(二)卷，P900-P902】\n（2）98.3.12審訊（審判）（有具結）【原審三卷，P228】\n 118、庚○○（被害人）\n（1）94.6.20警詢【警(二)卷，P904-P907】\n 119、乙申○（被害人）\n（1）94.6.11警詢【警(二)卷，P911-P913】\n 120、乙Ｐ○（被害人）\n（1）94.6.22警詢【警(二)卷，P915-P917】\n 121、乙ｃ○（被害人）\n（1）94.6.22警詢【警(二)卷，P919-P921】\n 122、ｎ○○（被害人）\n（1）94.6.10警詢【警(二)卷，P924-P926】\n 123、乙ｙ○（被害人）\n（1）94.6.11警詢【警(二)卷，P927-P929】\n 124、乙ｄ○（被害人）\n（1）94.6.19警詢【警(二)卷，P933-P935】\n 125、甲Ｙ○（被害人）\n（1）94.6.13警詢【警(二)卷，P938-P940】\n 126、甲丑○（被害人）\n（1）94.6.23警詢【警(二)卷，P944-P946】\n 127、乙Ｓ○（被害人）\n（1）94.7.4警詢【警(二)卷，P950-P952】\n 128、ｋ○○（被害人）\n（1）94.6.11警詢【警(二)卷，P956-P958】\n 129、Ｂ○○（被害人）\n（1）94.5.18警詢【警J卷，P67-P68】\n（2）94.6.11警詢【警(二)卷，P960-P962】\n 130、乙癸○（被害人）\n（1）94.6.23警詢【警(二)卷，P964-P966】\n 131、林至孟（被害人）\n（1）94.6.27警詢【警(二)卷，P968-P970】\n 132、甲戌○（被害人）\n（1）94.7.22警詢【警(二)卷，P972-P974】\n 133、Ｄ○○（被害人）\n（1）94.6.10警詢【警(二)卷，P980-P982】\n（2）98.3.12審訊（審判）（有具結）【原審三卷，P230-P231】\n 134、ｇ○○（被害人）\n（1）94.6.23警詢【警(二)卷，P984-P986】\n（2）98.3.12審訊（審判）（有具結）【原審三卷，P230-P231】\n 135、寅○○（被害人）\n（1）94.6.13警詢【警(二)卷，P991-P993】\n（2）98.3.12審訊（審判）（有具結）【原審三卷，P230-P231】\n 136、乙戌○（被害人）\n（1）94.6.11警詢【警(二)卷，P996-P998】\n 137、玄○○（被害人）\n（1）94.6.11警詢【警(二)卷，P1001-P1003】\n 138、林豊田（被害人）\n（1）94.6.11警詢【警(二)卷，P1006-P1008】\n 139、甲丁○（被害人）\n（1）94.6.11警詢【警(三)卷，P1010-P1012】\n 140、子○○（被害人）\n（1）94.6.18警詢【警(三)卷，P1016-P1019】\n 141、乙ｔ○（被害人）\n（1）94.6.19警詢【警(三)卷，P1030-P1032】\n 142、乙丁○（被害人）\n（1）94.6.24警詢【警(三)卷，P1036-P1038】\n 143、乙Ｔ○（被害人）\n（1）94.6.27警詢【警(三)卷，P1040-P1042】\n 144、甲宙○（被害人）\n（1）94.7.1警詢【警(三)卷，P1045-P1047】\n 145、丁○○（被害人）\n（1）94.6.11警詢【警(三)卷，P1049-P1051】\n 146、甲Ｆ○（被害人）\n（1）94.6.28警詢【警(三)卷，P1055-P1058】\n 147、乙丑○（被害人）\n（1）94.6.9警詢【警(三)卷，P1060-P1062】\n 148、丙○○（被害人）\n（1）94.6.11警詢【警(三)卷，P1063-P1065】\n 149、甲酉（被害人）\n（1）94.6.17警詢【警(三)卷，P1067-P1069】\n 150、甲庚○（被害人）\n（1）94.6.19警詢【警(三)卷，P1072-P1074】\n 151、甲ｅ○（被害人）\n（1）94.6.28警詢【警(三)卷，P1076-P1078】\n 152、甲Ｗ○（被害人）\n（1）94.6.28警詢【警(三)卷，P1080-P1082】\n 153、甲未○（被害人）\n（1）94.6.29警詢【警(三)卷，P1087-P1089】\n 154、甲Ｌ○（被害人）\n（1）94.7.1警詢【警(三)卷，P1095-P1097】\n 155、甲丙○（被害人）\n（1）94.6.24警詢【警(三)卷，P1100-P1102】\n 156、ｙ○○（被害人）\n（1）94.6.10警詢【警(三)卷，P1105-P1107】\n 157、甲Ｅ○（被害人）\n（1）94.6.21警詢【警(三)卷，P1109-P1111】\n 158、乙辛○（被害人）\n（1）94.6.9警詢【警(三)卷，P1115-P1117】\n（2）98.3.12審訊（審判）（有具結）【原審三卷，P232-P235】\n 159、乙ａ○（被害人）\n（1）94.6.11警詢【警(三)卷，P1120-P1122】\n 160、乙Ａ○（被害人）\n（1）94.6.11警詢【警(三)卷，P1124-P1126】\n 161、乙ｊ○（被害人）\n（1）94.6.11警詢【警(三)卷，P1130-P1132】\n（2）98.3.12審訊（審判）（有具結）【原審三卷，P232-P234】\n 162、ｑ○○（被害人）\n（1）94.6.16警詢【警(三)卷，P1134-P1136】\n（2）98.3.12審訊（審判）（有具結）【原審三卷，P232-P234】\n 163、甲午○（被害人）\n（1）94.6.19警詢【警(三)卷，P1141-P1143】\n 164、戌○○（被害人）\n（1）94.6.16警詢【警(三)卷，P1150-P1152】\n（2）95.1.10偵訊【偵二十卷，P272-P273】\n（3）98.3.12審訊（審判）（有具結）【原審三卷，P236-P237】\n 165、Ｓ○○（被害人）\n（1）94.6.21警詢【警(三)卷，P1158-P1160】\n 166、乙辰○（被害人）\n（1）94.6.24警詢【警(三)卷，P1162-P1164】\n（2）94.9.15偵訊【偵七卷，P31反面-P32】\n 167、甲甲○（被害人）\n（1）94.6.22警詢【警(三)卷，P1165-P1167】\n 168、甲Ｔ○（被害人）\n（1）94.6.22警詢【警(三)卷，P1171-P1173】\n 169、Ｋ○○（被害人）\n（1）94.5.18警詢【警J卷，P36-P37】\n（2）94.6.28警詢【警(三)卷，P1177-P1179】\n 170、乙乙○（被害人）\n（1）94.6.11警詢【警(三)卷，P1186-P1186-1】\n 171、乙卯○（被害人）\n（1）94.6.11警詢【警(三)卷，P1188-P1190】\n 172、甲ｏ○（被害人）\n（1）94.6.11警詢【警(三)卷，P1192-P1193】\n 173、甲巳○（被害人）\n（1）94.6.23警詢【警(三)卷，P1198-P1200】\n 174、ｂ○○（被害人）\n（1）94.6.10警詢【警(三)卷，P1203-P1205】\n 175、乙Ｖ○（被害人）\n（1）94.7.5警詢【警(三)卷，P1207-P1209】\n 176、甲卯○（被害人）\n（1）94.6.23警詢【警(三)卷，P1214-P1216】\n 177、甲壬○（被害人）\n（1）94.6.16警詢【警(三)卷，P1227-P1229】\n 178、甲ｌ○（被害人）\n（1）94.6.17警詢【警(三)卷，P1233-P1235】\n（2）98.3.12審訊（審判）（有具結）【原審三卷，P236-P238】\n 179、丑○○（被害人）\n（1）94.6.13警詢【警(三)卷，P1239-P1241】\n（2）98.3.12審訊（審判）（有具結）【原審三卷，P236-P237】\n 180、辰○○（被害人）\n（1）94.6.14警詢【警(三)卷，P1245-P1247】\n（2）94.9.22偵訊【偵九卷，P12】\n（3）98.3.12審訊（審判）（有具結）【原審三卷，P239】\n 181、甲Ｏ○（被害人）\n（1）94.6.15警詢【警(三)卷，P1250-P1251】\n（2）98.3.12審訊（審判）（有具結）【原審三卷，P239】\n 182、ｌ○○（被害人）\n（1）94.6.11警詢【警(三)卷，P1255-P1257】\n 183、甲Ｈ○（被害人）\n（1）94.6.11警詢【警(三)卷，P1259-P1261】\n 184、Ａ○○（被害人）\n（1）94.6.23警詢【警(三)卷，P1263-P1265】\n 185、乙Ｈ○（原名蔡祖恩，被害人）\n（1）94.6.10警詢【警(三)卷，P1269-P1271】\n（2）98.3.12審訊（審判）（有具結）【原審三卷，P239】\n 186、乙Ｚ○（被害人）\n（1）94.6.15警詢【警(三)卷，P1276】\n（2）98.3.12審訊（審判）（有具結）【原審三卷，P239-P240】\n 187、Ｚ○○（被害人）\n（1）94.7.21警詢【警(三)卷，P1283】\n 188、甲ｙ○（被害人）\n（1）94.6.11警詢【警(三)卷，P1287-P1289】\n 189、乙Ｏ○（被害人）\n（1）94.6.10警詢【警(三)卷，P1292-P1294】\n 190、乙宇○（被害人）\n（1）94.7.14警詢【警(三)卷，P1297-P1300】\n 191、甲Ａ○（被害人）\n（1）94.6.11警詢【警(三)卷，P1304-P1306】\n 192、乙ｇ○（被害人）\n（1）94.6.10警詢【警(三)卷，P1311-P1313】\n 193、甲己○（被害人）\n（1）94.6.10警詢【警(三)卷，P1318-P1319】\n（2）98.3.12審訊（審判）（有具結）【原審三卷，P241-P244】\n 194、乙玄○（被害人）\n（1）94.6.11警詢【警(三)卷，P1323-P1325】\n（2）98.3.12審訊（審判）（有具結）【原審三卷，P241】\n 195、甲ｘ○（被害人）\n（1）94.6.11警詢【警(三)卷，P1327-P1329】\n 196、Ｅ○○（被害人）\n（1）94.6.15警詢【警(三)卷，P1333-P1334】\n（2）98.3.12審訊（審判）（有具結）【原審三卷，P246-P247、\n     P249】\n 197、甲玄○（被害人）\n（1）94.6.28警詢【警(三)卷，P1338-P1340】\n（2）98.3.12審訊（審判）（有具結）【原審三卷，P247-P249】\n 198、乙ｗ○（被害人）\n（1）94.7.7警詢【警(三)卷，P1343-P1345】\n（2）98.3.12審訊（審判）（有具結）【原審三卷，P248-P249】\n 199、乙ｓ○（被害人）\n（1）94.7.15警詢【警(三)卷，P1350-P1353】\n 200、乙午○（被害人）\n（1）94.8.14警詢【警(三)卷，P1355-P1357】\n 201、乙己○（被害人）\n（1）94.4.13警詢【警(四)卷，P1486-P1489】\n（2）97.11.20審訊（審判）（有具結）【原審二卷，P271-P277】\n 202、甲ｑ○（被害人）\n（1）94.4.15警詢【警(四)卷，P1497-P1499】\n 203、天○○（被害人）\n（1）94.4.15警詢【警(四)卷，P1506-P1508】\n 204、涂義隆（被害人）\n（1）94.4.17警詢【警(四)卷，P1516-P1518】\n 205、己○○（被害人）\n（1）94.4.24警詢【警(四)卷，P1527-P1529】\n 206、Ｑ○○（被害人）\n（1）94.5.20警詢【警(四)卷，P1538-P1540】\n（2）98.3.12審訊（審判）（有具結）【原審三卷，P241-P244】\n 207、乙天○（被害人）\n（1）94.5.18警詢【警J卷，P54-P55】\n 208、蔡國勇（建築師）\n（1）94.9.15偵訊（有具結）【偵七卷，P32反面-P33】\n 209、單文程（見證律師）\n（1）94.6.30偵訊【偵十九卷，P74】\n（2）94.9.15偵訊（有具結）【偵七卷，P33】\n 210、乙Ｊ○（被害人）\n（1）94.9.21偵詢【偵十卷，P3】\n 211、黃雅琪（海閣林員工）\n（2）95.1.23偵訊【偵十四卷，P22】\n 212、魏祥韋（海閣林員工）\n（1）94.9.15偵訊【偵二十卷，P158】\n 213、吳俊德（海閣林員工）\n（1）94.9.15偵訊【偵二十卷，P159】\n 214、蕭佰蓉（海閣林員工）\n（1）94.9.15偵訊【偵二十卷，P160】\n（2）94.12.15偵訊【偵二十卷，P184】\n 215、Ｆ○○（被害人）\n（1）94.12.15偵訊【偵二十卷，P184】\n 216、乙Ｙ○（被害人）\n（1）95.1.10偵訊【偵二十卷，P269】\n（2）98.3.12審訊（審判）（有具結）【原審三卷，P241-P245】\n 217、ｑ○○\n（1）95.1.10偵訊【偵二十卷，P270-P271】\n 218、乙ｘ○（被害人）\n（1）98.3.12審訊（審判）（有具結）【原審三卷，P236-P237】\n丁、被告之供述：\n 1、戊○○\n（1）92.9.15警詢【偵十九卷，P102-P114】\n（2）94.6.21警詢【警(一)卷，P1-P9】\n（3）94.6.21警詢【警(一)卷，P11-P13】\n（4）94.6.21偵訊【偵五卷，P16】\n（5）94.6.29偵訊【偵五卷，P187-P189】\n（6）94.8.18偵訊【偵五卷，P231】\n（7）94.9.15偵訊【偵七卷，P32-P34】\n（8）94.9.22偵訊【偵九卷，P11-P12】\n（9）95.5.3偵訊【偵十三卷，P17-P18】\n（10）94.12.15偵訊【偵二十卷，P184】\n（11）95.1.10偵訊【偵二十卷，P269-P273】\n（12）94.6.29審訊（聲壓）【聲一卷，P4-P9】\n（13）94.8.23審訊（延押）【聲一卷，P11-P13】\n（14）94.7.11審訊（抗告）【抗一卷，P18-P21】\n（15）96.12.28審訊（準備）【原審一卷，P280】\n（16）97.4.16審訊（準備）【原審一卷，P321】\n（17）97.11.20審訊（審判）【原審二卷，P277-P278】\n 2、甲ｕ○\n（1）94.6.9警詢【警(一)卷，P35-P41】\n（2）94.7.15警詢【警(一)卷，P43-P44】\n（3）94.6.9偵訊【偵四卷，P4-P5】\n（4）97.4.16審訊（準備）【原審一卷，P321-P322】\n 3、甲ｄ○\n（1）94.6.9警詢【警(一)卷，P48-P52】\n（2）94.6.9偵訊【偵四卷，P6-P7】\n（3）97.4.16審訊（準備）【原審一卷，P322】\n 4、乙ｆ○（原名顏銘震）\n（1）94.6.9警詢 【警(一)卷，P57-P60】\n（2）94.6.9偵訊 【偵四卷，P2-P3】\n（3）97.4.16審訊（準備）【原審一卷，P322】\n 5、甲辛○\n（1）94.6.10警詢【警(一)卷，P63-P67】\n（2）94.9.14偵訊【偵二十卷，P55-P56】\n（3）97.4.16審訊（準備）【原審一卷，P322】\n 6、乙ｈ○\n（1）94.6.9警詢【警(一)卷，P77-P83】\n（2）94.9.14偵訊【偵二十卷，P56-P57】\n（3）97.4.16審訊（準備）【原審一卷，P322】\n 7、申○○\n（1）94.6.8警詢【警(一)卷，P69-P72】\n（2）94.9.14偵訊【偵二十卷，P56】\n（3）97.4.16審訊（準備）【原審一卷，P322】\n 8、乙丙○\n（1）94.6.9警詢【警(一)卷，P19-P28】\n（2）94.7.27警詢【警(一)卷，P29-P31】\n（3）94.6.9偵訊【偵四卷，P3-P4】\n（4）94.9.15偵訊【偵七卷，P33反面-P34】\n（5）97.4.16審訊（準備）【原審一卷，P322】\n 9、乙Ｆ○\n（1）94.6.30警詢【警(一)卷，P112-P114】\n（2）94.9.14偵訊【偵二十卷，P62-P63】\n（3）97.4.16審訊（準備）【原審一卷，P322】\n 10、乙地○\n（1）94.10.19偵訊【偵四卷，P21】\n（2）94.10.19偵訊【偵二十卷，P165-P166】\n（3）97.4.16審訊（準備）【原審一卷，P322】\n 11、Ｐ○○（原名吳俊德）\n（1）97.4.16審訊（準備）【原審一卷，P322】\n 12、乙Ｒ○\n（1）94.6.27警詢【警(一)卷，P183-P185】\n（2）94.9.14偵訊【偵二十卷，P72】\n（3）97.4.16審訊（準備）【原審一卷，P322】\n 13、甲Ｂ○\n（1）94.9.15偵訊【偵二十卷，P157】\n 14、甲ｗ○\n（1）94.6.8警詢【警(一)卷，P195-P199】\n（2）94.12.15偵訊【偵二十卷，P183-P184】\n（3）97.8.27審訊（準備）【原審二卷，P115】\n 15、午○○（原名史雅茜）\n（1）94.9.15偵訊【偵二十卷，P156】\n（2）95.7.16審訊（準備）【原審二卷，P74】\n（3）97.11.20審訊（審判）【原審二卷，P276-P277】\n 16、甲ｓ○\n（1）94.9.15偵訊【偵二十卷，P94-P95】\n 17、乙Ｉ○（原名蔡宜庭）\n（1）94.9.15偵訊【偵二十卷，P158】\n（2）94.12.15偵訊【偵二十卷，P184】\n（3）95.7.16審訊（準備）【原審二卷，P63】\n 18、Ｌ○○\n（1）94.9.15偵訊【偵二十卷，P93】\n（2）94.10.28偵詢【偵十六卷，P56-P57】\n（3）94.12.15偵訊【偵十八卷，P5-P6】\n（4）95.1.10偵訊【偵二十卷，P272】\n（5）95.1.23偵訊【偵十八卷，P16-P17】\n（6）95.3.14偵訊【偵十八卷，P22】\n（7）95.4.28偵訊【偵十八卷，P29-P30】\n（8）95.7.16審訊（準備）【原審二卷，P62】\n 19、乙ｋ○\n（1）94.9.15偵訊【偵二十卷，P94】\n（2）95.7.16審訊（準備）【原審二卷，P62-P63】\n 20、甲Ｉ○\n（1）94.9.15偵訊【偵二十卷，P157-P158】\n（2）97.8.27審訊（準備）【原審二卷，P118】\n 21、甲Ｊ○\n（1）94.9.15偵訊【偵二十卷，P87-P88】\n（2）95.7.16審訊（準備）【原審二卷，P63】\n 22、林詩怡\n（1）94.9.15偵訊【偵二十卷，P93-P94】\n（2）95.7.16審訊（準備）【原審二卷，P74】\n 23、乙Ｘ○\n（1）94.9.15偵訊【偵二十卷，P96】\n（2）95.7.16審訊（準備）【原審二卷，P63】\n 24、Ｊ○○\n（1）94.9.15偵訊【偵二十卷，P159】\n（2）95.7.16審訊（準備）【原審二卷，P63】\n 25、乙子○（原名黃彩惠）\n（1）94.9.15偵訊【偵二十卷，P95】\n（2）95.7.16審訊（準備）【原審二卷，P63】\n 26、甲ｖ○（原名馮志群）\n（1）94.9.15偵訊【偵二十卷，P88】\n（2）95.7.16審訊（準備）【原審二卷，P74】\n 27、未○○（原名史恆華）\n（1）94.6.28警詢【警(一)卷，P125-P128】\n（2）94.9.14偵訊【偵二十卷，P63-P64】\n（3）95.7.16審訊（準備）【原審二卷，P74】\n 28、甲子○\n（1）94.6.27警詢【警(一)卷，P176-P178】\n（2）94.9.14偵訊【偵二十卷，P71-P72】\n（3）95.7.16審訊（準備）【原審二卷，P75】\n 29、Ｉ○○\n（1）94.6.27警詢【警(一)卷，P158-P160】\n（2）94.9.14偵訊【偵二十卷，P70-P71】\n（3）95.7.16審訊（準備）【原審二卷，P75】\n 30、Ｃ○○\n（1）94.9.15偵訊【偵二十卷，P86】\n（2）95.7.16審訊（準備）【原審二卷，P75】\n 31、ｈ○○\n（1）94.6.8警詢【警(一)卷，P208-P213】\n（2）94.9.14偵訊【偵二十卷，P77-P78】\n（3）95.7.16審訊（準備）【原審二卷，P75】\n 32、乙Ｇ○\n（1）94.6.24警詢【警(一)卷，P223-P225】\n（2）94.9.14偵訊【偵二十卷，P78-P79】\n（3）95.7.16審訊（準備）【原審二卷，P75】\n 33、乙Ｄ○○\n（1）94.6.27警詢【警(一)卷，P163-P166】\n（2）94.10.19偵訊【偵四卷，P21反面】\n（3）94.10.19偵訊【偵二十卷，P166】\n（4）97.8.27審訊（準備）【原審二卷，P118】\n 34、甲ｆ○\n（1）94.9.15偵訊【偵二十卷，P160】\n（2）95.7.16審訊（準備）【原審二卷，P75】\n 35、乙Ｃ○\n（1）94.6.29警詢【警(一)卷，P189-P191】\n（2）94.9.14偵訊【偵二十卷，P72-P73】\n（3）95.7.16審訊（準備）【原審二卷，P75】\n 36、甲ｂ○\n（1）94.6.29警詢【警(一)卷，P148-P150】\n（2）94.9.14偵訊【偵二十卷，P65】\n（3）95.7.16審訊（準備）【原審二卷，P76】\n 37、甲Ｒ○\n（1）95.5.3偵訊【偵十三卷，P17-P18】\n（2）95.1.23偵訊【偵十四卷，P22】\n（3）95.7.16審訊（準備）【原審二卷，P76】\n 38、乙黃○\n（1）94.6.30警詢【警(一)卷，P137-P138】\n（2）94.9.15偵訊【偵七卷，P32】\n（3）94.9.14偵訊【偵二十卷，P64】\n（4）95.7.16審訊（準備）【原審二卷，P76】\n 39、甲ｍ○\n（1）94.7.1警詢【警(一)卷，P142-P143】\n（2）94.9.14偵訊【偵二十卷，P64-P65】\n（3）95.7.16審訊（準備）【原審二卷，P76】\n 40、甲Ｐ○\n（1）94.7.8警詢【警(一)卷，P170-P171】\n（2）94.9.14偵訊【偵二十卷，P71】\n（3）96.8.7審訊（準備）【原審一卷，P251反面】\n 41、Ｎ○○\n（1）94.9.15偵訊【偵二十卷，P86-P87】\n（2）97.8.27審訊（準備）【原審二卷，P115】\n 42、Ｘ○○\n（1）94.9.15偵訊【偵二十卷，P87】\n（2）96.8.7審訊（準備）【原審一卷，P251反面】\n 43、ａ○○（原名李裙鳳）\n（1）94.9.15偵訊【偵二十卷，P160】\n（2）96.8.7審訊（準備）【原審一卷，P252】\n 44、Ｍ○○\n（1）94.9.15偵訊【偵二十卷，P156-P157】\n（2）95.1.10偵訊【偵二十卷，P156-P157】\n（3）96.8.7審訊（準備）【原審一卷，P251反面-P252】",
  "structure": {
    "main": "上訴駁回。",
    "reason": "一、公訴意旨略以：\n(一)、被告戊○○係海閣林休閒渡假酒店股份有限公司（下稱海閣\n    林公司）之董事長，該公司前身為翻天創新國際股份有限公\n    司（下稱翻天創新公司），被告甲ｕ○係戊○○之秘書、顏\n    廉埕（原名顏銘震）、甲ｄ○係該公司之總經理、甲辛○、\n    乙ｈ○、乙地○係該公司之協理、申○○、乙Ｆ○係該公司\n    之經理、乙丙○係該公司之董事長特助（負責財務）、Ｐ○\n    ○（原名吳俊德）、甲Ｂ○係該公司之業務主任、乙Ｒ○係\n    該公司之襄理、甲ｗ○、午○○（原名史雅茜）、甲ｓ○、\n    蔡幸（原名蔡宜庭）、Ｌ○○、乙ｋ○、甲Ｉ○、甲Ｊ○\n    、林宥吟（原名林詩怡）、乙Ｘ○、Ｊ○○、乙子○（原名\n    黃彩惠）、甲ｖ○（原名馮志群）、未○○（原名史恆華）\n    、甲子○、Ｉ○○、Ｃ○○、ｈ○○、乙Ｇ○、乙Ｄ○○、\n    甲ｆ○、乙Ｃ○、甲ｂ○、甲Ｒ○、乙黃○、甲ｍ○、甲Ｐ\n    ○、Ｎ○○、Ｘ○○、ａ○○（原名李裙鳳）、Ｍ○○，均\n    係該公司之各級業務員（對外名稱為「專員」或「主任」，\n    下稱戊○○等44人）。\n(二)、被告戊○○等44人以海閣林公司名義，先動用少數資金在臺\n    東縣綠島鄉（下稱「綠島」）購得依法不得建造旅館之土地\n    ，共計建地3 筆、農地（應係「旱地」，詳後述）8 筆，再\n    以集合住宅的名義申請建造執照，隨即以在綠島投資興建五\n    星級休閒渡假大飯店為幌子，而渠等均明知海閣林公司僅取\n    得集合住宅建造執照，自始至終無法取得臺東縣政府所核發\n    之合法旅館使用執照，竟仍共同基於意圖為自己不法所有之\n    常業詐欺犯意聯絡，由戊○○總管公司業務，甲ｕ○擔任秘\n    書幫忙管理，乙丙○負責財務，顏銘震、甲ｄ○、甲辛○、\n    乙ｈ○、乙地○、申○○、乙Ｆ○負責公司內部各級幹部之\n    訓練、考核與管理，並安排業務員至婚友社或上網交友，吳\n    俊德、甲Ｂ○、乙Ｒ○負責對客戶說明，自民國91年4 月間\n    起，由各級業務員至婚友社或上網交友，以想要和對方交往\n    為藉口，隱瞞沒有合法旅館建築執照之事實，不斷遊說，而\n    向不知情之投資人誘騙投資海閣林休閒渡假酒店，每一投資\n    單位為新臺幣（下同）13萬5 千元，業務員（沒有底薪）每\n    賣出1 單位可抽取獎金（專員為9 千至1 萬元不等，主任為\n    1 萬3 千元），另總經理、協理、經理，依階級可分別抽取\n    3 千元至2 萬3 千元不等之獎金，所收入之款項均未經過合\n    格之會計師依實際收支情形確實作帳，除扣掉管銷以及上開\n    業務獎金之外，均流入戊○○私人帳戶內，且海閣林公司位\n    於高雄市新興區○○○路251 號12樓之1 的辦公處所等大批\n    房地產均登記在戊○○私人名下。嗣因該所謂五星級休閒渡\n    假大飯店之營業一直遙遙無期，且待投資被害人繳完款項後\n    ，業務員隨即失聯，投資之被害人始知受騙，截至94年6 月\n    8 日經檢察官指揮警方查獲為止，共有被害人1,336 人投資\n    3,654 個單位，詐得金額總計4 億9329萬元，已查出被害人\n    有ｒ○○等196 人（被害人姓名、投資單位數、被詐騙金額\n    ，詳如附表一、二所示）。\n(三)、嗣於94年6 月8 日經檢察官指揮內政部警政署刑事警察局偵\n    八隊二組與高雄縣政府警察局刑事警察大隊，至海閣林休閒\n    渡假酒店股份有限公司位於高雄市新興區○○○路251 號12\n    樓之1 、高雄市前金區○○○路235 號8 樓之4 等處所實施\n    搜索，扣得附表三「證據索引」甲、乙所示之物證及書證，\n    因認被告戊○○等人共同涉犯修正前刑法第340 條之常業詐\n    欺罪嫌。\n二、按犯罪事實，應依證據認定之，無證據不得認定犯罪事實；\n    又不能證明被告犯罪者，應諭知無罪之判決；刑事訴訟法第\n    154 條第2 項、第301 條第1 項各有明文。次按認定不利於\n    被告之證據須依積極證據，苟積極證據不足為不利於被告事\n    實之認定，即應為有利被告之認定，更不必有何有利之證據\n    ；又犯罪事實之認定，應憑證據，如無相當之證據，或證據\n    不足以證明，自不得以推測或擬制之方法，以為裁判之基礎\n    （最高法院30年上字第816 號、40年台上字第86號判例意旨\n    可參）；另按刑事訴訟法第161 條規定：檢察官就被告犯罪\n    事實，應負舉證責任，並指出證明之方法。因此，檢察官對\n    於起訴之犯罪事實，應負提出證據及說服之實質舉證責任。\n    倘其所提出之證據，不足為被告有罪之積極證明，或其闡明\n    之證明方法，無從說服法官以形成被告有罪之心證，基於無\n    罪推定之原則，自應為被告無罪判決之諭知（最高法院92年\n    台上字第128 號判例要旨足佐）。另按刑法第339 條第1 項\n    詐欺罪之成立，須行為人於主觀上有為自己或第三人不法所\n    有之意圖，客觀上有施用詐術，使對方陷於錯誤致為財產上\n    之處分行為，始足當之；若其所用方法，不能認為詐術，亦\n    不致使人陷於錯誤，即不構成該罪（最高法院46年台上字第\n    260 號判例參照）。至於民事關係當事人間，債務人於債之\n    關係成立後，如有未依債之本旨履行民事債務之情形，在一\n    般社會生活經驗上可能之原因甚多，而刑事被告依法不負自\n    證無罪之義務，若別無足以證明被告自始意圖不法所有之積\n    極證據，亦僅能認係民事債權債務糾紛，不得僅憑被告事後\n    不履行債務之客觀事態，而推定被告自始具有不法所有之詐\n    欺意圖。\n三、證據能力：\n(一)、後述證人等各警詢陳述，其性質雖屬傳聞證據，惟檢察官、\n    被告、辯護人已於本院審理調查上開筆錄予以提示並告以要\n    旨時，由檢察官、被告、辯護人表示意見，當事人或辯護人\n    已知上述筆錄乃傳聞證據，而就此證據能力均表示無意見，\n    即同意作為證據，且本院審酌上開筆錄作成時，較無人情施\n    壓或干擾，亦無不當取供之情形，認為以之作為本案之證據\n    亦屬適當，依刑事訴訟法第159 條之5 第1 項規定，自得為\n    證據。\n(二)、後述證人等各於偵查中經具結之陳述，並未曾提及檢察官在\n    偵查時有不法取供之情形，且亦無證據足以證明證人上開陳\n    述有顯不可信之情況，被告或其辯護人於本院復未再聲請詰\n    問何證人，而部分證人各於原審復已到庭接受詰問，足可認\n    定業已保障被告詰問權，依刑事訴訟法第159 條之1 第2 項\n    規定，自得為證據。\n(三)、後述引用之其他卷附書證，而屬於書面之傳聞證據部分，因\n    檢察官、被告、辯護人於本院審理調查上開書證予以提示並\n    告以要旨時，由檢察官、被告、辯護人表示意見，當事人、\n    辯護人已知此等書證乃傳聞證據，而就此證據能力均表示無\n    意見，亦未聲明異議，即視為同意作為證據，且本院審酌該\n    書證作成時之客觀情狀，並無證據證明此等書證有何遭變造\n    或偽造情事，認為以之作為本件論証之證據，均與待證事實\n    具有關聯性，作為本案之證據亦屬適當，依刑事訴訟法第15\n    9 條之5 第1 項規定，均認得為證據。\n四、公訴意旨認被告戊○○等44人共同涉犯常業詐欺罪嫌，係以\n    如附表三「證據索引」所示之「物證」、「書證」、「人證\n    」及「被告之供述」等情為據，然被告戊○○等44人於原審\n    均否認上開被訴犯行，辯詞各略如下：\n1 、戊○○：\n    我是海閣林休閒渡假酒店負責人，目前海閣林公司已經結案\n    ，現在公司改為風緻開發，負責人為顏銘震。內勤人員底薪\n    1 萬8 千元，全勤再加2 千元，每月內勤薪水約45萬元，業\n    務專員招攬投資獎金每筆1 萬元，主任每筆獎金1 萬3 千元\n    ，襄理每筆獎金1 萬5 千元，副理每筆獎金1 萬8 千元，經\n    理每筆獎金2 萬元，協理每筆獎金2 萬5 千元，副理每筆獎\n    金3 萬5 千元，董事長每筆獎金5 萬元。我沒有底薪，獎金\n    5 萬元還要扣掉間差，實際合夥人每投資1 單位13萬5 千元\n    ，只有8 萬5 千元存入公司帳戶。公司以海閣林休閒渡假酒\n    店在綠島興建五星級休閒渡假酒店對外招商，總共是6 千個\n    單位，實際招商約3 千6 百個單位左右，每單位13萬5 千元\n    ，募得投資金額大概4 億8 千多萬。一開始有申請旅館建照\n    ，因旅館未緊鄰八米道路等因素，被台東縣政府核退多次，\n    最後因時間緊迫，公司為把飯店蓋好，不得已先申請集合住\n    宅之建照，並動工興建目的是為了給合夥人一個交代，公司\n    有把握能變更成旅館用途並取得合法之使用執照。業務員招\n    攬投資的錢以現金交給公司會計或匯入公司帳戶，所募得4\n    億8 千多萬之款項用於黃復杰侵占公司7200萬元；被勒贖65\n    0 萬元；工程與投資約2 億元；購買公司資產約2 千萬元；\n    業務獎金已發放1 億8 千萬元；內勤職員薪資約1 千5 百萬\n    元；水電、租金開銷約3 千5 百萬元；購買綠島之土地約36\n    50萬元，總計約4 億8 千萬元。海閣林有陳列以一棟地上5\n    層地下1 層的樣品屋。我們計畫在綠島開設旅館，因資金不\n    足，所以對外募集資金我們有宣導，也跟業務員講一定要讓\n    客戶知道公司建築飯店的執照還沒發放下來，也很努力聲請\n    換發旅館執照。婚友中心只是客源其中之一的管道，也有從\n    親友、網路上找來，公司業務員大部分是未婚女生，所以從\n    婚友中心的客戶比例較高，只要客戶有錢、有意願我們會解\n    釋的很清楚。當時買農地沒辦法登記在公司名下，因公司要\n    有農業相關業務才能登記，所以我想先登記我名下，待房地\n    蓋好後再移轉登記公司名下。和被害人和解人數大概33人，\n    和解金額以投資款3 成為基準。公司財務乙丙○負責，顏銘\n    震是台中地區代理商，甲ｄ○是公司高階主管。現在進度與\n    3 年前一樣，旅館的使用執照已經核發，內部還沒開始裝潢\n    ，只做天花板、防火設備、門窗等，迄今仍無法營運還是因\n    資金不足，陸續與人和解，且綠島天氣不好，颱風後很多設\n    備要維修，沒有多餘的錢繼續蓋飯店。若不發放業務獎金，\n    對於業務的推展勢必無法推展，當初就是不足所以一定要先\n    發放獎金，才會再有資金進來，工程才能繼續進行等語（出\n    處：警卷(一)，P1-P9 、P11-P13 、偵五卷，P16 、P187-P18\n    9 、P231、偵七卷，P32-P34 、偵九卷，P11 -P12、偵十三\n    卷，P17-P18 、偵十九卷，P102-P114 、偵二十卷，P184、\n    P269-P2 73聲一卷，P4-P9 、P11-P1 3、抗一卷，P18-P21\n    、原審一卷，P280、P321、原審二卷，P277-P278 、原審四\n    卷，P193-P195 、P208反面）。\n2 、童微庭：\n    海閣林休閒渡假酒店股份有限公司負責人是戊○○，我們是\n    男女朋友，92年初進入海閣林公司擔任業務助理，當時已推\n    出綠島的業務，現擔任公司秘書，負責接待訪客、訂飲料或\n    便當及幫董事長處理一些雜務。公司有向政府登記營業執照\n    ，資本額應該是600 萬元，不清楚公司帳戶內之資金與戊○\n    ○私人帳戶內金錢之流通情形，我作秘書只有年終獎金，沒\n    辦法分紅利，業務員分多少紅利我也不清楚。知道公司在綠\n    島有蓋休閒渡假酒店，92年3 、4 月間公司開始以開發綠島\n    休閒渡假酒店為名對外募資，共募得2400個單位，每單位13\n    萬5 千元，約3 億2 千4 百萬元資金，資金應是存入公司帳\n    戶，由財務部徐淑瑩專責管理。公司在綠島購得土地約8筆\n    或11筆，海閣林休閒渡假酒店股份有限公司以戊○○的集合\n    住宅名義申請建照，但它是以休閒飯店的模式下去設計的。\n    業務員的銷售手法我不清楚。在公司我沒參與資金往來，也\n    沒遊說客戶投資。據我所知海閣林財務由董事長和會計人員\n    全權處理，財務是乙丙○等語（出處：警卷(一)，P35-P41 、\n    P43-P44 、偵四卷，P4-P5 、原審一卷，P321-P322 、原審\n    四卷，P195反面-P196 ）。\n3 、甲ｄ○：\n    海閣林休閒渡假酒店股份有限公司負責人是戊○○，我於92\n    年9 月至93年12月擔任高雄總公司副總經理，執掌人事考核\n    、協助新進人員應徵及參加公司會議，我管業務，負責一些\n    業務及與客戶間溝通事宜。92年1 月初進入公司時已推綠島\n    酒店。公司獎金制度我去推銷的1 筆（1 股）13萬5 千元，\n    我抽7 千元的獎金，我的組員推銷成交的我抽5 千元獎金，\n    襄理、協理抽的獎金我不知道，專員即最基層的員工1 筆抽\n    1 萬，但我所收入的獎金也提供公司24％之管銷費用，員工\n    沒有薪水，都靠業務招募合夥人的獎金；我是公司股東，也\n    有買1 筆公司的股份，我沒有薪水，沒有分紅，都靠業務招\n    募合夥人的獎金。海閣林休閒渡假酒店是在綠島蓋飯店以旅\n    館名義申請建照，公司92年間就開始對外募資，我們都把募\n    得資金交給財務部的會計徐淑瑩，資金何人管理我不清處。\n    戊○○告訴我們工程已經要完成了，一定會通過建照，我們\n    深信會通過，當時沒通過建照申請，所以對外招募以五星級\n    觀光大飯店名義招募。我們以要在綠島蓋一間五星級觀光酒\n    店名義，告知合夥人飯店前景看好，有很好的投資前景去對\n    外招募，公司沒幫合夥人辦貸款。我任職期間約完成10筆，\n    含我自己1 筆，我進公司時是1 筆13萬元，共招募2 人，一\n    為甲戌○買5 筆，另一為男性網友買4 筆，共領取7 萬元業\n    務獎金，進公司期間92年約領5 、60萬元獎金，93年約領3\n    、40萬元獎金。1 個單位13萬5 千元先全部繳回公司，我跟\n    下面業務員依階級一起分3 萬5 千元。在海閣林公司應該有\n    領到2 、3 百萬元業務獎金金額。大家都是20幾歲到海閣林\n    公司上班，入公司時公司有給我們很好的藍圖及前景，我自\n    己也有投資，公司給我們的訊息是工程有進行，我所知也是\n    正在興建中的飯店，若我知道是詐欺我有不可能會投資，我\n    認為公司給我們的是指日可待的藍圖等語（出處：警卷(一)，\n    P48-P52 、偵四卷，P6-P7 、原審一卷，P322、原審四卷，\n    P196反面、P208反面）。\n4 、乙ｆ○（原名顏銘震）：\n    我當初在海閣林公司是任職副總經理職務，負責台中辦事處\n    的業務，台中辦事處已在94年4 月結束。公司集資進來的錢\n    先進戊○○的帳戶，再匯進公司的帳戶。公司基層專員都是\n    領業績獎金，每招攬1 單位13萬5 千元的投資，可領1萬 元\n    的業績獎金，主任可抽3 千元，襄理抽2 千元，經理抽3 千\n    元，協理抽5 千元，副總抽1 萬2 千元，我和戊○○固定每\n    單位領1 萬2 千元，每筆13萬5 千元實際上進入公司的帳戶\n    內只有8 萬5 千元。業務員都透過網路交友和婚友社方式對\n    外尋找投資目標。高雄總公司及台中辦公室的租金、水電由\n    公司負責，業務部的管銷由戊○○負責，但台中辦事處人員\n    的薪水由我支付。海閣林在綠島購得之土地共11筆，金額共\n    約3 、4 千萬元以上。海閣林休閒渡假酒店是以戊○○名義\n    申請集合式住宅建照，一開始真的要申請旅館建照，但申請\n    不過，後來也是因工程款的問題才繼續對外以投資建造五星\n    級渡假酒店名義繼續招募投資。海閣林公司總共集資4 億多\n    元，我沒出資投資綠島開發案，綠島興建酒店大約共花超過\n    2 億元，投資客每年可分紅，92年底迄今我分得5 百至8 百\n    萬元。我在台中擔任朕聖企業公司的總經理，是間代銷公司\n    ，我們公司代銷海閣林公司綠島投資案，在台中、高雄運作\n    ，甲辛○、潘春枚、乙地○、Ｐ○○、乙Ｒ○、甲Ｂ○、黃\n    世杰、劉家沛、乙Ｉ○、Ｌ○○、甲Ｉ○、甲Ｊ○、ｍ○○\n    、黃彩惠、甲ｖ○、Ｃ○○、乙Ｄ○○、甲ｆ○、乙Ｃ○、\n    甲ｍ○、甲Ｐ○、Ｎ○○、Ｘ○○、Ｍ○○都是朕聖公司員\n    工。我與戊○○是好友，當時我知道他買了土地，飯店也在\n    興建中，才與公司員工一起代銷，朕聖企業沒有詐欺的意思\n    等語（出處：警卷(一)，P57-P60、偵四卷，P2-P3、原審一卷\n    ，P322、原審四卷，P196、P208反面-P209）。\n5 、甲辛○：\n    92年中戊○○叫我到海閣林休閒渡假酒店擔任業務主管，我\n    擔任經理，後擔任協理，工作內容為業務人員之管理和業務\n    推廣，沒底薪只有獎金，我大約招募300 多個單位。我手下\n    的業務每招攬投資1 單位，我可領2 萬3 千元，但要再扣掉\n    給業務及其他主管的錢，所以我實領5 千元（偵訊時改稱8\n    千元），任職期間領1 、2 百萬元。公司以要在綠島建照五\n    星級休閒渡假酒店名義對外招攬投資，投資1 筆13萬5 千元\n    ，對外招商3600單位。公司會安排女業務到婚友社拓展人脈\n    ，至於女業務在婚友社認識朋友後如何向他們介紹投資，我\n    不清楚。女業務招攬投資完款後，會將客戶投資的錢分別以\n    現金或匯款方式給乙丙○處理。海閣林在綠島總共買11筆土\n    地，海閣林休閒渡假酒店公司以集合住宅名義申請建照。戊\n    ○○解釋要先以集合住宅的名義，先把房子蓋起來，以便對\n    股東有交代，戊○○也說到時一定可變更成旅館用途，我們\n    才一直相信戊○○，才向合夥人說到時一定可變更成休閒旅\n    館。當時跟客戶介紹時有明確跟客戶告知，沒隱瞞，沒詐欺\n    客戶等語（出處：警卷(一)，P63-P67 、偵二十卷，P55-P56\n    、原審一卷，P322、原審四卷，P196反面-P197 、P209）。\n6 、乙ｈ○：\n    91年中進入公司當業務員，後升協理，現任董事長助理，執\n    行董事長交代的各項工作，沒出資投資海閣林休閒渡假酒店\n    ，沒底薪，介紹募集每單位13萬5 千元之合夥人，我可抽4\n    千元佣金，每月約可領5 萬元我經手招募的約30人左右，海\n    閣林休閒渡假酒店以蓋飯店為名，向合夥人募資。海閣林在\n    綠島有11筆土地，是以戊○○名義申請建照。業務員每單位\n    可抽1 萬元，我抽4 千元。不知道公司的休閒旅館沒有執照\n    。一開始我們即沒有要詐欺客戶，公司給我們的訊息是一個\n    很好的投資案才介紹給客戶等語（出處：警卷(一)，P77-P83\n    、偵二十卷，P56-P57 、原審一卷，P322、原審四卷，P209\n    ）。\n7 、申○○：\n    92年底戊○○叫我到海閣林休閒渡假酒店擔任董事，在公司\n    擔任業務經理，94年4 月離職，離職時我的團隊剩下4 個女\n    業務ｈ○○、Ｉ○○、張雅婷及李文倩。沒固定薪水，視每\n    月業績而定，每筆我可抽3 千元業績獎金，我旗下女業務也\n    大約抽佣3 千元。公司以要在綠島興建五星級休閒渡假酒店\n    為由對外招攬投資，對外招商3600單位。公司有時會安排女\n    業務到婚友社拓展人脈，女業務在婚友社認識朋友後如何向\n    他們介紹投資我不清楚。女業務招攬投資完款後，會將客戶\n    的錢以現金或匯款的方式給我，我再將錢匯到戊○○或公司\n    的帳戶，或以現金拿給財務部經理乙丙○。公司在綠島共購\n    買11筆土地，公司跟我們說有申請過建照，我們不知道通過\n    的是集合住宅的建照，不知道公司的休閒旅館沒有執照。公\n    司給我們的案子，我認為很好才去推銷，也認為工作還不錯\n    ，沒有詐欺等語（出處：警卷(一)，P69-P72、偵二十卷，P5\n    6 、原審一卷，P322、原審四卷，P209）。\n8 、乙丙○：\n    我擔任戊○○特別助理，負責載送戊○○外出，以前是擔任\n    會計，我月薪3 萬。業務員沒支領底薪，拉到客戶買股份後\n    才有獎金，1 股份為1 單位13萬5 千元，業務員可分1 萬元\n    ，13萬5 千元中8 萬5 千元交回公司，入戊○○或公司帳戶\n    ，業務分3 萬5 千元，1 萬5 千元給戊○○，海閣林公司經\n    營是以業務員招攬販賣不知情之客戶投資公司股份蓋五星級\n    大飯店為業務方式。幹部均教導業務員，利用打電話機會宣\n    導朋友或參加婚友社約會的男生，告訴他們海閣林要在綠島\n    蓋休閒渡假酒店，蓋完觀光大飯店，如公司有賺錢，股東就\n    可以分紅。91年中旬開始招募，92年購買10多筆土地約3600\n    萬元。戊○○告訴我綠島建地有一部分是農地，不能蓋房子\n    ，要變更才能取得觀光飯店之建照。戊○○以將來會興建五\n    星級渡假大酒店告訴我們，大家才會以此名義對外召攬集資\n    。我全部都是按照公司及老闆指示去辦理等語（出處：警卷\n    (一)，P19-P31 、偵四卷，P3-P4 、偵七卷，P33 反面-P34、\n    原審一卷，P322、原審四卷，P197反面-P198 、P209）。\n9 、乙Ｆ○：\n    92年底在海閣林台中辦事處擔任經理，是教育訓練的講師，\n    我不負責對外推銷業務，是向公司業務員上一些有關公司的\n    專業知識及加強員工信心的課程，不是業務訓練。我沒向任\n    何人推銷過海閣林公司的股份，我的業務員每成交1 單位我\n    可抽2 萬元業績獎金，但須支付公司的水電費。我知道海閣\n    林休閒渡假酒店在綠島興建的飯店以戊○○私人名義去申請\n    集合式住宅的建照，公司是說將來一定可以變更過，但這部\n    分我們不瞭解，所以公司怎麼說我們就怎麼對客戶說等語（\n    出處：警卷(一)，P112-P113、偵二十卷，P62-P63、原審一卷\n    ，P322、原審四卷，197反面、P209）。\n10、乙地○：\n    91年開始在海閣林任職協理，負責管理業務員，知道海閣林\n    公司實際上沒有旅館執照，業務員都知道，有告訴客戶是集\n    合住宅，薪水是1 個單位抽8 千或9 千元，沒有底薪。我是\n    在乙ｆ○（顏銘震）公司上班，當時我有一個產品代銷即將\n    結束，認為觀光休閒是個不錯的產業，才轉換跑道代銷此商\n    品，我們都依照公司的工程進行去做，不知道犯罪等語（出\n    處：偵二十卷，P165-P 166、原審一卷，P322、原審四卷，\n    P209 ）。\n11、Ｐ○○（原名吳俊德）：\n    我在公司擔任業務主任，看主管要我做什麼，就做什麼，他\n    們都是我的主管。我是代銷公司的員工，入行不久，我得到\n    的訊息是工程有在進行，不曉得觸法。通常我們會算報酬率\n    給客戶看，客戶認為合理才簽約等語（出處：原審一卷，P3\n    22、原審四卷，P209、P212）。\n12、乙Ｒ○：\n    92年開始在海閣林公司擔任專員，後升職主任、襄理，94年\n    離職，剛開始公司叫翻天創新公司，後才改名海閣林。工作\n    性質主要是針對女業務所帶回來的客戶，我要向他們介紹公\n    司所投資的產業、性質或工程進度等有關投資案相關事情，\n    資訊都從公司處得知，由公司提供資料、建照影本等相關資\n    料，然後再由女業務向他們介紹投資海閣林公司的股份，解\n    說時不一定會進公司，但簽約時一定會帶到公司。解說投資\n    期間客戶每年可獲利多少有講大概的數字，營運後1 年才可\n    分紅，還本要看客戶自己計算，如投資10萬元，每年可分1\n    萬即10年可還本。簽約時我只依照合夥協議書內容陳列之項\n    目解釋，沒告知支付業務員獎金及幹部報酬部分。我的主管\n    是甲辛○。專員的業績獎金是1 萬元，主任獎金是1 萬3 千\n    元，襄理獎金是1 萬5 千元，我底薪1 個月3 萬元，我解說\n    的部分1 單位可領到2 千元。我知道海閣林公司是以戊○○\n    私人名義申請集合式住宅建照去蓋的，公司有跟我們說未申\n    請過合格的旅館建照，為了趕快把建物蓋好，公司才先申請\n    集合式住宅來蓋，將來一定可變更為旅館的建築執照。有跟\n    客戶說明集合住宅的執照，沒有飯店、酒店的執照，建照在\n    變更當中。我認為公司有用心經營，客戶也都是成年人，應\n    該有判斷能力，我們是依照公司藍圖跟客戶解釋，若詐欺客\n    戶就不會買地、開工等語（出處：警卷(一)，P183-P185 、偵\n    二十卷，P72 、原審一卷，P322、原審四卷，P198、P209、\n    P211-P212）。\n13 、甲Ｂ○：\n    93年中在海閣林公司擔任專員，後當主任，薪水每月大約2\n    萬多，知道海閣林公司沒有飯店執照，有對客戶講是集合住\n    宅的執照，會申請變更。我也是代銷公司員工，職務內容與\n    乙Ｒ○同等語（出處：偵二十卷，原審四卷，P209反面、P2\n    12）。\n14、甲ｗ○：\n    93年在海閣林公司上班擔任業務專員，94年就被乙Ｒ○換到\n    風緻開發公司上班，期間約支領10萬元薪水。我在海閣林公\n    司沒有底薪，要談CASE才有薪水，不知道談CASE收入有多少\n    ，我在海閣林均只幫人介紹資料，我沒錢吃飯都跟甲辛○拿\n    。海閣林公司經營股份投資買賣。上級要我以綠島飯店開發\n    案去尋找客戶，以後會賺錢，我有對外賣出10個單位，1 單\n    位13萬5 千元可抽8 千元到1 萬元佣金，有賣給ｙ○○、甲\n    Ｅ○，當時有跟她們說是集合住宅的執照，之後會變更為飯\n    店，還有拿文件給他們看。我是代銷公司員工，我只是業務\n    員要賺錢，不知道是詐欺等語（出處：警卷(一)，P195-P199\n    、偵二十卷，P183-P184 、原審二卷，P115、原審四卷，P2\n    09反面）。\n15、午○○（原名史雅茜）：\n    92年在海閣林公司當專員，後升到主任，沒有底薪，是獎金\n    制，專員是1 單位1 萬元，主任是1 萬3 千元，前後領到的\n    獎金約幾10萬。申○○、未○○是我堂兄妹。不知道海閣林\n    沒有飯店執照，只知道有集合住宅建造執照，有對客戶說有\n    建照，公司跟客戶說明時有講是集合住宅的執照，會申請變\n    更，公司當時拿土地等投資案相關資料給我，我才去找客戶\n    ，有告知客戶相關訊息，客戶有到公司看過後，才決定投資\n    ，我有到綠島看過現場。有賣ｗ○○、乙ｒ○、乙Ｕ○、甲\n    ｐ○、Ｙ○○、黃○○、ｐ○○、甲ｉ○、乙Ｌ○、Ｒ○○\n    、Ｕ○○，當時我以朋友立場推薦給朋友，沒說要結婚，只\n    說要當朋友，沒說不買東西就不能交朋友等語（出處：偵二\n    十卷，P156、原審二卷，P74、P276-P277、原審四卷，P199\n    、P209反面）。\n16、甲ｓ○：\n    92年底進入海閣林公司擔任專員，薪水是獎金，1 單位9 千\n    元，知道海閣林公司沒有飯店的執照，但有集合住宅的執照\n    ，共約賣出50幾個單位，有向客戶說明是集合住宅的執照。\n    有賣丁○○、甲Ｆ○。老闆怎麼說就怎麼做，我沒有詐欺意\n    圖等語（出處；偵二十卷，P94-P95 、原審四卷，P209反面\n    ）。\n17、乙Ｉ○（原名蔡宜庭）：\n    92年底開始在海閣林公司當專員，沒有底薪，是獎金制，專\n    員1 個單位9 千元，知道海閣林公司沒有飯店執照，有對客\n    戶講是集合住宅的執照，會申請變更，共賣約40幾個單位，\n    有賣給ｌ○○、許見智、Ａ○○等大概4 個客戶，有拿到佣\n    金。沒有詐欺意圖，公司推出此投資案時，在綠島有蓋旅館\n    ，我有詳細跟客戶解說，也提到會變更建照等語（出處：偵\n    二十卷，P158、P184、原審二卷，P63 、原審四卷，P209反\n    面）。\n18、Ｌ○○：\n    93年初在海閣林公司擔任業務專員，薪水是獎金，1 單位9\n    千元，知道海閣林公司沒有飯店的執照，共賣出約5 、60個\n    單位，有向客戶說明是集合住宅的執照，有賣給乙酉○、甲\n    Ｎ○、乙亥○、甲Ｇ○、甲天○。我有請客人到公司瞭解狀\n    況。Ｍ○○是我姊姊等語（出處：偵十六卷，P6-P57、偵十\n    八卷，P5-P6 、P16-P17 、P22 、P29-P30 、偵二十卷，P9\n    3、P272、原審二卷，P62 、原審四卷，P209反面）。\n19、乙ｋ○：\n    91年底在海閣林公司擔任專員，後升到主任，當時公司名稱\n    是翻天，薪水是獎金，1 個單位9 千元，主任是1 萬3 千元\n    ，我大概可以抽9 千元，不知道海閣林公司沒有飯店的執照\n    ，當時公司正在買地，有向客戶說明執照的情形，共賣不到\n    10個單位，有賣乙Ｏ○。如公司所說，執照、什麼東西都有\n    ，簽約時都有看得到等語（出處：偵二十卷，P94、原審二\n    卷，P62-P63、原審四卷，P209反面）。\n20、甲Ｉ○：\n    當初在海閣林公司擔任業務，1 個單位13萬5 千元，佣金約\n    8 千至1 萬元。知道海閣林公司沒有飯店執照，有對客戶說\n    明是集合住宅的執照，共賣1 、20個單位，有賣給宇○○。\n    公司說什麼我們就做什麼等語（出處：偵二十卷，P157-P15\n    8 、原審二卷，P118、原審四卷，P209反面）。\n21、甲Ｊ○：\n    93年在海閣林公司擔任專員，薪水是獎金，1 個單位9 千元\n    ，知道海閣林公司沒有飯店的執照，但有集合住宅的執照並\n    有向客戶說明，共賣出約2 、30個單位，有賣辛○○、乙宙\n    ○、甲Ｑ○、乙ｏ○。我們是一般代銷公司，公司叫我們做\n    什麼就做什麼等語（出處：偵二十卷，P87-P88 、原審二卷\n    ，P63 、原審四卷，P209反面）。\n22、ｍ○○（原名林詩怡）：\n    92年間在海閣林公司擔任業務助理，我領底薪，每月1 萬5\n    、6 千元，沒有在賣單位，也沒有賣甲Ｃ○單位，當時甲Ｃ\n    ○是我負責開發，但產品介紹不是我，我有帶甲Ｃ○到公司\n    交由公司人員介紹。我在代銷公司上班，不知道飯店是否有\n    蓋好，沒有以結婚為前提認識客戶等語（出處：偵二十卷，\n     P93-P94、原審二卷，P74 ）。\n23、乙Ｘ○：\n    91年在海閣林公司擔任業務助理，當時公司是翻天，薪水是\n    獎金，1 單位1 萬元，當時公司已買完地在搭建，只知道有\n    執照，不知何執照。不知道綠島有無辦理登記，主管有跟我\n    們講，但我們沒直接去綠島瞭解，那時剛出社會，認為公司\n    提供訊息飯店有在興建，不知道要看執照，認為當時有在營\n    運，不是詐欺，約2 個半月我就離職，我負責綠島開發案及\n    跟客戶推銷，1 個單位約12、3 萬元，抽取8 、9 千元等語\n    （出處：偵二十卷，P96、原審二卷，P63、原審四卷，P210\n    ）。\n24、Ｊ○○：\n    91年在海閣林公司當任專員，後升到主任，沒底薪是獎金制\n    ，專員1 單位1 萬元，主任1 萬3 千元，不知道海閣林公司\n    沒飯店執照，沒帶客戶到公司，不記得賣多少單位，有賣給\n    亥○○、巳○○。沒拿到佣金。我沒詐欺，我到離開公司時\n    都認為是真的等語（出處：偵二十卷，P159、原審二卷，P6\n    3 、原審四卷，P210）。\n25、黃睦芸（原名黃彩惠）：\n    92年底進去海閣林公司擔任專員，薪水是獎金，1 單位9 千\n    元，知道海閣林公司沒飯店執照，共賣出約2 、30個單位，\n    有向他們說明是集合住宅的執照，有賣乙ａ○、乙Ａ○，有\n    領到佣金，我把客戶帶到公司後即由公司職員介紹。當時剛\n    進公司認為公司前景很好，是代銷公司等語（出處：偵二十\n    院，P95 、原審二卷，P63 、原審四卷，P210）。\n26、甲ｖ○（原名馮志群）：\n    92年進去海閣林公司擔任專員，後升到主任，薪水是獎金，\n    1 個單位1 萬元，主任1 萬3 千元，知道海閣林公司沒有飯\n    店的執照，但有集合式住宅的執照，共賣出約1 百個單位，\n    有向客戶說明是集合住宅的執照，是我帶客戶到公司，乙Ｒ\n    ○、吳俊德、甲Ｂ○向他們說明的。有賣給甲丙○、乙丑○\n    、丙○○、甲酉、甲庚○、甲ｅ○、甲Ｗ○、甲未○、甲Ｌ\n    ○，客戶大部分用貸款方式購買公司產品，由公司辦信用貸\n    款，我純粹負責推銷，以朋友心態與其聯繫，但客人若以交\n    女友心態問我，我會直接講明。我是代銷公司員工，有看到\n    建築執照、買地證件等，公司有跟我說日後建照會變更，我\n    沒威脅客戶不成交就不交往，董事長有帶我們到綠島看基地\n    等語（出處：偵二十卷，P88 、原審二卷，P74 、原審四卷\n    ，P210）。\n27、未○○（原名史恆華）：\n    92年我哥哥申○○介紹我進去海閣林公司擔任專員，後升到\n    主任、襄理，沒底薪，是領獎金，我的工作就是要推銷海閣\n    林公司的股份，大約推銷20人左右，我從參加婚友社著手開\n    發，專員的獎金是1 萬元，主任獎金是1 萬3 千元，襄理獎\n    金是1 萬5 千元，副理獎金是1 萬8 千元，經理獎金是2 萬\n    元。公司有拿1 張公文和很多資料給我們看，給我們看集合\n    住宅的執照，說已經申請過合法的建照，我們對這部分也是\n    一知半解，公司如何教育我們，我們就怎麼對客戶說。戊○\n    ○開會有說要以他名義申請建照比較好通過，他保證會將整\n    個飯店的產權都變更回公司名下。有賣過ｔ○○、吳宣昌、\n    甲Ｖ○、Ｏ○○、宙○○。我對客戶均稱公司在綠島興建飯\n    店，綠島目前無飯店，投資1 個單位13萬5 千元，將來應可\n    獲利，客戶有些是貸款購買，我沒幫其辦貸款，我帶客戶到\n    中正路公司由公司人員介紹，客戶有些是同事或朋友介紹，\n    我與客人沒牽過手。公司每個工程進度都會跟我們講，我會\n    告知客戶此訊息等語（出處：警卷(一)，P125-P128 、偵二十\n    卷，P63- P64、原審二卷，P74 、原審四卷，P199反面-P20\n    0 、P210）。\n28、甲子○：\n    92年在海閣林當兼職業務員，只負責在外接客戶推銷海閣林\n    公司的股份，成功時向公司拿我該得的獎金即1 萬元。我利\n    用想和對方交往的方法，誘導少數投資人投資海閣林，我沒\n    說過要結婚，有極力推銷，以公司給我們的訊息去做推銷。\n    。剛開始我不知道海閣林公司以何名義申請建照，但後來因\n    客戶在問，公司才跟我說是以戊○○名義去申請集合住宅的\n    建築執照，公司說到時再申請變更，這樣比較不會耽誤到正\n    式營運的時間。我都是將客戶帶到公司，由乙ｈ○向客戶介\n    紹，公司男客戶扮演女業務的親戚或乾哥，我都會跟客戶說\n    乙ｈ○是在公司擔任特助，由他向客戶介紹比較直接且較深\n    入。有賣過乙ｐ○、許福元、Ｖ○○。當時公司有帶我們到\n    綠島看動工，工程進度陸續在走，公司有跟我們回報，都是\n    聽從公司指示在走等語（出處：警卷(一)，P176-P178 、偵二\n    十卷，P71-P72 、原審二卷，P75 、原審四卷，P210）。\n29、Ｉ○○：\n    92年開始在海閣林公司擔任業務專員，後升到主任沒有底薪\n    ，薪水是獎金，業務員獎金是1 萬元，主任是1 萬3 千元。\n    我去婚友社認識新朋友，跟對方介紹投資海閣林的投資方案\n    ，主要希望對方能因投資海閣林而獲利。共向約20人推銷過\n    ，賣過5 、60個單位，總計完款60至70筆。我不知道建照方\n    面的事情，最近才知道公司在綠島蓋飯店是以戊○○私人名\n    義申請過集合式住宅建照，公司說將來一定可變更成功。公\n    司有拿集合住宅的執照給我們看，有跟客戶說有建照，沒說\n    是什麼建照，有賣過甲辰○、地○○、ｉ○○、甲宇○，我\n    是以朋友立場去推銷，公司有帶我們到綠島看動土典禮等語\n    （出處：警卷(一)，P158-P160、偵二十卷，P70-P71、原審二\n    卷，P75、原審四卷，P210）。\n30、Ｃ○○：\n    92年進去海閣林擔任專員，薪水是獎金，1 單位1 萬元，知\n    道海閣林公司沒有飯店的執照，但有集合住宅的執照，共賣\n    出約100 個單位，有向客戶說明是集合住宅的執照，日後會\n    變更，有賣甲申○、甲ｈ○等3 個客戶單位。客戶均在交友\n    中心認識，客人先衡量自己資力購買，甲申○當時經濟能力\n    佳所以購買9 或10單位，沒說要購買產品我才要與其作朋友\n    。我進公司後，瞭解公司有買地，飯店也有蓋，客戶到公司\n    有告知建照會變更，現以集合住宅興建等語（出處：偵二十\n    卷，P86 、原審二卷，P75 、原審四卷，P210）。\n31、ｈ○○：\n    擔任海閣林公司專員，販賣、推銷海閣林公司股份給不特定\n    人，1 單位13萬5 千元，可分配到1 萬元。前後大約招攬30\n    人投資，完款30筆，領取30萬左右業務獎金。有賣過卯○○\n    、乙Ｍ○、簡國恒、ｃ○○、乙Ｅ○、乙ｑ○、甲ｃ○、乙\n    寅○、Ｈ○○、甲Ｘ○單位。其中乙ｑ○是工人，因信貸不\n    足，只付部分款項，剩下由我墊付。有到綠島看建築等語（\n    出處：警卷(一)，P208-P213、偵二十卷，P77-P78、原審二卷\n    ，P75、原審四卷，P210反面）。\n32、乙Ｇ○：\n    91年在翻天創新國際股份有限公司任職，92年離職時公司改\n    名為海閣林公司，擔任會計兼業務，在海閣林有推銷公司的\n    股份，約推銷4 、5 人，賣5 、6 個單位，薪水是會計1 個\n    月2 萬3 千元加獎金即成交1 單位8 千元。我離職時公司尚\n    未購地，但有計畫在接洽購地事宜，已簽下建地，興建集合\n    住宅我不清楚。有賣過甲壬○等語（出處：警卷(一)，P223-P\n    225 、偵二十卷，P78-P79 、原審二卷，P75 、原審四卷，\n    P210反面）。\n33、陳佩琦：\n    93年在海閣林公司當專員，後升到主任，沒底薪是獎金制，\n    專員1 單位1 萬元，主任是1 萬3 千元。知道海閣林公司沒\n    有飯店執照，跟客戶說明時有講是集合住宅的執照，共賣20\n    幾個單位左右，有賣給乙申○、乙Ｐ○、乙ｃ○。我沒說要\n    先購買產品才可交友。我屬代銷公司，知道當時是以集合住\n    宅興建，但會變更用途，我有到綠島，有看到基地在興建飯\n    店，認為是真的投資等語（出處：偵二十卷，P160、原審二\n    卷，P75、原審四卷，P210反面）。\n34、乙Ｃ○：\n    93年在海閣林公司但任業務專員，後升到主任，沒有底薪，\n    是領獎金，業務員是1 個單位1 萬元，主任是1 萬3 千元，\n    94年覺得公司怪怪的就離職。大概向20個客戶推銷成功過海\n    閣林公司的股份，完款20筆左右，每單位專員的獎金是1 萬\n    元。我知道海閣林休閒渡假酒店是以戊○○私人名義去申請\n    集合式住宅建築執照，公司說將來一定可以變更過，公司怎\n    麼對我們說，我們就怎麼對客戶說。有賣過Ｓ○○，有帶他\n    到綠島看過。我認為我也被騙。當初都認為公司給我們的訊\n    息是真的等語（出處：警卷(一)，P189-P191 、偵二十卷，P\n    72- P73 、原審二卷，P75 、原審四卷，P210反面）。\n35、甲ｂ○：\n    93年在海閣林擔任業務專員，沒有底薪，是領獎金，1 個單\n    位1 萬元，大概向7 、8 個客戶推銷成功過，完款10幾筆左\n    右。不知道海閣林公司沒有酒店飯店執照，但知道海閣林休\n    閒度假酒店是以戊○○私人名義申請集合式住宅，公司說要\n    先把建物蓋起來，將來再去變更。有賣過ｋ○○、Ｂ○○、\n    ｊ○○、乙癸○，而乙癸○錢沒付完。入公司只是為了1 份\n    工作，主管叫我們做什麼就做什麼，沒有要欺騙客人，客戶\n    需要瞭解什麼就帶入公司由主管講解等語（出處：警卷(一)，\n    P148 - P150 、偵二十卷，P65 、原審二卷，P76 、原審四\n    卷，P210反面）。\n36、甲Ｒ○：\n    91年至92年在海閣林擔任專員，後來是襄理，沒有薪水，但\n    賣出單位有獎金，專員是1 單位8-9 千元，襄理是1 萬元，\n    共賣出10幾個單位，知道海閣林公司是集合住宅執照，有跟\n    買的客戶說明是集合住宅執照，說像民宿，有賣給甲Ｘ○、\n    甲丑○、乙Ｓ○單位。我以朋友立場告訴客人這是不錯的產\n    品可以投資，分享給客人等語（出處：偵十三卷，P17-P18\n    、偵十四卷，P22、原審二卷，P76、原審四卷，210反面）\n    。\n37、乙黃○：\n    劉珈妤也是我本人。92年間在海閣林公司擔任業務專員，後\n    升到主任，沒有底薪，是領獎金，業務員是1 個單位1 萬元\n    ，主任是1 萬3 千元，不知道海閣林沒有飯店執照，任職期\n    間大概向20個客戶推銷成功過，完款約4 、50個單位。領過\n    約10幾萬元業務獎金。沒帶過客戶到綠島。當時工程都有在\n    進行，不認為詐欺等語（出處：警卷(一)，P137-P138 、偵七\n    卷，P32 、偵二十卷，P64 、原審二卷，P76 、原審四卷，\n    P198 反面-P199 、P210反面）。\n38、甲ｍ○：\n    92年在海閣林公司任職，公司是在台中的辦事處，進去是業\n    務員，後升到主任，沒有底薪，是領獎金，業務員是1 單位\n    9 千元，主任是1 萬2 千元。我都從網路上認識朋友，跟他\n    們說海閣林的投資方案很好可賺大錢，看他們要不要投資，\n    如他們有意願，就帶他們到公司進一步瞭解，想投資的人沒\n    錢，我會介紹他們去貸款。知道海閣林公司沒有酒店飯店執\n    照，有跟客戶說是集合住宅執照，有賣給乙戌○、玄○○、\n    林豊田、甲丁○、子○○、乙ｔ○、乙丁○、乙Ｔ○、甲宙\n    ○。沒跟客戶說沒有購買不能當朋友，公司有帶我們到綠島\n    看工程，的確有動工、興建，公司當時也沒說執照沒核發。\n    我只是代銷海閣林產品，乙ｆ○叫我們做什麼我們就做，確\n    實沒以結婚為前提介紹投資等語（出處：警卷(一)，P142-P14\n    3 、偵二十卷，P64-P65 、原審二卷，P76 、原審四卷，P2\n    11）\n39、甲Ｐ○：\n    92年在台中朕聖公司擔任兼職業務員，主管叫我去推銷海閣\n    林公司的投資案，要在綠島蓋五星級大飯店，銷售海閣林飯\n    店股權，以股權銷售方式，每單位13萬5 千元，我只推銷給\n    庚○○4 個單位，說有很大商機，會有很大獲利，沒說獲利\n    多少，每單位我可抽1 萬元業績獎金，不知道海閣林沒有酒\n    店飯店執照，客戶有到公司現場，有看到執照。我沒去綠島\n    看過，但有委託朋友去綠島時幫我看，我朋友去問當地人，\n    當地人說沒聽過海閣林休閒渡假酒店，我覺得怪怪就不再推\n    銷海閣林的投資案。沒推銷給ｎ○○、乙ｄ○、乙ｙ○，我\n    依照公司的訊息介紹，沒跟客戶說以結婚為前提作為投資的\n    方向等語（出處：警卷(一)，P170-P171、偵二十卷，P71、原\n    審一卷，P251反面、原審四卷，P211）。\n40、Ｎ○○：\n    我在朕聖公司任職，不是在海閣林公司，沒有賣給甲ｔ○、\n    甲寅○、乙Ｑ○，當時我沒有介紹客戶，也沒到外面推銷，\n    只有在公司接電話，那是別人介紹的。記得當時很多客戶到\n    公司由負責解說的人解說，公司如何跟其解說我不清楚等語\n    （出處：偵二十卷，P86-P87 、原審二卷，P115、原審四卷\n    ，P211）。\n41、Ｘ○○：\n    92年在海閣林公司擔任業務員，主管要我從事海閣林投資案\n    股權推銷，要在綠島蓋五星級飯店，以股權銷售方式，每單\n    位13萬5 千元。薪水是獎金，1 個單位1 萬元，知道海閣林\n    公司沒有飯店的執照，有向客戶說明是集合住宅的執照，甲\n    ａ○問我說他想要賺錢，所以我向其推銷海閣林股權，我賣\n    他5 單位；甲ｇ○我推銷他14個單位188 萬元，乙天○我推\n    銷他6 個單位，他用信用貸款方式繳錢，有介紹他們產品，\n    沒說獲利多少等語（出處：偵二十卷，P87 、原審一卷，P2\n    51 反面、原審四卷，P211）\n42、ａ○○（原名李裙鳳）：\n    91年任職海閣林公司擔任業務員，後升到主任，主管要我從\n    事海閣林投資案股權推銷，要在綠島蓋五星級飯店，是以股\n    權銷售方式，每單位13萬5 千元，我只推銷給乙Ｂ○4 單位\n    ，說公司將綠島蓋五星級飯店，看其有無意願投資，沒有說\n    利潤多少，只說綠島現在沒有飯店，只有民宿，蓋飯店投資\n    報酬率會好，我有帶客戶到公司瞭解狀況，是客戶本身想投\n    資，沒有強迫其投資等語（出處：偵二十卷，P160、原審一\n    卷，P252、原審四卷，P211）。\n43、Ｍ○○：\n    92年在朕勝公司擔任業務員，主管要我推銷海閣林投資案股\n    權，要在綠島蓋五星級飯店，是以股權銷售方式，每單位13\n    萬5 千元。我沒有薪水，是獎金制，1 個單位9 千元，知道\n    海閣林公司沒有飯店執照，但有對客戶說明有集合住宅執照\n    ，會申請變更，共賣出3 、40個單位，有賣給癸○○、乙ｌ\n    ○、乙庚○、乙甲○，我跟他們推銷公司將在綠島蓋五星級\n    飯店，看其有無意願投資，有說利潤不錯，沒有明確講說利\n    潤有多少等語（出處：偵二十卷，P156-P157 、原審一卷，\n    P251 反面-P252 、原審四卷，P211）。\n44、乙Ｄ○○\n    我於91年間在翻天創新國際有限公司任職，後來公司改名海\n    閣林休閒渡假酒店公司，在海閣林擔任專員、主任、襄理，\n    對外開發業績，在公司內介紹客戶產品，以綠島開發案為主\n    ，有時業務會跟客戶說，親戚在海閣林公司上班，目的是將\n    客戶帶到公司，讓主管幫我們向客戶推銷，推銷成功約50筆\n    左右，專員的獎金是1 萬元，主任獎金是1 萬3 千元，襄理\n    獎金是1 萬5 千元，離職前公司就對我們說海閣林休閒渡假\n    酒店有申請過合法旅館的建築執照，是合法建照，我也都是\n    這樣跟客戶推銷，有賣給甲巳○、ｂ○○、乙Ｖ○、甲卯○\n    如起訴所載之投資單位，沒有要他們投資海閣林，才去婚友\n    社，是因為朋友關係，覺得真的會賺錢才跟客戶分享，我去\n    過綠島2 次，第1 次去現場在整理地基，第2 次去時已有建\n    築物存在，沒帶過4 位客戶去過綠島，但他們參加投資後好\n    像有去綠島看過等語（見警A 卷，P163-P166 、偵四卷，P2\n    1 反、偵二十卷，P166、原審二卷，P118、原審四卷，P311\n    -P312、P314）。\n五、經查：\n(一)、公訴意旨雖認被告戊○○等人以海閣林公司名義，先以少數\n    之資金在綠島地區購得依法不得建造旅館之土地（建地3 筆\n    、農地8 筆），且購得土地，均登記在被告戊○○名下，再\n    以集合住宅的名義申請建造執照，佯稱在綠島投資興建五星\n    級休閒渡假大飯店，且明知海閣林公司自始至終無法取得臺\n    東縣政府所核發之合法旅館建築執照，而向被害人詐騙投資\n    款等情。惟：\n 1、緣於91年4 、5 月間，另案被告黃復杰以在綠島投資購地建\n    造「海閣林休閒渡假酒店」為由，邀被告戊○○合夥，共同\n    籌劃設立翻天創新公司（址設高雄市前金區○○○路235 號\n    8 樓之5 ），黃復杰負責公司出資及總攬公司財政等營運事\n    項，戊○○則擔任招募公司股東、籌措資金及其餘公司事務\n    ，並由戊○○擔任翻天創新公司之登記負責人，該公司於91\n    年5 月7 日完成設立登記，2 人即擬定「合夥預定契約書」\n    （下稱「舊合夥預定契約書」），以購地興建「海閣林渡假\n    大酒店」名義，對外招募股東籌措資金；詎黃復杰與戊○○\n    ，自91年6 月24日起至92年3 月5 日間止，於綠島進行購地\n    之際，竟將部分募得資金，由戊○○連續轉帳共計72,094,2\n    00元之投資款項至黃復杰所指定之帳戶內，供黃復杰提領使\n    用，黃復杰得款上開7 千2 百萬餘元，即避不見面，2 人共\n    同連續業務侵占部分，黃復杰前經原審法院以92年度易字第\n    2253號判決判處有期徒刑4 年，並經本院94年度上易字第58\n    9 號判決駁回上訴確定；戊○○另經原審法院以98年度易字\n    第75號判處有期徒刑2 年，亦經本院98年度上易字第762 號\n    判決駁回上訴確定，合先敘明。\n 2、被告戊○○於92年4 月間，將翻天創新公司改籌組海閣林公\n    司，由戊○○擔任海閣林公司董事長，並增修「舊合夥預定\n    契約書」內容，重新擬定「合夥預定契約書」（下稱「新合\n    夥預定契約書」），以海閣林公司名義繼續招募股東及籌措\n    資金，並透過臺東市市民代表陳貞賢之介紹，委託臺東縣綠\n    島鄉公所秘書鄭文仁居中簽線，經多次協調土地買賣事宜，\n    由海閣林公司出資2,117 萬3 千元，向地主韓春麟購買坐落\n    臺東縣綠島鄉○○○段第1176、1178、1179、1180、1180-1\n    、1183、1183之1 、1185地號之土地（上開土地皆係「旱地\n    」，起訴書誤載為「農地」），並於92年5 、6 月間，將購\n    地款項匯入鄭文仁開設之合作金庫臺東分行帳戶；嗣戊○○\n    發現土地面積仍不足興建海閣林休閒渡假酒店，希望再購買\n    週邊其它建地，以擴大使用面積，復透過陳貞賢介紹，委託\n    鄭文仁居中簽線，經多次接洽，以1,389 萬之代價，向地主\n    鄭盛隆購買坐落臺東縣綠島鄉○○○段1152、1152-1、1152\n    -2地號之土地（3 筆土地皆為「建地」），並於92年8 月間\n    ，並將購地款項匯入鄭盛隆指定友人謝志忠之郵局帳戶等情\n    ；此據證人鄭文仁、韓春麟於警詢時證述甚詳（警(一)卷第25\n    2 至254 、265 、266 、309 、310 頁），復有海閣林公司\n    登記資料、股東名簿、股東繳納股款明細表、不動產買賣契\n    約書、鄭文仁之合作金庫銀行活期存款存摺影本、謝志忠之\n    郵政存簿儲金簿影本、土地所有權人土地資料謄本、地籍圖\n    影本，及土地異動索引資料各1 份在卷可稽（警卷(四)第1600\n    、1601、1740至1772頁，警卷(四)第256 至263 、267 至271\n    頁）。足證被告戊○○自92年4 月間起至同年8 月間止，確\n    有將海閣林公司募得之資金共計3 千5 百多萬元，在綠島地\n    區取得上開土地，並作為興建海閣林休閒渡假酒店之用途。\n 3、被告戊○○於92年8 月間在綠島購得上開土地後，因部分土\n    地地目係屬「旱地」，無法登記公司所有，而暫將土地登記\n    於戊○○名下；隨即委請蔡國勇建築師在上開地號1152、11\n    52-1、1152-2、1178、1180、1183等6 筆土地，規劃設計全\n    棟地上5 層、地下1 層共計49戶之「海閣林休閒渡假酒店」\n    （下稱「全案工程」、基地面積共計1571.64 平方公尺、法\n    定空地面積共計599.87平方公尺、總樓地板面積共計3124.4\n    2 平方公尺），並向臺東縣政府申請旅館執照，然因旁邊臨\n    時道路問題，尚未解決，縣府僅准核發集合住宅用途之建造\n    執照（93年3 月25日府城建字第000000000 號），戊○○支\n    付蔡國勇建築師約130 萬元之規劃設計費用，並取得建造執\n    照後，自93年4 月19日起，復將全案工程交由銘泉營造有限\n    公司（下稱銘泉營造公司），並按蔡國勇建築師之上開設計\n    規劃施工，全案工程於94年12月20日完工，工程款（含追加\n    工程款）總計9, 608萬，嗣於95年2 月10日取得臺東縣政府\n    核發之集合住宅使用執照（府城建字第Ｚ0000000000 號）等\n    情，業據證人即建築師蔡國勇於偵查中具結，及證人即銘泉\n    營造公司股東賴振東於警詢陳明在卷（偵七卷第32、33頁蔡\n    國勇筆錄、警卷(一)第272 至274 賴振東筆錄），並有綠島海\n    閣林旅館新建工程申請建築執照流程說明及相關資料（偵五\n    卷第192 至195 頁）、銘泉營造公司臺中商業銀行活期性存\n    款存摺影本、銘泉營造公司開立之發票影本（發票上面買受\n    人均記載「海閣林休閒渡假酒店」）、銘泉營造公司營造業\n    登記證書影本（警卷(一)第276 至291 頁）、臺東縣政府93年\n    3 月25日府城建字第000000000 號建造執照及95年2 月10日\n    府城建字第Ｚ0000000000 號使用執照（警卷(四)第1733頁，原\n    審卷(一)第262 至265 頁）在卷可稽；復有綠島海閣林施工程\n    藍圖、工程合約書、水電工程配置圖、鋼構配置圖、施工圖\n    本、平面配置圖、工程照片、綠島海閣林遊樂業整合性管理\n    系統建議書及餐飲管理系統建議書可佐。是被告戊○○自92\n    年8 月間起至95年2 月10日止，確將海閣林公司募得之資金\n    約9 千7 百多萬元，用以興建「海閣林休閒渡假酒店」，作\n    為綠島地區休閒遊樂渡假場所之事實無誤。\n 4、證人蔡國勇建築師於偵查中亦具結證稱：海閣林公司請我設\n    計時，說是要蓋飯店，我起初以旅館名義申請，但縣府說不\n    合法令，我建議用集合住宅名義申請，但蓋的標準，還是用\n    旅館方式去興建，以後再變更申請；當時因為旁邊臨時道路\n    的問題，沒有辦法解決，預計興建的旅館旁邊，雖有一條既\n    成道路，但要用捐贈道路土地，或收購隔壁民房的方式，當\n    作道路土地，才能解決臨時道路的問題等語（偵七卷第33頁\n    ），是被告戊○○委請蔡國勇建築師設計之初，原先即以旅\n    館規模之建造設計；且因臨時道路問題無法克服，才先以集\n    合住宅名義申請建造執照之事實亦明。又上開建築工程於95\n    年2 月10日取得上開集合住宅使用執照後，海閣林公司於95\n    年11月14日提出申請，經臺東縣政府審查符合旅館消防安全\n    設備，同意海閣林公司籌設旅館，並於一年內依建築法、都\n    市計畫法等相關法規辦理後，再申請旅館登記等情，有臺東\n    縣政府95年12月4 日府旅管字第0953038052號函及臺東縣消\n    防局95年12月28日消預審字第0950000119號函在卷可稽（原\n    審卷(一)第218 、219 頁），嗣被告戊○○於96年7 月17日再\n    提出申請，臺東縣政府於96年7 月26日爰准將上開集合住宅\n    （地上5 層、地下1 層、1 棟共計49戶）變更為「旅館用途\n    」之事實，亦有臺東縣政府96年7 月26日府城建字第Ｚ00000\n    00000 號（第01次變更）使用執照影本1 份附卷可查（原審\n    卷(一)第266 至269 頁），足徵上開集合住宅共計49戶確已合\n    法變更「旅館用途」。\n 5、據上各節，被告戊○○在綠島之購地資金，已投入約3,500\n    萬元，另興建「海閣林休閒渡假酒店」之設計及工程費用，\n    亦達約9,700 萬元。此外，臺東縣政府確於96年7 月26日准\n    將上開集合住宅49戶變更為「旅館用途」等情，均如前述。\n    是公訴人起訴所執「被告戊○○等人以少數資金購地，且明\n    知無法取得合法旅館建築執照，而向被害人詐騙投資款」等\n    情，尚有未洽。\n(二)、公訴意旨另認被告戊○○等人，自91年4 月間起，由海閣林\n    公司各級業務員至婚友社或上網交友，以與被害人交往為藉\n    口，隱瞞沒有合法旅館使用執照之事實，誘騙被害人投資海\n    閣林休閒渡假酒店，且被害人不知業務員有抽取高額獎金，\n    並於被害人繳完款項後，業務員隨即失聯，以此方式詐騙被\n    害人投資款等情。惟：\n 1、依卷附合夥預定契約書觀之，本件黃復杰及戊○○於91年5\n    月間擬定之「舊合夥預定契約書」（以翻天創新公司名義對\n    外簽約），及戊○○於92年4 月擬定之「新合夥預定契約書\n    」（以「海閣林」公司名義簽約，但部分契約書第1 行誤繕\n    「翻天創新」公司，嗣經更正為「海閣林」公司），均載明\n    投資人與翻天創新公司（或海閣林公司），雙方係針對共同\n    開發海閣林休閒渡假酒店之合夥出資事宜之相關權益事項而\n    簽訂契約；而新合夥預定契約書第1 條之1 載明「海閣林休\n    閒渡假酒店預定座落於臺東縣綠島鄉○○○段1152、1152-1\n    、1152-2、1176、1178、1179、1180、1180-1、1183、1183\n    之1 、11  85地號土地上」等語；而被告戊○○自92年4 月\n    間起至同年8 月間止，確將募得之資金約3 千5 百多萬元，\n    購得上開契約書所載明之土地，另於92年8 月間起至95年2\n    月10日止，亦將募得之資金約9 千7 百多萬元，用以興建「\n    海閣林休閒渡假酒店」，又本件臺東縣政府業於96年7 月26\n    日已將上開集合住宅49戶變更為「旅館用途」等情，皆如前\n    述，是被告戊○○確實已依上開合夥契約內容，在綠島購地\n    並完成上開渡假酒店之興建。則公訴人起訴指稱被告等人，\n    隱瞞無法在綠島取得合法旅館使用執照，而向被害人誘騙投\n    資海閣林休閒渡假酒店一節，亦難採認。\n 2、就下列被害人證述觀之，上開海閣林公司業務員於行銷過程\n    中，並未特別以結婚或交往為藉口，而誘騙投資人參加投資\n    事宜，且投資之前，亦未受業務人員姿色誘惑之影響；另就\n    扣案之海閣林公司所有之會議記錄、人事資料、員工教育手\n    冊及客戶電話資料內容觀之，查扣之書面資料，主要皆是傳\n    授業務員招攬客戶之技巧，並未提及如何使用詐術欺騙投資\n    人，亦未刻意安排業務員至婚友社或上網尋覓投資對象；縱\n    部分業務員曾向某被害人表示參與投資後，始願意與被害人\n    結婚或繼續交往等語，然此屬業務員為求績效所為之個人行\n    為，僅係吸引異性客戶之行銷手段，難認被告等人即有以業\n    務員欲與客戶結婚或交往為藉口，而誘騙投資人參加投資之\n    情：\n (1)證人ｒ○○證稱：未○○向我推銷海閣林公司在綠島的投資\n    案，她希望我認購愈多愈好，但我衡量能力，只能購買2 個\n    單位27萬元，我把身分證、薪轉存摺、印鑑都交給她去向高\n    雄二信銀行辦理信用貸款，共貸款80萬元，扣除後投資款後\n    ，約剩50幾萬元在戶頭裡，未○○要我多貸些，用剩餘的錢\n    來扣本息，我自己也有動用過部分款項，當時未○○沒有說\n    要與我交往等語（警卷(一)第317 至319 頁、原審二卷第155\n    至162 頁）。\n (2)證人甲ｊ○證稱：91年9 月在溫馨婚友社認識史恆華，她對\n    我推銷海閣林公司的股份，說她哥哥是海閣林公司的主管，\n    她邀我去高雄市○○路的海閣林公司瞭解營運狀況，還播放\n    DVD 簡介要把綠島變成觀光勝地，她說如生活想要好一點，\n    就要有良好的投資理財觀念，我沒想要追求她，她當時也沒\n    說要與我交往，也沒有說不投資就不跟我交朋友，從她介紹\n    投資案到我決定投資的過程間隔大概3 、4 個月，經過評估\n    後，我才決定要投資3 單位共40萬5 千元，因我身上現金不\n    夠，一部分資金是向銀行貸款等語（警卷(一)第323 至325 頁\n    、原審二卷第163 至169 頁）。\n (3)證人ｔ○○證稱：94年2 、3 月時，去「合緣婚友社」認識\n    未○○，她介紹我投資海閣林公司綠島飯店開發案，跟我說\n    如將來要在一起，要有良好的投資理財觀，我自己決定投資\n    10單位共135 萬元，資金是未○○幫我貸款，未○○有告訴\n    我將於94年7 月試賣，10月正式營運，我於投資後有與朋友\n    到綠島看過工地，當時正在施工當中等語（警卷(一)第328 至\n    330 頁、原審二卷第170 至180 頁）。\n (4)證人吳永成（原名吳宣昌）證稱：92年12月在「溫馨婚友社\n    」認識未○○，她鼓吹我投資海閣林公司綠島飯店開發案，\n    她沒有承諾會跟我結婚或進一步的發展，最後是我與她一起\n    決定投資金額，共投資10單位合計135 萬元，並由她幫我處\n    理貸款事項，我有將存摺、印章交給她處理等語（警卷(一)第\n    341 至343 頁、原審二卷第189 至197 頁）。\n (5)證人Ｏ○○證稱：92年11月在「溫馨婚友社」認識未○○，\n    她鼓吹我投資海閣林公司的綠島飯店開發案，告訴我綠島開\n    發案將是綠島第一家五星級大飯店，前景看好，一定可賺錢\n    ，有多少股份就有多少紅利，沒告訴我可能會賠錢，當時投\n    資2 單位共27萬元，資金來源是貸款，當時有說開發案尚未\n    取得台東縣政府核准，但要先建設，我於投資前有先去海閣\n    林公司看過模型，之後有去綠島看工地，第1 次去現場看時\n    是空地，大概隔1 年後，第2 次再去看時，已經是蓋到5 樓\n    的空屋，就我當時的認知，投資風險是一定有的，現在的投\n    資又不是一定會賺錢等語（警卷(一)第348 至350 頁、原審二\n    卷第180 至189 頁）。\n (6)證人ｗ○○證稱：92年1 月時，經朋友介紹認識陳怡文跟午\n    ○○（原名史雅茜），不斷向我遊說公司的投資方案，但他\n    們沒有跟我說不投資海閣林公司就不跟我作朋友，他們跟我\n    介紹投資案約1 個月後，我決定投資4 個單位共計54萬元，\n    就我認知中，沒有何種投資是百分之百會賺錢，而沒有風險\n    ，認為被騙是那時電視和新聞都有報導等語（警卷(一)第359\n    至361 頁、原審二卷第227 至232 頁）。\n (7)證人乙ｒ○證稱：92年在交友中心認識史雅茜，她對我推銷\n    海閣林公司綠島飯店開發案，我拿錢投資是因我想追求她，\n    也想做投資多賺點錢，她沒說如果我不投資，就不跟我做朋\n    友，她有向我解說投資內容，我用貸款作為投資的資金來源\n    ，我買2 個單位共27萬元，當時史雅茜有跟我說明投資金額\n    的紅利算法，於飯店營利後賺錢的情況下會發紅利，我是後\n    來看到報紙才覺得被騙，但我的認知裡，沒有投資是百分之\n    百會賺錢而絕無風險等語（警卷(一)第368 至370 頁、原審二\n    卷第233 至240 頁）。\n (8)證人黃○○證稱：93年在合欣婚友社認識史雅茜，她沒有要\n    求我投資，當時她要去海閣林公司簽約要我陪她去，幫她看\n    契約內容，之後閒聊時，她問我是否要投資，我當時想賺多\n    一點錢，所以投資3 單位共40萬5 千元，並以貸款取得投資\n    的資金，史雅茜有說飯店已經動工，並說公司有網站，上面\n    有資料及工程進度，我上網查看有一些主體結構正在蓋，我\n    認為沒有哪種投資是完全零風險，但她也沒說這件投資案是\n    有風險的，報紙刊登後，資料傳到我營區，長官說我非法投\n    資，我才認定本件投資案是場騙局（警卷(一)第383 至385 頁\n    、原審二卷第245 至251 頁）。\n (9)證人乙Ｌ○證稱：93年間在「和信婚友社」認識史雅茜，她\n    跟我說投資海閣林公司綠島開發案，如飯店正常營運有賺錢\n    時，每個單位可獲利8 千元左右，當時想賺錢，投資15單位\n    共計202 萬5 千元，我以貸款取得投資的資金，我決定投資\n    15個單位，是史雅茜跟我說能貸到多少錢就投資多少單位，\n    她沒說我不投資就不再與我聯絡等語（警卷(一)第393 至397\n    頁、原審二卷第256 至260 頁）。\n(10)證人甲申○證稱：93年在「溫馨婚友社」認識Ｃ○○，說將\n    來要在一起，我要有良好的投資理財觀念，她介紹海閣林在\n    綠島蓋度假飯店讓我知悉，我本來不想投資，她表現出不高\n    興的態度，我與她溝通後，決定投資9 個單位，後來投資10\n    單位135 萬元，最後1 個單位是跟劉佩妤買的，劉佩妤也是\n    在「溫馨婚友社」認識的，他們都沒有說不投資就不跟我往\n    來，投資的金額，部分是貸款、部分是現金，Ｃ○○陪我到\n    海閣林公司簽約前，有有仔細看過合約內容，她有跟我講投\n    資後如何分紅、何時開始獲利回收，但沒說明投資案可能會\n    賠錢，也沒分析投資案的風險，只說是不錯的投資案，投資\n    後每年可分到蠻多紅利，從Ｃ○○介紹投資到我正式簽約，\n    前後約2 、3 個月，我當時的認知沒有何種投資是完全是零\n    風險的，是新聞報導後，我才感覺被騙等語（警卷(一)第430\n    至432 頁、原審三卷第75至87頁）。\n(11)證人甲ｈ○證稱：92年在「蕙萊婚友社」認識Ｃ○○，她在\n    海閣林公司上班，說他親戚有在海閣林公司上班或投資，她\n    要我投資海閣林公司，說該投資案是溫泉休閒中心，有高獲\n    利，1 個單位13萬5 千元，我購買7 個單位合計94萬5 千元\n    ，她帶我去公司，有拿出綠島建設藍圖給我看，當時我是看\n    設計圖判斷才決定投資，我拿扣繳憑單等資料給Ｃ○○向萬\n    泰等3 家銀行辦貸款，貸款金額合計166 萬元，辦好後她帶\n    我到銀行開戶領錢，交付投資款後，我還是能順利聯絡到Ｃ\n    ○○，本件我看蘋果日報才知道這是詐騙集團，我不知道海\n    閣林公司在綠島的開發案，已經取得旅館的使用執照等語（\n    警卷(一)第435 至437 頁、原審三卷第88至94頁）。\n(12)證人乙ｉ○證稱：93年在「欣緣婚友社」認識Ｃ○○，當時\n    投資理財是想讓家人過得更好一點，所以投資海閣林公司的\n    綠島飯店開發案，我以現金投資1 單位13萬5 千元，我忘記\n    Ｃ○○或海閣林公司有無跟我說明投資案有可能會賠錢或獲\n    利不低，海閣林公司好像有跟我和解，本件我不追究了等語\n    （警卷(一)第452 至454 頁、原審三卷第94至96頁）。\n 3、海閣林公司業務員於行銷過程中，縱未向投資人告知每賣出\n    1 單位（13萬5 千元），業務員（沒有底薪）可抽取獎金（\n    專員為9 千至1 萬元不等，主任為1 萬3 千元），另上開公\n    司總經理、協理、經理，依階級可分別抽取3 千元至2 萬3\n    千元不等獎金之情，惟本件被告等人是否成立被訴常業詐欺\n    犯行，係以投資人於海閣林公司（或翻天創新公司）簽訂上\n    開合夥預定契約書時，被告等人有無施用詐術為判斷基準，\n    至於行銷獎金如何分配抽取及業務員與公司間薪資酬勞之內\n    部關係，以客觀社會常情，一般業務員在外推銷公司產品（\n    例如房屋、汽車、保險、信用卡、美容商品等），亦少有向\n    客戶說明業務員如何抽佣，分配獎金等情，無從僅以業務員\n    抽取獎金偏高，遽認被告等人即有不法詐欺之犯意與犯行，\n    且如上開被害人之證述，被害人訂約投資時，均已考量相關\n    之投資因素（如自身經濟能力、決定貸款額度、或曾到綠島\n    查看工程進度、或知悉本件仍有投資風險存在等），足徵被\n    害人均係出於自由意志而決定投資購買，並非陷於錯誤所致\n    。\n(三)、公訴意旨另以海閣林休閒渡假酒店，至今仍未營運，而認投\n    資之被害人確屬受騙等情。然上開新（舊）合夥預定契約書\n    第6 條固載上開酒店須於93年底公告正式營運等情，惟被告\n    戊○○於92年8 月間在綠島購得上開土地後，即委請蔡國勇\n    建築師規劃設計，於93年4 月19日由銘泉營造公司施工，並\n    於94年12月20日完工等情（如上所述），又上開工程略有遲\n    誤之原因，亦據證人即銘泉營造公司股東賴振東於警詢陳明\n    ：本件營造工程包括結構工程、裝修工程及水電工程等3 項\n    ，原本預計在94年8 月底以前完工，因離島天氣不穩定、運\n    輸補給不方便，且綠島工人不容易掌握等因素，才造成本件\n    工程遲誤（警卷(一)第273 頁），且於95年2 月10日取得上開\n    集合住宅使用執照，並據臺東縣政府於96年7 月26日准將上\n    開集合住宅變更為旅館用途等情（如上所述），復參以上開\n    酒店施工期間（93年4 月19日施工起至94年12月20日完工）\n    ，因海閣林公司於94年6 月8 日遭警搜索，並偵辦被告等人\n    及約談投資人，經媒體報導後致使原投資人紛紛退股，其他\n    民眾亦不敢冒然進行投資，造成海閣林公司資金不足，無法\n    繼續進行上開酒店裝潢及其他準備營運事項，導致無從營運\n    之情。是此部分亦難僅以上開酒店遲未營運一節，遽認被告\n    等人即有詐騙意圖。\n(四)、公訴意旨復以截至94年6 月8 日經警查獲，被害人1,336 人\n    投資3,654 個單位，查出被害人共計196 人，詐得總金額總\n    計4 億9329萬元；又投資人繳交款項未依實際收支情形確實\n    作帳，除扣掉管銷及上開業務獎金之外，餘均流入被告戊○\n    ○私人帳戶內，且海閣林公司辦公處所之房地產亦登記被告\n    戊○○名下，而認有詐騙情事。惟：\n 1、本件尚有1 千餘名投資人均未出面向檢、警機關提出告訴，\n    或以證人身分說明本件被騙之經過情形為何？起訴意旨僅憑\n    扣得之合夥預定契約書，遽認受騙被害人高達1,336 人，尚\n    乏依據。又被告戊○○等人如於收受投資款時，即自始有意\n    詐騙，何於偵、審期間仍持續進行上開酒店之興建事宜，至\n    終取得旅館之使用執照。另海閣林公司於案發後，亦與被害\n    人吳宣昌等33人陸續達成和解，並同意被害人退夥等情，有\n    卷附和解名單、刑事撤回告訴狀及和解退夥切結書在卷可參\n    （原審一卷第184 至202 頁、原審四卷第293 至297 頁）。\n    益證被告等人確有與投資人辦理退夥之誠意。\n 2、被告戊○○雖承募得投資金額計約4 億8 千多萬，然於91年\n    6 月24日起至92年3 月5 日間止，即將募得投資款項7, 200\n    多萬元匯至黃復杰所指定之帳戶內，供黃復杰提領使用（即\n    上開另案共同業務侵占部分），又購地資金亦投入約3,500\n    萬元，另興建上開酒店之設計及工程費用，亦支出達約9,70\n    0 萬元；而依海閣林公司抽取獎金之計算，發放業務獎金約\n    計1 億8 千萬元；另依卷附海閣林公司提出該公司歷年之會\n    計科目明細表、總分類帳、損益表觀之，購買公司資產約花\n    費2,000 萬元、公司內勤職員薪資已發放約1,500 萬元、公\n    司水電及租金等開銷約3,500 萬元；又戊○○前於92年3 月\n    間遭歹徒強押，而由海閣林公司支付650 萬贖款等情，亦有\n    臺灣高雄地方法院檢察署92年度偵字15924 號起訴書及原審\n    法院93年度重訴字第121 號判決書在卷可參。則被告戊○○\n    所為上開支付款項總額已達4 億6 千多萬元。此外，衡諸客\n    觀常情，於上開酒店購地、興建、申請相關執照等數年過程\n    中，定尚有其他支出而無單據或發票證明等相關之公關、交\n    際費用等，是公訴人起訴指稱本件投資人繳交款項後，扣除\n    管銷及上開業務獎金之外，均流入被告戊○○私人帳戶等情\n    ，尚與上開事證未合。至於公訴意旨所稱「投資人繳交款項\n    未經合格之會計師依實際收支情形確實作帳；海閣林公司辦\n    公處所之房地產亦登記被告戊○○名下」等情，係屬被告戊\n    ○○於收受投資款後所為之帳務管理是否確實，有無挪用海\n    閣林公司款項，而與本件起訴意旨所指之常業詐欺取財犯行\n    無涉。且亦尚乏其他積極證據佐認被告戊○○是否涉及未經\n    起訴之其他罪嫌部分，更無從以此等情狀，據以推論被告等\n    人於向本件被害人收受投資款之初，即有何基於詐欺取財之\n    不法犯意。\n六、綜上所述，本件在偏遠離島地區（綠島）投資合夥經營上開\n    酒店，其投資態樣本具有不確定性或交易風險，例如覓尋土\n    地困難、核發建照不易、施工進度遲誤、旅館執照延宕等因\n    素，而被告等人招攬投資之上開酒店，固未能依約如期營運\n    ，然此屬民事投資合夥關係衍生之債權債務糾紛，不能僅以\n    事後上開酒店未能營運，推論被告等44人自始即具有常業詐\n    欺之犯罪意圖。公訴人起訴所舉上開證據，均不足採為認定\n    被告等44人有修正前刑法第340 條常業詐欺犯行之積極證明\n    。此外，復查無其他積極證據足資證明被告等44人有何被訴\n    常業詐欺犯行，被告等44人被訴此罪，均屬不能證明，原審\n    因而為被告等44人均無罪之諭知，核無違誤。\n七、原審公訴人所提上訴意旨，猶執起訴所據各節，指摘原判決\n    不當，為無理由（如下所述），應予駁回。\n(一)、上訴理由略以：\n 1、原審法院判決理由一方面認定「被害人均係合夥投資關係」\n    ，另一方面又認定「業務員於行銷過程中，每賣出1 單位（\n    13萬5 千元），業務員（沒有底薪）可抽取獎金（專員為9\n    千至1 萬元不等，主任為1 萬3 千元），另上開公司總經理\n    、協理、經理，依階級可分別抽取3 千元至2 萬3 千元不等\n    獎金之情事」之理由，試想豈有公司「合夥」人出資金額先\n    由公司各層級主管、業務員層層抽成的道理？且發放給業務\n    員獎金竟至少高達新台幣（下同）1 億8 千萬元以上，顯見\n    本案渠等被告係以簽訂「投資契約書」之脫法方式，用以「\n    詐欺」廣大投資人使之「陷於錯誤」而將大筆金錢付出，供\n    被告戊○○等44人分層瓜分高達1 億8 千餘萬元之吸金款項\n    。渠等無異係以「多層次傳銷」變種手法「收受投資」，「\n    使加入股東或其他名義」「向多數人或不特定人收受款項或\n    吸收資金」，而與民法「合夥」關係顯然不同。原審未予查\n    明，混淆「合夥」與「詐欺吸金」之界限，判決所載理由顯\n    然矛盾，且與社會通念嚴重不符，難稱妥當！況被告等人以\n    「高額紅利」及「迅速還本」為號召之吸收資金行為，顯係\n    「約定與本金顯不相當之紅利、利息、股息或其他報酬」情\n    形，尚有違反銀行法第125 條、第29條、第29條之1 可能，\n    亦經原審法院審理時當庭諭知上開罪名，詎原審判決理由中\n    未見說明有關被告等人違反前揭銀行法罪名部分，判決所載\n    理由顯有疏漏！\n 2、原審判決將本件募得投資金額共計4 億8 千多萬用途予以切\n    割，顯然混淆一般公司「合理」支出款項，及「吸金公司」\n    支付予吸金業務員獎金之界限。蓋一般「渡假飯店開發公司\n    」主要業務係在於「開發土地」「興建飯店」，公司職員之\n    聘請主要工作亦應著眼於此。詎本案海閣林公司之員工至少\n    高達43人以上之主要工作內容，卻是「向多數人或不特定人\n    收受款項或吸收資金」且「從中分層抽取獎金」，所謂「內\n    勤職員」主要工作亦在管理「業務員」吸收資金事項，共支\n    出高達1 億9 千5 百萬餘元款項，佔被害人受詐騙之4 億8\n    千萬元款項至少5 分之2 ，與公司「合夥」通念顯然不同！\n    況「購買公司資產約花費2,000 萬元」，海閣林公司位於高\n    雄市之房地產均登記在被告戊○○名下；「綠島購得土地，\n    部分土地登記在戊○○名下」，均與合法經營公司登記資產\n    方式有違。\n 3、本案於95年5 月24日經本署起訴，被告等人為脫免刑責，只\n    得謀求「取得旅館使用執照」以求解套，與「積極營運酒店\n    情形」顯屬有間，原審法院未親自至綠島地區實地勘驗酒店\n    之建築規格、設計、內部裝潢是否具備五星級飯店等級規格\n    ，實際有無經營五星級飯店可能，徒以被告夥同之建築師所\n    提出文件，逕認「戊○○顯有積極營運上開酒店企圖」，罔\n    顧戊○○以興建旅館代替五星級飯店之情形，論理稍嫌速斷\n    ！況被告戊○○為脫免刑責，僅願意以被害人受詐騙投資款\n    項一成至三成予以和解，在被害人1,336 人中亦僅與被害人\n    吳宣昌等33人達成和解，和解金額僅1 千餘萬元，與被害人\n    總受詐騙金額4 億8 千餘萬元相比，無異杯水車薪，原審法\n    院據之認為「被告等人顯有進行退夥誠意」，亦難稱妥當。\n 4、況據被告戊○○當庭供承：「顏銘震他是台中地區的代理商\n    ；甲ｄ○算是公司的高階主管。」「公司協理、經理、主任\n    或襄理、專員或業務員只有一個共同身分即業務員，因為經\n    理也要做業務，他們只是職稱不同，但都要做業務」「當時\n    海閣林公司負責財務的人是乙丙○」等語，參以被告乙ｆ○\n    等人另案（臺灣高雄地方法院97年度重訴字第76號）涉及「\n    全方位停車場」詐欺吸金案件，益徵渠等為常業詐欺慣犯，\n    經常變換詐欺手法用以吸金，而海閣林公司大部分幹部、職\n    員主要工作內容即為「吸金」，甚至在高雄、台中地區亦設\n    立分公司用以吸金，原審法院均未審酌及此，遽為無罪諭知\n    ，顯然難稱妥當。又被告甲辛○當庭供承：「公司有提供很\n    多方式讓業務選擇去找客戶」「包含婚友社、陌生開發或朋\n    友之間等」等語，參以被告乙黃○供承：「公司叫我們去婚\n    友社找客戶」等語；被告午○○供承：「到婚友社找客戶是\n    公司建議的方案」等情，均足徵海閣林公司訓練大批員工到\n    婚友社招攬客戶，藉口交友為幌子，以高額紅利及迅速還本\n    為號召，並隱瞞「旅館未取得建築執照及使用執照」之現況\n    ，大量吸收現、退役軍人資金，甚至積極主動要求被害人向\n    銀行信用貸款高額款項以「吸收資金」。原審法院以「被害\n    人訂約參與投資，均係充分考量並盤算相關條件，非陷於錯\n    誤所致」「查扣之書面資料，主要皆是傳授業務員招攬客戶\n    之技巧，並未提及如何使用詐術欺騙投資人，亦未刻意安排\n    業務員至婚友社或上網尋覓投資對象」為由，諭知被告等人\n    均無罪，除與被告供承明顯不符合外，更嚴重違背社會對於\n    正常投資之通念，混淆「吸金」與「投資」界限。\n 5、據證人ｒ○○證述：「當時未○○與海閣林公司的人並無告\n    知我，該投資飯店的案件在台東縣政府當時並未經核可」「\n    她只說當時只缺資金」「海閣林公司相關人並無完全告知我\n    該投資案的風險及內容」等語；證人甲ｊ○證稱：「當時未\n    ○○跟海閣林公司相關人推銷綠島投資案時，完全沒有告知\n    海閣林公司當時尚未取得台東縣政府核准設立旅館」「若當\n    時知道海閣林公司並未取得台東縣政府的核准，我不願意拿\n    錢出來投資」「未○○在投資時沒有說本件投資他可以抽佣\n    」「當初未○○邀請我投資時說飯店兩、三年後蓋好，可以\n    分得錢」「每年紅利可以分」等語；證人ｔ○○證稱：「當\n    時未○○與我交往虛虛實實」「當時未○○跟我說如將來要\n    在一起要有好的投資觀，所以才要求我投資綠島開發案」「\n    （貸款）錢核撥後未○○就不跟我聯絡」「當時未○○及海\n    閣林公司人員並無跟我說明本案綠島開發案尚未經台東縣政\n    府核准」「若當時知悉本情狀我不可能還願意投資」「就女\n    朋友的定義，當時未○○算是在交往中」「我有明確跟她說\n    我喜歡她」「她有說過如果不投資大家就不用往來了」「是\n    因為她這樣講我才投資」「純粹都是貸款」「未○○鼓吹投\n    資時，並無跟我說本投資案她可以抽佣」「未○○說負責人\n    是她親戚」等語，並當庭指認在庭被告戊○○說未○○曾說\n    那是她哥哥；證人Ｏ○○證稱：「未○○態度很明顯，如果\n    我不投資本開發案就不往來」「她說很穩，但賺多賺少不一\n    定」等語；證人吳永成（原名吳宣昌）證稱：「當時未○○\n    幫我處理貸款事項」「我覺得被騙」「海閣林公司人員好像\n    說一股可以分多少，但沒具體說明，當時說一股可分得近萬\n    元。」「有說過一定賺，不會賠錢，蓋好後還可以轉賣」「\n    貸款是我與未○○一起決定」「講到這個是說為了我們以後\n    ，所以我才尊重她」等語，均足徵被告未○○有透過婚友社\n    管道，陸續認識7名被害人，並「以交往為藉口，隱瞞海閣\n    林公司真實狀況，以高額紅利為號召」誘騙被害人以吸收資\n    金之情形。\n 6、據證人ｗ○○證述：「我拿錢出來投資後陳怡文和午○○就\n    不和我聯絡」「若知道該投資案沒有經過政府許可，我不願\n    意投資」「當時被告等人沒有跟我說該飯店投資案有賠錢可\n    能」「沒有跟我分析該投資案的風險」等語；證人乙ｒ○證\n    稱：「當時想追求她，也做投資多賺點錢，才拿錢跟被告史\n    雅茜投資海閣林公司的綠島開發案」「資金來源係貸款」「\n    當時史雅茜或海閣林公司的人有跟我說明投資錢的紅利之算\n    法」「如果我知道當時海閣林公司的綠島開發案沒有經過政\n    府的許可，我不願意拿錢出來投資」等語；證人Ｙ○○證稱\n    ：「貸款是史雅茜提議」「拿錢出來投資後史雅茜就不和我\n    聯絡」「當時史雅茜及海閣林公司的人只有說明當年度就可\n    以建造完畢就可以營運可以發紅利」等語；證人黃○○證稱\n    ：「當時不知道史雅茜在我的投資案內可以抽成，是後來本\n    件事情有風聲出來時，我有去問，該婚友社告訴我史雅茜有\n    跟會員推銷東西，我以為是公司在亂講話有向她求證，她跟\n    我說沒有。」「當初說要蓋五星級飯店，現在只蓋一般飯店\n    」等語；證人乙Ｕ○證稱：「若我知道投資當時海閣林公司\n    尚未取得綠島開發案正式許可，我不會願意投資」「是史雅\n    茜找我投資」等語；證人乙Ｌ○證稱：「史雅茜跟我說投資\n    海閣林公司綠島開發案後每個單位都可以獲利八千元左右」\n    等語；證人Ｒ○○證稱：「當時史雅茜及海閣林公司人員鼓\n    吹我投資綠島開發案，標榜是綠島第一家五星級酒店」「是\n    史雅茜提議向銀行貸款來投資」等語；證人Ｕ○○證稱：「\n    她當時好像叫史雅玲（音譯）」「當時在交友社認識她，她\n    說要跟我交往，她說為了爾後的生活或退休後的生活要投資\n    」「史雅玲就是在場之午○○」「說投資13.5萬元，時間到\n    時公司會以50萬元買回股權」「她說會賺錢」等語；證人乙\n    己○證稱：「史雅茜鼓吹我去投資本件投資案」「和我接觸\n    時是用假名史雅玲」「她說如果我與你交往，未來做何打算\n    」「當時午○○是說不投資就不往來」「因為她這樣講我才\n    投資」「94年8 月間開始不接我的電話」「午○○或海閣林\n    公司的人有跟我說投資一定會分紅」等語；證人甲申○證稱\n    ：「我當時職業為軍人」「Ｃ○○有跟我說將來在一起，要\n    有良好的投資理財觀念」「本來我不想投資，她表現出不是\n    很高興的態度，我與她溝通幾次後，就先投資兩個單位，錢\n    是貸款取得後投資，陸陸續續在其身上投資9 個單位，一個\n    單位13.5萬元」「Ｃ○○好像有說她的親戚在海閣林公司上\n    班」「當時Ｃ○○跟海閣林公司人員，沒有跟我說綠島開發\n    案沒有經過台東縣政府核發執照」「Ｃ○○當時沒有無跟我\n    明白說明該投資案有可能賠錢」「印象中，Ｃ○○跟我說紅\n    利的年息蠻高的」「Ｃ○○說這個投資還不錯的投資案，我\n    投資後，每年可以分到蠻多紅利」「她沒有明講可抽成，她\n    說她不是公司的人，只介紹朋友去。」「如果我知道Ｃ○○\n    跟很多婚友社會員鼓吹投資的話，我應該不會去投資」「後\n    來我得知軍中學長也是Ｃ○○介紹去投資，也是在溫馨婚友\n    社認識，是軍中政三監察官約談後得知」「不知道本件投資\n    案劉佩妤可以抽成」「在決定投資之前，我沒有無仔細評估\n    過本投資案」「斷斷續續買到九個單位後，約Ｃ○○就比較\n    約不出來，打電話給她不是沒有接電話，就是口氣不好」等\n    語；證人甲ｈ○證稱：「當時不知道本件投資案，Ｃ○○可\n    以中從抽成」「我拿扣繳憑單、身分證正本、還有印章等交\n    給Ｃ○○，她拿去辦理貸款，辦好後，她帶我到銀行開戶領\n    錢」「被告Ｃ○○跟海閣林公司人員，有跟我說該投資案有\n    高獲利」「剛開始說我買七個單位第一年可能有幾十萬元獲\n    利，一個單位一年只有幾萬元收入」「她說一定獲利」「如\n    果沒有這樣的獲利情形，我不會投資」「都是Ｃ○○講，如\n    果我投資的話會有額外收入，生活會過得比較好」「Ｃ○○\n    有跟我說如果不投資就不跟我聯絡了」等語；證人乙ｉ○證\n    稱：「我是職業軍人」「是Ｃ○○介紹我投資該開發案」等\n    語；證人乙ｕ○證稱：「詐騙我的人名字叫林麗雯，當時她\n    是我女友，後來離開了，林芷萱不是她的真實姓名，騙我時\n    叫林麗雯，進海閣林公司工作後才改名林芷萱」等語；證人\n    乙Ｙ○證稱：「如果我知道當時海閣林公司就綠島投資興建\n    五星級休閒渡假大飯店尚未取得台東縣政府核發，我不會還\n    願意拿94.5萬元出來投資」等語；證人甲己○證稱：「過了\n    一年後我打電話到公司，才發現公司不見了，始知被騙」「\n    若我知道當時海閣林公司當時尚未取得旅館建築執照，我不\n    會會投資」等語；證人乙ｗ○證稱：「貸款核發下來後海閣\n    林公司有兩個業務員自行將款項提領出來」「當時在陽信銀\n    行辦理貸款完畢後，存摺、印章他們取走」等語，均足徵海\n    閣林公司所屬「辣妹兵團成員」利用婚友社機會認識現、退\n    役軍人用以吸金，或以假名交往，或刻意隱匿海閣林公司綠\n    島投資案之真實狀況，或藉口高額紅利吸引投資，並非單純\n    「業務員為求績效所為之個人行為」，亦非「充其量僅係吸\n    引異性客戶之行銷手段」，而係海閣林公司用以吸金之普遍\n    手段，光是在婚友社之受害人即高達數百人。\n 7、被告戊○○為公司首腦；被告乙丙○為該公司財務；被告甲\n    ｕ○、顏銘震、甲ｄ○、甲辛○、乙ｈ○、乙地○、申○○\n    、乙Ｆ○、吳俊德、甲Ｂ○、乙Ｒ○為該公司之核心幹部；\n    另外被告未○○詐騙人數7 人、午○○詐騙人數12 人 、Ｃ\n    ○○詐騙人數3 人、Ｉ○○詐騙人數6 人、Ｊ○○詐騙人數\n    4 人、Ｌ○○詐騙人數6 人、Ｍ○○詐騙人數5人 、Ｎ○○\n    詐騙人數3 人、Ｘ○○詐騙人數5 人、李瓊鳳詐騙人數1 人\n    、ｈ○○詐騙人數10人、林詩怡詐騙人數1人 、甲子○詐騙\n    人數5 人、甲Ｉ○詐騙人數1 人、甲Ｊ○詐騙人數4 人、甲\n    Ｐ○詐騙人數4 人、甲ｆ○詐騙人數3人 、甲Ｒ○詐騙人數\n    3 人、甲ｂ○詐騙人數4 人、甲ｄ○詐騙人數1 人、甲ｍ○\n    詐騙人數9 人、甲ｓ○詐騙人數2人 、甲ｖ○詐騙人數9 人\n    、甲ｗ○詐騙人數2 人、黃彩惠詐騙人數2 人、乙Ｃ○詐騙\n    人數1 人、乙黃○詐騙人數7人 、乙Ｄ○○詐騙人數4 人，\n    乙Ｇ○詐騙人數1 人、蔡幸（）（原名蔡宜庭）詐騙人數\n    4 人、乙Ｘ○詐騙人數1 人、乙ｋ○詐騙人數2 人，均惡性\n    非輕。且被告及其辯護人均對被害人於警詢中之證述不爭執\n    證據能力，詎原審法院對被害人於警詢指證予以忽略。\n(二)、經查：\n 1、本件上訴理由第1 、2 項雖以「豈有公司合夥人出資金額先\n    由公司各層級主管、業務員層層抽成的道理？且發放給業務\n    員獎金竟高達1 億8 千萬元以上」、「將本件募得投資金額\n    共計4 億8 千多萬用途予以切割」，而認被告等人係以簽訂\n    「投資契約書」之脫法方式，詐欺投資人使之陷於錯誤而付\n    出金錢，被告等人係以「多層次傳銷」變種手法「收受投資\n    」，而與民法「合夥」關係顯然不同。又原判決亦混淆一般\n    公司「合理」支出款項，及「吸金公司」支付予吸金業務員\n    獎金之界限云云，然：\n (1)投資合夥經營事業本須有一定之業務支出或人事成本等開銷\n    ，而業務獎金抽成多寡，繫於投資人與公司間之契約或協議\n    內容，本件被告等人係被訴常業詐欺罪嫌，亦即被告等人成\n    罪與否，自應審究投資人（即公訴人所指之被害人）與海閣\n    林公司簽訂上開合夥預定契約書時，被告等人有無施用詐術\n    之舉，而非純以該公司發放業務獎金多寡或如何分配使用投\n    資款項等情為斷。至於投資人倘對被告等人執行合夥關係之\n    履約情形有所疑義，亦屬雙方如何循民事程序予以處理，原\n    審公訴人提起上訴據此主張被告等人於向投資人收受投資款\n    時，即有詐欺之不法意圖等語，尚難成立。\n (2)本件投資人所簽訂之投資契約書，係屬經合格律師製作之契\n    約書（如下所述），亦難認被告等人有何以簽訂「投資契約\n    書」之脫法方式，詐欺投資人使之陷於錯誤而付出金錢之事\n    實。何況，海閣林公司之登記股東5 人，除被告戊○○外，\n    則為被告甲ｄ○、甲辛○、申○○、乙ｈ○等4 人，而被告\n    戊○○係屬最大股東（佔9 成以上），此有卷附之海閣林公\n    司股東繳款明細表、股東名簿足佐（見警卷(四)第1601、1602\n    頁），復參以被告戊○○所供「公司協理、經理或業務員，\n    只有一個共同身分即業務員」等情，則身兼股東之被告甲ｄ\n    ○、甲辛○、申○○、乙ｈ○等4 人雖屬公司之協理、經理\n    身分，但仍與其他共同被告等人之業務員身分無異，是除被\n    告戊○○外之其餘共同被告43人，均屬本於海閣林公司之業\n    務內容及被告戊○○之指示，以經合格律師製作之契約書從\n    事招攬投資人，亦難認本件除被告戊○○外之其餘共同被告\n    43人有何被訴共同常業詐欺之犯意存在。\n 2、本件上訴理由第1 、2 項另主張「被告等人以高額紅利及迅\n    速還本為號召之吸收資金行為，顯係約定與本金顯不相當之\n    紅利、利息、股息或其他報酬，有違反銀行法第125 條、第\n    29條、第29條之1 可能」、「海閣林公司位於高雄市之房地\n    產均登記在被告戊○○名下；綠島購得土地，部分土地登記\n    在戊○○名下，均與合法經營公司登記資產方式有違」等情\n    ，然本件投資人與海閣林公司（或翻天創新公司）簽訂上開\n    合夥預定契約書或收據之內容，並無約定有何「高額紅利」\n    及「迅速還本」等情，且無其他證據足以證明被告等人與投\n    資人如何約定相當利率之紅利或報酬之事實，自難證明被告\n    等人有何觸犯上開銀行法罪嫌之情；又上開契約書係由律師\n    草擬一節，已據證人即契約見證律師單文程於偵查中具結證\n    實在卷（見偵七卷第33頁），則被告等人以經合格律師製作\n    之上開契約書與投資人簽訂而收受投資款，亦難認被告等人\n    有何違反銀行法之犯意。至於上開公司房產、綠島土地如何\n    登記等情，亦屬被告等人執行合夥關係之履約糾葛，應由雙\n    方循民事程序確認解決。原審公訴人提起上訴執此主張，亦\n    非可採。\n 3、本件上訴理由第3 項固陳「被告等人經起訴後為脫免刑責，\n    只得謀求取得旅館使用執照以求解套」、「原審法院未親自\n    至綠島地區實地勘驗酒店之建築規格、設計、內部裝潢是否\n    具備五星級飯店等級規格，實際有無經營五星級飯店可能」\n    、「被告戊○○為脫免刑責，僅以投資款項一至三成與33名\n    被害人和解」等情，惟被告戊○○等人於綠島購地、興建旅\n    館欲經營上開酒店之事實，業經原審認定如上，經核與卷證\n    資料並無相違，則被告等人按照工程進度，依序申辦取得旅\n    館使用執照等過程，應合於常情事理，無從僅以被告等人曾\n    遭起訴上開罪嫌，遽以推論臆測即屬「脫免刑責以求解套」\n    。又上開酒店之興建規模，已有卷附之上開酒店新建工程申\n    請建築執照流程說明相關資料、建造執照、施工程藍圖、工\n    程合約書、水電工程配置圖、鋼構配置圖、施工圖本、平面\n    配置圖、工程照片、綠島海閣林遊樂業整合性管理系統建議\n    書及餐飲管理系統建議書、使用執照可佐，此部分待證事實\n    已明，則原審未親赴綠島履勘，自無不當。至於該酒店之內\n    部裝潢是否具備五星級飯店等級規格，實際有無經營五星級\n    飯店可能等情，均有賴日後之內部設計、規劃、裝潢及管理\n    ，而此部分營運之延宕因素，業據原審敘明如上，衡諸常情\n    ，並無不合。此外，和解成立與否在於雙方對於退夥金額之\n    認知是否合致，自無必然需以若干成數即能達成和解之情形\n    ，則被告戊○○以投資款項一至三成與33名被害人和解之情\n    ，即屬上開部分投資人對於和解條件之主觀認知，亦難據此\n    而認此屬被告戊○○之「脫免刑責」，從而，此部分上訴主\n    張均無可採。\n 4、本件上訴理由第4 、5 項雖以被告戊○○、甲辛○、午○○\n    等人供詞，及參以被告乙ｆ○等人另案（臺灣高雄地方法院\n    97年度重訴字第76號）涉及「全方位停車場」詐欺吸金案件\n    ，而認被告等人為常業詐欺慣犯，海閣林公司大部分幹部、\n    職員主要工作內容即為「吸金」，且訓練大批員工到婚友社\n    招攬客戶，藉口交友為幌子，吸收現、退役軍人資金等情，\n    然被告乙ｆ○另涉他案部分，係屬其個人另案情形，公訴人\n    起訴既未包含此部分，自難以此另案情形，推論本件其他共\n    同被告之被訴犯行；又被告等人經營上開酒店之合夥事業，\n    於招募合夥資金期間，自然業務主力在於招攬投資人，而擴\n    充行銷人脈以利招攬業務，更屬社會常見之商業推銷，而推\n    銷招攬僅係民事契約要約行為之一部分，至於投資人之承諾\n    成交即簽約與否，則屬投資人之自我判斷範圍，以此部分上\n    訴理由所載之上開被告供詞內容，無從逕認被告等人即屬「\n    詐欺吸金」而非「投資入夥」。\n 5、本件上訴理由第5 、6 項雖以「證人ｒ○○、甲ｊ○、ｔ○\n    ○、Ｏ○○、吳永成（原名吳宣昌）」等人證詞，而認被告\n    未○○有透過婚友社管道，陸續認識上開被害人，並以「交\n    往為藉口，隱瞞海閣林公司真實狀況，以高額紅利為號召誘\n    騙被害人以吸收資金等情，及以「證人ｗ○○、乙ｒ○、Ｙ\n    ○○、黃○○、乙Ｕ○、乙Ｌ○、Ｒ○○、Ｕ○○、乙己○\n    、甲申○、甲ｈ○、乙ｉ○、乙ｕ○、乙Ｙ○、甲己○、乙\n    ｗ○」等人證詞，並認海閣林公司所屬「辣妹兵團成員」利\n    用婚友社機會認識現、退役軍人用以吸金，或以假名交往，\n    或刻意隱匿海閣林公司綠島投資案之真實狀況，或藉口高額\n    紅利吸引投資，係海閣林公司用以吸金之普遍手段，光是在\n    婚友社之受害人即高達數百人等情，然原判決就此部分，業\n    已敘明「被告戊○○確實已依上開合夥契約內容，在綠島購\n    地並完成上開渡假酒店之興建；海閣林公司業務員於行銷過\n    程中，並未特別以結婚或交往為藉口，而誘騙投資人參加投\n    資事宜，且投資人於交款前，亦未受業務人員姿色誘惑之影\n    響，縱部分業務員曾向某被害人表示參與投資後，始願意與\n    被害人結婚或繼續交往等語，然此屬業務員為求績效所為之\n    個人行為，僅係吸引異性客戶之行銷手段，難認被告等人即\n    有以業務員欲與客戶結婚或交往為藉口，而誘騙投資人參加\n    投資」等情（如上所述），又上訴意旨所載被害人指稱之業\n    務員即被告未○○、午○○（原名史雅茜）、吳佳潁等人固\n    承其等有透過婚友社管道開發客戶一節，但均否認有以「與\n    被害人交往」為條件誘騙被害人投資，而依上開被害人及卷\n    附之其他投資人之陳述，部分投資人雖有提及公司業務員曾\n    對渠等表示「將來在一起」、「與其交往」、「不投資就不\n    來往」、「投資是為了以後」等語，惟參以當前社會男女交\n    往之情形，雙方對於所謂「交往」、「為以後」等情之認定\n    ，常因個人主觀情感之因素而有異，且是否繼續交往或僅係\n    維持普通朋友之誼，所受影響之因素復屬多元，更何況，被\n    害人於投資時均屬成年且有相當學識、經歷之人，實難僅以\n    公司女業務員於推銷投資時之部分言語，遽認投資人即有因\n    業務員欲與其結婚或交往，而陷於錯誤而遭誘騙投資之情。\n    至於被害人所指之「高額紅利」部分，亦屬投資人得循民事\n    契約關係求償之範疇，無從以此遽認被告等人違法吸金。\n 6、本件上訴理由第7 項雖以本件被害人等均於警詢指證歷歷，\n    且有扣案物證即合夥預定契約書所載事實，自可認被害人數\n    高達1336人等情，然卷附如附表三證據索引「丙」項之人證\n    關於被害人之警、偵陳述部分，均屬渠等如何投資交款等情\n    ，而關於部分被害人指訴有遭業務員以結婚或交往為藉口而\n    遭誘騙投資部分，尚難構成刑法詐欺犯行之要件，業已論述\n    如上，至於扣案物證即合夥預定契約書所載事實，亦僅可認\n    定有此部分契約所載之投資金額，不能據此逕認全屬受騙之\n    被害人數，是此部分上訴主張，亦非可採。\n八、被告午○○（原名史雅茜）、乙Ｉ○（原名蔡宜庭），均經\n    合法傳喚，無正當理由，未於98年12月22日本院審判期日到\n    庭（見本院二卷第99、127 、128 、220 頁之送達證書、刑\n    事報到單），依據刑事訴訟法第371 條規定，不待其陳述，\n    逕行判決。\n據上論斷，應依刑事訴訟法第368 條、第371 條，判決如主文。\n本案經檢察官許美女到庭執行職務。"
  },
  "characters": {
    "judges": [
      "莊崑山",
      "唐照明",
      "張意聰"
    ],
    "prosecutors": [
      "許美女"
    ],
    "lawyers": [
      "歐陽珮",
      "張清富",
      "邱明政",
      "郭家祺"
    ],
    "clerks": [
      "陳金"
    ],
    "plaintiffs": [

    ],
    "defendants": [
      "戊○○",
      "甲ｗ○",
      "ｈ○○",
      "乙丙○"
    ],
    "prosecutor_office": [

    ],
    "creditors": [

    ],
    "debtors": [

    ],
    "judicial_associate_officer": [

    ]
  },
  "adjudged_at": "2010-01-05",
  "created_at": "2016-01-05 15:09:56",
  "updated_at": "2016-01-05 15:09:56"
}