{
  "identify": "KSH-98-上更(二)-190-20100512-1",
  "court": {
    "name": "臺灣高等法院",
    "code": "KSH"
  },
  "division": {
    "name": "刑事",
    "code": "M"
  },
  "year": 98,
  "word": "上更(二)",
  "number": "190",
  "jcheck": "1",
  "reason": "違反毒品危害防制條例",
  "content": "臺灣高等法院高雄分院刑事判決     98年度上更(二)字第190號\n上  訴  人\n即  被  告  甲○○\n選任辯護人  邱基峻律師\n            張宗琦律師\n上列上訴人因違反毒品危害防制條例案件，不服臺灣高雄地方法\n院97年度訴字第1101號中華民國98年7 月9 日第一審判決（起訴\n案號：臺灣高雄地方法院檢察署97年度偵字第7453號），提起上\n訴，本院判決後，經最高法院第2 次發回更審，本院判決如下：\n    主    文\n原判決關於販賣第一級毒品部分撤銷。\n甲○○販賣第一級毒品，累犯，處有期徒刑拾陸年，褫奪公權伍\n年。扣案之行動電話壹具（含門號0000000000號SIM 卡）沒收；\n扣案之販賣第一級毒品所得財物新臺幣玖佰肆拾元沒收，未扣案\n之販賣第一級毒品所得財物新臺幣陸拾元沒收，如全部或一部不\n能沒收時，以其財產抵償之。\n    事    實\n一、甲○○於民國90年2 月間因強盜案件，經臺灣高雄少年法院\n    以89年度少訴字第19號判處有期徒刑4 年6 月確定，於92年\n    5 月2 日因縮短刑期假釋出監，假釋期間並付保護管束，於\n    93年9 月13日縮刑期滿未經撤銷假釋，視為執行完畢；又於\n    94年9 月間因施用毒品案件，經原審以94年度簡字4674號判\n    處有期徒刑4 月確定，於95年5 月23日縮刑期滿執行完畢。\n二、甲○○明知海洛因、甲基安非他命分別係毒品危害防制條例\n    第2 條第2 項第1 款、第2 款所列之第一級、第二級毒品，\n    不得非法持有、轉讓、販賣，且甲基安非他命亦為藥事法所\n    規定之禁藥，因具成癮性、濫用性及對社會危害性，不得轉\n    讓，竟同時基於販賣第一級毒品海洛因以營利之意圖及無償\n    轉讓禁藥（即第二級毒毒品甲基安非他命）之犯意，於97年\n    3 月4 日下午4 時26分、32分、40分許，接聽曾富煌（所涉\n    施用第一級毒品、第二級毒品罪嫌部分，經原審以97年度審\n    訴字第2143號判決分別判處有期徒刑8 月、4 月，應執行有\n    期徒刑10月確定）借用友人鄭淑月（所涉持有第一級毒品罪\n    嫌部分，經原審以97年度審簡字第3305號判決判處有期徒刑\n    4 月確定）所有之門號0000000000號行動電話，撥打至甲○\n    ○持用之門號0000000000號行動電話，曾富煌表明欲向甲○\n    ○購買新臺幣（下同）1,000 元海洛因及500 元甲基安非他\n    命，甲○○則表示願無償提供甲基安非他命給曾富煌施用，\n    其二人於電話中談妥交易1,000 元海洛因及轉讓甲基安非他\n    命後，相約在高雄市○○區○○路上之消防隊前碰面，曾富\n    煌乃騎乘機車搭載鄭淑月前往，雙方於上開消防隊前碰面後\n    ，隨即前往高雄市○○區○○路與加宏路口之「OK便利超商\n    」內，三人假意要購買飲料，由曾富煌交給鄭淑月1,000 元\n    紙鈔1 張，鄭淑月再將該1,000 元紙鈔及其選購之2 罐鋁箔\n    裝飲料交給甲○○，由甲○○至該超商櫃檯處結帳後，即同\n    時將海洛因及甲基安非他命各1 小包黏貼於上開飲料底部，\n    再將該黏有毒品之飲料交給鄭淑月，以此方式販賣海洛因1\n    小包（驗前淨重0.104 公克、驗餘淨重0.096 公克）及轉讓\n    禁藥即甲基安非他命1 小包（驗前淨重0.024 公克、驗餘淨\n    重0.014 公克）予曾富煌，並收取販賣海洛因之價金1,000\n    元得逞。嗣因高雄市政府警察局楠梓分局後勁派出所員警乙\n    ○○、丙○○於當日下午約近5 時許，在高雄市○○區○○\n    路與加宏路口附近見其轄區內之毒品列管人口鄭淑月被曾富\n    煌騎車搭載，乃自後跟監，見鄭淑月與鄭富煌於上開消防隊\n    前停留，約2 分鐘後被告即前往與鄭淑月、曾富煌會合，其\n    三人再一同前往上開超商內，待其等步出「OK便利超商」時\n    ，員警目睹鄭淑月手中握有上開甲○○所交付之2 包毒品及\n    鋁箔裝飲料（即飲料底部與手掌間之空隙有2 包毒品面），\n    而依現行犯規定逮捕鄭淑月，並當場查扣甲○○販賣、轉讓\n    予曾富煌之海洛因及甲基安非他命各1 小包，並自甲○○身\n    上扣得販賣海洛因所得1,000 元購買飲料後所找餘之現金94\n    0 元及甲○○所有供犯罪所用之行動電話1 具（含門號0000\n    000000號SIM 卡），復扣得鄭淑月所有之行動電話1 具（含\n    號0000000000號SIM 卡），始悉上情。\n三、案經高雄市政府警察局楠梓分局移送臺灣高雄地方法院檢察\n    署檢察官偵查起訴。\n    理    由\n壹、證據能力部分：\n一、本件被告之辯護人主張：扣案之2 包毒品係違背法定程序而\n    取得云云（本院卷第77頁）。惟查，高雄市政府警察局楠梓\n    分局後勁派出所員警乙○○、丙○○，於97年3 月4 日下午\n    4 點多至5 時許之某時，在高雄市○○區○○路與加宏路口\n    附近執行便依巡邏勤務時，發現轄區內之毒品列管人口鄭淑\n    月被曾富煌騎車搭載，形跡可疑，乃自後跟監，嗣鄭淑月與\n    鄭富煌於上開消防隊前停留，約2 分鐘後，被告即與鄭淑月\n    、曾富煌會合後，三人則一同進入高雄市○○區○○路與加\n    宏路口之「OK便利超商」內，待其三人步出「OK便利超商」\n    時，因員警看見鄭淑月手中所拿之飲料底部與手掌間之空隙\n    有上開被告交付之2 包毒品，而有持有毒品等犯行，乃依現\n    行犯規定，上前盤查並實施搜索，而查扣該2 包毒品等情，\n    業據證人即查獲之員警丙○○及乙○○於本院證述明確（本\n    院卷第95-100頁），並有扣押筆錄、扣押物品目錄表及高雄\n    市政府警察局楠梓分局刑事案件移送書在卷可參（影一卷第\n    1-2 頁，影二卷第2 、3 頁之背面）。可見員警係在執行便\n    衣巡邏勤務時，遇見轄區毒品列管人口之鄭淑月形跡可疑而\n    自後跟監，嗣發現鄭淑月與被告及曾富煌等人進入「OK便利\n    超商」，於涉出該家超商之際，鄭淑月之手中持有飲料，且\n    該飲料底部有上開海洛因及甲基安非他命，以持有毒品之現\n    行犯加以逮捕，並扣得上開2 包毒品，再執行附帶搜索而扣\n    得其餘之物，核與刑事訴訟法第88條第1 項、第130 條、第\n    133 條第1 項之規定尚無違背，即難認係違法取得證據，員\n    警查獲鄭淑月等及附帶搜索之過程，既無侵犯法律保障基本\n    權或違背法定程式之情事，該取得之證據資料即有證據能力\n    ，得為判決基礎。\n二、本件證人曾富煌、鄭淑月於偵查中具結後向檢察官所為之證\n    述，證人均未曾提及檢察官在偵查中有不法取供情事，亦查\n    無該證據作成時有何違法情事，並無顯有不可信之情況，依\n    刑事訴訟法第159 條之1 第2 項之規定，應適宜為本案之證\n    據而有證據能力。\n三、按鑑定人由審判長、受命法官或檢察官就下列之人選任1人\n    或數人充之：就鑑定事項有特別知識經驗者；經政府機關委\n    任有鑑定職務者；鑑定之經過及其結果，應命鑑定人以言詞\n    或書面報告；法院或檢察官得囑託醫院、學校或其他相當之\n    機關、團體為鑑定，或審查他人之鑑定，並準用第203 條至\n    第206 條之1 規定，刑事訴訟法第198 條、第206 條第1 項\n    、第208 條第1 項分別定有明文。本件卷附高雄市立凱旋醫\n    院97年4 月23日高市凱醫驗字第6814號濫用藥物成品檢驗鑑\n    定書（偵卷第59頁）及高雄市立凱旋醫院97年4 月7 日高市\n    凱醫驗字第6665號濫用藥物成品檢驗鑑定書（偵卷第7 頁背\n    面），雖係被告以外之人於審判外之書面陳述，然係臺灣高\n    雄地方法院檢察署囑託鑑定之書面報告，依據上開規定，為\n    刑事訴訟法第159 條第1 項規定之例外情形，均有證據能力\n    。\n四、按被告以外之人於審判外之陳述，雖不符刑事訴訟法第159\n    條之1 至之4 之規定，然經當事人於審判程序同意作為證據\n    ，法院審酌該言詞陳述或書面陳述作成時之情況，認為適當\n    者，亦得為證據，同法第159 條之5 第1 項定有明文。除上\n    開所述外，本判決下列所引用之證據，屬被告以外之人在審\n    判外陳述之傳聞證據部分，除依刑事訴訟法第159 條之1 至\n    第159 條第4 規定得為證據者外，其餘業經被告、辯護人及\n    檢察官於審理中同意作為證據（本院卷第78-79 頁），本院\n    審酌該等傳聞證據作成時之狀況，並無違法或不當等不宜作\n    為證據之情形，依前開說明，亦得作為證據。\n貳、認定事實所憑之證據及理由：\n    訊據被告坦承查扣之海洛因、甲基安非他命各1 小包係其於\n    查獲當日下午交付鄭淑月擬轉交曾富煌，及轉讓上開禁藥即\n    甲基安非他命予曾富煌之事實（本院卷第73、107 頁），惟\n    矢口否認有何販賣第一級毒品之犯行。辯稱：扣案之海洛因\n    及甲基安非他命均係其無償送給曾富煌施用，並無販賣營利\n    之意圖，扣案之購買飲料所找940 元是其尚未交還曾富煌即\n    為警查獲，該金錢並非其所有，且當日其交付毒品之地點係\n    在消防局前，並非在「OK便利超商」內云云。經查：\n一、高雄市政府警察局楠梓分局後勁派出所員警乙○○、丙○○\n    ，於97年3 月4 日下午4 點多至5 時許之某時，在高雄市○\n    ○區○○路與加宏路口附近執行便衣巡邏勤務時，發現轄區\n    內之毒品列管人口鄭淑月被曾富煌騎車搭載，形跡可疑，乃\n    自後跟監，嗣鄭淑月與鄭富煌於上開消防隊前停留，約2 分\n    鐘後，被告即與鄭淑月、曾富煌會合後，三人則一同進入高\n    雄市○○區○○路與加宏路口之「OK便利超商」內，員警乃\n    在該超商門口前等待，於其三人步出「OK便利超商」時，因\n    鄭淑月手中握有被告所交付之海洛因（驗前淨重0.104 公克\n    、驗餘淨重0.096 公克）、甲基安非他命（驗前淨重0.024\n    公克、驗餘淨重0.014 公克）各1 小包及鋁箔裝飲料（該2\n    包毒品放在手心，飲料壓在上面），乃將該2 包毒品查扣，\n    並在甲○○身上扣得以1,000 元向超商購買飲料後所找餘之\n    現金940 元及其所有之行動電話1 具（含0000000000號SIM\n    卡），復扣得鄭淑月所有之行動電話1 具（含號0000000000\n    號SIM 卡）等情，業據證人即本案查獲之員警丙○○及乙○\n    ○於本院審理時證述明確（本院卷第95-100頁），並有扣押\n    筆錄、扣押物品目錄表、扣押物照片在卷可參（警卷第17-2\n    0 、31-34 頁，影一卷第1-2 頁，影二卷第3 頁背面）。而\n    上開扣案之2 包毒品經送檢驗結果，分別呈海洛因及甲基安\n    非他命反應等情，亦有高雄市立凱旋醫院97年4 月23日高市\n    凱醫驗字第6814號濫用藥物成品檢驗鑑定書及97年4 月7 日\n    高市凱醫驗字第6665號濫用藥物成品檢驗鑑定書可憑（偵卷\n    第59、7 頁背面）。又被告於查獲當日即97年3 月4 日下午\n    4 時26分59秒、32分52秒、40分44秒許，以其所有之000000\n    0000號行動電話與曾富煌借用鄭淑月之0000000000號行動電\n    話，為上開3 次對話之事實，為被告坦承在卷，並經證人曾\n    富煌於偵查及原審證述明確（偵卷第90頁及原審卷第98頁）\n    ，復有被告持用之0000000000號行動電話之申請人資料暨通\n    聯紀錄在卷可證（偵卷第43、45-46 頁）。上開事實，均可\n    認定。\n二、被告雖否認上開販賣海洛因毒品之犯行（坦承轉讓甲基安非\n    他命之犯行，僅辯稱交付毒品之地點並非在「OK便利超商」\n    內），並以前詞置辯，惟查：\n(一)、證人曾富煌於97年6 月26日於偵查中證稱：其於97年3 月4\n    日下午4 時許，向鄭淑月借用0000000000號行電話撥打被告\n    0000000000號行動電話，向被告表示要購買1,000 元「軟的\n    」（台語）之「海洛因」及500 元「硬的」（台語）之「安\n    非他命」（下稱甲基安非他命）），被告便與其約在楠梓區\n    的消防隊碰面交易，其就載著鄭淑月至該地與被告碰面，雙\n    方見面後，被告要其等跟著他走，就到了OK超商，…在進入\n    超商前，其先從口袋拿1,000 元紙鈔交給鄭淑月，鄭淑月及\n    被告先到飲料區拿飲料，其則在櫃檯買菸，後來其也走到飲\n    料區，被告向其表示飲料下方有毒品，…鄭淑月將前揭1,00\n    0 元紙鈔拿給…被告，被告便拿著千元紙鈔，其拿著上開飲\n    料跟著被告一起去櫃檯付帳，…「（你當天要向甲○○購買\n    1,000 元『軟的』之海洛因及500 元『硬的』之甲基安非他\n    命，為何只交他1,000 元？）因為500 元的甲基安非他命，\n    甲○○沒有向我收錢，算送給我的，因為我是被告的老主顧\n    。」，…當天扣得之毒品是在上開「OK便利超商」向被告買\n    的，…其之前在警詢所述與被告約在該處，要請被告喝飲料\n    是假的，其等是假藉購買飲料，以掩飾交易毒品的過程等語\n    綦詳（偵卷第90-91 頁）；復於97年10月21日於原審證稱：\n    於97年3 月4 日下午4 點許，其載鄭淑月去右昌，中途先與\n    被告在消防隊碰面，被告叫其等一起走，就到1 家「OK便利\n    超商」，…在那邊碰面之原因係其向鄭淑月借手機打電話給\n    被告，要向被告討回手機，並要向被告拿海洛因，其跟被告\n    說跟他約在消防隊，要拿「查某」（海洛因）1,000 元，還\n    有500 元「硬的」（甲基安非他命），…到「OK便利超商」\n    後因其機車沒有熄火，其先拿自己所有的1,000 元給鄭淑月\n    ，請鄭淑月拿給被告，他們兩人一起走進去超商，去拿涼水\n    ，其跟在後面進去買菸，…其三人在櫃檯時，鄭淑月與甲○\n    ○拿涼水，鄭淑月手上拿涼水，其買菸，找完錢走出超商後\n    ，警察就將其等擋下，…「（你說500 元『硬的』是甲○○\n    要請的？）是甲○○在電話中主動跟我講的。」，…（提示\n    上開偵卷第46頁所示3 通電話通聯記錄）鄭淑月0000000000\n    號行動電話撥打給被告0000000000號行動電話之通聯紀錄，\n    那3 通是我打的等語在卷（院卷第93-98 頁）。再者，曾富\n    煌有施用海洛因及甲基安非他命習慣，且於查獲當日為警採\n    尿送驗結果（編號D97078號），確呈甲基安非他命、嗎啡及\n    可待因陽性反應等情，業據證人曾富煌於警詢供述明確（警\n    卷第5-7 頁），並有高雄市立凱旋醫院濫用藥物尿檢報告（\n    轉碼編號：A00000000 ）在卷可憑（偵卷第40頁），足見曾\n    富煌確有施用海洛因及甲基安非他命之習慣，而有向被告購\n    買海洛因毒品施用之動機，且參酌證人曾富煌所稱其係向被\n    告購買毒品之老主顧，自亦難排除被告有附隨贈送甲基安非\n    他命供被告施用之可能；佐以證人曾富煌上開於偵查及原審\n    具結後之證述內容，就其於查獲當日如何與被告聯絡購買毒\n    品及取得毒品之經過，前後相符，並無相互矛盾之情，又與\n    被告持用之0000000000號行動電話與鄭淑月0000000000號行\n    動電話，於查獲當日即97年3 月4 日下午4 時26分59秒、32\n    分52秒、40分44秒許之通聯記錄所示時間，大致相符，綜上\n    各情，其證述當日於電話中向被告表示要購買1,000 元海洛\n    因及500 元甲基安非他命，被告表示甲基安非他命部分無償\n    贈予其施用（意指甲基安非他命部分並非販賣，而係無償轉\n    讓），其乃透過鄭淑月交付1,000 元予被告，向被告購買1,\n    000 元海洛因，被告除交付扣案之海洛因外，並同時無償贈\n    與扣案之甲基安非他命給其等情，應堪採信。至於證人曾富\n    煌為警查獲後，於97年3 月4 日警詢雖供稱：扣案之毒品均\n    係鄭淑月所有云云（偵卷第6 頁），並於同年3 月5 日偵查\n    中供稱：扣案之毒品係鄭淑月向被告購買云云（偵卷第8 頁\n    ），然其嗣於97年6 月26日偵查及97年10月21日原審已更異\n    前詞，並詳述如上，而證人曾淑月迭於警詢、偵查及原審均\n    否認上開毒品係其向被告所購買，且被告於本院已坦承扣案\n    之2 包毒品係其交付給曾富煌施用等語，足認證人曾富煌此\n    部分於警詢及偵查中所述，與事實不符，不可採信。\n(二)、又證人鄭淑月於偵查中證稱：當天是曾富煌向其借手機，撥\n    打電話給被告，向被告購買海洛因及甲基安非他命，曾富煌\n    打電話時，其在曾富煌旁邊，所以其有看到他講電話，曾富\n    煌打電話後就騎乘機車載其，在路上遇到被告，被告就提議\n    到「OK便利超商」，被告說要請其及曾富煌喝飲料，其三人\n    一起到該超商門外時，曾富煌便叫其拿1,000 元給被告買飲\n    料，其在超商門外就從拿1,000 元給被告，其三人一同進入\n    該便利超商內，其和被告到飲料區選飲料，其選了2 罐飲料\n    拿去櫃檯要算錢時，在櫃臺將該2 罐飲料交給被告，被告結\n    帳後其拿起飲料時，便發現其中1 罐飲料下方黏有扣案之2\n    包毒品，所以其確定該2 包毒品是被告黏的沒錯，當時曾富\n    煌則站在其等身旁，…被告拿著該1,000 元結帳後，便將零\n    錢放在口袋了，其三人買完飲料後，剛出便利超商門口就被\n    警方查獲，當時其兩手拿住飲料，扣案毒品則置於飲料下方\n    ，所以毒品是從其手上的飲料查獲的等語（偵卷第65-66 頁\n    ）；並於原審證稱：97年3 月4 日下午4 時許，曾富煌騎機\n    車本來說要載其去找朋友，途中在右昌地區的路上向其借手\n    機，打完後，其和曾富煌在過了「OK便利超商」的消防隊前\n    與被告見面，雙方站在路的兩邊，被告說要去「OK便利超商\n    」，才又回頭到「OK便利超商」，…至「OK便利超商」後，\n    被告叫其去拿涼水，叫其拿了去櫃檯算錢，其拿了2 瓶涼水\n    去櫃檯算錢，由被告結帳，買飲料找的零錢由被告拿走，…\n    其再把涼水拿起來的時候，毒品已經黏在涼水的底下，…員\n    警扣到毒品時，其已經把毒品與涼水拆開，膠布還沒有拿起\n    來，其準備將毒品交給曾富煌，…當天付涼水的錢是曾富煌\n    給被告的，曾富煌在超商門口外面先拿給其1 張1,000 元紙\n    鈔，叫其拿給被告買涼水，其就把錢拿給被告等語（原審卷\n    第87頁背面-92 頁），已就曾富煌於查獲當日下午如何借用\n    其上開行動電話與被告聯絡，及其等三人在消防隊前碰面後\n    一同前往超商購買飲料暨被告交付扣案2 包毒品之經過等情\n    ，均能逐一詳加證述明確，且與證人曾富煌所述向被告購買\n    毒品，及查獲之員警丙○○、乙○○證述其等當日查獲被告\n    及鄭淑月、曾富煌等人之經過等情，大致相符（本院卷第\n    95-100頁）；佐以證人丙○○、乙○○確於被告身上扣得其\n    於超商內以1, 000元購買飲料後所找現金940 元及被告當日\n    下午與曾富煌連聯交易毒品所用之0000000000號行動電話（\n    含SIM 卡），並扣得鄭淑月所有借予曾富煌連聯被告購買毒\n    品所用之0000000000號行動電話（含SIM 卡）及被告交由鄭\n    淑月轉交曾富煌之海洛因及甲基安非他命各1 包，均已如前\n    述，綜上各情，足認證人鄭淑月上開所述，應屬可採。可見\n    曾富煌確於97年3 月4 日下午4 時多許，借用鄭淑月之行動\n    電話，與被告談妥上述交易毒品內容及約定在前揭消防隊前\n    見面，三人再一同前往「OK便利超商」，曾富煌則透過鄭淑\n    月將購買海洛因之價款1,000 元交付被告，並向被告收取購\n    買之海洛因及無償取得之甲基安非他命，雙方並以假藉進入\n    「OK便利超商」選購飲料，鄭淑月則先將1,000 元紙鈔及其\n    選購之飲料交由被告結帳，再由被告趁機將毒品膠黏於飲料\n    底部之方式，連同飲料一併交還鄭淑月  以遂行其販賣海洛\n    因及轉讓甲安非他命予曾富煌之目的。\n(三)、再者，被告於97年4 月29日偵查中亦供稱：我認識曾富煌，\n    但與鄭淑月不熟，查獲當日我最先進入超商，然後鄭淑月走\n    進店內，最後曾富煌走進來，那時候我是站在靠近店門口的\n    收銀櫃檯前，鄭淑月則站在我的左後方，曾富煌站在我的正\n    後方，我有問曾富煌要喝什麼飲料，他說隨便，我沒有問鄭\n    淑月要喝什麼，然後我們三人一起走到飲料區選飲料，我拿\n    了麥片牛奶及養樂多，鄭淑月則選了鋁箔包裝紅茶，曾富煌\n    沒有買飲料他又走開去買煙；是我拿錢出來結帳，但是該1,\n    000 元紙鈔是曾富煌的錢，是鄭淑月親手交給我的，「（為\n    何稱是曾富煌的錢？）因為我那時站在收銀櫃檯前，我有看\n    到店門外曾富煌騎乘機車載鄭淑月前來，在店外他將該1,00\n    0 元紙鈔交給鄭淑月，鄭淑月…交給我的，後來曾富煌才又\n    走進店內，我才會問曾富煌要喝什麼飲料。…我們電話約好\n    後，是先約在加昌路上的消防隊前碰面，然後再一起騎車到\n    該便利超商買飲料。」，我是有拿鄭淑月所稱之飲料給鄭淑\n    月等語（偵卷第49-50 頁）；並於本院供稱：在消防隊前見\n    面之前，曾富煌有先以鄭淑月之行動電話與其聯絡在消防隊\n    前見面，且扣案之海洛因及甲基安非他命係其於查獲前不久\n    交由鄭淑月轉交曾富煌（只辯稱在消防隊前交付），而員警\n    在其身上查扣940 元現金，則是曾富煌經由鄭淑月在超商門\n    口轉交給其1,000 元紙鈔於購買飲料後所找零款等語（本院\n    卷第74-76 頁）；均核與證人曾富煌證稱：其於當日下午4\n    點多借用鄭淑月之行動電話與被告約定消防隊前見面後，其\n    三人再先後進入超商內購買飲料（曾富煌購買香菸），於進\n    入超商之前，其拿1,000 元紙鈔給鄭淑月轉交被告等語，及\n    證人鄭淑月證稱：其依曾富煌之意，於超商門口將1,000 元\n    交給被告，三人進入該便利超商內，其與被告到飲料區選飲\n    料，其在櫃檯將飲料交給被告結帳後，其再拿回自己選購之\n    飲料，扣案之海洛因及甲基安非他命，係被告以膠黏於飲料\n    底部之方式交付等情相符。可見證人曾富煌、鄭淑月等人關\n    於本件販賣毒品之過程所為證述，均非憑空虛構，曾富煌於\n    查獲當日下午4 時多許，借用鄭淑月之行動電話與被告聯繫\n    購買1,000 元海洛因及500 元甲基安非他命，被告除與曾富\n    煌就該1,000 元海洛因買賣之意思表示達成合致外，另允諾\n    無償提供甲基安非他命予曾富煌，雙方於談妥後隨即相約在\n    消防隊前見面，再一同前往「OK便利超商」內交付毒品，且\n    曾富煌於進入超商前，則委請鄭淑月將購毒價金1,000 元交\n    付被告，被告以該1, 000結帳後，即順勢將店員所找940 元\n    放入其口袋，並將毒品黏附鄭淑月選購之飲料底部一併交付\n    鄭淑月，再由鄭淑月將毒品交付曾富煌，以此方式掩飾其販\n    賣海洛因及轉讓甲基安非他命之犯行，應可認定。故被告辯\n    稱：其交付毒品之地點係在消防局前，並非在「OK便利超商\n    」內，且扣案之購買飲料找零940 元是其尚未交還曾富煌之\n    款項，該金錢非其所有云云，顯係欲將其收取鄭淑月所交付\n    之1,000 元（於「OK便利超商」門口附近交付），與其交付\n    扣案之2 包毒品之行為，二者間作適當之切割，塑造成本件\n    只係單純轉讓毒品（實則只有甲基安非他命部分係無償轉讓\n    ），並無買賣價金之交付，以配合其上開辯詞，此由被告於\n    店員找零940 元後隨即放入其口袋，而未連同飲料、毒品一\n    併交由鄭淑月以轉交曾富煌等情，即可明瞭。\n(四)、至於扣案之海洛因、甲基安非他命之外包裝是否殘留膠布黏\n    貼痕跡一事（即最高法院發回意旨(三)，見該判決書第3 頁）\n    ，經本院調取扣案之「海洛因」及「甲基安非他命」證物（\n    含包裝袋）當庭勘驗結果：「扣案「海洛因」係以夾鏈袋\n    包裝，因查獲人員在該包裝袋上貼上標籤以載明毒品重量，\n    且該包毒品又歷經送驗、編號入庫等程序，其包裝袋一面已\n    貼上毒品重量之標籤（0.31）及批號、轉碼等字條，且因黏\n    貼紙條之關係，致無法撕下標籤、紙條以分辨是否曾經留有\n    膠布黏貼之痕跡；而包裝袋另一側並無張貼任何紙條，但無\n    法明顯辨識是否有貼過膠布黏貼痕跡。另扣案「甲基安非\n    他命」係夾鏈袋包裝，亦同上原因，其包裝袋一面已貼上\n    載明毒品重量之標籤（0.22）及批號、轉碼字條，已無法撕\n    下辨明是否留有膠布黏貼痕跡；另一側則無張貼任何紙條，\n    但無法明顯辨識是否有曾黏貼過膠布。」此有本院勘驗筆錄\n    及照片在卷可憑（本院卷第76頁及第81-1頁以下）。然查，\n    證人鄭淑月於原審已證稱：「（警方扣到毒品時，毒品、涼\n    水已經分開？）是，我把它拆開，膠布還沒有拿起來」等語\n    （原審卷第89頁），及查獲員警乙○○於本院證稱：鄭淑月\n    從「OK便利超商」出來，我看到鄭淑月手中有拿2 包毒品及\n    鋁箔裝的飲料，毒品是放在手心，飲料壓在上面，一看就可\n    以看得出來，是我從鄭淑月手中的毒品拿下來的，當時毒品\n    沒有黏著在飲料上等語（本院卷第99頁），可知鄭淑月於超\n    商內取得底部附黏2 包毒品後，即將膠黏之毒品與飲料分開\n    ，故於步出超商時，手中所持飲料及毒品已呈分開狀，又因\n    員警專注於鄭淑月手中之毒品，且飲料並非查緝之違禁物，\n    佐以在毒品交易實務上亦鮮見販毒者將毒品以膠布附著於飲\n    料下方，致員警未能即時發覺被告係以此精心設計之方式遮\n    掩其交付毒品之犯行，而未能將鄭淑月手中飲料（含膠布）\n    一併查扣；另一方面，本件查扣上開2 包毒品至本院勘驗其\n    外包裝袋，前後已相隔2 年多，該毒品包裝袋又歷經查獲、\n    檢院贓物庫及檢驗等人員多次觸摸，復經審理階段一再提示\n    辨識，而當時膠黏毒品之客體又係鄭淑月剛選購之冰冷飲料\n    ，其外包裝已含有微量水氣，且鄭淑月於取得飲料、毒品後\n    又隨即將其分開，故毒品包裝袋與膠布接觸之時間已屬短暫\n    ，本不易殘留易供辨識之膠布貼黏痕跡，惟扣案之2 包毒品\n    既係被告交付予鄭淑月，此為被告所不爭執，並經證人鄭淑\n    月證述明確，復經本院認定如前，若非被告以膠布將毒品黏\n    於飲料底部交付，則證人鄭淑月又豈能虛構如此具體之事實\n    ，自難以飲料及膠布未扣案，且因上開因素而無法勘驗出毒\n    品外包裝袋有無膠布黏貼痕跡，即認鄭淑月前揭關於被告交\n    付毒品之方式為不可採；反之，由被告與曾富煌於電話中談\n    妥販賣海洛因及轉讓甲基安非他命等細節，並在消防隊前見\n    面之時，被告並未將毒品交付曾富煌，而另行邀同前往「OK\n    便利超商」內，以上開迂迴隱避之方式交付毒品，其目的無\n    非係欲避免其上開販賣海洛因及轉讓甲基安非他命之犯行遭\n    他人發覺，才精心設計此一特殊之交易及轉讓毒品模式，以\n    隱藏其於上開「OK便利超商」，販賣1,000 元海洛因及同時\n    轉讓甲基安非他命予曾富煌之事實，至為明確。\n(五)、本件證人鄭淑月雖未及將毒品交付給曾富煌即為警查獲，然\n    查：被告與曾富煌於電話中已達成買賣1,000 元海洛因及轉\n    讓1 小包甲基安非他命毒品之意思合致，曾富煌並透過鄭淑\n    月轉交1,000 元價金給被告，被告再將毒品黏貼於飲料底部\n    之方式，交付毒品給鄭淑月轉交曾富煌等情，已如上述，足\n    見鄭淑月係曾富煌手足之延伸，曾富煌係透過鄭淑月代其支\n    付價金及收受毒品之行為，鄭淑月雖未及將毒品轉交曾富煌\n    即為警查獲，然被告交付毒品給鄭淑月之際，該2 包毒品既\n    已置於曾富煌之實力可得支配之範疇，堪認被告已完成毒品\n    買賣及轉讓之交付行為，自無礙其販賣海洛因及轉讓禁藥即\n    甲基安非他命等犯行既遂之認定。又被告雖僅向曾富煌收取\n    1,000 元，而同時交付海洛因及甲基安非他命各1 包予曾富\n    煌（由鄭淑月代為收受），惟證人曾富煌於97年6 月26日偵\n    查及97年10月21日原審已明確證稱：甲基安非他命被告沒有\n    向其收錢，算送給其的，因為其是被告的老主顧，…之前跟\n    被告買過3 、4 次海洛因、甲基安非他命（詳細次數因時間\n    太久已忘記了）；被告跟其兒子認識，會在其那裡出入，所\n    以當時在電話中也向被告要手機等語（偵卷第90頁及原審卷\n    第93頁背面、94、98頁）；且被告亦供稱：曾富煌是其同學\n    的父親，要還被告之手機，是其向曾富煌兒子曾啟鶴借的等\n    語（偵卷第50頁及97年度聲羈字第262 號卷第4 頁），足見\n    被告與曾富煌熟識，其考量與曾富煌曾有交易毒品之經驗及\n    特殊情誼，及往後尚可繼續交易等因素，於本次曾富煌表示\n    欲購買1,000 元海洛因及500 元甲基安非他命時，只向被告\n    收取販賣1 包海洛因之價金1,000 元，另主動表示願無償轉\n    讓1 小包甲基安非他命供曾富煌施用，並非不可能之事，況\n    且扣案之甲基安非他命數量甚少，是否具有曾富煌原先擬購\n    買之500 元價值，已有可疑，自難以曾富煌向被告表示欲購\n    買500 元甲基安非他命，即逕認被告所轉讓之甲基安非他命\n    具有500 元之價值，將曾富煌該次所購買之1,000 元海洛因\n    與被告轉讓之甲基安非他命二者混為一談，而以被告交付之\n    毒品價值合計1,500 元（即海洛因1,000 元＋甲基安非他命\n    500 元＝1,500 元），竟只向曾富煌收取1,000 元，據以質\n    疑被告販賣海洛因予曾富煌之營利意圖。\n(六)、按販賣毒品本無一定價格，各次買賣之價格，當亦各有差異\n    ，隨供需雙方之資力、關係之深淺、需求之數量、貨源之充\n    裕與否、販賣者對於資金之需求如何即殷切與否，以及政府\n    查緝之態度，進而為各種不同之風險評估，而為機動性之調\n    整，是其價格標準，自非一成不變，且販賣者從各種「價差\n    」或「量差」或係「純度」謀取利潤方式，或有差異，然其\n    所圖利益之非法販賣行為目的，則屬相同，並無二致，故販\n    賣之利得，除被告就販賣之價量俱臻明確供述外，委難察得\n    實情，況一般民眾普遍認知毒品之非法交易，政府一向查禁\n    森嚴，且重罰不寬貸，衡諸常情，倘非有利可圖絕無平白甘\n    冒被重罰高度風險之理，從而，舉凡其「有償交易」，除足\n    反證其確另基於某種非圖利本意之關係外，通常尚難因無法\n    查悉其買進、賣出之差價，而諉無營利之意思，或阻卻販賣\n    犯行之追訴。本件被告有施用毒品之習慣，業據其陳明在卷\n    ，並有臺灣高等法院被告前案紀錄表卷可憑（本院卷第36-4\n    3 頁），其顯已知持有、販賣毒品均為法所不許，且販賣毒\n    品犯行之法定刑度甚重之事實，依一般經驗法則，其苟非意\n    在營利，又何須干冒為警查獲被判重罪之風險，並精心設計\n    以上述假藉購買飲料之方式，藉機將海洛因販賣予曾富煌並\n    收取價金？再佐以被告於本院供稱：查獲那段時間其有在施\n    用海洛因，除扣案交付予曾富煌之海洛因外，其當時已無多\n    餘之海洛因可供施用等語（本院卷第95頁），更可顯示其販\n    賣上開海洛因具有營利意圖。\n(七)、至被告及其辯護人於本院聲請詰問證人曾富煌，欲證明本案\n    查扣之940 元現金是否係被告交付海洛因毒品之對價部分（\n    本院卷第77頁），茲因本件事證已臻明確，且曾富煌於已偵\n    查及原審就此待證事實詳加證述（詳前(一)所述），自無再行\n    傳喚之必要，且該位證人已於原審進行交互詰問，足以確保\n    被告之對質詰問權，併予敘明。\n二、綜上所述，被告前揭所辯，顯係卸責之詞，不足採信。本案\n    事證明確，被告於上開時、地，同時販賣1,000 元之第一級\n    毒品海洛因及轉讓禁藥即第二級毒品甲基安非他命之犯行，\n    均堪認定，應依法論處。\n、論罪科刑及撤銷改判之理由：\n一、比較新舊法：\n    按被告行為後，毒品危害防制條例第4 條第1 項業於98年5\n    月20日修正公佈，修正前毒品危害防制條例第4 條第1 項規\n    定之法定本刑：「製造、運輸、販賣第一級毒品者，處死刑\n    或無期徒刑；處無期徒刑者，得併科新臺幣1 千萬元以下罰\n    金」；修正後規定：「製造、運輸、販賣第一級毒品者，處\n    死刑或無期徒刑；處無期徒刑者，得併科新臺幣2 千萬元以\n    下罰金」。經比較修正前後條文內容，修正後所定罰金刑最\n    高數額較修正前提高，自以修正前之規定較有利於被告，自\n    應適用修正前毒品危害防制條例第4 條第1 項之規定論處。\n二、次按甲基安非他命係毒品危害防制條例第2 條第2 項第2 款\n    所明定之第二級毒品，不得持有、轉讓及販賣。又甲基安非\n    他命為第二級毒品，並經行政院衛生署於75年7 月11日以衛\n    署藥字第597627號重申公告禁止使用在案，迄未變更，仍應\n    認屬藥事法第22條第1 項第1 款所列之禁藥。故行為人明知\n    為禁藥即甲基安非他命而轉讓予他人者，除成立毒品危害防\n    制條例第8 條第2 項之轉讓第二級毒品罪外，亦構成藥事法\n    第83條第1 項之轉讓禁藥罪，此係屬同一犯罪行為而同時有\n    二種法律可資處罰之「法規競合」情形，應依「重法優於輕\n    法」、「後法優於前法」等法理，擇一處斷。而毒品危害防\n    制條例第8 條第2 項轉讓第二級毒品罪之法定本刑為「6 月\n    以上5 年以下有期徒刑，得併科新臺幣70萬元以下罰金」。\n    而93年4 月21日修正後藥事法第83條第1 項轉讓禁藥罪之法\n    定本刑為「7 年以下有期徒刑，得併科新臺幣500 萬元以下\n    罰金」，故除有轉讓之第二級毒品達毒品危害防制條例第8\n    條第6 項之一定數量，經依法加重其刑，致該法定刑較藥事\n    法第83條第1 項之法定刑為重之情形外，因藥事法第83條第\n    1 項為後法，且為重法，應優先適用藥事法處罰（最高法院\n    96年臺上字第3582號判決參照）。本件被告於前揭時、地，\n    無償轉讓甲基安非他命予證人曾富煌之行為，依上開法規競\n    合及重法優於輕法之適用法則，被告轉讓禁藥甲基安非他命\n    予曾富煌之犯行，應適用藥事法論處。\n三、核被告所為，係犯98年5 月20日修正前毒品危害防制條例第\n    4 條第1 項之販賣第一級毒品罪及藥事法第83條第1 項之轉\n    讓禁藥罪。被告持有第一級毒品海洛因及禁藥甲基安非他命\n    之低度行為，均為其販賣海洛因或轉讓甲基安非他命之高度\n    行為所吸收，均不另論罪。公訴意旨認被告上開轉讓甲基安\n    非他命之犯行，係犯修正前毒品危害防制條例第4 條第2 項\n    之販賣第二級毒品罪，惟被告就此交付甲基安非他命1 小包\n    之行為並未獲取對價，業如前述，是被告此部分犯行尚無販\n    賣第二級毒品罪可言，公訴人就此部分尚有誤會，惟其社會\n    基本事實既同一，爰依法變更起訴法條改依藥事法第83條第\n    1 項之罪論處。被告一行為同時觸犯販賣第一級毒品罪及轉\n    讓禁藥罪，為想像競合犯，應從一重依修正前毒品危害防制\n    條例第4 條第1 項之販賣第一級毒品罪處斷。被告有如犯罪\n    事實欄一所載之犯罪科刑執行情形，有上開前案紀錄表在卷\n    卷可稽，其於徒刑執行完畢後，於5 年內故意再犯本件有期\n    徒刑以上之二罪，均為累犯，應依刑法第47條第1 項規定加\n    重其刑，其中販賣第一級毒品罪關於死刑、無期徒刑部分，\n    依法不得加重，僅就法定刑中關於罰金部分加重其刑。又同\n    為販賣第一級毒品之人，其原因、動機不一，犯罪情節未必\n    盡同，或有大盤毒梟者，亦有中、小盤之分，甚或僅止於吸\n    毒者同儕間為求互通有無之有償轉讓者亦有之，其販賣行為\n    所造成危害社會之程度自屬有異，法律科處此類犯罪所設之\n    法定最低本刑卻同為無期徒刑，不可謂為不重。本件被告販\n    賣第一級毒品之犯行僅有1 次，且販賣數量輕微，犯罪所得\n    僅1,000 元，犯罪情節難與大盤毒梟者相提併論，即令處以\n    最低刑度即無期徒刑而禁錮終身，仍有致情法失平之處，誠\n    屬情輕法重，難謂符合刑罰之相當性，爰依刑法第59條規定\n    減輕其刑。被告就販賣第一級毒品犯行，有前揭刑之加重及\n    減輕事由，惟販賣第一級毒品罪關於死刑、無期徒刑部分，\n    依法不得加重，僅就法定刑中關於罰金刑部分先加後減之。\n四、原審予以被告論科，固非無見。惟查：\n(一)、被告行為後，毒品危害防制條例第4 條第1 項已於98年5 月\n    20日業經修正公布，經綜合比較結果，以修正後之規定較有\n    利於被告。原判決未及比較適用，已有未恰。\n(二)、又意圖營利係販賣毒品罪之構成要件，此一要件須於事實欄\n    詳載，並於理由欄說明其所憑認定之依據。原判決既未於事\n    實欄記載，復未說明其所憑認定之依據，自屬理由不備。\n(三)、被告轉讓甲基安非他命應依藥事法第83條第1 項之轉讓禁藥\n    罪論處；惟原判決論以毒品危害防制條例第8 條第2 項之轉\n    讓第二級毒品罪，亦有適用法則不當之違誤。\n五、被告上訴意旨，仍執前詞，否認販賣第一級毒品犯罪，固無\n    足取，然原判決既有上述可議，自應由本院將原判決此部分\n    撤銷改判。本院審酌被告為牟私利而販賣第一級毒品海洛因\n    及轉讓禁藥（甲基安非他命），殘害國民身心健康，足使社\n    會施用毒品人口增加，而相對提高社會負成本，減損勞動生\n    產力，影響社會層面至深且鉅，惟販賣對象僅有曾富煌1 人\n    ，實際販賣所得僅1, 000元等一切情狀，仍量處如主文第2\n    項所示之刑；並考量本案被告販賣第一級毒品之犯罪性質，\n    而有褫奪公權之必要，併依刑法第37條第2 項規定，宣告褫\n    奪公權5 年，以示懲儆。又扣案之海洛因、甲基安非他命各\n    1 小包（驗前淨重分別為0.104 公克、0.024 公克；驗餘淨\n    重分別為0.096 公克、0.014 公克）雖屬第一、二級毒品，\n    惟業經被告販賣、轉讓而交付予曾富煌，並經原審法院於判\n    決事實欄所載之鄭淑月持有第一、二級毒品及曾富煌施用第\n    一、二級毒品等案件宣告沒收銷燬，並已執行完畢（此有其\n    等之刑事判決及臺灣高等法院被告前案紀錄表可憑），爰不\n    予重複宣告沒收銷燬。再扣案之行動電話1 具（含門號0000\n    000000號SIM 卡），為被告所有，業據其供述在卷（原審卷\n    第137 頁），並有上開門號之申請人資料1 紙可證（偵查卷\n    第43頁），該行動電話及SIM 卡既均為被告所有，作為本件\n    販賣海洛因之聯絡工具，係供本件犯罪所用之物，均應依毒\n    品危害防制條例第19條第1 項之規定宣告沒收。又被告販賣\n    第一級毒品海洛因命予曾富煌，得款1,000 元（僅扣得940\n    元），係被告犯販賣第一級毒品罪所得財物，應依毒品危害\n    防制條例第19條第1 項規定宣告沒收；其中未扣案之60元部\n    分，如全部或一部不能沒收時，則以其財產抵償之。\n肆、被告被訴販賣第二級毒品甲基安非他命予廖俊豪部分，業經\n    原審判決無罪確定，爰不論列，一併敘明。\n據上論結，應依刑事訴訟法第369 條第1 項前段、第364 條、第\n300 條、第299 條第1 項前段，藥事法第83條第1 項，98年5 月\n20日修正前毒品危害防制條例第4 條第1 項、第19條第1 項，刑\n法第2 項第1 項前段、第11條前段、第37條第2 項、第47條第1\n項、第55條、第59條，判決如主文。\n本案經檢察官孫小玲到庭執行職務。\n中    華    民    國    99    年    5     月    12    日\n                  刑事第三庭    審判長法  官   莊崑山\n                                      法  官   莊松泉\n                                      法  官   唐照明\n以上正本證明與原本無異。\n如不服本判決應於收受本判決後10日內向本院提出上訴書狀，其\n未敘述上訴理由者，並得於提起上訴後10日內向本院補提理由書\n狀（均須按他造當事人之人數附繕本）「切勿逕送上級法院」。\n中    華    民    國    99    年    5     月    12    日\n                                      書記官   黃琳群\n附錄本判決論罪之法條：\n98年5月20日修正前毒品危害防制條例第4 條第1項\n製造、運輸、販賣第一級毒品者，處死刑或無期徒刑；處無期徒\n刑者，得併科新臺幣1 千萬元以下罰金。\n藥事法第83條第1項\n明知為偽藥或禁藥，而販賣、供應、調劑、運送、寄藏、牙保、\n轉讓或意圖販賣而陳列者，處7 年以下有期徒刑，得併科新臺幣\n5 百萬元以下罰金。",
  "structure": {
    "main": "原判決關於販賣第一級毒品部分撤銷。\n甲○○販賣第一級毒品，累犯，處有期徒刑拾陸年，褫奪公權伍\n年。扣案之行動電話壹具（含門號0000000000號SIM 卡）沒收；\n扣案之販賣第一級毒品所得財物新臺幣玖佰肆拾元沒收，未扣案\n之販賣第一級毒品所得財物新臺幣陸拾元沒收，如全部或一部不\n能沒收時，以其財產抵償之。",
    "fact": "一、甲○○於民國90年2 月間因強盜案件，經臺灣高雄少年法院\n    以89年度少訴字第19號判處有期徒刑4 年6 月確定，於92年\n    5 月2 日因縮短刑期假釋出監，假釋期間並付保護管束，於\n    93年9 月13日縮刑期滿未經撤銷假釋，視為執行完畢；又於\n    94年9 月間因施用毒品案件，經原審以94年度簡字4674號判\n    處有期徒刑4 月確定，於95年5 月23日縮刑期滿執行完畢。\n二、甲○○明知海洛因、甲基安非他命分別係毒品危害防制條例\n    第2 條第2 項第1 款、第2 款所列之第一級、第二級毒品，\n    不得非法持有、轉讓、販賣，且甲基安非他命亦為藥事法所\n    規定之禁藥，因具成癮性、濫用性及對社會危害性，不得轉\n    讓，竟同時基於販賣第一級毒品海洛因以營利之意圖及無償\n    轉讓禁藥（即第二級毒毒品甲基安非他命）之犯意，於97年\n    3 月4 日下午4 時26分、32分、40分許，接聽曾富煌（所涉\n    施用第一級毒品、第二級毒品罪嫌部分，經原審以97年度審\n    訴字第2143號判決分別判處有期徒刑8 月、4 月，應執行有\n    期徒刑10月確定）借用友人鄭淑月（所涉持有第一級毒品罪\n    嫌部分，經原審以97年度審簡字第3305號判決判處有期徒刑\n    4 月確定）所有之門號0000000000號行動電話，撥打至甲○\n    ○持用之門號0000000000號行動電話，曾富煌表明欲向甲○\n    ○購買新臺幣（下同）1,000 元海洛因及500 元甲基安非他\n    命，甲○○則表示願無償提供甲基安非他命給曾富煌施用，\n    其二人於電話中談妥交易1,000 元海洛因及轉讓甲基安非他\n    命後，相約在高雄市○○區○○路上之消防隊前碰面，曾富\n    煌乃騎乘機車搭載鄭淑月前往，雙方於上開消防隊前碰面後\n    ，隨即前往高雄市○○區○○路與加宏路口之「OK便利超商\n    」內，三人假意要購買飲料，由曾富煌交給鄭淑月1,000 元\n    紙鈔1 張，鄭淑月再將該1,000 元紙鈔及其選購之2 罐鋁箔\n    裝飲料交給甲○○，由甲○○至該超商櫃檯處結帳後，即同\n    時將海洛因及甲基安非他命各1 小包黏貼於上開飲料底部，\n    再將該黏有毒品之飲料交給鄭淑月，以此方式販賣海洛因1\n    小包（驗前淨重0.104 公克、驗餘淨重0.096 公克）及轉讓\n    禁藥即甲基安非他命1 小包（驗前淨重0.024 公克、驗餘淨\n    重0.014 公克）予曾富煌，並收取販賣海洛因之價金1,000\n    元得逞。嗣因高雄市政府警察局楠梓分局後勁派出所員警乙\n    ○○、丙○○於當日下午約近5 時許，在高雄市○○區○○\n    路與加宏路口附近見其轄區內之毒品列管人口鄭淑月被曾富\n    煌騎車搭載，乃自後跟監，見鄭淑月與鄭富煌於上開消防隊\n    前停留，約2 分鐘後被告即前往與鄭淑月、曾富煌會合，其\n    三人再一同前往上開超商內，待其等步出「OK便利超商」時\n    ，員警目睹鄭淑月手中握有上開甲○○所交付之2 包毒品及\n    鋁箔裝飲料（即飲料底部與手掌間之空隙有2 包毒品面），\n    而依現行犯規定逮捕鄭淑月，並當場查扣甲○○販賣、轉讓\n    予曾富煌之海洛因及甲基安非他命各1 小包，並自甲○○身\n    上扣得販賣海洛因所得1,000 元購買飲料後所找餘之現金94\n    0 元及甲○○所有供犯罪所用之行動電話1 具（含門號0000\n    000000號SIM 卡），復扣得鄭淑月所有之行動電話1 具（含\n    號0000000000號SIM 卡），始悉上情。\n三、案經高雄市政府警察局楠梓分局移送臺灣高雄地方法院檢察\n    署檢察官偵查起訴。",
    "reason": "壹、證據能力部分：\n一、本件被告之辯護人主張：扣案之2 包毒品係違背法定程序而\n    取得云云（本院卷第77頁）。惟查，高雄市政府警察局楠梓\n    分局後勁派出所員警乙○○、丙○○，於97年3 月4 日下午\n    4 點多至5 時許之某時，在高雄市○○區○○路與加宏路口\n    附近執行便依巡邏勤務時，發現轄區內之毒品列管人口鄭淑\n    月被曾富煌騎車搭載，形跡可疑，乃自後跟監，嗣鄭淑月與\n    鄭富煌於上開消防隊前停留，約2 分鐘後，被告即與鄭淑月\n    、曾富煌會合後，三人則一同進入高雄市○○區○○路與加\n    宏路口之「OK便利超商」內，待其三人步出「OK便利超商」\n    時，因員警看見鄭淑月手中所拿之飲料底部與手掌間之空隙\n    有上開被告交付之2 包毒品，而有持有毒品等犯行，乃依現\n    行犯規定，上前盤查並實施搜索，而查扣該2 包毒品等情，\n    業據證人即查獲之員警丙○○及乙○○於本院證述明確（本\n    院卷第95-100頁），並有扣押筆錄、扣押物品目錄表及高雄\n    市政府警察局楠梓分局刑事案件移送書在卷可參（影一卷第\n    1-2 頁，影二卷第2 、3 頁之背面）。可見員警係在執行便\n    衣巡邏勤務時，遇見轄區毒品列管人口之鄭淑月形跡可疑而\n    自後跟監，嗣發現鄭淑月與被告及曾富煌等人進入「OK便利\n    超商」，於涉出該家超商之際，鄭淑月之手中持有飲料，且\n    該飲料底部有上開海洛因及甲基安非他命，以持有毒品之現\n    行犯加以逮捕，並扣得上開2 包毒品，再執行附帶搜索而扣\n    得其餘之物，核與刑事訴訟法第88條第1 項、第130 條、第\n    133 條第1 項之規定尚無違背，即難認係違法取得證據，員\n    警查獲鄭淑月等及附帶搜索之過程，既無侵犯法律保障基本\n    權或違背法定程式之情事，該取得之證據資料即有證據能力\n    ，得為判決基礎。\n二、本件證人曾富煌、鄭淑月於偵查中具結後向檢察官所為之證\n    述，證人均未曾提及檢察官在偵查中有不法取供情事，亦查\n    無該證據作成時有何違法情事，並無顯有不可信之情況，依\n    刑事訴訟法第159 條之1 第2 項之規定，應適宜為本案之證\n    據而有證據能力。\n三、按鑑定人由審判長、受命法官或檢察官就下列之人選任1人\n    或數人充之：就鑑定事項有特別知識經驗者；經政府機關委\n    任有鑑定職務者；鑑定之經過及其結果，應命鑑定人以言詞\n    或書面報告；法院或檢察官得囑託醫院、學校或其他相當之\n    機關、團體為鑑定，或審查他人之鑑定，並準用第203 條至\n    第206 條之1 規定，刑事訴訟法第198 條、第206 條第1 項\n    、第208 條第1 項分別定有明文。本件卷附高雄市立凱旋醫\n    院97年4 月23日高市凱醫驗字第6814號濫用藥物成品檢驗鑑\n    定書（偵卷第59頁）及高雄市立凱旋醫院97年4 月7 日高市\n    凱醫驗字第6665號濫用藥物成品檢驗鑑定書（偵卷第7 頁背\n    面），雖係被告以外之人於審判外之書面陳述，然係臺灣高\n    雄地方法院檢察署囑託鑑定之書面報告，依據上開規定，為\n    刑事訴訟法第159 條第1 項規定之例外情形，均有證據能力\n    。\n四、按被告以外之人於審判外之陳述，雖不符刑事訴訟法第159\n    條之1 至之4 之規定，然經當事人於審判程序同意作為證據\n    ，法院審酌該言詞陳述或書面陳述作成時之情況，認為適當\n    者，亦得為證據，同法第159 條之5 第1 項定有明文。除上\n    開所述外，本判決下列所引用之證據，屬被告以外之人在審\n    判外陳述之傳聞證據部分，除依刑事訴訟法第159 條之1 至\n    第159 條第4 規定得為證據者外，其餘業經被告、辯護人及\n    檢察官於審理中同意作為證據（本院卷第78-79 頁），本院\n    審酌該等傳聞證據作成時之狀況，並無違法或不當等不宜作\n    為證據之情形，依前開說明，亦得作為證據。\n貳、認定事實所憑之證據及理由：\n    訊據被告坦承查扣之海洛因、甲基安非他命各1 小包係其於\n    查獲當日下午交付鄭淑月擬轉交曾富煌，及轉讓上開禁藥即\n    甲基安非他命予曾富煌之事實（本院卷第73、107 頁），惟\n    矢口否認有何販賣第一級毒品之犯行。辯稱：扣案之海洛因\n    及甲基安非他命均係其無償送給曾富煌施用，並無販賣營利\n    之意圖，扣案之購買飲料所找940 元是其尚未交還曾富煌即\n    為警查獲，該金錢並非其所有，且當日其交付毒品之地點係\n    在消防局前，並非在「OK便利超商」內云云。經查：\n一、高雄市政府警察局楠梓分局後勁派出所員警乙○○、丙○○\n    ，於97年3 月4 日下午4 點多至5 時許之某時，在高雄市○\n    ○區○○路與加宏路口附近執行便衣巡邏勤務時，發現轄區\n    內之毒品列管人口鄭淑月被曾富煌騎車搭載，形跡可疑，乃\n    自後跟監，嗣鄭淑月與鄭富煌於上開消防隊前停留，約2 分\n    鐘後，被告即與鄭淑月、曾富煌會合後，三人則一同進入高\n    雄市○○區○○路與加宏路口之「OK便利超商」內，員警乃\n    在該超商門口前等待，於其三人步出「OK便利超商」時，因\n    鄭淑月手中握有被告所交付之海洛因（驗前淨重0.104 公克\n    、驗餘淨重0.096 公克）、甲基安非他命（驗前淨重0.024\n    公克、驗餘淨重0.014 公克）各1 小包及鋁箔裝飲料（該2\n    包毒品放在手心，飲料壓在上面），乃將該2 包毒品查扣，\n    並在甲○○身上扣得以1,000 元向超商購買飲料後所找餘之\n    現金940 元及其所有之行動電話1 具（含0000000000號SIM\n    卡），復扣得鄭淑月所有之行動電話1 具（含號0000000000\n    號SIM 卡）等情，業據證人即本案查獲之員警丙○○及乙○\n    ○於本院審理時證述明確（本院卷第95-100頁），並有扣押\n    筆錄、扣押物品目錄表、扣押物照片在卷可參（警卷第17-2\n    0 、31-34 頁，影一卷第1-2 頁，影二卷第3 頁背面）。而\n    上開扣案之2 包毒品經送檢驗結果，分別呈海洛因及甲基安\n    非他命反應等情，亦有高雄市立凱旋醫院97年4 月23日高市\n    凱醫驗字第6814號濫用藥物成品檢驗鑑定書及97年4 月7 日\n    高市凱醫驗字第6665號濫用藥物成品檢驗鑑定書可憑（偵卷\n    第59、7 頁背面）。又被告於查獲當日即97年3 月4 日下午\n    4 時26分59秒、32分52秒、40分44秒許，以其所有之000000\n    0000號行動電話與曾富煌借用鄭淑月之0000000000號行動電\n    話，為上開3 次對話之事實，為被告坦承在卷，並經證人曾\n    富煌於偵查及原審證述明確（偵卷第90頁及原審卷第98頁）\n    ，復有被告持用之0000000000號行動電話之申請人資料暨通\n    聯紀錄在卷可證（偵卷第43、45-46 頁）。上開事實，均可\n    認定。\n二、被告雖否認上開販賣海洛因毒品之犯行（坦承轉讓甲基安非\n    他命之犯行，僅辯稱交付毒品之地點並非在「OK便利超商」\n    內），並以前詞置辯，惟查：\n(一)、證人曾富煌於97年6 月26日於偵查中證稱：其於97年3 月4\n    日下午4 時許，向鄭淑月借用0000000000號行電話撥打被告\n    0000000000號行動電話，向被告表示要購買1,000 元「軟的\n    」（台語）之「海洛因」及500 元「硬的」（台語）之「安\n    非他命」（下稱甲基安非他命）），被告便與其約在楠梓區\n    的消防隊碰面交易，其就載著鄭淑月至該地與被告碰面，雙\n    方見面後，被告要其等跟著他走，就到了OK超商，…在進入\n    超商前，其先從口袋拿1,000 元紙鈔交給鄭淑月，鄭淑月及\n    被告先到飲料區拿飲料，其則在櫃檯買菸，後來其也走到飲\n    料區，被告向其表示飲料下方有毒品，…鄭淑月將前揭1,00\n    0 元紙鈔拿給…被告，被告便拿著千元紙鈔，其拿著上開飲\n    料跟著被告一起去櫃檯付帳，…「（你當天要向甲○○購買\n    1,000 元『軟的』之海洛因及500 元『硬的』之甲基安非他\n    命，為何只交他1,000 元？）因為500 元的甲基安非他命，\n    甲○○沒有向我收錢，算送給我的，因為我是被告的老主顧\n    。」，…當天扣得之毒品是在上開「OK便利超商」向被告買\n    的，…其之前在警詢所述與被告約在該處，要請被告喝飲料\n    是假的，其等是假藉購買飲料，以掩飾交易毒品的過程等語\n    綦詳（偵卷第90-91 頁）；復於97年10月21日於原審證稱：\n    於97年3 月4 日下午4 點許，其載鄭淑月去右昌，中途先與\n    被告在消防隊碰面，被告叫其等一起走，就到1 家「OK便利\n    超商」，…在那邊碰面之原因係其向鄭淑月借手機打電話給\n    被告，要向被告討回手機，並要向被告拿海洛因，其跟被告\n    說跟他約在消防隊，要拿「查某」（海洛因）1,000 元，還\n    有500 元「硬的」（甲基安非他命），…到「OK便利超商」\n    後因其機車沒有熄火，其先拿自己所有的1,000 元給鄭淑月\n    ，請鄭淑月拿給被告，他們兩人一起走進去超商，去拿涼水\n    ，其跟在後面進去買菸，…其三人在櫃檯時，鄭淑月與甲○\n    ○拿涼水，鄭淑月手上拿涼水，其買菸，找完錢走出超商後\n    ，警察就將其等擋下，…「（你說500 元『硬的』是甲○○\n    要請的？）是甲○○在電話中主動跟我講的。」，…（提示\n    上開偵卷第46頁所示3 通電話通聯記錄）鄭淑月0000000000\n    號行動電話撥打給被告0000000000號行動電話之通聯紀錄，\n    那3 通是我打的等語在卷（院卷第93-98 頁）。再者，曾富\n    煌有施用海洛因及甲基安非他命習慣，且於查獲當日為警採\n    尿送驗結果（編號D97078號），確呈甲基安非他命、嗎啡及\n    可待因陽性反應等情，業據證人曾富煌於警詢供述明確（警\n    卷第5-7 頁），並有高雄市立凱旋醫院濫用藥物尿檢報告（\n    轉碼編號：A00000000 ）在卷可憑（偵卷第40頁），足見曾\n    富煌確有施用海洛因及甲基安非他命之習慣，而有向被告購\n    買海洛因毒品施用之動機，且參酌證人曾富煌所稱其係向被\n    告購買毒品之老主顧，自亦難排除被告有附隨贈送甲基安非\n    他命供被告施用之可能；佐以證人曾富煌上開於偵查及原審\n    具結後之證述內容，就其於查獲當日如何與被告聯絡購買毒\n    品及取得毒品之經過，前後相符，並無相互矛盾之情，又與\n    被告持用之0000000000號行動電話與鄭淑月0000000000號行\n    動電話，於查獲當日即97年3 月4 日下午4 時26分59秒、32\n    分52秒、40分44秒許之通聯記錄所示時間，大致相符，綜上\n    各情，其證述當日於電話中向被告表示要購買1,000 元海洛\n    因及500 元甲基安非他命，被告表示甲基安非他命部分無償\n    贈予其施用（意指甲基安非他命部分並非販賣，而係無償轉\n    讓），其乃透過鄭淑月交付1,000 元予被告，向被告購買1,\n    000 元海洛因，被告除交付扣案之海洛因外，並同時無償贈\n    與扣案之甲基安非他命給其等情，應堪採信。至於證人曾富\n    煌為警查獲後，於97年3 月4 日警詢雖供稱：扣案之毒品均\n    係鄭淑月所有云云（偵卷第6 頁），並於同年3 月5 日偵查\n    中供稱：扣案之毒品係鄭淑月向被告購買云云（偵卷第8 頁\n    ），然其嗣於97年6 月26日偵查及97年10月21日原審已更異\n    前詞，並詳述如上，而證人曾淑月迭於警詢、偵查及原審均\n    否認上開毒品係其向被告所購買，且被告於本院已坦承扣案\n    之2 包毒品係其交付給曾富煌施用等語，足認證人曾富煌此\n    部分於警詢及偵查中所述，與事實不符，不可採信。\n(二)、又證人鄭淑月於偵查中證稱：當天是曾富煌向其借手機，撥\n    打電話給被告，向被告購買海洛因及甲基安非他命，曾富煌\n    打電話時，其在曾富煌旁邊，所以其有看到他講電話，曾富\n    煌打電話後就騎乘機車載其，在路上遇到被告，被告就提議\n    到「OK便利超商」，被告說要請其及曾富煌喝飲料，其三人\n    一起到該超商門外時，曾富煌便叫其拿1,000 元給被告買飲\n    料，其在超商門外就從拿1,000 元給被告，其三人一同進入\n    該便利超商內，其和被告到飲料區選飲料，其選了2 罐飲料\n    拿去櫃檯要算錢時，在櫃臺將該2 罐飲料交給被告，被告結\n    帳後其拿起飲料時，便發現其中1 罐飲料下方黏有扣案之2\n    包毒品，所以其確定該2 包毒品是被告黏的沒錯，當時曾富\n    煌則站在其等身旁，…被告拿著該1,000 元結帳後，便將零\n    錢放在口袋了，其三人買完飲料後，剛出便利超商門口就被\n    警方查獲，當時其兩手拿住飲料，扣案毒品則置於飲料下方\n    ，所以毒品是從其手上的飲料查獲的等語（偵卷第65-66 頁\n    ）；並於原審證稱：97年3 月4 日下午4 時許，曾富煌騎機\n    車本來說要載其去找朋友，途中在右昌地區的路上向其借手\n    機，打完後，其和曾富煌在過了「OK便利超商」的消防隊前\n    與被告見面，雙方站在路的兩邊，被告說要去「OK便利超商\n    」，才又回頭到「OK便利超商」，…至「OK便利超商」後，\n    被告叫其去拿涼水，叫其拿了去櫃檯算錢，其拿了2 瓶涼水\n    去櫃檯算錢，由被告結帳，買飲料找的零錢由被告拿走，…\n    其再把涼水拿起來的時候，毒品已經黏在涼水的底下，…員\n    警扣到毒品時，其已經把毒品與涼水拆開，膠布還沒有拿起\n    來，其準備將毒品交給曾富煌，…當天付涼水的錢是曾富煌\n    給被告的，曾富煌在超商門口外面先拿給其1 張1,000 元紙\n    鈔，叫其拿給被告買涼水，其就把錢拿給被告等語（原審卷\n    第87頁背面-92 頁），已就曾富煌於查獲當日下午如何借用\n    其上開行動電話與被告聯絡，及其等三人在消防隊前碰面後\n    一同前往超商購買飲料暨被告交付扣案2 包毒品之經過等情\n    ，均能逐一詳加證述明確，且與證人曾富煌所述向被告購買\n    毒品，及查獲之員警丙○○、乙○○證述其等當日查獲被告\n    及鄭淑月、曾富煌等人之經過等情，大致相符（本院卷第\n    95-100頁）；佐以證人丙○○、乙○○確於被告身上扣得其\n    於超商內以1, 000元購買飲料後所找現金940 元及被告當日\n    下午與曾富煌連聯交易毒品所用之0000000000號行動電話（\n    含SIM 卡），並扣得鄭淑月所有借予曾富煌連聯被告購買毒\n    品所用之0000000000號行動電話（含SIM 卡）及被告交由鄭\n    淑月轉交曾富煌之海洛因及甲基安非他命各1 包，均已如前\n    述，綜上各情，足認證人鄭淑月上開所述，應屬可採。可見\n    曾富煌確於97年3 月4 日下午4 時多許，借用鄭淑月之行動\n    電話，與被告談妥上述交易毒品內容及約定在前揭消防隊前\n    見面，三人再一同前往「OK便利超商」，曾富煌則透過鄭淑\n    月將購買海洛因之價款1,000 元交付被告，並向被告收取購\n    買之海洛因及無償取得之甲基安非他命，雙方並以假藉進入\n    「OK便利超商」選購飲料，鄭淑月則先將1,000 元紙鈔及其\n    選購之飲料交由被告結帳，再由被告趁機將毒品膠黏於飲料\n    底部之方式，連同飲料一併交還鄭淑月  以遂行其販賣海洛\n    因及轉讓甲安非他命予曾富煌之目的。\n(三)、再者，被告於97年4 月29日偵查中亦供稱：我認識曾富煌，\n    但與鄭淑月不熟，查獲當日我最先進入超商，然後鄭淑月走\n    進店內，最後曾富煌走進來，那時候我是站在靠近店門口的\n    收銀櫃檯前，鄭淑月則站在我的左後方，曾富煌站在我的正\n    後方，我有問曾富煌要喝什麼飲料，他說隨便，我沒有問鄭\n    淑月要喝什麼，然後我們三人一起走到飲料區選飲料，我拿\n    了麥片牛奶及養樂多，鄭淑月則選了鋁箔包裝紅茶，曾富煌\n    沒有買飲料他又走開去買煙；是我拿錢出來結帳，但是該1,\n    000 元紙鈔是曾富煌的錢，是鄭淑月親手交給我的，「（為\n    何稱是曾富煌的錢？）因為我那時站在收銀櫃檯前，我有看\n    到店門外曾富煌騎乘機車載鄭淑月前來，在店外他將該1,00\n    0 元紙鈔交給鄭淑月，鄭淑月…交給我的，後來曾富煌才又\n    走進店內，我才會問曾富煌要喝什麼飲料。…我們電話約好\n    後，是先約在加昌路上的消防隊前碰面，然後再一起騎車到\n    該便利超商買飲料。」，我是有拿鄭淑月所稱之飲料給鄭淑\n    月等語（偵卷第49-50 頁）；並於本院供稱：在消防隊前見\n    面之前，曾富煌有先以鄭淑月之行動電話與其聯絡在消防隊\n    前見面，且扣案之海洛因及甲基安非他命係其於查獲前不久\n    交由鄭淑月轉交曾富煌（只辯稱在消防隊前交付），而員警\n    在其身上查扣940 元現金，則是曾富煌經由鄭淑月在超商門\n    口轉交給其1,000 元紙鈔於購買飲料後所找零款等語（本院\n    卷第74-76 頁）；均核與證人曾富煌證稱：其於當日下午4\n    點多借用鄭淑月之行動電話與被告約定消防隊前見面後，其\n    三人再先後進入超商內購買飲料（曾富煌購買香菸），於進\n    入超商之前，其拿1,000 元紙鈔給鄭淑月轉交被告等語，及\n    證人鄭淑月證稱：其依曾富煌之意，於超商門口將1,000 元\n    交給被告，三人進入該便利超商內，其與被告到飲料區選飲\n    料，其在櫃檯將飲料交給被告結帳後，其再拿回自己選購之\n    飲料，扣案之海洛因及甲基安非他命，係被告以膠黏於飲料\n    底部之方式交付等情相符。可見證人曾富煌、鄭淑月等人關\n    於本件販賣毒品之過程所為證述，均非憑空虛構，曾富煌於\n    查獲當日下午4 時多許，借用鄭淑月之行動電話與被告聯繫\n    購買1,000 元海洛因及500 元甲基安非他命，被告除與曾富\n    煌就該1,000 元海洛因買賣之意思表示達成合致外，另允諾\n    無償提供甲基安非他命予曾富煌，雙方於談妥後隨即相約在\n    消防隊前見面，再一同前往「OK便利超商」內交付毒品，且\n    曾富煌於進入超商前，則委請鄭淑月將購毒價金1,000 元交\n    付被告，被告以該1, 000結帳後，即順勢將店員所找940 元\n    放入其口袋，並將毒品黏附鄭淑月選購之飲料底部一併交付\n    鄭淑月，再由鄭淑月將毒品交付曾富煌，以此方式掩飾其販\n    賣海洛因及轉讓甲基安非他命之犯行，應可認定。故被告辯\n    稱：其交付毒品之地點係在消防局前，並非在「OK便利超商\n    」內，且扣案之購買飲料找零940 元是其尚未交還曾富煌之\n    款項，該金錢非其所有云云，顯係欲將其收取鄭淑月所交付\n    之1,000 元（於「OK便利超商」門口附近交付），與其交付\n    扣案之2 包毒品之行為，二者間作適當之切割，塑造成本件\n    只係單純轉讓毒品（實則只有甲基安非他命部分係無償轉讓\n    ），並無買賣價金之交付，以配合其上開辯詞，此由被告於\n    店員找零940 元後隨即放入其口袋，而未連同飲料、毒品一\n    併交由鄭淑月以轉交曾富煌等情，即可明瞭。\n(四)、至於扣案之海洛因、甲基安非他命之外包裝是否殘留膠布黏\n    貼痕跡一事（即最高法院發回意旨(三)，見該判決書第3 頁）\n    ，經本院調取扣案之「海洛因」及「甲基安非他命」證物（\n    含包裝袋）當庭勘驗結果：「扣案「海洛因」係以夾鏈袋\n    包裝，因查獲人員在該包裝袋上貼上標籤以載明毒品重量，\n    且該包毒品又歷經送驗、編號入庫等程序，其包裝袋一面已\n    貼上毒品重量之標籤（0.31）及批號、轉碼等字條，且因黏\n    貼紙條之關係，致無法撕下標籤、紙條以分辨是否曾經留有\n    膠布黏貼之痕跡；而包裝袋另一側並無張貼任何紙條，但無\n    法明顯辨識是否有貼過膠布黏貼痕跡。另扣案「甲基安非\n    他命」係夾鏈袋包裝，亦同上原因，其包裝袋一面已貼上\n    載明毒品重量之標籤（0.22）及批號、轉碼字條，已無法撕\n    下辨明是否留有膠布黏貼痕跡；另一側則無張貼任何紙條，\n    但無法明顯辨識是否有曾黏貼過膠布。」此有本院勘驗筆錄\n    及照片在卷可憑（本院卷第76頁及第81-1頁以下）。然查，\n    證人鄭淑月於原審已證稱：「（警方扣到毒品時，毒品、涼\n    水已經分開？）是，我把它拆開，膠布還沒有拿起來」等語\n    （原審卷第89頁），及查獲員警乙○○於本院證稱：鄭淑月\n    從「OK便利超商」出來，我看到鄭淑月手中有拿2 包毒品及\n    鋁箔裝的飲料，毒品是放在手心，飲料壓在上面，一看就可\n    以看得出來，是我從鄭淑月手中的毒品拿下來的，當時毒品\n    沒有黏著在飲料上等語（本院卷第99頁），可知鄭淑月於超\n    商內取得底部附黏2 包毒品後，即將膠黏之毒品與飲料分開\n    ，故於步出超商時，手中所持飲料及毒品已呈分開狀，又因\n    員警專注於鄭淑月手中之毒品，且飲料並非查緝之違禁物，\n    佐以在毒品交易實務上亦鮮見販毒者將毒品以膠布附著於飲\n    料下方，致員警未能即時發覺被告係以此精心設計之方式遮\n    掩其交付毒品之犯行，而未能將鄭淑月手中飲料（含膠布）\n    一併查扣；另一方面，本件查扣上開2 包毒品至本院勘驗其\n    外包裝袋，前後已相隔2 年多，該毒品包裝袋又歷經查獲、\n    檢院贓物庫及檢驗等人員多次觸摸，復經審理階段一再提示\n    辨識，而當時膠黏毒品之客體又係鄭淑月剛選購之冰冷飲料\n    ，其外包裝已含有微量水氣，且鄭淑月於取得飲料、毒品後\n    又隨即將其分開，故毒品包裝袋與膠布接觸之時間已屬短暫\n    ，本不易殘留易供辨識之膠布貼黏痕跡，惟扣案之2 包毒品\n    既係被告交付予鄭淑月，此為被告所不爭執，並經證人鄭淑\n    月證述明確，復經本院認定如前，若非被告以膠布將毒品黏\n    於飲料底部交付，則證人鄭淑月又豈能虛構如此具體之事實\n    ，自難以飲料及膠布未扣案，且因上開因素而無法勘驗出毒\n    品外包裝袋有無膠布黏貼痕跡，即認鄭淑月前揭關於被告交\n    付毒品之方式為不可採；反之，由被告與曾富煌於電話中談\n    妥販賣海洛因及轉讓甲基安非他命等細節，並在消防隊前見\n    面之時，被告並未將毒品交付曾富煌，而另行邀同前往「OK\n    便利超商」內，以上開迂迴隱避之方式交付毒品，其目的無\n    非係欲避免其上開販賣海洛因及轉讓甲基安非他命之犯行遭\n    他人發覺，才精心設計此一特殊之交易及轉讓毒品模式，以\n    隱藏其於上開「OK便利超商」，販賣1,000 元海洛因及同時\n    轉讓甲基安非他命予曾富煌之事實，至為明確。\n(五)、本件證人鄭淑月雖未及將毒品交付給曾富煌即為警查獲，然\n    查：被告與曾富煌於電話中已達成買賣1,000 元海洛因及轉\n    讓1 小包甲基安非他命毒品之意思合致，曾富煌並透過鄭淑\n    月轉交1,000 元價金給被告，被告再將毒品黏貼於飲料底部\n    之方式，交付毒品給鄭淑月轉交曾富煌等情，已如上述，足\n    見鄭淑月係曾富煌手足之延伸，曾富煌係透過鄭淑月代其支\n    付價金及收受毒品之行為，鄭淑月雖未及將毒品轉交曾富煌\n    即為警查獲，然被告交付毒品給鄭淑月之際，該2 包毒品既\n    已置於曾富煌之實力可得支配之範疇，堪認被告已完成毒品\n    買賣及轉讓之交付行為，自無礙其販賣海洛因及轉讓禁藥即\n    甲基安非他命等犯行既遂之認定。又被告雖僅向曾富煌收取\n    1,000 元，而同時交付海洛因及甲基安非他命各1 包予曾富\n    煌（由鄭淑月代為收受），惟證人曾富煌於97年6 月26日偵\n    查及97年10月21日原審已明確證稱：甲基安非他命被告沒有\n    向其收錢，算送給其的，因為其是被告的老主顧，…之前跟\n    被告買過3 、4 次海洛因、甲基安非他命（詳細次數因時間\n    太久已忘記了）；被告跟其兒子認識，會在其那裡出入，所\n    以當時在電話中也向被告要手機等語（偵卷第90頁及原審卷\n    第93頁背面、94、98頁）；且被告亦供稱：曾富煌是其同學\n    的父親，要還被告之手機，是其向曾富煌兒子曾啟鶴借的等\n    語（偵卷第50頁及97年度聲羈字第262 號卷第4 頁），足見\n    被告與曾富煌熟識，其考量與曾富煌曾有交易毒品之經驗及\n    特殊情誼，及往後尚可繼續交易等因素，於本次曾富煌表示\n    欲購買1,000 元海洛因及500 元甲基安非他命時，只向被告\n    收取販賣1 包海洛因之價金1,000 元，另主動表示願無償轉\n    讓1 小包甲基安非他命供曾富煌施用，並非不可能之事，況\n    且扣案之甲基安非他命數量甚少，是否具有曾富煌原先擬購\n    買之500 元價值，已有可疑，自難以曾富煌向被告表示欲購\n    買500 元甲基安非他命，即逕認被告所轉讓之甲基安非他命\n    具有500 元之價值，將曾富煌該次所購買之1,000 元海洛因\n    與被告轉讓之甲基安非他命二者混為一談，而以被告交付之\n    毒品價值合計1,500 元（即海洛因1,000 元＋甲基安非他命\n    500 元＝1,500 元），竟只向曾富煌收取1,000 元，據以質\n    疑被告販賣海洛因予曾富煌之營利意圖。\n(六)、按販賣毒品本無一定價格，各次買賣之價格，當亦各有差異\n    ，隨供需雙方之資力、關係之深淺、需求之數量、貨源之充\n    裕與否、販賣者對於資金之需求如何即殷切與否，以及政府\n    查緝之態度，進而為各種不同之風險評估，而為機動性之調\n    整，是其價格標準，自非一成不變，且販賣者從各種「價差\n    」或「量差」或係「純度」謀取利潤方式，或有差異，然其\n    所圖利益之非法販賣行為目的，則屬相同，並無二致，故販\n    賣之利得，除被告就販賣之價量俱臻明確供述外，委難察得\n    實情，況一般民眾普遍認知毒品之非法交易，政府一向查禁\n    森嚴，且重罰不寬貸，衡諸常情，倘非有利可圖絕無平白甘\n    冒被重罰高度風險之理，從而，舉凡其「有償交易」，除足\n    反證其確另基於某種非圖利本意之關係外，通常尚難因無法\n    查悉其買進、賣出之差價，而諉無營利之意思，或阻卻販賣\n    犯行之追訴。本件被告有施用毒品之習慣，業據其陳明在卷\n    ，並有臺灣高等法院被告前案紀錄表卷可憑（本院卷第36-4\n    3 頁），其顯已知持有、販賣毒品均為法所不許，且販賣毒\n    品犯行之法定刑度甚重之事實，依一般經驗法則，其苟非意\n    在營利，又何須干冒為警查獲被判重罪之風險，並精心設計\n    以上述假藉購買飲料之方式，藉機將海洛因販賣予曾富煌並\n    收取價金？再佐以被告於本院供稱：查獲那段時間其有在施\n    用海洛因，除扣案交付予曾富煌之海洛因外，其當時已無多\n    餘之海洛因可供施用等語（本院卷第95頁），更可顯示其販\n    賣上開海洛因具有營利意圖。\n(七)、至被告及其辯護人於本院聲請詰問證人曾富煌，欲證明本案\n    查扣之940 元現金是否係被告交付海洛因毒品之對價部分（\n    本院卷第77頁），茲因本件事證已臻明確，且曾富煌於已偵\n    查及原審就此待證事實詳加證述（詳前(一)所述），自無再行\n    傳喚之必要，且該位證人已於原審進行交互詰問，足以確保\n    被告之對質詰問權，併予敘明。\n二、綜上所述，被告前揭所辯，顯係卸責之詞，不足採信。本案\n    事證明確，被告於上開時、地，同時販賣1,000 元之第一級\n    毒品海洛因及轉讓禁藥即第二級毒品甲基安非他命之犯行，\n    均堪認定，應依法論處。\n、論罪科刑及撤銷改判之理由：\n一、比較新舊法：\n    按被告行為後，毒品危害防制條例第4 條第1 項業於98年5\n    月20日修正公佈，修正前毒品危害防制條例第4 條第1 項規\n    定之法定本刑：「製造、運輸、販賣第一級毒品者，處死刑\n    或無期徒刑；處無期徒刑者，得併科新臺幣1 千萬元以下罰\n    金」；修正後規定：「製造、運輸、販賣第一級毒品者，處\n    死刑或無期徒刑；處無期徒刑者，得併科新臺幣2 千萬元以\n    下罰金」。經比較修正前後條文內容，修正後所定罰金刑最\n    高數額較修正前提高，自以修正前之規定較有利於被告，自\n    應適用修正前毒品危害防制條例第4 條第1 項之規定論處。\n二、次按甲基安非他命係毒品危害防制條例第2 條第2 項第2 款\n    所明定之第二級毒品，不得持有、轉讓及販賣。又甲基安非\n    他命為第二級毒品，並經行政院衛生署於75年7 月11日以衛\n    署藥字第597627號重申公告禁止使用在案，迄未變更，仍應\n    認屬藥事法第22條第1 項第1 款所列之禁藥。故行為人明知\n    為禁藥即甲基安非他命而轉讓予他人者，除成立毒品危害防\n    制條例第8 條第2 項之轉讓第二級毒品罪外，亦構成藥事法\n    第83條第1 項之轉讓禁藥罪，此係屬同一犯罪行為而同時有\n    二種法律可資處罰之「法規競合」情形，應依「重法優於輕\n    法」、「後法優於前法」等法理，擇一處斷。而毒品危害防\n    制條例第8 條第2 項轉讓第二級毒品罪之法定本刑為「6 月\n    以上5 年以下有期徒刑，得併科新臺幣70萬元以下罰金」。\n    而93年4 月21日修正後藥事法第83條第1 項轉讓禁藥罪之法\n    定本刑為「7 年以下有期徒刑，得併科新臺幣500 萬元以下\n    罰金」，故除有轉讓之第二級毒品達毒品危害防制條例第8\n    條第6 項之一定數量，經依法加重其刑，致該法定刑較藥事\n    法第83條第1 項之法定刑為重之情形外，因藥事法第83條第\n    1 項為後法，且為重法，應優先適用藥事法處罰（最高法院\n    96年臺上字第3582號判決參照）。本件被告於前揭時、地，\n    無償轉讓甲基安非他命予證人曾富煌之行為，依上開法規競\n    合及重法優於輕法之適用法則，被告轉讓禁藥甲基安非他命\n    予曾富煌之犯行，應適用藥事法論處。\n三、核被告所為，係犯98年5 月20日修正前毒品危害防制條例第\n    4 條第1 項之販賣第一級毒品罪及藥事法第83條第1 項之轉\n    讓禁藥罪。被告持有第一級毒品海洛因及禁藥甲基安非他命\n    之低度行為，均為其販賣海洛因或轉讓甲基安非他命之高度\n    行為所吸收，均不另論罪。公訴意旨認被告上開轉讓甲基安\n    非他命之犯行，係犯修正前毒品危害防制條例第4 條第2 項\n    之販賣第二級毒品罪，惟被告就此交付甲基安非他命1 小包\n    之行為並未獲取對價，業如前述，是被告此部分犯行尚無販\n    賣第二級毒品罪可言，公訴人就此部分尚有誤會，惟其社會\n    基本事實既同一，爰依法變更起訴法條改依藥事法第83條第\n    1 項之罪論處。被告一行為同時觸犯販賣第一級毒品罪及轉\n    讓禁藥罪，為想像競合犯，應從一重依修正前毒品危害防制\n    條例第4 條第1 項之販賣第一級毒品罪處斷。被告有如犯罪\n    事實欄一所載之犯罪科刑執行情形，有上開前案紀錄表在卷\n    卷可稽，其於徒刑執行完畢後，於5 年內故意再犯本件有期\n    徒刑以上之二罪，均為累犯，應依刑法第47條第1 項規定加\n    重其刑，其中販賣第一級毒品罪關於死刑、無期徒刑部分，\n    依法不得加重，僅就法定刑中關於罰金部分加重其刑。又同\n    為販賣第一級毒品之人，其原因、動機不一，犯罪情節未必\n    盡同，或有大盤毒梟者，亦有中、小盤之分，甚或僅止於吸\n    毒者同儕間為求互通有無之有償轉讓者亦有之，其販賣行為\n    所造成危害社會之程度自屬有異，法律科處此類犯罪所設之\n    法定最低本刑卻同為無期徒刑，不可謂為不重。本件被告販\n    賣第一級毒品之犯行僅有1 次，且販賣數量輕微，犯罪所得\n    僅1,000 元，犯罪情節難與大盤毒梟者相提併論，即令處以\n    最低刑度即無期徒刑而禁錮終身，仍有致情法失平之處，誠\n    屬情輕法重，難謂符合刑罰之相當性，爰依刑法第59條規定\n    減輕其刑。被告就販賣第一級毒品犯行，有前揭刑之加重及\n    減輕事由，惟販賣第一級毒品罪關於死刑、無期徒刑部分，\n    依法不得加重，僅就法定刑中關於罰金刑部分先加後減之。\n四、原審予以被告論科，固非無見。惟查：\n(一)、被告行為後，毒品危害防制條例第4 條第1 項已於98年5 月\n    20日業經修正公布，經綜合比較結果，以修正後之規定較有\n    利於被告。原判決未及比較適用，已有未恰。\n(二)、又意圖營利係販賣毒品罪之構成要件，此一要件須於事實欄\n    詳載，並於理由欄說明其所憑認定之依據。原判決既未於事\n    實欄記載，復未說明其所憑認定之依據，自屬理由不備。\n(三)、被告轉讓甲基安非他命應依藥事法第83條第1 項之轉讓禁藥\n    罪論處；惟原判決論以毒品危害防制條例第8 條第2 項之轉\n    讓第二級毒品罪，亦有適用法則不當之違誤。\n五、被告上訴意旨，仍執前詞，否認販賣第一級毒品犯罪，固無\n    足取，然原判決既有上述可議，自應由本院將原判決此部分\n    撤銷改判。本院審酌被告為牟私利而販賣第一級毒品海洛因\n    及轉讓禁藥（甲基安非他命），殘害國民身心健康，足使社\n    會施用毒品人口增加，而相對提高社會負成本，減損勞動生\n    產力，影響社會層面至深且鉅，惟販賣對象僅有曾富煌1 人\n    ，實際販賣所得僅1, 000元等一切情狀，仍量處如主文第2\n    項所示之刑；並考量本案被告販賣第一級毒品之犯罪性質，\n    而有褫奪公權之必要，併依刑法第37條第2 項規定，宣告褫\n    奪公權5 年，以示懲儆。又扣案之海洛因、甲基安非他命各\n    1 小包（驗前淨重分別為0.104 公克、0.024 公克；驗餘淨\n    重分別為0.096 公克、0.014 公克）雖屬第一、二級毒品，\n    惟業經被告販賣、轉讓而交付予曾富煌，並經原審法院於判\n    決事實欄所載之鄭淑月持有第一、二級毒品及曾富煌施用第\n    一、二級毒品等案件宣告沒收銷燬，並已執行完畢（此有其\n    等之刑事判決及臺灣高等法院被告前案紀錄表可憑），爰不\n    予重複宣告沒收銷燬。再扣案之行動電話1 具（含門號0000\n    000000號SIM 卡），為被告所有，業據其供述在卷（原審卷\n    第137 頁），並有上開門號之申請人資料1 紙可證（偵查卷\n    第43頁），該行動電話及SIM 卡既均為被告所有，作為本件\n    販賣海洛因之聯絡工具，係供本件犯罪所用之物，均應依毒\n    品危害防制條例第19條第1 項之規定宣告沒收。又被告販賣\n    第一級毒品海洛因命予曾富煌，得款1,000 元（僅扣得940\n    元），係被告犯販賣第一級毒品罪所得財物，應依毒品危害\n    防制條例第19條第1 項規定宣告沒收；其中未扣案之60元部\n    分，如全部或一部不能沒收時，則以其財產抵償之。\n肆、被告被訴販賣第二級毒品甲基安非他命予廖俊豪部分，業經\n    原審判決無罪確定，爰不論列，一併敘明。\n據上論結，應依刑事訴訟法第369 條第1 項前段、第364 條、第\n300 條、第299 條第1 項前段，藥事法第83條第1 項，98年5 月\n20日修正前毒品危害防制條例第4 條第1 項、第19條第1 項，刑\n法第2 項第1 項前段、第11條前段、第37條第2 項、第47條第1\n項、第55條、第59條，判決如主文。\n本案經檢察官孫小玲到庭執行職務。\n中    華    民    國    99    年    5     月    12    日\n                  刑事第三庭    審判長法  官   莊崑山\n                                      法  官   莊松泉\n                                      法  官   唐照明\n以上正本證明與原本無異。\n如不服本判決應於收受本判決後10日內向本院提出上訴書狀，其\n未敘述上訴理由者，並得於提起上訴後10日內向本院補提理由書\n狀（均須按他造當事人之人數附繕本）「切勿逕送上級法院」。"
  },
  "characters": {
    "judges": [
      "莊崑山",
      "莊松泉",
      "唐照明"
    ],
    "prosecutors": [
      "孫小玲"
    ],
    "lawyers": [
      "邱基峻",
      "張宗琦"
    ],
    "clerks": [
      "黃琳群"
    ],
    "plaintiffs": [

    ],
    "defendants": [
      "甲"
    ],
    "prosecutor_office": [

    ],
    "creditors": [

    ],
    "debtors": [

    ],
    "judicial_associate_officer": [

    ]
  },
  "adjudged_at": "2010-05-12",
  "created_at": "2016-01-05 12:02:44",
  "updated_at": "2016-01-05 12:02:44"
}