{
  "identify": "KSH-98-上易-1033-20100104-1",
  "court": {
    "name": "臺灣高等法院",
    "code": "KSH"
  },
  "division": {
    "name": "刑事",
    "code": "M"
  },
  "year": 98,
  "word": "上易",
  "number": "1033",
  "jcheck": "1",
  "reason": "妨害自由等",
  "content": "臺灣高等法院高雄分院刑事判決        98年度上易字第1033號\n    上  訴  人  臺灣高雄地方法院檢察署檢察官\n    被      告  丁○○\n    被      告  甲○○\n    被      告  乙○○\n    被      告  丙○○\n上列上訴人因被告妨害自由等案件，不服臺灣高雄地方法院98年\n度易字第880 號中華民國98年11月30日第一審判決（起訴案號：\n臺灣高雄地方法院檢察署98年度偵字第12996 號），提起上訴，\n本院判決如下：\n    主  文\n上訴駁回。\n    理  由\n一、依刑事訴訟法第350 條、第361 條、第362 條、第367 條規\n    定，不服地方法院之第一審判決而上訴者，須提出上訴書狀\n    ，並應敘述具體理由，為上訴必備之程式；其所提出之書狀\n    未敘述上訴理由，或僅曾以言詞陳述上訴理由者，均應於上\n    訴期間屆滿後20日內補提理由書於第一審法院。第一審法院\n    經形式審查，認逾期未補提上訴理由者，應定期間先命補正\n    ；逾期未補正者，為上訴不合法律上之程式，應以裁定駁回\n    。倘已提出上訴理由，但所提非屬具體理由者，則由第二審\n    法院以上訴不合法律上之程式，判決駁回。而所謂具體理由\n    ，必係依據卷內既有訴訟資料或提出新事證，指摘或表明第\n    一審判決有何採證認事、用法或量刑等足以影響判決本旨之\n    不當或違法，而構成應予撤銷之具體事由，始克當之（例如\n    ：依憑證據法則具體指出所採證據何以不具證據能力，或依\n    憑卷證資料，明確指出所為證據證明力之判斷如何違背經驗\n    、論理法則）；倘僅泛言原判決認定事實錯誤、違背法令、\n    量刑失之過重或輕縱，而未依上揭意旨指出具體事由，或形\n    式上雖已指出具體事由，然該事由縱使屬實，亦不足以認為\n    原判決有何不當或違法者（例如：對不具有調查必要性之證\n    據，法院未依聲請調查亦未說明理由，或援用證據不當，但\n    除去該證據仍應為同一事實之認定），皆難謂係具體理由，\n    俾與第二審上訴制度旨在請求第二審法院撤銷、變更第一審\n    不當或違法之判決，以實現個案救濟之立法目的相契合，此\n    有最高法院97年台上字第892 號判決意旨可參照。\n二、本件公訴人循告訴人請求上訴意旨略以：被告4 人犯罪後拒\n    不與告訴人和解，犯罪後態度不佳，原審分別判處被告丁○\n    ○、丙○○拘役25日、被告甲○○拘役30日、被告乙○○應\n    執行拘役30日，如易科罰金均以新台幣1,000 元折算1 日，\n    量刑過輕等語，指摘原判決不當云云。然查：原審量刑已審\n    酌被告甲○○有前科，且構成累犯，然被告4 人犯後均坦承\n    犯行，態度尚可，但被告4 人至今均尚未與告訴人達成和解\n    等情，公訴人上訴未說明原審此部分審酌，有何違背論理法\n    則之處，則空言指摘原判決量刑過輕，難謂合法。綜上，上\n    訴意旨或未依據卷內既有訴訟資料或提出新事證，指摘或表\n    明第一審判決有何採證認事、用法或量刑等足以影響判決本\n    旨之不當或違法，而構成應予撤銷之具體事由，揆諸上開法\n    條規定及最高法院判決意旨，難認上訴合法，應予駁回。爰\n    不經言詞辯論，依刑事訴訟法第367 條前段、第372 條規定\n    ，判決如主文。\n中    華    民    國    99    年    1     月    4     日\n              刑事第二庭    審判長法  官  林正雄\n                                  法  官  陳啟造\n                                  法  官  黃壽燕\n以上正本證明與原本無異。\n不得上訴。\n中    華    民    國    99    年    1     月    4     日\n                                  書記官  鄭翠芬\n附錄本判決論罪科刑法條：\n刑法第304 條\n以強暴、脅迫使人行無義務之事或妨害人行使權利者，處3 年以\n下有期徒刑、拘役或3 百元以下罰金。\n前項之未遂犯罰之。\n刑法第354 條\n毀棄、損壞前2 條以外之他人之物或致令不堪用，足以生損害於\n公眾或他人者，處2 年以下有期徒刑、拘役或5 百元以下罰金。",
  "structure": {
    "main": "上訴駁回。",
    "reason": "一、依刑事訴訟法第350 條、第361 條、第362 條、第367 條規\n    定，不服地方法院之第一審判決而上訴者，須提出上訴書狀\n    ，並應敘述具體理由，為上訴必備之程式；其所提出之書狀\n    未敘述上訴理由，或僅曾以言詞陳述上訴理由者，均應於上\n    訴期間屆滿後20日內補提理由書於第一審法院。第一審法院\n    經形式審查，認逾期未補提上訴理由者，應定期間先命補正\n    ；逾期未補正者，為上訴不合法律上之程式，應以裁定駁回\n    。倘已提出上訴理由，但所提非屬具體理由者，則由第二審\n    法院以上訴不合法律上之程式，判決駁回。而所謂具體理由\n    ，必係依據卷內既有訴訟資料或提出新事證，指摘或表明第\n    一審判決有何採證認事、用法或量刑等足以影響判決本旨之\n    不當或違法，而構成應予撤銷之具體事由，始克當之（例如\n    ：依憑證據法則具體指出所採證據何以不具證據能力，或依\n    憑卷證資料，明確指出所為證據證明力之判斷如何違背經驗\n    、論理法則）；倘僅泛言原判決認定事實錯誤、違背法令、\n    量刑失之過重或輕縱，而未依上揭意旨指出具體事由，或形\n    式上雖已指出具體事由，然該事由縱使屬實，亦不足以認為\n    原判決有何不當或違法者（例如：對不具有調查必要性之證\n    據，法院未依聲請調查亦未說明理由，或援用證據不當，但\n    除去該證據仍應為同一事實之認定），皆難謂係具體理由，\n    俾與第二審上訴制度旨在請求第二審法院撤銷、變更第一審\n    不當或違法之判決，以實現個案救濟之立法目的相契合，此\n    有最高法院97年台上字第892 號判決意旨可參照。\n二、本件公訴人循告訴人請求上訴意旨略以：被告4 人犯罪後拒\n    不與告訴人和解，犯罪後態度不佳，原審分別判處被告丁○\n    ○、丙○○拘役25日、被告甲○○拘役30日、被告乙○○應\n    執行拘役30日，如易科罰金均以新台幣1,000 元折算1 日，\n    量刑過輕等語，指摘原判決不當云云。然查：原審量刑已審\n    酌被告甲○○有前科，且構成累犯，然被告4 人犯後均坦承\n    犯行，態度尚可，但被告4 人至今均尚未與告訴人達成和解\n    等情，公訴人上訴未說明原審此部分審酌，有何違背論理法\n    則之處，則空言指摘原判決量刑過輕，難謂合法。綜上，上\n    訴意旨或未依據卷內既有訴訟資料或提出新事證，指摘或表\n    明第一審判決有何採證認事、用法或量刑等足以影響判決本\n    旨之不當或違法，而構成應予撤銷之具體事由，揆諸上開法\n    條規定及最高法院判決意旨，難認上訴合法，應予駁回。爰\n    不經言詞辯論，依刑事訴訟法第367 條前段、第372 條規定\n    ，判決如主文。"
  },
  "characters": {
    "judges": [
      "林正雄",
      "陳啟造",
      "黃壽燕"
    ],
    "prosecutors": [

    ],
    "lawyers": [

    ],
    "clerks": [
      "鄭翠芬"
    ],
    "plaintiffs": [

    ],
    "defendants": [
      "丁○○",
      "乙○○"
    ],
    "prosecutor_office": [

    ],
    "creditors": [

    ],
    "debtors": [

    ],
    "judicial_associate_officer": [

    ]
  },
  "adjudged_at": "2010-01-04",
  "created_at": "2016-01-05 14:39:27",
  "updated_at": "2016-01-05 14:39:27"
}