{
  "identify": "KSH-99-上訴-383-20100512-1",
  "court": {
    "name": "臺灣高等法院",
    "code": "KSH"
  },
  "division": {
    "name": "刑事",
    "code": "M"
  },
  "year": 99,
  "word": "上訴",
  "number": "383",
  "jcheck": "1",
  "reason": "偽證",
  "content": "臺灣高等法院高雄分院刑事判決         99年度上訴字第383號\n上  訴  人  臺灣高雄地方法院檢察署檢察官\n被      告  丁○○\n上列上訴人因被告偽證案件，不服臺灣高雄地方法院98年度訴字\n第1662號中華民國98年12月30日第一審判決（起訴案號：臺灣高\n雄地方法院檢察署98年度偵字第16993 號），提起上訴，本院判\n決如下：\n    主  文\n上訴駁回。\n    理  由\n一、公訴意旨略以：被告丁○○前係土地代書，明知其自民國84\n    年6 月28日起至85年10月8 日止，係受陳萬吉之託，將附表\n    編號1 至7 所示丙○○、乙○○及甲○○名下之土地及建物\n    之所有權，分別移轉登記至陳仁閔及陳仁貴名下。嗣於94年\n    6 月14日上午10時16分許，在臺灣高雄地方法院檢察署（下\n    簡稱高雄地檢署）94年度偵續字第103 號陳仁貴等人偽造文\n    書等案件偵查中，以證人身分出庭應訊，經檢察官令其具結\n    後，詢問其：「本件當事人為何會委任你承辦？」時，竟虛\n    偽證稱：「那是雙方來我的辦公室辦的……」等語之不實事\n    項，足生損害於司法機關偵查及審理之正確性，因認被告涉\n    有刑法第168 條之偽證罪嫌云云。\n二、按犯罪事實應依證據認定之，無證據不得認定犯罪事實；不\n    能證明被告犯罪者，應諭知無罪之判決，刑事訴訟法第 154\n    條第2 項及第301 條第1 項分別定有明文。又按認定不利於\n    被告之事實，須依積極證據，苟積極證據不足為不利於被告\n    之認定時，即應為有利於被告之認定；認定犯罪事實所憑之\n    證據，雖不以直接證據為限，間接證據亦包括在內，然而無\n    論直接或間接證據，其為訴訟上之證明，須於通常一般之人\n    均不致有所懷疑，而得確信其為真實之程度者，始得據為有\n    罪之認定，最高法院30年上字第816 號及76年臺上字第4986\n    號判例意旨可資參照。另按檢察官就被告犯罪事實，應負舉\n    證責任，並指出證明之方法，是檢察官對於起訴之犯罪事實\n    ，應負提出證據及說服之實質舉證責任，倘其所提出之證據\n    ，不足為被告有罪之積極證明，或其指出證明之方法，無從\n    說服法院以形成被告有罪之心證，基於無罪推定之原則，自\n    不能為被告有罪之判決，最高法院92年臺上字第128 號判例\n    意旨亦可資參照。\n三、公訴意旨認被告丁○○涉有偽證罪嫌，無非係以被告於偵查\n    中之供述、證人陳雄河之證詞及告發人甲○○、乙○○、丙\n    ○○之指訴、臺灣高雄地方法院檢察署94年度偵續字第103\n    號卷附之偵訊筆錄及證人結文等為其主要論據。惟訊據被告\n    丁○○則堅決否認有何偽證之犯行，辯稱：伊當時在偵訊時\n    並不是說當時雙方當事人（丙○○、乙○○、甲○○及陳仁\n    閔及陳仁貴）有到辦公室來辦理，而是說「如果」雙方證件\n    齊全，伊就幫他們辦理，是檢察官誤解伊之意思等語。\n四、經查：\n（一）被告丁○○確於94年6 月14日上午10時16分許，在高雄地\n      檢署檢察官偵查時，以證人身分於該署94年度偵續字第10\n      3 號偽造文書等案件中作證，供前具結後，並於檢察官訊\n      問「本件之當事人為何會委任你承辦？」時，其答覆經筆\n      錄載為「那是雙方來我的辦公室要我辦的」云云，固有該\n      次偵訊筆錄附卷可稽（偵二卷106 頁）。惟經原審勘驗上\n      開案件94年6 月14日之偵訊錄音帶內容，當時檢察官係訊\n      問被告：「本件之當事人為何會將案件交給你辦？」，被\n      告係答稱：「我『如果』承辦案件，雙方當事人有來，證\n      件齊全我就幫他辦」等語，業經原審法院勘驗屬實，並製\n      有勘驗筆錄在卷可稽（原審卷22頁、第33頁），足見上開\n      檢察官於94年6 月14日上午10時16分許，在該案（臺灣高\n      雄地方法院檢察署94年度偵續字第103 號偽造文書等案件\n      ）所製作關於證人即被告丁○○所供述之內容，已有誤載\n      其所供述之意旨。是依被告當時於偵訊中所證述之文義觀\n      之，其係表示【倘】雙方當事人共同前來時，只要證件齊\n      全，其即可代為辦理之意，足見被告於該案作證時，並未\n      針對前開不動產之所有權移轉登記一事究係何人共同前來\n      伊辦公室委託前開不動產之所有權移轉登記有明確之證述\n      ，更未證稱該案係由陳萬吉、丙○○、乙○○及甲○○等\n      人共同前往其辦公室委託辦理等情，已甚顯明。又由被告\n      於當日偵訊中復供稱：（本件之相關證件是何人提供？）\n      是何人拿來的，已經過很久，我記不清了，但是【應該】\n      是雙方拿來的等語（偵二卷108 頁）。惟按被告既已供稱\n      不記得相關證件係由何人拿來，則何以又能證稱：該案是\n      由「雙方來我的辦公室辦的」等語，足見被告上開偵訊筆\n      錄內容中【應該】是雙方拿來云云，應屬個人推測之詞，\n      尚難認被告已就該部分明確證述：「本案不動產移轉登記\n      係由陳萬吉、丙○○、乙○○及甲○○等人共同前往被告\n      辦公室洽辦」，是被告上開所辯：伊並未於前開偵訊中證\n      稱：『那是雙方來我的辦公室要我辦的』等語，洵非無據\n      。又參諸原審勘驗被告當時之證述：「我【如果】承辦案\n      件……」及「細節我都忘了」等語以觀，被告確因時間久\n      遠，只能就其承辦案件之原則大致陳述，並未具體就細節\n      指證，故尚難對被告遽以偽證罪相繩。\n（二）另證人陳雄河之證言及告發人甲○○、乙○○、丙○○之\n      指訴，僅足認定被告係受陳萬吉委託代為辦理上開不動產\n      所有權移轉登記之情，惟均尚難認其於偵訊作證時故為虛\n      偽之陳述。此外，復查無其他證據足證被告有檢察官所指\n      偽證之犯行，揆諸前開說明，被告犯罪即屬不能證明，自\n      應為其無罪之諭知。\n五、原審以不能證明被告丁○○犯偽證罪，而為其無罪之諭知，\n    核無違誤；檢察官上訴意旨，猶執前詞，指摘原判決不當，\n    為無理由，應予駁回。\n據上論斷，應依刑事訴訟法第368 條，判決如主文。\n本案經檢察官陳建年到庭執行職務。\n中    華    民    國    99    年    5     月    12    日\n                    刑事第十庭  審判長法  官 陳中和\n                                      法  官 林水城\n                                      法  官 李政庭\n以上正本證明與原本無異。\n如不服本判決應於收受本判決後10日內向本院提出上訴書狀，其\n未敘述上訴理由者，並得於提起上訴後10日內向本院補提理由書\n狀（均須按他造當事人之人數附繕本）「切勿逕送上級法院」。\n中    華    民    國    99    年    5     月    12    日\n                                      書記官 周青玉",
  "structure": {
    "main": "上訴駁回。",
    "reason": "一、公訴意旨略以：被告丁○○前係土地代書，明知其自民國84\n    年6 月28日起至85年10月8 日止，係受陳萬吉之託，將附表\n    編號1 至7 所示丙○○、乙○○及甲○○名下之土地及建物\n    之所有權，分別移轉登記至陳仁閔及陳仁貴名下。嗣於94年\n    6 月14日上午10時16分許，在臺灣高雄地方法院檢察署（下\n    簡稱高雄地檢署）94年度偵續字第103 號陳仁貴等人偽造文\n    書等案件偵查中，以證人身分出庭應訊，經檢察官令其具結\n    後，詢問其：「本件當事人為何會委任你承辦？」時，竟虛\n    偽證稱：「那是雙方來我的辦公室辦的……」等語之不實事\n    項，足生損害於司法機關偵查及審理之正確性，因認被告涉\n    有刑法第168 條之偽證罪嫌云云。\n二、按犯罪事實應依證據認定之，無證據不得認定犯罪事實；不\n    能證明被告犯罪者，應諭知無罪之判決，刑事訴訟法第 154\n    條第2 項及第301 條第1 項分別定有明文。又按認定不利於\n    被告之事實，須依積極證據，苟積極證據不足為不利於被告\n    之認定時，即應為有利於被告之認定；認定犯罪事實所憑之\n    證據，雖不以直接證據為限，間接證據亦包括在內，然而無\n    論直接或間接證據，其為訴訟上之證明，須於通常一般之人\n    均不致有所懷疑，而得確信其為真實之程度者，始得據為有\n    罪之認定，最高法院30年上字第816 號及76年臺上字第4986\n    號判例意旨可資參照。另按檢察官就被告犯罪事實，應負舉\n    證責任，並指出證明之方法，是檢察官對於起訴之犯罪事實\n    ，應負提出證據及說服之實質舉證責任，倘其所提出之證據\n    ，不足為被告有罪之積極證明，或其指出證明之方法，無從\n    說服法院以形成被告有罪之心證，基於無罪推定之原則，自\n    不能為被告有罪之判決，最高法院92年臺上字第128 號判例\n    意旨亦可資參照。\n三、公訴意旨認被告丁○○涉有偽證罪嫌，無非係以被告於偵查\n    中之供述、證人陳雄河之證詞及告發人甲○○、乙○○、丙\n    ○○之指訴、臺灣高雄地方法院檢察署94年度偵續字第103\n    號卷附之偵訊筆錄及證人結文等為其主要論據。惟訊據被告\n    丁○○則堅決否認有何偽證之犯行，辯稱：伊當時在偵訊時\n    並不是說當時雙方當事人（丙○○、乙○○、甲○○及陳仁\n    閔及陳仁貴）有到辦公室來辦理，而是說「如果」雙方證件\n    齊全，伊就幫他們辦理，是檢察官誤解伊之意思等語。\n四、經查：\n（一）被告丁○○確於94年6 月14日上午10時16分許，在高雄地\n      檢署檢察官偵查時，以證人身分於該署94年度偵續字第10\n      3 號偽造文書等案件中作證，供前具結後，並於檢察官訊\n      問「本件之當事人為何會委任你承辦？」時，其答覆經筆\n      錄載為「那是雙方來我的辦公室要我辦的」云云，固有該\n      次偵訊筆錄附卷可稽（偵二卷106 頁）。惟經原審勘驗上\n      開案件94年6 月14日之偵訊錄音帶內容，當時檢察官係訊\n      問被告：「本件之當事人為何會將案件交給你辦？」，被\n      告係答稱：「我『如果』承辦案件，雙方當事人有來，證\n      件齊全我就幫他辦」等語，業經原審法院勘驗屬實，並製\n      有勘驗筆錄在卷可稽（原審卷22頁、第33頁），足見上開\n      檢察官於94年6 月14日上午10時16分許，在該案（臺灣高\n      雄地方法院檢察署94年度偵續字第103 號偽造文書等案件\n      ）所製作關於證人即被告丁○○所供述之內容，已有誤載\n      其所供述之意旨。是依被告當時於偵訊中所證述之文義觀\n      之，其係表示【倘】雙方當事人共同前來時，只要證件齊\n      全，其即可代為辦理之意，足見被告於該案作證時，並未\n      針對前開不動產之所有權移轉登記一事究係何人共同前來\n      伊辦公室委託前開不動產之所有權移轉登記有明確之證述\n      ，更未證稱該案係由陳萬吉、丙○○、乙○○及甲○○等\n      人共同前往其辦公室委託辦理等情，已甚顯明。又由被告\n      於當日偵訊中復供稱：（本件之相關證件是何人提供？）\n      是何人拿來的，已經過很久，我記不清了，但是【應該】\n      是雙方拿來的等語（偵二卷108 頁）。惟按被告既已供稱\n      不記得相關證件係由何人拿來，則何以又能證稱：該案是\n      由「雙方來我的辦公室辦的」等語，足見被告上開偵訊筆\n      錄內容中【應該】是雙方拿來云云，應屬個人推測之詞，\n      尚難認被告已就該部分明確證述：「本案不動產移轉登記\n      係由陳萬吉、丙○○、乙○○及甲○○等人共同前往被告\n      辦公室洽辦」，是被告上開所辯：伊並未於前開偵訊中證\n      稱：『那是雙方來我的辦公室要我辦的』等語，洵非無據\n      。又參諸原審勘驗被告當時之證述：「我【如果】承辦案\n      件……」及「細節我都忘了」等語以觀，被告確因時間久\n      遠，只能就其承辦案件之原則大致陳述，並未具體就細節\n      指證，故尚難對被告遽以偽證罪相繩。\n（二）另證人陳雄河之證言及告發人甲○○、乙○○、丙○○之\n      指訴，僅足認定被告係受陳萬吉委託代為辦理上開不動產\n      所有權移轉登記之情，惟均尚難認其於偵訊作證時故為虛\n      偽之陳述。此外，復查無其他證據足證被告有檢察官所指\n      偽證之犯行，揆諸前開說明，被告犯罪即屬不能證明，自\n      應為其無罪之諭知。\n五、原審以不能證明被告丁○○犯偽證罪，而為其無罪之諭知，\n    核無違誤；檢察官上訴意旨，猶執前詞，指摘原判決不當，\n    為無理由，應予駁回。\n據上論斷，應依刑事訴訟法第368 條，判決如主文。\n本案經檢察官陳建年到庭執行職務。"
  },
  "characters": {
    "judges": [
      "陳中和",
      "林水城",
      "李政庭"
    ],
    "prosecutors": [
      "陳建年"
    ],
    "lawyers": [

    ],
    "clerks": [

    ],
    "plaintiffs": [

    ],
    "defendants": [
      "丁○○"
    ],
    "prosecutor_office": [

    ],
    "creditors": [

    ],
    "debtors": [

    ],
    "judicial_associate_officer": [

    ]
  },
  "adjudged_at": "2010-05-12",
  "created_at": "2016-01-05 12:01:55",
  "updated_at": "2016-01-05 12:01:55"
}