{
  "identify": "KSH-99-聲-17-20100105-1",
  "court": {
    "name": "臺灣高等法院",
    "code": "KSH"
  },
  "division": {
    "name": "刑事",
    "code": "M"
  },
  "year": 99,
  "word": "聲",
  "number": "17",
  "jcheck": "1",
  "reason": "聲請付保護管束",
  "content": "臺灣高等法院高雄分院刑事裁定            99年度聲字第17號\n聲  請  人  臺灣高等法院高雄分院檢察署檢察官\n受  刑  人  甲○○\n上列受刑人因聲請付保護管束案件，經聲請人聲請付保護管束，\n本院裁定如下：\n    主  文\n甲○○假釋中付保護管束。\n    理  由\n查本件受刑人甲○○前犯毒品危害防制條例等罪，經本院判處應\n執行有期徒刑10年10月，嗣經最高法院駁回上訴確定執行在案。\n茲聲請人以受刑人甲○○業於民國98年12月25日核准假釋在案，\n而縮短刑期後終結日期為101 年6 月14日，聲請於其假釋中付保\n護管束等情。本院審核無異，應依刑事訴訟法第481 條第1 項，\n刑法第93條第2 項、第96條但書，裁定如主文。\n中    華    民    國    99    年    1     月    5     日\n                  刑事第九庭    審判長法  官  莊秋桃\n                                      法  官  謝宏宗\n                                      法  官  范惠瑩\n以上正本證明與原本無異。\n不得抗告。\n中    華    民    國    99    年    1     月    5     日\n                                      書記官  許信宗",
  "structure": {
    "main": "甲○○假釋中付保護管束。",
    "reason": "查本件受刑人甲○○前犯毒品危害防制條例等罪，經本院判處應\n執行有期徒刑10年10月，嗣經最高法院駁回上訴確定執行在案。\n茲聲請人以受刑人甲○○業於民國98年12月25日核准假釋在案，\n而縮短刑期後終結日期為101 年6 月14日，聲請於其假釋中付保\n護管束等情。本院審核無異，應依刑事訴訟法第481 條第1 項，\n刑法第93條第2 項、第96條但書，裁定如主文。"
  },
  "characters": {
    "judges": [
      "莊秋桃",
      "謝宏宗",
      "范惠瑩"
    ],
    "prosecutors": [

    ],
    "lawyers": [

    ],
    "clerks": [

    ],
    "plaintiffs": [

    ],
    "defendants": [

    ],
    "prosecutor_office": [
      "臺灣高等法院高雄分院檢察署檢察官"
    ],
    "creditors": [

    ],
    "debtors": [

    ],
    "judicial_associate_officer": [

    ]
  },
  "adjudged_at": "2010-01-05",
  "created_at": "2016-01-05 15:11:18",
  "updated_at": "2016-01-05 15:11:18"
}