{
  "identify": "KSH-98-上更(一)-3-20100104-2",
  "court": {
    "name": "臺灣高等法院",
    "code": "KSH"
  },
  "division": {
    "name": "民事",
    "code": "V"
  },
  "year": 98,
  "word": "上更(一)",
  "number": "3",
  "jcheck": "2",
  "reason": "返還擔保金",
  "content": "臺灣高等法院高雄分院民事裁定         98年度上更(一)字第3號\n上訴人即附\n帶被上訴人  甲○○\n            乙○○\n上列二人共同\n訴訟代理人  戴國石律師\n被上訴人即\n附帶上訴人  香港商捷時海外貿易有限公司台灣分公司\n                      設臺北市○○區○○街94號3樓\n法定代理人  蕭靜芳    住同上\n訴訟代理人  林炎平律師\n上列當事人間請求返還擔保金等事件，本院裁定如下：\n      主      文\n本件准由蕭靜芳為被上訴人香港商捷時海外貿易有限公司台灣分\n公司之法定代理人承受訴訟。\n      理      由\n一、按，訴訟程序於裁判送達後當然停止者，其承受訴訟之聲明\n    ，由為裁判之原法院裁定之，民事訴訟法第177 條第3 項定\n    有明文。\n二、經查，本件被上訴人香港商捷時海外貿易有限公司台灣分公\n    司之法定代理人已於民國98年10月30日變更為蕭靜芳，茲由\n    蕭靜芳聲明承受訴訟，並提出經濟部函及認許事項變更表為\n    證，經核屬實，應予准許。\n三、依民事訴訟法第177 條第3 項，裁定如主文。\n中    華    民    國    99    年    1     月    4     日\n                            民事第三庭\n                                審判長法官  張國彬\n                                法      官  吳登輝\n                                法      官  鄭月霞\n以上正本證明與原本無異。\n如不服本裁定應於送達後10日內向本院提出抗告狀（並按他造當\n事人之人數附繕本），並繳納抗告費新臺幣1,000 元。\n中    華    民    國    99    年    1     月    4     日\n                                書  記  官  白  蘭",
  "structure": {
    "main": "本件准由蕭靜芳為被上訴人香港商捷時海外貿易有限公司台灣分\n公司之法定代理人承受訴訟。",
    "reason": "一、按，訴訟程序於裁判送達後當然停止者，其承受訴訟之聲明\n    ，由為裁判之原法院裁定之，民事訴訟法第177 條第3 項定\n    有明文。\n二、經查，本件被上訴人香港商捷時海外貿易有限公司台灣分公\n    司之法定代理人已於民國98年10月30日變更為蕭靜芳，茲由\n    蕭靜芳聲明承受訴訟，並提出經濟部函及認許事項變更表為\n    證，經核屬實，應予准許。\n三、依民事訴訟法第177 條第3 項，裁定如主文。"
  },
  "characters": {
    "judges": [
      "吳登輝",
      "鄭月霞"
    ],
    "prosecutors": [

    ],
    "lawyers": [
      "戴國石",
      "林炎平"
    ],
    "clerks": [

    ],
    "plaintiffs": [

    ],
    "defendants": [

    ],
    "prosecutor_office": [

    ],
    "creditors": [

    ],
    "debtors": [

    ],
    "judicial_associate_officer": [

    ]
  },
  "adjudged_at": "2010-01-04",
  "created_at": "2016-01-05 14:40:40",
  "updated_at": "2016-01-05 14:40:40"
}