{
  "identify": "KSH-99-上訴-454-20100512-1",
  "court": {
    "name": "臺灣高等法院",
    "code": "KSH"
  },
  "division": {
    "name": "刑事",
    "code": "M"
  },
  "year": 99,
  "word": "上訴",
  "number": "454",
  "jcheck": "1",
  "reason": "妨害兵役",
  "content": "臺灣高等法院高雄分院刑事判決         99年度上訴字第454號\n上  訴  人  臺灣高雄地方法院檢察署檢察官\n被      告  甲○○\n上列上訴人因被告妨害兵役案件，不服臺灣高雄地方法院98年度\n訴字第1660號中華民國99年1 月13日第一審判決（起訴案號：臺\n灣高雄地方法院檢察署98年度偵緝字第1996號），提起上訴，本\n院判決如下：\n    主  文\n上訴駁回。\n    理  由\n一、公訴意旨略以：被告甲○○為役齡男子，竟意圖避免徵兵處\n    理，於民國97年初遷出其戶籍地高雄市○○區○○路55巷1\n    弄1 號，無故不申報，亦不與居住於戶籍地之家人聯繫，致\n    高雄市鼓山區公所於同年5 月8 日及8 月7 日所發送之徵兵\n    檢查通知書均未能送達於其本人，代收受之其姐林欣樺及其\n    母張美玉，亦無從轉告此一訊息，致未能接受徵兵處理，因\n    認被告涉嫌違反妨害兵役治罪條例第3 條第5 款之妨害役男\n    徵兵處理罪嫌（起訴書誤載為同條例第5 條第3 款之罪，惟\n    此業經原審公訴檢察官當庭更正如上，參見原審卷一第13-1\n    頁）。\n二、按犯罪事實應依證據認定之，無證據不得認定犯罪事實；不\n    能證明被告犯罪者，應諭知無罪之判決，刑事訴訟法第154\n    條第2 項、第301 條第1 項前段分別定有明文。復事實之認\n    定，應憑證據，如未能發現相當證據，或證據不足以證明，\n    自不能以推測或擬制之方法，為裁判基礎；又認定不利於被\n    告之事實，須依積極證據，苟積極證據不足為不利於被告事\n    實之認定時，即應為有利被告之認定，更不必有何有利之證\n    據；再認定犯罪事實，所憑之證據，雖不以直接證據為限，\n    間接證據亦包括在內，然無論直接或間接證據，其為訴訟上\n    之證明，須於通常一般之人均不致於有所懷疑，而得確信其\n    為真實之程度者，始得據之為有罪之認定，倘其證明尚未達\n    到此一程度，而有合理性懷疑之存在時，即無從為有罪之認\n    定（最高法院30年上字第816 號、40年臺上字第86號、76年\n    臺上字第4986號判例意旨參照）。\n三、證據能力部分：\n    按被告以外之人於審判外之陳述，雖不符刑事訴訟法第159\n    條之1 至之4 之規定，然經當事人於審判程序同意作為證據\n    ，法院審酌該言詞陳述或書面陳述作成時之情況，認為適當\n    者，亦得為證據，同法第159 條之5 第1 項定有明文。除上\n    開所述外，本判決下列所引用之證據，屬被告以外之人在審\n    判外陳述之傳聞證據部分，除依刑事訴訟法第159 條之1 至\n    第159 條第4 規定得為證據者外，其餘業經被告及檢察官於\n    審理中同意作為證據（本院卷第27頁），本院審酌該等傳聞\n    證據作成時之狀況，並無違法或不當等不宜作為證據之情形\n    ，依前開說明，亦得作為證據。\n四、檢察官認被告涉犯前開罪嫌，係以卷附高雄市鼓山區徵兵通\n    知書收據及高雄市立民生醫院未到檢名冊為其主要論據。訊\n    據被告堅決否認有何上開妨害役男徵兵處理之犯行，辯稱：\n    其於97年1 月間離開矯正機關後，雖曾短暫住過戶籍地，但\n    因為與家人關係不好，故過完農曆年後到3 月間就搬出去，\n    其不怕當兵，沒有避免徵兵處理之意圖等語。經查：\n(一)、按妨害兵役治罪條例第3 條第5 款所定：「役齡男子意圖避\n    免徵兵處理，而居住處所遷移，無故不申報，致未能接受徵\n    兵處理者」，係以「意圖避免徵兵處理」為其主觀構成要件\n    ，故被告是否成立該罪名，自應審酌有無避免徵兵處理之意\n    圖，且應由檢察官對於被告是否具有「意圖避免召集處理」\n    之主觀犯意，指出證明之方法。又按刑法之故意，係指認識\n    犯罪之構成事實，且進而決定為其行為之意思，而決定行為\n    之意思，皆有一定之遠因，即「動機」，通常動機與犯罪之\n    成立無關，或以之為科刑時應予審酌之事項，或為減刑之要\n    件，或為加重之要件，但於特殊之犯罪，若以之為主觀不法\n    構成要件之構成要素者，如刑法分則中規定以「意圖」為成\n    立要件之罪，法律既明定為犯罪構成要件，則動機已成為犯\n    罪內容之一部，不得再視為一般之動機，故目的犯（意圖犯\n    ）在主觀上除須具備犯罪故意之構成要件外，尚須具備法定\n    之不法意圖，否則其犯罪即無以成立，上開妨害兵役之罪，\n    既以行為人具有「意圖避免徵兵處理」為其主觀犯罪構成要\n    件，則並非行為人明知居住處所遷移有申報義務，即可逕認\n    其係以避免徵兵為不申報之積極目的，故尚難僅以行為人住\n    所遷移未申報，即推認其主觀上有避免召集之意圖。\n(二)、本件被告係77年12月18日出生之役齡男子，設籍於高雄市○\n    ○區○○路55巷1 弄1 號，嗣因遷出上開居住處所，致使高\n    雄市鼓山區公所兵役課分別於97年4 月25日、97年7 月24日\n    指定被告應於97年5 月8 日、97年8 月7 日前往參加役男徵\n    兵檢查之通知書無法送達等情，有被告戶籍資料、前開高雄\n    市鼓山區徵兵通知書收據及高雄市立民生醫院未到檢名冊在\n    卷可查（偵卷二第1-8 頁），且為被告所不爭執，是被告係\n    役齡男子，於遷出上開戶籍地後未依規定申報，致使前開徵\n    兵檢查通知書無法送達之事實，固堪認定。惟被告是否成立\n    上開妨害役男徵兵處理罪，仍需審酌被告是否具有「意圖避\n    免召集處理」之主觀犯意？經查：\n  1.按一般人遷移居住處所未依規定申報之原因及目的不一而足\n    ，諸如至外地求學、工作、避債、避仇或生性疏懶等情，均\n    有可能，並非僅止於「意圖避免徵兵處理」一端，自不得僅\n    以被告明知或應知有此申報義務而未依規定申報，即遽予推\n    認其主觀上有避免徵兵處理之意圖；再佐以我國社會現況，\n    實際上並未居住於戶籍地之情形非少，如僅因被告具有役男\n    之身分，遽認其未據實申報戶籍遷移必係出於避免徵兵處理\n    之意圖，顯有悖於一般生活經驗及論理法則。\n  2.本件被告前有多次逃家記錄，並多次接受矯治教育，最後1\n    次於95年11月6 日進入彰化少輔院接受感化教育，於97年1\n    月22日甫因停止感化教育出院等情，有臺灣高等法院被告前\n    案紀錄表在卷可查（原審卷二第17-21 頁及本院卷第16-1頁\n    ）；又被告家屬於接獲上開役男徵兵檢查通知書後，因被告\n    長期離家出走不知去向，而無法將徵兵之訊息轉知被告，被\n    告之父親林登文乃於97年5 月22日，向高雄市政府警察局鼓\n    山分局內惟派出所通報協尋之事實，業經本院向該局函查屬\n    實，並有該局內惟派出所受理各類案件紀錄表及處理失蹤人\n    口案件登記表暨資料報表可憑（本院卷第36-39 頁），可知\n    被告確因其個人與其家庭成員間互動之徵兵以外其他因素，\n    於本案徵兵檢查通知之前，已長時間遷移上開戶藉地在外居\n    住，並曾進入彰化少輔院接受感化教育至97年1 月22日，出\n    所後雖短暫停留在家，然不久又離家在外居住，其家人並不\n    知其去向而無法與其連繫，故被告辯稱：其自13歲起就有逃\n    學、逃家紀錄，於97年初自彰化感化院關出來，於過完農曆\n    年後（註：97年農曆初一至初五之時間為97年2 月7 日至11\n    日），就偷跑出來在外租屋工作，做麵包店學徒，平時都沒\n    有跟家人聯繫，後於97年12月、98年1 月左右才與家人聯絡\n    ，其姐姐林欣樺才向其表示有兵單通知等語，應可採信。\n  3.被告既因與其家人關係不佳，才未告知家人獨自外出工作，\n    且未住於上開戶籍地，茲因被告家人於收受徵兵檢查通知後\n    ，無法於規定應到場接受徵兵檢查時間之前連繫到被告本人\n    ，被告父親才向內惟派出所報案請求協尋，被告則在不知情\n    之情況下未到場接受徵兵檢查，可見被告並非基於「避免徵\n    兵處理」之積極目的，而故意未將其住居所遷移之事據實申\n    報，難認其主觀上具有避免徵兵處理之意圖，核與妨害兵役\n    治罪條例第3 條第5 款之妨害役男徵兵處理罪之主觀構成要\n    件不符。\n五、綜上所述，足見被告前開所辯，應屬可採，被告客觀上雖有\n    上開妨害兵役治罪條例第3 條第5 款之役齡男子於遷出戶籍\n    地後未依規定申報，致使前開徵兵檢查通知書無法送達之客\n    觀行為，但既無法證明被告主觀上有避免徵兵處理之意圖，\n    本院尚無從依檢察官所舉之前開事證，形成有罪之心證，自\n    難論以被告涉犯同條例第3 條第5 款之妨害役男徵兵處理罪\n    。此外，復查無其他積極證據足資證明被告有檢察官所指之\n    妨害役男徵兵處理之犯行，本件既不能證明被告犯罪，揆諸\n    上開說明，自應諭知被告為無罪之判決。\n六、原審因而以不能證明被告犯罪，而為被告無罪之諭知，核無\n    違誤。檢察官上訴，仍執陳詞，指摘原判決不當，為無理由\n    ，應予駁回。\n七、被告被訴詐欺部分，業經原審判處有期徒刑3 月確定，自不\n    另論列，附此敘明。\n據上論結，應依刑事訴訟法368條，判決如主文。\n本案經檢察官孫小玲到庭執行職務。\n中    華    民    國    99    年    5     月    12    日\n                  刑事第三庭    審判長法  官   莊崑山\n                                      法  官   莊松泉\n                                      法  官   唐照明\n以上正本證明與原本無異。\n如不服本判決應於收受本判決後10日內向本院提出上訴書狀，其\n未敘述上訴理由者，並得於提起上訴後10日內向本院補提理由書\n狀（均須按他造當事人之人數附繕本）「切勿逕送上級法院」。\n中    華    民    國    99    年    5     月    12    日\n                                      書記官   黃琳群",
  "structure": {
    "main": "上訴駁回。",
    "reason": "一、公訴意旨略以：被告甲○○為役齡男子，竟意圖避免徵兵處\n    理，於民國97年初遷出其戶籍地高雄市○○區○○路55巷1\n    弄1 號，無故不申報，亦不與居住於戶籍地之家人聯繫，致\n    高雄市鼓山區公所於同年5 月8 日及8 月7 日所發送之徵兵\n    檢查通知書均未能送達於其本人，代收受之其姐林欣樺及其\n    母張美玉，亦無從轉告此一訊息，致未能接受徵兵處理，因\n    認被告涉嫌違反妨害兵役治罪條例第3 條第5 款之妨害役男\n    徵兵處理罪嫌（起訴書誤載為同條例第5 條第3 款之罪，惟\n    此業經原審公訴檢察官當庭更正如上，參見原審卷一第13-1\n    頁）。\n二、按犯罪事實應依證據認定之，無證據不得認定犯罪事實；不\n    能證明被告犯罪者，應諭知無罪之判決，刑事訴訟法第154\n    條第2 項、第301 條第1 項前段分別定有明文。復事實之認\n    定，應憑證據，如未能發現相當證據，或證據不足以證明，\n    自不能以推測或擬制之方法，為裁判基礎；又認定不利於被\n    告之事實，須依積極證據，苟積極證據不足為不利於被告事\n    實之認定時，即應為有利被告之認定，更不必有何有利之證\n    據；再認定犯罪事實，所憑之證據，雖不以直接證據為限，\n    間接證據亦包括在內，然無論直接或間接證據，其為訴訟上\n    之證明，須於通常一般之人均不致於有所懷疑，而得確信其\n    為真實之程度者，始得據之為有罪之認定，倘其證明尚未達\n    到此一程度，而有合理性懷疑之存在時，即無從為有罪之認\n    定（最高法院30年上字第816 號、40年臺上字第86號、76年\n    臺上字第4986號判例意旨參照）。\n三、證據能力部分：\n    按被告以外之人於審判外之陳述，雖不符刑事訴訟法第159\n    條之1 至之4 之規定，然經當事人於審判程序同意作為證據\n    ，法院審酌該言詞陳述或書面陳述作成時之情況，認為適當\n    者，亦得為證據，同法第159 條之5 第1 項定有明文。除上\n    開所述外，本判決下列所引用之證據，屬被告以外之人在審\n    判外陳述之傳聞證據部分，除依刑事訴訟法第159 條之1 至\n    第159 條第4 規定得為證據者外，其餘業經被告及檢察官於\n    審理中同意作為證據（本院卷第27頁），本院審酌該等傳聞\n    證據作成時之狀況，並無違法或不當等不宜作為證據之情形\n    ，依前開說明，亦得作為證據。\n四、檢察官認被告涉犯前開罪嫌，係以卷附高雄市鼓山區徵兵通\n    知書收據及高雄市立民生醫院未到檢名冊為其主要論據。訊\n    據被告堅決否認有何上開妨害役男徵兵處理之犯行，辯稱：\n    其於97年1 月間離開矯正機關後，雖曾短暫住過戶籍地，但\n    因為與家人關係不好，故過完農曆年後到3 月間就搬出去，\n    其不怕當兵，沒有避免徵兵處理之意圖等語。經查：\n(一)、按妨害兵役治罪條例第3 條第5 款所定：「役齡男子意圖避\n    免徵兵處理，而居住處所遷移，無故不申報，致未能接受徵\n    兵處理者」，係以「意圖避免徵兵處理」為其主觀構成要件\n    ，故被告是否成立該罪名，自應審酌有無避免徵兵處理之意\n    圖，且應由檢察官對於被告是否具有「意圖避免召集處理」\n    之主觀犯意，指出證明之方法。又按刑法之故意，係指認識\n    犯罪之構成事實，且進而決定為其行為之意思，而決定行為\n    之意思，皆有一定之遠因，即「動機」，通常動機與犯罪之\n    成立無關，或以之為科刑時應予審酌之事項，或為減刑之要\n    件，或為加重之要件，但於特殊之犯罪，若以之為主觀不法\n    構成要件之構成要素者，如刑法分則中規定以「意圖」為成\n    立要件之罪，法律既明定為犯罪構成要件，則動機已成為犯\n    罪內容之一部，不得再視為一般之動機，故目的犯（意圖犯\n    ）在主觀上除須具備犯罪故意之構成要件外，尚須具備法定\n    之不法意圖，否則其犯罪即無以成立，上開妨害兵役之罪，\n    既以行為人具有「意圖避免徵兵處理」為其主觀犯罪構成要\n    件，則並非行為人明知居住處所遷移有申報義務，即可逕認\n    其係以避免徵兵為不申報之積極目的，故尚難僅以行為人住\n    所遷移未申報，即推認其主觀上有避免召集之意圖。\n(二)、本件被告係77年12月18日出生之役齡男子，設籍於高雄市○\n    ○區○○路55巷1 弄1 號，嗣因遷出上開居住處所，致使高\n    雄市鼓山區公所兵役課分別於97年4 月25日、97年7 月24日\n    指定被告應於97年5 月8 日、97年8 月7 日前往參加役男徵\n    兵檢查之通知書無法送達等情，有被告戶籍資料、前開高雄\n    市鼓山區徵兵通知書收據及高雄市立民生醫院未到檢名冊在\n    卷可查（偵卷二第1-8 頁），且為被告所不爭執，是被告係\n    役齡男子，於遷出上開戶籍地後未依規定申報，致使前開徵\n    兵檢查通知書無法送達之事實，固堪認定。惟被告是否成立\n    上開妨害役男徵兵處理罪，仍需審酌被告是否具有「意圖避\n    免召集處理」之主觀犯意？經查：\n  1.按一般人遷移居住處所未依規定申報之原因及目的不一而足\n    ，諸如至外地求學、工作、避債、避仇或生性疏懶等情，均\n    有可能，並非僅止於「意圖避免徵兵處理」一端，自不得僅\n    以被告明知或應知有此申報義務而未依規定申報，即遽予推\n    認其主觀上有避免徵兵處理之意圖；再佐以我國社會現況，\n    實際上並未居住於戶籍地之情形非少，如僅因被告具有役男\n    之身分，遽認其未據實申報戶籍遷移必係出於避免徵兵處理\n    之意圖，顯有悖於一般生活經驗及論理法則。\n  2.本件被告前有多次逃家記錄，並多次接受矯治教育，最後1\n    次於95年11月6 日進入彰化少輔院接受感化教育，於97年1\n    月22日甫因停止感化教育出院等情，有臺灣高等法院被告前\n    案紀錄表在卷可查（原審卷二第17-21 頁及本院卷第16-1頁\n    ）；又被告家屬於接獲上開役男徵兵檢查通知書後，因被告\n    長期離家出走不知去向，而無法將徵兵之訊息轉知被告，被\n    告之父親林登文乃於97年5 月22日，向高雄市政府警察局鼓\n    山分局內惟派出所通報協尋之事實，業經本院向該局函查屬\n    實，並有該局內惟派出所受理各類案件紀錄表及處理失蹤人\n    口案件登記表暨資料報表可憑（本院卷第36-39 頁），可知\n    被告確因其個人與其家庭成員間互動之徵兵以外其他因素，\n    於本案徵兵檢查通知之前，已長時間遷移上開戶藉地在外居\n    住，並曾進入彰化少輔院接受感化教育至97年1 月22日，出\n    所後雖短暫停留在家，然不久又離家在外居住，其家人並不\n    知其去向而無法與其連繫，故被告辯稱：其自13歲起就有逃\n    學、逃家紀錄，於97年初自彰化感化院關出來，於過完農曆\n    年後（註：97年農曆初一至初五之時間為97年2 月7 日至11\n    日），就偷跑出來在外租屋工作，做麵包店學徒，平時都沒\n    有跟家人聯繫，後於97年12月、98年1 月左右才與家人聯絡\n    ，其姐姐林欣樺才向其表示有兵單通知等語，應可採信。\n  3.被告既因與其家人關係不佳，才未告知家人獨自外出工作，\n    且未住於上開戶籍地，茲因被告家人於收受徵兵檢查通知後\n    ，無法於規定應到場接受徵兵檢查時間之前連繫到被告本人\n    ，被告父親才向內惟派出所報案請求協尋，被告則在不知情\n    之情況下未到場接受徵兵檢查，可見被告並非基於「避免徵\n    兵處理」之積極目的，而故意未將其住居所遷移之事據實申\n    報，難認其主觀上具有避免徵兵處理之意圖，核與妨害兵役\n    治罪條例第3 條第5 款之妨害役男徵兵處理罪之主觀構成要\n    件不符。\n五、綜上所述，足見被告前開所辯，應屬可採，被告客觀上雖有\n    上開妨害兵役治罪條例第3 條第5 款之役齡男子於遷出戶籍\n    地後未依規定申報，致使前開徵兵檢查通知書無法送達之客\n    觀行為，但既無法證明被告主觀上有避免徵兵處理之意圖，\n    本院尚無從依檢察官所舉之前開事證，形成有罪之心證，自\n    難論以被告涉犯同條例第3 條第5 款之妨害役男徵兵處理罪\n    。此外，復查無其他積極證據足資證明被告有檢察官所指之\n    妨害役男徵兵處理之犯行，本件既不能證明被告犯罪，揆諸\n    上開說明，自應諭知被告為無罪之判決。\n六、原審因而以不能證明被告犯罪，而為被告無罪之諭知，核無\n    違誤。檢察官上訴，仍執陳詞，指摘原判決不當，為無理由\n    ，應予駁回。\n七、被告被訴詐欺部分，業經原審判處有期徒刑3 月確定，自不\n    另論列，附此敘明。\n據上論結，應依刑事訴訟法368條，判決如主文。\n本案經檢察官孫小玲到庭執行職務。"
  },
  "characters": {
    "judges": [
      "莊崑山",
      "莊松泉",
      "唐照明"
    ],
    "prosecutors": [
      "孫小玲"
    ],
    "lawyers": [

    ],
    "clerks": [

    ],
    "plaintiffs": [

    ],
    "defendants": [
      "甲○○"
    ],
    "prosecutor_office": [

    ],
    "creditors": [

    ],
    "debtors": [

    ],
    "judicial_associate_officer": [

    ]
  },
  "adjudged_at": "2010-05-12",
  "created_at": "2016-01-05 12:02:53",
  "updated_at": "2016-01-05 12:02:53"
}