{
  "identify": "KSH-98-附民-97-20100105-1",
  "court": {
    "name": "臺灣高等法院",
    "code": "KSH"
  },
  "division": {
    "name": "刑事",
    "code": "M"
  },
  "year": 98,
  "word": "附民",
  "number": "97",
  "jcheck": "1",
  "reason": "損害賠償",
  "content": "臺灣高等法院高雄分院刑事附帶民事訴訟判決\n原      告  未○○\n被      告  甲○○\n            Ａ○○\n            宇○○\n            Ｏ○○原名顏銘震.\n            巳○○\n            Ｐ○○\n            丁○○\n            Ｄ○○\n            Ｊ○○\n            Ｆ○○\n            子○○原名吳俊德.\n            Ｍ○○\n            申○○\n            Ｃ○○\n            乙○○原名史雅茜.\n            黃○○\n            Ｌ○○原名蔡宜庭.\n            辛○○\n            Ｑ○○\n            酉○○\n            戌○○\n            辰○○原名林詩怡.\n            Ｎ○○\n            庚○○\n            Ｅ○○原名黃彩惠.\n            Ｂ○○原名馮志群.\n            丙○○原名史恆華.\n            午○○\n            己○○\n            戊○○\n            卯○○\n            Ｋ○○\n            宙○○\n            Ｈ○○\n            地○○\n            天○○\n            Ｇ○○\n            玄○○\n            亥○○\n            癸○○\n            丑○○\n            寅○○原名李裙鳳.\n            壬○○\n            Ｉ○○○\n上列被告因98年度上重訴字第23號常業詐欺案件，經原告提起附\n帶民事訴訟，請求損害賠償，本院判決如下：\n    主  文\n原告之訴及假執行之聲請均駁回。\n    事實及理由\n一、原告陳述略稱：求為判決被告等人應給付原告新台幣（下同\n    ）54萬元及加計之法定遲延利息，並陳明願供擔保，聲請為\n    假執行之宣告，並援用刑事訴訟之證據。\n    被告等人辯稱略以：請求駁回原告之訴及假執行之聲請。並\n    援用刑事訴訟所為之陳述，即不承認有何常業詐欺之侵權行\n    為。\n二、按刑事訴訟諭知無罪，免訴或不受理之判決者，對於附帶民\n    事訴訟部分應以判決駁回原告之訴，刑事訴訟法第503 條第\n    1 項前段定有明文。\n三、經查本院98年度上重訴字第23號被告甲○○等44人被訴常業\n    詐欺案件，業經本院判決被告等44人無罪（臺灣高雄地方法\n    院諭知被告等44人均無罪，檢察官不服原判決提起上訴後，\n    亦經本院判決上訴駁回）在案。揆諸首揭說明，本件原告之\n    訴，自應予以駁回；而其本訴既經駁回，假執行之聲請即失\n    所附麗，應併予駁回。\n據上論斷，應依訟法第503 條第1 項前段，判決如主文。\n中    華    民    國    99    年     1     月    5    日\n                    刑事第三庭  審判長法  官  莊崑山\n                                      法  官  唐照明\n                                      法  官  張意聰\n以上正本證明與原本無異。\n本判決非對於刑事訴訟之判決有上訴時不得上訴。\n如不服本判決應於收受本判決後10日內向本院提出上訴書狀，並\n應敘述具體理由，如未敘述上訴理由者，應於上訴期間屆滿後20\n日內補提理由書狀於本院（均須按他造當事人之人數附繕本）「\n切勿逕送上級法院」。\n中    華    民    國    99    年     1     月    5    日\n                                      書記官  陳金",
  "structure": {
    "main": "原告之訴及假執行之聲請均駁回。",
    "fact": "一、原告陳述略稱：求為判決被告等人應給付原告新台幣（下同\n    ）54萬元及加計之法定遲延利息，並陳明願供擔保，聲請為\n    假執行之宣告，並援用刑事訴訟之證據。\n    被告等人辯稱略以：請求駁回原告之訴及假執行之聲請。並\n    援用刑事訴訟所為之陳述，即不承認有何常業詐欺之侵權行\n    為。\n二、按刑事訴訟諭知無罪，免訴或不受理之判決者，對於附帶民\n    事訴訟部分應以判決駁回原告之訴，刑事訴訟法第503 條第\n    1 項前段定有明文。\n三、經查本院98年度上重訴字第23號被告甲○○等44人被訴常業\n    詐欺案件，業經本院判決被告等44人無罪（臺灣高雄地方法\n    院諭知被告等44人均無罪，檢察官不服原判決提起上訴後，\n    亦經本院判決上訴駁回）在案。揆諸首揭說明，本件原告之\n    訴，自應予以駁回；而其本訴既經駁回，假執行之聲請即失\n    所附麗，應併予駁回。\n據上論斷，應依訟法第503 條第1 項前段，判決如主文。",
    "reason": "一、原告陳述略稱：求為判決被告等人應給付原告新台幣（下同\n    ）54萬元及加計之法定遲延利息，並陳明願供擔保，聲請為\n    假執行之宣告，並援用刑事訴訟之證據。\n    被告等人辯稱略以：請求駁回原告之訴及假執行之聲請。並\n    援用刑事訴訟所為之陳述，即不承認有何常業詐欺之侵權行\n    為。\n二、按刑事訴訟諭知無罪，免訴或不受理之判決者，對於附帶民\n    事訴訟部分應以判決駁回原告之訴，刑事訴訟法第503 條第\n    1 項前段定有明文。\n三、經查本院98年度上重訴字第23號被告甲○○等44人被訴常業\n    詐欺案件，業經本院判決被告等44人無罪（臺灣高雄地方法\n    院諭知被告等44人均無罪，檢察官不服原判決提起上訴後，\n    亦經本院判決上訴駁回）在案。揆諸首揭說明，本件原告之\n    訴，自應予以駁回；而其本訴既經駁回，假執行之聲請即失\n    所附麗，應併予駁回。\n據上論斷，應依訟法第503 條第1 項前段，判決如主文。"
  },
  "characters": {
    "judges": [
      "莊崑山",
      "唐照明",
      "張意聰"
    ],
    "prosecutors": [

    ],
    "lawyers": [

    ],
    "clerks": [

    ],
    "plaintiffs": [
      "未○○"
    ],
    "defendants": [
      "甲○○"
    ],
    "prosecutor_office": [

    ],
    "creditors": [

    ],
    "debtors": [

    ],
    "judicial_associate_officer": [

    ]
  },
  "adjudged_at": "2010-01-05",
  "created_at": "2016-01-05 15:09:23",
  "updated_at": "2016-01-05 15:09:23"
}