{
  "identify": "KSH-99-上易-419-20100512-1",
  "court": {
    "name": "臺灣高等法院",
    "code": "KSH"
  },
  "division": {
    "name": "刑事",
    "code": "M"
  },
  "year": 99,
  "word": "上易",
  "number": "419",
  "jcheck": "1",
  "reason": "業務過失傷害",
  "content": "臺灣高等法院高雄分院刑事判決         99年度上易字第419號\n上  訴  人\n即 自 訴人    乙○○\n被      告    甲○○\n上列上訴人因被告業務過失傷害案件，不服臺灣高雄地方法院99\n年度審自字第2 號中華民國99年3 月23日第一審判決，提起上訴\n，本院判決如下：\n    主  文\n上訴駁回。\n    理  由\n一、自訴意旨略以：被告甲○○係國軍左營醫院腸胃科醫師，於\n    民國（以下同）94年3 月9 日為自訴人乙○○之夫程搢作胃\n    視鏡檢查時，因醫療疏失，怠於業務上必要之注意，麻醉過\n    量中毒，致程搢左半邊臉麻痺、眼睛模糊、食無知覺，造成\n    身體嚴重傷害等情，因認被告甲○○涉有刑法第284 條第2\n    項之業務過失傷害罪嫌。\n二、按提起自訴，應委任律師行之。自訴人未委任代理人，法院\n    應定期間以裁定命其委任代理人；逾期仍不委任者，應諭知\n    不受理之判決。另同一案件經檢察官依第228 條規定開始偵\n    查者，不得再行自訴。但告訴乃論之罪，經犯罪之直接被害\n    人提起自訴者，不在此限。不得提起自訴而提起者，應諭知\n    不受理之判決。諭知不受理之判決，並得不經言詞辯論為之\n    ，刑事訴訟法第343 條、第319 條第2 項、第329 條第2 項\n    、第323 條第1 項、第334 條及第307 條分別定有明文。\n三、經查：本件自訴人乙○○提起自訴時，並未委任律師為代理\n    人，經原審於99年1 月26日當庭告知須委任律師為自訴代理\n    人之相關規定，及未委任律師之法律效果，並裁定命其5 日\n    內委任律師為自訴代理人，如逾期未補正，則諭知不受理之\n    判決，有99年1 月26日原審筆錄可稽，惟自訴人乙○○並未\n    於期限內委任律師為自訴代理人。再者，自訴人之夫程搢於\n    94年8 月17日死亡，於死亡之前，曾以：「被告係國軍左營\n    醫院內科部腸胃科之醫師。程搢於94年3 月8 日因貧血及下\n    背痛症狀，前往國軍左營醫院就診，並住院接受治療，期間\n    主治醫師鍾立民建議進行胃視鏡檢查，以查明是否因腸胃道\n    異常出血導致貧血，程搢乃於同年月9 日接受被告施作上消\n    化道內視鏡檢查，檢查前被告讓程搢吞食麻醉劑麻醉食道，\n    惟因被告施用麻醉劑過量，導致檢查後，程搢視力受損模糊\n    ，且臉部麻痺」為由，認被告甲○○涉有業務過失傷害罪嫌\n    ，向國防部南部地方軍事法院檢察署提起告訴，經該署移由\n    臺灣高雄地方法院檢察署檢察官偵查後，認被告甲○○罪嫌\n    不足，於95年5 月5 日以94年度偵字第24737 號處分書為不\n    起訴處分等情，有戶役政資料、臺灣高等法院被告前案紀錄\n    表及前開不起訴處分書可參。準此，上開事實既經自訴人之\n    夫程搢提起告訴，並經檢察官偵查終結，認被告甲○○罪嫌\n    不足，而為不起訴處分，則參酌上開說明，自訴人乙○○係\n    程搢之妻，就程搢遭被告甲○○涉嫌業務過失傷害部分，並\n    非犯罪之直接被害人，於檢察官開始偵查、偵查終結後，自\n    不得再就同一案件提起自訴。又因本件自訴狀所載之犯罪事\n    實及被告，核與上開經不起訴處分之犯罪事實及被告相同，\n    自屬同一案件，自訴人於同一案件偵查終結後，再就同一案\n    件提起自訴，於法有違。從而，因自訴人乙○○提起自訴未\n    補正委任律師為代理人，且就不得提起自訴之案件提起自訴\n    ，揆諸前揭規定，自應諭知不受理之判決。\n四、原審以自訴人乙○○提起自訴未補正委任律師為代理人，且\n    就不得提起自訴之案件再行提起自訴，依法諭知不受理之判\n    決，核無不合，自訴人乙○○上訴指摘原判決不當，為無理\n    由，應予駁回，並不經言詞辯論而為判決。\n五、據上論斷，應依刑事訴訟法第368 條、第372 條，判決如主\n    文。\n中    華    民    國    99    年    5     月    12    日\n                  刑事第八庭    審判長法  官  洪兆隆\n                                      法  官  郭玫利\n                                      法  官  張盛喜\n以上正本證明與原本無異。\n不得上訴。\n中    華    民    國    99    年    5     月    12    日\n                                      書記官  黃一秋",
  "structure": {
    "main": "上訴駁回。",
    "reason": "一、自訴意旨略以：被告甲○○係國軍左營醫院腸胃科醫師，於\n    民國（以下同）94年3 月9 日為自訴人乙○○之夫程搢作胃\n    視鏡檢查時，因醫療疏失，怠於業務上必要之注意，麻醉過\n    量中毒，致程搢左半邊臉麻痺、眼睛模糊、食無知覺，造成\n    身體嚴重傷害等情，因認被告甲○○涉有刑法第284 條第2\n    項之業務過失傷害罪嫌。\n二、按提起自訴，應委任律師行之。自訴人未委任代理人，法院\n    應定期間以裁定命其委任代理人；逾期仍不委任者，應諭知\n    不受理之判決。另同一案件經檢察官依第228 條規定開始偵\n    查者，不得再行自訴。但告訴乃論之罪，經犯罪之直接被害\n    人提起自訴者，不在此限。不得提起自訴而提起者，應諭知\n    不受理之判決。諭知不受理之判決，並得不經言詞辯論為之\n    ，刑事訴訟法第343 條、第319 條第2 項、第329 條第2 項\n    、第323 條第1 項、第334 條及第307 條分別定有明文。\n三、經查：本件自訴人乙○○提起自訴時，並未委任律師為代理\n    人，經原審於99年1 月26日當庭告知須委任律師為自訴代理\n    人之相關規定，及未委任律師之法律效果，並裁定命其5 日\n    內委任律師為自訴代理人，如逾期未補正，則諭知不受理之\n    判決，有99年1 月26日原審筆錄可稽，惟自訴人乙○○並未\n    於期限內委任律師為自訴代理人。再者，自訴人之夫程搢於\n    94年8 月17日死亡，於死亡之前，曾以：「被告係國軍左營\n    醫院內科部腸胃科之醫師。程搢於94年3 月8 日因貧血及下\n    背痛症狀，前往國軍左營醫院就診，並住院接受治療，期間\n    主治醫師鍾立民建議進行胃視鏡檢查，以查明是否因腸胃道\n    異常出血導致貧血，程搢乃於同年月9 日接受被告施作上消\n    化道內視鏡檢查，檢查前被告讓程搢吞食麻醉劑麻醉食道，\n    惟因被告施用麻醉劑過量，導致檢查後，程搢視力受損模糊\n    ，且臉部麻痺」為由，認被告甲○○涉有業務過失傷害罪嫌\n    ，向國防部南部地方軍事法院檢察署提起告訴，經該署移由\n    臺灣高雄地方法院檢察署檢察官偵查後，認被告甲○○罪嫌\n    不足，於95年5 月5 日以94年度偵字第24737 號處分書為不\n    起訴處分等情，有戶役政資料、臺灣高等法院被告前案紀錄\n    表及前開不起訴處分書可參。準此，上開事實既經自訴人之\n    夫程搢提起告訴，並經檢察官偵查終結，認被告甲○○罪嫌\n    不足，而為不起訴處分，則參酌上開說明，自訴人乙○○係\n    程搢之妻，就程搢遭被告甲○○涉嫌業務過失傷害部分，並\n    非犯罪之直接被害人，於檢察官開始偵查、偵查終結後，自\n    不得再就同一案件提起自訴。又因本件自訴狀所載之犯罪事\n    實及被告，核與上開經不起訴處分之犯罪事實及被告相同，\n    自屬同一案件，自訴人於同一案件偵查終結後，再就同一案\n    件提起自訴，於法有違。從而，因自訴人乙○○提起自訴未\n    補正委任律師為代理人，且就不得提起自訴之案件提起自訴\n    ，揆諸前揭規定，自應諭知不受理之判決。\n四、原審以自訴人乙○○提起自訴未補正委任律師為代理人，且\n    就不得提起自訴之案件再行提起自訴，依法諭知不受理之判\n    決，核無不合，自訴人乙○○上訴指摘原判決不當，為無理\n    由，應予駁回，並不經言詞辯論而為判決。\n五、據上論斷，應依刑事訴訟法第368 條、第372 條，判決如主\n    文。"
  },
  "characters": {
    "judges": [
      "洪兆隆",
      "郭玫利",
      "張盛喜"
    ],
    "prosecutors": [

    ],
    "lawyers": [
      "月26日當庭告知須委任",
      "內委任",
      "於期限內委任",
      "補正委任"
    ],
    "clerks": [

    ],
    "plaintiffs": [

    ],
    "defendants": [
      "甲○○"
    ],
    "prosecutor_office": [

    ],
    "creditors": [

    ],
    "debtors": [

    ],
    "judicial_associate_officer": [

    ]
  },
  "adjudged_at": "2010-05-12",
  "created_at": "2016-01-05 12:01:53",
  "updated_at": "2016-01-05 12:01:53"
}