{
  "identify": "KSH-99-上更(一)-49-20100512-1",
  "court": {
    "name": "臺灣高等法院",
    "code": "KSH"
  },
  "division": {
    "name": "刑事",
    "code": "M"
  },
  "year": 99,
  "word": "上更(一)",
  "number": "49",
  "jcheck": "1",
  "reason": "重傷害",
  "content": "臺灣高等法院高雄分院刑事判決      99年度上更(一)字第49號\n上  訴  人\n即  被  告  甲○○\n上  訴  人\n即  被  告  丁○○\n前二人共同\n指定辯護人  本院公設辯護人   李佩娟\n上  訴  人\n即  被  告  丙○○\n選任辯護人  柳聰賢律師\n上列上訴人因重傷害案件，不服臺灣屏東地方法院95年度訴字第\n402 號中華民國96年8 月28日第一審判決（起訴案號：臺灣屏東\n地方法院檢察署93年度偵字第3256號），提起上訴，判決後最高\n法院發回更審，本院判決如下：\n     主  文\n原判決撤銷。\n甲○○、丁○○、丙○○共同犯傷害致人重傷罪，甲○○處有期\n徒刑伍年，丁○○、丙○○各處有期徒刑肆年。\n     事  實\n一、甲○○於民國92年11月15日晚上10時至11時許間某時，在屏\n    東縣屏東市○○路花田囍市ＫＴＶ前，因孫子傑之友人吳岱\n    玹之女友李佩貞與甲○○之友人在一起，雙方爭風吃醋，致\n    雙方人等發生互毆，甲○○及其友人乃遭毆打，且甲○○友\n    人「陳敏彰」、「榮興仔」（正確姓名、年籍不詳）並因而\n    受傷至屏東市基督教醫院就醫，甲○○因無故被毆打，心有\n    不甘。竟以電話聯絡丙○○、丁○○及多名不詳姓名成年男\n    子前往屏東市基督教醫院會合，準備去找對方毆打報復基於\n    遇見孫子傑同夥人即予以毆打之傷害犯意聯絡尋找孫子傑同\n    夥人，並持6 枝木製球棒等可供毆擊之物。適孫子傑與吳岱\n    玹分手後，改與友人乙○○、戊○○、己○○分騎2 部機車\n    出遊，甲○○等人於同月16日凌晨零時4 分許，在屏東縣屏\n    東市○○路與太原路口之東方白宮ＫＴＶ前，遇見孫子傑等\n    人，甲○○、丙○○、丁○○及其他多名不詳年籍之成年男\n    子，彼等主觀上雖認為以上開木製球棒作為鬥毆之工具，並\n    不預見鬥毆之傷害行為會造成人重傷之認識，惟在客觀上皆\n    應可預見所持上開木製球棒毆打人之頭部，有傷及被害人頭\n    部致人重傷之可能，即彼等對於實施之基本鬥毆傷害行為在\n    客觀上會發生致人於重傷之加重結果能預見，惟因亟思報復\n    ，竟均疏未加以注意防範彼等共同木製球棒毆打之行為足以\n    致人重傷之結果，由甲○○、丁○○、丙○○分持木製球棒\n    ，其他人或持木製球棒或徒手，基於傷害之犯意聯絡，聯手\n    毆打己○○，致己○○頭部被球棒擊中，因而受有頭部外傷\n    併左顱內腦挫傷硬腦膜出血、左側顱骨骨折、左顱內硬腦膜\n    下出血等傷害，並因而造成癲癇症及記憶力減退、智商降低\n    之後遺症，而於身體或健康有重大不治之傷害。\n二、案經己○○訴由屏東縣警察局屏東分局報請臺灣屏東地方法\n    院檢察署檢察官偵查起訴。\n     理  由\n壹、證據能力部分\n一、按刑事訴訟法第159 條之4 規定，除前3 條之情形外，下列\n    文書亦得為證據：(一)除顯有不可信之情況外，公務員職務上\n    製作之紀錄文書、證明文書。(二)除顯有不可信之情況外，從\n    事業務之人於業務上或通常業務過程所須製作之紀錄文書、\n    證明文書。此係因公務員職務上製作之紀錄文書或證明文書\n    ，係公務員依職權所為，與其責任、信譽攸關，若有錯誤、\n    虛偽，公務員可能因此擔負刑事及行政責任，且該等文書經\n    常處於可能受公開檢查之狀態，其正確性及真實之保障極高\n    ，具有一定程度之不可代替性；又從事業務之人在業務上或\n    通常業務過程製作之上開文書，因係於通常業務上不間斷而\n    規律之記載，一般均有會計等人員校對，記錄時亦無預見日\n    後將作為證據之偽造動機，其虛偽之可能性較小，且如讓製\n    作者以口頭方式在法庭上再重述過去之事實或數據，實際上\n    有其困難，具有一定程度之不可代替性。是除非有顯不可信\n    之情況外，上開公務文書及業務文書應具有證據能力。查本\n    件卷附財團法人義大醫院96年2 月12日義醫字第09600195號\n    函附之己○○之病情等文書資料，經查並無顯不可信之情況\n    ，上開文書亦具有證據能力，本件被告丙○○之辯護人於本\n    院準備程序時，對上開文書認無證據能力，尚非可採。\n二、次按被告以外之人於審判外之陳述，雖不符前四條之規定，\n    而經當事人於審判程序同意作為證據，法院審酌該言詞陳述\n    或書面陳述作成時之情況，認為適當者，亦得為證據，刑事\n    訴訟法第159 條之5 第1 項定有明文。本件被告及其辯護人\n    對下列所引證據屬被告以外之人在審判外陳述之傳聞證據部\n    分，均同意作為證據( 見本院上更一卷第56頁) 。本院斟酌\n    上開證據並無違法取得之情事，亦無證明力明顯過低之情形\n    ，認為作為本件被告認定犯罪有無之證據亦屬適當，是均得\n    採為本件論斷之證據。\n貳、實體部分\n一、訊據上訴人即被告甲○○、丙○○均否認有重傷害或殺人未\n    遂或傷害致重傷犯行，被告甲○○辯稱：伊只有傷害之犯意\n    ，我們是互毆，伊亦有受傷，係被害人己○○持刀砍伊，伊\n    才打他的等語。被告丙○○則辯稱：伊係經通知而於事後到\n    場，並未參與毆打，伊去的時候他們已經打完了，伊知道甲\n    ○○有打人，他是持棒子打被害人己○○，現場還有其他人\n    持棒子打被害人己○○，但是伊不認識等語。被告丁○○則\n    未於本院準備程序及審理中到庭，惟於原審及本院前審時則\n    辯稱：伊到達東方白宮ＫＴＶ前，雙方已經打完了，伊並沒\n    有參與毆打被害人己○○云云。\n二、查被告甲○○及其友人因於92年11月15日下午10時至11時許\n    間某時，在屏東縣屏東市○○路花田囍市ＫＴＶ前，與孫子\n    傑及其友人因故發生互毆，被告甲○○及其友人乃遭毆打，\n    且被告甲○○友人「陳敏彰」、「榮興仔」（正確姓名、年\n    籍不詳）並因而受傷至屏東市基督教醫院就醫，甲○○因無\n    故被毆打，心有不甘，即聯絡被告丙○○、丁○○及多名不\n    詳姓名成年男子共同攜帶6 枝木製球棒欲尋找對方孫子傑同\n    夥毆打報復，嗣於92年11月16日上午零時4 分許，在屏東縣\n    屏東市○○路與太原路口之東方白宮ＫＴＶ前，遇見孫子傑\n    、己○○、乙○○、戊○○4 人，被告甲○○、丁○○、丙\n    ○○分持木製球棒，其他不詳姓名成年男子或持木製球棒或\n    徒手，共同毆打己○○，致己○○受有頭部外傷併左顱內腦\n    挫傷硬腦膜出血、左側顱骨骨折、左顱內硬腦膜下出血等事\n    實，業據證人分別證述如下：\n  (1)證人李佩貞於警詢中供證：孫子傑、吳岱玹及另名不詳男子\n    與甲○○及其他不詳男子於11月15日在花田囍市KTV 外面馬\n    路打架，其原因是因為吳岱玹借我機車使用，我要還車給吳\n    岱玹，他到KTV 時看到我被甲○○等人載，可能吃醋，所以\n    吳岱玹等人就打甲○○等人等語（見警卷第38頁) ，核與被\n    告甲○○於警詢及原審中所證述：92年11月16日凌晨那件事\n    是我打電話叫丙○○、丁○○過去，因為92年11月15日22時\n    接近23時左右，在屏東巿廣東路花田囍市KTV 前被打，陳敏\n    璋、榮興仔就醫，我去看他們，我就在屏東市基督教醫院分\n    別打電話給他們2 人等語相符（見警卷第22頁反面、原審16\n    2 頁) ，並據證人孫子傑於偵查中具結證述：被打當日稍早\n    在花田囍市，我載吳岱玹去牽機車，吳岱玹因為他女友跟其\n    他男生在一起，吳岱玹就與對方起衝突，我有看到他被打，\n    兩邊就打了起來，後來兩邊停手，對方走了，我才去找己○\n    ○等語可按（見偵卷第123 頁) 。\n  (2)證人即現場目擊者趙莉萍於原審審理中具結供證：打人的一\n    方是開車的，當時車子停在路上等侯，騎機車的一方被攔下\n    來毆打，被打的一方並沒有拿東西等語（見原審卷第225 頁\n    ），再者，警員黃坤煌制作之職務報告書亦記載：警方在案\n    發現場並未發現打架犯案之兇器等情（見偵查卷第24頁），\n    衡諸當時告訴人己○○所受之傷勢嚴重，不可能取走所攜帶\n    之刀械，苟告訴人己○○確有持刀之行為，何以未在案發現\n    場扣得其所攜帶之刀械？況卷查並無任何人看到有持刀攻擊\n    被告甲○○之據證，足見被告甲○○辯稱：是己○○先拿刀\n    子衝過來云云，洵屬卸責之詞，並不足採。被告雖提出應診\n    時間92年11月19日人愛醫院出具之診斷證明書證明其被刀械\n    砍傷之情( 見警卷第2 頁) ，惟被告於案發之前已在花田囍\n    市ＫＴＶ與人發生爭執鬥毆，且依證人趙莉萍上開證言，係\n    告訴人己○○係先行遭被告甲○○等人攻擊，受有事實欄之\n    傷勢，是否有能力再對被告甲○○攻擊，自難僅憑被告甲○\n    ○單方之指述，遽認此傷勢係遭告訴人己○○持刀所為。其\n    辯護人請向警察局查詢是否有刀子扣案及向人愛醫院查詢被\n    告甲○○頭部是否為刀傷等情，自無必要，併此敘明。\n  (3)證人即與告訴人同行之乙○○於偵查及原審審理中均具結供\n    證：我到東方白宮ＫＴＶ那邊看到我表哥己○○躺在地上，\n    我到時看到很多人在打他，丁○○有拿棒子打己○○的頭部\n    等語（偵查卷第36、37頁；原審卷第170 頁背面、第171 頁\n    ）。\n  (4)證人戊○○於原審審理中結證稱：被告甲○○、丁○○及其\n    他人衝過來就打，己○○先遭被告甲○○毆打，其過去扶己\n    ○○時也遭毆打，其僅認得被告甲○○、丁○○，確有看到\n    被告甲○○、丁○○持木棒，被告甲○○持棒子毆打己○○\n    ，己○○被敲擊頭部等語( 見原審卷第221 ～223 頁），於\n    偵查中結證稱：確見被告丁○○有拿球棒毆打己○○等語(\n    見偵卷第38頁），於警詢證稱：被告丁○○、丙○○有拿球\n    棒參與毆打等語( 見警卷第32頁反面、第33頁）。\n  (5)證人孫子傑於原審審理中結證稱見到對方衝過來，大部分都\n    拿木棍，己○○第1 個被打，遭人持木棍毆打頭部，己○○\n    即倒在地上等語( 見原審卷第223 頁反面），於偵查中結證\n    稱一群人圍過來打，其中有一些人持木棍，該等人先打己○\n    ○，被告丁○○有在東方白宮ＫＴＶ動手毆打己○○等語(\n    見偵卷第122 ～123 頁）。至證人孫子傑於原審審理中雖證\n    稱印象中被告丁○○有在現場，但不確定等語（見原審卷第\n    224 頁），然證人孫子傑於警詢及偵查中均明確證稱被告丁\n    ○○有在場毆打己○○等語（見警卷第39頁、偵查卷第123\n    頁），與其於原審審理中證述不符，又證人孫子傑於警詢及\n    偵查時，因距事發時間較近，記憶應較清晰，而其於原審96\n    年7 月10日審理中作證時，與事發時間已相隔3 年餘，且因\n    被告等在庭，心理或有所顧忌，自應以證人孫子傑於偵查中\n    之證述較為可採。\n  (6)證人曹偉益於原審審理中結證稱：我與被告甲○○由被告丙\n    ○○開車載往東方白宮ＫＴＶ，被告丁○○於同時間亦到場\n    ，被告丙○○之車內駕駛座的左手邊和車門間的縫隙有放置\n    球棒，被告甲○○下車有持球棒等語( 見原審卷第168 ～\n    170 頁）。\n  (7)證人即共同被告甲○○於原審審理中結證稱：我在屏東基督\n    教醫院打電話給被告丁○○、丙○○，邀同前往助陣等語(\n    見原審卷第162 頁），於偵查中亦結證稱：我由被告丙○○\n    開車載往東方白宮ＫＴＶ，並於途中打電話邀被告丁○○一\n    同前往，被告丁○○、丙○○也有打起來，我找被告丁○○\n    、丙○○一起去助陣等語( 見偵卷第30、33頁），另於警詢\n    證述：當時前往東方白宮ＫＴＶ的人有被告丁○○、丙○○\n    等人，被告丁○○、丙○○有一同到達現場等語( 見警卷第\n    23頁正反面）。至證人即共同被告甲○○於原審審理中又改\n    證稱：被告丁○○、丙○○係打完後才到場等語( 見原審卷\n    第163 頁），然既核與其於上開證述不相一致，亦與證人乙\n    ○○、孫子傑、戊○○上開證述不符，證人即共同被告甲○\n    ○此部分證述，核與事證不符，自無可採。\n  (8)再被告甲○○亦迭次陳述其等帶6 枝木製球棒，其持1 枝球\n    棒與己○○對打等語( 見警卷第23頁正、反面、偵卷第30頁\n    31頁、原審卷第163 頁反面）。是證人乙○○、戊○○、孫\n    子傑、曹偉益證述或稱木棍或稱木棒或稱棒子，均應係木製\n    球棒之誤。此外，復有己○○人愛醫院診斷證明書、長庚紀\n    念醫院診斷證明書、現場監視器翻拍照片、己○○長庚紀念\n    醫院病歷附卷可佐( 見警卷第31、48～49頁、偵卷第60～88\n    頁、第164 頁）。從而，被告甲○○、丁○○、丙○○分持\n    木製球棒，其他不詳姓名成年男子或持木製球棒或徒手，共\n    同毆打己○○，致己○○受有頭部外傷併左顱內腦挫傷硬腦\n    膜出血、左側顱骨骨折、左顱內硬腦膜下出血之情，甚為明\n    確。被告丁○○、丙○○辯稱其等均係經通知而於事後到場\n    ，並未參與毆打等語，乃屬卸責之詞，無可採取。\n三、按共同正犯係共同實施犯罪行為之人，在共同意思範圍內，\n    各自分擔犯罪行為之一部，相互利用他人之行為，以達其犯\n    罪之目的，其成立不以全體均行參與實施犯罪構成要件之行\n    為為要件，參與構成要件之行為者，固為共同正犯，以自己\n    共同犯罪之意思，雖參與犯罪構成要件以外之行為，或以自\n    己共同犯罪之意思，事前同謀，而由其中一部分人實行犯罪\n    之行為者，亦均應認為共同正犯，使之對於全部行為所生之\n    結果，負其責任。查被告丁○○、丙○○二人係被告甲○○\n    邀同前往助陣等情，業據被告甲○○供證在卷，如前所述，\n    而被告丁○○於偵查中亦供稱：當時我在那裡，是被告甲○\n    ○打電話給我，要我去幫忙等情（見偵卷第33頁) ，被告丙\n    ○○則開車載被告甲○○、證人曹偉益到達現場，為證人曹\n    偉益證述如前，且二人均有參與本件毆打，是被告丁○○、\n    丙○○二人自應就件犯行負共同正犯之刑責。\n四、又按加重結果犯，以行為人能預見其結果之發生為要件，所\n    謂能預見乃指客觀情形而言，與主觀有無預見之情形不同，\n    若主觀上有預見，而結果之發生又不違背其本意時，則屬故\n    意範圍。又加重結果犯對於加重結果之發生，並無主觀上之\n    犯意可言，共犯中之一人所引起之加重結果，其他之人應否\n    同負加重結果之全部刑責，端視其就此加重結果之發生，於\n    客觀情形能否預見，而非以各共犯之間，主觀上對於加重結\n    果之發生，有無犯意之聯絡為斷（最高法院九十三年度台上\n    字第二六０號判決參照）。又刑法上之加重結果犯，以行為\n    人（客觀上）能預見其結果之發生而主觀上未預見為成立要\n    件；如行為人明知其行為足以發生一定之結果，而仍任意為\n    之，則屬故意之範疇。且刑法上之故意，分直接故意（確定\n    故意）與間接故意（不確定故意），「行為人對於構成犯罪\n    之事實，明知並有意使其發生者」為直接故意；「行為人對\n    於構成犯罪之事實，預見其發生而其發生並不違背其本意者\n    」為間接故意。而間接故意與加重結果犯之區別，在於間接\n    故意對犯罪事實之發生，客觀上有預見之可能，主觀上亦有\n    預見（不違背其本意），加重結果犯則對加重結果之發生，\n    客觀上雖有預見之可能但主觀上並未預見。其概念並不相同\n    ，應詳予區分（最高法院九十一年度台上字第一０四二號判\n    決參照）。\n五、再刑法第27 7條第2 項後段之傷害致人於重傷罪，係對於犯\n    普通傷害罪致發生重傷結果所規定之加重結果犯，參酌同法\n    第17條規定，以行為人對於普通傷害有犯意，而對於重傷之\n    結果在客觀上能預見，但主觀上不預見者為要件，此項構成\n    犯罪之事實，依刑事訴訟法第308 條、第310 條第1 款規定\n    ，不僅事實欄應明白認定，且須於理由內說明其憑以認定之\n    證據，方足以資論罪科刑（最高法院89年台上字第2486號判\n    決意旨參照）；又傷害致人於重傷罪，以行為人對於傷害行\n    為有犯意，而對於重傷之結果，客觀上能預見而主觀上不預\n    見者為限；如行為人對於重傷之結果主觀上有預見，而其結\n    果又不違背其本意時，則屬同法第278 條第1 項之使人受重\n    傷罪範圍，兩者迥不相同（最高法院89年台字第7626號判決\n    參照）。\n六、查刑法第10條第4 項就重傷之定義，於95年7 月1 日修正施\n    行，惟其中第6 款「其他於身體或健康，有重大不治或難治\n    之傷害」規定並未修正，故無新舊法比較問題，先予敘明。\n    又告訴人己○○因本件事故受有頭部外傷併左顱內腦挫傷硬\n    腦膜出血、左側顱骨骨折、左顱內硬腦膜下出血等傷害，經\n    送醫救治，仍造成癲癇症及記憶力減退、智商降低之後遺症\n    ，就智商與記憶力減退部分應無法恢復等情，業經原審函請\n    財團法人義大醫院鑑定無訛，有該院96年2 月12日義醫字第\n    096001 95 號函及所附心理衡鑑報告各1 份在卷可稽( 見原\n    審卷第10 9頁) 。雖被告等之辯護人於原審質疑智能不足部\n    分，是否確因本件事故所致，經原審函詢該院覆以：本件告\n    訴人並未提供其受傷前之智能衡鑑資資料以資比較，醫學上\n    又無法回溯測量病前智商，故無法明確認定此次受傷有否造\n    成其智能及記憶力衰退之情形，係以告訴人高中肄業且曾服\n    兵役而作推論認定等語，有該院96年6 月12日義醫字第0960\n    0759號函附卷可憑(見 原審卷第218 頁) 。而告訴人確係高\n    中肄業學歷，且係於服役期間發生此事故，並因受傷而停役\n    等情，有其停役令影本附卷可稽，苟其於本件事故前即有智\n    能不足之情形，何以於入伍時不申請免役，復參以告訴人係\n    因本件事故之傷害，因而領有身心殘障手冊，亦有中華民國\n    身心殘障手冊影本附卷可佐( 以上見偵卷第113 至116 頁)\n    ，足認被害人之智能不足及記憶力減退確因本件行為所致無\n    訛。準此，告訴人己○○之智商與記憶力減退部分既無法恢\n    復，即屬對其身體或健康有重大不治之傷害，應係重傷害無\n    誤，被告等之辯護人認告訴人己○○上開傷勢，尚未達重傷\n    之程度，自非可採。\n七、另加重結果犯以行為人能預見其結果之發生為要件，乃指客\n    觀情形而言，與主觀上有無預見之情形不同（最高法院四十\n    七年台上字第九二○號判例參照），又刑法上之傷害致重傷\n    係結果犯，如多數人下手毆打，本有犯意之聯絡，即屬共同\n    正犯，對於共犯間之實施行為，既互相利用，就傷害之結果\n    ，自應同負責任；又傷害之結果，自係上訴人等合同行為所\n    致，無論係何人所加之傷，在共犯間均應負全部之責，並無\n    分別何部分之傷孰為下手人之必要。卷查雙方並無深仇大恨\n    ，僅因被告甲○○於民國92年11月15日晚上10時至11時許間\n    某時，在屏東縣屏東市○○路花田囍市ＫＴＶ前，因孫子傑\n    之友人吳岱玹之女友李佩貞與甲○○之友人在一起，雙方爭\n    風吃醋，致雙方人等發生互毆，被告甲○○及其友人乃遭毆\n    打，且被告甲○○友人因受傷至屏東市基督教醫院就醫。被\n    告甲○○因無故被毆打，心有不甘，以電話聯絡被告丙○○\n    、丁○○及多名不詳姓名成年男子前往屏東市基督教醫院會\n    合，準備去找對方毆打報復而已，衡其行為動機，被告等人\n    自始主觀上應無明知之直接殺人故意，亦無主觀上有預見上\n    開毆打行為，會發生被害人死亡之結果，而無違背其本意之\n    情形，更無有意使發生之直接重傷之故意，亦非主觀上有預\n    見上開毆打行為會發生被害人重傷之結果，或被害人重傷之\n    結果並無違背被告之本意，是被告等人主觀上亦應無殺人、\n    重傷之間接故意，而係出於普通傷害犯意為之，至堪認定。\n    惟綜合上情以觀，則可認定被告等人在主觀上應係認為以上\n    開木製球棒作為毆打之工具，雖不預見毆打之傷害行為會造\n    成使人受重傷結果之認識，即未有使人重傷之犯意，然在客\n    觀上皆應可能預見持上開木製球棒毆打人之頭部，有傷及被\n    害人頭部致人重傷，即其對於所實施之基本毆打傷害行為在\n    客觀上有發生致人重傷加重結果之危險存在可得預見；質言\n    之，被告等在客觀上應可預見持兇器毆打行為足以致人重傷\n    之結果，乃基於共同傷害之意思，持上開木製球棒毆打告訴\n    人己○○。而按一般人之知識經驗，於毆打之際，持以上開\n    木製球棒作為傷害工具，又眾人合力集體為之，則被告等人\n    在客觀上得預見足以發生致重傷結果，竟疏未加以防範注意\n    ，以致發生告訴人己○○癲癇症及記憶力減退、智商降低之\n    後遺症，就智商與記憶力減退部分應無法恢復等重傷害之結\n    果，故當係互為利用他人之行為而達共同之目的，依整體觀\n    察，被告等人自應為共同行為結果負其責任，是傷害行為既\n    在被告等人共同意思範圍內，對於其餘人之實施行為，既互\n    相利用，且告訴人己○○係被告等人與其他共犯等人共同實\n    際參與毆打傷害而致重傷，其傷害與被害人重傷間，顯有相\n    當因果關係，則被告等人應就與傷害行為所生重傷加重結果\n    ，應共同負其責任。\n八、核被告三人上開所為，應成立刑法係犯刑法第277 條第2項\n    後段之傷害致重傷害罪，其三人與其他多名不詳姓名成年人\n    間有犯意聯絡及行為分擔，皆為共同正犯（本件被告等行為\n    後，修正前刑法第28條原規定：「二人以上共同『實施』犯\n    罪之行為者，皆為共同正犯」，被告行為後，刑法第28條修\n    正為：「二人以上共同『實行』犯罪之行為者，皆為共同正\n    犯」，將舊法之「實施」修正為「實行」。原「實施」之概\n    念，包含陰謀、預備、著手及實行等階段之行為，修正後僅\n    共同「實行」犯罪行為始成立共同正犯。是新法共同正犯之\n    範圍已有限縮，排除陰謀犯、預備犯之共同正犯。新舊法就\n    共同正犯之範圍既因此而有所變動，自屬犯罪後法律有變更\n    ，經比較新舊法結果，以被告三人行為後之法律較有利被告\n    ) 。公訴人起訴雖認被告三人犯刑法第278 條第1 項重傷害\n    罪嫌，然被告三人係在對於重傷害之結果客觀上得預見而未\n    預見之情形下，基於傷害之故意所為，業如前述，起訴法條\n    自應予以變更。再被告三人所犯上開傷害致重傷害罪名，業\n    於本院審理時已當庭告知( 見本院更一卷第52、87頁) ，業\n    已踐行刑事訴訟法第95條第1 款之程序，及命依該罪為辯論\n    ，並無突襲審判之問題，亦此併為說明。\n九、原審予以論罪科刑，固非無見，惟查被告三人係傷害致重傷\n    害罪，已如前述，原審認係犯重傷罪，尚有未洽，被告丁○\n    ○、丙○○上訴意旨否認犯罪，被告甲○○上訴意旨辯稱僅\n    有傷害犯行，均指摘原判決不當，為無理由，自應由本院將\n    原判決撤銷改判。爰審酌被告甲○○僅因前開爭風吃醋，與\n    對方互毆而有傷害、即夥同被告丁○○、丙○○及多名不詳\n    姓名成年男子或持木製球棒或徒手聯手毆打被害人己○○，\n    致被害人己○○受有頭部外傷併左顱內腦挫傷硬腦膜出血、\n    左側顱骨骨折、左顱內硬腦膜下出血，並造成上開所述被害\n    人己○○重傷之情形：被告丁○○、丙○○行為後未坦承犯\n    行，被告甲○○雖坦承部分犯行，然其係基於主導地位，另\n    被告甲○○、丁○○、丙○○均未賠償被害人等一切情狀，\n    爰各量處如主文第2 項所示之宣告刑。又被告等三人犯罪時\n    間雖在中華民國96年4 月24日以前，惟經本院諭知有期徒刑\n    逾一年六月之刑，依中華民國96年罪犯減刑條例第2 條第1\n    項第2 款規定，不符減刑條件，不予減刑，併此敘明。被告\n    甲○○、丁○○、丙○○等人持以毆打己○○所用木製球棒\n    ，雖其中2 枝木製球棒為被告甲○○所有，已經被告甲○○\n    陳明在卷，但未據扣案，亦無證據證明尚屬存在，其餘4 枝\n    木製球棒不能證明係被告或共犯所有，故不予宣告沒收，併\n    此敘明。\n十、被告丁○○經合法傳喚，無正當理由不到庭，不待其陳述逕\n    行判決。\n據上論斷，應依刑事訴訟法第371 條、第369 條第1 項前段、第\n364 條、第299 條第1 項前段、第300 條、刑法第28條、第277\n條第2 項後段，判決如主文。\n本案經檢察官姜麗儒到庭執行職務。\n中    華    民    國    99    年     5    月  12      日\n                 刑事第九庭     審判長法  官  莊秋桃\n                                      法  官  范惠瑩\n                                      法  官  田平安\n以上正本與原本無異。\n如不服本判決，應於判決送達後10日內向本院提出上訴狀，其未\n敘述理由者，並應於提出上訴狀後10日內向本院補提上訴理由狀\n（應附繕本）。\n中    華    民    國    99    年     5    月  12      日\n                                  書  記  官  張宗芳\n附錄本件判決論罪科刑法條：\n刑法第二百七十七條：\n傷害人之身體或健康者，處三年以下有期徒刑、拘役或一千元以下罰金。\n犯前項之罪因而致人於死者，處無期徒刑或七年以上有期徒刑；致重傷者，處三年以\n上十年以下有期徒刑。",
  "structure": {
    "main": "原判決撤銷。\n甲○○、丁○○、丙○○共同犯傷害致人重傷罪，甲○○處有期\n徒刑伍年，丁○○、丙○○各處有期徒刑肆年。",
    "fact": "一、甲○○於民國92年11月15日晚上10時至11時許間某時，在屏\n    東縣屏東市○○路花田囍市ＫＴＶ前，因孫子傑之友人吳岱\n    玹之女友李佩貞與甲○○之友人在一起，雙方爭風吃醋，致\n    雙方人等發生互毆，甲○○及其友人乃遭毆打，且甲○○友\n    人「陳敏彰」、「榮興仔」（正確姓名、年籍不詳）並因而\n    受傷至屏東市基督教醫院就醫，甲○○因無故被毆打，心有\n    不甘。竟以電話聯絡丙○○、丁○○及多名不詳姓名成年男\n    子前往屏東市基督教醫院會合，準備去找對方毆打報復基於\n    遇見孫子傑同夥人即予以毆打之傷害犯意聯絡尋找孫子傑同\n    夥人，並持6 枝木製球棒等可供毆擊之物。適孫子傑與吳岱\n    玹分手後，改與友人乙○○、戊○○、己○○分騎2 部機車\n    出遊，甲○○等人於同月16日凌晨零時4 分許，在屏東縣屏\n    東市○○路與太原路口之東方白宮ＫＴＶ前，遇見孫子傑等\n    人，甲○○、丙○○、丁○○及其他多名不詳年籍之成年男\n    子，彼等主觀上雖認為以上開木製球棒作為鬥毆之工具，並\n    不預見鬥毆之傷害行為會造成人重傷之認識，惟在客觀上皆\n    應可預見所持上開木製球棒毆打人之頭部，有傷及被害人頭\n    部致人重傷之可能，即彼等對於實施之基本鬥毆傷害行為在\n    客觀上會發生致人於重傷之加重結果能預見，惟因亟思報復\n    ，竟均疏未加以注意防範彼等共同木製球棒毆打之行為足以\n    致人重傷之結果，由甲○○、丁○○、丙○○分持木製球棒\n    ，其他人或持木製球棒或徒手，基於傷害之犯意聯絡，聯手\n    毆打己○○，致己○○頭部被球棒擊中，因而受有頭部外傷\n    併左顱內腦挫傷硬腦膜出血、左側顱骨骨折、左顱內硬腦膜\n    下出血等傷害，並因而造成癲癇症及記憶力減退、智商降低\n    之後遺症，而於身體或健康有重大不治之傷害。\n二、案經己○○訴由屏東縣警察局屏東分局報請臺灣屏東地方法\n    院檢察署檢察官偵查起訴。",
    "reason": "壹、證據能力部分\n一、按刑事訴訟法第159 條之4 規定，除前3 條之情形外，下列\n    文書亦得為證據：(一)除顯有不可信之情況外，公務員職務上\n    製作之紀錄文書、證明文書。(二)除顯有不可信之情況外，從\n    事業務之人於業務上或通常業務過程所須製作之紀錄文書、\n    證明文書。此係因公務員職務上製作之紀錄文書或證明文書\n    ，係公務員依職權所為，與其責任、信譽攸關，若有錯誤、\n    虛偽，公務員可能因此擔負刑事及行政責任，且該等文書經\n    常處於可能受公開檢查之狀態，其正確性及真實之保障極高\n    ，具有一定程度之不可代替性；又從事業務之人在業務上或\n    通常業務過程製作之上開文書，因係於通常業務上不間斷而\n    規律之記載，一般均有會計等人員校對，記錄時亦無預見日\n    後將作為證據之偽造動機，其虛偽之可能性較小，且如讓製\n    作者以口頭方式在法庭上再重述過去之事實或數據，實際上\n    有其困難，具有一定程度之不可代替性。是除非有顯不可信\n    之情況外，上開公務文書及業務文書應具有證據能力。查本\n    件卷附財團法人義大醫院96年2 月12日義醫字第09600195號\n    函附之己○○之病情等文書資料，經查並無顯不可信之情況\n    ，上開文書亦具有證據能力，本件被告丙○○之辯護人於本\n    院準備程序時，對上開文書認無證據能力，尚非可採。\n二、次按被告以外之人於審判外之陳述，雖不符前四條之規定，\n    而經當事人於審判程序同意作為證據，法院審酌該言詞陳述\n    或書面陳述作成時之情況，認為適當者，亦得為證據，刑事\n    訴訟法第159 條之5 第1 項定有明文。本件被告及其辯護人\n    對下列所引證據屬被告以外之人在審判外陳述之傳聞證據部\n    分，均同意作為證據( 見本院上更一卷第56頁) 。本院斟酌\n    上開證據並無違法取得之情事，亦無證明力明顯過低之情形\n    ，認為作為本件被告認定犯罪有無之證據亦屬適當，是均得\n    採為本件論斷之證據。\n貳、實體部分\n一、訊據上訴人即被告甲○○、丙○○均否認有重傷害或殺人未\n    遂或傷害致重傷犯行，被告甲○○辯稱：伊只有傷害之犯意\n    ，我們是互毆，伊亦有受傷，係被害人己○○持刀砍伊，伊\n    才打他的等語。被告丙○○則辯稱：伊係經通知而於事後到\n    場，並未參與毆打，伊去的時候他們已經打完了，伊知道甲\n    ○○有打人，他是持棒子打被害人己○○，現場還有其他人\n    持棒子打被害人己○○，但是伊不認識等語。被告丁○○則\n    未於本院準備程序及審理中到庭，惟於原審及本院前審時則\n    辯稱：伊到達東方白宮ＫＴＶ前，雙方已經打完了，伊並沒\n    有參與毆打被害人己○○云云。\n二、查被告甲○○及其友人因於92年11月15日下午10時至11時許\n    間某時，在屏東縣屏東市○○路花田囍市ＫＴＶ前，與孫子\n    傑及其友人因故發生互毆，被告甲○○及其友人乃遭毆打，\n    且被告甲○○友人「陳敏彰」、「榮興仔」（正確姓名、年\n    籍不詳）並因而受傷至屏東市基督教醫院就醫，甲○○因無\n    故被毆打，心有不甘，即聯絡被告丙○○、丁○○及多名不\n    詳姓名成年男子共同攜帶6 枝木製球棒欲尋找對方孫子傑同\n    夥毆打報復，嗣於92年11月16日上午零時4 分許，在屏東縣\n    屏東市○○路與太原路口之東方白宮ＫＴＶ前，遇見孫子傑\n    、己○○、乙○○、戊○○4 人，被告甲○○、丁○○、丙\n    ○○分持木製球棒，其他不詳姓名成年男子或持木製球棒或\n    徒手，共同毆打己○○，致己○○受有頭部外傷併左顱內腦\n    挫傷硬腦膜出血、左側顱骨骨折、左顱內硬腦膜下出血等事\n    實，業據證人分別證述如下：\n  (1)證人李佩貞於警詢中供證：孫子傑、吳岱玹及另名不詳男子\n    與甲○○及其他不詳男子於11月15日在花田囍市KTV 外面馬\n    路打架，其原因是因為吳岱玹借我機車使用，我要還車給吳\n    岱玹，他到KTV 時看到我被甲○○等人載，可能吃醋，所以\n    吳岱玹等人就打甲○○等人等語（見警卷第38頁) ，核與被\n    告甲○○於警詢及原審中所證述：92年11月16日凌晨那件事\n    是我打電話叫丙○○、丁○○過去，因為92年11月15日22時\n    接近23時左右，在屏東巿廣東路花田囍市KTV 前被打，陳敏\n    璋、榮興仔就醫，我去看他們，我就在屏東市基督教醫院分\n    別打電話給他們2 人等語相符（見警卷第22頁反面、原審16\n    2 頁) ，並據證人孫子傑於偵查中具結證述：被打當日稍早\n    在花田囍市，我載吳岱玹去牽機車，吳岱玹因為他女友跟其\n    他男生在一起，吳岱玹就與對方起衝突，我有看到他被打，\n    兩邊就打了起來，後來兩邊停手，對方走了，我才去找己○\n    ○等語可按（見偵卷第123 頁) 。\n  (2)證人即現場目擊者趙莉萍於原審審理中具結供證：打人的一\n    方是開車的，當時車子停在路上等侯，騎機車的一方被攔下\n    來毆打，被打的一方並沒有拿東西等語（見原審卷第225 頁\n    ），再者，警員黃坤煌制作之職務報告書亦記載：警方在案\n    發現場並未發現打架犯案之兇器等情（見偵查卷第24頁），\n    衡諸當時告訴人己○○所受之傷勢嚴重，不可能取走所攜帶\n    之刀械，苟告訴人己○○確有持刀之行為，何以未在案發現\n    場扣得其所攜帶之刀械？況卷查並無任何人看到有持刀攻擊\n    被告甲○○之據證，足見被告甲○○辯稱：是己○○先拿刀\n    子衝過來云云，洵屬卸責之詞，並不足採。被告雖提出應診\n    時間92年11月19日人愛醫院出具之診斷證明書證明其被刀械\n    砍傷之情( 見警卷第2 頁) ，惟被告於案發之前已在花田囍\n    市ＫＴＶ與人發生爭執鬥毆，且依證人趙莉萍上開證言，係\n    告訴人己○○係先行遭被告甲○○等人攻擊，受有事實欄之\n    傷勢，是否有能力再對被告甲○○攻擊，自難僅憑被告甲○\n    ○單方之指述，遽認此傷勢係遭告訴人己○○持刀所為。其\n    辯護人請向警察局查詢是否有刀子扣案及向人愛醫院查詢被\n    告甲○○頭部是否為刀傷等情，自無必要，併此敘明。\n  (3)證人即與告訴人同行之乙○○於偵查及原審審理中均具結供\n    證：我到東方白宮ＫＴＶ那邊看到我表哥己○○躺在地上，\n    我到時看到很多人在打他，丁○○有拿棒子打己○○的頭部\n    等語（偵查卷第36、37頁；原審卷第170 頁背面、第171 頁\n    ）。\n  (4)證人戊○○於原審審理中結證稱：被告甲○○、丁○○及其\n    他人衝過來就打，己○○先遭被告甲○○毆打，其過去扶己\n    ○○時也遭毆打，其僅認得被告甲○○、丁○○，確有看到\n    被告甲○○、丁○○持木棒，被告甲○○持棒子毆打己○○\n    ，己○○被敲擊頭部等語( 見原審卷第221 ～223 頁），於\n    偵查中結證稱：確見被告丁○○有拿球棒毆打己○○等語(\n    見偵卷第38頁），於警詢證稱：被告丁○○、丙○○有拿球\n    棒參與毆打等語( 見警卷第32頁反面、第33頁）。\n  (5)證人孫子傑於原審審理中結證稱見到對方衝過來，大部分都\n    拿木棍，己○○第1 個被打，遭人持木棍毆打頭部，己○○\n    即倒在地上等語( 見原審卷第223 頁反面），於偵查中結證\n    稱一群人圍過來打，其中有一些人持木棍，該等人先打己○\n    ○，被告丁○○有在東方白宮ＫＴＶ動手毆打己○○等語(\n    見偵卷第122 ～123 頁）。至證人孫子傑於原審審理中雖證\n    稱印象中被告丁○○有在現場，但不確定等語（見原審卷第\n    224 頁），然證人孫子傑於警詢及偵查中均明確證稱被告丁\n    ○○有在場毆打己○○等語（見警卷第39頁、偵查卷第123\n    頁），與其於原審審理中證述不符，又證人孫子傑於警詢及\n    偵查時，因距事發時間較近，記憶應較清晰，而其於原審96\n    年7 月10日審理中作證時，與事發時間已相隔3 年餘，且因\n    被告等在庭，心理或有所顧忌，自應以證人孫子傑於偵查中\n    之證述較為可採。\n  (6)證人曹偉益於原審審理中結證稱：我與被告甲○○由被告丙\n    ○○開車載往東方白宮ＫＴＶ，被告丁○○於同時間亦到場\n    ，被告丙○○之車內駕駛座的左手邊和車門間的縫隙有放置\n    球棒，被告甲○○下車有持球棒等語( 見原審卷第168 ～\n    170 頁）。\n  (7)證人即共同被告甲○○於原審審理中結證稱：我在屏東基督\n    教醫院打電話給被告丁○○、丙○○，邀同前往助陣等語(\n    見原審卷第162 頁），於偵查中亦結證稱：我由被告丙○○\n    開車載往東方白宮ＫＴＶ，並於途中打電話邀被告丁○○一\n    同前往，被告丁○○、丙○○也有打起來，我找被告丁○○\n    、丙○○一起去助陣等語( 見偵卷第30、33頁），另於警詢\n    證述：當時前往東方白宮ＫＴＶ的人有被告丁○○、丙○○\n    等人，被告丁○○、丙○○有一同到達現場等語( 見警卷第\n    23頁正反面）。至證人即共同被告甲○○於原審審理中又改\n    證稱：被告丁○○、丙○○係打完後才到場等語( 見原審卷\n    第163 頁），然既核與其於上開證述不相一致，亦與證人乙\n    ○○、孫子傑、戊○○上開證述不符，證人即共同被告甲○\n    ○此部分證述，核與事證不符，自無可採。\n  (8)再被告甲○○亦迭次陳述其等帶6 枝木製球棒，其持1 枝球\n    棒與己○○對打等語( 見警卷第23頁正、反面、偵卷第30頁\n    31頁、原審卷第163 頁反面）。是證人乙○○、戊○○、孫\n    子傑、曹偉益證述或稱木棍或稱木棒或稱棒子，均應係木製\n    球棒之誤。此外，復有己○○人愛醫院診斷證明書、長庚紀\n    念醫院診斷證明書、現場監視器翻拍照片、己○○長庚紀念\n    醫院病歷附卷可佐( 見警卷第31、48～49頁、偵卷第60～88\n    頁、第164 頁）。從而，被告甲○○、丁○○、丙○○分持\n    木製球棒，其他不詳姓名成年男子或持木製球棒或徒手，共\n    同毆打己○○，致己○○受有頭部外傷併左顱內腦挫傷硬腦\n    膜出血、左側顱骨骨折、左顱內硬腦膜下出血之情，甚為明\n    確。被告丁○○、丙○○辯稱其等均係經通知而於事後到場\n    ，並未參與毆打等語，乃屬卸責之詞，無可採取。\n三、按共同正犯係共同實施犯罪行為之人，在共同意思範圍內，\n    各自分擔犯罪行為之一部，相互利用他人之行為，以達其犯\n    罪之目的，其成立不以全體均行參與實施犯罪構成要件之行\n    為為要件，參與構成要件之行為者，固為共同正犯，以自己\n    共同犯罪之意思，雖參與犯罪構成要件以外之行為，或以自\n    己共同犯罪之意思，事前同謀，而由其中一部分人實行犯罪\n    之行為者，亦均應認為共同正犯，使之對於全部行為所生之\n    結果，負其責任。查被告丁○○、丙○○二人係被告甲○○\n    邀同前往助陣等情，業據被告甲○○供證在卷，如前所述，\n    而被告丁○○於偵查中亦供稱：當時我在那裡，是被告甲○\n    ○打電話給我，要我去幫忙等情（見偵卷第33頁) ，被告丙\n    ○○則開車載被告甲○○、證人曹偉益到達現場，為證人曹\n    偉益證述如前，且二人均有參與本件毆打，是被告丁○○、\n    丙○○二人自應就件犯行負共同正犯之刑責。\n四、又按加重結果犯，以行為人能預見其結果之發生為要件，所\n    謂能預見乃指客觀情形而言，與主觀有無預見之情形不同，\n    若主觀上有預見，而結果之發生又不違背其本意時，則屬故\n    意範圍。又加重結果犯對於加重結果之發生，並無主觀上之\n    犯意可言，共犯中之一人所引起之加重結果，其他之人應否\n    同負加重結果之全部刑責，端視其就此加重結果之發生，於\n    客觀情形能否預見，而非以各共犯之間，主觀上對於加重結\n    果之發生，有無犯意之聯絡為斷（最高法院九十三年度台上\n    字第二六０號判決參照）。又刑法上之加重結果犯，以行為\n    人（客觀上）能預見其結果之發生而主觀上未預見為成立要\n    件；如行為人明知其行為足以發生一定之結果，而仍任意為\n    之，則屬故意之範疇。且刑法上之故意，分直接故意（確定\n    故意）與間接故意（不確定故意），「行為人對於構成犯罪\n    之事實，明知並有意使其發生者」為直接故意；「行為人對\n    於構成犯罪之事實，預見其發生而其發生並不違背其本意者\n    」為間接故意。而間接故意與加重結果犯之區別，在於間接\n    故意對犯罪事實之發生，客觀上有預見之可能，主觀上亦有\n    預見（不違背其本意），加重結果犯則對加重結果之發生，\n    客觀上雖有預見之可能但主觀上並未預見。其概念並不相同\n    ，應詳予區分（最高法院九十一年度台上字第一０四二號判\n    決參照）。\n五、再刑法第27 7條第2 項後段之傷害致人於重傷罪，係對於犯\n    普通傷害罪致發生重傷結果所規定之加重結果犯，參酌同法\n    第17條規定，以行為人對於普通傷害有犯意，而對於重傷之\n    結果在客觀上能預見，但主觀上不預見者為要件，此項構成\n    犯罪之事實，依刑事訴訟法第308 條、第310 條第1 款規定\n    ，不僅事實欄應明白認定，且須於理由內說明其憑以認定之\n    證據，方足以資論罪科刑（最高法院89年台上字第2486號判\n    決意旨參照）；又傷害致人於重傷罪，以行為人對於傷害行\n    為有犯意，而對於重傷之結果，客觀上能預見而主觀上不預\n    見者為限；如行為人對於重傷之結果主觀上有預見，而其結\n    果又不違背其本意時，則屬同法第278 條第1 項之使人受重\n    傷罪範圍，兩者迥不相同（最高法院89年台字第7626號判決\n    參照）。\n六、查刑法第10條第4 項就重傷之定義，於95年7 月1 日修正施\n    行，惟其中第6 款「其他於身體或健康，有重大不治或難治\n    之傷害」規定並未修正，故無新舊法比較問題，先予敘明。\n    又告訴人己○○因本件事故受有頭部外傷併左顱內腦挫傷硬\n    腦膜出血、左側顱骨骨折、左顱內硬腦膜下出血等傷害，經\n    送醫救治，仍造成癲癇症及記憶力減退、智商降低之後遺症\n    ，就智商與記憶力減退部分應無法恢復等情，業經原審函請\n    財團法人義大醫院鑑定無訛，有該院96年2 月12日義醫字第\n    096001 95 號函及所附心理衡鑑報告各1 份在卷可稽( 見原\n    審卷第10 9頁) 。雖被告等之辯護人於原審質疑智能不足部\n    分，是否確因本件事故所致，經原審函詢該院覆以：本件告\n    訴人並未提供其受傷前之智能衡鑑資資料以資比較，醫學上\n    又無法回溯測量病前智商，故無法明確認定此次受傷有否造\n    成其智能及記憶力衰退之情形，係以告訴人高中肄業且曾服\n    兵役而作推論認定等語，有該院96年6 月12日義醫字第0960\n    0759號函附卷可憑(見 原審卷第218 頁) 。而告訴人確係高\n    中肄業學歷，且係於服役期間發生此事故，並因受傷而停役\n    等情，有其停役令影本附卷可稽，苟其於本件事故前即有智\n    能不足之情形，何以於入伍時不申請免役，復參以告訴人係\n    因本件事故之傷害，因而領有身心殘障手冊，亦有中華民國\n    身心殘障手冊影本附卷可佐( 以上見偵卷第113 至116 頁)\n    ，足認被害人之智能不足及記憶力減退確因本件行為所致無\n    訛。準此，告訴人己○○之智商與記憶力減退部分既無法恢\n    復，即屬對其身體或健康有重大不治之傷害，應係重傷害無\n    誤，被告等之辯護人認告訴人己○○上開傷勢，尚未達重傷\n    之程度，自非可採。\n七、另加重結果犯以行為人能預見其結果之發生為要件，乃指客\n    觀情形而言，與主觀上有無預見之情形不同（最高法院四十\n    七年台上字第九二○號判例參照），又刑法上之傷害致重傷\n    係結果犯，如多數人下手毆打，本有犯意之聯絡，即屬共同\n    正犯，對於共犯間之實施行為，既互相利用，就傷害之結果\n    ，自應同負責任；又傷害之結果，自係上訴人等合同行為所\n    致，無論係何人所加之傷，在共犯間均應負全部之責，並無\n    分別何部分之傷孰為下手人之必要。卷查雙方並無深仇大恨\n    ，僅因被告甲○○於民國92年11月15日晚上10時至11時許間\n    某時，在屏東縣屏東市○○路花田囍市ＫＴＶ前，因孫子傑\n    之友人吳岱玹之女友李佩貞與甲○○之友人在一起，雙方爭\n    風吃醋，致雙方人等發生互毆，被告甲○○及其友人乃遭毆\n    打，且被告甲○○友人因受傷至屏東市基督教醫院就醫。被\n    告甲○○因無故被毆打，心有不甘，以電話聯絡被告丙○○\n    、丁○○及多名不詳姓名成年男子前往屏東市基督教醫院會\n    合，準備去找對方毆打報復而已，衡其行為動機，被告等人\n    自始主觀上應無明知之直接殺人故意，亦無主觀上有預見上\n    開毆打行為，會發生被害人死亡之結果，而無違背其本意之\n    情形，更無有意使發生之直接重傷之故意，亦非主觀上有預\n    見上開毆打行為會發生被害人重傷之結果，或被害人重傷之\n    結果並無違背被告之本意，是被告等人主觀上亦應無殺人、\n    重傷之間接故意，而係出於普通傷害犯意為之，至堪認定。\n    惟綜合上情以觀，則可認定被告等人在主觀上應係認為以上\n    開木製球棒作為毆打之工具，雖不預見毆打之傷害行為會造\n    成使人受重傷結果之認識，即未有使人重傷之犯意，然在客\n    觀上皆應可能預見持上開木製球棒毆打人之頭部，有傷及被\n    害人頭部致人重傷，即其對於所實施之基本毆打傷害行為在\n    客觀上有發生致人重傷加重結果之危險存在可得預見；質言\n    之，被告等在客觀上應可預見持兇器毆打行為足以致人重傷\n    之結果，乃基於共同傷害之意思，持上開木製球棒毆打告訴\n    人己○○。而按一般人之知識經驗，於毆打之際，持以上開\n    木製球棒作為傷害工具，又眾人合力集體為之，則被告等人\n    在客觀上得預見足以發生致重傷結果，竟疏未加以防範注意\n    ，以致發生告訴人己○○癲癇症及記憶力減退、智商降低之\n    後遺症，就智商與記憶力減退部分應無法恢復等重傷害之結\n    果，故當係互為利用他人之行為而達共同之目的，依整體觀\n    察，被告等人自應為共同行為結果負其責任，是傷害行為既\n    在被告等人共同意思範圍內，對於其餘人之實施行為，既互\n    相利用，且告訴人己○○係被告等人與其他共犯等人共同實\n    際參與毆打傷害而致重傷，其傷害與被害人重傷間，顯有相\n    當因果關係，則被告等人應就與傷害行為所生重傷加重結果\n    ，應共同負其責任。\n八、核被告三人上開所為，應成立刑法係犯刑法第277 條第2項\n    後段之傷害致重傷害罪，其三人與其他多名不詳姓名成年人\n    間有犯意聯絡及行為分擔，皆為共同正犯（本件被告等行為\n    後，修正前刑法第28條原規定：「二人以上共同『實施』犯\n    罪之行為者，皆為共同正犯」，被告行為後，刑法第28條修\n    正為：「二人以上共同『實行』犯罪之行為者，皆為共同正\n    犯」，將舊法之「實施」修正為「實行」。原「實施」之概\n    念，包含陰謀、預備、著手及實行等階段之行為，修正後僅\n    共同「實行」犯罪行為始成立共同正犯。是新法共同正犯之\n    範圍已有限縮，排除陰謀犯、預備犯之共同正犯。新舊法就\n    共同正犯之範圍既因此而有所變動，自屬犯罪後法律有變更\n    ，經比較新舊法結果，以被告三人行為後之法律較有利被告\n    ) 。公訴人起訴雖認被告三人犯刑法第278 條第1 項重傷害\n    罪嫌，然被告三人係在對於重傷害之結果客觀上得預見而未\n    預見之情形下，基於傷害之故意所為，業如前述，起訴法條\n    自應予以變更。再被告三人所犯上開傷害致重傷害罪名，業\n    於本院審理時已當庭告知( 見本院更一卷第52、87頁) ，業\n    已踐行刑事訴訟法第95條第1 款之程序，及命依該罪為辯論\n    ，並無突襲審判之問題，亦此併為說明。\n九、原審予以論罪科刑，固非無見，惟查被告三人係傷害致重傷\n    害罪，已如前述，原審認係犯重傷罪，尚有未洽，被告丁○\n    ○、丙○○上訴意旨否認犯罪，被告甲○○上訴意旨辯稱僅\n    有傷害犯行，均指摘原判決不當，為無理由，自應由本院將\n    原判決撤銷改判。爰審酌被告甲○○僅因前開爭風吃醋，與\n    對方互毆而有傷害、即夥同被告丁○○、丙○○及多名不詳\n    姓名成年男子或持木製球棒或徒手聯手毆打被害人己○○，\n    致被害人己○○受有頭部外傷併左顱內腦挫傷硬腦膜出血、\n    左側顱骨骨折、左顱內硬腦膜下出血，並造成上開所述被害\n    人己○○重傷之情形：被告丁○○、丙○○行為後未坦承犯\n    行，被告甲○○雖坦承部分犯行，然其係基於主導地位，另\n    被告甲○○、丁○○、丙○○均未賠償被害人等一切情狀，\n    爰各量處如主文第2 項所示之宣告刑。又被告等三人犯罪時\n    間雖在中華民國96年4 月24日以前，惟經本院諭知有期徒刑\n    逾一年六月之刑，依中華民國96年罪犯減刑條例第2 條第1\n    項第2 款規定，不符減刑條件，不予減刑，併此敘明。被告\n    甲○○、丁○○、丙○○等人持以毆打己○○所用木製球棒\n    ，雖其中2 枝木製球棒為被告甲○○所有，已經被告甲○○\n    陳明在卷，但未據扣案，亦無證據證明尚屬存在，其餘4 枝\n    木製球棒不能證明係被告或共犯所有，故不予宣告沒收，併\n    此敘明。\n十、被告丁○○經合法傳喚，無正當理由不到庭，不待其陳述逕\n    行判決。\n據上論斷，應依刑事訴訟法第371 條、第369 條第1 項前段、第\n364 條、第299 條第1 項前段、第300 條、刑法第28條、第277\n條第2 項後段，判決如主文。\n本案經檢察官姜麗儒到庭執行職務。\n中    華    民    國    99    年     5    月  12      日\n                 刑事第九庭     審判長法  官  莊秋桃\n                                      法  官  范惠瑩\n                                      法  官  田平安\n以上正本與原本無異。\n如不服本判決，應於判決送達後10日內向本院提出上訴狀，其未\n敘述理由者，並應於提出上訴狀後10日內向本院補提上訴理由狀\n（應附繕本）。"
  },
  "characters": {
    "judges": [
      "莊秋桃",
      "范惠瑩",
      "田平安"
    ],
    "prosecutors": [
      "姜麗儒"
    ],
    "lawyers": [
      "柳聰賢"
    ],
    "clerks": [

    ],
    "plaintiffs": [

    ],
    "defendants": [
      "甲",
      "丁",
      "丙"
    ],
    "prosecutor_office": [

    ],
    "creditors": [

    ],
    "debtors": [

    ],
    "judicial_associate_officer": [

    ]
  },
  "adjudged_at": "2010-05-12",
  "created_at": "2016-01-05 12:02:57",
  "updated_at": "2016-01-05 12:02:57"
}