{
  "identify": "KSH-99-交上易-33-20100512-1",
  "court": {
    "name": "臺灣高等法院",
    "code": "KSH"
  },
  "division": {
    "name": "刑事",
    "code": "M"
  },
  "year": 99,
  "word": "交上易",
  "number": "33",
  "jcheck": "1",
  "reason": "過失傷害",
  "content": "臺灣高等法院高雄分院刑事判決        99年度交上易字第33號\n上  訴  人\n即  被  告  乙○○\n選任辯護人  湯金全律師\n            湯東穎律師\n上列上訴人因過失傷害案件，不服臺灣高雄地方法院98年度交易\n字第116 號中華民國99年1 月25日第一審判決（起訴案號：臺灣\n高雄地方法院檢察署98年度調偵字第1307號），提起上訴，本院\n判決如下：\n    主  文\n原判決撤銷。\n乙○○犯過失傷害罪，處有期徒刑參月，如易科罰金，以新台幣\n壹仟元折算壹日。\n    事  實\n一、乙○○於民國98年4 月25日上午10時5 分許，無駕駛執照駕\n    駛車牌號碼9019-QR 號自用小客車，沿高雄市苓雅區○○○\n    路由西向東行駛至五福國中校門前，欲左轉進入五福國中，\n    本應注意轉彎車應讓直行車先行，且應注意五福國中校門前\n    之五福一路東向西慢車道劃設有網狀線禁止臨時停車，當時\n    天候晴、日間有自然光線、路面乾燥、無缺陷、無障礙物、\n    視距良好，復無不能注意之情形，詎乙○○竟疏未注意甲○\n    ○駕駛ZNE －523 號機車沿五福一路慢車道由東往西行駛亦\n    近五福國中校門前，亦疏未注意五福國中校門前之五福一路\n    東向西慢車道劃設有網狀線禁止臨時停車，乙○○即駕車貿\n    然左轉而未讓甲○○之直行車先行，並因五福國中校門前已\n    停放其他車輛，乙○○遂暫停在五福國中校門前之五福一路\n    東向西慢車道網狀線上等候，適甲○○亦疏未注意車前狀況\n    及隨時採取必要安全措施，驟見乙○○之自用小客車停放在\n    前方慢車道上，乃閃煞不及而撞及黃淑芳之自用小客車右後\n    方車身，甲○○因而人車倒地，造成甲○○受有腦震盪、顏\n    面擦傷及撕裂傷、左膝蓋撕裂傷、左手手腕橈骨骨折、胸部\n    挫傷、臉眼瘀傷等傷害。乙○○於肇事後尚未被有偵查權限\n    之該管機關發覺犯行前，即向到場處理之員警承認為肇事人\n    而自首接受裁判。\n二、案經甲○○訴由高雄市政府警察局苓雅分局移請臺灣高雄地\n    方法院檢察署檢察官偵查起訴。\n    理  由\n一、證據能力之說明：\n    (一)高雄市立民生醫院診斷證明書、寶建醫院診斷證明書均係\n      從事業務之人依業務上所須製作之病歷紀錄文書而記載，\n      因病歷記錄時無預見日後將作為證據之偽造動機，其虛偽\n      之可能性較小，且如讓製作者以口頭方式在法庭上再重述\n      過去之事實或數據，實際上有其困難，具有一定程度之不\n      可代替性，復無顯不可信之情況，依刑事訴訟法第159 條\n      之4 規定，上開文書應具有證據能力。\n    (二)公務員職務上製作之紀錄文書、證明文書，除顯有不可信\n      之情況外，亦得為證據，刑事訴訟法第159 條之4 第1 款\n      定有明文。此所謂「紀錄文書」，係指就一定事實加以記\n      載之文書，而所謂「證明文書」，則指就一定事實之存否\n      而為證明之文書。上述「紀錄文書」或「證明文書」，並\n      不限於針對特定事件所製作。祇要公務員基於職務上就一\n      定事實之記載，或就一定事實之證明而製作之文書，若其\n      內容不涉及主觀之判斷或意見之記載，即屬於上述條款所\n      稱文書之範疇。是警察人員基於警察行政上所製作之交通\n      事故現場圖、道路交通事故調查報告表均在前開條款適用\n      之範圍，即應具有證據能力（最高法院98年度台上字第58\n      14號判決參照）。\n二、上訴人即被告乙○○（下稱被告）於事實欄所載時間無駕駛\n    執照駕車左轉而暫停在五福國中校門前之五福一路東向西慢\n    車道網狀線上，而後遭告訴人甲○○駕駛之機車撞及右後方\n    車身，甲○○因而人車倒地及受有腦震盪、顏面擦傷及撕裂\n    傷、左膝蓋撕裂傷、左手手腕橈骨骨折、胸部挫傷、臉眼瘀\n    傷等傷害等事實，已經證人即告訴人甲○○及證人沈亦良分\n    別於原審、本院審理中結證明確（見原審卷第18－19、26－\n    28頁、本院卷第55－59頁）；並有高雄市立民生醫院診斷證\n    明書、寶建醫院診斷證明書、交通事故現場圖、道路交通事\n    故調查報告表、現場照片附卷可稽（見警卷第6 、8 、14－\n    16、19－24頁）；且被告就上情亦不爭執，上開事實自堪以\n    認定。再依交通事故現場圖及現場照片所示，車禍發生後，\n    告訴人甲○○之機車倒地及物品散漏均係在五福一路東向西\n    慢車道上，顯見告訴人甲○○之機車撞及被告之自用小客車\n    左後方車身時，被告之自用小客車應係在五福一路東向西劃\n    設有網狀線之慢車道上，亦甚明確。按駕駛人駕駛汽車，應\n    遵守道路交通標誌、標線、號誌之指示，並服從交通指揮人\n    員之指揮；汽車行駛至交岔路口，轉彎車應讓直行車先行；\n    又汽車行駛時，駕駛人應注意車前狀況，並隨時採取必要之\n    安全措施；道路交通安全規則第90條、第102 條第1 項第7\n    款、第94條第3 項分別定有明文。另依道路交通標誌標線號\n    誌設置規則第173 條第1 項規定可知，網狀線用以告示車輛\n    駕駛人禁止在設置本標線之範圍內臨時停車，防止交通阻塞\n    。被告曾考領有駕駛執照，當知上開規定，而車禍發生當時\n    之天候晴、日間有自然光線、路面乾燥、無缺陷、無障礙物\n    、視距良好，有道路交通事故調查報告表可佐，被告復無不\n    能注意之情形，竟駕車貿然左轉而未讓告訴人甲○○之直行\n    車先行，並暫停在五福國中校門前之五福一路東向西慢車道\n    網狀線上，致告訴人甲○○閃煞不及而撞及被告之自用小客\n    車右後方車身，告訴人甲○○因而受有傷害，被告有過失責\n    任，且被告之過失與告訴人甲○○之受傷間有因果關係甚明\n    。再依證人沈亦良於原審及本院審理中均結證稱其駕駛機車\n    行駛在告訴人甲○○駕駛之機車後方，告訴人甲○○之機車\n    如向左偏應可閃避被告之自用客車等語（見原審卷第18頁、\n    本院卷第59頁），而告訴人甲○○始終陳稱未見被告之自用\n    小客車等語（見原審卷第28頁、本院卷第66、67頁），足見\n    告訴人甲○○疏未注意車前狀況而與有過失，然仍無解於被\n    告之過失責任。綜上所述，被告過失傷害犯行，事證明確，\n    堪以認定。\n三、核被告所為，係犯刑法第284 條第1 項前段之過失傷害罪。\n    又被告肇事時係無駕駛執照駕駛自用小客車，有證照查詢汽\n    車駕駛人資料在卷可稽（警卷第25頁），被告未領有合法駕\n    照而駕車致人受傷，應依道路交通管理處罰條例第86條第1\n    項加重其刑。另被告於肇事後尚未被有偵查權限之該管機關\n    發覺其姓名及犯罪事實前，即向到場處理之員警承認為肇事\n    人而自首接受裁判，已經道路交通事故調查報告表載明，符\n    合自首要件，應依刑法第62條前段規定減輕其刑。被告上開\n    刑之加減應先加後減。\n四、原審據以論處被告罪刑，固非無見。惟查：(一)被告之自用小\n    客車暫停在五福國中校門前之五福一路東向西慢車道網狀線\n    上，亦有未遵守道路交通標線之指示之過失，原審未為此部\n    分過失之認定，尚有未當。(二)告訴人甲○○固指訴其因車禍\n    致門牙牙齒斷裂，並提出富泉牙醫診所之診斷證明書為佐。\n    然觀諸高雄市立民生醫院診斷證明書、寶建醫院診斷證明書\n    所載，告訴人甲○○於98年4 月25日因車禍受有腦震盪、顏\n    面擦傷及撕裂傷、左膝蓋撕裂傷、左手手腕橈骨骨折、胸部\n    挫傷、臉眼瘀傷等傷害，均未記載有門牙牙齒斷裂之情形，\n    而告訴人甲○○係於98年5 月7 日始因牙齒斷裂至富泉牙醫\n    診所就診，距98年4 月25日車禍發生時間已有十餘日，是告\n    訴人甲○○之牙齒斷裂是否確係車禍造成，尚難確信。原判\n    決認告訴人甲○○因車禍致門牙牙齒斷裂，亦有未合。被告\n    上訴意旨以原判決量刑過重，指摘原判決不當，尚屬無理由\n    ，惟原判決另有上開可議之處，自應由本院將原判決撤銷改\n    判。爰審酌被告前未曾犯罪，有被告前案紀錄表足憑，因駕\n    車過失致告訴人甲○○受傷，且告訴人甲○○亦與有過失，\n    惟被告迄未賠償告訴人甲○○達成和解等一切情狀，量處如\n    主文所示之刑，並諭知易科罰金之折算標準。\n據上論結，應依刑事訴訟法第369 條第1 項前段、第364 條、第\n299 條第1 項前段，刑法第284 條第1 項前段、第62條前段、第\n41條第1 項前段，道路交通管理處罰條例第86條第1 項，刑法施\n行法第1 條之1， 判決如主文。\n本案經檢察官李門騫到庭執行職務。\n中    華    民    國    99    年    5     月    12    日\n                  刑事第八庭    審判長法  官  洪兆隆\n                                      法  官  張盛喜\n                                      法  官  郭玫利\n以上正本證明與原本無異。\n不得上訴。\n中    華    民    國    99    年    5     月    12    日\n                                      書記官  梁美姿\n附錄本件判決論罪科刑法條\n中華民國刑法第284條第1項：\n因過失傷害人者，處6 月以下有期徒刑、拘役或5 百元以下罰金\n，致重傷者，處1 年以下有期徒刑、拘役或5 百元以下罰金。",
  "structure": {
    "main": "原判決撤銷。\n乙○○犯過失傷害罪，處有期徒刑參月，如易科罰金，以新台幣\n壹仟元折算壹日。",
    "fact": "一、乙○○於民國98年4 月25日上午10時5 分許，無駕駛執照駕\n    駛車牌號碼9019-QR 號自用小客車，沿高雄市苓雅區○○○\n    路由西向東行駛至五福國中校門前，欲左轉進入五福國中，\n    本應注意轉彎車應讓直行車先行，且應注意五福國中校門前\n    之五福一路東向西慢車道劃設有網狀線禁止臨時停車，當時\n    天候晴、日間有自然光線、路面乾燥、無缺陷、無障礙物、\n    視距良好，復無不能注意之情形，詎乙○○竟疏未注意甲○\n    ○駕駛ZNE －523 號機車沿五福一路慢車道由東往西行駛亦\n    近五福國中校門前，亦疏未注意五福國中校門前之五福一路\n    東向西慢車道劃設有網狀線禁止臨時停車，乙○○即駕車貿\n    然左轉而未讓甲○○之直行車先行，並因五福國中校門前已\n    停放其他車輛，乙○○遂暫停在五福國中校門前之五福一路\n    東向西慢車道網狀線上等候，適甲○○亦疏未注意車前狀況\n    及隨時採取必要安全措施，驟見乙○○之自用小客車停放在\n    前方慢車道上，乃閃煞不及而撞及黃淑芳之自用小客車右後\n    方車身，甲○○因而人車倒地，造成甲○○受有腦震盪、顏\n    面擦傷及撕裂傷、左膝蓋撕裂傷、左手手腕橈骨骨折、胸部\n    挫傷、臉眼瘀傷等傷害。乙○○於肇事後尚未被有偵查權限\n    之該管機關發覺犯行前，即向到場處理之員警承認為肇事人\n    而自首接受裁判。\n二、案經甲○○訴由高雄市政府警察局苓雅分局移請臺灣高雄地\n    方法院檢察署檢察官偵查起訴。",
    "reason": "一、證據能力之說明：\n    (一)高雄市立民生醫院診斷證明書、寶建醫院診斷證明書均係\n      從事業務之人依業務上所須製作之病歷紀錄文書而記載，\n      因病歷記錄時無預見日後將作為證據之偽造動機，其虛偽\n      之可能性較小，且如讓製作者以口頭方式在法庭上再重述\n      過去之事實或數據，實際上有其困難，具有一定程度之不\n      可代替性，復無顯不可信之情況，依刑事訴訟法第159 條\n      之4 規定，上開文書應具有證據能力。\n    (二)公務員職務上製作之紀錄文書、證明文書，除顯有不可信\n      之情況外，亦得為證據，刑事訴訟法第159 條之4 第1 款\n      定有明文。此所謂「紀錄文書」，係指就一定事實加以記\n      載之文書，而所謂「證明文書」，則指就一定事實之存否\n      而為證明之文書。上述「紀錄文書」或「證明文書」，並\n      不限於針對特定事件所製作。祇要公務員基於職務上就一\n      定事實之記載，或就一定事實之證明而製作之文書，若其\n      內容不涉及主觀之判斷或意見之記載，即屬於上述條款所\n      稱文書之範疇。是警察人員基於警察行政上所製作之交通\n      事故現場圖、道路交通事故調查報告表均在前開條款適用\n      之範圍，即應具有證據能力（最高法院98年度台上字第58\n      14號判決參照）。\n二、上訴人即被告乙○○（下稱被告）於事實欄所載時間無駕駛\n    執照駕車左轉而暫停在五福國中校門前之五福一路東向西慢\n    車道網狀線上，而後遭告訴人甲○○駕駛之機車撞及右後方\n    車身，甲○○因而人車倒地及受有腦震盪、顏面擦傷及撕裂\n    傷、左膝蓋撕裂傷、左手手腕橈骨骨折、胸部挫傷、臉眼瘀\n    傷等傷害等事實，已經證人即告訴人甲○○及證人沈亦良分\n    別於原審、本院審理中結證明確（見原審卷第18－19、26－\n    28頁、本院卷第55－59頁）；並有高雄市立民生醫院診斷證\n    明書、寶建醫院診斷證明書、交通事故現場圖、道路交通事\n    故調查報告表、現場照片附卷可稽（見警卷第6 、8 、14－\n    16、19－24頁）；且被告就上情亦不爭執，上開事實自堪以\n    認定。再依交通事故現場圖及現場照片所示，車禍發生後，\n    告訴人甲○○之機車倒地及物品散漏均係在五福一路東向西\n    慢車道上，顯見告訴人甲○○之機車撞及被告之自用小客車\n    左後方車身時，被告之自用小客車應係在五福一路東向西劃\n    設有網狀線之慢車道上，亦甚明確。按駕駛人駕駛汽車，應\n    遵守道路交通標誌、標線、號誌之指示，並服從交通指揮人\n    員之指揮；汽車行駛至交岔路口，轉彎車應讓直行車先行；\n    又汽車行駛時，駕駛人應注意車前狀況，並隨時採取必要之\n    安全措施；道路交通安全規則第90條、第102 條第1 項第7\n    款、第94條第3 項分別定有明文。另依道路交通標誌標線號\n    誌設置規則第173 條第1 項規定可知，網狀線用以告示車輛\n    駕駛人禁止在設置本標線之範圍內臨時停車，防止交通阻塞\n    。被告曾考領有駕駛執照，當知上開規定，而車禍發生當時\n    之天候晴、日間有自然光線、路面乾燥、無缺陷、無障礙物\n    、視距良好，有道路交通事故調查報告表可佐，被告復無不\n    能注意之情形，竟駕車貿然左轉而未讓告訴人甲○○之直行\n    車先行，並暫停在五福國中校門前之五福一路東向西慢車道\n    網狀線上，致告訴人甲○○閃煞不及而撞及被告之自用小客\n    車右後方車身，告訴人甲○○因而受有傷害，被告有過失責\n    任，且被告之過失與告訴人甲○○之受傷間有因果關係甚明\n    。再依證人沈亦良於原審及本院審理中均結證稱其駕駛機車\n    行駛在告訴人甲○○駕駛之機車後方，告訴人甲○○之機車\n    如向左偏應可閃避被告之自用客車等語（見原審卷第18頁、\n    本院卷第59頁），而告訴人甲○○始終陳稱未見被告之自用\n    小客車等語（見原審卷第28頁、本院卷第66、67頁），足見\n    告訴人甲○○疏未注意車前狀況而與有過失，然仍無解於被\n    告之過失責任。綜上所述，被告過失傷害犯行，事證明確，\n    堪以認定。\n三、核被告所為，係犯刑法第284 條第1 項前段之過失傷害罪。\n    又被告肇事時係無駕駛執照駕駛自用小客車，有證照查詢汽\n    車駕駛人資料在卷可稽（警卷第25頁），被告未領有合法駕\n    照而駕車致人受傷，應依道路交通管理處罰條例第86條第1\n    項加重其刑。另被告於肇事後尚未被有偵查權限之該管機關\n    發覺其姓名及犯罪事實前，即向到場處理之員警承認為肇事\n    人而自首接受裁判，已經道路交通事故調查報告表載明，符\n    合自首要件，應依刑法第62條前段規定減輕其刑。被告上開\n    刑之加減應先加後減。\n四、原審據以論處被告罪刑，固非無見。惟查：(一)被告之自用小\n    客車暫停在五福國中校門前之五福一路東向西慢車道網狀線\n    上，亦有未遵守道路交通標線之指示之過失，原審未為此部\n    分過失之認定，尚有未當。(二)告訴人甲○○固指訴其因車禍\n    致門牙牙齒斷裂，並提出富泉牙醫診所之診斷證明書為佐。\n    然觀諸高雄市立民生醫院診斷證明書、寶建醫院診斷證明書\n    所載，告訴人甲○○於98年4 月25日因車禍受有腦震盪、顏\n    面擦傷及撕裂傷、左膝蓋撕裂傷、左手手腕橈骨骨折、胸部\n    挫傷、臉眼瘀傷等傷害，均未記載有門牙牙齒斷裂之情形，\n    而告訴人甲○○係於98年5 月7 日始因牙齒斷裂至富泉牙醫\n    診所就診，距98年4 月25日車禍發生時間已有十餘日，是告\n    訴人甲○○之牙齒斷裂是否確係車禍造成，尚難確信。原判\n    決認告訴人甲○○因車禍致門牙牙齒斷裂，亦有未合。被告\n    上訴意旨以原判決量刑過重，指摘原判決不當，尚屬無理由\n    ，惟原判決另有上開可議之處，自應由本院將原判決撤銷改\n    判。爰審酌被告前未曾犯罪，有被告前案紀錄表足憑，因駕\n    車過失致告訴人甲○○受傷，且告訴人甲○○亦與有過失，\n    惟被告迄未賠償告訴人甲○○達成和解等一切情狀，量處如\n    主文所示之刑，並諭知易科罰金之折算標準。\n據上論結，應依刑事訴訟法第369 條第1 項前段、第364 條、第\n299 條第1 項前段，刑法第284 條第1 項前段、第62條前段、第\n41條第1 項前段，道路交通管理處罰條例第86條第1 項，刑法施\n行法第1 條之1， 判決如主文。\n本案經檢察官李門騫到庭執行職務。\n中    華    民    國    99    年    5     月    12    日\n                  刑事第八庭    審判長法  官  洪兆隆\n                                      法  官  張盛喜\n                                      法  官  郭玫利\n以上正本證明與原本無異。\n不得上訴。"
  },
  "characters": {
    "judges": [
      "洪兆隆",
      "張盛喜",
      "郭玫利"
    ],
    "prosecutors": [
      "李門騫"
    ],
    "lawyers": [
      "湯金全",
      "湯東穎"
    ],
    "clerks": [
      "梁美姿"
    ],
    "plaintiffs": [

    ],
    "defendants": [
      "乙"
    ],
    "prosecutor_office": [

    ],
    "creditors": [

    ],
    "debtors": [

    ],
    "judicial_associate_officer": [

    ]
  },
  "adjudged_at": "2010-05-12",
  "created_at": "2016-01-05 12:02:26",
  "updated_at": "2016-01-05 12:02:26"
}