{
  "identify": "KSH-98-上易-870-20100105-1",
  "court": {
    "name": "臺灣高等法院",
    "code": "KSH"
  },
  "division": {
    "name": "刑事",
    "code": "M"
  },
  "year": 98,
  "word": "上易",
  "number": "870",
  "jcheck": "1",
  "reason": "竊盜",
  "content": "臺灣高等法院高雄分院刑事判決         98年度上易字第863號\n上  訴  人  臺灣高雄地方法院檢察署檢察官\n上  訴  人\n即  被  告  丙○○\n上  訴  人\n即  被  告  甲○○\n被      告  田玟慧\n被      告  郭慧琳\n被      告  李建信\n上列上訴人等因被告等竊盜案件，不服臺灣高雄地方法院98年度\n易字第540 號；第565 號中華民國98年9 月22日第一審判決（起\n訴案號：臺灣高雄地方法院檢察署97年度偵字第17637 號；追加\n起訴案號：同署98年度偵字第12303 號），提起上訴，本院判決\n如下：\n     主  文\n上訴駁回。\n     事  實\n一、丙○○於民國90年1 月間，因傷害致死案件，經臺灣高雄地\n    方法院以89年度訴字第2596號判決判處有期徒刑8 年6 月確\n    定，於96年8 月24日縮刑假釋出監，至98年2 月26日始假釋\n    期滿（不構成累犯）。甲○○於90年9 月間，因違反職役職\n    責案件，經國防部高等軍事法院高雄分院以90年度高審字第\n    102 號判決判處有期徒刑2 年6 月確定；又於94年11月間，\n    因傷害案件，經本院以94年度上訴字第24號判決判處有期徒\n    刑8 月確定；上開2 罪經定應執行刑為有期徒刑3 年，於96\n    年6 月28日縮刑期滿執行完畢（構成累犯）。郭慧琳於94年\n    12月間，因違反毒品危害防制條例案件，經臺灣高雄地方法\n    院以94年度訴字第4072號判決判處有期徒刑8 月確定，於96\n    年2 月19日縮刑期滿執行完畢（構成累犯）。\n二、詎仍不知悔改，意圖為自己不法之所有，由丙○○與田玟慧\n    2 人，或夥同甲○○、郭慧琳、李建信其中之1 人或2 人，\n    共同基於竊盜之犯意聯絡，持客觀上足供兇器使用之T 型扳\n    手、螺絲起子或鐵鏟等物，於附表一所示之時、地，以附表\n    一所示之方式，共同竊取如附表一所示他人所有或管領之水\n    溝蓋、汽車或觸媒轉換器等財物，嗣經被害人報案後，為警\n    循線查獲。\n三、丙○○、甲○○又意圖為自己不法所有，共同基於竊盜之犯\n    意聯絡，於97年5 月15日上午6 時許，在高雄縣橋頭鄉○○\n    村○○路壽生巷25號前，由丙○○持客觀上足供兇器使用之\n    Ｔ型扳手1 支，竊取乙○○所有之車號ZJ-6313 號自用小貨\n    車（車上並有乙○○所有之三用電表、銅管切管器、噴燈、\n    電動起子及工具1 批等物品），甲○○則在旁把風。得手後\n    供丙○○使用。嗣同年月21日凌晨2 時35分許，在高雄市○\n    ○區○○街與監理南街口丙○○所駕駛H8-6680 號之自用小\n    客車上查獲上開失竊物品，始悉上情。\n四、案經林貴興、溫仁德、乙○○分別訴由高雄縣政府警察局岡\n    山分局、高雄市政府警察局楠梓分局報請臺灣高雄地方法院\n    檢察署檢察官偵查起訴。\n    理  由\n壹、證據能力部分：\n一、證人田玟慧於警詢之供述有證據能力：\n  (一)按被告以外之人於審判外之言詞或書面陳述，除法律有規定\n    者外，不得作為證據；被告以外之人於檢察事務官、司法警\n    察官或司法警察調查中所為之陳述，與審判中不符時，其先\n    前之陳述具有較可信之特別情況，且為證明犯罪事實存否所\n    必要者，得為證據，刑事訴訟法第159 條第1 項、第159 條\n    之2 分別定有明文。是依上開條文規定，被告以外之人於檢\n    察事務官、司法警察（官）調查時所為之陳述，屬傳聞證據\n    ，依同法第159 條規定，本無證據能力，必須「具有較可信\n    之特別狀況」及「必要性」2 要件，始例外得適用上開第15\n    9 條之2 規定，認有證據能力。而所謂「具有較可信之特別\n    情況」係屬於證據能力之要件，法院應就偵查或調查筆錄製\n    作之原因、過程及其功能等加以觀察其信用性予以判斷；又\n    此之「必要性」要件，必須該陳述之重要待證事實部分，與\n    審判中之陳述有所不符，包括先前之陳述詳盡、於後簡略，\n    甚至改稱忘記、不知道等，雖非完全相異，但實質內容已有\n    不符者在內（最高法院96年度台上字4304號、96年度台上字\n    第4365號、96年度台上字第4414號判決意旨參考）。\n  (二)證人即共同被告田玟慧於警詢中之供述，對於被告丙○○而\n    言，本屬被告以外之人於審判外之言詞陳述。而上開證人係\n    被告丙○○是否犯有加重竊盜犯行之重要證人，該證人於警\n    詢時對於被告丙○○涉犯竊盜之情節陳述甚詳，惟於原審審\n    理時翻異前詞，改稱不知道云云，有警詢筆錄2 份及審判筆\n    錄1 份存卷可證（警卷第38至43頁、原審院二卷第76頁），\n    足見該證人於警詢中及原審審判中證述之內容不符。又該證\n    人於原審審理時未曾證稱於警詢時，有遭員警以強暴、脅迫\n    、利誘、詐欺、疲勞訊問、違法羈押或其他不正之方法而違\n    法調查之情事，且其於警詢時所為有關被告丙○○加重竊盜\n    事實之證述，相較其於原審審理時所為，距案發當時較近，\n    且非在被告丙○○面前所為，依此外部情況，顯較無受不當\n    干擾及事後串謀之可能性，堪認該證人於警詢中之陳述具有\n    特別可信之情況，且為證明被告丙○○之犯罪存否所必要，\n    依同法第159 條之2 規定，其於警詢中之陳述應具有證據能\n    力。\n二、其他傳聞證據部分：\n  (一)按被告以外之人於審判外之陳述，雖不符前4 條之規定，而\n    經當事人於審判程序中同意作為證據，法院審酌該言詞陳述\n    或書面陳述作成時之情況，認為適當者，亦得為證據。當事\n    人、代理人或辯護人於法院調查證據時，知有第159 條第1\n    項不得為證據之情形，而未於言詞辯論終結前聲明異議者，\n    視為有前項之同意，刑事訴訟法第159 條之5 定有明文。\n  (二)本件所引用之其他傳聞證據，檢察官、被告及辯護人於本院\n    準備程序中及審理時均知並無證據能力，惟均表示同意或無\n    意見等語，本院審酌該證據作成時之情況，認以之作為證據\n    亦屬適當，依上開規定均有證據能力。\n貳、實體部分：\n一、有罪部分：\n  (一)訊據上訴人即被告丙○○對於附表一編號1 至8 、10及事實\n    三；被告田玟慧對於附表一編號1 至10；上訴人即被告甲○\n    ○對於附表一編號8 至10；被告郭慧琳對於附表一編號9 、\n    10；被告李建信對於附表一編號3 所示之竊盜犯行，分別於\n    本院審理時坦承不諱，核與證人證人黃慧木、證人即被害人\n    何富鵬、陳美雲、馬錫恩、郭錦傳、塗永龍、尤嘉宏、蔡龍\n    統、乙○○，分別於警詢或偵查時之證述之情節相符。並有\n    搜索扣押筆錄、扣押物品目錄表、車輛尋獲電腦輸入單、贓\n    物認領保管單、行照影本及現場照片等在卷可佐，上開被告\n    之自白核與事實相符，其等確涉有前揭竊盜之犯行，堪以認\n    定。\n  (二)被告丙○○矢口否認涉有附表一編號9 所示之竊盜犯行，辯\n    稱：當天伊未去云云。惟查：\n  1.被告丙○○確犯有上開竊盜事實，業據證人即共同被告田玟\n    慧於警詢時證稱：被告丙○○於97年5 月14日19時許，駕駛\n    不詳牌號贓車、懸掛伊所有之H8-6680 號自用小客車車牌，\n    搭載「哲仔（指被告甲○○）」、「妹仔（指被告郭慧琳）\n    」與伊至高雄縣橋頭鄉○○○路148 巷6 弄巷道內，由「哲\n    仔」及被告丙○○下車竊取水溝蓋，伊與「妹仔」在車內把\n    風，並當場竊得6 個水溝蓋，然後將竊得之水溝蓋放置於該\n    贓車之後車廂內，再由被告丙○○與「哲仔」、「妹仔」與\n    伊共同駕乘該贓車逃逸現場，然後伊與「妹仔」中途下車至\n    網咖玩打電腦，「哲仔」及被告丙○○則駕駛該輛贓車去變\n    賣贓物等語（警卷第42頁）；證人即共同被告甲○○於偵查\n    時證稱：當時伊負責下車偷水溝蓋，被告丙○○、郭慧琳下\n    車巡看現場後，與被告田玟慧一起在車上把風；被告丙○○\n    知道伊要偷水溝蓋等語（偵卷第73頁），所證核與被害人即\n    橋隆商城之主委蔡龍統於警詢時證述之情節相符（警卷第82\n    頁），而被告丙○○為被告田玟慧之同居男友，被告郭慧琳\n    則為被告甲○○之未婚妻，其等經常共同出入活動，此為被\n    告丙○○、郭慧琳所不否認（偵卷第35至38、74至76頁），\n    證人即共同被告田玟慧、甲○○之證言應堪信為真實，此外\n    ，復有被告田玟慧指認現場照片2 張、車籍查詢基本資料詳\n    細畫面等附卷可考（警卷第98、106 、119 、125 頁）。\n  2.被告丙○○所辯，顯與事實相違，不足採憑。被告丙○○確\n    有與郭慧琳、甲○○、田玟慧共同為附表一編號9 之竊取水\n    溝蓋之犯行無訛。\n  (三)被告甲○○雖矢口否認有事實三之竊盜犯行，辯稱：當時伊\n    去廟邊上廁所，伊不知道被告丙○○去偷車，也未幫他把風\n    ，等到被告丙○○竊取上開車輛回來時，伊才知道他去偷車\n    云云。惟查：\n  1.被告甲○○確有夥同被告丙○○於事實三之時地，以T 型扳\n    手竊取車號ZJ-6313 號自用小貨車及該車上之三用電表等工\n    具之事實，業據被告甲○○於警詢時供稱：上開車輛是被告\n    丙○○提議行竊及竊取的，伊則在場把風，原本該批工具就\n    放在車上，是伊等一起行竊的等語（併案警卷第1 頁），於\n    偵查時供稱：上開車輛是由被告丙○○用T 型扳手偷來的，\n    伊在旁邊的廟內把風；當時伊去廟內上廁所，出來就看被告\n    丙○○偷了1 台車等語（併案偵卷第14頁），核與證人即共\n    同被告丙○○於警詢時供稱：車號ZJ-6313 號自用小貨車不\n    是伊偷竊的，是伊朋友「阿哲（即被告甲○○）」交給伊的\n    ，於97年5 月18、19日晚上，在高雄縣大社鄉一處公園將三\n    用電表、銅管切管器、噴燈、電動起子、工具1 批等物搬到\n    伊車上等語（見併案警卷第2 頁及背面），於偵查及原審準\n    備程序中供稱：係持T 型扳手行竊的等語（併案偵卷第16頁\n    ；原審院三卷第47頁），及證人即被害人乙○○於警詢所證\n    失竊之情節相符（併案警卷第7 至8 頁）。\n  2.此外，復有搜索扣押筆錄、扣押物品目錄表、贓物認領保管\n    單、行照影本、上開車輛之失竊及尋獲紀錄各1 份及相片2\n    張等件在卷可稽（併案警卷第11至15、18至19頁）。\n  3.被告甲○○嗣自原審審理時起否認此部分犯行，被告丙○○\n    亦證稱：該車是伊自己偷的云云，均核係事後卸責及迴護之\n    詞，均難採信，被告甲○○確涉有事實三之攜帶兇器竊盜犯\n    行無訛。\n  (四)被告丙○○對於附表一編號1 、2 ；被告甲○○對於附表一\n    編號8 至10部分，復均於本院審理時辯稱：未攜帶兇器行竊\n    云云。惟被告丙○○、甲○○等人竊取車輛之作案工具係T\n    型扳手，觸媒轉換器為螺絲起子，水溝蓋為鐵鏟等情，業據\n    證人即各該次竊盜之共同被告田玟慧於警詢時證述屬實，且\n    被告丙○○於本院審理前之各次筆錄，均對前開攜帶兇器竊\n    盜部分均坦承不諱，並未為此爭執；被告甲○○於本院審理\n    前之各次筆錄，亦均未為此抗辯，而各該次竊盜之共同被告\n    田玟慧、丙○○對於上開竊盜均係攜帶兇器犯之各節，則均\n    坦認不移。再衡諸經驗法則，水溝蓋係固定於水溝上方之凹\n    槽，多與地面密切接合，若未利用鐵鏟等工具，實難掀開及\n    竊取水溝蓋；而汽車之門鎖、電門大鎖及觸媒轉換器係分別\n    固定於車門、方向盤下方及排氣管上，若未利用T 型扳手、\n    螺絲扳手等工具，實不可能破壞門鎖、啟動引擎及拆卸觸媒\n    轉換器等情。堪認被告丙○○、甲○○於前揭竊盜犯行，均\n    係攜帶兇器犯之無疑，其等嗣於本院審理時始為上開抗辯，\n    核係飾卸之詞，均難憑採。\n三、\n  (一)按刑法第321 條第1 項第3 款之攜帶兇器竊盜罪，係以行為\n    人攜帶兇器竊盜為其加重條件，此所謂兇器，其種類並無限\n    制，凡客觀上足對人之生命、身體、安全構成威脅，具有危\n    險性之兇器均屬之，且祇須行竊時攜帶此種具有危險性之兇\n    器為已足，並不以攜帶之初有行兇之意圖為必要（最高法院\n    79年度台上字第5253號判例意旨參考）。被告丙○○等人於\n    竊取水溝蓋、汽車及觸媒轉換器時，所使用之T 型扳手、螺\n    絲起子、鐵鏟等工具雖未扣案，惟上開工具既能用以破壞門\n    鎖、發動引擎、拆卸觸媒轉換器及水溝蓋，足認上開工具材\n    質堅硬，客觀上均足以傷害人之生命、身體，性質上均屬具\n    有危險性之兇器無訛。\n  (二)核被告丙○○、田玟慧如附表一編號1 、2 、4 、5 、6 、\n    7 ；被告丙○○、甲○○如事實三所為，均係犯法第321 條\n    第1 項第3 款之攜帶兇器竊盜罪。被告丙○○、田玟慧、甲\n    ○○如附表一編號8 ；被告丙○○、田玟慧、甲○○、郭慧\n    琳如附表一編號9 ，及被告田玟慧、甲○○、郭慧琳如附表\n    一編號10所為，均係犯刑法第321 條第1 項第4 款、第3 款\n    之結夥三人以上攜帶兇器竊盜罪；被告丙○○、田玟慧、李\n    建信如附表一編號3 所為，係犯刑法第321 條第2 項、第1\n    項第4 款、第3 款之結夥三人以上攜帶兇器竊盜未遂罪。被\n    告丙○○與田玟慧就如附表一編號1 、2 、4 、5 、6 、7\n    ；被告丙○○、田玟慧、李建信就如附表一編號3 ；被告丙\n    ○○、田玟慧、甲○○就如附表一編號8 ；被告丙○○、田\n    玟慧、甲○○、郭慧琳就如附表一編號9 ；被告田玟慧、甲\n    ○○、郭慧琳就如附表一編號10，及被告丙○○、甲○○就\n    如事實三所示之犯行，彼此間互有犯意聯絡及行為分擔，均\n    為共同正犯。被告丙○○、田玟慧、李建信3 人就附表一編\n    號3 部分，已著手於竊盜行為之實行而不遂，為未遂犯，應\n    依刑法第25條第2 項規定減輕其刑。被告甲○○、郭慧琳2\n    人分別有如事實一所載科刑及執行完畢情形，有臺灣高等法\n    院被告前案紀錄表2 份在卷足憑，其等於受有期徒刑執行完\n    畢後，5 年內故意再犯本件法定刑為有期徒刑以上之前揭各\n    罪，均應論以累犯，並加重其刑。\n四、\n  (一)原審認被告罪證明確，因而適用刑法刑法第321 條第2 項（\n    原判決漏引）、第1 項第3 款、第4 款、第28條、第47條第\n    1 項、第41條第1 項、第51條第5 款之規定（原判決贅引刑\n    法第320 條第1 項、刑法施行法第1 條之1 ），並審酌被告\n    丙○○等5 人正值青壯，不思以正當途徑賺取財物，率爾竊\n    取他人財物，所為實有不該；另衡以被告丙○○為竊盜集團\n    之首腦，率領集團成員四處行竊，涉犯加重竊盜之情節最重\n    ，餘被告田玟慧等4 人情節較輕，復念其等於犯後已坦承大\n    部分犯行，且所竊得財物亦部分歸還被害人，有贓物認領保\n    管單5 份在卷可參，所生損害業已減輕等其他一切情狀，分\n    別量處附表一主文欄所載之刑，並就被告丙○○、田玟慧、\n    甲○○、郭慧琳部分，定其應執行之刑；再就被告丙○○、\n    田玟慧、李建信如附表一編號3 之竊盜部分，均諭知以1000\n    元折算1 日之易科罰金折算標準。被告丙○○等5 人持供犯\n    罪所用之T 型扳手、螺絲起子、鐵鏟等工具並未扣案，亦均\n    非違禁物，為免將來執行上之困難，不予宣告沒收。\n  (二)原判決認事用法，核無不合，量刑亦屬允當。檢察官認如表\n    一編號3 部分，量刑失衡，另被告丙○○有犯罪之習慣，原\n    審未為諭知強制工作，尚有未合，指摘原判決不當，提起上\n    訴，並無理由，應由予駁回。被告丙○○否認如附表一編號\n    9 部分，並認編號1 、2 部分並非攜帶兇器為之；被告甲○\n    ○否認事實三部分，並認如附表一編號8 至10部分，均未攜\n    帶兇器為之，亦分別指摘原判決不當，提起上訴，均無理由\n    ，亦應予以駁回。\n五、公訴人於認被告丙○○有竊盜前科，於服刑完畢後仍於短期\n    內一再犯竊盜案件，顯有犯罪之習慣，應於刑之執行前令入\n    勞動場所強制工作，以改遭其惡習云云。\n  (一)惟按保安處分係針對受處分人將來之危險性所為之處置，以\n    達教化、治療之目的，為刑罰之補充制度。我國現行刑法採\n    刑罰與保安處分雙軌制，係在維持行為責任之刑罰原則下，\n    為協助行為人再社會化之功能，以及改善行為人潛在之危險\n    性格，期能達成根治犯罪原因、預防犯罪之特別目的。是保\n    安處分中之強制工作，旨在對嚴重職業性犯罪及欠缺正確工\n    作觀念或無正常工作因而犯罪者，強制其從事勞動，學習一\n    技之長及正確之謀生觀念，使其日後重返社會，能適應社會\n    生活。保安處分之措施亦含社會隔離、拘束身體自由之性質\n    ，其限制人民之權利，實與刑罰同，本諸法治國家保障人權\n    之原理及刑法之保護作用，其法律規定之內容，應受比例原\n    則之規範，使保安處分之宣告，與行為人所為行為之嚴重性\n    、行為人所表現之危險性，及對於行為人未來行為之期待性\n    相當。刑法第90條及竊盜犯贓物犯保安處分條例第3 條第1\n    項關於強制工作之規定，均係本於上開意旨制定，而由法院\n    視個案中行為人之危險性格，以決定應否交付強制工作，以\n    達保安處分之特別預防之目的（司法院大法官會議釋字第\n    471 號解釋參考）。\n  (二)查被告丙○○自97年4 月中旬至同年5 月15日間，雖確有上\n    開10次竊盜犯行，已如上述。然被告在此之前，除於88年間\n    ，曾因竊盜犯行，經判處有期徒刑6 月確定外，即無其他竊\n    盜前科紀錄，有卷附臺灣高等法院被告前案紀錄表1 份附卷\n    可查，故是否堪認被告丙○○是否有犯罪習慣，已非無疑。\n    此外，復查無其他積極證據足資證明被告丙○○係以本件竊\n    盜犯行為其經濟生活之主要支柱，足徵被告前揭多次竊盜犯\n    行均應係因一時貪圖小利，始起意行竊，尚難認其係職業性\n    犯罪，亦難逕認其係因欠缺正確工作觀念或無正常工作而有\n    竊盜犯罪之習性，即與刑法第90條所稱：「有犯罪之習慣或\n    因遊蕩或懶惰成習而犯罪者」或竊盜犯贓物犯保安處分條例\n    第3 條前段：「18歲以上之竊盜犯、贓物犯，有犯罪之習慣\n    者」之規定有別，參諸前揭大法官會議解釋意旨，堪認被告\n    丙○○前揭所為，尚未具有常習性，對其未來之行為仍有期\n    待性，並參酌就強制工作並非矯正其竊盜犯行唯一方法，尚\n    需合乎比例原則以求法益間之均衡等情綜合以觀，認上開對\n    其宣告徒刑即足以收矯治之效，是尚無對被告丙○○宣告強\n    制工作之必要。\n貳、無罪部分：\n一、公訴意旨另以：被告丙○○、田玟慧、甲○○、郭慧琳意圖\n    為自己不法之所有，由丙○○與田玟慧2 人，或夥同甲○○\n    、郭慧琳2 人，共同基於竊盜之犯意聯絡，持客觀上足供兇\n    器使用之T 型扳手、螺絲起子或鐵鏟等物，於附表二所示之\n    時地，以附表二所示之方式，共同竊取如附表二所示他人所\n    有或管領之水溝蓋、汽車或觸媒轉換器等財物，嗣經被害人\n    報案後，為警循線查獲，因認被告丙○○等4 人另犯有刑法\n    第第321 條第4 款、第3 款之加重竊盜犯行云云。\n二、按犯罪事實應依證據認定之，無證據不得認定犯罪事實；無\n    證據能力、未經合法調查之證據，不得作為判斷之依據；不\n    能證明被告犯罪或其行為不罰者，應諭知無罪之判決，刑事\n    訴訟法第154 條第2 項、第155 條第2 項、第301 條第1 項\n    分別定有明文。次按認定不利於被告之事實，須依積極證據\n    ，苟積極證據不足為不利於被告事實之認定時，即應為有利\n    被告之認定，更不必有何有利之證據，復有最高法院30年上\n    字第816 號判例可資參考。又事實之認定，應憑證據，如未\n    能發現相當證據，或證據不足以證明，自不能以推測或擬制\n    之方法，為裁判基礎；認定犯罪事實，所憑之證據，雖不以\n    直接證據為限，間接證據亦包括在內，然無論直接或間接證\n    據，其為訴訟上之證明，須於通常一般之人均不致於有所懷\n    疑，而得確信其為真實之程度者，始得據之為有罪之認定，\n    倘其證明尚未達到此一程度，而有合理性懷疑之存在時，即\n    無從為有罪之認定（最高法院40年度台上字第86號、76年度\n    台上字第4986號判例意旨參考）。況刑事訴訟法第161 條第\n    1 項亦規定，檢察官就被告犯罪事實，應負舉證責任，並指\n    出證明之方法，是檢察官對於起訴之犯罪事實，應負提出證\n    據及說服之實質舉證責任，倘其所提出之證據，不足為被告\n    有罪之積極證明，或其指出證明之方法，無從說服法院以形\n    成被告有罪之心證，基於無罪推定之原則，自應為被告無罪\n    判決之諭知（最高法院92年度台上字第128 號判例意旨參考\n    ）。\n三、附表二編號1、2 部分：\n  (一)公訴人認被告丙○○、田玟慧、甲○○、郭慧琳涉犯如附表\n    二編號1 所示之犯行，及被告丙○○、田玟慧涉犯如附表二\n    編號2 所示之犯行，均係以被告田玟慧於警詢時之供述及指\n    認犯罪現場照片4 張為其論據。訊據被告丙○○等4 人均堅\n    詞否認有為如附表二編號1 所示之犯行；被告丙○○、田玟\n    慧亦堅詞否認有為如附表二編號2 所示之犯行。被告丙○○\n    、甲○○、郭慧琳均辯稱：伊等並未於上開時、地竊盜等語\n    。被告田玟慧則辯稱：伊只有待在車上，不知道被告丙○○\n    、甲○○、郭慧琳下車做什麼等語。\n  (二)經查：\n  1.高雄縣橋頭鄉公所設置於該鄉○○路旁之水溝蓋4 個，於97\n    年4 月間確曾遭竊之事實，固據證人即橋頭鄉公所建設課技\n    士林貴興於警詢時證述明確（警詢第56、57頁）；同年4 月\n    22日，溫仁德所有之車號ZR-4986 號自用小貨車及4839-XK\n    號自用小客車上之觸媒轉換器2 組均失竊各情，亦據證人溫\n    仁德於警詢時證述綦詳（警詢第58至60頁），並有被告田玟\n    慧之指認犯罪現場照片4 張（警卷第99、101 頁）。惟上開\n    證據僅得證明曾經失竊之事實，尚難以此推認上開物品必為\n    被告丙○○等4 人所竊取。\n  2.被告田玟慧於警詢時固供稱：於97年4 月中旬2 時許，伊與\n    被告丙○○、「哲仔」、郭慧琳在高雄縣橋頭鄉○○路旁竊\n    取水溝蓋，當時由被告丙○○與甲○○下車竊取路旁之水溝\n    蓋，伊與被告郭慧琳在車上，然後被告丙○○及「哲仔」竊\n    取得逞後，叫伊等將後車廂打開，再將該水溝蓋放置於該車\n    輛之後車廂內，先將「哲仔」、被告郭慧琳送回家，伊與被\n    告丙○○再開車至旅館睡覺；於97年4 月22日2 時許，被告\n    丙○○駕駛自用小客車，載伊跟「阿信」在高雄縣橋頭鄉○\n    ○村○道○路82號旁空地，由被告丙○○與「阿信」下車竊\n    取停放在該處的自用小貨車車號ZR-8496 與自用小客車車號\n    4839-XK 車子下方的觸媒轉換器，得手後由被告丙○○回車\n    上開車逃逸現場云云（警卷第41、48頁）。惟被告田玟慧已\n    於原審審理時翻異前詞，改稱：伊等只有路過上開地點，並\n    未下車等語（原審院二卷第68頁背面）。足見被告田玟慧於\n    前後之供述顯有瑕疵可指，尚難據為不利被告之認定。\n四、附表二編號3、4部分：\n  (一)公訴人認被告甲○○、郭慧琳涉犯如附表二編號3 、4 所示\n    之犯行，係以被告田玟慧於警詢之供述及指認犯罪現場照片\n    2 張為其論據。訊據被告甲○○、郭慧琳均堅詞否認有上開\n    犯行。被告甲○○、郭慧琳均辯稱：伊等並未於上開時地竊\n    盜等語\n  (二)經查：\n  1.本件確有如附表二編號3 、4 之營業用小客車、自用小貨車\n    及媒轉換器等失竊等事實，固據證人即被害人郭錦傳、塗永\n    龍於警詢中證述屬實，並有被告田玟慧之指認犯罪現場照片\n    2 張（見警卷第102 、105 頁）在卷可考。惟此僅得證明失\n    竊之客觀事實而已，尚難以此為不利被告之認定。\n  2.被告田玟慧於警詢時固供稱：於97年5 月5 日8 時許，被告\n    丙○○駕駛自用小客車載「哲仔」「妹仔」與伊至橋頭鄉○\n    ○路32之4 號前，由被告丙○○下車竊取車號737-NQ營業用\n    小客車，再由「哲仔」駕駛被告丙○○原本駕駛的車輛載伊\n    跟「妹仔」離開，與被告丙○○所駕駛的贓車一起去高雄縣\n    燕巢鄉○○村○○路50號前棄置，並竊取該車觸媒轉換器後\n    ，由被告丙○○駕駛原本的車子離去；又於97年5 月12日21\n    時許，被告丙○○駕駛車號不詳之贓車，載「哲仔」、「妹\n    仔」與伊至大社鄉○○路44巷6 號前，由被告丙○○下車竊\n    取自用小貨車車號VC-9391 自用小貨車，竊取得逞後，由被\n    告丙○○駕駛該贓車，「哲仔」駕駛被告丙○○原本駕駛的\n    車輛載伊跟「妹仔」離開，與被告丙○○駕駛的贓車一起去\n    高雄縣燕巢鄉○○路高鐵橋下棄置，並竊取該車觸媒轉換器\n    管後，由被告丙○○駕駛原本的車子離去；伊跟「妹仔」只\n    是坐在車後座，都沒有下車行竊，只是負責把風而已云云（\n    警卷第41至43頁）。然被告田玟慧於原審審理時已翻異前詞\n    ，改稱：伊不知道被告丙○○等人下車做什麼等語（原審院\n    一卷第76頁）。足見被告田玟慧之供述顯有前後矛盾之情形\n    ，尚難據此援為不利被告甲○○、郭慧琳之認定。\n  3.共同被告田玟慧、丙○○於本院審理時均已坦認此2 部分事\n    實，係其等所為等語，參諸證人即共同被告丙○○於原審審\n    理時具結證稱：如附表二編號3 、4 之犯行，被告甲○○、\n    郭慧琳有沒有去，伊不記得了等語（原審院二卷第69頁背面\n    ）等參互以觀，堪認如附表二編號3 、4 之竊盜事實，被告\n    甲○○、郭慧琳並未參與無訛。\n五、附表二編號5 部分：\n  (一)公訴人認被告郭慧琳涉犯此部分竊盜犯行，無非係以被告田\n    玟慧於警詢之供述及指認犯罪現場照片2 張為其論據。訊據\n    被告郭慧琳堅詞否認有為此部分犯行。辯稱：伊並未於上開\n    時地竊盜等語。\n  (二)經查：\n  1.本件確有如附表二編號5 之自用小客車及觸媒轉換器失竊之\n    事實，固據證人即被害人蔡龍統於警詢時證述明確，並有被\n    告田玟慧之指認犯罪現場照片2 張在卷可佐（警卷第104 頁\n    ），惟此僅得證明有失竊之客觀事實而已，尚難為不利被告\n    郭慧琳之認定。\n  2.被告田玟慧於警詢時固供稱：於97年5 月13日4 時許，被告\n    丙○○駕駛車號不詳之贓車，載「哲仔」、「妹仔」與伊至\n    大社鄉○○路63號前，由被告丙○○下車竊取車號F5-9373\n    自用小貨車，由丙○○駕駛竊得之贓車，「哲仔」駕駛被告\n    丙○○原本駕駛的車輛載伊跟「妹仔」離開，然後讓伊中途\n    下車後，伊就不曉得他們的去向；伊跟「妹仔」只是坐在車\n    後座，都沒有下車行竊，員負責把風而已云云（警卷第42、\n    43頁）。惟其已於原審審理時翻異前詞，改稱：伊不知道被\n    告丙○○等人下車做什麼等語（原審院一卷第76頁）。足見\n    被告田玟慧於警詢及原審審理中之供述，顯有前後不一之瑕\n    疵，自難遽予採信。參諸被告丙○○、田玟慧、甲○○已坦\n    認此部分竊盜乙節，堪認被告郭慧琳應無參與此部分竊盜事\n    實無訛。\n六、附表二編號6 部分：\n  (一)公訴人認被告丙○○涉犯此部分竊盜犯行，係以監視器翻拍\n    照片1 張為其論據。訊據被告丙○○堅詞否認有為此部分犯\n    行。辯稱：伊固有與被告甲○○、田玟慧、郭慧琳前往上開\n    地點，但是到現場後因看到有人，所以伊就離開，加上被告\n    甲○○、郭慧琳於當天早上就已經先騎機車至該處竊取水溝\n    蓋，所以伊才沒有下手作案；伊沒有於上開時間至上開地點\n    竊取水溝蓋等語。\n  (二)經查：\n  1.被告田玟慧、甲○○、郭慧琳於97年5 月15日下午2 時許，\n    在高雄縣橋頭鄉○○○路148 巷6 弄巷道內，共同竊取橋隆\n    商城所有之水溝蓋4 個之事實，業據證人即被害人蔡龍統於\n    警詢時證述明確，並為前揭被告3 人所是認不諱。\n  2.觀諸警方調閱案發地點附近之監視器畫面，確有錄得被告丙\n    ○○與被告甲○○、郭慧琳先後出現在上開地點附近之影像\n    ，此有監視器翻拍照片3 張存卷可考（警卷第125 頁）。然\n    查上開監視器影像拍攝之時間為97年5 月14日下午，而本次\n    犯罪時間為同年5 月15日，則上開監視器畫面自不足以認定\n    被告丙○○有與被告田玟慧、甲○○、郭慧琳共同為此部分\n    之竊盜犯行。\n七、綜上所述，被告丙○○、田玟慧、甲○○、郭慧琳所為之上\n    開辯解，尚堪採信。而公訴人所舉之證據與指出之證明方法\n    ，尚有合理性之懷疑存在，未達使本院確信被告丙○○等人\n    犯有刑法第321 條第1 項第3 款、第4 款之加重竊盜罪之事\n    實。揆諸前開說明，應認被告丙○○等4 人關於上開犯罪尚\n    屬不能證明。此外，本院復查無其他積極證據可資認定被告\n    丙○○等4 人涉有前開罪名，自屬不能證明被告犯罪。\n八、原審以上開如附表二部分，被告丙○○等4 人之犯罪不能證\n    明，因而分別為其等無罪之諭知，並無不合。檢察官以上開\n    附表二部分，原審未諭知有罪為不當，提起上訴，並無理由\n    ，應予駁回。\n參、據上論斷，應依刑事訴訟法第368 條，判決如主文。\n本案經檢察官劉玲興到庭執行職務。\n中    華    民    國    99    年    1     月    5     日\n                  刑事第七庭    審判長法  官  莊飛宗\n                                      法  官  黃憲文\n                                      法  官  陳明富\n以上正本證明與原本無異。\n本件判決不得上訴。\n中    華    民    國    99    年    1     月    5     日\n                                      書記官  劉鴻瑛\n附錄本論罪科刑之法條全文：\n刑法第321條：\n犯竊盜罪而有左列情形之一者，處6月以上5年以下有期徒刑：\n一、於夜間侵入住宅或有人居住之建築物、船艦，或隱匿其內而\n    犯之者。\n二、毀越門扇、牆垣或其他安全設備而犯之者。\n三、攜帶兇器而犯之者。\n四、結夥3 人以上而犯之者。\n五、乘火災、水災或其他災害之際而犯之者。\n六、在車站或埠頭而犯之者。\n前項之未遂罰之。\n附表一（有罪部分）：\n ┌──┬───────┬───────────┬───┬────┬──────────────┐\n │編號│犯罪時間、地點│竊盜方式及竊得財物    │被害人│被告    │主文（被告之論罪及科刑）    │\n ├──┼───────┼───────────┼───┼────┼──────────────┤\n │ 1  │於97年4 月中旬│丙○○駕駛田玟慧所有車│尚郁建│丙○○、│丙○○共同犯攜帶兇器竊盜罪，│\n │    │某日晚間7 時許│號H8 -6680號自用小客車│設實業│田玟慧  │處有期徒刑捌月。            │\n │    │，在高雄縣岡山│，搭載田玟慧前往，由田│股份有│        │田玟慧共同犯攜帶兇器竊盜罪，│\n │    │鎮○○○路58巷│玟慧在車上把風，丙○○│限公司│        │處有期徒刑柒月。            │\n │    │              │下車，以客觀上足供兇器│      │        │                            │\n │    │              │使用之鐵鏟，行竊水溝蓋│      │        │                            │\n │    │              │10 個得逞。           │      │        │                            │\n ├──┼───────┼───────────┼───┼────┼──────────────┤\n │ 2  │於97年4 月中旬│丙○○駕駛田玟慧所有車│尚郁建│丙○○、│丙○○共同犯攜帶兇器竊盜罪，│\n │    │某日（編號1 之│號H8-6680 號自小客車，│設實業│田玟慧  │處有期徒刑捌月。            │\n │    │翌日）凌晨2 時│搭載田玟慧前往，由田玟│股份有│        │田玟慧共同犯攜帶兇器竊盜罪，│\n │    │許，在高雄縣岡│慧在車上把風，丙○○下│限公司│        │處有期徒刑柒月。            │\n │    │山鎮○○○路58│車，以客觀上足供兇器使│      │        │                            │\n │    │巷            │用之鐵鏟，行竊水溝蓋9 │      │        │                            │\n │    │              │個得逞。              │      │        │                            │\n ├──┼───────┼───────────┼───┼────┼──────────────┤\n │ 3  │於97年4 月29日│丙○○駕駛承租之車號40│何富鵬│丙○○、│丙○○共同犯結夥三人以上攜帶│\n │    │凌晨3 時55分許│50-XD 號馬自達自用小客│      │田玟慧、│兇器竊盜罪，未遂，處有期徒刑│\n │    │，在高雄縣橋頭│車，搭載田玟慧、李建信│      │李建信  │肆月，如易科罰金，以新台幣壹│\n │    │鄉○○村○○路│前往，由丙○○、田玟慧│      │        │仟元折算壹日。田玟慧共同犯結│\n │    │242 號前      │在車上把風，李建信下車│      │        │夥三人以上攜帶兇器算盜罪，未│\n │    │              │，以客觀上足供兇器使用│      │        │遂，處有期徒刑參月，如易科罰│\n │    │              │之T 型扳手、螺絲起子，│      │        │金，以新台幣壹仟元折算壹日。│\n │    │              │破壞鑰匙孔及剪斷電源線│      │        │李建信共同犯結夥三人以上攜帶│\n │    │              │方式行竊車號VP-0093 號│      │        │兇器竊盜罪，未遂，處有期徒刑│\n │    │              │自用小貨車（價值約7 萬│      │        │參月，如易科罰金，以新臺幣壹│\n │    │              │元）時，為被害人發現而│      │        │仟元折算壹日。              │\n │    │              │逃逸（未遂）。        │      │        │                            │\n ├──┼───────┼───────────┼───┼────┼──────────────┤\n │ 4  │於97年5 月1 日│丙○○駕駛車號不詳車輛│陳美雲│丙○○、│丙○○共同犯攜帶兇器竊盜罪，│\n │    │晚間7 時許，在│，搭載田玟慧前往，由田│      │田玟慧  │處有期徒刑捌月。            │\n │    │高雄市楠梓區惠│玟慧在車上把風，丙○○│      │        │田玟慧共同犯攜帶兇器竊盜罪，│\n │    │豐里監理街43號│下車，以客觀上足供兇器│      │        │處有期徒刑柒月。            │\n │    │前            │使用之T 型扳手、螺絲起│      │        │                            │\n │    │              │子，行竊車號J8-7706 號│      │        │                            │\n │    │              │自用小貨車（價值約4 萬│      │        │                            │\n │    │              │元），得手後將該車開至│      │        │                            │\n │    │              │橋頭鄉南村公墓旁，拆下│      │        │                            │\n │    │              │該車觸媒轉換器，棄置該│      │        │                            │\n │    │              │自用小貨車後逃逸。    │      │        │                            │\n │    │              │                      │      │        │                            │\n ├──┼───────┼───────────┼───┼────┼──────────────┤\n │ 5  │於97年5 月3 日│丙○○駕駛車號不詳車輛│馬錫恩│丙○○、│丙○○共同犯攜帶兇器竊盜罪，│\n │    │上午10時許，在│，搭載田玟慧前往，由田│      │田玟慧  │處有期徒刑捌月。            │\n │    │高雄縣燕巢鄉義│玟慧在車上把風，丙○○│      │        │田玟慧共同犯攜帶兇器竊盜罪，│\n │    │大路旁        │下車，以客觀上足供兇器│      │        │處有期徒刑柒月。            │\n │    │              │使用之T 型扳手、螺絲起│      │        │                            │\n │    │              │子，行竊車號X2-4293 號│      │        │                            │\n │    │              │自用小客車（價值約1 萬│      │        │                            │\n │    │              │5, 000元），得手後將該│      │        │                            │\n │    │              │車開至高雄市楠梓區信昌│      │        │                            │\n │    │              │街50號前棄置後離開。  │      │        │                            │\n │    │              │                      │      │        │                            │\n ├──┼───────┼───────────┼───┼────┼──────────────┤\n │ 6  │於97年5 月5 日│丙○○駕駛車號不詳車輛│郭錦傳│丙○○、│丙○○共同犯攜帶兇器竊盜罪，│\n │    │上午8 時許，在│，搭載田玟慧前往，由田│      │田玟慧  │處有期徒刑捌月。            │\n │    │高雄縣橋頭鄉德│玟慧在車上把風，丙○○│      │        │田玟慧共同犯攜帶兇器竊盜罪，│\n │    │松村德松路32-4│下車，以客觀上足供兇器│      │        │處有期徒刑柒月。            │\n │    │號前          │使用之T 型扳手、螺絲起│      │        │                            │\n │    │              │子，行竊車號783-NQ 號 │      │        │                            │\n │    │              │營業用小客車（價值約4 │      │        │                            │\n │    │              │萬元），得手後，由田玟│      │        │                            │\n │    │              │慧駕駛原有車輛，丙○○│      │        │                            │\n │    │              │駕駛竊得之贓車，共同前│      │        │                            │\n │    │              │往高雄縣燕巢鄉○○路50│      │        │                            │\n │    │              │號前，欲拆除該車觸媒轉│      │        │                            │\n │    │              │換器，發現該車並無裝設│      │        │                            │\n │    │              │，遂拆下車上電瓶後，將│      │        │                            │\n │    │              │該車棄置，搭乘原車逃逸│      │        │                            │\n │    │              │。                    │      │        │                            │\n ├──┼───────┼───────────┼───┼────┼──────────────┤\n │ 7  │於97年5 月12日│丙○○駕駛車號不詳車輛│塗永龍│丙○○、│丙○○共同犯攜帶兇器竊盜罪，│\n │    │晚間9 時許，在│，搭載田玟慧前往，由田│      │田玟慧  │處有期徒刑捌月。            │\n │    │高雄縣大社鄉文│玟慧在車上把風，丙○○│      │        │田玟慧共同犯攜帶兇器竊盜罪，│\n │    │明路44 巷6號前│下車，以客觀上足供兇器│      │        │處有期徒刑柒月。            │\n │    │              │使用之T 型扳手、螺絲起│      │        │                            │\n │    │              │子，行竊車號VC-9391 號│      │        │                            │\n │    │              │自用小貨車（價值約5 萬│      │        │                            │\n │    │              │元），得手後，由田玟慧│      │        │                            │\n │    │              │駕駛原有車輛，丙○○駕│      │        │                            │\n │    │              │駛竊得之贓車，共同前往│      │        │                            │\n │    │              │高雄縣燕巢鄉○○路高鐵│      │        │                            │\n │    │              │橋下，拆除該車觸媒轉換│      │        │                            │\n │    │              │器後，棄置該車，搭乘原│      │        │                            │\n │    │              │車逃逸。              │      │        │                            │\n ├──┼───────┼───────────┼───┼────┼──────────────┤\n │ 8  │於97年5 月13日│丙○○駕駛車號不詳車輛│尤嘉宏│丙○○、│丙○○共同犯結夥三人以上攜帶│\n │    │凌晨4 時許，在│，搭載田玟慧、甲○○前│      │田玟慧、│兇器竊盜罪，處有期徒刑捌月。│\n │    │高雄縣大社鄉中│往，由田玟慧、甲○○在│      │甲○○  │田玟慧犯共同結夥三人以上攜帶│\n │    │山路63號前    │車上把風，丙○○下車，│      │        │兇器竊盜罪，處有期徒刑柒月。│\n │    │              │以客觀上足供兇器使用之│      │        │甲○○共同犯結夥三人以上攜帶│\n │    │              │T 型扳手、螺絲起子，行│      │        │兇器竊盜罪，累犯，處有期徒刑│\n │    │              │竊車號F5-9373 號自用小│      │        │捌月。                      │\n │    │              │貨車（價值約7 萬元），│      │        │                            │\n │    │              │得手後，由甲○○駕駛原│      │        │                            │\n │    │              │有車輛，丙○○駕駛竊得│      │        │                            │\n │    │              │之贓車，共同前往高雄縣│      │        │                            │\n │    │              │燕巢鄉○○路高鐵橋下，│      │        │                            │\n │    │              │拆除該車觸媒轉換器、電│      │        │                            │\n │    │              │瓶後，棄置該車，搭乘原│      │        │                            │\n │    │              │車逃逸。              │      │        │                            │\n ├──┼───────┼───────────┼───┼────┼──────────────┤\n │ 9  │於97年5 月14日│丙○○駕駛懸掛HS-6680 │橋隆商│丙○○、│丙○○共同犯結夥三人以上攜帶│\n │    │晚間7 時許，在│號車牌（田玟慧所有，已│城    │田玟慧、│兇器竊盜罪，處有期徒刑捌月。│\n │    │高雄縣橋頭鄉成│報廢）之贓車，搭載田玟│      │甲○○、│田玟慧共同犯結夥三人以上攜帶│\n │    │功南路148 巷6 │慧、甲○○、郭慧琳前往│      │郭慧琳  │兇器竊盜罪，處有期徒刑柒月。│\n │    │弄巷道內      │，由田玟慧、郭慧琳在車│      │        │甲○○共同犯結夥三人以上攜帶│\n │    │              │上把風，丙○○、甲○○│      │        │兇器竊盜罪，累犯，處有期徒刑│\n │    │              │下車，以客觀上足供兇器│      │        │捌月。郭慧琳共同犯結夥三人以│\n │    │              │使用之鐵鏟，行竊水溝蓋│      │        │上攜帶兇器竊盜罪，累犯，處有│\n │    │              │6個 （價值約7,200 元）│      │        │期徒刑捌月。                │\n │    │              │得逞。                │      │        │                            │\n ├──┼───────┼───────────┼───┼────┼──────────────┤\n │ 10 │於97年5 月15日│甲○○駕駛懸掛HS-6680 │橋隆商│田玟慧、│田玟慧共同犯結夥三人以上攜帶│\n │    │下午2 時許，在│號車牌（田玟慧所有，已│城    │甲○○、│兇器竊盜罪，處有期徒刑柒月。│\n │    │高雄縣橋頭鄉成│報廢）之贓車，搭載田玟│      │郭慧琳  │甲○○共同犯結夥三人以上攜帶│\n │    │功南路148 巷6 │慧、郭慧琳前往，由田玟│      │        │兇器竊盜罪，累犯，處有期徒刑│\n │    │弄巷道內      │慧、郭慧琳於車上把風，│      │        │捌月。郭慧琳共同犯結夥三人以│\n │    │              │甲○○下車，以客觀上足│      │        │上攜帶兇器竊盜罪，累犯，處有│\n │    │              │供兇器使用之鐵鏟，行竊│      │        │期徒刑捌月。                │\n │    │              │水溝蓋4 個（價值約4,80│      │        │                            │\n │    │              │0元） 得逞。          │      │        │                            │\n └──┴───────┴───────────┴───┴────┴──────────────┘\n附表二（無罪部分）：\n ┌──┬───────┬───────────┬───┬────┐\n │編號│犯罪時間、地點│竊盜方式及竊得財物    │被害人│被告    │\n ├──┼───────┼───────────┼───┼────┤\n │ 1  │於97年4 月中旬│丙○○駕駛車號不詳車輛│橋頭鄉│丙○○、│\n │    │某日凌晨2 時許│，搭載田玟慧、甲○○、│公所  │田玟慧、│\n │    │，在高雄縣橋頭│郭慧琳前往，由田玟慧、│      │甲○○、│\n │    │鄉○○路旁    │郭慧琳在車上把風，楊宗│      │郭慧琳  │\n │    │              │樺、甲○○下車，以客觀│      │        │\n │    │              │上足供兇器使用之鐵鏟，│      │        │\n │    │              │行竊水溝蓋4 個（價值約│      │        │\n │    │              │新臺幣1 萬元）得逞。  │      │        │\n ├──┼───────┼───────────┼───┼────┤\n │ 2  │於97年4 月22日│丙○○駕駛車號不詳車輛│溫仁德│丙○○、│\n │    │凌晨2 時許，在│，搭載田玟慧前往，由田│      │田玟慧  │\n │    │高雄縣橋頭鄉德│玟慧在車上把風，丙○○│      │        │\n │    │松村鐵道北路82│下車，以客觀上足供兇器│      │        │\n │    │號旁空地      │使用之T 型扳手、螺絲扳│      │        │\n │    │              │手，行竊車號ZR-4986 號│      │        │\n │    │              │自小貨車及4839-XK 號自│      │        │\n │    │              │小客車上之觸媒轉換器2 │      │        │\n │    │              │組（價值約2 萬2,000 元│      │        │\n │    │              │）得逞。              │      │        │\n ├──┼───────┼───────────┼───┼────┤\n │ 3  │於97年5 月5 日│丙○○駕駛車號不詳車輛│郭錦傳│甲○○、│\n │    │上午8 時許，在│，搭載田玟慧、甲○○、│      │郭慧琳（│\n │    │高雄縣橋頭鄉德│郭慧琳前往，由田玟慧、│      │公訴意旨│\n │    │松村德松路32-4│甲○○、郭慧琳在車上把│      │謂：與楊│\n │    │號前          │風，丙○○下車，以客觀│      │宗樺、田│\n │    │              │上足供兇器使用之T 型扳│      │玟慧共犯│\n │    │              │手、螺絲扳手，行竊車號│      │）      │\n │    │              │783-NQ號營業小客車（價│      │        │\n │    │              │值約4 萬元），得手後，│      │        │\n │    │              │由甲○○駕駛原有車輛，│      │        │\n │    │              │丙○○駕駛竊得之贓車，│      │        │\n │    │              │共同前往高雄縣燕巢鄉瓊│      │        │\n │    │              │招路50號前，欲拆除該車│      │        │\n │    │              │觸媒轉換器，發現該車並│      │        │\n │    │              │無裝設，遂拆下車上電瓶│      │        │\n │    │              │後，將該車棄置，搭乘原│      │        │\n │    │              │車逃逸。              │      │        │\n ├──┼───────┼───────────┼───┼────┤\n │ 4  │於97年5 月12日│丙○○駕駛車號不詳車輛│塗永龍│甲○○、│\n │    │晚間9 時許，在│，搭載田玟慧、甲○○、│      │郭慧琳（│\n │    │高雄縣大社鄉文│郭慧琳前往，由田玟慧、│      │公訴意旨│\n │    │明路44 巷6號前│甲○○、郭慧琳在車上把│      │謂：與楊│\n │    │              │風，丙○○下車，以客觀│      │宗樺、田│\n │    │              │上足供兇器使用之T 型扳│      │玟慧共犯│\n │    │              │手、螺絲扳手，行竊車號│      │）      │\n │    │              │VC-9391 號自小貨車（價│      │        │\n │    │              │值約5 萬元），得手後，│      │        │\n │    │              │由甲○○駕駛原有車輛，│      │        │\n │    │              │丙○○駕駛竊得之贓車，│      │        │\n │    │              │共同前往高雄縣燕巢鄉大│      │        │\n │    │              │學路高鐵橋下，拆除該車│      │        │\n │    │              │觸媒轉換器後，棄置該車│      │        │\n │    │              │，搭乘原車逃逸。      │      │        │\n ├──┼───────┼───────────┼───┼────┤\n │ 5  │於97年5 月13日│丙○○駕駛車號不詳車輛│尤嘉宏│郭慧琳（│\n │    │凌晨4 時許，在│，搭載田玟慧、甲○○、│      │公訴意旨│\n │    │高雄縣大社鄉中│郭慧琳前往，由田玟慧、│      │謂：與楊│\n │    │山路63號前    │甲○○、郭慧琳在車上把│      │宗樺、田│\n │    │              │風，丙○○下車，以客觀│      │玟慧、胡│\n │    │              │上足供兇器使用之T 型扳│      │健民共犯│\n │    │              │手、螺絲扳手，行竊車號│      │）      │\n │    │              │F5-9373 號自小貨車（價│      │        │\n │    │              │值約7 萬元），得手後，│      │        │\n │    │              │由甲○○駕駛原有車輛，│      │        │\n │    │              │丙○○駕駛竊得之贓車，│      │        │\n │    │              │共同前往高雄縣燕巢鄉大│      │        │\n │    │              │學路高鐵橋下，拆除該車│      │        │\n │    │              │觸媒轉換器、電瓶後，棄│      │        │\n │    │              │置該車，搭乘原車逃逸。│      │        │\n ├──┼───────┼───────────┼───┼────┤\n │ 6  │於97年5 月15日│丙○○駕駛懸掛HS-6680 │橋隆商│丙○○（│\n │    │下午2 時許，在│號車牌（田玟慧所有，已│城    │公訴意旨│\n │    │高雄縣橋頭鄉成│報廢）之贓車，搭載田玟│      │謂：與田│\n │    │功南路148 巷6 │慧、甲○○、郭慧琳前往│      │玟慧、胡│\n │    │弄巷道內      │，由田玟慧、郭慧琳在車│      │健民、郭│\n │    │              │上把風，丙○○、甲○○│      │慧琳共犯│\n │    │              │下車，以客觀上足供兇器│      │）      │\n │    │              │使用之鐵鏟，行竊水溝蓋│      │        │\n │    │              │4個 （價值約4,800 元）│      │        │\n │    │              │得逞。                │      │        │\n └──┴───────┴───────────┴───┴────┘",
  "structure": {
    "main": "上訴駁回。",
    "fact": "一、丙○○於民國90年1 月間，因傷害致死案件，經臺灣高雄地\n    方法院以89年度訴字第2596號判決判處有期徒刑8 年6 月確\n    定，於96年8 月24日縮刑假釋出監，至98年2 月26日始假釋\n    期滿（不構成累犯）。甲○○於90年9 月間，因違反職役職\n    責案件，經國防部高等軍事法院高雄分院以90年度高審字第\n    102 號判決判處有期徒刑2 年6 月確定；又於94年11月間，\n    因傷害案件，經本院以94年度上訴字第24號判決判處有期徒\n    刑8 月確定；上開2 罪經定應執行刑為有期徒刑3 年，於96\n    年6 月28日縮刑期滿執行完畢（構成累犯）。郭慧琳於94年\n    12月間，因違反毒品危害防制條例案件，經臺灣高雄地方法\n    院以94年度訴字第4072號判決判處有期徒刑8 月確定，於96\n    年2 月19日縮刑期滿執行完畢（構成累犯）。\n二、詎仍不知悔改，意圖為自己不法之所有，由丙○○與田玟慧\n    2 人，或夥同甲○○、郭慧琳、李建信其中之1 人或2 人，\n    共同基於竊盜之犯意聯絡，持客觀上足供兇器使用之T 型扳\n    手、螺絲起子或鐵鏟等物，於附表一所示之時、地，以附表\n    一所示之方式，共同竊取如附表一所示他人所有或管領之水\n    溝蓋、汽車或觸媒轉換器等財物，嗣經被害人報案後，為警\n    循線查獲。\n三、丙○○、甲○○又意圖為自己不法所有，共同基於竊盜之犯\n    意聯絡，於97年5 月15日上午6 時許，在高雄縣橋頭鄉○○\n    村○○路壽生巷25號前，由丙○○持客觀上足供兇器使用之\n    Ｔ型扳手1 支，竊取乙○○所有之車號ZJ-6313 號自用小貨\n    車（車上並有乙○○所有之三用電表、銅管切管器、噴燈、\n    電動起子及工具1 批等物品），甲○○則在旁把風。得手後\n    供丙○○使用。嗣同年月21日凌晨2 時35分許，在高雄市○\n    ○區○○街與監理南街口丙○○所駕駛H8-6680 號之自用小\n    客車上查獲上開失竊物品，始悉上情。\n四、案經林貴興、溫仁德、乙○○分別訴由高雄縣政府警察局岡\n    山分局、高雄市政府警察局楠梓分局報請臺灣高雄地方法院\n    檢察署檢察官偵查起訴。",
    "reason": "壹、證據能力部分：\n一、證人田玟慧於警詢之供述有證據能力：\n  (一)按被告以外之人於審判外之言詞或書面陳述，除法律有規定\n    者外，不得作為證據；被告以外之人於檢察事務官、司法警\n    察官或司法警察調查中所為之陳述，與審判中不符時，其先\n    前之陳述具有較可信之特別情況，且為證明犯罪事實存否所\n    必要者，得為證據，刑事訴訟法第159 條第1 項、第159 條\n    之2 分別定有明文。是依上開條文規定，被告以外之人於檢\n    察事務官、司法警察（官）調查時所為之陳述，屬傳聞證據\n    ，依同法第159 條規定，本無證據能力，必須「具有較可信\n    之特別狀況」及「必要性」2 要件，始例外得適用上開第15\n    9 條之2 規定，認有證據能力。而所謂「具有較可信之特別\n    情況」係屬於證據能力之要件，法院應就偵查或調查筆錄製\n    作之原因、過程及其功能等加以觀察其信用性予以判斷；又\n    此之「必要性」要件，必須該陳述之重要待證事實部分，與\n    審判中之陳述有所不符，包括先前之陳述詳盡、於後簡略，\n    甚至改稱忘記、不知道等，雖非完全相異，但實質內容已有\n    不符者在內（最高法院96年度台上字4304號、96年度台上字\n    第4365號、96年度台上字第4414號判決意旨參考）。\n  (二)證人即共同被告田玟慧於警詢中之供述，對於被告丙○○而\n    言，本屬被告以外之人於審判外之言詞陳述。而上開證人係\n    被告丙○○是否犯有加重竊盜犯行之重要證人，該證人於警\n    詢時對於被告丙○○涉犯竊盜之情節陳述甚詳，惟於原審審\n    理時翻異前詞，改稱不知道云云，有警詢筆錄2 份及審判筆\n    錄1 份存卷可證（警卷第38至43頁、原審院二卷第76頁），\n    足見該證人於警詢中及原審審判中證述之內容不符。又該證\n    人於原審審理時未曾證稱於警詢時，有遭員警以強暴、脅迫\n    、利誘、詐欺、疲勞訊問、違法羈押或其他不正之方法而違\n    法調查之情事，且其於警詢時所為有關被告丙○○加重竊盜\n    事實之證述，相較其於原審審理時所為，距案發當時較近，\n    且非在被告丙○○面前所為，依此外部情況，顯較無受不當\n    干擾及事後串謀之可能性，堪認該證人於警詢中之陳述具有\n    特別可信之情況，且為證明被告丙○○之犯罪存否所必要，\n    依同法第159 條之2 規定，其於警詢中之陳述應具有證據能\n    力。\n二、其他傳聞證據部分：\n  (一)按被告以外之人於審判外之陳述，雖不符前4 條之規定，而\n    經當事人於審判程序中同意作為證據，法院審酌該言詞陳述\n    或書面陳述作成時之情況，認為適當者，亦得為證據。當事\n    人、代理人或辯護人於法院調查證據時，知有第159 條第1\n    項不得為證據之情形，而未於言詞辯論終結前聲明異議者，\n    視為有前項之同意，刑事訴訟法第159 條之5 定有明文。\n  (二)本件所引用之其他傳聞證據，檢察官、被告及辯護人於本院\n    準備程序中及審理時均知並無證據能力，惟均表示同意或無\n    意見等語，本院審酌該證據作成時之情況，認以之作為證據\n    亦屬適當，依上開規定均有證據能力。\n貳、實體部分：\n一、有罪部分：\n  (一)訊據上訴人即被告丙○○對於附表一編號1 至8 、10及事實\n    三；被告田玟慧對於附表一編號1 至10；上訴人即被告甲○\n    ○對於附表一編號8 至10；被告郭慧琳對於附表一編號9 、\n    10；被告李建信對於附表一編號3 所示之竊盜犯行，分別於\n    本院審理時坦承不諱，核與證人證人黃慧木、證人即被害人\n    何富鵬、陳美雲、馬錫恩、郭錦傳、塗永龍、尤嘉宏、蔡龍\n    統、乙○○，分別於警詢或偵查時之證述之情節相符。並有\n    搜索扣押筆錄、扣押物品目錄表、車輛尋獲電腦輸入單、贓\n    物認領保管單、行照影本及現場照片等在卷可佐，上開被告\n    之自白核與事實相符，其等確涉有前揭竊盜之犯行，堪以認\n    定。\n  (二)被告丙○○矢口否認涉有附表一編號9 所示之竊盜犯行，辯\n    稱：當天伊未去云云。惟查：\n  1.被告丙○○確犯有上開竊盜事實，業據證人即共同被告田玟\n    慧於警詢時證稱：被告丙○○於97年5 月14日19時許，駕駛\n    不詳牌號贓車、懸掛伊所有之H8-6680 號自用小客車車牌，\n    搭載「哲仔（指被告甲○○）」、「妹仔（指被告郭慧琳）\n    」與伊至高雄縣橋頭鄉○○○路148 巷6 弄巷道內，由「哲\n    仔」及被告丙○○下車竊取水溝蓋，伊與「妹仔」在車內把\n    風，並當場竊得6 個水溝蓋，然後將竊得之水溝蓋放置於該\n    贓車之後車廂內，再由被告丙○○與「哲仔」、「妹仔」與\n    伊共同駕乘該贓車逃逸現場，然後伊與「妹仔」中途下車至\n    網咖玩打電腦，「哲仔」及被告丙○○則駕駛該輛贓車去變\n    賣贓物等語（警卷第42頁）；證人即共同被告甲○○於偵查\n    時證稱：當時伊負責下車偷水溝蓋，被告丙○○、郭慧琳下\n    車巡看現場後，與被告田玟慧一起在車上把風；被告丙○○\n    知道伊要偷水溝蓋等語（偵卷第73頁），所證核與被害人即\n    橋隆商城之主委蔡龍統於警詢時證述之情節相符（警卷第82\n    頁），而被告丙○○為被告田玟慧之同居男友，被告郭慧琳\n    則為被告甲○○之未婚妻，其等經常共同出入活動，此為被\n    告丙○○、郭慧琳所不否認（偵卷第35至38、74至76頁），\n    證人即共同被告田玟慧、甲○○之證言應堪信為真實，此外\n    ，復有被告田玟慧指認現場照片2 張、車籍查詢基本資料詳\n    細畫面等附卷可考（警卷第98、106 、119 、125 頁）。\n  2.被告丙○○所辯，顯與事實相違，不足採憑。被告丙○○確\n    有與郭慧琳、甲○○、田玟慧共同為附表一編號9 之竊取水\n    溝蓋之犯行無訛。\n  (三)被告甲○○雖矢口否認有事實三之竊盜犯行，辯稱：當時伊\n    去廟邊上廁所，伊不知道被告丙○○去偷車，也未幫他把風\n    ，等到被告丙○○竊取上開車輛回來時，伊才知道他去偷車\n    云云。惟查：\n  1.被告甲○○確有夥同被告丙○○於事實三之時地，以T 型扳\n    手竊取車號ZJ-6313 號自用小貨車及該車上之三用電表等工\n    具之事實，業據被告甲○○於警詢時供稱：上開車輛是被告\n    丙○○提議行竊及竊取的，伊則在場把風，原本該批工具就\n    放在車上，是伊等一起行竊的等語（併案警卷第1 頁），於\n    偵查時供稱：上開車輛是由被告丙○○用T 型扳手偷來的，\n    伊在旁邊的廟內把風；當時伊去廟內上廁所，出來就看被告\n    丙○○偷了1 台車等語（併案偵卷第14頁），核與證人即共\n    同被告丙○○於警詢時供稱：車號ZJ-6313 號自用小貨車不\n    是伊偷竊的，是伊朋友「阿哲（即被告甲○○）」交給伊的\n    ，於97年5 月18、19日晚上，在高雄縣大社鄉一處公園將三\n    用電表、銅管切管器、噴燈、電動起子、工具1 批等物搬到\n    伊車上等語（見併案警卷第2 頁及背面），於偵查及原審準\n    備程序中供稱：係持T 型扳手行竊的等語（併案偵卷第16頁\n    ；原審院三卷第47頁），及證人即被害人乙○○於警詢所證\n    失竊之情節相符（併案警卷第7 至8 頁）。\n  2.此外，復有搜索扣押筆錄、扣押物品目錄表、贓物認領保管\n    單、行照影本、上開車輛之失竊及尋獲紀錄各1 份及相片2\n    張等件在卷可稽（併案警卷第11至15、18至19頁）。\n  3.被告甲○○嗣自原審審理時起否認此部分犯行，被告丙○○\n    亦證稱：該車是伊自己偷的云云，均核係事後卸責及迴護之\n    詞，均難採信，被告甲○○確涉有事實三之攜帶兇器竊盜犯\n    行無訛。\n  (四)被告丙○○對於附表一編號1 、2 ；被告甲○○對於附表一\n    編號8 至10部分，復均於本院審理時辯稱：未攜帶兇器行竊\n    云云。惟被告丙○○、甲○○等人竊取車輛之作案工具係T\n    型扳手，觸媒轉換器為螺絲起子，水溝蓋為鐵鏟等情，業據\n    證人即各該次竊盜之共同被告田玟慧於警詢時證述屬實，且\n    被告丙○○於本院審理前之各次筆錄，均對前開攜帶兇器竊\n    盜部分均坦承不諱，並未為此爭執；被告甲○○於本院審理\n    前之各次筆錄，亦均未為此抗辯，而各該次竊盜之共同被告\n    田玟慧、丙○○對於上開竊盜均係攜帶兇器犯之各節，則均\n    坦認不移。再衡諸經驗法則，水溝蓋係固定於水溝上方之凹\n    槽，多與地面密切接合，若未利用鐵鏟等工具，實難掀開及\n    竊取水溝蓋；而汽車之門鎖、電門大鎖及觸媒轉換器係分別\n    固定於車門、方向盤下方及排氣管上，若未利用T 型扳手、\n    螺絲扳手等工具，實不可能破壞門鎖、啟動引擎及拆卸觸媒\n    轉換器等情。堪認被告丙○○、甲○○於前揭竊盜犯行，均\n    係攜帶兇器犯之無疑，其等嗣於本院審理時始為上開抗辯，\n    核係飾卸之詞，均難憑採。\n三、\n  (一)按刑法第321 條第1 項第3 款之攜帶兇器竊盜罪，係以行為\n    人攜帶兇器竊盜為其加重條件，此所謂兇器，其種類並無限\n    制，凡客觀上足對人之生命、身體、安全構成威脅，具有危\n    險性之兇器均屬之，且祇須行竊時攜帶此種具有危險性之兇\n    器為已足，並不以攜帶之初有行兇之意圖為必要（最高法院\n    79年度台上字第5253號判例意旨參考）。被告丙○○等人於\n    竊取水溝蓋、汽車及觸媒轉換器時，所使用之T 型扳手、螺\n    絲起子、鐵鏟等工具雖未扣案，惟上開工具既能用以破壞門\n    鎖、發動引擎、拆卸觸媒轉換器及水溝蓋，足認上開工具材\n    質堅硬，客觀上均足以傷害人之生命、身體，性質上均屬具\n    有危險性之兇器無訛。\n  (二)核被告丙○○、田玟慧如附表一編號1 、2 、4 、5 、6 、\n    7 ；被告丙○○、甲○○如事實三所為，均係犯法第321 條\n    第1 項第3 款之攜帶兇器竊盜罪。被告丙○○、田玟慧、甲\n    ○○如附表一編號8 ；被告丙○○、田玟慧、甲○○、郭慧\n    琳如附表一編號9 ，及被告田玟慧、甲○○、郭慧琳如附表\n    一編號10所為，均係犯刑法第321 條第1 項第4 款、第3 款\n    之結夥三人以上攜帶兇器竊盜罪；被告丙○○、田玟慧、李\n    建信如附表一編號3 所為，係犯刑法第321 條第2 項、第1\n    項第4 款、第3 款之結夥三人以上攜帶兇器竊盜未遂罪。被\n    告丙○○與田玟慧就如附表一編號1 、2 、4 、5 、6 、7\n    ；被告丙○○、田玟慧、李建信就如附表一編號3 ；被告丙\n    ○○、田玟慧、甲○○就如附表一編號8 ；被告丙○○、田\n    玟慧、甲○○、郭慧琳就如附表一編號9 ；被告田玟慧、甲\n    ○○、郭慧琳就如附表一編號10，及被告丙○○、甲○○就\n    如事實三所示之犯行，彼此間互有犯意聯絡及行為分擔，均\n    為共同正犯。被告丙○○、田玟慧、李建信3 人就附表一編\n    號3 部分，已著手於竊盜行為之實行而不遂，為未遂犯，應\n    依刑法第25條第2 項規定減輕其刑。被告甲○○、郭慧琳2\n    人分別有如事實一所載科刑及執行完畢情形，有臺灣高等法\n    院被告前案紀錄表2 份在卷足憑，其等於受有期徒刑執行完\n    畢後，5 年內故意再犯本件法定刑為有期徒刑以上之前揭各\n    罪，均應論以累犯，並加重其刑。\n四、\n  (一)原審認被告罪證明確，因而適用刑法刑法第321 條第2 項（\n    原判決漏引）、第1 項第3 款、第4 款、第28條、第47條第\n    1 項、第41條第1 項、第51條第5 款之規定（原判決贅引刑\n    法第320 條第1 項、刑法施行法第1 條之1 ），並審酌被告\n    丙○○等5 人正值青壯，不思以正當途徑賺取財物，率爾竊\n    取他人財物，所為實有不該；另衡以被告丙○○為竊盜集團\n    之首腦，率領集團成員四處行竊，涉犯加重竊盜之情節最重\n    ，餘被告田玟慧等4 人情節較輕，復念其等於犯後已坦承大\n    部分犯行，且所竊得財物亦部分歸還被害人，有贓物認領保\n    管單5 份在卷可參，所生損害業已減輕等其他一切情狀，分\n    別量處附表一主文欄所載之刑，並就被告丙○○、田玟慧、\n    甲○○、郭慧琳部分，定其應執行之刑；再就被告丙○○、\n    田玟慧、李建信如附表一編號3 之竊盜部分，均諭知以1000\n    元折算1 日之易科罰金折算標準。被告丙○○等5 人持供犯\n    罪所用之T 型扳手、螺絲起子、鐵鏟等工具並未扣案，亦均\n    非違禁物，為免將來執行上之困難，不予宣告沒收。\n  (二)原判決認事用法，核無不合，量刑亦屬允當。檢察官認如表\n    一編號3 部分，量刑失衡，另被告丙○○有犯罪之習慣，原\n    審未為諭知強制工作，尚有未合，指摘原判決不當，提起上\n    訴，並無理由，應由予駁回。被告丙○○否認如附表一編號\n    9 部分，並認編號1 、2 部分並非攜帶兇器為之；被告甲○\n    ○否認事實三部分，並認如附表一編號8 至10部分，均未攜\n    帶兇器為之，亦分別指摘原判決不當，提起上訴，均無理由\n    ，亦應予以駁回。\n五、公訴人於認被告丙○○有竊盜前科，於服刑完畢後仍於短期\n    內一再犯竊盜案件，顯有犯罪之習慣，應於刑之執行前令入\n    勞動場所強制工作，以改遭其惡習云云。\n  (一)惟按保安處分係針對受處分人將來之危險性所為之處置，以\n    達教化、治療之目的，為刑罰之補充制度。我國現行刑法採\n    刑罰與保安處分雙軌制，係在維持行為責任之刑罰原則下，\n    為協助行為人再社會化之功能，以及改善行為人潛在之危險\n    性格，期能達成根治犯罪原因、預防犯罪之特別目的。是保\n    安處分中之強制工作，旨在對嚴重職業性犯罪及欠缺正確工\n    作觀念或無正常工作因而犯罪者，強制其從事勞動，學習一\n    技之長及正確之謀生觀念，使其日後重返社會，能適應社會\n    生活。保安處分之措施亦含社會隔離、拘束身體自由之性質\n    ，其限制人民之權利，實與刑罰同，本諸法治國家保障人權\n    之原理及刑法之保護作用，其法律規定之內容，應受比例原\n    則之規範，使保安處分之宣告，與行為人所為行為之嚴重性\n    、行為人所表現之危險性，及對於行為人未來行為之期待性\n    相當。刑法第90條及竊盜犯贓物犯保安處分條例第3 條第1\n    項關於強制工作之規定，均係本於上開意旨制定，而由法院\n    視個案中行為人之危險性格，以決定應否交付強制工作，以\n    達保安處分之特別預防之目的（司法院大法官會議釋字第\n    471 號解釋參考）。\n  (二)查被告丙○○自97年4 月中旬至同年5 月15日間，雖確有上\n    開10次竊盜犯行，已如上述。然被告在此之前，除於88年間\n    ，曾因竊盜犯行，經判處有期徒刑6 月確定外，即無其他竊\n    盜前科紀錄，有卷附臺灣高等法院被告前案紀錄表1 份附卷\n    可查，故是否堪認被告丙○○是否有犯罪習慣，已非無疑。\n    此外，復查無其他積極證據足資證明被告丙○○係以本件竊\n    盜犯行為其經濟生活之主要支柱，足徵被告前揭多次竊盜犯\n    行均應係因一時貪圖小利，始起意行竊，尚難認其係職業性\n    犯罪，亦難逕認其係因欠缺正確工作觀念或無正常工作而有\n    竊盜犯罪之習性，即與刑法第90條所稱：「有犯罪之習慣或\n    因遊蕩或懶惰成習而犯罪者」或竊盜犯贓物犯保安處分條例\n    第3 條前段：「18歲以上之竊盜犯、贓物犯，有犯罪之習慣\n    者」之規定有別，參諸前揭大法官會議解釋意旨，堪認被告\n    丙○○前揭所為，尚未具有常習性，對其未來之行為仍有期\n    待性，並參酌就強制工作並非矯正其竊盜犯行唯一方法，尚\n    需合乎比例原則以求法益間之均衡等情綜合以觀，認上開對\n    其宣告徒刑即足以收矯治之效，是尚無對被告丙○○宣告強\n    制工作之必要。\n貳、無罪部分：\n一、公訴意旨另以：被告丙○○、田玟慧、甲○○、郭慧琳意圖\n    為自己不法之所有，由丙○○與田玟慧2 人，或夥同甲○○\n    、郭慧琳2 人，共同基於竊盜之犯意聯絡，持客觀上足供兇\n    器使用之T 型扳手、螺絲起子或鐵鏟等物，於附表二所示之\n    時地，以附表二所示之方式，共同竊取如附表二所示他人所\n    有或管領之水溝蓋、汽車或觸媒轉換器等財物，嗣經被害人\n    報案後，為警循線查獲，因認被告丙○○等4 人另犯有刑法\n    第第321 條第4 款、第3 款之加重竊盜犯行云云。\n二、按犯罪事實應依證據認定之，無證據不得認定犯罪事實；無\n    證據能力、未經合法調查之證據，不得作為判斷之依據；不\n    能證明被告犯罪或其行為不罰者，應諭知無罪之判決，刑事\n    訴訟法第154 條第2 項、第155 條第2 項、第301 條第1 項\n    分別定有明文。次按認定不利於被告之事實，須依積極證據\n    ，苟積極證據不足為不利於被告事實之認定時，即應為有利\n    被告之認定，更不必有何有利之證據，復有最高法院30年上\n    字第816 號判例可資參考。又事實之認定，應憑證據，如未\n    能發現相當證據，或證據不足以證明，自不能以推測或擬制\n    之方法，為裁判基礎；認定犯罪事實，所憑之證據，雖不以\n    直接證據為限，間接證據亦包括在內，然無論直接或間接證\n    據，其為訴訟上之證明，須於通常一般之人均不致於有所懷\n    疑，而得確信其為真實之程度者，始得據之為有罪之認定，\n    倘其證明尚未達到此一程度，而有合理性懷疑之存在時，即\n    無從為有罪之認定（最高法院40年度台上字第86號、76年度\n    台上字第4986號判例意旨參考）。況刑事訴訟法第161 條第\n    1 項亦規定，檢察官就被告犯罪事實，應負舉證責任，並指\n    出證明之方法，是檢察官對於起訴之犯罪事實，應負提出證\n    據及說服之實質舉證責任，倘其所提出之證據，不足為被告\n    有罪之積極證明，或其指出證明之方法，無從說服法院以形\n    成被告有罪之心證，基於無罪推定之原則，自應為被告無罪\n    判決之諭知（最高法院92年度台上字第128 號判例意旨參考\n    ）。\n三、附表二編號1、2 部分：\n  (一)公訴人認被告丙○○、田玟慧、甲○○、郭慧琳涉犯如附表\n    二編號1 所示之犯行，及被告丙○○、田玟慧涉犯如附表二\n    編號2 所示之犯行，均係以被告田玟慧於警詢時之供述及指\n    認犯罪現場照片4 張為其論據。訊據被告丙○○等4 人均堅\n    詞否認有為如附表二編號1 所示之犯行；被告丙○○、田玟\n    慧亦堅詞否認有為如附表二編號2 所示之犯行。被告丙○○\n    、甲○○、郭慧琳均辯稱：伊等並未於上開時、地竊盜等語\n    。被告田玟慧則辯稱：伊只有待在車上，不知道被告丙○○\n    、甲○○、郭慧琳下車做什麼等語。\n  (二)經查：\n  1.高雄縣橋頭鄉公所設置於該鄉○○路旁之水溝蓋4 個，於97\n    年4 月間確曾遭竊之事實，固據證人即橋頭鄉公所建設課技\n    士林貴興於警詢時證述明確（警詢第56、57頁）；同年4 月\n    22日，溫仁德所有之車號ZR-4986 號自用小貨車及4839-XK\n    號自用小客車上之觸媒轉換器2 組均失竊各情，亦據證人溫\n    仁德於警詢時證述綦詳（警詢第58至60頁），並有被告田玟\n    慧之指認犯罪現場照片4 張（警卷第99、101 頁）。惟上開\n    證據僅得證明曾經失竊之事實，尚難以此推認上開物品必為\n    被告丙○○等4 人所竊取。\n  2.被告田玟慧於警詢時固供稱：於97年4 月中旬2 時許，伊與\n    被告丙○○、「哲仔」、郭慧琳在高雄縣橋頭鄉○○路旁竊\n    取水溝蓋，當時由被告丙○○與甲○○下車竊取路旁之水溝\n    蓋，伊與被告郭慧琳在車上，然後被告丙○○及「哲仔」竊\n    取得逞後，叫伊等將後車廂打開，再將該水溝蓋放置於該車\n    輛之後車廂內，先將「哲仔」、被告郭慧琳送回家，伊與被\n    告丙○○再開車至旅館睡覺；於97年4 月22日2 時許，被告\n    丙○○駕駛自用小客車，載伊跟「阿信」在高雄縣橋頭鄉○\n    ○村○道○路82號旁空地，由被告丙○○與「阿信」下車竊\n    取停放在該處的自用小貨車車號ZR-8496 與自用小客車車號\n    4839-XK 車子下方的觸媒轉換器，得手後由被告丙○○回車\n    上開車逃逸現場云云（警卷第41、48頁）。惟被告田玟慧已\n    於原審審理時翻異前詞，改稱：伊等只有路過上開地點，並\n    未下車等語（原審院二卷第68頁背面）。足見被告田玟慧於\n    前後之供述顯有瑕疵可指，尚難據為不利被告之認定。\n四、附表二編號3、4部分：\n  (一)公訴人認被告甲○○、郭慧琳涉犯如附表二編號3 、4 所示\n    之犯行，係以被告田玟慧於警詢之供述及指認犯罪現場照片\n    2 張為其論據。訊據被告甲○○、郭慧琳均堅詞否認有上開\n    犯行。被告甲○○、郭慧琳均辯稱：伊等並未於上開時地竊\n    盜等語\n  (二)經查：\n  1.本件確有如附表二編號3 、4 之營業用小客車、自用小貨車\n    及媒轉換器等失竊等事實，固據證人即被害人郭錦傳、塗永\n    龍於警詢中證述屬實，並有被告田玟慧之指認犯罪現場照片\n    2 張（見警卷第102 、105 頁）在卷可考。惟此僅得證明失\n    竊之客觀事實而已，尚難以此為不利被告之認定。\n  2.被告田玟慧於警詢時固供稱：於97年5 月5 日8 時許，被告\n    丙○○駕駛自用小客車載「哲仔」「妹仔」與伊至橋頭鄉○\n    ○路32之4 號前，由被告丙○○下車竊取車號737-NQ營業用\n    小客車，再由「哲仔」駕駛被告丙○○原本駕駛的車輛載伊\n    跟「妹仔」離開，與被告丙○○所駕駛的贓車一起去高雄縣\n    燕巢鄉○○村○○路50號前棄置，並竊取該車觸媒轉換器後\n    ，由被告丙○○駕駛原本的車子離去；又於97年5 月12日21\n    時許，被告丙○○駕駛車號不詳之贓車，載「哲仔」、「妹\n    仔」與伊至大社鄉○○路44巷6 號前，由被告丙○○下車竊\n    取自用小貨車車號VC-9391 自用小貨車，竊取得逞後，由被\n    告丙○○駕駛該贓車，「哲仔」駕駛被告丙○○原本駕駛的\n    車輛載伊跟「妹仔」離開，與被告丙○○駕駛的贓車一起去\n    高雄縣燕巢鄉○○路高鐵橋下棄置，並竊取該車觸媒轉換器\n    管後，由被告丙○○駕駛原本的車子離去；伊跟「妹仔」只\n    是坐在車後座，都沒有下車行竊，只是負責把風而已云云（\n    警卷第41至43頁）。然被告田玟慧於原審審理時已翻異前詞\n    ，改稱：伊不知道被告丙○○等人下車做什麼等語（原審院\n    一卷第76頁）。足見被告田玟慧之供述顯有前後矛盾之情形\n    ，尚難據此援為不利被告甲○○、郭慧琳之認定。\n  3.共同被告田玟慧、丙○○於本院審理時均已坦認此2 部分事\n    實，係其等所為等語，參諸證人即共同被告丙○○於原審審\n    理時具結證稱：如附表二編號3 、4 之犯行，被告甲○○、\n    郭慧琳有沒有去，伊不記得了等語（原審院二卷第69頁背面\n    ）等參互以觀，堪認如附表二編號3 、4 之竊盜事實，被告\n    甲○○、郭慧琳並未參與無訛。\n五、附表二編號5 部分：\n  (一)公訴人認被告郭慧琳涉犯此部分竊盜犯行，無非係以被告田\n    玟慧於警詢之供述及指認犯罪現場照片2 張為其論據。訊據\n    被告郭慧琳堅詞否認有為此部分犯行。辯稱：伊並未於上開\n    時地竊盜等語。\n  (二)經查：\n  1.本件確有如附表二編號5 之自用小客車及觸媒轉換器失竊之\n    事實，固據證人即被害人蔡龍統於警詢時證述明確，並有被\n    告田玟慧之指認犯罪現場照片2 張在卷可佐（警卷第104 頁\n    ），惟此僅得證明有失竊之客觀事實而已，尚難為不利被告\n    郭慧琳之認定。\n  2.被告田玟慧於警詢時固供稱：於97年5 月13日4 時許，被告\n    丙○○駕駛車號不詳之贓車，載「哲仔」、「妹仔」與伊至\n    大社鄉○○路63號前，由被告丙○○下車竊取車號F5-9373\n    自用小貨車，由丙○○駕駛竊得之贓車，「哲仔」駕駛被告\n    丙○○原本駕駛的車輛載伊跟「妹仔」離開，然後讓伊中途\n    下車後，伊就不曉得他們的去向；伊跟「妹仔」只是坐在車\n    後座，都沒有下車行竊，員負責把風而已云云（警卷第42、\n    43頁）。惟其已於原審審理時翻異前詞，改稱：伊不知道被\n    告丙○○等人下車做什麼等語（原審院一卷第76頁）。足見\n    被告田玟慧於警詢及原審審理中之供述，顯有前後不一之瑕\n    疵，自難遽予採信。參諸被告丙○○、田玟慧、甲○○已坦\n    認此部分竊盜乙節，堪認被告郭慧琳應無參與此部分竊盜事\n    實無訛。\n六、附表二編號6 部分：\n  (一)公訴人認被告丙○○涉犯此部分竊盜犯行，係以監視器翻拍\n    照片1 張為其論據。訊據被告丙○○堅詞否認有為此部分犯\n    行。辯稱：伊固有與被告甲○○、田玟慧、郭慧琳前往上開\n    地點，但是到現場後因看到有人，所以伊就離開，加上被告\n    甲○○、郭慧琳於當天早上就已經先騎機車至該處竊取水溝\n    蓋，所以伊才沒有下手作案；伊沒有於上開時間至上開地點\n    竊取水溝蓋等語。\n  (二)經查：\n  1.被告田玟慧、甲○○、郭慧琳於97年5 月15日下午2 時許，\n    在高雄縣橋頭鄉○○○路148 巷6 弄巷道內，共同竊取橋隆\n    商城所有之水溝蓋4 個之事實，業據證人即被害人蔡龍統於\n    警詢時證述明確，並為前揭被告3 人所是認不諱。\n  2.觀諸警方調閱案發地點附近之監視器畫面，確有錄得被告丙\n    ○○與被告甲○○、郭慧琳先後出現在上開地點附近之影像\n    ，此有監視器翻拍照片3 張存卷可考（警卷第125 頁）。然\n    查上開監視器影像拍攝之時間為97年5 月14日下午，而本次\n    犯罪時間為同年5 月15日，則上開監視器畫面自不足以認定\n    被告丙○○有與被告田玟慧、甲○○、郭慧琳共同為此部分\n    之竊盜犯行。\n七、綜上所述，被告丙○○、田玟慧、甲○○、郭慧琳所為之上\n    開辯解，尚堪採信。而公訴人所舉之證據與指出之證明方法\n    ，尚有合理性之懷疑存在，未達使本院確信被告丙○○等人\n    犯有刑法第321 條第1 項第3 款、第4 款之加重竊盜罪之事\n    實。揆諸前開說明，應認被告丙○○等4 人關於上開犯罪尚\n    屬不能證明。此外，本院復查無其他積極證據可資認定被告\n    丙○○等4 人涉有前開罪名，自屬不能證明被告犯罪。\n八、原審以上開如附表二部分，被告丙○○等4 人之犯罪不能證\n    明，因而分別為其等無罪之諭知，並無不合。檢察官以上開\n    附表二部分，原審未諭知有罪為不當，提起上訴，並無理由\n    ，應予駁回。\n參、據上論斷，應依刑事訴訟法第368 條，判決如主文。\n本案經檢察官劉玲興到庭執行職務。\n中    華    民    國    99    年    1     月    5     日\n                  刑事第七庭    審判長法  官  莊飛宗\n                                      法  官  黃憲文\n                                      法  官  陳明富\n以上正本證明與原本無異。\n本件判決不得上訴。"
  },
  "characters": {
    "judges": [
      "莊飛宗",
      "黃憲文",
      "陳明富"
    ],
    "prosecutors": [
      "劉玲興"
    ],
    "lawyers": [

    ],
    "clerks": [
      "劉鴻瑛"
    ],
    "plaintiffs": [

    ],
    "defendants": [
      "田玟慧",
      "被      告  郭慧琳",
      "被      告  李建信"
    ],
    "prosecutor_office": [

    ],
    "creditors": [

    ],
    "debtors": [

    ],
    "judicial_associate_officer": [

    ]
  },
  "adjudged_at": "2010-01-05",
  "created_at": "2016-01-05 15:10:23",
  "updated_at": "2016-01-05 15:10:23"
}