{
  "identify": "KSH-98-上訴-1148-20100105-2",
  "court": {
    "name": "臺灣高等法院",
    "code": "KSH"
  },
  "division": {
    "name": "刑事",
    "code": "M"
  },
  "year": 98,
  "word": "上訴",
  "number": "1148",
  "jcheck": "2",
  "reason": "違反毒品危害防制條例",
  "content": "臺灣高等法院高雄分院刑事裁定        98年度上訴字第1148號\n上  訴  人  臺灣高雄地方法院檢察署檢察官\n上  訴  人\n即  被  告  甲○○\n選任辯護人  周振宇律師\n上  訴  人\n即  被  告  乙○○\n選任辯護人  盧俊誠律師\n上列被告因違反毒品危害防制條例等上訴案件，本院裁定如下：\n    主  文\n甲○○、乙○○羈押期間，自民國九十九年一月二十一日起，均\n延長貳月。\n    理  由\n一、上訴人即被告甲○○、乙○○前經本院認為犯罪嫌疑重大，\n    有刑事訴訟法第101 條第1 項第1 、3 款情形，非予羈押，\n    顯難進行審判或執行，於民國98年8 月21日執行羈押，至民\n    國99年1月20日第一次延長羈押期間即將屆滿。\n二、茲本院以前項原因依然存在，認有繼續羈押之必要，應自民\n    國99年1 月21日起，均延長羈押2 月，爰依刑事訴訟法第10\n    8 條第1 項、第5 項，裁定如主文。\n中    華    民    國    99    年     1    月    5     日\n                  刑事第五庭  審判長法  官  曾永宗\n                                    法  官  任森銓\n                                    法  官  鍾宗霖\n以上正本證明與原本無異。\n如不服本裁定應於送達後5 日內向本院提出抗告狀。\n中    華    民    國    99    年     1    月    5     日\n                                    書記官  陳武悅",
  "structure": {
    "main": "甲○○、乙○○羈押期間，自民國九十九年一月二十一日起，均\n延長貳月。",
    "reason": "一、上訴人即被告甲○○、乙○○前經本院認為犯罪嫌疑重大，\n    有刑事訴訟法第101 條第1 項第1 、3 款情形，非予羈押，\n    顯難進行審判或執行，於民國98年8 月21日執行羈押，至民\n    國99年1月20日第一次延長羈押期間即將屆滿。\n二、茲本院以前項原因依然存在，認有繼續羈押之必要，應自民\n    國99年1 月21日起，均延長羈押2 月，爰依刑事訴訟法第10\n    8 條第1 項、第5 項，裁定如主文。"
  },
  "characters": {
    "judges": [
      "曾永宗",
      "任森銓",
      "鍾宗霖"
    ],
    "prosecutors": [

    ],
    "lawyers": [
      "周振宇",
      "盧俊誠"
    ],
    "clerks": [

    ],
    "plaintiffs": [

    ],
    "defendants": [
      "甲",
      "乙"
    ],
    "prosecutor_office": [

    ],
    "creditors": [

    ],
    "debtors": [

    ],
    "judicial_associate_officer": [

    ]
  },
  "adjudged_at": "2010-01-05",
  "created_at": "2016-01-05 15:09:14",
  "updated_at": "2016-01-05 15:09:14"
}