{
  "identify": "KSH-98-上易-857-20100105-1",
  "court": {
    "name": "臺灣高等法院",
    "code": "KSH"
  },
  "division": {
    "name": "刑事",
    "code": "M"
  },
  "year": 98,
  "word": "上易",
  "number": "857",
  "jcheck": "1",
  "reason": "違反毒品危害防制條例",
  "content": "臺灣高等法院高雄分院刑事判決         98年度上易字第857號\n上  訴  人  甲○○\n即  被  告\n上列上訴人因違反毒品危害防制條例案件，不服臺灣高雄地方法\n院98年度易字第726 號中華民國98年8月27日第一審判決（起訴\n案號：臺灣高雄地方法院檢察署98年度毒偵字第389 號），提起\n上訴，本院判決如下：\n     主  文\n上訴駁回。\n    事  實\n一、甲○○前曾於95年間因施用毒品罪，經本院判處有期徒刑7\n    月確定，嗣經減刑為3 月又15日，於97年2 月7 日執行完畢\n    。詎其仍不知悔改，復基於施用第二級毒品甲基安非他命之\n    犯意，於98年1 月1 日下午3 時55分採尿回溯24小時內之某\n    時（不含公權力拘束之時間），在不詳地點以不詳方式，施\n    用第二級毒品甲基安非他命1 次，於同日下午2 時15分許，\n    在高雄縣大寮鄉○○路上，因形跡可疑而為警盤查，經警徵\n    得其同意後採集尿液送檢驗，結果呈甲基安非他命陽性反應\n    ，始查知上情。\n二、案經高雄市政府警察局苓雅分局移送臺灣高雄地方法院檢察\n    署檢察官偵查起訴。\n    理  由\n壹、證據能力部分：\n一、按鑑定之經過及其結果，應命鑑定人以言詞或報告，刑事訴\n    訟法第206 條第1 項定有明文。又法院或檢察官得囑託醫院\n    、學校或其他相當之機關、團體為鑑定，或審查他人之鑑定\n    ，並準用第203 條至第206 條之1 規定，刑事訴訟法第208\n    條第1 項亦有明文。查本案法務部調查局DNA 鑑識實驗室（\n    下稱調查局鑑驗室）所出具98年7 月2 日調科肆字第098003\n    63730 號鑑定書、高雄醫學大學附設中和紀念醫院（下稱高\n    雄醫學大學）所出具98年3 月3 日報告編號0000-000號檢驗\n    報告，係原審依職權囑託法務部調查局、高雄醫學院為鑑定\n    ，揆諸前揭說明，自屬「法律規定」得為證據者，應有證據\n    能力。\n二、又檢察官對於偵查中之案件，認須實施鑑定者，固應就具體\n    個案，選任鑑定人或囑託鑑定機關（團體）為之；但對於司\n    法警察機關調查中之案件，或有量大或急迫之情形，為因應\n    實務之現實需求，如檢察官針對該類案件之性質（例如：查\n    扣之毒品必須檢驗其成份、對於施用毒品之犯罪嫌疑人必須\n    檢驗其體內有無毒品代謝反應等）認為當然有鑑定之必要者\n    ，基於檢察一體原則，得由該管檢察長對於轄區內之案件，\n    以事前概括選任鑑定人或囑託鑑定機關（團體）之方式，俾\n    便轄區內之司法警察官、司法警察對於調查中之此類案件，\n    得即時送請事前已選任之鑑定人或囑託之鑑定機關（團體）\n    實施鑑定，該鑑定人或鑑定機關（團體）亦應視同受承辦檢\n    察官所選任或囑託而執行鑑定業務，其等出具之書面鑑定報\n    告應屬刑事訴訟法第206 條所定之傳聞例外，當具有證據能\n    力（法務部92年9 月1 日法檢字第0920035083號函可供參照\n    ）。本件被告之尿液，既經由查獲之警察單位依先前轄區檢\n    察署檢察長事前概括選任鑑定機關即高雄市立凱旋醫院（下\n    稱凱旋醫院），故凱旋醫院鑑定後於本案所出具之「濫用藥\n    物尿液檢驗報告」，即具有證據能力而得為本案之證據。\n三、次按被告以外之人（包括證人、鑑定人、告訴人、被害人及\n    共同被告等）於審判外之陳述雖不符刑事訴訟法第159 條之\n    1 至之4 等4 條之規定，而經當事人於審判程序同意作為證\n    據，法院審酌該言詞陳述或書面陳述作成時之情況，認為適\n    當者，得為證據。刑事訴訟法第159 條之5 第1 項定有明文\n    。查高雄市政府警察局苓雅分局搜索扣押筆錄、扣押物品目\n    錄表、濫用藥物尿液檢體監管紀錄表、煙毒、麻藥案件嫌疑\n    人尿液採證代碼對照表、毒品初步鑑驗報告等，其性質雖屬\n    傳聞證據，且當事人均已知上述證據乃傳聞證據，於原審及\n    本院審理時均同意作為證據，本院審酌上開證據與本案犯罪\n    事實具有關連性且無不當取得之情形，認為以之作為本案之\n    證據亦屬適當，揆諸前開規定，上開證據均應具有證據能力\n    。\n貳、實體部分：\n一、訊據上訴人即被告甲○○矢口否認有何施用第二級毒品甲基\n    安非他命之犯行，辯稱：我已經1 、2 年沒碰過甲基安非他\n    命了，可能係被查獲前1 晚，與朋友在密閉式空間相處，吸\n    入含甲基安非他命之二手菸，尿液檢驗報告才會出現陽性反\n    應云云。經查：\n  (一)被告於98年1 月1 日下午2 時15分許，在高雄縣大寮鄉○○\n    路上，因形跡可疑而為警盤查，經警徵得其同意採集後尿液\n    送往凱旋醫院鑑定，結果呈第二級毒品甲基安非他命陽性反\n    應之事實，業據被告於警詢時自承不諱，並有高雄市政府警\n    察局苓雅分局搜索扣押筆錄、扣押物品目錄表、、濫用藥物\n    尿液檢體監管紀錄表、煙毒、麻藥案件嫌疑人尿液採證代碼\n    對照表及凱旋醫院98年1 月12日濫用藥物尿液檢驗報告在卷\n    可按（見偵卷第4 至5 頁、7 至18頁、46頁），是此部分之\n    事實，堪以認定。\n  (二)被告於原審雖辯稱：送驗的尿液可能弄錯人了云云。惟查尿\n    液代碼F-98001 之尿液檢體係被告於98年1 月1 日下午3 時\n    55分，在高雄市○○區○○路派出所廁所內親自排放其尿液\n    於乾淨之尿瓶後，經其蓋以手印，並由警當面封緘等事實，\n    業據被告於警詢時供承在卷（見偵卷第5 頁反面），並有高\n    雄市政府警察局苓雅分局濫用藥物尿液檢體監管紀錄表、煙\n    毒、麻藥案件嫌疑人尿液採證代碼對照表在卷可查（見偵卷\n    第12、18頁），而該瓶尿液檢體，經原審依職權送往調查局\n    鑑驗室鑑定是否為被告所排放，其鑑定結果為：經比對尿液\n    與（被告）口腔棉棒之粒腺體DNAHVI序列均相同，研判二者\n    有可能（機率99.38 ％以上）來自同一人或其母系血緣關係\n    之人等語，有該局98年7 月2 日調科肆字第09800363730 號\n    鑑定書附卷可考（見原審一卷第83頁），顯見尿液代碼F-98\n    001 之尿液檢體確為被告所排放，員警自無錯置之可能性，\n    故被告上開所辯，顯係臨訟卸責之詞，不足採信。\n  (三)按服用安非他命後24小時內約有服用量之30％以原態排泄於\n    尿液中；甲基安非他命服用後24小時內約有服用量之70％排\n    泄於尿液中。毒品施用後於尿液中可檢出之時間，受施用劑\n    量及頻率、施用方式、飲水量之多寡、個人體質及其代謝情\n    況等因素影響，因個案而異。有行政院衛生署管制藥品管理\n    局於92年3 月10日管檢字第0920001495號函可參。本件被告\n    所排放之上開尿液檢體檢驗結果既有甲基安非他命、安非他\n    命類之陽性反應，且其代謝之甲基安非他命、安非他命濃度\n    分別高達5529ng/ml 、874ng/ml等情，有上開尿液檢驗報告\n    附卷可查，已遠高於行政院衛生署公告判定依據值甲基安非\n    他命之閾值500ng/ml且安非他命閥值大於100ng/ml之數值，\n    再參以上開尿液檢驗結果係採用氣相層析質譜分析法（GC/M\n    S ）進行確認，已足排除被告因吸二手菸或服用藥物導致呈\n    毒品偽陽性反應之可能，足徵被告確於於98年1 月1 日下午\n    3 時55分採尿前回溯24小時內之某時曾施用甲基安非他命等\n    情，至為顯明。\n  (四)綜上所述，被告空言辯稱其在採尿前未施用甲基安非他命，\n    顯係事後卸責之詞，殊無足採，本件事證明確，被告施用第\n    二級毒品之犯行，堪以認定。\n二、按甲基安非他命係屬毒品危害防制條例第2 條第2 項第2 款\n    所稱之第二級毒品，依法不得施用。核被告所為，係犯毒品\n    危害防制條例第10條第2 項之施用第二級毒品罪。其持有甲\n    基安非他命後，進而施用，其持有之低度行為應被其施用之\n    高度行為所吸收，不另論罪。又被告前曾於95年間因施用毒\n    品罪，經本院判處有期徒刑7 月確定，嗣經減刑為3 月又15\n    日，於97年2 月7 日執行完畢，有臺灣高等法院被告前案紀\n    錄表1 份附卷可稽，其於有期徒刑執行完畢後5 年內，再故\n    意犯本件有期徒刑以上之罪，為累犯，應依刑法第47條第1\n    項之規定加重其刑。\n三、原審因而適用毒品危害防制條例第10條第2 項，刑法第11條\n    前段、第47條第1 項之規定，並審酌被告前已有施用毒品前\n    科，本應徹底戒除毒癮，不料其竟仍繼續施用毒品，顯見其\n    並無戒除毒害之決心，復於原審及本院審理時，否認犯行，\n    致原審耗費司法資源為其做DNA 鑑定，故量刑實不宜從寬，\n    亦不宜低於先前所判處之7 月有期徒刑，另考量施用毒品者\n    乃自戕一己之身體健康，並具有病患性人格之特質，其行為\n    本身對社會所造成之危害並非直接、鉅大等一切情狀，量處\n    有期徒刑10月，至公訴檢察官雖當庭請求量處被告有期徒刑\n    11月，然審酌上述情況，認被告量處如上開之刑，較為適當\n    。又以扣案之白色晶體1 包（毛重0.3 公克），經送鑑驗結\n    果，含第四級毒品甲基麻黃鹼成分之事實，有高雄醫學大學\n    98 年3月3 日報告編號0000-000號檢驗報告，因與本案被告\n    施用第二級毒品犯行無關，且亦查無證據證明該甲基麻黃鹼\n    係專供被告施用毒品之器具或供被告犯罪所用，爰不另予宣\n    告沒收，於理由欄併予敘明；其認事用法，均無不合，量刑\n    亦屬適當，被告上訴意旨，仍執陳詞，否認犯罪，指摘原判\n    決不當，為無理由，應予駁回。\n據上論斷，應依刑事訴訟法第368 條，判決如主文。\n本案經檢察官張金塗到庭執行職務。\n中    華    民    國    99    年    1    月    5    日\n                  刑事第七庭    審判長法  官 莊飛宗\n                                      法  官 蔡廣昇\n                                      法  官 黃憲文\n以上正本證明與原本無異。\n不得上訴。\n中    華    民    國    99    年    1    月    5    日\n                                      書記官 戴志穎\n附錄本判決論罪科刑法條：\n毒品危害防制條例第10條第2項\n施用第二級毒品者，處3 年以下有期徒刑。",
  "structure": {
    "main": "上訴駁回。",
    "fact": "一、甲○○前曾於95年間因施用毒品罪，經本院判處有期徒刑7\n    月確定，嗣經減刑為3 月又15日，於97年2 月7 日執行完畢\n    。詎其仍不知悔改，復基於施用第二級毒品甲基安非他命之\n    犯意，於98年1 月1 日下午3 時55分採尿回溯24小時內之某\n    時（不含公權力拘束之時間），在不詳地點以不詳方式，施\n    用第二級毒品甲基安非他命1 次，於同日下午2 時15分許，\n    在高雄縣大寮鄉○○路上，因形跡可疑而為警盤查，經警徵\n    得其同意後採集尿液送檢驗，結果呈甲基安非他命陽性反應\n    ，始查知上情。\n二、案經高雄市政府警察局苓雅分局移送臺灣高雄地方法院檢察\n    署檢察官偵查起訴。",
    "reason": "壹、證據能力部分：\n一、按鑑定之經過及其結果，應命鑑定人以言詞或報告，刑事訴\n    訟法第206 條第1 項定有明文。又法院或檢察官得囑託醫院\n    、學校或其他相當之機關、團體為鑑定，或審查他人之鑑定\n    ，並準用第203 條至第206 條之1 規定，刑事訴訟法第208\n    條第1 項亦有明文。查本案法務部調查局DNA 鑑識實驗室（\n    下稱調查局鑑驗室）所出具98年7 月2 日調科肆字第098003\n    63730 號鑑定書、高雄醫學大學附設中和紀念醫院（下稱高\n    雄醫學大學）所出具98年3 月3 日報告編號0000-000號檢驗\n    報告，係原審依職權囑託法務部調查局、高雄醫學院為鑑定\n    ，揆諸前揭說明，自屬「法律規定」得為證據者，應有證據\n    能力。\n二、又檢察官對於偵查中之案件，認須實施鑑定者，固應就具體\n    個案，選任鑑定人或囑託鑑定機關（團體）為之；但對於司\n    法警察機關調查中之案件，或有量大或急迫之情形，為因應\n    實務之現實需求，如檢察官針對該類案件之性質（例如：查\n    扣之毒品必須檢驗其成份、對於施用毒品之犯罪嫌疑人必須\n    檢驗其體內有無毒品代謝反應等）認為當然有鑑定之必要者\n    ，基於檢察一體原則，得由該管檢察長對於轄區內之案件，\n    以事前概括選任鑑定人或囑託鑑定機關（團體）之方式，俾\n    便轄區內之司法警察官、司法警察對於調查中之此類案件，\n    得即時送請事前已選任之鑑定人或囑託之鑑定機關（團體）\n    實施鑑定，該鑑定人或鑑定機關（團體）亦應視同受承辦檢\n    察官所選任或囑託而執行鑑定業務，其等出具之書面鑑定報\n    告應屬刑事訴訟法第206 條所定之傳聞例外，當具有證據能\n    力（法務部92年9 月1 日法檢字第0920035083號函可供參照\n    ）。本件被告之尿液，既經由查獲之警察單位依先前轄區檢\n    察署檢察長事前概括選任鑑定機關即高雄市立凱旋醫院（下\n    稱凱旋醫院），故凱旋醫院鑑定後於本案所出具之「濫用藥\n    物尿液檢驗報告」，即具有證據能力而得為本案之證據。\n三、次按被告以外之人（包括證人、鑑定人、告訴人、被害人及\n    共同被告等）於審判外之陳述雖不符刑事訴訟法第159 條之\n    1 至之4 等4 條之規定，而經當事人於審判程序同意作為證\n    據，法院審酌該言詞陳述或書面陳述作成時之情況，認為適\n    當者，得為證據。刑事訴訟法第159 條之5 第1 項定有明文\n    。查高雄市政府警察局苓雅分局搜索扣押筆錄、扣押物品目\n    錄表、濫用藥物尿液檢體監管紀錄表、煙毒、麻藥案件嫌疑\n    人尿液採證代碼對照表、毒品初步鑑驗報告等，其性質雖屬\n    傳聞證據，且當事人均已知上述證據乃傳聞證據，於原審及\n    本院審理時均同意作為證據，本院審酌上開證據與本案犯罪\n    事實具有關連性且無不當取得之情形，認為以之作為本案之\n    證據亦屬適當，揆諸前開規定，上開證據均應具有證據能力\n    。\n貳、實體部分：\n一、訊據上訴人即被告甲○○矢口否認有何施用第二級毒品甲基\n    安非他命之犯行，辯稱：我已經1 、2 年沒碰過甲基安非他\n    命了，可能係被查獲前1 晚，與朋友在密閉式空間相處，吸\n    入含甲基安非他命之二手菸，尿液檢驗報告才會出現陽性反\n    應云云。經查：\n  (一)被告於98年1 月1 日下午2 時15分許，在高雄縣大寮鄉○○\n    路上，因形跡可疑而為警盤查，經警徵得其同意採集後尿液\n    送往凱旋醫院鑑定，結果呈第二級毒品甲基安非他命陽性反\n    應之事實，業據被告於警詢時自承不諱，並有高雄市政府警\n    察局苓雅分局搜索扣押筆錄、扣押物品目錄表、、濫用藥物\n    尿液檢體監管紀錄表、煙毒、麻藥案件嫌疑人尿液採證代碼\n    對照表及凱旋醫院98年1 月12日濫用藥物尿液檢驗報告在卷\n    可按（見偵卷第4 至5 頁、7 至18頁、46頁），是此部分之\n    事實，堪以認定。\n  (二)被告於原審雖辯稱：送驗的尿液可能弄錯人了云云。惟查尿\n    液代碼F-98001 之尿液檢體係被告於98年1 月1 日下午3 時\n    55分，在高雄市○○區○○路派出所廁所內親自排放其尿液\n    於乾淨之尿瓶後，經其蓋以手印，並由警當面封緘等事實，\n    業據被告於警詢時供承在卷（見偵卷第5 頁反面），並有高\n    雄市政府警察局苓雅分局濫用藥物尿液檢體監管紀錄表、煙\n    毒、麻藥案件嫌疑人尿液採證代碼對照表在卷可查（見偵卷\n    第12、18頁），而該瓶尿液檢體，經原審依職權送往調查局\n    鑑驗室鑑定是否為被告所排放，其鑑定結果為：經比對尿液\n    與（被告）口腔棉棒之粒腺體DNAHVI序列均相同，研判二者\n    有可能（機率99.38 ％以上）來自同一人或其母系血緣關係\n    之人等語，有該局98年7 月2 日調科肆字第09800363730 號\n    鑑定書附卷可考（見原審一卷第83頁），顯見尿液代碼F-98\n    001 之尿液檢體確為被告所排放，員警自無錯置之可能性，\n    故被告上開所辯，顯係臨訟卸責之詞，不足採信。\n  (三)按服用安非他命後24小時內約有服用量之30％以原態排泄於\n    尿液中；甲基安非他命服用後24小時內約有服用量之70％排\n    泄於尿液中。毒品施用後於尿液中可檢出之時間，受施用劑\n    量及頻率、施用方式、飲水量之多寡、個人體質及其代謝情\n    況等因素影響，因個案而異。有行政院衛生署管制藥品管理\n    局於92年3 月10日管檢字第0920001495號函可參。本件被告\n    所排放之上開尿液檢體檢驗結果既有甲基安非他命、安非他\n    命類之陽性反應，且其代謝之甲基安非他命、安非他命濃度\n    分別高達5529ng/ml 、874ng/ml等情，有上開尿液檢驗報告\n    附卷可查，已遠高於行政院衛生署公告判定依據值甲基安非\n    他命之閾值500ng/ml且安非他命閥值大於100ng/ml之數值，\n    再參以上開尿液檢驗結果係採用氣相層析質譜分析法（GC/M\n    S ）進行確認，已足排除被告因吸二手菸或服用藥物導致呈\n    毒品偽陽性反應之可能，足徵被告確於於98年1 月1 日下午\n    3 時55分採尿前回溯24小時內之某時曾施用甲基安非他命等\n    情，至為顯明。\n  (四)綜上所述，被告空言辯稱其在採尿前未施用甲基安非他命，\n    顯係事後卸責之詞，殊無足採，本件事證明確，被告施用第\n    二級毒品之犯行，堪以認定。\n二、按甲基安非他命係屬毒品危害防制條例第2 條第2 項第2 款\n    所稱之第二級毒品，依法不得施用。核被告所為，係犯毒品\n    危害防制條例第10條第2 項之施用第二級毒品罪。其持有甲\n    基安非他命後，進而施用，其持有之低度行為應被其施用之\n    高度行為所吸收，不另論罪。又被告前曾於95年間因施用毒\n    品罪，經本院判處有期徒刑7 月確定，嗣經減刑為3 月又15\n    日，於97年2 月7 日執行完畢，有臺灣高等法院被告前案紀\n    錄表1 份附卷可稽，其於有期徒刑執行完畢後5 年內，再故\n    意犯本件有期徒刑以上之罪，為累犯，應依刑法第47條第1\n    項之規定加重其刑。\n三、原審因而適用毒品危害防制條例第10條第2 項，刑法第11條\n    前段、第47條第1 項之規定，並審酌被告前已有施用毒品前\n    科，本應徹底戒除毒癮，不料其竟仍繼續施用毒品，顯見其\n    並無戒除毒害之決心，復於原審及本院審理時，否認犯行，\n    致原審耗費司法資源為其做DNA 鑑定，故量刑實不宜從寬，\n    亦不宜低於先前所判處之7 月有期徒刑，另考量施用毒品者\n    乃自戕一己之身體健康，並具有病患性人格之特質，其行為\n    本身對社會所造成之危害並非直接、鉅大等一切情狀，量處\n    有期徒刑10月，至公訴檢察官雖當庭請求量處被告有期徒刑\n    11月，然審酌上述情況，認被告量處如上開之刑，較為適當\n    。又以扣案之白色晶體1 包（毛重0.3 公克），經送鑑驗結\n    果，含第四級毒品甲基麻黃鹼成分之事實，有高雄醫學大學\n    98 年3月3 日報告編號0000-000號檢驗報告，因與本案被告\n    施用第二級毒品犯行無關，且亦查無證據證明該甲基麻黃鹼\n    係專供被告施用毒品之器具或供被告犯罪所用，爰不另予宣\n    告沒收，於理由欄併予敘明；其認事用法，均無不合，量刑\n    亦屬適當，被告上訴意旨，仍執陳詞，否認犯罪，指摘原判\n    決不當，為無理由，應予駁回。\n據上論斷，應依刑事訴訟法第368 條，判決如主文。\n本案經檢察官張金塗到庭執行職務。\n中    華    民    國    99    年    1    月    5    日\n                  刑事第七庭    審判長法  官 莊飛宗\n                                      法  官 蔡廣昇\n                                      法  官 黃憲文\n以上正本證明與原本無異。\n不得上訴。"
  },
  "characters": {
    "judges": [
      "莊飛宗",
      "蔡廣昇",
      "黃憲文"
    ],
    "prosecutors": [
      "張金塗"
    ],
    "lawyers": [

    ],
    "clerks": [
      "戴志穎"
    ],
    "plaintiffs": [

    ],
    "defendants": [
      "上列上訴人因違反毒品危害防制條例案件"
    ],
    "prosecutor_office": [

    ],
    "creditors": [

    ],
    "debtors": [

    ],
    "judicial_associate_officer": [

    ]
  },
  "adjudged_at": "2010-01-05",
  "created_at": "2016-01-05 15:11:13",
  "updated_at": "2016-01-05 15:11:13"
}