{
  "identify": "KSH-99-上訴-377-20100512-1",
  "court": {
    "name": "臺灣高等法院",
    "code": "KSH"
  },
  "division": {
    "name": "刑事",
    "code": "M"
  },
  "year": 99,
  "word": "上訴",
  "number": "377",
  "jcheck": "1",
  "reason": "違反毒品危害防制條例等",
  "content": "臺灣高等法院高雄分院刑事判決         99年度上訴字第377號\n上  訴  人\n即  被  告  甲○○\n選任辯護人  陳煜昇律師\n選任辯護人  張永昌律師\n上列上訴人因違反毒品危害防制條例等案件，不服臺灣高雄地方\n法院98年度訴字第1285號中華民國98年12月9 日第一審判決（起\n訴案號：臺灣高雄地方法院檢察署98年度偵字第5033號、7996\n號、8546號），提起上訴，本院判決如下：\n    主  文\n原判決關於甲○○販賣第一級毒品四罪部分及定執行刑部分撤銷\n。\n甲○○販賣附表一所示第一級毒品，處有期徒刑拾伍年陸月，褫\n奪公權肆年。扣案如附表二編號1 所示之物，沒收銷燬之，編號\n4 、5 、10所示之物，均沒收；未扣案之販賣毒品所得新臺幣肆\n仟元沒收之，如全部或一部不能沒收時，以其財產抵償之。\n甲○○其他被訴販賣第一級毒品參罪部分均無罪。\n    事  實\n一、甲○○（綽號「阿達」、「達仔」）明知海洛因係毒品危害\n    防制條例第2 條第2 項第1 款所列之第一級毒品，不得持有\n    、販賣或轉讓，竟意圖牟利，基於販賣第一級毒品海洛因之\n    犯意，以其申辦使用之手機門號0000000000、及其父李坤旺\n    申辦0000000000等門號為聯絡工具，為以下之販賣海洛因行\n    為，即於97年12月6 日17時許，高漢武搭乘立榮航空股份有\n    限公司（下稱「立榮航空」）班機自澎湖馬公機場出發，抵\n    達位於高雄市小港區之高雄國際航空站（下稱小港機場）後\n    ，以其上開手機門號聯絡甲○○，並搭計程車至高雄市○○\n    區○○路72之5 號10樓高家祥住處大樓1 樓之「萊爾富超商\n    」（下稱「高家祥住處樓下」），由甲○○以新台幣( 下同\n    )4,000元之價格，販售予高漢武海洛因1 包（毛重約0.6 公\n    克）。嗣於同（6 ）日18時15分，高漢武復搭「立榮航空」\n    班機返抵澎湖時，在馬公機場為警查獲，並扣得高漢武藏在\n    其運動鞋鞋墊內之海洛因1 包（驗前淨重0.106 公克，驗後\n    淨重0.097 公克，於其施用毒品案中）。嗣於97年12月8日\n    凌晨零時30分許，澎湖縣政府警察局經徵得高家祥之同意，\n    在其上開住處執行搜索，查獲甲○○，並扣得甲○○所有如\n    附表二所示之海洛因2 小包（合計淨重1.8 公克）、甲基安\n    非他命3 小包（分別淨重0.119 、0.687 、0.706 公克）、\n    香菸（峰牌）1 支、電子磅秤1 台、行動電話SIM 卡3 張、\n    帳單（記事本）1 冊、吸管分裝具5 支、分裝盒1 組（內有\n    分裝吸管小湯匙）、剪刀1 把、夾鍊袋206 個、鋁箔紙1張\n    ，小皮包1 個（內有3 萬6 千元) 等物。\n二、案經澎湖縣政府警察局移送臺灣高雄地方法院檢察署檢察官\n    偵查起訴。\n    理  由\n甲、有罪部分：\n壹、證據能力部分：\n一、按被告以外之人於審判外之言詞或書面陳述，除法律有規定\n    者外，不得作為證據，刑事訴訟法第159 條第1 項有明文。\n    本件證人高漢武於警詢中之陳述為審判外之陳述，且查無合\n    於同法第159 條之1 至第159 條之5 例外規定情形，且被告\n    之辯護人於本院中爭執其證據能力，依同法第159 條第1項\n    規定，證人高漢武於警詢中之陳述對被告即無證據能力。\n二、次按被告以外之人於審判外之陳述，雖不符前四條之規定，\n    而經當事人於審判程序同意作為證據，法院審酌該言詞陳述\n    或書面陳述作成時之情況，認為適當者，亦得為證據，刑事\n    訴訟法第159 條之5 第1 項定有明文。本件被告及其辯護人\n    於本院準備程序時，已表示除上開爭執證據能力之陳述證據\n    外，對下列所引證據屬被告以外之人在審判外陳述之傳聞證\n    據部分，均同意作為證據( 見本院卷第71頁) 。本院斟酌上\n    開證據並無違法取得之情事，亦無證明力明顯過低之情形，\n    認為作為本件被告認定犯罪有無之證據亦屬適當，是均得採\n    為本件論斷之證據。\n貳、實體部分：\n一、訊據被告矢口否認有何販賣第一級毒品海洛因與高漢武，於\n    原審及本院均辯稱：伊沒有販賣第一級毒品海洛因給高漢武\n    ，那天我們也沒有聯絡，伊也沒有去萊爾富或是高家祥的住\n    處，高家祥伊也是透過莊正和認識的，高漢武也是。97年12\n    月6 日伊沒有見到高漢武，他被查獲的海洛因不是伊賣他的\n    等語。\n二、證人高漢武於原審審理時具結證稱：（你在98年3 月26 日\n    偵訊時說「達仔就是甲○○」是否有這樣說？）有，達仔就\n    是甲○○；（這2 次查獲毒品海洛因都是達仔即甲○○賣給\n    你？）是；（案發時你的手機0000000000號、000000 0000\n    號都是你所有？）是；（你在97年12月6 日回澎湖時，在馬\n    公機場鞋子裡面查扣到1 包海洛因？）是；（這包海洛因跟\n    何人購買？）達仔；（是否就是剛才在場的被告甲○○？）\n    是等語明確（見原審2 卷第87正反、88反頁）；且於偵訊時\n    具結證稱：伊於97年12月6 日當天坐飛機到高雄，是在「高\n    家祥住處」買的，這次用4 千元買到1 包海洛因（約重0.6\n    公克），「達仔」就是甲○○，他跟高家祥住在一起，伊是\n    透過莊正和認識等語明確（見偵1 卷第36頁），前後參核相\n    符。此外，並有「立榮航空」98年6 月11日立航字第200903\n    93號函附來回旅客艙單（編號B7 -6168、6269），及證人高\n    漢武所持用門號0000000000、0000000000、0000000000，與\n    被告持用門號0000000000、0000000000手機雙向通聯紀錄各\n    1 份在卷可稽，亦比對相符（見偵1 卷第6 、7 、12至29、\n    50至59、65至68頁）。況且，證人高漢武因此查獲海洛因1\n    包（毛重0.6 公克），其施用第一級毒品犯行，業經檢察官\n    起訴，並經台灣澎湖地方法院98年度訴字第15號判決判處有\n    期徒刑8 月確定（98年9 月15日入監執行）等情，亦有上開\n    起訴書、判決書及台灣高等法院被告前案紀錄表在卷足參（\n    見原審2 卷第112 至120 頁) 。從而，被告有販賣海洛因1\n    次給證人高漢武之犯行，已屬明顯。\n三、雖證人高漢武於原審審理時先證稱：伊這2 次海洛因都是跟\n    人家買的，不一定，時間地點都不固定，1 次都買2 千元云\n    云（見原審2 卷第85反、86正頁）；然其同時具結證稱：達\n    仔就是被告甲○○，（12月6 日海洛因是在何處跟甲○○拿\n    的？）民族大樂後面那1 條路，就是高家祥他家樓下的「萊\n    爾富超商」買的，伊當時沒有上去；（12月6 日購買多少毒\n    品？）4 千元等語明確（見原審2 卷第88反頁）。此外，並\n    有證人高漢武持用手機，與被告持用手機雙向通聯紀錄在卷\n    ，如前所述。是證人高漢武上開證述之實在性，足堪印證：\n    證人高漢武上開翻異之詞，仍不足為被告有利之認定，被告\n    上開所辯，尚無從採取。\n四、再警方欲查出上開毒品上游，徵得證人高漢武之同意配合，\n    於97年12月7 日17時30分，由證人高漢武復搭乘復興航空運\n    輸股份有限公司（下稱「復興航空」）班機自澎湖馬公機場\n    出發，抵達小港機場後，以其手機門號0000000000、000000\n    0000，撥打甲○○手機門號00000000 00 ，向其稱：欲購買\n    毒品等情，嗣被告甲○○駕駛車號WQ-7631 白色自小客車搭\n    載莊正和前來，於同（7 ）日17時30分，開至在小港機場大\n    門外省道台17線公路南向外側快車道上（靠對面高雄公園側\n    ）停車，證人高漢武站於該快、慢車道分隔島上等候，隨即\n    提出2 千元還給甲○○，被告甲○○亦有交付海洛因1 包證\n    人高漢武等情( 此部分業經原審以被告甲○○係轉讓第一級\n    毒品未遂罪，判決有期徒刑8 月，被告甲○○上訴後，撤回\n    上訴，業已確定在案) ，亦據證人證人高漢武於偵查及原審\n    證述在卷( 見偵1 卷第36頁、原審2 卷第88頁) ，並經證人\n    莊正和於偵訊時具結證稱：當天係被告甲○○開車，伊坐在\n    副駕駛座，一起到高雄機場，伊有看到甲○○拿1 包白色東\n    西給高漢武等語屬實（見偵2 卷第17頁），並有「復興航空\n    」98年6 月29日地服字第98-140號函附搭乘紀錄艙單（編號\n    GE-0 219）在卷可稽（見偵1 卷第63、64頁）亦堪認定；是\n    依上情相互參酌，及證人高漢武復搭「立榮航空」班機返抵\n    澎湖時，在馬公機場為警查獲，並扣得證人高漢武藏在其運\n    動鞋鞋墊內之海洛因1 包後，配合澎湖縣政府警察局查獲被\n    告甲○○等情以觀，亦可印證被告甲○○確有前開販賣第一\n    級毒品給證人高漢武之事實。\n五、販賣毒品係政府嚴予查緝之違法行為，且毒品可任意分裝或\n    增減其份量，而每次買賣之價量，亦隨時依雙方關係之深淺\n    、當時之資力、需求程度及對行情之認知等因素，機動調整\n    ，因之販賣之利得，除經被告坦承犯行，或帳冊價量均記載\n    明確外，委難查得實情，是縱未確切查得販賣賺取之實際差\n    價，但除別有事證，足認係按同一價格轉讓，確未牟利之情\n    形外，尚難執此認非法販賣之事證有所不足，致知過坦承者\n    難辭重典，飾詞否認者反得逞僥倖，而失情理之平；且為販\n    賣毒品之不法行為者，苟無利可圖，應無甘冒持有毒品遭查\n    獲之極大風險，從事此買賣工作，是其販入之價格必較售出\n    之價格低廉，而有從中賺取買賣差價牟利之意圖及事實，應\n    屬符合論理法則而不違背社會通常經驗之合理判斷，從而被\n    告上開出售第一級毒品與證人高漢武之交易，具有營利之意\n    圖，亦堪認定。\n六、綜上所述，被告甲○○確定上開時地，以4000元價格販賣第\n    一級毒品1 包與證人高漢武之犯行，事證明確，堪以認定。\n七、按行為後法律有變更者，適用行為時之法律。但行為後之法\n    律有利於行為人者，適用最有利於行為人之法律，刑法第2\n    條第1 項定有明文。查本件被告行為後，有關論罪科刑所適\n    用之毒品危害防制條例，其中部分條文業於98年5 月20日修\n    正公布，98年5 月22日起施行，本件被告犯罪後，毒品危害\n    防制條例第4 條已有修正，修正後同條例第4 條第1 項規定\n    ：「製造、運輸、販賣第一級毒品者，處死刑、無期徒刑；\n    處無期徒刑者，得併科新臺幣2 千萬元以下罰金。」而就併\n    科罰金刑部分，與修正前之規定「得併科新臺幣1 千萬元以\n    下罰金。」相較，修正前最高金額為1 千萬元，而修正後則\n    係2 千萬元，以修正前之規定有利於被告。自應適用修正前\n    毒品危害防制條例第4 條第1 項之規定。\n八、核上開所為，係犯修正前毒品危害防制條例第4條 第1 項之\n    販賣第一級毒品罪；被告持有第一級毒品海洛因之低度行為\n    ，為販賣之高度行為所吸收，不另論罪。\n九、又本院復審酌被告販賣第一級毒品法定本刑為「死刑、無期\n    徒刑」，又販賣第一級毒品固屬應嚴加處罰之重大犯罪，然\n    同為販賣第一級毒品之人，其原因動機不一，犯罪情節未必\n    盡同，或有大盤毒梟者，亦有中、小盤之分，甚或僅止於吸\n    毒者同儕間為求互通有無之有償轉讓者亦有之，其販賣行為\n    所造成危害社會之程度自屬有異，法律科處此類犯罪所設之\n    法定最低本刑卻同為無期徒刑，不可謂為不重。而查被告販\n    賣之對象為證人高漢武1 人，且販毒所得僅4 千元，交易金\n    額尚輕，堪認應非大盤毒梟，犯罪情節尚難與大盤或中盤毒\n    梟者相提併論，本院即令處以被告最低刑度即無期徒刑而禁\n    錮終身，仍有致情法失平之處，誠屬情輕法重，其犯罪情狀\n    尚非全然無可憫恕之處，爰依刑法第59條規定，就販賣第一\n    級毒品罪酌減輕其刑。\n十、原審對被告上開部分，予以論罪科刑，固非無見。惟查( 一\n    ) 認定犯罪事實之證據，其判斷必須合理，否則即欠缺妥當\n    性。查扣案之附表二編號11之現金3 萬6000元，被告辯以上\n    開金額係買車的錢等語（見警1 卷第9 頁、本院卷第96頁)\n    ，詎原審在無證據證明上開現金與本件販賣毒品有關之下，\n    遽以上開3 萬6000元扣除本件之4000元，自依同條例第19條\n    第1 項規定，宣告沒收，至於所剩3 萬2000 元 始認定無證\n    據證明為犯本罪所得之財物，不予宣告沒收，自有所不當。\n     (二) 附表編號3 之香菸( 峰牌，內摻入海洛因)1支，係被\n    告於查獲當日正要施用，即為警查獲，業據被告甲○○於本\n    院審理時供明在卷( 見本院卷第99頁) ，核與本件販賣第一\n    級毒品無涉，原審予以沒收銷燬，亦有未合。( 三) 附表編\n    號6 之記事本一冊，則係被告甲○○記載之日日會，有關人\n    家欠其錢之記錄，亦據被告甲○○供明在卷( 見本院卷第97\n    頁) ，且觀記事本之內容，亦係記載Y 瑞借23000 、Y 茹借\n    10000 、小君借600 、五甲佑借2 萬、小凱借1 萬2 千等情\n    ，亦核與販賣第一級毒品無關，原審依毒品危害防制條例第\n    19條第1 項規定，併應宣告均沒收，自有不當。雖被告就上\n    開販賣第一級毒品部分，否認犯罪，指摘原判決不當，雖無\n    理由，惟原判決既有上開可議之處，自屬無可維持，應由本\n    院就原判決此部分及定執行刑併予撤銷。\n十一、爰審酌被告意圖牟利，販賣第一級毒品，嚴重違反我國法律\n    反毒、禁毒之政策，影響社會安全秩序甚鉅，更荼毒國人身\n    心健康，犯後否認犯行，惟考量被告販賣證人高漢武僅一次\n    ；尚非販賣毒品之大盤商，販賣時間亦不長等一切情狀，乃\n    量處如主文即附表一所示之刑，另就被告所犯販賣第一級毒\n    品罪之犯罪性質，嚴重侵害國家及社會法益，認有禠奪公權\n    之必要，併宣告禠奪公權4 年。\n十二、按查獲之第一級毒品及專供製造或施用第一級毒品之器具，\n    不問屬於犯人與否，均沒收銷燬之，毒品危害防制條例第18\n    條第1 項前段定有明文。扣案如附表二編號1 之海洛因2 包\n    （即檢驗編號第2 、3 包，合計淨重1.80公克），經檢驗確\n    屬第一級毒品；是依毒品危害防制條例第18條第1 項前段之\n    規定，併諭知均沒收銷燬之。因檢驗所耗用之上開毒品既已\n    滅失，不另為沒收銷燬之諭知。\n十三、按毒品危害防制條例第19條第1 項關於沒收之規定，係採義\n    務沒收主義，犯同條例第4 條至第9 條、第12條、第13條或\n    第14條第1 項、第2 項之罪者，其供犯罪所用之物或因犯罪\n    所得之財物，且屬犯人所有者，即應依該規定沒收，法院無\n    審酌之餘地，並不以專供犯罪所用之物為限（最高法院93年\n    度臺上字第1360號、第1365號、92年度臺上字第2608號判決\n    意旨參照），且犯同條例第4 條之罪者，其供犯罪所用或因\n    犯罪所得之財物應予沒收，如全部或一部不能沒收時，追徵\n    其價額或以其財產抵償之，該條例第19條第1 項規定甚明，\n    如所得財物為金錢而無法沒收時，應以其財產抵償之（最高\n    法院95年度臺上字第305 號判決意旨參照）。據此，被告販\n    賣第一級毒品所得財物4000元，因未扣案，除應依毒品危害\n    防制條例第19條第1 項規定分別宣告沒收之，並諭知如全部\n    或一部不能沒收時，以其財產抵償之。另扣案如附表二編號\n    4 、5 、10之電子磅秤1 台、行動電話1 支含門號00000000\n    00之SIM 卡1 張）、及夾鍊袋206 個，均為被告所有，業據\n    被告供明在卷，且核係供其分裝毒品海洛因之用，是依毒品\n    危害防制條例第19條第1 項規定，併應宣告均沒收。至於扣\n    案附表二編號11之現金3 萬6000元，被告辯稱係買車的錢，\n    如前所述，又無積極證據足以證明與本件販賣毒品有關，已\n    如前述，自不予逕行宣告沒收。另有關附表編號17之海洛因\n    1 包，業已販賣給證人高漢武，經證人高漢武交與澎湖警方\n    ，此部分已在證人高漢武經臺灣澎湖地方法院對證人高漢武\n    施用毒品之判決下諭知沒收在案( 見原審2 卷第117 頁) ，\n    自不予在本件被告販賣毒品之判決主刑下為之。\n十四、其餘扣案之物品，其中附表二編號2 部分，則屬甲基安非他\n    命3 包（其中1 包驗前淨重0.119 公克，驗後淨重0.110 公\n    克；1 包驗前淨重0.687 公克，驗後淨重0.678 公克；1 包\n    驗前淨重0.715 公克，驗後淨重0.706 公克），編號3 之香\n    菸( 峰牌，內摻入海洛因)1支，係其施用第一級毒品所用之\n    物，編號7 之吸管分裝具5 支、編號8 之分裝盒（內有分裝\n    吸管小湯匙）1 組、編號9 之剪刀（剪吸管分裝具）1 把，\n    均屬施用毒品之工具，編號6 之記事本一冊，則係被告甲○\n    ○記載之日日會，有關人家欠其錢之記錄，如前所述，另如\n    附表二編號14之行動電話2 支，係他人名義申辦，其中一支\n    0000000000號，其聲請人為案外人李坤旺，並非被告所有之\n    物；編號13之白色粉末第1 包（淨重1.36公克，空包裝重0.\n    19公克），並未檢出法定毒品成分；編號15、16之小皮包1\n    個、鋁箔紙1 張，不能證明係本件被告犯罪所得或供其犯罪\n    所用之物，及編號12之白色晶體1 包，雖經檢出為愷他命成\n    分（驗後淨重0.546 公克），屬第三級毒品，上開均與本件\n    被告所犯販毒第一級毒品罪無關，不予宣告沒收銷燬及沒收\n    之。\n乙、無罪部分：\n一、公訴意旨另以：被告甲○○於97年8 月下旬（20日至30日間\n    ）某日，在高雄市○○區○○路之「中正飯店」508 號房內\n    （下稱「中正飯店」），先後3 次，均1 萬元之價格，販售\n    數量不詳海洛因（毛重約1 公克）予翁丁元，因認此部分亦\n    涉犯毒品危害防制條例第4 條第1 項之販賣第一級毒品罪嫌\n    云云。\n二、公訴人認被告此部分亦涉犯上開罪嫌，無非以(1)被告甲○○\n    於警詢及偵查中之供述。(2)證人翁丁元於警詢及偵查中之證\n    述。(3)證人莊正和於警詢及偵查中之證述(4)本件扣案之海洛\n    因等為主要之論據。\n三、按犯罪事實應依證據認定之，無證據不得認定犯罪事實；又\n    不能證明被告犯罪者，應諭知無罪之判決，刑事訴訟法第一\n    百五十四條第二項、第三百零一條第一項分別定有規定。認\n    定不利於被告之事實，須依積極證據，苟積極證據不足為不\n    利於被告事實之認定時，即應為有利於被告之認定，更不必\n    有何有利之證據。此之所謂證據，須確屬能為被告有罪之證\n    明，而無瑕疵可指者，始足當之；再者，犯罪事實之認定，\n    應憑證據，所謂證據，須適於為被告犯罪事實之證明者，始\n    得採為斷罪資料，如未能發現相當證據，或證據不足以證明\n    ，自不能以推測或擬制之方法以為裁判基礎；又所謂認定犯\n    罪事實所憑之證據，雖不以直接證據為限，間接證據亦包括\n    在內，然而無論直接或間接證據，其為訴訟上之證明，須於\n    通常一般人均不致有所懷疑，而得確信其為真實之程度，始\n    得據之為有罪之認定，倘其證明尚未達到此一程度，而有合\n    理懷疑存在時，即應為無罪之判決（最高法院二十九年上字\n    第三一○五號、三十年上字第八一六號、四十年台上字第八\n    六號、五十三年台上字第二七五○號、七十六年台上字第四\n    九八六號分別著有判例參照）。復事實審法院對於證據之取\n    捨，依法雖有自由判斷之權，然積極證據不足證明犯罪事實\n    時，被告之抗辯或反證縱屬虛偽，仍不能以此資為積極證據\n    應予採信之理由；認定犯罪事實應依證據，為刑事訴訟法所\n    明定，故被告否認犯罪事實所持之辯解，縱屬不能成立，仍\n    非有積極證據足以證明其犯罪行為，不能遽為有罪之認定（\n    最高法院三十年上字第四八二、一八三一號分別著有判例參\n    照）。\n四、訊據被告堅決否認有上開販賣第一級毒品海洛因與證人翁丁\n    元之犯行，辯稱：伊沒有販賣第一級毒品給翁丁元，97年8\n    月伊有去過中正飯店且不止三次，伊去那裡找朋友，伊沒有\n    碰到過翁丁元、有看過莊正和不止三次，因為莊正和到南部\n    來那一陣子曾經住在那裡，翁丁元當時在通緝中，不可能在\n    現場，莊正和說翁丁元在場是不實在的等語。\n五、經查：\n  (1)證人翁丁元於警詢時係供述：第 1 次於 97 年 4 月中旬大\n    概在中午12時左右在高雄市中正飯店508 號房內向甲○○購\n    買海洛因，另第2 次於97年4 月中旬中午12時左右也是在高\n    雄市中正飯店508 號房內向甲○○購買海洛因，第3 次是在\n    97 年4月中旬中午12時左右在高雄市中正飯店508 號房內向\n    甲○○購買海洛因。我連續3 天都是向甲○○購買的。第1\n    、2 、3 次都是以10000 元向甲○○購買海洛因。數量大約\n    每次1 公克左右，甲○○都是用1 小包夾鍊袋裝拿給我的。\n    我都是直接前往高雄市中正大飯店508 號房那裡找甲○○購\n    買海洛因。我前往高雄市中正飯店508 號房內現場有莊正和\n    。我認識莊正和，因為他是澎湖人與他認識很久了。我認識\n    甲○○是莊正和介紹的等語（見警2卷第11、12頁)。\n  (2)證人翁丁元於偵查中則具結證述：我於97年4 月有跟甲○○\n    買過海洛因，是在高雄市中正飯店跟甲○○買的，我都是白\n    天跟他買的，被告住在飯店，我都到飯店跟他買，前後我跟\n    他買過3 次，時間大約在97年4 月中到5 月，確定時間我無\n    法肯定，我每次都是買1 萬元，量是1 公克左右。我去買的\n    時候莊正和有在場。莊正和3 次都有在場，我是自己去遇到\n    莊正和的等語( 見偵2 卷第16頁) 。\n  (3)證人翁丁元於原審則具結證述：海洛因之來源有跟朋友拿，\n    也有跟朋友買，有的不知道名字，向甲○○購買海洛因。我\n    到飯店跟甲○○拿的，飯店名字忘記了，飯店在鹽埕區。我\n    約97年夏天跟被告拿毒品，我去跟甲○○說要拿1 萬元的東\n    西，我當時身上沒有錢，我告訴他說我有貸款一筆錢，等貸\n    款下來再給被告錢，當時被告有將東西拿給我。我知道甲○\n    ○住在那裡，我都是直接去飯店找被告。我跟被告拿2 、3\n    次毒品。我沒有當場交付錢給被告，我騙他說有筆貸款要下\n    來，每次都是這樣，被告說等貸款下來再一次拿錢，我去買\n    毒品，除了被告，還有莊正和在場等語（見原審2 卷第61至\n    63 頁)。\n  (4)審酌證人翁丁元之上開供證，其中究竟向被告購買2 次或\n    3 次海洛因毒品? 購買之時間是97年4 月至5 月間，抑97\n    年夏天，即7 月、8 月間? 購買毒品之金額每次1000元是\n    否有交付給被告?上開供述並非完全一致，已有瑕疵可指。\n  (5)再證人莊正和於97年12月15日警詢係供稱：翁丁元是跟我在\n    高雄市○○區○○路72-5號10樓高家祥家中時，因甲○○來\n    找我，翁丁元就向他購買毒品海洛因等語（見警2 卷第19頁\n    ) ，於97年12月30日警詢時則供述：翁丁元供稱在 97 年 4\n    月份左右在高雄市中正飯店508 號房內曾向甲○○購買3 次\n    海洛因，我3 次都有在場，我只知道他們在交易買賣海洛因\n    ，我3 次都有親眼目睹甲○○親自拿毒品1 小包（以夾鏈袋\n    包裝）給翁丁元，至於數量及金額我就不清楚了等語( 見警\n    2 卷第25頁) 。於98年3 月9 日偵查中則具結證稱：翁丁元\n    97年4 月來高雄向甲○○買海洛因時我沒有在場，97年4 月\n    我人在澎湖，我97年3 月20幾號剛交保出來，我有去高雄，\n    但是沒幾天我就回澎湖了，翁丁元跟甲○○拿海洛因的時間\n    不是4 月，是8 月，地點在高雄中正飯店，是翁丁元時間記\n    錯了，我當時人確實在那裡，但是他們做什麼我不清楚，我\n    不清楚翁丁元所說他拿了3 次1 萬元給甲○○這部分，我不\n    知道他們是什麼原因拿錢的。因我看到的是用夾鏈袋裝的，\n    裡面是白色的東西等語（見偵2 卷第18頁) 。於原審時則具\n    結供證稱：97年間我住在高雄市中正飯店508 號房。甲○○\n    有到我那邊，他都會在那裡休息，我沒有看到翁丁元在中正\n    飯店向甲○○購買毒品的事情等語（見原審2 卷第65頁)。\n  (6)觀證人莊正和上開供述，對於證人翁丁元向被告購買毒品之\n    地點，係高雄市○○區○○路72-5號10樓高家祥家中，抑高\n    雄市中正飯店508 號房內? 證人翁丁元購買之時間，係97年\n    4 月，抑97年8 月? 證人翁丁元究竟有無交付金額? 亦係前\n    後不一，反覆不定，滋生疑義，尚難佐證使一般人對於證人\n    翁丁元之前開供述無合理之懷疑，而得確信其為真實，換言\n    之，即難採為證人翁丁元前開供詞之補強證據。\n六、是證人翁丁元之前開供述，既有前開不一致之瑕疵，且上開\n    除證人翁丁元之指證外，並無其他確實佐證，難僅憑上開證\n    人翁丁元片面之證述，遽為不利被告之認定。\n七、至扣案之第一級毒品海洛因，僅足以證明被告有販賣第一級\n    毒品與證人高漢武之事實，亦不足證明被告有上開販賣第一\n    級毒品海洛因犯行。\n八、綜上所述，本件並無其他積極證據足證被告有上開販賣第一\n    級毒品與證人翁丁元3 次之事實，被告此部分犯行即屬不能\n    證明。原審疏未詳查，率認被告有上開3 次販賣第一級毒品\n    給證人翁丁元，而予論罪科刑，被告上訴意旨否認犯行，非\n    無理由，自應由本院將原判決關於此部分撤銷改判，並為被\n    告無罪之諭知。\n丙、至被告另犯轉讓第一級毒品，經原審處有期徒刑壹年貳月，\n    及犯轉讓第一級毒品，未遂，經原審處有期徒刑拾月，雖被\n    告曾提起上訴，惟已撤回確定在案，不予論列，併此敘明。\n據上論斷，應依刑事訴訟法第369 條第1 項前段、第364 條、第\n299 條第1 項前段、第301 條第1 項，修正前毒品危害防制條例\n第4 條第1項、第18條第1 項前段、第19條第1 項，刑法第11 條\n、第2 條第1 項前段、第59條、第37條第2 項，判決如主文。\n本案經檢察官姜麗儒到庭執行職務。\n中    華    民    國    99    年    5     月    12    日\n                 刑事第九庭     審判長法  官  莊秋桃\n                                      法  官  范惠瑩\n                                      法  官  田平安\n以上正本與原本無異。\n如不服本判決，應於判決送達後10日內向本院提出上訴狀，其未\n敘述理由者，並應於提出上訴狀後10日內向本院補提上訴理由狀\n（應附繕本）。\n中    華    民    國    99    年    5     月    12    日\n                                  書  記  官  張宗芳\n附錄本件判決論罪科刑法條：\n修正前毒品危害防制條例第4條\n製造、運輸、販賣第一級毒品者，處死刑或無期徒刑；處無期徒\n刑者，得併科新臺幣1 千萬元以下罰金。\n製造、運輸、販賣第二級毒品者，處無期徒刑或7 年以上有期徒\n刑，得併科新臺幣7百萬元以下罰金。\n附表一：（被告販賣海洛因）\n┌──┬───┬────┬────┬────────┬───┬──────┬───┐\n│編號│行為人│行為時間│行為地點│行為經過（新台幣│罪數  │罪名及宣告刑│ 備註 │\n│    │      │        │        │，下同）        │      │            │      │\n├──┼───┼────┼────┼────────┼───┼──────┼───┤\n│    │      │        │        │                │      │            │      │\n│1   │同上  │97年12月│高雄市三│甲○○以營利為目│1 次  │甲○○販賣第│      │\n│    │      │6 日17時│民區裕誠│的，以其手機門號│      │一級毒品，處│      │\n│    │      │許      │路72之5 │與高漢武手機門號│      │有期徒刑15年│      │\n│    │      │        │號10樓「│聯絡，販賣價格4 │      │6 月，褫奪公│      │\n│    │      │        │高家祥住│千元之海洛因1 包│      │權4 年。    │      │\n│    │      │        │處」樓下│予高漢武（另案查│      │            │      │\n│    │      │        │        │扣）。          │      │            │      │\n│    │      │        │        │                │      │            │      │\n└──┴───┴────┴────┴────────┴───┴──────┴───┘\n 附表二：（扣案之物品）\n┌──┬────────┬───┬──────┬──────┐\n│編號│名稱、驗後淨重、│數  量│  檢驗結果  │ 備  註     │\n│    │新台幣（下同）  │      │            │（沒收）    │\n├──┼────────┼───┼──────┼──────┤\n│ 1  │海洛因（合計淨重│ 2包  │檢出第一級毒│依毒品危害防│\n│    │1.80公克，空包裝│      │品海洛因成分│制條例第18條│\n│    │總重2.93公克，即│      │            │第1 項前段，│\n│    │檢驗編號第2 、3 │      │            │沒收銷燬之  │\n│    │包）            │      │            │            │\n├──┼────────┼───┼──────┼──────┤\n│ 2  │甲基安非他命（其│ 3包  │檢出第二級毒│與被告販賣第│\n│    │中1 包驗前淨重0.│      │品甲基安非他│一級毒品無涉│\n│    │119 公克，驗後淨│      │命成分      │，不予宣告沒│\n│    │重0.110 公克；1 │      │            │收銷燬之。  │\n│    │包驗前淨重0.687 │      │            │            │\n│    │公克，驗後淨重1.│      │            │            │\n│    │678 公克；1 包驗│      │            │            │\n│    │前淨重0.715 公克│      │            │            │\n│    │，驗後淨重0.706 │      │            │            │\n│    │公克）          │      │            │            │\n├──┼────────┼───┼──────┼──────┤\n│ 3  │香菸（峰牌）（內│ 1支  │            │與被告販賣第│\n│    │摻入海洛因）    │      │            │一級毒品無涉│\n│    │                │      │            │，不予宣告沒│\n│    │                │      │            │收銷燬之。  │\n├──┼────────┼───┼──────┼──────┤\n│ 4  │電子磅秤        │ 1台  │            │依毒品危害防│\n│    │                │      │            │制條例第19條│\n│    │                │      │            │第1項，沒收 │\n├──┼────────┼───┼──────┼──────┤\n│ 5  │行動電話（含門號│ 1支  │            │同上        │\n│    │0000000000之SIM │      │            │            │\n│    │卡1張）         │      │            │            │\n│    │                │      │            │            │\n├──┼────────┼───┼──────┼──────┤\n│ 6  │帳單（記事本）  │ 1本  │            │與被告販賣第│\n│    │                │      │            │一級毒品無涉│\n│    │                │      │            │，不予宣告沒│\n│    │                │      │            │收之。      │\n├──┼────────┼───┼──────┼──────┤\n│ 7  │吸管分裝具      │ 5支  │            │同上        │\n├──┼────────┼───┼──────┼──────┤\n│ 8  │分裝盒（內有分裝│ 1組  │            │同上        │\n│    │吸管小湯匙）    │      │            │            │\n├──┼────────┼───┼──────┼──────┤\n│ 9  │剪刀（用以剪吸管│ 1把  │            │同上        │\n│    │分裝具、分裝盒）│      │            │            │\n├──┼────────┼───┼──────┼──────┤\n│ 10 │空夾鏈袋        │ 206個│            │依毒品危害防│\n│    │                │      │            │制條例第19條│\n│    │                │      │            │第1項，沒收 │\n├──┼────────┼───┼──────┼──────┤\n│    │                │      │            │            │\n│ 11 │現金3萬6千元    │      │與本案犯罪無│不予沒收    │\n│    │                │      │關          │            │\n├──┼────────┼───┼──────┼──────┤\n│ 12 │第三級毒品愷他命│ 1包  │檢出凱他命成│不於本案宣告│\n│    │                │      │分          │沒收        │\n├──┼────────┼───┼──────┼──────┤\n│ 13 │白色粉末（淨重  │ 1包  │無法定毒品成│不予沒收    │\n│    │1.36公克，空包裝│      │分          │            │\n│    │重0.19公克）    │      │            │            │\n├──┼────────┼───┼──────┼──────┤\n│ 14 │行動電話        │ 2支  │非被告所有之│不予沒收    │\n│    │                │      │物          │            │\n├──┼────────┼───┼──────┼──────┤\n│ 15 │小皮包          │ 1個  │與本件犯罪無│不予沒收    │\n│    │                │      │關          │            │\n├──┼────────┼───┼──────┼──────┤\n│ 16 │鋁箔紙          │1張   │同上        │不於本案宣告│\n│    │                │      │            │沒收        │\n├──┼────────┼───┼──────┼──────┤\n│ 17 │海洛因（驗前淨重│1包   │檢出第一級毒│與被告販賣第│\n│    │0.106 公克，驗後│      │品海洛因成分│一級毒品無涉│\n│    │淨重0.097 公克）│      │            │，不予宣告沒│\n│    │（高漢武返回澎湖│      │            │收銷燬之。  │\n│    │交由警方查扣）  │      │            │            │\n└──┴────────┴───┴──────┴──────┘",
  "structure": {
    "main": "原判決關於甲○○販賣第一級毒品四罪部分及定執行刑部分撤銷\n。\n甲○○販賣附表一所示第一級毒品，處有期徒刑拾伍年陸月，褫\n奪公權肆年。扣案如附表二編號1 所示之物，沒收銷燬之，編號\n4 、5 、10所示之物，均沒收；未扣案之販賣毒品所得新臺幣肆\n仟元沒收之，如全部或一部不能沒收時，以其財產抵償之。\n甲○○其他被訴販賣第一級毒品參罪部分均無罪。",
    "fact": "一、甲○○（綽號「阿達」、「達仔」）明知海洛因係毒品危害\n    防制條例第2 條第2 項第1 款所列之第一級毒品，不得持有\n    、販賣或轉讓，竟意圖牟利，基於販賣第一級毒品海洛因之\n    犯意，以其申辦使用之手機門號0000000000、及其父李坤旺\n    申辦0000000000等門號為聯絡工具，為以下之販賣海洛因行\n    為，即於97年12月6 日17時許，高漢武搭乘立榮航空股份有\n    限公司（下稱「立榮航空」）班機自澎湖馬公機場出發，抵\n    達位於高雄市小港區之高雄國際航空站（下稱小港機場）後\n    ，以其上開手機門號聯絡甲○○，並搭計程車至高雄市○○\n    區○○路72之5 號10樓高家祥住處大樓1 樓之「萊爾富超商\n    」（下稱「高家祥住處樓下」），由甲○○以新台幣( 下同\n    )4,000元之價格，販售予高漢武海洛因1 包（毛重約0.6 公\n    克）。嗣於同（6 ）日18時15分，高漢武復搭「立榮航空」\n    班機返抵澎湖時，在馬公機場為警查獲，並扣得高漢武藏在\n    其運動鞋鞋墊內之海洛因1 包（驗前淨重0.106 公克，驗後\n    淨重0.097 公克，於其施用毒品案中）。嗣於97年12月8日\n    凌晨零時30分許，澎湖縣政府警察局經徵得高家祥之同意，\n    在其上開住處執行搜索，查獲甲○○，並扣得甲○○所有如\n    附表二所示之海洛因2 小包（合計淨重1.8 公克）、甲基安\n    非他命3 小包（分別淨重0.119 、0.687 、0.706 公克）、\n    香菸（峰牌）1 支、電子磅秤1 台、行動電話SIM 卡3 張、\n    帳單（記事本）1 冊、吸管分裝具5 支、分裝盒1 組（內有\n    分裝吸管小湯匙）、剪刀1 把、夾鍊袋206 個、鋁箔紙1張\n    ，小皮包1 個（內有3 萬6 千元) 等物。\n二、案經澎湖縣政府警察局移送臺灣高雄地方法院檢察署檢察官\n    偵查起訴。",
    "reason": "甲、有罪部分：\n壹、證據能力部分：\n一、按被告以外之人於審判外之言詞或書面陳述，除法律有規定\n    者外，不得作為證據，刑事訴訟法第159 條第1 項有明文。\n    本件證人高漢武於警詢中之陳述為審判外之陳述，且查無合\n    於同法第159 條之1 至第159 條之5 例外規定情形，且被告\n    之辯護人於本院中爭執其證據能力，依同法第159 條第1項\n    規定，證人高漢武於警詢中之陳述對被告即無證據能力。\n二、次按被告以外之人於審判外之陳述，雖不符前四條之規定，\n    而經當事人於審判程序同意作為證據，法院審酌該言詞陳述\n    或書面陳述作成時之情況，認為適當者，亦得為證據，刑事\n    訴訟法第159 條之5 第1 項定有明文。本件被告及其辯護人\n    於本院準備程序時，已表示除上開爭執證據能力之陳述證據\n    外，對下列所引證據屬被告以外之人在審判外陳述之傳聞證\n    據部分，均同意作為證據( 見本院卷第71頁) 。本院斟酌上\n    開證據並無違法取得之情事，亦無證明力明顯過低之情形，\n    認為作為本件被告認定犯罪有無之證據亦屬適當，是均得採\n    為本件論斷之證據。\n貳、實體部分：\n一、訊據被告矢口否認有何販賣第一級毒品海洛因與高漢武，於\n    原審及本院均辯稱：伊沒有販賣第一級毒品海洛因給高漢武\n    ，那天我們也沒有聯絡，伊也沒有去萊爾富或是高家祥的住\n    處，高家祥伊也是透過莊正和認識的，高漢武也是。97年12\n    月6 日伊沒有見到高漢武，他被查獲的海洛因不是伊賣他的\n    等語。\n二、證人高漢武於原審審理時具結證稱：（你在98年3 月26 日\n    偵訊時說「達仔就是甲○○」是否有這樣說？）有，達仔就\n    是甲○○；（這2 次查獲毒品海洛因都是達仔即甲○○賣給\n    你？）是；（案發時你的手機0000000000號、000000 0000\n    號都是你所有？）是；（你在97年12月6 日回澎湖時，在馬\n    公機場鞋子裡面查扣到1 包海洛因？）是；（這包海洛因跟\n    何人購買？）達仔；（是否就是剛才在場的被告甲○○？）\n    是等語明確（見原審2 卷第87正反、88反頁）；且於偵訊時\n    具結證稱：伊於97年12月6 日當天坐飛機到高雄，是在「高\n    家祥住處」買的，這次用4 千元買到1 包海洛因（約重0.6\n    公克），「達仔」就是甲○○，他跟高家祥住在一起，伊是\n    透過莊正和認識等語明確（見偵1 卷第36頁），前後參核相\n    符。此外，並有「立榮航空」98年6 月11日立航字第200903\n    93號函附來回旅客艙單（編號B7 -6168、6269），及證人高\n    漢武所持用門號0000000000、0000000000、0000000000，與\n    被告持用門號0000000000、0000000000手機雙向通聯紀錄各\n    1 份在卷可稽，亦比對相符（見偵1 卷第6 、7 、12至29、\n    50至59、65至68頁）。況且，證人高漢武因此查獲海洛因1\n    包（毛重0.6 公克），其施用第一級毒品犯行，業經檢察官\n    起訴，並經台灣澎湖地方法院98年度訴字第15號判決判處有\n    期徒刑8 月確定（98年9 月15日入監執行）等情，亦有上開\n    起訴書、判決書及台灣高等法院被告前案紀錄表在卷足參（\n    見原審2 卷第112 至120 頁) 。從而，被告有販賣海洛因1\n    次給證人高漢武之犯行，已屬明顯。\n三、雖證人高漢武於原審審理時先證稱：伊這2 次海洛因都是跟\n    人家買的，不一定，時間地點都不固定，1 次都買2 千元云\n    云（見原審2 卷第85反、86正頁）；然其同時具結證稱：達\n    仔就是被告甲○○，（12月6 日海洛因是在何處跟甲○○拿\n    的？）民族大樂後面那1 條路，就是高家祥他家樓下的「萊\n    爾富超商」買的，伊當時沒有上去；（12月6 日購買多少毒\n    品？）4 千元等語明確（見原審2 卷第88反頁）。此外，並\n    有證人高漢武持用手機，與被告持用手機雙向通聯紀錄在卷\n    ，如前所述。是證人高漢武上開證述之實在性，足堪印證：\n    證人高漢武上開翻異之詞，仍不足為被告有利之認定，被告\n    上開所辯，尚無從採取。\n四、再警方欲查出上開毒品上游，徵得證人高漢武之同意配合，\n    於97年12月7 日17時30分，由證人高漢武復搭乘復興航空運\n    輸股份有限公司（下稱「復興航空」）班機自澎湖馬公機場\n    出發，抵達小港機場後，以其手機門號0000000000、000000\n    0000，撥打甲○○手機門號00000000 00 ，向其稱：欲購買\n    毒品等情，嗣被告甲○○駕駛車號WQ-7631 白色自小客車搭\n    載莊正和前來，於同（7 ）日17時30分，開至在小港機場大\n    門外省道台17線公路南向外側快車道上（靠對面高雄公園側\n    ）停車，證人高漢武站於該快、慢車道分隔島上等候，隨即\n    提出2 千元還給甲○○，被告甲○○亦有交付海洛因1 包證\n    人高漢武等情( 此部分業經原審以被告甲○○係轉讓第一級\n    毒品未遂罪，判決有期徒刑8 月，被告甲○○上訴後，撤回\n    上訴，業已確定在案) ，亦據證人證人高漢武於偵查及原審\n    證述在卷( 見偵1 卷第36頁、原審2 卷第88頁) ，並經證人\n    莊正和於偵訊時具結證稱：當天係被告甲○○開車，伊坐在\n    副駕駛座，一起到高雄機場，伊有看到甲○○拿1 包白色東\n    西給高漢武等語屬實（見偵2 卷第17頁），並有「復興航空\n    」98年6 月29日地服字第98-140號函附搭乘紀錄艙單（編號\n    GE-0 219）在卷可稽（見偵1 卷第63、64頁）亦堪認定；是\n    依上情相互參酌，及證人高漢武復搭「立榮航空」班機返抵\n    澎湖時，在馬公機場為警查獲，並扣得證人高漢武藏在其運\n    動鞋鞋墊內之海洛因1 包後，配合澎湖縣政府警察局查獲被\n    告甲○○等情以觀，亦可印證被告甲○○確有前開販賣第一\n    級毒品給證人高漢武之事實。\n五、販賣毒品係政府嚴予查緝之違法行為，且毒品可任意分裝或\n    增減其份量，而每次買賣之價量，亦隨時依雙方關係之深淺\n    、當時之資力、需求程度及對行情之認知等因素，機動調整\n    ，因之販賣之利得，除經被告坦承犯行，或帳冊價量均記載\n    明確外，委難查得實情，是縱未確切查得販賣賺取之實際差\n    價，但除別有事證，足認係按同一價格轉讓，確未牟利之情\n    形外，尚難執此認非法販賣之事證有所不足，致知過坦承者\n    難辭重典，飾詞否認者反得逞僥倖，而失情理之平；且為販\n    賣毒品之不法行為者，苟無利可圖，應無甘冒持有毒品遭查\n    獲之極大風險，從事此買賣工作，是其販入之價格必較售出\n    之價格低廉，而有從中賺取買賣差價牟利之意圖及事實，應\n    屬符合論理法則而不違背社會通常經驗之合理判斷，從而被\n    告上開出售第一級毒品與證人高漢武之交易，具有營利之意\n    圖，亦堪認定。\n六、綜上所述，被告甲○○確定上開時地，以4000元價格販賣第\n    一級毒品1 包與證人高漢武之犯行，事證明確，堪以認定。\n七、按行為後法律有變更者，適用行為時之法律。但行為後之法\n    律有利於行為人者，適用最有利於行為人之法律，刑法第2\n    條第1 項定有明文。查本件被告行為後，有關論罪科刑所適\n    用之毒品危害防制條例，其中部分條文業於98年5 月20日修\n    正公布，98年5 月22日起施行，本件被告犯罪後，毒品危害\n    防制條例第4 條已有修正，修正後同條例第4 條第1 項規定\n    ：「製造、運輸、販賣第一級毒品者，處死刑、無期徒刑；\n    處無期徒刑者，得併科新臺幣2 千萬元以下罰金。」而就併\n    科罰金刑部分，與修正前之規定「得併科新臺幣1 千萬元以\n    下罰金。」相較，修正前最高金額為1 千萬元，而修正後則\n    係2 千萬元，以修正前之規定有利於被告。自應適用修正前\n    毒品危害防制條例第4 條第1 項之規定。\n八、核上開所為，係犯修正前毒品危害防制條例第4條 第1 項之\n    販賣第一級毒品罪；被告持有第一級毒品海洛因之低度行為\n    ，為販賣之高度行為所吸收，不另論罪。\n九、又本院復審酌被告販賣第一級毒品法定本刑為「死刑、無期\n    徒刑」，又販賣第一級毒品固屬應嚴加處罰之重大犯罪，然\n    同為販賣第一級毒品之人，其原因動機不一，犯罪情節未必\n    盡同，或有大盤毒梟者，亦有中、小盤之分，甚或僅止於吸\n    毒者同儕間為求互通有無之有償轉讓者亦有之，其販賣行為\n    所造成危害社會之程度自屬有異，法律科處此類犯罪所設之\n    法定最低本刑卻同為無期徒刑，不可謂為不重。而查被告販\n    賣之對象為證人高漢武1 人，且販毒所得僅4 千元，交易金\n    額尚輕，堪認應非大盤毒梟，犯罪情節尚難與大盤或中盤毒\n    梟者相提併論，本院即令處以被告最低刑度即無期徒刑而禁\n    錮終身，仍有致情法失平之處，誠屬情輕法重，其犯罪情狀\n    尚非全然無可憫恕之處，爰依刑法第59條規定，就販賣第一\n    級毒品罪酌減輕其刑。\n十、原審對被告上開部分，予以論罪科刑，固非無見。惟查( 一\n    ) 認定犯罪事實之證據，其判斷必須合理，否則即欠缺妥當\n    性。查扣案之附表二編號11之現金3 萬6000元，被告辯以上\n    開金額係買車的錢等語（見警1 卷第9 頁、本院卷第96頁)\n    ，詎原審在無證據證明上開現金與本件販賣毒品有關之下，\n    遽以上開3 萬6000元扣除本件之4000元，自依同條例第19條\n    第1 項規定，宣告沒收，至於所剩3 萬2000 元 始認定無證\n    據證明為犯本罪所得之財物，不予宣告沒收，自有所不當。\n     (二) 附表編號3 之香菸( 峰牌，內摻入海洛因)1支，係被\n    告於查獲當日正要施用，即為警查獲，業據被告甲○○於本\n    院審理時供明在卷( 見本院卷第99頁) ，核與本件販賣第一\n    級毒品無涉，原審予以沒收銷燬，亦有未合。( 三) 附表編\n    號6 之記事本一冊，則係被告甲○○記載之日日會，有關人\n    家欠其錢之記錄，亦據被告甲○○供明在卷( 見本院卷第97\n    頁) ，且觀記事本之內容，亦係記載Y 瑞借23000 、Y 茹借\n    10000 、小君借600 、五甲佑借2 萬、小凱借1 萬2 千等情\n    ，亦核與販賣第一級毒品無關，原審依毒品危害防制條例第\n    19條第1 項規定，併應宣告均沒收，自有不當。雖被告就上\n    開販賣第一級毒品部分，否認犯罪，指摘原判決不當，雖無\n    理由，惟原判決既有上開可議之處，自屬無可維持，應由本\n    院就原判決此部分及定執行刑併予撤銷。\n十一、爰審酌被告意圖牟利，販賣第一級毒品，嚴重違反我國法律\n    反毒、禁毒之政策，影響社會安全秩序甚鉅，更荼毒國人身\n    心健康，犯後否認犯行，惟考量被告販賣證人高漢武僅一次\n    ；尚非販賣毒品之大盤商，販賣時間亦不長等一切情狀，乃\n    量處如主文即附表一所示之刑，另就被告所犯販賣第一級毒\n    品罪之犯罪性質，嚴重侵害國家及社會法益，認有禠奪公權\n    之必要，併宣告禠奪公權4 年。\n十二、按查獲之第一級毒品及專供製造或施用第一級毒品之器具，\n    不問屬於犯人與否，均沒收銷燬之，毒品危害防制條例第18\n    條第1 項前段定有明文。扣案如附表二編號1 之海洛因2 包\n    （即檢驗編號第2 、3 包，合計淨重1.80公克），經檢驗確\n    屬第一級毒品；是依毒品危害防制條例第18條第1 項前段之\n    規定，併諭知均沒收銷燬之。因檢驗所耗用之上開毒品既已\n    滅失，不另為沒收銷燬之諭知。\n十三、按毒品危害防制條例第19條第1 項關於沒收之規定，係採義\n    務沒收主義，犯同條例第4 條至第9 條、第12條、第13條或\n    第14條第1 項、第2 項之罪者，其供犯罪所用之物或因犯罪\n    所得之財物，且屬犯人所有者，即應依該規定沒收，法院無\n    審酌之餘地，並不以專供犯罪所用之物為限（最高法院93年\n    度臺上字第1360號、第1365號、92年度臺上字第2608號判決\n    意旨參照），且犯同條例第4 條之罪者，其供犯罪所用或因\n    犯罪所得之財物應予沒收，如全部或一部不能沒收時，追徵\n    其價額或以其財產抵償之，該條例第19條第1 項規定甚明，\n    如所得財物為金錢而無法沒收時，應以其財產抵償之（最高\n    法院95年度臺上字第305 號判決意旨參照）。據此，被告販\n    賣第一級毒品所得財物4000元，因未扣案，除應依毒品危害\n    防制條例第19條第1 項規定分別宣告沒收之，並諭知如全部\n    或一部不能沒收時，以其財產抵償之。另扣案如附表二編號\n    4 、5 、10之電子磅秤1 台、行動電話1 支含門號00000000\n    00之SIM 卡1 張）、及夾鍊袋206 個，均為被告所有，業據\n    被告供明在卷，且核係供其分裝毒品海洛因之用，是依毒品\n    危害防制條例第19條第1 項規定，併應宣告均沒收。至於扣\n    案附表二編號11之現金3 萬6000元，被告辯稱係買車的錢，\n    如前所述，又無積極證據足以證明與本件販賣毒品有關，已\n    如前述，自不予逕行宣告沒收。另有關附表編號17之海洛因\n    1 包，業已販賣給證人高漢武，經證人高漢武交與澎湖警方\n    ，此部分已在證人高漢武經臺灣澎湖地方法院對證人高漢武\n    施用毒品之判決下諭知沒收在案( 見原審2 卷第117 頁) ，\n    自不予在本件被告販賣毒品之判決主刑下為之。\n十四、其餘扣案之物品，其中附表二編號2 部分，則屬甲基安非他\n    命3 包（其中1 包驗前淨重0.119 公克，驗後淨重0.110 公\n    克；1 包驗前淨重0.687 公克，驗後淨重0.678 公克；1 包\n    驗前淨重0.715 公克，驗後淨重0.706 公克），編號3 之香\n    菸( 峰牌，內摻入海洛因)1支，係其施用第一級毒品所用之\n    物，編號7 之吸管分裝具5 支、編號8 之分裝盒（內有分裝\n    吸管小湯匙）1 組、編號9 之剪刀（剪吸管分裝具）1 把，\n    均屬施用毒品之工具，編號6 之記事本一冊，則係被告甲○\n    ○記載之日日會，有關人家欠其錢之記錄，如前所述，另如\n    附表二編號14之行動電話2 支，係他人名義申辦，其中一支\n    0000000000號，其聲請人為案外人李坤旺，並非被告所有之\n    物；編號13之白色粉末第1 包（淨重1.36公克，空包裝重0.\n    19公克），並未檢出法定毒品成分；編號15、16之小皮包1\n    個、鋁箔紙1 張，不能證明係本件被告犯罪所得或供其犯罪\n    所用之物，及編號12之白色晶體1 包，雖經檢出為愷他命成\n    分（驗後淨重0.546 公克），屬第三級毒品，上開均與本件\n    被告所犯販毒第一級毒品罪無關，不予宣告沒收銷燬及沒收\n    之。\n乙、無罪部分：\n一、公訴意旨另以：被告甲○○於97年8 月下旬（20日至30日間\n    ）某日，在高雄市○○區○○路之「中正飯店」508 號房內\n    （下稱「中正飯店」），先後3 次，均1 萬元之價格，販售\n    數量不詳海洛因（毛重約1 公克）予翁丁元，因認此部分亦\n    涉犯毒品危害防制條例第4 條第1 項之販賣第一級毒品罪嫌\n    云云。\n二、公訴人認被告此部分亦涉犯上開罪嫌，無非以(1)被告甲○○\n    於警詢及偵查中之供述。(2)證人翁丁元於警詢及偵查中之證\n    述。(3)證人莊正和於警詢及偵查中之證述(4)本件扣案之海洛\n    因等為主要之論據。\n三、按犯罪事實應依證據認定之，無證據不得認定犯罪事實；又\n    不能證明被告犯罪者，應諭知無罪之判決，刑事訴訟法第一\n    百五十四條第二項、第三百零一條第一項分別定有規定。認\n    定不利於被告之事實，須依積極證據，苟積極證據不足為不\n    利於被告事實之認定時，即應為有利於被告之認定，更不必\n    有何有利之證據。此之所謂證據，須確屬能為被告有罪之證\n    明，而無瑕疵可指者，始足當之；再者，犯罪事實之認定，\n    應憑證據，所謂證據，須適於為被告犯罪事實之證明者，始\n    得採為斷罪資料，如未能發現相當證據，或證據不足以證明\n    ，自不能以推測或擬制之方法以為裁判基礎；又所謂認定犯\n    罪事實所憑之證據，雖不以直接證據為限，間接證據亦包括\n    在內，然而無論直接或間接證據，其為訴訟上之證明，須於\n    通常一般人均不致有所懷疑，而得確信其為真實之程度，始\n    得據之為有罪之認定，倘其證明尚未達到此一程度，而有合\n    理懷疑存在時，即應為無罪之判決（最高法院二十九年上字\n    第三一○五號、三十年上字第八一六號、四十年台上字第八\n    六號、五十三年台上字第二七五○號、七十六年台上字第四\n    九八六號分別著有判例參照）。復事實審法院對於證據之取\n    捨，依法雖有自由判斷之權，然積極證據不足證明犯罪事實\n    時，被告之抗辯或反證縱屬虛偽，仍不能以此資為積極證據\n    應予採信之理由；認定犯罪事實應依證據，為刑事訴訟法所\n    明定，故被告否認犯罪事實所持之辯解，縱屬不能成立，仍\n    非有積極證據足以證明其犯罪行為，不能遽為有罪之認定（\n    最高法院三十年上字第四八二、一八三一號分別著有判例參\n    照）。\n四、訊據被告堅決否認有上開販賣第一級毒品海洛因與證人翁丁\n    元之犯行，辯稱：伊沒有販賣第一級毒品給翁丁元，97年8\n    月伊有去過中正飯店且不止三次，伊去那裡找朋友，伊沒有\n    碰到過翁丁元、有看過莊正和不止三次，因為莊正和到南部\n    來那一陣子曾經住在那裡，翁丁元當時在通緝中，不可能在\n    現場，莊正和說翁丁元在場是不實在的等語。\n五、經查：\n  (1)證人翁丁元於警詢時係供述：第 1 次於 97 年 4 月中旬大\n    概在中午12時左右在高雄市中正飯店508 號房內向甲○○購\n    買海洛因，另第2 次於97年4 月中旬中午12時左右也是在高\n    雄市中正飯店508 號房內向甲○○購買海洛因，第3 次是在\n    97 年4月中旬中午12時左右在高雄市中正飯店508 號房內向\n    甲○○購買海洛因。我連續3 天都是向甲○○購買的。第1\n    、2 、3 次都是以10000 元向甲○○購買海洛因。數量大約\n    每次1 公克左右，甲○○都是用1 小包夾鍊袋裝拿給我的。\n    我都是直接前往高雄市中正大飯店508 號房那裡找甲○○購\n    買海洛因。我前往高雄市中正飯店508 號房內現場有莊正和\n    。我認識莊正和，因為他是澎湖人與他認識很久了。我認識\n    甲○○是莊正和介紹的等語（見警2卷第11、12頁)。\n  (2)證人翁丁元於偵查中則具結證述：我於97年4 月有跟甲○○\n    買過海洛因，是在高雄市中正飯店跟甲○○買的，我都是白\n    天跟他買的，被告住在飯店，我都到飯店跟他買，前後我跟\n    他買過3 次，時間大約在97年4 月中到5 月，確定時間我無\n    法肯定，我每次都是買1 萬元，量是1 公克左右。我去買的\n    時候莊正和有在場。莊正和3 次都有在場，我是自己去遇到\n    莊正和的等語( 見偵2 卷第16頁) 。\n  (3)證人翁丁元於原審則具結證述：海洛因之來源有跟朋友拿，\n    也有跟朋友買，有的不知道名字，向甲○○購買海洛因。我\n    到飯店跟甲○○拿的，飯店名字忘記了，飯店在鹽埕區。我\n    約97年夏天跟被告拿毒品，我去跟甲○○說要拿1 萬元的東\n    西，我當時身上沒有錢，我告訴他說我有貸款一筆錢，等貸\n    款下來再給被告錢，當時被告有將東西拿給我。我知道甲○\n    ○住在那裡，我都是直接去飯店找被告。我跟被告拿2 、3\n    次毒品。我沒有當場交付錢給被告，我騙他說有筆貸款要下\n    來，每次都是這樣，被告說等貸款下來再一次拿錢，我去買\n    毒品，除了被告，還有莊正和在場等語（見原審2 卷第61至\n    63 頁)。\n  (4)審酌證人翁丁元之上開供證，其中究竟向被告購買2 次或\n    3 次海洛因毒品? 購買之時間是97年4 月至5 月間，抑97\n    年夏天，即7 月、8 月間? 購買毒品之金額每次1000元是\n    否有交付給被告?上開供述並非完全一致，已有瑕疵可指。\n  (5)再證人莊正和於97年12月15日警詢係供稱：翁丁元是跟我在\n    高雄市○○區○○路72-5號10樓高家祥家中時，因甲○○來\n    找我，翁丁元就向他購買毒品海洛因等語（見警2 卷第19頁\n    ) ，於97年12月30日警詢時則供述：翁丁元供稱在 97 年 4\n    月份左右在高雄市中正飯店508 號房內曾向甲○○購買3 次\n    海洛因，我3 次都有在場，我只知道他們在交易買賣海洛因\n    ，我3 次都有親眼目睹甲○○親自拿毒品1 小包（以夾鏈袋\n    包裝）給翁丁元，至於數量及金額我就不清楚了等語( 見警\n    2 卷第25頁) 。於98年3 月9 日偵查中則具結證稱：翁丁元\n    97年4 月來高雄向甲○○買海洛因時我沒有在場，97年4 月\n    我人在澎湖，我97年3 月20幾號剛交保出來，我有去高雄，\n    但是沒幾天我就回澎湖了，翁丁元跟甲○○拿海洛因的時間\n    不是4 月，是8 月，地點在高雄中正飯店，是翁丁元時間記\n    錯了，我當時人確實在那裡，但是他們做什麼我不清楚，我\n    不清楚翁丁元所說他拿了3 次1 萬元給甲○○這部分，我不\n    知道他們是什麼原因拿錢的。因我看到的是用夾鏈袋裝的，\n    裡面是白色的東西等語（見偵2 卷第18頁) 。於原審時則具\n    結供證稱：97年間我住在高雄市中正飯店508 號房。甲○○\n    有到我那邊，他都會在那裡休息，我沒有看到翁丁元在中正\n    飯店向甲○○購買毒品的事情等語（見原審2 卷第65頁)。\n  (6)觀證人莊正和上開供述，對於證人翁丁元向被告購買毒品之\n    地點，係高雄市○○區○○路72-5號10樓高家祥家中，抑高\n    雄市中正飯店508 號房內? 證人翁丁元購買之時間，係97年\n    4 月，抑97年8 月? 證人翁丁元究竟有無交付金額? 亦係前\n    後不一，反覆不定，滋生疑義，尚難佐證使一般人對於證人\n    翁丁元之前開供述無合理之懷疑，而得確信其為真實，換言\n    之，即難採為證人翁丁元前開供詞之補強證據。\n六、是證人翁丁元之前開供述，既有前開不一致之瑕疵，且上開\n    除證人翁丁元之指證外，並無其他確實佐證，難僅憑上開證\n    人翁丁元片面之證述，遽為不利被告之認定。\n七、至扣案之第一級毒品海洛因，僅足以證明被告有販賣第一級\n    毒品與證人高漢武之事實，亦不足證明被告有上開販賣第一\n    級毒品海洛因犯行。\n八、綜上所述，本件並無其他積極證據足證被告有上開販賣第一\n    級毒品與證人翁丁元3 次之事實，被告此部分犯行即屬不能\n    證明。原審疏未詳查，率認被告有上開3 次販賣第一級毒品\n    給證人翁丁元，而予論罪科刑，被告上訴意旨否認犯行，非\n    無理由，自應由本院將原判決關於此部分撤銷改判，並為被\n    告無罪之諭知。\n丙、至被告另犯轉讓第一級毒品，經原審處有期徒刑壹年貳月，\n    及犯轉讓第一級毒品，未遂，經原審處有期徒刑拾月，雖被\n    告曾提起上訴，惟已撤回確定在案，不予論列，併此敘明。\n據上論斷，應依刑事訴訟法第369 條第1 項前段、第364 條、第\n299 條第1 項前段、第301 條第1 項，修正前毒品危害防制條例\n第4 條第1項、第18條第1 項前段、第19條第1 項，刑法第11 條\n、第2 條第1 項前段、第59條、第37條第2 項，判決如主文。\n本案經檢察官姜麗儒到庭執行職務。\n中    華    民    國    99    年    5     月    12    日\n                 刑事第九庭     審判長法  官  莊秋桃\n                                      法  官  范惠瑩\n                                      法  官  田平安\n以上正本與原本無異。\n如不服本判決，應於判決送達後10日內向本院提出上訴狀，其未\n敘述理由者，並應於提出上訴狀後10日內向本院補提上訴理由狀\n（應附繕本）。"
  },
  "characters": {
    "judges": [
      "莊秋桃",
      "范惠瑩",
      "田平安"
    ],
    "prosecutors": [
      "姜麗儒"
    ],
    "lawyers": [
      "陳煜昇",
      "張永昌"
    ],
    "clerks": [

    ],
    "plaintiffs": [

    ],
    "defendants": [
      "甲"
    ],
    "prosecutor_office": [

    ],
    "creditors": [

    ],
    "debtors": [

    ],
    "judicial_associate_officer": [

    ]
  },
  "adjudged_at": "2010-05-12",
  "created_at": "2016-01-05 12:03:13",
  "updated_at": "2016-01-05 12:03:13"
}