{
  "identify": "KSH-98-附民-109-20100105-1",
  "court": {
    "name": "臺灣高等法院",
    "code": "KSH"
  },
  "division": {
    "name": "刑事",
    "code": "M"
  },
  "year": 98,
  "word": "附民",
  "number": "109",
  "jcheck": "1",
  "reason": "損害賠償",
  "content": "臺灣高等法院高雄分院刑事附帶民事訴訟判決\n原      告  Ａ女    （住址年籍資料詳卷）\n兼  法  定  Ａ母    （住址年籍資料詳卷）\n代  理  人\n共同送達代收人      林朋助律師（住屏東新復興路468號）\n被      告  甲○○\n上列被告因損害賠償案件（本院刑事案號：98年度上訴字第1538\n號），原告提起附帶民事訴訟，請求損害賠償，本院判決如下：\n    主  文\n原告之訴駁回。\n    事  實\n甲、原告方面：\n    聲明：被告應給付原告Ａ女新臺幣（下同）50萬元，應給付\n    原告Ａ母25萬元，及均自起訴狀繕本送達被告翌日起至清償\n    日止，按年息百分之五計算之利息。\n    陳述略以：被告係Ａ女就讀甲中學之數學老師，其卻利用擔\n    任課後輔導Ａ女數學課業機會，於97年1 月25日在高雄市美\n    術館及同年3 月9 日在中央公園，分別對Ａ女強制猥褻得逞\n    。為此依民法侵權行為之規定請求如聲明所示。\n乙、被告方面：被告未提出書狀，亦未作何陳述，惟依其在刑事\n              訴訟之陳述，不承認有何侵權行為。\n    理  由\n一、按刑事訴訟諭知無罪、免訴或不受理之判決者，應以判決駁\n    回原告之訴，刑事訴訟法第503 條第1 項前段定有明文。\n二、本件被告被訴損害賠償之刑事案件，業經本院刑事庭判決無\n    罪在案（臺灣高雄地方法院諭知無罪，檢察官不服原判決提\n    起上訴後，亦經本院判決上訴駁回）。依照首開規定，自應\n    駁回原告附帶提起之民事訴訟。\n三、據上論斷，應依刑事訴訟法第503 條第1 項前段，判決如主\n    文。\n中    華    民    國    99    年    1     月    5     日\n                  刑事第一庭    審判長法  官  周賢銳\n                                      法  官  徐美麗\n                                      法  官  施柏宏\n以上正本證明與原本無異。\n不得上訴。\n中    華    民    國    99    年    1     月    5     日\n                                      書記官  魏文常",
  "structure": {
    "main": "原告之訴駁回。",
    "fact": "甲、原告方面：\n    聲明：被告應給付原告Ａ女新臺幣（下同）50萬元，應給付\n    原告Ａ母25萬元，及均自起訴狀繕本送達被告翌日起至清償\n    日止，按年息百分之五計算之利息。\n    陳述略以：被告係Ａ女就讀甲中學之數學老師，其卻利用擔\n    任課後輔導Ａ女數學課業機會，於97年1 月25日在高雄市美\n    術館及同年3 月9 日在中央公園，分別對Ａ女強制猥褻得逞\n    。為此依民法侵權行為之規定請求如聲明所示。\n乙、被告方面：被告未提出書狀，亦未作何陳述，惟依其在刑事\n              訴訟之陳述，不承認有何侵權行為。",
    "reason": "一、按刑事訴訟諭知無罪、免訴或不受理之判決者，應以判決駁\n    回原告之訴，刑事訴訟法第503 條第1 項前段定有明文。\n二、本件被告被訴損害賠償之刑事案件，業經本院刑事庭判決無\n    罪在案（臺灣高雄地方法院諭知無罪，檢察官不服原判決提\n    起上訴後，亦經本院判決上訴駁回）。依照首開規定，自應\n    駁回原告附帶提起之民事訴訟。\n三、據上論斷，應依刑事訴訟法第503 條第1 項前段，判決如主\n    文。\n中    華    民    國    99    年    1     月    5     日\n                  刑事第一庭    審判長法  官  周賢銳\n                                      法  官  徐美麗\n                                      法  官  施柏宏\n以上正本證明與原本無異。\n不得上訴。"
  },
  "characters": {
    "judges": [
      "周賢銳",
      "徐美麗",
      "施柏宏"
    ],
    "prosecutors": [

    ],
    "lawyers": [
      "林朋助"
    ],
    "clerks": [

    ],
    "plaintiffs": [
      "Ａ女"
    ],
    "defendants": [
      "甲○○"
    ],
    "prosecutor_office": [

    ],
    "creditors": [

    ],
    "debtors": [

    ],
    "judicial_associate_officer": [

    ]
  },
  "adjudged_at": "2010-01-05",
  "created_at": "2016-01-05 15:11:00",
  "updated_at": "2016-01-05 15:11:00"
}