{
  "identify": "KSH-99-聲-505-20100512-1",
  "court": {
    "name": "臺灣高等法院",
    "code": "KSH"
  },
  "division": {
    "name": "刑事",
    "code": "M"
  },
  "year": 99,
  "word": "聲",
  "number": "505",
  "jcheck": "1",
  "reason": "聲請付保護管束",
  "content": "臺灣高等法院高雄分院刑事裁定           99年度聲字第505號\n聲  請  人  臺灣高等法院高雄分院檢察署檢察官\n受  刑  人  甲○○\n上列受刑人因聲請付保護管束案件，經聲請人聲請付保護管束，\n本院裁定如下：\n    主  文\n甲○○假釋中付保護管束。\n    理  由\n查本件受刑人甲○○前因違反台灣地區與不陸地區關係條例之罪\n，經本院判處有期徒刑1 年8 月確定執行在案。茲聲請人以受刑\n人甲○○業於民國99年5 月5 日核准假釋在案，而縮短刑期後終\n結日期為99年9 月27日，聲請於其假釋中付保護管束等情。本院\n審核無異，應依刑事訴訟法第481 條第1 項，刑法第93條第2 項\n、第96條但書，裁定如主文。\n中    華    民    國    99    年    5     月    12    日\n                  刑事第六庭    審判長法  官   王憲義\n                                      法  官   邱永貴\n                                      法  官   簡志瑩\n以上正本證明與原本無異。\n不得抗告。\n中    華    民    國    99    年    5     月    12    日\n                                      書記官   張文斌",
  "structure": {
    "main": "甲○○假釋中付保護管束。",
    "reason": "查本件受刑人甲○○前因違反台灣地區與不陸地區關係條例之罪\n，經本院判處有期徒刑1 年8 月確定執行在案。茲聲請人以受刑\n人甲○○業於民國99年5 月5 日核准假釋在案，而縮短刑期後終\n結日期為99年9 月27日，聲請於其假釋中付保護管束等情。本院\n審核無異，應依刑事訴訟法第481 條第1 項，刑法第93條第2 項\n、第96條但書，裁定如主文。"
  },
  "characters": {
    "judges": [
      "王憲義",
      "邱永貴",
      "簡志瑩"
    ],
    "prosecutors": [

    ],
    "lawyers": [

    ],
    "clerks": [

    ],
    "plaintiffs": [

    ],
    "defendants": [

    ],
    "prosecutor_office": [
      "臺灣高等法院高雄分院檢察署檢察官"
    ],
    "creditors": [

    ],
    "debtors": [

    ],
    "judicial_associate_officer": [

    ]
  },
  "adjudged_at": "2010-05-12",
  "created_at": "2016-01-05 12:03:16",
  "updated_at": "2016-01-05 12:03:16"
}