{
  "identify": "KSH-98-附民上-56-20100105-1",
  "court": {
    "name": "臺灣高等法院",
    "code": "KSH"
  },
  "division": {
    "name": "刑事",
    "code": "M"
  },
  "year": 98,
  "word": "附民上",
  "number": "56",
  "jcheck": "1",
  "reason": "損害賠償",
  "content": "臺灣高等法院高雄分院刑事附帶民事訴訟判決\n上  訴  人\n即  原  告  Ｅ○○\n被上訴人即\n被      告  甲○○\n            黃○○\n            地○○\n            Ｏ○○（原名顏銘震）\n            巳○○\n            Ｐ○○\n            丁○○\n            Ｃ○○\n            Ｊ○○\n            Ｆ○○\n            子○○（原名吳俊德）\n            Ｍ○○\n            未○○\n            Ｂ○○\n            乙○○（原名史雅茜）\n            玄○○\n            Ｌ○○（原名蔡宜庭）\n            辛○○\n            Ｑ○○\n            申○○\n            酉○○\n            辰○○（原名林詩怡）\n            Ｎ○○\n            庚○○\n            Ｄ○○（原名黃彩惠）\n            Ａ○○（原名馮志群）\n            丙○○（原名史恆華）\n            午○○\n            己○○\n                      樓之1\n            戊○○\n            卯○○\n            Ｋ○○\n            宇○○\n            Ｈ○○\n                      之1\n            天○○\n            亥○○\n            Ｇ○○\n            宙○○\n            戌○○\n            癸○○\n            丑○○\n            寅○○（原名李裙鳳）\n            壬○○\n            Ｉ○○○\n上列當事人間因損害賠償附帶民事訴訟案件，上訴人不服臺灣高\n雄地方法院中華民國98年7 月30日第一審附帶民事訴訟判決（96\n年度附民字第215 號），提起上訴，本院判決如下：\n    主  文\n上訴駁回。\n    事實及理由\n一、上訴人陳述略稱：求為將原判決廢棄，命被上訴人等44人應\n    連帶給付上訴人新台幣（下同）54萬元及加計之法定遲延利\n    息，並陳明願供擔保聲請為假執行宣告，並援用刑事訴訟之\n    證據。\n    被上訴人等辯稱略以：請求駁回上訴人之上訴。並援用刑事\n    訴訟所為之陳述，即不承認有何常業詐欺之侵權行為。\n二、按刑事訴訟諭知無罪，免訴或不受理之判決者，對於附帶民\n    事訴訟部分應以判決駁回原告之訴，刑事訴訟法第503 條第\n    1 項前段定有明文。\n三、經查本院98年度上重訴字第23號被告甲○○等44人被訴常業\n    詐欺案件，業經本院判決被告等44人無罪（臺灣高雄地方法\n    院諭知被告等44人均無罪，檢察官不服原判決提起上訴後，\n    亦經本院判決上訴駁回）在案。原判決依照首開規定，駁回\n    上訴人對於被上訴人等44人附帶提起之民事訴訟，經核並無\n    不合，上訴人上訴論旨，求予廢棄改判，均無理由，應予駁\n    回。\n據上論結，應依刑事訴訟法第490 條前段、第368 條，判決如主\n文。\n中    華    民    國    99    年     1     月    5    日\n                    刑事第三庭  審判長法  官  莊崑山\n                                      法  官  唐照明\n                                      法  官  張意聰\n以上正本證明與原本無異。\n本判決非對於刑事訴訟之判決有上訴時不得上訴。\n如不服本判決應於收受本判決後10日內向本院提出上訴書狀，並\n應敘述具體理由，如未敘述上訴理由者，應於上訴期間屆滿後20\n日內補提理由書狀於本院（均須按他造當事人之人數附繕本）「\n切勿逕送上級法院」。\n中    華    民    國    99    年     1     月    5    日\n                                      書記官  陳金",
  "structure": {
    "main": "上訴駁回。",
    "fact": "一、上訴人陳述略稱：求為將原判決廢棄，命被上訴人等44人應\n    連帶給付上訴人新台幣（下同）54萬元及加計之法定遲延利\n    息，並陳明願供擔保聲請為假執行宣告，並援用刑事訴訟之\n    證據。\n    被上訴人等辯稱略以：請求駁回上訴人之上訴。並援用刑事\n    訴訟所為之陳述，即不承認有何常業詐欺之侵權行為。\n二、按刑事訴訟諭知無罪，免訴或不受理之判決者，對於附帶民\n    事訴訟部分應以判決駁回原告之訴，刑事訴訟法第503 條第\n    1 項前段定有明文。\n三、經查本院98年度上重訴字第23號被告甲○○等44人被訴常業\n    詐欺案件，業經本院判決被告等44人無罪（臺灣高雄地方法\n    院諭知被告等44人均無罪，檢察官不服原判決提起上訴後，\n    亦經本院判決上訴駁回）在案。原判決依照首開規定，駁回\n    上訴人對於被上訴人等44人附帶提起之民事訴訟，經核並無\n    不合，上訴人上訴論旨，求予廢棄改判，均無理由，應予駁\n    回。\n據上論結，應依刑事訴訟法第490 條前段、第368 條，判決如主\n文。",
    "reason": "一、上訴人陳述略稱：求為將原判決廢棄，命被上訴人等44人應\n    連帶給付上訴人新台幣（下同）54萬元及加計之法定遲延利\n    息，並陳明願供擔保聲請為假執行宣告，並援用刑事訴訟之\n    證據。\n    被上訴人等辯稱略以：請求駁回上訴人之上訴。並援用刑事\n    訴訟所為之陳述，即不承認有何常業詐欺之侵權行為。\n二、按刑事訴訟諭知無罪，免訴或不受理之判決者，對於附帶民\n    事訴訟部分應以判決駁回原告之訴，刑事訴訟法第503 條第\n    1 項前段定有明文。\n三、經查本院98年度上重訴字第23號被告甲○○等44人被訴常業\n    詐欺案件，業經本院判決被告等44人無罪（臺灣高雄地方法\n    院諭知被告等44人均無罪，檢察官不服原判決提起上訴後，\n    亦經本院判決上訴駁回）在案。原判決依照首開規定，駁回\n    上訴人對於被上訴人等44人附帶提起之民事訴訟，經核並無\n    不合，上訴人上訴論旨，求予廢棄改判，均無理由，應予駁\n    回。\n據上論結，應依刑事訴訟法第490 條前段、第368 條，判決如主\n文。"
  },
  "characters": {
    "judges": [
      "莊崑山",
      "唐照明",
      "張意聰"
    ],
    "prosecutors": [

    ],
    "lawyers": [

    ],
    "clerks": [

    ],
    "plaintiffs": [
      "Ｅ○○",
      "被上訴人即"
    ],
    "defendants": [
      "甲○○"
    ],
    "prosecutor_office": [

    ],
    "creditors": [

    ],
    "debtors": [

    ],
    "judicial_associate_officer": [

    ]
  },
  "adjudged_at": "2010-01-05",
  "created_at": "2016-01-05 15:09:29",
  "updated_at": "2016-01-05 15:09:29"
}