{
  "identify": "KSH-98-上易-767-20100105-1",
  "court": {
    "name": "臺灣高等法院",
    "code": "KSH"
  },
  "division": {
    "name": "刑事",
    "code": "M"
  },
  "year": 98,
  "word": "上易",
  "number": "767",
  "jcheck": "1",
  "reason": "詐欺等",
  "content": "臺灣高等法院高雄分院刑事判決         98年度上易字第767號\n上  訴  人  臺灣高雄地方法院檢察署檢察官\n被      告  Ｑ○○\n被      告  Ｐ○○\n被      告  己○○\n被      告  Ｆ○○\n被      告  庚○○\n被      告  壬○○\n被      告  午○○\n被      告  Ｅ○○\n上列上訴人因被告詐欺等案件，不服臺灣高雄地方法院98年度易\n字第356 號中華民國98年8 月13日第一審判決（起訴案號：臺灣\n高雄地方法院檢察署97年度偵字第34744 號），提起上訴，本院\n判決如下：\n    主  文\n原判決除Ｐ○○無罪部分外，均撤銷。\nＱ○○犯如附表一、二所示共肆拾壹罪，均累犯，各處如附表一\n、二主文欄所示之刑。應執行有期徒刑柒年，並於刑之執行前，\n令入勞動處所強制工作參年。\nＰ○○犯如附表一編號23至25所示之參罪，均累犯，各處如附表\n一編號23至25主文欄所示之刑。應執行有期徒刑壹年壹月。\n己○○犯如附表一編號26至33、附表二編號7 至8 所示共拾罪，\n各處如附表一編號26至33、附表二編號7 至8 主文欄所示之刑。\n應執行有期徒刑參年。\n午○○犯如附表二編號1 至2 所示共貳罪，各處如附表二編號1\n至2 主文欄所示之刑。應執行有期徒刑壹年肆月。\nＥ○○犯如附表二編號3 、5 所示共貳罪，各處如附表二編號3\n、5 主文欄所示之刑。應執行有期徒刑捌月，如易科罰金，以新\n臺幣壹仟元折算壹日。\nＦ○○犯如附表二編號6 至7 所示共貳罪，各處如附表二編號6\n至7主 文欄所示之刑。應執行有期徒刑壹年柒月。\n庚○○犯收受贓物罪，處有期徒刑肆月，如易科罰金，以新臺幣\n壹仟元折算壹日。\n壬○○犯收受贓物罪，處有期徒刑參月，如易科罰金，以新臺幣\n壹仟元折算壹日。\n    事  實\n一、Ｑ○○前因詐欺案件，經法院判處有期徒刑4 月確定，甫於\n    民國96年7 月16日易科罰金執行完畢；Ｐ○○前因詐欺案件\n    ，經法院判處有期徒刑3 月確定，甫於96年12月24日易科罰\n    金執行完畢。\n二、Ｑ○○意圖為自己不法所有或分別各與附表一所示之提款人\n    Ｐ○○、己○○等人，共同基於意圖為自己不法所有之犯意\n    聯絡，明知渠等並無「SOGO禮券」、「汽車渦輪控制器」、\n    「汽車零件」、「統一超商禮券」等商品可供出售，竟自97\n    年6 月10日起至97年12月10日止，由Ｑ○○在高雄市各不特\n    定之網咖店上網，以附表一所示之虛偽雅虎拍賣帳號登入雅\n    虎拍賣網站，分別刊登販售上開商品之訊息，致附表一所示\n    Ａ○○等33人瀏覽上開販售商品之訊息後陷於錯誤，而下標\n    購買，並撥打Ｑ○○所留之人頭聯絡電話與其聯繫後，依Ｑ\n    ○○指示匯款至其所收購潘韋德等人（詳如附表一帳號所有\n    人欄所示）所有金融帳戶或Ｑ○○所申請之IBON帳號內（由\n    受騙之買家至超商操作IBON機器繳款），再由Ｑ○○自己，\n    或由Ｑ○○指示附表一所示之提款人Ｐ○○、己○○等人（\n    詳如附表一提款人欄所示）分別至自動提款機提領現金後，\n    Ｑ○○即關閉手機，切斷與Ａ○○等人之聯絡，致Ａ○○等\n    33人受騙並受有如附表一所示之財產上損害（詳細匯款日期\n    、金額、帳號及Ｑ○○等人之分工均詳如附表一所示）。\n三、Ｑ○○於97年6 月16日起至同年11月6 日止，復分別與附表\n    二所示之午○○、Ｅ○○、Ｆ○○、己○○等4 人，共同基\n    於意圖為自己不法所有之犯意聯絡，先由Ｑ○○在高雄市各\n    不特定之網咖店上網，以附表二所示之虛偽雅虎拍賣帳號登\n    入雅虎拍賣網站，刊登販售「SOGO禮券」或「液晶螢幕」等\n    商品之訊息，同時從拍賣網站上搜尋欲出售手錶、液晶螢幕\n    等賣家詳如附表二所示之Ｊ○○等7 人（附表二編號3 、4\n    係同一被害人乙○○），並出價得標，待取得Ｊ○○等7 人\n    所提供之匯款帳號後，即將該匯款帳號提供給欲購買Ｑ○○\n    上開網路拍賣商品之詳如附表二所示之買家汪婉宜等8 人，\n    作為上開買家匯款用之帳戶，致附表二所示之汪婉宜等8 人\n    之禮券買家、Ｊ○○等7 人之手錶賣家，買賣雙方均陷於錯\n    誤，由附表二所示之汪婉宜等禮券買家匯款至如附表二所示\n    之Ｊ○○等手錶賣家之帳戶，而附表二所示之Ｊ○○等手錶\n    賣家收到汪婉宜等禮券買家之匯款後，通知Ｑ○○取貨時，\n    Ｑ○○即斷絕與汪婉宜等禮券買家之聯繫，並與Ｊ○○等手\n    錶賣家聯絡見面交貨時間後，指派附表二所示知情之午○○\n    、Ｅ○○、Ｆ○○、己○○等人前往取得手錶等物品（具體\n    犯罪被害人、犯罪時間、手段所得財物及共犯之之分工，均\n    詳如附表二所示）。\n四、庚○○於97年11月3 日，明知附表二編號7 己○○所交付之\n    手錶係屬贓物，卻仍予以收受，並以新台幣（下同）4 萬元\n    之價格持以出售與不知情而經營鐘錶行之洪靖熙，所得價款\n    並從中分得5 千元。壬○○於97年11月8 日，明知附表二編\n    號8 Ｑ○○委請友人「王世賢」（真實年籍姓名不詳）所交\n    付之手錶係屬贓物，卻仍予以收受，並以2 萬5 千元之價格\n    持以出售與不知情之洪靖熙，所得價款並從中分得3 千元之\n    欠款。\n五、嗣經警據報循線於97年12月10日22時40分許，在高雄市○鎮\n    區○○路與光華路口「85度C 咖啡店」前查獲Ｑ○○、Ｐ○\n    ○、己○○、Ｆ○○等4 人，並執行附帶搜索；翌日8 時許\n    ，警方持搜索票，分別前往高雄市○○區○○街89號9 樓之\n    3 （Ｑ○○住處）、高雄縣鳳山市○○○街12號（己○○住\n    處）、高雄市前鎮區○○○路27號（Ｆ○○住處）等處執行\n    搜索，扣得Ｑ○○等人所有如附表三所示之物。\n六、案經Ａ○○等11人訴由高雄市政府警察局移送及臺北縣政府\n    警察局三重分局報告臺灣板橋地方法院檢察署呈請台灣高等\n    法院檢察署函轉臺灣高雄地方法院檢察署檢察官偵查起訴。\n    理  由\n壹、證據能力部分\n一、按被告以外之人於偵查中向檢察官所為陳述，除顯有不可信\n    之情況者外，得為證據，刑事訴訟法第159 條之1 第2 項定\n    有明文。查證人即附表一、二所列之被害人及各共同被告於\n    檢察官偵查時所為陳述，客觀上並無顯不可信之情況，且其\n    中證人Ｑ○○、己○○、午○○、Ｅ○○等人已經原審傳訊\n    到庭行交互詰問，其餘證人則經檢察官及被告於法院審理中\n    捨棄詰問權，是上開證人於偵查中之證詞自有證據能力。\n二、本判決所引用之其餘證據資料（詳後引證據），其中傳聞證\n    據部分（含各附表被害人於警詢之陳述及共同被告於審判外\n    之陳述），縱無刑事訴訟法第159 條之1 至第159 條之4 或\n    其他規定之傳聞證據例外情形，亦因各被告及檢察官或同意\n    可作為證據使用，或未聲明異議，依刑事訴訟法第159 條之\n    5 第1 項、第2 項之規定，本院審酌各該傳聞證據並非違法\n    取得，與待證事項具關聯性，證明力亦非明顯過低等情，認\n    以之作為證據係屬適當，具有證據能力。\n貳、實體部分\n一、訊據被告Ｑ○○固坦承有附表一編號13-33 、附表二之詐欺\n    犯行，惟否認有附表一編號1-12詐欺犯行，辯稱：附表一編\n    號1-12詐欺犯行非其所為，該犯行係另一批台中人所為（見\n    本院卷第152 頁）。被告Ｐ○○固坦承有於上開時地參與提\n    款之行為，惟否認有涉犯詐欺犯行，辯稱：Ｑ○○向我說該\n    錢是合法的，我才幫忙去提款（見本院卷第215 頁）。被告\n    己○○固坦承參與附表一編號26-33 之詐欺犯行，惟否認有\n    參與附表二編號7-8 詐欺犯行，辯稱：附表二編號7-8 詐欺\n    犯行，我並未參與去賣手錶，Ｑ○○也未分錢給我（見本院\n    卷第215 、218 頁）。被告Ｆ○○則否認有詐欺犯行，辯稱\n    ：我去賣附表二編號6-7 之手錶時，並不知該手錶係贓物（\n    見本院卷第215 頁）。被告庚○○否認有收受贓物犯行，辯\n    稱：己○○叫我去賣附表二編號7 手錶時，我不知該手錶係\n    贓物（見本院卷第215 頁）。被告壬○○否認有收受贓物犯\n    行，辯稱：我只是幫忙拿附表二編號8 手錶去賣而已，我不\n    知該手錶係贓物（見本院卷第215 、218 頁）。被告午○○\n    則坦承有共同參與附表二編號1-2 之詐欺犯行（見本院卷第\n    91 頁 ）。被告Ｅ○○則坦承有共同參與附表二編號3 、5\n    之詐欺犯行（見本院卷第91頁）。經查：\n  (一)被告Ｑ○○、Ｐ○○、己○○、Ｆ○○、午○○、Ｅ○○等\n    6 人分別有附表一編號13-33 及附表二所示之詐欺事實，被\n    告庚○○、壬○○2 人有上開受收贓物之事實，已據被告Ｑ\n    ○○、Ｐ○○、己○○、Ｆ○○、午○○、Ｅ○○、庚○○\n    、壬○○等8 人於原審坦承不諱，經核與匯款之被害人宇○\n    ○、辛○○、Ｍ○○、Ｋ○○、Ｏ○○、江智舜、甲○○、\n    Ｌ○○、子○○、丁○○、證人即提供詐騙帳戶之廖品臻、\n    證人即廖品臻之友人范栓瑄、被害人Ｃ○○、戊○○、Ｂ○\n    ○、Ｒ○○、癸○○、Ｔ○○、寅○○、辰○○、亥○○、\n    陳曉娟、Ｇ○○、巳○○、Ｊ○○、丑○○、Ｉ○○、未○\n    ○、乙○○、黃○○、玄○○、Ｕ○○、酉○○、林政德（\n    即酉○○之父）、Ｎ○○、申○○於警詢中或偵查中之指述\n    相符，並有被害人宇○○之內政部警政署反詐騙案件紀錄表\n    、國泰世華商業銀行帳號000000000000號存摺存款對帳單、\n    被害人辛○○之內政部警政署反詐騙案件紀錄表、統一超商\n    股份有限公司IBON代收款專用繳款證明、被害人Ｍ○○之統\n    一超商股份有限公司IBON代收款專用繳款證明、被害人Ｋ○\n    ○之內政部警政署反詐騙案件紀錄表、統一超商股份有限公\n    司IBON代收款專用繳款證明、雅虎拍賣網站網頁資料、被害\n    人Ｏ○○之內政部警政署反詐騙案件紀錄表、郵政自動櫃員\n    機交易明細表、郵政國內匯款執據、被害人江智舜之內政部\n    警政署反詐騙案件紀錄表、中國信託轉帳收執聯、雅虎拍賣\n    網站網頁資料、被害人甲○○之內政部警政署反詐騙案件紀\n    錄表、郵政自動櫃員機交易明細表、雅虎拍賣網站網頁資料\n    、被害人陳騏竤之內政部警政署反詐騙案件紀錄表、郵政自\n    動櫃員機交易明細表、雅虎拍賣網站網頁資料、被害人子○\n    ○之內政部警政署反詐騙案件紀錄表、郵政自動櫃員機交易\n    明細表、被害人丁○○之內政部警政署反詐騙案件紀錄表、\n    雅虎拍賣網站網頁資料、台新銀行自動櫃員機交易明細表、\n    被害人Ｃ○○之內政部警政署反詐騙案件紀錄表、國泰世華\n    銀行自動櫃員機交易明細表、被害人戊○○之內政部警政署\n    反詐騙案件紀錄表、郵政自動櫃員機交易明細表、雅虎奇摩\n    拍賣網站網頁資料、被害人Ｂ○○之內政部警政署反詐騙案\n    件紀錄表、玉山銀行網路ATM 匯款明細、郵政國內匯款執據\n    、被害人Ｒ○○之內政部警政署反詐騙案件紀錄表、中國信\n    託銀行網路ATM 匯款明細、土地銀行網路ATM 匯款明細、國\n    泰世華銀行網路ATM 匯款明細、被害人癸○○之內政部警政\n    署反詐騙案件紀錄表、台南縣仁德鄉農會自動櫃員機交易明\n    細表、郵政自動櫃員機交易明細表、中國信託自動櫃員機明\n    細表、被害人Ｔ○○之內政部警政署反詐騙案件紀錄表、遠\n    東國際商業銀行客戶交易明細表、台灣中小企業銀行存款憑\n    條、宅急便送貨單、被害人寅○○之內政部警政署反詐騙案\n    件紀錄表、遠東國際商業銀行存款交易明細、被害人辰○○\n    之內政部警政署反詐騙案件紀錄表、台新銀行自動櫃機交易\n    明細表、雅虎奇摩拍賣網站網頁資料、被害人亥○○之內政\n    部警政署反詐騙案件紀錄表、玉山銀行匯款執據、被害人陳\n    曉娟之內政部警政署反詐騙案件紀錄表、中國信託銀行匯款\n    執據、雅虎奇摩拍賣網站網頁資料、被害人Ｇ○○之內政部\n    警政署反詐騙案件紀錄表各1 份、被害人Ｊ○○指認相片、\n    被害人Ｊ○○提出之台北富邦高雄分行帳號：000000000000\n    （戶名：黃德隆）基本資料、交易往來明細、門號00000000\n    00號於97年6 月16日至17日之通信記錄、監視錄影翻拍畫面\n    4 幀、台北富邦銀行帳號0000 00000000 （戶名黃德隆）之\n    開戶資料、對帳單明細、存摺往來交易明細、各類存款歷史\n    對帳單、門號0000000000號用戶資料、通聯記錄、內政部警\n    政署反詐騙案件紀錄表、台北富邦銀行存摺類存款存入存根\n    、雅虎拍賣網站網頁資料、台北縣政府警察局三重分局光明\n    派出所受理刑事案建三聯單、被害人巳○○之受理詐騙帳戶\n    通報警示簡便格式表、被害人丑○○指認相片、被害人丑○\n    ○提出之雅虎拍賣網站網頁資料、第一銀行帳號000-000000\n    00000 （戶名：潘騰）開戶資料、交易往來明細、被害人卯\n    ○○之內政部警政署反詐騙案件紀錄表、高雄三信銀行活期\n    儲蓄存款存摺交易明細各1 份、被害人乙○○指認相片、被\n    害人乙○○提出之收據、彰化銀行鹽埕分行帳號000-000000\n    00000000（戶名：王黃麗華）開戶資料、存摺存款帳戶資料\n    及交易明細查詢各1 份、被害人之Ｉ○○內政部警政署反詐\n    騙案件紀錄表、第一銀行帳號000000 00000號往來交易明細\n    各1 紙、被害人未○○之內政部警政署反詐騙案件紀錄表、\n    郵政跨行匯款申請書各1 紙、被害人玄○○指認相片、被害\n    人玄○○提出之監視錄影翻拍畫面1 幀、電話000000000 於\n    97年8 月25日之通聯紀錄、彰化銀行業務往來申請書、印鑑\n    卡暨顧客資料卡、帳號000-00000000000000存摺存款帳戶及\n    交易明細查詢、被害人黃○○之內政部警政署反詐騙案件紀\n    錄表、華南商業銀行轉帳單據各1 紙、被害人酉○○提出之\n    雅虎拍賣網站網頁資料、第一銀行帳號00000000000 （戶名\n    ：酉○○）開戶資料、交易往來明細、被害人林政德（酉○\n    ○之父）指認相片、被害人Ｕ○○之內政部警政署反詐騙案\n    件紀錄表、被害人Ｎ○○指認相片、被害人Ｎ○○提出之郵\n    局申設帳號000000 00000000 號之存摺交易明細、雅虎拍賣\n    網站網頁資料、板橋文化路郵局帳號00000000000000號（戶\n    名：Ｎ○○）之開戶資料、客戶歷史交易清單、被害人Ｂ○\n    ○之內政部警政署反詐騙案件紀錄表、玉山銀行網路ATM 匯\n    款條、郵政國內匯款執據、三信銀行帳號0000000000號（見\n    戶名：宙○○）之開戶資料、客戶帳單明細單、被害人申○\n    ○之內政部警政署反詐騙案件紀錄表、台新銀行大里分行帳\n    號0000000000000 號存摺往來交易明細、台新銀行竹科分行\n    帳號0000000000000 存摺往來交易明細各1 份、高雄市政府\n    警察局刑事警察局大隊搜索、扣押筆錄、扣押物品目錄表各\n    9 份（受執行人：Ｑ○○、Ｑ○○、己○○、己○○、Ｐ○\n    ○、Ｆ○○、Ｆ○○、庚○○、壬○○）、高雄大順郵局帳\n    號00000000000000號（戶名：潘韋德）之開戶資料、客戶歷\n    史交易清單、新埤郵局帳號000-00000000000000號（戶名：\n    曾光展）之開戶資料、客戶歷史交易清單、鶯歌郵局帳號00\n    000000000000號（戶名：葉凱文）之客戶歷史交易清單、台\n    南友愛街郵局帳號00000000000000號（戶名：林柏良）之客\n    戶歷史交易清單、中和大華郵局帳號00000000000000號（戶\n    名：吳育慈）之開戶資料、客戶歷史交易清單、屏東復興郵\n    局帳號00000000 000000 號（戶名：林政慶）之客戶歷史交\n    易清單、楊梅郵局帳號00000000000000號（戶名：廖品臻）\n    之存摺封面、開戶資料、客戶歷史交易清單各1 份、Ｑ○○\n    、己○○分別於97年11月21日、97年11月24日之提款畫面2\n    幀、Ｅ○○書寫之便條1 紙、第一銀行澎湖分行98年2 月26\n    日一澎字第9 號函暨存戶Ｑ○○開戶資料、帳號0000000000\n    0 號往來交易明細、97檢總管11045 號扣押物品清單各1 紙\n    、Ｐ○○於持盧祥龍（上海商業銀永康分行00000000000000\n    000 ）之提款卡提款畫面2 幀、午○○、庚○○簽立之讓渡\n    書、身分證影本各1 紙、被告壬○○簽立之讓渡書、身分證\n    影本1 紙、被告Ｆ○○簽立之讓渡書、身分證影本1 紙、證\n    人洪靖熙提供所收購之手錶相片、97年聲監字第002046號臺\n    灣高雄地方法院通訊監察書及電話附表各1 份、Ｑ○○持用\n    之門號0000000000監聽譯文、Ｑ○○持用之門號0000000000\n    監聽譯文、Ｅ○○持用之門號0000000000監聽譯文各1 份在\n    卷可佐。\n  (二)被告Ｑ○○雖否認有附表一編號1 至12之詐欺犯行，於原審\n    並辯稱：附表一編號1-12之網路帳號weekenid及hoorscopes\n    並非伊所申請，係台中之詐騙集團成年成員溫平男等人所策\n    劃，伊僅有數次為該集團領錢云云。經查：\n  1.上開附表一編號1-12之被害人受有其上所載詐欺之事實，及\n    用以詐欺附表一編號1-12被害人之行動電話門號分別係如其\n    上所載之0000000000、0000000000、0000000000、00000000\n    00、0000000000等號碼，用以詐欺附表一編號1-8 、10-12\n    被害人之拍賣網站帳號分別係其上所載之「weekenid」及「\n    hoorscopes」之事實，為被告Ｑ○○所不爭執，並經被害人\n    Ａ○○、戌○○、地○○、Ｓ○○、Ｄ○○、丙○○、Ｈ○\n    ○、Ｗ○○、卯○○、Ｙ○○、Ｘ○○、Ｖ○○於警詢、偵\n    訊中證述明確，復有被害人Ａ○○提供之陽信銀行存款往來\n    交易明細、被害人戌○○之內政部警政署反詐騙案件紀錄表\n    、台新銀行自動櫃員機交易明細表、被害人地○○之內政部\n    警政署反詐騙案件紀錄表、郵政自動櫃員機交易明細表、被\n    害人Ｓ○○之內政部警政署反詐騙案件紀錄表、雅虎拍賣網\n    站網頁資料、台新銀行自動櫃員機交易明細表、被害人Ｄ○\n    ○之內政部警政署反詐騙案件紀錄表、郵政儲金匯業局自動\n    櫃員機儲戶交易明細表、被害人丙○○之內政部警政署反詐\n    騙案件紀錄表、國泰世華銀行客戶交易明細表、雅虎拍賣網\n    站網頁資料、被害人Ｈ○○之內政部警政署反詐騙案件紀錄\n    表、被害人Ｗ○○之內政部警政署反詐騙案件紀錄表、郵政\n    自動櫃員機交易明細表、雅虎拍賣網站網頁資料、被害人卯\n    ○○之內政部警政署反詐騙案件紀錄表、高雄三信銀行活期\n    儲蓄存款存摺交易明細、被害人Ｙ○○之內政部警政署反詐\n    騙案件紀錄表、郵政自動櫃員機交易明細表、雅虎拍賣網站\n    網頁資料、被害人Ｘ○○之內政部警政署反詐騙案件紀錄表\n    、郵政自動櫃員機交易明細表、被害人Ｖ○○之內政部警政\n    署反詐騙案件紀錄表、彰化銀行存摺交易明細、台新銀行自\n    動櫃員機交易明細表各1 份在卷可稽。\n  2.被告Ｑ○○確有詐騙附表二編號1 、2 被害人Ｊ○○、汪婉\n    宜、丑○○、卯○○等4 人之事實，已據被告Ｑ○○坦承不\n    諱，並有上開證據可資佐證。而行動電話門號0000000000係\n    用以詐騙附表二編號1 之被害人汪婉宜之號碼；行動電話門\n    號0000000000係用以詐騙附表二編號2 之被害人卯○○之號\n    碼；行動電話門號0000000000係用以詐騙附表二編號一之被\n    害人Ｊ○○及汪婉宜之號碼等情，分別經上開被害人於警詢\n    或偵查中證述明確，是行動電話行號0000000000、00000000\n    00、0000000000之號碼，均係Ｑ○○用以詐騙被害人之門號\n    ，應堪認定。\n  3.被告Ｑ○○雖對附表一編號1-12詐欺犯行，以上揭情詞置辯\n    ，惟比對上開行動電話門號可知：被告Ｑ○○用以詐欺附表\n    一編號1-4 被害人之行動電話門號0000000000，即為其用以\n    詐騙附表二編號1 之被害人汪婉宜之號碼（0000000000）；\n    被告Ｑ○○用以詐欺附表一編號5 被害人之行動電話門號00\n    00000000、0000000000、0000000000等3 線，即其用以詐騙\n    附表二編號1 被害人汪婉宜之號碼（0000000000）、附表二\n    編號2 被害人卯○○之號碼（0000000000）、附表二編號1\n    被害人Ｊ○○及汪婉宜之號碼（0000000000），是附表一編\n    號1-5 之犯行，應係被告Ｑ○○所為，至為明確。又被告Ｑ\n    ○○用以詐欺附表一編號5-9 被害人之行動電話門號中之門\n    號0000000000，即其用以詐騙附表二編號2 之被害人卯○○\n    之號碼（0000000000），是附表一編號5-9 之犯行，亦係被\n    告Ｑ○○所為無誤。再比對用以詐欺上開附表一編號1-12被\n    害人之拍賣網站帳號可知：被告Ｑ○○用以詐欺附表一編號\n    10-12 被害人之拍賣網站帳號「hoorscopes」，即其用以詐\n    騙附表一編號6-8 被害人之拍賣網站帳號（hoorscopes），\n    而被告Ｑ○○詐欺附表一編號6-8 被害人，既已確認如上，\n    則附表一編號10至12之犯行，亦應係被告Ｑ○○所為。況且\n    ，被告Ｑ○○用以詐欺附表一編號5-9 、附表二編號2 被害\n    人之行動電話門號0000000000，所搭配用以詐欺附表一編號\n    5 被害人之拍賣網站帳號係「weekenid」；同一門號（0000\n    000000）所搭配用以詐欺附表一編號6-8 被害人之拍賣網站\n    帳號同時又係「hoorscopes」，由此亦足佐證拍賣網站帳號\n    「weekenid」、「hoorscopes」均係Ｑ○○用以詐欺之帳號\n    。\n  4.被告Ｑ○○於原審復辯稱：共同被告己○○、午○○、Ｅ○\n    ○等人可證明附表一編號1-12並非伊所為云云。惟經原審傳\n    喚上開共同被告己○○、午○○、Ｅ○○等人為證人，並經\n    交互詰問，渠等均不能對被告Ｑ○○上開辯詞，有所佐證。\n    況被告毆永毅於原審訊問之初，原已坦承上開犯行（見原審\n    卷一第39頁），嗣於原審進行準備程序及審理程序時，始翻\n    異前供，而核其辯詞，毫無佐證，又與事實相違，自無可採\n    。\n  5.綜上所陳，被告Ｑ○○確有附表一編號1-12之詐騙行為，堪\n    予認定。\n  (三)被告Ｐ○○雖以上揭情詞置辯，惟查：被告Ｐ○○有附表一\n    編號23-25 之詐欺犯行，已據其於偵查、原審準備程序及審\n    判程序、本院準備程序時多次自白犯罪在案（見偵查卷4 第\n    138-139 頁、原審卷1 第68、210 頁、原審卷2 第44、102\n    頁、本院卷91頁），且其於警詢中自承：「我賣過4 張電話\n    卡門號2 次及手機1 次給Ｑ○○，我曾幫Ｑ○○找過人頭帳\n    戶供Ｑ○○詐騙使用，並找人替Ｑ○○領取詐騙所得，而替\n    Ｑ○○領錢的人要求二成傭金，於是我便向Ｑ○○要求三成\n    傭金，其中我可賺得一成傭金」（見警卷1 第69-70 頁）等\n    情，於偵查中自承：「我有去ATM 幫Ｑ○○領過詐騙所得2\n    、3 次，承認有當車手幫Ｑ○○領錢之詐欺犯行」等情（見\n    偵查卷4 第138-139 頁」，經核與被告Ｑ○○供述：Ｐ○○\n    有幫其領過附表一編號23-25 約10萬元之款項等情相符（見\n    原審卷2 第45頁），是其前開犯罪之自白，自堪採信。被告\n    Ｐ○○既知道幫Ｑ○○所提領款項係詐騙所得，且分得詐騙\n    款項，其確有附表一編號23-25 之詐欺犯行，堪以認定。其\n    上開所辯，顯係事後卸責之詞，自無可採。\n  (四)被告己○○雖否認有參與附表二編號7-8 之詐欺犯行，並以\n    上揭情詞置辯，惟查：被告己○○有附表二編號7-8 之詐欺\n    犯行，已據其於偵查、原審準備程序及審判程序、本院準備\n    稱序時多次自白犯罪在案（見偵查卷4 第10-12 頁、原審卷\n    1 第69、210 頁、原審卷2 第102 頁、本院卷91頁），且其\n    於警詢及偵查中自承：「97年11間，Ｑ○○要我陪同他到台\n    中市○○○○路口，由我向一名不詳年籍男子拿一支寶格麗\n    手錶，那次他沒有給我錢，但來回吃喝玩樂均由他支付。我\n    有介紹朋友Ｆ○○給Ｑ○○認識，他幫Ｑ○○賣了二次手錶\n    」等情（見警卷1 第41頁、偵查卷4 第11頁），經核與Ｑ○\n    ○於本院供述：「我請己○○去幫我拿東西，我給他一些走\n    路工」等語相符（見本院卷第210 頁），是其前開犯罪之自\n    白，自堪採信。被告己○○既有參與詐騙所得手錶之取貨行\n    為，且分得詐騙利益，其確有附表二編號7-8 之詐欺犯行，\n    自堪認定。其上開所辯，顯係事後卸責之詞，自無可採。\n  (五)被告Ｆ○○雖辯稱參與附表二編號6-7 手錶變賣時，不知該\n    手錶係屬贓物，惟查：被告Ｆ○○有附表二編號6-7 之詐欺\n    犯行，已據其於偵查、原審準備程序及審判程序、本院準備\n    稱序時多次自白犯罪在案（見偵查卷4 第18頁、原審卷1 第\n    69、210 頁、原審卷2 第102 頁、本院卷91頁），且其於偵\n    查中自承：「我有幫Ｑ○○拿過二次手錶，第一次他拿一支\n    亞米茄手錶給我，要我去五福路的六六鐘錶行賣，賣了7 萬\n    多元，他有還我5 千元。第二次是97年11間，Ｑ○○要我陪\n    他坐高鐵去板橋。到板橋後，我們就坐計程車去一家超商，\n    就有人拿二支錶及一萬元給我，我就把東西轉交給Ｑ○○。\n    我當時知道Ｑ○○係在從事詐欺，知道他的錶是騙來的」等\n    情明確（見偵查卷4 第18頁），核與Ｑ○○供述Ｆ○○有參\n    與詐騙所得手錶之取貨及變賣行為相符，是其前開犯罪之自\n    白，應堪採信。被告Ｆ○○既有參與詐騙所得手錶之取貨及\n    變賣行為，且分得詐騙利益，其確有附表二編號6-7 之詐欺\n    犯行，自堪認定。其上開所辯，顯係事後卸責之詞，自無可\n    採。\n  (六)被告庚○○雖否認附表二編號7 之收受贓物犯行，並以上揭\n    情詞置辯，惟查：被告庚○○有附表二編號7 收受贓物犯行\n    ，已據其於偵查、原審準備程序及審判程序、本院準備稱序\n    時多次自白犯罪在案（見偵查卷4 第23頁、原審卷1 第210\n    頁、原審卷2 第102 頁、本院卷91頁），且其於偵查中自承\n    ：「我有欠己○○借款，他要我幫忙賣一支亞米茄手錶，賣\n    了4 萬元，賣了之後，己○○有給我5 千元。賣錶當時我覺\n    得該錶可能是贓物，但我欠他錢，不好意思拒絕」等情明確\n    （見偵查卷4 第28-29 頁），而衡諸常情，對他人來路不明\n    的名貴手錶，持有人不敢自己變賣，卻委託他人出面變賣，\n    且變賣後即可分得5 千元之利益，客觀上自難認變賣之人無\n    贓物之認識，是其前開犯罪之自白，應堪採信。被告庚○○\n    既有收受詐騙所得手錶，且進而出面變賣並分得利益，其確\n    有附表二編號7 收受贓物犯行，自堪認定。其上開所辯，顯\n    係事後卸責之詞，自無可採。\n  (七)被告壬○○雖否認有附表二編號8 收受贓物犯行，並以上揭\n    情詞置辯，惟查：被告壬○○有附表二編號8 收受贓物犯行\n    ，已據其於偵查、原審準備程序及審判程序、本院準備稱序\n    時多次自白犯罪在案（見偵查卷4 第28 頁、原審卷1 第210\n    頁、原審卷2 第126 頁、本院卷91頁），且其於偵查中自承\n    ：「賣手錶當時我知道該手錶可能係贓物。手錶賣了2 萬5\n    千元，賣了之後，王世賢還我3 千元」等情明確（見偵查卷\n    4 第28-29 頁），而衡諸常情，對他人來路不明的名貴手錶\n    ，持有人不敢自己變賣，卻委託他人出面變賣，且變賣後即\n    可分得3 千元之利益，客觀上自難認變賣之人無贓物之認識\n    ，是其前開犯罪之自白，應堪採信。被告壬○○既有收受詐\n    騙所得手錶，且進而出面變賣並分得利益，其確有附表二編\n    號8 收受贓物犯行，自堪認定。其上開所辯，顯係事後卸責\n    之詞，自無可採。\n  (八)綜上所述，被告Ｑ○○等人上開所辯，均屬卸飾之詞，殊無\n    可採。渠等有詐欺及受收贓物犯行，事證明確，堪以認定，\n    應予依法論科。\n二、論罪科刑部分：\n  (一)核被告Ｑ○○、Ｐ○○、己○○、午○○、Ｅ○○、Ｆ○○\n    6 人所為，均係犯刑法第339 條第1 項之詐欺取財罪；被告\n    庚○○、壬○○所為係犯刑法第349 條第1項 之收受贓物罪\n    。被告Ｑ○○分別與被告Ｐ○○就附表一編號23-25 之3 次\n    詐欺犯行、與被告己○○就附表一編號26-33 及附表二編號\n    7 、8 之10次詐欺犯行、與被告午○○就附表二編號1 、2\n    之2 次詐欺犯行、與被告Ｅ○○就附表二編號3 、5 之2 次\n    詐欺犯行、與被告Ｆ○○就附表二編號6 、7 之2 次詐欺犯\n    行，均有犯意聯絡與行為分擔，應論以共同正犯。被告Ｑ○\n    ○、己○○、Ｆ○○、午○○、Ｅ○○等5 人就附表二各編\n    號係以一詐騙行為同時詐騙二名被害人之財產法益，係一行\n    為而觸犯數罪名，為同種想像競合犯，應從受害人較重部分\n    處斷。另被告Ｑ○○、Ｐ○○、己○○、午○○、Ｅ○○、\n    Ｆ○○等6 人先後多次詐欺之行為，犯意各別，應予分論併\n    罰。又被告Ｑ○○、Ｐ○○有如事實欄所述之前科，有台灣\n    高等法院被告前案紀錄表在卷可查，其二人於受有期徒刑執\n    行完畢後，5 年內故意再犯本件法定刑為有期徒刑以上刑之\n    罪，為累犯，均應依刑法第47條第1 項規定加重其刑。\n  (二)上訴意旨認被告Ｑ○○在高雄市各不特定之網咖店上網，以\n    被告Ｅ○○申請之「freeapo 」、「boboto520 」、「phoh\n    evd 」、「swuaooi 」、「samwindlezz 」及「wowo 510」\n    等虛偽雅虎拍賣帳號登入雅虎拍賣網站，進行網路拍賣詐騙\n    ，被告Ｑ○○及Ｅ○○就偽冒他人名義而申請網路會員帳戶\n    使用之行為，涉犯偽造及行使偽造準私文書罪嫌，原審未予\n    審理，顯有違法等語。然按【刑事訴訟法第264 條第2 項關\n    於起訴書程式之規定，旨在界定起訴及審判之範圍，並兼顧\n    被告防禦權之行使，其中屬於絕對必要記載事項之「犯罪事\n    實」，係指犯罪構成要件之具體事實。故所謂犯罪已經起訴\n    ，係指起訴書之犯罪事實欄，已就特定犯罪構成要件之基本\n    事實，具體記載，並足據以與其他犯罪事實區分，始克當之\n    】（最高法院92年台上字第60號刑事判決參照）。查刑法第\n    220 條、第216 條及第210 條之偽造及行使偽造準私文書罪\n    ，以「偽造私文書，足以生損害於公眾或他人」為要件，此\n    項構成要件之具體事實，須於起訴書事實欄內有相當之記載\n    ，始得謂為已經起訴。本件起訴書之犯罪事實欄，對於被告\n    Ｑ○○及Ｅ○○以何人名義偽造文書，致何人生有損害均未\n    論述，且遍查卷內亦無其所指偽造「準私文書」之證據可資\n    佐證，另於起訴書被告所犯法條欄內亦未論及被告犯有此項\n    罪名。本院另查該項罪名與被告於本案論罪部分並無裁判或\n    實質上一罪關係，亦無追加起訴情形。本件原起訴書對被告\n    Ｑ○○及Ｅ○○涉犯偽造及行使偽造準私文書罪嫌之犯罪事\n    實、證據及所犯法條，既未論述，客觀上自難謂該部分犯罪\n    已依法起訴，上訴意旨遽謂該「偽造及行使偽造準私文書罪\n    」部分已經起訴，尚有誤會。\n  (三)另公訴人認被告Ｐ○○提供予被告Ｑ○○集團使用之「盧祥\n    龍所有，帳號00000000000000號上海商業銀行」帳號，除有\n    判決書附表一編號23-25 之被害人外，尚有閔昭夏及施文壹\n    （見警三卷第75、76頁），被害金額分為29,989元及360,22\n    8 元，此部分與已起訴部分（即提供詐騙他人使用之金融機\n    構人頭帳戶之行為）具同種想像競合之裁判上一罪關係，原\n    審未及審酌，有已受請求事項未予判決之違法情形。惟查：\n    被告毆永毅及Ｐ○○對附表一、二之犯行，均係95年7 月1\n    日刑法修正後所犯，且其2 人所犯上開詐欺罪均屬一罪一罰\n    之數罪併罰情形，公訴人於原起訴書既未對被害人閔昭夏及\n    施文壹部分予以起訴，原審法院自不得予以審理，應由檢察\n    官另行追加起訴或另行起訴，始為適法。上訴意旨認該被害\n    人部分與本案有屬裁判上一罪關係，亦屬誤會。\n  (四)原審據以論處被告罪刑，固非無見；惟查：(1)有罪之判決書\n    應記載事實，所謂事實不僅指犯罪行為而言，即犯罪之動機\n    、目的、手段、結果等，與論罪科刑有關之事項，亦應依法\n    認定予以明確之記載（最高法院90年台上字第5510號刑事判\n    決參照）。本件原判決認定被告Ｑ○○等人有附表一所示之\n    詐欺犯行，惟其對被告販售何種商品，何以有不法所有之犯\n    罪意圖均未於犯罪事實載明，且於附表一之各欄項次下，亦\n    未認定記載，自難謂屬適法。(2)按量刑之輕重，固屬事實審\n    法院得依職權自由裁量之事項，惟仍應受比例原則及公平原\n    則之限制，否則其判決即非適法。刑事審判旨在實現刑罰權\n    分配的正義，故法院對有罪被告之科刑，應符合罪刑相當之\n    原則，使輕重得宜，罰當其罪，以契合社會之法律感情，此\n    所以刑法第57條明定科刑時應審酌一切情狀，尤應注意該條\n    各款所列事項以為科刑輕重之標準（最高法院93年度台上字\n    第5073號判決意旨參照）。查被告Ｑ○○等人共同以網路購\n    物對於網路尋交易之被害人予以詐騙，渠等犯罪事前計畫縝\n    密，嚴重敗壞社會風氣，危害國內商場交易秩序與社會互信\n    甚鉅，量刑實難寬待，且本件被害人被詐騙金額不一，低則\n    詐騙數千元，高則詐騙十幾萬元，另被告庚○○、壬○○收\n    受贓物之情節非一，所得利益亦不相同，如均量處同一刑責\n    ，實有違公平及比例原則，原審對此漏未審酌，難認妥適。\n    (3)被告Ｑ○○、己○○、Ｆ○○、午○○、Ｅ○○等5 人就\n    附表二各編號犯行，係以一詐騙行為同時詐騙二名被害人之\n    財產法益，係一行為而觸犯數罪名，為同種想像競合犯，應\n    從受害人較重部分處斷。原審對附表二各編號內之犯行論以\n    二罪，尚有未洽。檢察官以原審量刑過輕不當提起上訴，為\n    屬有據，且原審亦有上開可議之處，自應由本院將原判決有\n    罪部分暨定執行刑部分予以撤銷改判。\n  (五)爰審酌被告Ｑ○○、Ｐ○○、己○○、午○○、Ｅ○○、Ｆ\n    ○○等6 人，均年輕力壯，不思努力工作，竟利用網路交易\n    較一般交易為隱匿之特性，與網路交易平台無力全面清查真\n    正帳號使用者之弱點，及網路交易相對人為圖一時之便利而\n    有疏忽之際，從事網路詐騙之行為，破壞網路交易安全，對\n    被害人財產及社會秩序危害重大，嚴重影響社會互信，國人\n    深惡痛絕，且被告Ｑ○○就上開犯行，係處於主導地位，而\n    被告Ｐ○○、己○○、午○○、Ｅ○○、Ｆ○○則係分別擔\n    任車手收款或收取所購物品工作，及犯罪期間、次數、所得\n    ，且僅與部分被害人達成和解，兼衡各被告犯罪動機、目的\n    、手段、所生損害及犯後態度等一切情狀，各量處如主文所\n    示之刑及就被告庚○○、壬○○、Ｅ○○3 人諭知易科罰金\n    之折算標準，並定其應執行刑及諭知易科罰金之折算標準（\n    其中被告Ｅ○○部分，刑法第41條第2 項於被告行為時原規\n    定：「前項規定於數罪併罰，其應執行之刑未逾6 月者，亦\n    適用之」，於98年12月30日新法修正為第41條第8 項，其內\n    容為：「第一項至第4 項及第7 項之規定，於數罪併罰之數\n    罪均得易科罰金或易服社會勞動，其應執行之刑逾6 月者，\n    亦適用之」，兩相比較，新法易科罰金於數罪併罰之數罪均\n    得易科罰金或易服社會勞動，且不受應執行6 月之限制，是\n    比較新舊法結果，以適用修正後之刑法規定較為有利），又\n    被告Ｑ○○係網路購物詐欺集團之主導人，其於97年6 月10\n    日至同年12月10日遭查獲時止，於密集時間內詐騙多達41件\n    犯行，其手段具有同質性，顯係有犯罪之習慣及再犯之可能\n    性，僅藉刑罰之執行尚不足以根絕其惡性，並依據其行為之\n    嚴重性、所表現之危險性及對其未來行為之期待性等情，為\n    矯正其不良習性，爰對其情節最重之附表二編號1 被害人汪\n    婉宜部分，依刑法第90條規定併為被告Ｑ○○應於刑之執行\n    前，令入勞動處所強制工作3 年之諭知。\n  (六)又按「刑法上沒收因犯罪所得之物，應指因犯罪行為直接所\n    產生或取得特定之原物，故除法律規定得追徵價額或其他特\n    別之規定外，因變賣盜贓或侵占之物所得之價金，既非因犯\n    罪直接所取得特定之物，自不得為沒收之對象」、「刑罰之\n    執行，係對於人身及財產之侵害，應止於犯罪行為人之一身\n    為原則。沒收為刑罰之一種；刑法上所謂屬於犯罪行為人因\n    犯罪所得之沒收物，乃指無他人對於該物得主張法律上之權\n    利者而言；倘該物原屬被害人所有，而為犯罪行為人因犯罪\n    而取得或變易獲得，該被害人既仍得對之為法律上權利之主\n    張，自難認該當於沒收之要件。」，有最高法院70年度台上\n    字第5569號、96年度台上字第5390判決，可資參照。扣案附\n    表三編號1 至13、16、20、36-40 、42、43所示之物雖各為\n    上開被告所有，但無從證明係供被告為本案所涉49件中之何\n    件犯行所用，且俱係偶供犯罪所用，並非不能為正常使用之\n    物，亦無沒收之實益，爰不沒收。附表三編號21至32雖為Ｐ\n    ○○所有，但不能證明與本案有關，亦不沒收。附表三編號\n    14 、15 、17、18、19、33、34、35、41，雖係被告Ｑ○○\n    等人詐欺所得之財物或所變得之財物，被害人尚得對之為法\n    律上權利之主張，參照上開說明，均不沒收，應另由執行機\n    關另為適法之處理。附表三編號44、45則與本案無關，自無\n    庸於本件宣告沒收。\n三、被告Ｐ○○被訴與被告Ｑ○○等人共同為附表一編號1 至22\n    、26至33及附表二編號1 至8 之詐欺犯行，業經原審判決無\n    罪，檢察官未據上訴而告確定，併予敘明。\n據上論結，應依刑事訴訟法第369 條第1 項前段、第364 條、第\n299 條第1 項前段，刑法第2 條第1 項、第28條、第339 條第1\n項、第349 條第1 項、第55條、第47條第1 項、第41條第1 項前\n段、第51條笫5 款、第90條，98年12月30日新修正刑法第41條第\n8 項，刑法施行法第1 條之1 ，判決如主文。\n本案經檢察官許月雲到庭執行職務。\n中    華    民    國    99    年    1     月    5     日\n                  刑事第一庭    審判長法  官  周賢銳\n                                      法  官  徐美麗\n                                      法  官  施柏宏\n以上正本證明與原本無異。\n不得上訴。\n中    華    民    國    99    年    1     月    5     日\n                                      書記官  魏文常\n附表一：犯罪事實二部分\n┌─┬─────┬─────┬─────────┬───┬───┬────┬───┬───┬───┬───────────┐\n│編│詐騙電話  │詐騙拍賣帳│匯入金融帳號      │帳號所│被害人│匯款日期│提款人│被騙  │被告  │主文                  │\n│號│          │號        │                  │有人  │      │        │      │金額  │      │                      │\n├─┼─────┼─────┼─────────┼───┼───┼────┼───┼───┼───┼───────────┤\n│1 │0000000000│weekenid  │000-00000000000000│潘韋德│Ａ○○│97.06.10│Ｑ○○│10000 │Ｑ○○│Ｑ○○犯詐欺取財罪，累│\n│  │          │          │                  │      │      │        │      │      │      │犯，處有期徒刑伍月。  │\n├─┼─────┼─────┼─────────┼───┼───┼────┼───┼───┼───┼───────────┤\n│2 │0000000000│weekenid  │000-00000000000000│潘韋德│戌○○│97.06.11│Ｑ○○│7650  │Ｑ○○│Ｑ○○犯詐欺取財罪，累│\n│  │          │          │                  │      │      │        │      │      │      │犯，處有期徒刑肆月。  │\n├─┼─────┼─────┼─────────┼───┼───┼────┼───┼───┼───┼───────────┤\n│3 │0000000000│weekenid  │000-00000000000000│潘韋德│地○○│97.06.13│Ｑ○○│4600  │Ｑ○○│Ｑ○○犯詐欺取財罪，累│\n│  │          │          │                  │      │      │        │      │      │      │犯，處有期徒刑肆月。  │\n├─┼─────┼─────┼─────────┼───┼───┼────┼───┼───┼───┼───────────┤\n│4 │0000000000│weekenid  │000-00000000000000│潘韋德│Ｓ○○│97.06.13│Ｑ○○│18400 │Ｑ○○│Ｑ○○犯詐欺取財罪，累│\n│  │          │          │                  │      │      │        │      │      │      │犯，處有期徒刑伍月。  │\n├─┼─────┼─────┼─────────┼───┼───┼────┼───┼───┼───┼───────────┤\n│5 │0000000000│weekenid  │000-00000000000000│曾光展│Ｄ○○│97.06.15│Ｑ○○│33000 │Ｑ○○│Ｑ○○犯詐欺取財罪，累│\n│  │0000000000│          │                  │      │      │        │      │      │      │犯，處有期徒刑陸月。  │\n├─┼─────┼─────┼─────────┼───┼───┼────┼───┼───┼───┼───────────┤\n│6 │0000000000│hoorscopes│000-00000000000000│葉凱文│丙○○│97.06.29│Ｑ○○│7000  │Ｑ○○│Ｑ○○犯詐欺取財罪，累│\n│  │0000000000│          │                  │      │      │        │      │      │      │犯，處有期徒刑肆月。  │\n├─┼─────┼─────┼─────────┼───┼───┼────┼───┼───┼───┼───────────┤\n│7 │0000000000│hoorscooes│000-00000000000000│葉凱文│Ｈ○○│97.07.02│Ｑ○○│2000  │Ｑ○○│Ｑ○○犯詐欺取財罪，累│\n│  │          │          │                  │      │      │        │      │      │      │犯，處有期徒刑肆月。  │\n├─┼─────┼─────┼─────────┼───┼───┼────┼───┼───┼───┼───────────┤\n│8 │0000000000│hoorscopes│000-00000000000000│葉凱文│Ｗ○○│97.07.03│Ｑ○○│5000  │Ｑ○○│Ｑ○○犯詐欺取財罪，累│\n│  │0000000000│          │                  │      │      │        │      │      │      │犯，處有期徒刑肆月。  │\n├─┼─────┼─────┼─────────┼───┼───┼────┼───┼───┼───┼───────────┤\n│9 │0000000000│          │000-00000000000000│葉凱文│卯○○│97.07.04│Ｑ○○│3400（│Ｑ○○│Ｑ○○犯詐欺取財罪，累│\n│  │0000000000│          │                  │      │      │        │      │起訴書│      │犯，處有期徒刑肆月。  │\n│  │0000000000│          │                  │      │      │        │      │誤載為│      │                      │\n│  │          │          │                  │      │      │        │      │2000）│      │                      │\n├─┼─────┼─────┼─────────┼───┼───┼────┼───┼───┼───┼───────────┤\n│10│0000000000│hoorscooes│000-00000000000000│林政慶│Ｙ○○│97.07.07│Ｑ○○│10000 │Ｑ○○│Ｑ○○犯詐欺取財罪，累│\n│  │          │          │                  │      │      │        │      │      │      │犯，處有期徒刑伍月。  │\n├─┼─────┼─────┼─────────┼───┼───┼────┼───┼───┼───┼───────────┤\n│11│0000000000│hoorscopes│000-0000000000000 │蘇育民│Ｘ○○│97.07.20│Ｑ○○│2500  │Ｑ○○│Ｑ○○犯詐欺取財罪，累│\n│  │          │          │                  │      │      │        │      │      │      │犯，處有期徒刑肆月。  │\n├─┼─────┼─────┼─────────┼───┼───┼────┼───┼───┼───┼───────────┤\n│12│0000000000│hoorscopes│000-0000000000000 │蘇育民│Ｖ○○│97.07.21│Ｑ○○│9000  │Ｑ○○│Ｑ○○犯詐欺取財罪，累│\n│  │          │          │                  │      │      │        │      │      │      │犯，處有期徒刑肆月。  │\n├─┼─────┼─────┼─────────┼───┼───┼────┼───┼───┼───┼───────────┤\n│13│0000000000│phohevd   │000-00000000000000│吳育慈│宇○○│97.08.20│Ｑ○○│10000 │Ｑ○○│Ｑ○○犯詐欺取財罪，累│\n│  │          │          │                  │      │      │        │      │      │      │犯，處有期徒刑伍月。  │\n├─┼─────┼─────┼─────────┼───┼───┼────┼───┼───┼───┼───────────┤\n│14│0000000000│boboto520 │（ibon）          │      │辛○○│97.09.12│Ｑ○○│5025  │Ｑ○○│Ｑ○○犯詐欺取財罪，累│\n│  │          │          │                  │      │      │        │      │      │      │犯，處有期徒刑肆月。  │\n├─┼─────┼─────┼─────────┼───┼───┼────┼───┼───┼───┼───────────┤\n│15│0000000000│boboto520 │（ibon）          │      │Ｍ○○│97.09.25│Ｑ○○│20000 │Ｑ○○│Ｑ○○犯詐欺取財罪，累│\n│  │          │          │                  │      │      │        │      │      │      │犯，處有期徒刑伍月。  │\n├─┼─────┼─────┼─────────┼───┼───┼────┼───┼───┼───┼───────────┤\n│16│0000000000│boboto520 │（ibon）          │      │Ｋ○○│97.09.27│Ｑ○○│27075 │Ｑ○○│Ｑ○○犯詐欺取財罪，累│\n│  │          │          │                  │      │      │        │      │      │      │犯，處有期徒刑伍月。  │\n├─┼─────┼─────┼─────────┼───┼───┼────┼───┼───┼───┼───────────┤\n│17│0000000000│kosopro   │000-00000000000000│陳重榮│Ｏ○○│97.10.11│Ｑ○○│19000 │Ｑ○○│Ｑ○○犯詐欺取財罪，累│\n│  │          │@kimo.com │                  │      │      │        │      │      │      │犯，處有期徒刑伍月。  │\n├─┼─────┼─────┼─────────┼───┼───┼────┼───┼───┼───┼───────────┤\n│18│0000000000│kosopro   │000-00000000000000│洪艾媚│天○○│97.10.15│Ｑ○○│14600 │Ｑ○○│Ｑ○○犯詐欺取財罪，累│\n│  │0000000000│@kimo.com │                  │      │      │        │      │      │      │犯，處有期徒刑伍月。  │\n├─┼─────┼─────┼─────────┼───┼───┼────┼───┼───┼───┼───────────┤\n│19│0000000000│samwindles│000-00000000000000│陳重榮│甲○○│97.10.15│Ｑ○○│9400  │Ｑ○○│Ｑ○○犯詐欺取財罪，累│\n│  │          │samwindles│                  │      │      │        │      │      │      │犯，處有期徒刑肆月。  │\n│  │          │@kimo.com │                  │      │      │        │      │      │      │                      │\n├─┼─────┼─────┼─────────┼───┼───┼────┼───┼───┼───┼───────────┤\n│20│0000000000│kosopro   │000-00000000000000│洪艾媚│陳騏竤│97.10.16│Ｑ○○│7500  │Ｑ○○│Ｑ○○犯詐欺取財罪，累│\n│  │0000000000│@kimo.com │                  │      │      │        │      │      │      │犯，處有期徒刑肆月。  │\n├─┼─────┼─────┼─────────┼───┼───┼────┼───┼───┼───┼───────────┤\n│21│0000000000│          │000-00000000000000│洪艾媚│子○○│97.10.16│Ｑ○○│15000 │Ｑ○○│Ｑ○○犯詐欺取財罪，累│\n│  │0000000000│          │                  │      │      │        │      │      │      │犯，處有期徒刑伍月。  │\n├─┼─────┼─────┼─────────┼───┼───┼────┼───┼───┼───┼───────────┤\n│22│0000000000│kosopro   │000-00000000000000│廖品臻│丁○○│97.10.30│Ｑ○○│8000  │Ｑ○○│Ｑ○○犯詐欺取財罪，累│\n│  │          │@kimo.com │                  │      │      │        │      │      │      │犯，處有期徒刑肆月。  │\n├─┼─────┼─────┼─────────┼───┼───┼────┼───┼───┼───┼───────────┤\n│23│0000000000│freeappo  │000-00000000000000│盧祥龍│Ｃ○○│97.11.01│Ｐ○○│27750 │Ｑ○○│Ｑ○○共同犯詐欺取財罪│\n│  │          │          │                  │      │      │        │      │      │Ｐ○○│，累犯，處有期徒刑伍月│\n│  │          │          │                  │      │      │        │      │      │      │。                    │\n│  │          │          │                  │      │      │        │      │      │      │Ｐ○○共同犯詐欺取財罪│\n│  │          │          │                  │      │      │        │      │      │      │，累犯，處有期徒刑肆月│\n│  │          │          │                  │      │      │        │      │      │      │。                    │\n├─┼─────┼─────┼─────────┼───┼───┼────┼───┼───┼───┼───────────┤\n│24│0000000000│kosopro   │000-00000000000000│盧祥龍│戊○○│97.11.01│Ｐ○○│20500 │Ｑ○○│Ｑ○○共同犯詐欺取財罪│\n│  │          │@kimo.com │                  │      │      │        │      │      │Ｐ○○│，累犯，處有期徒刑伍月│\n│  │          │          │                  │      │      │        │      │      │      │。                    │\n│  │          │          │                  │      │      │        │      │      │      │Ｐ○○共同犯詐欺取財罪│\n│  │          │          │                  │      │      │        │      │      │      │，累犯，處有期徒刑肆月│\n│  │          │          │                  │      │      │        │      │      │      │。                    │\n├─┼─────┼─────┼─────────┼───┼───┼────┼───┼───┼───┼───────────┤\n│25│0000000000│freeappo  │000-00000000000000│盧祥龍│Ｂ○○│97.11.02│Ｐ○○│50000 │Ｑ○○│Ｑ○○共同犯詐欺取財罪│\n│  │          │          │                  │      │      │        │      │      │Ｐ○○│，累犯，處有期徒刑玖月│\n│  │          │          │                  │      │      │        │      │      │      │。                    │\n│  │          │          │                  │      │      │        │      │      │      │Ｐ○○共同犯詐欺取財罪│\n│  │          │          │                  │      │      │        │      │      │      │，累犯，處有期徒刑柒月│\n│  │          │          │                  │      │      │        │      │      │      │。                    │\n├─┼─────┼─────┼─────────┼───┼───┼────┼───┼───┼───┼───────────┤\n│26│0000000000│wowo510   │000-00000000000000│解順發│Ｒ○○│97.11.20│己○○│81900 │Ｑ○○│Ｑ○○共同犯詐欺取財罪│\n│  │0000000000│          │                  │      │      │        │      │      │己○○│，累犯，處有期徒刑拾月│\n│  │          │          │                  │      │      │        │      │      │      │。                    │\n│  │          │          │                  │      │      │        │      │      │      │己○○共同犯詐欺取財罪│\n│  │          │          │                  │      │      │        │      │      │      │，處有期徒刑捌月。    │\n├─┼─────┼─────┼─────────┼───┼───┼────┼───┼───┼───┼───────────┤\n│27│0000000000│wowo510   │000-00000000000000│解順發│癸○○│97.11.22│己○○│50900 │Ｑ○○│Ｑ○○共同犯詐欺取財罪│\n│  │0000000000│          │                  │      │      │        │      │      │己○○│，累犯，處有期徒刑玖月│\n│  │          │          │                  │      │      │        │      │      │      │。                    │\n│  │          │          │                  │      │      │        │      │      │      │己○○共同犯詐欺取財罪│\n│  │          │          │                  │      │      │        │      │      │      │，處有期徒刑柒月。    │\n├─┼─────┼─────┼─────────┼───┼───┼────┼───┼───┼───┼───────────┤\n│28│0000000000│wowo510   │000-00000000000   │解順發│Ｔ○○│97.11.24│己○○│136000│Ｑ○○│Ｑ○○共同犯詐欺取財罪│\n│  │0000000000│          │                  │      │      │        │      │      │己○○│，累犯，處有期徒刑壹年│\n│  │          │          │                  │      │      │        │      │      │      │。                    │\n│  │          │          │                  │      │      │        │      │      │      │己○○共同犯詐欺取財  │\n│  │          │          │                  │      │      │        │      │      │      │罪，處有期徒刑拾月。  │\n├─┼─────┼─────┼─────────┼───┼───┼────┼───┼───┼───┼───────────┤\n│29│0000000000│wowo510   │000-00000000000   │解順發│寅○○│97.11.24│己○○│9200  │Ｑ○○│Ｑ○○共同犯詐欺取財罪│\n│  │0000000000│          │                  │      │      │        │      │      │己○○│，累犯，處有期徒刑肆月│\n│  │          │          │                  │      │      │        │      │      │      │。                    │\n│  │          │          │                  │      │      │        │      │      │      │己○○共同犯詐欺取財  │\n│  │          │          │                  │      │      │        │      │      │      │罪，處有期徒刑參月。  │\n├─┼─────┼─────┼─────────┼───┼───┼────┼───┼───┼───┼───────────┤\n│30│0000000000│dolcegabba│000-000000000000  │      │辰○○│97.11.27│己○○│22000 │Ｑ○○│Ｑ○○共同犯詐欺取財罪│\n│  │0000000000│@kimo.com │                  │      │      │        │      │      │己○○│，累犯，處有期徒刑伍月│\n│  │          │          │                  │      │      │        │      │      │      │。                    │\n│  │          │          │                  │      │      │        │      │      │      │己○○共同犯詐欺取財罪│\n│  │          │          │                  │      │      │        │      │      │      │，處有期徒刑參月      │\n│  │          │          │                  │      │      │        │      │      │      │。                    │\n├─┼─────┼─────┼─────────┼───┼───┼────┼───┼───┼───┼───────────┤\n│31│0000000000│wowo510   │000-0000000000000 │盧建達│亥○○│97.12.06│己○○│18400 │Ｑ○○│Ｑ○○共同犯詐欺取財罪│\n│  │          │          │                  │      │      │        │      │      │己○○│，累犯，處有期徒刑伍月│\n│  │          │          │                  │      │      │        │      │      │      │。                    │\n│  │          │          │                  │      │      │        │      │      │      │己○○共同犯詐欺取財  │\n│  │          │          │                  │      │      │        │      │      │      │罪，處有期徒刑參月。  │\n├─┼─────┼─────┼─────────┼───┼───┼────┼───┼───┼───┼───────────┤\n│32│0000000000│wowo510   │000-00000000000000│李維芳│陳曉娟│97.12.10│己○○│27450 │Ｑ○○│Ｑ○○共同犯詐欺取財罪│\n│  │          │          │                  │      │      │        │      │      │己○○│，累犯，處有期徒刑伍月│\n│  │          │          │                  │      │      │        │      │      │      │。                    │\n│  │          │          │                  │      │      │        │      │      │      │己○○共同犯詐欺取財罪│\n│  │          │          │                  │      │      │        │      │      │      │，處有期徒刑參月。    │\n├─┼─────┼─────┼─────────┼───┼───┼────┼───┼───┼───┼───────────┤\n│33│0000000000│wowo510   │000-00000000000000│李維芳│Ｇ○○│97.12.10│己○○│45470 │Ｑ○○│Ｑ○○共同犯詐欺取財罪│\n│  │          │          │                  │      │      │        │      │      │己○○│，累犯，處有期徒刑陸月│\n│  │          │          │                  │      │      │        │      │      │      │。                    │\n│  │          │          │                  │      │      │        │      │      │      │己○○共同犯詐欺取財罪│\n│  │          │          │                  │      │      │        │      │      │      │，處有期徒刑肆月。    │\n└─┴─────┴─────┴─────────┴───┴───┴────┴───┴───┴───┴───────────┘\n附表二：犯罪事實三部分\n┌─┬───┬─────┬────┬────┬────┬───┬────┬─┬─┬───┬──────────────┬──┐\n│編│被害人│買賣物品  │金融帳號│詐騙電話│詐騙雅虎│遭詐騙│匯款日期│取│變│被告  │主文                        │備註│\n│號│      │          │        │        │帳號    │金額  │        │貨│賣│      │                            │    │\n│  │      │          │        │        │        │      │        │人│之│      │                            │    │\n│  │      │          │        │        │        │      │        │  │人│      │                            │    │\n├─┼───┼─────┼────┼────┼────┼───┼────┼─┼─┼───┼──────────────┼──┤\n│1 │Ｊ○○│賣手錶    │000-0000│0916    │        │163200│        │歐│歐│Ｑ○○│Ｑ○○共同犯詐欺取財罪，累犯│    │\n│  │      │          │00000000│094932  │        │      │        │永│永│午○○│，處有期徒刑壹年肆月，並於刑│    │\n│  │      │          │        │0927    │        │      │        │毅│毅│      │之執行前，令入勞動處所強制工│    │\n│  │      │          │        │139548  │        │      │        │、│、│      │作參年。                    │    │\n│  │      │          │        │        │        │      │        │林│林│      │午○○共同犯詐欺取財罪，處有│    │\n│  │      │          │        │        │        │      │        │上│上│      │期徒刑壹年。                │    │\n│  ├───┼─────┼────┼────┼────┼───┼────┤富│富├───┤                            ├──┤\n│  │巳○○│買禮券    │        │0916    │weekenid│163200│97.06.16│  │  │Ｑ○○│                            │    │\n│  │      │          │        │094932  │        │      │        │  │  │午○○│                            │    │\n├─┼───┼─────┼────┼────┼────┼───┼────┼─┼─┼───┼──────────────┼──┤\n│2 │丑○○│賣手錶    │000-0000│        │        │10000 │        │林│  │Ｑ○○│Ｑ○○共同犯詐欺取財罪，累犯│    │\n│  │      │          │0000000 │        │        │      │        │上│  │午○○│，處有期徒刑柒月。          │    │\n│  │      │          │        │        │        │      │        │富│  │      │午○○共同犯詐欺取財罪，處有│    │\n│  │      │          │        │        │        │      │        │  │  │      │期徒刑伍月。                │    │\n│  ├───┼─────┼────┼────┼────┼───┼────┤  │  ├───┤                            ├──┤\n│  │卯○○│買虛擬寶物│        │0925    │        │13400 │97.07.07│  │  │Ｑ○○│                            │另34│\n│  │      │          │        │616444  │        │      │        │  │  │午○○│                            │00  │\n│  │      │          │        │        │        │      │        │  │  │      │                            │元匯│\n│  │      │          │        │        │        │      │        │  │  │      │                            │入葉│\n│  │      │          │        │        │        │      │        │  │  │      │                            │凱文│\n│  │      │          │        │        │        │      │        │  │  │      │                            │帳戶│\n├─┼───┼─────┼────┼────┼────┼───┼────┼─┼─┼───┼──────────────┼──┤\n│3 │乙○○│賣手錶    │000-0000│0935    │        │18000 │        │歐│陳│Ｑ○○│Ｑ○○共同犯詐欺取財罪，累犯│    │\n│  │      │          │00000000│312850  │        │      │        │永│志│Ｅ○○│，處有期徒柒月。            │    │\n│  │      │          │10      │        │        │      │        │毅│宏│      │Ｅ○○共同犯詐欺取財罪，處有│    │\n│  │      │          │        │        │        │      │        │  │  │      │期徒刑伍月，如易科罰金，以新│    │\n│  │      │          │        │        │        │      │        │  │  │      │臺幣壹仟元折算壹日。        │    │\n│  ├───┼─────┼────┼────┼────┼───┼────┤  │  ├───┤                            ├──┤\n│  │Ｉ○○│買禮券    │        │0927    │swuaooi │18000 │97.07.24│  │  │Ｑ○○│                            │    │\n│  │      │          │        │144178  │        │      │        │  │  │Ｅ○○│                            │    │\n├─┼───┼─────┼────┼────┼────┼───┼────┼─┼─┼───┼──────────────┼──┤\n│4 │乙○○│賣手錶    │000-0000│0935    │        │13120 │        │歐│  │Ｑ○○│Ｑ○○犯詐欺取財罪，累犯，處│    │\n│  │      │          │00000000│312850  │        │      │        │永│  │      │有期徒刑柒月。              │    │\n│  │      │          │10      │        │        │      │        │毅│  │      │                            │    │\n│  ├───┼─────┼────┼────┼────┼───┼────┤  │  ├───┤                            ├──┤\n│  │未○○│買禮券    │        │0927    │swuaooi │13120 │97.07.25│  │  │Ｑ○○│                            │    │\n│  │      │          │        │144178  │        │      │        │  │  │      │                            │    │\n├─┼───┼─────┼────┼────┼────┼───┼────┼─┼─┼───┼──────────────┼──┤\n│5 │玄○○│賣液晶螢幕│000-0000│0935    │        │4500  │        │陳│  │Ｑ○○│Ｑ○○共同犯詐欺取財罪，累犯│    │\n│  │      │          │00000000│312850  │        │      │        │志│  │Ｅ○○│，處有期徒刑陸月。          │    │\n│  │      │          │00      │        │        │      │        │宏│  │      │Ｅ○○共同犯詐欺取財罪，處有│    │\n│  │      │          │        │        │        │      │        │  │  │      │期徒刑肆月，如易科罰金，以新│    │\n│  │      │          │        │        │        │      │        │  │  │      │臺幣壹仟元折算壹日。        │    │\n│  ├───┼─────┼────┼────┼────┼───┼────┤  │  ├───┤                            ├──┤\n│  │黃○○│買禮券    │        │0935    │phohevd │4500  │97.08.25│  │  │Ｑ○○│                            │    │\n│  │      │          │        │312850  │        │      │        │  │  │Ｅ○○│                            │    │\n├─┼───┼─────┼────┼────┼────┼───┼────┼─┼─┼───┼──────────────┼──┤\n│6 │酉○○│賣手錶    │000-0000│0983    │        │93000 │        │歐│陳│Ｑ○○│Ｑ○○共同犯詐欺取財罪，累犯│    │\n│  │      │          │0000000 │044053  │        │      │        │永│忠│Ｆ○○│，處有期徒刑壹年。          │    │\n│  │      │          │        │        │        │      │        │毅│宏│      │Ｆ○○共同犯詐欺取財罪，處  │    │\n│  │      │          │        │        │        │      │        │  │  │      │有期徒刑拾月。              │    │\n│  ├───┼─────┼────┼────┼────┼───┼────┤  │  ├───┤                            ├──┤\n│  │Ｕ○○│買禮券    │        │0983    │freeappo│93000 │97.10.17│  │  │Ｑ○○│                            │    │\n│  │      │          │        │044053  │        │      │        │  │  │Ｆ○○│                            │    │\n├─┼───┼─────┼────┼────┼────┼───┼────┼─┼─┼───┼──────────────┼──┤\n│7 │Ｎ○○│賣手錶    │000-0000│0927開頭│        │100000│        │陳│吳│Ｑ○○│Ｑ○○共同犯詐欺取財罪，累犯│    │\n│  │      │          │00000000│        │        │      │        │忠│俊│Ｆ○○│，處有期徒刑壹年貳月。      │    │\n│  │      │          │32      │        │        │      │        │宏│煌│己○○│Ｆ○○共同犯詐欺取財罪，處有│    │\n│  │      │          │        │        │        │      │        │、│、│      │期徒刑拾月。                │    │\n│  │      │          │        │        │        │      │        │歐│吳│      │己○○共同犯詐欺取財罪，處有│    │\n│  │      │          │        │        │        │      │        │永│振│      │期徒刑拾月。                │    │\n│  │      │          │        │        │        │      │        │毅│輝│      │                            │    │\n│  ├───┼─────┼────┼────┼────┼───┼────┤  │  ├───┤                            ├──┤\n│  │Ｂ○○│買禮券    │        │0927    │freeappo│150000│97.11.03│  │  │Ｑ○○│                            │另  │\n│  │      │          │        │059221  │        │      │        │  │  │Ｆ○○│                            │5000│\n│  │      │          │        │        │        │      │        │  │  │己○○│                            │元匯│\n│  │      │          │        │        │        │      │        │  │  │      │                            │入盧│\n│  │      │          │        │        │        │      │        │  │  │      │                            │祥龍│\n│  │      │          │        │        │        │      │        │  │  │      │                            │帳戶│\n├─┼───┼─────┼────┼────┼────┼───┼────┼─┼─┼───┼──────────────┼──┤\n│8 │宙○○│賣手錶    │000-0000│        │        │46000 │        │歐│呂│Ｑ○○│Ｑ○○共同犯詐欺取財罪，累犯│變賣│\n│  │      │          │338323  │        │        │      │        │永│銘│己○○│，處有期徒刑拾月。          │得款│\n│  │      │          │        │        │        │      │        │毅│霖│      │己○○共同犯詐欺取財罪，處有│5000│\n│  │      │          │        │        │        │      │        │、│  │      │期徒刑捌月。                │元  │\n│  │      │          │        │        │        │      │        │吳│  │      │                            │    │\n│  │      │          │        │        │        │      │        │俊│  │      │                            │    │\n│  │      │          │        │        │        │      │        │煌│  │      │                            │    │\n│  ├───┼─────┼────┼────┼────┼───┼────┤  │  ├───┤                            ├──┤\n│  │申○○│買禮券    │        │0938    │freeappo│46000 │97.11.06│  │  │Ｑ○○│                            │    │\n│  │      │          │        │310647  │        │      │        │  │  │己○○│                            │    │\n└─┴───┴─────┴────┴────┴────┴───┴────┴─┴─┴───┴──────────────┴──┘\n 附表三：扣押物品明細\n   ┌──┬──────────────┬──┬────────────┐\n   │編號│項目                        │數量│所有人                  │\n   ├──┼──────────────┼──┼────────────┤\n   │ 1  │筆記本                      │1本 │Ｑ○○。扣押處所：高雄市│\n   │    │                            │    │光華路及一心路口（85 度C│\n   │    │                            │    │前                      │\n   ├──┼──────────────┼──┼────────────┤\n   │ 2  │天堂遊戲帳號、匯款帳戶、8591│1本 │                        │\n   │    │支出收入金額、Ibon代碼等筆記│    │同上                    │\n   │    │本、紙條                    │    │                        │\n   ├──┼──────────────┼──┼────────────┤\n   │ 3  │遊戲帳號密碼、網路購物用筆記│1本 │                        │\n   │    │本                          │    │同上                    │\n   ├──┼──────────────┼──┼────────────┤\n   │ 4  │第一銀行存摺00000000000     │3本 │同上                    │\n   ├──┼──────────────┼──┼────────────┤\n   │ 5  │SAMSUNG手機（0000000000）   │1支 │                        │\n   │    │000000000000000             │    │同上                    │\n   ├──┼──────────────┼──┼────────────┤\n   │ 6  │SAMSUNG手機（0000000000）   │1支 │                        │\n   │    │000000000000000             │    │同上                    │\n   ├──┼──────────────┼──┼────────────┤\n   │ 7  │NOKIA手機（0000000000）     │1支 │                        │\n   │    │000000000000000             │    │同上                    │\n   ├──┼──────────────┼──┼────────────┤\n   │ 8  │第一銀行金融卡00000000000   │1張 │同上                    │\n   ├──┼──────────────┼──┼────────────┤\n   │ 9  │郵局金融卡00000000000000    │1張 │同上                    │\n   ├──┼──────────────┼──┼────────────┤\n   │ 10 │大卡空卡0000000000          │1張 │同上                    │\n   ├──┼──────────────┼──┼────────────┤\n   │ 11 │大卡空卡0000000000          │1張 │同上                    │\n   ├──┼──────────────┼──┼────────────┤\n   │ 12 │船員外勞卡空卡0000000000    │1張 │同上                    │\n   ├──┼──────────────┼──┼────────────┤\n   │ 13 │IC電話卡                    │2張 │同上                    │\n   ├──┼──────────────┼──┼────────────┤\n   │ 14 │鋼製手環、戒指              │2只 │同上                    │\n   ├──┼──────────────┼──┼────────────┤\n   │ 15 │現金2,800元                 │    │同上                    │\n   ├──┼──────────────┼──┼────────────┤\n   │ 16 │身分證影本                  │1張 │同上                    │\n   ├──┼──────────────┼──┼────────────┤\n   │ 17 │BMW汽車（5318-TG）          │1台 │同上                    │\n   ├──┼──────────────┼──┼────────────┤\n   │ 18 │OMEGA海馬系列手錶           │1支 │同上                    │\n   ├──┼──────────────┼──┼────────────┤\n   │ 19 │VIEWSONIC液晶螢幕（型號     │1台 │Ｑ○○。扣押處所：高雄市│\n   │    │VA2216W）                   │    │苓雅區○○街89號9樓之3  │\n   ├──┼──────────────┼──┼────────────┤\n   │ 20 │SONYERICSSON手機            │1支 │同上                    │\n   │    │（000000000000000）         │    │                        │\n   ├──┼──────────────┼──┼────────────┤\n   │ 21 │各式手機(不含門號SIM卡）    │43支│Ｐ○○。扣押處所：高雄市│\n   │    │（詳警卷76-83頁）           │    │光華路及一心路口（85度C │\n   ├──┼──────────────┼──┼────────────┤\n   │ 22 │各式手機(含SIM卡、門號      │    │同上                    │\n   │    │0000000000、0000000000、    │7支 │                        │\n   │    │0000000000、0000000000、    │    │                        │\n   │    │0000000000、0000000000、    │    │                        │\n   │    │0000000000、0000000000、    │    │                        │\n   │    │0000000000                  │    │                        │\n   ├──┼──────────────┼──┼────────────┤\n   │ 23 │各式無線網卡、數據卡        │20盒│同上                    │\n   ├──┼──────────────┼──┼────────────┤\n   │ 24 │電話卡本（內含SIM卡共199張、│5本 │                        │\n   │    │空卡27張）                  │    │同上                    │\n   ├──┼──────────────┼──┼────────────┤\n   │ 25 │威寶旺卡、臺灣大哥大電話卡、│62張│                        │\n   │    │南頻電信電話卡              │    │同上                    │\n   ├──┼──────────────┼──┼────────────┤\n   │ 26 │電話儲值卡、補充卡          │60張│同上                    │\n   ├──┼──────────────┼──┼────────────┤\n   │ 27 │SIM卡（0000000000、         │2張 │同上                    │\n   ├──┼──────────────┼──┼────────────┤\n   │ 28 │中國信託存摺、金融卡（Ｐ○○│1本 │                        │\n   │    │000000000000）              │    │同上                    │\n   ├──┼──────────────┼──┼────────────┤\n   │ 29 │中國信託存摺、金融卡（劉容羽│1本 │                        │\n   │    │000000000000）              │    │同上                    │\n   ├──┼──────────────┼──┼────────────┤\n   │ 30 │小筆電（ASUS EeePC）        │2台 │同上                    │\n   ├──┼──────────────┼──┼────────────┤\n   │ 31 │身分證影本                  │20張│同上                    │\n   ├──┼──────────────┼──┼────────────┤\n   │ 32 │宅急便、快遞貨單及收件資料  │24張│同上                    │\n   ├──┼──────────────┼──┼────────────┤\n   │ 33 │現金（千元鈔）              │50張│同上                    │\n   ├──┼──────────────┼──┼────────────┤\n   │ 34 │現金                        │5500│己○○。扣押處所：高雄市│\n   │    │                            │元  │光華路與一心路口（85度C │\n   ├──┼──────────────┼──┼────────────┤\n   │ 35 │ORIS手錶                    │1支 │同上                    │\n   ├──┼──────────────┼──┼────────────┤\n   │ 36 │郵局存摺、提款卡（黃瑞寶    │1本 │                        │\n   │    │00000000000000）、印鑑、身分│    │同上                    │\n   │    │證影本                      │    │                        │\n   ├──┼──────────────┼──┼────────────┤\n   │ 37 │NOKIA行動電話（0000000000） │1支 │                        │\n   │    │000000000000000             │    │同上                    │\n   ├──┼──────────────┼──┼────────────┤\n   │ 38 │高雄三信存摺（李維芳        │1本 │                        │\n   │    │00000000000000）、提款卡、印│    │同上                    │\n   │    │鑑、身分證影本              │    │                        │\n   ├──┼──────────────┼──┼────────────┤\n   │ 39 │SASMUNG手機（000000000000000│1支 │己○○。扣押處所：高雄縣│\n   │    │）                          │    │鳳山市○○○街12號      │\n   ├──┼──────────────┼──┼────────────┤\n   │ 40 │LG手機（0000000000）        │1支 │Ｆ○○。扣押處所：高雄市│\n   │    │                            │    │中華路與民生路口（米西亞│\n   │    │                            │    │鋼琴酒吧）              │\n   ├──┼──────────────┼──┼────────────┤\n   │ 41 │現金（千元鈔）              │35張│同上                    │\n   ├──┼──────────────┼──┼────────────┤\n   │ 42 │NOKIA手機（含SIM卡門        │1支 │庚○○。扣押處所：臺南縣│\n   │    │號0000000000 ）             │    │永康市○○街88巷1號     │\n   ├──┼──────────────┼──┼────────────┤\n   │ 43 │SONY ERICSSON手機（含SIM卡門│1支 │壬○○。扣押處所：高雄縣│\n   │    │號0000000000）              │    │鳳山市○○○路59號10樓  │\n   ├──┼──────────────┼──┼────────────┤\n   │ 44 │二級毒品MDMA                │17顆│同上（另案偵辦）        │\n   ├──┼──────────────┼──┼────────────┤\n   │ 45 │三級毒品K他命               │39  │                        │\n   │    │                            │公克│同上（另案偵辦）        │\n   └──┴──────────────┴──┴────────────┘\n附錄本件判決論罪科刑法條：\n刑法第339條（普通詐欺罪）\n意圖為自己或第三人不法之所有，以詐術使人將本人或第三人之\n物交付者，處 5 年以下有期徒刑、拘役或科或併科 1 千元以下\n罰金。\n以前項方法得財產上不法之利益或使第三人得之者，亦同。\n前二項之未遂犯罰之。\n刑法第349條（普通贓物罪）\n收受贓物者，處 3 年以下有期徒刑、拘役或 5 百元以下罰金。\n搬運、寄藏、故買贓物或為牙保者，處 5 年以下有期徒刑、拘\n役或科或併科 1 千元以下罰金。\n因贓物變得之財物，以贓物論。",
  "structure": {
    "main": "原判決除Ｐ○○無罪部分外，均撤銷。\nＱ○○犯如附表一、二所示共肆拾壹罪，均累犯，各處如附表一\n、二主文欄所示之刑。應執行有期徒刑柒年，並於刑之執行前，\n令入勞動處所強制工作參年。\nＰ○○犯如附表一編號23至25所示之參罪，均累犯，各處如附表\n一編號23至25主文欄所示之刑。應執行有期徒刑壹年壹月。\n己○○犯如附表一編號26至33、附表二編號7 至8 所示共拾罪，\n各處如附表一編號26至33、附表二編號7 至8 主文欄所示之刑。\n應執行有期徒刑參年。\n午○○犯如附表二編號1 至2 所示共貳罪，各處如附表二編號1\n至2 主文欄所示之刑。應執行有期徒刑壹年肆月。\nＥ○○犯如附表二編號3 、5 所示共貳罪，各處如附表二編號3\n、5 主文欄所示之刑。應執行有期徒刑捌月，如易科罰金，以新\n臺幣壹仟元折算壹日。\nＦ○○犯如附表二編號6 至7 所示共貳罪，各處如附表二編號6\n至7主 文欄所示之刑。應執行有期徒刑壹年柒月。\n庚○○犯收受贓物罪，處有期徒刑肆月，如易科罰金，以新臺幣\n壹仟元折算壹日。\n壬○○犯收受贓物罪，處有期徒刑參月，如易科罰金，以新臺幣\n壹仟元折算壹日。",
    "fact": "一、Ｑ○○前因詐欺案件，經法院判處有期徒刑4 月確定，甫於\n    民國96年7 月16日易科罰金執行完畢；Ｐ○○前因詐欺案件\n    ，經法院判處有期徒刑3 月確定，甫於96年12月24日易科罰\n    金執行完畢。\n二、Ｑ○○意圖為自己不法所有或分別各與附表一所示之提款人\n    Ｐ○○、己○○等人，共同基於意圖為自己不法所有之犯意\n    聯絡，明知渠等並無「SOGO禮券」、「汽車渦輪控制器」、\n    「汽車零件」、「統一超商禮券」等商品可供出售，竟自97\n    年6 月10日起至97年12月10日止，由Ｑ○○在高雄市各不特\n    定之網咖店上網，以附表一所示之虛偽雅虎拍賣帳號登入雅\n    虎拍賣網站，分別刊登販售上開商品之訊息，致附表一所示\n    Ａ○○等33人瀏覽上開販售商品之訊息後陷於錯誤，而下標\n    購買，並撥打Ｑ○○所留之人頭聯絡電話與其聯繫後，依Ｑ\n    ○○指示匯款至其所收購潘韋德等人（詳如附表一帳號所有\n    人欄所示）所有金融帳戶或Ｑ○○所申請之IBON帳號內（由\n    受騙之買家至超商操作IBON機器繳款），再由Ｑ○○自己，\n    或由Ｑ○○指示附表一所示之提款人Ｐ○○、己○○等人（\n    詳如附表一提款人欄所示）分別至自動提款機提領現金後，\n    Ｑ○○即關閉手機，切斷與Ａ○○等人之聯絡，致Ａ○○等\n    33人受騙並受有如附表一所示之財產上損害（詳細匯款日期\n    、金額、帳號及Ｑ○○等人之分工均詳如附表一所示）。\n三、Ｑ○○於97年6 月16日起至同年11月6 日止，復分別與附表\n    二所示之午○○、Ｅ○○、Ｆ○○、己○○等4 人，共同基\n    於意圖為自己不法所有之犯意聯絡，先由Ｑ○○在高雄市各\n    不特定之網咖店上網，以附表二所示之虛偽雅虎拍賣帳號登\n    入雅虎拍賣網站，刊登販售「SOGO禮券」或「液晶螢幕」等\n    商品之訊息，同時從拍賣網站上搜尋欲出售手錶、液晶螢幕\n    等賣家詳如附表二所示之Ｊ○○等7 人（附表二編號3 、4\n    係同一被害人乙○○），並出價得標，待取得Ｊ○○等7 人\n    所提供之匯款帳號後，即將該匯款帳號提供給欲購買Ｑ○○\n    上開網路拍賣商品之詳如附表二所示之買家汪婉宜等8 人，\n    作為上開買家匯款用之帳戶，致附表二所示之汪婉宜等8 人\n    之禮券買家、Ｊ○○等7 人之手錶賣家，買賣雙方均陷於錯\n    誤，由附表二所示之汪婉宜等禮券買家匯款至如附表二所示\n    之Ｊ○○等手錶賣家之帳戶，而附表二所示之Ｊ○○等手錶\n    賣家收到汪婉宜等禮券買家之匯款後，通知Ｑ○○取貨時，\n    Ｑ○○即斷絕與汪婉宜等禮券買家之聯繫，並與Ｊ○○等手\n    錶賣家聯絡見面交貨時間後，指派附表二所示知情之午○○\n    、Ｅ○○、Ｆ○○、己○○等人前往取得手錶等物品（具體\n    犯罪被害人、犯罪時間、手段所得財物及共犯之之分工，均\n    詳如附表二所示）。\n四、庚○○於97年11月3 日，明知附表二編號7 己○○所交付之\n    手錶係屬贓物，卻仍予以收受，並以新台幣（下同）4 萬元\n    之價格持以出售與不知情而經營鐘錶行之洪靖熙，所得價款\n    並從中分得5 千元。壬○○於97年11月8 日，明知附表二編\n    號8 Ｑ○○委請友人「王世賢」（真實年籍姓名不詳）所交\n    付之手錶係屬贓物，卻仍予以收受，並以2 萬5 千元之價格\n    持以出售與不知情之洪靖熙，所得價款並從中分得3 千元之\n    欠款。\n五、嗣經警據報循線於97年12月10日22時40分許，在高雄市○鎮\n    區○○路與光華路口「85度C 咖啡店」前查獲Ｑ○○、Ｐ○\n    ○、己○○、Ｆ○○等4 人，並執行附帶搜索；翌日8 時許\n    ，警方持搜索票，分別前往高雄市○○區○○街89號9 樓之\n    3 （Ｑ○○住處）、高雄縣鳳山市○○○街12號（己○○住\n    處）、高雄市前鎮區○○○路27號（Ｆ○○住處）等處執行\n    搜索，扣得Ｑ○○等人所有如附表三所示之物。\n六、案經Ａ○○等11人訴由高雄市政府警察局移送及臺北縣政府\n    警察局三重分局報告臺灣板橋地方法院檢察署呈請台灣高等\n    法院檢察署函轉臺灣高雄地方法院檢察署檢察官偵查起訴。",
    "reason": "壹、證據能力部分\n一、按被告以外之人於偵查中向檢察官所為陳述，除顯有不可信\n    之情況者外，得為證據，刑事訴訟法第159 條之1 第2 項定\n    有明文。查證人即附表一、二所列之被害人及各共同被告於\n    檢察官偵查時所為陳述，客觀上並無顯不可信之情況，且其\n    中證人Ｑ○○、己○○、午○○、Ｅ○○等人已經原審傳訊\n    到庭行交互詰問，其餘證人則經檢察官及被告於法院審理中\n    捨棄詰問權，是上開證人於偵查中之證詞自有證據能力。\n二、本判決所引用之其餘證據資料（詳後引證據），其中傳聞證\n    據部分（含各附表被害人於警詢之陳述及共同被告於審判外\n    之陳述），縱無刑事訴訟法第159 條之1 至第159 條之4 或\n    其他規定之傳聞證據例外情形，亦因各被告及檢察官或同意\n    可作為證據使用，或未聲明異議，依刑事訴訟法第159 條之\n    5 第1 項、第2 項之規定，本院審酌各該傳聞證據並非違法\n    取得，與待證事項具關聯性，證明力亦非明顯過低等情，認\n    以之作為證據係屬適當，具有證據能力。\n貳、實體部分\n一、訊據被告Ｑ○○固坦承有附表一編號13-33 、附表二之詐欺\n    犯行，惟否認有附表一編號1-12詐欺犯行，辯稱：附表一編\n    號1-12詐欺犯行非其所為，該犯行係另一批台中人所為（見\n    本院卷第152 頁）。被告Ｐ○○固坦承有於上開時地參與提\n    款之行為，惟否認有涉犯詐欺犯行，辯稱：Ｑ○○向我說該\n    錢是合法的，我才幫忙去提款（見本院卷第215 頁）。被告\n    己○○固坦承參與附表一編號26-33 之詐欺犯行，惟否認有\n    參與附表二編號7-8 詐欺犯行，辯稱：附表二編號7-8 詐欺\n    犯行，我並未參與去賣手錶，Ｑ○○也未分錢給我（見本院\n    卷第215 、218 頁）。被告Ｆ○○則否認有詐欺犯行，辯稱\n    ：我去賣附表二編號6-7 之手錶時，並不知該手錶係贓物（\n    見本院卷第215 頁）。被告庚○○否認有收受贓物犯行，辯\n    稱：己○○叫我去賣附表二編號7 手錶時，我不知該手錶係\n    贓物（見本院卷第215 頁）。被告壬○○否認有收受贓物犯\n    行，辯稱：我只是幫忙拿附表二編號8 手錶去賣而已，我不\n    知該手錶係贓物（見本院卷第215 、218 頁）。被告午○○\n    則坦承有共同參與附表二編號1-2 之詐欺犯行（見本院卷第\n    91 頁 ）。被告Ｅ○○則坦承有共同參與附表二編號3 、5\n    之詐欺犯行（見本院卷第91頁）。經查：\n  (一)被告Ｑ○○、Ｐ○○、己○○、Ｆ○○、午○○、Ｅ○○等\n    6 人分別有附表一編號13-33 及附表二所示之詐欺事實，被\n    告庚○○、壬○○2 人有上開受收贓物之事實，已據被告Ｑ\n    ○○、Ｐ○○、己○○、Ｆ○○、午○○、Ｅ○○、庚○○\n    、壬○○等8 人於原審坦承不諱，經核與匯款之被害人宇○\n    ○、辛○○、Ｍ○○、Ｋ○○、Ｏ○○、江智舜、甲○○、\n    Ｌ○○、子○○、丁○○、證人即提供詐騙帳戶之廖品臻、\n    證人即廖品臻之友人范栓瑄、被害人Ｃ○○、戊○○、Ｂ○\n    ○、Ｒ○○、癸○○、Ｔ○○、寅○○、辰○○、亥○○、\n    陳曉娟、Ｇ○○、巳○○、Ｊ○○、丑○○、Ｉ○○、未○\n    ○、乙○○、黃○○、玄○○、Ｕ○○、酉○○、林政德（\n    即酉○○之父）、Ｎ○○、申○○於警詢中或偵查中之指述\n    相符，並有被害人宇○○之內政部警政署反詐騙案件紀錄表\n    、國泰世華商業銀行帳號000000000000號存摺存款對帳單、\n    被害人辛○○之內政部警政署反詐騙案件紀錄表、統一超商\n    股份有限公司IBON代收款專用繳款證明、被害人Ｍ○○之統\n    一超商股份有限公司IBON代收款專用繳款證明、被害人Ｋ○\n    ○之內政部警政署反詐騙案件紀錄表、統一超商股份有限公\n    司IBON代收款專用繳款證明、雅虎拍賣網站網頁資料、被害\n    人Ｏ○○之內政部警政署反詐騙案件紀錄表、郵政自動櫃員\n    機交易明細表、郵政國內匯款執據、被害人江智舜之內政部\n    警政署反詐騙案件紀錄表、中國信託轉帳收執聯、雅虎拍賣\n    網站網頁資料、被害人甲○○之內政部警政署反詐騙案件紀\n    錄表、郵政自動櫃員機交易明細表、雅虎拍賣網站網頁資料\n    、被害人陳騏竤之內政部警政署反詐騙案件紀錄表、郵政自\n    動櫃員機交易明細表、雅虎拍賣網站網頁資料、被害人子○\n    ○之內政部警政署反詐騙案件紀錄表、郵政自動櫃員機交易\n    明細表、被害人丁○○之內政部警政署反詐騙案件紀錄表、\n    雅虎拍賣網站網頁資料、台新銀行自動櫃員機交易明細表、\n    被害人Ｃ○○之內政部警政署反詐騙案件紀錄表、國泰世華\n    銀行自動櫃員機交易明細表、被害人戊○○之內政部警政署\n    反詐騙案件紀錄表、郵政自動櫃員機交易明細表、雅虎奇摩\n    拍賣網站網頁資料、被害人Ｂ○○之內政部警政署反詐騙案\n    件紀錄表、玉山銀行網路ATM 匯款明細、郵政國內匯款執據\n    、被害人Ｒ○○之內政部警政署反詐騙案件紀錄表、中國信\n    託銀行網路ATM 匯款明細、土地銀行網路ATM 匯款明細、國\n    泰世華銀行網路ATM 匯款明細、被害人癸○○之內政部警政\n    署反詐騙案件紀錄表、台南縣仁德鄉農會自動櫃員機交易明\n    細表、郵政自動櫃員機交易明細表、中國信託自動櫃員機明\n    細表、被害人Ｔ○○之內政部警政署反詐騙案件紀錄表、遠\n    東國際商業銀行客戶交易明細表、台灣中小企業銀行存款憑\n    條、宅急便送貨單、被害人寅○○之內政部警政署反詐騙案\n    件紀錄表、遠東國際商業銀行存款交易明細、被害人辰○○\n    之內政部警政署反詐騙案件紀錄表、台新銀行自動櫃機交易\n    明細表、雅虎奇摩拍賣網站網頁資料、被害人亥○○之內政\n    部警政署反詐騙案件紀錄表、玉山銀行匯款執據、被害人陳\n    曉娟之內政部警政署反詐騙案件紀錄表、中國信託銀行匯款\n    執據、雅虎奇摩拍賣網站網頁資料、被害人Ｇ○○之內政部\n    警政署反詐騙案件紀錄表各1 份、被害人Ｊ○○指認相片、\n    被害人Ｊ○○提出之台北富邦高雄分行帳號：000000000000\n    （戶名：黃德隆）基本資料、交易往來明細、門號00000000\n    00號於97年6 月16日至17日之通信記錄、監視錄影翻拍畫面\n    4 幀、台北富邦銀行帳號0000 00000000 （戶名黃德隆）之\n    開戶資料、對帳單明細、存摺往來交易明細、各類存款歷史\n    對帳單、門號0000000000號用戶資料、通聯記錄、內政部警\n    政署反詐騙案件紀錄表、台北富邦銀行存摺類存款存入存根\n    、雅虎拍賣網站網頁資料、台北縣政府警察局三重分局光明\n    派出所受理刑事案建三聯單、被害人巳○○之受理詐騙帳戶\n    通報警示簡便格式表、被害人丑○○指認相片、被害人丑○\n    ○提出之雅虎拍賣網站網頁資料、第一銀行帳號000-000000\n    00000 （戶名：潘騰）開戶資料、交易往來明細、被害人卯\n    ○○之內政部警政署反詐騙案件紀錄表、高雄三信銀行活期\n    儲蓄存款存摺交易明細各1 份、被害人乙○○指認相片、被\n    害人乙○○提出之收據、彰化銀行鹽埕分行帳號000-000000\n    00000000（戶名：王黃麗華）開戶資料、存摺存款帳戶資料\n    及交易明細查詢各1 份、被害人之Ｉ○○內政部警政署反詐\n    騙案件紀錄表、第一銀行帳號000000 00000號往來交易明細\n    各1 紙、被害人未○○之內政部警政署反詐騙案件紀錄表、\n    郵政跨行匯款申請書各1 紙、被害人玄○○指認相片、被害\n    人玄○○提出之監視錄影翻拍畫面1 幀、電話000000000 於\n    97年8 月25日之通聯紀錄、彰化銀行業務往來申請書、印鑑\n    卡暨顧客資料卡、帳號000-00000000000000存摺存款帳戶及\n    交易明細查詢、被害人黃○○之內政部警政署反詐騙案件紀\n    錄表、華南商業銀行轉帳單據各1 紙、被害人酉○○提出之\n    雅虎拍賣網站網頁資料、第一銀行帳號00000000000 （戶名\n    ：酉○○）開戶資料、交易往來明細、被害人林政德（酉○\n    ○之父）指認相片、被害人Ｕ○○之內政部警政署反詐騙案\n    件紀錄表、被害人Ｎ○○指認相片、被害人Ｎ○○提出之郵\n    局申設帳號000000 00000000 號之存摺交易明細、雅虎拍賣\n    網站網頁資料、板橋文化路郵局帳號00000000000000號（戶\n    名：Ｎ○○）之開戶資料、客戶歷史交易清單、被害人Ｂ○\n    ○之內政部警政署反詐騙案件紀錄表、玉山銀行網路ATM 匯\n    款條、郵政國內匯款執據、三信銀行帳號0000000000號（見\n    戶名：宙○○）之開戶資料、客戶帳單明細單、被害人申○\n    ○之內政部警政署反詐騙案件紀錄表、台新銀行大里分行帳\n    號0000000000000 號存摺往來交易明細、台新銀行竹科分行\n    帳號0000000000000 存摺往來交易明細各1 份、高雄市政府\n    警察局刑事警察局大隊搜索、扣押筆錄、扣押物品目錄表各\n    9 份（受執行人：Ｑ○○、Ｑ○○、己○○、己○○、Ｐ○\n    ○、Ｆ○○、Ｆ○○、庚○○、壬○○）、高雄大順郵局帳\n    號00000000000000號（戶名：潘韋德）之開戶資料、客戶歷\n    史交易清單、新埤郵局帳號000-00000000000000號（戶名：\n    曾光展）之開戶資料、客戶歷史交易清單、鶯歌郵局帳號00\n    000000000000號（戶名：葉凱文）之客戶歷史交易清單、台\n    南友愛街郵局帳號00000000000000號（戶名：林柏良）之客\n    戶歷史交易清單、中和大華郵局帳號00000000000000號（戶\n    名：吳育慈）之開戶資料、客戶歷史交易清單、屏東復興郵\n    局帳號00000000 000000 號（戶名：林政慶）之客戶歷史交\n    易清單、楊梅郵局帳號00000000000000號（戶名：廖品臻）\n    之存摺封面、開戶資料、客戶歷史交易清單各1 份、Ｑ○○\n    、己○○分別於97年11月21日、97年11月24日之提款畫面2\n    幀、Ｅ○○書寫之便條1 紙、第一銀行澎湖分行98年2 月26\n    日一澎字第9 號函暨存戶Ｑ○○開戶資料、帳號0000000000\n    0 號往來交易明細、97檢總管11045 號扣押物品清單各1 紙\n    、Ｐ○○於持盧祥龍（上海商業銀永康分行00000000000000\n    000 ）之提款卡提款畫面2 幀、午○○、庚○○簽立之讓渡\n    書、身分證影本各1 紙、被告壬○○簽立之讓渡書、身分證\n    影本1 紙、被告Ｆ○○簽立之讓渡書、身分證影本1 紙、證\n    人洪靖熙提供所收購之手錶相片、97年聲監字第002046號臺\n    灣高雄地方法院通訊監察書及電話附表各1 份、Ｑ○○持用\n    之門號0000000000監聽譯文、Ｑ○○持用之門號0000000000\n    監聽譯文、Ｅ○○持用之門號0000000000監聽譯文各1 份在\n    卷可佐。\n  (二)被告Ｑ○○雖否認有附表一編號1 至12之詐欺犯行，於原審\n    並辯稱：附表一編號1-12之網路帳號weekenid及hoorscopes\n    並非伊所申請，係台中之詐騙集團成年成員溫平男等人所策\n    劃，伊僅有數次為該集團領錢云云。經查：\n  1.上開附表一編號1-12之被害人受有其上所載詐欺之事實，及\n    用以詐欺附表一編號1-12被害人之行動電話門號分別係如其\n    上所載之0000000000、0000000000、0000000000、00000000\n    00、0000000000等號碼，用以詐欺附表一編號1-8 、10-12\n    被害人之拍賣網站帳號分別係其上所載之「weekenid」及「\n    hoorscopes」之事實，為被告Ｑ○○所不爭執，並經被害人\n    Ａ○○、戌○○、地○○、Ｓ○○、Ｄ○○、丙○○、Ｈ○\n    ○、Ｗ○○、卯○○、Ｙ○○、Ｘ○○、Ｖ○○於警詢、偵\n    訊中證述明確，復有被害人Ａ○○提供之陽信銀行存款往來\n    交易明細、被害人戌○○之內政部警政署反詐騙案件紀錄表\n    、台新銀行自動櫃員機交易明細表、被害人地○○之內政部\n    警政署反詐騙案件紀錄表、郵政自動櫃員機交易明細表、被\n    害人Ｓ○○之內政部警政署反詐騙案件紀錄表、雅虎拍賣網\n    站網頁資料、台新銀行自動櫃員機交易明細表、被害人Ｄ○\n    ○之內政部警政署反詐騙案件紀錄表、郵政儲金匯業局自動\n    櫃員機儲戶交易明細表、被害人丙○○之內政部警政署反詐\n    騙案件紀錄表、國泰世華銀行客戶交易明細表、雅虎拍賣網\n    站網頁資料、被害人Ｈ○○之內政部警政署反詐騙案件紀錄\n    表、被害人Ｗ○○之內政部警政署反詐騙案件紀錄表、郵政\n    自動櫃員機交易明細表、雅虎拍賣網站網頁資料、被害人卯\n    ○○之內政部警政署反詐騙案件紀錄表、高雄三信銀行活期\n    儲蓄存款存摺交易明細、被害人Ｙ○○之內政部警政署反詐\n    騙案件紀錄表、郵政自動櫃員機交易明細表、雅虎拍賣網站\n    網頁資料、被害人Ｘ○○之內政部警政署反詐騙案件紀錄表\n    、郵政自動櫃員機交易明細表、被害人Ｖ○○之內政部警政\n    署反詐騙案件紀錄表、彰化銀行存摺交易明細、台新銀行自\n    動櫃員機交易明細表各1 份在卷可稽。\n  2.被告Ｑ○○確有詐騙附表二編號1 、2 被害人Ｊ○○、汪婉\n    宜、丑○○、卯○○等4 人之事實，已據被告Ｑ○○坦承不\n    諱，並有上開證據可資佐證。而行動電話門號0000000000係\n    用以詐騙附表二編號1 之被害人汪婉宜之號碼；行動電話門\n    號0000000000係用以詐騙附表二編號2 之被害人卯○○之號\n    碼；行動電話門號0000000000係用以詐騙附表二編號一之被\n    害人Ｊ○○及汪婉宜之號碼等情，分別經上開被害人於警詢\n    或偵查中證述明確，是行動電話行號0000000000、00000000\n    00、0000000000之號碼，均係Ｑ○○用以詐騙被害人之門號\n    ，應堪認定。\n  3.被告Ｑ○○雖對附表一編號1-12詐欺犯行，以上揭情詞置辯\n    ，惟比對上開行動電話門號可知：被告Ｑ○○用以詐欺附表\n    一編號1-4 被害人之行動電話門號0000000000，即為其用以\n    詐騙附表二編號1 之被害人汪婉宜之號碼（0000000000）；\n    被告Ｑ○○用以詐欺附表一編號5 被害人之行動電話門號00\n    00000000、0000000000、0000000000等3 線，即其用以詐騙\n    附表二編號1 被害人汪婉宜之號碼（0000000000）、附表二\n    編號2 被害人卯○○之號碼（0000000000）、附表二編號1\n    被害人Ｊ○○及汪婉宜之號碼（0000000000），是附表一編\n    號1-5 之犯行，應係被告Ｑ○○所為，至為明確。又被告Ｑ\n    ○○用以詐欺附表一編號5-9 被害人之行動電話門號中之門\n    號0000000000，即其用以詐騙附表二編號2 之被害人卯○○\n    之號碼（0000000000），是附表一編號5-9 之犯行，亦係被\n    告Ｑ○○所為無誤。再比對用以詐欺上開附表一編號1-12被\n    害人之拍賣網站帳號可知：被告Ｑ○○用以詐欺附表一編號\n    10-12 被害人之拍賣網站帳號「hoorscopes」，即其用以詐\n    騙附表一編號6-8 被害人之拍賣網站帳號（hoorscopes），\n    而被告Ｑ○○詐欺附表一編號6-8 被害人，既已確認如上，\n    則附表一編號10至12之犯行，亦應係被告Ｑ○○所為。況且\n    ，被告Ｑ○○用以詐欺附表一編號5-9 、附表二編號2 被害\n    人之行動電話門號0000000000，所搭配用以詐欺附表一編號\n    5 被害人之拍賣網站帳號係「weekenid」；同一門號（0000\n    000000）所搭配用以詐欺附表一編號6-8 被害人之拍賣網站\n    帳號同時又係「hoorscopes」，由此亦足佐證拍賣網站帳號\n    「weekenid」、「hoorscopes」均係Ｑ○○用以詐欺之帳號\n    。\n  4.被告Ｑ○○於原審復辯稱：共同被告己○○、午○○、Ｅ○\n    ○等人可證明附表一編號1-12並非伊所為云云。惟經原審傳\n    喚上開共同被告己○○、午○○、Ｅ○○等人為證人，並經\n    交互詰問，渠等均不能對被告Ｑ○○上開辯詞，有所佐證。\n    況被告毆永毅於原審訊問之初，原已坦承上開犯行（見原審\n    卷一第39頁），嗣於原審進行準備程序及審理程序時，始翻\n    異前供，而核其辯詞，毫無佐證，又與事實相違，自無可採\n    。\n  5.綜上所陳，被告Ｑ○○確有附表一編號1-12之詐騙行為，堪\n    予認定。\n  (三)被告Ｐ○○雖以上揭情詞置辯，惟查：被告Ｐ○○有附表一\n    編號23-25 之詐欺犯行，已據其於偵查、原審準備程序及審\n    判程序、本院準備程序時多次自白犯罪在案（見偵查卷4 第\n    138-139 頁、原審卷1 第68、210 頁、原審卷2 第44、102\n    頁、本院卷91頁），且其於警詢中自承：「我賣過4 張電話\n    卡門號2 次及手機1 次給Ｑ○○，我曾幫Ｑ○○找過人頭帳\n    戶供Ｑ○○詐騙使用，並找人替Ｑ○○領取詐騙所得，而替\n    Ｑ○○領錢的人要求二成傭金，於是我便向Ｑ○○要求三成\n    傭金，其中我可賺得一成傭金」（見警卷1 第69-70 頁）等\n    情，於偵查中自承：「我有去ATM 幫Ｑ○○領過詐騙所得2\n    、3 次，承認有當車手幫Ｑ○○領錢之詐欺犯行」等情（見\n    偵查卷4 第138-139 頁」，經核與被告Ｑ○○供述：Ｐ○○\n    有幫其領過附表一編號23-25 約10萬元之款項等情相符（見\n    原審卷2 第45頁），是其前開犯罪之自白，自堪採信。被告\n    Ｐ○○既知道幫Ｑ○○所提領款項係詐騙所得，且分得詐騙\n    款項，其確有附表一編號23-25 之詐欺犯行，堪以認定。其\n    上開所辯，顯係事後卸責之詞，自無可採。\n  (四)被告己○○雖否認有參與附表二編號7-8 之詐欺犯行，並以\n    上揭情詞置辯，惟查：被告己○○有附表二編號7-8 之詐欺\n    犯行，已據其於偵查、原審準備程序及審判程序、本院準備\n    稱序時多次自白犯罪在案（見偵查卷4 第10-12 頁、原審卷\n    1 第69、210 頁、原審卷2 第102 頁、本院卷91頁），且其\n    於警詢及偵查中自承：「97年11間，Ｑ○○要我陪同他到台\n    中市○○○○路口，由我向一名不詳年籍男子拿一支寶格麗\n    手錶，那次他沒有給我錢，但來回吃喝玩樂均由他支付。我\n    有介紹朋友Ｆ○○給Ｑ○○認識，他幫Ｑ○○賣了二次手錶\n    」等情（見警卷1 第41頁、偵查卷4 第11頁），經核與Ｑ○\n    ○於本院供述：「我請己○○去幫我拿東西，我給他一些走\n    路工」等語相符（見本院卷第210 頁），是其前開犯罪之自\n    白，自堪採信。被告己○○既有參與詐騙所得手錶之取貨行\n    為，且分得詐騙利益，其確有附表二編號7-8 之詐欺犯行，\n    自堪認定。其上開所辯，顯係事後卸責之詞，自無可採。\n  (五)被告Ｆ○○雖辯稱參與附表二編號6-7 手錶變賣時，不知該\n    手錶係屬贓物，惟查：被告Ｆ○○有附表二編號6-7 之詐欺\n    犯行，已據其於偵查、原審準備程序及審判程序、本院準備\n    稱序時多次自白犯罪在案（見偵查卷4 第18頁、原審卷1 第\n    69、210 頁、原審卷2 第102 頁、本院卷91頁），且其於偵\n    查中自承：「我有幫Ｑ○○拿過二次手錶，第一次他拿一支\n    亞米茄手錶給我，要我去五福路的六六鐘錶行賣，賣了7 萬\n    多元，他有還我5 千元。第二次是97年11間，Ｑ○○要我陪\n    他坐高鐵去板橋。到板橋後，我們就坐計程車去一家超商，\n    就有人拿二支錶及一萬元給我，我就把東西轉交給Ｑ○○。\n    我當時知道Ｑ○○係在從事詐欺，知道他的錶是騙來的」等\n    情明確（見偵查卷4 第18頁），核與Ｑ○○供述Ｆ○○有參\n    與詐騙所得手錶之取貨及變賣行為相符，是其前開犯罪之自\n    白，應堪採信。被告Ｆ○○既有參與詐騙所得手錶之取貨及\n    變賣行為，且分得詐騙利益，其確有附表二編號6-7 之詐欺\n    犯行，自堪認定。其上開所辯，顯係事後卸責之詞，自無可\n    採。\n  (六)被告庚○○雖否認附表二編號7 之收受贓物犯行，並以上揭\n    情詞置辯，惟查：被告庚○○有附表二編號7 收受贓物犯行\n    ，已據其於偵查、原審準備程序及審判程序、本院準備稱序\n    時多次自白犯罪在案（見偵查卷4 第23頁、原審卷1 第210\n    頁、原審卷2 第102 頁、本院卷91頁），且其於偵查中自承\n    ：「我有欠己○○借款，他要我幫忙賣一支亞米茄手錶，賣\n    了4 萬元，賣了之後，己○○有給我5 千元。賣錶當時我覺\n    得該錶可能是贓物，但我欠他錢，不好意思拒絕」等情明確\n    （見偵查卷4 第28-29 頁），而衡諸常情，對他人來路不明\n    的名貴手錶，持有人不敢自己變賣，卻委託他人出面變賣，\n    且變賣後即可分得5 千元之利益，客觀上自難認變賣之人無\n    贓物之認識，是其前開犯罪之自白，應堪採信。被告庚○○\n    既有收受詐騙所得手錶，且進而出面變賣並分得利益，其確\n    有附表二編號7 收受贓物犯行，自堪認定。其上開所辯，顯\n    係事後卸責之詞，自無可採。\n  (七)被告壬○○雖否認有附表二編號8 收受贓物犯行，並以上揭\n    情詞置辯，惟查：被告壬○○有附表二編號8 收受贓物犯行\n    ，已據其於偵查、原審準備程序及審判程序、本院準備稱序\n    時多次自白犯罪在案（見偵查卷4 第28 頁、原審卷1 第210\n    頁、原審卷2 第126 頁、本院卷91頁），且其於偵查中自承\n    ：「賣手錶當時我知道該手錶可能係贓物。手錶賣了2 萬5\n    千元，賣了之後，王世賢還我3 千元」等情明確（見偵查卷\n    4 第28-29 頁），而衡諸常情，對他人來路不明的名貴手錶\n    ，持有人不敢自己變賣，卻委託他人出面變賣，且變賣後即\n    可分得3 千元之利益，客觀上自難認變賣之人無贓物之認識\n    ，是其前開犯罪之自白，應堪採信。被告壬○○既有收受詐\n    騙所得手錶，且進而出面變賣並分得利益，其確有附表二編\n    號8 收受贓物犯行，自堪認定。其上開所辯，顯係事後卸責\n    之詞，自無可採。\n  (八)綜上所述，被告Ｑ○○等人上開所辯，均屬卸飾之詞，殊無\n    可採。渠等有詐欺及受收贓物犯行，事證明確，堪以認定，\n    應予依法論科。\n二、論罪科刑部分：\n  (一)核被告Ｑ○○、Ｐ○○、己○○、午○○、Ｅ○○、Ｆ○○\n    6 人所為，均係犯刑法第339 條第1 項之詐欺取財罪；被告\n    庚○○、壬○○所為係犯刑法第349 條第1項 之收受贓物罪\n    。被告Ｑ○○分別與被告Ｐ○○就附表一編號23-25 之3 次\n    詐欺犯行、與被告己○○就附表一編號26-33 及附表二編號\n    7 、8 之10次詐欺犯行、與被告午○○就附表二編號1 、2\n    之2 次詐欺犯行、與被告Ｅ○○就附表二編號3 、5 之2 次\n    詐欺犯行、與被告Ｆ○○就附表二編號6 、7 之2 次詐欺犯\n    行，均有犯意聯絡與行為分擔，應論以共同正犯。被告Ｑ○\n    ○、己○○、Ｆ○○、午○○、Ｅ○○等5 人就附表二各編\n    號係以一詐騙行為同時詐騙二名被害人之財產法益，係一行\n    為而觸犯數罪名，為同種想像競合犯，應從受害人較重部分\n    處斷。另被告Ｑ○○、Ｐ○○、己○○、午○○、Ｅ○○、\n    Ｆ○○等6 人先後多次詐欺之行為，犯意各別，應予分論併\n    罰。又被告Ｑ○○、Ｐ○○有如事實欄所述之前科，有台灣\n    高等法院被告前案紀錄表在卷可查，其二人於受有期徒刑執\n    行完畢後，5 年內故意再犯本件法定刑為有期徒刑以上刑之\n    罪，為累犯，均應依刑法第47條第1 項規定加重其刑。\n  (二)上訴意旨認被告Ｑ○○在高雄市各不特定之網咖店上網，以\n    被告Ｅ○○申請之「freeapo 」、「boboto520 」、「phoh\n    evd 」、「swuaooi 」、「samwindlezz 」及「wowo 510」\n    等虛偽雅虎拍賣帳號登入雅虎拍賣網站，進行網路拍賣詐騙\n    ，被告Ｑ○○及Ｅ○○就偽冒他人名義而申請網路會員帳戶\n    使用之行為，涉犯偽造及行使偽造準私文書罪嫌，原審未予\n    審理，顯有違法等語。然按【刑事訴訟法第264 條第2 項關\n    於起訴書程式之規定，旨在界定起訴及審判之範圍，並兼顧\n    被告防禦權之行使，其中屬於絕對必要記載事項之「犯罪事\n    實」，係指犯罪構成要件之具體事實。故所謂犯罪已經起訴\n    ，係指起訴書之犯罪事實欄，已就特定犯罪構成要件之基本\n    事實，具體記載，並足據以與其他犯罪事實區分，始克當之\n    】（最高法院92年台上字第60號刑事判決參照）。查刑法第\n    220 條、第216 條及第210 條之偽造及行使偽造準私文書罪\n    ，以「偽造私文書，足以生損害於公眾或他人」為要件，此\n    項構成要件之具體事實，須於起訴書事實欄內有相當之記載\n    ，始得謂為已經起訴。本件起訴書之犯罪事實欄，對於被告\n    Ｑ○○及Ｅ○○以何人名義偽造文書，致何人生有損害均未\n    論述，且遍查卷內亦無其所指偽造「準私文書」之證據可資\n    佐證，另於起訴書被告所犯法條欄內亦未論及被告犯有此項\n    罪名。本院另查該項罪名與被告於本案論罪部分並無裁判或\n    實質上一罪關係，亦無追加起訴情形。本件原起訴書對被告\n    Ｑ○○及Ｅ○○涉犯偽造及行使偽造準私文書罪嫌之犯罪事\n    實、證據及所犯法條，既未論述，客觀上自難謂該部分犯罪\n    已依法起訴，上訴意旨遽謂該「偽造及行使偽造準私文書罪\n    」部分已經起訴，尚有誤會。\n  (三)另公訴人認被告Ｐ○○提供予被告Ｑ○○集團使用之「盧祥\n    龍所有，帳號00000000000000號上海商業銀行」帳號，除有\n    判決書附表一編號23-25 之被害人外，尚有閔昭夏及施文壹\n    （見警三卷第75、76頁），被害金額分為29,989元及360,22\n    8 元，此部分與已起訴部分（即提供詐騙他人使用之金融機\n    構人頭帳戶之行為）具同種想像競合之裁判上一罪關係，原\n    審未及審酌，有已受請求事項未予判決之違法情形。惟查：\n    被告毆永毅及Ｐ○○對附表一、二之犯行，均係95年7 月1\n    日刑法修正後所犯，且其2 人所犯上開詐欺罪均屬一罪一罰\n    之數罪併罰情形，公訴人於原起訴書既未對被害人閔昭夏及\n    施文壹部分予以起訴，原審法院自不得予以審理，應由檢察\n    官另行追加起訴或另行起訴，始為適法。上訴意旨認該被害\n    人部分與本案有屬裁判上一罪關係，亦屬誤會。\n  (四)原審據以論處被告罪刑，固非無見；惟查：(1)有罪之判決書\n    應記載事實，所謂事實不僅指犯罪行為而言，即犯罪之動機\n    、目的、手段、結果等，與論罪科刑有關之事項，亦應依法\n    認定予以明確之記載（最高法院90年台上字第5510號刑事判\n    決參照）。本件原判決認定被告Ｑ○○等人有附表一所示之\n    詐欺犯行，惟其對被告販售何種商品，何以有不法所有之犯\n    罪意圖均未於犯罪事實載明，且於附表一之各欄項次下，亦\n    未認定記載，自難謂屬適法。(2)按量刑之輕重，固屬事實審\n    法院得依職權自由裁量之事項，惟仍應受比例原則及公平原\n    則之限制，否則其判決即非適法。刑事審判旨在實現刑罰權\n    分配的正義，故法院對有罪被告之科刑，應符合罪刑相當之\n    原則，使輕重得宜，罰當其罪，以契合社會之法律感情，此\n    所以刑法第57條明定科刑時應審酌一切情狀，尤應注意該條\n    各款所列事項以為科刑輕重之標準（最高法院93年度台上字\n    第5073號判決意旨參照）。查被告Ｑ○○等人共同以網路購\n    物對於網路尋交易之被害人予以詐騙，渠等犯罪事前計畫縝\n    密，嚴重敗壞社會風氣，危害國內商場交易秩序與社會互信\n    甚鉅，量刑實難寬待，且本件被害人被詐騙金額不一，低則\n    詐騙數千元，高則詐騙十幾萬元，另被告庚○○、壬○○收\n    受贓物之情節非一，所得利益亦不相同，如均量處同一刑責\n    ，實有違公平及比例原則，原審對此漏未審酌，難認妥適。\n    (3)被告Ｑ○○、己○○、Ｆ○○、午○○、Ｅ○○等5 人就\n    附表二各編號犯行，係以一詐騙行為同時詐騙二名被害人之\n    財產法益，係一行為而觸犯數罪名，為同種想像競合犯，應\n    從受害人較重部分處斷。原審對附表二各編號內之犯行論以\n    二罪，尚有未洽。檢察官以原審量刑過輕不當提起上訴，為\n    屬有據，且原審亦有上開可議之處，自應由本院將原判決有\n    罪部分暨定執行刑部分予以撤銷改判。\n  (五)爰審酌被告Ｑ○○、Ｐ○○、己○○、午○○、Ｅ○○、Ｆ\n    ○○等6 人，均年輕力壯，不思努力工作，竟利用網路交易\n    較一般交易為隱匿之特性，與網路交易平台無力全面清查真\n    正帳號使用者之弱點，及網路交易相對人為圖一時之便利而\n    有疏忽之際，從事網路詐騙之行為，破壞網路交易安全，對\n    被害人財產及社會秩序危害重大，嚴重影響社會互信，國人\n    深惡痛絕，且被告Ｑ○○就上開犯行，係處於主導地位，而\n    被告Ｐ○○、己○○、午○○、Ｅ○○、Ｆ○○則係分別擔\n    任車手收款或收取所購物品工作，及犯罪期間、次數、所得\n    ，且僅與部分被害人達成和解，兼衡各被告犯罪動機、目的\n    、手段、所生損害及犯後態度等一切情狀，各量處如主文所\n    示之刑及就被告庚○○、壬○○、Ｅ○○3 人諭知易科罰金\n    之折算標準，並定其應執行刑及諭知易科罰金之折算標準（\n    其中被告Ｅ○○部分，刑法第41條第2 項於被告行為時原規\n    定：「前項規定於數罪併罰，其應執行之刑未逾6 月者，亦\n    適用之」，於98年12月30日新法修正為第41條第8 項，其內\n    容為：「第一項至第4 項及第7 項之規定，於數罪併罰之數\n    罪均得易科罰金或易服社會勞動，其應執行之刑逾6 月者，\n    亦適用之」，兩相比較，新法易科罰金於數罪併罰之數罪均\n    得易科罰金或易服社會勞動，且不受應執行6 月之限制，是\n    比較新舊法結果，以適用修正後之刑法規定較為有利），又\n    被告Ｑ○○係網路購物詐欺集團之主導人，其於97年6 月10\n    日至同年12月10日遭查獲時止，於密集時間內詐騙多達41件\n    犯行，其手段具有同質性，顯係有犯罪之習慣及再犯之可能\n    性，僅藉刑罰之執行尚不足以根絕其惡性，並依據其行為之\n    嚴重性、所表現之危險性及對其未來行為之期待性等情，為\n    矯正其不良習性，爰對其情節最重之附表二編號1 被害人汪\n    婉宜部分，依刑法第90條規定併為被告Ｑ○○應於刑之執行\n    前，令入勞動處所強制工作3 年之諭知。\n  (六)又按「刑法上沒收因犯罪所得之物，應指因犯罪行為直接所\n    產生或取得特定之原物，故除法律規定得追徵價額或其他特\n    別之規定外，因變賣盜贓或侵占之物所得之價金，既非因犯\n    罪直接所取得特定之物，自不得為沒收之對象」、「刑罰之\n    執行，係對於人身及財產之侵害，應止於犯罪行為人之一身\n    為原則。沒收為刑罰之一種；刑法上所謂屬於犯罪行為人因\n    犯罪所得之沒收物，乃指無他人對於該物得主張法律上之權\n    利者而言；倘該物原屬被害人所有，而為犯罪行為人因犯罪\n    而取得或變易獲得，該被害人既仍得對之為法律上權利之主\n    張，自難認該當於沒收之要件。」，有最高法院70年度台上\n    字第5569號、96年度台上字第5390判決，可資參照。扣案附\n    表三編號1 至13、16、20、36-40 、42、43所示之物雖各為\n    上開被告所有，但無從證明係供被告為本案所涉49件中之何\n    件犯行所用，且俱係偶供犯罪所用，並非不能為正常使用之\n    物，亦無沒收之實益，爰不沒收。附表三編號21至32雖為Ｐ\n    ○○所有，但不能證明與本案有關，亦不沒收。附表三編號\n    14 、15 、17、18、19、33、34、35、41，雖係被告Ｑ○○\n    等人詐欺所得之財物或所變得之財物，被害人尚得對之為法\n    律上權利之主張，參照上開說明，均不沒收，應另由執行機\n    關另為適法之處理。附表三編號44、45則與本案無關，自無\n    庸於本件宣告沒收。\n三、被告Ｐ○○被訴與被告Ｑ○○等人共同為附表一編號1 至22\n    、26至33及附表二編號1 至8 之詐欺犯行，業經原審判決無\n    罪，檢察官未據上訴而告確定，併予敘明。\n據上論結，應依刑事訴訟法第369 條第1 項前段、第364 條、第\n299 條第1 項前段，刑法第2 條第1 項、第28條、第339 條第1\n項、第349 條第1 項、第55條、第47條第1 項、第41條第1 項前\n段、第51條笫5 款、第90條，98年12月30日新修正刑法第41條第\n8 項，刑法施行法第1 條之1 ，判決如主文。\n本案經檢察官許月雲到庭執行職務。\n中    華    民    國    99    年    1     月    5     日\n                  刑事第一庭    審判長法  官  周賢銳\n                                      法  官  徐美麗\n                                      法  官  施柏宏\n以上正本證明與原本無異。\n不得上訴。"
  },
  "characters": {
    "judges": [
      "周賢銳",
      "徐美麗",
      "施柏宏"
    ],
    "prosecutors": [
      "許月雲"
    ],
    "lawyers": [

    ],
    "clerks": [
      "魏文常"
    ],
    "plaintiffs": [

    ],
    "defendants": [
      "Ｑ○○",
      "被      告  Ｐ○○",
      "被      告  己○○",
      "被      告  Ｆ○○",
      "被      告  庚○○",
      "被      告  壬○○",
      "被      告  午○○",
      "被      告  Ｅ○○"
    ],
    "prosecutor_office": [

    ],
    "creditors": [

    ],
    "debtors": [

    ],
    "judicial_associate_officer": [

    ]
  },
  "adjudged_at": "2010-01-05",
  "created_at": "2016-01-05 15:10:12",
  "updated_at": "2016-01-05 15:10:12"
}