{
  "identify": "KSH-98-上訴-920-20100104-1",
  "court": {
    "name": "臺灣高等法院",
    "code": "KSH"
  },
  "division": {
    "name": "刑事",
    "code": "M"
  },
  "year": 98,
  "word": "上訴",
  "number": "920",
  "jcheck": "1",
  "reason": "違反毒品危害防制條例",
  "content": "臺灣高等法院高雄分院刑事判決         98年度上訴字第920號\n上  訴  人\n即  被  告  寅○○\n            癸○○\n以上2人共同\n選任辯護人  洪幼珍律師\n上  訴  人\n即  被  告  巳○○\n選任辯護人  徐文彬律師\n上  訴  人\n即  被  告  子○○\n選任辯護人  曾慶雲律師\n上  訴  人\n即  被  告  申○○\n選任辯護人  吳建勛律師\n            梁宗憲律師\n            陶德斌律師\n上  訴  人\n即  被  告  庚○○\n選任辯護人  洪世崇律師\n            許惠珠律師\n上  訴  人\n即  被  告  未○○\n            甲○○\n上 1 人 之\n選任辯護人  曾慶雲律師\n上  訴  人\n即  被  告  乙○○\n選任辯護人  李淑妃律師\n上列上訴人等因違反毒品危害防制條例案件，不服臺灣澎湖地方\n法院97年訴字第13號中華民國98年5 月4 日第一審判決（起訴案\n號：臺灣澎湖地方法院檢察署96年度偵字第748 、749 、782 、\n796 、798 、806 、807 、808 、811 、848 、876 號，97年度\n偵字第50、75、167 、272 、281 號）及移送併辦（同署97年度\n偵字第359 號），提起上訴，本院判決如下：\n     主  文\n原判決關於寅○○、癸○○販賣第一級毒品、巳○○販賣第二級\n毒品及其定執行刑部分均撤銷。\n寅○○販賣第一級毒品，累犯，共計罪，各處有期徒刑拾年\n，行動電話、販毒所得之沒收、抵償均如附表一(二)應沒收之物(1)\n、(2)所示。\n巳○○販賣第二級毒品，共計貳罪，各處有期徒刑貳年捌月，扣\n案之夾鏈袋壹包（內裝小夾鏈袋捌拾陸個）沒收，行動電話、販\n毒所得之沒收、追徵價額、抵償均如附表四(一)應沒收之物(1)、(2)\n）所示。\n癸○○共同販賣第一級毒品，累犯，共計拾罪，各處有期徒刑拾\n壹年貳月，行動電話、販毒所得之沒收、追徵價額、抵償均如附\n表九(一)應沒收之物(1)、(2)所示。\n其他上訴駁回。\n寅○○前開第二項撤銷改判部分與第五項上訴駁回部分（幫助施\n用第一級毒品，累犯，處有期徒刑拾月），應執行有期徒刑拾肆\n年，行動電話、販毒所得之沒收、抵償均如附表一(二)應沒收之物\n(1)、(2)所示。\n巳○○前開第三項撤銷改判部分與第五項上訴駁回部分販賣第一\n級毒品，共計貳罪，各處有期徒刑拾伍年貳月，扣案之夾鏈袋壹\n包（內裝小夾鏈袋捌拾陸個）沒收，行動電話、販毒所得之沒收\n、追徵價額、抵償均如附表四(二)應沒收之物(1)、(2)所示。應執行\n有期徒刑拾伍年月，扣案之夾鏈袋壹包（內裝小夾鏈袋捌拾陸\n個）沒收，行動電話、販毒所得之沒收、追徵價額、抵償均如附\n表四(一)、(二)應沒收之物(1)、(2)所示。\n癸○○前開第四項撤銷改判部分與第五項上訴駁回部分（共同轉\n讓第一級毒品，累犯，處有期徒刑壹年陸月；又轉讓第一級毒品\n，累犯，共計貳罪，各處有期徒刑壹年陸月；又轉讓禁藥，累犯\n，處有期徒刑壹年；又幫助施用第一級毒品，累犯，共計參罪，\n各處有期徒刑捌月；又幫助施用第二級毒品，累犯，處有期徒刑\n肆月）。應執行有期徒刑拾年，行動電話、販毒所得之沒收、\n追徵價額、抵償均如附表九(一)應沒收之物(1)、(2)所示。\n     事  實\n一、寅○○曾因公共危險、過失傷害、竊盜等案件，經法院各判\n    處有期徒刑8 月、3 月、4 月，嗣定應執行刑1 年1 月確定\n    ，於民國94年6 月20日執行完畢，又因詐欺案件，經法院判\n    處有期徒刑4 月確定，於94年11月16日易科罰金執行完畢，\n    猶不知悔改，明知海洛因係毒品危害防制條例第2 條第2 項\n    第1 款所列之第一級毒品，依法不得販賣或施用，竟基於幫\n    助施用第一級毒品海洛因之犯意，於96年10月28日，在澎湖\n    縣馬公市大愛牛排館內與子○○集資，由寅○○向他人購買\n    海洛因2 小包後，2 人分食，幫助子○○施用海洛因1 次；\n    另基於販賣第一級毒品以營利之犯意，以其所有之門號0000\n    000000號、0000000000號行動電話與欲購買海洛因之癸○○\n    、壬○○相互聯繫交易細節後，分別於96年11月4 日、11月\n    16日，在馬公市○○路「都家堡」商店對面、馬公國小旁之\n    統一超商門口、安一山莊前，3 次將海洛因賣予癸○○、壬\n    ○○以牟利（幫助施用、販賣之時、地、手法、對象、毒品\n    種類、數量、金額及應沒收之物，均詳如附表一(一)、(二)）。\n    嗣經警查獲，扣得其所有供犯罪所用之0000000000號、0000\n    000000號行動電話各1 支。寅○○於警詢供出海洛因來源，\n    因而使警方查獲販毒之子○○、乙○○及另案之午○○。\n二、子○○曾於95年間，因賭博案件，經原審判處有期徒刑8 月\n    ，緩刑3 年確定（不構成累犯），猶不知警惕，竟在緩刑期\n    間內，明知海洛因係毒品危害防制條例第2 條第2 項第1 款\n    所列之第一級毒品，依法不得販賣或施用，竟基於幫助施用\n    海洛因之犯意，於96年11月15日邀同未○○集資新台幣（下\n    同）2,000 元（子○○出資500 元，未○○出資1,500 元）\n    ，並由子○○出面購得海洛因1 小包，除其中1/4 留供自己\n    施用外，所餘3/4 於同日14時35分許，在澎湖縣農會生鮮超\n    市門口，交予未○○，嗣由未○○在馬公市某地施用之（未\n    ○○施用毒品部分見附表六編號2 ）；另基於販賣第一級毒\n    品以營利之犯意，於96年11月16日14時許，在澎湖縣馬公市\n    ○○路66號住處，先向寅○○預收2,000 元並允諾販賣等值\n    之海洛因，旋再以其所有之門號0000000000號諾基亞牌行動\n    電話告知寅○○交易地點後，在澎湖縣馬公國小旁統一超商\n    內，交付海洛因1 小包（重0.3 公克）予寅○○（嗣寅○○\n    將該買得之0.3 公克海洛因轉賣予壬○○（見附表一(二)編號\n    3 ）），寅○○為警查獲後，供出海洛因來源為子○○；另\n    由寅○○配合警方辦案，於同日16時35分許，撥打子○○上\n    開手機，與本有販賣第一級毒品犯意之子○○約定交易海洛\n    因之地點，旋子○○持海洛因1 小包，至馬公市○○路66西\n    餐廳附近等候，擬將之販賣予寅○○時，當場為警查獲而未\n    得逞（幫助施用、販賣之時、地、手法、對象、毒品種類、\n    數量、金額及應沒收之物，均詳如附表二(一)、(二)）。嗣經警\n    扣得第一級毒品海洛因1 小包（淨重0.11公克，空包裝重0.\n    33公克）及其所有供犯罪所用之0000000000號行動電話1 支\n    。\n三、申○○明知海洛因、安非他命分屬毒品危害防制條例第2 條\n    第2 項第1 、2 款所列之第一、二級毒品，依法不得販賣或\n    轉讓，竟與辰○○（另由本院通緝中）、癸○○、乙○○或\n    庚○○，共同基於販賣第一級毒品海洛因或第二級毒品安非\n    他命以營利之犯意，持其所有之門號0000000000號行動電話\n    ，或分由庚○○、癸○○持其所有之0000000000號、000000\n    0000號行動電話，與欲購買毒品之人相互聯繫交易細節後，\n    販賣海洛因、安非他命各4 次、3 次；另基於轉讓第一級毒\n    品海洛因之犯意，自96年11月12日起，在澎湖縣馬公市享溫\n    馨KT V等地，轉讓海洛因予陳志盟等人，共計4 次（販賣、\n    轉讓之時、地、手法、對象、毒品種類、數量、金額及應沒\n    收之物，均詳如附表三(一)、(二)、(三)）。\n四、巳○○明知海洛因、安非他命分屬毒品危害防制條例第2 條\n    第2 項第1 、2 款所列之第一、二級毒品，依法均不得販賣\n    ，竟基於販賣第一、二級毒品以營利之犯意，以其所有之門\n    號0000000000號行動電話與欲購買毒品之戊○○、癸○○相\n    互聯繫交易細節，並以夾鏈袋分裝毒品後，分別於96年10月\n    初某日及同年11月6 日，2 次販賣安非他命予戊○○、癸○\n    ○；另於96年11月2 日、同月3 日，2 次販賣海洛因予癸○\n    ○（販賣之時、地、手法、對象、毒品種類、數量、金額及\n    應沒收之物，均詳如附表四(一)、(二)）。嗣經警扣得其所有供\n    販毒分裝毒品所用之夾鏈袋1 包（內裝小夾鏈袋86個）。巳\n    ○○於偵查中，供出安非他命來源，因而使警查獲販賣安非\n    他命之酉○○（另案審理）。\n五、庚○○曾於93年間，因賭博案件，經法院判處有期徒刑3 月\n    確定，於93年11月5 日易科罰金執行完畢，猶不知悔改，明\n    知安非他命屬毒品危害防制條例第2 條第2 項第2 款所列之\n    第二級毒品，依法不得販賣，竟與辰○○、申○○共同基於\n    販賣第二級毒品以營利之犯意，持其所有之門號0000000000\n    號行動電話，或由申○○持其所有之0000000000號行動電話\n    ，與欲購買毒品之人相互聯繫交易細節後，於96年11月10日\n    ，2 次販賣安非他命予歐家雄、丁○○（販賣之時、地、手\n    法、對象、毒品種類、數量、金額及應沒收之物，均詳如附\n    表五）。\n六、未○○曾因違反毒品危害防制條例案件，經法院判處有期徒\n    刑7 月，嗣減為有期徒刑3 月15日確定，於96年7 月17日執\n    行完畢，其明知海洛因係毒品危害防制條例第2 條第2 項第\n    1 款所列之第一級毒品，依法不得施用，竟基於施用海洛因\n    之犯意，自96年11月中旬某日起至同年11月28日止，在澎湖\n    縣馬公市○○路李子林婦產科前等地，施用海洛因4 次（施\n    用之時、地、毒品種類，均詳如附表六）。\n七、甲○○曾因違反毒品危害防制條例案件，分別經臺灣高雄地\n    方法院判處有期徒刑8 月、1 年確定，於93年12月1 日接續\n    執行縮刑期滿執行完畢，猶不知悔改，明知海洛因係毒品危\n    害防制條例第2 條第2 項第1 款所列之第一級毒品，依法不\n    得販賣、轉讓或施用，竟基於販賣第一級毒品以營利之犯意\n    ，以其所有之門號0000000000號行動電話與欲購買海洛因之\n    人相互聯繫交易細節後，自96年8 月5 日11時38分起至同年\n    11月6 日止，在澎湖縣西嶼鄉○○村○○○○○道路等地，\n    分別將海洛因賣予己○○等人牟利，總計販賣11次；另基於\n    轉讓海洛因之犯意，於96年11月6 日，在澎湖縣西嶼鄉外垵\n    村慈航寺附近，轉讓海洛因1 包予癸○○；又基於幫助施用\n    海洛因之犯意，自96年9 月28日18時51分起至同年10月28日\n    21時36分止，在澎湖縣西嶼鄉外垵國小附近等地，以與丙○\n    ○合資購買海洛因，再由甲○○出面拿取海洛因後與丙○○\n    分食之方式，幫助丙○○施用海洛因，共計5 次（販賣、轉\n    讓、幫助施用之時、地、手法、對象、毒品種類、數量、金\n    額及應沒收之物，均詳如附表七(一)、(二)、(三)）。\n八、乙○○明知海洛因、安非他命分屬毒品危害防制條例第2 條\n    第2 項第1 、2 款所列之第一、二級毒品，依法不得販賣、\n    轉讓或施用，竟基於幫助施用海洛因之犯意，於96年9 月底\n    某日，在澎湖縣白沙鄉講美村廟旁，以與寅○○合資購買海\n    洛因，再由乙○○出面拿取海洛因後與寅○○分食之方式，\n    幫助寅○○施用海洛因1 次；另基於販賣第一、二級毒品以\n    營利之犯意（附表八(二)部分與癸○○有犯意聯絡，附表八(三)\n    編號1 部分與辰○○有犯意聯絡，附表八(三)編號3 部分與辰\n    ○○、申○○有犯意聯絡），持其所有之門號0000000000號\n    行動電話，或由癸○○持其所有之0000000000號行動電話，\n    或由申○○持其所有之0000000000號行動電話，與欲購買毒\n    品之人相互聯繫交易細節後，自96年10月12日起至同年月13\n    日止，在澎湖縣馬公市百合民宿，3 次將海洛因賣予丁○○\n    等人牟利，又自96年10月26日起至同年11月6 日止，在澎湖\n    縣馬公市燦坤量販店後方公園等地，3 次將安非他命賣予酉\n    ○○等人牟利；另基於轉讓海洛因之犯意，自96年11月初某\n    日起至同年11月12日止，在其光復路租屋處等地，轉讓海洛\n    因予癸○○等人，共計7 次（販賣、轉讓、幫助施用之時、\n    地、手法、對象、毒品種類、數量、金額及應沒收之物，均\n    詳如附表八(一)、(二)、(三)、(四)）。\n九、癸○○曾因違反毒品危害防制條例案件，經法院定應執行刑\n    判處有期徒刑1 年6 月，嗣減為有期徒刑9 月確定，於96年\n    7 月16日執行完畢，猶不知悔改，明知海洛因、安非他命分\n    屬毒品危害防制條例第2 條第2 項第1 、2 款所列之第一、\n    二級毒品，且安非他命業經中央衛生主管機關行政院衛生署\n    公告列為禁藥管理，屬藥事法第22條第1 項第1 款所規範之\n    禁藥，依法均不得販賣、轉讓或施用，竟基於販賣、轉讓或\n    幫助施用第一、二級毒品之單獨或共同犯意，於附表九(一)時\n    地，持其所有之門號0000000000號行動電話，或由申○○持\n    其所有之0000000000號行動電話，與欲購買海洛因之人相互\n    聯繫交易細節後，販賣海洛因共10次；於附表九(二)、(三)時地\n    ，分別轉讓海洛因、安非他命各3 次、1 次；於附表九(四)、\n    (五)時地，分別幫助他人施用海洛因、安非他命各3 次、1 次\n    （販賣、轉讓、幫助施用之時、地、手法、對象、毒品種類\n    、數量、金額及應沒收之物，均詳如附表九(一)、(二)、(三)、(四)\n    、(五)）。癸○○於警詢時，供出其所販賣海洛因來源，因而\n    使警查獲販毒之乙○○、辰○○及另案審理之金正剛。並於\n    偵查中及本院審理時自白販賣第一級毒品海洛因。\n十、案經澎湖縣政府警察局馬公分局報告、澎湖縣政府警察局移\n    送臺灣澎湖地方法院檢察署檢察官、臺灣澎湖地方法院檢察\n    署檢察官自動檢舉偵查起訴及移送併辦。\n     理  由\n甲、程序部分：\n一、按被告以外之人於偵查中向檢察官所為陳述，除顯有不可信\n    之情況者外，得為證據，刑事訴訟法第159 條之1 第2 項定\n    有明文。又偵查中對被告以外之人所為之偵查筆錄，或被告\n    以外之人向檢察官所提之書面陳述，性質上雖均屬傳聞證據\n    ，惟就該立法理由觀之，係考量現階段刑事訴訟法規定檢察\n    官代表國家偵查犯罪、實施公訴，依法其有訊問被告、證人\n    及鑑定人之權，而實務運作時，檢察官偵查中向被告以外之\n    人所取得之陳述，原則上均能遵守法律規定，鮮少以強暴、\n    脅迫及其他不正之方法取得供述證據，其可信度極高，而有\n    此例外之規定，故除反對被告以外之人於偵查中所為之供述\n    得具有證據能力之一方，已釋明該供述「顯有不可信之情況\n    」之理由外，不宜遽指該被告以外之人於偵查中之陳述不具\n    證據能力。證人未○○於另案（臺灣澎湖地方法院檢察署96\n    年度毒偵字第38號、97年度毒偵字第10號）偵查中所為之陳\n    述，經查未有何不法取供等顯不可信之情況，自有證據能力\n    。\n二、證人寅○○於警詢中之供述屬傳聞證據，雖其於警詢中就有\n    關向被告子○○買受海洛因之供述，與審判中之陳述並非一\n    致，惟寅○○於警詢中之供述係出於其販賣毒品予案外人壬\n    ○○而當場為警查獲，在無可迴避之情勢下進而交待其毒品\n    來源等情，堪認其警詢中之供述具有特別可信之情況，且為\n    證明被告子○○犯罪所必要者，依刑事訴訟法第159 條之2\n    規定，自有證據能力，得為證據。\n三、本判決以下所引用之傳聞證據，被告等及其辯護人於本院審\n    理時，均表示不爭執，且未於言詞辯論終結前聲明異議，本\n    院審酌上開傳聞證據作成時，並無不法之情事，認為適當，\n    依刑事訴訟法第159 條之5 第2 項規定，均有證據能力，得\n    為證據。\n乙、實體部分：原審所列認定事實之理由，本院均予引用。\n壹、被告寅○○部分\n一、訊據上訴人即被告寅○○對於上揭附表一(一)幫助羅智強施用\n    海洛因之犯行，於原審及本院審理時坦承不諱，對於附表一\n    (二)所示交易行為，亦不爭執，惟辯稱：伊係與癸○○、壬○\n    ○分別合資購買毒品後分食之，並非販賣毒品給癸○○及壬\n    ○○云云。\n二、經查：被告寅○○對於附表一(一)犯行之自白，核與證人子○\n    ○於警詢及原審審理中證述之情節相符，堪認屬實。又被告\n    寅○○於96年11月4 日23時28分至23時42分以其所有之門號\n    0000000000號行動電話與癸○○相互聯繫買賣毒品交易細節\n    一情，有監聽譯文附卷可稽（警卷，頁205 ），參諸證人癸\n    ○○於警詢中（97年2 月1 日第4 次調查筆錄，警卷，頁19\n    4~195 ）供稱：「（問：警方提示96年11月4 日17時10分你\n    與寅○○通話譯文（A ：癸○○、B ：寅○○）內容：「A\n    ：晚一點可以麻煩一下嗎？B ：晚一點喔？好啦好啦。」意\n    喻為何？）這是我要寅○○幫我調毒品海洛因，後來我在11\n    月4 日與高文琳每人出500 元共計1,000 元在光復路都家堡\n    外面向寅○○購買毒品海洛因後與高文琳當場在我E6-4712\n    號車上共同施用。」、「（問：警方提示96年11月4 日23時\n    28分、23時31分、23時34分、23時42分，你與寅○○4 通通\n    話譯文（A ：癸○○、B ：寅○○）內容：「A ：阿我拿2,\n    000 塊去還你好了、B ：好啦、那要抓2 尾，我給你秤重一\n    點，那魚啦（土魠）。A ：剩拿1,000 阿馬卡趕一下（快一\n    點）。B ：我在馬公國小，麻煩你來馬公國小7-ELEVEN這。\n    」，意喻為何？）「抓2 尾」是指2000元、「秤重一點」」\n    是寅○○叫我一次買2,000 元他寅○○可用多一點的量（毒\n    品海洛因）給我、「土魠」指的是毒品海洛因、「用漂亮一\n    點啦」是我叫寅○○毒品的量用多一點。96年11月4 日當天\n    跟高文琳在光復路都家堡外向寅○○買1,000 元品海洛因後\n    ，在4 日晚上23時30分左右與高文琳合資以1,000 元在馬公\n    國小7-11超商門口向寅○○買第2 次毒品海洛因，同樣當場\n    在我E6-4712 號車上共同施用。」，於原審審理中亦證稱：\n    「（問：96年11月4 日，有無於馬公市都家堡對面向寅○○\n    買毒品？）有，‧‧‧。」、「（問：你當初買的數量及金\n    錢？）大概是壹仟元。」、「（問：同日是否另於馬公國小\n    旁超市再向他買毒品？）是。」、「（問：這次購買毒品情\n    形如何？）與上次同。」等語，均直指係向被告寅○○購買\n    毒品無誤，並無與被告寅○○合資購買後分食之情事，況被\n    告寅○○於警詢中（97年3 月7 日第5 次調查筆錄，警卷，\n    頁779 ）已自承：「（問：96年11月4 日癸○○是否在光復\n    路都家堡對面以1,000 元向你購買毒品海洛因？）有這件事\n    。」、「（問：96年11月4 日癸○○是否在馬公國小7-11超\n    商以1,000 元向你購買毒品海洛因？）有這件事。」等語，\n    足認被告寅○○確有附表一(二)編號1 、2 之販毒行為。再者\n    ，被告寅○○於警詢中（96年12月10日第2 次調查筆錄，警\n    卷，頁684 ）供稱：「（問：警方於今（16日）下午15時許\n    ，於安一山莊（馬公巿忠孝路105 號）前大馬路埋伏查緝毒\n    品案件時，你是否在場？做何事？）有，我拿一包毒品（海\n    洛因）交給壬○○時被警方查獲。」、「（問：警方當場於\n    壬○○左手查扣之一級毒品海洛因（毛重0.3 公克）是否為\n    你所有？是我交他的。」、「（問：你如何跟壬○○連絡購\n    買毒品？）大約今（16日）14時許，壬○○主動打電話給我\n    叫我幫他調2,000 元的毒品‧‧‧，然後我就連絡壬○○把\n    錢拿到我家門口就交給我，我再幫他連絡購買。」、於原審\n    審理中（98年4 月2 日上午審判筆錄）供稱：「（問：有無\n    在安一山莊前把一包海洛因交給壬○○？）有，‧‧‧，毒\n    品先交給壬○○，壬○○拿了毒品騎了10公尺就被警察查獲\n    ，‧‧‧」，證人壬○○則於警詢中（96年11月16日第1 次\n    調查筆錄，警卷，頁886 ）供稱：「（問：你今（16）日，\n    於何時？何地？是因何事被警方帶回警局製作筆錄？）在96\n    年11月16日15時左右。在馬公巿忠孝路安一飯店前。因購買\n    毒品，被警方帶回。」、「（問：上記時地是何人？購買何\n    種毒品？金額？數量為何？）向寅○○。購買毒品海洛因。\n    購買新台幣2,000 元。1 小包、重量不清楚。」、「（問：\n    你是以何種方式連絡寅○○至上記地點購買毒品海洛因？）\n    我在96年11月16日14時30分以0000000000號行動電話，撥打\n    寅○○所持0000000000號行動電話，連絡寅○○相互約在安\n    一飯店前交易毒品的。」等語，足見被告寅○○亦有附表一\n    (二)編號3 之販毒行為。被告寅○○辯稱：係與癸○○、壬○\n    ○合資購買後分食毒品云云，與上開事證不符，不足採信。\n三、被告寅○○於本院審理中雖聲請傳訊證人壬○○，惟查被告\n    寅○○確有販賣毒品予壬○○之犯行，已至為明確，已如前\n    述，無再調查之必要，爰依刑事訴訟法第163 條之2 第2 項\n    第3 款規定，駁回其聲請，併此明。另證人即共同被告癸\n    ○○於本院審理時雖證述：寅○○有與我一起出資去購買毒\n    品，購買之後一起施用毒品，共向寅○○調毒品2 次，寅○\n    ○都有出資等語（見本院卷二第10、11頁）。與證人癸○○\n    於原審所證述之上開情節不符，顯係事後迴護之詞，自難採\n    為有利於被告寅○○之認定。\n四、參諸有償提供他人毒品可能罹犯毒品危害防制條例相關重罪\n    ，上開被告寅○○交付海洛因並均收取價金之行為，應係有\n    利可圖，否則豈有鋌而走險甘冒罹犯重罪風險之理等情，足\n    見被告寅○○係基於營利意圖，而為附表一(二)所示之3 次販\n    賣海洛因行為，足堪認定。\n五、綜上，被告寅○○確有附表一(一)、(二)所示之幫助施用、販賣\n    海洛因之事實，事證明確，其犯行堪以認定。\n六、核被告寅○○就附表一（一）所為，係犯刑法第30條第1 項\n    、毒品危害防制條例第10條第1 項幫助施用第一級毒品罪；\n    其附表一（二）之所為，均係犯毒品危害防制條例第4 條第\n    1 項販賣第一級毒品罪。又被告寅○○就附表一（一）、附\n    表一（二）編號3 所示犯行，或係與子○○合資購買海洛因\n    後分食之，或係直接販賣海洛因予壬○○，核其此部分所為\n    ，係犯幫助施用第一級毒品罪、販賣第一級毒品罪，公訴人\n    認被告寅○○此部分均係犯轉讓第一級毒品罪，尚有未洽，\n    惟基本社會事實同一，爰變更起訴法條。被告寅○○就上開\n    販賣第一級毒品罪，於警詢時，供出毒品來源，因而使警方\n    破獲同案之被告子○○、乙○○及另案之被告午○○，有其\n    96年11月16日、同年11月23日警詢筆錄在卷可考，亦據證人\n    午○○於原審審理時證述屬實（見原審卷三43頁）。自依毒\n    品危害防制條例第17條第1 項規定減輕其刑。被告以上所犯\n    2 罪，犯意各別，罪名互殊，應予分論併罰。被告寅○○曾\n    因公共危險、過失傷害、竊盜等案件，經法院各判處有期徒\n    刑8 月、3 月、4 月，嗣定應執行刑1 年1 月確定，於94年\n    6 月20日執行完畢，又因詐欺案件，經法院判處有期徒刑4\n    月確定，於94年11月16日易科罰金執行完畢，其於5 年內故\n    意再犯本件有期徒刑以上之罪，為累犯，應加重其刑（死刑\n    、無期徒刑部分不得加重）。附表一（一）之犯行，依刑法\n    第30條第2 項減輕其刑，並先加後減之。被告寅○○無販毒\n    之前科紀錄，而所犯販賣第一級毒品犯行之法定刑為「死刑\n    或無期徒刑；處無期徒刑者，得併科新臺幣1 千萬元以下罰\n    金」，本件其販賣之海洛因，數量非鉅，所得非多，與專門\n    販售毒品之大盤尚難相提並論，犯罪情狀在客觀上可引起一\n    般人之同情，倘科以上開罪名之法定最輕本刑，猶嫌過重，\n    爰就其販賣第一級毒品罪部分，依刑法第59條規定，酌減其\n    刑，並先加後減之。\n七、原審就被告幫助施用第一級毒品罪部分，因而適用刑法第30\n    條，毒品危害防制條例第10條第1 項之規定，並審酌被告犯\n    後坦承犯行，態度良好等一切情狀，量處被告有期徒刑10月\n    。經核原審此部分認事用法並無不合，量刑亦屬適度。被告\n    上訴意旨，指摘原審此部分判決量刑過重不當，為無理由，\n    應予駁回。\n八、原審就被告販賣第一級毒品罪部分予以論科，固非無見，惟\n    查被告於警詢時，已供出毒品來源，並使警方查獲販毒之同\n    案被告子○○、乙○○，及另案被告午○○，已如前述，原\n    審未依毒品危害防制條例第17條第1 項規定，減輕其刑，自\n    有未合。被告上訴意旨，否認犯罪，固無足取，然原審此部\n    分判決既有上述可議，自應由本院將原審此部分判決撤銷改\n    判。審酌被告所犯情節非重，且能供出毒品上源，使警方查\n    獲販毒之子○○、乙○○、午○○等人等一切情狀，量處如\n    主文第2 項所示之刑。並與上訴駁回部分所處有期徒刑10月\n    ，並定其應執行刑有期徒刑14年。扣案之0000000000號、00\n    00000000號行動電話各1 支，均係其所有供犯罪所用之物，\n    應依毒品危害防制條例第19條第1 項之規定宣告沒收。又按\n    販賣毒品所得之對價，不問其中何部分屬於成本，何部分屬\n    於犯罪所得之財物，應均予沒收，此有65年度第5 次刑庭庭\n    推總會議決議意旨可資參照。被告寅○○如附表一（二）所\n    示販毒所得，均應依毒品危害防制條例第19條第1 項之規定\n    沒收，如全部或一部不能沒收時，均以其財產抵償之。扣案\n    之附表一（二）編號3 所示之海洛因1 小包，因已賣予壬○\n    ○，查獲時已在壬○○實力支配下，自毋庸於被告寅○○項\n    下宣告沒收。\n貳、被告子○○部分\n一、訊據上訴人即被告子○○矢口否認有上開幫助施用或販賣第\n    一級毒品海洛因之犯行，辯稱：伊於96年11月15日沒有買到\n    毒品，所以也沒有交毒品給未○○；96年11月16日寅○○是\n    拿2000元償還欠伊之債務，伊並與寅○○在伊家中一起施用\n    毒品，施用所餘之毒品嗣由伊攜至66西餐廳附近擬再次與寅\n    ○○一同施用，惟經警方查扣，伊無幫助施用或販賣海洛因\n    之犯意或行為云云。\n    經查：被告子○○於警詢中（96年12月18日第2 次調查筆錄\n    ，警卷，頁13~15 ）供稱：「（問：你於上述供稱有轉讓海\n    洛因毒品給未○○一次，詳細轉讓方式及時間、地點為何？\n    聯絡方式？）於96年11月13日至15日某日下午約於14時至16\n    日許，他以0932（詳細號碼不詳）之行動電話撥打我持用之\n    0000000000號手機與我聯絡，問我有沒有辦法購買海洛因毒\n    品，我說我要問看看，掛電話後我撥打洪家駒持用之電話00\n    00000000號手機，詢問他有無海因，他答稱有，我隨即再撥\n    打未○○手機聯繫告知我有辦法調到海洛因，就與未○○相\n    約在馬公巿光復路「和興」大飯店門口見面，他拿1500元給\n    我，我出資500 元共計2000元，我當他面撥打給洪家駒告知\n    他向其購買2000元海洛因毒品，相約在澎湖縣農會生鮮超巿\n    門口見面交易購買。我就先行離開騎乘機車到該處等候洪家\n    駒，過了約5 至10分鐘，洪家駒駕駛黑色轎車（台北巿車籍\n    車牌不詳）獨自前來，邀我上車交易，我上車後將2000元交\n    給洪家駒後，他拿一包夾鏈袋裝置之海洛因毒品給我，我就\n    下車騎機車返家先行施用一次約四分之一數量後，再聯絡未\n    ○○到馬公巿「澎湖縣農會生鮮超巿」門口見面（經查詳細\n    時間為96年11月15日14時33分），將剩餘之四分之三海洛因\n    拿給未○○後各自離去。」、「（問：你向洪家駒購買過幾\n    次毒品？分別於何時在何處購買？數量？價錢為何？）‧‧\n    ‧。第一次就是上述洪家駒於96年11月15日，在馬公「澎湖\n    縣農會生鮮超巿」門口見面，以2000元之代價，與未○○合\n    資向其購買海洛因一包（我施用四分之一包、未○○分得四\n    分之三海洛因）。‧‧‧。」，已詳為供述其與共同被告未\n    ○○如何合資購買海洛因後分食等情，核與共同被告未○○\n    於另案（臺灣澎湖地方法院檢察署96年度毒偵字第38號、97\n    年度毒偵字第10號）檢察官偵查時坦認：於96年11月中旬，\n    有與被告子○○合資購買海洛因後，自行施用海洛因1 次等\n    情相符（未○○施用毒品部分詳如後述），被告子○○及證\n    人未○○於原審審理中均翻異前詞，供稱：該次沒有拿到毒\n    品，也沒有施用云云，分屬卸責、迴護之詞，均不足採。被\n    告子○○確有與未○○合資購買海洛因，並由被告子○○出\n    面購買海洛因後交予未○○分食之犯行，堪以認定。又被告\n    子○○於警詢中（96年11月16日第1 次調查筆錄，澎警刑字\n    第0961213551號卷，頁3 、6 ）供稱：「（問：寅○○如何\n    與你聯繫取得海洛因毒品？）。他起先是以0000000000號行\n    動電話撥打我所持有之0000000000行動電話，... 。」、「\n    （問：警方查扣你持有之行動電話是否為你當場與寅○○聯\n    繫毒品交易之手機？）就是這支NOKIA 黑色手機沒錯。」，\n    於96年12月18日檢察官偵查中（96偵749 卷，頁37）供稱：\n    「（問：96年11月16日下午2 點、4 點半左右為何要拿毒品\n    給寅○○？）寅○○一直打電話給我，‧‧‧，後來寅○○\n    就跑到我文光路住處找我，要我幫他調海洛因，並塞了2000\n    元給我，我說等一下，後來我就打電話給洪家駒，那時寅○\n    ○已經先離開。後來洪家駒表示有毒品，我就跟洪家駒拿，\n    洪家駒將毒品送到我家，我再打電話給寅○○到馬小附近的\n    7-11拿毒品。4 點半那一次寅○○又打電話問我是否可以調\n    ，我又打電話給洪家駒，洪家駒直接拿毒品給我，我帶在身\n    上，後來在忠孝路66西餐廳附近等寅○○時就被抓了。」等\n    語，證人寅○○則於警詢中（96年11月16日第1 次調查筆錄\n    ，警卷，頁33~34 ）供稱：「（問：該毒品（即交予壬○○\n    並經警查扣之海洛因）是向何人購買？重量、價值為何？）\n    我是向子○○（經查證：男、69.10.08日，身分證Ｚ0000000\n    00、住馬公巿光明里文光路66號）購買的，重量經警方查證\n    為0.3 公克（毛重），價值2 仟元。」、「（問：你如何與\n    子○○連絡購買毒品事宜？）我先打電話給子○○後問有沒\n    有毒品，他說有，然後他就叫我先錢拿過去他家門口給他，\n    叫我先回去等電話，然後我就先回家（安一山莊前）與壬○\n    ○一起等電話，我們差不多等了一、二十分鐘，他打電話給\n    我叫我到馬公國小旁7-11超商內找他，他就在7-11超商內當\n    場將毒品交給我，當我把該毒品拿回去交給壬○○後就被警\n    方當場查獲。」、於原審審理中供稱：「（問：被警察抓到\n    後，警察有無問你東西哪裡來的？）有，我說向子○○拿的\n    。」、「（問：警察跟你說什麼？）警察叫我再打一次電話\n    給子○○買毒品，叫我引誘他出來。」、「配合警方這次，\n    我在電話中也是跟子○○說我2000元麻煩他幫我調毒品，他\n    有說要拿2000元毒品過來給我」等語，是互核被告子○○、\n    證人寅○○2 人之供述，再參諸扣案之由被告子○○身上扣\n    獲之毒品1 小包（毒品淨重0.11公克，空包裝重0.33公克）\n    及另案由壬○○身上扣獲之0.3 公克毒品，確均屬海洛因無\n    訛，有法務部調查局鑑定書附卷可稽等情，足認被告子○○\n    確有附表二（二）所示販賣海洛因之犯行。被告子○○及證\n    人寅○○於原審審理中供稱：寅○○係清償積欠之債務2000\n    元，該2000元與0.3 公克之海洛因無交易之對價關係及被告\n    子○○辯稱：係持毒品擬與寅○○一同施用而遭查獲云云，\n    均與前揭事證不符，顯係卸責、迴護之詞，均不足採。又寅\n    ○○於96年11月16日配合警方辦案，虛以電話向被告子○○\n    索求毒品前，被告莊智前甫於前一刻之同日14時許販賣海洛\n    因0.3 公克予寅○○，乃被告子○○旋於同日16時35分許，\n    再次慨然應允並攜帶毒品至約定地點等待交付，顯然被告子\n    ○○就此次販賣之行為，本有犯意，尚非出於警方指示寅○\n    ○索藥行為之引誘，此與陷害教唆係使原無犯罪意思之人因\n    唆使而萌生犯意之情形，迥不相侔。\n二、證人即同案被告未○○於本院審理中雖證述：96年11月15日\n    左右，我原本要託子○○去購買毒品，後來我錢不夠，他就\n    不理我，子○○沒有拿毒品給我，我也沒有將錢交給子○○\n    等語（見本院卷二第21頁）。惟查被告子○○確有與未○○\n    合資購買毒品，幫助未○○施用第一級毒品之事，業據證人\n    未○○於警訊及偵查中證述明確。足見證人未○○於本院審\n    理中上開證詞，無非事後迴護之詞，自難採為有利於被告子\n    ○○之認定。另證人即共同被告寅○○於本院審理中雖證述\n    ：96年11月16日14時許，我有拿2 千元還給子○○，請他順\n    便拿一些毒品給我施用。給錢之後約15至20分鐘，他就交毒\n    品一小包約0.3 公克給我，但在電話中沒說要買毒品。第2\n    次被警查獲後，警方要我配合，所以同日16時35分許，我打\n    電話約子○○出來向他購買毒品，但我本身並無購買毒品的\n    意思。惟查證人寅○○第一次向子○○購入毒品之後，立即\n    出售予壬○○，後即被警查獲，寅○○乃配合警方打電話給\n    子○○，要求再次購買毒品，而誘捕子○○等情，已據其於\n    警詢及原審審理證述明確。足見證人寅○○於本院審理時上\n    開證述，無非事後迴護之詞，自難採為有利於被告子○○之\n    認定。\n三、參諸有償提供他人毒品可能罹犯毒品危害防制條例相關重罪\n    ，上開被告子○○於96年11月16日之2 次犯行，或已交付海\n    洛因並收取價金，或持海洛因等候交易而為警查獲，應均有\n    營利之所圖，否則豈有鋌而走險甘冒罹犯重罪風險之理等情\n    ，足見被告子○○係基於營利意圖而販賣海洛因予寅○○，\n    堪以認定。綜上，被告子○○確有如附表二所示幫助施用、\n    販賣海洛因之事實，事證明確，其犯行堪以認定。\n四、核被告子○○就附表二（一）所為，係犯刑法第30條第1 項\n    、毒品危害防制條例第10條第1 項幫助施用第一級毒品罪；\n    其附表二（二）編號1 之所為，係犯毒品危害防制條例第4\n    條第1 項販賣第一級毒品罪；其附表二（二）編號2 之所為\n    ，則係犯毒品危害防制條例第4 條第6 項、第1 項販賣第一\n    級毒品未遂罪。又被告子○○附表二（一）之犯行，係代為\n    合資購買海洛因後，再與未○○分食，核其此部分所為，係\n    犯幫助施用第一級毒品罪，公訴人認被告子○○此部分係犯\n    毒品危害防制條例第8 條第1 項轉讓第一級毒品罪，尚有未\n    洽，惟基本社會事實同一，爰變更起訴法條。被告子○○就\n    上開犯行，犯意各別，行為互殊，應分論併罰。附表二（一\n    ）、附表二（二）編號2 之犯行，應分別依刑法第30條第2\n    項、第25條第2 項減輕其刑。被告子○○無販毒之前科紀錄\n    ，而所犯販賣第一級毒品犯行之法定刑為「死刑或無期徒刑\n    ；處無期徒刑者，得併科新臺幣1 千萬元以下罰金」，本件\n    其販賣之海洛因，數量非鉅，所得非多，與專門販售毒品之\n    大盤尚難相提並論，犯罪情狀在客觀上可引起一般人之同情\n    ，倘科以上開罪名之法定最輕本刑，猶嫌過重，爰就其販賣\n    第一級毒品罪部分，依刑法第59條規定，酌減其刑，附表二\n    （二）編號2 部分並遞減之。\n五、原審因而適用刑法第30條、第25條第2 項、第59條、第51條\n    第5 款，毒品危害防制條例第4 條第1 項、第6 項、第10條\n    第1 項、第18條第1 項前段、第19條第1 項規定，並審酌被\n    告犯後翻異前詞，未見悔意等一切情狀，就被告幫助施用第\n    一級毒品部分量處有期徒刑8 月，就其販賣第一級毒品部分\n    量處有期徒刑15年2 月，就其販賣第一級毒品未遂部分量處\n    有期徒刑8 年，並定其應執行刑有期徒刑16年。並認扣案之\n    0000000000號行動電話1 支，係其所有供犯罪所用之物，應\n    依毒品危害防制條例第19條第1 項之規定宣告沒收。其如附\n    表二（二）編號1 所示販毒所得，應依毒品危害防制條例第\n    19條第1 項之規定沒收，如全部或一部不能沒收時，以其財\n    產抵償之。扣案之附表二（二）編號2 所示之海洛因1 小包\n    ，應依毒品危害防制條例第18條第1 項前段之規定，宣告沒\n    收並銷燬之。至扣案子○○所有之夾鏈袋16個及吸管分裝器\n    1 支，尚無證據顯示係屬其供犯罪所用之物，爰不宣告沒收\n    。經核原判決認事用法並無不合，量刑亦屬適度，被告子○\n    ○上訴意旨，仍執前詞，否認犯罪，指摘原判決不當，為無\n    理由，應予駁回。\n參、被告申○○部分\n一、訊據上訴人即被告申○○對於附表三（三）轉讓海洛因之事\n    實，於本院審理時坦承不諱，對於附表三（一）、（二）之\n    交易行為，雖不爭執，惟矢口否認有販賣第一、二級毒品之\n    犯行辯稱：無販賣毒品之犯意云云。\n    經查：被告申○○自白附表三（三）之犯行，核與證人癸○\n    ○、陳志盟、翁丁元於警詢或原審審理中證述之情節相合。\n    又被告申○○關於附表三（一）、（二）之犯行，亦據證人\n    辰○○、乙○○、庚○○、丑○○、歐家雄、丁○○、癸○\n    ○、甲○○、午○○於警詢或原審審理中供證屬實。參諸被\n    告申○○於警詢中（96年12月17日第3 次筆錄，澎警刑字第\n    0971213122號警卷，頁346 、97年1 月28日第5 次筆錄，澎\n    警刑字第0971213122號警卷，頁418~419 ）供稱：「（問：\n    為何辰○○等人有毒品過來澎湖都會找你過去幫忙調配、分\n    裝？且是由癸○○、乙○○等人在負責連絡你？）乙○○本\n    來跟癸○○就熟識，李早知我跟癸○○施打毒品大都我在出\n    錢，所以有意思叫我要過去買，因為我到安一山莊協助分裝\n    毒品時，辰○○有向我們在場人提到如果幫他賣掉1 小包毒\n    品海洛因（新台幣1000元計），我們就可從中獲取新台幣20\n    0 元利潤。後來因調配失敗，所分裝之毒品又被在場協助分\n    裝的寅○○搶走了，所以根本沒東西可拿。」、「（問：你\n    是否在96年9 至10月間就知道乙○○、癸○○要幫忙辰○○\n    賣毒品的事？是否曾親自答應癸○○可以協助一同販賣？）\n    是的。沒有什麼親自答應，只是癸○○約我要去哪賣毒品或\n    叫我拿毒品給午○○、甲○○，或向午○○、甲○○收取賣\n    毒品的錢時，我不會反對沒去。」等語，顯然早知共同被告\n    辰○○、癸○○、乙○○等人有販賣毒品之情事，乃於附表\n    三（一）、（二）所示時地，協助辰○○、癸○○、乙○○\n    、庚○○為毒品交易之電話聯絡、交付毒品或收取金錢之行\n    為，顯有與渠等共同販毒之犯意聯絡及行為分擔，被告申○\n    ○辯稱：伊無販賣毒品之犯意云云，尚非可採。\n二、綜上，被告申○○確有附表三（一）、（二）、（三）所示\n    之販賣或轉讓海洛因、安非他命之事實，事證明確，其犯行\n    堪以認定。\n三、核被告申○○就附表三（一）所為，均係犯毒品危害防制條\n    例第4 條第1 項販賣第一級毒品罪；其附表三（二）之所為\n    ，均係犯毒品危害防制條例第4 條第2 項販賣第二級毒品罪\n    ；其附表三（三）之所為，則均係犯毒品危害防制條例第8\n    條第1 項轉讓第一級毒品罪。其就附表三（一）、（二）之\n    犯行，分別與辰○○、癸○○、乙○○或庚○○有犯意之聯\n    絡及行為之分擔，均屬共同正犯。其就上開犯行，犯意各別\n    ，行為互殊，應分論併罰。被告申○○無販毒之前科紀錄，\n    而所犯販賣第一、二級毒品犯行之法定刑分別為「死刑或無\n    期徒刑；處無期徒刑者，得併科新臺幣1 千萬元以下罰金」\n    、「無期徒刑或7 年以上有期徒刑，得併科新臺幣7 百萬元\n    以下罰金」，本件其販賣之海洛因、安非他命，數量非鉅，\n    所得非多，與專門販售毒品之大盤尚難相提並論，犯罪情狀\n    在客觀上可引起一般人之同情，倘科以上開罪名之法定最輕\n    本刑，猶嫌過重，爰就其販賣第一、二級毒品罪部分，均依\n    刑法第59條規定，酌減其刑。\n四、原審因而適用毒品危害防制條例第4 條第1 項、第2 項、第\n    8 條第1 項、第19條第1 項、刑法第28條、第59條、第51條\n    第5 款之規定，並審酌被告犯後坦承部分犯行，態度尚佳等\n    一切情狀，就被告販賣第一級毒品，共4 罪，各處有期徒刑\n    15年2 月；就販賣第二級毒品部分，共3 罪，各處有期徒刑\n    3 年8 月，就其轉讓第一級毒品共3 罪，各處有期徒刑1 年\n    6 月，並定其應執行刑有期徒刑16年。並認未扣案之000000\n    0000號、0000000000、0000000000號行動電話各1 支，分屬\n    被告申○○、共犯癸○○、庚○○所有供犯罪所用之物，應\n    依毒品危害防制條例第19條第1 項之規定沒收，如全部或一\n    部不能沒收時，均追徵其價額或以其財產抵償之。又共同正\n    犯之犯罪所得，因係合併計算，為避免執行時發生重複沒收\n    之情形，故各共同正犯之間係採連帶沒收主義，於裁判時僅\n    諭知連帶沒收，不得就全體共同正犯之總所得，對各該共同\n    正犯分別重複諭知沒收，有最高法院95年度台上字第1781號\n    判決要旨可資參照。被告申○○如附表三（一）、（二）所\n    示販毒所得，應依毒品危害防制條例第19條第1 項之規定與\n    辰○○、癸○○、庚○○等人連帶沒收，如全部或一部不能\n    沒收時，均以其財產抵償之。至扣案申○○所有之手機2 支\n    （均含SIM 卡），尚無證據顯示係屬其供犯罪所用之物，爰\n    不宣告沒收。經核原審此部分判決認事用法並無不合，量刑\n    亦屬適度，被告上訴意旨，或否認犯罪，或指摘原審此部分\n    判決量刑過重不當，為無理由，應予駁回。\n肆、被告巳○○部分\n一、訊據被告巳○○對於附表四（一）（二）所示交付毒品之行\n    為，均坦承不諱，惟矢口否認有販賣第一、二級毒品之犯意\n    ，辯稱：伊無販賣之營利犯意，祇是幫朋友調毒品云云。\n二、經查：被告巳○○對於附表四（一）（二）等事實之供述，\n    核與證人戊○○於警詢（96年12月18日第1 次調查筆錄，00\n    00000000號警卷，頁15）、證人癸○○於警詢（97年2 月1\n    日第4 次調查筆錄，警卷，頁186 、190 －192 、97年3 月\n    18日對質筆錄，警卷，頁1110、97年3 月19日對質筆錄，警\n    卷，頁1126）及原審審理中之證述相符，並有監聽譯文（96\n    年11月2 日1744~2035 時譯文，警卷，頁199 、96年11月3\n    日06時06分譯文，警卷，頁203 、96年11月7 日1929時、96\n    年11月10日1633時譯文，警卷，頁204 ）附卷可稽，足見被\n    告巳○○確以其所有之門號0000000000號行動電話與欲購買\n    安非他命、海洛因之戊○○、癸○○相互聯繫交易細節後，\n    於附表四（一）（二）之時、地，分別販賣安非他命及海洛\n    因。\n三、被告巳○○販賣予戊○○、癸○○之毒品安非他命，係向其\n    上線酉○○所購入等情，業據證人酉○○於本院審理時證述\n    明確（見本院卷二第12、13頁）。被告巳○○於偵查中供出\n    其販賣毒品之來源，使警方因而查獲販毒之酉○○，自得依\n    毒品危害防制條例第17條第1 項規定。至於被告巳○○另稱\n    ：伊販賣之安非他命亦向卯○○購入云云。然查證人卯○○\n    於本院審理時結稱：我並沒有和巳○○交易過毒品，我本身\n    沒有在販毒，也沒有因販毒被警方偵辦過等情（見本院卷二\n    第15、16頁）。另辯護人詰問證人辛○○「（於96年11月2\n    、3 日在澎湖縣光復路飯店內，巳○○稱有向人拿安非他命\n    ，當時你有否在場？看到情形如何？）我不知道日期，我有\n    在場，巳○○接到電話後，就向飯店內一位叫「志哥」的人\n    拿東西，我看到白白一包應該是海洛因，巳○○拿1 千元給\n    志哥。」「（97年3 月19日警訊筆錄上所附卯○○的照片，\n    「志哥」是否照片上之個人？）我無法確定，因為時間已經\n    很久。」（見本院卷二第7 、8 頁）。是證人辛○○之上開\n    證詞，亦難採為有利於被告巳○○，從而，被告巳○○上開\n    指稱，尚屬無據，併此明。\n四、參諸有償提供他人毒品可能罹犯毒品危害防制條例相關重罪\n    ，上開被告巳○○交付毒品或收取價金之行為，應係有利可\n    圖，否則豈有鋌而走險甘冒罹犯重罪風險之理等情，足見其\n    係基於營利意圖，而為附表四（一）（二）所示之販賣毒品\n    行為，被告巳○○辯稱：無營利之意思云云，不足採信。證\n    人戊○○於本院證述係請巳○○幫忙買等語，亦不足為被告\n    巳○○未從中獲利之有利證明。\n五、綜上，被告巳○○確有附表四（一）、（二）所示之販賣安\n    非他命、海洛因之事實，事證明確，其犯行堪以認定。\n六、核被告巳○○就附表四（一）所為，均係犯毒品危害防制條\n    例第4 條第2 項販賣第二級毒品罪，被告於偵查中供出毒品\n    來源，使警方破獲販毒者酉○○，已如前述，應依同條例第\n    17條第1 項規定，減輕其刑，其附表四（二）之所為，均係\n    犯毒品危害防制條例第4 條第1 項販賣第一級毒品罪。其就\n    上開犯行，犯意各別，行為互殊，應分論併罰。被告巳○○\n    無販毒之前科紀錄，而所犯販賣第一、二級毒品犯行之法定\n    刑分別為「死刑或無期徒刑；處無期徒刑者，得併科新臺幣\n    1 千萬元以下罰金」、「無期徒刑或7 年以上有期徒刑，得\n    併科新臺幣7 百萬元以下罰金」，本件其販賣之海洛因、安\n    非他命，數量非鉅，所得非多，與專門販售毒品之大盤尚難\n    相提並論，犯罪情狀在客觀上可引起一般人之同情，倘科以\n    上開罪名之法定最輕本刑，猶嫌過重，爰就其販賣第一、二\n    級毒品罪部分，均依刑法第59條規定，酌減其刑。被告販賣\n    第二級毒品罪部分，依法遞減之。\n七、原審就被告販賣第一級毒品部分，因而適用毒品危害防制條\n    例第4 條第1 項、刑法第59條、第51條第5 款之規定，並審\n    酌被告已坦承部分犯行，態度尚佳等一切情狀，就其販賣第\n    一級毒品，共2 罪，各處有期徒刑15年2 月。並認扣案之夾\n    鏈袋壹包（內裝小夾鏈袋捌拾陸個）沒收，行動電話、販毒\n    所得之沒收、追徵價額、抵償均如附表四（二）應沒收之物\n    （1 ）、（2 ）所示。經核原審此部分判決認事用法並無不\n    合，量刑尚屬適度，被告上訴意旨，仍執前詞，否認犯罪，\n    指摘原審此部分判決不當，為無理由，應予駁回。\n八、原審就被告販賣第二級毒品部分予以論科，固非無見，惟被\n    告於偵查中，已供出安非他命來源，因而使警方破獲安非他\n    命之酉○○，有其97年3 月17日偵查筆錄（見97年偵字第16\n    7 號卷第6 頁）在卷可稽。並證據人酉○○於偵查中及本院\n    審理時證述屬實（見同上卷第6 頁及本院卷二第12、13頁）\n    。原審未依毒品危害防制條例第17條第1 項規定減輕其刑，\n    自有未合。被告上訴意旨，否認犯罪，固無足取，然原審此\n    部分判決既有上述可議，自應由本院將原審此部分判決及其\n    定執行刑撤銷改判。審酌被告於偵查中坦承犯行，並供出毒\n    品來源，使警方查獲販毒之酉○○等一切情狀，就其所犯販\n    賣第二級毒品，共2 罪，各處有期徒刑2 年8 月。並與其上\n    訴駁回所處販賣第一級毒品，共2 罪，各處有期徒刑15年2\n    月，並定其應執行刑有期徒刑15年3 月。未扣案之00000000\n    00號行動電話1 支，屬其所有供犯罪所用之物，應依毒品危\n    害防制條例第19條第1 項之規定沒收，如全部或一部不能沒\n    收時，追徵其價額或以其財產抵償之。附表四（一）、（二\n    ）所示販毒所得，應依毒品危害防制條例第19條第1 項之規\n    定沒收，如全部或一部不能沒收時，均以其財產抵償之。扣\n    案之夾鏈袋1 包（內裝小夾鏈袋86個）係被告巳○○所有供\n    犯罪所用之物，應依刑法第38條第1 項第2 款，宣告沒收。\n    至扣案之海洛因（毛重0.2 公克）、安非他命（毛重2 克）\n    及注射針筒1 支，均係供被告巳○○吸毒所用之物，已據其\n    於原審97年度訴字第1 號案件中供述在卷，該等物品與其販\n    毒犯行無涉，爰不另宣告沒收。\n伍、被告庚○○部分：\n一、訊據被告庚○○矢口否認有何販賣毒品犯行，辯稱：伊無販\n    賣之營利犯意或行為云云。\n二、經查：被告庚○○於警詢中（97年1 月3 日第2 次調查筆錄\n    ，警卷，頁447~448 、97年1 月3 日第2 次調查筆錄，警卷\n    ，頁448 ）供稱：「（問：96年11月10日20時25分，申○○\n    是否曾撥打你0000000000號電話告訴你歐家雄要毒品，電話\n    中你叫蔡到乙○○家拿，後來歐家雄是否與你連絡？由何人\n    販賣何種毒品給歐家雄？）確實有這件事情。當天申○○沒\n    來，是歐家雄打我電話，我跟辰○○說過後我與辰○○一同\n    前往馬公國中大門前，由辰○○親自把毒品安非他命賣給歐\n    家雄。」、「（問：你因故於96年11月10日23時10以電話告\n    知申○○「那裡就是用那個拿5 （碰掉）」，他（指歐家雄\n    ）說你之前有欠一個2 的。）這就是歐家雄沒拿錢給辰○○\n    原因，因為當天歐家雄跟我說申○○有欠他（歐家雄）錢，\n    歐跟辰○○說要抵申○○所欠的錢，辰○○才叫我打電話問\n    申○○。」、「（問：申○○是否曾於96年11月11日00時18\n    分撥打你0000000000號電話告訴你丁○○要買毒品？‧‧‧\n    ）‧‧‧，我確實有跟辰○○到中興國小旁7-11超商前找申\n    ○○、綽號「鳥嶼老仔」丁○○、及林另一位我不認識的朋\n    友，辰○○也確實有拿1 小包毒品安非他命給丁○○，辰○\n    ○上車後有跟我提到丁○○沒有付錢。」等語，核與證人辰\n    ○○、申○○、歐家雄、丁○○於警詢或原審審理中證稱：\n    上開2 次行為被告庚○○均有參與電話聯絡或交付毒品等語\n    大致相符，且有96年11月11日00時18分電話監聽譯文（警卷\n    ，頁389 ）附卷可稽。參諸被告庚○○於警詢中（97年1 月\n    3 日第2 次筆錄，澎警刑字第0971213122號警卷，頁448 、\n    97 年1月31日第4 次筆錄，澎警刑字第0971213122號警卷，\n    頁478 ）供稱：「（問：你與陳（建榮）施用之毒品來源為\n    何（請詳述購買時地與金額）？）毒品來源有些是辰○○免\n    費提供，‧‧‧」、「（問：96年10月間居住於乙○○家目\n    的為何？期間是否曾參與協助辰○○、乙○○、申○○、癸\n    ○○、寅○○等人販賣毒品行為？）方便向辰○○購買毒品\n    。‧‧‧，會在安一山莊幫辰○○分裝毒品是因為辰○○常\n    會提供免費毒品讓我施用，‧‧‧」等語，堪認其早知共同\n    被告辰○○等人有販賣毒品之情事，乃於附表五協助辰○○\n    、申○○為毒品交易之電話聯絡、交付毒品等行為，顯有與\n    渠等共同販賣之犯意聯絡及行為分擔，被告庚○○辯稱：係\n    辰○○1 人販毒，伊無與他人共同販賣毒品云云，尚非可採\n    。\n三、綜上，被告庚○○確有附表五所示之販賣安非他命之事實，\n    事證明確，其犯行堪以認定。\n四、核被告庚○○就附表五所為，均係犯毒品危害防制條例第4\n    條第2 項販賣第二級毒品罪。其就附表五之犯行，均分別與\n    辰○○、申○○有犯意之聯絡及行為之分擔，均屬共同正犯\n    。其就上開犯行，犯意各別，行為互殊，應分論併罰。被告\n    庚○○曾於93年間，因賭博案件，經法院判處有期徒刑3 月\n    確定，於93年11月5 日易科罰金執行完畢，其於5 年內故意\n    再犯本件有期徒刑以上之罪，為累犯，應加重其刑（無期徒\n    刑部分不得加重）。被告庚○○無販毒之前科紀錄，而所犯\n    販賣第二級毒品犯行之法定刑為「無期徒刑或7 年以上有期\n    徒刑，得併科新臺幣7 百萬元以下罰金」，本件其販賣之安\n    非他命，數量非鉅，所得非多，與專門販售毒品之大盤尚難\n    相提並論，犯罪情狀在客觀上可引起一般人之同情，倘科以\n    上開罪名之法定最輕本刑，猶嫌過重，爰就其販賣第二級毒\n    品犯行，均依刑法第59條規定，酌減其刑，並先加後減之。\n五、原審因而適用毒品危害防制條例第4 條第2 項、第19條第1\n    項、刑法第28條、第47條第1 項、第51條第5 款之規定，並\n    審酌被告大部分坦承犯行，所犯情節非重等一切情狀，就其\n    所犯販賣第二級毒品2 罪，各量處有期徒刑3 年8 月，並定\n    其應執行刑有期徒刑4 年。並認未扣案之0000000000號、00\n    00000000號行動電話各1 支，分屬共犯申○○、被告庚○○\n    所有供犯罪所用之物，應依毒品危害防制條例第19條第1項\n    之規定沒收，如全部或一部不能沒收時，均追徵其價額或以\n    其財產抵償之。被告庚○○如附表五編號2 所示販毒所得，\n    應依毒品危害防制條例第19條第1 項之規定，與辰○○、申\n    ○○連帶沒收，如全部或一部不能沒收時，以其財產抵償之\n    。經核原審此部分判決認事用法並無不合，量刑亦屬適度，\n    被告上訴意旨，仍執前詞，否認犯罪，指摘原審此部分判決\n    不當，為無理由，應予駁回。\n陸、被告未○○部分\n一、訊據被告未○○對於附表六編號1 、3 、4 施用第一級毒品\n    海洛因之犯行，坦承不諱，惟矢口否認有何編號2 之施用毒\n    品犯行，辯稱：該次拿錢給被告子○○去調毒品，但子○○\n    沒調到，伊沒有拿到毒品，所以也沒有施用云云。\n二、經查：被告未○○對於附表六編號1 、3 、4 犯行之自白，\n    核與證人癸○○（97年1 月31日第2 次調查筆錄，警卷，頁\n    1238、97年3 月18日對質筆錄，警卷，頁1257~1258 ）、翁\n    維昌（97年3 月21日第1 次調查筆錄，警卷，頁1153）、己\n    ○○（對質筆錄，警卷，頁1259~1260 ）於警詢中或本院審\n    理中之供述相符，堪認屬實。又被告未○○於警詢中自承（\n    96年11月16日第4 次調查筆錄，警卷頁28~29 ）：「（問：\n    於96年11月15日下午約於14時至16時許，你是否以0932之行\n    動話撥打子○○持用之0000000000號手機，並問他有沒有辦\n    法購買海洛因毒品，事後他就與你相約在馬公巿光復路「和\n    興」大飯店門口見面，你拿1500元給他，子○○另出資500\n    元共計2000元，他購買毒品後，約你於96年11月15日14時33\n    分，到馬公巿「澎湖縣農會生鮮超巿」門口見面，將剩餘之\n    四分之三海洛因毒品拿給你後，雙方才各自離去？）‧‧‧\n    。於上述時、地，子○○有將海洛因毒品拿給我後，雙方才\n    各自離去沒錯。」等語，又於另案（臺灣澎湖地方法院檢察\n    署96年度毒偵字第38號、97年度毒偵字第10號）檢察官偵查\n    時坦認：於96年11月中旬，有與被告子○○合資購買海洛因\n    後，自行施用海洛因1 次等情，而共同被告子○○亦於警詢\n    中供稱該次確與未○○合資購買毒品後，由子○○施用1/ 4\n    ，所餘3/4 在澎湖縣農會生鮮超巿門口交予未○○等語（96\n    年12月18日警詢第2 次調查筆錄，警卷，頁13~15 ，參見上\n    開被告子○○部分理由欄），足見被告未○○確有與子○○\n    合資購買海洛因後，自行施用海洛因1 次之犯行，被告未○\n    ○及證人子○○於原審審理中均翻異前詞，供稱：該次沒有\n    拿到毒品，也沒有施用云云，分屬卸責、迴護之詞，均不足\n    採。\n三、被告雖又辯稱：附表六施用海洛因之犯行，業經檢察官緩起\n    訴處分在案，自不得再對其起訴云云。惟查被告未○○附表\n    六所示犯行併同其他施用海洛因犯行，固曾經臺灣澎湖地方\n    法院檢察署96年度毒偵字第38號、97年度毒偵字第10號於97\n    年3 月5 日為緩起訴處分，緩起訴期間為1 年在案。然本件\n    檢察官係另以發現新事實、新證據為由（即原審已另諭知被\n    告無罪確定部分），自得於緩起訴期間內就同一案件逕行起\n    訴，原緩起訴處分並因此而失效力（最高法院94年度台非字\n    第215 號判決參照）。從而，被告所辯上情，自無可取。綜\n    上所述，本件事證明確，被告之犯行，堪以認定。\n四、核被告未○○就附表六所為，均係犯毒品危害防制條例第10\n    條第1 項施用第一級毒品罪。其持有毒品之行為為施用之行\n    為所吸收，不另論罪。其就上開犯行，犯意各別，行為互殊\n    ，應分論併罰。又被告未○○曾因違反毒品危害防制條例案\n    件，經法院判處有期徒刑7 月，嗣減為有期徒刑3 月15日確\n    定，於96年7 月17日執行完畢，其於5 年內故意再犯本件有\n    期徒刑以上之罪，為累犯，應加重其刑。又施用毒品具成癮\n    性，其戒除本屬不易，現行各地方法院檢察署毒品減害計劃\n    之戒癮療程法，目的即在積極協助吸毒者戒除毒癮，本件被\n    告未○○施用毒品之行為，前經臺灣澎湖地方法院檢察署96\n    年度毒偵字第38號、97年度毒偵字第10號於97年3 月5 日為\n    緩起訴處分，命令被告接受美沙冬替代療法，而被告在緩起\n    訴期間內已積極履行檢察官所命處遇措施，顯見本件被告未\n    ○○所為附表六施用海洛因之犯行，情有可憫，爰依刑法第\n    59條規定，減輕其刑，並先加後減之。\n五、原審因而適用毒品危害防制條例第10條第1 項、第41條、第\n    47條第1 項、第59條、第51條第5 款之規定，並審酌被告犯\n    後大致坦承犯行，態度尚佳等一切情狀，就被告所犯施用第\n    一級毒品4 罪，各處有期徒刑4 月，並定其應執行刑有期徒\n    刑5 月，並諭知如易科罰金，以新臺幣1 千元折算1 日。經\n    核原審此部分判決認事用法並無不合，量刑亦屬適度。被告\n    上訴意旨，仍執前詞，指摘原審此部分判決不當，為無理由\n    ，應予駁回。\n柒、被告甲○○部分\n一、訊據上訴人即被告甲○○對於附表七（一）編號1-4 、6 、\n    7-10、附表七（二）及附表七（三）所示之交易毒品行為，\n    均坦承不諱，惟矢口否認有販賣第一級毒品之犯行，辯稱：\n    伊並無販賣毒品之營利犯意云云。惟查上開事實，業據證人\n    己○○、申○○、寅○○、癸○○、乙○○、庚○○、丙○\n    ○、丁○○於警詢或本院審理中之證述甚詳，並有通訊監察\n    譯文表（警卷，頁176 、222 ）附卷可稽。\n二、被告甲○○雖辯稱：附表七（一）編號5 之時地，伊係與癸\n    ○○、申○○合資後，由伊向許晉曄購買毒品後，與癸○○\n    、申○○分食云云。惟被告甲○○於警詢中（97年3 月5 日\n    第5 次調查筆錄，警卷，頁697 ）自承：96年9 月底至10月\n    初某日晚上約19至20時許，在西嶼鄉外垵村「慈航寺」前路\n    口處，係由癸○○撥打伊持用之000000000 號手機，欲向伊\n    調買海洛因，伊要癸○○於該處等候，伊並打給許晉曄聯絡\n    ，嗣伊到外垵村「藍語」網咖前路口，拿取以夾鏈袋裝妥數\n    量約1000元之海洛因後，前往「慈航寺」前路口處交給癸○\n    ○並收取現金1000元，且申○○也在場等語，核與證人申○\n    ○、癸○○於警詢或原審審理中均供稱：係向被告甲○○購\n    買毒品等語相符，足認被告甲○○有附表七（一）編號5 之\n    犯行。被告甲○○辯稱：未販賣毒品，係合資向許晉曄購買\n    云云，尚非可採。又被告甲○○另辯稱：附表七（一）編號\n    11之時地，係由丁○○與癸○○交易毒品，伊僅在場，伊未\n    販賣毒品云云。惟證人癸○○已於警詢（97年1 月25日第3\n    次調查筆錄，警卷，頁16 7）供稱：「（問：警方提示96年\n    11月6 日20時35分你與申○○通話譯文內容：「A ：我們剛\n    上去、我們5 個人拿3 支。B ：阿他那東西跟下午拿的差很\n    多、阿「維昌」呢？A ：「維昌」吹去阿」意喻為何？）我\n    在向申○○談跟甲○○買毒品的情形。因為96年11月06日下\n    午我跟高文琳2 人一同去外垵村慈航寺向甲○○購買2000元\n    毒品海洛因施用後，覺得甲○○賣的毒品數量跟品質很不錯\n    ，所以晚上我又跟翁維昌、高文琳、乙○○、庚○○5 人合\n    資由我開車載他們（翁維昌沒上去只是將1500元寄放我這由\n    我幫翁買下來）再上去跟甲○○購買3000元毒品海洛因，\n    ... 。」，又於原審審理中（原審98年4 月1 日審判筆錄）\n    供稱：「這次有跟甲○○買海洛因」、「（問：（提示警券\n    176 頁譯文）這段譯文什麼意思？）我想起來了，我是跟甲\n    ○○聯絡，甲○○跟我見面說東西是丁○○的，他說他沒有\n    東西。」等語，且有96年11月6 日20時35分電話監聽譯文（\n    警卷，頁176 ）附卷可稽，足認被告甲○○有附表七（一）\n    編號11之犯行。被告甲○○辯稱：未販賣毒品，係丁○○賣\n    的云云，亦非可採。\n三、被告甲○○另於警詢中自承：伊持所有之0000000000號手機\n    與己○○、癸○○等人約定交易時間、地點等後，再完成交\n    易；參諸有償提供他人毒品可能罹犯毒品危害防制條例相關\n    重罪，上開被告甲○○11次交付海洛因並均收取價金之行為\n    ，應係有利可圖，否則豈有鋌而走險甘冒罹犯重罪風險之理\n    等情，足見被告甲○○係基於營利意圖，以上開手機聯絡毒\n    品交易事宜，而有附表七（一）所示之11次販賣海洛因行為\n    ，足堪認定。被告辯稱：伊無販賣毒品之營利犯意云云，顯\n    係卸責之詞，不足採信。證人即同案被告癸○○於本院審理\n    時雖證述：96年11、12月間，曾拜託甲○○調毒品，幾次已\n    忘記了。調毒品之金額大約都在1 、2 千元。請甲○○調毒\n    品，並沒有給酬勞，因為朋友之間平常就有在請客等語（見\n    本院卷二第11、12頁）。然與證人癸○○於警詢及原審審理\n    證述其係向甲○○購買毒品之情節不符，顯係事後迴護之詞\n    ，自難採為有利於被告甲○○之認定。\n四、綜上所述，本件事 證明確，被告甲○○確有附表七（一）\n    、（二）、（三）之犯行，均堪認定。\n五、核被告甲○○就附表七（一）所為，均係犯毒品危害防制條\n    例第4 條第1 項販賣第一級毒品罪；其附表七（二）之所為\n    ，係犯毒品危害防制條例第8 條第1 項轉讓第一級毒品罪；\n    其附表七（三）所為，均係犯刑法第30條第1 項、毒品危害\n    防制條例第10條第1 項幫助施用第一級毒品罪。又被告甲○\n    ○就附表七（二）、（三）所示犯行，或係與他人互換毒品\n    ，難認有何圖利之販賣情事，或係代為合資購買毒品後，再\n    與丙○○分食，並非轉讓、販賣毒品，核其此部分所為，係\n    犯轉讓、幫助施用第一級毒品罪，公訴人認被告甲○○此部\n    分係犯販賣、轉讓第一級毒品罪，均有未洽，惟基本社會事\n    實同一，爰變更起訴法條。公訴人雖認被告甲○○與案外人\n    許晉曄就附表七（一）編號1 至6 之犯行，係屬共同正犯。\n    惟查證人己○○於附表七（一）編號1 至4 、6 之時間，係\n    直接以手機與被告甲○○為交易毒品之聯絡，此有電話監聽\n    譯文附卷可稽，又附表七（一）編號5 之犯行，亦係由證人\n    癸○○直接與被告甲○○洽談後交易，有如上述（證人癸○\n    ○、申○○於另案澎湖地檢署97年度偵字第904 號偵查中亦\n    同此證述），雖被告甲○○供稱：該6 次犯行伊都是替許晉\n    曄販賣云云，惟販賣毒品者或有為弱化自己販賣毒品重責而\n    推諉主要責任予毒品提供者之動機，亦即被告甲○○之供述\n    充其量僅能認為其供出毒品來源為案外人許晉曄，尚不能遽\n    以認定案外人許晉曄為屬共犯，又證人己○○於警詢或原審\n    審理中固供稱：有時係由許晉曄親自交付毒品給伊云云，惟\n    參諸被告甲○○另於原審審理中供稱：許晉曄與己○○有金\n    錢糾紛，己○○不便與許晉曄聯繫，才透過伊聯絡許晉曄買\n    賣毒品等語，衡情案外人許晉曄即無可能再與己○○有所接\n    觸，遑論直接交付毒品與己○○，是證人己○○此部分之供\n    述，非無可疑，不能遽採。本件被告甲○○就附表七（一）\n    編號1 至6 之犯行，既查無其他證據足資認定案外人許晉曄\n    有共同參與之情事，公訴人遽認許晉曄係屬共同正犯，自有\n    未洽。被告甲○○就上開犯行，犯意各別，行為互殊，應分\n    論併罰。被告甲○○曾因違反毒品危害防制條例案件，分別\n    經臺灣高雄地方法院判處有期徒刑8 月、1 年確定，於93年\n    12月1 日接續執行縮刑期滿執行完畢，其於5 年內故意再犯\n    本件有期徒刑以上之罪，為累犯，應加重其刑（死刑、無期\n    徒刑部分不得加重）。附表七（三）之犯行，依刑法第30條\n    第2 項減輕其刑，並先加後減之。被告甲○○無販毒之前科\n    紀錄，而所犯販賣第一級毒品犯行之法定刑為「死刑或無期\n    徒刑；處無期徒刑者，得併科新臺幣1 千萬元以下罰金」，\n    本件其販賣之海洛因，數量非鉅，所得非多，與專門販售毒\n    品之大盤尚難相提並論，犯罪情狀在客觀上可引起一般人之\n    同情，倘科以上開罪名之法定最輕本刑，猶嫌過重，爰就其\n    販賣第一級毒品罪部分，依刑法第59條規定，酌減其刑，並\n    先加後減之。\n六、原審因而適用毒品危害防制條例第4 條第1 項、第8 條第1\n    項、第10條第1 項、第19條第1 項，刑法第30條、第47條第\n    1 項、第59條、第51條第5 款規定，並審酌被告甲○○犯後\n    坦承部分犯行，態度尚佳等一切情狀，就其販賣第一級毒品\n    11罪部分，各處有期徒刑15年2 月；轉讓第一級毒品部分，\n    量處有期徒刑1 年6 月；幫助施用第一級毒品5 罪部分，各\n    處有期徒刑10月，並定其應執行刑有期徒刑16年6 月。並認\n    未扣案之0000000000號行動電話1 支，係其所有供犯罪所用\n    之物，應依毒品危害防制條例第19條第1 項之規定沒收，如\n    全部或一部不能沒收時，均追徵其價額或以其財產抵償之。\n    被告甲○○如附表七（一）所示販毒所得，均應依毒品危害\n    防制條例第19條第1 項之規定沒收，如全部或一部不能沒收\n    時，均以其財產抵償之。扣案之甲○○所有之夾鏈袋4 個及\n    綠色谷關青藥膏1 個，均無證據顯示係屬其供犯罪所用之物\n    ，爰不宣告沒收。經核原審此部分判決認事用法並無不合，\n    量刑亦屬適度，被告上訴意旨，或否認犯罪，或指摘原審此\n    部分判決量刑過重不當，為無理由，應予駁回。\n捌、被告乙○○部分\n一、上訴人即被告乙○○未於本院最後審理期日到場，惟訊據被\n    告乙○○對於附表八（一）、（四）幫助施用、轉讓海洛因\n    之犯行，均坦承不諱，惟矢口否認有附表八（二）、（三）\n    之販賣毒品行為，辯稱：伊未參與毒品交易云云。\n二、經查：被告乙○○對於附表八（一）、（四）幫助施用、轉\n    讓海洛因犯行之自白，核與證人寅○○、癸○○、申○○、\n    庚○○、翁丁元於原審審理中之證述相符，堪認屬實。又被\n    告乙○○與癸○○係先至高雄購買海洛因，且約定由乙○○\n    出錢，癸○○負責賣海洛因將錢還乙○○，乙○○再從中獲\n    取免費半錢一半之海洛因，嗣由另案被告金文隆攜回毒品，\n    被告乙○○、癸○○再共同為附表八（二）編號1 、2 、3\n    之犯行，此據被告乙○○及證人癸○○於警詢中（97年3 月\n    5 日對質筆錄，警卷，頁230 、313 ）供述屬實，證人癸○\n    ○供稱：「（問：96年9 月某日至96年10月13日在澎湖百合\n    民宿販賣給丁○○、午○○2 人3 次毒品海洛因之分工情形\n    如何？）不是96年9 月是96年10月某日才開始販賣。96年10\n    月某日我會跟乙○○去高雄要向辰○○購買毒品是要自己施\n    用，後來在高雄賣我們毒品的人變成綽號「金剛」男子，我\n    與乙○○才有了買毒品回澎湖販賣的共識（乙○○出錢、我\n    負責賣毒品將錢還乙○○、乙○○從中獲取免費半錢一半毒\n    品海洛因），綽號「金剛」男子才叫金文隆幫我們把毒品帶\n    回澎湖，與乙○○共同前往百合民宿由我將毒品海洛因販賣\n    給丁○○跟午○○、再將賣毒品的錢拿給乙○○。」，被告\n    乙○○則稱：「（問：96年9 月某日至96年10月13日在澎湖\n    百合民宿販賣給丁○○、午○○2 人3 次毒品海洛因之分工\n    情形如何？）與莊和和所說相同。」等語，復與證人癸○○\n    、午○○、丁○○於原審審理中之證述相符，且有96年10月\n    12日15時07分、96年10月13日22時08分監聽譯文（警卷173\n    ）附卷可稽，被告乙○○辯稱：案發時伊僅出現在現場，沒\n    有共同販賣毒品之犯意云云，不足採信。另關於附表八（三\n    ）編號1部 分，查被告乙○○及證人酉○○於警詢中供稱（\n    97年3 月10日對質筆錄，警卷，頁1021、97年3 月6 日對質\n    筆錄，警卷，頁318 、97年3 月19日對質筆錄，警卷，頁\n    1122）：「問：丙（即酉○○）於警訊第3 次筆錄中與乙○\n    ○、甲（即辰○○）同車交易6000元安非他命交易情形為何\n    ？）丙即酉○○：我確定是乙○○打電話問我要不要買毒品\n    ，後來是甲在車上將毒品交給我，隔天在光復路229 號乙○\n    ○住處將這6000元拿給乙○○本人。」、「問：你是否於96\n    年8 至9 月某日下午17時許以電話詢問酉○○是否要買毒品\n    ，並在燦坤3C量販店賣場後方公園由辰○○販售1 包價值60\n    00元半錢重的毒品安非他命給酉○○？）乙○○：有這件事\n    。時間是我忘了。」、「問：96年10月26日乙（即辰○○）\n    、丙（即乙○○）是否在燦坤3C量販店後方公園附近販售安\n    非他命半錢給酉○○，價值6000元？後來酉○○是否在光復\n    路229 號4 樓將這6000元交給丙？）丙即乙○○：有這件事\n    ，毒品是辰○○交給酉○○，‧‧‧。」等語，2 人已詳就\n    乙○○打電話與酉○○接洽毒品交易事宜，並由辰○○交付\n    毒品等情，互為一致之供述，被告乙○○、證人酉○○嗣於\n    原審審理中翻異前供，自屬卸責、迴護之詞，不能遽採。另\n    關於附表八（三）編號2 之行為，業據被告乙○○於警詢中\n    （97年3 月6 日對質筆錄，警卷，頁429 ）供承：「問：96\n    年11月6 日何人在西衛里海邊車上賣4000元毒品安非他命給\n    丁○○？）乙○○：有這件事，但是是2000元。」等語，核\n    與證人申○○、丁○○於本院審理中之證述相符，且有96年\n    11月6 日16時54分監聽譯文（警卷，頁386 ）附卷可稽；再\n    者關於附表八（三）編號3 之行為，亦據被告乙○○於警詢\n    及原審審理中自承：有叫申○○來拿取安非他命等語，核與\n    證人申○○等於原審審理中之證述相符，被告乙○○所辯未\n    販賣毒品云云，不足採信。\n三、綜上，被告乙○○確有附表八（一）、（二）、（三）、（\n    四）所示之販賣、轉讓、幫助施用海洛因或安非他命之事實\n    ，事證明確，其犯行堪以認定。\n四、核被告乙○○就附表八（一）所為，係犯刑法第30條第1 項\n    、毒品危害防制條例第10條第1 項幫助施用第一級毒品罪；\n    其附表八（二）所為，均係犯毒品危害防制條例第4 條第1\n    項販賣第一級毒品罪；其附表八（三）之所為，均係犯毒品\n    危害防制條例第4 條第2 項販賣第二級毒品罪；其附表八（\n    四）之所為，則均係犯毒品危害防制條例第8 條第1 項轉讓\n    第一級毒品罪。又被告乙○○就附表八（一）所示犯行，係\n    代為合資購買海洛因後，再與寅○○分食，核其此部分所為\n    ，係犯幫助施用第一級毒品罪，公訴人認其此部分係犯販賣\n    第一級毒品罪，尚有未洽，惟基本社會事實同一，爰變更起\n    訴法條。其就附表八（二）、附表八（三）編號1 、3 之犯\n    行，分別與癸○○、辰○○、申○○等人有犯意之聯絡及行\n    為之分擔，均屬共同正犯。其就上開犯行，犯意各別，行為\n    互殊，應分論併罰。附表八（一）之犯行，依刑法第30條第\n    2 項減輕其刑。被告乙○○無販毒之前科紀錄，而所犯販賣\n    第一、二級毒品犯行之法定刑分別為「死刑或無期徒刑；處\n    無期徒刑者，得併科新臺幣1 千萬元以下罰金」、「無期徒\n    刑或7 年以上有期徒刑，得併科新臺幣7 百萬元以下罰金」\n    ，本件其販賣之海洛因、安非他命，數量非鉅，所得非多，\n    與專門販售毒品之大盤尚難相提並論，犯罪情狀在客觀上可\n    引起一般人之同情，倘科以上開罪名之法定最輕本刑，猶嫌\n    過重，爰就其販賣第一、二級毒品罪部分，均依刑法第59條\n    規定，酌減其刑。\n五、原審因而適用毒品危害防制條例第4 條第1 項、第2 項、第\n    10條第1 項、第8 條第1 項、第19條第1 項、刑法第28條、\n    第30條第2 項、第59條、第51條第5 款規定，並審酌被告乙\n    ○○犯後否認犯行，態度非佳等一切情狀，就其幫助施用第\n    一級毒品部分，量處有期徒刑8 月；共同販賣第一級毒品3\n    罪部分，各處有期徒刑15年2 月；販賣第二級毒品3 罪部分\n    ，各處有期徒刑3 年8 月；轉讓第一級毒品7 罪部分，各處\n    有期徒刑1 年6 月，並定其應執行刑有期徒刑18年。並認未\n    扣案之0000000000號、0000000000號、0000000000號行動電\n    話各1 支，分屬被告乙○○、共犯申○○、癸○○所有供犯\n    罪所用之物，應依毒品危害防制條例第19條第1 項之規定沒\n    收，如全部或一部不能沒收時，均追徵其價額或以其財產抵\n    償之。被告乙○○如附表八（二）、（三）所示販毒所得，\n    應依毒品危害防制條例第19條第1 項之規定沒收（共犯部分\n    應與辰○○或癸○○連帶沒收），如全部或一部不能沒收時\n    ，均以其財產抵償之。經原審此部分判決認事用法並無不合\n    ，量刑亦屬適度，被告上訴意旨，仍執前詞，或否認犯罪，\n    或指摘原審此部分判決量刑，過重不當，難認有理由，應予\n    駁回。\n六、被告乙○○經合法傳喚，無正當理由不到庭，爰不待其陳述\n    逕行判決。\n玖、被告癸○○部分\n一、附表九之事實，業據上訴人即被告癸○○分別於偵查中、原\n    審及本院審理中坦承不諱，核與證人丁○○、午○○、乙○\n    ○、辰○○、申○○、甲○○、庚○○、翁維昌、未○○、\n    翁丁元、己○○於警詢或原審審理中證述之情節相符，事證\n    明確，被告癸○○確有附表九（一）、（二）、（三）、（\n    四）、（五）所示之販賣、轉讓、幫助施用海洛因或安非他\n    命之犯行，均堪認定。證人午○○於本院審理中雖證述：我\n    只是請癸○○調毒品，因為大家是朋友，我是請癸○○幫我\n    買毒品等語（見本院卷二第8 頁），然與被告癸○○於本院\n    審理時自白販賣之情節不符，自難採信，併此明。\n二、核被告癸○○附表九（一）所為，均係犯毒品危害防制條例\n    第4 條第1 項販賣第一級毒品罪；其附表九（二）所為，均\n    係犯毒品危害防制條例第8 條第1 項轉讓第一級毒品罪；其\n    附表九（三）所為，係犯藥事法第83條第1 項轉讓禁藥罪；\n    其附表九（四）所為，均係犯刑法第30條第1 項、毒品危害\n    防制條例第10條第1 項幫助施用第一級毒品罪；其附表九（\n    五）所為，係犯刑法第30條第1 項、毒品危害防制條例第10\n    條第2 項幫助施用第二級毒品罪。按安非他命為毒品危害防\n    制條例第2 條第2 項第2 款所明定之第二級毒品；且經行政\n    院衛生署於75年7 月11日以衛署藥字第59762 7 號公告，為\n    有效管理安非他命類藥品與其衍生物之冊類及其製劑，重申\n    公告禁止使用，而均屬藥事法第22條第1 款所規定之禁藥。\n    故行為人明知為禁藥即「安非他命」而轉讓與他人者，除成\n    立毒品危害防制條例第8 條第2 項之「轉讓第二級毒品罪」\n    外，亦構成藥事法第83條第1 項之「轉讓禁藥罪」，此係屬\n    同一犯罪行為而同時有二種法律可資處罰之「法規競合」情\n    形，應依「重法優於輕法」、「後法優於前法」等法理，擇\n    一處斷。而毒品危害防制條例第8 條第2 項轉讓第二級毒品\n    罪之法定本刑為「6 月以上5 年以下有期徒刑，得併科新台\n    幣70萬元以下罰金」。93年4 月21日修正後藥事法第83條第\n    1 項轉讓禁藥罪之法定本刑為「7 年以下有期徒刑，得併科\n    新台幣5 百萬元以下罰金」。故除轉讓之第二級毒品達毒品\n    危害防制條例第8 條第6 項之一定數量，經依法加重其刑，\n    致該法定刑較藥事法第83條第1 項之法定刑為重之情形外，\n    因藥事法第83條第1 項為後法，且為重法，應優先適用藥事\n    法處罰（最高法院96年度台上字第3582號判決意旨參照），\n    而本件被告癸○○轉讓安非他命之數量未達毒品危害防制條\n    例第8 條第6 項所定之數量，是故核其就附表九（三）所為\n    ，係犯藥事法第83條第1 項轉讓禁藥罪。公訴人認其此部分\n    係犯販賣第二級毒品罪，尚有未洽；又被告癸○○就附表九\n    （四）及附表九（五）所示犯行，均係代他人購買毒品後，\n    再與他人分食，核其此部分所為，係分別犯幫助施用第一、\n    二級毒品罪，公訴人認其此部分係犯販賣或轉讓海洛因、安\n    非他命罪，亦有未洽，惟基本社會事實同一，爰均變更起訴\n    法條。另被告癸○○於96年10月28日與辰○○共同自高雄攜\n    帶海洛因1/4 錢至澎湖之行為（即起訴書附表一編號23部分\n    ），因該次攜帶之毒品係供附表九（一）編號4 之販毒所用\n    ，該運輸行為屬販賣之部分行為，不另論罪，公訴人認被告\n    癸○○該部分攜帶毒品行為另構成運輸第一級毒品罪，亦有\n    未洽。其就附表九（一）、附表九（二）編號1 之犯行，分\n    別與乙○○、辰○○、申○○有犯意之聯絡及行為之分擔，\n    均屬共同正犯。其就上開犯行，犯意各別，行為互殊，應分\n    論併罰。被告癸○○曾因違反毒品危害防制條例案件，經法\n    院定應執行刑判處有期徒刑1 年6 月，嗣減為有期徒刑9 月\n    確定，於96年7 月16日執行完畢，其於5 年內故意再犯本件\n    有期徒刑以上之罪，為累犯，應加重其刑（死刑、無期徒刑\n    部分不得加重）。附表九（四）、（五）之犯行，均依刑法\n    第30條第2 項減輕其刑，並先加後減之。被告癸○○無販毒\n    之前科紀錄，而所犯販賣第一級毒品犯行之法定刑為「死刑\n    或無期徒刑；處無期徒刑者，得併科新臺幣1 千萬元以下罰\n    金」，本件其販賣之海洛因，數量非鉅，所得非多，與專門\n    販售毒品之大盤尚難相提並論，犯罪情狀在客觀上可引起一\n    般人之同情，倘科以上開罪名之法定最輕本刑，猶嫌過重，\n    爰就其販賣第一級毒品罪部分，均依刑法第59條規定，酌減\n    其刑。又被告癸○○於警詢時供出其所販賣海洛因之來源，\n    使警方因而查獲販毒之乙○○、辰○○及另案之金正剛，有\n    其97年1 月8 日警詢筆錄（警卷第112 頁），及原審97年度\n    訴字第33號（認定金正剛販賣海洛因予癸○○）在卷可稽。\n    應依毒品危害防制條例第17條第1 項規定，減輕其刑。又癸\n    ○○於偵查中及審判中均自白販賣第一級毒品，亦依同條例\n    第17條第2 項規定，遞減其刑。\n三、原審就癸○○轉讓第一級毒品、轉讓禁藥、幫助施用第一、\n    二級毒品部分，因而適用毒品危害防制條例第8 條第1 項、\n    第10條第1 項、第2 項、藥事法第83條第1 項、刑法第28條\n    、第30條第2 項、第51條第5 款之規定，並審酌被告犯後坦\n    承犯行，態度良好等一切情狀，就其共同轉讓第一級毒品部\n    分，量處有期徒刑1 年6 月；轉讓第一級毒品2 罪部分，各\n    處有期徒刑1 年6 月；幫助施用第一級毒品3 罪部分，各處\n    有期徒刑8 月；幫助施用第二級毒品部分，量處有期徒刑4\n    月。經核原審此部分判決認事用法並無不合，量刑亦屬適度\n    。癸○○上訴意旨，指摘原審此部分判決量刑過重不當，為\n    無理由，應予駁回。\n四、原審就癸○○販賣第一級毒品部分予以論科，固非無見，惟\n    查癸○○於警詢中，供出其販賣海洛因之來，使警方因而查\n    獲販毒之乙○○、辰○○及另案之金正剛，自應依毒品危害\n    防制條例第17條第1 項規定，減輕其刑，原審漏未審酌，自\n    有未當。癸○○上訴意旨，指摘原審此部分判決不當，為有\n    理由，自應由本院將原審此部分判決及其定執行刑部分予以\n    撤銷改判。審酌被告於偵查中及審判中自白犯行，並於警詢\n    中供出其所販賣毒品海洛因之來源，使警方因而查獲販毒之\n    乙○○、辰○○及另案金正剛等人，態度甚佳等一切情狀，\n    就其所犯販賣第一級毒品10罪，各處有期徒刑11年2 月，並\n    與其上訴駁回所處共同轉讓第一級毒品，累犯，處有期徒刑\n    1 年6 月；又轉讓第一級毒品，累犯，共計2 罪，各處有期\n    徒刑1 年6 月；又轉讓禁藥，累犯，處有期徒刑1 年；又幫\n    助施用第一級毒品，累犯，共計3 罪，各處有期徒刑8 月；\n    又幫助施用第二級毒品，累犯，處有期徒刑4 月。應執行有\n    期徒刑13年，行動電話、販毒所得之沒收、追徵價額、抵償\n    均如附表九（一）應沒收之物（1 ）、（2 ）所示。\n據上論斷，應依刑事訴訟法第368 條、第369 條第1 項前段、第\n299 條第1 項前段、第371 條、毒品危害防制條例第4條 第1 項\n、第2 項、第17條第1 項、第2 項、第18條第1 項前段、第19條\n第1 項、刑法第28條、第47條第1 項、第59條、第51條第5 款，\n判決如主文。\n本案經檢察官蔡國禎到庭執行職務。\n中    華    民    國     99     年     1     月   4   日\n                  刑事第九庭    審判長法  官  莊秋桃\n                                      法  官  范惠瑩\n                                      法  官  謝宏宗\n                                                                 4\n以上正本證明與原本無異。\n除幫助施用第二級毒品外，其他各罪均如不服本判決應於收受本\n判決後10日內向本院提出上訴書狀，其未述上訴理由者，並得\n於提起上訴後10日內向本院補提理由書狀（均須按他造當事人之\n人數附繕本) 「切勿逕送上級法院」。\n中    華    民    國     99     年     1     月   7   日\n                                      書記官   蘇恒仁\n附錄本判決論罪科刑法條：\n毒品危害防制條例第4條第1項、第2項\n製造、運輸、販賣第一級毒品者，處死刑或無期徒刑；處無期徒\n刑者，得併科新臺幣 2 千萬元以下罰金。\n製造、運輸、販賣第二級毒品者，處無期徒刑或 7 年以上有期\n徒刑，得併科新臺幣 1 千萬元以下罰金。\n毒品危害防制條例第8條第1項\n轉讓第一級毒品者，處 1 年以上 7 年以下有期徒刑，得併科新\n臺幣 1 百萬元以下罰金。\n毒品危害防制條例第10條第1項、第2項\n施用第一級毒品者，處 6 月以上 5 年以下有期徒刑。\n施用第二級毒品者，處 3 年以下有期徒刑。\n藥事法第83條第1項\n明知為偽藥或禁藥，而販賣、供應、調劑、運送、寄藏、牙保、\n轉讓或意圖販賣而陳列者，處 7 年以下有期徒刑，得併科新臺\n幣 5 百萬元以下罰金。\n附件：\n附表一\n（一）\n┌──────────────────────────────┐\n│被告寅○○幫助施用海洛因一覽表                              │\n├─┬────┬──────┬────────────────┤\n│編│犯罪時間│犯罪地點    │犯罪手法、對象、毒品種類、數量及│\n│號│        │            │金額（單位：新台幣元）          │\n├─┼────┼──────┼────────────────┤\n│1 │96年10月│澎湖縣馬公市│寅○○自己出資並向子○○收取1000│\n│  │28日    │大愛平價牛排│元，集資後再由寅○○出面購買海洛│\n│  │        │店內        │因2小包後，2人分食之。          │\n└─┴────┴──────┴────────────────┘\n（二）\n┌──────────────────────────────┐\n│被告寅○○販賣海洛因一覽表                                  │\n├─┬──┬──┬───────┬──────┬───────┤\n│編│犯罪│犯罪│犯罪手法、對象│應沒收之物(1)│應沒收之物(2)  │\n│號│時間│地點│、毒品種類、數│            │（單位：新台幣│\n│  │    │    │量及金額（單位│            │ 元）         │\n│  │    │    │：新台幣元）  │            │              │\n├─┼──┼──┼───────┼──────┼───────┤\n│1 │96年│澎湖│以0000000000號│扣案之門號  │販賣第一級毒品│\n│  │11月│縣馬│行動電話聯絡交│0000000000號│所得1000元沒收│\n│  │4日 │公市│易事宜，販賣海│行動電話1支 │，如全部或一部│\n│  │    │光復│洛因1小包予莊 │沒收。      │不能沒收時，以│\n│  │    │路「│正和，得款1000│            │其財產抵償之。│\n│  │    │都家│元。          │            │              │\n│  │    │堡」│              │            │              │\n│  │    │商店│              │            │              │\n│  │    │對面│              │            │              │\n├─┼──┼──┼───────┼──────┼───────┤\n│2 │96年│澎湖│以0000000000號│扣案之門號  │販賣第一級毒品│\n│  │11月│縣馬│行動電話聯絡交│0000000000號│所得1000元沒收│\n│  │4日 │公市│易事宜，販賣海│行動電話1支 │，如全部或一部│\n│  │    │馬公│洛因1小包予莊 │沒收。      │不能沒收時，以│\n│  │    │國小│正和，得款1000│            │其財產抵償之。│\n│  │    │旁之│元。          │            │              │\n│  │    │統一│              │            │              │\n│  │    │超商│              │            │              │\n│  │    │門口│              │            │              │\n├─┼──┼──┼───────┼──────┼───────┤\n│3 │96年│澎湖│以0000000000號│扣案之門號  │販賣第一級毒品│\n│  │11月│縣馬│行動電話聯絡交│0000000000號│所得2000元沒收│\n│  │16日│公市│易事宜，販賣海│行動電話1支 │，如全部或一部│\n│  │    │安一│洛因1小包予張 │沒收。      │不能沒收時，以│\n│  │    │山莊│梧樹，得款2000│            │其財產抵償之。│\n│  │    │前  │元。          │            │              │\n└─┴──┴──┴───────┴──────┴───────┘\n附表二\n（一）\n┌──────────────────────────────┐\n│被告子○○幫助施用海洛因一覽表                              │\n├─┬────┬───────┬───────────────┤\n│編│犯罪時間│犯罪地點      │犯罪手法、對象、毒品種類、數量│\n│號│        │              │及金額（單位：新台幣元）      │\n├─┼────┼───────┼───────────────┤\n│1 │96年11月│澎湖縣馬公巿某│子○○自己出資500元並向未○○ │\n│  │15日14時│地（起訴書誤載│收取1500元，集資後再由子○○出│\n│  │35分    │為大勇街30號農│面購買海洛因1包後，將3/4海洛因│\n│  │        │會生鮮超巿）  │交予未○○，嗣由未○○施用之。│\n└─┴────┴───────┴───────────────┘\n（二）\n┌──────────────────────────────┐\n│被告子○○販賣海洛因一覽表                                  │\n├─┬──┬──┬───────┬──────┬───────┤\n│編│犯罪│犯罪│犯罪手法、對象│應沒收之物(1)│應沒收之物(2)  │\n│號│時間│地點│、毒品種類、數│            │（單位：新台幣│\n│  │    │    │量及金額（單位│            │ 元）         │\n│  │    │    │：新台幣元）  │            │              │\n├─┼──┼──┼───────┼──────┼───────┤\n│1 │96年│澎湖│以0000000000號│扣案之門號  │販賣第一級毒品│\n│  │11月│縣馬│行動電話聯絡交│0000000000號│所得2000元沒收│\n│  │16日│公市│易事宜，販賣海│行動電話1支 │，如全部或一部│\n│  │14時│馬公│洛因1小包予陳 │沒收。      │不能沒收時，以│\n│  │    │國小│永豊，得款2000│            │其財產抵償之。│\n│  │    │旁之│元。          │            │              │\n│  │    │統一│              │            │              │\n│  │    │超商│              │            │              │\n│  │    │內  │              │            │              │\n├─┼──┼──┼───────┼──────┼───────┤\n│2 │96年│澎湖│以0000000000號│扣案之門號  │              │\n│  │11月│縣馬│行動電話聯絡交│0000000000號│              │\n│  │16日│公市│易事宜，販賣海│行動電話1支 │              │\n│  │16時│忠孝│洛因1小包予陳 │沒收。      │              │\n│  │35分│路66│永豊，未遂。  │            │              │\n│  │    │西餐│              │            │              │\n│  │    │廳附│              │            │              │\n│  │    │近  │              │            │              │\n└─┴──┴──┴───────┴──────┴───────┘\n附表三\n（一）\n┌──────────────────────────────┐\n│被告申○○販賣海洛因一覽表                                  │\n├─┬──┬──┬───────┬──────┬───────┤\n│編│犯罪│犯罪│犯罪手法、對象│應沒收之物(1)│應沒收之物(2)  │\n│號│時間│地點│、毒品種類、數│            │（單位：新台幣│\n│  │    │    │量及金額（單位│            │元）          │\n│  │    │    │：新台幣元）  │            │              │\n├─┼──┼──┼───────┼──────┼───────┤\n│1 │96年│澎湖│辰○○、癸○○│未扣案之門號│販賣第一級毒品│\n│  │10月│縣馬│、申○○基於犯│0000000000號│所得5000元與陳│\n│  │26日│公市│意之聯絡，由莊│行動電話1支 │建榮、癸○○連│\n│  │    │新生│正和以其所有之│沒收，如全部│帶沒收，如全部│\n│  │    │路「│0000000000號行│或一部不能沒│或一部不能沒收│\n│  │    │沁樂│動電話聯絡交易│收時，追徵其│時，以其財產抵│\n│  │    │園」│事宜，再由蔡俊│價額或以其財│償之。        │\n│  │    │前  │明交付海洛因，│產抵償之。  │              │\n│  │    │    │販賣海洛因1包 │            │              │\n│  │    │    │予甲○○，得款│            │              │\n│  │    │    │5000元，嗣收取│            │              │\n│  │    │    │之款項5000元歸│            │              │\n│  │    │    │辰○○所有。  │            │              │\n├─┼──┼──┼───────┼──────┼───────┤\n│2 │96年│澎湖│辰○○、癸○○│未扣案之門號│販賣第一級毒品│\n│  │10月│縣馬│、申○○基於犯│0000000000號│所得4000元與陳│\n│  │26日│公市│意之聯絡，由莊│行動電話1支 │建榮、癸○○連│\n│  │至同│澎湖│正和以其所有之│沒收，如全部│帶沒收，如全部│\n│  │月28│科技│0000000000號行│或一部不能沒│或一部不能沒收│\n│  │日間│大學│動電話聯絡交易│收時，追徵其│時，以其財產抵│\n│  │某日│前  │事宜，再由蔡俊│價額或以其財│償之          │\n│  │    │    │明交付海洛因，│產抵償之。  │              │\n│  │    │    │販賣海洛因1包 │            │              │\n│  │    │    │予甲○○，價值│            │              │\n│  │    │    │5000元，嗣收取│            │              │\n│  │    │    │之款項4000 元 │            │              │\n│  │    │    │（尚欠1000元）│            │              │\n│  │    │    │歸辰○○所有。│            │              │\n├─┼──┼──┼───────┼──────┼───────┤\n│3 │96年│澎湖│辰○○、癸○○│未扣案之門號│販賣第一級毒品│\n│  │10月│縣馬│、申○○基於犯│0000000000號│所得3000元與陳│\n│  │底某│公市│意之聯絡，由蔡│行動電話1支 │建榮、癸○○連│\n│  │日  │南海│俊明以其所有  │沒收，如全部│帶沒收，如全部│\n│  │    │碼頭│0000000000號行│或一部不能沒│或一部不能沒收│\n│  │    │候船│動電話與欲購買│收時，追徵其│時，以其財產抵│\n│  │    │室後│毒品之丑○○聯│價額或以其財│償之。        │\n│  │    │方  │絡後，申○○復│產抵償之。  │              │\n│  │    │    │聯絡辰○○以取│            │              │\n│  │    │    │得海洛因，再由│            │              │\n│  │    │    │癸○○交付海洛│            │              │\n│  │    │    │因，販賣海洛因│            │              │\n│  │    │    │1包予丑○○， │            │              │\n│  │    │    │得款3000元，嗣│            │              │\n│  │    │    │收取之款項3000│            │              │\n│  │    │    │元歸辰○○所有│            │              │\n│  │    │    │。            │            │              │\n├─┼──┼──┼───────┼──────┼───────┤\n│4 │96年│澎湖│辰○○、癸○○│未扣案之門號│              │\n│  │10月│縣馬│、申○○基於犯│0000000000號│              │\n│  │底某│公市│意之聯絡，由莊│行動電話1支 │              │\n│  │日  │林森│正和以其所有之│沒收，如全部│              │\n│  │    │路李│0000000000號行│或一部不能沒│              │\n│  │    │子林│動電話聯絡交易│收時，追徵其│              │\n│  │    │婦產│事宜，再由蔡俊│價額或以其財│              │\n│  │    │科前│明交付海洛因，│產抵償之。  │              │\n│  │    │    │販賣海洛因1包 │            │              │\n│  │    │    │予午○○，價值│            │              │\n│  │    │    │5000元，但尚未│            │              │\n│  │    │    │收取款項。    │            │              │\n└─┴──┴──┴───────┴──────┴───────┘\n（二）\n┌──────────────────────────────┐\n│被告申○○販賣安非他命一覽表                                │\n├─┬──┬──┬───────┬──────┬───────┤\n│編│犯罪│犯罪│犯罪手法、對象│應沒收之物(1)│應沒收之物(2)  │\n│號│時間│地點│、毒品種類、數│            │（單位：新台幣│\n│  │    │    │量及金額（單位│            │元）          │\n│  │    │    │：新台幣元）  │            │              │\n├─┼──┼──┼───────┼──────┼───────┤\n│1 │96年│澎湖│辰○○、乙○○│未扣案之門號│              │\n│  │11月│縣馬│、申○○基於犯│0000000000號│              │\n│  │6日 │公市│意之聯絡，由蔡│行動電話1支 │              │\n│  │    │南海│俊明以其所有之│沒收，如全部│              │\n│  │    │碼頭│0000000000號行│或一部不能沒│              │\n│  │    │    │動電話與丑○○│收時，追徵其│              │\n│  │    │    │聯絡，再由蔡俊│價額或以其財│              │\n│  │    │    │明向乙○○拿取│產抵償之。  │              │\n│  │    │    │辰○○所有之安│            │              │\n│  │    │    │非他命，將安非│            │              │\n│  │    │    │他命置放CD盒內│            │              │\n│  │    │    │，寄放船上送至│            │              │\n│  │    │    │虎井交丑○○收│            │              │\n│  │    │    │受，販賣安非他│            │              │\n│  │    │    │命予丑○○，價│            │              │\n│  │    │    │值2000元，但尚│            │              │\n│  │    │    │未收取款項。  │            │              │\n├─┼──┼──┼───────┼──────┼───────┤\n│2 │96年│澎湖│辰○○、庚○○│未扣案之門號│              │\n│  │11月│縣馬│、申○○基於犯│0000000000號│              │\n│  │10日│公市│意之聯絡，由蔡│、0000000000│              │\n│  │    │馬公│俊明以其所有之│號行動電話各│              │\n│  │    │國中│0000000000號行│1支沒收，如 │              │\n│  │    │大門│動電話與歐家雄│全部或一部不│              │\n│  │    │前  │聯絡後，再由歐│能沒收時，均│              │\n│  │    │    │家雄撥打申○○│追徵其價額或│              │\n│  │    │    │告知之00000000│以其財產抵償│              │\n│  │    │    │97號庚○○行動│之。        │              │\n│  │    │    │電話，由庚○○│            │              │\n│  │    │    │與歐家雄約定交│            │              │\n│  │    │    │易時地後，再由│            │              │\n│  │    │    │庚○○、辰○○│            │              │\n│  │    │    │出面販賣安非他│            │              │\n│  │    │    │命1包予歐家雄 │            │              │\n│  │    │    │，價值5000元，│            │              │\n│  │    │    │但未收取款項（│            │              │\n│  │    │    │以申○○積欠之│            │              │\n│  │    │    │5000元債務相抵│            │              │\n│  │    │    │）。          │            │              │\n├─┼──┼──┼───────┼──────┼───────┤\n│3 │96年│澎湖│辰○○、庚○○│未扣案之門號│販賣第二級毒品│\n│  │11月│縣馬│、申○○基於犯│0000000000號│所得2000元與陳│\n│  │10日│公市│意之聯絡，由蔡│行動電話1支 │建榮、庚○○連│\n│  │（起│中興│俊明以其所有之│沒收，如全部│帶沒收，如全部│\n│  │訴書│國小│0000000000號行│或一部不能沒│或一部不能沒收│\n│  │誤載│旁統│動電話與丁○○│收時，追徵其│時，以其財產抵│\n│  │為11│一超│、庚○○分別聯│價額或以其財│償之。        │\n│  │月11│商前│絡後，再由夏敏│產抵償之。  │              │\n│  │日）│    │雄、辰○○出面│            │              │\n│  │    │    │販賣安非他命1 │            │              │\n│  │    │    │包予丁○○，價│            │              │\n│  │    │    │值2000元，並當│            │              │\n│  │    │    │場先收取1000元│            │              │\n│  │    │    │價款，所餘1000│            │              │\n│  │    │    │元嗣由申○○收│            │              │\n│  │    │    │取後轉交庚○○│            │              │\n│  │    │    │。            │            │              │\n└─┴──┴──┴───────┴──────┴───────┘\n（三）\n┌──────────────────────────────┐\n│被告申○○轉讓海洛因一覽表                                  │\n├─┬────┬───────┬───────────────┤\n│編│犯罪時間│犯罪地點      │犯罪手法、對象、毒品種類、數量│\n│號│        │              │                              │\n├─┼────┼───────┼───────────────┤\n│1 │96年11月│澎湖縣馬公市享│轉讓海洛因1小包，予陳志盟。   │\n│  │12日    │溫馨KTV       │                              │\n├─┼────┼───────┼───────────────┤\n│2 │96年11月│澎湖縣馬公市陽│轉讓海洛因1小包，予陳志盟。   │\n│  │15日    │明路90 號前   │                              │\n├─┼────┼───────┼───────────────┤\n│3 │96年11月│澎湖縣馬公市陽│轉讓海洛因1小包，予癸○○。   │\n│  │18日    │明路關帝廟前  │                              │\n├─┼────┼───────┼───────────────┤\n│4 │96年11月│澎湖縣馬公市石│轉讓海洛因予翁丁元、翁維昌。  │\n│  │21日    │泉里1- 60號   │                              │\n└─┴────┴───────┴───────────────┘\n附表四\n（一）\n┌──────────────────────────────┐\n│被告巳○○販賣安非他命一覽表                                │\n├─┬──┬──┬───────┬──────┬───────┤\n│編│犯罪│犯罪│犯罪手法、對象│應沒收之物(1)│應沒收之物(2)  │\n│號│時間│地點│、毒品種類、數│            │（單位：新台幣│\n│  │    │    │量及金額（單位│            │元）          │\n│  │    │    │：新台幣元）  │            │              │\n├─┼──┼──┼───────┼──────┼───────┤\n│1 │96年│澎湖│以0000000000號│未扣案之門號│販賣第二級毒品│\n│  │10月│縣馬│行動電話聯絡交│0000000000號│所得2000元沒收│\n│  │初某│公市│易事宜，販賣安│行動電話1支 │，如全部或一部│\n│  │日  │南海│非他命1小包予 │沒收，如全部│不能沒收時，以│\n│  │    │旅遊│戊○○，得款  │或一部不能沒│其財產抵償之。│\n│  │    │中心│2000元。      │收時，追徵其│              │\n│  │    │前  │              │價額或以其財│              │\n│  │    │    │              │產抵償之。  │              │\n├─┼──┼──┼───────┼──────┼───────┤\n│2 │96年│澎湖│以0000000000號│未扣案之門號│販賣第二級毒品│\n│  │11月│縣馬│行動電話聯絡交│0000000000號│所得500元沒收 │\n│  │6日 │公市│易事宜，販賣安│行動電話1支 │，如全部或一部│\n│  │    │石泉│非他命2小包予 │沒收，如全部│不能沒收時，以│\n│  │    │國小│癸○○，價值  │或一部不能沒│其財產抵償之  │\n│  │    │對面│3500元，嗣莊正│收時，追徵其│              │\n│  │    │（豐│和僅給付500元 │價額或以其財│              │\n│  │    │裕冷│，尚積欠3000元│產抵償之。  │              │\n│  │    │凍公│（癸○○匯款  │            │              │\n│  │    │司附│2000元償還另筆│            │              │\n│  │    │近  │債務1500元，其│            │              │\n│  │    │    │餘500元作為清 │            │              │\n│  │    │    │償本次買毒品之│            │              │\n│  │    │    │欠款）        │            │              │\n└─┴──┴──┴───────┴──────┴───────┘\n（二）\n┌──────────────────────────────┐\n│被告巳○○販賣海洛因一覽表                                  │\n├─┬──┬──┬───────┬──────┬───────┤\n│編│犯罪│犯罪│犯罪手法、對象│應沒收之物(1)│應沒收之物(2)  │\n│號│時間│地點│、毒品種類、數│            │（單位：新台幣│\n│  │    │    │量及金額（單位│            │元）          │\n│  │    │    │：新台幣元）  │            │              │\n├─┼──┼──┼───────┼──────┼───────┤\n│1 │96年│澎湖│以0000000000號│未扣案之門號│販賣第一級毒品│\n│  │11月│縣馬│行動電話聯絡交│0000000000號│所得3000元沒收│\n│  │2日 │公市│易事宜，販賣海│行動電話1支 │，如全部或一部│\n│  │    │光復│洛因予癸○○，│沒收，如全部│不能沒收時，以│\n│  │    │路近│得款3000元。  │或一部不能沒│其財產抵償之。│\n│  │    │南檳│              │收時，追徵其│              │\n│  │    │榔店│              │價額或以其財│              │\n│  │    │前  │              │產抵償之。  │              │\n├─┼──┼──┼───────┼──────┼───────┤\n│2 │96年│澎湖│以0000000000號│未扣案之門號│              │\n│  │11月│縣馬│行動電話聯絡交│0000000000號│              │\n│  │3日 │公市│易事宜，販賣海│行動電話1支 │              │\n│  │    │光復│洛因予癸○○，│沒收，如全部│              │\n│  │    │路近│價值1000元，嗣│或一部不能沒│              │\n│  │    │南檳│癸○○未給付價│收時，追徵其│              │\n│  │    │榔店│款。          │價額或以其財│              │\n│  │    │前  │              │產抵償之。  │              │\n└─┴──┴──┴───────┴──────┴───────┘\n附表五\n┌──────────────────────────────┐\n│被告庚○○販賣安非他命一覽表                                │\n├─┬──┬──┬───────┬──────┬───────┤\n│編│犯罪│犯罪│犯罪手法、對象│應沒收之物(1)│應沒收之物(2)  │\n│號│時間│地點│、毒品種類、數│            │（單位：新台幣│\n│  │    │    │量及金額（單位│            │元）          │\n│  │    │    │：新台幣元）  │            │              │\n├─┼──┼──┼───────┼──────┼───────┤\n│1 │同附│同附│同附表三（二）│未扣案之門號│              │\n│  │表三│表三│編號2         │0000000000號│              │\n│  │（二│（二│              │、0000000000│              │\n│  │）編│）編│              │號行動電話各│              │\n│  │號2 │號2 │              │1支沒收，如 │              │\n│  │    │    │              │全部或一部不│              │\n│  │    │    │              │能沒收時，均│              │\n│  │    │    │              │追徵其價額或│              │\n│  │    │    │              │以其財產抵償│              │\n│  │    │    │              │之。        │              │\n├─┼──┼──┼───────┼──────┼───────┤\n│2 │同附│同附│同附表三（二）│未扣案之門號│販賣第二級毒品│\n│  │表三│表三│編號3         │0000000000號│所得2000元與陳│\n│  │（二│（二│              │行動電話1支 │建榮、申○○連│\n│  │）編│）編│              │沒收，如全部│帶沒收，如全部│\n│  │號3 │號3 │              │或一部不能沒│或一部不能沒收│\n│  │    │    │              │收時，追徵其│時，以其財產抵│\n│  │    │    │              │價額或以其財│償之。        │\n│  │    │    │              │產抵償之。  │              │\n└─┴──┴──┴───────┴──────┴───────┘\n附表六\n┌──────────────────────────────┐\n│被告未○○施用海洛因一覽表                                  │\n├─┬────┬─────────────┬─────────┤\n│編│犯罪時間│犯罪地點                  │施用毒品種類、次數│\n│號│        │                          │                  │\n├─┼────┼─────────────┼─────────┤\n│1 │96年11月│澎湖縣馬公市○○路李子林婦│施用海洛因1次。   │\n│  │中旬某日│產科前汽車內              │                  │\n├─┼────┼─────────────┼─────────┤\n│2 │96年11月│澎湖縣馬公市某地（起訴書誤│施用海洛因1次。   │\n│  │15日14時│載為大勇街30號農會生鮮超市│                  │\n│  │35分許  │）                        │                  │\n├─┼────┼─────────────┼─────────┤\n│3 │96年11月│澎湖縣馬公市東衛里統一超商│施用海洛因1次。   │\n│  │25日    │附近                      │                  │\n├─┼────┼─────────────┼─────────┤\n│4 │96年11月│澎湖縣白沙鄉水族館附近    │施用海洛因1次。   │\n│  │28日    │                          │                  │\n└─┴────┴─────────────┴─────────┘\n附表七\n（一）\n┌──────────────────────────────┐\n│被告甲○○販賣海洛因一覽表                                  │\n├─┬──┬──┬───────┬──────┬───────┤\n│編│犯罪│犯罪│犯罪手法、對象│應沒收之物(1)│應沒收之物(2)  │\n│號│時間│地點│、毒品種類、數│            │（單位：新台幣│\n│  │    │    │量及金額（單位│            │元）          │\n│  │    │    │：新台幣元）  │            │              │\n├─┼──┼──┼───────┼──────┼───────┤\n│1 │96年│澎湖│以0000000000號│未扣案之門號│販賣第一級毒品│\n│  │8月5│縣西│行動電話聯絡交│0000000000號│所得1000元沒收│\n│  │日11│嶼鄉│易事宜，販賣海│行動電話1支 │，如全部或一部│\n│  │時38│外垵│洛因1小包予洪 │沒收，如全部│不能沒收時，以│\n│  │分許│村慈│輝文，得款1000│或一部不能沒│其財產抵償之。│\n│  │    │航寺│元。          │收時，追徵其│              │\n│  │    │附近│              │價額或以其財│              │\n│  │    │道路│              │產抵償之。  │              │\n├─┼──┼──┼───────┼──────┼───────┤\n│2 │96年│澎湖│以0000000000號│未扣案之門號│販賣第一級毒品│\n│  │8月 │縣西│行動電話聯絡交│0000000000號│所得1000元沒收│\n│  │30日│嶼鄉│易事宜，販賣海│行動電話1支 │，如全部或一部│\n│  │20時│外垵│洛因1小包予洪 │沒收，如全部│不能沒收時，以│\n│  │37分│村慈│輝文，得款1000│或一部不能沒│其財產抵償之。│\n│  │許  │航寺│元。          │收時，追徵其│              │\n│  │    │附近│              │價額或以其財│              │\n│  │    │道路│              │產抵償之。  │              │\n├─┼──┼──┼───────┼──────┼───────┤\n│3 │96年│澎湖│以0000000000號│未扣案之門號│販賣第一級毒品│\n│  │9月 │縣西│行動電話聯絡交│0000000000號│所得1000元沒收│\n│  │10日│嶼鄉│易事宜，販賣海│行動電話1支 │，如全部或一部│\n│  │18時│外垵│洛因1小包予洪 │沒收，如全部│不能沒收時，以│\n│  │40分│村慈│輝文，得款1000│或一部不能沒│其財產抵償之。│\n│  │許  │航寺│元。          │收時，追徵其│              │\n│  │    │附近│              │價額或以其財│              │\n│  │    │道路│              │產抵償之。  │              │\n├─┼──┼──┼───────┼──────┼───────┤\n│4 │96年│澎湖│以0000000000號│未扣案之門號│販賣第一級毒品│\n│  │9月 │縣西│行動電話聯絡交│0000000000號│所得1000元沒收│\n│  │11日│嶼鄉│易事宜，販賣海│行動電話1支 │，如全部或一部│\n│  │19時│外垵│洛因1小包予洪 │沒收，如全部│不能沒收時，以│\n│  │57分│村慈│輝文，得款1000│或一部不能沒│其財產抵償之。│\n│  │許  │航寺│元。          │收時，追徵其│              │\n│  │    │附近│              │價額或以其財│              │\n│  │    │道路│              │產抵償之。  │              │\n├─┼──┼──┼───────┼──────┼───────┤\n│5 │96年│澎湖│以0000000000號│未扣案之門號│販賣第一級毒品│\n│  │9月 │縣西│行動電話聯絡交│0000000000號│所得1000元沒收│\n│  │底10│嶼鄉│易事宜，販賣海│行動電話1支 │，如全部或一部│\n│  │月初│外垵│洛因1小包予莊 │沒收，如全部│不能沒收時，以│\n│  │某日│村慈│正和、申○○，│或一部不能沒│其財產抵償之。│\n│  │19時│航寺│得款1000元。  │收時，追徵其│              │\n│  │許  │附近│              │價額或以其財│              │\n│  │    │道路│              │產抵償之。  │              │\n├─┼──┼──┼───────┼──────┼───────┤\n│6 │96年│澎湖│以0000000000號│未扣案之門號│販賣第一級毒品│\n│  │10月│縣西│行動電話聯絡交│0000000000號│所得1000元沒收│\n│  │8日 │嶼鄉│易事宜，販賣海│行動電話1支 │，如全部或一部│\n│  │19時│外垵│洛因1小包值予 │沒收，如全部│不能沒收時，以│\n│  │27分│村慈│己○○，得款  │或一部不能沒│其財產抵償之。│\n│  │許  │航寺│1000元。      │收時，追徵其│              │\n│  │    │附近│              │價額或以其財│              │\n│  │    │道路│              │產抵償之。  │              │\n├─┼──┼──┼───────┼──────┼───────┤\n│7 │96年│澎湖│以0000000000號│未扣案之門號│販賣第一級毒品│\n│  │10月│縣西│行動電話聯絡交│0000000000號│所得2000元沒收│\n│  │某日│嶼鄉│易事宜，販賣海│行動電話1支 │，如全部或一部│\n│  │    │外垵│洛因1小包予莊 │沒收，如全部│不能沒收時，以│\n│  │    │村廟│正和、寅○○，│或一部不能沒│其財產抵償之。│\n│  │    │前  │得款2000元。  │收時，追徵其│              │\n│  │    │    │              │價額或以其財│              │\n│  │    │    │              │產抵償之。  │              │\n├─┼──┼──┼───────┼──────┼───────┤\n│8 │96年│澎湖│以0000000000號│未扣案之門號│販賣第一級毒品│\n│  │10月│縣西│行動電話聯絡交│0000000000號│所得1000元沒收│\n│  │底11│嶼鄉│易事宜，販賣海│行動電話1支 │，如全部或一部│\n│  │月初│外垵│洛因1小包予李 │沒收，如全部│不能沒收時，以│\n│  │某日│村廟│志堅、庚○○，│或一部不能沒│其財產抵償之。│\n│  │    │前  │得款1000元。  │收時，追徵其│              │\n│  │    │    │              │價額或以其財│              │\n│  │    │    │              │產抵償之。  │              │\n├─┼──┼──┼───────┼──────┼───────┤\n│9 │96年│澎湖│以0000000000號│未扣案之門號│販賣第一級毒品│\n│  │11月│縣西│行動電話聯絡交│0000000000號│所得1000元沒收│\n│  │2日 │嶼鄉│易事宜，販賣海│行動電話1支 │，如全部或一部│\n│  │    │外垵│洛因1小包予莊 │沒收，如全部│不能沒收時，以│\n│  │    │村慈│正和，得款1000│或一部不能沒│其財產抵償之。│\n│  │    │航寺│元。          │收時，追徵其│              │\n│  │    │附近│              │價額或以其財│              │\n│  │    │    │              │產抵償之。  │              │\n├─┼──┼──┼───────┼──────┼───────┤\n│10│96年│澎湖│以0000000000號│未扣案之門號│販賣第一級毒品│\n│  │11月│縣西│行動電話聯絡交│0000000000號│所得2000元沒收│\n│  │6日 │嶼鄉│易事宜，販賣海│行動電話1支 │，如全部或一部│\n│  │    │外垵│洛因1小包予莊 │沒收，如全部│不能沒收時，以│\n│  │    │村慈│正和，得款2000│或一部不能沒│其財產抵償之。│\n│  │    │航寺│元。          │收時，追徵其│              │\n│  │    │附近│              │價額或以其財│              │\n│  │    │    │              │產抵償之。  │              │\n├─┼──┼──┼───────┼──────┼───────┤\n│11│96年│澎湖│以0000000000號│未扣案之門號│販賣第一級毒品│\n│  │11月│縣西│行動電話聯絡交│0000000000號│所得3000元沒收│\n│  │6日 │嶼鄉│易事宜，販賣海│行動電話1支 │，如全部或一部│\n│  │    │外垵│洛因3小包予莊 │沒收，如全部│不能沒收時，以│\n│  │    │村慈│正和，得款3000│或一部不能沒│其財產抵償之。│\n│  │    │航寺│元。          │收時，追徵其│              │\n│  │    │附近│              │價額或以其財│              │\n│  │    │    │              │產抵償之。  │              │\n└─┴──┴──┴───────┴──────┴───────┘\n（二）\n┌──────────────────────────────┐\n│被告甲○○轉讓海洛因一覽表                                  │\n├─┬────┬───────┬───────────────┤\n│編│犯罪時間│犯罪地點      │犯罪手法、對象、毒品種類、數量│\n│號│        │              │                              │\n├─┼────┼───────┼───────────────┤\n│1 │96年11月│澎湖縣西嶼鄉外│轉讓海洛因1小包，予癸○○（與 │\n│  │6日     │垵村慈航寺附近│癸○○互換附表九（三）編號１所│\n│  │        │              │示之毒品）。                  │\n└─┴────┴───────┴───────────────┘\n（三）\n┌──────────────────────────────┐\n│被告甲○○幫助施用海洛因一覽表                              │\n├─┬────┬───────┬───────────────┤\n│編│犯罪時間│犯罪地點      │犯罪手法、對象、毒品種類、數量│\n│號│        │              │及金額（單位：新台幣元）      │\n├─┼────┼───────┼───────────────┤\n│1 │96年9月2│澎湖縣西嶼鄉外│甲○○自己出資並向丙○○收取  │\n│  │8日18時 │垵國小附近    │1500元，集資後再由甲○○出面購│\n│  │51分許  │              │買海洛因2 小包後，2人分食之。 │\n├─┼────┼───────┼───────────────┤\n│2 │96年10月│澎湖縣西嶼鄉外│甲○○自己出資並向丙○○收取  │\n│  │14日8時 │垵村慈航寺附近│700元，集資後再由甲○○出面購 │\n│  │許      │              │買海洛因1 支（以白色吸管包裝）│\n│  │        │              │後，2人分食之。               │\n├─┼────┼───────┼───────────────┤\n│3 │96年10月│澎湖縣西嶼鄉外│甲○○自己出資並向丙○○收取  │\n│  │17日7時 │垵村慈航寺附近│700元，集資後再由甲○○出面購 │\n│  │許      │              │買海洛因1 支（以白色吸管包裝）│\n│  │        │              │後，2人分食之。               │\n├─┼────┼───────┼───────────────┤\n│4 │96年10月│澎湖縣西嶼鄉外│甲○○自己出資並向丙○○收取  │\n│  │23日20時│垵村慈航寺附近│700元，集資後再由甲○○出面購 │\n│  │許      │              │買海洛因2 支（以白色吸管包裝）│\n│  │        │              │後，2人分食之。               │\n├─┼────┼───────┼───────────────┤\n│5 │96年10月│澎湖縣馬公市縣│甲○○自己出資並向丙○○收取金│\n│  │28日21時│立體育館附近  │錢，集資後再由甲○○出面購買海│\n│  │36分許  │              │洛因2支（以白色吸管包裝）後，2│\n│  │        │              │人分食之。                    │\n└─┴────┴───────┴───────────────┘\n附表八\n（一）\n┌──────────────────────────────┐\n│被告乙○○幫助施用海洛因一覽表                              │\n├─┬────┬───────┬───────────────┤\n│編│犯罪時間│犯罪地點      │犯罪手法、對象、毒品種類、數量│\n│號│        │              │及金額（單位：新台幣元）      │\n├─┼────┼───────┼───────────────┤\n│1 │96年9月 │澎湖縣白沙鄉講│乙○○自己出資並向寅○○收取  │\n│  │底某日  │美村廟旁      │2000元，集資後再由乙○○出面購│\n│  │        │              │買海洛因1小包後，2人分食之。  │\n└─┴────┴───────┴───────────────┘\n（二）\n┌──────────────────────────────┐\n│被告乙○○販賣海洛因一覽表                                  │\n├─┬──┬──┬───────┬──────┬───────┤\n│編│犯罪│犯罪│犯罪手法、對象│應沒收之物(1)│應沒收之物(2)  │\n│號│時間│地點│、毒品種類、數│            │（單位：新台幣│\n│  │    │    │量及金額（單位│            │元）          │\n│  │    │    │：新台幣元）  │            │              │\n├─┼──┼──┼───────┼──────┼───────┤\n│1 │96年│澎湖│乙○○、癸○○│未扣案之門號│販賣第一級毒品│\n│  │10月│縣馬│先至高雄購買毒│0000000000號│所得10000元與 │\n│  │12日│公市│品（由乙○○出│行動電話1支 │癸○○連帶沒收│\n│  │    │百合│資），嗣由另案│沒收，如全部│，如全部或一部│\n│  │    │民宿│被告金文隆將毒│或一部不能沒│不能沒收時，以│\n│  │    │    │品攜至澎湖後，│收時，追徵其│其財產抵償之。│\n│  │    │    │乙○○與癸○○│價額或以其財│              │\n│  │    │    │基於犯意之聯絡│產抵償之。  │              │\n│  │    │    │，由癸○○以其│            │              │\n│  │    │    │所有之        │            │              │\n│  │    │    │0000000000號行│            │              │\n│  │    │    │動電話聯絡交易│            │              │\n│  │    │    │事宜，再由莊正│            │              │\n│  │    │    │和、乙○○出面│            │              │\n│  │    │    │交付海洛因，販│            │              │\n│  │    │    │賣海洛因予林寶│            │              │\n│  │    │    │吉，得款10000 │            │              │\n│  │    │    │元。          │            │              │\n├─┼──┼──┼───────┼──────┼───────┤\n│2 │96年│澎湖│乙○○、癸○○│未扣案之門號│販賣第一級毒品│\n│  │10月│縣馬│先至高雄購買毒│0000000000號│所得10000元與 │\n│  │12日│公市│品（由乙○○出│行動電話1支 │癸○○連帶沒收│\n│  │    │百合│資），嗣由另案│沒收，如全部│，如全部或一部│\n│  │    │民宿│被告金文隆將毒│或一部不能沒│不能沒收時，以│\n│  │    │    │品攜至澎湖後，│收時，追徵其│其財產抵償之。│\n│  │    │    │乙○○與癸○○│價額或以其財│              │\n│  │    │    │基於犯意之聯絡│產抵償之。  │              │\n│  │    │    │，由癸○○以其│            │              │\n│  │    │    │所有之        │            │              │\n│  │    │    │0000000000號行│            │              │\n│  │    │    │動電話聯絡交易│            │              │\n│  │    │    │事宜，再由莊正│            │              │\n│  │    │    │和、乙○○出面│            │              │\n│  │    │    │交付海洛因，販│            │              │\n│  │    │    │賣海洛因予黃天│            │              │\n│  │    │    │成，得款10000 │            │              │\n│  │    │    │元。          │            │              │\n├─┼──┼──┼───────┼──────┼───────┤\n│3 │96年│澎湖│乙○○、癸○○│未扣案之門號│販賣第一級毒品│\n│  │10月│縣馬│先至高雄購買毒│0000000000號│所得10000元與 │\n│  │13日│公市│品（由乙○○出│行動電話1支 │癸○○連帶沒收│\n│  │    │百合│資），嗣由另案│沒收，如全部│，如全部或一部│\n│  │    │民宿│被告金文隆將毒│或一部不能沒│不能沒收時，以│\n│  │    │    │品攜至澎湖後，│收時，追徵其│其財產抵償之。│\n│  │    │    │乙○○與癸○○│價額或以其財│              │\n│  │    │    │基於犯意之聯絡│產抵償之。  │              │\n│  │    │    │，由癸○○以其│            │              │\n│  │    │    │所有之        │            │              │\n│  │    │    │0000000000號行│            │              │\n│  │    │    │動電話聯絡交易│            │              │\n│  │    │    │事宜，再由莊正│            │              │\n│  │    │    │和、乙○○出面│            │              │\n│  │    │    │交付海洛因，販│            │              │\n│  │    │    │賣海洛因予林寶│            │              │\n│  │    │    │吉，得款10000 │            │              │\n│  │    │    │元。          │            │              │\n└─┴──┴──┴───────┴──────┴───────┘\n（三）\n┌──────────────────────────────┐\n│被告乙○○販賣安非他命一覽表                                │\n├─┬──┬──┬───────┬──────┬───────┤\n│編│犯罪│犯罪│犯罪手法、對象│應沒收之物(1)│應沒收之物(2)  │\n│號│時間│地點│、毒品種類、數│            │（單位：新台幣│\n│  │    │    │量及金額（單位│            │元）          │\n│  │    │    │：新台幣元）  │            │              │\n├─┼──┼──┼───────┼──────┼───────┤\n│1 │96年│澎湖│乙○○與辰○○│未扣案之門號│販賣第二級毒品│\n│  │10月│縣馬│基於犯意之聯絡│0000000000號│所得6000元與陳│\n│  │26日│公市│，由乙○○以其│行動電話1支 │建榮連帶沒收，│\n│  │    │燦坤│所有之        │沒收，如全部│如全部或一部不│\n│  │    │量販│0000000000號行│或一部不能沒│能沒收時，以其│\n│  │    │店後│動電話聯絡交易│收時，追徵其│財產抵償之。  │\n│  │    │方公│事宜，再由陳建│價額或以其財│              │\n│  │    │園  │榮出面交付安非│產抵償之。  │              │\n│  │    │    │他命，嗣由李志│            │              │\n│  │    │    │堅收款，販賣安│            │              │\n│  │    │    │非他命予酉○○│            │              │\n│  │    │    │，得款6000元。│            │              │\n├─┼──┼──┼───────┼──────┼───────┤\n│2 │96年│澎湖│販賣安非他命1 │            │販賣第二級毒品│\n│  │11月│縣馬│小包予丁○○，│            │所得2000元沒收│\n│  │6日 │公市│得款2000元。  │            │，如全部或一部│\n│  │    │西衛│              │            │不能沒收時，以│\n│  │    │里海│              │            │其財產抵償之。│\n│  │    │邊車│              │            │              │\n│  │    │上  │              │            │              │\n├─┼──┼──┼───────┼──────┼───────┤\n│3 │同附│同附│同附表三（二）│未扣案之門號│              │\n│  │表三│表三│編號1         │0000000000號│              │\n│  │（二│（二│              │行動電話1支 │              │\n│  │）編│）編│              │沒收，如全部│              │\n│  │號1 │號1 │              │或一部不能沒│              │\n│  │    │    │              │收時，追徵其│              │\n│  │    │    │              │價額或以其財│              │\n│  │    │    │              │產抵償之。  │              │\n└─┴──┴──┴───────┴──────┴───────┘\n（四）\n┌──────────────────────────────┐\n│被告乙○○轉讓海洛因一覽表                                  │\n├─┬────┬─────────┬─────────────┤\n│編│犯罪時間│犯罪地點          │犯罪手法、對象、毒品種類、│\n│號│        │                  │數量                      │\n├─┼────┼─────────┼─────────────┤\n│1 │96年11月│澎湖縣馬公市○○路│轉讓海洛因（1支針筒量）予 │\n│  │初某日  │229號4樓乙○○租屋│癸○○。                  │\n│  │        │處                │                          │\n├─┼────┼─────────┼─────────────┤\n│2 │96年11月│澎湖縣馬公市南海碼│轉讓海洛因，予申○○。    │\n│  │2日     │頭（起訴書誤載為光│                          │\n│  │        │復路229號4樓乙○○│                          │\n│  │        │租屋處）          │                          │\n├─┼────┼─────────┼─────────────┤\n│3 │96年11月│澎湖縣馬公市○○路│轉讓海洛因，予癸○○。    │\n│  │4日     │229號4樓乙○○租屋│                          │\n│  │        │處                │                          │\n├─┼────┼─────────┼─────────────┤\n│4 │96年11月│澎湖縣馬公市○○路│轉讓海洛因，予庚○○、陳永│\n│  │5日     │229號4樓乙○○租屋│豊。                      │\n│  │        │處                │                          │\n├─┼────┼─────────┼─────────────┤\n│5 │96年11月│澎湖縣馬公市興仁里│轉讓海洛因，予癸○○。    │\n│  │5日     │統一超商前        │                          │\n├─┼────┼─────────┼─────────────┤\n│6 │96年11月│澎湖縣馬公市○○路│轉讓海洛因，予翁丁元。    │\n│  │12日    │翁丁元住處        │                          │\n├─┼────┼─────────┼─────────────┤\n│7 │96年11月│澎湖縣馬公市○○路│轉讓海洛因，予癸○○。    │\n│  │12日    │關帝廟前          │                          │\n└─┴────┴─────────┴─────────────┘\n附表九\n（一）\n┌──────────────────────────────┐\n│被告癸○○販賣海洛因一覽表                                  │\n├─┬──┬──┬───────┬──────┬───────┤\n│編│犯罪│犯罪│犯罪手法、對象│應沒收之物(1)│應沒收之物(2)  │\n│號│時間│地點│、毒品種類、數│            │（單位：新台幣│\n│  │    │    │量及金額（單位│            │元）          │\n│  │    │    │：新台幣元）  │            │              │\n├─┼──┼──┼───────┼──────┼───────┤\n│1 │同附│同附│同附表八（二）│未扣案之門號│販賣第一級毒品│\n│  │表八│表八│編號1         │0000000000號│所得10000元與 │\n│  │（二│（二│              │行動電話1支 │乙○○連帶沒收│\n│  │）編│）編│              │沒收，如全部│，如全部或一部│\n│  │號1 │號1 │              │或一部不能沒│不能沒收時，以│\n│  │    │    │              │收時，追徵其│其財產抵償之。│\n│  │    │    │              │價額或以其財│              │\n│  │    │    │              │產抵償之。  │              │\n├─┼──┼──┼───────┼──────┼───────┤\n│2 │同附│同附│同附表八（二）│未扣案之門號│販賣第一級毒品│\n│  │表八│表八│編號2         │0000000000號│所得10000元與 │\n│  │（二│（二│              │行動電話1支 │乙○○連帶沒收│\n│  │）編│）編│              │沒收，如全部│，如全部或一部│\n│  │號2 │號2 │              │或一部不能沒│不能沒收時，以│\n│  │    │    │              │收時，追徵其│其財產抵償之。│\n│  │    │    │              │價額或以其財│              │\n│  │    │    │              │產抵償之。  │              │\n├─┼──┼──┼───────┼──────┼───────┤\n│3 │同附│同附│同附表八（二）│未扣案之門號│販賣第一級毒品│\n│  │表八│表八│編號3         │0000000000號│所得10000元與 │\n│  │（二│（二│              │行動電話1支 │乙○○連帶沒收│\n│  │）編│）編│              │沒收，如全部│，如全部或一部│\n│  │號3 │號3 │              │或一部不能沒│不能沒收時，以│\n│  │    │    │              │收時，追徵其│其財產抵償之。│\n│  │    │    │              │價額或以其財│              │\n│  │    │    │              │產抵償之。  │              │\n├─┼──┼──┼───────┼──────┼───────┤\n│4 │同附│同附│同附表三（一）│未扣案之門號│販賣第一級毒品│\n│  │表三│表三│編號1         │0000000000號│所得5000元與陳│\n│  │（一│（一│              │行動電話1支 │建榮、申○○連│\n│  │）編│）編│              │沒收，如全部│帶沒收，如全部│\n│  │號1 │號1 │              │或一部不能沒│或一部不能沒收│\n│  │    │    │              │收時，追徵其│時，以其財產抵│\n│  │    │    │              │價額或以其財│償之。        │\n│  │    │    │              │產抵償之。  │              │\n├─┼──┼──┼───────┼──────┼───────┤\n│5 │96年│澎湖│辰○○、癸○○│未扣案之門號│販賣第一級毒品│\n│  │10月│縣馬│基於犯意之聯絡│0000000000號│所得5000元與陳│\n│  │某日│公市│，由癸○○以其│行動電話1支 │建榮連帶沒收，│\n│  │    │西衛│所有之        │沒收，如全部│如全部或一部不│\n│  │    │里海│0000000000號行│或一部不能沒│能沒收時，以其│\n│  │    │邊  │動電話聯絡交易│收時，追徵其│財產抵償之。  │\n│  │    │    │事宜，再由莊正│價額或以其財│              │\n│  │    │    │和交付毒品，販│產抵償之。  │              │\n│  │    │    │賣海洛因1包予 │            │              │\n│  │    │    │午○○，價值  │            │              │\n│  │    │    │5000元，嗣收取│            │              │\n│  │    │    │之款項5000元歸│            │              │\n│  │    │    │辰○○所有。  │            │              │\n├─┼──┼──┼───────┼──────┼───────┤\n│6 │同附│同附│同附表三（一）│未扣案之門號│販賣第一級毒品│\n│  │表三│表三│編號3         │0000000000號│所得3000元與陳│\n│  │（一│（一│              │行動電話1支 │建榮、申○○連│\n│  │）編│）編│              │沒收，如全部│帶沒收，如全部│\n│  │號3 │號3 │              │或一部不能沒│或一部不能沒收│\n│  │    │    │              │收時，追徵其│時，以其財產抵│\n│  │    │    │              │價額或以其財│償之。        │\n│  │    │    │              │產抵償之。  │              │\n├─┼──┼──┼───────┼──────┼───────┤\n│7 │同附│同附│同附表三（一）│未扣案之門號│              │\n│  │表三│表三│編號4         │0000000000號│              │\n│  │（一│（一│              │行動電話1支 │              │\n│  │）編│）編│              │沒收，如全部│              │\n│  │號4 │號4 │              │或一部不能沒│              │\n│  │    │    │              │收時，追徵其│              │\n│  │    │    │              │價額或以其財│              │\n│  │    │    │              │產抵償之。  │              │\n├─┼──┼──┼───────┼──────┼───────┤\n│8 │同附│同附│同附表三（一）│未扣案之門號│販賣第一級毒品│\n│  │表三│表三│編號2         │0000000000號│所得4000元與陳│\n│  │（一│（一│              │行動電話1支 │建榮、申○○連│\n│  │）編│）編│              │沒收，如全部│帶沒收，如全部│\n│  │號2 │號2 │              │或一部不能沒│或一部不能沒收│\n│  │    │    │              │收時，追徵其│時，以其財產抵│\n│  │    │    │              │價額或以其財│償之。        │\n│  │    │    │              │產抵償之。  │              │\n├─┼──┼──┼───────┼──────┼───────┤\n│9 │96年│澎湖│辰○○、癸○○│未扣案之門號│              │\n│  │11月│縣馬│基於犯意之聯絡│0000000000號│              │\n│  │某日│公市│，由癸○○以其│行動電話1支 │              │\n│  │    │光復│所有之        │沒收，如全部│              │\n│  │    │路  │0000000000號行│或一部不能沒│              │\n│  │    │229 │動電話聯絡交易│收時，追徵其│              │\n│  │    │號4 │事宜，再由莊正│價額或以其財│              │\n│  │    │樓李│和交付毒品，販│產抵償之。  │              │\n│  │    │志堅│賣價值2000元之│            │              │\n│  │    │租屋│海洛因予庚○○│            │              │\n│  │    │處  │，惟嗣未收取款│            │              │\n│  │    │    │項。          │            │              │\n├─┼──┼──┼───────┼──────┼───────┤\n│10│96年│澎湖│辰○○、癸○○│未扣案之門號│              │\n│  │11月│縣馬│基於犯意之聯絡│0000000000號│              │\n│  │某日│公市│，由癸○○以其│行動電話1支 │              │\n│  │    │忠孝│所有之        │沒收，如全部│              │\n│  │    │路70│0000000000號行│或一部不能沒│              │\n│  │    │巷4 │動電話聯絡交易│收時，追徵其│              │\n│  │    │號外│事宜，再由莊正│價額或以其財│              │\n│  │    │    │和交付毒品，販│產抵償之。  │              │\n│  │    │    │賣價值2000元之│            │              │\n│  │    │    │海洛因予庚○○│            │              │\n│  │    │    │，惟嗣未收取款│            │              │\n│  │    │    │項。          │            │              │\n└─┴──┴──┴───────┴──────┴───────┘\n（二）\n┌──────────────────────────────┐\n│被告癸○○轉讓海洛因一覽表                                  │\n├─┬────┬──────────┬────────────┤\n│編│犯罪時間│犯罪地點            │犯罪手法、對象、毒品種類│\n│號│        │                    │、數量                  │\n├─┼────┼──────────┼────────────┤\n│1 │96年10月│澎湖縣馬公市○○路  │癸○○與辰○○基於犯意之│\n│  │29日    │229號4樓乙○○租屋處│聯絡，轉讓海洛因予乙○○│\n│  │        │                    │。                      │\n├─┼────┼──────────┼────────────┤\n│2 │96年11月│澎湖縣馬公市李子林婦│轉讓海洛因予申○○。    │\n│  │3日     │產科前              │                        │\n├─┼────┼──────────┼────────────┤\n│3 │96年11月│澎湖縣馬公市李子林婦│轉讓海洛因予申○○。    │\n│  │7日     │產科對面            │                        │\n└─┴────┴──────────┴────────────┘\n（三）\n┌──────────────────────────────┐\n│被告癸○○轉讓安非他命一覽表                                │\n├─┬────┬────────┬──────────────┤\n│編│犯罪時間│犯罪地點        │犯罪手法、對象、毒品種類、數│\n│號│        │                │量                          │\n├─┼────┼────────┼──────────────┤\n│1 │96年11月│澎湖縣西嶼鄉外垵│轉讓安非他命予甲○○。（與呂│\n│  │6日     │村慈航寺附近    │光榮互換附表七（二）編號1所 │\n│  │        │                │示之毒品）                  │\n└─┴────┴────────┴──────────────┘\n（四）\n┌──────────────────────────────┐\n│被告癸○○幫助施用海洛因一覽表                              │\n├─┬────┬───────┬───────────────┤\n│編│犯罪時間│犯罪地點      │犯罪手法、對象、毒品種類、數量│\n│號│        │              │及金額（單位：                │\n│  │        │              │新台幣元）                    │\n├─┼────┼───────┼───────────────┤\n│1 │96年11月│澎湖縣馬公市鎖│癸○○自己出資並向翁維昌收取  │\n│  │6日     │港里翁維昌住處│1500元，集資後再由癸○○出面購│\n│  │        │前            │買海洛因1小包後，2人分食之。  │\n├─┼────┼───────┼───────────────┤\n│2 │96年11月│澎湖縣西嶼鄉清│癸○○收取甲○○之2000元後，出│\n│  │13日    │心餐廳前      │面代甲○○購買海洛因1小包後，2│\n│  │        │              │人分食之。                    │\n├─┼────┼───────┼───────────────┤\n│3 │96年11月│澎湖縣馬公市林│癸○○自己出資，並向未○○收取│\n│  │月中旬某│森路、朝陽路口│1000元後，合資由癸○○出面購買│\n│  │日      │              │海洛因1小包後，2人分食之。    │\n└─┴────┴───────┴───────────────┘\n（五）\n┌──────────────────────────────┐\n│被告癸○○幫助施用安非他命一覽表                            │\n├─┬────┬────┬──────────────────┤\n│編│犯罪時間│犯罪地點│犯罪手法、對象、毒品種類、數量及金額│\n│號│        │        │（單位：新台幣元）                  │\n├─┼────┼────┼──────────────────┤\n│1 │96年11月│澎湖縣馬│癸○○向翁丁元收取1000元，代為向陳建│\n│  │10日    │公市中華│榮購買安非他命，購得後交給翁丁元，因│\n│  │        │路翁丁元│翁丁元嫌量不足，翁丁元遂再拿3000元連│\n│  │        │住處    │同原購得之安非他命請癸○○代向辰○○│\n│  │        │        │重新購買，惟辰○○直接將4000元（含原│\n│  │        │        │收取之1000元）連同上開退貨之安非他命│\n│  │        │        │交予癸○○轉交翁丁元，嗣由翁丁元、莊│\n│  │        │        │正和分食上開安非他命。              │\n└─┴────┴────┴──────────────────┘",
  "structure": {
    "main": "原判決關於寅○○、癸○○販賣第一級毒品、巳○○販賣第二級\n毒品及其定執行刑部分均撤銷。\n寅○○販賣第一級毒品，累犯，共計罪，各處有期徒刑拾年\n，行動電話、販毒所得之沒收、抵償均如附表一(二)應沒收之物(1)\n、(2)所示。\n巳○○販賣第二級毒品，共計貳罪，各處有期徒刑貳年捌月，扣\n案之夾鏈袋壹包（內裝小夾鏈袋捌拾陸個）沒收，行動電話、販\n毒所得之沒收、追徵價額、抵償均如附表四(一)應沒收之物(1)、(2)\n）所示。\n癸○○共同販賣第一級毒品，累犯，共計拾罪，各處有期徒刑拾\n壹年貳月，行動電話、販毒所得之沒收、追徵價額、抵償均如附\n表九(一)應沒收之物(1)、(2)所示。\n其他上訴駁回。\n寅○○前開第二項撤銷改判部分與第五項上訴駁回部分（幫助施\n用第一級毒品，累犯，處有期徒刑拾月），應執行有期徒刑拾肆\n年，行動電話、販毒所得之沒收、抵償均如附表一(二)應沒收之物\n(1)、(2)所示。\n巳○○前開第三項撤銷改判部分與第五項上訴駁回部分販賣第一\n級毒品，共計貳罪，各處有期徒刑拾伍年貳月，扣案之夾鏈袋壹\n包（內裝小夾鏈袋捌拾陸個）沒收，行動電話、販毒所得之沒收\n、追徵價額、抵償均如附表四(二)應沒收之物(1)、(2)所示。應執行\n有期徒刑拾伍年月，扣案之夾鏈袋壹包（內裝小夾鏈袋捌拾陸\n個）沒收，行動電話、販毒所得之沒收、追徵價額、抵償均如附\n表四(一)、(二)應沒收之物(1)、(2)所示。\n癸○○前開第四項撤銷改判部分與第五項上訴駁回部分（共同轉\n讓第一級毒品，累犯，處有期徒刑壹年陸月；又轉讓第一級毒品\n，累犯，共計貳罪，各處有期徒刑壹年陸月；又轉讓禁藥，累犯\n，處有期徒刑壹年；又幫助施用第一級毒品，累犯，共計參罪，\n各處有期徒刑捌月；又幫助施用第二級毒品，累犯，處有期徒刑\n肆月）。應執行有期徒刑拾年，行動電話、販毒所得之沒收、\n追徵價額、抵償均如附表九(一)應沒收之物(1)、(2)所示。",
    "fact": "一、寅○○曾因公共危險、過失傷害、竊盜等案件，經法院各判\n    處有期徒刑8 月、3 月、4 月，嗣定應執行刑1 年1 月確定\n    ，於民國94年6 月20日執行完畢，又因詐欺案件，經法院判\n    處有期徒刑4 月確定，於94年11月16日易科罰金執行完畢，\n    猶不知悔改，明知海洛因係毒品危害防制條例第2 條第2 項\n    第1 款所列之第一級毒品，依法不得販賣或施用，竟基於幫\n    助施用第一級毒品海洛因之犯意，於96年10月28日，在澎湖\n    縣馬公市大愛牛排館內與子○○集資，由寅○○向他人購買\n    海洛因2 小包後，2 人分食，幫助子○○施用海洛因1 次；\n    另基於販賣第一級毒品以營利之犯意，以其所有之門號0000\n    000000號、0000000000號行動電話與欲購買海洛因之癸○○\n    、壬○○相互聯繫交易細節後，分別於96年11月4 日、11月\n    16日，在馬公市○○路「都家堡」商店對面、馬公國小旁之\n    統一超商門口、安一山莊前，3 次將海洛因賣予癸○○、壬\n    ○○以牟利（幫助施用、販賣之時、地、手法、對象、毒品\n    種類、數量、金額及應沒收之物，均詳如附表一(一)、(二)）。\n    嗣經警查獲，扣得其所有供犯罪所用之0000000000號、0000\n    000000號行動電話各1 支。寅○○於警詢供出海洛因來源，\n    因而使警方查獲販毒之子○○、乙○○及另案之午○○。\n二、子○○曾於95年間，因賭博案件，經原審判處有期徒刑8 月\n    ，緩刑3 年確定（不構成累犯），猶不知警惕，竟在緩刑期\n    間內，明知海洛因係毒品危害防制條例第2 條第2 項第1 款\n    所列之第一級毒品，依法不得販賣或施用，竟基於幫助施用\n    海洛因之犯意，於96年11月15日邀同未○○集資新台幣（下\n    同）2,000 元（子○○出資500 元，未○○出資1,500 元）\n    ，並由子○○出面購得海洛因1 小包，除其中1/4 留供自己\n    施用外，所餘3/4 於同日14時35分許，在澎湖縣農會生鮮超\n    市門口，交予未○○，嗣由未○○在馬公市某地施用之（未\n    ○○施用毒品部分見附表六編號2 ）；另基於販賣第一級毒\n    品以營利之犯意，於96年11月16日14時許，在澎湖縣馬公市\n    ○○路66號住處，先向寅○○預收2,000 元並允諾販賣等值\n    之海洛因，旋再以其所有之門號0000000000號諾基亞牌行動\n    電話告知寅○○交易地點後，在澎湖縣馬公國小旁統一超商\n    內，交付海洛因1 小包（重0.3 公克）予寅○○（嗣寅○○\n    將該買得之0.3 公克海洛因轉賣予壬○○（見附表一(二)編號\n    3 ）），寅○○為警查獲後，供出海洛因來源為子○○；另\n    由寅○○配合警方辦案，於同日16時35分許，撥打子○○上\n    開手機，與本有販賣第一級毒品犯意之子○○約定交易海洛\n    因之地點，旋子○○持海洛因1 小包，至馬公市○○路66西\n    餐廳附近等候，擬將之販賣予寅○○時，當場為警查獲而未\n    得逞（幫助施用、販賣之時、地、手法、對象、毒品種類、\n    數量、金額及應沒收之物，均詳如附表二(一)、(二)）。嗣經警\n    扣得第一級毒品海洛因1 小包（淨重0.11公克，空包裝重0.\n    33公克）及其所有供犯罪所用之0000000000號行動電話1 支\n    。\n三、申○○明知海洛因、安非他命分屬毒品危害防制條例第2 條\n    第2 項第1 、2 款所列之第一、二級毒品，依法不得販賣或\n    轉讓，竟與辰○○（另由本院通緝中）、癸○○、乙○○或\n    庚○○，共同基於販賣第一級毒品海洛因或第二級毒品安非\n    他命以營利之犯意，持其所有之門號0000000000號行動電話\n    ，或分由庚○○、癸○○持其所有之0000000000號、000000\n    0000號行動電話，與欲購買毒品之人相互聯繫交易細節後，\n    販賣海洛因、安非他命各4 次、3 次；另基於轉讓第一級毒\n    品海洛因之犯意，自96年11月12日起，在澎湖縣馬公市享溫\n    馨KT V等地，轉讓海洛因予陳志盟等人，共計4 次（販賣、\n    轉讓之時、地、手法、對象、毒品種類、數量、金額及應沒\n    收之物，均詳如附表三(一)、(二)、(三)）。\n四、巳○○明知海洛因、安非他命分屬毒品危害防制條例第2 條\n    第2 項第1 、2 款所列之第一、二級毒品，依法均不得販賣\n    ，竟基於販賣第一、二級毒品以營利之犯意，以其所有之門\n    號0000000000號行動電話與欲購買毒品之戊○○、癸○○相\n    互聯繫交易細節，並以夾鏈袋分裝毒品後，分別於96年10月\n    初某日及同年11月6 日，2 次販賣安非他命予戊○○、癸○\n    ○；另於96年11月2 日、同月3 日，2 次販賣海洛因予癸○\n    ○（販賣之時、地、手法、對象、毒品種類、數量、金額及\n    應沒收之物，均詳如附表四(一)、(二)）。嗣經警扣得其所有供\n    販毒分裝毒品所用之夾鏈袋1 包（內裝小夾鏈袋86個）。巳\n    ○○於偵查中，供出安非他命來源，因而使警查獲販賣安非\n    他命之酉○○（另案審理）。\n五、庚○○曾於93年間，因賭博案件，經法院判處有期徒刑3 月\n    確定，於93年11月5 日易科罰金執行完畢，猶不知悔改，明\n    知安非他命屬毒品危害防制條例第2 條第2 項第2 款所列之\n    第二級毒品，依法不得販賣，竟與辰○○、申○○共同基於\n    販賣第二級毒品以營利之犯意，持其所有之門號0000000000\n    號行動電話，或由申○○持其所有之0000000000號行動電話\n    ，與欲購買毒品之人相互聯繫交易細節後，於96年11月10日\n    ，2 次販賣安非他命予歐家雄、丁○○（販賣之時、地、手\n    法、對象、毒品種類、數量、金額及應沒收之物，均詳如附\n    表五）。\n六、未○○曾因違反毒品危害防制條例案件，經法院判處有期徒\n    刑7 月，嗣減為有期徒刑3 月15日確定，於96年7 月17日執\n    行完畢，其明知海洛因係毒品危害防制條例第2 條第2 項第\n    1 款所列之第一級毒品，依法不得施用，竟基於施用海洛因\n    之犯意，自96年11月中旬某日起至同年11月28日止，在澎湖\n    縣馬公市○○路李子林婦產科前等地，施用海洛因4 次（施\n    用之時、地、毒品種類，均詳如附表六）。\n七、甲○○曾因違反毒品危害防制條例案件，分別經臺灣高雄地\n    方法院判處有期徒刑8 月、1 年確定，於93年12月1 日接續\n    執行縮刑期滿執行完畢，猶不知悔改，明知海洛因係毒品危\n    害防制條例第2 條第2 項第1 款所列之第一級毒品，依法不\n    得販賣、轉讓或施用，竟基於販賣第一級毒品以營利之犯意\n    ，以其所有之門號0000000000號行動電話與欲購買海洛因之\n    人相互聯繫交易細節後，自96年8 月5 日11時38分起至同年\n    11月6 日止，在澎湖縣西嶼鄉○○村○○○○○道路等地，\n    分別將海洛因賣予己○○等人牟利，總計販賣11次；另基於\n    轉讓海洛因之犯意，於96年11月6 日，在澎湖縣西嶼鄉外垵\n    村慈航寺附近，轉讓海洛因1 包予癸○○；又基於幫助施用\n    海洛因之犯意，自96年9 月28日18時51分起至同年10月28日\n    21時36分止，在澎湖縣西嶼鄉外垵國小附近等地，以與丙○\n    ○合資購買海洛因，再由甲○○出面拿取海洛因後與丙○○\n    分食之方式，幫助丙○○施用海洛因，共計5 次（販賣、轉\n    讓、幫助施用之時、地、手法、對象、毒品種類、數量、金\n    額及應沒收之物，均詳如附表七(一)、(二)、(三)）。\n八、乙○○明知海洛因、安非他命分屬毒品危害防制條例第2 條\n    第2 項第1 、2 款所列之第一、二級毒品，依法不得販賣、\n    轉讓或施用，竟基於幫助施用海洛因之犯意，於96年9 月底\n    某日，在澎湖縣白沙鄉講美村廟旁，以與寅○○合資購買海\n    洛因，再由乙○○出面拿取海洛因後與寅○○分食之方式，\n    幫助寅○○施用海洛因1 次；另基於販賣第一、二級毒品以\n    營利之犯意（附表八(二)部分與癸○○有犯意聯絡，附表八(三)\n    編號1 部分與辰○○有犯意聯絡，附表八(三)編號3 部分與辰\n    ○○、申○○有犯意聯絡），持其所有之門號0000000000號\n    行動電話，或由癸○○持其所有之0000000000號行動電話，\n    或由申○○持其所有之0000000000號行動電話，與欲購買毒\n    品之人相互聯繫交易細節後，自96年10月12日起至同年月13\n    日止，在澎湖縣馬公市百合民宿，3 次將海洛因賣予丁○○\n    等人牟利，又自96年10月26日起至同年11月6 日止，在澎湖\n    縣馬公市燦坤量販店後方公園等地，3 次將安非他命賣予酉\n    ○○等人牟利；另基於轉讓海洛因之犯意，自96年11月初某\n    日起至同年11月12日止，在其光復路租屋處等地，轉讓海洛\n    因予癸○○等人，共計7 次（販賣、轉讓、幫助施用之時、\n    地、手法、對象、毒品種類、數量、金額及應沒收之物，均\n    詳如附表八(一)、(二)、(三)、(四)）。\n九、癸○○曾因違反毒品危害防制條例案件，經法院定應執行刑\n    判處有期徒刑1 年6 月，嗣減為有期徒刑9 月確定，於96年\n    7 月16日執行完畢，猶不知悔改，明知海洛因、安非他命分\n    屬毒品危害防制條例第2 條第2 項第1 、2 款所列之第一、\n    二級毒品，且安非他命業經中央衛生主管機關行政院衛生署\n    公告列為禁藥管理，屬藥事法第22條第1 項第1 款所規範之\n    禁藥，依法均不得販賣、轉讓或施用，竟基於販賣、轉讓或\n    幫助施用第一、二級毒品之單獨或共同犯意，於附表九(一)時\n    地，持其所有之門號0000000000號行動電話，或由申○○持\n    其所有之0000000000號行動電話，與欲購買海洛因之人相互\n    聯繫交易細節後，販賣海洛因共10次；於附表九(二)、(三)時地\n    ，分別轉讓海洛因、安非他命各3 次、1 次；於附表九(四)、\n    (五)時地，分別幫助他人施用海洛因、安非他命各3 次、1 次\n    （販賣、轉讓、幫助施用之時、地、手法、對象、毒品種類\n    、數量、金額及應沒收之物，均詳如附表九(一)、(二)、(三)、(四)\n    、(五)）。癸○○於警詢時，供出其所販賣海洛因來源，因而\n    使警查獲販毒之乙○○、辰○○及另案審理之金正剛。並於\n    偵查中及本院審理時自白販賣第一級毒品海洛因。\n十、案經澎湖縣政府警察局馬公分局報告、澎湖縣政府警察局移\n    送臺灣澎湖地方法院檢察署檢察官、臺灣澎湖地方法院檢察\n    署檢察官自動檢舉偵查起訴及移送併辦。",
    "reason": "甲、程序部分：\n一、按被告以外之人於偵查中向檢察官所為陳述，除顯有不可信\n    之情況者外，得為證據，刑事訴訟法第159 條之1 第2 項定\n    有明文。又偵查中對被告以外之人所為之偵查筆錄，或被告\n    以外之人向檢察官所提之書面陳述，性質上雖均屬傳聞證據\n    ，惟就該立法理由觀之，係考量現階段刑事訴訟法規定檢察\n    官代表國家偵查犯罪、實施公訴，依法其有訊問被告、證人\n    及鑑定人之權，而實務運作時，檢察官偵查中向被告以外之\n    人所取得之陳述，原則上均能遵守法律規定，鮮少以強暴、\n    脅迫及其他不正之方法取得供述證據，其可信度極高，而有\n    此例外之規定，故除反對被告以外之人於偵查中所為之供述\n    得具有證據能力之一方，已釋明該供述「顯有不可信之情況\n    」之理由外，不宜遽指該被告以外之人於偵查中之陳述不具\n    證據能力。證人未○○於另案（臺灣澎湖地方法院檢察署96\n    年度毒偵字第38號、97年度毒偵字第10號）偵查中所為之陳\n    述，經查未有何不法取供等顯不可信之情況，自有證據能力\n    。\n二、證人寅○○於警詢中之供述屬傳聞證據，雖其於警詢中就有\n    關向被告子○○買受海洛因之供述，與審判中之陳述並非一\n    致，惟寅○○於警詢中之供述係出於其販賣毒品予案外人壬\n    ○○而當場為警查獲，在無可迴避之情勢下進而交待其毒品\n    來源等情，堪認其警詢中之供述具有特別可信之情況，且為\n    證明被告子○○犯罪所必要者，依刑事訴訟法第159 條之2\n    規定，自有證據能力，得為證據。\n三、本判決以下所引用之傳聞證據，被告等及其辯護人於本院審\n    理時，均表示不爭執，且未於言詞辯論終結前聲明異議，本\n    院審酌上開傳聞證據作成時，並無不法之情事，認為適當，\n    依刑事訴訟法第159 條之5 第2 項規定，均有證據能力，得\n    為證據。\n乙、實體部分：原審所列認定事實之理由，本院均予引用。\n壹、被告寅○○部分\n一、訊據上訴人即被告寅○○對於上揭附表一(一)幫助羅智強施用\n    海洛因之犯行，於原審及本院審理時坦承不諱，對於附表一\n    (二)所示交易行為，亦不爭執，惟辯稱：伊係與癸○○、壬○\n    ○分別合資購買毒品後分食之，並非販賣毒品給癸○○及壬\n    ○○云云。\n二、經查：被告寅○○對於附表一(一)犯行之自白，核與證人子○\n    ○於警詢及原審審理中證述之情節相符，堪認屬實。又被告\n    寅○○於96年11月4 日23時28分至23時42分以其所有之門號\n    0000000000號行動電話與癸○○相互聯繫買賣毒品交易細節\n    一情，有監聽譯文附卷可稽（警卷，頁205 ），參諸證人癸\n    ○○於警詢中（97年2 月1 日第4 次調查筆錄，警卷，頁19\n    4~195 ）供稱：「（問：警方提示96年11月4 日17時10分你\n    與寅○○通話譯文（A ：癸○○、B ：寅○○）內容：「A\n    ：晚一點可以麻煩一下嗎？B ：晚一點喔？好啦好啦。」意\n    喻為何？）這是我要寅○○幫我調毒品海洛因，後來我在11\n    月4 日與高文琳每人出500 元共計1,000 元在光復路都家堡\n    外面向寅○○購買毒品海洛因後與高文琳當場在我E6-4712\n    號車上共同施用。」、「（問：警方提示96年11月4 日23時\n    28分、23時31分、23時34分、23時42分，你與寅○○4 通通\n    話譯文（A ：癸○○、B ：寅○○）內容：「A ：阿我拿2,\n    000 塊去還你好了、B ：好啦、那要抓2 尾，我給你秤重一\n    點，那魚啦（土魠）。A ：剩拿1,000 阿馬卡趕一下（快一\n    點）。B ：我在馬公國小，麻煩你來馬公國小7-ELEVEN這。\n    」，意喻為何？）「抓2 尾」是指2000元、「秤重一點」」\n    是寅○○叫我一次買2,000 元他寅○○可用多一點的量（毒\n    品海洛因）給我、「土魠」指的是毒品海洛因、「用漂亮一\n    點啦」是我叫寅○○毒品的量用多一點。96年11月4 日當天\n    跟高文琳在光復路都家堡外向寅○○買1,000 元品海洛因後\n    ，在4 日晚上23時30分左右與高文琳合資以1,000 元在馬公\n    國小7-11超商門口向寅○○買第2 次毒品海洛因，同樣當場\n    在我E6-4712 號車上共同施用。」，於原審審理中亦證稱：\n    「（問：96年11月4 日，有無於馬公市都家堡對面向寅○○\n    買毒品？）有，‧‧‧。」、「（問：你當初買的數量及金\n    錢？）大概是壹仟元。」、「（問：同日是否另於馬公國小\n    旁超市再向他買毒品？）是。」、「（問：這次購買毒品情\n    形如何？）與上次同。」等語，均直指係向被告寅○○購買\n    毒品無誤，並無與被告寅○○合資購買後分食之情事，況被\n    告寅○○於警詢中（97年3 月7 日第5 次調查筆錄，警卷，\n    頁779 ）已自承：「（問：96年11月4 日癸○○是否在光復\n    路都家堡對面以1,000 元向你購買毒品海洛因？）有這件事\n    。」、「（問：96年11月4 日癸○○是否在馬公國小7-11超\n    商以1,000 元向你購買毒品海洛因？）有這件事。」等語，\n    足認被告寅○○確有附表一(二)編號1 、2 之販毒行為。再者\n    ，被告寅○○於警詢中（96年12月10日第2 次調查筆錄，警\n    卷，頁684 ）供稱：「（問：警方於今（16日）下午15時許\n    ，於安一山莊（馬公巿忠孝路105 號）前大馬路埋伏查緝毒\n    品案件時，你是否在場？做何事？）有，我拿一包毒品（海\n    洛因）交給壬○○時被警方查獲。」、「（問：警方當場於\n    壬○○左手查扣之一級毒品海洛因（毛重0.3 公克）是否為\n    你所有？是我交他的。」、「（問：你如何跟壬○○連絡購\n    買毒品？）大約今（16日）14時許，壬○○主動打電話給我\n    叫我幫他調2,000 元的毒品‧‧‧，然後我就連絡壬○○把\n    錢拿到我家門口就交給我，我再幫他連絡購買。」、於原審\n    審理中（98年4 月2 日上午審判筆錄）供稱：「（問：有無\n    在安一山莊前把一包海洛因交給壬○○？）有，‧‧‧，毒\n    品先交給壬○○，壬○○拿了毒品騎了10公尺就被警察查獲\n    ，‧‧‧」，證人壬○○則於警詢中（96年11月16日第1 次\n    調查筆錄，警卷，頁886 ）供稱：「（問：你今（16）日，\n    於何時？何地？是因何事被警方帶回警局製作筆錄？）在96\n    年11月16日15時左右。在馬公巿忠孝路安一飯店前。因購買\n    毒品，被警方帶回。」、「（問：上記時地是何人？購買何\n    種毒品？金額？數量為何？）向寅○○。購買毒品海洛因。\n    購買新台幣2,000 元。1 小包、重量不清楚。」、「（問：\n    你是以何種方式連絡寅○○至上記地點購買毒品海洛因？）\n    我在96年11月16日14時30分以0000000000號行動電話，撥打\n    寅○○所持0000000000號行動電話，連絡寅○○相互約在安\n    一飯店前交易毒品的。」等語，足見被告寅○○亦有附表一\n    (二)編號3 之販毒行為。被告寅○○辯稱：係與癸○○、壬○\n    ○合資購買後分食毒品云云，與上開事證不符，不足採信。\n三、被告寅○○於本院審理中雖聲請傳訊證人壬○○，惟查被告\n    寅○○確有販賣毒品予壬○○之犯行，已至為明確，已如前\n    述，無再調查之必要，爰依刑事訴訟法第163 條之2 第2 項\n    第3 款規定，駁回其聲請，併此明。另證人即共同被告癸\n    ○○於本院審理時雖證述：寅○○有與我一起出資去購買毒\n    品，購買之後一起施用毒品，共向寅○○調毒品2 次，寅○\n    ○都有出資等語（見本院卷二第10、11頁）。與證人癸○○\n    於原審所證述之上開情節不符，顯係事後迴護之詞，自難採\n    為有利於被告寅○○之認定。\n四、參諸有償提供他人毒品可能罹犯毒品危害防制條例相關重罪\n    ，上開被告寅○○交付海洛因並均收取價金之行為，應係有\n    利可圖，否則豈有鋌而走險甘冒罹犯重罪風險之理等情，足\n    見被告寅○○係基於營利意圖，而為附表一(二)所示之3 次販\n    賣海洛因行為，足堪認定。\n五、綜上，被告寅○○確有附表一(一)、(二)所示之幫助施用、販賣\n    海洛因之事實，事證明確，其犯行堪以認定。\n六、核被告寅○○就附表一（一）所為，係犯刑法第30條第1 項\n    、毒品危害防制條例第10條第1 項幫助施用第一級毒品罪；\n    其附表一（二）之所為，均係犯毒品危害防制條例第4 條第\n    1 項販賣第一級毒品罪。又被告寅○○就附表一（一）、附\n    表一（二）編號3 所示犯行，或係與子○○合資購買海洛因\n    後分食之，或係直接販賣海洛因予壬○○，核其此部分所為\n    ，係犯幫助施用第一級毒品罪、販賣第一級毒品罪，公訴人\n    認被告寅○○此部分均係犯轉讓第一級毒品罪，尚有未洽，\n    惟基本社會事實同一，爰變更起訴法條。被告寅○○就上開\n    販賣第一級毒品罪，於警詢時，供出毒品來源，因而使警方\n    破獲同案之被告子○○、乙○○及另案之被告午○○，有其\n    96年11月16日、同年11月23日警詢筆錄在卷可考，亦據證人\n    午○○於原審審理時證述屬實（見原審卷三43頁）。自依毒\n    品危害防制條例第17條第1 項規定減輕其刑。被告以上所犯\n    2 罪，犯意各別，罪名互殊，應予分論併罰。被告寅○○曾\n    因公共危險、過失傷害、竊盜等案件，經法院各判處有期徒\n    刑8 月、3 月、4 月，嗣定應執行刑1 年1 月確定，於94年\n    6 月20日執行完畢，又因詐欺案件，經法院判處有期徒刑4\n    月確定，於94年11月16日易科罰金執行完畢，其於5 年內故\n    意再犯本件有期徒刑以上之罪，為累犯，應加重其刑（死刑\n    、無期徒刑部分不得加重）。附表一（一）之犯行，依刑法\n    第30條第2 項減輕其刑，並先加後減之。被告寅○○無販毒\n    之前科紀錄，而所犯販賣第一級毒品犯行之法定刑為「死刑\n    或無期徒刑；處無期徒刑者，得併科新臺幣1 千萬元以下罰\n    金」，本件其販賣之海洛因，數量非鉅，所得非多，與專門\n    販售毒品之大盤尚難相提並論，犯罪情狀在客觀上可引起一\n    般人之同情，倘科以上開罪名之法定最輕本刑，猶嫌過重，\n    爰就其販賣第一級毒品罪部分，依刑法第59條規定，酌減其\n    刑，並先加後減之。\n七、原審就被告幫助施用第一級毒品罪部分，因而適用刑法第30\n    條，毒品危害防制條例第10條第1 項之規定，並審酌被告犯\n    後坦承犯行，態度良好等一切情狀，量處被告有期徒刑10月\n    。經核原審此部分認事用法並無不合，量刑亦屬適度。被告\n    上訴意旨，指摘原審此部分判決量刑過重不當，為無理由，\n    應予駁回。\n八、原審就被告販賣第一級毒品罪部分予以論科，固非無見，惟\n    查被告於警詢時，已供出毒品來源，並使警方查獲販毒之同\n    案被告子○○、乙○○，及另案被告午○○，已如前述，原\n    審未依毒品危害防制條例第17條第1 項規定，減輕其刑，自\n    有未合。被告上訴意旨，否認犯罪，固無足取，然原審此部\n    分判決既有上述可議，自應由本院將原審此部分判決撤銷改\n    判。審酌被告所犯情節非重，且能供出毒品上源，使警方查\n    獲販毒之子○○、乙○○、午○○等人等一切情狀，量處如\n    主文第2 項所示之刑。並與上訴駁回部分所處有期徒刑10月\n    ，並定其應執行刑有期徒刑14年。扣案之0000000000號、00\n    00000000號行動電話各1 支，均係其所有供犯罪所用之物，\n    應依毒品危害防制條例第19條第1 項之規定宣告沒收。又按\n    販賣毒品所得之對價，不問其中何部分屬於成本，何部分屬\n    於犯罪所得之財物，應均予沒收，此有65年度第5 次刑庭庭\n    推總會議決議意旨可資參照。被告寅○○如附表一（二）所\n    示販毒所得，均應依毒品危害防制條例第19條第1 項之規定\n    沒收，如全部或一部不能沒收時，均以其財產抵償之。扣案\n    之附表一（二）編號3 所示之海洛因1 小包，因已賣予壬○\n    ○，查獲時已在壬○○實力支配下，自毋庸於被告寅○○項\n    下宣告沒收。\n貳、被告子○○部分\n一、訊據上訴人即被告子○○矢口否認有上開幫助施用或販賣第\n    一級毒品海洛因之犯行，辯稱：伊於96年11月15日沒有買到\n    毒品，所以也沒有交毒品給未○○；96年11月16日寅○○是\n    拿2000元償還欠伊之債務，伊並與寅○○在伊家中一起施用\n    毒品，施用所餘之毒品嗣由伊攜至66西餐廳附近擬再次與寅\n    ○○一同施用，惟經警方查扣，伊無幫助施用或販賣海洛因\n    之犯意或行為云云。\n    經查：被告子○○於警詢中（96年12月18日第2 次調查筆錄\n    ，警卷，頁13~15 ）供稱：「（問：你於上述供稱有轉讓海\n    洛因毒品給未○○一次，詳細轉讓方式及時間、地點為何？\n    聯絡方式？）於96年11月13日至15日某日下午約於14時至16\n    日許，他以0932（詳細號碼不詳）之行動電話撥打我持用之\n    0000000000號手機與我聯絡，問我有沒有辦法購買海洛因毒\n    品，我說我要問看看，掛電話後我撥打洪家駒持用之電話00\n    00000000號手機，詢問他有無海因，他答稱有，我隨即再撥\n    打未○○手機聯繫告知我有辦法調到海洛因，就與未○○相\n    約在馬公巿光復路「和興」大飯店門口見面，他拿1500元給\n    我，我出資500 元共計2000元，我當他面撥打給洪家駒告知\n    他向其購買2000元海洛因毒品，相約在澎湖縣農會生鮮超巿\n    門口見面交易購買。我就先行離開騎乘機車到該處等候洪家\n    駒，過了約5 至10分鐘，洪家駒駕駛黑色轎車（台北巿車籍\n    車牌不詳）獨自前來，邀我上車交易，我上車後將2000元交\n    給洪家駒後，他拿一包夾鏈袋裝置之海洛因毒品給我，我就\n    下車騎機車返家先行施用一次約四分之一數量後，再聯絡未\n    ○○到馬公巿「澎湖縣農會生鮮超巿」門口見面（經查詳細\n    時間為96年11月15日14時33分），將剩餘之四分之三海洛因\n    拿給未○○後各自離去。」、「（問：你向洪家駒購買過幾\n    次毒品？分別於何時在何處購買？數量？價錢為何？）‧‧\n    ‧。第一次就是上述洪家駒於96年11月15日，在馬公「澎湖\n    縣農會生鮮超巿」門口見面，以2000元之代價，與未○○合\n    資向其購買海洛因一包（我施用四分之一包、未○○分得四\n    分之三海洛因）。‧‧‧。」，已詳為供述其與共同被告未\n    ○○如何合資購買海洛因後分食等情，核與共同被告未○○\n    於另案（臺灣澎湖地方法院檢察署96年度毒偵字第38號、97\n    年度毒偵字第10號）檢察官偵查時坦認：於96年11月中旬，\n    有與被告子○○合資購買海洛因後，自行施用海洛因1 次等\n    情相符（未○○施用毒品部分詳如後述），被告子○○及證\n    人未○○於原審審理中均翻異前詞，供稱：該次沒有拿到毒\n    品，也沒有施用云云，分屬卸責、迴護之詞，均不足採。被\n    告子○○確有與未○○合資購買海洛因，並由被告子○○出\n    面購買海洛因後交予未○○分食之犯行，堪以認定。又被告\n    子○○於警詢中（96年11月16日第1 次調查筆錄，澎警刑字\n    第0961213551號卷，頁3 、6 ）供稱：「（問：寅○○如何\n    與你聯繫取得海洛因毒品？）。他起先是以0000000000號行\n    動電話撥打我所持有之0000000000行動電話，... 。」、「\n    （問：警方查扣你持有之行動電話是否為你當場與寅○○聯\n    繫毒品交易之手機？）就是這支NOKIA 黑色手機沒錯。」，\n    於96年12月18日檢察官偵查中（96偵749 卷，頁37）供稱：\n    「（問：96年11月16日下午2 點、4 點半左右為何要拿毒品\n    給寅○○？）寅○○一直打電話給我，‧‧‧，後來寅○○\n    就跑到我文光路住處找我，要我幫他調海洛因，並塞了2000\n    元給我，我說等一下，後來我就打電話給洪家駒，那時寅○\n    ○已經先離開。後來洪家駒表示有毒品，我就跟洪家駒拿，\n    洪家駒將毒品送到我家，我再打電話給寅○○到馬小附近的\n    7-11拿毒品。4 點半那一次寅○○又打電話問我是否可以調\n    ，我又打電話給洪家駒，洪家駒直接拿毒品給我，我帶在身\n    上，後來在忠孝路66西餐廳附近等寅○○時就被抓了。」等\n    語，證人寅○○則於警詢中（96年11月16日第1 次調查筆錄\n    ，警卷，頁33~34 ）供稱：「（問：該毒品（即交予壬○○\n    並經警查扣之海洛因）是向何人購買？重量、價值為何？）\n    我是向子○○（經查證：男、69.10.08日，身分證Ｚ0000000\n    00、住馬公巿光明里文光路66號）購買的，重量經警方查證\n    為0.3 公克（毛重），價值2 仟元。」、「（問：你如何與\n    子○○連絡購買毒品事宜？）我先打電話給子○○後問有沒\n    有毒品，他說有，然後他就叫我先錢拿過去他家門口給他，\n    叫我先回去等電話，然後我就先回家（安一山莊前）與壬○\n    ○一起等電話，我們差不多等了一、二十分鐘，他打電話給\n    我叫我到馬公國小旁7-11超商內找他，他就在7-11超商內當\n    場將毒品交給我，當我把該毒品拿回去交給壬○○後就被警\n    方當場查獲。」、於原審審理中供稱：「（問：被警察抓到\n    後，警察有無問你東西哪裡來的？）有，我說向子○○拿的\n    。」、「（問：警察跟你說什麼？）警察叫我再打一次電話\n    給子○○買毒品，叫我引誘他出來。」、「配合警方這次，\n    我在電話中也是跟子○○說我2000元麻煩他幫我調毒品，他\n    有說要拿2000元毒品過來給我」等語，是互核被告子○○、\n    證人寅○○2 人之供述，再參諸扣案之由被告子○○身上扣\n    獲之毒品1 小包（毒品淨重0.11公克，空包裝重0.33公克）\n    及另案由壬○○身上扣獲之0.3 公克毒品，確均屬海洛因無\n    訛，有法務部調查局鑑定書附卷可稽等情，足認被告子○○\n    確有附表二（二）所示販賣海洛因之犯行。被告子○○及證\n    人寅○○於原審審理中供稱：寅○○係清償積欠之債務2000\n    元，該2000元與0.3 公克之海洛因無交易之對價關係及被告\n    子○○辯稱：係持毒品擬與寅○○一同施用而遭查獲云云，\n    均與前揭事證不符，顯係卸責、迴護之詞，均不足採。又寅\n    ○○於96年11月16日配合警方辦案，虛以電話向被告子○○\n    索求毒品前，被告莊智前甫於前一刻之同日14時許販賣海洛\n    因0.3 公克予寅○○，乃被告子○○旋於同日16時35分許，\n    再次慨然應允並攜帶毒品至約定地點等待交付，顯然被告子\n    ○○就此次販賣之行為，本有犯意，尚非出於警方指示寅○\n    ○索藥行為之引誘，此與陷害教唆係使原無犯罪意思之人因\n    唆使而萌生犯意之情形，迥不相侔。\n二、證人即同案被告未○○於本院審理中雖證述：96年11月15日\n    左右，我原本要託子○○去購買毒品，後來我錢不夠，他就\n    不理我，子○○沒有拿毒品給我，我也沒有將錢交給子○○\n    等語（見本院卷二第21頁）。惟查被告子○○確有與未○○\n    合資購買毒品，幫助未○○施用第一級毒品之事，業據證人\n    未○○於警訊及偵查中證述明確。足見證人未○○於本院審\n    理中上開證詞，無非事後迴護之詞，自難採為有利於被告子\n    ○○之認定。另證人即共同被告寅○○於本院審理中雖證述\n    ：96年11月16日14時許，我有拿2 千元還給子○○，請他順\n    便拿一些毒品給我施用。給錢之後約15至20分鐘，他就交毒\n    品一小包約0.3 公克給我，但在電話中沒說要買毒品。第2\n    次被警查獲後，警方要我配合，所以同日16時35分許，我打\n    電話約子○○出來向他購買毒品，但我本身並無購買毒品的\n    意思。惟查證人寅○○第一次向子○○購入毒品之後，立即\n    出售予壬○○，後即被警查獲，寅○○乃配合警方打電話給\n    子○○，要求再次購買毒品，而誘捕子○○等情，已據其於\n    警詢及原審審理證述明確。足見證人寅○○於本院審理時上\n    開證述，無非事後迴護之詞，自難採為有利於被告子○○之\n    認定。\n三、參諸有償提供他人毒品可能罹犯毒品危害防制條例相關重罪\n    ，上開被告子○○於96年11月16日之2 次犯行，或已交付海\n    洛因並收取價金，或持海洛因等候交易而為警查獲，應均有\n    營利之所圖，否則豈有鋌而走險甘冒罹犯重罪風險之理等情\n    ，足見被告子○○係基於營利意圖而販賣海洛因予寅○○，\n    堪以認定。綜上，被告子○○確有如附表二所示幫助施用、\n    販賣海洛因之事實，事證明確，其犯行堪以認定。\n四、核被告子○○就附表二（一）所為，係犯刑法第30條第1 項\n    、毒品危害防制條例第10條第1 項幫助施用第一級毒品罪；\n    其附表二（二）編號1 之所為，係犯毒品危害防制條例第4\n    條第1 項販賣第一級毒品罪；其附表二（二）編號2 之所為\n    ，則係犯毒品危害防制條例第4 條第6 項、第1 項販賣第一\n    級毒品未遂罪。又被告子○○附表二（一）之犯行，係代為\n    合資購買海洛因後，再與未○○分食，核其此部分所為，係\n    犯幫助施用第一級毒品罪，公訴人認被告子○○此部分係犯\n    毒品危害防制條例第8 條第1 項轉讓第一級毒品罪，尚有未\n    洽，惟基本社會事實同一，爰變更起訴法條。被告子○○就\n    上開犯行，犯意各別，行為互殊，應分論併罰。附表二（一\n    ）、附表二（二）編號2 之犯行，應分別依刑法第30條第2\n    項、第25條第2 項減輕其刑。被告子○○無販毒之前科紀錄\n    ，而所犯販賣第一級毒品犯行之法定刑為「死刑或無期徒刑\n    ；處無期徒刑者，得併科新臺幣1 千萬元以下罰金」，本件\n    其販賣之海洛因，數量非鉅，所得非多，與專門販售毒品之\n    大盤尚難相提並論，犯罪情狀在客觀上可引起一般人之同情\n    ，倘科以上開罪名之法定最輕本刑，猶嫌過重，爰就其販賣\n    第一級毒品罪部分，依刑法第59條規定，酌減其刑，附表二\n    （二）編號2 部分並遞減之。\n五、原審因而適用刑法第30條、第25條第2 項、第59條、第51條\n    第5 款，毒品危害防制條例第4 條第1 項、第6 項、第10條\n    第1 項、第18條第1 項前段、第19條第1 項規定，並審酌被\n    告犯後翻異前詞，未見悔意等一切情狀，就被告幫助施用第\n    一級毒品部分量處有期徒刑8 月，就其販賣第一級毒品部分\n    量處有期徒刑15年2 月，就其販賣第一級毒品未遂部分量處\n    有期徒刑8 年，並定其應執行刑有期徒刑16年。並認扣案之\n    0000000000號行動電話1 支，係其所有供犯罪所用之物，應\n    依毒品危害防制條例第19條第1 項之規定宣告沒收。其如附\n    表二（二）編號1 所示販毒所得，應依毒品危害防制條例第\n    19條第1 項之規定沒收，如全部或一部不能沒收時，以其財\n    產抵償之。扣案之附表二（二）編號2 所示之海洛因1 小包\n    ，應依毒品危害防制條例第18條第1 項前段之規定，宣告沒\n    收並銷燬之。至扣案子○○所有之夾鏈袋16個及吸管分裝器\n    1 支，尚無證據顯示係屬其供犯罪所用之物，爰不宣告沒收\n    。經核原判決認事用法並無不合，量刑亦屬適度，被告子○\n    ○上訴意旨，仍執前詞，否認犯罪，指摘原判決不當，為無\n    理由，應予駁回。\n參、被告申○○部分\n一、訊據上訴人即被告申○○對於附表三（三）轉讓海洛因之事\n    實，於本院審理時坦承不諱，對於附表三（一）、（二）之\n    交易行為，雖不爭執，惟矢口否認有販賣第一、二級毒品之\n    犯行辯稱：無販賣毒品之犯意云云。\n    經查：被告申○○自白附表三（三）之犯行，核與證人癸○\n    ○、陳志盟、翁丁元於警詢或原審審理中證述之情節相合。\n    又被告申○○關於附表三（一）、（二）之犯行，亦據證人\n    辰○○、乙○○、庚○○、丑○○、歐家雄、丁○○、癸○\n    ○、甲○○、午○○於警詢或原審審理中供證屬實。參諸被\n    告申○○於警詢中（96年12月17日第3 次筆錄，澎警刑字第\n    0971213122號警卷，頁346 、97年1 月28日第5 次筆錄，澎\n    警刑字第0971213122號警卷，頁418~419 ）供稱：「（問：\n    為何辰○○等人有毒品過來澎湖都會找你過去幫忙調配、分\n    裝？且是由癸○○、乙○○等人在負責連絡你？）乙○○本\n    來跟癸○○就熟識，李早知我跟癸○○施打毒品大都我在出\n    錢，所以有意思叫我要過去買，因為我到安一山莊協助分裝\n    毒品時，辰○○有向我們在場人提到如果幫他賣掉1 小包毒\n    品海洛因（新台幣1000元計），我們就可從中獲取新台幣20\n    0 元利潤。後來因調配失敗，所分裝之毒品又被在場協助分\n    裝的寅○○搶走了，所以根本沒東西可拿。」、「（問：你\n    是否在96年9 至10月間就知道乙○○、癸○○要幫忙辰○○\n    賣毒品的事？是否曾親自答應癸○○可以協助一同販賣？）\n    是的。沒有什麼親自答應，只是癸○○約我要去哪賣毒品或\n    叫我拿毒品給午○○、甲○○，或向午○○、甲○○收取賣\n    毒品的錢時，我不會反對沒去。」等語，顯然早知共同被告\n    辰○○、癸○○、乙○○等人有販賣毒品之情事，乃於附表\n    三（一）、（二）所示時地，協助辰○○、癸○○、乙○○\n    、庚○○為毒品交易之電話聯絡、交付毒品或收取金錢之行\n    為，顯有與渠等共同販毒之犯意聯絡及行為分擔，被告申○\n    ○辯稱：伊無販賣毒品之犯意云云，尚非可採。\n二、綜上，被告申○○確有附表三（一）、（二）、（三）所示\n    之販賣或轉讓海洛因、安非他命之事實，事證明確，其犯行\n    堪以認定。\n三、核被告申○○就附表三（一）所為，均係犯毒品危害防制條\n    例第4 條第1 項販賣第一級毒品罪；其附表三（二）之所為\n    ，均係犯毒品危害防制條例第4 條第2 項販賣第二級毒品罪\n    ；其附表三（三）之所為，則均係犯毒品危害防制條例第8\n    條第1 項轉讓第一級毒品罪。其就附表三（一）、（二）之\n    犯行，分別與辰○○、癸○○、乙○○或庚○○有犯意之聯\n    絡及行為之分擔，均屬共同正犯。其就上開犯行，犯意各別\n    ，行為互殊，應分論併罰。被告申○○無販毒之前科紀錄，\n    而所犯販賣第一、二級毒品犯行之法定刑分別為「死刑或無\n    期徒刑；處無期徒刑者，得併科新臺幣1 千萬元以下罰金」\n    、「無期徒刑或7 年以上有期徒刑，得併科新臺幣7 百萬元\n    以下罰金」，本件其販賣之海洛因、安非他命，數量非鉅，\n    所得非多，與專門販售毒品之大盤尚難相提並論，犯罪情狀\n    在客觀上可引起一般人之同情，倘科以上開罪名之法定最輕\n    本刑，猶嫌過重，爰就其販賣第一、二級毒品罪部分，均依\n    刑法第59條規定，酌減其刑。\n四、原審因而適用毒品危害防制條例第4 條第1 項、第2 項、第\n    8 條第1 項、第19條第1 項、刑法第28條、第59條、第51條\n    第5 款之規定，並審酌被告犯後坦承部分犯行，態度尚佳等\n    一切情狀，就被告販賣第一級毒品，共4 罪，各處有期徒刑\n    15年2 月；就販賣第二級毒品部分，共3 罪，各處有期徒刑\n    3 年8 月，就其轉讓第一級毒品共3 罪，各處有期徒刑1 年\n    6 月，並定其應執行刑有期徒刑16年。並認未扣案之000000\n    0000號、0000000000、0000000000號行動電話各1 支，分屬\n    被告申○○、共犯癸○○、庚○○所有供犯罪所用之物，應\n    依毒品危害防制條例第19條第1 項之規定沒收，如全部或一\n    部不能沒收時，均追徵其價額或以其財產抵償之。又共同正\n    犯之犯罪所得，因係合併計算，為避免執行時發生重複沒收\n    之情形，故各共同正犯之間係採連帶沒收主義，於裁判時僅\n    諭知連帶沒收，不得就全體共同正犯之總所得，對各該共同\n    正犯分別重複諭知沒收，有最高法院95年度台上字第1781號\n    判決要旨可資參照。被告申○○如附表三（一）、（二）所\n    示販毒所得，應依毒品危害防制條例第19條第1 項之規定與\n    辰○○、癸○○、庚○○等人連帶沒收，如全部或一部不能\n    沒收時，均以其財產抵償之。至扣案申○○所有之手機2 支\n    （均含SIM 卡），尚無證據顯示係屬其供犯罪所用之物，爰\n    不宣告沒收。經核原審此部分判決認事用法並無不合，量刑\n    亦屬適度，被告上訴意旨，或否認犯罪，或指摘原審此部分\n    判決量刑過重不當，為無理由，應予駁回。\n肆、被告巳○○部分\n一、訊據被告巳○○對於附表四（一）（二）所示交付毒品之行\n    為，均坦承不諱，惟矢口否認有販賣第一、二級毒品之犯意\n    ，辯稱：伊無販賣之營利犯意，祇是幫朋友調毒品云云。\n二、經查：被告巳○○對於附表四（一）（二）等事實之供述，\n    核與證人戊○○於警詢（96年12月18日第1 次調查筆錄，00\n    00000000號警卷，頁15）、證人癸○○於警詢（97年2 月1\n    日第4 次調查筆錄，警卷，頁186 、190 －192 、97年3 月\n    18日對質筆錄，警卷，頁1110、97年3 月19日對質筆錄，警\n    卷，頁1126）及原審審理中之證述相符，並有監聽譯文（96\n    年11月2 日1744~2035 時譯文，警卷，頁199 、96年11月3\n    日06時06分譯文，警卷，頁203 、96年11月7 日1929時、96\n    年11月10日1633時譯文，警卷，頁204 ）附卷可稽，足見被\n    告巳○○確以其所有之門號0000000000號行動電話與欲購買\n    安非他命、海洛因之戊○○、癸○○相互聯繫交易細節後，\n    於附表四（一）（二）之時、地，分別販賣安非他命及海洛\n    因。\n三、被告巳○○販賣予戊○○、癸○○之毒品安非他命，係向其\n    上線酉○○所購入等情，業據證人酉○○於本院審理時證述\n    明確（見本院卷二第12、13頁）。被告巳○○於偵查中供出\n    其販賣毒品之來源，使警方因而查獲販毒之酉○○，自得依\n    毒品危害防制條例第17條第1 項規定。至於被告巳○○另稱\n    ：伊販賣之安非他命亦向卯○○購入云云。然查證人卯○○\n    於本院審理時結稱：我並沒有和巳○○交易過毒品，我本身\n    沒有在販毒，也沒有因販毒被警方偵辦過等情（見本院卷二\n    第15、16頁）。另辯護人詰問證人辛○○「（於96年11月2\n    、3 日在澎湖縣光復路飯店內，巳○○稱有向人拿安非他命\n    ，當時你有否在場？看到情形如何？）我不知道日期，我有\n    在場，巳○○接到電話後，就向飯店內一位叫「志哥」的人\n    拿東西，我看到白白一包應該是海洛因，巳○○拿1 千元給\n    志哥。」「（97年3 月19日警訊筆錄上所附卯○○的照片，\n    「志哥」是否照片上之個人？）我無法確定，因為時間已經\n    很久。」（見本院卷二第7 、8 頁）。是證人辛○○之上開\n    證詞，亦難採為有利於被告巳○○，從而，被告巳○○上開\n    指稱，尚屬無據，併此明。\n四、參諸有償提供他人毒品可能罹犯毒品危害防制條例相關重罪\n    ，上開被告巳○○交付毒品或收取價金之行為，應係有利可\n    圖，否則豈有鋌而走險甘冒罹犯重罪風險之理等情，足見其\n    係基於營利意圖，而為附表四（一）（二）所示之販賣毒品\n    行為，被告巳○○辯稱：無營利之意思云云，不足採信。證\n    人戊○○於本院證述係請巳○○幫忙買等語，亦不足為被告\n    巳○○未從中獲利之有利證明。\n五、綜上，被告巳○○確有附表四（一）、（二）所示之販賣安\n    非他命、海洛因之事實，事證明確，其犯行堪以認定。\n六、核被告巳○○就附表四（一）所為，均係犯毒品危害防制條\n    例第4 條第2 項販賣第二級毒品罪，被告於偵查中供出毒品\n    來源，使警方破獲販毒者酉○○，已如前述，應依同條例第\n    17條第1 項規定，減輕其刑，其附表四（二）之所為，均係\n    犯毒品危害防制條例第4 條第1 項販賣第一級毒品罪。其就\n    上開犯行，犯意各別，行為互殊，應分論併罰。被告巳○○\n    無販毒之前科紀錄，而所犯販賣第一、二級毒品犯行之法定\n    刑分別為「死刑或無期徒刑；處無期徒刑者，得併科新臺幣\n    1 千萬元以下罰金」、「無期徒刑或7 年以上有期徒刑，得\n    併科新臺幣7 百萬元以下罰金」，本件其販賣之海洛因、安\n    非他命，數量非鉅，所得非多，與專門販售毒品之大盤尚難\n    相提並論，犯罪情狀在客觀上可引起一般人之同情，倘科以\n    上開罪名之法定最輕本刑，猶嫌過重，爰就其販賣第一、二\n    級毒品罪部分，均依刑法第59條規定，酌減其刑。被告販賣\n    第二級毒品罪部分，依法遞減之。\n七、原審就被告販賣第一級毒品部分，因而適用毒品危害防制條\n    例第4 條第1 項、刑法第59條、第51條第5 款之規定，並審\n    酌被告已坦承部分犯行，態度尚佳等一切情狀，就其販賣第\n    一級毒品，共2 罪，各處有期徒刑15年2 月。並認扣案之夾\n    鏈袋壹包（內裝小夾鏈袋捌拾陸個）沒收，行動電話、販毒\n    所得之沒收、追徵價額、抵償均如附表四（二）應沒收之物\n    （1 ）、（2 ）所示。經核原審此部分判決認事用法並無不\n    合，量刑尚屬適度，被告上訴意旨，仍執前詞，否認犯罪，\n    指摘原審此部分判決不當，為無理由，應予駁回。\n八、原審就被告販賣第二級毒品部分予以論科，固非無見，惟被\n    告於偵查中，已供出安非他命來源，因而使警方破獲安非他\n    命之酉○○，有其97年3 月17日偵查筆錄（見97年偵字第16\n    7 號卷第6 頁）在卷可稽。並證據人酉○○於偵查中及本院\n    審理時證述屬實（見同上卷第6 頁及本院卷二第12、13頁）\n    。原審未依毒品危害防制條例第17條第1 項規定減輕其刑，\n    自有未合。被告上訴意旨，否認犯罪，固無足取，然原審此\n    部分判決既有上述可議，自應由本院將原審此部分判決及其\n    定執行刑撤銷改判。審酌被告於偵查中坦承犯行，並供出毒\n    品來源，使警方查獲販毒之酉○○等一切情狀，就其所犯販\n    賣第二級毒品，共2 罪，各處有期徒刑2 年8 月。並與其上\n    訴駁回所處販賣第一級毒品，共2 罪，各處有期徒刑15年2\n    月，並定其應執行刑有期徒刑15年3 月。未扣案之00000000\n    00號行動電話1 支，屬其所有供犯罪所用之物，應依毒品危\n    害防制條例第19條第1 項之規定沒收，如全部或一部不能沒\n    收時，追徵其價額或以其財產抵償之。附表四（一）、（二\n    ）所示販毒所得，應依毒品危害防制條例第19條第1 項之規\n    定沒收，如全部或一部不能沒收時，均以其財產抵償之。扣\n    案之夾鏈袋1 包（內裝小夾鏈袋86個）係被告巳○○所有供\n    犯罪所用之物，應依刑法第38條第1 項第2 款，宣告沒收。\n    至扣案之海洛因（毛重0.2 公克）、安非他命（毛重2 克）\n    及注射針筒1 支，均係供被告巳○○吸毒所用之物，已據其\n    於原審97年度訴字第1 號案件中供述在卷，該等物品與其販\n    毒犯行無涉，爰不另宣告沒收。\n伍、被告庚○○部分：\n一、訊據被告庚○○矢口否認有何販賣毒品犯行，辯稱：伊無販\n    賣之營利犯意或行為云云。\n二、經查：被告庚○○於警詢中（97年1 月3 日第2 次調查筆錄\n    ，警卷，頁447~448 、97年1 月3 日第2 次調查筆錄，警卷\n    ，頁448 ）供稱：「（問：96年11月10日20時25分，申○○\n    是否曾撥打你0000000000號電話告訴你歐家雄要毒品，電話\n    中你叫蔡到乙○○家拿，後來歐家雄是否與你連絡？由何人\n    販賣何種毒品給歐家雄？）確實有這件事情。當天申○○沒\n    來，是歐家雄打我電話，我跟辰○○說過後我與辰○○一同\n    前往馬公國中大門前，由辰○○親自把毒品安非他命賣給歐\n    家雄。」、「（問：你因故於96年11月10日23時10以電話告\n    知申○○「那裡就是用那個拿5 （碰掉）」，他（指歐家雄\n    ）說你之前有欠一個2 的。）這就是歐家雄沒拿錢給辰○○\n    原因，因為當天歐家雄跟我說申○○有欠他（歐家雄）錢，\n    歐跟辰○○說要抵申○○所欠的錢，辰○○才叫我打電話問\n    申○○。」、「（問：申○○是否曾於96年11月11日00時18\n    分撥打你0000000000號電話告訴你丁○○要買毒品？‧‧‧\n    ）‧‧‧，我確實有跟辰○○到中興國小旁7-11超商前找申\n    ○○、綽號「鳥嶼老仔」丁○○、及林另一位我不認識的朋\n    友，辰○○也確實有拿1 小包毒品安非他命給丁○○，辰○\n    ○上車後有跟我提到丁○○沒有付錢。」等語，核與證人辰\n    ○○、申○○、歐家雄、丁○○於警詢或原審審理中證稱：\n    上開2 次行為被告庚○○均有參與電話聯絡或交付毒品等語\n    大致相符，且有96年11月11日00時18分電話監聽譯文（警卷\n    ，頁389 ）附卷可稽。參諸被告庚○○於警詢中（97年1 月\n    3 日第2 次筆錄，澎警刑字第0971213122號警卷，頁448 、\n    97 年1月31日第4 次筆錄，澎警刑字第0971213122號警卷，\n    頁478 ）供稱：「（問：你與陳（建榮）施用之毒品來源為\n    何（請詳述購買時地與金額）？）毒品來源有些是辰○○免\n    費提供，‧‧‧」、「（問：96年10月間居住於乙○○家目\n    的為何？期間是否曾參與協助辰○○、乙○○、申○○、癸\n    ○○、寅○○等人販賣毒品行為？）方便向辰○○購買毒品\n    。‧‧‧，會在安一山莊幫辰○○分裝毒品是因為辰○○常\n    會提供免費毒品讓我施用，‧‧‧」等語，堪認其早知共同\n    被告辰○○等人有販賣毒品之情事，乃於附表五協助辰○○\n    、申○○為毒品交易之電話聯絡、交付毒品等行為，顯有與\n    渠等共同販賣之犯意聯絡及行為分擔，被告庚○○辯稱：係\n    辰○○1 人販毒，伊無與他人共同販賣毒品云云，尚非可採\n    。\n三、綜上，被告庚○○確有附表五所示之販賣安非他命之事實，\n    事證明確，其犯行堪以認定。\n四、核被告庚○○就附表五所為，均係犯毒品危害防制條例第4\n    條第2 項販賣第二級毒品罪。其就附表五之犯行，均分別與\n    辰○○、申○○有犯意之聯絡及行為之分擔，均屬共同正犯\n    。其就上開犯行，犯意各別，行為互殊，應分論併罰。被告\n    庚○○曾於93年間，因賭博案件，經法院判處有期徒刑3 月\n    確定，於93年11月5 日易科罰金執行完畢，其於5 年內故意\n    再犯本件有期徒刑以上之罪，為累犯，應加重其刑（無期徒\n    刑部分不得加重）。被告庚○○無販毒之前科紀錄，而所犯\n    販賣第二級毒品犯行之法定刑為「無期徒刑或7 年以上有期\n    徒刑，得併科新臺幣7 百萬元以下罰金」，本件其販賣之安\n    非他命，數量非鉅，所得非多，與專門販售毒品之大盤尚難\n    相提並論，犯罪情狀在客觀上可引起一般人之同情，倘科以\n    上開罪名之法定最輕本刑，猶嫌過重，爰就其販賣第二級毒\n    品犯行，均依刑法第59條規定，酌減其刑，並先加後減之。\n五、原審因而適用毒品危害防制條例第4 條第2 項、第19條第1\n    項、刑法第28條、第47條第1 項、第51條第5 款之規定，並\n    審酌被告大部分坦承犯行，所犯情節非重等一切情狀，就其\n    所犯販賣第二級毒品2 罪，各量處有期徒刑3 年8 月，並定\n    其應執行刑有期徒刑4 年。並認未扣案之0000000000號、00\n    00000000號行動電話各1 支，分屬共犯申○○、被告庚○○\n    所有供犯罪所用之物，應依毒品危害防制條例第19條第1項\n    之規定沒收，如全部或一部不能沒收時，均追徵其價額或以\n    其財產抵償之。被告庚○○如附表五編號2 所示販毒所得，\n    應依毒品危害防制條例第19條第1 項之規定，與辰○○、申\n    ○○連帶沒收，如全部或一部不能沒收時，以其財產抵償之\n    。經核原審此部分判決認事用法並無不合，量刑亦屬適度，\n    被告上訴意旨，仍執前詞，否認犯罪，指摘原審此部分判決\n    不當，為無理由，應予駁回。\n陸、被告未○○部分\n一、訊據被告未○○對於附表六編號1 、3 、4 施用第一級毒品\n    海洛因之犯行，坦承不諱，惟矢口否認有何編號2 之施用毒\n    品犯行，辯稱：該次拿錢給被告子○○去調毒品，但子○○\n    沒調到，伊沒有拿到毒品，所以也沒有施用云云。\n二、經查：被告未○○對於附表六編號1 、3 、4 犯行之自白，\n    核與證人癸○○（97年1 月31日第2 次調查筆錄，警卷，頁\n    1238、97年3 月18日對質筆錄，警卷，頁1257~1258 ）、翁\n    維昌（97年3 月21日第1 次調查筆錄，警卷，頁1153）、己\n    ○○（對質筆錄，警卷，頁1259~1260 ）於警詢中或本院審\n    理中之供述相符，堪認屬實。又被告未○○於警詢中自承（\n    96年11月16日第4 次調查筆錄，警卷頁28~29 ）：「（問：\n    於96年11月15日下午約於14時至16時許，你是否以0932之行\n    動話撥打子○○持用之0000000000號手機，並問他有沒有辦\n    法購買海洛因毒品，事後他就與你相約在馬公巿光復路「和\n    興」大飯店門口見面，你拿1500元給他，子○○另出資500\n    元共計2000元，他購買毒品後，約你於96年11月15日14時33\n    分，到馬公巿「澎湖縣農會生鮮超巿」門口見面，將剩餘之\n    四分之三海洛因毒品拿給你後，雙方才各自離去？）‧‧‧\n    。於上述時、地，子○○有將海洛因毒品拿給我後，雙方才\n    各自離去沒錯。」等語，又於另案（臺灣澎湖地方法院檢察\n    署96年度毒偵字第38號、97年度毒偵字第10號）檢察官偵查\n    時坦認：於96年11月中旬，有與被告子○○合資購買海洛因\n    後，自行施用海洛因1 次等情，而共同被告子○○亦於警詢\n    中供稱該次確與未○○合資購買毒品後，由子○○施用1/ 4\n    ，所餘3/4 在澎湖縣農會生鮮超巿門口交予未○○等語（96\n    年12月18日警詢第2 次調查筆錄，警卷，頁13~15 ，參見上\n    開被告子○○部分理由欄），足見被告未○○確有與子○○\n    合資購買海洛因後，自行施用海洛因1 次之犯行，被告未○\n    ○及證人子○○於原審審理中均翻異前詞，供稱：該次沒有\n    拿到毒品，也沒有施用云云，分屬卸責、迴護之詞，均不足\n    採。\n三、被告雖又辯稱：附表六施用海洛因之犯行，業經檢察官緩起\n    訴處分在案，自不得再對其起訴云云。惟查被告未○○附表\n    六所示犯行併同其他施用海洛因犯行，固曾經臺灣澎湖地方\n    法院檢察署96年度毒偵字第38號、97年度毒偵字第10號於97\n    年3 月5 日為緩起訴處分，緩起訴期間為1 年在案。然本件\n    檢察官係另以發現新事實、新證據為由（即原審已另諭知被\n    告無罪確定部分），自得於緩起訴期間內就同一案件逕行起\n    訴，原緩起訴處分並因此而失效力（最高法院94年度台非字\n    第215 號判決參照）。從而，被告所辯上情，自無可取。綜\n    上所述，本件事證明確，被告之犯行，堪以認定。\n四、核被告未○○就附表六所為，均係犯毒品危害防制條例第10\n    條第1 項施用第一級毒品罪。其持有毒品之行為為施用之行\n    為所吸收，不另論罪。其就上開犯行，犯意各別，行為互殊\n    ，應分論併罰。又被告未○○曾因違反毒品危害防制條例案\n    件，經法院判處有期徒刑7 月，嗣減為有期徒刑3 月15日確\n    定，於96年7 月17日執行完畢，其於5 年內故意再犯本件有\n    期徒刑以上之罪，為累犯，應加重其刑。又施用毒品具成癮\n    性，其戒除本屬不易，現行各地方法院檢察署毒品減害計劃\n    之戒癮療程法，目的即在積極協助吸毒者戒除毒癮，本件被\n    告未○○施用毒品之行為，前經臺灣澎湖地方法院檢察署96\n    年度毒偵字第38號、97年度毒偵字第10號於97年3 月5 日為\n    緩起訴處分，命令被告接受美沙冬替代療法，而被告在緩起\n    訴期間內已積極履行檢察官所命處遇措施，顯見本件被告未\n    ○○所為附表六施用海洛因之犯行，情有可憫，爰依刑法第\n    59條規定，減輕其刑，並先加後減之。\n五、原審因而適用毒品危害防制條例第10條第1 項、第41條、第\n    47條第1 項、第59條、第51條第5 款之規定，並審酌被告犯\n    後大致坦承犯行，態度尚佳等一切情狀，就被告所犯施用第\n    一級毒品4 罪，各處有期徒刑4 月，並定其應執行刑有期徒\n    刑5 月，並諭知如易科罰金，以新臺幣1 千元折算1 日。經\n    核原審此部分判決認事用法並無不合，量刑亦屬適度。被告\n    上訴意旨，仍執前詞，指摘原審此部分判決不當，為無理由\n    ，應予駁回。\n柒、被告甲○○部分\n一、訊據上訴人即被告甲○○對於附表七（一）編號1-4 、6 、\n    7-10、附表七（二）及附表七（三）所示之交易毒品行為，\n    均坦承不諱，惟矢口否認有販賣第一級毒品之犯行，辯稱：\n    伊並無販賣毒品之營利犯意云云。惟查上開事實，業據證人\n    己○○、申○○、寅○○、癸○○、乙○○、庚○○、丙○\n    ○、丁○○於警詢或本院審理中之證述甚詳，並有通訊監察\n    譯文表（警卷，頁176 、222 ）附卷可稽。\n二、被告甲○○雖辯稱：附表七（一）編號5 之時地，伊係與癸\n    ○○、申○○合資後，由伊向許晉曄購買毒品後，與癸○○\n    、申○○分食云云。惟被告甲○○於警詢中（97年3 月5 日\n    第5 次調查筆錄，警卷，頁697 ）自承：96年9 月底至10月\n    初某日晚上約19至20時許，在西嶼鄉外垵村「慈航寺」前路\n    口處，係由癸○○撥打伊持用之000000000 號手機，欲向伊\n    調買海洛因，伊要癸○○於該處等候，伊並打給許晉曄聯絡\n    ，嗣伊到外垵村「藍語」網咖前路口，拿取以夾鏈袋裝妥數\n    量約1000元之海洛因後，前往「慈航寺」前路口處交給癸○\n    ○並收取現金1000元，且申○○也在場等語，核與證人申○\n    ○、癸○○於警詢或原審審理中均供稱：係向被告甲○○購\n    買毒品等語相符，足認被告甲○○有附表七（一）編號5 之\n    犯行。被告甲○○辯稱：未販賣毒品，係合資向許晉曄購買\n    云云，尚非可採。又被告甲○○另辯稱：附表七（一）編號\n    11之時地，係由丁○○與癸○○交易毒品，伊僅在場，伊未\n    販賣毒品云云。惟證人癸○○已於警詢（97年1 月25日第3\n    次調查筆錄，警卷，頁16 7）供稱：「（問：警方提示96年\n    11月6 日20時35分你與申○○通話譯文內容：「A ：我們剛\n    上去、我們5 個人拿3 支。B ：阿他那東西跟下午拿的差很\n    多、阿「維昌」呢？A ：「維昌」吹去阿」意喻為何？）我\n    在向申○○談跟甲○○買毒品的情形。因為96年11月06日下\n    午我跟高文琳2 人一同去外垵村慈航寺向甲○○購買2000元\n    毒品海洛因施用後，覺得甲○○賣的毒品數量跟品質很不錯\n    ，所以晚上我又跟翁維昌、高文琳、乙○○、庚○○5 人合\n    資由我開車載他們（翁維昌沒上去只是將1500元寄放我這由\n    我幫翁買下來）再上去跟甲○○購買3000元毒品海洛因，\n    ... 。」，又於原審審理中（原審98年4 月1 日審判筆錄）\n    供稱：「這次有跟甲○○買海洛因」、「（問：（提示警券\n    176 頁譯文）這段譯文什麼意思？）我想起來了，我是跟甲\n    ○○聯絡，甲○○跟我見面說東西是丁○○的，他說他沒有\n    東西。」等語，且有96年11月6 日20時35分電話監聽譯文（\n    警卷，頁176 ）附卷可稽，足認被告甲○○有附表七（一）\n    編號11之犯行。被告甲○○辯稱：未販賣毒品，係丁○○賣\n    的云云，亦非可採。\n三、被告甲○○另於警詢中自承：伊持所有之0000000000號手機\n    與己○○、癸○○等人約定交易時間、地點等後，再完成交\n    易；參諸有償提供他人毒品可能罹犯毒品危害防制條例相關\n    重罪，上開被告甲○○11次交付海洛因並均收取價金之行為\n    ，應係有利可圖，否則豈有鋌而走險甘冒罹犯重罪風險之理\n    等情，足見被告甲○○係基於營利意圖，以上開手機聯絡毒\n    品交易事宜，而有附表七（一）所示之11次販賣海洛因行為\n    ，足堪認定。被告辯稱：伊無販賣毒品之營利犯意云云，顯\n    係卸責之詞，不足採信。證人即同案被告癸○○於本院審理\n    時雖證述：96年11、12月間，曾拜託甲○○調毒品，幾次已\n    忘記了。調毒品之金額大約都在1 、2 千元。請甲○○調毒\n    品，並沒有給酬勞，因為朋友之間平常就有在請客等語（見\n    本院卷二第11、12頁）。然與證人癸○○於警詢及原審審理\n    證述其係向甲○○購買毒品之情節不符，顯係事後迴護之詞\n    ，自難採為有利於被告甲○○之認定。\n四、綜上所述，本件事 證明確，被告甲○○確有附表七（一）\n    、（二）、（三）之犯行，均堪認定。\n五、核被告甲○○就附表七（一）所為，均係犯毒品危害防制條\n    例第4 條第1 項販賣第一級毒品罪；其附表七（二）之所為\n    ，係犯毒品危害防制條例第8 條第1 項轉讓第一級毒品罪；\n    其附表七（三）所為，均係犯刑法第30條第1 項、毒品危害\n    防制條例第10條第1 項幫助施用第一級毒品罪。又被告甲○\n    ○就附表七（二）、（三）所示犯行，或係與他人互換毒品\n    ，難認有何圖利之販賣情事，或係代為合資購買毒品後，再\n    與丙○○分食，並非轉讓、販賣毒品，核其此部分所為，係\n    犯轉讓、幫助施用第一級毒品罪，公訴人認被告甲○○此部\n    分係犯販賣、轉讓第一級毒品罪，均有未洽，惟基本社會事\n    實同一，爰變更起訴法條。公訴人雖認被告甲○○與案外人\n    許晉曄就附表七（一）編號1 至6 之犯行，係屬共同正犯。\n    惟查證人己○○於附表七（一）編號1 至4 、6 之時間，係\n    直接以手機與被告甲○○為交易毒品之聯絡，此有電話監聽\n    譯文附卷可稽，又附表七（一）編號5 之犯行，亦係由證人\n    癸○○直接與被告甲○○洽談後交易，有如上述（證人癸○\n    ○、申○○於另案澎湖地檢署97年度偵字第904 號偵查中亦\n    同此證述），雖被告甲○○供稱：該6 次犯行伊都是替許晉\n    曄販賣云云，惟販賣毒品者或有為弱化自己販賣毒品重責而\n    推諉主要責任予毒品提供者之動機，亦即被告甲○○之供述\n    充其量僅能認為其供出毒品來源為案外人許晉曄，尚不能遽\n    以認定案外人許晉曄為屬共犯，又證人己○○於警詢或原審\n    審理中固供稱：有時係由許晉曄親自交付毒品給伊云云，惟\n    參諸被告甲○○另於原審審理中供稱：許晉曄與己○○有金\n    錢糾紛，己○○不便與許晉曄聯繫，才透過伊聯絡許晉曄買\n    賣毒品等語，衡情案外人許晉曄即無可能再與己○○有所接\n    觸，遑論直接交付毒品與己○○，是證人己○○此部分之供\n    述，非無可疑，不能遽採。本件被告甲○○就附表七（一）\n    編號1 至6 之犯行，既查無其他證據足資認定案外人許晉曄\n    有共同參與之情事，公訴人遽認許晉曄係屬共同正犯，自有\n    未洽。被告甲○○就上開犯行，犯意各別，行為互殊，應分\n    論併罰。被告甲○○曾因違反毒品危害防制條例案件，分別\n    經臺灣高雄地方法院判處有期徒刑8 月、1 年確定，於93年\n    12月1 日接續執行縮刑期滿執行完畢，其於5 年內故意再犯\n    本件有期徒刑以上之罪，為累犯，應加重其刑（死刑、無期\n    徒刑部分不得加重）。附表七（三）之犯行，依刑法第30條\n    第2 項減輕其刑，並先加後減之。被告甲○○無販毒之前科\n    紀錄，而所犯販賣第一級毒品犯行之法定刑為「死刑或無期\n    徒刑；處無期徒刑者，得併科新臺幣1 千萬元以下罰金」，\n    本件其販賣之海洛因，數量非鉅，所得非多，與專門販售毒\n    品之大盤尚難相提並論，犯罪情狀在客觀上可引起一般人之\n    同情，倘科以上開罪名之法定最輕本刑，猶嫌過重，爰就其\n    販賣第一級毒品罪部分，依刑法第59條規定，酌減其刑，並\n    先加後減之。\n六、原審因而適用毒品危害防制條例第4 條第1 項、第8 條第1\n    項、第10條第1 項、第19條第1 項，刑法第30條、第47條第\n    1 項、第59條、第51條第5 款規定，並審酌被告甲○○犯後\n    坦承部分犯行，態度尚佳等一切情狀，就其販賣第一級毒品\n    11罪部分，各處有期徒刑15年2 月；轉讓第一級毒品部分，\n    量處有期徒刑1 年6 月；幫助施用第一級毒品5 罪部分，各\n    處有期徒刑10月，並定其應執行刑有期徒刑16年6 月。並認\n    未扣案之0000000000號行動電話1 支，係其所有供犯罪所用\n    之物，應依毒品危害防制條例第19條第1 項之規定沒收，如\n    全部或一部不能沒收時，均追徵其價額或以其財產抵償之。\n    被告甲○○如附表七（一）所示販毒所得，均應依毒品危害\n    防制條例第19條第1 項之規定沒收，如全部或一部不能沒收\n    時，均以其財產抵償之。扣案之甲○○所有之夾鏈袋4 個及\n    綠色谷關青藥膏1 個，均無證據顯示係屬其供犯罪所用之物\n    ，爰不宣告沒收。經核原審此部分判決認事用法並無不合，\n    量刑亦屬適度，被告上訴意旨，或否認犯罪，或指摘原審此\n    部分判決量刑過重不當，為無理由，應予駁回。\n捌、被告乙○○部分\n一、上訴人即被告乙○○未於本院最後審理期日到場，惟訊據被\n    告乙○○對於附表八（一）、（四）幫助施用、轉讓海洛因\n    之犯行，均坦承不諱，惟矢口否認有附表八（二）、（三）\n    之販賣毒品行為，辯稱：伊未參與毒品交易云云。\n二、經查：被告乙○○對於附表八（一）、（四）幫助施用、轉\n    讓海洛因犯行之自白，核與證人寅○○、癸○○、申○○、\n    庚○○、翁丁元於原審審理中之證述相符，堪認屬實。又被\n    告乙○○與癸○○係先至高雄購買海洛因，且約定由乙○○\n    出錢，癸○○負責賣海洛因將錢還乙○○，乙○○再從中獲\n    取免費半錢一半之海洛因，嗣由另案被告金文隆攜回毒品，\n    被告乙○○、癸○○再共同為附表八（二）編號1 、2 、3\n    之犯行，此據被告乙○○及證人癸○○於警詢中（97年3 月\n    5 日對質筆錄，警卷，頁230 、313 ）供述屬實，證人癸○\n    ○供稱：「（問：96年9 月某日至96年10月13日在澎湖百合\n    民宿販賣給丁○○、午○○2 人3 次毒品海洛因之分工情形\n    如何？）不是96年9 月是96年10月某日才開始販賣。96年10\n    月某日我會跟乙○○去高雄要向辰○○購買毒品是要自己施\n    用，後來在高雄賣我們毒品的人變成綽號「金剛」男子，我\n    與乙○○才有了買毒品回澎湖販賣的共識（乙○○出錢、我\n    負責賣毒品將錢還乙○○、乙○○從中獲取免費半錢一半毒\n    品海洛因），綽號「金剛」男子才叫金文隆幫我們把毒品帶\n    回澎湖，與乙○○共同前往百合民宿由我將毒品海洛因販賣\n    給丁○○跟午○○、再將賣毒品的錢拿給乙○○。」，被告\n    乙○○則稱：「（問：96年9 月某日至96年10月13日在澎湖\n    百合民宿販賣給丁○○、午○○2 人3 次毒品海洛因之分工\n    情形如何？）與莊和和所說相同。」等語，復與證人癸○○\n    、午○○、丁○○於原審審理中之證述相符，且有96年10月\n    12日15時07分、96年10月13日22時08分監聽譯文（警卷173\n    ）附卷可稽，被告乙○○辯稱：案發時伊僅出現在現場，沒\n    有共同販賣毒品之犯意云云，不足採信。另關於附表八（三\n    ）編號1部 分，查被告乙○○及證人酉○○於警詢中供稱（\n    97年3 月10日對質筆錄，警卷，頁1021、97年3 月6 日對質\n    筆錄，警卷，頁318 、97年3 月19日對質筆錄，警卷，頁\n    1122）：「問：丙（即酉○○）於警訊第3 次筆錄中與乙○\n    ○、甲（即辰○○）同車交易6000元安非他命交易情形為何\n    ？）丙即酉○○：我確定是乙○○打電話問我要不要買毒品\n    ，後來是甲在車上將毒品交給我，隔天在光復路229 號乙○\n    ○住處將這6000元拿給乙○○本人。」、「問：你是否於96\n    年8 至9 月某日下午17時許以電話詢問酉○○是否要買毒品\n    ，並在燦坤3C量販店賣場後方公園由辰○○販售1 包價值60\n    00元半錢重的毒品安非他命給酉○○？）乙○○：有這件事\n    。時間是我忘了。」、「問：96年10月26日乙（即辰○○）\n    、丙（即乙○○）是否在燦坤3C量販店後方公園附近販售安\n    非他命半錢給酉○○，價值6000元？後來酉○○是否在光復\n    路229 號4 樓將這6000元交給丙？）丙即乙○○：有這件事\n    ，毒品是辰○○交給酉○○，‧‧‧。」等語，2 人已詳就\n    乙○○打電話與酉○○接洽毒品交易事宜，並由辰○○交付\n    毒品等情，互為一致之供述，被告乙○○、證人酉○○嗣於\n    原審審理中翻異前供，自屬卸責、迴護之詞，不能遽採。另\n    關於附表八（三）編號2 之行為，業據被告乙○○於警詢中\n    （97年3 月6 日對質筆錄，警卷，頁429 ）供承：「問：96\n    年11月6 日何人在西衛里海邊車上賣4000元毒品安非他命給\n    丁○○？）乙○○：有這件事，但是是2000元。」等語，核\n    與證人申○○、丁○○於本院審理中之證述相符，且有96年\n    11月6 日16時54分監聽譯文（警卷，頁386 ）附卷可稽；再\n    者關於附表八（三）編號3 之行為，亦據被告乙○○於警詢\n    及原審審理中自承：有叫申○○來拿取安非他命等語，核與\n    證人申○○等於原審審理中之證述相符，被告乙○○所辯未\n    販賣毒品云云，不足採信。\n三、綜上，被告乙○○確有附表八（一）、（二）、（三）、（\n    四）所示之販賣、轉讓、幫助施用海洛因或安非他命之事實\n    ，事證明確，其犯行堪以認定。\n四、核被告乙○○就附表八（一）所為，係犯刑法第30條第1 項\n    、毒品危害防制條例第10條第1 項幫助施用第一級毒品罪；\n    其附表八（二）所為，均係犯毒品危害防制條例第4 條第1\n    項販賣第一級毒品罪；其附表八（三）之所為，均係犯毒品\n    危害防制條例第4 條第2 項販賣第二級毒品罪；其附表八（\n    四）之所為，則均係犯毒品危害防制條例第8 條第1 項轉讓\n    第一級毒品罪。又被告乙○○就附表八（一）所示犯行，係\n    代為合資購買海洛因後，再與寅○○分食，核其此部分所為\n    ，係犯幫助施用第一級毒品罪，公訴人認其此部分係犯販賣\n    第一級毒品罪，尚有未洽，惟基本社會事實同一，爰變更起\n    訴法條。其就附表八（二）、附表八（三）編號1 、3 之犯\n    行，分別與癸○○、辰○○、申○○等人有犯意之聯絡及行\n    為之分擔，均屬共同正犯。其就上開犯行，犯意各別，行為\n    互殊，應分論併罰。附表八（一）之犯行，依刑法第30條第\n    2 項減輕其刑。被告乙○○無販毒之前科紀錄，而所犯販賣\n    第一、二級毒品犯行之法定刑分別為「死刑或無期徒刑；處\n    無期徒刑者，得併科新臺幣1 千萬元以下罰金」、「無期徒\n    刑或7 年以上有期徒刑，得併科新臺幣7 百萬元以下罰金」\n    ，本件其販賣之海洛因、安非他命，數量非鉅，所得非多，\n    與專門販售毒品之大盤尚難相提並論，犯罪情狀在客觀上可\n    引起一般人之同情，倘科以上開罪名之法定最輕本刑，猶嫌\n    過重，爰就其販賣第一、二級毒品罪部分，均依刑法第59條\n    規定，酌減其刑。\n五、原審因而適用毒品危害防制條例第4 條第1 項、第2 項、第\n    10條第1 項、第8 條第1 項、第19條第1 項、刑法第28條、\n    第30條第2 項、第59條、第51條第5 款規定，並審酌被告乙\n    ○○犯後否認犯行，態度非佳等一切情狀，就其幫助施用第\n    一級毒品部分，量處有期徒刑8 月；共同販賣第一級毒品3\n    罪部分，各處有期徒刑15年2 月；販賣第二級毒品3 罪部分\n    ，各處有期徒刑3 年8 月；轉讓第一級毒品7 罪部分，各處\n    有期徒刑1 年6 月，並定其應執行刑有期徒刑18年。並認未\n    扣案之0000000000號、0000000000號、0000000000號行動電\n    話各1 支，分屬被告乙○○、共犯申○○、癸○○所有供犯\n    罪所用之物，應依毒品危害防制條例第19條第1 項之規定沒\n    收，如全部或一部不能沒收時，均追徵其價額或以其財產抵\n    償之。被告乙○○如附表八（二）、（三）所示販毒所得，\n    應依毒品危害防制條例第19條第1 項之規定沒收（共犯部分\n    應與辰○○或癸○○連帶沒收），如全部或一部不能沒收時\n    ，均以其財產抵償之。經原審此部分判決認事用法並無不合\n    ，量刑亦屬適度，被告上訴意旨，仍執前詞，或否認犯罪，\n    或指摘原審此部分判決量刑，過重不當，難認有理由，應予\n    駁回。\n六、被告乙○○經合法傳喚，無正當理由不到庭，爰不待其陳述\n    逕行判決。\n玖、被告癸○○部分\n一、附表九之事實，業據上訴人即被告癸○○分別於偵查中、原\n    審及本院審理中坦承不諱，核與證人丁○○、午○○、乙○\n    ○、辰○○、申○○、甲○○、庚○○、翁維昌、未○○、\n    翁丁元、己○○於警詢或原審審理中證述之情節相符，事證\n    明確，被告癸○○確有附表九（一）、（二）、（三）、（\n    四）、（五）所示之販賣、轉讓、幫助施用海洛因或安非他\n    命之犯行，均堪認定。證人午○○於本院審理中雖證述：我\n    只是請癸○○調毒品，因為大家是朋友，我是請癸○○幫我\n    買毒品等語（見本院卷二第8 頁），然與被告癸○○於本院\n    審理時自白販賣之情節不符，自難採信，併此明。\n二、核被告癸○○附表九（一）所為，均係犯毒品危害防制條例\n    第4 條第1 項販賣第一級毒品罪；其附表九（二）所為，均\n    係犯毒品危害防制條例第8 條第1 項轉讓第一級毒品罪；其\n    附表九（三）所為，係犯藥事法第83條第1 項轉讓禁藥罪；\n    其附表九（四）所為，均係犯刑法第30條第1 項、毒品危害\n    防制條例第10條第1 項幫助施用第一級毒品罪；其附表九（\n    五）所為，係犯刑法第30條第1 項、毒品危害防制條例第10\n    條第2 項幫助施用第二級毒品罪。按安非他命為毒品危害防\n    制條例第2 條第2 項第2 款所明定之第二級毒品；且經行政\n    院衛生署於75年7 月11日以衛署藥字第59762 7 號公告，為\n    有效管理安非他命類藥品與其衍生物之冊類及其製劑，重申\n    公告禁止使用，而均屬藥事法第22條第1 款所規定之禁藥。\n    故行為人明知為禁藥即「安非他命」而轉讓與他人者，除成\n    立毒品危害防制條例第8 條第2 項之「轉讓第二級毒品罪」\n    外，亦構成藥事法第83條第1 項之「轉讓禁藥罪」，此係屬\n    同一犯罪行為而同時有二種法律可資處罰之「法規競合」情\n    形，應依「重法優於輕法」、「後法優於前法」等法理，擇\n    一處斷。而毒品危害防制條例第8 條第2 項轉讓第二級毒品\n    罪之法定本刑為「6 月以上5 年以下有期徒刑，得併科新台\n    幣70萬元以下罰金」。93年4 月21日修正後藥事法第83條第\n    1 項轉讓禁藥罪之法定本刑為「7 年以下有期徒刑，得併科\n    新台幣5 百萬元以下罰金」。故除轉讓之第二級毒品達毒品\n    危害防制條例第8 條第6 項之一定數量，經依法加重其刑，\n    致該法定刑較藥事法第83條第1 項之法定刑為重之情形外，\n    因藥事法第83條第1 項為後法，且為重法，應優先適用藥事\n    法處罰（最高法院96年度台上字第3582號判決意旨參照），\n    而本件被告癸○○轉讓安非他命之數量未達毒品危害防制條\n    例第8 條第6 項所定之數量，是故核其就附表九（三）所為\n    ，係犯藥事法第83條第1 項轉讓禁藥罪。公訴人認其此部分\n    係犯販賣第二級毒品罪，尚有未洽；又被告癸○○就附表九\n    （四）及附表九（五）所示犯行，均係代他人購買毒品後，\n    再與他人分食，核其此部分所為，係分別犯幫助施用第一、\n    二級毒品罪，公訴人認其此部分係犯販賣或轉讓海洛因、安\n    非他命罪，亦有未洽，惟基本社會事實同一，爰均變更起訴\n    法條。另被告癸○○於96年10月28日與辰○○共同自高雄攜\n    帶海洛因1/4 錢至澎湖之行為（即起訴書附表一編號23部分\n    ），因該次攜帶之毒品係供附表九（一）編號4 之販毒所用\n    ，該運輸行為屬販賣之部分行為，不另論罪，公訴人認被告\n    癸○○該部分攜帶毒品行為另構成運輸第一級毒品罪，亦有\n    未洽。其就附表九（一）、附表九（二）編號1 之犯行，分\n    別與乙○○、辰○○、申○○有犯意之聯絡及行為之分擔，\n    均屬共同正犯。其就上開犯行，犯意各別，行為互殊，應分\n    論併罰。被告癸○○曾因違反毒品危害防制條例案件，經法\n    院定應執行刑判處有期徒刑1 年6 月，嗣減為有期徒刑9 月\n    確定，於96年7 月16日執行完畢，其於5 年內故意再犯本件\n    有期徒刑以上之罪，為累犯，應加重其刑（死刑、無期徒刑\n    部分不得加重）。附表九（四）、（五）之犯行，均依刑法\n    第30條第2 項減輕其刑，並先加後減之。被告癸○○無販毒\n    之前科紀錄，而所犯販賣第一級毒品犯行之法定刑為「死刑\n    或無期徒刑；處無期徒刑者，得併科新臺幣1 千萬元以下罰\n    金」，本件其販賣之海洛因，數量非鉅，所得非多，與專門\n    販售毒品之大盤尚難相提並論，犯罪情狀在客觀上可引起一\n    般人之同情，倘科以上開罪名之法定最輕本刑，猶嫌過重，\n    爰就其販賣第一級毒品罪部分，均依刑法第59條規定，酌減\n    其刑。又被告癸○○於警詢時供出其所販賣海洛因之來源，\n    使警方因而查獲販毒之乙○○、辰○○及另案之金正剛，有\n    其97年1 月8 日警詢筆錄（警卷第112 頁），及原審97年度\n    訴字第33號（認定金正剛販賣海洛因予癸○○）在卷可稽。\n    應依毒品危害防制條例第17條第1 項規定，減輕其刑。又癸\n    ○○於偵查中及審判中均自白販賣第一級毒品，亦依同條例\n    第17條第2 項規定，遞減其刑。\n三、原審就癸○○轉讓第一級毒品、轉讓禁藥、幫助施用第一、\n    二級毒品部分，因而適用毒品危害防制條例第8 條第1 項、\n    第10條第1 項、第2 項、藥事法第83條第1 項、刑法第28條\n    、第30條第2 項、第51條第5 款之規定，並審酌被告犯後坦\n    承犯行，態度良好等一切情狀，就其共同轉讓第一級毒品部\n    分，量處有期徒刑1 年6 月；轉讓第一級毒品2 罪部分，各\n    處有期徒刑1 年6 月；幫助施用第一級毒品3 罪部分，各處\n    有期徒刑8 月；幫助施用第二級毒品部分，量處有期徒刑4\n    月。經核原審此部分判決認事用法並無不合，量刑亦屬適度\n    。癸○○上訴意旨，指摘原審此部分判決量刑過重不當，為\n    無理由，應予駁回。\n四、原審就癸○○販賣第一級毒品部分予以論科，固非無見，惟\n    查癸○○於警詢中，供出其販賣海洛因之來，使警方因而查\n    獲販毒之乙○○、辰○○及另案之金正剛，自應依毒品危害\n    防制條例第17條第1 項規定，減輕其刑，原審漏未審酌，自\n    有未當。癸○○上訴意旨，指摘原審此部分判決不當，為有\n    理由，自應由本院將原審此部分判決及其定執行刑部分予以\n    撤銷改判。審酌被告於偵查中及審判中自白犯行，並於警詢\n    中供出其所販賣毒品海洛因之來源，使警方因而查獲販毒之\n    乙○○、辰○○及另案金正剛等人，態度甚佳等一切情狀，\n    就其所犯販賣第一級毒品10罪，各處有期徒刑11年2 月，並\n    與其上訴駁回所處共同轉讓第一級毒品，累犯，處有期徒刑\n    1 年6 月；又轉讓第一級毒品，累犯，共計2 罪，各處有期\n    徒刑1 年6 月；又轉讓禁藥，累犯，處有期徒刑1 年；又幫\n    助施用第一級毒品，累犯，共計3 罪，各處有期徒刑8 月；\n    又幫助施用第二級毒品，累犯，處有期徒刑4 月。應執行有\n    期徒刑13年，行動電話、販毒所得之沒收、追徵價額、抵償\n    均如附表九（一）應沒收之物（1 ）、（2 ）所示。\n據上論斷，應依刑事訴訟法第368 條、第369 條第1 項前段、第\n299 條第1 項前段、第371 條、毒品危害防制條例第4條 第1 項\n、第2 項、第17條第1 項、第2 項、第18條第1 項前段、第19條\n第1 項、刑法第28條、第47條第1 項、第59條、第51條第5 款，\n判決如主文。\n本案經檢察官蔡國禎到庭執行職務。\n中    華    民    國     99     年     1     月   4   日\n                  刑事第九庭    審判長法  官  莊秋桃\n                                      法  官  范惠瑩\n                                      法  官  謝宏宗\n                                                                 4\n以上正本證明與原本無異。\n除幫助施用第二級毒品外，其他各罪均如不服本判決應於收受本\n判決後10日內向本院提出上訴書狀，其未述上訴理由者，並得\n於提起上訴後10日內向本院補提理由書狀（均須按他造當事人之\n人數附繕本) 「切勿逕送上級法院」。"
  },
  "characters": {
    "judges": [
      "莊秋桃",
      "范惠瑩",
      "謝宏宗"
    ],
    "prosecutors": [
      "蔡國禎"
    ],
    "lawyers": [
      "洪幼珍",
      "徐文彬",
      "曾慶雲",
      "吳建勛",
      "梁宗憲",
      "陶德斌",
      "洪世崇",
      "許惠珠",
      "曾慶雲",
      "李淑妃"
    ],
    "clerks": [
      "蘇恒仁"
    ],
    "plaintiffs": [

    ],
    "defendants": [
      "寅",
      "巳",
      "子",
      "申",
      "庚",
      "未",
      "乙"
    ],
    "prosecutor_office": [

    ],
    "creditors": [

    ],
    "debtors": [

    ],
    "judicial_associate_officer": [

    ]
  },
  "adjudged_at": "2010-01-04",
  "created_at": "2016-01-05 14:40:22",
  "updated_at": "2016-01-05 14:40:22"
}