{
  "identify": "KSH-98-抗-407-20100104-1",
  "court": {
    "name": "臺灣高等法院",
    "code": "KSH"
  },
  "division": {
    "name": "刑事",
    "code": "M"
  },
  "year": 98,
  "word": "抗",
  "number": "407",
  "jcheck": "1",
  "reason": "沒入保證金",
  "content": "臺灣高等法院高雄分院刑事裁定           98年度抗字第407號\n抗  告  人\n即具保人    甲○○○  民國38.\n被      告  乙○○\n上列抗告人因沒入保證金案件，不服臺灣高雄地方法院中華民國\n98年12月7 日裁定（98年度審易字第2483號），提起抗告，本院\n裁定如下：\n    主  文\n抗告駁回。\n    理  由\n一、抗告意旨略以：被告乙○○雖未遵期於民國98年11月12下午\n    4 時15分到庭，然係因其於當日下午約3 時10分許，身體突\n    感不適，經送醫院注射點滴，斯時抗告人即具保人（下稱抗\n    告人）甲○○○即委請女兒撥打電話至法院請假，而接聽者\n    告以該股書記官已前往開庭，抗告人於下午5 時15分許，再\n    次去電，接聽人員告知抗告人等候通知再行出庭，惟抗告人\n    嗣則未再收到法院任何開庭通知，而於98年12月11日即收受\n    法院沒入保證金之裁定，爰依法提起抗告，請求再予查明等\n    語。\n二、按具保之被告逃匿者，應命具保人繳納指定之保證金額，並\n    沒入之，保證金已繳納者，沒入之；前項規定，於檢察官依\n    刑事訴訟法第93條第3 項但書及第228 條第4 項命具保者，\n    準用之，刑事訴訟法第118 條定有明文。查抗告人因被告乙\n    ○○涉嫌竊盜案件，經臺灣高雄地方法院檢察署檢察官於98\n    年8 月14日指定保證金額新臺幣1 萬元，由抗告人繳納現金\n    後，已將被告釋放，然被告經臺灣高雄地方法院法官依其住\n    居所傳喚，並命抗告人偕同被告到庭應訊，被告均未到庭，\n    嗣經法官派警拘提，被告亦未到案，此有臺灣高雄地方法院\n    被告及抗告人傳票送達證書、拘票、報告書等件附卷可稽；\n    又被告斯時並未在監執行或受羈押，亦有臺灣高等法院被告\n    前案紀錄表在卷足憑，足見被告當時業已逃匿無訛。抗告人\n    雖執前詞為辯，然其並未提出任何證據以為證明，本難遽信\n    ；再參以被告於為警緝獲後，經原審法官訊以：為什麼都不\n    來開庭？其答以：我有來開庭，我應該是去地檢署開庭等語\n    。所為答覆明顯與抗告人前揭所辯有所不符，是抗告人前開\n    所辯，顯非事實，自無可採。\n三、原審因而裁定將抗告人甲○○○所繳納之保證金新臺幣1 萬\n    元予以沒入，核無不合。抗告人仍執前詞，指摘原裁定不當\n    ，為無理由，應予駁回。\n據上論結，應依刑事訴訟法第412 條，裁定如主文。\n中    華    民    國    99    年    1     月    4     日\n                  刑事第一庭    審判長法  官 翁慶珍\n                                      法  官 黃仁松\n                                      法  官 徐美麗\n以上正本證明與原本無異。\n不得再抗告。\n中    華    民    國    99    年    1     月    4     日\n                                      書記官 賴梅琴",
  "structure": {
    "main": "抗告駁回。",
    "reason": "一、抗告意旨略以：被告乙○○雖未遵期於民國98年11月12下午\n    4 時15分到庭，然係因其於當日下午約3 時10分許，身體突\n    感不適，經送醫院注射點滴，斯時抗告人即具保人（下稱抗\n    告人）甲○○○即委請女兒撥打電話至法院請假，而接聽者\n    告以該股書記官已前往開庭，抗告人於下午5 時15分許，再\n    次去電，接聽人員告知抗告人等候通知再行出庭，惟抗告人\n    嗣則未再收到法院任何開庭通知，而於98年12月11日即收受\n    法院沒入保證金之裁定，爰依法提起抗告，請求再予查明等\n    語。\n二、按具保之被告逃匿者，應命具保人繳納指定之保證金額，並\n    沒入之，保證金已繳納者，沒入之；前項規定，於檢察官依\n    刑事訴訟法第93條第3 項但書及第228 條第4 項命具保者，\n    準用之，刑事訴訟法第118 條定有明文。查抗告人因被告乙\n    ○○涉嫌竊盜案件，經臺灣高雄地方法院檢察署檢察官於98\n    年8 月14日指定保證金額新臺幣1 萬元，由抗告人繳納現金\n    後，已將被告釋放，然被告經臺灣高雄地方法院法官依其住\n    居所傳喚，並命抗告人偕同被告到庭應訊，被告均未到庭，\n    嗣經法官派警拘提，被告亦未到案，此有臺灣高雄地方法院\n    被告及抗告人傳票送達證書、拘票、報告書等件附卷可稽；\n    又被告斯時並未在監執行或受羈押，亦有臺灣高等法院被告\n    前案紀錄表在卷足憑，足見被告當時業已逃匿無訛。抗告人\n    雖執前詞為辯，然其並未提出任何證據以為證明，本難遽信\n    ；再參以被告於為警緝獲後，經原審法官訊以：為什麼都不\n    來開庭？其答以：我有來開庭，我應該是去地檢署開庭等語\n    。所為答覆明顯與抗告人前揭所辯有所不符，是抗告人前開\n    所辯，顯非事實，自無可採。\n三、原審因而裁定將抗告人甲○○○所繳納之保證金新臺幣1 萬\n    元予以沒入，核無不合。抗告人仍執前詞，指摘原裁定不當\n    ，為無理由，應予駁回。\n據上論結，應依刑事訴訟法第412 條，裁定如主文。"
  },
  "characters": {
    "judges": [
      "翁慶珍",
      "黃仁松",
      "徐美麗"
    ],
    "prosecutors": [

    ],
    "lawyers": [

    ],
    "clerks": [
      "告以該股"
    ],
    "plaintiffs": [

    ],
    "defendants": [
      "乙○○"
    ],
    "prosecutor_office": [

    ],
    "creditors": [

    ],
    "debtors": [

    ],
    "judicial_associate_officer": [

    ]
  },
  "adjudged_at": "2010-01-04",
  "created_at": "2016-01-05 14:39:41",
  "updated_at": "2016-01-05 14:39:41"
}