{
  "identify": "PCD-99-訴-972-20100512-1",
  "court": {
    "name": "臺灣新北地方法院",
    "code": "PCD"
  },
  "division": {
    "name": "刑事",
    "code": "M"
  },
  "year": 99,
  "word": "訴",
  "number": "972",
  "jcheck": "1",
  "reason": "毒品危害防制條例",
  "content": "臺灣板橋地方法院刑事判決               99年度訴字第972號\n公  訴  人  臺灣板橋地方法院檢察署檢察官\n被      告  甲○○\n上列被告因違反毒品危害防制條例案件，經檢察官提起公訴（99\n年度毒偵字第990 號），被告於準備程序中就被訴事實為有罪之\n陳述，經本院合議庭裁定由受命法官獨任進行簡式審判程序，判\n決如下：\n    主  文\n甲○○施用第一級毒品，累犯，處有期徒刑柒月。\n    事  實\n一、甲○○曾於民國97年間，因施用第一級毒品案件，經本院以\n    97年度毒聲字第917 號裁定送勒戒處所觀察、勒戒後，認有\n    繼續施用毒品之傾向，經本院以97年度毒聲字第1593號裁定\n    令入戒治處所施以強制戒治，業於98年4 月3 日強制戒治執\n    行完畢釋放，並經臺灣板橋地方法院檢察署檢察官以98年度\n    戒毒偵字326 號為不起訴處分確定；復於上開觀察、勒戒執\n    行完畢釋放後5 年內之98年間，因施用第一級毒品案件，經\n    本院以98年度簡字第6933號判處有期徒刑5 月，嗣於98年10\n    月5 日確定，並於98年11月4 日易科罰金執行完畢（於本案\n    構成累犯）；再因施用第一級毒品案件，經本院以98年度訴\n    字第3581號判處有期徒刑6 月，嗣於98年11月26日確定，並\n    於98年12月29日易科罰金執行完畢（於本案構成累犯）；又\n    因施用第一級毒品案件，經本院以98年度訴字第4374號判處\n    有期徒刑6 月，嗣於99年2 月1 日確定，並於99年3 月16日\n    易科罰金執行完畢（於本案不構成累犯）。詎甲○○仍不知\n    悔改，基於施用第一級毒品海洛因之犯意，於99年1 月19日\n    晚間某時（起訴書略載為99年1 月20日為警採尿前26小時內\n    之某時），在其位於臺北縣土城市○○街16號3 樓之住所內\n    ，以注射針筒注射之方式，施用海洛因1 次。嗣於99年1 月\n    20日上午9 時30分許，在臺北縣土城市○○街16號前為警查\n    獲，並扣得注射針筒2 支。經警採集其尿液檢體送驗後，結\n    果呈現可待因及嗎啡陽性反應，始悉上情。\n二、案經臺北縣政府警察局淡水分局移送臺灣板橋地方法院檢察\n    署檢察官偵查起訴。\n    理  由\n一、本案被告甲○○所犯係死刑、無期徒刑、最輕本刑為3 年以\n    上有期徒刑以外之罪，其於準備程序中就前揭被訴事實為有\n    罪之陳述，經受命法官告知簡式審判程序之旨，並聽取其與\n    公訴人之意見後，本院認無不得或不宜改依簡式審判程序進\n    行之情事，依刑事訴訟法第273 條之1 第1 項、第284 條之\n    1 規定，裁定本案由受命法官獨任進行簡式審判程序；且依\n    刑事訴訟法第273 條之2 及第159 條第2 項規定，不適用傳\n    聞法則有關限制證據能力之相關規定，合先敘明。\n二、上揭犯罪事實，業據被告於本院審理時自白不諱，且被告為\n    警查獲後，經警採集其尿液檢體送驗，先以酵素免疫分析法\n    （EIA ）初步檢驗，呈現鴉片類陽性反應，再以氣相層析質\n    譜儀法（GC/MS ）確認檢驗，亦呈現可待因及嗎啡陽性反應\n    等情，有臺灣檢驗科技股份有限公司於99年2 月6 日所出具\n    報告編號UL/2010/10793 號濫用藥物檢驗報告、臺北縣政府\n    警察局查獲毒品案件尿液檢體監管紀錄表各1 份在卷可稽（\n    見偵查卷宗第40、41頁），足徵被告任意性之自白與事實相\n    符，應堪採信。再被告前於97年間，因施用毒品案件，經本\n    院以97年度毒聲字第917 號裁定送勒戒處所觀察、勒戒後，\n    認有繼續施用毒品之傾向，經本院以97年度毒聲字第1593號\n    裁定令入戒治處所施以強制戒治，業於98年4 月3 日強制戒\n    治執行完畢釋放，並經臺灣板橋地方法院檢察署檢察官以98\n    年度戒毒偵字326 號為不起訴處分確定等情，亦有臺灣高等\n    法院被告前案紀錄表1 份附卷可參，足認被告係於上述強制\n    戒治執行完畢釋放後5 年內為本案施用毒品犯行，自應依毒\n    品危害防制條例第23條第2 項規定，依法追訴、處罰。本案\n    事證明確，被告犯行洵堪認定，應依法論科。\n三、按海洛因係毒品危害防制條例第2 條第2 項第1 款所明定之\n    第一級毒品。是核被告所為，係犯毒品危害防制條例第10條\n    第1 項之施用第一級毒品罪。被告施用海洛因前後，持有海\n    洛因之低度行為，為施用之高度行為所吸收，不另論罪。被\n    告有上述事實欄所載之科刑及執行紀錄，此觀卷附臺灣高等\n    法院被告前案紀錄表1 份即明，其於受有期徒刑之執行完畢\n    後，5 年以內故意再犯本件有期徒刑以上之罪，為累犯，應\n    依刑法第47條第1 項規定加重其刑。爰審酌被告曾因施用毒\n    品案件，經觀察、勒戒及強制戒治執行完畢釋放，並獲得不\n    起訴處分之寬典（見卷附臺灣高等法院被告前案紀錄表），\n    猶不知悔改，而再犯本件施用第一級毒品罪，顯見其戒除毒\n    癮之意志薄弱，雖在財團法人徐元智先生醫藥基金會附設亞\n    東紀念醫院接受美沙冬替代療法治療，惟未能完全依指示取\n    藥服用（見本院卷宗第28頁之亞東紀念醫院診斷證明書1 紙\n    及第29至32頁之替代療法就診資料1 份），且施用毒品係自\n    戕行為，對他人法益尚無具體危害，兼衡被告之品行、智識\n    程度、生活狀況、犯罪之動機、目的、手段、坦承犯行之犯\n    罪後態度、檢察官求處有期徒刑7 月等一切情狀，量處如主\n    文所示之刑，以資懲儆。至為警扣得之注射針筒2 支，被告\n    於偵查中、本院準備程序及審理時均堅詞否認為其所有，復\n    查無其他積極證據足以認定上開扣案物品確係被告所有之物\n    ，爰不予宣告沒收，附此敘明。\n據上論斷，應依刑事訴訟法第273 條之1 第1 項、第299 條第1\n項前段，毒品危害防制條例第10條第1 項，刑法第11條前段、第\n47條第1 項，判決如主文。\n本案經檢察官張世聰到庭執行職務。\n中    華    民    國    99    年     5    月    12    日\n                  刑事第九庭    法  官    賴彥魁\n上列正本證明與原本無異。\n如不服本判決，應於判決送達後10日內，向本院提出上訴書狀，\n並應敘述具體理由；其未敘述上訴理由者，應於上訴期間屆滿後\n20日內向本院補提理由書（均須按他造當事人之人數附繕本），\n「切勿逕送上級法院」。\n                                書記官    楊文祥\n中    華    民    國    99    年     5    月    12    日\n附錄本案論罪科刑法條全文：\n毒品危害防制條例第10條\n施用第一級毒品者，處6 月以上5 年以下有期徒刑。\n施用第二級毒品者，處3 年以下有期徒刑。",
  "structure": {
    "main": "甲○○施用第一級毒品，累犯，處有期徒刑柒月。",
    "fact": "一、甲○○曾於民國97年間，因施用第一級毒品案件，經本院以\n    97年度毒聲字第917 號裁定送勒戒處所觀察、勒戒後，認有\n    繼續施用毒品之傾向，經本院以97年度毒聲字第1593號裁定\n    令入戒治處所施以強制戒治，業於98年4 月3 日強制戒治執\n    行完畢釋放，並經臺灣板橋地方法院檢察署檢察官以98年度\n    戒毒偵字326 號為不起訴處分確定；復於上開觀察、勒戒執\n    行完畢釋放後5 年內之98年間，因施用第一級毒品案件，經\n    本院以98年度簡字第6933號判處有期徒刑5 月，嗣於98年10\n    月5 日確定，並於98年11月4 日易科罰金執行完畢（於本案\n    構成累犯）；再因施用第一級毒品案件，經本院以98年度訴\n    字第3581號判處有期徒刑6 月，嗣於98年11月26日確定，並\n    於98年12月29日易科罰金執行完畢（於本案構成累犯）；又\n    因施用第一級毒品案件，經本院以98年度訴字第4374號判處\n    有期徒刑6 月，嗣於99年2 月1 日確定，並於99年3 月16日\n    易科罰金執行完畢（於本案不構成累犯）。詎甲○○仍不知\n    悔改，基於施用第一級毒品海洛因之犯意，於99年1 月19日\n    晚間某時（起訴書略載為99年1 月20日為警採尿前26小時內\n    之某時），在其位於臺北縣土城市○○街16號3 樓之住所內\n    ，以注射針筒注射之方式，施用海洛因1 次。嗣於99年1 月\n    20日上午9 時30分許，在臺北縣土城市○○街16號前為警查\n    獲，並扣得注射針筒2 支。經警採集其尿液檢體送驗後，結\n    果呈現可待因及嗎啡陽性反應，始悉上情。\n二、案經臺北縣政府警察局淡水分局移送臺灣板橋地方法院檢察\n    署檢察官偵查起訴。",
    "reason": "一、本案被告甲○○所犯係死刑、無期徒刑、最輕本刑為3 年以\n    上有期徒刑以外之罪，其於準備程序中就前揭被訴事實為有\n    罪之陳述，經受命法官告知簡式審判程序之旨，並聽取其與\n    公訴人之意見後，本院認無不得或不宜改依簡式審判程序進\n    行之情事，依刑事訴訟法第273 條之1 第1 項、第284 條之\n    1 規定，裁定本案由受命法官獨任進行簡式審判程序；且依\n    刑事訴訟法第273 條之2 及第159 條第2 項規定，不適用傳\n    聞法則有關限制證據能力之相關規定，合先敘明。\n二、上揭犯罪事實，業據被告於本院審理時自白不諱，且被告為\n    警查獲後，經警採集其尿液檢體送驗，先以酵素免疫分析法\n    （EIA ）初步檢驗，呈現鴉片類陽性反應，再以氣相層析質\n    譜儀法（GC/MS ）確認檢驗，亦呈現可待因及嗎啡陽性反應\n    等情，有臺灣檢驗科技股份有限公司於99年2 月6 日所出具\n    報告編號UL/2010/10793 號濫用藥物檢驗報告、臺北縣政府\n    警察局查獲毒品案件尿液檢體監管紀錄表各1 份在卷可稽（\n    見偵查卷宗第40、41頁），足徵被告任意性之自白與事實相\n    符，應堪採信。再被告前於97年間，因施用毒品案件，經本\n    院以97年度毒聲字第917 號裁定送勒戒處所觀察、勒戒後，\n    認有繼續施用毒品之傾向，經本院以97年度毒聲字第1593號\n    裁定令入戒治處所施以強制戒治，業於98年4 月3 日強制戒\n    治執行完畢釋放，並經臺灣板橋地方法院檢察署檢察官以98\n    年度戒毒偵字326 號為不起訴處分確定等情，亦有臺灣高等\n    法院被告前案紀錄表1 份附卷可參，足認被告係於上述強制\n    戒治執行完畢釋放後5 年內為本案施用毒品犯行，自應依毒\n    品危害防制條例第23條第2 項規定，依法追訴、處罰。本案\n    事證明確，被告犯行洵堪認定，應依法論科。\n三、按海洛因係毒品危害防制條例第2 條第2 項第1 款所明定之\n    第一級毒品。是核被告所為，係犯毒品危害防制條例第10條\n    第1 項之施用第一級毒品罪。被告施用海洛因前後，持有海\n    洛因之低度行為，為施用之高度行為所吸收，不另論罪。被\n    告有上述事實欄所載之科刑及執行紀錄，此觀卷附臺灣高等\n    法院被告前案紀錄表1 份即明，其於受有期徒刑之執行完畢\n    後，5 年以內故意再犯本件有期徒刑以上之罪，為累犯，應\n    依刑法第47條第1 項規定加重其刑。爰審酌被告曾因施用毒\n    品案件，經觀察、勒戒及強制戒治執行完畢釋放，並獲得不\n    起訴處分之寬典（見卷附臺灣高等法院被告前案紀錄表），\n    猶不知悔改，而再犯本件施用第一級毒品罪，顯見其戒除毒\n    癮之意志薄弱，雖在財團法人徐元智先生醫藥基金會附設亞\n    東紀念醫院接受美沙冬替代療法治療，惟未能完全依指示取\n    藥服用（見本院卷宗第28頁之亞東紀念醫院診斷證明書1 紙\n    及第29至32頁之替代療法就診資料1 份），且施用毒品係自\n    戕行為，對他人法益尚無具體危害，兼衡被告之品行、智識\n    程度、生活狀況、犯罪之動機、目的、手段、坦承犯行之犯\n    罪後態度、檢察官求處有期徒刑7 月等一切情狀，量處如主\n    文所示之刑，以資懲儆。至為警扣得之注射針筒2 支，被告\n    於偵查中、本院準備程序及審理時均堅詞否認為其所有，復\n    查無其他積極證據足以認定上開扣案物品確係被告所有之物\n    ，爰不予宣告沒收，附此敘明。\n據上論斷，應依刑事訴訟法第273 條之1 第1 項、第299 條第1\n項前段，毒品危害防制條例第10條第1 項，刑法第11條前段、第\n47條第1 項，判決如主文。\n本案經檢察官張世聰到庭執行職務。\n中    華    民    國    99    年     5    月    12    日\n                  刑事第九庭    法  官    賴彥魁\n上列正本證明與原本無異。\n如不服本判決，應於判決送達後10日內，向本院提出上訴書狀，\n並應敘述具體理由；其未敘述上訴理由者，應於上訴期間屆滿後\n20日內向本院補提理由書（均須按他造當事人之人數附繕本），\n「切勿逕送上級法院」。\n                                書記官    楊文祥"
  },
  "characters": {
    "judges": [
      "賴彥魁"
    ],
    "prosecutors": [
      "張世聰"
    ],
    "lawyers": [

    ],
    "clerks": [
      "楊文祥"
    ],
    "plaintiffs": [

    ],
    "defendants": [
      "甲○○"
    ],
    "prosecutor_office": [
      "臺灣板橋地方法院檢察署檢察官"
    ],
    "creditors": [

    ],
    "debtors": [

    ],
    "judicial_associate_officer": [

    ]
  },
  "adjudged_at": "2010-05-12",
  "created_at": "2016-01-05 12:26:54",
  "updated_at": "2016-01-05 12:26:54"
}