{
  "identify": "PCD-99-訴緝-31-20100512-1",
  "court": {
    "name": "臺灣新北地方法院",
    "code": "PCD"
  },
  "division": {
    "name": "刑事",
    "code": "M"
  },
  "year": 99,
  "word": "訴緝",
  "number": "31",
  "jcheck": "1",
  "reason": "毒品危害防制條例",
  "content": "臺灣板橋地方法院刑事判決              99年度訴緝字第31號\n公  訴  人  臺灣板橋地方法院檢察署檢察官\n被      告  乙○○\n指定辯護人  本院公設辯護人  丁○○\n上列被告因違反毒品危害防制條例案件，經檢察官提起公訴（97\n年度偵字第2116號），本院判決如下：\n    主  文\n乙○○販賣第二級毒品，累犯，處有期徒刑柒年陸月；扣案之門\n號0000000000號SIM 卡壹枚沒收，販賣第二級毒品所\n得財物新臺幣貳仟元沒收，如全部或一部不能沒收時，以其財產\n抵償之。\n其餘被訴販賣第二級毒品未遂部分無罪。\n    事  實\n一、乙○○前曾於民國96年間因施用毒品案件，經本院以96年度\n    簡字第4695號判決判處有期徒刑六月，減為有期徒刑三月確\n    定，其後於96年10月4 日易科罰金執行完畢。詎其猶不知悔\n    改，明知甲基安非他命係屬毒品危害防制條例第2 條第2 項\n    第2 款所稱之第二級毒品，不得販賣、持有，竟基於販賣第\n    二級毒品甲基安非他命之犯意，由乙○○以門號為00000000\n    00號行動電話與丙○○門號為0000000000號行動電話聯絡購\n    買毒品，並於96年11月2 月1 時許，在臺北縣板橋市○○路\n    ○ 段257 號前，約定以每公克新台幣（下同）5,000 元之價\n    格販賣甲基安非他命1 包予丙○○施用，丙○○旋取得毒品\n    並先交付2000元予乙○○，尚積欠乙○○3000元。嗣於97年\n    1 月2 日16時許，在臺北縣板橋市○○路○ 段255 巷口為警\n    當場查獲，並從乙○○身上查扣海洛因1 包（淨重0.28公克\n    ）、安非他命6 包（淨重共計5.52公克）、分裝袋6 個及SI\n    M 卡（0000000000號）1 張。復經其同意由警方至臺北縣板\n    橋市○○街49巷33號2 樓搜索，並扣得海洛因4 包（淨重0.\n    87公克）、安非他命6 包（淨重5.02公克）、電子磅秤1 台\n    、玻璃球管吸食器6 支、吸管勺子3 支、安非他命吸食過濾\n    器1 支、分裝袋共計356 個。\n二、案經臺北縣政府警察局中和分局報請臺灣板橋地方法院檢察\n    署檢察官偵查起訴。\n    理  由\n壹、證據能力：\n一、按被告之自白，非出於強暴、脅迫、利誘、詐欺、疲勞訊問\n    、違法羈押或其他不正之方法，且與事實相符者，得為證據\n    ，刑事訴訟法第156 條第1 項有明文規定。被告之辯護人為\n    被告辯稱：被告之警詢過程，錄音不連續，疑有警員干擾被\n    告，且被告有藥癮發作，注意力不集中之情形，因被告自白\n    非出於任意性，依刑事訴訟法第156 條第1 項之規定，無證\n    據能力云云。查：經本院勘驗被告之警詢錄音帶內容，其結\n    果為「警方除部分問題係事先打好之外，其餘係採一問一答\n    的方式製作，國台語夾雜，語氣正常，但中間有多次疑似錄\n    音中斷，且警詢錄音帶為60分鐘1 卷，但與警詢筆錄所記載\n    製作筆錄之時間長達2 小時又40分鐘，其間警迫問被告是否\n    藥癮發作部分，被告注意力似乎並不集中」等語，有本院97\n    年10月3 日準備程序筆錄1 份可參（見本院97年度訴字第\n    1803 號 刑事卷第167 至173 頁），而製作被告筆錄之證人\n    甲○○固證稱：伊製作被告之警詢筆錄時，有把錄音機打開\n    ，打開之後就沒有關掉直到詢問結束等語，然被告製作筆錄\n    之過程未顯現於錄音帶之內容計有1 小時又40分鐘，員警未\n    注意錄音帶是否需換面，或需更換一卷錄意帶，顯然不合常\n    理，足徵被告之警詢確有可能未全程連續錄音，再者，被告\n    於第二次警詢時，被告一開始是否認拿藥去賣，表示伊是出\n    來要跟丙○○拿光碟片，但被告之此段陳述未見於被告之警\n    詢筆錄內，而在被告做出此部分陳述後，即出現疑似錄音中\n    斷的聲音，經此中斷，被告又出現「就是黃文祥打電話給我\n    ，他說要調藥，我拿去給他。」之回答，足徵製作筆錄過程\n    無法排除有警員介入干擾被告自由意志之情況，況被告於製\n    作筆錄過程中，亦出現被告疑似藥癮發作，注意力不集中之\n    狀況，綜上各情，自難認被告之警詢自白有證據能力。\n二、至被告乙○○之辯護人為被告乙○○抗辯：證人丙○○於警\n    詢時所為之證述，為被告以外之人於審判外之陳述，依刑事\n    訴訟法第159 條第1 項之規定，無證據能力。惟按被告以外\n    之人於檢察事務官、司法警察官或司法警察調查中所為之陳\n    述，與審判中不符時，其先前之陳述具有較可信之特別情況\n    ，且為證明犯罪事實存否所必要者，得為證據。刑事訴訟法\n    第159 條之2 定有明文。至警詢中之陳述具備可信性與必要\n    性，事實審法院除應衡酌該警詢筆錄作成之外部情況，就詢\n    問有無出於不正方法、陳述是否出於非任意性等適法性與否\n    為整體之考量外，應兼顧基於發見真實之需求，具有重要關\n    係。經查：證人丙○○於警詢之供述，依其記載內容，係採\n    取一問一答方式，且其於警詢時之供述較接近案發時點，記\n    憶應較為清晰，憑信性甚高，而當時未直接面對被告乙○○\n    心理壓力較小，且其於警詢、偵查所為證述之內容，其對基\n    本事實之供述始終一致，況證人丙○○與被告乙○○間亦無\n    仇恨，業據證人承述在卷，自無設詞誣陷友人，且所供並涉\n    及本身犯罪之自白，應無甘冒身陷囹圄之危險而為虛偽陳述\n    之可能，是證人丙○○之警詢筆錄具有可信之特別情況，而\n    丙○○之警詢筆錄，基於發見真實之需求，並有重要關係，\n    而為證明犯罪事實之存否並有必要，故其於警詢之陳述，本\n    院認符合刑事訴訟法第159 條之2 之情形，認應有證據能力\n    。\n三、第按被告以外之人於審判外之陳述，雖不符前4 條之規定，\n    而經當事人於審判程序同意作為證據，法院審酌該言詞陳述\n    或書面陳述作成時之情況，認為適當者，亦得為證據。當事\n    人或辯護人於法院調查證據時，知有第159 條第1 項不得為\n    證據之情形，而未於言詞辯論終結前聲明異議者，視為有前\n    項之同意。刑事訴訟法第159 條之5 定有明文。本案被告乙\n    ○○及其辯護人於本院審理時對於檢察官所提各項證據方法\n    之證據能力均表示「沒意見」（上述一、二除外），且本案\n    言詞辯論終結前，被告並未爭執被告以外之人於審判外之言\n    詞及書面陳述，無證據能力，揆諸上開規定，應認被告乙○\n    ○及其辯護人已同意上開各該證據方法得作為證據，而本院\n    審酌上開各該證據均非非法取得之證據，並無證據力明顯過\n    低之情形，復經本院於審判期日就上開證據依法進行調查、\n    辯論，依法自有證據能力，附此敘明。\n貳、有罪部分：\n一、得心證之理由：訊據被告乙○○雖坦承與證人丙○○認識，\n    惟矢口否認有何販賣第二級毒品之犯行，辯稱：96年11月2\n    日與丙○○見面，但只是討論安非他命之價格，並未交易云\n    云。然查：\n(一)、被告於96年11月2 月1 時許，在臺北縣板橋市○○路○ 段25\n    7 號前，以每公克5,000 元之價格販賣甲基安非他命1 包予\n    丙○○施用，丙○○先交付2000元予被告，尚欠被告3000元\n    等情，業據證人丙○○迭於警詢時、偵查中及審理時均結證\n    屬實（見97年度偵字第2116號偵查卷第16、19、98至99頁，\n    本院97年度訴字第1803號刑事卷第189 至190 頁）；查依證\n    人丙○○自警詢、偵查中及本院審理時經具結後之陳述勾稽\n    ，就正確之毒品交易時間、價額給付方式等項縱稍有未符，\n    但始終未曾否認其購得毒品之來源確係被告，指證歷歷，彰\n    彰明甚，且證人丙○○與被告並無何重大怨隙，應無設詞構\n    陷之理，更可認定證人丙○○證稱其確有於上開時地自被告\n    購買毒品甲基安非他命一節，要屬徵而可信。\n(二)、另證人丙○○於97年1 月2 為警查獲時所採尿液確有甲基安\n    非他命毒品之反應，有臺灣板橋地方法院檢察署97年度毒偵\n    字第584 號聲請簡易判決處刑書2 份（見同上偵查卷第11 4\n    、115 頁）附卷足憑，足徵證人丙○○確有施用第二級毒品\n    之情形。另對照被告乙○○前於87年間因違反麻醉藥品管理\n    處罰條例案件，經判處應執行有期徒刑6 年；因前於93年間\n    因連續販賣第二級毒品及轉讓禁藥等案件，經判處8 年4 月\n    確定，又曾於94年間因施用毒品案件，經檢察官聲請臺灣臺\n    北地方法院裁定送觀察、勒戒及強制戒治後，於95年8 月29\n    日執行完畢釋放，並經臺灣臺北地方法院檢察署檢察官以95\n    年度戒毒偵字第131 號不起訴處分確定在案。其前又曾於96\n    年間因施用毒品案件，經本院以96年度簡字第4695號判決判\n    處有期徒刑六月，減為有期徒刑三月確定，又於97年間因施\n    用第一、二級毒品案件，經本院以97年度訴字第2043號判處\n    有期徒刑1 年2 月等情觀之，有臺灣高等法院被告前案紀錄\n    表1 份可參，足徵被告確有沾染毒品之惡習及其與毒品接觸\n    之程度甚重。\n(三)、第按目前社會上非法販賣海洛因、安非他命犯罪之型態不一\n    ，有所謂「大盤」、「中盤」或「小盤」販賣者，亦有吸食\n    者彼此之間偶而互供有無之零星交易者，在屬前者之情形（\n    即大中小盤），經深入查證，如機會掌握得宜，或許可查獲\n    與非法販賣安非他命有關之販賣工具（諸如電子秤、帳冊、\n    分裝袋等物）或多數知情或購買者等證人之證詞，以作為法\n    院判決認定之依據，然在後者之情形（即吸食者之間偶發性\n    零星交易），因該種零星交易犯罪行為，在性質上本無須使\n    用任何販賣工具，亦無須記載帳冊，且其交易時間短暫（僅\n    須數秒之時間），交易方法簡單隱密（在不易為人注意之場\n    所一手交錢，一手交貨），交易對象單純（買方僅一人），\n    交易時未必有他人在場知悉其事，亦無所謂犯罪之被害人，\n    在被告堅不承認其犯行之情況下，茍非警方事先獲知情報而\n    埋伏於交易現場當場查獲，否則往往僅能在事後依據購買者\n    之供出來源作為認定事實之主要依據，法院縱再作深入之調\n    查，基於該種犯罪之性質所侷限，亦無從查得其他直接明顯\n    之關連性物證以為補強佐證，其有效之調查途徑在客觀上顯\n    然已告窮盡。本件被告涉嫌非法販賣甲基安非他命予證人丙\n    ○○之犯罪型態即屬此類情形之標準型態，惟法院固不應僅\n    憑購買者片面之指證，不查明是否與事實相符即遽行據以認\n    定被告之非法販賣甲基安非他命犯行，亦不應不調查其他相\n    關事證，即片面依購買者之指證而認定被告犯罪，然於此不\n    得不予特別指明者，即安非他命購買者所為不利於被告之指\n    證在證據法則上亦屬「人證」之一種，與「被告之自白」經\n    法律特別規定不得作為認定事實唯一證據之情形顯然不同，\n    茍購買者之指證並無「重大」矛盾瑕疵，亦未違背經驗法則\n    與論理法則，且核與案件之其他相關事實（如有吸用毒品之\n    背景、彼此無重大仇隙，指證態度明確肯定、指證係基於自\n    由意識、彼此常有互供有無之現象等）相符者，自應認其所\n    為不利於被告之指證已有前述各項相關事實情況證據以資佐\n    證，而強化其證言之憑信性，此時，法院即應依其職權本於\n    法律規定之採證法則判斷其證言之憑信性以認定事實，不應\n    執著於未能查得其他「直接物證」或其他所謂之直接「補強\n    證據」，即對購買者所為對被告不利之明確指證，全然棄置\n    不採，而遽為被告無罪之諭知，惟依前述說明，本件犯罪樣\n    態既無任何物證及證人指證以外之其他直接證據以資參證，\n    因此，所謂之補強證據應從廣義解釋，認前述與判斷證人證\n    言是否可信之各項相關事實情況均包括之，從而，法院為判\n    斷購買者即證人所為之購買來源證述是否真實可信，仍應進\n    一步詳查與本案相關之各項情況及事實，亦即購買者即證人\n    與被告之關係、彼此交往之背景、有無重大恩怨糾葛，確認\n    證人無懷怨誣陷被告之可能後，再觀察被告是否有沾染毒品\n    之惡習及其與毒品接觸之程度，以及證人所述其向被告購買\n    毒品之時間、地點、價額、次數及數量是否明確，前後是否\n    相符，有無重大矛盾或瑕疵（如輕微出入尚無大礙，惟應敘\n    明原委），其所為不利於被告指證之語意是否堅決，態度是\n    否肯定，其指證購買甲基安非他命情節是否合於經驗法則（\n    即常情）及論理法則（即常理），被告否認之態度以及所為\n    各項辯解及其聲請調查之證據是否可推翻證人對其不利之指\n    證而採為其有利之認定依據等各項相關情況（以上各項與案\n    件相關之情況均應認屬間接情況證據，應可解釋為廣義之補\n    強證據），以作為認定被告是否犯罪之依據。\n(四)、本件證人丙○○證稱：伊戒治出來後因伊朋友也有在用毒品\n    ，伊朋友給伊乙○○之電話說可以透過張美拿到毒品，於案\n    發前約認識乙○○2 個月，與乙○○並無仇恨等語，是證人\n    丙○○與被告之關係，依二人彼此交往之背景，並無重大恩\n    怨糾葛，足見證人並無懷怨誣陷被告之可能，再參酌被告長\n    期有沾染毒品之惡習，與毒品接觸之程度亦甚深，業如前述\n    ，而證人丙○○前述其向被告購買毒品之時間、地點、價額\n    前後大致均相符，並無重大矛盾或瑕疵，且其自始至終均指\n    證其所施用毒品來源確係被告，指證歷歷，是證人丙○○對\n    被告不利之指證，綜合上情，應可作為認定被告犯罪之依據\n    。\n(五)、末按甲基安非他命等毒品，本無一定之公定價格，是其各次\n    買賣之價格，當亦各有差異，或隨供需雙方之資力、關係之\n    深淺、需求之數量、貨源之充裕與否、販賣者對於資金之需\n    求程度，以及政府查緝之態度，進而為各種不同之風險評估\n    ，而為機動性之調整，是其價格標準，自非一成不變，且販\n    賣者從各種「價差」或「量差」或「純度」謀取利潤方式，\n    亦有差異，然其所圖利益之非法販賣行為目的，則屬相同，\n    並無二致。因之，販賣利得，除經被告坦承，或其價量至臻\n    明確外，確實難以究其原委。然按一般民眾普遍認知之毒品\n    非法交易，向為政府查禁森嚴且重罰不寬貸，衡諸常情，倘\n    非有利可圖，絕無平白甘冒被重罰風險之理，從而，舉凡有\n    償交易，除足反證其確另基於某種非圖利本意之關係外，通\n    常尚難因無法查悉其買進、賣出之差價，而諉無營利之意思\n    ，或阻卻販賣犯行之追訴。查被告為智識正常之成年人，對\n    於甲基安非他命價格昂貴，取得不易，毒品交易為政府檢警\n    機關嚴予取締之犯罪，法律並就此懸有重典處罰，當知之甚\n    稔，而被告與證人丙○○僅屬一般交往，倘無從中賺取差價\n    或投機貪圖小利，豈有甘冒重典依購入價格轉售或代購之理\n    ？是被告主觀上具有營利之意圖，亦臻明確。\n(五)、綜上各情參互以析，被告上開所辯，核係事後卸責之詞，無\n    足採信，本案事證已臻明確，被告上開販賣第二級毒品犯行\n    ，洵堪認定，應依法論科。\n二、論罪與科刑：\n(一)、被告行為後，毒品危害防制條例第4 條2 項業經修正，並經\n    總統於98年5 月20日公布，而於同年月22日起施行，修正前\n    該條例第4 條第2 項原規定：「製造、運輸、販賣第二級毒\n    品者，處無期徒刑或七年以上有期徒刑，得併科新臺幣七百\n    萬元以下罰金」，修正後同條第2 項則規定：「製造、運輸\n    、販賣第二級毒品者，處無期徒刑或七年以上有期徒刑，得\n    併科新臺幣一千萬元以下罰金」；比較新舊法之結果，修正\n    後之規定並未較有利於被告，依刑法第2 條第1 項前段之規\n    定，本件自應適用被告行為時即修正前之毒品危害防制條例\n    第4 條第2 項規定。\n(二)、核被告所為，係犯修正前毒品危害防制條例第4 條第2 項之\n    販賣第二級毒品罪；被告販賣前後持有第二級毒品甲基安非\n    他命之低度行為，為其販賣之高度行為所吸收，不另論罪。\n    查被告前有如事實欄所述科刑執行完畢情形，有臺灣高等法\n    院被告前案紀錄表在卷可按，其受有期徒刑執行完畢後，於\n    五年內故意再犯本案之罪，係屬累犯，應依刑法第47條第1\n    項之規定加重其刑，惟因法定刑為無期徒刑者不得加重，故\n    僅就有期徒刑及罰金刑部分加重其刑。爰審酌被告素行非佳\n    ，有多次違反毒品危害防制條例等前案紀錄，不思以正途謀\n    生，無視於政府推動禁毒的政策，使毒品甲基安非他命流入\n    市面，毒害他人，但念獲利並非鉅大，與坊間大盤販賣毒品\n    者之犯罪情節顯有不同，及被告之智識程度（國小肄業）、\n    生活狀況，及其犯罪之手段、動機、目的及被告犯後否認犯\n    行並無悔意之態度等一切情狀，量處如主文所示之刑。\n(三)、被告販賣第二級毒品安非他命所得2000元，雖未扣案，但既\n    為販毒所得，應依毒品危害防制條例第19條第1 項規定併予\n    宣告沒收，如全部或一部不能沒收，以其財產抵償之。另為\n    警扣得之門號0000000000號SIM 卡1 個，則為被告所有供本\n    案犯罪所用之物，應依法宣告沒收。至於經警方查扣之海洛\n    因1 包（淨重0.28公克）、安非他命6 包（淨重共計5.52公\n    克）、分裝袋6 個、海洛因4 包（淨重0.87公克）、安非他\n    命6 包（淨重5.02公克）、電子磅秤1 台、玻璃球管吸食器\n    6 支、吸管勺子3 支、安非他命吸食過濾器1 支、分裝袋共\n    計356 個等物，無證據足以證明與被告本件販賣第二級毒品\n    犯行直接關涉，爰不併予宣告沒收。\n參、無罪部分：\n一、公訴意旨另略以：被告乙○○基於販賣第二級毒品甲基安非\n    他命之犯意，於97年1 月2 日16時許，乙○○與丙○○相約\n    在臺北縣板橋市○○路○ 段255 巷口進行甲基安非他命毒品\n    交易時，為警當場查獲而未得逞，並從乙○○身上查扣海洛\n    因1 包（淨重0.28公克）、安非他命6 包（淨重共計5.52公\n    克）、分裝袋6 個及SIM 卡1 張。復經其同意由警方至臺北\n    縣板橋市○○街49巷33號2 樓搜索，並扣得海洛因4 包（淨\n    重0.87公克）、安非他命6 包（淨重5.02公克）、電子磅秤\n    1 台、玻璃球管吸食器6 支、吸管勺子3 支、安非他命吸食\n    過濾器1 支、分裝袋共計356 個。因指被告乙○○涉犯毒品\n    危害防制條例第4 條第6 項、第2 項販賣第二級毒品未遂罪\n    嫌。\n二、按犯罪事實應依證據認定之，無證據不得認定其犯罪事實；\n    又不能證明被告犯罪者，應諭知無罪之判決，刑事訴訟法第\n    154條第2項、第301條第1項分別定有明文。又認定犯罪事實\n    ，須依積極證據，苟積極證據不足為不利於被告事實之認定\n    時，即應為有利於被告之認定，更不必有何有利之證據，最\n    高法院30年上字第816號判例可資參照。而所謂「積極證據\n    足以為不利被告事實之認定」，依據同院76年臺上字第4986\n    號判例意旨，係指據為訴訟上證明之全盤證據資料，在客觀\n    上已達於通常一般之人均不致於有所懷疑，而得確信被告確\n    曾犯罪之程度；若未達到此一程度，而有合理懷疑之存在時\n    ，即無從為被告有罪之確信。且按認定犯罪事實應依證據，\n    為刑事訴訟法所明定，故被告否認犯罪事實所持之辯解，縱\n    屬不能成立，仍非有積極證據足以證明其犯罪行為，不能遽\n    為有罪之認定（最高法院30年上字第1831號判例參照）。\n三、公訴意旨指被告乙○○涉有前開販賣第二級毒品未遂犯行，\n    無非以被告之供述、證人丙○○於警詢及偵查中之證述，及\n    證人即承辦員警甲○○於偵查中之證述，雙向通聯紀錄2 份\n    ，臺灣板橋地方法院檢察署97年度毒偵字第584 號聲請簡易\n    判決處刑書1 份，扣案之甲基安非他命12包及照片28張、內\n    政部警政署刑事警察局97年1 月14日刑鑑字第0970003274號\n    鑑定書等為其論據。訊之被告乙○○固坦承有於前揭時地與\n    丙○○電話聯絡之事實，惟堅決否認有何販賣第二級毒品甲\n    基安非他命犯行，辯稱：97年1 月2 日伊係剛自台北購買完\n    毒品要返家，路上接到丙○○電話，問伊有無毒品，1 包多\n    少錢，伊則問丙○○有無將DVD 光碟帶出來，可不可以還伊\n    ，才與丙○○相約見面，並非為了交易毒品相約見面等語。\n    經查：\n(一)、本件販賣第二級毒品甲基安非他命案查獲之經過，係證人丙\n    ○○於97年1 月2 日為警查獲持有毒品甲基安非他命，經丙\n    ○○供出毒品來源為被告後，配合警方電話聯絡被告，佯稱\n    購買5, 000元甲基安非他命，並相約前揭時地交易，經警在\n    前開地點埋伏而查獲被告等情，業據證人丙○○於本院審理\n    時（見本院97年度訴字第1803號刑事卷第190 、191 頁）；\n    證人即承辦員警甲○○於偵查及本院審理時分別證述在卷（\n    見同上偵查卷第110 頁、本院99年3 月30日審理筆錄第5頁\n    ），互核相符，堪信為真實。\n(二)、證人丙○○於本院審理時證稱：「（你跟被告說什麼？）我\n    說還她錢。警察的意思是說叫我要去，就是要我說是跟誰買\n    ，我的意思是說我先還她錢。（你電話中有請被告帶藥出來\n    嗎？你電話中怎麼跟乙○○說？）好像有，因為是警察跟我\n    說要這樣。（你說警察從你電話中搜尋到乙○○電話之後，\n    你打電話給乙○○是跟她說什麼？）請她幫我調5 千，順便\n    要還她錢。」等語（見本院97年度訴字第1803號刑事卷第19\n    1 頁）。證人甲○○則稱：「（問：丙○○當天撥手機，撥\n    了幾通？）那時候快要2 點，大概1 點55分左右，撥給大姐\n    之後就直接通了，他們講一會兒，因為對談都是他們在談，\n    他講得很小聲，那時候我在辦公室的管制門，因為我怕警察\n    無線電的聲音會發出來，所以他跟大姐的對話我不清楚，等\n    丙○○講完之後，他跟我說他已經約好了。（問：丙○○有\n    沒有說他約好是怎麼約？）就是約到板橋中山路那邊麥當勞\n    之後，到那裡再打電話給大姐。（問：你是否清楚丙○○約\n    的內容？是要什麼毒品或是要做什麼？）隱隱約約有聽到丙\n    ○○說大姐那邊有沒有，他急著要。（問：你有沒有聽到丙\n    ○○要還大姐錢？）沒有，最後我有聽到丙○○說『我要\n    5000 塊 』。（問：所以你有沒有聽到丙○○說要還大姐\n    3000塊的事情？）沒有。（問：你有沒有聽到他們講到什麼\n    DDT 或是光碟片的事情？）沒有，他們講的時間很短，沒有\n    多久就結束了，他們講完電話的時候，丙○○就主動告知我\n    說他已經跟大姐約好了，跟她講說他要5000塊的安非他命。\n    」等語（見本院99年3 月30日審理筆錄第12、13頁），顯見\n    警方所謂丙○○有於前揭時地與被告電話聯絡買賣甲基安非\n    他命毒品事宜及交易甲基安非他命毒品，均係出於證人丙○\n    ○之告知，渠等並未親自聽聞丙○○與被告間聯絡買賣海洛\n    因毒品之電話內容，而丙○○究係以返還前積欠被告交易毒\n    品之金錢為由，抑或以要購買毒品甲基安非他命而與被告聯\n    繫，即有疑義。又證人丙○○既係配合警方聯絡被告交易毒\n    品，並由警方在交易地點埋伏，是其意在使被告受刑事處分\n    ，其證言之真偽，是否與事實相符，自應詳加辨析。再參以\n    證人丙○○所謂與被告間之聯絡及交易甲基安非他命，均係\n    其個人進行，僅由警方在場埋伏，而警方未於交易時親見親\n    聞有金錢與毒品之交易，亦非無疑，是證人丙○○前揭所述\n    ，難謂無瑕。至證人丙○○有於前揭交易時間前與被告間電\n    話聯絡之紀錄，固有通聯紀錄1 件附卷可稽，並為被告所不\n    否認（見同上偵查卷第103 頁），惟該通聯紀錄之通話內容\n    為何，僅有證人丙○○之證詞，且被告否認該通電話係丙○\n    ○要向伊購買毒品，自尚難因有該電話通聯，遽認證人丙○\n    ○證稱伊是以電話聯絡被告購買毒品甲基安非他命屬實。\n(三)、又按刑法上所謂陷害教唆，係指行為人原無犯罪之意思，純\n    因具有司法警察權者之設計誘陷，以唆使其萌生犯意，待其\n    形式上符合著手於犯罪行為之實行時，再予逮捕者而言。此\n    種「陷害教唆」，因行為人原無犯罪之意思，具有司法警察\n    權者復伺機逮捕，係以不正當手段入人於罪，尚難遽認被陷\n    害教唆者成立犯罪。至刑事偵查技術上所謂之「釣魚」者，\n    則指對於原已犯罪或具有犯罪故意之人，司法警察於獲悉後\n    為取得證據，以設計引誘之方式，佯與之為對合行為，使其\n    暴露犯罪事證，待其著手於犯罪行為之實行時，予以逮捕、\n    偵辦者而言。後者因犯罪行為人主觀上原即有犯罪之意思，\n    倘客觀上又已著手於犯罪行為之實行時，自得成立未遂犯，\n    與「陷害教唆」情形迥然有別。「釣魚」因屬偵查犯罪技巧\n    之範疇，並未違反憲法對於基本人權之保障，且於公共利益\n    之維護有其必要性，故依「釣魚」方式所蒐集之證據資料，\n    非無證據能力（最高法院96年台上字第6628號判決意旨參照\n    ）。本院綜觀全卷被告所涉於97年1 月2 日販賣甲基安非他\n    命予丙○○之犯行，僅有證人丙○○之單一指述，別無其他\n    證據可資佐參，而其證詞尚非無瑕，已如前述；況縱證人丙\n    ○○所述前揭與被告聯絡及交易毒品甲基安非他命屬實，惟\n    此係配合警方之查緝行動而為，是被告於證人丙○○上開聯\n    絡購買甲基安非他命前，是否即有販賣甲基安非他命之營利\n    意圖，自有再行斟酌之餘地。是本案並無積極證據足資證明\n    於證人丙○○配合警方查緝毒品與被告為購買甲基安非他命\n    電話聯絡前，被告即有販賣甲基安非他命之犯意。故縱證人\n    丙○○有於前揭時地與被告電話聯絡並交易第二級毒品甲基\n    安非他命，依檢察官所舉之證據尚無從證明被告於本案前，\n    有其他販賣甲基安非他命予證人丙○○之行為，是被告於97\n    年1 月2 日販賣第二級毒品甲基安非他命予丙○○之行為，\n    係證人丙○○為配合警方查緝毒品，而配合員警設計引誘教\n    唆所致，核屬「陷害教唆」無訛，參諸前揭說明，自難科以\n    此部分被告販賣第二級毒品罪責。\n四、綜上所述，檢察官所提出之證據，尚不能使本院形成被告此\n    部分於97年1 月2 日有販賣第二級毒品予證人丙○○有罪之\n    確信。此外，復查無其他積極證據足資證明被告有此部分被\n    訴販賣第二級毒品甲基安非他命之犯行。揆諸首揭說明，自\n    屬不能證明被告此部分之犯罪，自應諭知無罪之判決。\n據上論斷，應依刑事訴訟法第299 條第1 項前段、第301 條第1\n項，毒品危害防制條例第4 條第2 項（修正前）、第19條第1 項\n，刑法第11條前段、第2 條第1 項前段、第47條第1 項，判決如\n主文。\n本案經檢察官陳宣每到庭執行職務\n中    華    民    國    99    年    5    月    12     日\n                  刑事第十五庭  審判長法  官  吳幸娥\n                                      法  官  許炎灶\n                                      法  官  廖欣儀\n以上正本證明與原本無異。\n如不服本判決，應於判決送達後10日內敘明上訴理由，向本院提\n出上訴狀 (應附繕本)， 上訴於臺灣高等法院。其未敘述上訴理\n由者，應於上訴期間屆滿後20日內向本院補提理由書「切勿逕送\n上級法院」。\n                                      書記官  黃頌棻\n中    華    民    國    99    年    5    月    14    日\n附錄本案論罪科刑法條全文：\n毒品危害防制條例第4條（修正前）\n製造、運輸、販賣第一級毒品者，處死刑或無期徒刑；處無期徒\n刑者，得併科新臺幣一千萬元以下罰金。\n製造、運輸、販賣第二級毒品者，處無期徒刑或七年以上有期徒\n刑，得併科新臺幣七百萬元以下罰金。\n製造、運輸、販賣第三級毒品者，處五年以上有期徒刑，得併科\n新臺幣五百萬元以下罰金。\n製造、運輸、販賣第四級毒品者，處三年以上十年以下有期徒刑\n，得併科新臺幣三百萬元以下罰金。\n製造、運輸、販賣專供製造或施用毒品之器具者，處一年以上七\n年以下有期徒刑，得併科新臺幣一百萬元以下罰金。\n前五項之未遂犯罰之。",
  "structure": {
    "main": "乙○○販賣第二級毒品，累犯，處有期徒刑柒年陸月；扣案之門\n號0000000000號SIM 卡壹枚沒收，販賣第二級毒品所\n得財物新臺幣貳仟元沒收，如全部或一部不能沒收時，以其財產\n抵償之。\n其餘被訴販賣第二級毒品未遂部分無罪。",
    "fact": "一、乙○○前曾於民國96年間因施用毒品案件，經本院以96年度\n    簡字第4695號判決判處有期徒刑六月，減為有期徒刑三月確\n    定，其後於96年10月4 日易科罰金執行完畢。詎其猶不知悔\n    改，明知甲基安非他命係屬毒品危害防制條例第2 條第2 項\n    第2 款所稱之第二級毒品，不得販賣、持有，竟基於販賣第\n    二級毒品甲基安非他命之犯意，由乙○○以門號為00000000\n    00號行動電話與丙○○門號為0000000000號行動電話聯絡購\n    買毒品，並於96年11月2 月1 時許，在臺北縣板橋市○○路\n    ○ 段257 號前，約定以每公克新台幣（下同）5,000 元之價\n    格販賣甲基安非他命1 包予丙○○施用，丙○○旋取得毒品\n    並先交付2000元予乙○○，尚積欠乙○○3000元。嗣於97年\n    1 月2 日16時許，在臺北縣板橋市○○路○ 段255 巷口為警\n    當場查獲，並從乙○○身上查扣海洛因1 包（淨重0.28公克\n    ）、安非他命6 包（淨重共計5.52公克）、分裝袋6 個及SI\n    M 卡（0000000000號）1 張。復經其同意由警方至臺北縣板\n    橋市○○街49巷33號2 樓搜索，並扣得海洛因4 包（淨重0.\n    87公克）、安非他命6 包（淨重5.02公克）、電子磅秤1 台\n    、玻璃球管吸食器6 支、吸管勺子3 支、安非他命吸食過濾\n    器1 支、分裝袋共計356 個。\n二、案經臺北縣政府警察局中和分局報請臺灣板橋地方法院檢察\n    署檢察官偵查起訴。",
    "reason": "壹、證據能力：\n一、按被告之自白，非出於強暴、脅迫、利誘、詐欺、疲勞訊問\n    、違法羈押或其他不正之方法，且與事實相符者，得為證據\n    ，刑事訴訟法第156 條第1 項有明文規定。被告之辯護人為\n    被告辯稱：被告之警詢過程，錄音不連續，疑有警員干擾被\n    告，且被告有藥癮發作，注意力不集中之情形，因被告自白\n    非出於任意性，依刑事訴訟法第156 條第1 項之規定，無證\n    據能力云云。查：經本院勘驗被告之警詢錄音帶內容，其結\n    果為「警方除部分問題係事先打好之外，其餘係採一問一答\n    的方式製作，國台語夾雜，語氣正常，但中間有多次疑似錄\n    音中斷，且警詢錄音帶為60分鐘1 卷，但與警詢筆錄所記載\n    製作筆錄之時間長達2 小時又40分鐘，其間警迫問被告是否\n    藥癮發作部分，被告注意力似乎並不集中」等語，有本院97\n    年10月3 日準備程序筆錄1 份可參（見本院97年度訴字第\n    1803 號 刑事卷第167 至173 頁），而製作被告筆錄之證人\n    甲○○固證稱：伊製作被告之警詢筆錄時，有把錄音機打開\n    ，打開之後就沒有關掉直到詢問結束等語，然被告製作筆錄\n    之過程未顯現於錄音帶之內容計有1 小時又40分鐘，員警未\n    注意錄音帶是否需換面，或需更換一卷錄意帶，顯然不合常\n    理，足徵被告之警詢確有可能未全程連續錄音，再者，被告\n    於第二次警詢時，被告一開始是否認拿藥去賣，表示伊是出\n    來要跟丙○○拿光碟片，但被告之此段陳述未見於被告之警\n    詢筆錄內，而在被告做出此部分陳述後，即出現疑似錄音中\n    斷的聲音，經此中斷，被告又出現「就是黃文祥打電話給我\n    ，他說要調藥，我拿去給他。」之回答，足徵製作筆錄過程\n    無法排除有警員介入干擾被告自由意志之情況，況被告於製\n    作筆錄過程中，亦出現被告疑似藥癮發作，注意力不集中之\n    狀況，綜上各情，自難認被告之警詢自白有證據能力。\n二、至被告乙○○之辯護人為被告乙○○抗辯：證人丙○○於警\n    詢時所為之證述，為被告以外之人於審判外之陳述，依刑事\n    訴訟法第159 條第1 項之規定，無證據能力。惟按被告以外\n    之人於檢察事務官、司法警察官或司法警察調查中所為之陳\n    述，與審判中不符時，其先前之陳述具有較可信之特別情況\n    ，且為證明犯罪事實存否所必要者，得為證據。刑事訴訟法\n    第159 條之2 定有明文。至警詢中之陳述具備可信性與必要\n    性，事實審法院除應衡酌該警詢筆錄作成之外部情況，就詢\n    問有無出於不正方法、陳述是否出於非任意性等適法性與否\n    為整體之考量外，應兼顧基於發見真實之需求，具有重要關\n    係。經查：證人丙○○於警詢之供述，依其記載內容，係採\n    取一問一答方式，且其於警詢時之供述較接近案發時點，記\n    憶應較為清晰，憑信性甚高，而當時未直接面對被告乙○○\n    心理壓力較小，且其於警詢、偵查所為證述之內容，其對基\n    本事實之供述始終一致，況證人丙○○與被告乙○○間亦無\n    仇恨，業據證人承述在卷，自無設詞誣陷友人，且所供並涉\n    及本身犯罪之自白，應無甘冒身陷囹圄之危險而為虛偽陳述\n    之可能，是證人丙○○之警詢筆錄具有可信之特別情況，而\n    丙○○之警詢筆錄，基於發見真實之需求，並有重要關係，\n    而為證明犯罪事實之存否並有必要，故其於警詢之陳述，本\n    院認符合刑事訴訟法第159 條之2 之情形，認應有證據能力\n    。\n三、第按被告以外之人於審判外之陳述，雖不符前4 條之規定，\n    而經當事人於審判程序同意作為證據，法院審酌該言詞陳述\n    或書面陳述作成時之情況，認為適當者，亦得為證據。當事\n    人或辯護人於法院調查證據時，知有第159 條第1 項不得為\n    證據之情形，而未於言詞辯論終結前聲明異議者，視為有前\n    項之同意。刑事訴訟法第159 條之5 定有明文。本案被告乙\n    ○○及其辯護人於本院審理時對於檢察官所提各項證據方法\n    之證據能力均表示「沒意見」（上述一、二除外），且本案\n    言詞辯論終結前，被告並未爭執被告以外之人於審判外之言\n    詞及書面陳述，無證據能力，揆諸上開規定，應認被告乙○\n    ○及其辯護人已同意上開各該證據方法得作為證據，而本院\n    審酌上開各該證據均非非法取得之證據，並無證據力明顯過\n    低之情形，復經本院於審判期日就上開證據依法進行調查、\n    辯論，依法自有證據能力，附此敘明。\n貳、有罪部分：\n一、得心證之理由：訊據被告乙○○雖坦承與證人丙○○認識，\n    惟矢口否認有何販賣第二級毒品之犯行，辯稱：96年11月2\n    日與丙○○見面，但只是討論安非他命之價格，並未交易云\n    云。然查：\n(一)、被告於96年11月2 月1 時許，在臺北縣板橋市○○路○ 段25\n    7 號前，以每公克5,000 元之價格販賣甲基安非他命1 包予\n    丙○○施用，丙○○先交付2000元予被告，尚欠被告3000元\n    等情，業據證人丙○○迭於警詢時、偵查中及審理時均結證\n    屬實（見97年度偵字第2116號偵查卷第16、19、98至99頁，\n    本院97年度訴字第1803號刑事卷第189 至190 頁）；查依證\n    人丙○○自警詢、偵查中及本院審理時經具結後之陳述勾稽\n    ，就正確之毒品交易時間、價額給付方式等項縱稍有未符，\n    但始終未曾否認其購得毒品之來源確係被告，指證歷歷，彰\n    彰明甚，且證人丙○○與被告並無何重大怨隙，應無設詞構\n    陷之理，更可認定證人丙○○證稱其確有於上開時地自被告\n    購買毒品甲基安非他命一節，要屬徵而可信。\n(二)、另證人丙○○於97年1 月2 為警查獲時所採尿液確有甲基安\n    非他命毒品之反應，有臺灣板橋地方法院檢察署97年度毒偵\n    字第584 號聲請簡易判決處刑書2 份（見同上偵查卷第11 4\n    、115 頁）附卷足憑，足徵證人丙○○確有施用第二級毒品\n    之情形。另對照被告乙○○前於87年間因違反麻醉藥品管理\n    處罰條例案件，經判處應執行有期徒刑6 年；因前於93年間\n    因連續販賣第二級毒品及轉讓禁藥等案件，經判處8 年4 月\n    確定，又曾於94年間因施用毒品案件，經檢察官聲請臺灣臺\n    北地方法院裁定送觀察、勒戒及強制戒治後，於95年8 月29\n    日執行完畢釋放，並經臺灣臺北地方法院檢察署檢察官以95\n    年度戒毒偵字第131 號不起訴處分確定在案。其前又曾於96\n    年間因施用毒品案件，經本院以96年度簡字第4695號判決判\n    處有期徒刑六月，減為有期徒刑三月確定，又於97年間因施\n    用第一、二級毒品案件，經本院以97年度訴字第2043號判處\n    有期徒刑1 年2 月等情觀之，有臺灣高等法院被告前案紀錄\n    表1 份可參，足徵被告確有沾染毒品之惡習及其與毒品接觸\n    之程度甚重。\n(三)、第按目前社會上非法販賣海洛因、安非他命犯罪之型態不一\n    ，有所謂「大盤」、「中盤」或「小盤」販賣者，亦有吸食\n    者彼此之間偶而互供有無之零星交易者，在屬前者之情形（\n    即大中小盤），經深入查證，如機會掌握得宜，或許可查獲\n    與非法販賣安非他命有關之販賣工具（諸如電子秤、帳冊、\n    分裝袋等物）或多數知情或購買者等證人之證詞，以作為法\n    院判決認定之依據，然在後者之情形（即吸食者之間偶發性\n    零星交易），因該種零星交易犯罪行為，在性質上本無須使\n    用任何販賣工具，亦無須記載帳冊，且其交易時間短暫（僅\n    須數秒之時間），交易方法簡單隱密（在不易為人注意之場\n    所一手交錢，一手交貨），交易對象單純（買方僅一人），\n    交易時未必有他人在場知悉其事，亦無所謂犯罪之被害人，\n    在被告堅不承認其犯行之情況下，茍非警方事先獲知情報而\n    埋伏於交易現場當場查獲，否則往往僅能在事後依據購買者\n    之供出來源作為認定事實之主要依據，法院縱再作深入之調\n    查，基於該種犯罪之性質所侷限，亦無從查得其他直接明顯\n    之關連性物證以為補強佐證，其有效之調查途徑在客觀上顯\n    然已告窮盡。本件被告涉嫌非法販賣甲基安非他命予證人丙\n    ○○之犯罪型態即屬此類情形之標準型態，惟法院固不應僅\n    憑購買者片面之指證，不查明是否與事實相符即遽行據以認\n    定被告之非法販賣甲基安非他命犯行，亦不應不調查其他相\n    關事證，即片面依購買者之指證而認定被告犯罪，然於此不\n    得不予特別指明者，即安非他命購買者所為不利於被告之指\n    證在證據法則上亦屬「人證」之一種，與「被告之自白」經\n    法律特別規定不得作為認定事實唯一證據之情形顯然不同，\n    茍購買者之指證並無「重大」矛盾瑕疵，亦未違背經驗法則\n    與論理法則，且核與案件之其他相關事實（如有吸用毒品之\n    背景、彼此無重大仇隙，指證態度明確肯定、指證係基於自\n    由意識、彼此常有互供有無之現象等）相符者，自應認其所\n    為不利於被告之指證已有前述各項相關事實情況證據以資佐\n    證，而強化其證言之憑信性，此時，法院即應依其職權本於\n    法律規定之採證法則判斷其證言之憑信性以認定事實，不應\n    執著於未能查得其他「直接物證」或其他所謂之直接「補強\n    證據」，即對購買者所為對被告不利之明確指證，全然棄置\n    不採，而遽為被告無罪之諭知，惟依前述說明，本件犯罪樣\n    態既無任何物證及證人指證以外之其他直接證據以資參證，\n    因此，所謂之補強證據應從廣義解釋，認前述與判斷證人證\n    言是否可信之各項相關事實情況均包括之，從而，法院為判\n    斷購買者即證人所為之購買來源證述是否真實可信，仍應進\n    一步詳查與本案相關之各項情況及事實，亦即購買者即證人\n    與被告之關係、彼此交往之背景、有無重大恩怨糾葛，確認\n    證人無懷怨誣陷被告之可能後，再觀察被告是否有沾染毒品\n    之惡習及其與毒品接觸之程度，以及證人所述其向被告購買\n    毒品之時間、地點、價額、次數及數量是否明確，前後是否\n    相符，有無重大矛盾或瑕疵（如輕微出入尚無大礙，惟應敘\n    明原委），其所為不利於被告指證之語意是否堅決，態度是\n    否肯定，其指證購買甲基安非他命情節是否合於經驗法則（\n    即常情）及論理法則（即常理），被告否認之態度以及所為\n    各項辯解及其聲請調查之證據是否可推翻證人對其不利之指\n    證而採為其有利之認定依據等各項相關情況（以上各項與案\n    件相關之情況均應認屬間接情況證據，應可解釋為廣義之補\n    強證據），以作為認定被告是否犯罪之依據。\n(四)、本件證人丙○○證稱：伊戒治出來後因伊朋友也有在用毒品\n    ，伊朋友給伊乙○○之電話說可以透過張美拿到毒品，於案\n    發前約認識乙○○2 個月，與乙○○並無仇恨等語，是證人\n    丙○○與被告之關係，依二人彼此交往之背景，並無重大恩\n    怨糾葛，足見證人並無懷怨誣陷被告之可能，再參酌被告長\n    期有沾染毒品之惡習，與毒品接觸之程度亦甚深，業如前述\n    ，而證人丙○○前述其向被告購買毒品之時間、地點、價額\n    前後大致均相符，並無重大矛盾或瑕疵，且其自始至終均指\n    證其所施用毒品來源確係被告，指證歷歷，是證人丙○○對\n    被告不利之指證，綜合上情，應可作為認定被告犯罪之依據\n    。\n(五)、末按甲基安非他命等毒品，本無一定之公定價格，是其各次\n    買賣之價格，當亦各有差異，或隨供需雙方之資力、關係之\n    深淺、需求之數量、貨源之充裕與否、販賣者對於資金之需\n    求程度，以及政府查緝之態度，進而為各種不同之風險評估\n    ，而為機動性之調整，是其價格標準，自非一成不變，且販\n    賣者從各種「價差」或「量差」或「純度」謀取利潤方式，\n    亦有差異，然其所圖利益之非法販賣行為目的，則屬相同，\n    並無二致。因之，販賣利得，除經被告坦承，或其價量至臻\n    明確外，確實難以究其原委。然按一般民眾普遍認知之毒品\n    非法交易，向為政府查禁森嚴且重罰不寬貸，衡諸常情，倘\n    非有利可圖，絕無平白甘冒被重罰風險之理，從而，舉凡有\n    償交易，除足反證其確另基於某種非圖利本意之關係外，通\n    常尚難因無法查悉其買進、賣出之差價，而諉無營利之意思\n    ，或阻卻販賣犯行之追訴。查被告為智識正常之成年人，對\n    於甲基安非他命價格昂貴，取得不易，毒品交易為政府檢警\n    機關嚴予取締之犯罪，法律並就此懸有重典處罰，當知之甚\n    稔，而被告與證人丙○○僅屬一般交往，倘無從中賺取差價\n    或投機貪圖小利，豈有甘冒重典依購入價格轉售或代購之理\n    ？是被告主觀上具有營利之意圖，亦臻明確。\n(五)、綜上各情參互以析，被告上開所辯，核係事後卸責之詞，無\n    足採信，本案事證已臻明確，被告上開販賣第二級毒品犯行\n    ，洵堪認定，應依法論科。\n二、論罪與科刑：\n(一)、被告行為後，毒品危害防制條例第4 條2 項業經修正，並經\n    總統於98年5 月20日公布，而於同年月22日起施行，修正前\n    該條例第4 條第2 項原規定：「製造、運輸、販賣第二級毒\n    品者，處無期徒刑或七年以上有期徒刑，得併科新臺幣七百\n    萬元以下罰金」，修正後同條第2 項則規定：「製造、運輸\n    、販賣第二級毒品者，處無期徒刑或七年以上有期徒刑，得\n    併科新臺幣一千萬元以下罰金」；比較新舊法之結果，修正\n    後之規定並未較有利於被告，依刑法第2 條第1 項前段之規\n    定，本件自應適用被告行為時即修正前之毒品危害防制條例\n    第4 條第2 項規定。\n(二)、核被告所為，係犯修正前毒品危害防制條例第4 條第2 項之\n    販賣第二級毒品罪；被告販賣前後持有第二級毒品甲基安非\n    他命之低度行為，為其販賣之高度行為所吸收，不另論罪。\n    查被告前有如事實欄所述科刑執行完畢情形，有臺灣高等法\n    院被告前案紀錄表在卷可按，其受有期徒刑執行完畢後，於\n    五年內故意再犯本案之罪，係屬累犯，應依刑法第47條第1\n    項之規定加重其刑，惟因法定刑為無期徒刑者不得加重，故\n    僅就有期徒刑及罰金刑部分加重其刑。爰審酌被告素行非佳\n    ，有多次違反毒品危害防制條例等前案紀錄，不思以正途謀\n    生，無視於政府推動禁毒的政策，使毒品甲基安非他命流入\n    市面，毒害他人，但念獲利並非鉅大，與坊間大盤販賣毒品\n    者之犯罪情節顯有不同，及被告之智識程度（國小肄業）、\n    生活狀況，及其犯罪之手段、動機、目的及被告犯後否認犯\n    行並無悔意之態度等一切情狀，量處如主文所示之刑。\n(三)、被告販賣第二級毒品安非他命所得2000元，雖未扣案，但既\n    為販毒所得，應依毒品危害防制條例第19條第1 項規定併予\n    宣告沒收，如全部或一部不能沒收，以其財產抵償之。另為\n    警扣得之門號0000000000號SIM 卡1 個，則為被告所有供本\n    案犯罪所用之物，應依法宣告沒收。至於經警方查扣之海洛\n    因1 包（淨重0.28公克）、安非他命6 包（淨重共計5.52公\n    克）、分裝袋6 個、海洛因4 包（淨重0.87公克）、安非他\n    命6 包（淨重5.02公克）、電子磅秤1 台、玻璃球管吸食器\n    6 支、吸管勺子3 支、安非他命吸食過濾器1 支、分裝袋共\n    計356 個等物，無證據足以證明與被告本件販賣第二級毒品\n    犯行直接關涉，爰不併予宣告沒收。\n參、無罪部分：\n一、公訴意旨另略以：被告乙○○基於販賣第二級毒品甲基安非\n    他命之犯意，於97年1 月2 日16時許，乙○○與丙○○相約\n    在臺北縣板橋市○○路○ 段255 巷口進行甲基安非他命毒品\n    交易時，為警當場查獲而未得逞，並從乙○○身上查扣海洛\n    因1 包（淨重0.28公克）、安非他命6 包（淨重共計5.52公\n    克）、分裝袋6 個及SIM 卡1 張。復經其同意由警方至臺北\n    縣板橋市○○街49巷33號2 樓搜索，並扣得海洛因4 包（淨\n    重0.87公克）、安非他命6 包（淨重5.02公克）、電子磅秤\n    1 台、玻璃球管吸食器6 支、吸管勺子3 支、安非他命吸食\n    過濾器1 支、分裝袋共計356 個。因指被告乙○○涉犯毒品\n    危害防制條例第4 條第6 項、第2 項販賣第二級毒品未遂罪\n    嫌。\n二、按犯罪事實應依證據認定之，無證據不得認定其犯罪事實；\n    又不能證明被告犯罪者，應諭知無罪之判決，刑事訴訟法第\n    154條第2項、第301條第1項分別定有明文。又認定犯罪事實\n    ，須依積極證據，苟積極證據不足為不利於被告事實之認定\n    時，即應為有利於被告之認定，更不必有何有利之證據，最\n    高法院30年上字第816號判例可資參照。而所謂「積極證據\n    足以為不利被告事實之認定」，依據同院76年臺上字第4986\n    號判例意旨，係指據為訴訟上證明之全盤證據資料，在客觀\n    上已達於通常一般之人均不致於有所懷疑，而得確信被告確\n    曾犯罪之程度；若未達到此一程度，而有合理懷疑之存在時\n    ，即無從為被告有罪之確信。且按認定犯罪事實應依證據，\n    為刑事訴訟法所明定，故被告否認犯罪事實所持之辯解，縱\n    屬不能成立，仍非有積極證據足以證明其犯罪行為，不能遽\n    為有罪之認定（最高法院30年上字第1831號判例參照）。\n三、公訴意旨指被告乙○○涉有前開販賣第二級毒品未遂犯行，\n    無非以被告之供述、證人丙○○於警詢及偵查中之證述，及\n    證人即承辦員警甲○○於偵查中之證述，雙向通聯紀錄2 份\n    ，臺灣板橋地方法院檢察署97年度毒偵字第584 號聲請簡易\n    判決處刑書1 份，扣案之甲基安非他命12包及照片28張、內\n    政部警政署刑事警察局97年1 月14日刑鑑字第0970003274號\n    鑑定書等為其論據。訊之被告乙○○固坦承有於前揭時地與\n    丙○○電話聯絡之事實，惟堅決否認有何販賣第二級毒品甲\n    基安非他命犯行，辯稱：97年1 月2 日伊係剛自台北購買完\n    毒品要返家，路上接到丙○○電話，問伊有無毒品，1 包多\n    少錢，伊則問丙○○有無將DVD 光碟帶出來，可不可以還伊\n    ，才與丙○○相約見面，並非為了交易毒品相約見面等語。\n    經查：\n(一)、本件販賣第二級毒品甲基安非他命案查獲之經過，係證人丙\n    ○○於97年1 月2 日為警查獲持有毒品甲基安非他命，經丙\n    ○○供出毒品來源為被告後，配合警方電話聯絡被告，佯稱\n    購買5, 000元甲基安非他命，並相約前揭時地交易，經警在\n    前開地點埋伏而查獲被告等情，業據證人丙○○於本院審理\n    時（見本院97年度訴字第1803號刑事卷第190 、191 頁）；\n    證人即承辦員警甲○○於偵查及本院審理時分別證述在卷（\n    見同上偵查卷第110 頁、本院99年3 月30日審理筆錄第5頁\n    ），互核相符，堪信為真實。\n(二)、證人丙○○於本院審理時證稱：「（你跟被告說什麼？）我\n    說還她錢。警察的意思是說叫我要去，就是要我說是跟誰買\n    ，我的意思是說我先還她錢。（你電話中有請被告帶藥出來\n    嗎？你電話中怎麼跟乙○○說？）好像有，因為是警察跟我\n    說要這樣。（你說警察從你電話中搜尋到乙○○電話之後，\n    你打電話給乙○○是跟她說什麼？）請她幫我調5 千，順便\n    要還她錢。」等語（見本院97年度訴字第1803號刑事卷第19\n    1 頁）。證人甲○○則稱：「（問：丙○○當天撥手機，撥\n    了幾通？）那時候快要2 點，大概1 點55分左右，撥給大姐\n    之後就直接通了，他們講一會兒，因為對談都是他們在談，\n    他講得很小聲，那時候我在辦公室的管制門，因為我怕警察\n    無線電的聲音會發出來，所以他跟大姐的對話我不清楚，等\n    丙○○講完之後，他跟我說他已經約好了。（問：丙○○有\n    沒有說他約好是怎麼約？）就是約到板橋中山路那邊麥當勞\n    之後，到那裡再打電話給大姐。（問：你是否清楚丙○○約\n    的內容？是要什麼毒品或是要做什麼？）隱隱約約有聽到丙\n    ○○說大姐那邊有沒有，他急著要。（問：你有沒有聽到丙\n    ○○要還大姐錢？）沒有，最後我有聽到丙○○說『我要\n    5000 塊 』。（問：所以你有沒有聽到丙○○說要還大姐\n    3000塊的事情？）沒有。（問：你有沒有聽到他們講到什麼\n    DDT 或是光碟片的事情？）沒有，他們講的時間很短，沒有\n    多久就結束了，他們講完電話的時候，丙○○就主動告知我\n    說他已經跟大姐約好了，跟她講說他要5000塊的安非他命。\n    」等語（見本院99年3 月30日審理筆錄第12、13頁），顯見\n    警方所謂丙○○有於前揭時地與被告電話聯絡買賣甲基安非\n    他命毒品事宜及交易甲基安非他命毒品，均係出於證人丙○\n    ○之告知，渠等並未親自聽聞丙○○與被告間聯絡買賣海洛\n    因毒品之電話內容，而丙○○究係以返還前積欠被告交易毒\n    品之金錢為由，抑或以要購買毒品甲基安非他命而與被告聯\n    繫，即有疑義。又證人丙○○既係配合警方聯絡被告交易毒\n    品，並由警方在交易地點埋伏，是其意在使被告受刑事處分\n    ，其證言之真偽，是否與事實相符，自應詳加辨析。再參以\n    證人丙○○所謂與被告間之聯絡及交易甲基安非他命，均係\n    其個人進行，僅由警方在場埋伏，而警方未於交易時親見親\n    聞有金錢與毒品之交易，亦非無疑，是證人丙○○前揭所述\n    ，難謂無瑕。至證人丙○○有於前揭交易時間前與被告間電\n    話聯絡之紀錄，固有通聯紀錄1 件附卷可稽，並為被告所不\n    否認（見同上偵查卷第103 頁），惟該通聯紀錄之通話內容\n    為何，僅有證人丙○○之證詞，且被告否認該通電話係丙○\n    ○要向伊購買毒品，自尚難因有該電話通聯，遽認證人丙○\n    ○證稱伊是以電話聯絡被告購買毒品甲基安非他命屬實。\n(三)、又按刑法上所謂陷害教唆，係指行為人原無犯罪之意思，純\n    因具有司法警察權者之設計誘陷，以唆使其萌生犯意，待其\n    形式上符合著手於犯罪行為之實行時，再予逮捕者而言。此\n    種「陷害教唆」，因行為人原無犯罪之意思，具有司法警察\n    權者復伺機逮捕，係以不正當手段入人於罪，尚難遽認被陷\n    害教唆者成立犯罪。至刑事偵查技術上所謂之「釣魚」者，\n    則指對於原已犯罪或具有犯罪故意之人，司法警察於獲悉後\n    為取得證據，以設計引誘之方式，佯與之為對合行為，使其\n    暴露犯罪事證，待其著手於犯罪行為之實行時，予以逮捕、\n    偵辦者而言。後者因犯罪行為人主觀上原即有犯罪之意思，\n    倘客觀上又已著手於犯罪行為之實行時，自得成立未遂犯，\n    與「陷害教唆」情形迥然有別。「釣魚」因屬偵查犯罪技巧\n    之範疇，並未違反憲法對於基本人權之保障，且於公共利益\n    之維護有其必要性，故依「釣魚」方式所蒐集之證據資料，\n    非無證據能力（最高法院96年台上字第6628號判決意旨參照\n    ）。本院綜觀全卷被告所涉於97年1 月2 日販賣甲基安非他\n    命予丙○○之犯行，僅有證人丙○○之單一指述，別無其他\n    證據可資佐參，而其證詞尚非無瑕，已如前述；況縱證人丙\n    ○○所述前揭與被告聯絡及交易毒品甲基安非他命屬實，惟\n    此係配合警方之查緝行動而為，是被告於證人丙○○上開聯\n    絡購買甲基安非他命前，是否即有販賣甲基安非他命之營利\n    意圖，自有再行斟酌之餘地。是本案並無積極證據足資證明\n    於證人丙○○配合警方查緝毒品與被告為購買甲基安非他命\n    電話聯絡前，被告即有販賣甲基安非他命之犯意。故縱證人\n    丙○○有於前揭時地與被告電話聯絡並交易第二級毒品甲基\n    安非他命，依檢察官所舉之證據尚無從證明被告於本案前，\n    有其他販賣甲基安非他命予證人丙○○之行為，是被告於97\n    年1 月2 日販賣第二級毒品甲基安非他命予丙○○之行為，\n    係證人丙○○為配合警方查緝毒品，而配合員警設計引誘教\n    唆所致，核屬「陷害教唆」無訛，參諸前揭說明，自難科以\n    此部分被告販賣第二級毒品罪責。\n四、綜上所述，檢察官所提出之證據，尚不能使本院形成被告此\n    部分於97年1 月2 日有販賣第二級毒品予證人丙○○有罪之\n    確信。此外，復查無其他積極證據足資證明被告有此部分被\n    訴販賣第二級毒品甲基安非他命之犯行。揆諸首揭說明，自\n    屬不能證明被告此部分之犯罪，自應諭知無罪之判決。\n據上論斷，應依刑事訴訟法第299 條第1 項前段、第301 條第1\n項，毒品危害防制條例第4 條第2 項（修正前）、第19條第1 項\n，刑法第11條前段、第2 條第1 項前段、第47條第1 項，判決如\n主文。\n本案經檢察官陳宣每到庭執行職務\n中    華    民    國    99    年    5    月    12     日\n                  刑事第十五庭  審判長法  官  吳幸娥\n                                      法  官  許炎灶\n                                      法  官  廖欣儀\n以上正本證明與原本無異。\n如不服本判決，應於判決送達後10日內敘明上訴理由，向本院提\n出上訴狀 (應附繕本)， 上訴於臺灣高等法院。其未敘述上訴理\n由者，應於上訴期間屆滿後20日內向本院補提理由書「切勿逕送\n上級法院」。\n                                      書記官  黃頌棻"
  },
  "characters": {
    "judges": [
      "吳幸娥",
      "許炎灶",
      "廖欣儀"
    ],
    "prosecutors": [
      "陳宣每"
    ],
    "lawyers": [

    ],
    "clerks": [
      "黃頌棻"
    ],
    "plaintiffs": [

    ],
    "defendants": [
      "乙○○"
    ],
    "prosecutor_office": [
      "臺灣板橋地方法院檢察署檢察官"
    ],
    "creditors": [

    ],
    "debtors": [

    ],
    "judicial_associate_officer": [

    ]
  },
  "adjudged_at": "2010-05-12",
  "created_at": "2016-01-05 12:23:40",
  "updated_at": "2016-01-05 12:23:40"
}