{
  "identify": "PCD-99-易-1348-20100512-1",
  "court": {
    "name": "臺灣新北地方法院",
    "code": "PCD"
  },
  "division": {
    "name": "刑事",
    "code": "M"
  },
  "year": 99,
  "word": "易",
  "number": "1348",
  "jcheck": "1",
  "reason": "毀損等",
  "content": "臺灣板橋地方法院刑事判決              99年度易字第1348號\n聲  請  人  臺灣板橋地方法院檢察署檢察官\n被      告  甲○○\n上列被告因毀損等案件，經檢察官聲請以簡易判決處刑（99年度\n偵字第9290號），本院認不宜以簡易判決處刑，改適用通常程序\n審理，判決如下：\n    主  文\n本件公訴不受理。\n    理  由\n一、聲請意旨略以：被告甲○○明知未經他人之同意，不得任意\n    進入他人所有之建築物，竟分別基於毀損及侵入建築物之犯\n    意，於民國98年12月26日下午3 時許，先以徒手破壞位於臺\n    北縣五股鄉○○路16巷15號9 樓用以封閉冷氣孔的木板後，\n    再侵入該建築物內。因告訴人即該建築物所有權人乙○○發\n    現遭他人入侵，乃報警究辦，始悉上情，因認被告涉有刑法\n    第354 條毀損器物罪嫌及同法第306 條第1 項之侵入住宅罪\n    嫌。\n二、按告訴乃論之罪，告訴人於第一審辯論終結前，得撤回其告\n    訴，告訴經撤回者，應諭知不受理之判決，且此項判決得不\n    經言詞辯論為之，刑事訴訟法第238 條第1 項、第303 條第\n    3 款、第307 條分別定有明文。聲請人認被告之行為，係分\n    別犯刑法第354 條毀損器物罪及同法第306 條第1 項侵入住\n    宅罪，依同法第357 條及308 條第1 項之規定，均須告訴乃\n    論。茲告訴人已具狀撤回告訴，有刑事撤回告訴狀1 份在卷\n    可稽，揆諸前開說明，爰不經言詞辯論，逕諭知不受理之判\n    決。\n三、依刑事訴訟法第452 條、第303 條第3 款、第307 條，判決\n    如主文。\n中    華    民    國    99    年    5     月    12    日\n                  刑事第二十三庭 審判長法  官  徐蘭萍\n                                       法  官  黃繼瑜\n                                       法  官  黃司熒\n上列正本證明與原本無異。\n如不服本判決，應於判決送達後10日內敘明上訴理由，向本院提\n出上訴狀 (應附繕本) ，上訴於臺灣高等法院。其未敘述上訴理\n由者，應於上訴期間屆滿後20日內向本院補提理由書「切勿逕送\n上級法院」。\n                                       書記官  李逸翔\n中    華    民    國    99    年    5     月    12    日",
  "structure": {
    "main": "本件公訴不受理。",
    "reason": "一、聲請意旨略以：被告甲○○明知未經他人之同意，不得任意\n    進入他人所有之建築物，竟分別基於毀損及侵入建築物之犯\n    意，於民國98年12月26日下午3 時許，先以徒手破壞位於臺\n    北縣五股鄉○○路16巷15號9 樓用以封閉冷氣孔的木板後，\n    再侵入該建築物內。因告訴人即該建築物所有權人乙○○發\n    現遭他人入侵，乃報警究辦，始悉上情，因認被告涉有刑法\n    第354 條毀損器物罪嫌及同法第306 條第1 項之侵入住宅罪\n    嫌。\n二、按告訴乃論之罪，告訴人於第一審辯論終結前，得撤回其告\n    訴，告訴經撤回者，應諭知不受理之判決，且此項判決得不\n    經言詞辯論為之，刑事訴訟法第238 條第1 項、第303 條第\n    3 款、第307 條分別定有明文。聲請人認被告之行為，係分\n    別犯刑法第354 條毀損器物罪及同法第306 條第1 項侵入住\n    宅罪，依同法第357 條及308 條第1 項之規定，均須告訴乃\n    論。茲告訴人已具狀撤回告訴，有刑事撤回告訴狀1 份在卷\n    可稽，揆諸前開說明，爰不經言詞辯論，逕諭知不受理之判\n    決。\n三、依刑事訴訟法第452 條、第303 條第3 款、第307 條，判決\n    如主文。"
  },
  "characters": {
    "judges": [
      "徐蘭萍",
      "黃繼瑜",
      "黃司熒"
    ],
    "prosecutors": [

    ],
    "lawyers": [

    ],
    "clerks": [
      "李逸翔"
    ],
    "plaintiffs": [

    ],
    "defendants": [
      "甲○○"
    ],
    "prosecutor_office": [
      "臺灣板橋地方法院檢察署檢察官"
    ],
    "creditors": [

    ],
    "debtors": [

    ],
    "judicial_associate_officer": [

    ]
  },
  "adjudged_at": "2010-05-12",
  "created_at": "2016-01-05 12:22:52",
  "updated_at": "2016-01-05 12:22:52"
}