{
  "identify": "PCD-99-訴-796-20100512-1",
  "court": {
    "name": "臺灣新北地方法院",
    "code": "PCD"
  },
  "division": {
    "name": "刑事",
    "code": "M"
  },
  "year": 99,
  "word": "訴",
  "number": "796",
  "jcheck": "1",
  "reason": "偽造文書等",
  "content": "臺灣板橋地方法院刑事判決               99年度訴字第796號\n公  訴  人  臺灣板橋地方院檢察署檢察官\n被      告  甲○○\n上列被告因偽造文書等案件，經檢察官提起公訴（99年度偵字第\n2760號），本院依簡式審判程序判決如下：\n    主  文\n甲○○犯如附表二所示之罪，均累犯，各處如附表二所示之宣告\n刑暨應沒收之物。應執行有期徒刑拾月，如易科罰金，以新臺幣\n壹仟元折算壹日。如附表一所示簽帳單上偽造之「乙○○」署押\n共計枚沒收。\n    事  實\n一、甲○○前曾因詐欺案件，經本院以96年度簡字第3726號判決\n    有期徒刑3 月，嗣因合於中華民國96年罪犯減刑條例之規定\n    ，復經本院以96年度聲減字第6181號裁定減為有期徒刑1 月\n    又15日，於民國96年10月12日易科罰金執行完畢，竟猶不知\n    悛悔，於98年9 月23日19時許，基於意圖為自己不法所有之\n    竊盜犯意，在臺北縣板橋市○○路155 巷7 號2 樓住處，徒\n    手竊取其弟（起訴書誤載為「其兄」，應予更正）乙○○所\n    有之花旗銀行信用卡1 張得手（卡號：0000000000000000號\n    ）。嗣另基於行使偽造私文書及意圖為自己不法所有之單一\n    接續犯意，持上開信用卡，分別於如附表一編號一至三所示\n    之時間、地點，至各該特約商店刷卡消費如附表一編號一至\n    三所示之金額，佯稱其為有權使用該信用卡之乙○○本人，\n    在簽帳單上偽造「乙○○」之署押各1 枚，再將上開簽帳單\n    交付予前開特約商店不知情之店員加以行使，致使該等特約\n    商店店員陷於錯誤，誤為乙○○本人而提供服務，致生損害\n    於花旗銀行、附表一編號一至三所示之商店及乙○○。其後\n    甲○○復基於意圖為自己不法所有之詐欺犯意，於如附表一\n    編號四所示之時間、地點，持上開信用卡至義記銀樓刷卡消\n    費購買金飾共計新臺幣（下同）18,400元，致使不知情之店\n    員陷於錯誤而同意刷卡結帳，惟因乙○○已發覺信用卡遭竊\n    而向花旗銀行掛失信用卡，始未遭甲○○盜刷得逞，義記銀\n    樓因之而未交付任何財物予甲○○。嗣乙○○報警處理，經\n    警循線查獲，始悉上情。\n二、案經乙○○訴由臺北市政府警察局中山分局移送臺灣板橋地\n    方法院檢察署檢察官偵查起訴。\n    理  由\n一、本院於準備程序進行中，被告甲○○就被訴事實為有罪之陳\n    述，經告知被告簡式審判程序之旨，並聽取公訴人及被告之\n    意見後，裁定進行簡式審判程序。\n二、前揭事實，業據被告於警詢時、偵查中及本院審理時坦承不\n    諱，核與證人即告訴人乙○○於警詢時及偵查中證述情節相\n    符，並有上開花旗銀行信用卡簽單影本3 紙、花旗銀行客戶\n    交易明細一覽表1 紙、友友大飯店監視錄影器翻拍照片13幀\n    在卷可稽。且按，信用卡簽帳單，係持卡人向特約商店消費\n    後，簽署持卡人之姓名，由特約商店將第一聯交持卡人收執\n    ，第二聯則由特約商店存查，資以向發卡銀行請款。該簽帳\n    單由持卡人簽名，即表示持卡人同意依據其與發卡銀行間之\n    約定，對其所購物品或接受服務，均應按簽帳單之消費金額\n    ，付款與發卡銀行。故持卡人於簽帳單簽名，係對所簽金額\n    負擔付款之義務，性質上屬消費付款契約書，亦為私文書，\n    最高法院90年度台上字第6898號判決可資參照。而被告未經\n    告訴人乙○○之授權或同意，擅自持乙○○前開花旗銀行信\n    用卡至如附表一所示商店消費接受服務或購買商品，在如附\n    表一編號四之商店雖因信用卡遭掛失而未得逞，惟其在如附\n    表一編號一至三所示商店持卡消費同時並偽造「乙○○」名\n    義之簽帳單，交付特約商店人員，致不知情之商店、花旗銀\n    行陷於錯誤，使被告接受服務而詐得財產上不法利益，自足\n    以生損害於告訴人乙○○、如附表一編號一至三所示之商店\n    及花旗銀行。至被告在本院審理時雖提出罹有精神病之診斷\n    證明書1 紙供參，惟被告在本院訊問時對答如流，神情與常\n    人無異，且依其在警詢時之供述，亦無證據顯示其行為時之\n    意識能力與控制能力有何欠缺或顯著減低之心理結果，是自\n    無送請醫療院所鑑定其精神狀況之必要，併此敘明。從而，\n    堪認被告自白核與事實相符。是事證明確，被告前開犯行均\n    洵堪認定，應予依法論科。\n三、查被告所為如事實欄一所示之犯行，核分別係犯如附表二所\n    犯法條欄所示之罪名。公訴意旨就被告持信用卡刷卡於如附\n    表一編號一至三所示商店接受服務所受不法利益部分，雖認\n    係犯刑法第339 條第1 項之詐欺取財罪，惟詐欺取財罪以詐\n    得現實之財物為要件，而被告至酒店（有小姐陪酒、出場）\n    、電影院及飯店住宿消費則係獲得店家所提供之服務，核屬\n    財產上之不法利益，公訴意旨此部分認定容有未洽，惟社會\n    基本事實並無不同，爰依法變更起訴法條。又被告於如附表\n    一編號一至三所示商店簽帳單上所為偽造署押之行為，均屬\n    偽造私文書之部分行為，偽造私文書之低度行為復為行使之\n    高度行為所吸收，均不另論罪。再被告所為如附表一編號一\n    至三所示之犯行，均係以一交付簽帳單之行為同時觸犯行使\n    偽造私文書罪及詐欺得利罪，均屬以一行為觸犯數罪名之想\n    像競合犯，均應依刑法第55條規定，從一重之行使偽造私文\n    書罪處斷。又按數行為於同時同地或密切接近之時地實施，\n    侵害同一之法益，各行為之獨立性極為薄弱，依一般社會健\n    全觀念，在時間差距上，難以強行分開，在刑法評價上，以\n    視為數個舉動之接續施行，合為包括之一行為予以評價，較\n    為合理，即屬接續犯，而為包括之一罪，最高法院86年台上\n    字第3295號判例意旨可資參照。查被告在警詢時供稱：案發\n    當天伊偷了乙○○之信用卡後，剛好接到中山區酒店的電話\n    叫客，故伊當晚就持上開信用卡前往該酒店消費，接著有帶\n    該酒店小姐去刷卡買電影票看電影，然後該酒店小姐叫伊去\n    飯店等她，所以伊又去飯店刷卡等語，是被告所為如附表一\n    編號一至三所示3 次行使偽造私文書、詐欺犯行，既屬時間\n    、地點密接，且均與酒店小姐相關，堪認係基於單一不法意\n    圖之多次接續動作，屬接續犯，自應論以包括一罪。又被告\n    所為如附表二所示之各罪間，犯意各別、行為互異，應予分\n    論併罰。又被告已著手於如附表二編號五所示詐欺取財之犯\n    罪行為之實行而不遂，為未遂犯，應依刑法第25條第2 項規\n    定減輕其刑。末查，被告前受有如事實欄第一項所示之犯罪\n    科刑及執行情形，有臺灣高等法院被告前案紀錄表1 份附卷\n    可稽，其於受有期徒刑執行完畢後，5 年以內故意再犯本件\n    有期徒刑以上之3 罪，均為累犯，均應依刑法第47條第1 項\n    規定加重其刑，並就如附表二編號三所示之罪，先加後減之\n    。爰審酌被告前因已竊取其父黃添益之信用上盜刷消費而經\n    警查獲，詎不知悔改，復竊取其弟乙○○之信用卡盜刷消費\n    ，致生損害於前開銀行、商店及告訴人，兼衡被告之素行、\n    生活狀況、智識程度、犯罪之動機、目的、手段、所生之危\n    害及犯罪後之態度等一切情狀，分別量處如主文所示之刑，\n    並定其應執行刑。末按依釋字第662 號解釋：「中華民國94\n    年2 月2 日修正公布之現行刑法第41條第2 項，關於數罪併\n    罰，數宣告刑均得易科罰金，而定應執行刑之刑逾6 個月者\n    ，排除適用同條第1 項得易科罰金之規定部分，與憲法第23\n    條規定有違，並與本院釋字第366 號解釋意旨不符，應自本\n    解釋公布之日起失其效力。」，而刑法第41條第8 項於98年\n    12月30日經總統公布：「第1 項至第4 項及第7 項之規定，\n    於數罪併罰之數罪，均得易科罰金或易服社會勞動者，其應\n    執行之刑逾6 月者，亦得適用之」，再依同日修正之刑法施\n    行法第10條第2 項規定「刑法修正條文及本法修正條文，除\n    另定施行日期者外，自公布日施行」，故修正之刑法第41條\n    第8 項業已於98年12月30日生效，是以對於數罪併罰，數宣\n    告刑均得易科罰金，而定應執行之刑超過6 個月之案件，依\n    98年12月30日修正公布之刑法第41條第8 項，均得易科罰金\n    ，而本案被告行為時之修正前刑法第41條2 項既業已失效，\n    故自毋庸為新舊法之比較，故本件被告所定執行刑雖逾6 個\n    月，依上開說明，亦應諭知易科罰金之折算標準。從而，併\n    就被告之宣告刑及應執行部分，分別諭知易科罰金之折算標\n    準。\n四、末以，被告在如附表一編號一至三所示商店消費時在信用卡\n    簽帳單商店存根欄上偽造之「乙○○」署押共計3 枚，爰依\n    刑法第219 條規定宣告沒收之；另被告所持有如附表一編號\n    一至三所示各該簽帳單持卡人收執聯，未據扣案，無何事證\n    足證其仍存在，且依常情，簽帳消費迄今已時隔數月，一般\n    人以將之丟棄銷毀為常，為免執行困難，應認已滅失而不存\n    在，故不為沒收之諭知，附此敘明。\n據上論斷，應依刑事訴訟法第273 條之1 第1 項、第299 條第1\n項前段、第300 條，刑法第320 條第1 項、第210 條、第216 條\n、第339 條、第25條第2 項、第41條第1 項前段、第8 項、第55\n條、第47條第1 項、第51條第5 款、第219 條，刑法施行法第1\n條之1 第1 項、第2 項前段，判決如主文。\n本案經檢察官林慈雁到庭執行職務。\n中    華    民    國    99    年    5     月    12    日\n                  刑事第十三庭  法  官  王士珮\n以上正本證明與原本無異。\n如不服本判決應於收受判決後10日內向本院提出上訴書狀，並應\n敘述具體理由。其未敘述上訴理由者，應於上訴期間屆滿後20日\n內向本院補提理由書（均須按他造當事人之人數附繕本）「切勿\n逕送上級法院」。\n                                書記官  金和國\n中    華    民    國    99    年    5     月    12    日\n附錄本案論罪科刑法條全文：\n中華民國刑法第210 條\n偽造、變造私文書，足以生損害於公眾或他人者，處5 年以下有\n期徒刑。\n中華民國刑法第216 條\n行使第210 條至第215 條之文書者，依偽造、變造文書或登載不\n實事項或使登載不實事項之規定處斷。\n中華民國刑法第320條\n意圖為自己或第三人不法之所有，而竊取他人之動產者，為竊盜\n罪，處5 年以下有期徒刑、拘役或500 元以下罰金。\n意圖為自己或第三人不法之利益，而竊佔他人之不動產者，依前\n項之規定處斷。\n前2 項之未遂犯罰之。\n中華民國刑法第339 條\n意圖為自己或第三人不法之所有，以詐術使人將本人或第三人之\n物交付者，處5 年以下有期徒刑、拘役或科或併科1000元以下罰\n金。\n以前項方法得財產上不法之利益或使第三人得之者，亦同。\n前2 項之未遂犯罰之。\n附表一：\n┌──┬──────┬────┬────┬────────┬───────┐\n│編號│ 刷卡時間   │ 金  額 │商店名稱│    地  址      │   備    註   │\n├──┼──────┼────┼────┼────────┼───────┤\n│ 一 │98年9月23日 │30,000元│金鈺銘酒│臺北市中山區民生│簽帳單均為1 式│\n│    │23時44分    │        │吧      │東路1 段29號2樓 │2 聯，各為顧客│\n│    │            │        │        │                │收執聯及特約商│\n├──┼──────┼────┼────┼────────┤店存根聯，僅在│\n│ 二 │98年9月24日 │450元   │欣欣晶華│臺北市中山區林森│存根聯簽名，無│\n│    │0時53分     │        │影城    │北路247號       │複寫功能，被告│\n│    │            │        │        │                │在前開商店之簽│\n├──┼──────┼────┼────┼────────┤帳單上各偽簽「│\n│ 三 │98年9月24日 │1,930元 │友友大飯│臺北市中山區長春│乙○○」署押1 │\n│    │2時47分     │        │店      │路24號          │枚。          │\n│    │            │        │        │                │              │\n├──┼──────┼────┼────┼────────┼───────┤\n│ 四 │98年9月24日 │184,000 │義記銀樓│臺北縣中和市德光│因乙○○已掛失│\n│    │10時25分    │元      │        │路71號          │信用卡，致未盜│\n│    │            │        │        │                │刷成功        │\n└──┴──────┴────┴────┴────────┴───────┘\n附表二：\n┌──┬────────┬──────┬─────────────────┐\n│編號│ 犯罪事實       │ 所犯法條   │            罪名暨宣告刑          │\n│    │                │            │            及應沒收之物          │\n├──┼────────┼──────┼─────────────────┤\n│ 一 │如事實欄一所述竊│刑法第320 條│甲○○犯竊盜罪，累犯，處有期徒刑│\n│    │取乙○○信用卡之│第1 項      │月，如易科罰金，以新臺幣壹仟元折算│\n│    │竊盜犯行        │            │壹日。                            │\n├──┼────────┼──────┼─────────────────┤\n│ 二 │如事實欄一所述在│刑法第216 條│甲○○犯行使偽造私文書罪，累犯，處│\n│    │附表一編號一至三│、第210 條及│有期徒刑陸月，如易科罰金，以新臺幣│\n│    │所載商店盜刷信用│同法第339 條│壹仟元折算壹日。如附表一所示簽帳單│\n│    │卡之行使偽造私文│第2項       │上偽造之「乙○○」署押共計枚沒收│\n│    │書、詐欺得利犯行│            │。                                │\n├──┼────────┼──────┼─────────────────┤\n│ 三 │如事實欄一所述在│刑法第339 條│甲○○犯詐欺取財未遂罪，累犯，處有│\n│    │附表一編號四所載│第3 項、第1 │期徒刑月，如易科罰金，以新臺幣壹│\n│    │商店盜刷信用卡之│項          │仟元折算壹日。                    │\n│    │詐欺未遂犯行    │            │                                  │\n└──┴────────┴──────┴─────────────────┘",
  "structure": {
    "main": "甲○○犯如附表二所示之罪，均累犯，各處如附表二所示之宣告\n刑暨應沒收之物。應執行有期徒刑拾月，如易科罰金，以新臺幣\n壹仟元折算壹日。如附表一所示簽帳單上偽造之「乙○○」署押\n共計枚沒收。",
    "fact": "一、甲○○前曾因詐欺案件，經本院以96年度簡字第3726號判決\n    有期徒刑3 月，嗣因合於中華民國96年罪犯減刑條例之規定\n    ，復經本院以96年度聲減字第6181號裁定減為有期徒刑1 月\n    又15日，於民國96年10月12日易科罰金執行完畢，竟猶不知\n    悛悔，於98年9 月23日19時許，基於意圖為自己不法所有之\n    竊盜犯意，在臺北縣板橋市○○路155 巷7 號2 樓住處，徒\n    手竊取其弟（起訴書誤載為「其兄」，應予更正）乙○○所\n    有之花旗銀行信用卡1 張得手（卡號：0000000000000000號\n    ）。嗣另基於行使偽造私文書及意圖為自己不法所有之單一\n    接續犯意，持上開信用卡，分別於如附表一編號一至三所示\n    之時間、地點，至各該特約商店刷卡消費如附表一編號一至\n    三所示之金額，佯稱其為有權使用該信用卡之乙○○本人，\n    在簽帳單上偽造「乙○○」之署押各1 枚，再將上開簽帳單\n    交付予前開特約商店不知情之店員加以行使，致使該等特約\n    商店店員陷於錯誤，誤為乙○○本人而提供服務，致生損害\n    於花旗銀行、附表一編號一至三所示之商店及乙○○。其後\n    甲○○復基於意圖為自己不法所有之詐欺犯意，於如附表一\n    編號四所示之時間、地點，持上開信用卡至義記銀樓刷卡消\n    費購買金飾共計新臺幣（下同）18,400元，致使不知情之店\n    員陷於錯誤而同意刷卡結帳，惟因乙○○已發覺信用卡遭竊\n    而向花旗銀行掛失信用卡，始未遭甲○○盜刷得逞，義記銀\n    樓因之而未交付任何財物予甲○○。嗣乙○○報警處理，經\n    警循線查獲，始悉上情。\n二、案經乙○○訴由臺北市政府警察局中山分局移送臺灣板橋地\n    方法院檢察署檢察官偵查起訴。",
    "reason": "一、本院於準備程序進行中，被告甲○○就被訴事實為有罪之陳\n    述，經告知被告簡式審判程序之旨，並聽取公訴人及被告之\n    意見後，裁定進行簡式審判程序。\n二、前揭事實，業據被告於警詢時、偵查中及本院審理時坦承不\n    諱，核與證人即告訴人乙○○於警詢時及偵查中證述情節相\n    符，並有上開花旗銀行信用卡簽單影本3 紙、花旗銀行客戶\n    交易明細一覽表1 紙、友友大飯店監視錄影器翻拍照片13幀\n    在卷可稽。且按，信用卡簽帳單，係持卡人向特約商店消費\n    後，簽署持卡人之姓名，由特約商店將第一聯交持卡人收執\n    ，第二聯則由特約商店存查，資以向發卡銀行請款。該簽帳\n    單由持卡人簽名，即表示持卡人同意依據其與發卡銀行間之\n    約定，對其所購物品或接受服務，均應按簽帳單之消費金額\n    ，付款與發卡銀行。故持卡人於簽帳單簽名，係對所簽金額\n    負擔付款之義務，性質上屬消費付款契約書，亦為私文書，\n    最高法院90年度台上字第6898號判決可資參照。而被告未經\n    告訴人乙○○之授權或同意，擅自持乙○○前開花旗銀行信\n    用卡至如附表一所示商店消費接受服務或購買商品，在如附\n    表一編號四之商店雖因信用卡遭掛失而未得逞，惟其在如附\n    表一編號一至三所示商店持卡消費同時並偽造「乙○○」名\n    義之簽帳單，交付特約商店人員，致不知情之商店、花旗銀\n    行陷於錯誤，使被告接受服務而詐得財產上不法利益，自足\n    以生損害於告訴人乙○○、如附表一編號一至三所示之商店\n    及花旗銀行。至被告在本院審理時雖提出罹有精神病之診斷\n    證明書1 紙供參，惟被告在本院訊問時對答如流，神情與常\n    人無異，且依其在警詢時之供述，亦無證據顯示其行為時之\n    意識能力與控制能力有何欠缺或顯著減低之心理結果，是自\n    無送請醫療院所鑑定其精神狀況之必要，併此敘明。從而，\n    堪認被告自白核與事實相符。是事證明確，被告前開犯行均\n    洵堪認定，應予依法論科。\n三、查被告所為如事實欄一所示之犯行，核分別係犯如附表二所\n    犯法條欄所示之罪名。公訴意旨就被告持信用卡刷卡於如附\n    表一編號一至三所示商店接受服務所受不法利益部分，雖認\n    係犯刑法第339 條第1 項之詐欺取財罪，惟詐欺取財罪以詐\n    得現實之財物為要件，而被告至酒店（有小姐陪酒、出場）\n    、電影院及飯店住宿消費則係獲得店家所提供之服務，核屬\n    財產上之不法利益，公訴意旨此部分認定容有未洽，惟社會\n    基本事實並無不同，爰依法變更起訴法條。又被告於如附表\n    一編號一至三所示商店簽帳單上所為偽造署押之行為，均屬\n    偽造私文書之部分行為，偽造私文書之低度行為復為行使之\n    高度行為所吸收，均不另論罪。再被告所為如附表一編號一\n    至三所示之犯行，均係以一交付簽帳單之行為同時觸犯行使\n    偽造私文書罪及詐欺得利罪，均屬以一行為觸犯數罪名之想\n    像競合犯，均應依刑法第55條規定，從一重之行使偽造私文\n    書罪處斷。又按數行為於同時同地或密切接近之時地實施，\n    侵害同一之法益，各行為之獨立性極為薄弱，依一般社會健\n    全觀念，在時間差距上，難以強行分開，在刑法評價上，以\n    視為數個舉動之接續施行，合為包括之一行為予以評價，較\n    為合理，即屬接續犯，而為包括之一罪，最高法院86年台上\n    字第3295號判例意旨可資參照。查被告在警詢時供稱：案發\n    當天伊偷了乙○○之信用卡後，剛好接到中山區酒店的電話\n    叫客，故伊當晚就持上開信用卡前往該酒店消費，接著有帶\n    該酒店小姐去刷卡買電影票看電影，然後該酒店小姐叫伊去\n    飯店等她，所以伊又去飯店刷卡等語，是被告所為如附表一\n    編號一至三所示3 次行使偽造私文書、詐欺犯行，既屬時間\n    、地點密接，且均與酒店小姐相關，堪認係基於單一不法意\n    圖之多次接續動作，屬接續犯，自應論以包括一罪。又被告\n    所為如附表二所示之各罪間，犯意各別、行為互異，應予分\n    論併罰。又被告已著手於如附表二編號五所示詐欺取財之犯\n    罪行為之實行而不遂，為未遂犯，應依刑法第25條第2 項規\n    定減輕其刑。末查，被告前受有如事實欄第一項所示之犯罪\n    科刑及執行情形，有臺灣高等法院被告前案紀錄表1 份附卷\n    可稽，其於受有期徒刑執行完畢後，5 年以內故意再犯本件\n    有期徒刑以上之3 罪，均為累犯，均應依刑法第47條第1 項\n    規定加重其刑，並就如附表二編號三所示之罪，先加後減之\n    。爰審酌被告前因已竊取其父黃添益之信用上盜刷消費而經\n    警查獲，詎不知悔改，復竊取其弟乙○○之信用卡盜刷消費\n    ，致生損害於前開銀行、商店及告訴人，兼衡被告之素行、\n    生活狀況、智識程度、犯罪之動機、目的、手段、所生之危\n    害及犯罪後之態度等一切情狀，分別量處如主文所示之刑，\n    並定其應執行刑。末按依釋字第662 號解釋：「中華民國94\n    年2 月2 日修正公布之現行刑法第41條第2 項，關於數罪併\n    罰，數宣告刑均得易科罰金，而定應執行刑之刑逾6 個月者\n    ，排除適用同條第1 項得易科罰金之規定部分，與憲法第23\n    條規定有違，並與本院釋字第366 號解釋意旨不符，應自本\n    解釋公布之日起失其效力。」，而刑法第41條第8 項於98年\n    12月30日經總統公布：「第1 項至第4 項及第7 項之規定，\n    於數罪併罰之數罪，均得易科罰金或易服社會勞動者，其應\n    執行之刑逾6 月者，亦得適用之」，再依同日修正之刑法施\n    行法第10條第2 項規定「刑法修正條文及本法修正條文，除\n    另定施行日期者外，自公布日施行」，故修正之刑法第41條\n    第8 項業已於98年12月30日生效，是以對於數罪併罰，數宣\n    告刑均得易科罰金，而定應執行之刑超過6 個月之案件，依\n    98年12月30日修正公布之刑法第41條第8 項，均得易科罰金\n    ，而本案被告行為時之修正前刑法第41條2 項既業已失效，\n    故自毋庸為新舊法之比較，故本件被告所定執行刑雖逾6 個\n    月，依上開說明，亦應諭知易科罰金之折算標準。從而，併\n    就被告之宣告刑及應執行部分，分別諭知易科罰金之折算標\n    準。\n四、末以，被告在如附表一編號一至三所示商店消費時在信用卡\n    簽帳單商店存根欄上偽造之「乙○○」署押共計3 枚，爰依\n    刑法第219 條規定宣告沒收之；另被告所持有如附表一編號\n    一至三所示各該簽帳單持卡人收執聯，未據扣案，無何事證\n    足證其仍存在，且依常情，簽帳消費迄今已時隔數月，一般\n    人以將之丟棄銷毀為常，為免執行困難，應認已滅失而不存\n    在，故不為沒收之諭知，附此敘明。\n據上論斷，應依刑事訴訟法第273 條之1 第1 項、第299 條第1\n項前段、第300 條，刑法第320 條第1 項、第210 條、第216 條\n、第339 條、第25條第2 項、第41條第1 項前段、第8 項、第55\n條、第47條第1 項、第51條第5 款、第219 條，刑法施行法第1\n條之1 第1 項、第2 項前段，判決如主文。\n本案經檢察官林慈雁到庭執行職務。\n中    華    民    國    99    年    5     月    12    日\n                  刑事第十三庭  法  官  王士珮\n以上正本證明與原本無異。\n如不服本判決應於收受判決後10日內向本院提出上訴書狀，並應\n敘述具體理由。其未敘述上訴理由者，應於上訴期間屆滿後20日\n內向本院補提理由書（均須按他造當事人之人數附繕本）「切勿\n逕送上級法院」。\n                                書記官  金和國"
  },
  "characters": {
    "judges": [
      "王士珮"
    ],
    "prosecutors": [
      "林慈雁"
    ],
    "lawyers": [

    ],
    "clerks": [
      "金和國"
    ],
    "plaintiffs": [

    ],
    "defendants": [
      "甲○○"
    ],
    "prosecutor_office": [
      "臺灣板橋地方院檢察署檢察官"
    ],
    "creditors": [

    ],
    "debtors": [

    ],
    "judicial_associate_officer": [

    ]
  },
  "adjudged_at": "2010-05-12",
  "created_at": "2016-01-05 12:26:45",
  "updated_at": "2016-01-05 12:26:45"
}