{
  "identify": "PCD-99-易-1347-20100512-1",
  "court": {
    "name": "臺灣新北地方法院",
    "code": "PCD"
  },
  "division": {
    "name": "刑事",
    "code": "M"
  },
  "year": 99,
  "word": "易",
  "number": "1347",
  "jcheck": "1",
  "reason": "妨害自由",
  "content": "臺灣板橋地方法院刑事判決              99年度易字第1347號\n聲  請  人  臺灣板橋地方法院檢察署檢察官\n被      告  甲○○\n上列被告因妨害自由案件，經檢察官聲請以簡易判決處刑（99年\n度調偵字第354 號），本院認不宜以簡易判決處刑，改適用通常\n程序審理，判決如下：\n    主  文\n本件公訴不受理。\n    理  由\n一、聲請意旨略以：被告甲○○於民國98年11月28日上午11時許\n    ，因承包臺北縣中和市○○路239 巷1 號1 樓便利商店戶外\n    燈具照明工程，為便利施工，遂基於侵入住宅之犯意，未得\n    告訴人即中和市○○路239 巷3 號2 樓之2 建物所有權人乙\n    ○○之同意，即攀爬至該址露台內進行施工，因認被告涉有\n    刑法第306條第1項之侵入住宅罪嫌。\n二、按告訴乃論之罪，告訴人於第一審辯論終結前，得撤回其告\n    訴，告訴經撤回者，應諭知不受理之判決，且此項判決得不\n    經言詞辯論為之，刑事訴訟法第238 條第1 項、第303 條第\n    3 款、第307 條分別定有明文。聲請人認被告之行為，係犯\n    刑法第306 條第1 項侵入住宅罪，依同法第308 條第1 項之\n    規定，須告訴乃論。茲告訴人已具狀撤回告訴，有刑事撤回\n    告訴狀1 份在卷可稽，揆諸前開說明，爰不經言詞辯論，逕\n    諭知不受理之判決。\n三、依刑事訴訟法第452 條、第303 條第3 款、第307 條，判決\n    如主文。\n中    華    民    國    99    年    5     月    12    日\n                  刑事第二十三庭 審判長法  官  徐蘭萍\n                                       法  官  黃繼瑜\n                                       法  官  黃司熒\n上列正本證明與原本無異。\n如不服本判決，應於判決送達後10日內敘明上訴理由，向本院提\n出上訴狀 (應附繕本) ，上訴於臺灣高等法院。其未敘述上訴理\n由者，應於上訴期間屆滿後20日內向本院補提理由書「切勿逕送\n上級法院」。\n                                       書記官  李逸翔\n中    華    民    國    99    年    5     月    12    日",
  "structure": {
    "main": "本件公訴不受理。",
    "reason": "一、聲請意旨略以：被告甲○○於民國98年11月28日上午11時許\n    ，因承包臺北縣中和市○○路239 巷1 號1 樓便利商店戶外\n    燈具照明工程，為便利施工，遂基於侵入住宅之犯意，未得\n    告訴人即中和市○○路239 巷3 號2 樓之2 建物所有權人乙\n    ○○之同意，即攀爬至該址露台內進行施工，因認被告涉有\n    刑法第306條第1項之侵入住宅罪嫌。\n二、按告訴乃論之罪，告訴人於第一審辯論終結前，得撤回其告\n    訴，告訴經撤回者，應諭知不受理之判決，且此項判決得不\n    經言詞辯論為之，刑事訴訟法第238 條第1 項、第303 條第\n    3 款、第307 條分別定有明文。聲請人認被告之行為，係犯\n    刑法第306 條第1 項侵入住宅罪，依同法第308 條第1 項之\n    規定，須告訴乃論。茲告訴人已具狀撤回告訴，有刑事撤回\n    告訴狀1 份在卷可稽，揆諸前開說明，爰不經言詞辯論，逕\n    諭知不受理之判決。\n三、依刑事訴訟法第452 條、第303 條第3 款、第307 條，判決\n    如主文。"
  },
  "characters": {
    "judges": [
      "徐蘭萍",
      "黃繼瑜",
      "黃司熒"
    ],
    "prosecutors": [

    ],
    "lawyers": [

    ],
    "clerks": [
      "李逸翔"
    ],
    "plaintiffs": [

    ],
    "defendants": [
      "甲○○"
    ],
    "prosecutor_office": [
      "臺灣板橋地方法院檢察署檢察官"
    ],
    "creditors": [

    ],
    "debtors": [

    ],
    "judicial_associate_officer": [

    ]
  },
  "adjudged_at": "2010-05-12",
  "created_at": "2016-01-05 12:22:49",
  "updated_at": "2016-01-05 12:22:49"
}