{
  "identify": "PCD-99-訴-223-20100512-1",
  "court": {
    "name": "臺灣新北地方法院",
    "code": "PCD"
  },
  "division": {
    "name": "刑事",
    "code": "M"
  },
  "year": 99,
  "word": "訴",
  "number": "223",
  "jcheck": "1",
  "reason": "妨害性自主",
  "content": "臺灣板橋地方法院刑事判決               99年度訴字第223號\n公  訴  人  臺灣板橋地方法院檢察署檢察官\n被      告  甲○○\n指定辯護人  本院公設辯護人湯明純\n上列被告因妨害性自主案件，經檢察官提起公訴（98年度偵字第\n31763 號），本院判決如下：\n    主  文                                              \n甲○○犯侵入住宅強制猥褻罪，累犯，處有期徒刑年陸月。\n    事  實\n一、甲○○前曾因侵占案件，經臺灣桃園地方法院判處有期徒刑\n    2 月確定，於民國95年1 月27日易科罰金執行完畢。詎仍不\n    知悔改，於98年10月22日19時許，在臺北縣蘆洲市○○○路\n    ○ 段328 巷17弄內，見代號00000000號（79年8 月生，真實\n    姓名年籍詳卷，下稱A 女）一人獨行，認有機可乘乃向前搭\n    訕，經A 女拒絕後，遂基於對女子侵入住宅強制猥褻之犯意\n    ，騎乘車牌號碼686-CYD 號重型機車尾隨A 女，見A 女行至\n    位於臺北縣蘆洲市之住處（詳細地址詳卷），趁A 女開啟該\n    處公寓1 樓大門後，欲關上大門之際，阻礙A 女關起大門，\n    於未經A 女許可之情形下，緊隨A 女進入該公寓樓梯間而侵\n    入住宅（侵入住宅部分未據告訴），隨即違反A 女意願，強\n    行將A 女壓向牆壁，用手撫摸A 女之胸部，以此強暴之方式\n    對A 女為強制猥褻行為得逞。嗣甲○○欲進一步強行親吻A\n    女時，因A 女大喊救命，甲○○始罷手離去。\n二、案經臺北縣政府警察局蘆洲分局報告臺灣板橋地方法院檢察\n    署檢察官偵查起訴。\n    理  由                                              \n一、按被告以外之人於審判外之言詞或書面陳述，除法律有規定\n    者外，不得作為證據，刑事訴訟法第159 條第1 項定有明文\n    。查本件證人A 女在警詢時之證述，業經被告及辯護人爭執\n    無證據能力，而檢察官並未釋明上開證據有傳聞證據之例外\n    ，且本院審酌證人A 女上開審判外之陳述，核與其在本院審\n    理時，以證人身分到庭具結並接受交互詰問所為證述內容，\n    並無不符，即無適用刑事訴訟法第159 條之2 規定傳聞證據\n    例外之餘地，是證人A 女上開警詢之證述，自不得作為證據\n    ，合先敘明。\n二、訊據被告甲○○在本院審理時固坦承在前揭時地有尾隨被害\n    人A 女進入上開公寓樓梯間等情，惟矢口否認有何強制猥褻\n    之犯行，辯稱：伊沒有將被害人壓向牆壁觸摸他胸部，伊只\n    有拉扯被害人，她站在樓梯前，伊用一隻手拉被害人的手肘\n    ，伊想把他拉下來聊天，伊是不小心碰到被害人的胸部，伊\n    沒有印象是碰到被害人哪邊的胸部。又伊沒有要親吻被害人\n    ，當時在樓梯間拉扯之間，伊應該是有把被害人壓向牆壁，\n    伊與她拉扯的目的只是想要讓被害人到門口聊天，伊想跟她\n    認識。伊可能真的有碰觸到被害人，但摸和碰觸不一樣，伊\n    只是與被害人拉扯時，有與他比較靠近，後來被害人叫救命\n    ，伊就走了，伊沒有碰到被害人身體其他部位，伊要走的時\n    候，是有罵被害人三字經云云。然查：\n  (一)前揭事實，業據證人即被害人A 女在本院審理時具結證稱：\n    於上開時地，伊下車要返回住處途中，被告來跟伊搭訕，被\n    告問伊要去哪裡，伊那時沒有戴眼鏡，伊想說他是不是伊國\n    小還是伊國中的同學，伊就說「我要回家」，被告說我們出\n    去玩好不好，伊一直在看他是誰，後來伊發現他是伊不認識\n    的人，伊說「我不要」，伊就走了。伊走到伊家樓下時，被\n    告把車騎到伊家樓下，被告就跟伊進去公寓大門，把門半掩\n    ，被告用一隻手壓住伊，然後把伊推到牆壁上，即把伊壓在\n    牆壁上，就像小朋友量身高一樣，也就是伊的背部緊貼牆壁\n    ，而被告正面面對伊。被告就用右手摸伊左邊的胸部，大概\n    摸了2 、3 秒，被告另一隻手在做什麼伊沒有印象了，伊就\n    推開被告的手，然後躲，被告手往下摸時，頭就下來準備要\n    親吻伊，在還沒有親到伊時，伊就大喊救命，被告罵伊一句\n    髒話後就離開了等語。此外，復有被告騎乘車號686-CYD 號\n    重型機車行經附近路口之監視錄影翻拍照片4 幀、車籍查詢\n    －基本資料詳細畫面，並經上開機車車主即證人鄭韋志於警\n    詢時證述前開時間確係由被告使用該機車無訛。又觀諸證人\n    A 女自警詢迄本院審理時，證述始終一致，且無任何矛盾齟\n    齬之處，其在本院審理時並經具結擔保其證言之真實性，自\n    堪採信。\n  (二)又被告在本院審理時雖以前開情詞置辯，辯護人亦以A 女因\n    突遭陌生人碰觸胸部，對為此行為之人自屬不滿，在此情況\n    下自應斟酌是否適宜僅以A 女之指訴，即認定被告所為係出\n    於故意云云置辯，然查，被告在警詢時已供承：伊見A 女要\n    上樓就伸出右手拉她的左手不讓她上樓，伊是用左手抓被害\n    人右邊胸部，伊有將A 女強壓在牆壁上，摸她胸部且要親A\n    女的臉，在這過程中A 女有抗拒，A 女大喊救命，伊就放開\n    手就走了等語；嗣在偵查中亦供稱：因為伊想認識A 女，她\n    說不要，伊就用手抓她右邊胸部，抓一下，她突然喊救命，\n    伊就放手走掉等語。而按被告之自白，非出於強暴、脅迫、\n    利誘、詐欺、疲勞訊問、違法羈押或其他不正之方法，且與\n    事實相符者，得為證據，刑事訴訟法第156 條第1 項定有明\n    文，查被告在警詢時及偵查中之供述既係出於其自由意志下\n    所為，應具任意性，且核與證人A 女指述情節相符，是其事\n    後在本院審理時翻異之詞，委不足採，堪認被告確係出於強\n    制猥褻之故意，而出手撫摸A 女之胸部。\n  (三)綜上所述，被告前開辯解，顯係事後避就卸責之詞，委不足\n    採。本件事證明確，被告犯行洵堪認定，應予依法論科。\n三、論罪科刑部分：\n  (一)按犯刑法第224 條之強制猥褻罪，而有刑法第222 條第1 項\n    第7 款規定之「侵入住宅或有人居住之建築物、船艦或隱匿\n    其內犯之者。」情形，係犯刑法第224 條之1 之加重強制猥\n    褻罪。又上開該加重條件規定所謂之「住宅」，乃指人類日\n    常居住之場所而言，公寓亦屬之。至公寓樓下之「樓梯間」\n    ，雖僅供各住戶出入通行，然就公寓之整體而言，該樓梯間\n    為該公寓之一部分，而與該公寓有密切不可分之關係，是侵\n    入公寓樓下之樓梯間，即難謂無同時妨害居住安全之情形（\n    最高法院76年台上字第2972號判例要旨參照）。而所謂之「\n    侵入」係指未經該條款所指之住宅、建築物、船艦之管領人\n    或居住其內有權同意他人得否進入之人之允許而進入。查被\n    告係於被害人Ａ女進入公寓後正欲關起鐵門時，大力將鐵門\n    推開，阻礙Ａ女關門之方式，進入該公寓樓梯間等情，已如\n    前述，則被告既本無權利進入Ａ女居住之公寓，竟以上開方\n    式尾隨A 女進入該公寓樓梯間，自屬侵入住宅之行為。是核\n    被告所為，係犯刑法第224 條之1 之加重強制猥褻罪。起訴\n    書原雖認被告所為係犯刑法第224 條之強制猥褻罪嫌，然此\n    業經蒞庭檢察官於99年2 月26日本院準備程序陳明更正起訴\n    法條為同法第224 條之1 、第221 條第1 項第7 款之侵入住\n    宅強制猥褻罪嫌，附此敘明。又查，被告前曾受有如事實欄\n    第一項所載之犯罪科刑及執行情形，有臺灣高等法院被告前\n    案紀錄表1 份在卷可憑，其於受有期徒刑之執行完畢後，5\n    年以內故意再犯本件有期徒刑以上之罪，為累犯，應依刑法\n    第47條第1 項之規定加重其刑。\n  (二)再查88年4 月21日修正前刑法第224 條第1 項之構成要件，\n    原規定「對於男女以強暴、脅迫、藥劑、催眠術或他法，至\n    使不能抗拒而為猥褻之行為」，而所謂「他法」，依當時規\n    定固指類似於強暴、脅迫、藥劑、催眠術或與之相當之方法\n    。惟於88年4 月21日修正時，已修正為「對於男女以強暴、\n    脅迫、恐嚇、催眠術或其他違反其意願之方法，而為猥褻之\n    行為者（修正後僅有一項）」，依立法理由說明，係以原條\n    文之「至使不能抗拒」，要件過於嚴格，容易造成受侵害者\n    ，因為需要「拚命抵抗」而致生命或身體方面受更大之傷害\n    ，故修正為「違反其意願之方法」（即不以「至使不能抗拒\n    」為要件）。則修正後所稱其他「違反其意願之方法」，應\n    係指該條所列舉之強暴、脅迫、恐嚇、催眠術以外，其他一\n    切違反被害人意願之方法，妨害被害人之意思自由者而言，\n    不以類似於所列舉之強暴、脅迫、恐嚇、催眠術等相當之其\n    他強制方法，足以壓抑被害人之性自主決定權為必要，始符\n    立法本旨（最高法院97年度第5 次刑事庭會議決議參照）。\n    換言之，刑法第224 條修正後，已經明文揭示擴張強制猥褻\n    行為適用之範圍，自不待言。又性騷擾防治法第25條所規定\n    之強制觸摸罪，係指行為人對於被害人之身體為偷襲式、短\n    暫性之不當觸摸行為，而不符刑法第224 條強制猥褻罪之構\n    成要件，始足當之（參最高法院97年度台上字第4621號判決\n    要旨）。查本件被告於前揭時地在路上搭訕被害人，經被害\n    人拒絕後，即尾隨被害人，在被害人進入住處公寓1 樓大門\n    後，竟緊隨推門進入而侵入該公寓樓梯間，將被害人壓向牆\n    壁，用手撫摸被害人之胸部，此舉顯然係屬違反被害人意願\n    之強暴方法，致被害人性自主決定權受侵害，且被害人於受\n    害過程中，有求救、推開等反抗之舉措，已意識到遭被告侵\n    犯之情狀，與性騷擾情節輕微，而於被害人察覺性自主決定\n    權受到侵害時，行為人行為已終了，無壓抑被害人意志之性\n    騷擾行為，迥然不同。是以，被告上開行為當屬猥褻行為，\n    而非性騷擾行為至明。是被告之辯護人以本件至多構成性騷\n    擾防治法第25條所規定之強制觸摸罪云云置辯，委不足採。\n  (三)爰審酌被告於街道上偶然碰見Ａ女即起色心，為逞一己之私\n    慾，以強暴方法違反A 女之意願對被害人行上開加重強制猥\n    褻犯行，妨害他人性自主權，使A 女身心受創甚鉅，並斟酌\n    其犯罪之動機、手段、目的、智識程度、犯後態度等一切情\n    狀，爰量處如主文所示之刑，以示懲儆。\n據上論斷，應依刑事訴訟法第299 條第1 項前段，刑法第224 條\n之1 、第47條第1 項，判決如主文。\n本案經檢察官林慈雁到庭執行職務。\n中    華    民    國    99    年    5     月    12    日\n                  刑事第十三庭  審判長法  官  王士珮\n                                      法  官  楊明佳\n                                      法  官  方鴻愷\n以上正本證明與原本無異。\n如不服本判決應於收受判決後10日內向本院提出上訴書狀，並\n應敘述具體理由。其未敘述上訴理由者，應於上訴期間屆滿後\n20日內向本院補提理由書（均須按他造當事人之人數附繕本）\n「切勿逕送上級法院」。\n                                書記官  金和國\n中    華    民    國    99    年    5     月    12    日\n附錄本案論罪科刑法條全文：\n中華民國刑法第224條之1\n犯前條之罪而有第222 條第1 項各款情形之一者，處3 年以上10\n年以下有期徒刑。",
  "structure": {
    "main": "甲○○犯侵入住宅強制猥褻罪，累犯，處有期徒刑年陸月。",
    "fact": "一、甲○○前曾因侵占案件，經臺灣桃園地方法院判處有期徒刑\n    2 月確定，於民國95年1 月27日易科罰金執行完畢。詎仍不\n    知悔改，於98年10月22日19時許，在臺北縣蘆洲市○○○路\n    ○ 段328 巷17弄內，見代號00000000號（79年8 月生，真實\n    姓名年籍詳卷，下稱A 女）一人獨行，認有機可乘乃向前搭\n    訕，經A 女拒絕後，遂基於對女子侵入住宅強制猥褻之犯意\n    ，騎乘車牌號碼686-CYD 號重型機車尾隨A 女，見A 女行至\n    位於臺北縣蘆洲市之住處（詳細地址詳卷），趁A 女開啟該\n    處公寓1 樓大門後，欲關上大門之際，阻礙A 女關起大門，\n    於未經A 女許可之情形下，緊隨A 女進入該公寓樓梯間而侵\n    入住宅（侵入住宅部分未據告訴），隨即違反A 女意願，強\n    行將A 女壓向牆壁，用手撫摸A 女之胸部，以此強暴之方式\n    對A 女為強制猥褻行為得逞。嗣甲○○欲進一步強行親吻A\n    女時，因A 女大喊救命，甲○○始罷手離去。\n二、案經臺北縣政府警察局蘆洲分局報告臺灣板橋地方法院檢察\n    署檢察官偵查起訴。",
    "reason": "一、按被告以外之人於審判外之言詞或書面陳述，除法律有規定\n    者外，不得作為證據，刑事訴訟法第159 條第1 項定有明文\n    。查本件證人A 女在警詢時之證述，業經被告及辯護人爭執\n    無證據能力，而檢察官並未釋明上開證據有傳聞證據之例外\n    ，且本院審酌證人A 女上開審判外之陳述，核與其在本院審\n    理時，以證人身分到庭具結並接受交互詰問所為證述內容，\n    並無不符，即無適用刑事訴訟法第159 條之2 規定傳聞證據\n    例外之餘地，是證人A 女上開警詢之證述，自不得作為證據\n    ，合先敘明。\n二、訊據被告甲○○在本院審理時固坦承在前揭時地有尾隨被害\n    人A 女進入上開公寓樓梯間等情，惟矢口否認有何強制猥褻\n    之犯行，辯稱：伊沒有將被害人壓向牆壁觸摸他胸部，伊只\n    有拉扯被害人，她站在樓梯前，伊用一隻手拉被害人的手肘\n    ，伊想把他拉下來聊天，伊是不小心碰到被害人的胸部，伊\n    沒有印象是碰到被害人哪邊的胸部。又伊沒有要親吻被害人\n    ，當時在樓梯間拉扯之間，伊應該是有把被害人壓向牆壁，\n    伊與她拉扯的目的只是想要讓被害人到門口聊天，伊想跟她\n    認識。伊可能真的有碰觸到被害人，但摸和碰觸不一樣，伊\n    只是與被害人拉扯時，有與他比較靠近，後來被害人叫救命\n    ，伊就走了，伊沒有碰到被害人身體其他部位，伊要走的時\n    候，是有罵被害人三字經云云。然查：\n  (一)前揭事實，業據證人即被害人A 女在本院審理時具結證稱：\n    於上開時地，伊下車要返回住處途中，被告來跟伊搭訕，被\n    告問伊要去哪裡，伊那時沒有戴眼鏡，伊想說他是不是伊國\n    小還是伊國中的同學，伊就說「我要回家」，被告說我們出\n    去玩好不好，伊一直在看他是誰，後來伊發現他是伊不認識\n    的人，伊說「我不要」，伊就走了。伊走到伊家樓下時，被\n    告把車騎到伊家樓下，被告就跟伊進去公寓大門，把門半掩\n    ，被告用一隻手壓住伊，然後把伊推到牆壁上，即把伊壓在\n    牆壁上，就像小朋友量身高一樣，也就是伊的背部緊貼牆壁\n    ，而被告正面面對伊。被告就用右手摸伊左邊的胸部，大概\n    摸了2 、3 秒，被告另一隻手在做什麼伊沒有印象了，伊就\n    推開被告的手，然後躲，被告手往下摸時，頭就下來準備要\n    親吻伊，在還沒有親到伊時，伊就大喊救命，被告罵伊一句\n    髒話後就離開了等語。此外，復有被告騎乘車號686-CYD 號\n    重型機車行經附近路口之監視錄影翻拍照片4 幀、車籍查詢\n    －基本資料詳細畫面，並經上開機車車主即證人鄭韋志於警\n    詢時證述前開時間確係由被告使用該機車無訛。又觀諸證人\n    A 女自警詢迄本院審理時，證述始終一致，且無任何矛盾齟\n    齬之處，其在本院審理時並經具結擔保其證言之真實性，自\n    堪採信。\n  (二)又被告在本院審理時雖以前開情詞置辯，辯護人亦以A 女因\n    突遭陌生人碰觸胸部，對為此行為之人自屬不滿，在此情況\n    下自應斟酌是否適宜僅以A 女之指訴，即認定被告所為係出\n    於故意云云置辯，然查，被告在警詢時已供承：伊見A 女要\n    上樓就伸出右手拉她的左手不讓她上樓，伊是用左手抓被害\n    人右邊胸部，伊有將A 女強壓在牆壁上，摸她胸部且要親A\n    女的臉，在這過程中A 女有抗拒，A 女大喊救命，伊就放開\n    手就走了等語；嗣在偵查中亦供稱：因為伊想認識A 女，她\n    說不要，伊就用手抓她右邊胸部，抓一下，她突然喊救命，\n    伊就放手走掉等語。而按被告之自白，非出於強暴、脅迫、\n    利誘、詐欺、疲勞訊問、違法羈押或其他不正之方法，且與\n    事實相符者，得為證據，刑事訴訟法第156 條第1 項定有明\n    文，查被告在警詢時及偵查中之供述既係出於其自由意志下\n    所為，應具任意性，且核與證人A 女指述情節相符，是其事\n    後在本院審理時翻異之詞，委不足採，堪認被告確係出於強\n    制猥褻之故意，而出手撫摸A 女之胸部。\n  (三)綜上所述，被告前開辯解，顯係事後避就卸責之詞，委不足\n    採。本件事證明確，被告犯行洵堪認定，應予依法論科。\n三、論罪科刑部分：\n  (一)按犯刑法第224 條之強制猥褻罪，而有刑法第222 條第1 項\n    第7 款規定之「侵入住宅或有人居住之建築物、船艦或隱匿\n    其內犯之者。」情形，係犯刑法第224 條之1 之加重強制猥\n    褻罪。又上開該加重條件規定所謂之「住宅」，乃指人類日\n    常居住之場所而言，公寓亦屬之。至公寓樓下之「樓梯間」\n    ，雖僅供各住戶出入通行，然就公寓之整體而言，該樓梯間\n    為該公寓之一部分，而與該公寓有密切不可分之關係，是侵\n    入公寓樓下之樓梯間，即難謂無同時妨害居住安全之情形（\n    最高法院76年台上字第2972號判例要旨參照）。而所謂之「\n    侵入」係指未經該條款所指之住宅、建築物、船艦之管領人\n    或居住其內有權同意他人得否進入之人之允許而進入。查被\n    告係於被害人Ａ女進入公寓後正欲關起鐵門時，大力將鐵門\n    推開，阻礙Ａ女關門之方式，進入該公寓樓梯間等情，已如\n    前述，則被告既本無權利進入Ａ女居住之公寓，竟以上開方\n    式尾隨A 女進入該公寓樓梯間，自屬侵入住宅之行為。是核\n    被告所為，係犯刑法第224 條之1 之加重強制猥褻罪。起訴\n    書原雖認被告所為係犯刑法第224 條之強制猥褻罪嫌，然此\n    業經蒞庭檢察官於99年2 月26日本院準備程序陳明更正起訴\n    法條為同法第224 條之1 、第221 條第1 項第7 款之侵入住\n    宅強制猥褻罪嫌，附此敘明。又查，被告前曾受有如事實欄\n    第一項所載之犯罪科刑及執行情形，有臺灣高等法院被告前\n    案紀錄表1 份在卷可憑，其於受有期徒刑之執行完畢後，5\n    年以內故意再犯本件有期徒刑以上之罪，為累犯，應依刑法\n    第47條第1 項之規定加重其刑。\n  (二)再查88年4 月21日修正前刑法第224 條第1 項之構成要件，\n    原規定「對於男女以強暴、脅迫、藥劑、催眠術或他法，至\n    使不能抗拒而為猥褻之行為」，而所謂「他法」，依當時規\n    定固指類似於強暴、脅迫、藥劑、催眠術或與之相當之方法\n    。惟於88年4 月21日修正時，已修正為「對於男女以強暴、\n    脅迫、恐嚇、催眠術或其他違反其意願之方法，而為猥褻之\n    行為者（修正後僅有一項）」，依立法理由說明，係以原條\n    文之「至使不能抗拒」，要件過於嚴格，容易造成受侵害者\n    ，因為需要「拚命抵抗」而致生命或身體方面受更大之傷害\n    ，故修正為「違反其意願之方法」（即不以「至使不能抗拒\n    」為要件）。則修正後所稱其他「違反其意願之方法」，應\n    係指該條所列舉之強暴、脅迫、恐嚇、催眠術以外，其他一\n    切違反被害人意願之方法，妨害被害人之意思自由者而言，\n    不以類似於所列舉之強暴、脅迫、恐嚇、催眠術等相當之其\n    他強制方法，足以壓抑被害人之性自主決定權為必要，始符\n    立法本旨（最高法院97年度第5 次刑事庭會議決議參照）。\n    換言之，刑法第224 條修正後，已經明文揭示擴張強制猥褻\n    行為適用之範圍，自不待言。又性騷擾防治法第25條所規定\n    之強制觸摸罪，係指行為人對於被害人之身體為偷襲式、短\n    暫性之不當觸摸行為，而不符刑法第224 條強制猥褻罪之構\n    成要件，始足當之（參最高法院97年度台上字第4621號判決\n    要旨）。查本件被告於前揭時地在路上搭訕被害人，經被害\n    人拒絕後，即尾隨被害人，在被害人進入住處公寓1 樓大門\n    後，竟緊隨推門進入而侵入該公寓樓梯間，將被害人壓向牆\n    壁，用手撫摸被害人之胸部，此舉顯然係屬違反被害人意願\n    之強暴方法，致被害人性自主決定權受侵害，且被害人於受\n    害過程中，有求救、推開等反抗之舉措，已意識到遭被告侵\n    犯之情狀，與性騷擾情節輕微，而於被害人察覺性自主決定\n    權受到侵害時，行為人行為已終了，無壓抑被害人意志之性\n    騷擾行為，迥然不同。是以，被告上開行為當屬猥褻行為，\n    而非性騷擾行為至明。是被告之辯護人以本件至多構成性騷\n    擾防治法第25條所規定之強制觸摸罪云云置辯，委不足採。\n  (三)爰審酌被告於街道上偶然碰見Ａ女即起色心，為逞一己之私\n    慾，以強暴方法違反A 女之意願對被害人行上開加重強制猥\n    褻犯行，妨害他人性自主權，使A 女身心受創甚鉅，並斟酌\n    其犯罪之動機、手段、目的、智識程度、犯後態度等一切情\n    狀，爰量處如主文所示之刑，以示懲儆。\n據上論斷，應依刑事訴訟法第299 條第1 項前段，刑法第224 條\n之1 、第47條第1 項，判決如主文。\n本案經檢察官林慈雁到庭執行職務。\n中    華    民    國    99    年    5     月    12    日\n                  刑事第十三庭  審判長法  官  王士珮\n                                      法  官  楊明佳\n                                      法  官  方鴻愷\n以上正本證明與原本無異。\n如不服本判決應於收受判決後10日內向本院提出上訴書狀，並\n應敘述具體理由。其未敘述上訴理由者，應於上訴期間屆滿後\n20日內向本院補提理由書（均須按他造當事人之人數附繕本）\n「切勿逕送上級法院」。\n                                書記官  金和國"
  },
  "characters": {
    "judges": [
      "王士珮",
      "楊明佳",
      "方鴻愷"
    ],
    "prosecutors": [
      "林慈雁"
    ],
    "lawyers": [

    ],
    "clerks": [
      "金和國"
    ],
    "plaintiffs": [

    ],
    "defendants": [
      "甲○○"
    ],
    "prosecutor_office": [
      "臺灣板橋地方法院檢察署檢察官"
    ],
    "creditors": [

    ],
    "debtors": [

    ],
    "judicial_associate_officer": [

    ]
  },
  "adjudged_at": "2010-05-12",
  "created_at": "2016-01-05 12:22:36",
  "updated_at": "2016-01-05 12:22:36"
}