{
  "identify": "PCD-99-訴-1044-20100512-1",
  "court": {
    "name": "臺灣新北地方法院",
    "code": "PCD"
  },
  "division": {
    "name": "刑事",
    "code": "M"
  },
  "year": 99,
  "word": "訴",
  "number": "1044",
  "jcheck": "1",
  "reason": "毒品危害防制條例",
  "content": "臺灣板橋地方法院刑事判決              99年度訴字第1044號\n公  訴  人  臺灣板橋地方法院檢察署檢察官\n被      告  甲○○\n上列被告因違反毒品危害防制條例案件，經檢察官提起公訴（99\n年度毒偵字第1989號），本院依簡式審判程序判決如下：\n    主  文\n甲○○施用第一級毒品，累犯，處有期徒刑柒月；扣案之第一級\n毒品海洛因壹包（驗餘淨重零點零陸貳零公克）沒收銷燬。\n    事  實\n一、甲○○前因施用毒品案件，經臺灣臺北地方法院以97年度毒\n    聲字第109 號裁定送觀察、勒戒後，認有繼續施用毒品之傾\n    向，再經同法院以97年度毒聲字第425 號裁定施以強制戒治\n    ，於民國98年2 月23日執行完畢釋放，並由臺灣臺北地方法\n    院檢察署檢察官以98年度戒毒偵字第56號為不起訴處分確定\n    。另因竊盜案件，經臺灣高等法院以97年度上易字第2533號\n    判處有期徒刑7 月確定，已於98年9 月22日縮刑期滿執行完\n    畢。仍不知悔改，於上開強制戒治執行完畢釋放後5 年內，\n    基於施用第一級毒品之犯意，於99年2 月24日17時許，在臺\n    北縣泰山鄉○○路某無人居住之公寓內，以將海洛因置於注\n    射針筒施打手臂之方法，施用第一級毒品海洛因1 次。嗣為\n    警於同日19時許，在臺北縣泰山鄉○○路與新生街口查獲，\n    並扣得第一級毒品海洛因他命1 包（淨重0.0640公克，取樣\n    0.0020公克鑑定用罄，驗餘淨重0.0620公克），經警採集其\n    尿液檢體送驗結果，呈鴉片類之陽性反應，始悉上情。\n二、案經臺北市政府警察局中正第一分局報請臺灣板橋地方法院\n    檢察署檢察官偵查起訴。本院於準備程序進行中，被告就被\n    訴事實為有罪之陳述，經告知被告簡式審判程序之旨，並聽\n    取當事人之意見後，裁定由受命法官獨任進行簡式審判程序\n    。\n    理  由\n一、上揭事實，業據被告甲○○於檢察官偵訊及本院審理時坦承\n    不諱，並有白色粉末1 包扣案可資佐證，且上開扣案物經送\n    鑑定結果，確為第一級毒品海洛因無訛，淨重0.0640公克，\n    取樣0.0020公克鑑定用罄，驗餘淨重0.0620公克等情，亦有\n    交通部民用航空局航空醫務中心99年3 月10日航藥鑑字第09\n    91494 號毒品鑑定書1 份在卷可憑。又被告為警查獲後，經\n    警採集其尿液檢體送驗結果，呈鴉片類之陽性反應，有臺北\n    市政府警察局偵辦毒品案件尿液檢體委驗單、臺灣尖端先進\n    生技醫藥股份有限公司99年3 月12日濫用藥物檢驗報告各1\n    份附卷可稽，足認被告之任意性自白與事實相符，堪值採信\n    。此外，被告前因施用毒品案件，經臺灣臺北地方法院以97\n    年度毒聲字第109 號裁定送觀察、勒戒後，認有繼續施用毒\n    品之傾向，再經同法院以97年度毒聲字第425 號裁定施以強\n    制戒治，於98年2 月23日執行完畢釋放，並由臺灣臺北地方\n    法院檢察署檢察官以98年度戒毒偵字第56號為不起訴處分確\n    定等情，則有臺灣高等法院被告前案紀錄表在卷可考，其於\n    觀察、勒戒執行完畢後5 年內，再犯本案施用毒品罪，應依\n    法訴追處罰。綜上所述，本案事證明確，被告犯行堪予認定\n    ，應依法論科。\n二、查海洛因係屬毒品危害防制條例所定之第一級毒品。核被告\n    所為，係犯毒品危害防制條例第10條第1 項之施用第一級毒\n    品罪。其持有第一級毒品海洛因之低度行為，為施用之高度\n    行為所吸收，不另論罪。又被告前因竊盜案件，經臺灣高等\n    法院以97年度上易字第2533號判處有期徒刑7 月確定，已於\n    98年9 月22日縮刑期滿執行完畢等情，有臺灣高等法院被告\n    前案紀錄表可憑，其於有期徒刑執行完畢後5 年內，故意再\n    犯本案有期徒刑以上之罪，為累犯，應依刑法第47條第1 項\n    規定加重其刑。爰審酌被告前因施用毒品，曾受觀察、勒戒\n    及強制戒治之執行完畢，獲有不起訴處分之寬典，仍不思戒\n    除惡習，再次漠視法令而犯本罪，非但戕害健康，對於社會\n    風氣、治安亦潛有相當危害，惟念其施用毒品所生惡害，實\n    以自戕身心健康為主，對於他人生命、身體、財產等法益，\n    尚無重大明顯之實害，兼衡其素行狀況、智識程度、犯罪之\n    動機、目的、手段暨於檢察官偵訊及本院審理時均坦承犯行\n    、態度良好等一切情狀，量處如主文所示之刑，以示懲儆。\n    扣案之海洛因他命1 包（淨重0.0640公克，取樣0.0020公克\n    鑑定用罄，驗餘合計淨重0.0620公克），為本案查獲之第一\n    級毒品，不問屬於犯人與否，應依毒品危害防制條例第18條\n    1 項前段規定沒收銷燬。\n據上論斷，應依刑事訴訟法第273 條之1 第1 項、第299 條第1\n項前段，毒品危害防制條例第10條第1 項、第18條第1 項前段，\n刑法第11條前段、第47條第1 項，判決如主文。\n本案經檢察官黃明絹到庭執行職務。\n中    華    民    國    99    年    5     月    12    日\n                  刑事第八庭    法  官  朱嘉川\n以上正本證明與原本無異。\n如不服本判決應於收受送達後10日內向本院提出上訴書狀，並應\n敘述具體理由；其未敘述上訴理由者，應於上訴期間屆滿後20日\n內向本院補提理由書（均須按他造當事人之人數附繕本）「切勿\n逕送上級法院」。\n                                書記官  陳聖儒\n中    華    民    國    99    年    5     月    12    日\n附錄本案論罪科刑法條全文：\n毒品危害防制條例第10條\n施用第一級毒品者，處6 月以上5 年以下有期徒刑。\n施用第二級毒品者，處3 年以下有期徒刑。",
  "structure": {
    "main": "甲○○施用第一級毒品，累犯，處有期徒刑柒月；扣案之第一級\n毒品海洛因壹包（驗餘淨重零點零陸貳零公克）沒收銷燬。",
    "fact": "一、甲○○前因施用毒品案件，經臺灣臺北地方法院以97年度毒\n    聲字第109 號裁定送觀察、勒戒後，認有繼續施用毒品之傾\n    向，再經同法院以97年度毒聲字第425 號裁定施以強制戒治\n    ，於民國98年2 月23日執行完畢釋放，並由臺灣臺北地方法\n    院檢察署檢察官以98年度戒毒偵字第56號為不起訴處分確定\n    。另因竊盜案件，經臺灣高等法院以97年度上易字第2533號\n    判處有期徒刑7 月確定，已於98年9 月22日縮刑期滿執行完\n    畢。仍不知悔改，於上開強制戒治執行完畢釋放後5 年內，\n    基於施用第一級毒品之犯意，於99年2 月24日17時許，在臺\n    北縣泰山鄉○○路某無人居住之公寓內，以將海洛因置於注\n    射針筒施打手臂之方法，施用第一級毒品海洛因1 次。嗣為\n    警於同日19時許，在臺北縣泰山鄉○○路與新生街口查獲，\n    並扣得第一級毒品海洛因他命1 包（淨重0.0640公克，取樣\n    0.0020公克鑑定用罄，驗餘淨重0.0620公克），經警採集其\n    尿液檢體送驗結果，呈鴉片類之陽性反應，始悉上情。\n二、案經臺北市政府警察局中正第一分局報請臺灣板橋地方法院\n    檢察署檢察官偵查起訴。本院於準備程序進行中，被告就被\n    訴事實為有罪之陳述，經告知被告簡式審判程序之旨，並聽\n    取當事人之意見後，裁定由受命法官獨任進行簡式審判程序\n    。",
    "reason": "一、上揭事實，業據被告甲○○於檢察官偵訊及本院審理時坦承\n    不諱，並有白色粉末1 包扣案可資佐證，且上開扣案物經送\n    鑑定結果，確為第一級毒品海洛因無訛，淨重0.0640公克，\n    取樣0.0020公克鑑定用罄，驗餘淨重0.0620公克等情，亦有\n    交通部民用航空局航空醫務中心99年3 月10日航藥鑑字第09\n    91494 號毒品鑑定書1 份在卷可憑。又被告為警查獲後，經\n    警採集其尿液檢體送驗結果，呈鴉片類之陽性反應，有臺北\n    市政府警察局偵辦毒品案件尿液檢體委驗單、臺灣尖端先進\n    生技醫藥股份有限公司99年3 月12日濫用藥物檢驗報告各1\n    份附卷可稽，足認被告之任意性自白與事實相符，堪值採信\n    。此外，被告前因施用毒品案件，經臺灣臺北地方法院以97\n    年度毒聲字第109 號裁定送觀察、勒戒後，認有繼續施用毒\n    品之傾向，再經同法院以97年度毒聲字第425 號裁定施以強\n    制戒治，於98年2 月23日執行完畢釋放，並由臺灣臺北地方\n    法院檢察署檢察官以98年度戒毒偵字第56號為不起訴處分確\n    定等情，則有臺灣高等法院被告前案紀錄表在卷可考，其於\n    觀察、勒戒執行完畢後5 年內，再犯本案施用毒品罪，應依\n    法訴追處罰。綜上所述，本案事證明確，被告犯行堪予認定\n    ，應依法論科。\n二、查海洛因係屬毒品危害防制條例所定之第一級毒品。核被告\n    所為，係犯毒品危害防制條例第10條第1 項之施用第一級毒\n    品罪。其持有第一級毒品海洛因之低度行為，為施用之高度\n    行為所吸收，不另論罪。又被告前因竊盜案件，經臺灣高等\n    法院以97年度上易字第2533號判處有期徒刑7 月確定，已於\n    98年9 月22日縮刑期滿執行完畢等情，有臺灣高等法院被告\n    前案紀錄表可憑，其於有期徒刑執行完畢後5 年內，故意再\n    犯本案有期徒刑以上之罪，為累犯，應依刑法第47條第1 項\n    規定加重其刑。爰審酌被告前因施用毒品，曾受觀察、勒戒\n    及強制戒治之執行完畢，獲有不起訴處分之寬典，仍不思戒\n    除惡習，再次漠視法令而犯本罪，非但戕害健康，對於社會\n    風氣、治安亦潛有相當危害，惟念其施用毒品所生惡害，實\n    以自戕身心健康為主，對於他人生命、身體、財產等法益，\n    尚無重大明顯之實害，兼衡其素行狀況、智識程度、犯罪之\n    動機、目的、手段暨於檢察官偵訊及本院審理時均坦承犯行\n    、態度良好等一切情狀，量處如主文所示之刑，以示懲儆。\n    扣案之海洛因他命1 包（淨重0.0640公克，取樣0.0020公克\n    鑑定用罄，驗餘合計淨重0.0620公克），為本案查獲之第一\n    級毒品，不問屬於犯人與否，應依毒品危害防制條例第18條\n    1 項前段規定沒收銷燬。\n據上論斷，應依刑事訴訟法第273 條之1 第1 項、第299 條第1\n項前段，毒品危害防制條例第10條第1 項、第18條第1 項前段，\n刑法第11條前段、第47條第1 項，判決如主文。\n本案經檢察官黃明絹到庭執行職務。\n中    華    民    國    99    年    5     月    12    日\n                  刑事第八庭    法  官  朱嘉川\n以上正本證明與原本無異。\n如不服本判決應於收受送達後10日內向本院提出上訴書狀，並應\n敘述具體理由；其未敘述上訴理由者，應於上訴期間屆滿後20日\n內向本院補提理由書（均須按他造當事人之人數附繕本）「切勿\n逕送上級法院」。\n                                書記官  陳聖儒"
  },
  "characters": {
    "judges": [
      "朱嘉川"
    ],
    "prosecutors": [
      "黃明絹"
    ],
    "lawyers": [

    ],
    "clerks": [
      "陳聖儒"
    ],
    "plaintiffs": [

    ],
    "defendants": [
      "甲○○"
    ],
    "prosecutor_office": [
      "臺灣板橋地方法院檢察署檢察官"
    ],
    "creditors": [

    ],
    "debtors": [

    ],
    "judicial_associate_officer": [

    ]
  },
  "adjudged_at": "2010-05-12",
  "created_at": "2016-01-05 12:26:57",
  "updated_at": "2016-01-05 12:26:57"
}