{
  "identify": "PCD-99-訴-949-20100512-1",
  "court": {
    "name": "臺灣新北地方法院",
    "code": "PCD"
  },
  "division": {
    "name": "刑事",
    "code": "M"
  },
  "year": 99,
  "word": "訴",
  "number": "949",
  "jcheck": "1",
  "reason": "毒品危害防制條例",
  "content": "臺灣板橋地方法院刑事判決               99年度訴字第949號\n公  訴  人  臺灣板橋地方法院檢察署檢察官\n被      告  甲○○\n上列被告因違反毒品危害防制條例案件，經檢察官提起公訴（98\n年度毒偵字第7764號、99年度毒偵字第557 號），本院依簡式審\n判程序判決如下：\n    主  文\n甲○○施用第一級毒品，處有期徒刑捌月。又施用第二級毒品，\n處有期徒刑肆月。又施用第一級毒品，處有期徒刑捌月；扣案之\n注射針筒壹支沒收。應執行有期徒刑壹年伍月；扣案之注射針筒\n壹支沒收。\n    事  實\n一、甲○○前因施用毒品案件，經本院以92年度毒聲字第2189號\n    裁定送觀察、勒戒後，認有繼續施用毒品之傾向，再經本院\n    以92年度毒聲字第2459號裁定施以強制戒治，嗣因成效評定\n    為合格，於民國93年3 月10日停止戒治，所餘期間付保護管\n    束，迄93年8 月5 日期滿未經撤銷停止戒治，視為強制戒治\n    執行完畢，並由臺灣板橋地方法院檢察署檢察官以93年度戒\n    毒偵字第145 號為不起訴處分確定。惟於上開強制戒治執行\n    完畢後5 年內，又迭因施用第一、二級毒品案件，先後經：\n    (一)臺灣桃園地方法院以93年度訴字第1816號判處有期徒刑7\n    月確定；(二)本院以95年度訴字第1488號判處有期徒刑10月、\n    3 月，並經臺灣高等法院以95年度上訴字第3016號、最高法\n    院以96年度台上字第87號駁回上訴確定（上開二案，嗣經臺\n    灣高等法院以96年度聲減字第4110號裁定減刑，並與另犯贓\n    物、違反槍砲彈藥刀械管制條案件經減刑後之刑，合併定其\n    應執行刑為有期徒刑1 年9 月確定；再與另犯偽造文書、竊\n    盜案件，經臺灣高等法院以同一裁定減刑並合併定其應執行\n    刑之有期徒刑5 月，及另犯竊盜、違反槍砲彈藥刀械管制條\n    例案件，經本院以94年度聲字第1434號裁定應合併執行之有\n    期徒刑1 年8 月接續執行，於97年12月15日縮短刑期假釋出\n    監，但嗣經撤銷假釋，目前仍在監執行殘刑5 月又15日中，\n    不致使本案成立累犯，起訴書誤認成立累犯）；(三)本院以98\n    年度訴字第3058號判處有期徒刑10月、5 月，應執行有期徒\n    刑1 年1 月確定；(四)本院以98年度訴字第3858號判處有期徒\n    刑7 月、3 月，應執行有期徒刑9 月確定（上開二案，目前\n    仍在監執行中，亦不致使本案成立累犯）。\n二、詎甲○○仍不思戒除惡習，分別為下列行為：\n  (一)基於施用第一、二級毒品之犯意，於98年8 月16日下午某時\n    （起訴書誤載為98年8 月14日20時20分許），在其位於臺北\n    縣板橋市縣○○道○ 段247 巷3 號5 樓住處，各以將海洛因\n    置入注射針筒施打手臂、將甲基安非他命置入吸食器之玻璃\n    球燒烤吸聞所生煙氣之方法，分別施用第一級毒品海洛因、\n    第二級毒品甲基安非他命各1 次。嗣甲○○因另涉竊盜案件\n    ，於同日18時20分許為警查獲，於警詢時同意警方採集其尿\n    涉檢體送驗，並於有偵查犯罪權限之機關人員知悉其涉犯上\n    開施用第一、二級毒品罪嫌前，分別向警察、檢察官承認而\n    自首之，並接受裁判。\n  (二)基於施用第一級毒品之犯意，於98年12月31日16時50分許，\n    在臺北縣三重市「大同公園」廁所內，以將海洛因置入注射\n    針筒施打手臂之方法，施用第一級毒品海洛因1 次。嗣甲○\n    ○於同日16時55分許，在臺北縣三重市○○○路186 號前，\n    遇警盤查，同意警方對其實施搜索，並於有偵查犯罪權限之\n    機關人員知悉其涉犯上開施用第一級毒品罪嫌前，主動向警\n    察坦承有施用毒品惡習，且交出其所有、供施用第一級毒品\n    海洛因所用之注射針筒1 支而自首之，並接受裁判。\n三、案經臺北縣政府警察局新莊分局、三重分局報請臺灣板橋地\n    方法院檢察署檢察官偵查起訴。本院於準備程序進行中，被\n    告就被訴事實為有罪之陳述，經告知被告簡式審判程序之旨\n    ，並聽取當事人之意見後，裁定由受命法官獨任進行簡式審\n    判程序。\n    理  由\n一、上揭事實，均據被告甲○○於本院審理時坦承不諱，且有注\n    射針筒1 支扣案可資佐證。又被告先後二次為警查獲後，經\n    警採集其尿液檢體送驗結果，第一次呈鴉片類及安非他命類\n    之陽性反應、第二次呈鴉片類之陽性反應，此有臺灣檢驗科\n    技股份有限公司98年10月9 日、99年1 月25日濫用藥物檢驗\n    報告各1 份附卷可稽，足以擔保被告之自白與事實相符，而\n    值採信。\n二、按毒品危害防制條例於92年7 月9 日修正公布，自93年1 月\n    9 日施行，其中第20條、第23條將施用毒品之刑事處遇程序\n    ，區分為「初犯」及「5 年內再犯」、「5 年後再犯」。依\n    其立法理由之說明：「初犯」，經觀察、勒戒或強制戒治後\n    ，應為不起訴處分或不付審理之裁定；經觀察、勒戒或強制\n    戒治執行完畢釋放後，「5 年內再犯」者，因其再犯率甚高\n    ，原實施之觀察、勒戒及強制戒治既已無法收其實效，爰依\n    法追訴或裁定交付審理。至於經觀察、勒戒或強制戒治執行\n    完畢釋放後，「5 年後再犯」者，前所實施之觀察、勒戒或\n    強制戒治已足以遮斷其施用毒品之毒癮，為期自新及協助其\n    斷除毒癮，仍適用「初犯」規定，先經觀察、勒戒或強制戒\n    治之程序。從而依修正後之規定，僅限於「初犯」及「5 年\n    後再犯」二種情形，始應先經觀察、勒戒或強制戒治程序。\n    倘被告於5 年內已再犯，經依法追訴處罰，縱其第3 次（或\n    第3 次以上）再度施用毒品之時間，在初犯經觀察、勒戒或\n    強制戒治執行完畢釋放5 年以後，已不合於「5 年後再犯」\n    之規定，且因已於「5 年內再犯」，顯見其再犯率甚高，原\n    實施觀察、勒戒或強制戒治，已無法收其實效，即應依該條\n    例第10條處罰（最高法院95年第7 次刑事庭會議決定參照）\n    。查被告有上揭事實欄第一項所示之觀察、勒戒、強制戒治\n    及科刑處罰紀錄，此有臺灣高等法院被告前案紀錄表在卷可\n    憑。被告於93年8 月5 日強制戒治執行完畢後5 年內，又迭\n    因施用第一、二級毒品案件，先後經：(一)臺灣桃園地方法院\n    以93年度訴字第1816號判處有期徒刑7 月確定；(二)本院以95\n    年度訴字第1488號判處有期徒刑10月、3 月，並經臺灣高等\n    法院以95年度上訴字第3016號、最高法院以96年度台上字第\n    87號駁回上訴確定；(三)本院以98年度訴字第3058號判處有期\n    徒刑10月、5 月，應執行有期徒刑1 年1 月確定；(四)本院以\n    98年度訴字第3858號判處有期徒刑7 月、3 月，應執行有期\n    徒刑9 月確定，縱被告於本案施用毒品之時間，係在上開強\n    制戒治執行完畢5 年以後，揆諸前揭說明，仍應依毒品危害\n    防制條例第10條規定處罰。綜上所述，本案事證明確，被告\n    犯行堪予認定，應依法論科。\n三、查海洛因、甲基安非他命分別係屬毒品危害防制條例所定之\n    第一、二級毒品。是核被告所為，係犯毒品危害防制條例第\n    10條第1 項之施用第一級毒品罪、同條第2 項之施用第二級\n    毒品罪。其持有第一級毒品海洛因、第二級毒品甲基安非他\n    命之低度行為，各為施用之高度行為所吸收，均不另論罪。\n    被告先後犯施用第一級毒品罪2 罪、施用第二級毒品罪1 罪\n    ，所犯上開3 罪，犯意各別，行為互殊，應予分論併罰。就\n    上開事實欄第二項(一)部分，被告係因另涉竊盜案件為警查獲\n    ，於警詢時同意警方採集其尿涉檢體送驗，並於有偵查犯罪\n    權限之機關人員知悉其涉犯該部分施用第一、二級毒品罪嫌\n    前，分別向警察、檢察官承認而自首之；就上開事實欄第二\n    項(二)部分，被告係在路上遇警盤查，同意警方對其實施搜索\n    ，並於有偵查犯罪權限之機關人員知悉其涉犯上開施用第一\n    級毒品罪嫌前，主動向警察坦承有施用毒品惡習，且交出扣\n    案之注射針筒1 支而自首之，此觀相關警詢、偵訊筆錄所載\n    甚明，嗣被告亦未逃避接受裁判，合於自首要件，爰依刑法\n    第62條前段規定減輕其刑。爰審酌被告前因施用毒品，曾受\n    觀察、勒戒及強制戒治之執行完畢，獲有不起訴處分之寬典\n    ，並迭經論罪科刑，仍不思戒除惡習，再次漠視法令而犯本\n    罪，非但戕害健康，對於社會風氣、治安亦潛有相當危害，\n    惟念其施用毒品所生惡害，實以自戕身心健康為主，對於他\n    人生命、身體、財產等法益，尚無重大明顯之實害，兼衡其\n    素行狀況、智識程度、犯罪之動機、目的、手段及犯罪後之\n    態度等一切情狀，分別量處如主文所示之刑，並定其應執行\n    刑，以示懲儆。扣案之注射針筒1 支，為被告所有，供其犯\n    上揭事實欄第二項(二)部分之施用第一級毒品罪所用之物，業\n    據被告供承在卷，爰依刑法第38條第1 項第2 款規定宣告沒\n    收之。\n據上論斷，應依刑事訴訟法第273 條之1 第1 項、第299 條第1\n項前段，毒品危害防制條例第10條第1 項、第2 項，刑法第11條\n前段、第62條前段、第51條第5 款、第38條第1 項第2 款，判決\n如主文。\n本案經檢察官黃明絹到庭執行職務。\n中    華    民    國    99    年    5     月    12    日\n                  刑事第八庭    法  官  朱嘉川\n以上正本證明與原本無異。\n如不服本判決應於收受送達後10日內向本院提出上訴書狀，並應\n敘述具體理由；其未敘述上訴理由者，應於上訴期間屆滿後20日\n內向本院補提理由書（均須按他造當事人之人數附繕本）「切勿\n逕送上級法院」。\n                                書記官  陳聖儒\n中    華    民    國    99    年    5     月    12    日\n附錄本案論罪科刑法條全文：\n毒品危害防制條例第10條\n施用第一級毒品者，處6 月以上5 年以下有期徒刑。\n施用第二級毒品者，處3 年以下有期徒刑。",
  "structure": {
    "main": "甲○○施用第一級毒品，處有期徒刑捌月。又施用第二級毒品，\n處有期徒刑肆月。又施用第一級毒品，處有期徒刑捌月；扣案之\n注射針筒壹支沒收。應執行有期徒刑壹年伍月；扣案之注射針筒\n壹支沒收。",
    "fact": "一、甲○○前因施用毒品案件，經本院以92年度毒聲字第2189號\n    裁定送觀察、勒戒後，認有繼續施用毒品之傾向，再經本院\n    以92年度毒聲字第2459號裁定施以強制戒治，嗣因成效評定\n    為合格，於民國93年3 月10日停止戒治，所餘期間付保護管\n    束，迄93年8 月5 日期滿未經撤銷停止戒治，視為強制戒治\n    執行完畢，並由臺灣板橋地方法院檢察署檢察官以93年度戒\n    毒偵字第145 號為不起訴處分確定。惟於上開強制戒治執行\n    完畢後5 年內，又迭因施用第一、二級毒品案件，先後經：\n    (一)臺灣桃園地方法院以93年度訴字第1816號判處有期徒刑7\n    月確定；(二)本院以95年度訴字第1488號判處有期徒刑10月、\n    3 月，並經臺灣高等法院以95年度上訴字第3016號、最高法\n    院以96年度台上字第87號駁回上訴確定（上開二案，嗣經臺\n    灣高等法院以96年度聲減字第4110號裁定減刑，並與另犯贓\n    物、違反槍砲彈藥刀械管制條案件經減刑後之刑，合併定其\n    應執行刑為有期徒刑1 年9 月確定；再與另犯偽造文書、竊\n    盜案件，經臺灣高等法院以同一裁定減刑並合併定其應執行\n    刑之有期徒刑5 月，及另犯竊盜、違反槍砲彈藥刀械管制條\n    例案件，經本院以94年度聲字第1434號裁定應合併執行之有\n    期徒刑1 年8 月接續執行，於97年12月15日縮短刑期假釋出\n    監，但嗣經撤銷假釋，目前仍在監執行殘刑5 月又15日中，\n    不致使本案成立累犯，起訴書誤認成立累犯）；(三)本院以98\n    年度訴字第3058號判處有期徒刑10月、5 月，應執行有期徒\n    刑1 年1 月確定；(四)本院以98年度訴字第3858號判處有期徒\n    刑7 月、3 月，應執行有期徒刑9 月確定（上開二案，目前\n    仍在監執行中，亦不致使本案成立累犯）。\n二、詎甲○○仍不思戒除惡習，分別為下列行為：\n  (一)基於施用第一、二級毒品之犯意，於98年8 月16日下午某時\n    （起訴書誤載為98年8 月14日20時20分許），在其位於臺北\n    縣板橋市縣○○道○ 段247 巷3 號5 樓住處，各以將海洛因\n    置入注射針筒施打手臂、將甲基安非他命置入吸食器之玻璃\n    球燒烤吸聞所生煙氣之方法，分別施用第一級毒品海洛因、\n    第二級毒品甲基安非他命各1 次。嗣甲○○因另涉竊盜案件\n    ，於同日18時20分許為警查獲，於警詢時同意警方採集其尿\n    涉檢體送驗，並於有偵查犯罪權限之機關人員知悉其涉犯上\n    開施用第一、二級毒品罪嫌前，分別向警察、檢察官承認而\n    自首之，並接受裁判。\n  (二)基於施用第一級毒品之犯意，於98年12月31日16時50分許，\n    在臺北縣三重市「大同公園」廁所內，以將海洛因置入注射\n    針筒施打手臂之方法，施用第一級毒品海洛因1 次。嗣甲○\n    ○於同日16時55分許，在臺北縣三重市○○○路186 號前，\n    遇警盤查，同意警方對其實施搜索，並於有偵查犯罪權限之\n    機關人員知悉其涉犯上開施用第一級毒品罪嫌前，主動向警\n    察坦承有施用毒品惡習，且交出其所有、供施用第一級毒品\n    海洛因所用之注射針筒1 支而自首之，並接受裁判。\n三、案經臺北縣政府警察局新莊分局、三重分局報請臺灣板橋地\n    方法院檢察署檢察官偵查起訴。本院於準備程序進行中，被\n    告就被訴事實為有罪之陳述，經告知被告簡式審判程序之旨\n    ，並聽取當事人之意見後，裁定由受命法官獨任進行簡式審\n    判程序。",
    "reason": "一、上揭事實，均據被告甲○○於本院審理時坦承不諱，且有注\n    射針筒1 支扣案可資佐證。又被告先後二次為警查獲後，經\n    警採集其尿液檢體送驗結果，第一次呈鴉片類及安非他命類\n    之陽性反應、第二次呈鴉片類之陽性反應，此有臺灣檢驗科\n    技股份有限公司98年10月9 日、99年1 月25日濫用藥物檢驗\n    報告各1 份附卷可稽，足以擔保被告之自白與事實相符，而\n    值採信。\n二、按毒品危害防制條例於92年7 月9 日修正公布，自93年1 月\n    9 日施行，其中第20條、第23條將施用毒品之刑事處遇程序\n    ，區分為「初犯」及「5 年內再犯」、「5 年後再犯」。依\n    其立法理由之說明：「初犯」，經觀察、勒戒或強制戒治後\n    ，應為不起訴處分或不付審理之裁定；經觀察、勒戒或強制\n    戒治執行完畢釋放後，「5 年內再犯」者，因其再犯率甚高\n    ，原實施之觀察、勒戒及強制戒治既已無法收其實效，爰依\n    法追訴或裁定交付審理。至於經觀察、勒戒或強制戒治執行\n    完畢釋放後，「5 年後再犯」者，前所實施之觀察、勒戒或\n    強制戒治已足以遮斷其施用毒品之毒癮，為期自新及協助其\n    斷除毒癮，仍適用「初犯」規定，先經觀察、勒戒或強制戒\n    治之程序。從而依修正後之規定，僅限於「初犯」及「5 年\n    後再犯」二種情形，始應先經觀察、勒戒或強制戒治程序。\n    倘被告於5 年內已再犯，經依法追訴處罰，縱其第3 次（或\n    第3 次以上）再度施用毒品之時間，在初犯經觀察、勒戒或\n    強制戒治執行完畢釋放5 年以後，已不合於「5 年後再犯」\n    之規定，且因已於「5 年內再犯」，顯見其再犯率甚高，原\n    實施觀察、勒戒或強制戒治，已無法收其實效，即應依該條\n    例第10條處罰（最高法院95年第7 次刑事庭會議決定參照）\n    。查被告有上揭事實欄第一項所示之觀察、勒戒、強制戒治\n    及科刑處罰紀錄，此有臺灣高等法院被告前案紀錄表在卷可\n    憑。被告於93年8 月5 日強制戒治執行完畢後5 年內，又迭\n    因施用第一、二級毒品案件，先後經：(一)臺灣桃園地方法院\n    以93年度訴字第1816號判處有期徒刑7 月確定；(二)本院以95\n    年度訴字第1488號判處有期徒刑10月、3 月，並經臺灣高等\n    法院以95年度上訴字第3016號、最高法院以96年度台上字第\n    87號駁回上訴確定；(三)本院以98年度訴字第3058號判處有期\n    徒刑10月、5 月，應執行有期徒刑1 年1 月確定；(四)本院以\n    98年度訴字第3858號判處有期徒刑7 月、3 月，應執行有期\n    徒刑9 月確定，縱被告於本案施用毒品之時間，係在上開強\n    制戒治執行完畢5 年以後，揆諸前揭說明，仍應依毒品危害\n    防制條例第10條規定處罰。綜上所述，本案事證明確，被告\n    犯行堪予認定，應依法論科。\n三、查海洛因、甲基安非他命分別係屬毒品危害防制條例所定之\n    第一、二級毒品。是核被告所為，係犯毒品危害防制條例第\n    10條第1 項之施用第一級毒品罪、同條第2 項之施用第二級\n    毒品罪。其持有第一級毒品海洛因、第二級毒品甲基安非他\n    命之低度行為，各為施用之高度行為所吸收，均不另論罪。\n    被告先後犯施用第一級毒品罪2 罪、施用第二級毒品罪1 罪\n    ，所犯上開3 罪，犯意各別，行為互殊，應予分論併罰。就\n    上開事實欄第二項(一)部分，被告係因另涉竊盜案件為警查獲\n    ，於警詢時同意警方採集其尿涉檢體送驗，並於有偵查犯罪\n    權限之機關人員知悉其涉犯該部分施用第一、二級毒品罪嫌\n    前，分別向警察、檢察官承認而自首之；就上開事實欄第二\n    項(二)部分，被告係在路上遇警盤查，同意警方對其實施搜索\n    ，並於有偵查犯罪權限之機關人員知悉其涉犯上開施用第一\n    級毒品罪嫌前，主動向警察坦承有施用毒品惡習，且交出扣\n    案之注射針筒1 支而自首之，此觀相關警詢、偵訊筆錄所載\n    甚明，嗣被告亦未逃避接受裁判，合於自首要件，爰依刑法\n    第62條前段規定減輕其刑。爰審酌被告前因施用毒品，曾受\n    觀察、勒戒及強制戒治之執行完畢，獲有不起訴處分之寬典\n    ，並迭經論罪科刑，仍不思戒除惡習，再次漠視法令而犯本\n    罪，非但戕害健康，對於社會風氣、治安亦潛有相當危害，\n    惟念其施用毒品所生惡害，實以自戕身心健康為主，對於他\n    人生命、身體、財產等法益，尚無重大明顯之實害，兼衡其\n    素行狀況、智識程度、犯罪之動機、目的、手段及犯罪後之\n    態度等一切情狀，分別量處如主文所示之刑，並定其應執行\n    刑，以示懲儆。扣案之注射針筒1 支，為被告所有，供其犯\n    上揭事實欄第二項(二)部分之施用第一級毒品罪所用之物，業\n    據被告供承在卷，爰依刑法第38條第1 項第2 款規定宣告沒\n    收之。\n據上論斷，應依刑事訴訟法第273 條之1 第1 項、第299 條第1\n項前段，毒品危害防制條例第10條第1 項、第2 項，刑法第11條\n前段、第62條前段、第51條第5 款、第38條第1 項第2 款，判決\n如主文。\n本案經檢察官黃明絹到庭執行職務。\n中    華    民    國    99    年    5     月    12    日\n                  刑事第八庭    法  官  朱嘉川\n以上正本證明與原本無異。\n如不服本判決應於收受送達後10日內向本院提出上訴書狀，並應\n敘述具體理由；其未敘述上訴理由者，應於上訴期間屆滿後20日\n內向本院補提理由書（均須按他造當事人之人數附繕本）「切勿\n逕送上級法院」。\n                                書記官  陳聖儒"
  },
  "characters": {
    "judges": [
      "朱嘉川"
    ],
    "prosecutors": [
      "黃明絹"
    ],
    "lawyers": [

    ],
    "clerks": [
      "陳聖儒"
    ],
    "plaintiffs": [

    ],
    "defendants": [
      "甲○○"
    ],
    "prosecutor_office": [
      "臺灣板橋地方法院檢察署檢察官"
    ],
    "creditors": [

    ],
    "debtors": [

    ],
    "judicial_associate_officer": [

    ]
  },
  "adjudged_at": "2010-05-12",
  "created_at": "2016-01-05 12:26:52",
  "updated_at": "2016-01-05 12:26:52"
}