{
  "identify": "PCD-99-易-759-20100512-4",
  "court": {
    "name": "臺灣新北地方法院",
    "code": "PCD"
  },
  "division": {
    "name": "刑事",
    "code": "M"
  },
  "year": 99,
  "word": "易",
  "number": "759",
  "jcheck": "4",
  "reason": "詐欺",
  "content": "臺灣板橋地方法院刑事判決               99年度易字第759號\n公  訴  人  臺灣板橋地方法院檢察署檢察官\n被      告  丙○○\n上列被告因詐欺案件，經檢察官提起公訴（98年度偵字第31821號）\n，本院判決如下：\n    主  文\n本件管轄錯誤，移送於臺灣桃園地方法院。\n    理  由\n一、公訴意旨略以：被告丙○○於民國98年1 月初，原依報刊廣\n    告應徵工作，俟其與真實姓名年籍不詳、綽號「蔡哥」之成\n    年男子聯絡後，明知其所從事之工作，係以詐術收取人頭帳\n    戶，竟與該詐欺集團成員共同基於意圖為自己不法所有之犯\n    意，為圖牟利，遂應允以每次新臺幣1,000 元之代價收取帳\n    戶，期間「蔡哥」以門號0000000000或0000000000之行動電\n    話與被告所使用之門號0000000000行動電話聯繫，由「蔡哥\n    」指示被告至附表二各編號所示地點，向遭詐欺集團以應徵\n    工作為由受詐騙如附表二所示之被害人收取履歷表、金融機\n    構存摺、金融卡、密碼等證件，待被告取得後，再依「蔡哥\n    」之指示放置在火車站置物櫃，被告再以手機簡訊或撥打電\n    話告知「蔡哥」置物櫃之編號及密碼，俟「蔡哥」取得上開\n    證件後，再以電話通知被告至何編號（密碼）之置物櫃領取\n    報酬，經循線追查，始悉上情，因認被告涉犯刑法第339 條\n    第1 項之詐欺取財罪嫌等語。\n二、按案件由犯罪地或被告之住所、居所或所在地之法院管轄；\n    無管轄權之案件，應諭知管轄錯誤之判決，並同時諭知移送\n    於管轄法院，而此管轄錯誤判決，得不經言詞辯論為之，刑\n    事訴訟法第5 條第1 項、第304 條、第307 條分別定有明文\n    。\n三、查被告丙○○固對公訴人所指之犯行供承不諱，並經證人即\n    被害人丁○○、己○○於警詢、偵查中指述綦詳，惟本件公\n    訴意旨所指之犯罪地係在桃園縣中壢市之中壢後火車站，而\n    被告經檢察官於99年3 月19日起訴時其住所、居所均係在桃\n    園縣龜山鄉，被告則因另案經借提至臺灣彰化監獄彰化分監\n    ，均非在本院轄區內，亦有被告個人基本資料查詢、遷徒紀\n    錄資料查詢結果、臺灣高等法院在監在押全國紀錄表在卷足\n    稽。本院對同案起訴之被告乙○○被訴詐欺取財部分（詳見\n    附表一所示，業經本院另行審結）雖有管轄權，但細繹起訴\n    意旨，「蔡哥」之人迄未能具體查明，且被告與乙○○間又\n    無數人共犯一罪或數罪、數人同時在同一處所各別犯罪等情\n    形，並非相牽連之案件，要無牽連管轄可言。綜上，本院就\n    被告丙○○部分無管轄權甚明，茲公訴人仍向本院提起公訴\n    ，揆諸上開規定，自有未合，爰不經言詞辯論，逕為諭知管\n    轄錯誤之判決，並移送於管轄之臺灣桃園地方法院。\n據上論斷，應依刑事訴訟法第304 條、第307 條，判決如主文。\n中    華    民    國    99    年    5     月    12    日\n                刑事第十一庭  審判長法  官  張江澤\n                                    法  官  劉景宜\n                                    法  官  陳海寧\n以上正本證明與原本無異。\n如不服本判決應於收受判決後10日內向本院提出上訴書狀，並\n應敘述具體理由。其未敘述上訴理由者，應於上訴期間屆滿後\n20日內向本院補提理由書（均須按他造當事人之人數附繕本）\n「切勿逕送上級法院」。\n                                    書記官  梁宜庭\n中    華    民    國    99    年    5     月    14    日\n 附表一：\n ┌──┬───┬────┬──────┬────┬─────┐\n │編號│被害人│詐騙時間│詐騙方式    │詐騙地點│詐得之帳戶│\n ├──┼───┼────┼──────┼────┼─────┤\n │ 1  │戊○○│98年1月 │刊登報紙，應│臺北縣板│中國信託銀│\n │    │      │12日    │徵司機，需提│橋市錢櫃│行帳戶（帳│\n │    │      │        │供帳戶、金融│KTV     │號00000000│\n │    │      │        │卡          │        │91號）    │\n ├──┼───┼────┼──────┼────┼─────┤\n │ 2  │甲○○│97年底  │刊登報紙，應│中和南勢│中國信託銀│\n │    │      │        │徵司機，需提│角      │行帳戶（帳│\n │    │      │        │供帳戶、金融│        │號00000000│\n │    │      │        │卡          │        │66號）、合│\n │    │      │        │            │        │作金庫帳戶│\n │    │      │        │            │        │（帳號0560│\n │    │      │        │            │        │000000000 │\n │    │      │        │            │        │號）      │\n └──┴───┴────┴──────┴────┴─────┘\n 附表二：\n ┌──┬───┬────┬──────┬────┬─────┐\n │編號│被害人│詐騙時間│詐騙方式    │詐騙地點│詐得之帳戶│\n ├──┼───┼────┼──────┼────┼─────┤\n │ 1  │丁○○│98.2.19 │刊登報紙，應│中壢後火│渣打銀行帳│\n │    │      │        │徵司機，客人│車站    │戶（帳號  │\n │    │      │        │會把款項直接│        │0000000000│\n │    │      │        │匯入司機帳戶│        │566006號）│\n │    │      │        │內，所以需要│        │          │\n │    │      │        │提供帳戶、金│        │          │\n │    │      │        │融卡、密碼  │        │          │\n ├──┼───┼────┼──────┼────┼─────┤\n │ 2  │己○○│98.2.19 │刊登報紙，應│中壢後火│中國信託銀│\n │    │      │        │徵司機，客人│車站    │行帳戶（帳│\n │    │      │        │會把款項直接│        │號00000000│\n │    │      │        │匯入司機帳戶│        │00000000號│\n │    │      │        │內，所以需要│        │）        │\n │    │      │        │提供帳戶、金│        │          │\n │    │      │        │融卡、密碼  │        │          │\n └──┴───┴────┴──────┴────┴─────┘",
  "structure": {
    "main": "本件管轄錯誤，移送於臺灣桃園地方法院。",
    "reason": "一、公訴意旨略以：被告丙○○於民國98年1 月初，原依報刊廣\n    告應徵工作，俟其與真實姓名年籍不詳、綽號「蔡哥」之成\n    年男子聯絡後，明知其所從事之工作，係以詐術收取人頭帳\n    戶，竟與該詐欺集團成員共同基於意圖為自己不法所有之犯\n    意，為圖牟利，遂應允以每次新臺幣1,000 元之代價收取帳\n    戶，期間「蔡哥」以門號0000000000或0000000000之行動電\n    話與被告所使用之門號0000000000行動電話聯繫，由「蔡哥\n    」指示被告至附表二各編號所示地點，向遭詐欺集團以應徵\n    工作為由受詐騙如附表二所示之被害人收取履歷表、金融機\n    構存摺、金融卡、密碼等證件，待被告取得後，再依「蔡哥\n    」之指示放置在火車站置物櫃，被告再以手機簡訊或撥打電\n    話告知「蔡哥」置物櫃之編號及密碼，俟「蔡哥」取得上開\n    證件後，再以電話通知被告至何編號（密碼）之置物櫃領取\n    報酬，經循線追查，始悉上情，因認被告涉犯刑法第339 條\n    第1 項之詐欺取財罪嫌等語。\n二、按案件由犯罪地或被告之住所、居所或所在地之法院管轄；\n    無管轄權之案件，應諭知管轄錯誤之判決，並同時諭知移送\n    於管轄法院，而此管轄錯誤判決，得不經言詞辯論為之，刑\n    事訴訟法第5 條第1 項、第304 條、第307 條分別定有明文\n    。\n三、查被告丙○○固對公訴人所指之犯行供承不諱，並經證人即\n    被害人丁○○、己○○於警詢、偵查中指述綦詳，惟本件公\n    訴意旨所指之犯罪地係在桃園縣中壢市之中壢後火車站，而\n    被告經檢察官於99年3 月19日起訴時其住所、居所均係在桃\n    園縣龜山鄉，被告則因另案經借提至臺灣彰化監獄彰化分監\n    ，均非在本院轄區內，亦有被告個人基本資料查詢、遷徒紀\n    錄資料查詢結果、臺灣高等法院在監在押全國紀錄表在卷足\n    稽。本院對同案起訴之被告乙○○被訴詐欺取財部分（詳見\n    附表一所示，業經本院另行審結）雖有管轄權，但細繹起訴\n    意旨，「蔡哥」之人迄未能具體查明，且被告與乙○○間又\n    無數人共犯一罪或數罪、數人同時在同一處所各別犯罪等情\n    形，並非相牽連之案件，要無牽連管轄可言。綜上，本院就\n    被告丙○○部分無管轄權甚明，茲公訴人仍向本院提起公訴\n    ，揆諸上開規定，自有未合，爰不經言詞辯論，逕為諭知管\n    轄錯誤之判決，並移送於管轄之臺灣桃園地方法院。\n據上論斷，應依刑事訴訟法第304 條、第307 條，判決如主文。"
  },
  "characters": {
    "judges": [
      "張江澤",
      "劉景宜",
      "陳海寧"
    ],
    "prosecutors": [

    ],
    "lawyers": [

    ],
    "clerks": [
      "梁宜庭"
    ],
    "plaintiffs": [

    ],
    "defendants": [
      "丙○○"
    ],
    "prosecutor_office": [
      "臺灣板橋地方法院檢察署檢察官"
    ],
    "creditors": [

    ],
    "debtors": [

    ],
    "judicial_associate_officer": [

    ]
  },
  "adjudged_at": "2010-05-12",
  "created_at": "2016-01-05 12:25:03",
  "updated_at": "2016-01-05 12:25:03"
}