{
  "identify": "PCD-98-訴-1063-20100512-1",
  "court": {
    "name": "臺灣新北地方法院",
    "code": "PCD"
  },
  "division": {
    "name": "民事",
    "code": "V"
  },
  "year": 98,
  "word": "訴",
  "number": "1063",
  "jcheck": "1",
  "reason": "拆屋還地等",
  "content": "臺灣板橋地方法院民事判決              98年度訴字第1063號\n原      告  戊○○\n            乙○○\n            丙○○\n            丁○○\n上四人共同\n訴訟代理人  林彥增律師\n複  代理人  郭芳宜律師\n被      告  庚○○○\n訴訟代理人  辛○\n被      告  己○○\n            甲○○\n上列當事人間請求拆屋還地等事件，經本院於民國99年4 月21日\n言詞辯論終結，判決如下：\n    主  文\n確認原告就門牌號碼臺北縣三峽鎮○○路67巷27號之房屋如附圖\n(二)14 4（A ）所示面積67 .84平方公尺、143 （A ）所示面積87\n.95 平方公尺、97（A ）所示面積2.83平方公尺有優先承買權存\n在；被告庚○○○與甲○○間就上開房屋以新臺幣28萬元所為之\n買賣行為，准原告以同一價額優先承買。\n原告其餘之訴及假執行之聲請均駁回。\n訴訟費用由原告負擔二分之一，餘由被告負擔。\n    事實及理由\n壹、程序事項：\n一、按訴狀送達後，原告不得將原訴變更或追加他訴。但有下列\n    各款情形之一者，不在此限：... 2.請求之基礎事實同一者\n    。3.擴張或減縮應受判決事項之聲明者。... 7.不甚礙被告\n    之防禦及訴訟之終結者。民事訴訟法第255 條第1 項第2 、\n    3 、7 款定有明文。查原告起訴時之聲明為「被告庚○○\n    ○、己○○、梁富寶應將坐落臺北縣三峽鎮○○段144 地號\n    土地上建物門牌號碼臺北縣三峽鎮○○路67巷27號如附圖(一)\n    A 所示面積41 .75平方公尺之房屋，於原告給付新臺幣126,\n     000元之同時交付予原告。被告甲○○應將坐落臺北縣三\n    峽鎮○○段143 地號土地上建物門牌號碼臺北縣三峽鎮○○\n    路67巷27號如附圖(一)B 所示面積86.46 平方公尺及同段97地\n    號土地上同門牌號碼建物如附圖(一)C 所示面積2.83平方公尺\n    之房屋拆除，將土地返還予原告。被告甲○○應自上開門\n    牌號碼房屋遷出。願供擔保請准宣告假執行。」，嗣經本\n    院履勘現場及測量面積後，原告於98年11月3 日具狀更正聲\n    明為「確認被告甲○○與被告庚○○○間就坐落門牌號碼\n    臺北縣三峽鎮○○路67巷27號建物如附圖(二)144 （A ）所示\n    面積67.84 平方公尺部分於民國97年8 月14日之買賣關係不\n    存在。被告庚○○○、己○○應將坐落臺北縣三峽鎮○○\n    路67巷27號建物如附圖(二)144 （A ）所示面積67.84 平方公\n    尺之房屋，於原告給付新臺幣12萬6 千元之同時交付予原告\n    ，歸原告所有。被告甲○○應將坐落臺北縣三峽鎮○○段\n    143 地號土地上建物門牌號碼臺北縣三峽鎮○○路67巷27號\n    如附圖(二)143 （A ）所示面積87.95 平方公尺及同段97地號\n    土地上同門牌號碼建物如附圖97（A ）所示面積2.83平方公\n    尺之房屋拆除，將土地返還原告。被告甲○○應自第一項\n    門牌號碼房屋遷出。願供擔保請准宣告假執行。」，後又\n    於99年1 月6 日具狀更正聲明為：「確認原告等就坐落門\n    牌號碼臺北縣三峽鎮○○路67巷27號之房屋如附圖(二)14 4（\n    A ）所示面積67.84 平方公尺部分有優先承買權存在。被\n    告等就上開房屋部分以新臺幣12萬6 千元所為之買賣行為，\n    准由原告等以同一價額優先承購。被告甲○○應自前項門\n    牌號碼房屋如附圖144 （A ）部分遷出。被告甲○○應將\n    坐落臺北縣三峽鎮○○段143 地號土地上建物門牌號碼臺北\n    縣三峽鎮○○路67巷27號如附圖(二)143 （A ）所示面積87.9\n    5 平方公尺及同段97地號土地上同門牌號碼建物如附圖97（\n    A ）所示面積2.83平方公尺之房屋拆除，將土地返還原告。\n    願供擔保請准宣告假執行。」，後原告以附圖(二)之14 4（\n    A ）、143 （A ）、97（A ）等三部分係合一，不能分別獨\n    立，而又於99年4 月16日提出言詞辯論要旨續狀更正聲明為\n    ：「甲、先位聲明確認原告等就坐落門牌號碼臺北縣三峽\n    鎮○○路67巷27號之房屋如附圖(二)14 4（A ）所示面積67.8\n    4 平方公尺、143 （A ）所示面積87.95 平方公尺、97（A\n    ）所示面積2.83平方公尺有優先承買權存在。被告等就上\n    開房屋部分以新臺幣28萬元所為之買賣行為，准由原告等以\n    同一價額優先承購。被告甲○○應自前項門牌號碼房屋如\n    附圖144 （A ）、143 （A ）、97（A ）遷出，被告等應將\n    上開房屋全部交付原告。願供擔保請准宣告假執行。」「\n    乙、備位聲明確認原告等就坐落門牌號碼臺北縣三峽鎮○\n    ○路67巷27號之房屋如附圖(二)14 4（A ）所示面積67.8 4平\n    方公尺部分有優先承買權存在。被告等就上開房屋部分以\n    新臺幣12萬6 千元所為之買賣行為，准由原告等以同一價額\n    優先承購。被告甲○○應自前項門牌號碼房屋如附圖144\n    （A ）部分遷出。被告甲○○應將坐落臺北縣三峽鎮○○\n    段143 地號土地上建物門牌號碼臺北縣三峽鎮○○路67巷27\n    號如附圖(二)143 （A ）所示面積87.95 平方公尺及同段97地\n    號土地上同門牌號碼建物如附圖97（A ）所示面積2.83平方\n    公尺之房屋拆除，將土地返還原告。願供擔保請准宣告假\n    執行。」，揆諸首揭規定，原告所為訴之變更，合於法律規\n    定，應予准許。\n二、原告以被告梁富寶已於94年7 月10日死亡，有戶籍謄本在卷\n    可稽，乃於本院98年7 月9 日言詞辯論期日當庭表示撤回對\n    被告梁富寶之起訴（本院卷第65頁），核無不合，併予敘明\n    。\n三、本件被告己○○經合法送達，未於言詞辯論期日到場，核無\n    民事訴訟法第386 條各款所列情形，爰依原告聲請，由其一\n    造辯論而為判決。\n貳、實體事項：\n一、原告起訴主張：\n(一)、緣坐落臺北縣三峽鎮○○段97、143 、144 地號等三筆土地\n    為原告四人所共有（下稱系爭97、143 、144 地號土地），\n    應有部分為原告戊○○、丁○○各1/3 ，原告乙○○、丙○\n    ○各1/6 ，有土地登記第二類謄本可證。被告庚○○○、己\n    ○○、梁富寶（已歿）原有門牌號碼臺北縣三峽鎮○○路67\n    巷27號房屋（下稱系爭房屋）。而系爭房屋分別占用系爭三\n    筆土地之部份，即如附圖(二)14 4（A ）所示面積67.84 平方\n    公尺、143 （A ）所示面積87.95 平方公尺、97（A ）所示\n    面積2.83平方公尺，並就上開部分對原告有基地租用權。惟\n    民國97年8 月14日被告庚○○○將系爭房屋之全部以總價新\n    臺幣（下同）28萬元賣予被告甲○○，如讓渡書所示。但被\n    告等均未通知原告是否優先承買，而依土地法第104 條規定\n    ，房屋出賣時，基地所有權人有依同樣條件優先購買之權，\n    出賣人未通知優先購買權人而與第三人訂立買賣契約者，其\n    契約不得對抗優先購買權人。是原告依上開法條規定，自得\n    向被告主張優先購買權，且被告間之上開房屋買賣契約不能\n    對抗原告，應屬無效。故原告先位聲明請求確認原告對系爭\n    房屋之全部有以同一價額亦即28萬元優先承買之權利，並依\n    民法第767 條規定，主張被告甲○○就系爭房屋為無權占有\n    ，應自系爭房屋遷出，並將系爭房屋全部交付原告。若鈞院\n    認原告之優先承買權僅存在附圖(二)14 4（A ）部分，則原告\n    之備位聲明係請求確認原告等就系爭房屋如附圖(二)144 （A\n    ）所示面積67.84 平方公尺部分有優先承買權存在，而依比\n    例，原告得以12萬6 千元優先承購之，並依民法第767 條前\n    段規定，請求被告甲○○自系爭房屋如附圖144 （A ）部分\n    遷出，以及將如附圖(二)143 （A ）、97（A ）部分拆除，將\n    土地返還予原告等語。\n(二)、甲、先位聲明：確認原告等就坐落門牌號碼臺北縣三峽鎮\n        ○○路67巷27號之房屋如附圖(二)14 4（A ）所示面積67\n        .84 平方公尺、143 （A ）所示面積87.95 平方公尺、\n        97（A ）所示面積2.83平方公尺有優先承買權存在。\n        被告等就上開房屋部分以新臺幣28萬元所為之買賣行為\n        ，准由原告等以同一價額優先承購。被告甲○○應自\n        前項門牌號碼房屋如附圖144 （A ）、143 （A ）、97\n        （A ）遷出，被告等應將上開房屋全部交付原告。願\n        供擔保請准宣告假執行。\n    乙、備位聲明：確認原告等就坐落門牌號碼臺北縣三峽鎮\n        ○○路67巷27號之房屋如附圖(二)144 （A ）所示面積67\n        .8 4 平 方公尺部分有優先承買權存在。被告等就上\n        開房屋部分以新臺幣12萬6 千元所為之買賣行為，准由\n        原告等以同一價額優先承購。被告甲○○應自前項門\n        牌號碼房屋如附圖144 （A ）部分遷出。被告甲○○\n        應將坐落臺北縣三峽鎮○○段143 地號土地上建物門牌\n        號碼臺北縣三峽鎮○○路67 巷27 號如附圖(二)143 （A\n        ）所示面積87.95 平方公尺及同段97地號土地上同門牌\n        號碼建物如附圖97（A ）所示面積2. 83 平方公尺之房\n        屋拆除，將土地返還原告。願供擔保請准宣告假執行\n        。\n二、被告則答辯以：\n(一)、被告等對於系爭97、143 、144 地號土地為原告四人共有，\n    應有部分為原告戊○○、丁○○各1/3 ，原告乙○○、丙○\n    ○各1/6 ，被告庚○○○、己○○、梁富寶（已歿）原有系\n    爭房屋，系爭房屋占用情形如附圖(二)14 4（A ）所示面積67\n    .84 平方公尺、143 （A ）所示面積87.95 平方公尺、97（\n    A ）所示面積2.83平方公尺，97年8 月14日被告庚○○○將\n    系爭房屋之全部以總價28萬元賣予被告甲○○，系爭房屋的\n    三個部分不能獨立分開，也只有一個大門出入，被告等均未\n    通知原告是否優先承買等情，均不爭執。被告庚○○○另陳\n    稱系爭房屋很久以前就蓋成這樣，伊在使用期間沒有付租金\n    給原告，一直相安無事，所以當初賣給被告甲○○時並沒有\n    通知原告是否優先承買；被告己○○則經合法通知，並未提\n    出任何書狀或陳述；被告甲○○則陳稱伊購買系爭房屋時並\n    不知道原告與其餘被告間有糾紛，更不知道要通知原告是否\n    優先承買等語。\n(二)、聲明：原告之訴及假執行之聲請均駁回；如受不利之判決，\n    願供擔保請准宣告免為假執行。\n三、兩造不爭執事項：\n(一)、坐落臺北縣三峽鎮○○段97、143 、144 地號等三筆土地為\n    原告四人所共有（下稱系爭97、143 、144 地號土地），應\n    有部分為原告戊○○、丁○○各1/3 ，原告乙○○、丙○○\n    各1/6 ，並有兩造不爭執之土地登記第二類謄本在卷可證（\n    本院卷第66-71頁）。\n(二)、被告庚○○○、己○○原有系爭房屋，嗣被告甲○○於97年\n    8 月14日以28萬元向被告庚○○○購得系爭房屋全部，並有\n    兩造不爭執之讓渡書在卷可稽（本院卷第31、32頁）。\n(三)、系爭房屋占用系爭三筆土地之位置及面積均如附圖(二)所示，\n    並有兩造不爭執之本院履勘筆錄及臺北縣樹林地政事務所土\n    地複丈成果圖在卷可憑（本院卷第80-82.85頁）。\n(四)、被告庚○○○將系爭房屋出售予被告甲○○時，被告等均未\n    通知原告是否行使優先承買權（本院卷第105 頁背面）。\n(五)、系爭房屋如附圖(二)144 （A ）、143 （A ）、97（A ）所示\n    之三個部分並非分別獨立，只有一個大門出入，是一個建築\n    主體。\n(六)、系爭房屋現由被告甲○○占有使用中。\n四、本院得心證之理由：\n(一)、按土地法第104 條第2 項已於64年7 月24日修訂為出賣人未\n    通知優先購買權人而與第三人訂立買賣契約者，其契約不得\n    對抗優先購買權人，是厥後該項優先購買權即具物權之效力\n    。上訴人間之買賣，既在土地法修訂以後，則有上開優先購\n    買權之被上訴人請求確認其就系爭土地有優先購買權，命上\n    訴人甲塗銷已為之所有權移轉登記，由上訴人乙與被上訴人\n    補訂書面契約，並協同辦理所有權移轉登記，委無不合。有\n    最高法院65年度台上字第2701號、67年度台上字第479 號裁\n    判意旨可參。又按土地法第104 條第1 項規定房屋出賣時，\n    基地所有權人有依同樣條件優先購買之權，旨在使地上建物\n    之利用與其基地所有權合歸於一人，藉以發揮土地之利用價\n    值，盡經濟上之效用，並避免租賃關係消滅後，建物因無使\n    用土地權限遭拆除還地，防杜紛爭。此有最高法院91年度台\n    上字第2154號判決意旨可參。再按，土地法第104 條第1 項\n    後段所謂基地承租人之房屋出賣時，基地所有權人有依同樣\n    條件優先購買之權，係指成立買賣契約之形成權而言。此項\n    房屋買賣之債權契約，與為移轉物權所訂立之物權契約並不\n    相同。祇須承租人出賣其房屋，基地所有權人即得行使優先\n    權，至房屋之所有權能否移轉登記，在所不問。亦有最高法\n    院85年度台上字第1051號裁判意旨可參。經查，本件系爭97\n    、143 、144 地號等三筆土地為原告四人所共有，應有部分\n    為原告戊○○、丁○○各1/3 ，原告乙○○、丙○○各1/6\n    ，系爭房屋原為被告庚○○○、己○○所有，系爭房屋占用\n    系爭三筆土地之位置及面積均如附圖(二)所示，嗣被告甲○○\n    於97年8 月14日以28萬元向被告庚○○○購得系爭房屋全部\n    ，出賣系爭房屋當時被告均未通知原告是否行使優先承買權\n    等情，為兩造所不爭執，業如上述，揆諸上開說明，是原告\n    依土地法第104 條第1 項後段之規定，請求確認原告就門牌\n    號碼臺北縣三峽鎮○○路67巷27號之房屋有優先承買權存在\n    ，原告得以同一價額亦即28萬元優先承購之，為有理由。\n(二)、次按執行法院宜就該第三人主張有優先承買權部分之土地，\n    通知地政機關會同測量，並繪製複丈成果圖，再分別函查地\n    政機關及相關主管機關（如建築管理機關）詢問該部分土地\n    有無不能分割或不能單獨使用之情事（如畸零地或無法建築\n    ）。倘無不能分割，又無不能單獨使用情事，得分標拍賣，\n    並就該部分土地標別載明第三人有優先承買權之旨。若有不\n    能分割或不能單獨使用情事，則不得分標拍賣，僅能註明第\n    三人有優先承買權，但第三人主張優先承買權時，應就全部\n    土地合併主張，不得僅就該部分土地為之。此有司法院94年\n    第4 期民事業務研究會研討結論可資參照。經查，本件系爭\n    房屋如附圖(二)144 （A ）、143 （A ）、97（A ）所示之三\n    個部分並非分別獨立，只有一個大門出入，是一個建築主體\n    等情，為兩造所不爭執，且被告庚○○○對上開三筆土地均\n    主張有土地租用權，亦即系爭房屋係屬不能分割、不能單獨\n    使用者，而依上揭說明，原告主張優先承買權時，即應就全\n    部系爭房屋合併主張，不得僅就部分房屋為之，是則本件原\n    告請求確認就系爭房屋之全部有優先承買權，並請求以同一\n    價格優先承買與被告庚○○○形成買賣契約，自屬有據。惟\n    另一被告己○○並非系爭買賣契約之出賣人，原告併將其列\n    為買賣行為當事人，請求以同一價格優先承買，自不能准許\n    。\n(三)、至原告請求被告甲○○應自系爭房屋之全部遷出，被告等應\n    將系爭房屋之全部交付予原告部分，經查，按土地法第104\n    條第1 項後段所謂坐落基地上房屋出賣時，基地所有權人有\n    依同樣條件優先購買之權，係指成立買賣契約之形成權而言\n    ，業如上述，故本件原告請求確認其等對系爭房屋有優先承\n    買權部分，自僅取得成立買賣債權契約之形成權，而非移轉\n    所有權之物權契約，在原告尚未受讓系爭未辦保存登記房屋\n    之事實上處分權之前，依法自尚不得請求被告甲○○或其他\n    原有事實上處分權之被告庚○○○、己○○遷讓或返還系爭\n    房屋，是原告此部分請求，為無理由。\n五、綜上所述，原告請求確認其等就門牌號碼臺北縣三峽鎮○○\n    路67巷27號之房屋如附圖(二)14 4（A ）所示面積67 .84平方\n    公尺、143 （A ）所示面積87.95 平方公尺、97（A ）所示\n    面積2.83平方公尺有優先承買權存在；被告庚○○○與甲○\n    ○間就上開房屋以新臺幣28萬元所為之買賣行為，准原告以\n    同一價額優先承買，為有理由，應予准許；逾此範圍所為之\n    請求，為無理由，應予駁回。又原告先位聲明既屬有理由，\n    本院即毋庸再就其備位聲明為審理。\n六、本件原告勝訴部分乃係確認之訴及意思表示形成權之判決，\n    並無宣告假執行之必要，其假執行之聲請應予駁回。至原告\n    敗訴部分，其假行之聲請已失所附麗，不應准許，併予駁回\n    。\n七、本件判決事證基礎已臻明確，兩造其餘主張、陳述及所提證\n    據暨攻擊、防禦方法，經本院審酌後，認與判決結果均無影\n    響，爰不一一論述，併予敘明。\n八、結論：據上論結，本件原告之訴為一部有理由，一部無理由\n    ，依民事訴訟法第79條，判決如主文。\n中    華    民    國    99    年    5     月    12    日\n                  民事第三庭  審判長法  官  朱耀平\n                                    法  官  徐玉玲\n                                    法  官  吳金芳\n以上正本係照原本作成。\n如對本判決上訴，須於判決送達後20日內向本院提出上訴狀。\n中    華    民    國    99    年    5     月    14    日\n                                    書記官  陳昭綾\n附圖(一)（一頁）\n附圖(二)（一頁）",
  "structure": {
    "main": "確認原告就門牌號碼臺北縣三峽鎮○○路67巷27號之房屋如附圖\n(二)14 4（A ）所示面積67 .84平方公尺、143 （A ）所示面積87\n.95 平方公尺、97（A ）所示面積2.83平方公尺有優先承買權存\n在；被告庚○○○與甲○○間就上開房屋以新臺幣28萬元所為之\n買賣行為，准原告以同一價額優先承買。\n原告其餘之訴及假執行之聲請均駁回。\n訴訟費用由原告負擔二分之一，餘由被告負擔。",
    "fact": "壹、程序事項：\n一、按訴狀送達後，原告不得將原訴變更或追加他訴。但有下列\n    各款情形之一者，不在此限：... 2.請求之基礎事實同一者\n    。3.擴張或減縮應受判決事項之聲明者。... 7.不甚礙被告\n    之防禦及訴訟之終結者。民事訴訟法第255 條第1 項第2 、\n    3 、7 款定有明文。查原告起訴時之聲明為「被告庚○○\n    ○、己○○、梁富寶應將坐落臺北縣三峽鎮○○段144 地號\n    土地上建物門牌號碼臺北縣三峽鎮○○路67巷27號如附圖(一)\n    A 所示面積41 .75平方公尺之房屋，於原告給付新臺幣126,\n     000元之同時交付予原告。被告甲○○應將坐落臺北縣三\n    峽鎮○○段143 地號土地上建物門牌號碼臺北縣三峽鎮○○\n    路67巷27號如附圖(一)B 所示面積86.46 平方公尺及同段97地\n    號土地上同門牌號碼建物如附圖(一)C 所示面積2.83平方公尺\n    之房屋拆除，將土地返還予原告。被告甲○○應自上開門\n    牌號碼房屋遷出。願供擔保請准宣告假執行。」，嗣經本\n    院履勘現場及測量面積後，原告於98年11月3 日具狀更正聲\n    明為「確認被告甲○○與被告庚○○○間就坐落門牌號碼\n    臺北縣三峽鎮○○路67巷27號建物如附圖(二)144 （A ）所示\n    面積67.84 平方公尺部分於民國97年8 月14日之買賣關係不\n    存在。被告庚○○○、己○○應將坐落臺北縣三峽鎮○○\n    路67巷27號建物如附圖(二)144 （A ）所示面積67.84 平方公\n    尺之房屋，於原告給付新臺幣12萬6 千元之同時交付予原告\n    ，歸原告所有。被告甲○○應將坐落臺北縣三峽鎮○○段\n    143 地號土地上建物門牌號碼臺北縣三峽鎮○○路67巷27號\n    如附圖(二)143 （A ）所示面積87.95 平方公尺及同段97地號\n    土地上同門牌號碼建物如附圖97（A ）所示面積2.83平方公\n    尺之房屋拆除，將土地返還原告。被告甲○○應自第一項\n    門牌號碼房屋遷出。願供擔保請准宣告假執行。」，後又\n    於99年1 月6 日具狀更正聲明為：「確認原告等就坐落門\n    牌號碼臺北縣三峽鎮○○路67巷27號之房屋如附圖(二)14 4（\n    A ）所示面積67.84 平方公尺部分有優先承買權存在。被\n    告等就上開房屋部分以新臺幣12萬6 千元所為之買賣行為，\n    准由原告等以同一價額優先承購。被告甲○○應自前項門\n    牌號碼房屋如附圖144 （A ）部分遷出。被告甲○○應將\n    坐落臺北縣三峽鎮○○段143 地號土地上建物門牌號碼臺北\n    縣三峽鎮○○路67巷27號如附圖(二)143 （A ）所示面積87.9\n    5 平方公尺及同段97地號土地上同門牌號碼建物如附圖97（\n    A ）所示面積2.83平方公尺之房屋拆除，將土地返還原告。\n    願供擔保請准宣告假執行。」，後原告以附圖(二)之14 4（\n    A ）、143 （A ）、97（A ）等三部分係合一，不能分別獨\n    立，而又於99年4 月16日提出言詞辯論要旨續狀更正聲明為\n    ：「甲、先位聲明確認原告等就坐落門牌號碼臺北縣三峽\n    鎮○○路67巷27號之房屋如附圖(二)14 4（A ）所示面積67.8\n    4 平方公尺、143 （A ）所示面積87.95 平方公尺、97（A\n    ）所示面積2.83平方公尺有優先承買權存在。被告等就上\n    開房屋部分以新臺幣28萬元所為之買賣行為，准由原告等以\n    同一價額優先承購。被告甲○○應自前項門牌號碼房屋如\n    附圖144 （A ）、143 （A ）、97（A ）遷出，被告等應將\n    上開房屋全部交付原告。願供擔保請准宣告假執行。」「\n    乙、備位聲明確認原告等就坐落門牌號碼臺北縣三峽鎮○\n    ○路67巷27號之房屋如附圖(二)14 4（A ）所示面積67.8 4平\n    方公尺部分有優先承買權存在。被告等就上開房屋部分以\n    新臺幣12萬6 千元所為之買賣行為，准由原告等以同一價額\n    優先承購。被告甲○○應自前項門牌號碼房屋如附圖144\n    （A ）部分遷出。被告甲○○應將坐落臺北縣三峽鎮○○\n    段143 地號土地上建物門牌號碼臺北縣三峽鎮○○路67巷27\n    號如附圖(二)143 （A ）所示面積87.95 平方公尺及同段97地\n    號土地上同門牌號碼建物如附圖97（A ）所示面積2.83平方\n    公尺之房屋拆除，將土地返還原告。願供擔保請准宣告假\n    執行。」，揆諸首揭規定，原告所為訴之變更，合於法律規\n    定，應予准許。\n二、原告以被告梁富寶已於94年7 月10日死亡，有戶籍謄本在卷\n    可稽，乃於本院98年7 月9 日言詞辯論期日當庭表示撤回對\n    被告梁富寶之起訴（本院卷第65頁），核無不合，併予敘明\n    。\n三、本件被告己○○經合法送達，未於言詞辯論期日到場，核無\n    民事訴訟法第386 條各款所列情形，爰依原告聲請，由其一\n    造辯論而為判決。\n貳、實體事項：\n一、原告起訴主張：\n(一)、緣坐落臺北縣三峽鎮○○段97、143 、144 地號等三筆土地\n    為原告四人所共有（下稱系爭97、143 、144 地號土地），\n    應有部分為原告戊○○、丁○○各1/3 ，原告乙○○、丙○\n    ○各1/6 ，有土地登記第二類謄本可證。被告庚○○○、己\n    ○○、梁富寶（已歿）原有門牌號碼臺北縣三峽鎮○○路67\n    巷27號房屋（下稱系爭房屋）。而系爭房屋分別占用系爭三\n    筆土地之部份，即如附圖(二)14 4（A ）所示面積67.84 平方\n    公尺、143 （A ）所示面積87.95 平方公尺、97（A ）所示\n    面積2.83平方公尺，並就上開部分對原告有基地租用權。惟\n    民國97年8 月14日被告庚○○○將系爭房屋之全部以總價新\n    臺幣（下同）28萬元賣予被告甲○○，如讓渡書所示。但被\n    告等均未通知原告是否優先承買，而依土地法第104 條規定\n    ，房屋出賣時，基地所有權人有依同樣條件優先購買之權，\n    出賣人未通知優先購買權人而與第三人訂立買賣契約者，其\n    契約不得對抗優先購買權人。是原告依上開法條規定，自得\n    向被告主張優先購買權，且被告間之上開房屋買賣契約不能\n    對抗原告，應屬無效。故原告先位聲明請求確認原告對系爭\n    房屋之全部有以同一價額亦即28萬元優先承買之權利，並依\n    民法第767 條規定，主張被告甲○○就系爭房屋為無權占有\n    ，應自系爭房屋遷出，並將系爭房屋全部交付原告。若鈞院\n    認原告之優先承買權僅存在附圖(二)14 4（A ）部分，則原告\n    之備位聲明係請求確認原告等就系爭房屋如附圖(二)144 （A\n    ）所示面積67.84 平方公尺部分有優先承買權存在，而依比\n    例，原告得以12萬6 千元優先承購之，並依民法第767 條前\n    段規定，請求被告甲○○自系爭房屋如附圖144 （A ）部分\n    遷出，以及將如附圖(二)143 （A ）、97（A ）部分拆除，將\n    土地返還予原告等語。\n(二)、甲、先位聲明：確認原告等就坐落門牌號碼臺北縣三峽鎮\n        ○○路67巷27號之房屋如附圖(二)14 4（A ）所示面積67\n        .84 平方公尺、143 （A ）所示面積87.95 平方公尺、\n        97（A ）所示面積2.83平方公尺有優先承買權存在。\n        被告等就上開房屋部分以新臺幣28萬元所為之買賣行為\n        ，准由原告等以同一價額優先承購。被告甲○○應自\n        前項門牌號碼房屋如附圖144 （A ）、143 （A ）、97\n        （A ）遷出，被告等應將上開房屋全部交付原告。願\n        供擔保請准宣告假執行。\n    乙、備位聲明：確認原告等就坐落門牌號碼臺北縣三峽鎮\n        ○○路67巷27號之房屋如附圖(二)144 （A ）所示面積67\n        .8 4 平 方公尺部分有優先承買權存在。被告等就上\n        開房屋部分以新臺幣12萬6 千元所為之買賣行為，准由\n        原告等以同一價額優先承購。被告甲○○應自前項門\n        牌號碼房屋如附圖144 （A ）部分遷出。被告甲○○\n        應將坐落臺北縣三峽鎮○○段143 地號土地上建物門牌\n        號碼臺北縣三峽鎮○○路67 巷27 號如附圖(二)143 （A\n        ）所示面積87.95 平方公尺及同段97地號土地上同門牌\n        號碼建物如附圖97（A ）所示面積2. 83 平方公尺之房\n        屋拆除，將土地返還原告。願供擔保請准宣告假執行\n        。\n二、被告則答辯以：\n(一)、被告等對於系爭97、143 、144 地號土地為原告四人共有，\n    應有部分為原告戊○○、丁○○各1/3 ，原告乙○○、丙○\n    ○各1/6 ，被告庚○○○、己○○、梁富寶（已歿）原有系\n    爭房屋，系爭房屋占用情形如附圖(二)14 4（A ）所示面積67\n    .84 平方公尺、143 （A ）所示面積87.95 平方公尺、97（\n    A ）所示面積2.83平方公尺，97年8 月14日被告庚○○○將\n    系爭房屋之全部以總價28萬元賣予被告甲○○，系爭房屋的\n    三個部分不能獨立分開，也只有一個大門出入，被告等均未\n    通知原告是否優先承買等情，均不爭執。被告庚○○○另陳\n    稱系爭房屋很久以前就蓋成這樣，伊在使用期間沒有付租金\n    給原告，一直相安無事，所以當初賣給被告甲○○時並沒有\n    通知原告是否優先承買；被告己○○則經合法通知，並未提\n    出任何書狀或陳述；被告甲○○則陳稱伊購買系爭房屋時並\n    不知道原告與其餘被告間有糾紛，更不知道要通知原告是否\n    優先承買等語。\n(二)、聲明：原告之訴及假執行之聲請均駁回；如受不利之判決，\n    願供擔保請准宣告免為假執行。\n三、兩造不爭執事項：\n(一)、坐落臺北縣三峽鎮○○段97、143 、144 地號等三筆土地為\n    原告四人所共有（下稱系爭97、143 、144 地號土地），應\n    有部分為原告戊○○、丁○○各1/3 ，原告乙○○、丙○○\n    各1/6 ，並有兩造不爭執之土地登記第二類謄本在卷可證（\n    本院卷第66-71頁）。\n(二)、被告庚○○○、己○○原有系爭房屋，嗣被告甲○○於97年\n    8 月14日以28萬元向被告庚○○○購得系爭房屋全部，並有\n    兩造不爭執之讓渡書在卷可稽（本院卷第31、32頁）。\n(三)、系爭房屋占用系爭三筆土地之位置及面積均如附圖(二)所示，\n    並有兩造不爭執之本院履勘筆錄及臺北縣樹林地政事務所土\n    地複丈成果圖在卷可憑（本院卷第80-82.85頁）。\n(四)、被告庚○○○將系爭房屋出售予被告甲○○時，被告等均未\n    通知原告是否行使優先承買權（本院卷第105 頁背面）。\n(五)、系爭房屋如附圖(二)144 （A ）、143 （A ）、97（A ）所示\n    之三個部分並非分別獨立，只有一個大門出入，是一個建築\n    主體。\n(六)、系爭房屋現由被告甲○○占有使用中。\n四、本院得心證之理由：\n(一)、按土地法第104 條第2 項已於64年7 月24日修訂為出賣人未\n    通知優先購買權人而與第三人訂立買賣契約者，其契約不得\n    對抗優先購買權人，是厥後該項優先購買權即具物權之效力\n    。上訴人間之買賣，既在土地法修訂以後，則有上開優先購\n    買權之被上訴人請求確認其就系爭土地有優先購買權，命上\n    訴人甲塗銷已為之所有權移轉登記，由上訴人乙與被上訴人\n    補訂書面契約，並協同辦理所有權移轉登記，委無不合。有\n    最高法院65年度台上字第2701號、67年度台上字第479 號裁\n    判意旨可參。又按土地法第104 條第1 項規定房屋出賣時，\n    基地所有權人有依同樣條件優先購買之權，旨在使地上建物\n    之利用與其基地所有權合歸於一人，藉以發揮土地之利用價\n    值，盡經濟上之效用，並避免租賃關係消滅後，建物因無使\n    用土地權限遭拆除還地，防杜紛爭。此有最高法院91年度台\n    上字第2154號判決意旨可參。再按，土地法第104 條第1 項\n    後段所謂基地承租人之房屋出賣時，基地所有權人有依同樣\n    條件優先購買之權，係指成立買賣契約之形成權而言。此項\n    房屋買賣之債權契約，與為移轉物權所訂立之物權契約並不\n    相同。祇須承租人出賣其房屋，基地所有權人即得行使優先\n    權，至房屋之所有權能否移轉登記，在所不問。亦有最高法\n    院85年度台上字第1051號裁判意旨可參。經查，本件系爭97\n    、143 、144 地號等三筆土地為原告四人所共有，應有部分\n    為原告戊○○、丁○○各1/3 ，原告乙○○、丙○○各1/6\n    ，系爭房屋原為被告庚○○○、己○○所有，系爭房屋占用\n    系爭三筆土地之位置及面積均如附圖(二)所示，嗣被告甲○○\n    於97年8 月14日以28萬元向被告庚○○○購得系爭房屋全部\n    ，出賣系爭房屋當時被告均未通知原告是否行使優先承買權\n    等情，為兩造所不爭執，業如上述，揆諸上開說明，是原告\n    依土地法第104 條第1 項後段之規定，請求確認原告就門牌\n    號碼臺北縣三峽鎮○○路67巷27號之房屋有優先承買權存在\n    ，原告得以同一價額亦即28萬元優先承購之，為有理由。\n(二)、次按執行法院宜就該第三人主張有優先承買權部分之土地，\n    通知地政機關會同測量，並繪製複丈成果圖，再分別函查地\n    政機關及相關主管機關（如建築管理機關）詢問該部分土地\n    有無不能分割或不能單獨使用之情事（如畸零地或無法建築\n    ）。倘無不能分割，又無不能單獨使用情事，得分標拍賣，\n    並就該部分土地標別載明第三人有優先承買權之旨。若有不\n    能分割或不能單獨使用情事，則不得分標拍賣，僅能註明第\n    三人有優先承買權，但第三人主張優先承買權時，應就全部\n    土地合併主張，不得僅就該部分土地為之。此有司法院94年\n    第4 期民事業務研究會研討結論可資參照。經查，本件系爭\n    房屋如附圖(二)144 （A ）、143 （A ）、97（A ）所示之三\n    個部分並非分別獨立，只有一個大門出入，是一個建築主體\n    等情，為兩造所不爭執，且被告庚○○○對上開三筆土地均\n    主張有土地租用權，亦即系爭房屋係屬不能分割、不能單獨\n    使用者，而依上揭說明，原告主張優先承買權時，即應就全\n    部系爭房屋合併主張，不得僅就部分房屋為之，是則本件原\n    告請求確認就系爭房屋之全部有優先承買權，並請求以同一\n    價格優先承買與被告庚○○○形成買賣契約，自屬有據。惟\n    另一被告己○○並非系爭買賣契約之出賣人，原告併將其列\n    為買賣行為當事人，請求以同一價格優先承買，自不能准許\n    。\n(三)、至原告請求被告甲○○應自系爭房屋之全部遷出，被告等應\n    將系爭房屋之全部交付予原告部分，經查，按土地法第104\n    條第1 項後段所謂坐落基地上房屋出賣時，基地所有權人有\n    依同樣條件優先購買之權，係指成立買賣契約之形成權而言\n    ，業如上述，故本件原告請求確認其等對系爭房屋有優先承\n    買權部分，自僅取得成立買賣債權契約之形成權，而非移轉\n    所有權之物權契約，在原告尚未受讓系爭未辦保存登記房屋\n    之事實上處分權之前，依法自尚不得請求被告甲○○或其他\n    原有事實上處分權之被告庚○○○、己○○遷讓或返還系爭\n    房屋，是原告此部分請求，為無理由。\n五、綜上所述，原告請求確認其等就門牌號碼臺北縣三峽鎮○○\n    路67巷27號之房屋如附圖(二)14 4（A ）所示面積67 .84平方\n    公尺、143 （A ）所示面積87.95 平方公尺、97（A ）所示\n    面積2.83平方公尺有優先承買權存在；被告庚○○○與甲○\n    ○間就上開房屋以新臺幣28萬元所為之買賣行為，准原告以\n    同一價額優先承買，為有理由，應予准許；逾此範圍所為之\n    請求，為無理由，應予駁回。又原告先位聲明既屬有理由，\n    本院即毋庸再就其備位聲明為審理。\n六、本件原告勝訴部分乃係確認之訴及意思表示形成權之判決，\n    並無宣告假執行之必要，其假執行之聲請應予駁回。至原告\n    敗訴部分，其假行之聲請已失所附麗，不應准許，併予駁回\n    。\n七、本件判決事證基礎已臻明確，兩造其餘主張、陳述及所提證\n    據暨攻擊、防禦方法，經本院審酌後，認與判決結果均無影\n    響，爰不一一論述，併予敘明。\n八、結論：據上論結，本件原告之訴為一部有理由，一部無理由\n    ，依民事訴訟法第79條，判決如主文。",
    "reason": "壹、程序事項：\n一、按訴狀送達後，原告不得將原訴變更或追加他訴。但有下列\n    各款情形之一者，不在此限：... 2.請求之基礎事實同一者\n    。3.擴張或減縮應受判決事項之聲明者。... 7.不甚礙被告\n    之防禦及訴訟之終結者。民事訴訟法第255 條第1 項第2 、\n    3 、7 款定有明文。查原告起訴時之聲明為「被告庚○○\n    ○、己○○、梁富寶應將坐落臺北縣三峽鎮○○段144 地號\n    土地上建物門牌號碼臺北縣三峽鎮○○路67巷27號如附圖(一)\n    A 所示面積41 .75平方公尺之房屋，於原告給付新臺幣126,\n     000元之同時交付予原告。被告甲○○應將坐落臺北縣三\n    峽鎮○○段143 地號土地上建物門牌號碼臺北縣三峽鎮○○\n    路67巷27號如附圖(一)B 所示面積86.46 平方公尺及同段97地\n    號土地上同門牌號碼建物如附圖(一)C 所示面積2.83平方公尺\n    之房屋拆除，將土地返還予原告。被告甲○○應自上開門\n    牌號碼房屋遷出。願供擔保請准宣告假執行。」，嗣經本\n    院履勘現場及測量面積後，原告於98年11月3 日具狀更正聲\n    明為「確認被告甲○○與被告庚○○○間就坐落門牌號碼\n    臺北縣三峽鎮○○路67巷27號建物如附圖(二)144 （A ）所示\n    面積67.84 平方公尺部分於民國97年8 月14日之買賣關係不\n    存在。被告庚○○○、己○○應將坐落臺北縣三峽鎮○○\n    路67巷27號建物如附圖(二)144 （A ）所示面積67.84 平方公\n    尺之房屋，於原告給付新臺幣12萬6 千元之同時交付予原告\n    ，歸原告所有。被告甲○○應將坐落臺北縣三峽鎮○○段\n    143 地號土地上建物門牌號碼臺北縣三峽鎮○○路67巷27號\n    如附圖(二)143 （A ）所示面積87.95 平方公尺及同段97地號\n    土地上同門牌號碼建物如附圖97（A ）所示面積2.83平方公\n    尺之房屋拆除，將土地返還原告。被告甲○○應自第一項\n    門牌號碼房屋遷出。願供擔保請准宣告假執行。」，後又\n    於99年1 月6 日具狀更正聲明為：「確認原告等就坐落門\n    牌號碼臺北縣三峽鎮○○路67巷27號之房屋如附圖(二)14 4（\n    A ）所示面積67.84 平方公尺部分有優先承買權存在。被\n    告等就上開房屋部分以新臺幣12萬6 千元所為之買賣行為，\n    准由原告等以同一價額優先承購。被告甲○○應自前項門\n    牌號碼房屋如附圖144 （A ）部分遷出。被告甲○○應將\n    坐落臺北縣三峽鎮○○段143 地號土地上建物門牌號碼臺北\n    縣三峽鎮○○路67巷27號如附圖(二)143 （A ）所示面積87.9\n    5 平方公尺及同段97地號土地上同門牌號碼建物如附圖97（\n    A ）所示面積2.83平方公尺之房屋拆除，將土地返還原告。\n    願供擔保請准宣告假執行。」，後原告以附圖(二)之14 4（\n    A ）、143 （A ）、97（A ）等三部分係合一，不能分別獨\n    立，而又於99年4 月16日提出言詞辯論要旨續狀更正聲明為\n    ：「甲、先位聲明確認原告等就坐落門牌號碼臺北縣三峽\n    鎮○○路67巷27號之房屋如附圖(二)14 4（A ）所示面積67.8\n    4 平方公尺、143 （A ）所示面積87.95 平方公尺、97（A\n    ）所示面積2.83平方公尺有優先承買權存在。被告等就上\n    開房屋部分以新臺幣28萬元所為之買賣行為，准由原告等以\n    同一價額優先承購。被告甲○○應自前項門牌號碼房屋如\n    附圖144 （A ）、143 （A ）、97（A ）遷出，被告等應將\n    上開房屋全部交付原告。願供擔保請准宣告假執行。」「\n    乙、備位聲明確認原告等就坐落門牌號碼臺北縣三峽鎮○\n    ○路67巷27號之房屋如附圖(二)14 4（A ）所示面積67.8 4平\n    方公尺部分有優先承買權存在。被告等就上開房屋部分以\n    新臺幣12萬6 千元所為之買賣行為，准由原告等以同一價額\n    優先承購。被告甲○○應自前項門牌號碼房屋如附圖144\n    （A ）部分遷出。被告甲○○應將坐落臺北縣三峽鎮○○\n    段143 地號土地上建物門牌號碼臺北縣三峽鎮○○路67巷27\n    號如附圖(二)143 （A ）所示面積87.95 平方公尺及同段97地\n    號土地上同門牌號碼建物如附圖97（A ）所示面積2.83平方\n    公尺之房屋拆除，將土地返還原告。願供擔保請准宣告假\n    執行。」，揆諸首揭規定，原告所為訴之變更，合於法律規\n    定，應予准許。\n二、原告以被告梁富寶已於94年7 月10日死亡，有戶籍謄本在卷\n    可稽，乃於本院98年7 月9 日言詞辯論期日當庭表示撤回對\n    被告梁富寶之起訴（本院卷第65頁），核無不合，併予敘明\n    。\n三、本件被告己○○經合法送達，未於言詞辯論期日到場，核無\n    民事訴訟法第386 條各款所列情形，爰依原告聲請，由其一\n    造辯論而為判決。\n貳、實體事項：\n一、原告起訴主張：\n(一)、緣坐落臺北縣三峽鎮○○段97、143 、144 地號等三筆土地\n    為原告四人所共有（下稱系爭97、143 、144 地號土地），\n    應有部分為原告戊○○、丁○○各1/3 ，原告乙○○、丙○\n    ○各1/6 ，有土地登記第二類謄本可證。被告庚○○○、己\n    ○○、梁富寶（已歿）原有門牌號碼臺北縣三峽鎮○○路67\n    巷27號房屋（下稱系爭房屋）。而系爭房屋分別占用系爭三\n    筆土地之部份，即如附圖(二)14 4（A ）所示面積67.84 平方\n    公尺、143 （A ）所示面積87.95 平方公尺、97（A ）所示\n    面積2.83平方公尺，並就上開部分對原告有基地租用權。惟\n    民國97年8 月14日被告庚○○○將系爭房屋之全部以總價新\n    臺幣（下同）28萬元賣予被告甲○○，如讓渡書所示。但被\n    告等均未通知原告是否優先承買，而依土地法第104 條規定\n    ，房屋出賣時，基地所有權人有依同樣條件優先購買之權，\n    出賣人未通知優先購買權人而與第三人訂立買賣契約者，其\n    契約不得對抗優先購買權人。是原告依上開法條規定，自得\n    向被告主張優先購買權，且被告間之上開房屋買賣契約不能\n    對抗原告，應屬無效。故原告先位聲明請求確認原告對系爭\n    房屋之全部有以同一價額亦即28萬元優先承買之權利，並依\n    民法第767 條規定，主張被告甲○○就系爭房屋為無權占有\n    ，應自系爭房屋遷出，並將系爭房屋全部交付原告。若鈞院\n    認原告之優先承買權僅存在附圖(二)14 4（A ）部分，則原告\n    之備位聲明係請求確認原告等就系爭房屋如附圖(二)144 （A\n    ）所示面積67.84 平方公尺部分有優先承買權存在，而依比\n    例，原告得以12萬6 千元優先承購之，並依民法第767 條前\n    段規定，請求被告甲○○自系爭房屋如附圖144 （A ）部分\n    遷出，以及將如附圖(二)143 （A ）、97（A ）部分拆除，將\n    土地返還予原告等語。\n(二)、甲、先位聲明：確認原告等就坐落門牌號碼臺北縣三峽鎮\n        ○○路67巷27號之房屋如附圖(二)14 4（A ）所示面積67\n        .84 平方公尺、143 （A ）所示面積87.95 平方公尺、\n        97（A ）所示面積2.83平方公尺有優先承買權存在。\n        被告等就上開房屋部分以新臺幣28萬元所為之買賣行為\n        ，准由原告等以同一價額優先承購。被告甲○○應自\n        前項門牌號碼房屋如附圖144 （A ）、143 （A ）、97\n        （A ）遷出，被告等應將上開房屋全部交付原告。願\n        供擔保請准宣告假執行。\n    乙、備位聲明：確認原告等就坐落門牌號碼臺北縣三峽鎮\n        ○○路67巷27號之房屋如附圖(二)144 （A ）所示面積67\n        .8 4 平 方公尺部分有優先承買權存在。被告等就上\n        開房屋部分以新臺幣12萬6 千元所為之買賣行為，准由\n        原告等以同一價額優先承購。被告甲○○應自前項門\n        牌號碼房屋如附圖144 （A ）部分遷出。被告甲○○\n        應將坐落臺北縣三峽鎮○○段143 地號土地上建物門牌\n        號碼臺北縣三峽鎮○○路67 巷27 號如附圖(二)143 （A\n        ）所示面積87.95 平方公尺及同段97地號土地上同門牌\n        號碼建物如附圖97（A ）所示面積2. 83 平方公尺之房\n        屋拆除，將土地返還原告。願供擔保請准宣告假執行\n        。\n二、被告則答辯以：\n(一)、被告等對於系爭97、143 、144 地號土地為原告四人共有，\n    應有部分為原告戊○○、丁○○各1/3 ，原告乙○○、丙○\n    ○各1/6 ，被告庚○○○、己○○、梁富寶（已歿）原有系\n    爭房屋，系爭房屋占用情形如附圖(二)14 4（A ）所示面積67\n    .84 平方公尺、143 （A ）所示面積87.95 平方公尺、97（\n    A ）所示面積2.83平方公尺，97年8 月14日被告庚○○○將\n    系爭房屋之全部以總價28萬元賣予被告甲○○，系爭房屋的\n    三個部分不能獨立分開，也只有一個大門出入，被告等均未\n    通知原告是否優先承買等情，均不爭執。被告庚○○○另陳\n    稱系爭房屋很久以前就蓋成這樣，伊在使用期間沒有付租金\n    給原告，一直相安無事，所以當初賣給被告甲○○時並沒有\n    通知原告是否優先承買；被告己○○則經合法通知，並未提\n    出任何書狀或陳述；被告甲○○則陳稱伊購買系爭房屋時並\n    不知道原告與其餘被告間有糾紛，更不知道要通知原告是否\n    優先承買等語。\n(二)、聲明：原告之訴及假執行之聲請均駁回；如受不利之判決，\n    願供擔保請准宣告免為假執行。\n三、兩造不爭執事項：\n(一)、坐落臺北縣三峽鎮○○段97、143 、144 地號等三筆土地為\n    原告四人所共有（下稱系爭97、143 、144 地號土地），應\n    有部分為原告戊○○、丁○○各1/3 ，原告乙○○、丙○○\n    各1/6 ，並有兩造不爭執之土地登記第二類謄本在卷可證（\n    本院卷第66-71頁）。\n(二)、被告庚○○○、己○○原有系爭房屋，嗣被告甲○○於97年\n    8 月14日以28萬元向被告庚○○○購得系爭房屋全部，並有\n    兩造不爭執之讓渡書在卷可稽（本院卷第31、32頁）。\n(三)、系爭房屋占用系爭三筆土地之位置及面積均如附圖(二)所示，\n    並有兩造不爭執之本院履勘筆錄及臺北縣樹林地政事務所土\n    地複丈成果圖在卷可憑（本院卷第80-82.85頁）。\n(四)、被告庚○○○將系爭房屋出售予被告甲○○時，被告等均未\n    通知原告是否行使優先承買權（本院卷第105 頁背面）。\n(五)、系爭房屋如附圖(二)144 （A ）、143 （A ）、97（A ）所示\n    之三個部分並非分別獨立，只有一個大門出入，是一個建築\n    主體。\n(六)、系爭房屋現由被告甲○○占有使用中。\n四、本院得心證之理由：\n(一)、按土地法第104 條第2 項已於64年7 月24日修訂為出賣人未\n    通知優先購買權人而與第三人訂立買賣契約者，其契約不得\n    對抗優先購買權人，是厥後該項優先購買權即具物權之效力\n    。上訴人間之買賣，既在土地法修訂以後，則有上開優先購\n    買權之被上訴人請求確認其就系爭土地有優先購買權，命上\n    訴人甲塗銷已為之所有權移轉登記，由上訴人乙與被上訴人\n    補訂書面契約，並協同辦理所有權移轉登記，委無不合。有\n    最高法院65年度台上字第2701號、67年度台上字第479 號裁\n    判意旨可參。又按土地法第104 條第1 項規定房屋出賣時，\n    基地所有權人有依同樣條件優先購買之權，旨在使地上建物\n    之利用與其基地所有權合歸於一人，藉以發揮土地之利用價\n    值，盡經濟上之效用，並避免租賃關係消滅後，建物因無使\n    用土地權限遭拆除還地，防杜紛爭。此有最高法院91年度台\n    上字第2154號判決意旨可參。再按，土地法第104 條第1 項\n    後段所謂基地承租人之房屋出賣時，基地所有權人有依同樣\n    條件優先購買之權，係指成立買賣契約之形成權而言。此項\n    房屋買賣之債權契約，與為移轉物權所訂立之物權契約並不\n    相同。祇須承租人出賣其房屋，基地所有權人即得行使優先\n    權，至房屋之所有權能否移轉登記，在所不問。亦有最高法\n    院85年度台上字第1051號裁判意旨可參。經查，本件系爭97\n    、143 、144 地號等三筆土地為原告四人所共有，應有部分\n    為原告戊○○、丁○○各1/3 ，原告乙○○、丙○○各1/6\n    ，系爭房屋原為被告庚○○○、己○○所有，系爭房屋占用\n    系爭三筆土地之位置及面積均如附圖(二)所示，嗣被告甲○○\n    於97年8 月14日以28萬元向被告庚○○○購得系爭房屋全部\n    ，出賣系爭房屋當時被告均未通知原告是否行使優先承買權\n    等情，為兩造所不爭執，業如上述，揆諸上開說明，是原告\n    依土地法第104 條第1 項後段之規定，請求確認原告就門牌\n    號碼臺北縣三峽鎮○○路67巷27號之房屋有優先承買權存在\n    ，原告得以同一價額亦即28萬元優先承購之，為有理由。\n(二)、次按執行法院宜就該第三人主張有優先承買權部分之土地，\n    通知地政機關會同測量，並繪製複丈成果圖，再分別函查地\n    政機關及相關主管機關（如建築管理機關）詢問該部分土地\n    有無不能分割或不能單獨使用之情事（如畸零地或無法建築\n    ）。倘無不能分割，又無不能單獨使用情事，得分標拍賣，\n    並就該部分土地標別載明第三人有優先承買權之旨。若有不\n    能分割或不能單獨使用情事，則不得分標拍賣，僅能註明第\n    三人有優先承買權，但第三人主張優先承買權時，應就全部\n    土地合併主張，不得僅就該部分土地為之。此有司法院94年\n    第4 期民事業務研究會研討結論可資參照。經查，本件系爭\n    房屋如附圖(二)144 （A ）、143 （A ）、97（A ）所示之三\n    個部分並非分別獨立，只有一個大門出入，是一個建築主體\n    等情，為兩造所不爭執，且被告庚○○○對上開三筆土地均\n    主張有土地租用權，亦即系爭房屋係屬不能分割、不能單獨\n    使用者，而依上揭說明，原告主張優先承買權時，即應就全\n    部系爭房屋合併主張，不得僅就部分房屋為之，是則本件原\n    告請求確認就系爭房屋之全部有優先承買權，並請求以同一\n    價格優先承買與被告庚○○○形成買賣契約，自屬有據。惟\n    另一被告己○○並非系爭買賣契約之出賣人，原告併將其列\n    為買賣行為當事人，請求以同一價格優先承買，自不能准許\n    。\n(三)、至原告請求被告甲○○應自系爭房屋之全部遷出，被告等應\n    將系爭房屋之全部交付予原告部分，經查，按土地法第104\n    條第1 項後段所謂坐落基地上房屋出賣時，基地所有權人有\n    依同樣條件優先購買之權，係指成立買賣契約之形成權而言\n    ，業如上述，故本件原告請求確認其等對系爭房屋有優先承\n    買權部分，自僅取得成立買賣債權契約之形成權，而非移轉\n    所有權之物權契約，在原告尚未受讓系爭未辦保存登記房屋\n    之事實上處分權之前，依法自尚不得請求被告甲○○或其他\n    原有事實上處分權之被告庚○○○、己○○遷讓或返還系爭\n    房屋，是原告此部分請求，為無理由。\n五、綜上所述，原告請求確認其等就門牌號碼臺北縣三峽鎮○○\n    路67巷27號之房屋如附圖(二)14 4（A ）所示面積67 .84平方\n    公尺、143 （A ）所示面積87.95 平方公尺、97（A ）所示\n    面積2.83平方公尺有優先承買權存在；被告庚○○○與甲○\n    ○間就上開房屋以新臺幣28萬元所為之買賣行為，准原告以\n    同一價額優先承買，為有理由，應予准許；逾此範圍所為之\n    請求，為無理由，應予駁回。又原告先位聲明既屬有理由，\n    本院即毋庸再就其備位聲明為審理。\n六、本件原告勝訴部分乃係確認之訴及意思表示形成權之判決，\n    並無宣告假執行之必要，其假執行之聲請應予駁回。至原告\n    敗訴部分，其假行之聲請已失所附麗，不應准許，併予駁回\n    。\n七、本件判決事證基礎已臻明確，兩造其餘主張、陳述及所提證\n    據暨攻擊、防禦方法，經本院審酌後，認與判決結果均無影\n    響，爰不一一論述，併予敘明。\n八、結論：據上論結，本件原告之訴為一部有理由，一部無理由\n    ，依民事訴訟法第79條，判決如主文。"
  },
  "characters": {
    "judges": [
      "朱耀平",
      "徐玉玲",
      "吳金芳"
    ],
    "prosecutors": [

    ],
    "lawyers": [
      "林彥增",
      "郭芳宜"
    ],
    "clerks": [
      "陳昭綾"
    ],
    "plaintiffs": [
      "戊"
    ],
    "defendants": [
      "庚○○○",
      "己○○"
    ],
    "prosecutor_office": [

    ],
    "creditors": [

    ],
    "debtors": [

    ],
    "judicial_associate_officer": [

    ]
  },
  "adjudged_at": "2010-05-12",
  "created_at": "2016-01-05 12:28:27",
  "updated_at": "2016-01-05 12:28:27"
}