{
  "identify": "PCD-98-訴-2388-20100512-3",
  "court": {
    "name": "臺灣新北地方法院",
    "code": "PCD"
  },
  "division": {
    "name": "刑事",
    "code": "M"
  },
  "year": 98,
  "word": "訴",
  "number": "2388",
  "jcheck": "3",
  "reason": "槍砲彈藥刀械管制",
  "content": "臺灣板橋地方法院刑事裁定              98年度訴字第2388號\n公  訴  人  臺灣板橋地方法院檢察署檢察官\n被      告  甲○○\n指定辯護人  本院公設辯護人  吳天明\n上列被告因違反槍砲彈藥刀械管制條例案件，本院裁定如下：\n    主  文\n甲○○自民國玖拾玖年伍月貳拾壹日起延長羈押貳月。\n    理  由\n一、被告甲○○因違反槍砲彈藥刀械管制條例案件，前經本院合\n    法傳喚、拘提無著後，予以發布通緝在案，嗣經緝獲並經本\n    院訊問後，認其涉犯未經許可持有可發射子彈具有殺傷力之\n    改造手槍、未經許可持有子彈等罪嫌，犯罪嫌疑重大，且經\n    通緝到案，有逃亡事實，而有羈押之必要，依刑事訴訟法第\n    一百零一條第一項第一款規定，於民國九十九年二月二十一\n    日起諭知予以羈押在案。\n二、茲本院以羈押期間，即將屆滿，於九十九年五月十二日依法\n    訊問被告甲○○及其指定辯護人後，認被告甲○○之原羈押\n    原因仍然存在，有繼續羈押之必要，應自九十九年五月二十\n    一日起，再延長羈押二月。\n三、爰依刑事訴訟法第一百零八條第一項、第二項，裁定如主文\n    。\n中    華    民    國    99    年    5     月    12    日\n                  刑事第六庭    審判長法  官  胡堅勤\n                                      法  官  盧軍傑\n                                      法  官  林家賢\n如不服本裁定，應於裁定送達後五日內，向本院提出抗告狀（應\n附繕本），抗告於臺灣高等法院。\n                                      書記官  林政良\n中    華    民    國    99    年    5     月    12    日",
  "structure": {
    "main": "甲○○自民國玖拾玖年伍月貳拾壹日起延長羈押貳月。",
    "reason": "一、被告甲○○因違反槍砲彈藥刀械管制條例案件，前經本院合\n    法傳喚、拘提無著後，予以發布通緝在案，嗣經緝獲並經本\n    院訊問後，認其涉犯未經許可持有可發射子彈具有殺傷力之\n    改造手槍、未經許可持有子彈等罪嫌，犯罪嫌疑重大，且經\n    通緝到案，有逃亡事實，而有羈押之必要，依刑事訴訟法第\n    一百零一條第一項第一款規定，於民國九十九年二月二十一\n    日起諭知予以羈押在案。\n二、茲本院以羈押期間，即將屆滿，於九十九年五月十二日依法\n    訊問被告甲○○及其指定辯護人後，認被告甲○○之原羈押\n    原因仍然存在，有繼續羈押之必要，應自九十九年五月二十\n    一日起，再延長羈押二月。\n三、爰依刑事訴訟法第一百零八條第一項、第二項，裁定如主文\n    。"
  },
  "characters": {
    "judges": [
      "胡堅勤",
      "盧軍傑",
      "林家賢"
    ],
    "prosecutors": [

    ],
    "lawyers": [

    ],
    "clerks": [
      "林政良"
    ],
    "plaintiffs": [

    ],
    "defendants": [
      "甲○○"
    ],
    "prosecutor_office": [
      "臺灣板橋地方法院檢察署檢察官"
    ],
    "creditors": [

    ],
    "debtors": [

    ],
    "judicial_associate_officer": [

    ]
  },
  "adjudged_at": "2010-05-12",
  "created_at": "2016-01-05 12:22:46",
  "updated_at": "2016-01-05 12:22:46"
}