{
  "identify": "PCD-99-司聲更-6-20100512-2",
  "court": {
    "name": "臺灣新北地方法院",
    "code": "PCD"
  },
  "division": {
    "name": "民事",
    "code": "V"
  },
  "year": 99,
  "word": "司聲更",
  "number": "6",
  "jcheck": "2",
  "reason": "確定訴訟費用額",
  "content": "臺灣板橋地方法院民事裁定             99年度司聲更字第6號\n聲  請  人  德商萬寶龍文具有限公司Montblanc-Simplo Gmbh\n法定代理人  乙○○\n            丙○○\n代  理  人  李志珊律師\n            郭建中律師\n相  對  人  上友工業股份有限公司\n法定代理人  甲○○\n上列當事人間宣告確定判決准予強制執行事件，聲請人聲請確定\n訴訟費用額，本院裁定如下：\n    主  文\n本件聲請人應賠償相對人之訴訟費用額確定為新臺幣貳萬玖仟玖\n佰肆拾玖元，並應自本裁定送達之翌日起至清償日止，加給按週\n年利率百分之五計算之利息。\n    理  由\n一、按法院未於訴訟費用之裁判確定其費用額者，第一審受訴法\n    院於該裁判有執行力後，應依聲請以裁定確定之；依第1 項\n    確定之訴訟費用額，應於裁定送達之翌日起，加給按法定利\n    率計算之利息。當事人分擔訴訟費用者，法院為確定費用額\n    之裁判時，除前條第2 項情形外，應視為各當事人應負擔之\n    費用，已就相等之額抵銷，而確定其一造應賠償他造之差額\n    ，民事訴訟法第91條第1 項、第3 項、第93條分別定有明文\n    。\n二、本件聲請人與相對人間宣告確定判決准予強制執行事件，經\n    本院以91年度訴字第2160號民事判決英國高等法院於西元20\n    00年8月25日所為HC1999 NO0617號民事確定判決應予承認；\n    英國最高法院估費處基於英國高等法院於西元 2000年8月25\n    日所為HC1999 NO0617 號民事確定判決所為命相對人應給付\n    聲請人訴訟費用英鎊92,213.66元並附加自西元1999年12月1\n    日起至相對人實際清償日之止，依週年利率百分之 8計算之\n    利息確定裁定，准予強制執行。訴訟費用由相對人負擔，並\n    駁回聲請人其餘之請求。嗣相對人就該判決提起上訴，並經\n    臺灣高等法院以92年度上字第802號、最高法院95 年度台上\n    字第293號、臺灣高等法院95年度上更（一）字第36 號民事\n    判決，廢棄除確定部分外原第一審判決關於主文第二項准許\n    強制執行之金額超過「英鎊92,213.66元」 部分，及除確定\n    部分外，訴訟費用之裁判均廢棄；並駁回前開廢棄部分聲請\n    人在第一審之訴；原判決主文第一項其中關於西元 2000年8\n    月25日之記載應更正為西元1999年12月1日； 第一、二審及\n    發回前第三審訴訟費用除確定部分外，由相對人負擔三分之\n    一，餘由聲請人負擔。雖相對人再提起第三審上訴，業經最\n    高法院98年度台上字第80號民事判決駁回其上訴，第三審訴\n    訟費用由相對人負擔後而告確定。另相對人復對該確定民事\n    判決提起再審之訴，經最高法院98年度台再字第46號民事判\n    決駁回再審之訴，再審訴訟費用由相對人負擔。\n三、經查：\n   （一）經本院調卷審查後，聲請人於本院91年度訴字第 2160\n         號第一審程序預納裁判費用新臺幣（下同）55,589 元\n         及送達郵費476元，其中送達郵費部分已於第二審程序\n         全額退還予聲請人。相對人於臺灣高等法院第92 年度\n         上字第802號第二審程序預納裁判費用85,815元、送達\n         郵費544元及於最高法院第95年度台上字第293 號第三\n         審程序預納裁判費用86,359元，以上合計228,307元均\n         屬本件訴訟費用。另聲請人於最高法院95 年度台上字\n         第293號、98年度台上字第80號委任律師之酬金復經最\n         高法院於98年12月2日以98年度台聲字第1218號民事裁\n         定核定共為100,000元，經本院以99年4月26日板院輔\n         民事秋99司聲更6字第027180號函詢最高法院發回前與\n         發回後第三審之個別律師酬金數額，經最高法院99 年\n         5月3日民五98台聲1218字第099000001號函覆就95年度\n         台上字第293號及98年度台上字第80號兩案個別核定50\n         ,000元律師酬金。\n   （二）臺灣高等法院95 年度上更（一）字第36號民事判決第\n         一、二審及發回前第三審訴訟費用除確定部分外 ，由\n         相對人負擔三分之一，餘由聲請人負擔。 查聲請人原\n         起訴聲明請求確認英國高等法院之禁制令及最高法院\n         估費處核定訴訟費用裁定之效力部分， 經本院91年度\n         訴字第2160 號民事判決以欠缺訴之利益而予以駁回，\n         聲請人未聲明不服， 故該部分之請求已告確定。惟聲\n         請人就該部分未納裁判費， 是上開聲請人及相對人就\n         上開第一、二審、 發回前第三審訴訟費用及律師酬金\n         ，應依臺灣高等法院95年度上更 （一）字第36號民事\n         判決由聲請人負擔三分之二為 185,538元（即228,307\n         元×2/3＋50,000×2/3元） 。另聲請人於最高法院98\n         年度台上字第80 號預納之第三審律師酬金50,000元，\n         應由相對人負擔。 則聲請人應負擔部分之訴訟費用，\n         與前揭聲請人已預納之訴訟費用155,589元（即第一審\n         裁判費55,589元＋第三審律師酬金100,000元）相互抵\n         銷後，聲請人應賠償相對人之訴訟費用額確定為29,94\n         9（即185,538－155,589＝29,949）。爰裁定如主文所\n         示。\n四、依民事訴訟法第91條、第93條，裁定如主文。\n五、如不符本裁定，應於裁定送達後10日內，以書狀向司法事務\n    官提出異議。\n中    華    民    國    99    年    5     月    12    日\n                  民事第三庭    司法事務官  陳虹吟",
  "structure": {
    "main": "本件聲請人應賠償相對人之訴訟費用額確定為新臺幣貳萬玖仟玖\n佰肆拾玖元，並應自本裁定送達之翌日起至清償日止，加給按週\n年利率百分之五計算之利息。",
    "reason": "一、按法院未於訴訟費用之裁判確定其費用額者，第一審受訴法\n    院於該裁判有執行力後，應依聲請以裁定確定之；依第1 項\n    確定之訴訟費用額，應於裁定送達之翌日起，加給按法定利\n    率計算之利息。當事人分擔訴訟費用者，法院為確定費用額\n    之裁判時，除前條第2 項情形外，應視為各當事人應負擔之\n    費用，已就相等之額抵銷，而確定其一造應賠償他造之差額\n    ，民事訴訟法第91條第1 項、第3 項、第93條分別定有明文\n    。\n二、本件聲請人與相對人間宣告確定判決准予強制執行事件，經\n    本院以91年度訴字第2160號民事判決英國高等法院於西元20\n    00年8月25日所為HC1999 NO0617號民事確定判決應予承認；\n    英國最高法院估費處基於英國高等法院於西元 2000年8月25\n    日所為HC1999 NO0617 號民事確定判決所為命相對人應給付\n    聲請人訴訟費用英鎊92,213.66元並附加自西元1999年12月1\n    日起至相對人實際清償日之止，依週年利率百分之 8計算之\n    利息確定裁定，准予強制執行。訴訟費用由相對人負擔，並\n    駁回聲請人其餘之請求。嗣相對人就該判決提起上訴，並經\n    臺灣高等法院以92年度上字第802號、最高法院95 年度台上\n    字第293號、臺灣高等法院95年度上更（一）字第36 號民事\n    判決，廢棄除確定部分外原第一審判決關於主文第二項准許\n    強制執行之金額超過「英鎊92,213.66元」 部分，及除確定\n    部分外，訴訟費用之裁判均廢棄；並駁回前開廢棄部分聲請\n    人在第一審之訴；原判決主文第一項其中關於西元 2000年8\n    月25日之記載應更正為西元1999年12月1日； 第一、二審及\n    發回前第三審訴訟費用除確定部分外，由相對人負擔三分之\n    一，餘由聲請人負擔。雖相對人再提起第三審上訴，業經最\n    高法院98年度台上字第80號民事判決駁回其上訴，第三審訴\n    訟費用由相對人負擔後而告確定。另相對人復對該確定民事\n    判決提起再審之訴，經最高法院98年度台再字第46號民事判\n    決駁回再審之訴，再審訴訟費用由相對人負擔。\n三、經查：\n   （一）經本院調卷審查後，聲請人於本院91年度訴字第 2160\n         號第一審程序預納裁判費用新臺幣（下同）55,589 元\n         及送達郵費476元，其中送達郵費部分已於第二審程序\n         全額退還予聲請人。相對人於臺灣高等法院第92 年度\n         上字第802號第二審程序預納裁判費用85,815元、送達\n         郵費544元及於最高法院第95年度台上字第293 號第三\n         審程序預納裁判費用86,359元，以上合計228,307元均\n         屬本件訴訟費用。另聲請人於最高法院95 年度台上字\n         第293號、98年度台上字第80號委任律師之酬金復經最\n         高法院於98年12月2日以98年度台聲字第1218號民事裁\n         定核定共為100,000元，經本院以99年4月26日板院輔\n         民事秋99司聲更6字第027180號函詢最高法院發回前與\n         發回後第三審之個別律師酬金數額，經最高法院99 年\n         5月3日民五98台聲1218字第099000001號函覆就95年度\n         台上字第293號及98年度台上字第80號兩案個別核定50\n         ,000元律師酬金。\n   （二）臺灣高等法院95 年度上更（一）字第36號民事判決第\n         一、二審及發回前第三審訴訟費用除確定部分外 ，由\n         相對人負擔三分之一，餘由聲請人負擔。 查聲請人原\n         起訴聲明請求確認英國高等法院之禁制令及最高法院\n         估費處核定訴訟費用裁定之效力部分， 經本院91年度\n         訴字第2160 號民事判決以欠缺訴之利益而予以駁回，\n         聲請人未聲明不服， 故該部分之請求已告確定。惟聲\n         請人就該部分未納裁判費， 是上開聲請人及相對人就\n         上開第一、二審、 發回前第三審訴訟費用及律師酬金\n         ，應依臺灣高等法院95年度上更 （一）字第36號民事\n         判決由聲請人負擔三分之二為 185,538元（即228,307\n         元×2/3＋50,000×2/3元） 。另聲請人於最高法院98\n         年度台上字第80 號預納之第三審律師酬金50,000元，\n         應由相對人負擔。 則聲請人應負擔部分之訴訟費用，\n         與前揭聲請人已預納之訴訟費用155,589元（即第一審\n         裁判費55,589元＋第三審律師酬金100,000元）相互抵\n         銷後，聲請人應賠償相對人之訴訟費用額確定為29,94\n         9（即185,538－155,589＝29,949）。爰裁定如主文所\n         示。\n四、依民事訴訟法第91條、第93條，裁定如主文。\n五、如不符本裁定，應於裁定送達後10日內，以書狀向司法事務\n    官提出異議。"
  },
  "characters": {
    "judges": [

    ],
    "prosecutors": [

    ],
    "lawyers": [
      "李志珊",
      "郭建中",
      "發回後第三審之個別",
      "發回前第三審訴訟費用及",
      "號預納之第三審"
    ],
    "clerks": [

    ],
    "plaintiffs": [

    ],
    "defendants": [

    ],
    "prosecutor_office": [
      "德商萬寶龍文具有限公司Montblanc"
    ],
    "creditors": [

    ],
    "debtors": [

    ],
    "judicial_associate_officer": [
      "陳虹吟"
    ]
  },
  "adjudged_at": "2010-05-12",
  "created_at": "2016-01-05 12:28:44",
  "updated_at": "2016-01-05 12:28:44"
}