{
  "identify": "SCD-99-審竹交簡-352-20100512-1",
  "court": {
    "name": "臺灣新竹地方法院",
    "code": "SCD"
  },
  "division": {
    "name": "刑事",
    "code": "M"
  },
  "year": 99,
  "word": "審竹交簡",
  "number": "352",
  "jcheck": "1",
  "reason": "公共危險",
  "content": "臺灣新竹地方法院刑事簡易判決    99年度審竹交簡字第352 號\n聲  請  人  臺灣新竹地方法院檢察署檢察官\n被      告  甲○○\n上列被告因公共危險案件，經檢察官聲請以簡易判決處刑（99年\n度速偵字第589 號），本院判決如下：\n    主  文\n甲○○犯不能安全駕駛動力交通工具罪，累犯，處有期徒刑肆月\n，如易科罰金，以新臺幣壹仟元折算壹日。\n    事實及證據\n一、本件犯罪事實及證據，除犯罪事實欄：「．．．（第7 行後\n    段）嗣因飲酒後過於勞累而逕將車輛停放在國道1 號公路南\n    向103.3 公里（新竹市○○○道內，．．．」應予以補充外\n    ，餘均引用檢察官聲請簡易判決處刑書之記載（如附件）。\n二、論罪科刑部分：\n（一）論罪：\n  １、被告甲○○所為，係犯刑法第185 條之3 服用酒類不能安\n      全駕駛動力交通工具而駕駛罪。\n  ２、累犯：被告前曾於民國96年6 月間，因公共危險案件，經\n      臺灣苗栗地方法院（下稱苗栗地院）於96年7 月18日，以\n      96年度苗交簡字第376 號判決，判處有期徒刑3 月，嗣於\n      96年8 月6 日確定，並於96年12月17日易科罰金執行完畢\n      等情，有臺灣高等法院被告前案紀錄表及刑案資料查註紀\n      錄表各1 份為證，其於5 年以內故意再犯本件有期徒刑以\n      上之罪，為累犯，應依刑法第47條第1 項規定，加重其刑\n      。\n（二）科刑：審酌被告前已有2 次酒醉駕車前科，分別經本院及\n      苗栗地院分別判處拘役40日、有期徒刑3 月，有臺灣高等\n      法院被告前案紀錄表可證，竟不知警惕，再次服用酒類不\n      能安全駕駛動力交通工具之情形下，酒精濃度高達每公升\n      0.70毫克，仍貿然駕駛自用小客車上路，嚴重危及道路交\n      通安全，缺乏尊重其他用路人生命、財產安全之觀念，兼\n      衡被告之智識程度、素行、所生危害及犯罪後態度等一切\n      情狀，量處如主文所示之刑，並諭知易科罰金之折算標準\n      ，以資懲儆。\n三、依刑事訴訟法第449 條第1 項前段、第454 條第2 項，刑法\n    第185 條之3 、第47條第1 項、第41條第1 項前段，刑法施\n    行法第1 條之1 第1 項，逕以簡易判決處刑如主文。\n四、如不服本件判決，得自收受送達之日起10日內，向本院提起\n    上訴。\n中    華    民    國    99    年    5     月    12    日\n                    新竹簡易庭法  官          馮俊郎\n以上正本證明與原本無異。\n中    華    民    國    99    年    5     月    12    日\n                              書記官          王思穎\n附錄本案論罪科刑實體法條全文：\n刑法第185 條之3 ：\n服用毒品、麻醉藥品、酒類或其他相類之物，不能安全駕駛動力\n交通工具而駕駛者，處1 年以下有期徒刑、拘役或科或併科15萬\n元以下罰金。\n附件：\n臺灣新竹地方法院檢察署檢察官聲請簡易判決處刑書\n                                    99年度速偵字第589 號\n    被      告  甲○○  男  43歲（民國○○年○○月○○日生）\n                        國民身分證統一編號：Ｚ000000000號\n                        住苗栗縣公館鄉○○街3 巷7 號\n上列被告因公共危險案件，業經偵查終結，認為宜以簡易判決處\n刑，茲將犯罪事實及證據並所犯法條分敘如下：\n        犯罪事實\n１、甲○○前於民國96年間，因公共危險（刑法第185 條之3）\n    案件，經臺灣苗栗地方法院以96年度苗交簡字第376 號判決\n    判處有期徒刑3 月確定，於96年12月17日易科罰金執行完畢\n    。詎仍不知悔改，甲○○於99年3 月27日中午12時10分許，\n    在新竹市○○○路某工地飲酒結束後，已因之欠缺通常注意\n    力，而無安全駕駛車輛之能力，仍駕駛車牌號碼MF-3528 號\n    自用小客車欲沿國道1 號公路返回苗栗縣公館鄉住處，嗣因\n    飲酒後過於勞累而逕將車輛停放在國道1 號公路南向103.3\n    公里避車道內，而為警於同日下午2 時20分許在上開地點查\n    獲，經對其施以吐氣所含酒精濃度測試，測得濃度達每公升\n    0.70毫克，始悉上情。\n２、案經內政部警政署國道公路警察局第二警察隊報告偵辦。\n        證據並所犯法條\n１、證據：\n  (1)被告甲○○警詢、偵訊有關飲用酒類後，駕駛車輛行駛國道\n    公路過程之供述。\n  (2)查獲警員製作之職務報告1 紙。\n  (3)酒精測定紀錄表、刑法第185 條之3 案件測試觀察紀錄表、\n    汽車駕駛人酒後生理協調平衡檢測紀錄表(一)、(二)及舉發違反\n    道路交通管理事件通知單影本。\n２、核被告所為，係犯刑法第185 條之3 之服用酒類不能安全駕\n    駛動力交通工具而駕駛之罪嫌。另被告有如犯罪事實欄所述\n    之前案及執行紀錄，此有刑案資料查註紀錄表附卷可稽，其\n    受徒刑之執行完畢後，5 年以內故意再犯有期徒刑以上之本\n    罪，為累犯，請依刑法第47條第1 項規定加重其刑。\n３、依刑事訴訟法第451 條第1 項聲請逕以簡易判決處刑。\n    此    致\n臺灣新竹地方法院\n中    華    民    國    99    年    4     月    6     日\n                              檢 察 官    鄒 茂 瑜\n本件證明與原本無異\n中    華    民    國    99    年    4     月    16    日\n                              書 記 官    林 慧 菁\n所犯法條：\n中華民國刑法第185 條之3\n服用毒品、麻醉藥品、酒類或其他相類之物，不能安全駕駛動力\n交通工具而駕駛者，處一年以下有期徒刑、拘役或科或併科十五\n萬元以下罰金。",
  "structure": {
    "main": "甲○○犯不能安全駕駛動力交通工具罪，累犯，處有期徒刑肆月\n，如易科罰金，以新臺幣壹仟元折算壹日。\n    事實及證據\n一、本件犯罪事實及證據，除犯罪事實欄：「．．．（第7 行後\n    段）嗣因飲酒後過於勞累而逕將車輛停放在國道1 號公路南\n    向103.3 公里（新竹市○○○道內，．．．」應予以補充外\n    ，餘均引用檢察官聲請簡易判決處刑書之記載（如附件）。\n二、論罪科刑部分：\n（一）論罪：\n  １、被告甲○○所為，係犯刑法第185 條之3 服用酒類不能安\n      全駕駛動力交通工具而駕駛罪。\n  ２、累犯：被告前曾於民國96年6 月間，因公共危險案件，經\n      臺灣苗栗地方法院（下稱苗栗地院）於96年7 月18日，以\n      96年度苗交簡字第376 號判決，判處有期徒刑3 月，嗣於\n      96年8 月6 日確定，並於96年12月17日易科罰金執行完畢\n      等情，有臺灣高等法院被告前案紀錄表及刑案資料查註紀\n      錄表各1 份為證，其於5 年以內故意再犯本件有期徒刑以\n      上之罪，為累犯，應依刑法第47條第1 項規定，加重其刑\n      。\n（二）科刑：審酌被告前已有2 次酒醉駕車前科，分別經本院及\n      苗栗地院分別判處拘役40日、有期徒刑3 月，有臺灣高等\n      法院被告前案紀錄表可證，竟不知警惕，再次服用酒類不\n      能安全駕駛動力交通工具之情形下，酒精濃度高達每公升\n      0.70毫克，仍貿然駕駛自用小客車上路，嚴重危及道路交\n      通安全，缺乏尊重其他用路人生命、財產安全之觀念，兼\n      衡被告之智識程度、素行、所生危害及犯罪後態度等一切\n      情狀，量處如主文所示之刑，並諭知易科罰金之折算標準\n      ，以資懲儆。\n三、依刑事訴訟法第449 條第1 項前段、第454 條第2 項，刑法\n    第185 條之3 、第47條第1 項、第41條第1 項前段，刑法施\n    行法第1 條之1 第1 項，逕以簡易判決處刑如主文。\n四、如不服本件判決，得自收受送達之日起10日內，向本院提起\n    上訴。\n中    華    民    國    99    年    5     月    12    日\n                    新竹簡易庭法  官          馮俊郎\n以上正本證明與原本無異。\n中    華    民    國    99    年    5     月    12    日\n                              書記官          王思穎\n附錄本案論罪科刑實體法條全文：\n刑法第185 條之3 ：\n服用毒品、麻醉藥品、酒類或其他相類之物，不能安全駕駛動力\n交通工具而駕駛者，處1 年以下有期徒刑、拘役或科或併科15萬\n元以下罰金。\n附件：\n臺灣新竹地方法院檢察署檢察官聲請簡易判決處刑書\n                                    99年度速偵字第589 號\n    被      告  甲○○  男  43歲（民國○○年○○月○○日生）\n                        國民身分證統一編號：Ｚ000000000號\n                        住苗栗縣公館鄉○○街3 巷7 號\n上列被告因公共危險案件，業經偵查終結，認為宜以簡易判決處\n刑，茲將犯罪事實及證據並所犯法條分敘如下：",
    "fact": "１、甲○○前於民國96年間，因公共危險（刑法第185 條之3）\n    案件，經臺灣苗栗地方法院以96年度苗交簡字第376 號判決\n    判處有期徒刑3 月確定，於96年12月17日易科罰金執行完畢\n    。詎仍不知悔改，甲○○於99年3 月27日中午12時10分許，\n    在新竹市○○○路某工地飲酒結束後，已因之欠缺通常注意\n    力，而無安全駕駛車輛之能力，仍駕駛車牌號碼MF-3528 號\n    自用小客車欲沿國道1 號公路返回苗栗縣公館鄉住處，嗣因\n    飲酒後過於勞累而逕將車輛停放在國道1 號公路南向103.3\n    公里避車道內，而為警於同日下午2 時20分許在上開地點查\n    獲，經對其施以吐氣所含酒精濃度測試，測得濃度達每公升\n    0.70毫克，始悉上情。\n２、案經內政部警政署國道公路警察局第二警察隊報告偵辦。\n        證據並所犯法條\n１、證據：\n  (1)被告甲○○警詢、偵訊有關飲用酒類後，駕駛車輛行駛國道\n    公路過程之供述。\n  (2)查獲警員製作之職務報告1 紙。\n  (3)酒精測定紀錄表、刑法第185 條之3 案件測試觀察紀錄表、\n    汽車駕駛人酒後生理協調平衡檢測紀錄表(一)、(二)及舉發違反\n    道路交通管理事件通知單影本。\n２、核被告所為，係犯刑法第185 條之3 之服用酒類不能安全駕\n    駛動力交通工具而駕駛之罪嫌。另被告有如犯罪事實欄所述\n    之前案及執行紀錄，此有刑案資料查註紀錄表附卷可稽，其\n    受徒刑之執行完畢後，5 年以內故意再犯有期徒刑以上之本\n    罪，為累犯，請依刑法第47條第1 項規定加重其刑。\n３、依刑事訴訟法第451 條第1 項聲請逕以簡易判決處刑。\n    此    致\n臺灣新竹地方法院"
  },
  "characters": {
    "judges": [
      "馮俊郎"
    ],
    "prosecutors": [

    ],
    "lawyers": [

    ],
    "clerks": [
      "王思穎"
    ],
    "plaintiffs": [

    ],
    "defendants": [
      "甲○○",
      "甲○○  男  43歲（民國○○年○○月○○日生）"
    ],
    "prosecutor_office": [
      "臺灣新竹地方法院檢察署檢察官"
    ],
    "creditors": [

    ],
    "debtors": [

    ],
    "judicial_associate_officer": [

    ]
  },
  "adjudged_at": "2010-05-12",
  "created_at": "2016-01-05 12:42:51",
  "updated_at": "2016-01-05 12:42:51"
}