{
  "identify": "SCD-99-竹北交簡-280-20100512-1",
  "court": {
    "name": "臺灣新竹地方法院",
    "code": "SCD"
  },
  "division": {
    "name": "刑事",
    "code": "M"
  },
  "year": 99,
  "word": "竹北交簡",
  "number": "280",
  "jcheck": "1",
  "reason": "公共危險",
  "content": "臺灣新竹地方法院刑事簡易判決     99年度竹北交簡字第280號\n    聲  請  人  臺灣新竹地方法院檢察署檢察官\n    被      告  甲○○\n上列被告因公共危險案件，經檢察官聲請以簡易判決處刑（99年\n度偵字第2614號），本院判決如下：\n    主  文\n甲○○服用酒類，不能安全駕駛動力交通工具而駕駛，處罰金新\n臺幣陸萬貳仟元，如易服勞役，以新臺幣壹仟元折算壹日。\n    事實及理由\n一、本件本院認定被告甲○○之犯罪事實、證據及應適用法條，\n    除證據欄（2）第2行「反道路交通管理事件通知單」應補充\n    為「違反道路交通管理事件通知單」外，其餘均引用檢察官\n    聲請簡易判決處刑書之記載（如附件）。\n二、爰審酌被告曾於民國92年間因公共危險案件，經本院以92年\n    度竹交簡字第13號判決判處罰金銀元12,000元確定，嗣於92\n    年5 月1 日罰金繳清執行完畢，此有被告之臺灣高等法院少\n    年前案紀錄表及臺灣新竹地方法院檢察署刑案資料查註紀錄\n    表各1 份在卷可稽，惟被告不知警惕，再犯相同之本件公共\n    危險案件，且呼氣酒精濃度達每公升0.56毫克及被告犯罪之\n    動機、目的、犯罪手段、品行、智識程度、犯罪後坦承不諱\n    等一切情狀，量處如主文所示之刑，並諭知易服勞役之折算\n    標準。\n三、依刑事訴訟法第449 條第1 項前段、第3 項、第454 條第2\n    項，刑法第185 條之3 、第42條第3 項前段，刑法施行法第\n    1 條之1 第1 項，逕以簡易判決處刑如主文。\n四、如不服本判決，得自收受送達之日起10日內，向本院提起上\n    訴。其未敘述上訴理由者，並應由上訴期間屆滿後20日內向\n    本院補提理由書狀上訴（需按他造當事人之人數附繕本）「\n    切勿逕送上級法院」。\n中    華    民    國    99    年    5     月    12    日\n                  竹北簡易庭法  官  陳明珠\n以上正本證明與原本無異。\n中    華    民    國    99    年    5     月    12    日\n                            書記官  陳秀子\n附錄本院論罪科刑法條：\n刑法第185條之3\n服用毒品、麻醉藥品、酒類或其他相類似之物，不能安全駕駛動\n力交通工具而駕駛者，處一年以下有期徒刑、拘役或科或併科十\n五萬元以下罰金。\n（附件）",
  "structure": {
    "main": "甲○○服用酒類，不能安全駕駛動力交通工具而駕駛，處罰金新\n臺幣陸萬貳仟元，如易服勞役，以新臺幣壹仟元折算壹日。",
    "fact": "一、本件本院認定被告甲○○之犯罪事實、證據及應適用法條，\n    除證據欄（2）第2行「反道路交通管理事件通知單」應補充\n    為「違反道路交通管理事件通知單」外，其餘均引用檢察官\n    聲請簡易判決處刑書之記載（如附件）。\n二、爰審酌被告曾於民國92年間因公共危險案件，經本院以92年\n    度竹交簡字第13號判決判處罰金銀元12,000元確定，嗣於92\n    年5 月1 日罰金繳清執行完畢，此有被告之臺灣高等法院少\n    年前案紀錄表及臺灣新竹地方法院檢察署刑案資料查註紀錄\n    表各1 份在卷可稽，惟被告不知警惕，再犯相同之本件公共\n    危險案件，且呼氣酒精濃度達每公升0.56毫克及被告犯罪之\n    動機、目的、犯罪手段、品行、智識程度、犯罪後坦承不諱\n    等一切情狀，量處如主文所示之刑，並諭知易服勞役之折算\n    標準。\n三、依刑事訴訟法第449 條第1 項前段、第3 項、第454 條第2\n    項，刑法第185 條之3 、第42條第3 項前段，刑法施行法第\n    1 條之1 第1 項，逕以簡易判決處刑如主文。\n四、如不服本判決，得自收受送達之日起10日內，向本院提起上\n    訴。其未敘述上訴理由者，並應由上訴期間屆滿後20日內向\n    本院補提理由書狀上訴（需按他造當事人之人數附繕本）「\n    切勿逕送上級法院」。",
    "reason": "一、本件本院認定被告甲○○之犯罪事實、證據及應適用法條，\n    除證據欄（2）第2行「反道路交通管理事件通知單」應補充\n    為「違反道路交通管理事件通知單」外，其餘均引用檢察官\n    聲請簡易判決處刑書之記載（如附件）。\n二、爰審酌被告曾於民國92年間因公共危險案件，經本院以92年\n    度竹交簡字第13號判決判處罰金銀元12,000元確定，嗣於92\n    年5 月1 日罰金繳清執行完畢，此有被告之臺灣高等法院少\n    年前案紀錄表及臺灣新竹地方法院檢察署刑案資料查註紀錄\n    表各1 份在卷可稽，惟被告不知警惕，再犯相同之本件公共\n    危險案件，且呼氣酒精濃度達每公升0.56毫克及被告犯罪之\n    動機、目的、犯罪手段、品行、智識程度、犯罪後坦承不諱\n    等一切情狀，量處如主文所示之刑，並諭知易服勞役之折算\n    標準。\n三、依刑事訴訟法第449 條第1 項前段、第3 項、第454 條第2\n    項，刑法第185 條之3 、第42條第3 項前段，刑法施行法第\n    1 條之1 第1 項，逕以簡易判決處刑如主文。\n四、如不服本判決，得自收受送達之日起10日內，向本院提起上\n    訴。其未敘述上訴理由者，並應由上訴期間屆滿後20日內向\n    本院補提理由書狀上訴（需按他造當事人之人數附繕本）「\n    切勿逕送上級法院」。"
  },
  "characters": {
    "judges": [
      "陳明珠"
    ],
    "prosecutors": [

    ],
    "lawyers": [

    ],
    "clerks": [
      "陳秀子"
    ],
    "plaintiffs": [

    ],
    "defendants": [
      "甲○○"
    ],
    "prosecutor_office": [
      "臺灣新竹地方法院檢察署檢察官"
    ],
    "creditors": [

    ],
    "debtors": [

    ],
    "judicial_associate_officer": [

    ]
  },
  "adjudged_at": "2010-05-12",
  "created_at": "2016-01-05 12:42:14",
  "updated_at": "2016-01-05 12:42:14"
}