{
  "identify": "SCD-99-審竹交簡-362-20100512-1",
  "court": {
    "name": "臺灣新竹地方法院",
    "code": "SCD"
  },
  "division": {
    "name": "刑事",
    "code": "M"
  },
  "year": 99,
  "word": "審竹交簡",
  "number": "362",
  "jcheck": "1",
  "reason": "公共危險",
  "content": "臺灣新竹地方法院刑事簡易判決     99年度審竹交簡字第362號\n聲  請  人  臺灣新竹地方法院檢察署檢察官\n被      告  甲○○\n上列被告因公共危險案件，經檢察官聲請以簡易判決處刑（99年\n度速偵字第713 號），本院判決如下：\n    主  文\n甲○○犯不能安全駕駛動力交通工具罪，處罰金新臺幣柒萬元，\n如易服勞役，以新臺幣壹仟元折算壹日。緩刑貳年，緩刑期內付\n保護管束，並應於判決確定後壹年內，向執行檢察官指定之政府\n機關、政府機構、行政法人、社區或其他符合公益目的之機構或\n團體，提供肆拾小時之義務勞務。\n    事實及證據\n一、本件犯罪事實及證據，除犯罪事實欄：「一、…（第7 行後\n    段）為警在新竹市○○路與民權路111 巷交岔路路口處攔檢\n    查獲，並於同日凌晨3 時54分許測得甲○○之酒精濃度呼氣\n    值達每公升0.94毫克。」，及證據欄：「（二）…（第2 行\n    後段）汽機車駕駛人酒後生理協調平衡檢測紀錄表1 張」應\n    予更正、補充外，餘均引用檢察官聲請簡易判決處刑書之記\n    載（如附件）。\n二、被告甲○○前未曾因故意犯罪受有期徒刑以上刑之宣告，此\n    有臺灣高等法院被告前案紀錄表及刑案資料查註紀錄表各1\n    份在卷可查，因一時失慮酒後駕車致罹刑章，經此偵查程序\n    及科刑之教訓後，應已知所警惕，相信不會再犯，本院綜核\n    各情認上開刑之宣告，已足策其自新，所宣告之刑，以暫不\n    執行為適當，爰併予宣告緩刑2 年。再因被告係酒後不能安\n    全駕駛而駕車，而近年政府行政部門迭經透過傳播媒體大力\n    宣導酒醉後不得開車之政令及法律知識，傳播媒體更時時透\n    過影像、文字描繪傳達出因酒醉後駕車所造成之用路人受傷\n    、死亡及損害公共設施等情形，被告受有教育且為一具有相\n    當智識經驗之成年人，當能知曉酒醉後駕車對所有用路人之\n    安全有相當程度之危險性，竟無視禁令，足見其守法觀念有\n    待加強，為使其習得正確之法律概念並遏止被告仍有酒醉後\n    駕車之可能，及時刻記取酒醉後駕車係不法之行為，有加強\n    對被告追蹤、考核及輔導之必要，又為促使被告日後得以知\n    曉尊重法治，及為期被告於服務社會中得導正其偏差行為與\n    觀念，爰依刑法第74條第2 項第5 款之規定，諭知被告應於\n    判決確定後1 年內，向執行檢察官指定之政府機關、政府機\n    構、行政法人、社區或其他符合公益目的之機構或團體，提\n    供40小時之義務勞務，並依刑法第93條第1 項第2 款諭知緩\n    刑期內付保護管束，期能使被告於義務勞務過程及保護管束\n    期間，確切明瞭其行為之不當與危險性，並培養正確法治觀\n    念，相信如此當較僅給予被告罰金、或處以拘役、6 個月以\n    下有期徒刑而得易科罰金甚或拘束其身體自由之刑罰，更能\n    達到法律制定之目的。至於被告究應向何政府機關、政府機\n    構、行政法人、社區或其他符合公益目的之機構或團體提供\n    義務勞務，屬執行之問題，應由執行檢察官斟酌全案情節及\n    各政府機關、政府機構、行政法人、社區或其他符合公益目\n    的之機構或團體之需求，妥為指定。再者，倘被告違反上開\n    所定負擔情節重大，足認原宣告之緩刑難收其預期效果，而\n    有執行刑罰之必要，依刑法第75條之1 第1 項第4 款規定，\n    得撤銷其緩刑之宣告，併此敘明。\n三、依刑事訴訟法第449 條第1 項前段、第450 條第1 項、第45\n    4 條第2 項，刑法第185 條之3 、第42條第3 項前段、第74\n    條第1 項第1 款、第2 項第5 款、第93條第1 項第2 款，刑\n    法施行法第1 條之1 第1 項，逕以簡易判決處刑如主文。\n四、如不服本件判決，得自收受送達之日起10日內，向本院提起\n    上訴。\n中    華    民    國    99    年    5     月    12    日\n                    新竹簡易庭法  官          馮俊郎\n以上正本證明與原本無異。\n中    華    民    國    99    年    5     月    12    日\n                              書記官          王思穎\n附錄本案論罪科刑實體法條全文：\n刑法第185 條之3 ：\n服用毒品、麻醉藥品、酒類或其他相類之物，不能安全駕駛動力\n交通工具而駕駛者，處1 年以下有期徒刑、拘役或科或併科15萬\n元以下罰金。\n附件：\n臺灣新竹地方法院檢察署檢察官聲請簡易判決處刑書\n                                     99年度速偵字第713號\n    被      告  甲○○  男30歲（民國○○年○○月○○日生）\n                        住新竹縣竹東鎮○○里○○鄰○○路1\n                        段168號\n                        身分證統一編號：Ｚ000000000號\n上被告因公共危險案件，業經偵查終結，認為宜以簡易判決處刑\n，茲將犯罪事實及證據並所犯法條分敘如下：\n          犯罪事實\n一、甲○○明知在服用酒類或其他相類之物後，將使其駕駛車輛\n    時之注意力減低、反應能力趨緩，而危及其他用路人之行車\n    往來安全。竟於民國99年4月17日凌晨1時起至凌晨2時許止\n    ，在新竹市○○路某PUB店內，飲用2瓶海尼根啤酒，已達不\n    能安全駕駛動力交通工具之狀態後，復駕駛1615—QB號自用\n    小客車欲返回其位於新竹縣竹東鎮○○里○○鄰○○路1段168\n    號之住處。嗣於98年4月17日凌晨2時30分許，為警在新竹市\n    ○○路與民權路11巷交岔路路口處攔檢查獲，並測得甲○○\n    之酒精濃度呼氣值達每公升0‧94毫克。\n二、案經新竹市警察局第二分局報告偵辦。\n          證據並所犯法條\n一、證據：(一)被告甲○○之自白。\n          (二)酒精測定0‧94MG／L測定數據紙1紙、刑法第185\n              條之3案件測試觀察紀錄表1張、汽車駕駛人酒後\n              生理協調平衡檢測紀錄卡1張、竹市警交字第\n              E00000000號舉發違反道路交通管理事件通知單1\n              紙在卷可資佐證。\n二、所犯法條：核被告所為係犯刑法第185 條之3 公共危險罪嫌\n    。\n三、依刑事訴訟法第451 條第1 項聲請逕以簡易判決處刑。\n    此    致\n臺灣新竹地方法院\n中    華    民    國    99    年    4     月    26    日\n                              檢察官  林 佳  穎\n本件證明與原本無異\n中    華    民    國    99    年    4     月    26    日\n                              書記官  曾  美  松\n參考法條：\n刑法第185條之3\n服用毒品、麻醉藥品、酒類或其他相類之物，不能安全駕駛動力\n交通工具而駕駛者，處1年以下有期徒刑、拘役或科或併科15萬\n元以下罰金。",
  "structure": {
    "main": "甲○○犯不能安全駕駛動力交通工具罪，處罰金新臺幣柒萬元，\n如易服勞役，以新臺幣壹仟元折算壹日。緩刑貳年，緩刑期內付\n保護管束，並應於判決確定後壹年內，向執行檢察官指定之政府\n機關、政府機構、行政法人、社區或其他符合公益目的之機構或\n團體，提供肆拾小時之義務勞務。\n    事實及證據\n一、本件犯罪事實及證據，除犯罪事實欄：「一、…（第7 行後\n    段）為警在新竹市○○路與民權路111 巷交岔路路口處攔檢\n    查獲，並於同日凌晨3 時54分許測得甲○○之酒精濃度呼氣\n    值達每公升0.94毫克。」，及證據欄：「（二）…（第2 行\n    後段）汽機車駕駛人酒後生理協調平衡檢測紀錄表1 張」應\n    予更正、補充外，餘均引用檢察官聲請簡易判決處刑書之記\n    載（如附件）。\n二、被告甲○○前未曾因故意犯罪受有期徒刑以上刑之宣告，此\n    有臺灣高等法院被告前案紀錄表及刑案資料查註紀錄表各1\n    份在卷可查，因一時失慮酒後駕車致罹刑章，經此偵查程序\n    及科刑之教訓後，應已知所警惕，相信不會再犯，本院綜核\n    各情認上開刑之宣告，已足策其自新，所宣告之刑，以暫不\n    執行為適當，爰併予宣告緩刑2 年。再因被告係酒後不能安\n    全駕駛而駕車，而近年政府行政部門迭經透過傳播媒體大力\n    宣導酒醉後不得開車之政令及法律知識，傳播媒體更時時透\n    過影像、文字描繪傳達出因酒醉後駕車所造成之用路人受傷\n    、死亡及損害公共設施等情形，被告受有教育且為一具有相\n    當智識經驗之成年人，當能知曉酒醉後駕車對所有用路人之\n    安全有相當程度之危險性，竟無視禁令，足見其守法觀念有\n    待加強，為使其習得正確之法律概念並遏止被告仍有酒醉後\n    駕車之可能，及時刻記取酒醉後駕車係不法之行為，有加強\n    對被告追蹤、考核及輔導之必要，又為促使被告日後得以知\n    曉尊重法治，及為期被告於服務社會中得導正其偏差行為與\n    觀念，爰依刑法第74條第2 項第5 款之規定，諭知被告應於\n    判決確定後1 年內，向執行檢察官指定之政府機關、政府機\n    構、行政法人、社區或其他符合公益目的之機構或團體，提\n    供40小時之義務勞務，並依刑法第93條第1 項第2 款諭知緩\n    刑期內付保護管束，期能使被告於義務勞務過程及保護管束\n    期間，確切明瞭其行為之不當與危險性，並培養正確法治觀\n    念，相信如此當較僅給予被告罰金、或處以拘役、6 個月以\n    下有期徒刑而得易科罰金甚或拘束其身體自由之刑罰，更能\n    達到法律制定之目的。至於被告究應向何政府機關、政府機\n    構、行政法人、社區或其他符合公益目的之機構或團體提供\n    義務勞務，屬執行之問題，應由執行檢察官斟酌全案情節及\n    各政府機關、政府機構、行政法人、社區或其他符合公益目\n    的之機構或團體之需求，妥為指定。再者，倘被告違反上開\n    所定負擔情節重大，足認原宣告之緩刑難收其預期效果，而\n    有執行刑罰之必要，依刑法第75條之1 第1 項第4 款規定，\n    得撤銷其緩刑之宣告，併此敘明。\n三、依刑事訴訟法第449 條第1 項前段、第450 條第1 項、第45\n    4 條第2 項，刑法第185 條之3 、第42條第3 項前段、第74\n    條第1 項第1 款、第2 項第5 款、第93條第1 項第2 款，刑\n    法施行法第1 條之1 第1 項，逕以簡易判決處刑如主文。\n四、如不服本件判決，得自收受送達之日起10日內，向本院提起\n    上訴。\n中    華    民    國    99    年    5     月    12    日\n                    新竹簡易庭法  官          馮俊郎\n以上正本證明與原本無異。\n中    華    民    國    99    年    5     月    12    日\n                              書記官          王思穎\n附錄本案論罪科刑實體法條全文：\n刑法第185 條之3 ：\n服用毒品、麻醉藥品、酒類或其他相類之物，不能安全駕駛動力\n交通工具而駕駛者，處1 年以下有期徒刑、拘役或科或併科15萬\n元以下罰金。\n附件：\n臺灣新竹地方法院檢察署檢察官聲請簡易判決處刑書\n                                     99年度速偵字第713號\n    被      告  甲○○  男30歲（民國○○年○○月○○日生）\n                        住新竹縣竹東鎮○○里○○鄰○○路1\n                        段168號\n                        身分證統一編號：Ｚ000000000號\n上被告因公共危險案件，業經偵查終結，認為宜以簡易判決處刑\n，茲將犯罪事實及證據並所犯法條分敘如下：",
    "fact": "一、甲○○明知在服用酒類或其他相類之物後，將使其駕駛車輛\n    時之注意力減低、反應能力趨緩，而危及其他用路人之行車\n    往來安全。竟於民國99年4月17日凌晨1時起至凌晨2時許止\n    ，在新竹市○○路某PUB店內，飲用2瓶海尼根啤酒，已達不\n    能安全駕駛動力交通工具之狀態後，復駕駛1615—QB號自用\n    小客車欲返回其位於新竹縣竹東鎮○○里○○鄰○○路1段168\n    號之住處。嗣於98年4月17日凌晨2時30分許，為警在新竹市\n    ○○路與民權路11巷交岔路路口處攔檢查獲，並測得甲○○\n    之酒精濃度呼氣值達每公升0‧94毫克。\n二、案經新竹市警察局第二分局報告偵辦。\n          證據並所犯法條\n一、證據：(一)被告甲○○之自白。\n          (二)酒精測定0‧94MG／L測定數據紙1紙、刑法第185\n              條之3案件測試觀察紀錄表1張、汽車駕駛人酒後\n              生理協調平衡檢測紀錄卡1張、竹市警交字第\n              E00000000號舉發違反道路交通管理事件通知單1\n              紙在卷可資佐證。\n二、所犯法條：核被告所為係犯刑法第185 條之3 公共危險罪嫌\n    。\n三、依刑事訴訟法第451 條第1 項聲請逕以簡易判決處刑。\n    此    致\n臺灣新竹地方法院"
  },
  "characters": {
    "judges": [
      "馮俊郎"
    ],
    "prosecutors": [

    ],
    "lawyers": [

    ],
    "clerks": [
      "王思穎",
      "曾美松"
    ],
    "plaintiffs": [

    ],
    "defendants": [
      "甲○○",
      "甲○○  男30歲（民國○○年○○月○○日生）"
    ],
    "prosecutor_office": [
      "臺灣新竹地方法院檢察署檢察官"
    ],
    "creditors": [

    ],
    "debtors": [

    ],
    "judicial_associate_officer": [

    ]
  },
  "adjudged_at": "2010-05-12",
  "created_at": "2016-01-05 12:43:03",
  "updated_at": "2016-01-05 12:43:03"
}