{
  "identify": "SCD-99-審竹簡-591-20100512-1",
  "court": {
    "name": "臺灣新竹地方法院",
    "code": "SCD"
  },
  "division": {
    "name": "刑事",
    "code": "M"
  },
  "year": 99,
  "word": "審竹簡",
  "number": "591",
  "jcheck": "1",
  "reason": "竊盜",
  "content": "臺灣新竹地方法院刑事簡易判決       99年度審竹簡字第591號\n聲  請  人  臺灣新竹地方法院檢察署檢察官\n被      告  甲○○\n上列被告因竊盜案件，經檢察官聲請以簡易判決處刑（99年度偵\n字第2530號），本院判決如下：\n    主  文\n甲○○犯竊盜罪，處拘役拾日，如易科罰金，以新臺幣壹仟元折\n算壹日。緩刑貳年，緩刑期內付保護管束，並應於判決確定後壹\n年內，向執行檢察官指定之政府機關、政府機構、行政法人、社\n區或其他符合公益目的之機構或團體，提供肆拾小時之義務勞務\n。\n    事實及證據\n一、本件犯罪事實及證據，除犯罪事實欄：「二、案經新竹市警\n    察局第二分局報告偵辦。」應予更正外，餘均引用檢察官聲\n    請簡易判決處刑書之記載（如附件）。\n二、論罪及科刑：\n（一）論罪：被告甲○○所為，係犯刑法第320 條第1 項之竊盜\n      罪。\n（二）科刑：\n  １、主刑：審酌被告因一時貪念而起意偷竊之犯罪動機、目的\n      及手段，任意竊取他人財物，其所為顯不尊重他人財產權\n      益，及竊盜所得財物之價值非鉅，以及犯罪後坦白承認犯\n      行等一切情狀，量處如主文所示之刑，並諭知易科罰金之\n      折算標準，以資懲儆。\n  ２、緩刑及付保護管束：被告前未曾因故意犯罪受有期徒刑以\n      上刑之宣告，此有臺灣高等法院被告前案紀錄表及刑案資\n      料查註紀錄表各1 份在卷可查，因一時失慮致罹刑典，經\n      此次偵查程序及科刑之教訓後，應已知所警惕，相信不會\n      再犯，本院綜核各情認上開刑之宣告，已足策其自新，所\n      宣告之刑，以暫不執行為適當，爰併予宣告緩刑2 年。另\n      為使其深切反省，爰依刑法第74條第2 項第5 款之規定，\n      諭知被告應於判決確定後1 年內，向執行檢察官指定之政\n      府機關、政府機構、行政法人、社區或其他符合公益目的\n      之機構或團體，提供40小時之義務勞務，並依刑法第93條\n      第1 項第2 款諭知緩刑期內付保護管束，以啟自新，兼觀\n      後效。至於被告究應向何政府機關、政府機構、行政法人\n      、社區或其他符合公益目的之機構或團體提供義務勞務，\n      屬執行之問題，應由執行檢察官斟酌全案情節及各政府機\n      關、政府機構、行政法人、社區或其他符合公益目的之機\n      構或團體之需求，妥為指定。再者，倘被告違反上開所定\n      負擔情節重大，足認原宣告之緩刑難收其預期效果，而有\n      執行刑罰之必要，依刑法第75條之1 第1 項第4 款規定，\n      得撤銷其緩刑之宣告，併此敘明。\n三、依刑事訴訟法第449 條第1 項前段、第450 條第1 項、第45\n    4 條第2 項，刑法第320 條第1 項、第41條第1 項前段、第\n    74條第1 項第1 款、第2 項第5 款、第93條第1 項第2 款，\n    刑法施行法第1 條之1 第1 項、第2 項前段，逕以簡易判決\n    處刑如主文。\n四、如不服本件判決，得自收受送達之日起10日內，向本院提起\n    上訴。\n中    華    民    國    99    年    5     月    12    日\n                    新竹簡易庭法  官          馮俊郎\n以上正本證明與原本無異。\n中    華    民    國    99    年    5     月    12    日\n                              書記官          王思穎\n附錄本案論罪科刑實體法條全文：\n刑法第320 條第1 項：\n意圖為自己或第三人不法之所有，而竊取他人之動產者，為竊盜\n罪，處5 年以下有期徒刑、拘役或500 元以下罰金。（罰金之貨\n幣單位改為新臺幣，並提高為30倍）\n附件：\n臺灣新竹地方法院檢察署檢察官聲請簡易判決處刑書\n                                      99年度偵字第2530號\n    被      告  甲○○  女  21歲（民國○○年○○月○○日生）\n                        住新竹縣竹東鎮○○路170巷31弄17\n                        號\n                        國民身分證統一編號：Ｚ000000000號\n上列被告因竊盜案件，已經偵查終結，認為宜聲請以簡易判決處\n刑，茲敘述犯罪事實及證據並所犯法條如下：\n        犯罪事實\n一、甲○○意圖為自己不法之所有，於民國99年3月5日19時30分\n    許，在新竹市○區○○路300號「大潤發賣場」內，徒手竊\n    取角型洗衣網、單人床包組等價值新臺幣（下同）1,710元\n    之商品，得手後藏置於其隨身攜帶之包包袋子內，未將袋內\n    物品結帳，即離開收銀檯。經櫃臺人員發覺有異，通知「大\n    潤發」安管課課員乙○○尾隨察看後，由乙○○在該店服務\n    台前，要求甲○○出示袋內多餘商品之結帳交易證明，甲○\n    ○當場未能提出，反而藉故逃離現場，經乙○○報警後始循\n    線查獲。\n二、案經新竹市警察局第一分局報告偵辦。\n        證據並所犯法條\n一、證據：\n（一）被告甲○○之自白。\n（二）證人乙○○之證述。\n（三）贓物認領保管單1張、「大潤發」遭竊物品估價送貨單1張\n      、監視錄影翻拍照片2張、蒐證照片2張在卷可資佐證，被\n      告犯嫌堪以認定。\n二、核被告甲○○所為，係犯刑法第320條第1項之竊盜罪嫌。\n三、依刑事訴訟法第451 條第1 項聲請逕以簡易判決處刑。\n    此  致\n臺灣新竹地方法院\n中    華    民    國    99    年    4     月    14    日\n                              檢察官  林 佳  穎\n本件證明與原本無異\n中    華    民    國    99    年    4     月    26    日\n                              書記官  曾  美  松\n參考法條：\n刑法第320條第1項\n意圖為自己或第三人不法之所有，而竊取他人之動產者，為竊盜\n罪，處5年以下有期徒刑、拘役或5百元以下罰金。",
  "structure": {
    "main": "甲○○犯竊盜罪，處拘役拾日，如易科罰金，以新臺幣壹仟元折\n算壹日。緩刑貳年，緩刑期內付保護管束，並應於判決確定後壹\n年內，向執行檢察官指定之政府機關、政府機構、行政法人、社\n區或其他符合公益目的之機構或團體，提供肆拾小時之義務勞務\n。\n    事實及證據\n一、本件犯罪事實及證據，除犯罪事實欄：「二、案經新竹市警\n    察局第二分局報告偵辦。」應予更正外，餘均引用檢察官聲\n    請簡易判決處刑書之記載（如附件）。\n二、論罪及科刑：\n（一）論罪：被告甲○○所為，係犯刑法第320 條第1 項之竊盜\n      罪。\n（二）科刑：\n  １、主刑：審酌被告因一時貪念而起意偷竊之犯罪動機、目的\n      及手段，任意竊取他人財物，其所為顯不尊重他人財產權\n      益，及竊盜所得財物之價值非鉅，以及犯罪後坦白承認犯\n      行等一切情狀，量處如主文所示之刑，並諭知易科罰金之\n      折算標準，以資懲儆。\n  ２、緩刑及付保護管束：被告前未曾因故意犯罪受有期徒刑以\n      上刑之宣告，此有臺灣高等法院被告前案紀錄表及刑案資\n      料查註紀錄表各1 份在卷可查，因一時失慮致罹刑典，經\n      此次偵查程序及科刑之教訓後，應已知所警惕，相信不會\n      再犯，本院綜核各情認上開刑之宣告，已足策其自新，所\n      宣告之刑，以暫不執行為適當，爰併予宣告緩刑2 年。另\n      為使其深切反省，爰依刑法第74條第2 項第5 款之規定，\n      諭知被告應於判決確定後1 年內，向執行檢察官指定之政\n      府機關、政府機構、行政法人、社區或其他符合公益目的\n      之機構或團體，提供40小時之義務勞務，並依刑法第93條\n      第1 項第2 款諭知緩刑期內付保護管束，以啟自新，兼觀\n      後效。至於被告究應向何政府機關、政府機構、行政法人\n      、社區或其他符合公益目的之機構或團體提供義務勞務，\n      屬執行之問題，應由執行檢察官斟酌全案情節及各政府機\n      關、政府機構、行政法人、社區或其他符合公益目的之機\n      構或團體之需求，妥為指定。再者，倘被告違反上開所定\n      負擔情節重大，足認原宣告之緩刑難收其預期效果，而有\n      執行刑罰之必要，依刑法第75條之1 第1 項第4 款規定，\n      得撤銷其緩刑之宣告，併此敘明。\n三、依刑事訴訟法第449 條第1 項前段、第450 條第1 項、第45\n    4 條第2 項，刑法第320 條第1 項、第41條第1 項前段、第\n    74條第1 項第1 款、第2 項第5 款、第93條第1 項第2 款，\n    刑法施行法第1 條之1 第1 項、第2 項前段，逕以簡易判決\n    處刑如主文。\n四、如不服本件判決，得自收受送達之日起10日內，向本院提起\n    上訴。\n中    華    民    國    99    年    5     月    12    日\n                    新竹簡易庭法  官          馮俊郎\n以上正本證明與原本無異。\n中    華    民    國    99    年    5     月    12    日\n                              書記官          王思穎\n附錄本案論罪科刑實體法條全文：\n刑法第320 條第1 項：\n意圖為自己或第三人不法之所有，而竊取他人之動產者，為竊盜\n罪，處5 年以下有期徒刑、拘役或500 元以下罰金。（罰金之貨\n幣單位改為新臺幣，並提高為30倍）\n附件：\n臺灣新竹地方法院檢察署檢察官聲請簡易判決處刑書\n                                      99年度偵字第2530號\n    被      告  甲○○  女  21歲（民國○○年○○月○○日生）\n                        住新竹縣竹東鎮○○路170巷31弄17\n                        號\n                        國民身分證統一編號：Ｚ000000000號\n上列被告因竊盜案件，已經偵查終結，認為宜聲請以簡易判決處\n刑，茲敘述犯罪事實及證據並所犯法條如下：",
    "fact": "一、甲○○意圖為自己不法之所有，於民國99年3月5日19時30分\n    許，在新竹市○區○○路300號「大潤發賣場」內，徒手竊\n    取角型洗衣網、單人床包組等價值新臺幣（下同）1,710元\n    之商品，得手後藏置於其隨身攜帶之包包袋子內，未將袋內\n    物品結帳，即離開收銀檯。經櫃臺人員發覺有異，通知「大\n    潤發」安管課課員乙○○尾隨察看後，由乙○○在該店服務\n    台前，要求甲○○出示袋內多餘商品之結帳交易證明，甲○\n    ○當場未能提出，反而藉故逃離現場，經乙○○報警後始循\n    線查獲。\n二、案經新竹市警察局第一分局報告偵辦。\n        證據並所犯法條\n一、證據：\n（一）被告甲○○之自白。\n（二）證人乙○○之證述。\n（三）贓物認領保管單1張、「大潤發」遭竊物品估價送貨單1張\n      、監視錄影翻拍照片2張、蒐證照片2張在卷可資佐證，被\n      告犯嫌堪以認定。\n二、核被告甲○○所為，係犯刑法第320條第1項之竊盜罪嫌。\n三、依刑事訴訟法第451 條第1 項聲請逕以簡易判決處刑。\n    此  致\n臺灣新竹地方法院"
  },
  "characters": {
    "judges": [
      "馮俊郎"
    ],
    "prosecutors": [

    ],
    "lawyers": [

    ],
    "clerks": [
      "王思穎",
      "曾美松"
    ],
    "plaintiffs": [

    ],
    "defendants": [
      "甲○○",
      "甲○○  女  21歲（民國○○年○○月○○日生）"
    ],
    "prosecutor_office": [
      "臺灣新竹地方法院檢察署檢察官"
    ],
    "creditors": [

    ],
    "debtors": [

    ],
    "judicial_associate_officer": [

    ]
  },
  "adjudged_at": "2010-05-12",
  "created_at": "2016-01-05 12:42:56",
  "updated_at": "2016-01-05 12:42:56"
}