{
  "identify": "SCD-99-審竹交簡-347-20100512-1",
  "court": {
    "name": "臺灣新竹地方法院",
    "code": "SCD"
  },
  "division": {
    "name": "刑事",
    "code": "M"
  },
  "year": 99,
  "word": "審竹交簡",
  "number": "347",
  "jcheck": "1",
  "reason": "公共危險",
  "content": "臺灣新竹地方法院刑事簡易判決    99年度審竹交簡字第347 號\n聲  請  人  臺灣新竹地方法院檢察署檢察官\n被      告  甲○○\n上列被告因公共危險案件，經檢察官聲請以簡易判決處刑（99年\n度速偵字第684 號），本院判決如下：\n    主  文\n甲○○犯不能安全駕駛動力交通工具罪，處罰金新臺幣拾萬元，\n如易服勞役，以新臺幣壹仟元折算壹日。緩刑貳年，緩刑期內付\n保護管束，並應於判決確定後陸個月內向公庫支付新臺幣萬元\n，及於判決確定後壹年內向指定之政府機關、政府機構、行政法\n人、社區或其他符合公益目的之機構或團體，提供陸拾小時之義\n務勞務。\n    事實及證據\n一、本件犯罪事實及證據，均引用檢察官聲請簡易判決處刑書之\n    記載（如附件）。\n二、被告甲○○所為，係犯刑法第185 條之3 服用酒類不能安全\n    駕駛動力交通工具而駕駛罪。爰審酌被告前已有1 次酒醉駕\n    車紀錄，經臺灣新竹地方法院檢察署檢察官為緩起訴處分，\n    有臺灣高等法院被告前案紀錄表可證，竟不知警惕，再次服\n    用酒類不能安全駕駛動力交通工具之情形下，酒精濃度達每\n    公升1.45毫克，仍貿然駕駛自用小貨車上路，嚴重危及道路\n    交通安全，缺乏尊重其他用路人生命、財產安全之觀念，兼\n    衡被告之智識程度、素行、所生危害及犯罪後態度等一切情\n    狀，量處如主文所示之刑，並諭知易服勞役之折算標準，以\n    資懲儆。\n三、被告甲○○前雖曾因故意犯罪受有期徒刑以上刑之宣告，然\n    執行完畢後，5 年以內未曾因故意犯罪受有期徒刑以上刑之\n    宣告，此有臺灣高等法院被告前案紀錄表及刑案資料查註紀\n    錄表各1 份在卷可查，因一時失慮酒後駕車致罹刑章，經此\n    偵查程序及科刑之教訓後，應已知所警惕，相信不會再犯，\n    本院綜核各情認上開刑之宣告，已足策其自新，所宣告之刑\n    ，以暫不執行為適當，爰併予宣告緩刑2 年。另為使其深切\n    反省，爰依刑法第74條第2 項第4 款之規定，諭知被告應於\n    判決確定後6 個月內向公庫支付新臺幣3 萬元。再因被告係\n    酒後不能安全駕駛而駕車，而近年政府行政部門迭經透過傳\n    播媒體大力宣導酒醉後不得開車之政令及法律知識，傳播媒\n    體更時時透過影像、文字描繪傳達出因酒醉後駕車所造成之\n    用路人受傷、死亡及損害公共設施等情形，被告受有教育且\n    為一具有相當智識經驗之成年人，當能知曉酒醉後駕車對所\n    有用路人之安全有相當程度之危險性，竟無視禁令，足見其\n    守法觀念有待加強，為使其習得正確之法律概念並遏止被告\n    仍有酒醉後駕車之可能，及時刻記取酒醉後駕車係不法之行\n    為，有加強對被告追蹤、考核及輔導之必要，又為促使被告\n    日後得以知曉尊重法治，及為期被告於服務社會中得導正其\n    偏差行為與觀念，爰依刑法第74條第2 項第5 款之規定，諭\n    知被告應於判決確定後1 年內向指定之政府機關、政府機構\n    、行政法人、社區或其他符合公益目的之機構或團體，提供\n    60小時之義務勞務，並依刑法第93條第1 項第2 款諭知緩刑\n    期內付保護管束，期能使被告於義務勞務過程及保護管束期\n    間，確切明瞭其行為之不當與危險性，並培養正確法治觀念\n    ，相信如此當較僅給予被告罰金、或處以拘役、6 個月以下\n    有期徒刑而得易科罰金甚或拘束其身體自由之刑罰，更能達\n    到法律制定之目的。至於被告究應向何政府機關、政府機構\n    、行政法人、社區或其他符合公益目的之機構或團體提供義\n    務勞務，屬執行之問題，應由執行檢察官斟酌全案情節及各\n    政府機關、政府機構、行政法人、社區或其他符合公益目的\n    之機構或團體之需求，妥為指定。再者，倘被告於本案期間\n    ，違反上開所定負擔情節重大，足認原宣告之緩刑難收其預\n    期效果，而有執行刑罰之必要，依刑法第75條之1 第1 項第\n    4 款規定，得撤銷其緩刑之宣告，併此敘明。\n四、依刑事訴訟法第449 條第1 項前段、第450 條第1 項、第45\n    4 條第2 項，刑法第185 條之3 、第42條第3 項前段、第74\n    條第1 項第2 款、第2 項第4 款、第5 款、第93條第1 項第\n    2 款，刑法施行法第1 條之1 第1 項，逕以簡易判決處刑如\n    主文。\n五、如不服本件判決，得自收受送達之日起10日內，向本院提起\n    上訴。\n中    華    民    國    99    年    5     月    12    日\n                    新竹簡易庭法  官          馮俊郎\n以上正本證明與原本無異。\n中    華    民    國    99    年    5     月    12    日\n                              書記官          王思穎\n附錄本案論罪科刑實體法條全文：\n刑法第185 條之3 ：\n服用毒品、麻醉藥品、酒類或其他相類之物，不能安全駕駛動力\n交通工具而駕駛者，處1 年以下有期徒刑、拘役或科或併科15萬\n元以下罰金。\n附件：\n臺灣新竹地方法院檢察署檢察官聲請簡易判決處刑書\n                                    99年度速偵字第684 號\n    被      告  甲○○  男  51歲（民國○○年○○月○ 日生）\n                        住新竹市○○區○○路35號\n                        國民身分證統一編號：Ｚ000000000號\n上列被告因公共危險案件，業經偵查終結，認為宜聲請以簡易判\n決處刑，茲將犯罪事實及證據並所犯法條分敘如下：\n        犯罪事實\n一、甲○○明知酒後駕車將導致其注意能力減低、反應能力變慢\n    ，在此時如駕車行駛於道路上，隨時有致他人於死、傷之危\n    險，竟自民國99年4 月12日中午12時15分許起，在位於新竹\n    市○○路71巷之鄰居住處內飲用私釀米酒2 杯，至同日下午\n    4 時許止，已達不能安全駕駛動力交通工具之程度，卻仍於\n    同日下午5 時許酒後駕駛車牌號碼H2-2471 號自用小貨車，\n    自該處出發，前往其叔父廖金倉位於新竹市○○區○○路15\n    號之住處。嗣經廖金倉報警，經警到場處理，並對甲○○進\n    行酒精檢測，於同日下午6 時2 分許，測得其呼氣所含酒精\n    濃度達每公升1.45毫克，而得悉上情。\n二、案經新竹市警察局第三分局報告偵辦。\n        證據並所犯法條\n一、證據：\n（一）被告甲○○於警詢及偵查中之自白。\n（二）證人廖金倉於警詢之證述。\n（三）酒精測試紙、刑法第185 條之3 案件測試觀察紀錄表、汽\n      機車駕駛人酒後生理協調平衡檢測紀錄表、新竹市警察局\n      舉發違反道路交通管理事件通知單各1 份。\n二、核被告所為，係犯刑法第185 條之3 公共危險罪嫌。\n三、依刑事訴訟法第451 條第1 項聲請逕以簡易判決處刑。\n    此    致\n臺灣新竹地方法院\n中    華    民    國    99    年    4     月    16    日\n                        檢  察  官  王  唯  怡\n本件證明與原本無異\n中    華    民    國    99    年    4     月    21    日\n                        書  記  官  賴  玉  華\n參考法條：\n刑法第185 條之3\n服用毒品、麻醉藥品、酒類或其他相類之物，不能安全駕駛動力\n交通工具而駕駛者，處一年以下有期徒刑、拘役或科或併科十五\n萬元以下罰金。",
  "structure": {
    "main": "甲○○犯不能安全駕駛動力交通工具罪，處罰金新臺幣拾萬元，\n如易服勞役，以新臺幣壹仟元折算壹日。緩刑貳年，緩刑期內付\n保護管束，並應於判決確定後陸個月內向公庫支付新臺幣萬元\n，及於判決確定後壹年內向指定之政府機關、政府機構、行政法\n人、社區或其他符合公益目的之機構或團體，提供陸拾小時之義\n務勞務。\n    事實及證據\n一、本件犯罪事實及證據，均引用檢察官聲請簡易判決處刑書之\n    記載（如附件）。\n二、被告甲○○所為，係犯刑法第185 條之3 服用酒類不能安全\n    駕駛動力交通工具而駕駛罪。爰審酌被告前已有1 次酒醉駕\n    車紀錄，經臺灣新竹地方法院檢察署檢察官為緩起訴處分，\n    有臺灣高等法院被告前案紀錄表可證，竟不知警惕，再次服\n    用酒類不能安全駕駛動力交通工具之情形下，酒精濃度達每\n    公升1.45毫克，仍貿然駕駛自用小貨車上路，嚴重危及道路\n    交通安全，缺乏尊重其他用路人生命、財產安全之觀念，兼\n    衡被告之智識程度、素行、所生危害及犯罪後態度等一切情\n    狀，量處如主文所示之刑，並諭知易服勞役之折算標準，以\n    資懲儆。\n三、被告甲○○前雖曾因故意犯罪受有期徒刑以上刑之宣告，然\n    執行完畢後，5 年以內未曾因故意犯罪受有期徒刑以上刑之\n    宣告，此有臺灣高等法院被告前案紀錄表及刑案資料查註紀\n    錄表各1 份在卷可查，因一時失慮酒後駕車致罹刑章，經此\n    偵查程序及科刑之教訓後，應已知所警惕，相信不會再犯，\n    本院綜核各情認上開刑之宣告，已足策其自新，所宣告之刑\n    ，以暫不執行為適當，爰併予宣告緩刑2 年。另為使其深切\n    反省，爰依刑法第74條第2 項第4 款之規定，諭知被告應於\n    判決確定後6 個月內向公庫支付新臺幣3 萬元。再因被告係\n    酒後不能安全駕駛而駕車，而近年政府行政部門迭經透過傳\n    播媒體大力宣導酒醉後不得開車之政令及法律知識，傳播媒\n    體更時時透過影像、文字描繪傳達出因酒醉後駕車所造成之\n    用路人受傷、死亡及損害公共設施等情形，被告受有教育且\n    為一具有相當智識經驗之成年人，當能知曉酒醉後駕車對所\n    有用路人之安全有相當程度之危險性，竟無視禁令，足見其\n    守法觀念有待加強，為使其習得正確之法律概念並遏止被告\n    仍有酒醉後駕車之可能，及時刻記取酒醉後駕車係不法之行\n    為，有加強對被告追蹤、考核及輔導之必要，又為促使被告\n    日後得以知曉尊重法治，及為期被告於服務社會中得導正其\n    偏差行為與觀念，爰依刑法第74條第2 項第5 款之規定，諭\n    知被告應於判決確定後1 年內向指定之政府機關、政府機構\n    、行政法人、社區或其他符合公益目的之機構或團體，提供\n    60小時之義務勞務，並依刑法第93條第1 項第2 款諭知緩刑\n    期內付保護管束，期能使被告於義務勞務過程及保護管束期\n    間，確切明瞭其行為之不當與危險性，並培養正確法治觀念\n    ，相信如此當較僅給予被告罰金、或處以拘役、6 個月以下\n    有期徒刑而得易科罰金甚或拘束其身體自由之刑罰，更能達\n    到法律制定之目的。至於被告究應向何政府機關、政府機構\n    、行政法人、社區或其他符合公益目的之機構或團體提供義\n    務勞務，屬執行之問題，應由執行檢察官斟酌全案情節及各\n    政府機關、政府機構、行政法人、社區或其他符合公益目的\n    之機構或團體之需求，妥為指定。再者，倘被告於本案期間\n    ，違反上開所定負擔情節重大，足認原宣告之緩刑難收其預\n    期效果，而有執行刑罰之必要，依刑法第75條之1 第1 項第\n    4 款規定，得撤銷其緩刑之宣告，併此敘明。\n四、依刑事訴訟法第449 條第1 項前段、第450 條第1 項、第45\n    4 條第2 項，刑法第185 條之3 、第42條第3 項前段、第74\n    條第1 項第2 款、第2 項第4 款、第5 款、第93條第1 項第\n    2 款，刑法施行法第1 條之1 第1 項，逕以簡易判決處刑如\n    主文。\n五、如不服本件判決，得自收受送達之日起10日內，向本院提起\n    上訴。\n中    華    民    國    99    年    5     月    12    日\n                    新竹簡易庭法  官          馮俊郎\n以上正本證明與原本無異。\n中    華    民    國    99    年    5     月    12    日\n                              書記官          王思穎\n附錄本案論罪科刑實體法條全文：\n刑法第185 條之3 ：\n服用毒品、麻醉藥品、酒類或其他相類之物，不能安全駕駛動力\n交通工具而駕駛者，處1 年以下有期徒刑、拘役或科或併科15萬\n元以下罰金。\n附件：\n臺灣新竹地方法院檢察署檢察官聲請簡易判決處刑書\n                                    99年度速偵字第684 號\n    被      告  甲○○  男  51歲（民國○○年○○月○ 日生）\n                        住新竹市○○區○○路35號\n                        國民身分證統一編號：Ｚ000000000號\n上列被告因公共危險案件，業經偵查終結，認為宜聲請以簡易判\n決處刑，茲將犯罪事實及證據並所犯法條分敘如下：",
    "fact": "一、甲○○明知酒後駕車將導致其注意能力減低、反應能力變慢\n    ，在此時如駕車行駛於道路上，隨時有致他人於死、傷之危\n    險，竟自民國99年4 月12日中午12時15分許起，在位於新竹\n    市○○路71巷之鄰居住處內飲用私釀米酒2 杯，至同日下午\n    4 時許止，已達不能安全駕駛動力交通工具之程度，卻仍於\n    同日下午5 時許酒後駕駛車牌號碼H2-2471 號自用小貨車，\n    自該處出發，前往其叔父廖金倉位於新竹市○○區○○路15\n    號之住處。嗣經廖金倉報警，經警到場處理，並對甲○○進\n    行酒精檢測，於同日下午6 時2 分許，測得其呼氣所含酒精\n    濃度達每公升1.45毫克，而得悉上情。\n二、案經新竹市警察局第三分局報告偵辦。\n        證據並所犯法條\n一、證據：\n（一）被告甲○○於警詢及偵查中之自白。\n（二）證人廖金倉於警詢之證述。\n（三）酒精測試紙、刑法第185 條之3 案件測試觀察紀錄表、汽\n      機車駕駛人酒後生理協調平衡檢測紀錄表、新竹市警察局\n      舉發違反道路交通管理事件通知單各1 份。\n二、核被告所為，係犯刑法第185 條之3 公共危險罪嫌。\n三、依刑事訴訟法第451 條第1 項聲請逕以簡易判決處刑。\n    此    致\n臺灣新竹地方法院"
  },
  "characters": {
    "judges": [
      "馮俊郎"
    ],
    "prosecutors": [

    ],
    "lawyers": [

    ],
    "clerks": [
      "王思穎"
    ],
    "plaintiffs": [

    ],
    "defendants": [
      "甲○○",
      "甲○○  男  51歲（民國○○年○○月○ 日生）"
    ],
    "prosecutor_office": [
      "臺灣新竹地方法院檢察署檢察官"
    ],
    "creditors": [

    ],
    "debtors": [

    ],
    "judicial_associate_officer": [

    ]
  },
  "adjudged_at": "2010-05-12",
  "created_at": "2016-01-05 12:43:01",
  "updated_at": "2016-01-05 12:43:01"
}