{
  "identify": "SCD-99-除-149-20100512-1",
  "court": {
    "name": "臺灣新竹地方法院",
    "code": "SCD"
  },
  "division": {
    "name": "民事",
    "code": "V"
  },
  "year": 99,
  "word": "除",
  "number": "149",
  "jcheck": "1",
  "reason": "除權判決",
  "content": "臺灣新竹地方法院民事判決               99年度除字第149號\n聲  請  人  豪山國際股份有限公司\n法定代理人  甲○○\n訴訟代理人  乙○○\n上列聲請人聲請宣告支票無效事件，本院判決如下：\n    主  文\n附表所載之支票無效。\n訴訟費用由聲請人負擔。\n    事  實\n本件聲請意旨略以：聲請人執有附表所載之支票，因遺失而前經\n聲請本院以98年度司催字第502 號公示催告，並刊登新聞紙在案\n，現申報權利期間已滿，無人申報權利及提出原支票，為此聲請\n宣告該表所載支票無效。\n    理  由\n一、查附表所載之支票，經本院以98年度司催字第502 號公示催\n    告在案。\n二、所定申報權利期間已於民國99年4 月18日屆滿，迄今無人申\n    報權利及提出原支票，聲請人之聲請，應予准許。\n三、依民事訴訟法第564條第1項，判決如主文。\n中    華    民    國    99    年    5     月    12    日\n                              臺灣新竹地方法院民事第一庭\n                                      法  官  許翠玲\n以上正本係照原本作成。\n不得上訴。\n中    華    民    國    99    年    5     月    12    日\n                                      書記官  陳思璟\n┌──────────────────────────────────────────────────────┐\n│附表：                                                                                   98年度司催字第502號│\n├──┬───────┬────────┬──────┬──────────┬───────────┬────┤\n│編號│發    票    人│  付    款    人│發  票  日  │票    面    金    額│支     票     號    碼│備    考│\n│    │              │                │            │    ︵新台幣︶      │                      │        │\n├──┼───────┼────────┼──────┼──────────┼───────────┼────┤\n│001 │林吉妹      │華南商業銀行大眾│98年11月30日│2,600元             │SC0000000             │        │\n│    │              │分行            │            │                    │                      │        │\n├──┼───────┼────────┼──────┼──────────┼───────────┼────┤\n│002 │星光國際有限公│永豐商業銀行光華│99年1月5日  │546,901元           │AC0000000             │        │\n│    │司廖文權      │分行            │            │                    │                      │        │\n├──┼───────┼────────┼──────┼──────────┼───────────┼────┤\n│003 │萬濱企業有限公│臺灣銀行竹北分行│98年11月30日│33,465元            │AB0000000             │        │\n│    │司黃瓊徵      │                │            │                    │                      │        │\n├──┼───────┼────────┼──────┼──────────┼───────────┼────┤\n│004 │國際優水生活有│第一商業銀行竹東│98年12月31日│7,300元             │AA0000000             │        │\n│    │限公司羅志偉  │分行            │            │                    │                      │        │\n└──┴───────┴────────┴──────┴──────────┴───────────┴────┘",
  "structure": {
    "main": "附表所載之支票無效。\n訴訟費用由聲請人負擔。",
    "fact": "本件聲請意旨略以：聲請人執有附表所載之支票，因遺失而前經\n聲請本院以98年度司催字第502 號公示催告，並刊登新聞紙在案\n，現申報權利期間已滿，無人申報權利及提出原支票，為此聲請\n宣告該表所載支票無效。",
    "reason": "一、查附表所載之支票，經本院以98年度司催字第502 號公示催\n    告在案。\n二、所定申報權利期間已於民國99年4 月18日屆滿，迄今無人申\n    報權利及提出原支票，聲請人之聲請，應予准許。\n三、依民事訴訟法第564條第1項，判決如主文。\n中    華    民    國    99    年    5     月    12    日\n                              臺灣新竹地方法院民事第一庭\n                                      法  官  許翠玲\n以上正本係照原本作成。\n不得上訴。"
  },
  "characters": {
    "judges": [
      "許翠玲"
    ],
    "prosecutors": [

    ],
    "lawyers": [

    ],
    "clerks": [
      "陳思璟"
    ],
    "plaintiffs": [

    ],
    "defendants": [

    ],
    "prosecutor_office": [
      "豪山國際股份有限公司"
    ],
    "creditors": [

    ],
    "debtors": [

    ],
    "judicial_associate_officer": [

    ]
  },
  "adjudged_at": "2010-05-12",
  "created_at": "2016-01-05 12:46:03",
  "updated_at": "2016-01-05 12:46:03"
}