{
  "identify": "SCD-99-審竹交簡-370-20100512-1",
  "court": {
    "name": "臺灣新竹地方法院",
    "code": "SCD"
  },
  "division": {
    "name": "刑事",
    "code": "M"
  },
  "year": 99,
  "word": "審竹交簡",
  "number": "370",
  "jcheck": "1",
  "reason": "公共危險",
  "content": "臺灣新竹地方法院刑事簡易判決     99年度審竹交簡字第370號\n聲  請  人  臺灣新竹地方法院檢察署檢察官\n被      告  甲○○\n上列被告因公共危險案件，經檢察官聲請以簡易判決處刑（99年\n度偵字第2379號），本院判決如下：\n    主  文\n甲○○犯肇事致人傷害逃逸罪，處有期徒刑陸月，如易科罰金，\n以新臺幣壹仟元折算壹日。緩刑貳年，緩刑期內付保護管束，並\n應於判決確定後壹年內，向執行檢察官指定之政府機關、政府機\n構、行政法人、社區或其他符合公益目的之機構或團體，提供陸\n拾小時之義務勞務。\n    事實及證據\n一、本件犯罪事實及證據，除犯罪事實欄：「１、…（第8 行後\n    段）受有擦傷、下肢挫傷、臉部開放性傷口、頭皮及頸挫傷\n    等傷害（過失傷害部分，業據撤回告訴，另為不起訴處分）\n    …２、案經李秉畇訴由新竹市警察局第三分局報告偵辦。」\n    應予補充、更正外，餘均引用檢察官聲請簡易判決處刑書之\n    記載（如附件）。\n二、論罪及科刑：\n（一）論罪：被告甲○○所為，係犯刑法第185 條之4 之肇事致\n      人傷害逃逸罪。\n（二）科刑：\n  １、主刑：審酌被告駕駛自小客車肇事後，未採取即時之救護\n      作為，卻逃離現場，罔顧受傷者生命、身體安全，犯罪所\n      生之危害非輕，及被告犯後坦白承認犯行等一切情狀，量\n      處如主文所示之刑，並諭知易科罰金之折算標準，以示懲\n      儆。\n  ２、緩刑及付保護管束：被告前未曾因故意犯罪受有期徒刑以\n      上刑之宣告，此有臺灣高等法院被告前案紀錄表及刑案資\n      料查註紀錄表各1 份在卷可查，因一時失慮，致罹刑章，\n      經此偵查程序及科刑之教訓後，應已知所警惕，相信不會\n      再犯，本院綜核各情認上開刑之宣告，已足策其自新，所\n      宣告之刑，以暫不執行為適當，爰併予宣告緩刑2 年。再\n      被告受有教育且為一具有相當智識經驗之成年人，當能知\n      曉駕車肇事逃逸，將延誤對受傷之被害人即時救護之黃金\n      時間，大大提高傷勢加遽之危險，竟無視人身救治之急迫\n      ，足見其守法觀念有待加強，為使其習得正確之法律概念\n      ，並時刻記取駕車肇事後應對傷者採取適當之救護措拖，\n      有加強對被告追蹤、考核及輔導之必要；又為促使被告日\n      後得以知曉尊重法治，及為期被告於服務社會中得導正其\n      偏差行為與觀念，爰依刑法第74條第2 項第5 款之規定，\n      諭知被告應於判決確定後1 年內，向執行檢察官指定之政\n      府機關、政府機構、行政法人、社區或其他符合公益目的\n      之機構或團體，提供60小時之義務勞務，並依刑法第93條\n      第1 項第2 款諭知緩刑期內付保護管束，期能使被告於義\n      務勞務過程及保護管束期間，確切明瞭其行為之不當與危\n      險性，並培養正確法治觀念，相信如此，更能達到法律制\n      定之目的。至於被告究應向何政府機關、政府機構、行政\n      法人、社區或其他符合公益目的之機構或團體提供義務勞\n      務，屬執行之問題，應由執行檢察官斟酌全案情節及各政\n      府機關、政府機構、行政法人、社區或其他符合公益目的\n      之機構或團體之需求，妥為指定。再者，倘被告違反上開\n      所定負擔情節重大，足認原宣告之緩刑難收其預期效果，\n      而有執行刑罰之必要，依刑法第75條之1 第1 項第4 款規\n      定，得撤銷其緩刑之宣告，併此敘明。\n三、依刑事訴訟法第449 條第1 項前段、第450 條第1 項、第45\n    4 條第2 項，刑法第185 條之4 、第41條第1 項前段、第74\n    條第1 項第1 款、第2 項第5 款、第93條第1 項第2 款，逕\n    以簡易判決處刑如主文。\n四、如不服本件判決，得自收受送達之日起10日內，向本院提起\n    上訴。\n中    華    民    國    99    年    5     月    12    日\n                    新竹簡易庭法  官          馮俊郎\n以上正本證明與原本無異。\n中    華    民    國    99    年    5     月    12    日\n                              書記官          王思穎\n附錄本案論罪科刑實體法條全文：\n刑法第185 條之4 ：\n駕駛動力交通工具肇事，致人死傷而逃逸者，處6 月以上5 年以\n下有期徒刑。\n附件：\n臺灣新竹地方法院檢察署檢察官聲請簡易判決處刑書\n                                      99年度偵字第2379號\n    被      告  甲○○  男  46歲（民國○○年○○月○○日生）\n                        國民身分證統一編號：Ｚ000000000號\n                        住新竹縣竹北市○○路○段88巷88號\n                        居新竹市○區○○路90號6樓\n上列被告因公共危險案件，業經偵查終結，認為宜以簡易判決處\n刑，茲將犯罪事實及證據並所犯法條分敘如下：\n        犯罪事實\n１、甲○○於民國99年1月20日上午，駕駛車號號碼5490-TW號自\n    用小客車，沿新竹市○○路往振興路方向行駛，迨同日上午\n    6 時35分許，行經南大路近國立新竹教育大學校門前，應注\n    意車前狀況，隨時採取必要之安全措施，而依當時天候晴，\n    路面無缺陷、障礙物及視距良好等情狀，俱無不能注意之情\n    事，竟因精神不濟疏未注意由李秉畇所騎乘之車號 711-GKM\n    號重型機車正在前方行進，致所駕駛車輛撞擊李秉畇機車之\n    排氣管，使李秉畇因而人車倒地，受有擦傷、下肢挫傷、臉\n    部開放性傷口、頭皮及頸挫傷等傷害（過失傷害部分，業據\n    撤回告訴）。詎甲○○知悉其已肇事，應有使他人傷亡情事\n    ，竟於肇事致人成傷後，旋即駕駛車輛逃逸，嗣經警調取路\n    口監視器，始循線查獲上情。\n２、案經李秉畇訴由新竹市警察局第二分局報告偵辦。\n        證據並所犯法條\n１、證據：\n  (1)被告甲○○偵訊時之自白。\n  (2)告訴人李秉畇警詢及偵訊時之指訴。\n  (3)查獲警員製作之偵查報告1 紙。\n  (4)新竹市警察局交通隊道路交通事故現場圖、調查報告表(一)(二)\n    、現場及車損照片14張。\n  (5)新竹市○○○道路交通事故肇事人自首情形紀錄表。\n  (6)監視器攝錄影像翻拍照片2 張。\n  (7)新竹國泰綜合醫院診斷證明書。\n２、核被告所為，係犯刑法第185條之4之肇事逃逸罪嫌。\n３、依刑事訴訟法第451條第1項聲請逕以簡易判決處刑。\n    此    致\n臺灣新竹地方法院\n中    華    民    國    99    年    3     月    25    日\n                              檢 察 官    鄒 茂 瑜\n本件證明與原本無異\n中    華    民    國    99    年    4     月    2     日\n                              書 記 官    林 慧 菁\n所犯法條：\n中華民國刑法第185條之4\n（肇事遺棄罪）\n駕駛動力交通工具肇事，致人死傷而逃逸者，處6月以上5年以下\n有期徒刑。",
  "structure": {
    "main": "甲○○犯肇事致人傷害逃逸罪，處有期徒刑陸月，如易科罰金，\n以新臺幣壹仟元折算壹日。緩刑貳年，緩刑期內付保護管束，並\n應於判決確定後壹年內，向執行檢察官指定之政府機關、政府機\n構、行政法人、社區或其他符合公益目的之機構或團體，提供陸\n拾小時之義務勞務。\n    事實及證據\n一、本件犯罪事實及證據，除犯罪事實欄：「１、…（第8 行後\n    段）受有擦傷、下肢挫傷、臉部開放性傷口、頭皮及頸挫傷\n    等傷害（過失傷害部分，業據撤回告訴，另為不起訴處分）\n    …２、案經李秉畇訴由新竹市警察局第三分局報告偵辦。」\n    應予補充、更正外，餘均引用檢察官聲請簡易判決處刑書之\n    記載（如附件）。\n二、論罪及科刑：\n（一）論罪：被告甲○○所為，係犯刑法第185 條之4 之肇事致\n      人傷害逃逸罪。\n（二）科刑：\n  １、主刑：審酌被告駕駛自小客車肇事後，未採取即時之救護\n      作為，卻逃離現場，罔顧受傷者生命、身體安全，犯罪所\n      生之危害非輕，及被告犯後坦白承認犯行等一切情狀，量\n      處如主文所示之刑，並諭知易科罰金之折算標準，以示懲\n      儆。\n  ２、緩刑及付保護管束：被告前未曾因故意犯罪受有期徒刑以\n      上刑之宣告，此有臺灣高等法院被告前案紀錄表及刑案資\n      料查註紀錄表各1 份在卷可查，因一時失慮，致罹刑章，\n      經此偵查程序及科刑之教訓後，應已知所警惕，相信不會\n      再犯，本院綜核各情認上開刑之宣告，已足策其自新，所\n      宣告之刑，以暫不執行為適當，爰併予宣告緩刑2 年。再\n      被告受有教育且為一具有相當智識經驗之成年人，當能知\n      曉駕車肇事逃逸，將延誤對受傷之被害人即時救護之黃金\n      時間，大大提高傷勢加遽之危險，竟無視人身救治之急迫\n      ，足見其守法觀念有待加強，為使其習得正確之法律概念\n      ，並時刻記取駕車肇事後應對傷者採取適當之救護措拖，\n      有加強對被告追蹤、考核及輔導之必要；又為促使被告日\n      後得以知曉尊重法治，及為期被告於服務社會中得導正其\n      偏差行為與觀念，爰依刑法第74條第2 項第5 款之規定，\n      諭知被告應於判決確定後1 年內，向執行檢察官指定之政\n      府機關、政府機構、行政法人、社區或其他符合公益目的\n      之機構或團體，提供60小時之義務勞務，並依刑法第93條\n      第1 項第2 款諭知緩刑期內付保護管束，期能使被告於義\n      務勞務過程及保護管束期間，確切明瞭其行為之不當與危\n      險性，並培養正確法治觀念，相信如此，更能達到法律制\n      定之目的。至於被告究應向何政府機關、政府機構、行政\n      法人、社區或其他符合公益目的之機構或團體提供義務勞\n      務，屬執行之問題，應由執行檢察官斟酌全案情節及各政\n      府機關、政府機構、行政法人、社區或其他符合公益目的\n      之機構或團體之需求，妥為指定。再者，倘被告違反上開\n      所定負擔情節重大，足認原宣告之緩刑難收其預期效果，\n      而有執行刑罰之必要，依刑法第75條之1 第1 項第4 款規\n      定，得撤銷其緩刑之宣告，併此敘明。\n三、依刑事訴訟法第449 條第1 項前段、第450 條第1 項、第45\n    4 條第2 項，刑法第185 條之4 、第41條第1 項前段、第74\n    條第1 項第1 款、第2 項第5 款、第93條第1 項第2 款，逕\n    以簡易判決處刑如主文。\n四、如不服本件判決，得自收受送達之日起10日內，向本院提起\n    上訴。\n中    華    民    國    99    年    5     月    12    日\n                    新竹簡易庭法  官          馮俊郎\n以上正本證明與原本無異。\n中    華    民    國    99    年    5     月    12    日\n                              書記官          王思穎\n附錄本案論罪科刑實體法條全文：\n刑法第185 條之4 ：\n駕駛動力交通工具肇事，致人死傷而逃逸者，處6 月以上5 年以\n下有期徒刑。\n附件：\n臺灣新竹地方法院檢察署檢察官聲請簡易判決處刑書\n                                      99年度偵字第2379號\n    被      告  甲○○  男  46歲（民國○○年○○月○○日生）\n                        國民身分證統一編號：Ｚ000000000號\n                        住新竹縣竹北市○○路○段88巷88號\n                        居新竹市○區○○路90號6樓\n上列被告因公共危險案件，業經偵查終結，認為宜以簡易判決處\n刑，茲將犯罪事實及證據並所犯法條分敘如下：",
    "fact": "１、甲○○於民國99年1月20日上午，駕駛車號號碼5490-TW號自\n    用小客車，沿新竹市○○路往振興路方向行駛，迨同日上午\n    6 時35分許，行經南大路近國立新竹教育大學校門前，應注\n    意車前狀況，隨時採取必要之安全措施，而依當時天候晴，\n    路面無缺陷、障礙物及視距良好等情狀，俱無不能注意之情\n    事，竟因精神不濟疏未注意由李秉畇所騎乘之車號 711-GKM\n    號重型機車正在前方行進，致所駕駛車輛撞擊李秉畇機車之\n    排氣管，使李秉畇因而人車倒地，受有擦傷、下肢挫傷、臉\n    部開放性傷口、頭皮及頸挫傷等傷害（過失傷害部分，業據\n    撤回告訴）。詎甲○○知悉其已肇事，應有使他人傷亡情事\n    ，竟於肇事致人成傷後，旋即駕駛車輛逃逸，嗣經警調取路\n    口監視器，始循線查獲上情。\n２、案經李秉畇訴由新竹市警察局第二分局報告偵辦。\n        證據並所犯法條\n１、證據：\n  (1)被告甲○○偵訊時之自白。\n  (2)告訴人李秉畇警詢及偵訊時之指訴。\n  (3)查獲警員製作之偵查報告1 紙。\n  (4)新竹市警察局交通隊道路交通事故現場圖、調查報告表(一)(二)\n    、現場及車損照片14張。\n  (5)新竹市○○○道路交通事故肇事人自首情形紀錄表。\n  (6)監視器攝錄影像翻拍照片2 張。\n  (7)新竹國泰綜合醫院診斷證明書。\n２、核被告所為，係犯刑法第185條之4之肇事逃逸罪嫌。\n３、依刑事訴訟法第451條第1項聲請逕以簡易判決處刑。\n    此    致\n臺灣新竹地方法院"
  },
  "characters": {
    "judges": [
      "馮俊郎"
    ],
    "prosecutors": [

    ],
    "lawyers": [

    ],
    "clerks": [
      "王思穎"
    ],
    "plaintiffs": [

    ],
    "defendants": [
      "甲○○",
      "甲○○  男  46歲（民國○○年○○月○○日生）"
    ],
    "prosecutor_office": [
      "臺灣新竹地方法院檢察署檢察官"
    ],
    "creditors": [

    ],
    "debtors": [

    ],
    "judicial_associate_officer": [

    ]
  },
  "adjudged_at": "2010-05-12",
  "created_at": "2016-01-05 12:43:16",
  "updated_at": "2016-01-05 12:43:16"
}