{
  "identify": "SCD-99-選訴-8-20100512-4",
  "court": {
    "name": "臺灣新竹地方法院",
    "code": "SCD"
  },
  "division": {
    "name": "刑事",
    "code": "M"
  },
  "year": 99,
  "word": "選訴",
  "number": "8",
  "jcheck": "4",
  "reason": "違反選舉罷免法等",
  "content": "臺灣新竹地方法院刑事判決               99年度選訴字第8號\n公  訴  人  臺灣新竹地方法院檢察署察察官\n被      告  乙○○\n指定辯護人  朱昭勳律師\n上列被告因違反公職人員選舉罷免法案件，經檢察官提起公訴（\n98年度選偵字第32號），本院判決如下：\n    主  文\n乙○○犯公職人員選舉罷免法第九十九條第一項之交付賄賂罪，\n處有期徒刑壹年拾月，緩刑肆年。緩刑期間付保護管束。並應向\n國庫支付新臺幣拾萬元。褫奪公權貳年。未扣案如附表所示之賄\n賂均沒收。\n    事  實\n一、乙○○明知林思銘為98年新竹縣議會第17屆縣議員選舉第八\n    選區登記第3 號候選人，於民國98年12月5 日進行選舉投票\n    ，乙○○為期不知情之林思銘能順利當選，竟基於對於有投\n    票權之人，行求賄賂而約其投票權為一定行使之犯意，分別\n    為下列行為：\n    (一)於民國98年10月23日下午某時許，前往具有新竹縣議會第\n      17屆議員第八選區投票權人丙○○位於新竹縣竹東鎮○○\n      路310 巷25號住處，以每票新臺幣（下同）500 元代價，\n      交付2,000 元之賄款予丙○○（丙○○涉犯投票受賄罪部\n      分，另經本院判決有期徒刑3 月，緩刑2 年），約丙○○\n      及其不知情而具有投票權之家屬蔣玉蘭、林佩儀、林貞儀\n      共4 名，於此次縣議員選舉時投票予林思銘之一定行使，\n      丙○○當場將乙○○交付之2,000 元收受為賄賂，而許以\n      於此次竹東鎮選區議員選舉時投票予林思銘之一定行使，\n      惟事後丙○○並未將賄款轉交蔣玉蘭、林佩儀、林貞儀。\n    (二)復於同日下午某時許，前往具有新竹縣議會第17屆議員第\n      八選區投票權人甲○○設籍位於新竹縣竹東鎮○○路310\n      巷23號之住處，以每票500 元代價，交付1,000 元之賄款\n      予甲○○（甲○○涉犯投票受賄罪部分，另經本院判決有\n      期徒刑3 月，緩刑2 年），約甲○○及其不知情而具有投\n      票權之家屬沈瑞賓共2 名，於此次縣議員選舉時投票予林\n      思銘之一定行使，甲○○將乙○○當場交付之1,000 元收\n      受為賄賂，而許以於此次竹東鎮選區議員選舉時投票予林\n      思銘之一定行使，惟事後甲○○實際並未將賄款轉交沈瑞\n      賓。嗣經法務部調查局新竹縣調查站獲悉檢舉情資，經傳\n      喚丙○○、甲○○、乙○○到案，始循線查獲上情。\n二、案經新竹縣政府警察局竹東分局報告臺灣新竹地方法院檢察\n    署檢察官偵查起訴。\n    理  由\n壹、程序事項：\n    按被告以外之人於審判外之言詞或書面陳述，除法律有規定\n    者外，不得作為證據；又被告以外之人於審判外之陳述，雖\n    不符合同法第159條之1至第159條之4之規定，但經當事人於\n    審判程序同意作為證據，法院審酌該言詞陳述或書面陳述作\n    成時之情況，認為適當者，亦得為證據。當事人、代理人或\n    辯護人於法院調查證據時，知有第159條第1項不得為證據之\n    情形，而未於言詞辯論終結前聲明異議者，視為有前項之同\n    意，刑事訴訟法第159條第1項及第159條之5分別定有明文。\n    經查，本判決下列所引用之被告以外之人於審判外之陳述，\n    屬傳聞證據部分，檢察官、被告、辯護人於本院準備、審理\n    程序中均表示沒有意見，且迄於言詞辯論終結前亦未聲明異\n    議。本院審酌上開證據資料製作時之情況，尚無違法不當及\n    證明力明顯過低之瑕疵，亦認為以之作為證據應屬適當，故\n    揆諸前開規定，爰依刑事訴訟法第159 條之5 規定，認前揭\n    證據資料均有證據能力。\n貳、實體部分：\n一、訊據被告乙○○對於交付賄賂犯行坦認不諱，並有下列證據\n    可資為證：\n    (一)證人丙○○於警詢、偵查中證述：伊與被告係林姓宗親會\n      之會員，本次98年三合一選舉伊有投票權，伊家共有4 票\n      。被告於98年10月20日打電話向伊表示，宗親要支持一下\n      ，因為本次只有林思銘一位宗親出來參選，所以被告說縣\n      議員要支持宗親林思銘。被告打完電話隔2 、3 天後，被\n      告1 個人親自來伊家，拿現金2,000 元（2 張千元大鈔）\n      ，每票500 元，向伊表示要支持宗親，伊當時有向被告表\n      示好等語（見98選他120 偵查卷第9-10頁、第15-16 頁）\n      。\n    (二)證人甲○○於警詢、偵查中證述：伊具有98年12月5 日新\n      竹縣第17屆縣議員竹東鎮選區選舉投票權，在伊戶籍內有\n      投票權之選舉人有2 人。伊知道這次選舉林思銘有出來參\n      選縣議員。伊有參加林姓宗親會，但自從8 年前伊先生往\n      生後，伊就沒有參加。大約1 個月前的一個傍晚，被告突\n      然來伊家中拜訪，問伊家中有幾票，伊回答被告有2 票，\n      是伊跟伊妹妹兒子，被告就拿1,000 元給伊，並叫伊在此\n      次縣議員選舉中投票給林思銘，伊有收下等語（見同上偵\n      查卷第6-7 頁、第14-15 頁）。\n    (三)並有臺灣省新竹縣議會第17屆議員選舉選舉公報、證人丙\n      ○○及其家人蔣玉蘭、林佩儀、林貞儀等全戶戶籍資料查\n      詢結果單7 紙、證人甲○○及其家人沈瑞賓全戶戶籍資料\n      查詢結果單2 紙（見98選偵32偵查卷第33-34 頁、本院卷\n      第76-82 頁、第45-46 頁）附卷可憑。\n    (四)足見被告將賄賂現金2,000 元、1,000 元分別交付證人丙\n      ○○、甲○○，而約其等及其餘具有投票權之家人，於98\n      年新竹縣議會第17屆縣議員選舉投票予第八選區3 號候選\n      人林思銘時，證人丙○○、甲○○對於被告交付前開金錢\n      目的已然認識而予收受，益徵其等有受賄意思而予收受，\n      應堪認定。\n    (五)是認被告上開自白與事實相符，而堪採信。\n    (六)綜上所述，本件事證明確，被告交付賄賂罪之犯行，洵堪\n      認定，應予依法論罪科刑。\n二、論罪科刑部分：\n    (一)按投票行賄罪之處罰分別規定於刑法第144 條及公職人員\n      選舉罷免法第99條第1 項，而本件係公職人員選舉罷免法\n      第2 條所規定之地方公職人員選舉，公職人員選舉罷免法\n      第99條第1 項自屬刑法第144 條之特別法，依特別法優於\n      普通法之規定，應優先適用公職人員選舉罷免法。次按公\n      職人員選舉罷免法第99條第1 項之賄選罪，以對於有投票\n      權之人，行求、期約或交付賄賂或其他不正利益，而約其\n      不行使投票權或為一定之行使者為構成要件，其行求、期\n      約、交付行為，係屬階段行為，其行求賄賂階段，屬行賄\n      者單方意思表示行為，不以相對人允諾為必要；而交付賄\n      賂階段，則以行賄者已實施交付賄賂之行為，一經交付，\n      罪即成立，雖不以收受者確已承諾，或進而為一定投票權\n      之行使為必要，但仍以收受者已收受，而有受賄意思者為\n      限（最高法院93年度台上字第5802號、93年度台上字第26\n      72號判決意旨可參）。\n    (二)被告以每票500 元之代價，交付予具有投票權之丙○○（\n      戶籍內共有4 票，合計交付2,000 元）、甲○○（戶籍內\n      共有2 票，合計交付1,000 元），證人丙○○、甲○○等\n      人亦知悉被告交付款項之意涵，已如前述，綜合社會價值\n      觀念、授受雙方之認知及其交付現金之客觀情狀以觀，足\n      認該現金之交付、收受與投票權為一定行使間，具有對價\n      關係。核被告對丙○○、甲○○行賄部分，係犯公職人員\n      選舉罷免法第99條第1 項之對於有投票權之人，交付賄賂\n      ，而約其投票權為一定之行使罪。\n    (三)再公職人員選舉罷免法之投票行賄罪係侵害國家法益之罪\n      ，以一行為同時對多數有投票權之人交付賄賂，約其不行\n      使投票權或為一定之行使，祇侵害一個國家法益，應僅成\n      立一投票行賄罪，已據前述。而該罪之預備犯，僅止於該\n      罪著手實行前之準備階段，嗣若進而實行行賄之行為，即\n      為行賄所吸收，不另論罪。則以一行為同時對多數有投票\n      權人行賄，尚且論以一罪，其以一行為同時對多數有投票\n      權之人部分賄選，部分尚在預備賄選階段，尤僅能論以一\n      罪。本件被告乙○○分別對丙○○、甲○○行賄之同時，\n      併託其等轉達被告行賄之意思及轉交賄款，而同時對彼等\n      本人行賄及預備對其等家屬多人行賄，即認被告係以一行\n      為同時實行賄選及預備賄選，自應論以一投票行賄罪。\n    (四)又所稱之集合犯，係一種構成要件類型，亦即立法者針對\n      特定刑罰規範之構成要件，已預設其本身係持續實行之複\n      次行為，具備反覆、延續之行為特徵，將之總括或擬制成\n      一個構成要件之『集合犯』行為；此種犯罪，以反覆實行\n      為典型、常態之行為方式，具侵害法益之同一性，因刑法\n      評價上為構成要件之行為單數，因而僅包括的成立一罪。\n      其與接續犯之不同，在於接續犯所適用之構成要件行為文\n      義本身並不具反覆實行之特質，非屬立法規範所定之構成\n      犯為嚴格。是除集合犯外，每一種構成要件行為皆得以接\n      續犯方式為之，因此集合犯亦有喻之為『法定接續犯』者\n      。此與修正前連續犯係指行為人在主觀上基於一個概括之\n      犯意，而反覆實行客觀上可以獨立成罪之同一罪名之行為\n      者，均尚屬有間。公職人員選舉罷免法第99第1 項所定之\n      對有投票權人交付賄賂或不正利益罪之賄選行為，乃行為\n      人基於足以讓候選人當選票數之賄選目的，反覆向多數人\n      交付賄賂或其他不正利益，約定不行使投票權或為一定行\n      使；是對有投票權人交付賄賂或其他不正利益之犯行，於\n      構成要件類型上，本質上已具備反覆、延續之行為特徵，\n      其持續多次對有投票權人交付賄賂或其他不正利益即為此\n      類犯罪之典型或常態，於刑法評價上自應僅成立集合犯一\n      罪。被告乙○○對於有投票權之證人丙○○、甲○○等2\n      人分別交付賄賂，而約其等投票權為一定之行使2 次犯行\n      ，即應論以集合犯之交付賄賂一罪。\n    (五)爰審酌選舉乃民主政治最重要之表徵，須由選民評斷候選\n      人之才德、品行、學識、操守、政見而選賢與能，其攸關\n      國家政治之良窳甚鉅，而賄選為敗壞選風之主要根源，不\n      惟抹滅實行民主政治之真意，亦影響選舉之公正性與社會\n      之風氣，扭曲選舉制度尋求民意之真實性，本件被告為支\n      持候選人林思銘，竟未循正常方式，以行求賄賂為賄選之\n      手段，妨害投票之公正、公平及純潔，固不可取，惟被告\n      僅行賄丙○○、甲○○及其家人、行賄金額不多、影響選\n      情甚微、年紀非輕、且被告為中度肢障人士，謀生不易，\n      而屬低收入戶，亦有新竹縣竹東鎮公所低收入戶證明書、\n      中華民國殘障手冊（本院卷第56、58頁），在卷可憑，因\n      思及與候選人林思銘具宗親之誼，而欲藉由此次選舉活動\n      如林思銘日後順利當選，能向林思銘謀取工作之犯罪具體\n      情狀，確屬情輕法重，客觀上足以引起社會一般人之同情\n      ，本院基於衡平原則，認為處以法定最輕刑度猶嫌過重，\n      是其犯罪之情狀顯堪憫恕，爰依刑法第59條之規定，酌量\n      減輕其刑。併審酌被告於本院坦承犯行之態度，國小畢業\n      智識程度、擔任油漆之工作等一切情狀，量處如主文所示\n      之刑。末查被告未曾因故意犯有期徒刑以上之刑之宣告，\n      有臺灣高等法院被告前案紀錄表在卷可徵，被告因一時失\n      慮，致罹刑典，事後已具悔意，經此教訓，當知所警惕，\n      本院認其所宣告之刑以暫不執行為適當，爰諭知緩刑4 年\n      ，以啟自新。再為期其能導正其觀念，爰依刑法第93條第\n      1 項規定，於緩刑期間付保護管束。\n    (六)另緩刑宣告，得斟酌情形，命犯罪行為人為下列各款事項\n      ：(一)向被害人道歉。(二)立悔過書。(三)向被害人支付相當數\n      額之財產或非財產上之損害賠償。(四)向公庫支付一定之金\n      額。(五)向指定之公益團體、地方自治團體或社區提供40小\n      時以上240 小時以下之義務勞務(六)完成戒癮治療、精神治\n      療、心理輔導或其他適當之處遇措施。(七)保護被害人安全\n      之必要命令。(八)預防再犯所為之必要命令。參酌被告辯護\n      人具狀表明被告願捐款國庫之陳述，併依刑法第74條第2\n      項第4 款之規定，命其應向公庫支付10萬元，以啟自新。\n      又刑法第74條第4 項規定，前開支付之負擔得為民事強制\n      執行名義，倘被告不履行，且情節重大，足認原宣告之緩\n      刑難收其預期效果，而有執行刑罰之必要者，依刑法第75\n      條之1 第1 項第4 款規定，得撤銷其緩刑宣告，附此敘明\n      。\n    (七)公職人員選舉罷免法第113 條第3 項規定：「犯本章之罪\n      或刑法分則第六章之妨害投票罪，宣告有期徒刑以上之刑\n      者，並宣告褫奪公權。」，惟該法並未規定褫奪公權宣告\n      之期間標準，而公職人員選舉罷免法為刑法之特別法，刑\n      法總則除於其他法令有特別規定外，亦適用之，故褫奪公\n      權之宣告即應適用刑法第37條第2 項之規定。本件被告既\n      經判處有期徒刑以上之刑，應依法諭知被告褫奪公權2 年\n      。\n三、沒收部分：\n    (一)按公職人員選舉罷免法第99條第3 項規定：預備或用以行\n      求期約或交付之賄賂，不問屬於犯人與否，沒收之，係刑\n      法第38條第1 項第2 款、第3 項但書之特別規定，採義務\n      沒收主義，故苟能證明係預備或用以行求期約或交付之賄\n      賂，不問屬於犯人與否，均應宣告沒收，不以當場搜獲扣\n      押者為限。是未扣案用以交付之如附表所示之賄賂，應依\n      現行公職人員選舉罷免法第99條第3 項之規定諭知沒收。\n    (二)另如其賄賂已交付予有投票權之人收受，因收受者係犯刑\n      法第143 條第1 項之投票受賄罪，其收受之賄賂應依同法\n      條第2 項之規定沒收之，如全部或一部不能沒收時，追徵\n      其價額。故犯投票行賄罪者，其已交付之賄賂，自應依刑\n      法第143 條第2 項之規定，於其對向共犯所犯投票受賄罪\n      之從刑宣告追徵、沒收，不得再依上開規定沒收。故被告\n      交付丙○○、甲○○之賄賂各500 元，自不得再依現行公\n      職人員選舉罷免法第99條第3 項規定，於本案被告項下為\n      沒收之諭知，附此敘明。\n據上論斷，應依刑事訴訟法第299 條第1 項前段，公職人員選舉\n罷免法第99條第1 項、第3 項、第113 條第3 項，刑法第11條前\n段、第37條第2 項、第59條、第74條第1 項第1 款、第2 項第4\n款、第93條第1 項，判決如主文。\n本案經檢察官陳宏兆到庭執行職務。\n中    華    民    國    99    年    5     月    12    日\n                  刑事第四庭    審判長法  官    黃美文\n                                      法  官    朱美璘\n                                      法  官    邱玉汝\n以上正本證明與原本無異。\n如不服本判決應於收受判決後10日內向本院提出上訴書狀，並應\n敘述具體理由。其未敘述上訴理由者，應於上訴期間屆滿後20日\n內向本院補提理由書(均須按他造當事人之人數附繕本)「切勿逕\n送上級法院」。\n中    華    民    國    99    年    5     月    12    日\n                                      書記官    陳怡芳\n附錄本案論罪科刑法條：\n公職人員選舉罷免法第99條：\n對於有投票權之人，行求期約或交付賄賂或其他不正利益，而約\n其不行使投票權或為一定之行使者，處三年以上十年以下有期徒\n刑，得併科新臺幣一百萬元以上一千萬元以下罰金。\n預備犯前項之罪者，處一年以下有期徒刑。\n預備或用以行求期約或交付之賄賂，不問屬於犯人與否，沒收之\n。\n犯第一項或第二項之罪，於犯罪後六個月內自首者，減輕或免除\n其刑；因而查獲候選人為正犯或共犯者，免除其刑。\n犯第一項或第二項之罪，在偵查中自白者，減輕其刑；因而查獲\n候選人為正犯或共犯者，減輕或免除其刑。\n附表：\n┌──┬────────────┬────────────┐\n│編號│賄  賂  對  象          │匯款金額（新臺幣）      │\n├──┼────────────┼────────────┤\n│ 1  │蔣玉蘭、林佩儀、林貞儀  │共計1,500元（每位500元）│\n├──┼────────────┼────────────┤\n│ 2  │沈瑞賓                  │500元                   │\n└──┴────────────┴────────────┘",
  "structure": {
    "main": "乙○○犯公職人員選舉罷免法第九十九條第一項之交付賄賂罪，\n處有期徒刑壹年拾月，緩刑肆年。緩刑期間付保護管束。並應向\n國庫支付新臺幣拾萬元。褫奪公權貳年。未扣案如附表所示之賄\n賂均沒收。",
    "fact": "一、乙○○明知林思銘為98年新竹縣議會第17屆縣議員選舉第八\n    選區登記第3 號候選人，於民國98年12月5 日進行選舉投票\n    ，乙○○為期不知情之林思銘能順利當選，竟基於對於有投\n    票權之人，行求賄賂而約其投票權為一定行使之犯意，分別\n    為下列行為：\n    (一)於民國98年10月23日下午某時許，前往具有新竹縣議會第\n      17屆議員第八選區投票權人丙○○位於新竹縣竹東鎮○○\n      路310 巷25號住處，以每票新臺幣（下同）500 元代價，\n      交付2,000 元之賄款予丙○○（丙○○涉犯投票受賄罪部\n      分，另經本院判決有期徒刑3 月，緩刑2 年），約丙○○\n      及其不知情而具有投票權之家屬蔣玉蘭、林佩儀、林貞儀\n      共4 名，於此次縣議員選舉時投票予林思銘之一定行使，\n      丙○○當場將乙○○交付之2,000 元收受為賄賂，而許以\n      於此次竹東鎮選區議員選舉時投票予林思銘之一定行使，\n      惟事後丙○○並未將賄款轉交蔣玉蘭、林佩儀、林貞儀。\n    (二)復於同日下午某時許，前往具有新竹縣議會第17屆議員第\n      八選區投票權人甲○○設籍位於新竹縣竹東鎮○○路310\n      巷23號之住處，以每票500 元代價，交付1,000 元之賄款\n      予甲○○（甲○○涉犯投票受賄罪部分，另經本院判決有\n      期徒刑3 月，緩刑2 年），約甲○○及其不知情而具有投\n      票權之家屬沈瑞賓共2 名，於此次縣議員選舉時投票予林\n      思銘之一定行使，甲○○將乙○○當場交付之1,000 元收\n      受為賄賂，而許以於此次竹東鎮選區議員選舉時投票予林\n      思銘之一定行使，惟事後甲○○實際並未將賄款轉交沈瑞\n      賓。嗣經法務部調查局新竹縣調查站獲悉檢舉情資，經傳\n      喚丙○○、甲○○、乙○○到案，始循線查獲上情。\n二、案經新竹縣政府警察局竹東分局報告臺灣新竹地方法院檢察\n    署檢察官偵查起訴。",
    "reason": "壹、程序事項：\n    按被告以外之人於審判外之言詞或書面陳述，除法律有規定\n    者外，不得作為證據；又被告以外之人於審判外之陳述，雖\n    不符合同法第159條之1至第159條之4之規定，但經當事人於\n    審判程序同意作為證據，法院審酌該言詞陳述或書面陳述作\n    成時之情況，認為適當者，亦得為證據。當事人、代理人或\n    辯護人於法院調查證據時，知有第159條第1項不得為證據之\n    情形，而未於言詞辯論終結前聲明異議者，視為有前項之同\n    意，刑事訴訟法第159條第1項及第159條之5分別定有明文。\n    經查，本判決下列所引用之被告以外之人於審判外之陳述，\n    屬傳聞證據部分，檢察官、被告、辯護人於本院準備、審理\n    程序中均表示沒有意見，且迄於言詞辯論終結前亦未聲明異\n    議。本院審酌上開證據資料製作時之情況，尚無違法不當及\n    證明力明顯過低之瑕疵，亦認為以之作為證據應屬適當，故\n    揆諸前開規定，爰依刑事訴訟法第159 條之5 規定，認前揭\n    證據資料均有證據能力。\n貳、實體部分：\n一、訊據被告乙○○對於交付賄賂犯行坦認不諱，並有下列證據\n    可資為證：\n    (一)證人丙○○於警詢、偵查中證述：伊與被告係林姓宗親會\n      之會員，本次98年三合一選舉伊有投票權，伊家共有4 票\n      。被告於98年10月20日打電話向伊表示，宗親要支持一下\n      ，因為本次只有林思銘一位宗親出來參選，所以被告說縣\n      議員要支持宗親林思銘。被告打完電話隔2 、3 天後，被\n      告1 個人親自來伊家，拿現金2,000 元（2 張千元大鈔）\n      ，每票500 元，向伊表示要支持宗親，伊當時有向被告表\n      示好等語（見98選他120 偵查卷第9-10頁、第15-16 頁）\n      。\n    (二)證人甲○○於警詢、偵查中證述：伊具有98年12月5 日新\n      竹縣第17屆縣議員竹東鎮選區選舉投票權，在伊戶籍內有\n      投票權之選舉人有2 人。伊知道這次選舉林思銘有出來參\n      選縣議員。伊有參加林姓宗親會，但自從8 年前伊先生往\n      生後，伊就沒有參加。大約1 個月前的一個傍晚，被告突\n      然來伊家中拜訪，問伊家中有幾票，伊回答被告有2 票，\n      是伊跟伊妹妹兒子，被告就拿1,000 元給伊，並叫伊在此\n      次縣議員選舉中投票給林思銘，伊有收下等語（見同上偵\n      查卷第6-7 頁、第14-15 頁）。\n    (三)並有臺灣省新竹縣議會第17屆議員選舉選舉公報、證人丙\n      ○○及其家人蔣玉蘭、林佩儀、林貞儀等全戶戶籍資料查\n      詢結果單7 紙、證人甲○○及其家人沈瑞賓全戶戶籍資料\n      查詢結果單2 紙（見98選偵32偵查卷第33-34 頁、本院卷\n      第76-82 頁、第45-46 頁）附卷可憑。\n    (四)足見被告將賄賂現金2,000 元、1,000 元分別交付證人丙\n      ○○、甲○○，而約其等及其餘具有投票權之家人，於98\n      年新竹縣議會第17屆縣議員選舉投票予第八選區3 號候選\n      人林思銘時，證人丙○○、甲○○對於被告交付前開金錢\n      目的已然認識而予收受，益徵其等有受賄意思而予收受，\n      應堪認定。\n    (五)是認被告上開自白與事實相符，而堪採信。\n    (六)綜上所述，本件事證明確，被告交付賄賂罪之犯行，洵堪\n      認定，應予依法論罪科刑。\n二、論罪科刑部分：\n    (一)按投票行賄罪之處罰分別規定於刑法第144 條及公職人員\n      選舉罷免法第99條第1 項，而本件係公職人員選舉罷免法\n      第2 條所規定之地方公職人員選舉，公職人員選舉罷免法\n      第99條第1 項自屬刑法第144 條之特別法，依特別法優於\n      普通法之規定，應優先適用公職人員選舉罷免法。次按公\n      職人員選舉罷免法第99條第1 項之賄選罪，以對於有投票\n      權之人，行求、期約或交付賄賂或其他不正利益，而約其\n      不行使投票權或為一定之行使者為構成要件，其行求、期\n      約、交付行為，係屬階段行為，其行求賄賂階段，屬行賄\n      者單方意思表示行為，不以相對人允諾為必要；而交付賄\n      賂階段，則以行賄者已實施交付賄賂之行為，一經交付，\n      罪即成立，雖不以收受者確已承諾，或進而為一定投票權\n      之行使為必要，但仍以收受者已收受，而有受賄意思者為\n      限（最高法院93年度台上字第5802號、93年度台上字第26\n      72號判決意旨可參）。\n    (二)被告以每票500 元之代價，交付予具有投票權之丙○○（\n      戶籍內共有4 票，合計交付2,000 元）、甲○○（戶籍內\n      共有2 票，合計交付1,000 元），證人丙○○、甲○○等\n      人亦知悉被告交付款項之意涵，已如前述，綜合社會價值\n      觀念、授受雙方之認知及其交付現金之客觀情狀以觀，足\n      認該現金之交付、收受與投票權為一定行使間，具有對價\n      關係。核被告對丙○○、甲○○行賄部分，係犯公職人員\n      選舉罷免法第99條第1 項之對於有投票權之人，交付賄賂\n      ，而約其投票權為一定之行使罪。\n    (三)再公職人員選舉罷免法之投票行賄罪係侵害國家法益之罪\n      ，以一行為同時對多數有投票權之人交付賄賂，約其不行\n      使投票權或為一定之行使，祇侵害一個國家法益，應僅成\n      立一投票行賄罪，已據前述。而該罪之預備犯，僅止於該\n      罪著手實行前之準備階段，嗣若進而實行行賄之行為，即\n      為行賄所吸收，不另論罪。則以一行為同時對多數有投票\n      權人行賄，尚且論以一罪，其以一行為同時對多數有投票\n      權之人部分賄選，部分尚在預備賄選階段，尤僅能論以一\n      罪。本件被告乙○○分別對丙○○、甲○○行賄之同時，\n      併託其等轉達被告行賄之意思及轉交賄款，而同時對彼等\n      本人行賄及預備對其等家屬多人行賄，即認被告係以一行\n      為同時實行賄選及預備賄選，自應論以一投票行賄罪。\n    (四)又所稱之集合犯，係一種構成要件類型，亦即立法者針對\n      特定刑罰規範之構成要件，已預設其本身係持續實行之複\n      次行為，具備反覆、延續之行為特徵，將之總括或擬制成\n      一個構成要件之『集合犯』行為；此種犯罪，以反覆實行\n      為典型、常態之行為方式，具侵害法益之同一性，因刑法\n      評價上為構成要件之行為單數，因而僅包括的成立一罪。\n      其與接續犯之不同，在於接續犯所適用之構成要件行為文\n      義本身並不具反覆實行之特質，非屬立法規範所定之構成\n      犯為嚴格。是除集合犯外，每一種構成要件行為皆得以接\n      續犯方式為之，因此集合犯亦有喻之為『法定接續犯』者\n      。此與修正前連續犯係指行為人在主觀上基於一個概括之\n      犯意，而反覆實行客觀上可以獨立成罪之同一罪名之行為\n      者，均尚屬有間。公職人員選舉罷免法第99第1 項所定之\n      對有投票權人交付賄賂或不正利益罪之賄選行為，乃行為\n      人基於足以讓候選人當選票數之賄選目的，反覆向多數人\n      交付賄賂或其他不正利益，約定不行使投票權或為一定行\n      使；是對有投票權人交付賄賂或其他不正利益之犯行，於\n      構成要件類型上，本質上已具備反覆、延續之行為特徵，\n      其持續多次對有投票權人交付賄賂或其他不正利益即為此\n      類犯罪之典型或常態，於刑法評價上自應僅成立集合犯一\n      罪。被告乙○○對於有投票權之證人丙○○、甲○○等2\n      人分別交付賄賂，而約其等投票權為一定之行使2 次犯行\n      ，即應論以集合犯之交付賄賂一罪。\n    (五)爰審酌選舉乃民主政治最重要之表徵，須由選民評斷候選\n      人之才德、品行、學識、操守、政見而選賢與能，其攸關\n      國家政治之良窳甚鉅，而賄選為敗壞選風之主要根源，不\n      惟抹滅實行民主政治之真意，亦影響選舉之公正性與社會\n      之風氣，扭曲選舉制度尋求民意之真實性，本件被告為支\n      持候選人林思銘，竟未循正常方式，以行求賄賂為賄選之\n      手段，妨害投票之公正、公平及純潔，固不可取，惟被告\n      僅行賄丙○○、甲○○及其家人、行賄金額不多、影響選\n      情甚微、年紀非輕、且被告為中度肢障人士，謀生不易，\n      而屬低收入戶，亦有新竹縣竹東鎮公所低收入戶證明書、\n      中華民國殘障手冊（本院卷第56、58頁），在卷可憑，因\n      思及與候選人林思銘具宗親之誼，而欲藉由此次選舉活動\n      如林思銘日後順利當選，能向林思銘謀取工作之犯罪具體\n      情狀，確屬情輕法重，客觀上足以引起社會一般人之同情\n      ，本院基於衡平原則，認為處以法定最輕刑度猶嫌過重，\n      是其犯罪之情狀顯堪憫恕，爰依刑法第59條之規定，酌量\n      減輕其刑。併審酌被告於本院坦承犯行之態度，國小畢業\n      智識程度、擔任油漆之工作等一切情狀，量處如主文所示\n      之刑。末查被告未曾因故意犯有期徒刑以上之刑之宣告，\n      有臺灣高等法院被告前案紀錄表在卷可徵，被告因一時失\n      慮，致罹刑典，事後已具悔意，經此教訓，當知所警惕，\n      本院認其所宣告之刑以暫不執行為適當，爰諭知緩刑4 年\n      ，以啟自新。再為期其能導正其觀念，爰依刑法第93條第\n      1 項規定，於緩刑期間付保護管束。\n    (六)另緩刑宣告，得斟酌情形，命犯罪行為人為下列各款事項\n      ：(一)向被害人道歉。(二)立悔過書。(三)向被害人支付相當數\n      額之財產或非財產上之損害賠償。(四)向公庫支付一定之金\n      額。(五)向指定之公益團體、地方自治團體或社區提供40小\n      時以上240 小時以下之義務勞務(六)完成戒癮治療、精神治\n      療、心理輔導或其他適當之處遇措施。(七)保護被害人安全\n      之必要命令。(八)預防再犯所為之必要命令。參酌被告辯護\n      人具狀表明被告願捐款國庫之陳述，併依刑法第74條第2\n      項第4 款之規定，命其應向公庫支付10萬元，以啟自新。\n      又刑法第74條第4 項規定，前開支付之負擔得為民事強制\n      執行名義，倘被告不履行，且情節重大，足認原宣告之緩\n      刑難收其預期效果，而有執行刑罰之必要者，依刑法第75\n      條之1 第1 項第4 款規定，得撤銷其緩刑宣告，附此敘明\n      。\n    (七)公職人員選舉罷免法第113 條第3 項規定：「犯本章之罪\n      或刑法分則第六章之妨害投票罪，宣告有期徒刑以上之刑\n      者，並宣告褫奪公權。」，惟該法並未規定褫奪公權宣告\n      之期間標準，而公職人員選舉罷免法為刑法之特別法，刑\n      法總則除於其他法令有特別規定外，亦適用之，故褫奪公\n      權之宣告即應適用刑法第37條第2 項之規定。本件被告既\n      經判處有期徒刑以上之刑，應依法諭知被告褫奪公權2 年\n      。\n三、沒收部分：\n    (一)按公職人員選舉罷免法第99條第3 項規定：預備或用以行\n      求期約或交付之賄賂，不問屬於犯人與否，沒收之，係刑\n      法第38條第1 項第2 款、第3 項但書之特別規定，採義務\n      沒收主義，故苟能證明係預備或用以行求期約或交付之賄\n      賂，不問屬於犯人與否，均應宣告沒收，不以當場搜獲扣\n      押者為限。是未扣案用以交付之如附表所示之賄賂，應依\n      現行公職人員選舉罷免法第99條第3 項之規定諭知沒收。\n    (二)另如其賄賂已交付予有投票權之人收受，因收受者係犯刑\n      法第143 條第1 項之投票受賄罪，其收受之賄賂應依同法\n      條第2 項之規定沒收之，如全部或一部不能沒收時，追徵\n      其價額。故犯投票行賄罪者，其已交付之賄賂，自應依刑\n      法第143 條第2 項之規定，於其對向共犯所犯投票受賄罪\n      之從刑宣告追徵、沒收，不得再依上開規定沒收。故被告\n      交付丙○○、甲○○之賄賂各500 元，自不得再依現行公\n      職人員選舉罷免法第99條第3 項規定，於本案被告項下為\n      沒收之諭知，附此敘明。\n據上論斷，應依刑事訴訟法第299 條第1 項前段，公職人員選舉\n罷免法第99條第1 項、第3 項、第113 條第3 項，刑法第11條前\n段、第37條第2 項、第59條、第74條第1 項第1 款、第2 項第4\n款、第93條第1 項，判決如主文。\n本案經檢察官陳宏兆到庭執行職務。\n中    華    民    國    99    年    5     月    12    日\n                  刑事第四庭    審判長法  官    黃美文\n                                      法  官    朱美璘\n                                      法  官    邱玉汝\n以上正本證明與原本無異。\n如不服本判決應於收受判決後10日內向本院提出上訴書狀，並應\n敘述具體理由。其未敘述上訴理由者，應於上訴期間屆滿後20日\n內向本院補提理由書(均須按他造當事人之人數附繕本)「切勿逕\n送上級法院」。"
  },
  "characters": {
    "judges": [
      "黃美文",
      "朱美璘",
      "邱玉汝"
    ],
    "prosecutors": [
      "陳宏兆"
    ],
    "lawyers": [
      "朱昭勳"
    ],
    "clerks": [
      "陳怡芳"
    ],
    "plaintiffs": [

    ],
    "defendants": [
      "乙○○"
    ],
    "prosecutor_office": [
      "臺灣新竹地方法院檢察署察察官"
    ],
    "creditors": [

    ],
    "debtors": [

    ],
    "judicial_associate_officer": [

    ]
  },
  "adjudged_at": "2010-05-12",
  "created_at": "2016-01-05 12:42:38",
  "updated_at": "2016-01-05 12:42:38"
}