{
  "identify": "SLD-99-撤緩-77-20100512-1",
  "court": {
    "name": "臺灣士林地方法院",
    "code": "SLD"
  },
  "division": {
    "name": "刑事",
    "code": "M"
  },
  "year": 99,
  "word": "撤緩",
  "number": "77",
  "jcheck": "1",
  "reason": "撤銷緩刑",
  "content": "臺灣士林地方法院刑事裁定              99年度撤緩字第77號\n聲  請  人  臺灣士林地方法院檢察署檢察官\n被      告  甲○○\n上列聲請人因受刑人即被告恐嚇危害安全案件，聲請撤銷緩刑之\n宣告（99年度執聲字第489 號），本院裁定如下：\n    主  文\n聲請駁回。\n    理  由\n一、聲請意旨略稱：受刑人甲○○因犯背信案件，經臺灣高等法\n    院於民國99年2 月10日以98年度上易字第3000號（92年度偵\n    字第2246號）判決判處有期徒刑1 年8 月，緩刑3 年，於99\n    年2 月10日確定在案。惟受刑人於緩刑期前即97年12月9 日\n    及同年12月29日因更犯恐嚇危害安全罪，經本院於99年1 月\n    29日以98年度訴字第270 號判決分別判處有期徒刑4 月、3\n    月、4 月，如易科罰金均以新臺幣（下同）1 千元折算1 日\n    ，應執行有期徒刑10月，如易科罰金以1 千元折算1 日，並\n    經臺灣高等法院以99年度上訴字第1175號判決駁回上訴，於\n    99 年3月31日確定，已足認原宣告之緩刑難收其預期效果，\n    合於刑法第75條之1 第1 項第1 款所定撤銷緩刑宣告之原因\n    ，爰依刑事訴訟法第476 條規定聲請撤銷緩刑。\n二、按受緩刑之宣告，於緩刑前因故意犯他罪，而在緩刑期內受\n    得易科罰金之有期徒刑、拘役或罰金之宣告確定，足認原宣\n    告之緩刑難收其預期效果，而有執行刑罰之必要者，得撤銷\n    其宣告，刑法第75條之1 第1 項第1 款固定有明文。惟被告\n    受緩刑宣告後，如欲撤銷其緩刑宣告，除需被告合於刑法第\n    75條之1 第1 項所規定之4 款法定事由外，尚須以「足認原\n    宣告之緩刑難收其預期效果，而有執行刑罰之必要者」，法\n    院始得依職權裁量撤銷之。本條採用裁量撤銷主義，賦予法\n    院撤銷與否之權限，特於第1 項規定實質要件為「足認原宣\n    告之緩刑難收其預期效果，而有執行刑罰之必要」，供作審\n    認之標準。亦即於上揭「得」撤銷緩刑之情形，法官應依職\n    權本於合目的性之裁量，妥適審酌被告所犯前後數罪間，關\n    於法益侵害之性質、再犯之原因、違反法規範之情節是否重\n    大、被告主觀犯意所顯現之惡性及其反社會性等情，是否已\n    使前案原為促使惡性輕微之被告或偶發犯、初犯改過自新而\n    宣告之緩刑，已難收其預期之效果，而確有執行刑罰之必要\n    ，此與刑法第75條第1 項所定2 款要件有一具備，即毋庸再\n    行審酌其他情狀，應逕予撤銷緩刑之情形不同，先予敘明。\n三、經查：\n  (一)受刑人甲○○因犯背信案件，經臺灣高等法院於99年2 月10\n    日以98年度上易字第3000號（92年度偵字第2246號）判決判\n    處有期徒刑1 年8 月，緩刑3 年，於99年2 月10日確定在案\n    （下稱前案）。復於緩刑期前即97年12月9 日及同年12月29\n    日因更犯恐嚇危害安全罪，經本院於99年1 月29日以98年度\n    訴字第270 號判決分別判處有期徒刑4 月、3 月、4 月，如\n    易科罰金均以1 千元折算1 日，應執行有期徒刑10月，如易\n    科罰金以1 千元折算1 日，並經臺灣高等法院以99年度上訴\n    字第1175號判決駁回上訴，於99年3 月31日確定（下稱後案\n    ）等情，有上開二案判決書各1 份附卷可憑，顯見受刑人緩\n    刑前因故意犯他罪，而於緩刑期內受得易科罰金之有期徒刑\n    宣告確定，受刑人已合於刑法第75條之1 第1 項第1 款之撤\n    銷緩刑事由無疑。\n  (二)受刑人雖於前案詐欺案件緩刑前因故意犯他罪，而在緩刑期\n    內受得易科罰金之有期徒刑宣告確定，然刑法緩刑制度係為\n    促進惡性輕微之被告或偶發犯、初犯利於改過自新而設，刑\n    法第75條之1 又已課予法院裁量之義務，已如前述，則被告\n    雖合於上開要件，然是否已足認前案緩刑宣告難收其預期效\n    果，而有執行刑罰之必要，仍須衡酌相關情況決定之。衡諸\n    受刑人後案所犯係刑法第304 條第1 項之強制罪、第305 條\n    恐嚇危害安全罪、第306 條侵入他人住宅罪，此三罪之最重\n    法定本刑僅係3 年以下有期徒刑之罪，原均非重罪，兩案犯\n    罪手法、所侵害法益亦不相同，且受刑人前案之犯罪時間為\n    90年9 、10月間，而後案犯罪時間則為97年12月間，二案犯\n    罪時間先後間隔已逾7 年，後案犯罪時復尚未經宣告緩刑，\n    亦難遽認受刑人發生在先之恐嚇危害安全等行為對發生在後\n    之緩刑宣告有何難收預期效果之情形；再者受刑人前案受有\n    期徒刑1 年8 月，緩刑3 年之宣告，乃因其素行良好，僅基\n    於受僱人身分須服從上級指示而犯案，有前述判決可參，應\n    有一定之儆懲矯正之效，於緩刑前所犯後案，亦不足以認受\n    刑人並無悔意，衡情不能因此遽認其前案緩刑之宣告難收預\n    期效果而有執行刑罰之必要。\n四、綜上，聲請人雖依刑事訴訟法第476 條、刑法第75條之1 第\n    1 項第1 款規定聲請撤銷受刑人前案緩刑之宣告，惟經本院\n    審酌前開各情，尚難認受刑人原宣告之緩刑難收其預期效果\n    ，而有執行刑罰之必要，此外，卷存證據亦無其他可認受刑\n    人前案緩刑宣告難收預期效果之積極事證，是本件聲請並無\n    理由應予駁回。\n五、依刑事訴訟法第220 條之規定，裁定如主文。\n中    華    民    國    99    年    5     月    12    日\n                  刑事第五庭法  官  黃珮茹\n以上正本證明與原本無異。\n如不服本裁定應於送達後5日內向本院提出抗告狀。\n                            書記官  張馨尹\n中    華    民    國    99    年    5     月    12    日",
  "structure": {
    "main": "聲請駁回。",
    "reason": "一、聲請意旨略稱：受刑人甲○○因犯背信案件，經臺灣高等法\n    院於民國99年2 月10日以98年度上易字第3000號（92年度偵\n    字第2246號）判決判處有期徒刑1 年8 月，緩刑3 年，於99\n    年2 月10日確定在案。惟受刑人於緩刑期前即97年12月9 日\n    及同年12月29日因更犯恐嚇危害安全罪，經本院於99年1 月\n    29日以98年度訴字第270 號判決分別判處有期徒刑4 月、3\n    月、4 月，如易科罰金均以新臺幣（下同）1 千元折算1 日\n    ，應執行有期徒刑10月，如易科罰金以1 千元折算1 日，並\n    經臺灣高等法院以99年度上訴字第1175號判決駁回上訴，於\n    99 年3月31日確定，已足認原宣告之緩刑難收其預期效果，\n    合於刑法第75條之1 第1 項第1 款所定撤銷緩刑宣告之原因\n    ，爰依刑事訴訟法第476 條規定聲請撤銷緩刑。\n二、按受緩刑之宣告，於緩刑前因故意犯他罪，而在緩刑期內受\n    得易科罰金之有期徒刑、拘役或罰金之宣告確定，足認原宣\n    告之緩刑難收其預期效果，而有執行刑罰之必要者，得撤銷\n    其宣告，刑法第75條之1 第1 項第1 款固定有明文。惟被告\n    受緩刑宣告後，如欲撤銷其緩刑宣告，除需被告合於刑法第\n    75條之1 第1 項所規定之4 款法定事由外，尚須以「足認原\n    宣告之緩刑難收其預期效果，而有執行刑罰之必要者」，法\n    院始得依職權裁量撤銷之。本條採用裁量撤銷主義，賦予法\n    院撤銷與否之權限，特於第1 項規定實質要件為「足認原宣\n    告之緩刑難收其預期效果，而有執行刑罰之必要」，供作審\n    認之標準。亦即於上揭「得」撤銷緩刑之情形，法官應依職\n    權本於合目的性之裁量，妥適審酌被告所犯前後數罪間，關\n    於法益侵害之性質、再犯之原因、違反法規範之情節是否重\n    大、被告主觀犯意所顯現之惡性及其反社會性等情，是否已\n    使前案原為促使惡性輕微之被告或偶發犯、初犯改過自新而\n    宣告之緩刑，已難收其預期之效果，而確有執行刑罰之必要\n    ，此與刑法第75條第1 項所定2 款要件有一具備，即毋庸再\n    行審酌其他情狀，應逕予撤銷緩刑之情形不同，先予敘明。\n三、經查：\n  (一)受刑人甲○○因犯背信案件，經臺灣高等法院於99年2 月10\n    日以98年度上易字第3000號（92年度偵字第2246號）判決判\n    處有期徒刑1 年8 月，緩刑3 年，於99年2 月10日確定在案\n    （下稱前案）。復於緩刑期前即97年12月9 日及同年12月29\n    日因更犯恐嚇危害安全罪，經本院於99年1 月29日以98年度\n    訴字第270 號判決分別判處有期徒刑4 月、3 月、4 月，如\n    易科罰金均以1 千元折算1 日，應執行有期徒刑10月，如易\n    科罰金以1 千元折算1 日，並經臺灣高等法院以99年度上訴\n    字第1175號判決駁回上訴，於99年3 月31日確定（下稱後案\n    ）等情，有上開二案判決書各1 份附卷可憑，顯見受刑人緩\n    刑前因故意犯他罪，而於緩刑期內受得易科罰金之有期徒刑\n    宣告確定，受刑人已合於刑法第75條之1 第1 項第1 款之撤\n    銷緩刑事由無疑。\n  (二)受刑人雖於前案詐欺案件緩刑前因故意犯他罪，而在緩刑期\n    內受得易科罰金之有期徒刑宣告確定，然刑法緩刑制度係為\n    促進惡性輕微之被告或偶發犯、初犯利於改過自新而設，刑\n    法第75條之1 又已課予法院裁量之義務，已如前述，則被告\n    雖合於上開要件，然是否已足認前案緩刑宣告難收其預期效\n    果，而有執行刑罰之必要，仍須衡酌相關情況決定之。衡諸\n    受刑人後案所犯係刑法第304 條第1 項之強制罪、第305 條\n    恐嚇危害安全罪、第306 條侵入他人住宅罪，此三罪之最重\n    法定本刑僅係3 年以下有期徒刑之罪，原均非重罪，兩案犯\n    罪手法、所侵害法益亦不相同，且受刑人前案之犯罪時間為\n    90年9 、10月間，而後案犯罪時間則為97年12月間，二案犯\n    罪時間先後間隔已逾7 年，後案犯罪時復尚未經宣告緩刑，\n    亦難遽認受刑人發生在先之恐嚇危害安全等行為對發生在後\n    之緩刑宣告有何難收預期效果之情形；再者受刑人前案受有\n    期徒刑1 年8 月，緩刑3 年之宣告，乃因其素行良好，僅基\n    於受僱人身分須服從上級指示而犯案，有前述判決可參，應\n    有一定之儆懲矯正之效，於緩刑前所犯後案，亦不足以認受\n    刑人並無悔意，衡情不能因此遽認其前案緩刑之宣告難收預\n    期效果而有執行刑罰之必要。\n四、綜上，聲請人雖依刑事訴訟法第476 條、刑法第75條之1 第\n    1 項第1 款規定聲請撤銷受刑人前案緩刑之宣告，惟經本院\n    審酌前開各情，尚難認受刑人原宣告之緩刑難收其預期效果\n    ，而有執行刑罰之必要，此外，卷存證據亦無其他可認受刑\n    人前案緩刑宣告難收預期效果之積極事證，是本件聲請並無\n    理由應予駁回。\n五、依刑事訴訟法第220 條之規定，裁定如主文。"
  },
  "characters": {
    "judges": [
      "黃珮茹"
    ],
    "prosecutors": [

    ],
    "lawyers": [

    ],
    "clerks": [
      "張馨尹"
    ],
    "plaintiffs": [

    ],
    "defendants": [
      "甲○○"
    ],
    "prosecutor_office": [
      "臺灣士林地方法院檢察署檢察官"
    ],
    "creditors": [

    ],
    "debtors": [

    ],
    "judicial_associate_officer": [

    ]
  },
  "adjudged_at": "2010-05-12",
  "created_at": "2016-01-05 12:20:10",
  "updated_at": "2016-01-05 12:20:10"
}