{
  "identify": "SLD-99-審易-249-20100512-1",
  "court": {
    "name": "臺灣士林地方法院",
    "code": "SLD"
  },
  "division": {
    "name": "刑事",
    "code": "M"
  },
  "year": 99,
  "word": "審易",
  "number": "249",
  "jcheck": "1",
  "reason": "妨害名譽",
  "content": "臺灣士林地方法院刑事判決             99年度審易字第249號\n公  訴  人  臺灣士林地方法院檢察署檢察官\n被      告  甲○○\n選任辯護人  蘇誌明  律師\n上列被告因妨害名譽案件，經檢察官提起公訴（98年度偵字第82\n10號），本院判決如下：\n    主  文\n本件公訴不受理。\n    理  由\n一、公訴意旨如起訴書所載 （如附件起訴書） 。\n二、按告訴乃論之罪，告訴人於第一審辯論終結前得撤回其告訴\n    ，又告訴經撤回者，應諭知不受理之判決，刑事訴訟法第23\n    8 條第1 項、第303 條第3 款分別定有明文。\n三、查本件告訴人浩漢忠孝工程股份有限公司告訴被告甲○○妨\n    害名譽案件，起訴書認係觸犯刑法第310 條第2 項之罪，依\n    同法第314 條之規定，須告訴乃論。茲據告訴人浩漢忠孝工\n    程股份有限公司撤回告訴，依照首開說明，本件爰不經言詞\n    辯論，逕為不受理之諭知。\n據上論斷，應依刑事訴訟法第303 條第3 款、第307 條，判決如\n主文。\n中    華    民    國    99    年    5     月    12    日\n                  刑事第一庭法  官  雷雯華\n以上正本證明與原本無異。\n如不服本判決，應於收受送達後10日內向本院提出上訴書狀，其\n未敘述上訴理由者，應於上訴期間屆滿後20日內向本院補提理由\n書狀（均須按他造當事人之人數附繕本）。\n                            書記官  陳麗津\n中    華    民    國    99    年    5     月    12    日",
  "structure": {
    "main": "本件公訴不受理。",
    "reason": "一、公訴意旨如起訴書所載 （如附件起訴書） 。\n二、按告訴乃論之罪，告訴人於第一審辯論終結前得撤回其告訴\n    ，又告訴經撤回者，應諭知不受理之判決，刑事訴訟法第23\n    8 條第1 項、第303 條第3 款分別定有明文。\n三、查本件告訴人浩漢忠孝工程股份有限公司告訴被告甲○○妨\n    害名譽案件，起訴書認係觸犯刑法第310 條第2 項之罪，依\n    同法第314 條之規定，須告訴乃論。茲據告訴人浩漢忠孝工\n    程股份有限公司撤回告訴，依照首開說明，本件爰不經言詞\n    辯論，逕為不受理之諭知。\n據上論斷，應依刑事訴訟法第303 條第3 款、第307 條，判決如\n主文。"
  },
  "characters": {
    "judges": [
      "雷雯華"
    ],
    "prosecutors": [

    ],
    "lawyers": [

    ],
    "clerks": [
      "陳麗津"
    ],
    "plaintiffs": [

    ],
    "defendants": [
      "甲○○"
    ],
    "prosecutor_office": [
      "臺灣士林地方法院檢察署檢察官"
    ],
    "creditors": [

    ],
    "debtors": [

    ],
    "judicial_associate_officer": [

    ]
  },
  "adjudged_at": "2010-05-12",
  "created_at": "2016-01-05 12:20:29",
  "updated_at": "2016-01-05 12:20:29"
}