{
  "identify": "SLD-99-訴-58-20100512-1",
  "court": {
    "name": "臺灣士林地方法院",
    "code": "SLD"
  },
  "division": {
    "name": "刑事",
    "code": "M"
  },
  "year": 99,
  "word": "訴",
  "number": "58",
  "jcheck": "1",
  "reason": "搶奪",
  "content": "臺灣士林地方法院刑事判決                99年度訴字第58號\n公  訴  人  臺灣士林地方法院檢察署檢察官\n被      告  乙○○\n            丙○○\n上列被告因搶奪案件，經檢察官提起公訴（99年度偵字第2781號\n），經訊問被告後，被告為認罪之答辯，本院合議庭裁定改由受\n命法官獨任進行簡式審判程序，茲判決如下：\n    主  文\n乙○○、丙○○共同意圖為自己不法之所有，而搶奪他人之動產\n，乙○○累犯，處有期徒刑壹年，丙○○處有期徒刑拾月。\n    事  實\n一、乙○○前因贓物及竊盜等案件，分別經臺灣板橋地方法院及\n    臺灣臺北地方法院判決處有期徒刑4月及7月確定，2案件經\n    定應執行刑為有期徒刑10月，再分別經減刑為有期徒刑2月\n    、3月15日，而定應執行刑為有期徒刑5月確定，甫於民國98\n    年5月21日因縮短刑期執行完畢，翌日出監。詎乙○○仍不\n    知悔改，因缺錢花用，而與丙○○共同基於為自己不法所有\n    之意圖，先由乙○○於99年2月22日19時至21時間之某時，\n    駕駛其所有之車牌號碼2775-YM號自用小客車（下稱系爭車\n    輛）至臺北縣五股鄉○○○○道附近搭載丙○○後，往臺北\n    市士林區方向行駛，嗣於同日23時15分許，在臺北市士林區\n    士林夜市○○○○路口停等紅燈時，因見甲○○獨自一人騎\n    乘機車同時停等紅燈，認有機可乘，乙○○及丙○○即共同\n    基於搶奪之犯意聯絡，由乙○○駕駛系爭車輛尾隨甲○○至\n    臺北市○○區○○街、後港街口，在車上把風及為後續接應\n    ，丙○○則下車，待甲○○在臺北市○○區○○街6號前停\n    妥機車後，乘其不及防備之際，徒手搶奪其所有之皮包1只\n    （內有現金新臺幣 (下同)9,000 元、自用小客車駕照、普\n    通重型機車駕照、健保卡、身分證、輕型機車行照及保險卡\n    、人身保險業務員登錄證、中國信託金融卡、第一銀行信用\n    卡、合作金庫金融卡、郵政儲金金融卡各1張、雙卡行動電\n    話1支、相機1台等物）得手，隨即搭乘乙○○所駕駛停等於\n    巷口接應之系爭車輛迅速逃逸，並在車上將搶得皮包內之財\n    物取出朋分花用，丙○○分得現金3,700元，乙○○則分得\n    剩餘現金及其他物品。嗣甲○○報警處理，經警調閱案發地\n    附近之監視錄影畫面而循線查獲。\n二、案經臺北市政府警察局士林分局報告臺灣士林地方法院檢察\n    署檢察官偵查起訴。\n    理  由\n一、本件被告乙○○、被告丙○○所犯非死刑、無期徒刑、最輕\n    本刑為3年以上有期徒刑之罪，或高等法院管轄第一審之案\n    件，經訊問被告後，渠等均為認罪之答辯，經告以簡式審判\n    程序之旨，並聽取檢察官及被告之意見後，本院合議庭裁定\n    改由受命法官獨任依簡式審判程序進行審理，是本件之證據\n    調查，依刑事訴訟法第273條之2規定，不受同法第159條第1\n    項、第161條之2、第161條之3、第163條之1及第164條至第\n    170條規定之限制，合先敘明。\n二、上揭犯罪事實，業據被告乙○○（見99年度偵字第2781號卷\n    【下稱偵字卷】第77-80、95-96頁、本院99年度訴字第58號\n    卷【下稱本院卷】第34-37、61-62、63-67頁）、被告丙○\n    ○（見偵字卷第13-18、74-77、96-98頁、本院卷第34-37、\n    61-62、63-67頁）坦承不諱，核與證人即被害人甲○○之證\n    述內容相符（見偵字卷第9-10、11-12、109-110頁），復有\n    證人甲○○所有之自用小客車駕照、普通重型機車駕照、身\n    分證、輕型機車行照及保險卡、人身保險業務員登錄證、中\n    國信託金融卡、第一銀行信用卡、合作金庫金融卡、郵政儲\n    金金融卡影本各1張、扣押物品目錄表2份、贓物認領保管單\n    1紙、查獲現場照片8張及案發地附近之監視錄影畫面7張在\n    卷可稽（見偵字卷第26-27、39-40、46、48、50-53、34、\n    71-72頁），足證渠等前開自白核與事實相符而堪採信。從\n    而，本件事證明確，被告乙○○、被告丙○○上開犯行堪以\n    認定，應依法論科。\n三、核被告乙○○及被告丙○○所為，均係犯刑法第325條第1項\n    普通搶奪罪。被告乙○○、被告丙○○有犯意之聯絡及行為\n    之分擔，皆為共同正犯。又被告乙○○有犯罪事實欄所載前\n    科執行情形，此有臺灣高等法院被告前案紀錄表在卷可按，\n    其於有期徒刑執行完畢後，5年內故意再犯本件有期徒刑以\n    上之罪，為累犯，應依刑法第47條第1項之規定加重其刑。\n    爰審酌被告乙○○、被告丙○○均正值青壯，竟不思循正當\n    途徑獲致財物，而貪圖慾便，隨機於路上尋找行搶對象，使\n    晚歸婦女時時刻刻處於恐懼之中，造成社會治安之敗壞甚鉅\n    ，實屬可議，惟念及渠等犯後尚知坦承犯行，亦得被害人甲\n    ○○之原諒，暨渠等生活狀況、品行、素行、智識程度、犯\n    罪所生之危害等一切情狀，分別量處如主文所示之刑。另公\n    訴人分別具體求處被告乙○○、被告丙○○各有期徒刑3年\n    ，固非無見，惟本院斟酌前開事項，認公訴人所求刑度尚嫌\n    過重，附此敘明。\n四、至檢察官另建請對被告乙○○、丙○○諭知強制工作，以資\n    矯治等語。惟按保安處分係針對受處分人將來之危險性所為\n    之處置，以達教化、治療之目的，為刑罰之補充制度，保安\n    處分中之強制工作，旨在對嚴重職業性犯罪及欠缺正確工作\n    觀念或無正常工作因而犯罪者，強制其從事勞動，學習一技\n    之長及正確之謀生觀念，使其日後重返社會，能適應社會生\n    活，然保安處分之措施亦含社會隔離、拘束身體自由之性質\n    ，其限制人民之權利，實與刑罰同，自應受比例原則之規範\n    ，使保安處分之宣告，與行為人所為行為之嚴重性、行為人\n    所表現之危險性，及對行為人未來行為之期待性相當（最高\n    法院91年度台上字第4625號判決意旨參照）。查被告乙○○\n    於本案搶奪犯行前所為之贓物、竊盜犯行，均係於95年間，\n    被告丙○○於本案搶奪犯行前所為之竊盜、詐欺、搶奪犯行\n    ，分別係於94、95年間，其間渠等均無另涉財產犯罪犯行經\n    法院判處有期徒刑，依卷內現存事證尚難即認渠等有犯罪之\n    習慣或有何因遊蕩或懶惰成習而為本件犯行之情事，是依比\n    例原則，綜合其所表現之危險性及對其未來之期待性等情以\n    觀，本院認宣告如主文所示之刑，與渠等本案犯行之處罰已\n    屬相當，並足收儆懲之效，尚無另宣告強制工作以預防矯治\n    其社會危險性之必要，爰均不另諭知於刑之執行前令入勞動\n    場所強制工作，附此敘明。\n據上論斷，應依刑事訴訟法第273條之1第1項、第284條之1、第\n299條第1項前段，刑法第28條、第325條第1項、第47條第1項，\n判決如主文。\n本案經檢察官江耀民到庭執行職務。\n中    華    民    國    99    年     5    月    12    日\n                  刑事第三庭法  官  謝佳純\n以上正本證明與原本無異。\n如不服本判決應於收受判決後10日內向本院提出上訴書狀，並應\n敘述具體理由；其未敘述上訴之理由者，應於上訴期間屆滿後20\n日內向本院補提理由書（均須按他造當事人之人數附繕本），切\n勿逕送上級法院。\n                            書記官  阮弘毅\n中    華    民    國    99    年    5     月    12    日\n附錄本件所犯法條全文：\n刑法第325條\n意圖為自己或第三人不法之所有，而搶奪他人之動產者，處 6 月\n以上 5 年以下有期徒刑。\n因而致人於死者，處無期徒刑或 7 年以上有期徒刑，致重傷者，\n處 3 年以上 10 年以下有期徒刑。\n第 1 項之未遂犯罰之。",
  "structure": {
    "main": "乙○○、丙○○共同意圖為自己不法之所有，而搶奪他人之動產\n，乙○○累犯，處有期徒刑壹年，丙○○處有期徒刑拾月。",
    "fact": "一、乙○○前因贓物及竊盜等案件，分別經臺灣板橋地方法院及\n    臺灣臺北地方法院判決處有期徒刑4月及7月確定，2案件經\n    定應執行刑為有期徒刑10月，再分別經減刑為有期徒刑2月\n    、3月15日，而定應執行刑為有期徒刑5月確定，甫於民國98\n    年5月21日因縮短刑期執行完畢，翌日出監。詎乙○○仍不\n    知悔改，因缺錢花用，而與丙○○共同基於為自己不法所有\n    之意圖，先由乙○○於99年2月22日19時至21時間之某時，\n    駕駛其所有之車牌號碼2775-YM號自用小客車（下稱系爭車\n    輛）至臺北縣五股鄉○○○○道附近搭載丙○○後，往臺北\n    市士林區方向行駛，嗣於同日23時15分許，在臺北市士林區\n    士林夜市○○○○路口停等紅燈時，因見甲○○獨自一人騎\n    乘機車同時停等紅燈，認有機可乘，乙○○及丙○○即共同\n    基於搶奪之犯意聯絡，由乙○○駕駛系爭車輛尾隨甲○○至\n    臺北市○○區○○街、後港街口，在車上把風及為後續接應\n    ，丙○○則下車，待甲○○在臺北市○○區○○街6號前停\n    妥機車後，乘其不及防備之際，徒手搶奪其所有之皮包1只\n    （內有現金新臺幣 (下同)9,000 元、自用小客車駕照、普\n    通重型機車駕照、健保卡、身分證、輕型機車行照及保險卡\n    、人身保險業務員登錄證、中國信託金融卡、第一銀行信用\n    卡、合作金庫金融卡、郵政儲金金融卡各1張、雙卡行動電\n    話1支、相機1台等物）得手，隨即搭乘乙○○所駕駛停等於\n    巷口接應之系爭車輛迅速逃逸，並在車上將搶得皮包內之財\n    物取出朋分花用，丙○○分得現金3,700元，乙○○則分得\n    剩餘現金及其他物品。嗣甲○○報警處理，經警調閱案發地\n    附近之監視錄影畫面而循線查獲。\n二、案經臺北市政府警察局士林分局報告臺灣士林地方法院檢察\n    署檢察官偵查起訴。",
    "reason": "一、本件被告乙○○、被告丙○○所犯非死刑、無期徒刑、最輕\n    本刑為3年以上有期徒刑之罪，或高等法院管轄第一審之案\n    件，經訊問被告後，渠等均為認罪之答辯，經告以簡式審判\n    程序之旨，並聽取檢察官及被告之意見後，本院合議庭裁定\n    改由受命法官獨任依簡式審判程序進行審理，是本件之證據\n    調查，依刑事訴訟法第273條之2規定，不受同法第159條第1\n    項、第161條之2、第161條之3、第163條之1及第164條至第\n    170條規定之限制，合先敘明。\n二、上揭犯罪事實，業據被告乙○○（見99年度偵字第2781號卷\n    【下稱偵字卷】第77-80、95-96頁、本院99年度訴字第58號\n    卷【下稱本院卷】第34-37、61-62、63-67頁）、被告丙○\n    ○（見偵字卷第13-18、74-77、96-98頁、本院卷第34-37、\n    61-62、63-67頁）坦承不諱，核與證人即被害人甲○○之證\n    述內容相符（見偵字卷第9-10、11-12、109-110頁），復有\n    證人甲○○所有之自用小客車駕照、普通重型機車駕照、身\n    分證、輕型機車行照及保險卡、人身保險業務員登錄證、中\n    國信託金融卡、第一銀行信用卡、合作金庫金融卡、郵政儲\n    金金融卡影本各1張、扣押物品目錄表2份、贓物認領保管單\n    1紙、查獲現場照片8張及案發地附近之監視錄影畫面7張在\n    卷可稽（見偵字卷第26-27、39-40、46、48、50-53、34、\n    71-72頁），足證渠等前開自白核與事實相符而堪採信。從\n    而，本件事證明確，被告乙○○、被告丙○○上開犯行堪以\n    認定，應依法論科。\n三、核被告乙○○及被告丙○○所為，均係犯刑法第325條第1項\n    普通搶奪罪。被告乙○○、被告丙○○有犯意之聯絡及行為\n    之分擔，皆為共同正犯。又被告乙○○有犯罪事實欄所載前\n    科執行情形，此有臺灣高等法院被告前案紀錄表在卷可按，\n    其於有期徒刑執行完畢後，5年內故意再犯本件有期徒刑以\n    上之罪，為累犯，應依刑法第47條第1項之規定加重其刑。\n    爰審酌被告乙○○、被告丙○○均正值青壯，竟不思循正當\n    途徑獲致財物，而貪圖慾便，隨機於路上尋找行搶對象，使\n    晚歸婦女時時刻刻處於恐懼之中，造成社會治安之敗壞甚鉅\n    ，實屬可議，惟念及渠等犯後尚知坦承犯行，亦得被害人甲\n    ○○之原諒，暨渠等生活狀況、品行、素行、智識程度、犯\n    罪所生之危害等一切情狀，分別量處如主文所示之刑。另公\n    訴人分別具體求處被告乙○○、被告丙○○各有期徒刑3年\n    ，固非無見，惟本院斟酌前開事項，認公訴人所求刑度尚嫌\n    過重，附此敘明。\n四、至檢察官另建請對被告乙○○、丙○○諭知強制工作，以資\n    矯治等語。惟按保安處分係針對受處分人將來之危險性所為\n    之處置，以達教化、治療之目的，為刑罰之補充制度，保安\n    處分中之強制工作，旨在對嚴重職業性犯罪及欠缺正確工作\n    觀念或無正常工作因而犯罪者，強制其從事勞動，學習一技\n    之長及正確之謀生觀念，使其日後重返社會，能適應社會生\n    活，然保安處分之措施亦含社會隔離、拘束身體自由之性質\n    ，其限制人民之權利，實與刑罰同，自應受比例原則之規範\n    ，使保安處分之宣告，與行為人所為行為之嚴重性、行為人\n    所表現之危險性，及對行為人未來行為之期待性相當（最高\n    法院91年度台上字第4625號判決意旨參照）。查被告乙○○\n    於本案搶奪犯行前所為之贓物、竊盜犯行，均係於95年間，\n    被告丙○○於本案搶奪犯行前所為之竊盜、詐欺、搶奪犯行\n    ，分別係於94、95年間，其間渠等均無另涉財產犯罪犯行經\n    法院判處有期徒刑，依卷內現存事證尚難即認渠等有犯罪之\n    習慣或有何因遊蕩或懶惰成習而為本件犯行之情事，是依比\n    例原則，綜合其所表現之危險性及對其未來之期待性等情以\n    觀，本院認宣告如主文所示之刑，與渠等本案犯行之處罰已\n    屬相當，並足收儆懲之效，尚無另宣告強制工作以預防矯治\n    其社會危險性之必要，爰均不另諭知於刑之執行前令入勞動\n    場所強制工作，附此敘明。\n據上論斷，應依刑事訴訟法第273條之1第1項、第284條之1、第\n299條第1項前段，刑法第28條、第325條第1項、第47條第1項，\n判決如主文。\n本案經檢察官江耀民到庭執行職務。\n中    華    民    國    99    年     5    月    12    日\n                  刑事第三庭法  官  謝佳純\n以上正本證明與原本無異。\n如不服本判決應於收受判決後10日內向本院提出上訴書狀，並應\n敘述具體理由；其未敘述上訴之理由者，應於上訴期間屆滿後20\n日內向本院補提理由書（均須按他造當事人之人數附繕本），切\n勿逕送上級法院。\n                            書記官  阮弘毅"
  },
  "characters": {
    "judges": [
      "謝佳純"
    ],
    "prosecutors": [
      "江耀民"
    ],
    "lawyers": [

    ],
    "clerks": [
      "阮弘毅"
    ],
    "plaintiffs": [

    ],
    "defendants": [
      "乙○○"
    ],
    "prosecutor_office": [
      "臺灣士林地方法院檢察署檢察官"
    ],
    "creditors": [

    ],
    "debtors": [

    ],
    "judicial_associate_officer": [

    ]
  },
  "adjudged_at": "2010-05-12",
  "created_at": "2016-01-05 12:20:46",
  "updated_at": "2016-01-05 12:20:46"
}