{
  "identify": "SLD-99-訴-582-20100512-1",
  "court": {
    "name": "臺灣士林地方法院",
    "code": "SLD"
  },
  "division": {
    "name": "民事",
    "code": "V"
  },
  "year": 99,
  "word": "訴",
  "number": "582",
  "jcheck": "1",
  "reason": "清償借款",
  "content": "臺灣士林地方法院民事裁定               99年度訴字第582號\n原      告  甲○○\n被      告  乙○○原名蔡嘉榮.\n上列當事人間清償借款事件，本院裁定如下：\n    主  文\n原告之訴駁回。\n訴訟費用由原告負擔。\n    理  由\n一、按提起民事訴訟應繳納裁判費，此為必備之程式；又原告之\n    訴，起訴不合程式或不備其他要件，依其情形可以補正，經\n    審判長定期間命其補正而不補正者，法院應以裁定駁回之，\n    民事訴訟法第249 條第1 項第6 款定有明文。且民事訴訟法\n    第249 條第1 項但書關於審判長權限之規定，於受命法官行\n    準備程序時準用之，此觀諸同法第272條規定自明。\n二、經查，本件原告起訴未據繳納裁判費，嗣經受命法官於民國\n    99年4 月16日裁定命原告於5 日內補正，該項裁定已於同年\n    月26日送達原告，有送達證書附卷可憑。原告逾期迄未補正\n    ，揆諸上開規定，其訴顯難認為合法，應予駁回。\n三、爰裁定如主文。\n中    華    民    國    99    年    5     月    12    日\n                  民事第三庭  審判長法  官  張國勳\n                                    法  官  施月燿\n                                    法  官  林尚諭\n以上正本證明與原本無異。\n如對本裁定抗告，應於裁定送達後10日內向本院提出抗告狀。\n中    華    民    國    99    年    5     月    17    日\n                                    書記官  吳華瑋",
  "structure": {
    "main": "原告之訴駁回。\n訴訟費用由原告負擔。",
    "reason": "一、按提起民事訴訟應繳納裁判費，此為必備之程式；又原告之\n    訴，起訴不合程式或不備其他要件，依其情形可以補正，經\n    審判長定期間命其補正而不補正者，法院應以裁定駁回之，\n    民事訴訟法第249 條第1 項第6 款定有明文。且民事訴訟法\n    第249 條第1 項但書關於審判長權限之規定，於受命法官行\n    準備程序時準用之，此觀諸同法第272條規定自明。\n二、經查，本件原告起訴未據繳納裁判費，嗣經受命法官於民國\n    99年4 月16日裁定命原告於5 日內補正，該項裁定已於同年\n    月26日送達原告，有送達證書附卷可憑。原告逾期迄未補正\n    ，揆諸上開規定，其訴顯難認為合法，應予駁回。\n三、爰裁定如主文。"
  },
  "characters": {
    "judges": [
      "張國勳",
      "施月燿",
      "林尚諭"
    ],
    "prosecutors": [

    ],
    "lawyers": [

    ],
    "clerks": [

    ],
    "plaintiffs": [
      "甲○○"
    ],
    "defendants": [
      "乙○○原名蔡嘉榮."
    ],
    "prosecutor_office": [

    ],
    "creditors": [

    ],
    "debtors": [

    ],
    "judicial_associate_officer": [

    ]
  },
  "adjudged_at": "2010-05-12",
  "created_at": "2016-01-05 12:22:03",
  "updated_at": "2016-01-05 12:22:03"
}