{
  "identify": "SLD-99-審交簡-108-20100512-1",
  "court": {
    "name": "臺灣士林地方法院",
    "code": "SLD"
  },
  "division": {
    "name": "刑事",
    "code": "M"
  },
  "year": 99,
  "word": "審交簡",
  "number": "108",
  "jcheck": "1",
  "reason": "公共危險",
  "content": "臺灣士林地方法院刑事簡易判決       99年度審交簡字第108號\n公  訴  人  臺灣士林地方法院檢察署檢察官\n被      告  甲○○\n上列被告因公共危險案件，經檢察官提起公訴（98年度偵字第16\n156 號），被告於本院準備程序中自白犯罪（99年度審交訴字第\n20號），本院合議庭認宜逕以簡易判決處刑，爰裁定由受命法官\n獨任行簡易程序審理，並判決如下：\n    主  文\n甲○○駕駛動力交通工具肇事，致人受傷而逃逸，處有期徒刑肆\n月，如易科罰金，以新臺幣壹仟元折算壹日。緩刑貳年。\n    事實及理由\n一、本件犯罪事實及證據，除均引用檢察官起訴書（詳如附件）\n    之記載外，證據部分並補充：被告甲○○於本院準備程序中\n    坦承犯行（參見本院卷第18頁），核其自白，與起訴書所舉\n    事證相符，堪認屬實，本案事證明確，被告犯行可以認定，\n    應依法論科。\n二、核被告甲○○所為，係犯刑法第185 條之4 駕駛動力交通工\n    具肇事逃逸罪。又被告於肇事後，雖一度騎駛機車離開現場\n    ，惟於當日下午某時許，在有偵查權之機關或公務員發覺其\n    犯罪前，主動以電話撥打110 向交通大隊謝姓警務員承認其\n    為肇事人，並接受裁判，有臺北市政府警察局內湖分局疑似\n    道路交通事故肇事逃逸追查表、臺北市政府警察局內湖分局\n    交通分隊交通事故談話紀錄表各1 紙在卷可按（附於偵卷第\n    20頁、第32頁），應認已符合自首要件，爰依刑法第62條前\n    段之規定，減輕其刑。爰審酌被告駕駛車輛肇事後逃逸，對\n    於被害人之身體及求償權之行使造成危害，然犯後坦承犯行\n    ，尚見悔意，並考量被害人所受傷勢程度尚屬輕微，復未提\n    出過失傷害之刑事告訴暨被告犯罪之動機、目的、手段及其\n    智識程度、生活狀況等一切情狀，量處如主文所示之刑，並\n    諭知易科罰金之折算標準，以資懲儆。\n三、末查，被告前未曾因故意犯罪受有期徒刑以上刑之宣告，此\n    有臺灣高等法院被告前案紀錄表在卷可稽，其因一時失慮，\n    致罹刑章，犯後已坦承犯行，深具悔意，堪認被告經此次偵\n    審程序及刑之宣告後，當能知所警惕，而無再犯之虞，本院\n    因認所宣告之刑，以暫不執行為適當，爰依刑法第74條第1\n    項第1 款之規定宣告緩刑2 年，用啟自新。\n四、檢察官、被告如不服本判決，應於收受送達後10日內向本院\n    提出上訴書狀。\n五、依刑事訴訟法第449 條第2 項、第3 項、第454 條第2 項，\n    刑法第185 條之4 、第62條前段、第41條第1 項前段，第74\n    條第1 項第1 款，逕以簡易判決處刑如主文。\n本案經檢察官孟玉梅到庭執行準備程序職務。\n中    華    民    國    99    年    5     月    12    日\n                  交通法庭法  官  吳祚丞\n以上正本證明與原本無異。\n                          書記官  丁梅芬\n中    華    民    國    99    年    5     月    12    日\n附錄論罪科刑法條：\n刑法第185條之4\n駕駛動力交通工具肇事，致人死傷而逃逸者，處 6 月以上 5 年\n以下有期徒刑。",
  "structure": {
    "main": "甲○○駕駛動力交通工具肇事，致人受傷而逃逸，處有期徒刑肆\n月，如易科罰金，以新臺幣壹仟元折算壹日。緩刑貳年。",
    "fact": "一、本件犯罪事實及證據，除均引用檢察官起訴書（詳如附件）\n    之記載外，證據部分並補充：被告甲○○於本院準備程序中\n    坦承犯行（參見本院卷第18頁），核其自白，與起訴書所舉\n    事證相符，堪認屬實，本案事證明確，被告犯行可以認定，\n    應依法論科。\n二、核被告甲○○所為，係犯刑法第185 條之4 駕駛動力交通工\n    具肇事逃逸罪。又被告於肇事後，雖一度騎駛機車離開現場\n    ，惟於當日下午某時許，在有偵查權之機關或公務員發覺其\n    犯罪前，主動以電話撥打110 向交通大隊謝姓警務員承認其\n    為肇事人，並接受裁判，有臺北市政府警察局內湖分局疑似\n    道路交通事故肇事逃逸追查表、臺北市政府警察局內湖分局\n    交通分隊交通事故談話紀錄表各1 紙在卷可按（附於偵卷第\n    20頁、第32頁），應認已符合自首要件，爰依刑法第62條前\n    段之規定，減輕其刑。爰審酌被告駕駛車輛肇事後逃逸，對\n    於被害人之身體及求償權之行使造成危害，然犯後坦承犯行\n    ，尚見悔意，並考量被害人所受傷勢程度尚屬輕微，復未提\n    出過失傷害之刑事告訴暨被告犯罪之動機、目的、手段及其\n    智識程度、生活狀況等一切情狀，量處如主文所示之刑，並\n    諭知易科罰金之折算標準，以資懲儆。\n三、末查，被告前未曾因故意犯罪受有期徒刑以上刑之宣告，此\n    有臺灣高等法院被告前案紀錄表在卷可稽，其因一時失慮，\n    致罹刑章，犯後已坦承犯行，深具悔意，堪認被告經此次偵\n    審程序及刑之宣告後，當能知所警惕，而無再犯之虞，本院\n    因認所宣告之刑，以暫不執行為適當，爰依刑法第74條第1\n    項第1 款之規定宣告緩刑2 年，用啟自新。\n四、檢察官、被告如不服本判決，應於收受送達後10日內向本院\n    提出上訴書狀。\n五、依刑事訴訟法第449 條第2 項、第3 項、第454 條第2 項，\n    刑法第185 條之4 、第62條前段、第41條第1 項前段，第74\n    條第1 項第1 款，逕以簡易判決處刑如主文。\n本案經檢察官孟玉梅到庭執行準備程序職務。",
    "reason": "一、本件犯罪事實及證據，除均引用檢察官起訴書（詳如附件）\n    之記載外，證據部分並補充：被告甲○○於本院準備程序中\n    坦承犯行（參見本院卷第18頁），核其自白，與起訴書所舉\n    事證相符，堪認屬實，本案事證明確，被告犯行可以認定，\n    應依法論科。\n二、核被告甲○○所為，係犯刑法第185 條之4 駕駛動力交通工\n    具肇事逃逸罪。又被告於肇事後，雖一度騎駛機車離開現場\n    ，惟於當日下午某時許，在有偵查權之機關或公務員發覺其\n    犯罪前，主動以電話撥打110 向交通大隊謝姓警務員承認其\n    為肇事人，並接受裁判，有臺北市政府警察局內湖分局疑似\n    道路交通事故肇事逃逸追查表、臺北市政府警察局內湖分局\n    交通分隊交通事故談話紀錄表各1 紙在卷可按（附於偵卷第\n    20頁、第32頁），應認已符合自首要件，爰依刑法第62條前\n    段之規定，減輕其刑。爰審酌被告駕駛車輛肇事後逃逸，對\n    於被害人之身體及求償權之行使造成危害，然犯後坦承犯行\n    ，尚見悔意，並考量被害人所受傷勢程度尚屬輕微，復未提\n    出過失傷害之刑事告訴暨被告犯罪之動機、目的、手段及其\n    智識程度、生活狀況等一切情狀，量處如主文所示之刑，並\n    諭知易科罰金之折算標準，以資懲儆。\n三、末查，被告前未曾因故意犯罪受有期徒刑以上刑之宣告，此\n    有臺灣高等法院被告前案紀錄表在卷可稽，其因一時失慮，\n    致罹刑章，犯後已坦承犯行，深具悔意，堪認被告經此次偵\n    審程序及刑之宣告後，當能知所警惕，而無再犯之虞，本院\n    因認所宣告之刑，以暫不執行為適當，爰依刑法第74條第1\n    項第1 款之規定宣告緩刑2 年，用啟自新。\n四、檢察官、被告如不服本判決，應於收受送達後10日內向本院\n    提出上訴書狀。\n五、依刑事訴訟法第449 條第2 項、第3 項、第454 條第2 項，\n    刑法第185 條之4 、第62條前段、第41條第1 項前段，第74\n    條第1 項第1 款，逕以簡易判決處刑如主文。\n本案經檢察官孟玉梅到庭執行準備程序職務。"
  },
  "characters": {
    "judges": [
      "吳祚丞"
    ],
    "prosecutors": [

    ],
    "lawyers": [

    ],
    "clerks": [
      "丁梅芬"
    ],
    "plaintiffs": [

    ],
    "defendants": [
      "甲○○"
    ],
    "prosecutor_office": [
      "臺灣士林地方法院檢察署檢察官"
    ],
    "creditors": [

    ],
    "debtors": [

    ],
    "judicial_associate_officer": [

    ]
  },
  "adjudged_at": "2010-05-12",
  "created_at": "2016-01-05 12:20:21",
  "updated_at": "2016-01-05 12:20:21"
}