{
  "identify": "SLD-99-審易-822-20100512-1",
  "court": {
    "name": "臺灣士林地方法院",
    "code": "SLD"
  },
  "division": {
    "name": "刑事",
    "code": "M"
  },
  "year": 99,
  "word": "審易",
  "number": "822",
  "jcheck": "1",
  "reason": "侵入住宅",
  "content": "臺灣士林地方法院刑事判決             99年度審易字第822號\n公  訴  人  臺灣士林地方法院檢察署檢察官\n被      告  乙○○\n上列被告因侵入住宅案件，經檢察官聲請簡易判決處刑（99年度\n偵字第593 號），本院內湖簡易庭認不宜以簡易判決處刑（99年\n度湖簡字第166 號），移由本院改依通常程序審理，本院判決如\n下：\n    主  文\n本件公訴不受理。\n    理  由\n一、公訴意旨如聲請簡易判決處刑書所載（簡易判決處刑之聲請\n    與提起公訴有同一之效力，聲請簡易判決處刑書詳如附件）\n    。\n二、按告訴乃論之罪，告訴人於第一審辯論終結前得撤回其告訴\n    ，又告訴經撤回者，應諭知不受理之判決，刑事訴訟法第23\n    8 條第1 項、第303 條第3 款分別定有明文。\n三、查本件告訴人甲○○告訴被告乙○○侵入住宅案件，聲請簡\n    易判決處刑書認係觸犯刑法第306 條第1 項之罪，依同法第\n    308 條第1 項之規定，須告訴乃論。茲據告訴人甲○○撤回\n    告訴，依照首開說明，本件爰不經言詞辯論，逕為不受理之\n    諭知。\n據上論斷，應依刑事訴訟法第452 條、第303 條第3 款、第307\n條，判決如主文。\n中    華    民    國    99    年    5     月    12    日\n                  刑事第一庭法  官  雷雯華\n以上正本證明與原本無異。\n如不服本判決，應於收受送達後10日內向本院提出上訴書狀，其\n未敘述上訴之理由者並得於提起上訴後20日內向本院補提理由書\n（均須按他造當事人之人數附繕本）。\n                            書記官  陳麗津\n中    華    民    國    99    年    5     月    12    日",
  "structure": {
    "main": "本件公訴不受理。",
    "reason": "一、公訴意旨如聲請簡易判決處刑書所載（簡易判決處刑之聲請\n    與提起公訴有同一之效力，聲請簡易判決處刑書詳如附件）\n    。\n二、按告訴乃論之罪，告訴人於第一審辯論終結前得撤回其告訴\n    ，又告訴經撤回者，應諭知不受理之判決，刑事訴訟法第23\n    8 條第1 項、第303 條第3 款分別定有明文。\n三、查本件告訴人甲○○告訴被告乙○○侵入住宅案件，聲請簡\n    易判決處刑書認係觸犯刑法第306 條第1 項之罪，依同法第\n    308 條第1 項之規定，須告訴乃論。茲據告訴人甲○○撤回\n    告訴，依照首開說明，本件爰不經言詞辯論，逕為不受理之\n    諭知。\n據上論斷，應依刑事訴訟法第452 條、第303 條第3 款、第307\n條，判決如主文。"
  },
  "characters": {
    "judges": [
      "雷雯華"
    ],
    "prosecutors": [

    ],
    "lawyers": [

    ],
    "clerks": [
      "陳麗津"
    ],
    "plaintiffs": [

    ],
    "defendants": [
      "乙○○"
    ],
    "prosecutor_office": [
      "臺灣士林地方法院檢察署檢察官"
    ],
    "creditors": [

    ],
    "debtors": [

    ],
    "judicial_associate_officer": [

    ]
  },
  "adjudged_at": "2010-05-12",
  "created_at": "2016-01-05 12:20:33",
  "updated_at": "2016-01-05 12:20:33"
}