{
  "identify": "SLD-99-聲-666-20100512-1",
  "court": {
    "name": "臺灣士林地方法院",
    "code": "SLD"
  },
  "division": {
    "name": "刑事",
    "code": "M"
  },
  "year": 99,
  "word": "聲",
  "number": "666",
  "jcheck": "1",
  "reason": "宣告沒收",
  "content": "臺灣士林地方法院刑事裁定               99年度聲字第666號\n聲  請  人  臺灣士林地方法院檢察署檢察官\n被      告  丙○○\n            乙○○\n            甲○○  30歲民.\n            丁○○○\n上列聲請人因被告等犯賭博案件（99年度偵字第3197號），聲請\n單獨宣告沒收違禁物（99年度聲沒字第58號），本院裁定如下：\n    主  文\n扣案之賭具四色牌貳副、賭資新臺幣參仟貳佰伍拾元均沒收。\n    理  由\n一、按檢察官依刑事訴訟法第253 條或第253 條之1 為不起訴或\n    緩起訴處分者，對供犯罪所用、供犯罪預備或因犯罪所得之\n    物，以屬於被告者為限，得單獨聲請法院宣告沒收，刑事訴\n    訟法第259 條之1 定有明文。\n二、聲請意旨略以：如附件聲請書所載。\n三、經查，被告丙○○等因賭博案件，經臺灣士林地方法院檢察\n    署檢察官於民國99年3 月13日以99年度偵字第3197號為不起\n    訴處分確定，而扣案之賭具四色牌2 副、賭資新臺幣3,25 0\n    元，係分屬被告等人所有且為被告等人供犯罪所用之物，業\n    經被告等人於偵訊中供承明確，是揆諸上開說明，聲請人聲\n    請宣告沒收，核與上開規定相符，應予准許，爰裁定如主文\n    。\n四、依刑事訴訟法第259條之1 ，裁定如主文。\n中    華    民    國    99    年    5     月    12    日\n                  刑事第五庭法  官  黃珮茹\n以上正本證明與原本無異。\n如不服本裁定應於送達後5日內向本院提出抗告狀。\n                            書記官  張馨尹\n中    華    民    國    99    年    5     月    12    日",
  "structure": {
    "main": "扣案之賭具四色牌貳副、賭資新臺幣參仟貳佰伍拾元均沒收。",
    "reason": "一、按檢察官依刑事訴訟法第253 條或第253 條之1 為不起訴或\n    緩起訴處分者，對供犯罪所用、供犯罪預備或因犯罪所得之\n    物，以屬於被告者為限，得單獨聲請法院宣告沒收，刑事訴\n    訟法第259 條之1 定有明文。\n二、聲請意旨略以：如附件聲請書所載。\n三、經查，被告丙○○等因賭博案件，經臺灣士林地方法院檢察\n    署檢察官於民國99年3 月13日以99年度偵字第3197號為不起\n    訴處分確定，而扣案之賭具四色牌2 副、賭資新臺幣3,25 0\n    元，係分屬被告等人所有且為被告等人供犯罪所用之物，業\n    經被告等人於偵訊中供承明確，是揆諸上開說明，聲請人聲\n    請宣告沒收，核與上開規定相符，應予准許，爰裁定如主文\n    。\n四、依刑事訴訟法第259條之1 ，裁定如主文。"
  },
  "characters": {
    "judges": [
      "黃珮茹"
    ],
    "prosecutors": [

    ],
    "lawyers": [

    ],
    "clerks": [
      "張馨尹"
    ],
    "plaintiffs": [

    ],
    "defendants": [
      "丙○○"
    ],
    "prosecutor_office": [
      "臺灣士林地方法院檢察署檢察官"
    ],
    "creditors": [

    ],
    "debtors": [

    ],
    "judicial_associate_officer": [

    ]
  },
  "adjudged_at": "2010-05-12",
  "created_at": "2016-01-05 12:20:40",
  "updated_at": "2016-01-05 12:20:40"
}