{
  "identify": "TCH-98-上易-422-20100105-1",
  "court": {
    "name": "臺灣高等法院",
    "code": "TCH"
  },
  "division": {
    "name": "民事",
    "code": "V"
  },
  "year": 98,
  "word": "上易",
  "number": "422",
  "jcheck": "1",
  "reason": "損害賠償",
  "content": "臺灣高等法院臺中分院民事判決         98年度上易字第422號\n上  訴  人  彰化縣埔心鄉公所\n法定代理人  乙○○\n訴訟代理人  陳世煌律師\n訴訟代理人  黃俊昇律師\n被 上 訴人  雅立山企業有限公司\n                        樓\n法定代理人  甲○\n                        樓\n法定代理人  戊○○\n法定代理人  丙○○\n法定代理人  庚○○\n法定代理人  丁○○\n法定代理人  己○○\n共      同\n訴訟代理人  吳光中律師\n上列當事人間請求損害賠償事件，上訴人對於中華民國98年8月14\n日臺灣臺中地方法院97年度訴字第2914號第一審判決提起上訴，\n本院於98年12月22日言詞辯論終結，判決如下：\n    主  文\n上訴駁回。\n第二審訴訟費用由上訴人負擔。\n    事實及理由\n一、查被上訴人於民國91年12月4日經主管機關為解散登記後，\n    迄未向原法院聲請呈報清算人，有經濟部函附公司變更登記\n    事項卡、及原法院查詢之審理單在卷可稽（見原審卷第60、\n    86至91頁），依公司法第24條、第25條、第26條之1、第113\n    條準用第79條規定，被上訴人應行清算程序，惟因股東未另\n    行選任清算人，依法即應以被上訴人全體股東為清算人，對\n    外代表公司進行本件訴訟，合先說明。\n二、上訴人主張：上訴人曾於90年3月7日將彰化縣埔心鄉內第三\n    （經口）、第四（舊館）、第五（新館）、第六（羅厝）、\n    第七（梧鳳）、第八（二重）第六座公墓，墓區內計約29.0\n    6公頃之除草維護工作，委由被上訴人施作。嗣因第四（舊\n    館）、第七（梧鳳）公墓有除草需要，且依中央機關未達公\n    告金額採購招標辦法第5條規定得不經公告程序，逕洽廠商\n    採購，上訴人遂於91年9月4日聯繫有公墓除草經驗之被上訴\n    人進行議價，並於同日議定按原條件以新台幣（下同）65,0\n    00元將第四（舊館）、第七（梧鳳）公墓除草工作委由被上\n    訴人施作，並確定被上訴人應於91年10月28日進行公墓除草\n    工作。詎被上訴人於91年10月28日上午以放火燃燒方式清除\n    第四公墓內之雜草時，竟未預先在四周開闢防火巷，加以當\n    日風勢強勁，致火勢失控蔓延至公墓北側之埔心鄉○○段86\n    2地號農地，造成訴外人黃永懷、黃坤煌及黃福賜合資種植\n    之圓葉蒲葵遭火焚毀，損失共計410萬元。嗣訴外人黃永懷\n    （訴外人黃坤煌、及黃福賜之請求權讓與黃永懷）與上訴人\n    於95年11月15日鈞院95年上國更(一)字第2號國家賠償事件審\n    理中達成和解，上訴人同意給付黃永懷99萬元，並已於96年\n    2月15日給付完畢。惟此損害係因被上訴人上開行為所造行\n    ，被上訴人顯有過失，上訴人因和解支付予黃永懷之99萬元\n    ，及因該事件支出一至三審裁判費暨第三審律師酬金計120,\n    035元，合計為1,110,035元，爰依國家賠償法第4條第2項規\n    定，請求被上訴人應給付予上訴人（上訴人於本院審理中已\n    捨棄此項法律關係主張，就此部分茲不再論述）。又倘認被\n    上訴人清除公墓雜草所為之行為，非屬行使公權力，然本件\n    係因被上訴人之加害給付致第三人之作物遭焚毀，並造成第\n    三人向上訴人追償，上訴人自受有損害；而兩造於91年9月4\n    日議定之除草工作雖未再立書面契約，然依被上訴人開立予\n    上訴人之統一發票，及事發後上訴人邀同被上訴人協商賠償\n    事宜之函文，即可證上訴人業將上開第四（舊館）、第七（\n    梧鳳）公墓除草維護工作委由被上訴人施作，兩造間確有契\n    約關係存在，則上訴人代被上訴人與第三人達成和解，並代\n    為償還上開賠償金額後，自得依兩造間之承攬契約、及無因\n    管理、不當得利法律關係，請求被上訴人給付上訴人上開賠\n    償金額及必要費用。爰聲明求為判決：被上訴人應給付上訴\n    人1,110,035元，及自起訴狀繕本送達翌日起至清償日止，\n    按年息5%計算之利息；上訴人願供擔保，請准宣告假執行。\n    【原審判決駁回上訴人之訴及其假執行之聲請。上訴人不服\n    ，提起本件上訴。】\n三、被上訴人則辯以：被上訴人於91年9月4日與上訴人議定之除\n    草工作，於91年10月23日即已完成，迄今未領到錢係因上訴\n    人沒有通知，故91年10月28日發生之火災係上訴人自行僱工\n    處理所釀致災害，與被上訴人無涉。被上訴人雖曾於90年3\n    月7日與上訴人簽訂承包一般公墓除草維護工作契約，然該\n    契約期間係自簽約之日起至90年3月25日止，且已驗收合格\n    完成，並領取工程款，兩造契約關係已告終結；本件火災發\n    生時，兩造間既未訂有書面除草契約，上訴人依前開合約書\n    第6條約定主張被上訴人應負本件損害賠償責任，即屬無據\n    。又縱認兩造間有承攬契約存在，系爭火災係被上訴人派人\n    除草所致者，依民法第189條規定、及最高法院18年上字第2\n    010號判例意旨，定作人於定作或指示無過失時，對承攬人\n    為承攬事項加害於第三人者，不負賠償責任；上訴人既主張\n    其與被上訴人間有公墓除草之承攬契約存在，上訴人為定作\n    人，依上訴人於訴外人黃永懷對其請求國家賠償時所為之拒\n    絕賠償理由書所載，上訴人主張其對於承攬事務並無定作或\n    指示上之任何過失，則上訴人對於訴外人黃永懷等人自無須\n    負損害賠償責任，被上訴人對上訴人亦無加害給付之情事。\n    至上訴人自願放棄法律所賦與之權利，與訴外人黃永懷和解\n    ，其所為係屬無義務之給付，所致財產之損害，自與被上訴\n    人無涉，不能因上訴人與黃永懷於上開國家賠償事件中成立\n    和解，並賠償黃永懷之損害，即認符合加害給付要件。況依\n    上訴人於原審提出之91年10月31日心鄉民字第0910010940號\n    函內容，可知上訴人於91年10月31日即已知上開舊館公墓北\n    側0.4公頃農地苗園，因處理雜草焚燒工作不慎遭毀損之情\n    事，是系爭火災縱為被上訴人除草所致，而上訴人得依承攬\n    契約法律關係向被上訴人請求賠償者，上訴人之損害賠償請\n    求權，依民法第514條規定，亦已逾1年短期時效，而罹於時\n    效消滅，被上訴人自得拒絕賠償。再者，系爭火災為91年10\n    月28日，如認放火工人係被上訴人所聘僱，則訴外人黃永懷\n    等三人於92年4月接獲上訴人之拒絕賠償理由書時，即應知\n    該公墓除草承攬人為被上訴人，其等對於被上訴人之侵權行\n    為損害賠償請求權，自斯時起算至上訴人95年11月15日與訴\n    外人為訴訟上和解時，早逾民法第197條所定之2年請求權時\n    效，被上訴人本即可拒絕賠償，故上訴人上開所為之和解，\n    顯不利於被上訴人，且不符合被上訴人明示或可得推知之意\n    思，自不符合無因管理之要件，而無無因管理規定之適用。\n    又被上訴人既為上開國家賠償事件中之利害關係人，依民事\n    訴訟法第65條規定上訴人應為告知訴訟，然上訴人竟未為告\n    知訴訟，即擅自與第三人為訴訟上之和解，因而產生之上開\n    費用，自屬上訴人自己行為所致之損害，應自行負責，其請\n    求被上訴人賠償，於法無據。又上訴人另依不當得利法律關\n    係請求，惟被上訴人本得以黃永懷等人之請求權已罹於時效\n    為由拒絕賠償，惟上訴人卻仍與之和解並為之清償，顯未使\n    被上訴人獲得任何利益，上訴人主張兩造間財產損益變動，\n    得依不當得利規定處理，亦屬無據等語。\n四、查上訴人主張其曾於90年3月7日將彰化縣埔心鄉內第三（經\n    口）、第四（舊館）、第五（新館）、第六（羅厝）、第七\n    （梧鳳）、第八（二重）第六座公墓，墓區內計約29.06公\n    頃之除草維護工作，委由被上訴人施作；嗣因第四（舊館）\n    、第七（梧鳳）公墓除草工作，依中央機關未達公告金額採\n    購招標辦法第5條規定，得不經公告程序，逕洽廠商採購，\n    上訴人於91年9月4日聯繫有公墓除草經驗之被上訴人人員張\n    力升進行議價；被上訴人曾於91年10月23日開立載有「舊館\n    、梧鳳公墓除草公作，金額65,000元」之統一發票予上訴人\n    ；彰化縣第四（舊館）公墓於91年10月28日上午以放火燃燒\n    方式，清除第四公墓內之雜草時，因未預先於放火燃燒前之\n    四周開闢防火巷，致火勢失控蔓延至公墓北側之埔心鄉○○\n    段862地號農地，造成訴外人黃永懷、黃坤煌及黃福賜合資\n    種植之圓葉蒲葵遭火焚毀；而上訴人與訴外人黃永懷於95年\n    11月15日於本院95年上國更(一)字第2號國家賠償事件審理中\n    成立和解，上訴人同意給付黃永懷99萬元，並已於96年2月\n    15日給付完畢等情，業據上訴人提出公墓除草維護工作合約\n    書、原法院92年國字第4號判決、本院94年上國字第5號判決\n    、本院95年上國更(一)字第2號和解筆錄、最高法院95年台上\n    字第1445號判決、上訴人與訴外人黃永懷等人於95年11月9\n    日商討和解會議記錄、黃永懷於96年2月15日出具已領受99\n    萬元和解金之收據、上訴人簽呈、及被上訴人開立之統一發\n    票等件為證，並為被上訴人所不爭執，堪信上訴人上開部分\n    之主張為真實。\n五、惟上訴人主張兩造間就91年10月第四（舊館）、第七（梧鳳\n    ）公墓之除草工作有承攬契約關係存在，且系爭火災係被上\n    訴人派人除草所致；被上訴人未開闢防火巷或採取其他安全\n    措施即以放火焚燒之方式清除雜草，造成訴外人黃永懷、黃\n    坤煌、及黃福賜合資種植之圓葉蒲葵遭火焚毀，被上訴人執\n    行承攬工作顯有疏失，對上訴人應負損害賠償責任，則上訴\n    人代被上訴人與訴外人黃永懷達成和解，並代為賠償99萬元\n    、及其他必要費用總計1,110,035元，自得依兩造間承攬契\n    約、及民法無因管理、不當得利法律關係，請求被上訴人給\n    付等節，則為被上訴人所否認，並以上詞置辯。經查：\n  (一)關於彰化縣埔心鄉第四（舊館）公墓，91年10月28日發生火\n    災之除草工作，是否為被上訴人所承攬施作部分：\n  1.查上訴人主張第四（舊館）、第七（梧鳳）公墓91年度除草\n    工作，係其於91年9月4日聯繫被上訴人法定代理人張力升進\n    行議價，並於同日議定以65,000元，將該二公墓除草工作委\n    由被上訴人施作一節，業據上訴人提出兩造於90年3月7日簽\n    訂合約書、上訴人機關簽呈暨簽准公文、及被上訴人於91年\n    10月23日開立載有：「舊館、梧鳳公墓除草公作，金額65,0\n    00元」之統一發票（見原審卷第76至79頁、及第124至126頁\n    ）為證，並經被上訴人法定代理人張力升於原法院98年4月\n    16日審理中自承在卷（見原審卷第157頁），及據證人即負\n    責埔心鄉公所總務工作人員黃進智於原審審理中證稱：「90\n    年3月7日起至90年3月25日之期間內的除草業務是被上訴人\n    負責的。後來91年9月時候我們業務單位再提出申請，要做\n    除草工作，因為是10萬元以下，被上訴人以前有承包過我們\n    這個工作，做的還不錯，所以我們就直接找被上訴人議價，\n    我打電話找被上訴人公司的張力升，打電話後他隔天就來我\n    們公所總務室商談如何除草的細節」等語（見原審卷第108\n    頁背面及第109頁），及證人即負責埔心鄉公所公墓業務承\n    辦人員陳冠良證稱：「91年9月公所欲施作舊館（第四公墓\n    ）、梧鳳公墓（第七公墓）除草工作時，因金額僅65,000元\n    ，沒有超過10萬元，總務科沒有經過上網直接找被上訴人來\n    談，我跟總務、雅立山公司的張力升三人洽談，之前簽約的\n    時候也是張力升，談的條件就是65,000元，範圍就是剛剛所\n    述的兩個公墓」等語甚詳（見原審卷第110頁），則上訴人\n    主張第四（舊館）公墓91年度除草工作，係由被上訴人承攬\n    施作一節，即堪認為真實。\n  2.被上訴人雖以：其於91年10月23日即已完成彰化縣第四（舊\n    館）公墓之除草工作，迄今未領到錢係因上訴人沒有通知，\n    故其於91年10月28日不可能再派員除草，當日發生之火災應\n    係上訴人自行僱工處理所釀致災害，與被上訴人無涉等語。\n    惟查：兩造就彰化縣第四（舊館）公墓於91年10月28日上午\n    ，確有人以放火燃燒方式清除雜草時，因未預先於放火燃燒\n    前四周開闢防火巷，致火勢失控蔓延至公墓北側之埔心鄉○\n    ○段第862地號農地，造成訴外人黃永懷、黃坤煌及黃福賜\n    合資種植之圓葉蒲葵遭火焚毀一節，均不爭執（見原審卷第\n    156頁背面）；又依兩造於90年3月7日所訂合約書內容記載\n    ，被上訴人所承包之公墓除草工作係以噴灑除草藥劑及焚燒\n    方式整理（見原審卷第8、10頁）；再參以證人陳冠良證稱\n    ：「91年9月3日我們跟被上訴人聯絡，9月4日其來跟我們談\n    除草工作，我們請其91年9月20日到10月20日間去施作，如\n    果提早完工，我們就提早驗收完畢。被上訴人應該是9月4日\n    就開始去施作了，本來的驗收時間是91年10月23日，因為當\n    天消防隊沒有辦法支援，所以我們與廠商聯繫後驗收時間改\n    為91年10月28日，我與被上訴人的聯繫都是張力升，驗收的\n    情形是被上訴人要將公墓現場的草處理好，通常除草的驗收\n    我們會請廠商開好防火巷，請消防隊到，廠商處理好除好的\n    草才會完成，結果當天消防隊員還沒有來，公所的人也還沒\n    有到，張力升也還沒有到，但是張力升的工人先到了，他的\n    工人就先放火燒草了。」等語（見原審卷第110頁），又依\n    彰化縣消防局98年4月17日0980011582號函記載：「本案經\n    轄區埔心分隊調閱相關資料之後，當日（即91年10月28日）\n    確有執行本轄埔心鄉舊館公墓防火宣導與警戒工作之勤務．\n    ．．」等語（見原審卷第146至151頁），足認；彰化縣第四\n   （舊館）公墓91年度之除草工作迄至91年10月28日上午，應\n    仍尚未完成。而被上訴人固於91年10月23日先簽發統一發票\n    予承辦人員，惟上訴人迄今尚未付款，為被上訴人所不爭執\n    ，再參以證人陳冠良證稱：「發票有送來公所，但我們還沒\n    有就本件的款項給付給被上訴人，因為發生焚燒到鄰地的事\n    件，所以65,000元還沒有支付」等語（見原審卷第110頁背\n    面），顯見，上開除草工作應尚未施作完畢驗收，上訴人始\n    未於被上訴人出具發票時付款；又被上訴人倘確已於91年10\n    月23日清除雜草完畢，衡情尚無可能於其交付統一發票向上\n    訴人請款後，任憑上訴人恁置多年未付款而未為請求之理，\n    是被上訴人辯稱，其已於91年10月23日將彰化縣第四（舊館\n    ）公墓雜草清除完畢，不可能於91年10月28日再派員除草云\n    云，非為可採。又被上訴人確向上訴人承攬系爭除草工作，\n    且於91年10月28日第四（舊館）公墓尚有雜草待除，既已如\n    上述，則該除草工作既為被上訴人所承攬之工作，他人何須\n    無故代其除草？且於該日上午確有人員以火燒方式除草，證\n    人陳冠良亦證稱：「發生火災當天其有到現場，其到達現場\n    的時候公墓已經煙霧迷漫，廠商的工人在場，但是張力升還\n    沒有到。張力升後來到的時候有告訴我們那個工人是他從和\n    美請來的。」等語（見原審卷第111頁），再參諸上訴人曾\n    於事發後之91年10月31日發函予被上訴人，請其儘速會同上\n    訴人與地主商討賠償事宜等情（見原審卷第80頁），足見，\n    案發日在現場從事放火除草之人員，確係被上訴人為進行其\n    承攬之除草工作所委派無訛，被上訴人辯稱當日發生之火災\n    係上訴人自行僱工處理所釀致災害，與被上訴人公司無涉云\n    云，亦無足採。\n  (二)彰化縣埔心鄉第四（舊館）公墓91年10月28日發生火災之除\n    草工作，為被上訴人所承攬施作，上訴人支出之上開和解金\n    及必要費用，得否依承攬契約請求被上訴人賠償損害？按承\n    攬人因執行承攬事項，不法侵害他人之權利者，定作人不負\n    損害賠償責任；但定作人於定作或指示有過失者，不在此限\n    。民法第189條亦定有明文。即定作人於定作或指示無過失\n    者，就承攬人因執行承攬事項，不法侵害他人之權利，不負\n    損害賠償責任。查上訴人委請被上訴人除草，被上訴人以放\n    火方式為之，因系爭放火除草之地點與訴外人黃永懷、黃坤\n    煌及黃福賜種植圓葉蒲葵之田地相鄰，於放火燒草之際可能\n    延及他人受損之情事，為兩造所明知，是於被上訴人放火除\n    草之際，上訴人本有委請彰化縣消防局埔心分隊派員執行警\n    戒工作之勤務，且被上訴人亦應先行開闢防火巷以免火勢過\n    大延及他人；詎被上訴人未待消防人員到達，更未在現場闢\n    出防火巷，即自行放火除草致損及他人所種植之農作物，則\n    被上訴人就黃永懷、黃坤煌及黃福賜所受之上開損害，即應\n    由被上訴人負侵權行為損害賠償責任。上訴人既已委請彰化\n    縣消防局埔心分隊派員執行警戒工作之勤務，有上開彰化縣\n    消防局函文附於原審卷內可稽，其於訴外人黃永懷請求國家\n    賠償時所為之拒絕賠償理由書，亦載明本件工作係由被上訴\n    人所承攬，依民法第189條規定，其不負賠償責任等語（見\n    本院卷第59頁），及依上訴人主張兩造承攬契約沿用90年3\n    月7日合約條款第6條約定，即：「乙方（即被上訴人）於進\n    行焚燒及噴灑除草藥劑時應預防危險，如因此損害私人財產\n    造成其他糾紛一切賠償責任，均應由乙方自行負責，甲方（\n    即上訴人）不負任何責任」等語，依該約定，如有任何損害\n    發生，須對第三人負賠償責任者，係施作者之被上訴人，上\n    訴人本毋庸負本件賠償責任。是上訴人於上開國家賠償事件\n    中，與訴外人黃永懷達成和解並給付和解金，應與兩造間簽\n    訂之承攬契約約定條款無涉，則上訴人依承攬契約法律關係\n    ，請求被上訴人應賠償其支出之損害金及相關必要費用，核\n    屬無據。\n  (三)上訴人得否就其與訴外人黃永懷和解所支出之損害賠償及其\n    他必要費用，依無因管理、及不當得利法律關係請求被上訴\n    人負賠償責任？\n  1.上訴人主張其支付予訴外人黃永懷之上開賠償金及其他必要\n    費用，亦得依民法無因管理法律關係，請求被上訴人給付等\n    語。按未受委任，並無義務，而為他人管理事務者，其管理\n    應依本人明示或可得推知之意思，以有利於本人之方法為之\n    。又管理人開始管理時，以能通知為限，應即通知本人；如\n    無急迫之情事，應俟本人之指示。再管理事務利於本人，並\n    不違反本人明示或可得推知之意思者，管理人為本人支出必\n    要或有益之費用，或負擔債務，或受損害時，得請求本人償\n    還其費用及自支出時起之利息，或清償其所負擔之債務或賠\n    償其損害。民法第172條、第173條第1項、及第176條第1項\n    定有明文。又按侵權行為所生之損害賠償請求權，自請求權\n    人知有損害及賠償義務人時起，二年間不行使而消滅。自有\n    侵權行為時起，逾10年者亦同。民法第197條第1項亦有明文\n    。查系爭火災發生於91年10月28日，又訴外人黃永懷等三人\n    請求上訴人國家賠償遭拒絕，其等至遲於92年4月間接獲上\n    訴人之拒絕賠償理由書時，即知侵權行為人為被上訴人，損\n    害賠償請求權自該時起算至上訴人95年11月15日與訴外人為\n    訴訟上和解時，早已罹於時效而消滅，而上訴人於上開國家\n    賠償事件中，卻仍於95年11月15日與訴外人黃永懷達成和解\n    ，並給付黃永懷99萬元，雖可認上訴人之上開行為，有未受\n    委任，並無義務，而為被上訴人管理事務之行為，與無因管\n    理要件，尚屬相符；惟上訴人自系爭災發生時，即已知被上\n    訴人對訴外人黃永懷應負損害賠償責任，其並無不能通知被\n    上訴人之情事，惟卻未依民事訴訟法第65條規定，告知被上\n    訴人及時參加訴訟，使被上訴人對於該損害賠償金額、賠償\n    範圍、甚或時效問題，有答辯之機會，則上訴人於95年11月\n    15日與訴外人黃永懷達成和解，給付黃永懷99萬元，已難認\n    上訴人所為上開事務之管理，為有利於本人之被上訴人，自\n    不符上開適法無因管理人得請求本人償還費用、或賠償損害\n    之要件。上訴人依民法無因管理法律關係，請求被上訴人應\n    給付上開損害賠償金及其他必要費用，亦洵屬無據。\n  2.上訴人於本院又主張依民法不當得利法律關係請求一節．按\n    無法律上之原因而受利益，致他人受損害者，應返還其利益\n    。民法第179條前段定有明文。查訴外人黃永懷對被上訴人\n    之侵權行為請求權，早已罹於時效而消滅，已如上述，被上\n    訴人本得拒絕為賠償，無庸對訴外人黃永懷為任何之賠償給\n    付，則上訴人主張其代被上訴人清償予黃永懷，顯未使被上\n    訴人受有任何利益可言，上訴人主張兩造間財產損益有變動\n    云云，應依不當得利規定處理云云，亦為無理由。\n六、綜上所述，上訴人主張依承攬契約、無因管理、及不當得利\n    法律關係，請求被上訴人應給付上訴人1,110,035元，及自\n    起訴狀繕本送達翌日起至清償日止，按年息5%計算之利息，\n    為無理由，應予駁回。原審為上訴人敗訴之判決，並無不合\n    ，上訴意旨猶執詞指摘原判決不當，求予廢棄改判，為無理\n    由，應予駁回。\n七、本案事實已臻明確，兩造其餘攻擊防禦方法，不足以影響本\n    判決結果，爰不一一論述，併此敘明。\n據上論結：本件上訴為無理由，依民事訴訟法第449條第1項、第\n78條，判決如主文。\n中    華    民    國    99    年     1    月     5    日\n                民事第四庭    審判長法  官  陳蘇宗\n                                    法  官  黃永祥\n                                    法  官  張浴美\n以上正本係照原本作成。\n不得上訴。\n                                    書記官  阮正枝\n中    華    民    國    99    年    1     月    5     日\n                                                      Ｓ\n",
  "structure": {
    "main": "上訴駁回。\n第二審訴訟費用由上訴人負擔。",
    "fact": "一、查被上訴人於民國91年12月4日經主管機關為解散登記後，\n    迄未向原法院聲請呈報清算人，有經濟部函附公司變更登記\n    事項卡、及原法院查詢之審理單在卷可稽（見原審卷第60、\n    86至91頁），依公司法第24條、第25條、第26條之1、第113\n    條準用第79條規定，被上訴人應行清算程序，惟因股東未另\n    行選任清算人，依法即應以被上訴人全體股東為清算人，對\n    外代表公司進行本件訴訟，合先說明。\n二、上訴人主張：上訴人曾於90年3月7日將彰化縣埔心鄉內第三\n    （經口）、第四（舊館）、第五（新館）、第六（羅厝）、\n    第七（梧鳳）、第八（二重）第六座公墓，墓區內計約29.0\n    6公頃之除草維護工作，委由被上訴人施作。嗣因第四（舊\n    館）、第七（梧鳳）公墓有除草需要，且依中央機關未達公\n    告金額採購招標辦法第5條規定得不經公告程序，逕洽廠商\n    採購，上訴人遂於91年9月4日聯繫有公墓除草經驗之被上訴\n    人進行議價，並於同日議定按原條件以新台幣（下同）65,0\n    00元將第四（舊館）、第七（梧鳳）公墓除草工作委由被上\n    訴人施作，並確定被上訴人應於91年10月28日進行公墓除草\n    工作。詎被上訴人於91年10月28日上午以放火燃燒方式清除\n    第四公墓內之雜草時，竟未預先在四周開闢防火巷，加以當\n    日風勢強勁，致火勢失控蔓延至公墓北側之埔心鄉○○段86\n    2地號農地，造成訴外人黃永懷、黃坤煌及黃福賜合資種植\n    之圓葉蒲葵遭火焚毀，損失共計410萬元。嗣訴外人黃永懷\n    （訴外人黃坤煌、及黃福賜之請求權讓與黃永懷）與上訴人\n    於95年11月15日鈞院95年上國更(一)字第2號國家賠償事件審\n    理中達成和解，上訴人同意給付黃永懷99萬元，並已於96年\n    2月15日給付完畢。惟此損害係因被上訴人上開行為所造行\n    ，被上訴人顯有過失，上訴人因和解支付予黃永懷之99萬元\n    ，及因該事件支出一至三審裁判費暨第三審律師酬金計120,\n    035元，合計為1,110,035元，爰依國家賠償法第4條第2項規\n    定，請求被上訴人應給付予上訴人（上訴人於本院審理中已\n    捨棄此項法律關係主張，就此部分茲不再論述）。又倘認被\n    上訴人清除公墓雜草所為之行為，非屬行使公權力，然本件\n    係因被上訴人之加害給付致第三人之作物遭焚毀，並造成第\n    三人向上訴人追償，上訴人自受有損害；而兩造於91年9月4\n    日議定之除草工作雖未再立書面契約，然依被上訴人開立予\n    上訴人之統一發票，及事發後上訴人邀同被上訴人協商賠償\n    事宜之函文，即可證上訴人業將上開第四（舊館）、第七（\n    梧鳳）公墓除草維護工作委由被上訴人施作，兩造間確有契\n    約關係存在，則上訴人代被上訴人與第三人達成和解，並代\n    為償還上開賠償金額後，自得依兩造間之承攬契約、及無因\n    管理、不當得利法律關係，請求被上訴人給付上訴人上開賠\n    償金額及必要費用。爰聲明求為判決：被上訴人應給付上訴\n    人1,110,035元，及自起訴狀繕本送達翌日起至清償日止，\n    按年息5%計算之利息；上訴人願供擔保，請准宣告假執行。\n    【原審判決駁回上訴人之訴及其假執行之聲請。上訴人不服\n    ，提起本件上訴。】\n三、被上訴人則辯以：被上訴人於91年9月4日與上訴人議定之除\n    草工作，於91年10月23日即已完成，迄今未領到錢係因上訴\n    人沒有通知，故91年10月28日發生之火災係上訴人自行僱工\n    處理所釀致災害，與被上訴人無涉。被上訴人雖曾於90年3\n    月7日與上訴人簽訂承包一般公墓除草維護工作契約，然該\n    契約期間係自簽約之日起至90年3月25日止，且已驗收合格\n    完成，並領取工程款，兩造契約關係已告終結；本件火災發\n    生時，兩造間既未訂有書面除草契約，上訴人依前開合約書\n    第6條約定主張被上訴人應負本件損害賠償責任，即屬無據\n    。又縱認兩造間有承攬契約存在，系爭火災係被上訴人派人\n    除草所致者，依民法第189條規定、及最高法院18年上字第2\n    010號判例意旨，定作人於定作或指示無過失時，對承攬人\n    為承攬事項加害於第三人者，不負賠償責任；上訴人既主張\n    其與被上訴人間有公墓除草之承攬契約存在，上訴人為定作\n    人，依上訴人於訴外人黃永懷對其請求國家賠償時所為之拒\n    絕賠償理由書所載，上訴人主張其對於承攬事務並無定作或\n    指示上之任何過失，則上訴人對於訴外人黃永懷等人自無須\n    負損害賠償責任，被上訴人對上訴人亦無加害給付之情事。\n    至上訴人自願放棄法律所賦與之權利，與訴外人黃永懷和解\n    ，其所為係屬無義務之給付，所致財產之損害，自與被上訴\n    人無涉，不能因上訴人與黃永懷於上開國家賠償事件中成立\n    和解，並賠償黃永懷之損害，即認符合加害給付要件。況依\n    上訴人於原審提出之91年10月31日心鄉民字第0910010940號\n    函內容，可知上訴人於91年10月31日即已知上開舊館公墓北\n    側0.4公頃農地苗園，因處理雜草焚燒工作不慎遭毀損之情\n    事，是系爭火災縱為被上訴人除草所致，而上訴人得依承攬\n    契約法律關係向被上訴人請求賠償者，上訴人之損害賠償請\n    求權，依民法第514條規定，亦已逾1年短期時效，而罹於時\n    效消滅，被上訴人自得拒絕賠償。再者，系爭火災為91年10\n    月28日，如認放火工人係被上訴人所聘僱，則訴外人黃永懷\n    等三人於92年4月接獲上訴人之拒絕賠償理由書時，即應知\n    該公墓除草承攬人為被上訴人，其等對於被上訴人之侵權行\n    為損害賠償請求權，自斯時起算至上訴人95年11月15日與訴\n    外人為訴訟上和解時，早逾民法第197條所定之2年請求權時\n    效，被上訴人本即可拒絕賠償，故上訴人上開所為之和解，\n    顯不利於被上訴人，且不符合被上訴人明示或可得推知之意\n    思，自不符合無因管理之要件，而無無因管理規定之適用。\n    又被上訴人既為上開國家賠償事件中之利害關係人，依民事\n    訴訟法第65條規定上訴人應為告知訴訟，然上訴人竟未為告\n    知訴訟，即擅自與第三人為訴訟上之和解，因而產生之上開\n    費用，自屬上訴人自己行為所致之損害，應自行負責，其請\n    求被上訴人賠償，於法無據。又上訴人另依不當得利法律關\n    係請求，惟被上訴人本得以黃永懷等人之請求權已罹於時效\n    為由拒絕賠償，惟上訴人卻仍與之和解並為之清償，顯未使\n    被上訴人獲得任何利益，上訴人主張兩造間財產損益變動，\n    得依不當得利規定處理，亦屬無據等語。\n四、查上訴人主張其曾於90年3月7日將彰化縣埔心鄉內第三（經\n    口）、第四（舊館）、第五（新館）、第六（羅厝）、第七\n    （梧鳳）、第八（二重）第六座公墓，墓區內計約29.06公\n    頃之除草維護工作，委由被上訴人施作；嗣因第四（舊館）\n    、第七（梧鳳）公墓除草工作，依中央機關未達公告金額採\n    購招標辦法第5條規定，得不經公告程序，逕洽廠商採購，\n    上訴人於91年9月4日聯繫有公墓除草經驗之被上訴人人員張\n    力升進行議價；被上訴人曾於91年10月23日開立載有「舊館\n    、梧鳳公墓除草公作，金額65,000元」之統一發票予上訴人\n    ；彰化縣第四（舊館）公墓於91年10月28日上午以放火燃燒\n    方式，清除第四公墓內之雜草時，因未預先於放火燃燒前之\n    四周開闢防火巷，致火勢失控蔓延至公墓北側之埔心鄉○○\n    段862地號農地，造成訴外人黃永懷、黃坤煌及黃福賜合資\n    種植之圓葉蒲葵遭火焚毀；而上訴人與訴外人黃永懷於95年\n    11月15日於本院95年上國更(一)字第2號國家賠償事件審理中\n    成立和解，上訴人同意給付黃永懷99萬元，並已於96年2月\n    15日給付完畢等情，業據上訴人提出公墓除草維護工作合約\n    書、原法院92年國字第4號判決、本院94年上國字第5號判決\n    、本院95年上國更(一)字第2號和解筆錄、最高法院95年台上\n    字第1445號判決、上訴人與訴外人黃永懷等人於95年11月9\n    日商討和解會議記錄、黃永懷於96年2月15日出具已領受99\n    萬元和解金之收據、上訴人簽呈、及被上訴人開立之統一發\n    票等件為證，並為被上訴人所不爭執，堪信上訴人上開部分\n    之主張為真實。\n五、惟上訴人主張兩造間就91年10月第四（舊館）、第七（梧鳳\n    ）公墓之除草工作有承攬契約關係存在，且系爭火災係被上\n    訴人派人除草所致；被上訴人未開闢防火巷或採取其他安全\n    措施即以放火焚燒之方式清除雜草，造成訴外人黃永懷、黃\n    坤煌、及黃福賜合資種植之圓葉蒲葵遭火焚毀，被上訴人執\n    行承攬工作顯有疏失，對上訴人應負損害賠償責任，則上訴\n    人代被上訴人與訴外人黃永懷達成和解，並代為賠償99萬元\n    、及其他必要費用總計1,110,035元，自得依兩造間承攬契\n    約、及民法無因管理、不當得利法律關係，請求被上訴人給\n    付等節，則為被上訴人所否認，並以上詞置辯。經查：\n  (一)關於彰化縣埔心鄉第四（舊館）公墓，91年10月28日發生火\n    災之除草工作，是否為被上訴人所承攬施作部分：\n  1.查上訴人主張第四（舊館）、第七（梧鳳）公墓91年度除草\n    工作，係其於91年9月4日聯繫被上訴人法定代理人張力升進\n    行議價，並於同日議定以65,000元，將該二公墓除草工作委\n    由被上訴人施作一節，業據上訴人提出兩造於90年3月7日簽\n    訂合約書、上訴人機關簽呈暨簽准公文、及被上訴人於91年\n    10月23日開立載有：「舊館、梧鳳公墓除草公作，金額65,0\n    00元」之統一發票（見原審卷第76至79頁、及第124至126頁\n    ）為證，並經被上訴人法定代理人張力升於原法院98年4月\n    16日審理中自承在卷（見原審卷第157頁），及據證人即負\n    責埔心鄉公所總務工作人員黃進智於原審審理中證稱：「90\n    年3月7日起至90年3月25日之期間內的除草業務是被上訴人\n    負責的。後來91年9月時候我們業務單位再提出申請，要做\n    除草工作，因為是10萬元以下，被上訴人以前有承包過我們\n    這個工作，做的還不錯，所以我們就直接找被上訴人議價，\n    我打電話找被上訴人公司的張力升，打電話後他隔天就來我\n    們公所總務室商談如何除草的細節」等語（見原審卷第108\n    頁背面及第109頁），及證人即負責埔心鄉公所公墓業務承\n    辦人員陳冠良證稱：「91年9月公所欲施作舊館（第四公墓\n    ）、梧鳳公墓（第七公墓）除草工作時，因金額僅65,000元\n    ，沒有超過10萬元，總務科沒有經過上網直接找被上訴人來\n    談，我跟總務、雅立山公司的張力升三人洽談，之前簽約的\n    時候也是張力升，談的條件就是65,000元，範圍就是剛剛所\n    述的兩個公墓」等語甚詳（見原審卷第110頁），則上訴人\n    主張第四（舊館）公墓91年度除草工作，係由被上訴人承攬\n    施作一節，即堪認為真實。\n  2.被上訴人雖以：其於91年10月23日即已完成彰化縣第四（舊\n    館）公墓之除草工作，迄今未領到錢係因上訴人沒有通知，\n    故其於91年10月28日不可能再派員除草，當日發生之火災應\n    係上訴人自行僱工處理所釀致災害，與被上訴人無涉等語。\n    惟查：兩造就彰化縣第四（舊館）公墓於91年10月28日上午\n    ，確有人以放火燃燒方式清除雜草時，因未預先於放火燃燒\n    前四周開闢防火巷，致火勢失控蔓延至公墓北側之埔心鄉○\n    ○段第862地號農地，造成訴外人黃永懷、黃坤煌及黃福賜\n    合資種植之圓葉蒲葵遭火焚毀一節，均不爭執（見原審卷第\n    156頁背面）；又依兩造於90年3月7日所訂合約書內容記載\n    ，被上訴人所承包之公墓除草工作係以噴灑除草藥劑及焚燒\n    方式整理（見原審卷第8、10頁）；再參以證人陳冠良證稱\n    ：「91年9月3日我們跟被上訴人聯絡，9月4日其來跟我們談\n    除草工作，我們請其91年9月20日到10月20日間去施作，如\n    果提早完工，我們就提早驗收完畢。被上訴人應該是9月4日\n    就開始去施作了，本來的驗收時間是91年10月23日，因為當\n    天消防隊沒有辦法支援，所以我們與廠商聯繫後驗收時間改\n    為91年10月28日，我與被上訴人的聯繫都是張力升，驗收的\n    情形是被上訴人要將公墓現場的草處理好，通常除草的驗收\n    我們會請廠商開好防火巷，請消防隊到，廠商處理好除好的\n    草才會完成，結果當天消防隊員還沒有來，公所的人也還沒\n    有到，張力升也還沒有到，但是張力升的工人先到了，他的\n    工人就先放火燒草了。」等語（見原審卷第110頁），又依\n    彰化縣消防局98年4月17日0980011582號函記載：「本案經\n    轄區埔心分隊調閱相關資料之後，當日（即91年10月28日）\n    確有執行本轄埔心鄉舊館公墓防火宣導與警戒工作之勤務．\n    ．．」等語（見原審卷第146至151頁），足認；彰化縣第四\n   （舊館）公墓91年度之除草工作迄至91年10月28日上午，應\n    仍尚未完成。而被上訴人固於91年10月23日先簽發統一發票\n    予承辦人員，惟上訴人迄今尚未付款，為被上訴人所不爭執\n    ，再參以證人陳冠良證稱：「發票有送來公所，但我們還沒\n    有就本件的款項給付給被上訴人，因為發生焚燒到鄰地的事\n    件，所以65,000元還沒有支付」等語（見原審卷第110頁背\n    面），顯見，上開除草工作應尚未施作完畢驗收，上訴人始\n    未於被上訴人出具發票時付款；又被上訴人倘確已於91年10\n    月23日清除雜草完畢，衡情尚無可能於其交付統一發票向上\n    訴人請款後，任憑上訴人恁置多年未付款而未為請求之理，\n    是被上訴人辯稱，其已於91年10月23日將彰化縣第四（舊館\n    ）公墓雜草清除完畢，不可能於91年10月28日再派員除草云\n    云，非為可採。又被上訴人確向上訴人承攬系爭除草工作，\n    且於91年10月28日第四（舊館）公墓尚有雜草待除，既已如\n    上述，則該除草工作既為被上訴人所承攬之工作，他人何須\n    無故代其除草？且於該日上午確有人員以火燒方式除草，證\n    人陳冠良亦證稱：「發生火災當天其有到現場，其到達現場\n    的時候公墓已經煙霧迷漫，廠商的工人在場，但是張力升還\n    沒有到。張力升後來到的時候有告訴我們那個工人是他從和\n    美請來的。」等語（見原審卷第111頁），再參諸上訴人曾\n    於事發後之91年10月31日發函予被上訴人，請其儘速會同上\n    訴人與地主商討賠償事宜等情（見原審卷第80頁），足見，\n    案發日在現場從事放火除草之人員，確係被上訴人為進行其\n    承攬之除草工作所委派無訛，被上訴人辯稱當日發生之火災\n    係上訴人自行僱工處理所釀致災害，與被上訴人公司無涉云\n    云，亦無足採。\n  (二)彰化縣埔心鄉第四（舊館）公墓91年10月28日發生火災之除\n    草工作，為被上訴人所承攬施作，上訴人支出之上開和解金\n    及必要費用，得否依承攬契約請求被上訴人賠償損害？按承\n    攬人因執行承攬事項，不法侵害他人之權利者，定作人不負\n    損害賠償責任；但定作人於定作或指示有過失者，不在此限\n    。民法第189條亦定有明文。即定作人於定作或指示無過失\n    者，就承攬人因執行承攬事項，不法侵害他人之權利，不負\n    損害賠償責任。查上訴人委請被上訴人除草，被上訴人以放\n    火方式為之，因系爭放火除草之地點與訴外人黃永懷、黃坤\n    煌及黃福賜種植圓葉蒲葵之田地相鄰，於放火燒草之際可能\n    延及他人受損之情事，為兩造所明知，是於被上訴人放火除\n    草之際，上訴人本有委請彰化縣消防局埔心分隊派員執行警\n    戒工作之勤務，且被上訴人亦應先行開闢防火巷以免火勢過\n    大延及他人；詎被上訴人未待消防人員到達，更未在現場闢\n    出防火巷，即自行放火除草致損及他人所種植之農作物，則\n    被上訴人就黃永懷、黃坤煌及黃福賜所受之上開損害，即應\n    由被上訴人負侵權行為損害賠償責任。上訴人既已委請彰化\n    縣消防局埔心分隊派員執行警戒工作之勤務，有上開彰化縣\n    消防局函文附於原審卷內可稽，其於訴外人黃永懷請求國家\n    賠償時所為之拒絕賠償理由書，亦載明本件工作係由被上訴\n    人所承攬，依民法第189條規定，其不負賠償責任等語（見\n    本院卷第59頁），及依上訴人主張兩造承攬契約沿用90年3\n    月7日合約條款第6條約定，即：「乙方（即被上訴人）於進\n    行焚燒及噴灑除草藥劑時應預防危險，如因此損害私人財產\n    造成其他糾紛一切賠償責任，均應由乙方自行負責，甲方（\n    即上訴人）不負任何責任」等語，依該約定，如有任何損害\n    發生，須對第三人負賠償責任者，係施作者之被上訴人，上\n    訴人本毋庸負本件賠償責任。是上訴人於上開國家賠償事件\n    中，與訴外人黃永懷達成和解並給付和解金，應與兩造間簽\n    訂之承攬契約約定條款無涉，則上訴人依承攬契約法律關係\n    ，請求被上訴人應賠償其支出之損害金及相關必要費用，核\n    屬無據。\n  (三)上訴人得否就其與訴外人黃永懷和解所支出之損害賠償及其\n    他必要費用，依無因管理、及不當得利法律關係請求被上訴\n    人負賠償責任？\n  1.上訴人主張其支付予訴外人黃永懷之上開賠償金及其他必要\n    費用，亦得依民法無因管理法律關係，請求被上訴人給付等\n    語。按未受委任，並無義務，而為他人管理事務者，其管理\n    應依本人明示或可得推知之意思，以有利於本人之方法為之\n    。又管理人開始管理時，以能通知為限，應即通知本人；如\n    無急迫之情事，應俟本人之指示。再管理事務利於本人，並\n    不違反本人明示或可得推知之意思者，管理人為本人支出必\n    要或有益之費用，或負擔債務，或受損害時，得請求本人償\n    還其費用及自支出時起之利息，或清償其所負擔之債務或賠\n    償其損害。民法第172條、第173條第1項、及第176條第1項\n    定有明文。又按侵權行為所生之損害賠償請求權，自請求權\n    人知有損害及賠償義務人時起，二年間不行使而消滅。自有\n    侵權行為時起，逾10年者亦同。民法第197條第1項亦有明文\n    。查系爭火災發生於91年10月28日，又訴外人黃永懷等三人\n    請求上訴人國家賠償遭拒絕，其等至遲於92年4月間接獲上\n    訴人之拒絕賠償理由書時，即知侵權行為人為被上訴人，損\n    害賠償請求權自該時起算至上訴人95年11月15日與訴外人為\n    訴訟上和解時，早已罹於時效而消滅，而上訴人於上開國家\n    賠償事件中，卻仍於95年11月15日與訴外人黃永懷達成和解\n    ，並給付黃永懷99萬元，雖可認上訴人之上開行為，有未受\n    委任，並無義務，而為被上訴人管理事務之行為，與無因管\n    理要件，尚屬相符；惟上訴人自系爭災發生時，即已知被上\n    訴人對訴外人黃永懷應負損害賠償責任，其並無不能通知被\n    上訴人之情事，惟卻未依民事訴訟法第65條規定，告知被上\n    訴人及時參加訴訟，使被上訴人對於該損害賠償金額、賠償\n    範圍、甚或時效問題，有答辯之機會，則上訴人於95年11月\n    15日與訴外人黃永懷達成和解，給付黃永懷99萬元，已難認\n    上訴人所為上開事務之管理，為有利於本人之被上訴人，自\n    不符上開適法無因管理人得請求本人償還費用、或賠償損害\n    之要件。上訴人依民法無因管理法律關係，請求被上訴人應\n    給付上開損害賠償金及其他必要費用，亦洵屬無據。\n  2.上訴人於本院又主張依民法不當得利法律關係請求一節．按\n    無法律上之原因而受利益，致他人受損害者，應返還其利益\n    。民法第179條前段定有明文。查訴外人黃永懷對被上訴人\n    之侵權行為請求權，早已罹於時效而消滅，已如上述，被上\n    訴人本得拒絕為賠償，無庸對訴外人黃永懷為任何之賠償給\n    付，則上訴人主張其代被上訴人清償予黃永懷，顯未使被上\n    訴人受有任何利益可言，上訴人主張兩造間財產損益有變動\n    云云，應依不當得利規定處理云云，亦為無理由。\n六、綜上所述，上訴人主張依承攬契約、無因管理、及不當得利\n    法律關係，請求被上訴人應給付上訴人1,110,035元，及自\n    起訴狀繕本送達翌日起至清償日止，按年息5%計算之利息，\n    為無理由，應予駁回。原審為上訴人敗訴之判決，並無不合\n    ，上訴意旨猶執詞指摘原判決不當，求予廢棄改判，為無理\n    由，應予駁回。\n七、本案事實已臻明確，兩造其餘攻擊防禦方法，不足以影響本\n    判決結果，爰不一一論述，併此敘明。\n據上論結：本件上訴為無理由，依民事訴訟法第449條第1項、第\n78條，判決如主文。",
    "reason": "一、查被上訴人於民國91年12月4日經主管機關為解散登記後，\n    迄未向原法院聲請呈報清算人，有經濟部函附公司變更登記\n    事項卡、及原法院查詢之審理單在卷可稽（見原審卷第60、\n    86至91頁），依公司法第24條、第25條、第26條之1、第113\n    條準用第79條規定，被上訴人應行清算程序，惟因股東未另\n    行選任清算人，依法即應以被上訴人全體股東為清算人，對\n    外代表公司進行本件訴訟，合先說明。\n二、上訴人主張：上訴人曾於90年3月7日將彰化縣埔心鄉內第三\n    （經口）、第四（舊館）、第五（新館）、第六（羅厝）、\n    第七（梧鳳）、第八（二重）第六座公墓，墓區內計約29.0\n    6公頃之除草維護工作，委由被上訴人施作。嗣因第四（舊\n    館）、第七（梧鳳）公墓有除草需要，且依中央機關未達公\n    告金額採購招標辦法第5條規定得不經公告程序，逕洽廠商\n    採購，上訴人遂於91年9月4日聯繫有公墓除草經驗之被上訴\n    人進行議價，並於同日議定按原條件以新台幣（下同）65,0\n    00元將第四（舊館）、第七（梧鳳）公墓除草工作委由被上\n    訴人施作，並確定被上訴人應於91年10月28日進行公墓除草\n    工作。詎被上訴人於91年10月28日上午以放火燃燒方式清除\n    第四公墓內之雜草時，竟未預先在四周開闢防火巷，加以當\n    日風勢強勁，致火勢失控蔓延至公墓北側之埔心鄉○○段86\n    2地號農地，造成訴外人黃永懷、黃坤煌及黃福賜合資種植\n    之圓葉蒲葵遭火焚毀，損失共計410萬元。嗣訴外人黃永懷\n    （訴外人黃坤煌、及黃福賜之請求權讓與黃永懷）與上訴人\n    於95年11月15日鈞院95年上國更(一)字第2號國家賠償事件審\n    理中達成和解，上訴人同意給付黃永懷99萬元，並已於96年\n    2月15日給付完畢。惟此損害係因被上訴人上開行為所造行\n    ，被上訴人顯有過失，上訴人因和解支付予黃永懷之99萬元\n    ，及因該事件支出一至三審裁判費暨第三審律師酬金計120,\n    035元，合計為1,110,035元，爰依國家賠償法第4條第2項規\n    定，請求被上訴人應給付予上訴人（上訴人於本院審理中已\n    捨棄此項法律關係主張，就此部分茲不再論述）。又倘認被\n    上訴人清除公墓雜草所為之行為，非屬行使公權力，然本件\n    係因被上訴人之加害給付致第三人之作物遭焚毀，並造成第\n    三人向上訴人追償，上訴人自受有損害；而兩造於91年9月4\n    日議定之除草工作雖未再立書面契約，然依被上訴人開立予\n    上訴人之統一發票，及事發後上訴人邀同被上訴人協商賠償\n    事宜之函文，即可證上訴人業將上開第四（舊館）、第七（\n    梧鳳）公墓除草維護工作委由被上訴人施作，兩造間確有契\n    約關係存在，則上訴人代被上訴人與第三人達成和解，並代\n    為償還上開賠償金額後，自得依兩造間之承攬契約、及無因\n    管理、不當得利法律關係，請求被上訴人給付上訴人上開賠\n    償金額及必要費用。爰聲明求為判決：被上訴人應給付上訴\n    人1,110,035元，及自起訴狀繕本送達翌日起至清償日止，\n    按年息5%計算之利息；上訴人願供擔保，請准宣告假執行。\n    【原審判決駁回上訴人之訴及其假執行之聲請。上訴人不服\n    ，提起本件上訴。】\n三、被上訴人則辯以：被上訴人於91年9月4日與上訴人議定之除\n    草工作，於91年10月23日即已完成，迄今未領到錢係因上訴\n    人沒有通知，故91年10月28日發生之火災係上訴人自行僱工\n    處理所釀致災害，與被上訴人無涉。被上訴人雖曾於90年3\n    月7日與上訴人簽訂承包一般公墓除草維護工作契約，然該\n    契約期間係自簽約之日起至90年3月25日止，且已驗收合格\n    完成，並領取工程款，兩造契約關係已告終結；本件火災發\n    生時，兩造間既未訂有書面除草契約，上訴人依前開合約書\n    第6條約定主張被上訴人應負本件損害賠償責任，即屬無據\n    。又縱認兩造間有承攬契約存在，系爭火災係被上訴人派人\n    除草所致者，依民法第189條規定、及最高法院18年上字第2\n    010號判例意旨，定作人於定作或指示無過失時，對承攬人\n    為承攬事項加害於第三人者，不負賠償責任；上訴人既主張\n    其與被上訴人間有公墓除草之承攬契約存在，上訴人為定作\n    人，依上訴人於訴外人黃永懷對其請求國家賠償時所為之拒\n    絕賠償理由書所載，上訴人主張其對於承攬事務並無定作或\n    指示上之任何過失，則上訴人對於訴外人黃永懷等人自無須\n    負損害賠償責任，被上訴人對上訴人亦無加害給付之情事。\n    至上訴人自願放棄法律所賦與之權利，與訴外人黃永懷和解\n    ，其所為係屬無義務之給付，所致財產之損害，自與被上訴\n    人無涉，不能因上訴人與黃永懷於上開國家賠償事件中成立\n    和解，並賠償黃永懷之損害，即認符合加害給付要件。況依\n    上訴人於原審提出之91年10月31日心鄉民字第0910010940號\n    函內容，可知上訴人於91年10月31日即已知上開舊館公墓北\n    側0.4公頃農地苗園，因處理雜草焚燒工作不慎遭毀損之情\n    事，是系爭火災縱為被上訴人除草所致，而上訴人得依承攬\n    契約法律關係向被上訴人請求賠償者，上訴人之損害賠償請\n    求權，依民法第514條規定，亦已逾1年短期時效，而罹於時\n    效消滅，被上訴人自得拒絕賠償。再者，系爭火災為91年10\n    月28日，如認放火工人係被上訴人所聘僱，則訴外人黃永懷\n    等三人於92年4月接獲上訴人之拒絕賠償理由書時，即應知\n    該公墓除草承攬人為被上訴人，其等對於被上訴人之侵權行\n    為損害賠償請求權，自斯時起算至上訴人95年11月15日與訴\n    外人為訴訟上和解時，早逾民法第197條所定之2年請求權時\n    效，被上訴人本即可拒絕賠償，故上訴人上開所為之和解，\n    顯不利於被上訴人，且不符合被上訴人明示或可得推知之意\n    思，自不符合無因管理之要件，而無無因管理規定之適用。\n    又被上訴人既為上開國家賠償事件中之利害關係人，依民事\n    訴訟法第65條規定上訴人應為告知訴訟，然上訴人竟未為告\n    知訴訟，即擅自與第三人為訴訟上之和解，因而產生之上開\n    費用，自屬上訴人自己行為所致之損害，應自行負責，其請\n    求被上訴人賠償，於法無據。又上訴人另依不當得利法律關\n    係請求，惟被上訴人本得以黃永懷等人之請求權已罹於時效\n    為由拒絕賠償，惟上訴人卻仍與之和解並為之清償，顯未使\n    被上訴人獲得任何利益，上訴人主張兩造間財產損益變動，\n    得依不當得利規定處理，亦屬無據等語。\n四、查上訴人主張其曾於90年3月7日將彰化縣埔心鄉內第三（經\n    口）、第四（舊館）、第五（新館）、第六（羅厝）、第七\n    （梧鳳）、第八（二重）第六座公墓，墓區內計約29.06公\n    頃之除草維護工作，委由被上訴人施作；嗣因第四（舊館）\n    、第七（梧鳳）公墓除草工作，依中央機關未達公告金額採\n    購招標辦法第5條規定，得不經公告程序，逕洽廠商採購，\n    上訴人於91年9月4日聯繫有公墓除草經驗之被上訴人人員張\n    力升進行議價；被上訴人曾於91年10月23日開立載有「舊館\n    、梧鳳公墓除草公作，金額65,000元」之統一發票予上訴人\n    ；彰化縣第四（舊館）公墓於91年10月28日上午以放火燃燒\n    方式，清除第四公墓內之雜草時，因未預先於放火燃燒前之\n    四周開闢防火巷，致火勢失控蔓延至公墓北側之埔心鄉○○\n    段862地號農地，造成訴外人黃永懷、黃坤煌及黃福賜合資\n    種植之圓葉蒲葵遭火焚毀；而上訴人與訴外人黃永懷於95年\n    11月15日於本院95年上國更(一)字第2號國家賠償事件審理中\n    成立和解，上訴人同意給付黃永懷99萬元，並已於96年2月\n    15日給付完畢等情，業據上訴人提出公墓除草維護工作合約\n    書、原法院92年國字第4號判決、本院94年上國字第5號判決\n    、本院95年上國更(一)字第2號和解筆錄、最高法院95年台上\n    字第1445號判決、上訴人與訴外人黃永懷等人於95年11月9\n    日商討和解會議記錄、黃永懷於96年2月15日出具已領受99\n    萬元和解金之收據、上訴人簽呈、及被上訴人開立之統一發\n    票等件為證，並為被上訴人所不爭執，堪信上訴人上開部分\n    之主張為真實。\n五、惟上訴人主張兩造間就91年10月第四（舊館）、第七（梧鳳\n    ）公墓之除草工作有承攬契約關係存在，且系爭火災係被上\n    訴人派人除草所致；被上訴人未開闢防火巷或採取其他安全\n    措施即以放火焚燒之方式清除雜草，造成訴外人黃永懷、黃\n    坤煌、及黃福賜合資種植之圓葉蒲葵遭火焚毀，被上訴人執\n    行承攬工作顯有疏失，對上訴人應負損害賠償責任，則上訴\n    人代被上訴人與訴外人黃永懷達成和解，並代為賠償99萬元\n    、及其他必要費用總計1,110,035元，自得依兩造間承攬契\n    約、及民法無因管理、不當得利法律關係，請求被上訴人給\n    付等節，則為被上訴人所否認，並以上詞置辯。經查：\n  (一)關於彰化縣埔心鄉第四（舊館）公墓，91年10月28日發生火\n    災之除草工作，是否為被上訴人所承攬施作部分：\n  1.查上訴人主張第四（舊館）、第七（梧鳳）公墓91年度除草\n    工作，係其於91年9月4日聯繫被上訴人法定代理人張力升進\n    行議價，並於同日議定以65,000元，將該二公墓除草工作委\n    由被上訴人施作一節，業據上訴人提出兩造於90年3月7日簽\n    訂合約書、上訴人機關簽呈暨簽准公文、及被上訴人於91年\n    10月23日開立載有：「舊館、梧鳳公墓除草公作，金額65,0\n    00元」之統一發票（見原審卷第76至79頁、及第124至126頁\n    ）為證，並經被上訴人法定代理人張力升於原法院98年4月\n    16日審理中自承在卷（見原審卷第157頁），及據證人即負\n    責埔心鄉公所總務工作人員黃進智於原審審理中證稱：「90\n    年3月7日起至90年3月25日之期間內的除草業務是被上訴人\n    負責的。後來91年9月時候我們業務單位再提出申請，要做\n    除草工作，因為是10萬元以下，被上訴人以前有承包過我們\n    這個工作，做的還不錯，所以我們就直接找被上訴人議價，\n    我打電話找被上訴人公司的張力升，打電話後他隔天就來我\n    們公所總務室商談如何除草的細節」等語（見原審卷第108\n    頁背面及第109頁），及證人即負責埔心鄉公所公墓業務承\n    辦人員陳冠良證稱：「91年9月公所欲施作舊館（第四公墓\n    ）、梧鳳公墓（第七公墓）除草工作時，因金額僅65,000元\n    ，沒有超過10萬元，總務科沒有經過上網直接找被上訴人來\n    談，我跟總務、雅立山公司的張力升三人洽談，之前簽約的\n    時候也是張力升，談的條件就是65,000元，範圍就是剛剛所\n    述的兩個公墓」等語甚詳（見原審卷第110頁），則上訴人\n    主張第四（舊館）公墓91年度除草工作，係由被上訴人承攬\n    施作一節，即堪認為真實。\n  2.被上訴人雖以：其於91年10月23日即已完成彰化縣第四（舊\n    館）公墓之除草工作，迄今未領到錢係因上訴人沒有通知，\n    故其於91年10月28日不可能再派員除草，當日發生之火災應\n    係上訴人自行僱工處理所釀致災害，與被上訴人無涉等語。\n    惟查：兩造就彰化縣第四（舊館）公墓於91年10月28日上午\n    ，確有人以放火燃燒方式清除雜草時，因未預先於放火燃燒\n    前四周開闢防火巷，致火勢失控蔓延至公墓北側之埔心鄉○\n    ○段第862地號農地，造成訴外人黃永懷、黃坤煌及黃福賜\n    合資種植之圓葉蒲葵遭火焚毀一節，均不爭執（見原審卷第\n    156頁背面）；又依兩造於90年3月7日所訂合約書內容記載\n    ，被上訴人所承包之公墓除草工作係以噴灑除草藥劑及焚燒\n    方式整理（見原審卷第8、10頁）；再參以證人陳冠良證稱\n    ：「91年9月3日我們跟被上訴人聯絡，9月4日其來跟我們談\n    除草工作，我們請其91年9月20日到10月20日間去施作，如\n    果提早完工，我們就提早驗收完畢。被上訴人應該是9月4日\n    就開始去施作了，本來的驗收時間是91年10月23日，因為當\n    天消防隊沒有辦法支援，所以我們與廠商聯繫後驗收時間改\n    為91年10月28日，我與被上訴人的聯繫都是張力升，驗收的\n    情形是被上訴人要將公墓現場的草處理好，通常除草的驗收\n    我們會請廠商開好防火巷，請消防隊到，廠商處理好除好的\n    草才會完成，結果當天消防隊員還沒有來，公所的人也還沒\n    有到，張力升也還沒有到，但是張力升的工人先到了，他的\n    工人就先放火燒草了。」等語（見原審卷第110頁），又依\n    彰化縣消防局98年4月17日0980011582號函記載：「本案經\n    轄區埔心分隊調閱相關資料之後，當日（即91年10月28日）\n    確有執行本轄埔心鄉舊館公墓防火宣導與警戒工作之勤務．\n    ．．」等語（見原審卷第146至151頁），足認；彰化縣第四\n   （舊館）公墓91年度之除草工作迄至91年10月28日上午，應\n    仍尚未完成。而被上訴人固於91年10月23日先簽發統一發票\n    予承辦人員，惟上訴人迄今尚未付款，為被上訴人所不爭執\n    ，再參以證人陳冠良證稱：「發票有送來公所，但我們還沒\n    有就本件的款項給付給被上訴人，因為發生焚燒到鄰地的事\n    件，所以65,000元還沒有支付」等語（見原審卷第110頁背\n    面），顯見，上開除草工作應尚未施作完畢驗收，上訴人始\n    未於被上訴人出具發票時付款；又被上訴人倘確已於91年10\n    月23日清除雜草完畢，衡情尚無可能於其交付統一發票向上\n    訴人請款後，任憑上訴人恁置多年未付款而未為請求之理，\n    是被上訴人辯稱，其已於91年10月23日將彰化縣第四（舊館\n    ）公墓雜草清除完畢，不可能於91年10月28日再派員除草云\n    云，非為可採。又被上訴人確向上訴人承攬系爭除草工作，\n    且於91年10月28日第四（舊館）公墓尚有雜草待除，既已如\n    上述，則該除草工作既為被上訴人所承攬之工作，他人何須\n    無故代其除草？且於該日上午確有人員以火燒方式除草，證\n    人陳冠良亦證稱：「發生火災當天其有到現場，其到達現場\n    的時候公墓已經煙霧迷漫，廠商的工人在場，但是張力升還\n    沒有到。張力升後來到的時候有告訴我們那個工人是他從和\n    美請來的。」等語（見原審卷第111頁），再參諸上訴人曾\n    於事發後之91年10月31日發函予被上訴人，請其儘速會同上\n    訴人與地主商討賠償事宜等情（見原審卷第80頁），足見，\n    案發日在現場從事放火除草之人員，確係被上訴人為進行其\n    承攬之除草工作所委派無訛，被上訴人辯稱當日發生之火災\n    係上訴人自行僱工處理所釀致災害，與被上訴人公司無涉云\n    云，亦無足採。\n  (二)彰化縣埔心鄉第四（舊館）公墓91年10月28日發生火災之除\n    草工作，為被上訴人所承攬施作，上訴人支出之上開和解金\n    及必要費用，得否依承攬契約請求被上訴人賠償損害？按承\n    攬人因執行承攬事項，不法侵害他人之權利者，定作人不負\n    損害賠償責任；但定作人於定作或指示有過失者，不在此限\n    。民法第189條亦定有明文。即定作人於定作或指示無過失\n    者，就承攬人因執行承攬事項，不法侵害他人之權利，不負\n    損害賠償責任。查上訴人委請被上訴人除草，被上訴人以放\n    火方式為之，因系爭放火除草之地點與訴外人黃永懷、黃坤\n    煌及黃福賜種植圓葉蒲葵之田地相鄰，於放火燒草之際可能\n    延及他人受損之情事，為兩造所明知，是於被上訴人放火除\n    草之際，上訴人本有委請彰化縣消防局埔心分隊派員執行警\n    戒工作之勤務，且被上訴人亦應先行開闢防火巷以免火勢過\n    大延及他人；詎被上訴人未待消防人員到達，更未在現場闢\n    出防火巷，即自行放火除草致損及他人所種植之農作物，則\n    被上訴人就黃永懷、黃坤煌及黃福賜所受之上開損害，即應\n    由被上訴人負侵權行為損害賠償責任。上訴人既已委請彰化\n    縣消防局埔心分隊派員執行警戒工作之勤務，有上開彰化縣\n    消防局函文附於原審卷內可稽，其於訴外人黃永懷請求國家\n    賠償時所為之拒絕賠償理由書，亦載明本件工作係由被上訴\n    人所承攬，依民法第189條規定，其不負賠償責任等語（見\n    本院卷第59頁），及依上訴人主張兩造承攬契約沿用90年3\n    月7日合約條款第6條約定，即：「乙方（即被上訴人）於進\n    行焚燒及噴灑除草藥劑時應預防危險，如因此損害私人財產\n    造成其他糾紛一切賠償責任，均應由乙方自行負責，甲方（\n    即上訴人）不負任何責任」等語，依該約定，如有任何損害\n    發生，須對第三人負賠償責任者，係施作者之被上訴人，上\n    訴人本毋庸負本件賠償責任。是上訴人於上開國家賠償事件\n    中，與訴外人黃永懷達成和解並給付和解金，應與兩造間簽\n    訂之承攬契約約定條款無涉，則上訴人依承攬契約法律關係\n    ，請求被上訴人應賠償其支出之損害金及相關必要費用，核\n    屬無據。\n  (三)上訴人得否就其與訴外人黃永懷和解所支出之損害賠償及其\n    他必要費用，依無因管理、及不當得利法律關係請求被上訴\n    人負賠償責任？\n  1.上訴人主張其支付予訴外人黃永懷之上開賠償金及其他必要\n    費用，亦得依民法無因管理法律關係，請求被上訴人給付等\n    語。按未受委任，並無義務，而為他人管理事務者，其管理\n    應依本人明示或可得推知之意思，以有利於本人之方法為之\n    。又管理人開始管理時，以能通知為限，應即通知本人；如\n    無急迫之情事，應俟本人之指示。再管理事務利於本人，並\n    不違反本人明示或可得推知之意思者，管理人為本人支出必\n    要或有益之費用，或負擔債務，或受損害時，得請求本人償\n    還其費用及自支出時起之利息，或清償其所負擔之債務或賠\n    償其損害。民法第172條、第173條第1項、及第176條第1項\n    定有明文。又按侵權行為所生之損害賠償請求權，自請求權\n    人知有損害及賠償義務人時起，二年間不行使而消滅。自有\n    侵權行為時起，逾10年者亦同。民法第197條第1項亦有明文\n    。查系爭火災發生於91年10月28日，又訴外人黃永懷等三人\n    請求上訴人國家賠償遭拒絕，其等至遲於92年4月間接獲上\n    訴人之拒絕賠償理由書時，即知侵權行為人為被上訴人，損\n    害賠償請求權自該時起算至上訴人95年11月15日與訴外人為\n    訴訟上和解時，早已罹於時效而消滅，而上訴人於上開國家\n    賠償事件中，卻仍於95年11月15日與訴外人黃永懷達成和解\n    ，並給付黃永懷99萬元，雖可認上訴人之上開行為，有未受\n    委任，並無義務，而為被上訴人管理事務之行為，與無因管\n    理要件，尚屬相符；惟上訴人自系爭災發生時，即已知被上\n    訴人對訴外人黃永懷應負損害賠償責任，其並無不能通知被\n    上訴人之情事，惟卻未依民事訴訟法第65條規定，告知被上\n    訴人及時參加訴訟，使被上訴人對於該損害賠償金額、賠償\n    範圍、甚或時效問題，有答辯之機會，則上訴人於95年11月\n    15日與訴外人黃永懷達成和解，給付黃永懷99萬元，已難認\n    上訴人所為上開事務之管理，為有利於本人之被上訴人，自\n    不符上開適法無因管理人得請求本人償還費用、或賠償損害\n    之要件。上訴人依民法無因管理法律關係，請求被上訴人應\n    給付上開損害賠償金及其他必要費用，亦洵屬無據。\n  2.上訴人於本院又主張依民法不當得利法律關係請求一節．按\n    無法律上之原因而受利益，致他人受損害者，應返還其利益\n    。民法第179條前段定有明文。查訴外人黃永懷對被上訴人\n    之侵權行為請求權，早已罹於時效而消滅，已如上述，被上\n    訴人本得拒絕為賠償，無庸對訴外人黃永懷為任何之賠償給\n    付，則上訴人主張其代被上訴人清償予黃永懷，顯未使被上\n    訴人受有任何利益可言，上訴人主張兩造間財產損益有變動\n    云云，應依不當得利規定處理云云，亦為無理由。\n六、綜上所述，上訴人主張依承攬契約、無因管理、及不當得利\n    法律關係，請求被上訴人應給付上訴人1,110,035元，及自\n    起訴狀繕本送達翌日起至清償日止，按年息5%計算之利息，\n    為無理由，應予駁回。原審為上訴人敗訴之判決，並無不合\n    ，上訴意旨猶執詞指摘原判決不當，求予廢棄改判，為無理\n    由，應予駁回。\n七、本案事實已臻明確，兩造其餘攻擊防禦方法，不足以影響本\n    判決結果，爰不一一論述，併此敘明。\n據上論結：本件上訴為無理由，依民事訴訟法第449條第1項、第\n78條，判決如主文。"
  },
  "characters": {
    "judges": [
      "陳蘇宗",
      "黃永祥",
      "張浴美"
    ],
    "prosecutors": [

    ],
    "lawyers": [
      "陳世煌",
      "黃俊昇",
      "吳光中"
    ],
    "clerks": [
      "阮正枝"
    ],
    "plaintiffs": [

    ],
    "defendants": [

    ],
    "prosecutor_office": [

    ],
    "creditors": [

    ],
    "debtors": [

    ],
    "judicial_associate_officer": [

    ]
  },
  "adjudged_at": "2010-01-05",
  "created_at": "2016-01-05 15:07:37",
  "updated_at": "2016-01-05 15:07:37"
}