{
  "identify": "TCH-98-建上-52-20100512-1",
  "court": {
    "name": "臺灣高等法院",
    "code": "TCH"
  },
  "division": {
    "name": "民事",
    "code": "V"
  },
  "year": 98,
  "word": "建上",
  "number": "52",
  "jcheck": "1",
  "reason": "給付修繕費",
  "content": "臺灣高等法院臺中分院民事判決          98年度建上字第52號\n上  訴  人   合作金庫商業銀行股份有限公司\n法定代理人   丁○○\n訴訟代理人   丙○○\n             吳光陸律師\n被 上 訴人   戊○○\n             乙○○\n上二人共同\n訴訟代理人   周仲鼎律師\n上列當事人間請求給付修繕費事件，上訴人對於民國98年5月15\n日臺灣台中地方法院96年度重訴字第426號第一審判決提起上訴\n，本院於民國99年4月28日言詞辯論終結，判決如下：\n    主  文\n原判決關於以本金新臺幣柒佰零伍萬壹仟陸佰零捌元計付超過自\n民國九十六年十月十七日起至清償日止按年息百分之五計算利息\n部分，及該部分假執行之宣告，暨訴訟費用之裁判均廢棄。\n上廢棄部分，被上訴人在第一審之訴及假執行之聲請均駁回。\n其餘上訴駁回。\n第一、二審訴訟費用由上訴人負擔百分之八十五，餘由被上訴人\n負擔。\n    事實及理由\n甲、程序方面：上訴人之法定代理人於民國98年1月5日變更為丁\n    ○○，並於98年6月4日具狀向本院聲明承受訴訟，有上訴人\n    提出之變更登記表影本及民事聲明承受訴訟狀一份在本院卷\n    為證（見本院卷(一)第4-11頁），核無不合，應予准許。\n乙、實體方面：\n壹、聲明部分：\n一、上訴人方面：(一)原判決不利於上訴人部分廢棄。(二)上開廢棄\n    部分，被上訴人在第一審之訴及假執行之聲請均駁回。\n二、被上訴人方面：駁回上訴。\n貳、陳述及理由部分：\n一、被上訴人主張：\n(一)、兩造為坐落台中市○○區○○段 325地號（下稱系爭土地）\n    上金矽谷銀河鉅星大樓（下稱系爭大樓）之區分所有權人，\n    被上訴人為建號台中市○○區○○段2117至2121建號即門牌\n    號碼台中市○○路○段151號9樓、10樓、11 樓、12樓、13樓\n    、14樓之1、14樓之2之建物（下稱系爭大樓之 9至15樓）區\n    分所有權人，上訴人則為建號台中市○○區○○段2102、21\n    04至2116建號即門牌號碼台中市○○路○段151號、151號2樓\n    、3樓、4樓、5樓、6樓之 1、之2、之3、之4、7樓之1、之2\n    、之3、之4、8樓建物（下稱系爭大樓1至 8樓）之區分所有\n    權人。雖兩造曾就系爭大樓外牆公共設施修繕工程，協議按\n    應有比例出資整修，即被上訴人為41.66％ （被上訴人戊○\n    ○為41.24％、被上訴人乙○○0.42％），上訴人則為58.34\n    ％。然就公共管道間之水、電力、消防及排煙幹管部分，是\n    否屬共用部分及是否須修復，兩造未能達成協議，被上訴人\n    為免發生公安意外及儘速符合相關建築及消防法規，且上開\n    修繕之保存行為實屬緊急及必要，故被上訴人委由訴外人威\n    祐科技有限公司（下稱威祐公司）對公共管道間之水、電力\n    、消防及排煙幹管部分加以修復，全部共用修繕工程金額為\n    新台幣（下同）12,087,090元，上訴人自應依兩造間應有部\n    分之比例分擔上開款項，爰求為命上訴人給付 7,051,608元\n    及自起訴狀繕本送達翌日起至清償日止按年息百分之 5計算\n    利息，及供擔保准為假執行宣告之判決。\n(二)、在本院補充陳述：\n  1.系爭大樓有修繕必要，業經兩造委任之建築師己○○評估在\n    案，嗣後亦經己○○建築師監造修繕完畢，並經台中建築師\n    公會鑑定屬實：被上訴人於標購大樓後，即與上訴人商討大\n    樓整修事宜，雙方並共同委任己○○建築師就大樓之整個外\n    觀及大樓內部作整修評估，並共同支付設計及監造費用 100\n    萬元。後被上訴人即依照建築師之規劃，交由威祐科技有限\n    公司承攬施工，由己○○建築師事務所負責監工（相關監工\n    費用皆以包含於上開 100萬元），未避免爭議，己○○建築\n    師亦依其專業將共同管道間及逃生樓梯部分之公共設施與上\n    訴人之私有部分加以區隔，分別計價，己○○建築師上開計\n    價結果，經台中建築師公會鑑定後，再扣除非公設部分之修\n    繕費，即為原審判決上訴人應負擔之金額，上訴人之上訴並\n    無理由。\n  2.己○○建築師認定兩造共同分擔之金額，係已排除上訴人主\n    張之「小公」部分：己○○建築師計算兩造須分擔之公設部\n    分，只計算大樓管道間及大樓逃生樓梯等空間部分，即上訴\n    人所指之「大公」部分，至於每樓層供公共使用之公共廁所\n    、走道照明、走道牆壁等設施，原本亦應屬公共設施部份（\n    即上訴人所謂之「小公」部分）卻漏未計入，此部分被上訴\n    人雖不贊同且仍有疑異，惟因並未計入公設部分請求，是上\n    訴人上訴理由中關於小公、大公部分之陳述，自無可採。\n  3.上訴人私下委託建築師所為之鑑定，不應作為有利上訴之依\n    據，本件仍應以台灣省建築師公會之鑑定為依據：上訴人私\n    下委託建築師所為之鑑定（下稱私人鑑定報告），並非由法\n    院所囑託鑑定，且費用亦由上訴人所支出，故上開建築師基\n    於上訴人之委任關係，其所為之鑑定以難祈客觀，故被上訴\n    人認上開鑑定報告實不應作為有利上訴之依據。又上訴人之\n    鑑定報告，並未會同法院及被上訴人，該鑑定報告所依據之\n    資料、資訊，亦不充足，實難期待其鑑定具有客觀及中立之\n    立場。本件兩造在原審已合意由台灣省建築師公會鑑定，台\n    灣省建築師公會並多次會同兩造到現場探勘，並請兩造各自\n    陳述意見，原審亦會同兩造及台灣省建築師公會鑑定建築師\n    、己○○建築師等人，一同前往系爭大樓就鑑定報告為說明\n    ，況上開鑑定報告之內容亦非全然對被上訴人有利，可信度\n    應屬較高。被上訴人在原審亦因之而自動減縮訴之聲明以示\n    尊重，然反觀上訴人卻因為未全然符合其利益，即一再質疑\n    上開鑑定之公信力，實屬不該。\n二、上訴人則以：\n(一)、系爭大樓早於80年 2月26日即建築完成，領有使用執照，並\n    無被上訴人所謂無法正常申請使用執照之情形，即被上訴人\n    所有之部分，僅因原所有權人未能充分利用，致被上訴人於\n    95年3月7日，經法院拍賣程序取得時，有失修損壞情形，然\n    此與使用執照無涉，並非不可使用，且依強制執行法第69條\n    之規定，被上訴人應自行承擔物之瑕疵之風險，豈可為圖己\n    用之利，強求上訴人為其分擔修繕費用，殊不合理。又兩造\n    雖曾就系爭大樓外牆公共設施修繕工程，協議按應有比例出\n    資整修，惟就被上訴人起訴主張公共管道間之水、電力、消\n    防及排煙幹管之修繕費用，並未達成合意，且該部分亦非共\n    用，再參以上訴人自88年起，即已於系爭大樓經營銀行業務\n    迄今，顯見並無被上訴人所稱公共管道間之主幹管已年久失\n    修、不堪使用，致生公共危險之虞，即並無修繕之必要，是\n    以，被上訴人所主張系爭部分之修繕，均係供被上訴人己用\n    之部分，故應由被上訴人自行支出修繕費用。復系爭部分之\n    修繕，更不屬民法第820第2項之「簡易修繕或其他保存行為\n    」，系爭修繕僅屬被上訴人為自己之經濟效用而有修繕必要\n    ，從而，為同條第3 項所稱之「改良行為」，非經共有人過\n    半數，並其應有部分合計已過半數者之同意不得為之，故上\n    訴人並無分攤修繕費用之責。再者，縱屬公用部分，系爭修\n    繕亦僅供個別樓層使用，即屬「一部共用部分」，而應由該\n    「一部共用部分」之區分所有權人即被上訴人自行負擔修繕\n    費用。\n(二)、在本院補充陳述：\n  1.蓋系爭大樓早有使用執照，建物完成後，已有使用，故不可\n    能有未能使用或有相關應具備之設備尚未裝修。上訴人拍賣\n    承受後，其中3至8樓因尚未擬定使用計畫，除部分作倉庫使\n    用外，其餘閒置，但均有善盡維修管理之責，部分設施雖屬\n    老舊，但尚能維持正常運作，水電供應正常，消防安檢亦有\n    通過，未有影響公共安全之虞，故無被上訴人所稱有急迫修\n    繕之必要。上訴人所屬1樓至2樓設立分行使用迄今，亦復如\n    此，若有立即公安危險，早就遭主管機關勒令停業，又何以\n    能在該大樓營業數年？自無被上訴人主張因有損壞，無法申\n    請使用執照。足見被上訴人所稱有修繕之急迫性與必要性，\n    自非事實。\n  2.被上訴人所稱修繕公共管道間之主幹管，包括消防灑水系統\n    、消防給水系統、一般給水系統、排水系統、污水系統及透\n    氣管線，上訴人否認其所修繕者為「主幹管」。縱屬真實，\n    上訴人亦否認有修繕之必要，蓋「主幹管」雖供整棟大樓公\n    用，但上開幹管均非一體成型，而係多段接管而成，此由被\n    上訴人在第一審提出之原證2照片即可證明，各樓層所屬幹\n    管若有修繕必要，亦僅須就樓層所屬接管處予以修繕或更換\n    即可，並無須整個主幹管均予修繕或更換。系爭大樓雖為兩\n    造共有，但因兩造各自所有樓層明確，則修繕各自樓層之共\n    有部分，即應自行負擔，例如各項水、電管線，即使經過共\n    同管道間，若非屬供整棟大樓使用之主幹管而僅是供個別樓\n    層使用，即屬「一部共用部分」，應由該「一部共用部分」\n    之區分所有權人自行負擔修繕費用。台灣省建築師公會就附\n    件六之整修工程項目，認屬共用部分，並未詳細區分，說明\n    何者屬「大公」或「小公」，其鑑定應非可信。\n  3.茲就被上訴人在第一審提出之合約書、第一、二、三、四次\n    估計價、結算表等，比較其內容製作統計表，發見其間有不\n    實之處，足見己○○建築師之估驗及結算不實。再己○○建\n    築師證稱其估算之金額12,624,418元，包括大公、小公部分\n    之工程款，至於大公或小公應由鑑定單位認定，但台灣省建\n    築師公會並未區分大公、小公，與己○○建築師上開證述內\n    容不符，是不僅該鑑定不實，且無法證明被上訴人之修繕均\n    屬大公，況依己○○證稱，其就被上訴人主張之共用部分修\n    繕之合約，係其與被上訴人達成共識的共用部分，則該合約\n    之修繕，是否確為共用部分，應非確論，否則何以稱應由鑑\n    定單位認定？甚此被上訴人起訴主張之共用部分，亦未經台\n    灣省建築師公會肯定均為共用部分可明。\n三、兩造就下列事實不為爭執，並有土地及建物謄本（見原審卷\n    (一)第11 -27頁反面）、兩造之協議書（見原審卷(一)第42頁）\n    、存證信函（見原審卷(一)第46 -47頁）、被上訴人之匯款單\n    及收據（見原審卷(一)第 52-54頁）、臺灣省建築師公會於97\n    年6月18日所出具之鑑定報告各1份在卷為佐，堪信為真，並\n    得採為判決基礎：\n(一)、兩造為系爭土地上系爭大樓之區分所有權人，被上訴人為系\n    爭大樓之9至15樓之區分所有權人，上訴人則為系爭大樓1至\n    8樓之區分所有權人。\n(二)、兩造曾就系爭大樓外牆公共設施修繕工程，協議按應有比例\n    出資整修，兩造應有部分比例為被上訴人 41.66％（被上訴\n    人戊○○為41.24％、被上訴人乙○○ 0.42％），上訴人則\n    為58.34％。\n(三)、被上訴人確曾就系爭大樓修繕費用所支應之修繕事項於動工\n    前通知上訴人，惟經上訴人於96年 9月14日以系爭修繕費用\n    非公用及非必要為由，而以96年9月14日合金總總字第09600\n    29474號函覆拒絕支付（見原審卷(一)第121頁）。\n(四)、被上訴人確曾匯款13,278,162元予訴外人魏英如（見原審卷\n    (一)第52-54頁）。\n(五)、臺灣省建築師公會於97年6月18日所出具之鑑定報告認「9層\n    至15層各戶電表集中箱體」、「提供電表用電開關變電箱」\n    及「提供公設梯間及梯廳、茶水間用電分盤」，乃不為共用\n    部分。\n四、至於被上訴人主張：其與上訴人共有之系爭大樓，因「公共\n    管道間」之「消防灑水系統、消防給水系統、污水系統、排\n    水系統及透氣管線」，與系爭大樓公共逃生梯各樓層中之「\n    消防栓廂設備、廣播設備及緊急逃生照明設備、排煙管道設\n    備、電信弱電箱」等共用設備修繕，因該等部分受有損害而\n    有修繕之必要，且屬於民法第820第2項所稱之「簡易修繕或\n    其他保存行為」，被上訴人經通知上訴人共同修繕未果後，\n    自行修繕，上訴人就被上訴人修繕所支出之費用，依法應按\n    所有權比例負擔，惟上訴人拒絕給付，被上訴人得請求上訴\n    人償還墊款等語，則惟上訴人否認，並以前詞抗辯，是本件\n    爭點為：被上訴人主張上訴人應依持分比例分擔系爭大樓共\n    用部分之修繕費7,062,608元，是否有理由？經查：\n(一)、本件被上訴人主張其所修繕者為系爭大樓「公共管道間」之\n    「消防灑水系統、消防給水系統、污水系統、排水系統及透\n    氣管線」及系爭大樓公共逃生梯各樓層中之「消防栓廂設備\n    、廣播設備及緊急逃生照明設備、排煙管道設備、電信弱電\n    箱」等設備，該等設備為系爭大樓之共用部分，雖為上訴人\n    所否認，惟查：\n  1.按「本法所稱建築物設備為敷設於建築物之電氣、煤氣、給\n    水、排水、空氣調節、昇降、消防、防空避難及污物處理等\n    設備」，建築法第10條定有明文。又「公寓大廈共用部分不\n    得獨立使用供做專有部分。其為下列各款者，並不得為約定\n    專用部分：一、公寓大廈本身所占之地面。二、連通數個專\n    有部分之走廊或樓梯，及其通往室外之通路或門廳；社區○\n    ○巷道、防火巷弄。三、公寓大廈基礎、主要樑柱、承重牆\n    壁、樓地板及屋頂之構造。四、約定專用有違法令使用限制\n    之規定者。五、其他有固定使用方法，並屬區分所有權人生\n    活利用上不可或缺之共用部分。」。公寓大廈管理條例第 7\n    條亦定有明文。本件敷設於系爭建築物如附表所示之電器、\n    煤氣、給水、排水等管線設備（除壹、電氣設備工程中之一\n    『項次一用途說明為9層至15 層各戶電錶集中箱體』、『項\n    次二之用途說明為提供電錶用電的開關受電箱』、『項次四\n    之用途說明為提供公設梯間及梯廳、茶水間用電分盤』等三\n    項不為共用部分，其餘項目均為共用部分，詳後敘說明），\n    係為供所有住戶共同使用，雖有部分管線設備位於專有部分\n    ，惟區分所有權人室內裝修時，於其專有部分內變更修改上\n    開管線乙節，依前開規定，敷設於建築物屬共用部分之電氣\n    、煤氣、給水、排水等，係屬有固定使用方法，並屬區分所\n    有權人生活利用上不可或缺之共用部分之建築物設備，雖有\n    部分管線設備通過專有部分，然依前揭條例第7條第5款規定\n    ，該等設備不得為約定專用部分，其性質上仍屬共用設備，\n    被上訴人主張公共管線為兩造共用之建築設備，應非無據。\n  2.又依被上訴人提出之施工照片及如附表所示之施工項目，被\n    上訴人所指之「公共管道間」本為「消防灑水系統、消防給\n    水系統、污水系統、排水系統及透氣管線」之必經地，即上\n    開管線皆為共同管線，由公共管道間中之各個主幹管連接至\n    1 至15樓各樓層，再由各樓層以次幹管連接至各住戶，故並\n    非每一樓層或每一樓層之各住戶獨自由公共管道間接管。而\n    消防栓廂設備，係指消防栓廂所連接消防泵浦、消防給水幹\n    管、相關火警連接設備及消防栓警急電源設備等。廣播設備\n    及警急停電逃生照明設備，則係各樓層大樓逃生梯間之廣播\n    器及與一樓大廳之廣播連線系統和警急停電逃生照明設備。\n    排煙管道設備，則包含排煙閘門、排煙閘門管線、排煙機及\n    排煙通道等。電信弱電箱，則包含弱電箱體、電話弱電幹線\n    、有線電幹線及寬頻網路幹管等。亦即所有電話有線電視及\n    寬頻網路皆須透過電信弱電幹線裝置於各樓層之電信弱電箱\n    ，再由各樓層分配到所須之該樓層住戶中。上開設備皆位於\n    公共逃生樓梯空間，即公共逃生樓梯空間為整棟系爭大樓公\n    共設備之公共管線運輸幹線，由此公共管線分配到各樓住戶\n    中，故並非如上訴人所述相關管線乃各樓層或各住戶獨立牽\n    拉管線，是以，公共管線運輸幹線有損害，則整棟大樓之相\n    關設備皆受影響，應可認定。\n  3.再查，本件被上訴人所修繕消防管線設備部分，乃系爭大樓\n    整體消防安全系統，包含火災之自動排煙管線設備、火災自\n    動灑水管設備及消防栓之消防噴水管線設備等三大消防管線\n    設備，上開管線並非各樓層獨立，而是系爭大樓共同之管線\n    ，蓋火警發生時必為全部消防系統一同啟動，消防系統當無\n    可能各樓層，甚至各戶獨立灑水或排煙。且系爭大樓之消防\n    灑水管線因有漏水及無法蓄壓之情形，又排煙管亦因年久失\n    修亦無法正常排煙，故須修繕填補漏水，如此方能使系爭大\n    樓由地下 3樓至地上15樓之消防管路功能正常運作。即所有\n    消防灑水、排煙設施能一體正常運作，位於底層之消防警報\n    設備始能正常啟動，並透過消防廣播系統通知所有位於系爭\n    大樓之人員安全疏散，此相關消防廣播系統之設備，既因年\n    久失修而損害，被上訴人從上訴人所在之樓層即地下室至15\n    樓全面更換修復，自非為被上訴人之利益而修繕。又上開設\n    備管道乃系爭大樓排水排煙或排放污水之主幹管，一體影響\n    全棟大樓之消防灑水、排煙設備運作，應屬建物之共用附屬\n    物，非僅供部分區分所有權人使用。依民法第 799條規定，\n    該等設備應推定為各所有人之共有，其修繕費及其他負擔，\n    自應由各所有人，按其所有部分之價值分擔之。\n  4.至於被上訴人所修繕之電信弱電工程，乃系爭大樓之基礎相\n    關弱電工程費用，其包含系爭大樓各樓層之電話、網路及有\n    線電視線之電信弱電箱修復，以便系爭大樓之各用戶日後能\n    按其需要獨自花費牽線使用，且於今電話及網路科技發達且\n    普遍之社會中，各樓住戶均以共用管線對外連結電話及網路\n    設備，何能要求各樓層中之各住戶獨立花費至大樓外獨自牽\n    立個別管線，是系爭電信弱電箱亦屬大樓之共用設備，亦可\n    認定。\n  5.另本件如附表所示被上訴人所修繕之工程，經兩造在原審合\n    意指定由台灣省建築師公會鑑定是否屬公用部分，經該公會\n    鑑定結果，亦認除「壹、電氣設備工程中之一『項次一用途\n    說明為 9層至15層各戶電錶集中箱體』、『項次二之用途說\n    明為提供電錶用電的開關受電箱』、『項次四之用途說明為\n    提供公設梯間及梯廳、茶水間用電分盤』」等三項不為共用\n    部分，其餘項目均為共用部分，亦有該公會97年 6月18日台\n    建師鑑（97038）字第129404號鑑定報告1份，在卷可參，更\n    明被上訴人主張如附表所示被上訴人所修繕之工程，除壹、\n    電氣設備工程中之一『項次一用途說明為 9層至15層各戶電\n    錶集中箱體』、『項次二之用途說明為提供電錶用電的開關\n    受電箱』、『項次四之用途說明為提供公設梯間及梯廳、茶\n    水間用電分盤』等三項外，其他工程修繕均係對兩造在系爭\n    大樓「生活利用上不可或缺」設備為修繕，有該公會97年 6\n    月18日台建師鑑（97038）字第 1294-4號鑑定報告書一份為\n    佐，並經參與該會鑑定過程之建築師庚○○○○○在本院結\n    證屬實（見本院卷(一)第9-11頁），上訴人否認被上訴人上開\n    修繕工程係針對兩造共有之公有區域設備為修繕等語，自無\n    可採。上訴人另在本院審理期間自行囑託訴外人甲○○及趙\n    天佐建築師鑑定，並提甲○○及趙天佐建築師之鑑定報告書\n    一冊（外放）為佐，並抗辯臺灣省建築師公會之上開鑑定報\n    告，與其所提出之之鑑定報告結論並不相同，臺灣省建築師\n    公會就甲○○及趙天佐建築師之鑑定報告書第 5頁第5、6項\n    即泡沫設備及排煙設備之鑑定意見亦前後不一，臺灣省建築\n    師公會之鑑定報告顯不可採等語。惟查，臺灣省建築師公會\n    之上開鑑定報告並無錯誤，至於臺灣省建築師公會98年10月\n    9日台建師鑑（97038）字第3451號函說明三記載：「上訴人\n    所送黃耀呈建築師事務所鑑定之鑑定報告書第5頁第5、6 項\n    可以接受為私有部分」等語（見本院卷(一)第 152頁），及嗣\n    後該會於98年12月11日函分別就泡沫設備及排煙設備所為之\n    說明：「一第五項泡沫設備可以接受為『私有部分』說明如\n    下：泡沬設備係裝置於停車空間之滅火設備，若該停車空間\n    產權全部屬於私人則應歸類為『私有部分』，若該停車空間\n    屬共同持有部分則應歸類為『公有部分』、二第六類排煙設\n    備可以接受為『私有部分』說明如下：依建築技術規則排煙\n    分區設於各戶居室排煙及特別安全梯或緊急升降機間，若排\n    煙設備屬居室排煙則為『私有部分』，若排煙設備屬特別安\n    全梯或緊急升降機間則為『公有部分』，依整修工程項目表\n    第六項排煙設備a、b、c 所述施工位置及用途說明並未存在\n    私有部分，故此部分應認定為『公有部分』」等語（見本院\n    卷(一)第 232頁），並非要變更臺灣省建築師公會上開鑑定之\n    結論一節，業經鑑定證人即參與上開鑑定報告之建築師羅榮\n    源在本院結證屬實，並證稱：「一兩份函的意思都不是要變\n    更原來鑑定之結論，而是說明有可能是私有，但因為本案的\n    建物是共有的所以第一份函的所謂第五頁第五、六項並非指\n    該部分是私有部分，理由是第五項地下室停車場是共同持分\n    所以該部分的泡沫設備應屬於公共設施，另外一項是第六項\n    排煙設備經再確認還是認為是共同部分，依據原來建築師的\n    施工圖該部分仍屬共有部分。二九十八年十二月十一日函部\n    分確認第五、六項確為共有部分，該函之意思是泡沫設備及\n    排煙設備可能產生私有部分之情形，本件建物依照建築師施\n    工圖上開二部分確實屬於公共設施。」、「本人不能對別人\n    的鑑定報告書發表意見，所以前開二份函文內容所指的是建\n    築師公會所做鑑定報告之項目。」、「【法官提示本院卷第\n    一五二頁，九十八年十月九日覆函說明三、所謂的該鑑定報\n    告書所述第五、六項可以接受為『私有部分』，其餘確認為\n    大樓共用部分，是指建築師公會的鑑定報告書或是上訴人在\n    本院提出的鑑定報告書？（提示並告以要旨）】鑑定證人庚\n    ○○○○○答：「上開函文的第五、六項是指建築師公會鑑\n    定報告書內之泡沫設備及排煙設備，如果該建物是屬於私有\n    的則其泡沫設備及排煙設備即屬於私有，但是本件是屬於共\n    同持有，所以仍屬於共同設備。我的函會這樣寫是指可能產\n    生的情形而已，並非指本件就是私有部分，所以結論就如鑑\n    定報告書所述。」等語（見本院卷(二)第 9頁反面、第10、11\n    頁），是自難據上開臺灣省建築師公會之二份函為該公會有\n    認同甲○○及趙天佐建築師之鑑定結論或有變更其在原審所\n    為鑑定結論之依據，況上開甲○○及趙天佐建築師係受上訴\n    人單方面委任，並非由兩造合意或法院指定之鑑定人，鑑定\n    時亦未會同法院及兩造到場表示意見，自不足採信。是上訴\n    人抗辯臺灣省建築師公會之鑑定報告與甲○○及趙天佐之上\n    開鑑定報告結論不同，及臺灣省建築師公會上開二份函之內\n    容前後矛盾，應以甲○○及趙天佐之鑑定報告為可採等語，\n    顯不可採等語，自無理由。\n(二)、又被上訴人主張就前述系爭大樓公用「公共管道間」之「消\n    防灑水系統、消防給水系統、污水系統、排水系統及透氣管\n    線」與系爭大樓公共逃生梯各樓層中之「消防栓廂設備、廣\n    播設備及緊急逃生照明設備、排煙管道設備、電信弱電箱」\n    部分之修繕，為保存系爭大樓即避免損害而為修繕，其修繕\n    屬必要之保存行為，雖為上訴人否認，然查：\n  1.系爭大樓於80年 2月26日取得使用執照，上訴人於87年間曾\n    委託訴外人長譽水電工程有限公司辦理水電消防等復原工程\n    ，依其工程估價單所載工程款合計為 23,778,668元（含稅）\n    之事實，有上訴人提出系爭大樓使用執照影本 1份附在原審\n    卷（見原審卷(一)第68-70頁）、合作金庫工程合約書影本1份\n    在本院卷（見本院卷(一)第 60-99頁）為佐，足認系爭大樓雖\n    於80年 2月26日取得使用執照，惟不足以證明已符合堪用狀\n    態，否則上訴人於87年間即無支出大筆工程款進行復原工程\n    之必要，是上訴人抗辯系爭大樓於80年 2月26日取得使用執\n    照，並無不能使用情形，無進行修繕必要等語，自無足取。\n    再本院審酌系爭大樓取得使用執照迄上訴人為上開復原工程\n    之87年間相距約 8年，至被上訴人進行本件修繕工程之96年\n    間亦已相距約16年時間，而上訴人為復原工程迄被上訴人為\n    本件修繕工程時則相距約 9年時間，上訴人於87年間辦理復\n    原工程之工程費已多達 2,300餘萬元之多，足認系爭大樓原\n    來之水電消防設備於87年間係處在若不進行復原工程不足以\n    堪用之狀態，否則上訴人亦無進行水電消防等復原工程之必\n    要，再上訴人自進行上開修復工程迄今僅使用系爭大樓之一\n    、二樓，其餘三至八樓部分並未使用，且因三至八樓並未使\n    用，故每年之消防安檢僅檢查一、二樓部分，並未就三至八\n    樓部分做檢查等情，業經上訴人在本院自陳在卷（見本院卷\n    (一)第 119頁反面），是縱認上訴人曾於87年間為水電消防之\n    復原工程，惟因上訴人長期僅使用系爭大樓一、二樓部分，\n    其餘三至八樓部分則未使用且未進行消防安檢，亦僅足認其\n    一、二樓部分係得使用狀態，於上訴人未舉證證明系爭大樓\n    全棟之共用設備部分於87年間經其進行復原工程迄96年間止\n    均處在堪用狀態，自難認上訴人抗辯其曾於87年為上開復原\n    工程以後，系爭大樓全部之公共設備均為堪用狀態為可採，\n    況系爭大樓於96年12月間仍有多項設施不合格，致被上訴人\n    不能申請變更使用，迄本件修繕後始通過檢驗，由台中市政\n    於97年1月16日發給合格證明字號97府都建室字第0022-00號\n    建築物室內裝修合格證明書之事實，亦有被上訴人所提出之\n    台中市政府合格證明字號97府都建室字第 0022-00號建築物\n    室內裝修合格證明、台中市政府97年1月17日府都管字第097\n    0015950號函影本各1份在原審卷為證（見原審卷(一)第220-22\n    1 頁），是被上訴人主張系爭大樓有修繕必要，其修繕部分\n    均為公共管道間之水、電力、消防及排煙幹管等設備，該等\n    設備年久失修損壞，嚴重影響大樓之消防、照明及逃生等公\n    共安全問題，且系爭大樓之相關電器設備、給排水設備及電\n    信弱電工程亦嚴重損壞或尚未裝修，導致系爭大樓無法正常\n    ，若未修繕，則系爭大樓除上訴人已使用之1樓及2樓部分外\n    ，餘皆無法正常使用，且因未完成修繕，消防安檢亦無法通\n    過，致被上訴人無法申請變更執照，故前開設施確有修繕之\n    必要等語，自足採信，且應認被上訴人所為之修繕，顯屬防\n    止共有物之滅失、毀損或權利之喪失、限制等為目的，以維\n    持大樓基本堪用狀態，發揮其應有效用之行為，是本件修繕\n    自屬民法第820第2項規定之「其他保存行為」。\n  2.再查，系爭大樓之共有人僅有兩造共為三人，共有人人數不\n    多，自無召開區分所有權人會議籌組公寓大廈管理委員會之\n    必要（系爭大樓於本案涉訟後之97年 1月28日，已報備設置\n    管理負責人），系爭大樓之公用設備之修繕、管理，依民法\n    第 820條規定為之即可，此由系爭大樓之外牆係由兩造以協\n    議方式修繕完畢，且按各共有人所有權應有部分比例負擔修\n    繕費用，益證就系爭大樓共用之部分以由兩造共負管理之責\n    並依應有部分比例各自分擔修繕費用之方式為之，並無困難\n    。再按民法第820條第2項所稱「保存行為」係指以防止共有\n    物之滅失、毀損或權利之喪失、限制等為目的，以維持現狀\n    之行為，本件系爭大樓公用「公共管道間」之「消防灑水系\n    統、消防給水系統、污水系統、排水系統及透氣管線」與系\n    爭大樓公共逃生梯各樓層中之「消防栓廂設備、廣播設備及\n    緊急逃生照明設備、排煙管道設備、電信弱電箱」等兩造共\n    用部分之設備，本即為防止共有物之滅失、毀損之設施，該\n    等設備既有毀損，並有礙系爭大樓之安全維護及使用之完整\n    性，自應由兩造共負修繕之責任，惟本件被上訴人請求上訴\n    人共同協議修繕，業經上訴人拒絕，有96年8月8日台中漢口\n    郵局第804號存證信函影本1份在原審卷為佐（見原審卷(一)第\n    46、47頁），被上訴人因而自行發包修繕以保存系爭大樓之\n    使用完整性及維護整棟大樓之安全，其為保存系爭大樓所為\n    之修繕，實屬必要。上訴人抗辯本件修繕未經其同意及系爭\n    修繕非屬必要之保存行為，並進而拒絕負擔修繕費用，自屬\n    無據。\n(三)、再查，被上訴人主張系爭大樓如附表所示之修繕工程業已全\n    部完工，被上訴人亦已支付全部工程款之事實，業據被上訴\n    人所提出匯款紀錄、（公有部分）整修工程詳細價目表影本\n    被上訴人與威祐公司之合約書、良岳營造有限公司書節本、\n    開立予被上訴人之統一發票、被上訴人之匯款紀錄、被上訴\n    人於98年 3月12日與威祐公司簽訂之「協議書」、台中銀行\n    中台中分行匯款單、第一次公有及私有結算表、96年 9月13\n    日合作金庫匯款單、第二次公有及私有結算表、96年10月11\n    日合作金庫匯款單、第三次公有及私有結算表、96年11月 9\n    日合作金庫匯款單、第四次公有及私有結算表、97年 1月10\n    日合作金庫匯款單、錯誤之公有結算表副本、竣工圖表、竣\n    工查驗紀錄、己○○建築師事務所96年10月30日安建字第96\n    076號函、己○○建築師事務所96年11月12日安建字第96085\n    號函、威祐公司之匯款單等件各 1份在原審卷為證（見原審\n    卷(二)第146-147頁、第131-144頁、第149-152頁、第153頁、\n    第241-270 頁），堪信為真。再查，被上訴人主張本件共用\n    設備修繕工程（即附表所示全部工程）之工程款合計為12,6\n    24,418元（含5%之稅金，稅前金額為12,023,255元）一節，\n    有己○○建築師事務所98年3月5日安建字第 98022號確認函\n    、結算表各1份在原審卷可稽（見原審卷(二)第117-125頁），\n    並經己○○建築師在本院結證屬實（見本院卷(一)第 133頁反\n    面、第 134頁），堪信為真。另查，附表所示之工程經兩造\n    在原審合意指定台灣省建築公會鑑定該修繕工程何部分為公\n    用，何部分為私用結果，經臺灣建築額公會鑑定結果，認如\n    附表所示被上訴人所修繕之工程中，除「壹、電氣設備工程\n    中之一『項次一用途說明為 9層至15層各戶電錶集中箱體』\n    、『項次二之用途說明為提供電錶用電的開關受電箱』、『\n    項次四之用途說明為提供公設梯間及梯廳、茶水間用電分盤\n    』」等三項外，其他工程修繕均屬共用設備之事實，已如前\n    述，是本件依被上訴人主張以稅前金額即12,023,255元扣除\n    上開經鑑定非屬共用設備部分之工程款（見原審卷(二)第 126\n    頁反面、第127頁），即扣除9層至15層各戶電錶集中箱體部\n    分100,500元、提供電錶用電的開關受電箱部分268,800元、\n    提供公設梯間及梯廳、茶水間用電分盤部分 142,440元，其\n    稅後餘額為12,087,090元（計算式為：12,023,255元－100,\n    500元－268,800元－142,440元＝11,511,515元。11,511,51\n    5＋〔11,511,5155%〕＝12,087,090元 ）應可認定。另本\n    件被上訴人發包整修時，就公用及私人使用之修繕費，已分\n    別列冊結算有前述（公有部分）整修工程詳細價目表、四次\n    公有、私有結算表在卷可稽，且經己○○建築師確認結算，\n    亦有前開己○○建築師事務所98年3月5日安建字第 98022號\n    確認函文1份、結算表1份在原審卷為佐，上訴人以被上訴人\n    進行之本件修繕工程有公用、私用設備不分情形，拒絕償還\n    被上訴人代墊之修繕費，並無理由。\n(四)、按「共有物之管理費，及其他擔負，除契約另有訂定外，應\n    由各共有人，按其應有部分分擔之。共有人中之一人，就共\n    有物之擔負為支付，而逾其所應分擔之部分者，對於其他共\n    有人，得按其各應分擔之部分，請求償還」，民法第 822條\n    定有明文。本件兩造共有之系爭大樓附屬之公用設備，因有\n    修繕之必要，且經被上訴人完成修繕，其應支付之修繕費用\n    為12,087,090元，依前開法文規定，自應由兩造就系爭負用\n    按應有部分之比例分攤。準此，被上訴人主張上訴人應依其\n    所有權應有部分之比例即58.34%分擔7,051,608元 （計算式\n    ：00000000元58.34%＝0000000元。 元以下四捨五入），\n    核屬有據。再上開修繕費用12,087,090元已由被上訴人支付\n    亦如前述，是被上訴人請求上訴人返還被上訴人應分擔額7,\n    051,608元，為有理由，應予准許。\n五、綜上所述，被上訴人主張上訴人應分擔系爭大樓之公用設備\n    修繕費7,051,608元 ，已由被上訴人代為支付，上訴人迄未\n    返還被上訴人，均如前述。從而，被上訴人依修繕費用償還\n    請求權之法律關係，請求上訴人給付7,051,608元 ，及自起\n    訴狀繕本送達（見原審卷(一)第62頁）之翌日即96年10月17日\n    起至清償日止按年息百分之 5計算之利息，為有理由，應予\n    准許。至於逾上開金額之請求（即利息請求逾自96年10月17\n    日起算部分），則無理由，不應准許。原審就上開應准許部\n    分，為上訴人敗訴判決，並依兩造陳明，分別酌定相當供擔\n    保金額，為准免假執行之宣告，核無不合。上訴論旨指摘原\n    判決不當，求予廢棄改判，為無理由，應予駁回。至於上開\n    不應准許部分，原審未查，遽為上訴人敗訴判決，自有未洽\n    ，應由本院予以廢棄改判如主文所示。\n六、本件事證已臻明確，兩造其餘主張攻擊防禦方法及舉據，經\n    審核後認不影響本件判決結果，爰不予一一論列。另上訴人\n    請求囑託中華民國電機技師公會全國聯合會派員鑑定本件修\n    繕之電氣、消防是否為共用部分，施作之數量及單價是否屬\n    實，費用為若干等情，因該部分業經兩造在原審合意囑託臺\n    灣省建築師公會為鑑定，該鑑定報告結論並無明顯重大瑕疵\n    或不當之處，並經鑑定證人羅榮源在本院證稱明確，上訴人\n    聲請再囑託訴外人中華民國電機技師公會全國聯合會重為鑑\n    定，自無必要。另上訴人聲請本院向台灣電力股份有限公司\n    台中區營業處調取用電設計審查及竣工檢驗之圖說及文件、\n    向台灣自來水股份有限公司第四區管理處調取自來水設計審\n    、竣工檢驗之圖說及文件、向台中市消防局調取消防案全設\n    備設計審查、竣工檢驗之圖說及文件，以查明被上訴人主張\n    之共用部分項目及實際施作數量部分，因該部分業經監造之\n    己○○建築師事務所提出前開函文及相關文件資料為佐，並\n    經己○○建築師在本院結證在卷，核亦無不明確之處，上訴\n    人聲請再調閱上開文件重為調查，同無必要，併予敘明。\n據上論結，本件上訴為一部有理由，一部無理由，依民事訴訟法\n第449條第1項、第450條、第79條，判決如主文。\n中    華    民    國    99    年    5     月    12    日\n                民事第六庭    審判長法  官  袁再興\n                                    法  官  盧江陽\n                                    法  官  陳賢慧\n以上正本係照原本作成。\n如對本判決上訴，須於收受判決送達後20日內向本院提出上訴書\n狀，其未表明上訴理由者，應於提出上訴後20日內向本院提出上\n訴理由書（須按他造人數附具繕本）。\n上訴時應提出委任律師為訴訟代理人之委任狀。具有民事訴訟法\n第466條之1第1項但書或第2項之情形為訴訟代理人者，另應附具\n律師及格證書及釋明委任人與受任人有該條項所定關係之釋明文\n書影本。\n                                    書記官  吳麗琴\n中    華    民    國    99    年    5     月    13    日\n                                                      Ｖ",
  "structure": {
    "main": "原判決關於以本金新臺幣柒佰零伍萬壹仟陸佰零捌元計付超過自\n民國九十六年十月十七日起至清償日止按年息百分之五計算利息\n部分，及該部分假執行之宣告，暨訴訟費用之裁判均廢棄。\n上廢棄部分，被上訴人在第一審之訴及假執行之聲請均駁回。\n其餘上訴駁回。\n第一、二審訴訟費用由上訴人負擔百分之八十五，餘由被上訴人\n負擔。",
    "fact": "甲、程序方面：上訴人之法定代理人於民國98年1月5日變更為丁\n    ○○，並於98年6月4日具狀向本院聲明承受訴訟，有上訴人\n    提出之變更登記表影本及民事聲明承受訴訟狀一份在本院卷\n    為證（見本院卷(一)第4-11頁），核無不合，應予准許。\n乙、實體方面：\n壹、聲明部分：\n一、上訴人方面：(一)原判決不利於上訴人部分廢棄。(二)上開廢棄\n    部分，被上訴人在第一審之訴及假執行之聲請均駁回。\n二、被上訴人方面：駁回上訴。\n貳、陳述及理由部分：\n一、被上訴人主張：\n(一)、兩造為坐落台中市○○區○○段 325地號（下稱系爭土地）\n    上金矽谷銀河鉅星大樓（下稱系爭大樓）之區分所有權人，\n    被上訴人為建號台中市○○區○○段2117至2121建號即門牌\n    號碼台中市○○路○段151號9樓、10樓、11 樓、12樓、13樓\n    、14樓之1、14樓之2之建物（下稱系爭大樓之 9至15樓）區\n    分所有權人，上訴人則為建號台中市○○區○○段2102、21\n    04至2116建號即門牌號碼台中市○○路○段151號、151號2樓\n    、3樓、4樓、5樓、6樓之 1、之2、之3、之4、7樓之1、之2\n    、之3、之4、8樓建物（下稱系爭大樓1至 8樓）之區分所有\n    權人。雖兩造曾就系爭大樓外牆公共設施修繕工程，協議按\n    應有比例出資整修，即被上訴人為41.66％ （被上訴人戊○\n    ○為41.24％、被上訴人乙○○0.42％），上訴人則為58.34\n    ％。然就公共管道間之水、電力、消防及排煙幹管部分，是\n    否屬共用部分及是否須修復，兩造未能達成協議，被上訴人\n    為免發生公安意外及儘速符合相關建築及消防法規，且上開\n    修繕之保存行為實屬緊急及必要，故被上訴人委由訴外人威\n    祐科技有限公司（下稱威祐公司）對公共管道間之水、電力\n    、消防及排煙幹管部分加以修復，全部共用修繕工程金額為\n    新台幣（下同）12,087,090元，上訴人自應依兩造間應有部\n    分之比例分擔上開款項，爰求為命上訴人給付 7,051,608元\n    及自起訴狀繕本送達翌日起至清償日止按年息百分之 5計算\n    利息，及供擔保准為假執行宣告之判決。\n(二)、在本院補充陳述：\n  1.系爭大樓有修繕必要，業經兩造委任之建築師己○○評估在\n    案，嗣後亦經己○○建築師監造修繕完畢，並經台中建築師\n    公會鑑定屬實：被上訴人於標購大樓後，即與上訴人商討大\n    樓整修事宜，雙方並共同委任己○○建築師就大樓之整個外\n    觀及大樓內部作整修評估，並共同支付設計及監造費用 100\n    萬元。後被上訴人即依照建築師之規劃，交由威祐科技有限\n    公司承攬施工，由己○○建築師事務所負責監工（相關監工\n    費用皆以包含於上開 100萬元），未避免爭議，己○○建築\n    師亦依其專業將共同管道間及逃生樓梯部分之公共設施與上\n    訴人之私有部分加以區隔，分別計價，己○○建築師上開計\n    價結果，經台中建築師公會鑑定後，再扣除非公設部分之修\n    繕費，即為原審判決上訴人應負擔之金額，上訴人之上訴並\n    無理由。\n  2.己○○建築師認定兩造共同分擔之金額，係已排除上訴人主\n    張之「小公」部分：己○○建築師計算兩造須分擔之公設部\n    分，只計算大樓管道間及大樓逃生樓梯等空間部分，即上訴\n    人所指之「大公」部分，至於每樓層供公共使用之公共廁所\n    、走道照明、走道牆壁等設施，原本亦應屬公共設施部份（\n    即上訴人所謂之「小公」部分）卻漏未計入，此部分被上訴\n    人雖不贊同且仍有疑異，惟因並未計入公設部分請求，是上\n    訴人上訴理由中關於小公、大公部分之陳述，自無可採。\n  3.上訴人私下委託建築師所為之鑑定，不應作為有利上訴之依\n    據，本件仍應以台灣省建築師公會之鑑定為依據：上訴人私\n    下委託建築師所為之鑑定（下稱私人鑑定報告），並非由法\n    院所囑託鑑定，且費用亦由上訴人所支出，故上開建築師基\n    於上訴人之委任關係，其所為之鑑定以難祈客觀，故被上訴\n    人認上開鑑定報告實不應作為有利上訴之依據。又上訴人之\n    鑑定報告，並未會同法院及被上訴人，該鑑定報告所依據之\n    資料、資訊，亦不充足，實難期待其鑑定具有客觀及中立之\n    立場。本件兩造在原審已合意由台灣省建築師公會鑑定，台\n    灣省建築師公會並多次會同兩造到現場探勘，並請兩造各自\n    陳述意見，原審亦會同兩造及台灣省建築師公會鑑定建築師\n    、己○○建築師等人，一同前往系爭大樓就鑑定報告為說明\n    ，況上開鑑定報告之內容亦非全然對被上訴人有利，可信度\n    應屬較高。被上訴人在原審亦因之而自動減縮訴之聲明以示\n    尊重，然反觀上訴人卻因為未全然符合其利益，即一再質疑\n    上開鑑定之公信力，實屬不該。\n二、上訴人則以：\n(一)、系爭大樓早於80年 2月26日即建築完成，領有使用執照，並\n    無被上訴人所謂無法正常申請使用執照之情形，即被上訴人\n    所有之部分，僅因原所有權人未能充分利用，致被上訴人於\n    95年3月7日，經法院拍賣程序取得時，有失修損壞情形，然\n    此與使用執照無涉，並非不可使用，且依強制執行法第69條\n    之規定，被上訴人應自行承擔物之瑕疵之風險，豈可為圖己\n    用之利，強求上訴人為其分擔修繕費用，殊不合理。又兩造\n    雖曾就系爭大樓外牆公共設施修繕工程，協議按應有比例出\n    資整修，惟就被上訴人起訴主張公共管道間之水、電力、消\n    防及排煙幹管之修繕費用，並未達成合意，且該部分亦非共\n    用，再參以上訴人自88年起，即已於系爭大樓經營銀行業務\n    迄今，顯見並無被上訴人所稱公共管道間之主幹管已年久失\n    修、不堪使用，致生公共危險之虞，即並無修繕之必要，是\n    以，被上訴人所主張系爭部分之修繕，均係供被上訴人己用\n    之部分，故應由被上訴人自行支出修繕費用。復系爭部分之\n    修繕，更不屬民法第820第2項之「簡易修繕或其他保存行為\n    」，系爭修繕僅屬被上訴人為自己之經濟效用而有修繕必要\n    ，從而，為同條第3 項所稱之「改良行為」，非經共有人過\n    半數，並其應有部分合計已過半數者之同意不得為之，故上\n    訴人並無分攤修繕費用之責。再者，縱屬公用部分，系爭修\n    繕亦僅供個別樓層使用，即屬「一部共用部分」，而應由該\n    「一部共用部分」之區分所有權人即被上訴人自行負擔修繕\n    費用。\n(二)、在本院補充陳述：\n  1.蓋系爭大樓早有使用執照，建物完成後，已有使用，故不可\n    能有未能使用或有相關應具備之設備尚未裝修。上訴人拍賣\n    承受後，其中3至8樓因尚未擬定使用計畫，除部分作倉庫使\n    用外，其餘閒置，但均有善盡維修管理之責，部分設施雖屬\n    老舊，但尚能維持正常運作，水電供應正常，消防安檢亦有\n    通過，未有影響公共安全之虞，故無被上訴人所稱有急迫修\n    繕之必要。上訴人所屬1樓至2樓設立分行使用迄今，亦復如\n    此，若有立即公安危險，早就遭主管機關勒令停業，又何以\n    能在該大樓營業數年？自無被上訴人主張因有損壞，無法申\n    請使用執照。足見被上訴人所稱有修繕之急迫性與必要性，\n    自非事實。\n  2.被上訴人所稱修繕公共管道間之主幹管，包括消防灑水系統\n    、消防給水系統、一般給水系統、排水系統、污水系統及透\n    氣管線，上訴人否認其所修繕者為「主幹管」。縱屬真實，\n    上訴人亦否認有修繕之必要，蓋「主幹管」雖供整棟大樓公\n    用，但上開幹管均非一體成型，而係多段接管而成，此由被\n    上訴人在第一審提出之原證2照片即可證明，各樓層所屬幹\n    管若有修繕必要，亦僅須就樓層所屬接管處予以修繕或更換\n    即可，並無須整個主幹管均予修繕或更換。系爭大樓雖為兩\n    造共有，但因兩造各自所有樓層明確，則修繕各自樓層之共\n    有部分，即應自行負擔，例如各項水、電管線，即使經過共\n    同管道間，若非屬供整棟大樓使用之主幹管而僅是供個別樓\n    層使用，即屬「一部共用部分」，應由該「一部共用部分」\n    之區分所有權人自行負擔修繕費用。台灣省建築師公會就附\n    件六之整修工程項目，認屬共用部分，並未詳細區分，說明\n    何者屬「大公」或「小公」，其鑑定應非可信。\n  3.茲就被上訴人在第一審提出之合約書、第一、二、三、四次\n    估計價、結算表等，比較其內容製作統計表，發見其間有不\n    實之處，足見己○○建築師之估驗及結算不實。再己○○建\n    築師證稱其估算之金額12,624,418元，包括大公、小公部分\n    之工程款，至於大公或小公應由鑑定單位認定，但台灣省建\n    築師公會並未區分大公、小公，與己○○建築師上開證述內\n    容不符，是不僅該鑑定不實，且無法證明被上訴人之修繕均\n    屬大公，況依己○○證稱，其就被上訴人主張之共用部分修\n    繕之合約，係其與被上訴人達成共識的共用部分，則該合約\n    之修繕，是否確為共用部分，應非確論，否則何以稱應由鑑\n    定單位認定？甚此被上訴人起訴主張之共用部分，亦未經台\n    灣省建築師公會肯定均為共用部分可明。\n三、兩造就下列事實不為爭執，並有土地及建物謄本（見原審卷\n    (一)第11 -27頁反面）、兩造之協議書（見原審卷(一)第42頁）\n    、存證信函（見原審卷(一)第46 -47頁）、被上訴人之匯款單\n    及收據（見原審卷(一)第 52-54頁）、臺灣省建築師公會於97\n    年6月18日所出具之鑑定報告各1份在卷為佐，堪信為真，並\n    得採為判決基礎：\n(一)、兩造為系爭土地上系爭大樓之區分所有權人，被上訴人為系\n    爭大樓之9至15樓之區分所有權人，上訴人則為系爭大樓1至\n    8樓之區分所有權人。\n(二)、兩造曾就系爭大樓外牆公共設施修繕工程，協議按應有比例\n    出資整修，兩造應有部分比例為被上訴人 41.66％（被上訴\n    人戊○○為41.24％、被上訴人乙○○ 0.42％），上訴人則\n    為58.34％。\n(三)、被上訴人確曾就系爭大樓修繕費用所支應之修繕事項於動工\n    前通知上訴人，惟經上訴人於96年 9月14日以系爭修繕費用\n    非公用及非必要為由，而以96年9月14日合金總總字第09600\n    29474號函覆拒絕支付（見原審卷(一)第121頁）。\n(四)、被上訴人確曾匯款13,278,162元予訴外人魏英如（見原審卷\n    (一)第52-54頁）。\n(五)、臺灣省建築師公會於97年6月18日所出具之鑑定報告認「9層\n    至15層各戶電表集中箱體」、「提供電表用電開關變電箱」\n    及「提供公設梯間及梯廳、茶水間用電分盤」，乃不為共用\n    部分。\n四、至於被上訴人主張：其與上訴人共有之系爭大樓，因「公共\n    管道間」之「消防灑水系統、消防給水系統、污水系統、排\n    水系統及透氣管線」，與系爭大樓公共逃生梯各樓層中之「\n    消防栓廂設備、廣播設備及緊急逃生照明設備、排煙管道設\n    備、電信弱電箱」等共用設備修繕，因該等部分受有損害而\n    有修繕之必要，且屬於民法第820第2項所稱之「簡易修繕或\n    其他保存行為」，被上訴人經通知上訴人共同修繕未果後，\n    自行修繕，上訴人就被上訴人修繕所支出之費用，依法應按\n    所有權比例負擔，惟上訴人拒絕給付，被上訴人得請求上訴\n    人償還墊款等語，則惟上訴人否認，並以前詞抗辯，是本件\n    爭點為：被上訴人主張上訴人應依持分比例分擔系爭大樓共\n    用部分之修繕費7,062,608元，是否有理由？經查：\n(一)、本件被上訴人主張其所修繕者為系爭大樓「公共管道間」之\n    「消防灑水系統、消防給水系統、污水系統、排水系統及透\n    氣管線」及系爭大樓公共逃生梯各樓層中之「消防栓廂設備\n    、廣播設備及緊急逃生照明設備、排煙管道設備、電信弱電\n    箱」等設備，該等設備為系爭大樓之共用部分，雖為上訴人\n    所否認，惟查：\n  1.按「本法所稱建築物設備為敷設於建築物之電氣、煤氣、給\n    水、排水、空氣調節、昇降、消防、防空避難及污物處理等\n    設備」，建築法第10條定有明文。又「公寓大廈共用部分不\n    得獨立使用供做專有部分。其為下列各款者，並不得為約定\n    專用部分：一、公寓大廈本身所占之地面。二、連通數個專\n    有部分之走廊或樓梯，及其通往室外之通路或門廳；社區○\n    ○巷道、防火巷弄。三、公寓大廈基礎、主要樑柱、承重牆\n    壁、樓地板及屋頂之構造。四、約定專用有違法令使用限制\n    之規定者。五、其他有固定使用方法，並屬區分所有權人生\n    活利用上不可或缺之共用部分。」。公寓大廈管理條例第 7\n    條亦定有明文。本件敷設於系爭建築物如附表所示之電器、\n    煤氣、給水、排水等管線設備（除壹、電氣設備工程中之一\n    『項次一用途說明為9層至15 層各戶電錶集中箱體』、『項\n    次二之用途說明為提供電錶用電的開關受電箱』、『項次四\n    之用途說明為提供公設梯間及梯廳、茶水間用電分盤』等三\n    項不為共用部分，其餘項目均為共用部分，詳後敘說明），\n    係為供所有住戶共同使用，雖有部分管線設備位於專有部分\n    ，惟區分所有權人室內裝修時，於其專有部分內變更修改上\n    開管線乙節，依前開規定，敷設於建築物屬共用部分之電氣\n    、煤氣、給水、排水等，係屬有固定使用方法，並屬區分所\n    有權人生活利用上不可或缺之共用部分之建築物設備，雖有\n    部分管線設備通過專有部分，然依前揭條例第7條第5款規定\n    ，該等設備不得為約定專用部分，其性質上仍屬共用設備，\n    被上訴人主張公共管線為兩造共用之建築設備，應非無據。\n  2.又依被上訴人提出之施工照片及如附表所示之施工項目，被\n    上訴人所指之「公共管道間」本為「消防灑水系統、消防給\n    水系統、污水系統、排水系統及透氣管線」之必經地，即上\n    開管線皆為共同管線，由公共管道間中之各個主幹管連接至\n    1 至15樓各樓層，再由各樓層以次幹管連接至各住戶，故並\n    非每一樓層或每一樓層之各住戶獨自由公共管道間接管。而\n    消防栓廂設備，係指消防栓廂所連接消防泵浦、消防給水幹\n    管、相關火警連接設備及消防栓警急電源設備等。廣播設備\n    及警急停電逃生照明設備，則係各樓層大樓逃生梯間之廣播\n    器及與一樓大廳之廣播連線系統和警急停電逃生照明設備。\n    排煙管道設備，則包含排煙閘門、排煙閘門管線、排煙機及\n    排煙通道等。電信弱電箱，則包含弱電箱體、電話弱電幹線\n    、有線電幹線及寬頻網路幹管等。亦即所有電話有線電視及\n    寬頻網路皆須透過電信弱電幹線裝置於各樓層之電信弱電箱\n    ，再由各樓層分配到所須之該樓層住戶中。上開設備皆位於\n    公共逃生樓梯空間，即公共逃生樓梯空間為整棟系爭大樓公\n    共設備之公共管線運輸幹線，由此公共管線分配到各樓住戶\n    中，故並非如上訴人所述相關管線乃各樓層或各住戶獨立牽\n    拉管線，是以，公共管線運輸幹線有損害，則整棟大樓之相\n    關設備皆受影響，應可認定。\n  3.再查，本件被上訴人所修繕消防管線設備部分，乃系爭大樓\n    整體消防安全系統，包含火災之自動排煙管線設備、火災自\n    動灑水管設備及消防栓之消防噴水管線設備等三大消防管線\n    設備，上開管線並非各樓層獨立，而是系爭大樓共同之管線\n    ，蓋火警發生時必為全部消防系統一同啟動，消防系統當無\n    可能各樓層，甚至各戶獨立灑水或排煙。且系爭大樓之消防\n    灑水管線因有漏水及無法蓄壓之情形，又排煙管亦因年久失\n    修亦無法正常排煙，故須修繕填補漏水，如此方能使系爭大\n    樓由地下 3樓至地上15樓之消防管路功能正常運作。即所有\n    消防灑水、排煙設施能一體正常運作，位於底層之消防警報\n    設備始能正常啟動，並透過消防廣播系統通知所有位於系爭\n    大樓之人員安全疏散，此相關消防廣播系統之設備，既因年\n    久失修而損害，被上訴人從上訴人所在之樓層即地下室至15\n    樓全面更換修復，自非為被上訴人之利益而修繕。又上開設\n    備管道乃系爭大樓排水排煙或排放污水之主幹管，一體影響\n    全棟大樓之消防灑水、排煙設備運作，應屬建物之共用附屬\n    物，非僅供部分區分所有權人使用。依民法第 799條規定，\n    該等設備應推定為各所有人之共有，其修繕費及其他負擔，\n    自應由各所有人，按其所有部分之價值分擔之。\n  4.至於被上訴人所修繕之電信弱電工程，乃系爭大樓之基礎相\n    關弱電工程費用，其包含系爭大樓各樓層之電話、網路及有\n    線電視線之電信弱電箱修復，以便系爭大樓之各用戶日後能\n    按其需要獨自花費牽線使用，且於今電話及網路科技發達且\n    普遍之社會中，各樓住戶均以共用管線對外連結電話及網路\n    設備，何能要求各樓層中之各住戶獨立花費至大樓外獨自牽\n    立個別管線，是系爭電信弱電箱亦屬大樓之共用設備，亦可\n    認定。\n  5.另本件如附表所示被上訴人所修繕之工程，經兩造在原審合\n    意指定由台灣省建築師公會鑑定是否屬公用部分，經該公會\n    鑑定結果，亦認除「壹、電氣設備工程中之一『項次一用途\n    說明為 9層至15層各戶電錶集中箱體』、『項次二之用途說\n    明為提供電錶用電的開關受電箱』、『項次四之用途說明為\n    提供公設梯間及梯廳、茶水間用電分盤』」等三項不為共用\n    部分，其餘項目均為共用部分，亦有該公會97年 6月18日台\n    建師鑑（97038）字第129404號鑑定報告1份，在卷可參，更\n    明被上訴人主張如附表所示被上訴人所修繕之工程，除壹、\n    電氣設備工程中之一『項次一用途說明為 9層至15層各戶電\n    錶集中箱體』、『項次二之用途說明為提供電錶用電的開關\n    受電箱』、『項次四之用途說明為提供公設梯間及梯廳、茶\n    水間用電分盤』等三項外，其他工程修繕均係對兩造在系爭\n    大樓「生活利用上不可或缺」設備為修繕，有該公會97年 6\n    月18日台建師鑑（97038）字第 1294-4號鑑定報告書一份為\n    佐，並經參與該會鑑定過程之建築師庚○○○○○在本院結\n    證屬實（見本院卷(一)第9-11頁），上訴人否認被上訴人上開\n    修繕工程係針對兩造共有之公有區域設備為修繕等語，自無\n    可採。上訴人另在本院審理期間自行囑託訴外人甲○○及趙\n    天佐建築師鑑定，並提甲○○及趙天佐建築師之鑑定報告書\n    一冊（外放）為佐，並抗辯臺灣省建築師公會之上開鑑定報\n    告，與其所提出之之鑑定報告結論並不相同，臺灣省建築師\n    公會就甲○○及趙天佐建築師之鑑定報告書第 5頁第5、6項\n    即泡沫設備及排煙設備之鑑定意見亦前後不一，臺灣省建築\n    師公會之鑑定報告顯不可採等語。惟查，臺灣省建築師公會\n    之上開鑑定報告並無錯誤，至於臺灣省建築師公會98年10月\n    9日台建師鑑（97038）字第3451號函說明三記載：「上訴人\n    所送黃耀呈建築師事務所鑑定之鑑定報告書第5頁第5、6 項\n    可以接受為私有部分」等語（見本院卷(一)第 152頁），及嗣\n    後該會於98年12月11日函分別就泡沫設備及排煙設備所為之\n    說明：「一第五項泡沫設備可以接受為『私有部分』說明如\n    下：泡沬設備係裝置於停車空間之滅火設備，若該停車空間\n    產權全部屬於私人則應歸類為『私有部分』，若該停車空間\n    屬共同持有部分則應歸類為『公有部分』、二第六類排煙設\n    備可以接受為『私有部分』說明如下：依建築技術規則排煙\n    分區設於各戶居室排煙及特別安全梯或緊急升降機間，若排\n    煙設備屬居室排煙則為『私有部分』，若排煙設備屬特別安\n    全梯或緊急升降機間則為『公有部分』，依整修工程項目表\n    第六項排煙設備a、b、c 所述施工位置及用途說明並未存在\n    私有部分，故此部分應認定為『公有部分』」等語（見本院\n    卷(一)第 232頁），並非要變更臺灣省建築師公會上開鑑定之\n    結論一節，業經鑑定證人即參與上開鑑定報告之建築師羅榮\n    源在本院結證屬實，並證稱：「一兩份函的意思都不是要變\n    更原來鑑定之結論，而是說明有可能是私有，但因為本案的\n    建物是共有的所以第一份函的所謂第五頁第五、六項並非指\n    該部分是私有部分，理由是第五項地下室停車場是共同持分\n    所以該部分的泡沫設備應屬於公共設施，另外一項是第六項\n    排煙設備經再確認還是認為是共同部分，依據原來建築師的\n    施工圖該部分仍屬共有部分。二九十八年十二月十一日函部\n    分確認第五、六項確為共有部分，該函之意思是泡沫設備及\n    排煙設備可能產生私有部分之情形，本件建物依照建築師施\n    工圖上開二部分確實屬於公共設施。」、「本人不能對別人\n    的鑑定報告書發表意見，所以前開二份函文內容所指的是建\n    築師公會所做鑑定報告之項目。」、「【法官提示本院卷第\n    一五二頁，九十八年十月九日覆函說明三、所謂的該鑑定報\n    告書所述第五、六項可以接受為『私有部分』，其餘確認為\n    大樓共用部分，是指建築師公會的鑑定報告書或是上訴人在\n    本院提出的鑑定報告書？（提示並告以要旨）】鑑定證人庚\n    ○○○○○答：「上開函文的第五、六項是指建築師公會鑑\n    定報告書內之泡沫設備及排煙設備，如果該建物是屬於私有\n    的則其泡沫設備及排煙設備即屬於私有，但是本件是屬於共\n    同持有，所以仍屬於共同設備。我的函會這樣寫是指可能產\n    生的情形而已，並非指本件就是私有部分，所以結論就如鑑\n    定報告書所述。」等語（見本院卷(二)第 9頁反面、第10、11\n    頁），是自難據上開臺灣省建築師公會之二份函為該公會有\n    認同甲○○及趙天佐建築師之鑑定結論或有變更其在原審所\n    為鑑定結論之依據，況上開甲○○及趙天佐建築師係受上訴\n    人單方面委任，並非由兩造合意或法院指定之鑑定人，鑑定\n    時亦未會同法院及兩造到場表示意見，自不足採信。是上訴\n    人抗辯臺灣省建築師公會之鑑定報告與甲○○及趙天佐之上\n    開鑑定報告結論不同，及臺灣省建築師公會上開二份函之內\n    容前後矛盾，應以甲○○及趙天佐之鑑定報告為可採等語，\n    顯不可採等語，自無理由。\n(二)、又被上訴人主張就前述系爭大樓公用「公共管道間」之「消\n    防灑水系統、消防給水系統、污水系統、排水系統及透氣管\n    線」與系爭大樓公共逃生梯各樓層中之「消防栓廂設備、廣\n    播設備及緊急逃生照明設備、排煙管道設備、電信弱電箱」\n    部分之修繕，為保存系爭大樓即避免損害而為修繕，其修繕\n    屬必要之保存行為，雖為上訴人否認，然查：\n  1.系爭大樓於80年 2月26日取得使用執照，上訴人於87年間曾\n    委託訴外人長譽水電工程有限公司辦理水電消防等復原工程\n    ，依其工程估價單所載工程款合計為 23,778,668元（含稅）\n    之事實，有上訴人提出系爭大樓使用執照影本 1份附在原審\n    卷（見原審卷(一)第68-70頁）、合作金庫工程合約書影本1份\n    在本院卷（見本院卷(一)第 60-99頁）為佐，足認系爭大樓雖\n    於80年 2月26日取得使用執照，惟不足以證明已符合堪用狀\n    態，否則上訴人於87年間即無支出大筆工程款進行復原工程\n    之必要，是上訴人抗辯系爭大樓於80年 2月26日取得使用執\n    照，並無不能使用情形，無進行修繕必要等語，自無足取。\n    再本院審酌系爭大樓取得使用執照迄上訴人為上開復原工程\n    之87年間相距約 8年，至被上訴人進行本件修繕工程之96年\n    間亦已相距約16年時間，而上訴人為復原工程迄被上訴人為\n    本件修繕工程時則相距約 9年時間，上訴人於87年間辦理復\n    原工程之工程費已多達 2,300餘萬元之多，足認系爭大樓原\n    來之水電消防設備於87年間係處在若不進行復原工程不足以\n    堪用之狀態，否則上訴人亦無進行水電消防等復原工程之必\n    要，再上訴人自進行上開修復工程迄今僅使用系爭大樓之一\n    、二樓，其餘三至八樓部分並未使用，且因三至八樓並未使\n    用，故每年之消防安檢僅檢查一、二樓部分，並未就三至八\n    樓部分做檢查等情，業經上訴人在本院自陳在卷（見本院卷\n    (一)第 119頁反面），是縱認上訴人曾於87年間為水電消防之\n    復原工程，惟因上訴人長期僅使用系爭大樓一、二樓部分，\n    其餘三至八樓部分則未使用且未進行消防安檢，亦僅足認其\n    一、二樓部分係得使用狀態，於上訴人未舉證證明系爭大樓\n    全棟之共用設備部分於87年間經其進行復原工程迄96年間止\n    均處在堪用狀態，自難認上訴人抗辯其曾於87年為上開復原\n    工程以後，系爭大樓全部之公共設備均為堪用狀態為可採，\n    況系爭大樓於96年12月間仍有多項設施不合格，致被上訴人\n    不能申請變更使用，迄本件修繕後始通過檢驗，由台中市政\n    於97年1月16日發給合格證明字號97府都建室字第0022-00號\n    建築物室內裝修合格證明書之事實，亦有被上訴人所提出之\n    台中市政府合格證明字號97府都建室字第 0022-00號建築物\n    室內裝修合格證明、台中市政府97年1月17日府都管字第097\n    0015950號函影本各1份在原審卷為證（見原審卷(一)第220-22\n    1 頁），是被上訴人主張系爭大樓有修繕必要，其修繕部分\n    均為公共管道間之水、電力、消防及排煙幹管等設備，該等\n    設備年久失修損壞，嚴重影響大樓之消防、照明及逃生等公\n    共安全問題，且系爭大樓之相關電器設備、給排水設備及電\n    信弱電工程亦嚴重損壞或尚未裝修，導致系爭大樓無法正常\n    ，若未修繕，則系爭大樓除上訴人已使用之1樓及2樓部分外\n    ，餘皆無法正常使用，且因未完成修繕，消防安檢亦無法通\n    過，致被上訴人無法申請變更執照，故前開設施確有修繕之\n    必要等語，自足採信，且應認被上訴人所為之修繕，顯屬防\n    止共有物之滅失、毀損或權利之喪失、限制等為目的，以維\n    持大樓基本堪用狀態，發揮其應有效用之行為，是本件修繕\n    自屬民法第820第2項規定之「其他保存行為」。\n  2.再查，系爭大樓之共有人僅有兩造共為三人，共有人人數不\n    多，自無召開區分所有權人會議籌組公寓大廈管理委員會之\n    必要（系爭大樓於本案涉訟後之97年 1月28日，已報備設置\n    管理負責人），系爭大樓之公用設備之修繕、管理，依民法\n    第 820條規定為之即可，此由系爭大樓之外牆係由兩造以協\n    議方式修繕完畢，且按各共有人所有權應有部分比例負擔修\n    繕費用，益證就系爭大樓共用之部分以由兩造共負管理之責\n    並依應有部分比例各自分擔修繕費用之方式為之，並無困難\n    。再按民法第820條第2項所稱「保存行為」係指以防止共有\n    物之滅失、毀損或權利之喪失、限制等為目的，以維持現狀\n    之行為，本件系爭大樓公用「公共管道間」之「消防灑水系\n    統、消防給水系統、污水系統、排水系統及透氣管線」與系\n    爭大樓公共逃生梯各樓層中之「消防栓廂設備、廣播設備及\n    緊急逃生照明設備、排煙管道設備、電信弱電箱」等兩造共\n    用部分之設備，本即為防止共有物之滅失、毀損之設施，該\n    等設備既有毀損，並有礙系爭大樓之安全維護及使用之完整\n    性，自應由兩造共負修繕之責任，惟本件被上訴人請求上訴\n    人共同協議修繕，業經上訴人拒絕，有96年8月8日台中漢口\n    郵局第804號存證信函影本1份在原審卷為佐（見原審卷(一)第\n    46、47頁），被上訴人因而自行發包修繕以保存系爭大樓之\n    使用完整性及維護整棟大樓之安全，其為保存系爭大樓所為\n    之修繕，實屬必要。上訴人抗辯本件修繕未經其同意及系爭\n    修繕非屬必要之保存行為，並進而拒絕負擔修繕費用，自屬\n    無據。\n(三)、再查，被上訴人主張系爭大樓如附表所示之修繕工程業已全\n    部完工，被上訴人亦已支付全部工程款之事實，業據被上訴\n    人所提出匯款紀錄、（公有部分）整修工程詳細價目表影本\n    被上訴人與威祐公司之合約書、良岳營造有限公司書節本、\n    開立予被上訴人之統一發票、被上訴人之匯款紀錄、被上訴\n    人於98年 3月12日與威祐公司簽訂之「協議書」、台中銀行\n    中台中分行匯款單、第一次公有及私有結算表、96年 9月13\n    日合作金庫匯款單、第二次公有及私有結算表、96年10月11\n    日合作金庫匯款單、第三次公有及私有結算表、96年11月 9\n    日合作金庫匯款單、第四次公有及私有結算表、97年 1月10\n    日合作金庫匯款單、錯誤之公有結算表副本、竣工圖表、竣\n    工查驗紀錄、己○○建築師事務所96年10月30日安建字第96\n    076號函、己○○建築師事務所96年11月12日安建字第96085\n    號函、威祐公司之匯款單等件各 1份在原審卷為證（見原審\n    卷(二)第146-147頁、第131-144頁、第149-152頁、第153頁、\n    第241-270 頁），堪信為真。再查，被上訴人主張本件共用\n    設備修繕工程（即附表所示全部工程）之工程款合計為12,6\n    24,418元（含5%之稅金，稅前金額為12,023,255元）一節，\n    有己○○建築師事務所98年3月5日安建字第 98022號確認函\n    、結算表各1份在原審卷可稽（見原審卷(二)第117-125頁），\n    並經己○○建築師在本院結證屬實（見本院卷(一)第 133頁反\n    面、第 134頁），堪信為真。另查，附表所示之工程經兩造\n    在原審合意指定台灣省建築公會鑑定該修繕工程何部分為公\n    用，何部分為私用結果，經臺灣建築額公會鑑定結果，認如\n    附表所示被上訴人所修繕之工程中，除「壹、電氣設備工程\n    中之一『項次一用途說明為 9層至15層各戶電錶集中箱體』\n    、『項次二之用途說明為提供電錶用電的開關受電箱』、『\n    項次四之用途說明為提供公設梯間及梯廳、茶水間用電分盤\n    』」等三項外，其他工程修繕均屬共用設備之事實，已如前\n    述，是本件依被上訴人主張以稅前金額即12,023,255元扣除\n    上開經鑑定非屬共用設備部分之工程款（見原審卷(二)第 126\n    頁反面、第127頁），即扣除9層至15層各戶電錶集中箱體部\n    分100,500元、提供電錶用電的開關受電箱部分268,800元、\n    提供公設梯間及梯廳、茶水間用電分盤部分 142,440元，其\n    稅後餘額為12,087,090元（計算式為：12,023,255元－100,\n    500元－268,800元－142,440元＝11,511,515元。11,511,51\n    5＋〔11,511,5155%〕＝12,087,090元 ）應可認定。另本\n    件被上訴人發包整修時，就公用及私人使用之修繕費，已分\n    別列冊結算有前述（公有部分）整修工程詳細價目表、四次\n    公有、私有結算表在卷可稽，且經己○○建築師確認結算，\n    亦有前開己○○建築師事務所98年3月5日安建字第 98022號\n    確認函文1份、結算表1份在原審卷為佐，上訴人以被上訴人\n    進行之本件修繕工程有公用、私用設備不分情形，拒絕償還\n    被上訴人代墊之修繕費，並無理由。\n(四)、按「共有物之管理費，及其他擔負，除契約另有訂定外，應\n    由各共有人，按其應有部分分擔之。共有人中之一人，就共\n    有物之擔負為支付，而逾其所應分擔之部分者，對於其他共\n    有人，得按其各應分擔之部分，請求償還」，民法第 822條\n    定有明文。本件兩造共有之系爭大樓附屬之公用設備，因有\n    修繕之必要，且經被上訴人完成修繕，其應支付之修繕費用\n    為12,087,090元，依前開法文規定，自應由兩造就系爭負用\n    按應有部分之比例分攤。準此，被上訴人主張上訴人應依其\n    所有權應有部分之比例即58.34%分擔7,051,608元 （計算式\n    ：00000000元58.34%＝0000000元。 元以下四捨五入），\n    核屬有據。再上開修繕費用12,087,090元已由被上訴人支付\n    亦如前述，是被上訴人請求上訴人返還被上訴人應分擔額7,\n    051,608元，為有理由，應予准許。\n五、綜上所述，被上訴人主張上訴人應分擔系爭大樓之公用設備\n    修繕費7,051,608元 ，已由被上訴人代為支付，上訴人迄未\n    返還被上訴人，均如前述。從而，被上訴人依修繕費用償還\n    請求權之法律關係，請求上訴人給付7,051,608元 ，及自起\n    訴狀繕本送達（見原審卷(一)第62頁）之翌日即96年10月17日\n    起至清償日止按年息百分之 5計算之利息，為有理由，應予\n    准許。至於逾上開金額之請求（即利息請求逾自96年10月17\n    日起算部分），則無理由，不應准許。原審就上開應准許部\n    分，為上訴人敗訴判決，並依兩造陳明，分別酌定相當供擔\n    保金額，為准免假執行之宣告，核無不合。上訴論旨指摘原\n    判決不當，求予廢棄改判，為無理由，應予駁回。至於上開\n    不應准許部分，原審未查，遽為上訴人敗訴判決，自有未洽\n    ，應由本院予以廢棄改判如主文所示。\n六、本件事證已臻明確，兩造其餘主張攻擊防禦方法及舉據，經\n    審核後認不影響本件判決結果，爰不予一一論列。另上訴人\n    請求囑託中華民國電機技師公會全國聯合會派員鑑定本件修\n    繕之電氣、消防是否為共用部分，施作之數量及單價是否屬\n    實，費用為若干等情，因該部分業經兩造在原審合意囑託臺\n    灣省建築師公會為鑑定，該鑑定報告結論並無明顯重大瑕疵\n    或不當之處，並經鑑定證人羅榮源在本院證稱明確，上訴人\n    聲請再囑託訴外人中華民國電機技師公會全國聯合會重為鑑\n    定，自無必要。另上訴人聲請本院向台灣電力股份有限公司\n    台中區營業處調取用電設計審查及竣工檢驗之圖說及文件、\n    向台灣自來水股份有限公司第四區管理處調取自來水設計審\n    、竣工檢驗之圖說及文件、向台中市消防局調取消防案全設\n    備設計審查、竣工檢驗之圖說及文件，以查明被上訴人主張\n    之共用部分項目及實際施作數量部分，因該部分業經監造之\n    己○○建築師事務所提出前開函文及相關文件資料為佐，並\n    經己○○建築師在本院結證在卷，核亦無不明確之處，上訴\n    人聲請再調閱上開文件重為調查，同無必要，併予敘明。\n據上論結，本件上訴為一部有理由，一部無理由，依民事訴訟法\n第449條第1項、第450條、第79條，判決如主文。",
    "reason": "甲、程序方面：上訴人之法定代理人於民國98年1月5日變更為丁\n    ○○，並於98年6月4日具狀向本院聲明承受訴訟，有上訴人\n    提出之變更登記表影本及民事聲明承受訴訟狀一份在本院卷\n    為證（見本院卷(一)第4-11頁），核無不合，應予准許。\n乙、實體方面：\n壹、聲明部分：\n一、上訴人方面：(一)原判決不利於上訴人部分廢棄。(二)上開廢棄\n    部分，被上訴人在第一審之訴及假執行之聲請均駁回。\n二、被上訴人方面：駁回上訴。\n貳、陳述及理由部分：\n一、被上訴人主張：\n(一)、兩造為坐落台中市○○區○○段 325地號（下稱系爭土地）\n    上金矽谷銀河鉅星大樓（下稱系爭大樓）之區分所有權人，\n    被上訴人為建號台中市○○區○○段2117至2121建號即門牌\n    號碼台中市○○路○段151號9樓、10樓、11 樓、12樓、13樓\n    、14樓之1、14樓之2之建物（下稱系爭大樓之 9至15樓）區\n    分所有權人，上訴人則為建號台中市○○區○○段2102、21\n    04至2116建號即門牌號碼台中市○○路○段151號、151號2樓\n    、3樓、4樓、5樓、6樓之 1、之2、之3、之4、7樓之1、之2\n    、之3、之4、8樓建物（下稱系爭大樓1至 8樓）之區分所有\n    權人。雖兩造曾就系爭大樓外牆公共設施修繕工程，協議按\n    應有比例出資整修，即被上訴人為41.66％ （被上訴人戊○\n    ○為41.24％、被上訴人乙○○0.42％），上訴人則為58.34\n    ％。然就公共管道間之水、電力、消防及排煙幹管部分，是\n    否屬共用部分及是否須修復，兩造未能達成協議，被上訴人\n    為免發生公安意外及儘速符合相關建築及消防法規，且上開\n    修繕之保存行為實屬緊急及必要，故被上訴人委由訴外人威\n    祐科技有限公司（下稱威祐公司）對公共管道間之水、電力\n    、消防及排煙幹管部分加以修復，全部共用修繕工程金額為\n    新台幣（下同）12,087,090元，上訴人自應依兩造間應有部\n    分之比例分擔上開款項，爰求為命上訴人給付 7,051,608元\n    及自起訴狀繕本送達翌日起至清償日止按年息百分之 5計算\n    利息，及供擔保准為假執行宣告之判決。\n(二)、在本院補充陳述：\n  1.系爭大樓有修繕必要，業經兩造委任之建築師己○○評估在\n    案，嗣後亦經己○○建築師監造修繕完畢，並經台中建築師\n    公會鑑定屬實：被上訴人於標購大樓後，即與上訴人商討大\n    樓整修事宜，雙方並共同委任己○○建築師就大樓之整個外\n    觀及大樓內部作整修評估，並共同支付設計及監造費用 100\n    萬元。後被上訴人即依照建築師之規劃，交由威祐科技有限\n    公司承攬施工，由己○○建築師事務所負責監工（相關監工\n    費用皆以包含於上開 100萬元），未避免爭議，己○○建築\n    師亦依其專業將共同管道間及逃生樓梯部分之公共設施與上\n    訴人之私有部分加以區隔，分別計價，己○○建築師上開計\n    價結果，經台中建築師公會鑑定後，再扣除非公設部分之修\n    繕費，即為原審判決上訴人應負擔之金額，上訴人之上訴並\n    無理由。\n  2.己○○建築師認定兩造共同分擔之金額，係已排除上訴人主\n    張之「小公」部分：己○○建築師計算兩造須分擔之公設部\n    分，只計算大樓管道間及大樓逃生樓梯等空間部分，即上訴\n    人所指之「大公」部分，至於每樓層供公共使用之公共廁所\n    、走道照明、走道牆壁等設施，原本亦應屬公共設施部份（\n    即上訴人所謂之「小公」部分）卻漏未計入，此部分被上訴\n    人雖不贊同且仍有疑異，惟因並未計入公設部分請求，是上\n    訴人上訴理由中關於小公、大公部分之陳述，自無可採。\n  3.上訴人私下委託建築師所為之鑑定，不應作為有利上訴之依\n    據，本件仍應以台灣省建築師公會之鑑定為依據：上訴人私\n    下委託建築師所為之鑑定（下稱私人鑑定報告），並非由法\n    院所囑託鑑定，且費用亦由上訴人所支出，故上開建築師基\n    於上訴人之委任關係，其所為之鑑定以難祈客觀，故被上訴\n    人認上開鑑定報告實不應作為有利上訴之依據。又上訴人之\n    鑑定報告，並未會同法院及被上訴人，該鑑定報告所依據之\n    資料、資訊，亦不充足，實難期待其鑑定具有客觀及中立之\n    立場。本件兩造在原審已合意由台灣省建築師公會鑑定，台\n    灣省建築師公會並多次會同兩造到現場探勘，並請兩造各自\n    陳述意見，原審亦會同兩造及台灣省建築師公會鑑定建築師\n    、己○○建築師等人，一同前往系爭大樓就鑑定報告為說明\n    ，況上開鑑定報告之內容亦非全然對被上訴人有利，可信度\n    應屬較高。被上訴人在原審亦因之而自動減縮訴之聲明以示\n    尊重，然反觀上訴人卻因為未全然符合其利益，即一再質疑\n    上開鑑定之公信力，實屬不該。\n二、上訴人則以：\n(一)、系爭大樓早於80年 2月26日即建築完成，領有使用執照，並\n    無被上訴人所謂無法正常申請使用執照之情形，即被上訴人\n    所有之部分，僅因原所有權人未能充分利用，致被上訴人於\n    95年3月7日，經法院拍賣程序取得時，有失修損壞情形，然\n    此與使用執照無涉，並非不可使用，且依強制執行法第69條\n    之規定，被上訴人應自行承擔物之瑕疵之風險，豈可為圖己\n    用之利，強求上訴人為其分擔修繕費用，殊不合理。又兩造\n    雖曾就系爭大樓外牆公共設施修繕工程，協議按應有比例出\n    資整修，惟就被上訴人起訴主張公共管道間之水、電力、消\n    防及排煙幹管之修繕費用，並未達成合意，且該部分亦非共\n    用，再參以上訴人自88年起，即已於系爭大樓經營銀行業務\n    迄今，顯見並無被上訴人所稱公共管道間之主幹管已年久失\n    修、不堪使用，致生公共危險之虞，即並無修繕之必要，是\n    以，被上訴人所主張系爭部分之修繕，均係供被上訴人己用\n    之部分，故應由被上訴人自行支出修繕費用。復系爭部分之\n    修繕，更不屬民法第820第2項之「簡易修繕或其他保存行為\n    」，系爭修繕僅屬被上訴人為自己之經濟效用而有修繕必要\n    ，從而，為同條第3 項所稱之「改良行為」，非經共有人過\n    半數，並其應有部分合計已過半數者之同意不得為之，故上\n    訴人並無分攤修繕費用之責。再者，縱屬公用部分，系爭修\n    繕亦僅供個別樓層使用，即屬「一部共用部分」，而應由該\n    「一部共用部分」之區分所有權人即被上訴人自行負擔修繕\n    費用。\n(二)、在本院補充陳述：\n  1.蓋系爭大樓早有使用執照，建物完成後，已有使用，故不可\n    能有未能使用或有相關應具備之設備尚未裝修。上訴人拍賣\n    承受後，其中3至8樓因尚未擬定使用計畫，除部分作倉庫使\n    用外，其餘閒置，但均有善盡維修管理之責，部分設施雖屬\n    老舊，但尚能維持正常運作，水電供應正常，消防安檢亦有\n    通過，未有影響公共安全之虞，故無被上訴人所稱有急迫修\n    繕之必要。上訴人所屬1樓至2樓設立分行使用迄今，亦復如\n    此，若有立即公安危險，早就遭主管機關勒令停業，又何以\n    能在該大樓營業數年？自無被上訴人主張因有損壞，無法申\n    請使用執照。足見被上訴人所稱有修繕之急迫性與必要性，\n    自非事實。\n  2.被上訴人所稱修繕公共管道間之主幹管，包括消防灑水系統\n    、消防給水系統、一般給水系統、排水系統、污水系統及透\n    氣管線，上訴人否認其所修繕者為「主幹管」。縱屬真實，\n    上訴人亦否認有修繕之必要，蓋「主幹管」雖供整棟大樓公\n    用，但上開幹管均非一體成型，而係多段接管而成，此由被\n    上訴人在第一審提出之原證2照片即可證明，各樓層所屬幹\n    管若有修繕必要，亦僅須就樓層所屬接管處予以修繕或更換\n    即可，並無須整個主幹管均予修繕或更換。系爭大樓雖為兩\n    造共有，但因兩造各自所有樓層明確，則修繕各自樓層之共\n    有部分，即應自行負擔，例如各項水、電管線，即使經過共\n    同管道間，若非屬供整棟大樓使用之主幹管而僅是供個別樓\n    層使用，即屬「一部共用部分」，應由該「一部共用部分」\n    之區分所有權人自行負擔修繕費用。台灣省建築師公會就附\n    件六之整修工程項目，認屬共用部分，並未詳細區分，說明\n    何者屬「大公」或「小公」，其鑑定應非可信。\n  3.茲就被上訴人在第一審提出之合約書、第一、二、三、四次\n    估計價、結算表等，比較其內容製作統計表，發見其間有不\n    實之處，足見己○○建築師之估驗及結算不實。再己○○建\n    築師證稱其估算之金額12,624,418元，包括大公、小公部分\n    之工程款，至於大公或小公應由鑑定單位認定，但台灣省建\n    築師公會並未區分大公、小公，與己○○建築師上開證述內\n    容不符，是不僅該鑑定不實，且無法證明被上訴人之修繕均\n    屬大公，況依己○○證稱，其就被上訴人主張之共用部分修\n    繕之合約，係其與被上訴人達成共識的共用部分，則該合約\n    之修繕，是否確為共用部分，應非確論，否則何以稱應由鑑\n    定單位認定？甚此被上訴人起訴主張之共用部分，亦未經台\n    灣省建築師公會肯定均為共用部分可明。\n三、兩造就下列事實不為爭執，並有土地及建物謄本（見原審卷\n    (一)第11 -27頁反面）、兩造之協議書（見原審卷(一)第42頁）\n    、存證信函（見原審卷(一)第46 -47頁）、被上訴人之匯款單\n    及收據（見原審卷(一)第 52-54頁）、臺灣省建築師公會於97\n    年6月18日所出具之鑑定報告各1份在卷為佐，堪信為真，並\n    得採為判決基礎：\n(一)、兩造為系爭土地上系爭大樓之區分所有權人，被上訴人為系\n    爭大樓之9至15樓之區分所有權人，上訴人則為系爭大樓1至\n    8樓之區分所有權人。\n(二)、兩造曾就系爭大樓外牆公共設施修繕工程，協議按應有比例\n    出資整修，兩造應有部分比例為被上訴人 41.66％（被上訴\n    人戊○○為41.24％、被上訴人乙○○ 0.42％），上訴人則\n    為58.34％。\n(三)、被上訴人確曾就系爭大樓修繕費用所支應之修繕事項於動工\n    前通知上訴人，惟經上訴人於96年 9月14日以系爭修繕費用\n    非公用及非必要為由，而以96年9月14日合金總總字第09600\n    29474號函覆拒絕支付（見原審卷(一)第121頁）。\n(四)、被上訴人確曾匯款13,278,162元予訴外人魏英如（見原審卷\n    (一)第52-54頁）。\n(五)、臺灣省建築師公會於97年6月18日所出具之鑑定報告認「9層\n    至15層各戶電表集中箱體」、「提供電表用電開關變電箱」\n    及「提供公設梯間及梯廳、茶水間用電分盤」，乃不為共用\n    部分。\n四、至於被上訴人主張：其與上訴人共有之系爭大樓，因「公共\n    管道間」之「消防灑水系統、消防給水系統、污水系統、排\n    水系統及透氣管線」，與系爭大樓公共逃生梯各樓層中之「\n    消防栓廂設備、廣播設備及緊急逃生照明設備、排煙管道設\n    備、電信弱電箱」等共用設備修繕，因該等部分受有損害而\n    有修繕之必要，且屬於民法第820第2項所稱之「簡易修繕或\n    其他保存行為」，被上訴人經通知上訴人共同修繕未果後，\n    自行修繕，上訴人就被上訴人修繕所支出之費用，依法應按\n    所有權比例負擔，惟上訴人拒絕給付，被上訴人得請求上訴\n    人償還墊款等語，則惟上訴人否認，並以前詞抗辯，是本件\n    爭點為：被上訴人主張上訴人應依持分比例分擔系爭大樓共\n    用部分之修繕費7,062,608元，是否有理由？經查：\n(一)、本件被上訴人主張其所修繕者為系爭大樓「公共管道間」之\n    「消防灑水系統、消防給水系統、污水系統、排水系統及透\n    氣管線」及系爭大樓公共逃生梯各樓層中之「消防栓廂設備\n    、廣播設備及緊急逃生照明設備、排煙管道設備、電信弱電\n    箱」等設備，該等設備為系爭大樓之共用部分，雖為上訴人\n    所否認，惟查：\n  1.按「本法所稱建築物設備為敷設於建築物之電氣、煤氣、給\n    水、排水、空氣調節、昇降、消防、防空避難及污物處理等\n    設備」，建築法第10條定有明文。又「公寓大廈共用部分不\n    得獨立使用供做專有部分。其為下列各款者，並不得為約定\n    專用部分：一、公寓大廈本身所占之地面。二、連通數個專\n    有部分之走廊或樓梯，及其通往室外之通路或門廳；社區○\n    ○巷道、防火巷弄。三、公寓大廈基礎、主要樑柱、承重牆\n    壁、樓地板及屋頂之構造。四、約定專用有違法令使用限制\n    之規定者。五、其他有固定使用方法，並屬區分所有權人生\n    活利用上不可或缺之共用部分。」。公寓大廈管理條例第 7\n    條亦定有明文。本件敷設於系爭建築物如附表所示之電器、\n    煤氣、給水、排水等管線設備（除壹、電氣設備工程中之一\n    『項次一用途說明為9層至15 層各戶電錶集中箱體』、『項\n    次二之用途說明為提供電錶用電的開關受電箱』、『項次四\n    之用途說明為提供公設梯間及梯廳、茶水間用電分盤』等三\n    項不為共用部分，其餘項目均為共用部分，詳後敘說明），\n    係為供所有住戶共同使用，雖有部分管線設備位於專有部分\n    ，惟區分所有權人室內裝修時，於其專有部分內變更修改上\n    開管線乙節，依前開規定，敷設於建築物屬共用部分之電氣\n    、煤氣、給水、排水等，係屬有固定使用方法，並屬區分所\n    有權人生活利用上不可或缺之共用部分之建築物設備，雖有\n    部分管線設備通過專有部分，然依前揭條例第7條第5款規定\n    ，該等設備不得為約定專用部分，其性質上仍屬共用設備，\n    被上訴人主張公共管線為兩造共用之建築設備，應非無據。\n  2.又依被上訴人提出之施工照片及如附表所示之施工項目，被\n    上訴人所指之「公共管道間」本為「消防灑水系統、消防給\n    水系統、污水系統、排水系統及透氣管線」之必經地，即上\n    開管線皆為共同管線，由公共管道間中之各個主幹管連接至\n    1 至15樓各樓層，再由各樓層以次幹管連接至各住戶，故並\n    非每一樓層或每一樓層之各住戶獨自由公共管道間接管。而\n    消防栓廂設備，係指消防栓廂所連接消防泵浦、消防給水幹\n    管、相關火警連接設備及消防栓警急電源設備等。廣播設備\n    及警急停電逃生照明設備，則係各樓層大樓逃生梯間之廣播\n    器及與一樓大廳之廣播連線系統和警急停電逃生照明設備。\n    排煙管道設備，則包含排煙閘門、排煙閘門管線、排煙機及\n    排煙通道等。電信弱電箱，則包含弱電箱體、電話弱電幹線\n    、有線電幹線及寬頻網路幹管等。亦即所有電話有線電視及\n    寬頻網路皆須透過電信弱電幹線裝置於各樓層之電信弱電箱\n    ，再由各樓層分配到所須之該樓層住戶中。上開設備皆位於\n    公共逃生樓梯空間，即公共逃生樓梯空間為整棟系爭大樓公\n    共設備之公共管線運輸幹線，由此公共管線分配到各樓住戶\n    中，故並非如上訴人所述相關管線乃各樓層或各住戶獨立牽\n    拉管線，是以，公共管線運輸幹線有損害，則整棟大樓之相\n    關設備皆受影響，應可認定。\n  3.再查，本件被上訴人所修繕消防管線設備部分，乃系爭大樓\n    整體消防安全系統，包含火災之自動排煙管線設備、火災自\n    動灑水管設備及消防栓之消防噴水管線設備等三大消防管線\n    設備，上開管線並非各樓層獨立，而是系爭大樓共同之管線\n    ，蓋火警發生時必為全部消防系統一同啟動，消防系統當無\n    可能各樓層，甚至各戶獨立灑水或排煙。且系爭大樓之消防\n    灑水管線因有漏水及無法蓄壓之情形，又排煙管亦因年久失\n    修亦無法正常排煙，故須修繕填補漏水，如此方能使系爭大\n    樓由地下 3樓至地上15樓之消防管路功能正常運作。即所有\n    消防灑水、排煙設施能一體正常運作，位於底層之消防警報\n    設備始能正常啟動，並透過消防廣播系統通知所有位於系爭\n    大樓之人員安全疏散，此相關消防廣播系統之設備，既因年\n    久失修而損害，被上訴人從上訴人所在之樓層即地下室至15\n    樓全面更換修復，自非為被上訴人之利益而修繕。又上開設\n    備管道乃系爭大樓排水排煙或排放污水之主幹管，一體影響\n    全棟大樓之消防灑水、排煙設備運作，應屬建物之共用附屬\n    物，非僅供部分區分所有權人使用。依民法第 799條規定，\n    該等設備應推定為各所有人之共有，其修繕費及其他負擔，\n    自應由各所有人，按其所有部分之價值分擔之。\n  4.至於被上訴人所修繕之電信弱電工程，乃系爭大樓之基礎相\n    關弱電工程費用，其包含系爭大樓各樓層之電話、網路及有\n    線電視線之電信弱電箱修復，以便系爭大樓之各用戶日後能\n    按其需要獨自花費牽線使用，且於今電話及網路科技發達且\n    普遍之社會中，各樓住戶均以共用管線對外連結電話及網路\n    設備，何能要求各樓層中之各住戶獨立花費至大樓外獨自牽\n    立個別管線，是系爭電信弱電箱亦屬大樓之共用設備，亦可\n    認定。\n  5.另本件如附表所示被上訴人所修繕之工程，經兩造在原審合\n    意指定由台灣省建築師公會鑑定是否屬公用部分，經該公會\n    鑑定結果，亦認除「壹、電氣設備工程中之一『項次一用途\n    說明為 9層至15層各戶電錶集中箱體』、『項次二之用途說\n    明為提供電錶用電的開關受電箱』、『項次四之用途說明為\n    提供公設梯間及梯廳、茶水間用電分盤』」等三項不為共用\n    部分，其餘項目均為共用部分，亦有該公會97年 6月18日台\n    建師鑑（97038）字第129404號鑑定報告1份，在卷可參，更\n    明被上訴人主張如附表所示被上訴人所修繕之工程，除壹、\n    電氣設備工程中之一『項次一用途說明為 9層至15層各戶電\n    錶集中箱體』、『項次二之用途說明為提供電錶用電的開關\n    受電箱』、『項次四之用途說明為提供公設梯間及梯廳、茶\n    水間用電分盤』等三項外，其他工程修繕均係對兩造在系爭\n    大樓「生活利用上不可或缺」設備為修繕，有該公會97年 6\n    月18日台建師鑑（97038）字第 1294-4號鑑定報告書一份為\n    佐，並經參與該會鑑定過程之建築師庚○○○○○在本院結\n    證屬實（見本院卷(一)第9-11頁），上訴人否認被上訴人上開\n    修繕工程係針對兩造共有之公有區域設備為修繕等語，自無\n    可採。上訴人另在本院審理期間自行囑託訴外人甲○○及趙\n    天佐建築師鑑定，並提甲○○及趙天佐建築師之鑑定報告書\n    一冊（外放）為佐，並抗辯臺灣省建築師公會之上開鑑定報\n    告，與其所提出之之鑑定報告結論並不相同，臺灣省建築師\n    公會就甲○○及趙天佐建築師之鑑定報告書第 5頁第5、6項\n    即泡沫設備及排煙設備之鑑定意見亦前後不一，臺灣省建築\n    師公會之鑑定報告顯不可採等語。惟查，臺灣省建築師公會\n    之上開鑑定報告並無錯誤，至於臺灣省建築師公會98年10月\n    9日台建師鑑（97038）字第3451號函說明三記載：「上訴人\n    所送黃耀呈建築師事務所鑑定之鑑定報告書第5頁第5、6 項\n    可以接受為私有部分」等語（見本院卷(一)第 152頁），及嗣\n    後該會於98年12月11日函分別就泡沫設備及排煙設備所為之\n    說明：「一第五項泡沫設備可以接受為『私有部分』說明如\n    下：泡沬設備係裝置於停車空間之滅火設備，若該停車空間\n    產權全部屬於私人則應歸類為『私有部分』，若該停車空間\n    屬共同持有部分則應歸類為『公有部分』、二第六類排煙設\n    備可以接受為『私有部分』說明如下：依建築技術規則排煙\n    分區設於各戶居室排煙及特別安全梯或緊急升降機間，若排\n    煙設備屬居室排煙則為『私有部分』，若排煙設備屬特別安\n    全梯或緊急升降機間則為『公有部分』，依整修工程項目表\n    第六項排煙設備a、b、c 所述施工位置及用途說明並未存在\n    私有部分，故此部分應認定為『公有部分』」等語（見本院\n    卷(一)第 232頁），並非要變更臺灣省建築師公會上開鑑定之\n    結論一節，業經鑑定證人即參與上開鑑定報告之建築師羅榮\n    源在本院結證屬實，並證稱：「一兩份函的意思都不是要變\n    更原來鑑定之結論，而是說明有可能是私有，但因為本案的\n    建物是共有的所以第一份函的所謂第五頁第五、六項並非指\n    該部分是私有部分，理由是第五項地下室停車場是共同持分\n    所以該部分的泡沫設備應屬於公共設施，另外一項是第六項\n    排煙設備經再確認還是認為是共同部分，依據原來建築師的\n    施工圖該部分仍屬共有部分。二九十八年十二月十一日函部\n    分確認第五、六項確為共有部分，該函之意思是泡沫設備及\n    排煙設備可能產生私有部分之情形，本件建物依照建築師施\n    工圖上開二部分確實屬於公共設施。」、「本人不能對別人\n    的鑑定報告書發表意見，所以前開二份函文內容所指的是建\n    築師公會所做鑑定報告之項目。」、「【法官提示本院卷第\n    一五二頁，九十八年十月九日覆函說明三、所謂的該鑑定報\n    告書所述第五、六項可以接受為『私有部分』，其餘確認為\n    大樓共用部分，是指建築師公會的鑑定報告書或是上訴人在\n    本院提出的鑑定報告書？（提示並告以要旨）】鑑定證人庚\n    ○○○○○答：「上開函文的第五、六項是指建築師公會鑑\n    定報告書內之泡沫設備及排煙設備，如果該建物是屬於私有\n    的則其泡沫設備及排煙設備即屬於私有，但是本件是屬於共\n    同持有，所以仍屬於共同設備。我的函會這樣寫是指可能產\n    生的情形而已，並非指本件就是私有部分，所以結論就如鑑\n    定報告書所述。」等語（見本院卷(二)第 9頁反面、第10、11\n    頁），是自難據上開臺灣省建築師公會之二份函為該公會有\n    認同甲○○及趙天佐建築師之鑑定結論或有變更其在原審所\n    為鑑定結論之依據，況上開甲○○及趙天佐建築師係受上訴\n    人單方面委任，並非由兩造合意或法院指定之鑑定人，鑑定\n    時亦未會同法院及兩造到場表示意見，自不足採信。是上訴\n    人抗辯臺灣省建築師公會之鑑定報告與甲○○及趙天佐之上\n    開鑑定報告結論不同，及臺灣省建築師公會上開二份函之內\n    容前後矛盾，應以甲○○及趙天佐之鑑定報告為可採等語，\n    顯不可採等語，自無理由。\n(二)、又被上訴人主張就前述系爭大樓公用「公共管道間」之「消\n    防灑水系統、消防給水系統、污水系統、排水系統及透氣管\n    線」與系爭大樓公共逃生梯各樓層中之「消防栓廂設備、廣\n    播設備及緊急逃生照明設備、排煙管道設備、電信弱電箱」\n    部分之修繕，為保存系爭大樓即避免損害而為修繕，其修繕\n    屬必要之保存行為，雖為上訴人否認，然查：\n  1.系爭大樓於80年 2月26日取得使用執照，上訴人於87年間曾\n    委託訴外人長譽水電工程有限公司辦理水電消防等復原工程\n    ，依其工程估價單所載工程款合計為 23,778,668元（含稅）\n    之事實，有上訴人提出系爭大樓使用執照影本 1份附在原審\n    卷（見原審卷(一)第68-70頁）、合作金庫工程合約書影本1份\n    在本院卷（見本院卷(一)第 60-99頁）為佐，足認系爭大樓雖\n    於80年 2月26日取得使用執照，惟不足以證明已符合堪用狀\n    態，否則上訴人於87年間即無支出大筆工程款進行復原工程\n    之必要，是上訴人抗辯系爭大樓於80年 2月26日取得使用執\n    照，並無不能使用情形，無進行修繕必要等語，自無足取。\n    再本院審酌系爭大樓取得使用執照迄上訴人為上開復原工程\n    之87年間相距約 8年，至被上訴人進行本件修繕工程之96年\n    間亦已相距約16年時間，而上訴人為復原工程迄被上訴人為\n    本件修繕工程時則相距約 9年時間，上訴人於87年間辦理復\n    原工程之工程費已多達 2,300餘萬元之多，足認系爭大樓原\n    來之水電消防設備於87年間係處在若不進行復原工程不足以\n    堪用之狀態，否則上訴人亦無進行水電消防等復原工程之必\n    要，再上訴人自進行上開修復工程迄今僅使用系爭大樓之一\n    、二樓，其餘三至八樓部分並未使用，且因三至八樓並未使\n    用，故每年之消防安檢僅檢查一、二樓部分，並未就三至八\n    樓部分做檢查等情，業經上訴人在本院自陳在卷（見本院卷\n    (一)第 119頁反面），是縱認上訴人曾於87年間為水電消防之\n    復原工程，惟因上訴人長期僅使用系爭大樓一、二樓部分，\n    其餘三至八樓部分則未使用且未進行消防安檢，亦僅足認其\n    一、二樓部分係得使用狀態，於上訴人未舉證證明系爭大樓\n    全棟之共用設備部分於87年間經其進行復原工程迄96年間止\n    均處在堪用狀態，自難認上訴人抗辯其曾於87年為上開復原\n    工程以後，系爭大樓全部之公共設備均為堪用狀態為可採，\n    況系爭大樓於96年12月間仍有多項設施不合格，致被上訴人\n    不能申請變更使用，迄本件修繕後始通過檢驗，由台中市政\n    於97年1月16日發給合格證明字號97府都建室字第0022-00號\n    建築物室內裝修合格證明書之事實，亦有被上訴人所提出之\n    台中市政府合格證明字號97府都建室字第 0022-00號建築物\n    室內裝修合格證明、台中市政府97年1月17日府都管字第097\n    0015950號函影本各1份在原審卷為證（見原審卷(一)第220-22\n    1 頁），是被上訴人主張系爭大樓有修繕必要，其修繕部分\n    均為公共管道間之水、電力、消防及排煙幹管等設備，該等\n    設備年久失修損壞，嚴重影響大樓之消防、照明及逃生等公\n    共安全問題，且系爭大樓之相關電器設備、給排水設備及電\n    信弱電工程亦嚴重損壞或尚未裝修，導致系爭大樓無法正常\n    ，若未修繕，則系爭大樓除上訴人已使用之1樓及2樓部分外\n    ，餘皆無法正常使用，且因未完成修繕，消防安檢亦無法通\n    過，致被上訴人無法申請變更執照，故前開設施確有修繕之\n    必要等語，自足採信，且應認被上訴人所為之修繕，顯屬防\n    止共有物之滅失、毀損或權利之喪失、限制等為目的，以維\n    持大樓基本堪用狀態，發揮其應有效用之行為，是本件修繕\n    自屬民法第820第2項規定之「其他保存行為」。\n  2.再查，系爭大樓之共有人僅有兩造共為三人，共有人人數不\n    多，自無召開區分所有權人會議籌組公寓大廈管理委員會之\n    必要（系爭大樓於本案涉訟後之97年 1月28日，已報備設置\n    管理負責人），系爭大樓之公用設備之修繕、管理，依民法\n    第 820條規定為之即可，此由系爭大樓之外牆係由兩造以協\n    議方式修繕完畢，且按各共有人所有權應有部分比例負擔修\n    繕費用，益證就系爭大樓共用之部分以由兩造共負管理之責\n    並依應有部分比例各自分擔修繕費用之方式為之，並無困難\n    。再按民法第820條第2項所稱「保存行為」係指以防止共有\n    物之滅失、毀損或權利之喪失、限制等為目的，以維持現狀\n    之行為，本件系爭大樓公用「公共管道間」之「消防灑水系\n    統、消防給水系統、污水系統、排水系統及透氣管線」與系\n    爭大樓公共逃生梯各樓層中之「消防栓廂設備、廣播設備及\n    緊急逃生照明設備、排煙管道設備、電信弱電箱」等兩造共\n    用部分之設備，本即為防止共有物之滅失、毀損之設施，該\n    等設備既有毀損，並有礙系爭大樓之安全維護及使用之完整\n    性，自應由兩造共負修繕之責任，惟本件被上訴人請求上訴\n    人共同協議修繕，業經上訴人拒絕，有96年8月8日台中漢口\n    郵局第804號存證信函影本1份在原審卷為佐（見原審卷(一)第\n    46、47頁），被上訴人因而自行發包修繕以保存系爭大樓之\n    使用完整性及維護整棟大樓之安全，其為保存系爭大樓所為\n    之修繕，實屬必要。上訴人抗辯本件修繕未經其同意及系爭\n    修繕非屬必要之保存行為，並進而拒絕負擔修繕費用，自屬\n    無據。\n(三)、再查，被上訴人主張系爭大樓如附表所示之修繕工程業已全\n    部完工，被上訴人亦已支付全部工程款之事實，業據被上訴\n    人所提出匯款紀錄、（公有部分）整修工程詳細價目表影本\n    被上訴人與威祐公司之合約書、良岳營造有限公司書節本、\n    開立予被上訴人之統一發票、被上訴人之匯款紀錄、被上訴\n    人於98年 3月12日與威祐公司簽訂之「協議書」、台中銀行\n    中台中分行匯款單、第一次公有及私有結算表、96年 9月13\n    日合作金庫匯款單、第二次公有及私有結算表、96年10月11\n    日合作金庫匯款單、第三次公有及私有結算表、96年11月 9\n    日合作金庫匯款單、第四次公有及私有結算表、97年 1月10\n    日合作金庫匯款單、錯誤之公有結算表副本、竣工圖表、竣\n    工查驗紀錄、己○○建築師事務所96年10月30日安建字第96\n    076號函、己○○建築師事務所96年11月12日安建字第96085\n    號函、威祐公司之匯款單等件各 1份在原審卷為證（見原審\n    卷(二)第146-147頁、第131-144頁、第149-152頁、第153頁、\n    第241-270 頁），堪信為真。再查，被上訴人主張本件共用\n    設備修繕工程（即附表所示全部工程）之工程款合計為12,6\n    24,418元（含5%之稅金，稅前金額為12,023,255元）一節，\n    有己○○建築師事務所98年3月5日安建字第 98022號確認函\n    、結算表各1份在原審卷可稽（見原審卷(二)第117-125頁），\n    並經己○○建築師在本院結證屬實（見本院卷(一)第 133頁反\n    面、第 134頁），堪信為真。另查，附表所示之工程經兩造\n    在原審合意指定台灣省建築公會鑑定該修繕工程何部分為公\n    用，何部分為私用結果，經臺灣建築額公會鑑定結果，認如\n    附表所示被上訴人所修繕之工程中，除「壹、電氣設備工程\n    中之一『項次一用途說明為 9層至15層各戶電錶集中箱體』\n    、『項次二之用途說明為提供電錶用電的開關受電箱』、『\n    項次四之用途說明為提供公設梯間及梯廳、茶水間用電分盤\n    』」等三項外，其他工程修繕均屬共用設備之事實，已如前\n    述，是本件依被上訴人主張以稅前金額即12,023,255元扣除\n    上開經鑑定非屬共用設備部分之工程款（見原審卷(二)第 126\n    頁反面、第127頁），即扣除9層至15層各戶電錶集中箱體部\n    分100,500元、提供電錶用電的開關受電箱部分268,800元、\n    提供公設梯間及梯廳、茶水間用電分盤部分 142,440元，其\n    稅後餘額為12,087,090元（計算式為：12,023,255元－100,\n    500元－268,800元－142,440元＝11,511,515元。11,511,51\n    5＋〔11,511,5155%〕＝12,087,090元 ）應可認定。另本\n    件被上訴人發包整修時，就公用及私人使用之修繕費，已分\n    別列冊結算有前述（公有部分）整修工程詳細價目表、四次\n    公有、私有結算表在卷可稽，且經己○○建築師確認結算，\n    亦有前開己○○建築師事務所98年3月5日安建字第 98022號\n    確認函文1份、結算表1份在原審卷為佐，上訴人以被上訴人\n    進行之本件修繕工程有公用、私用設備不分情形，拒絕償還\n    被上訴人代墊之修繕費，並無理由。\n(四)、按「共有物之管理費，及其他擔負，除契約另有訂定外，應\n    由各共有人，按其應有部分分擔之。共有人中之一人，就共\n    有物之擔負為支付，而逾其所應分擔之部分者，對於其他共\n    有人，得按其各應分擔之部分，請求償還」，民法第 822條\n    定有明文。本件兩造共有之系爭大樓附屬之公用設備，因有\n    修繕之必要，且經被上訴人完成修繕，其應支付之修繕費用\n    為12,087,090元，依前開法文規定，自應由兩造就系爭負用\n    按應有部分之比例分攤。準此，被上訴人主張上訴人應依其\n    所有權應有部分之比例即58.34%分擔7,051,608元 （計算式\n    ：00000000元58.34%＝0000000元。 元以下四捨五入），\n    核屬有據。再上開修繕費用12,087,090元已由被上訴人支付\n    亦如前述，是被上訴人請求上訴人返還被上訴人應分擔額7,\n    051,608元，為有理由，應予准許。\n五、綜上所述，被上訴人主張上訴人應分擔系爭大樓之公用設備\n    修繕費7,051,608元 ，已由被上訴人代為支付，上訴人迄未\n    返還被上訴人，均如前述。從而，被上訴人依修繕費用償還\n    請求權之法律關係，請求上訴人給付7,051,608元 ，及自起\n    訴狀繕本送達（見原審卷(一)第62頁）之翌日即96年10月17日\n    起至清償日止按年息百分之 5計算之利息，為有理由，應予\n    准許。至於逾上開金額之請求（即利息請求逾自96年10月17\n    日起算部分），則無理由，不應准許。原審就上開應准許部\n    分，為上訴人敗訴判決，並依兩造陳明，分別酌定相當供擔\n    保金額，為准免假執行之宣告，核無不合。上訴論旨指摘原\n    判決不當，求予廢棄改判，為無理由，應予駁回。至於上開\n    不應准許部分，原審未查，遽為上訴人敗訴判決，自有未洽\n    ，應由本院予以廢棄改判如主文所示。\n六、本件事證已臻明確，兩造其餘主張攻擊防禦方法及舉據，經\n    審核後認不影響本件判決結果，爰不予一一論列。另上訴人\n    請求囑託中華民國電機技師公會全國聯合會派員鑑定本件修\n    繕之電氣、消防是否為共用部分，施作之數量及單價是否屬\n    實，費用為若干等情，因該部分業經兩造在原審合意囑託臺\n    灣省建築師公會為鑑定，該鑑定報告結論並無明顯重大瑕疵\n    或不當之處，並經鑑定證人羅榮源在本院證稱明確，上訴人\n    聲請再囑託訴外人中華民國電機技師公會全國聯合會重為鑑\n    定，自無必要。另上訴人聲請本院向台灣電力股份有限公司\n    台中區營業處調取用電設計審查及竣工檢驗之圖說及文件、\n    向台灣自來水股份有限公司第四區管理處調取自來水設計審\n    、竣工檢驗之圖說及文件、向台中市消防局調取消防案全設\n    備設計審查、竣工檢驗之圖說及文件，以查明被上訴人主張\n    之共用部分項目及實際施作數量部分，因該部分業經監造之\n    己○○建築師事務所提出前開函文及相關文件資料為佐，並\n    經己○○建築師在本院結證在卷，核亦無不明確之處，上訴\n    人聲請再調閱上開文件重為調查，同無必要，併予敘明。\n據上論結，本件上訴為一部有理由，一部無理由，依民事訴訟法\n第449條第1項、第450條、第79條，判決如主文。"
  },
  "characters": {
    "judges": [
      "袁再興",
      "盧江陽",
      "陳賢慧"
    ],
    "prosecutors": [

    ],
    "lawyers": [
      "吳光陸",
      "周仲鼎",
      "上訴時應提出委任"
    ],
    "clerks": [
      "吳麗琴"
    ],
    "plaintiffs": [

    ],
    "defendants": [

    ],
    "prosecutor_office": [

    ],
    "creditors": [

    ],
    "debtors": [

    ],
    "judicial_associate_officer": [

    ]
  },
  "adjudged_at": "2010-05-12",
  "created_at": "2016-01-05 12:00:27",
  "updated_at": "2016-01-05 12:00:27"
}