{
  "identify": "TCH-98-上易-401-20100105-1",
  "court": {
    "name": "臺灣高等法院",
    "code": "TCH"
  },
  "division": {
    "name": "民事",
    "code": "V"
  },
  "year": 98,
  "word": "上易",
  "number": "401",
  "jcheck": "1",
  "reason": "損害賠償",
  "content": "臺灣高等法院臺中分院民事判決         98年度上易字第401號\n上  訴  人  甲○○\n訴訟代理人  戊○○\n上  訴  人  庚○○（民國○○○年○月○日生）\n兼  法  定\n代  理  人  己○○\n            辛○○\n共      同\n訴訟代理人  柯開運律師\n被 上訴 人  丁○○（民國○○○年○月○○日生）\n                        3樓\n法定代理人  丙○○\n            乙○○\n上列當事人間請求損害賠償事件，上訴人對於民國九十八年八月\n六日臺灣彰化地方法院第一審判決（九十七年度訴字第六六四號\n），提起上訴，本院於九十八年十二月二十二日言詞辯論終結，\n判決如下：\n    主  文\n原判決關於命上訴人連帶給付超過新臺幣三十八萬一千六百零四\n元本息及該部分假執行之宣告暨訴訟費用之裁判均廢棄（確定部\n分除外）。\n上開廢棄部分，被上訴人在第一審之訴及假執行之聲請均駁回。\n其餘上訴駁回。\n第一、二審訴訟費用（確定部分除外），由上訴人連帶負擔百分\n之七十四，餘由被上訴人負擔。\n    事實及理由\n一、本件被上訴人主張：\n    (一)上訴人甲○○係彰化縣和美鎮○○路一六三號群勝美語短\n      期補習班之負責人，本應注意並防止補習班四週環境對就\n      讀兒童可能引起之危險，應有符合標準之安全設備，詎疏\n      於注意設置符合標準之安全設備，亦未指定老師在場監督\n      屬於幼齡之在班補習學生之作息，適於民國九十六年十月\n      十二日下午一時許，伊在補習班二樓玩跑步競賽遊戲，遭\n      上訴人庚○○因過失未注意安全，出其不意自後推擠，致\n      伊受有右手刺傷合併二條肌腱斷裂、兩指神經斷裂，一條\n      動脈斷裂合併十一公分長疤痕醜形傷害。\n    (二)庚○○係限制行為能力人，對侵權行為與其法定代理人即\n      上訴人己○○、辛○○應負共同責任，與甲○○對被上訴\n      人之侵權受損有共同之原因，茲依侵權行為損害賠償法則\n      ，就被上訴人得請求之項目及金額，分述如下：\n      醫療費用：新臺幣（下同）一萬九千五百零五元。\n      整形費用：伊受傷後，留有十一公分之疤痕醜形，估計\n        整形費用需四萬元。\n      增加生活上所需費用：\n        (1)赴醫治療之交通費：三萬一千五百元。\n        (2)伊母乙○○陪同就診需請假所損失之工資，以半日工\n          資五百元，醫療及復健約五十六次計，共二萬八千元\n          。\n        (3)相當於看護之費用：伊右手受傷，自受傷十五日內即\n          九十六年十月十二日起至同年月二十七日，日常生活\n          無法自理，乙○○負責照顧看護，以一天相當於二千\n          元看護費，共計三萬元。\n        (4)以上合計八萬九千五百元。\n      精神慰撫金：伊原有天真快樂之童年，因上開傷害經開\n        刀縫合傷口後，右手拇指及食指仍感麻木無力，需作經\n        常性之復健治療，且留下十一公分長之疤痕醜形，身心\n        受有極大之痛苦，請求精神慰撫金四十萬元。\n    (三)事故發生後，己○○、辛○○已給付慰問金一萬元，伊同\n      意扣除等情。爰求為命上訴人應連帶給付伊五十一萬九千\n      二百元，及加計甲○○自九十八年十一月十九日、其餘上\n      訴人均自同年月二十一日起算法定遲延利息，並願供擔保\n      請准為假執行宣告之判決（未繫屬本院者，不予贅論）。\n二、上訴人則以：\n    (一)被上訴人提出醫療費用單據，總金額為一萬九千一百七十\n      一元，與其主張一萬九千五百零五元不符，其中九十七年\n      八月二十九日及同年十月一日就醫，有三筆金額均各為五\n      十元，應有重複。至整形費用被上訴人尚未支出，不能為\n      請求。又被上訴人提出之交通費用單據，尚無法證明確有\n      支出交通費用三萬一千五百元，而被上訴人並未住院，實\n      無須看護費用，且乙○○並未證明其請假之工資損失。另\n      被上訴人請求精神慰撫金四十萬元，亦屬過高。\n    (二)己○○及辛○○業給付被上訴人慰問金一萬元，應就被上\n      訴人請求之金額中扣除。又被上訴人在不得嬉戲之教室任\n      意嬉戲跑步，應有過失，且其過失責任較重，依過失相抵\n      原則，應減輕伊百分之八十之責任等語，資為抗辯。\n三、原審判命上訴人應連帶給付被上訴人五十一萬九千二百元本\n    息，上訴人聲明不服，兩造於本院各聲明如下：\n    (一)上訴人方面：\n      原判決廢棄。\n      上開廢棄部分，被上訴人在第一審之訴及假執行之聲請\n        均駁回。\n      第一、二審訴訟費用由被上訴人負擔。\n    (二)被上訴人方面：\n      上訴駁回。\n      訴訟費用由上訴人負擔。\n四、兩造不爭執之事實：\n    (一)甲○○係彰化縣和美鎮○○路一六三號群勝美語短期補習\n      班之負責人，九十六年十月十二日下午一時許，被上訴人\n      在補習班二樓玩跑步競賽遊戲，遭庚○○自後推擠，致被\n      上訴人受有右手刺傷合併二條肌腱斷裂、兩指神經斷裂，\n      一條動脈斷裂合併十一公分長疤痕醜形傷害。\n    (二)庚○○係八十六年九月一日出生，己○○及辛○○為其法\n      定代理人。\n    (三)甲○○因本件業務過失傷害罪，經臺灣彰化地方法院以九\n      十七年度彰簡字第八二八號刑事簡易判決，判處拘役二十\n      日確定在案。\n    (四)事故發生後，己○○、辛○○已給付被上訴人慰問金一萬\n      元，被上訴人同意自請求金額中扣除。\n五、得心證之理由：\n    (一)按因故意或過失，不法侵害他人之權利者，負損害賠償責\n      任。數人共同不法侵害他人之權利者，連帶負損害賠償責\n      任。無行為能力人或限制行為能力人，不法侵害他人之權\n      利者，以行為時有識別能力為限，與其法定代理人連帶負\n      損害賠償責任。不法侵害他人之身體或健康者，對於被害\n      人因此喪失或減少勞動能力或增加生活上之需要時，應負\n      損害賠償責任。不法侵害他人之身體、健康、名譽、自由\n      、信用、隱私、貞操，或不法侵害其他人格法益而情節重\n      大者，被害人雖非財產上之損害，亦得請求賠償相當之金\n      額。民法第一百八十四條第一項前段、第一百八十五條第\n      一項前段、第一百八十七條第一項、第一百九十三條第一\n      項及第一百九十五條第一項分別定有明文。經查：\n      甲○○為上開補習班之負責人，本應注意並防止補習班\n        四週環境對就讀兒童可能引起之危險，應有符合標準之\n        安全設備，詎其疏於注意，未設置符合標準之安全設備\n        ，更未指定老師在場監督屬於幼齡之在班補習學生之作\n        息，則於前揭時、地，被上訴人玩跑步競賽遊戲，遭庚\n        ○○出其不意自後推擠，致被上訴人受有上述傷害，顯\n        然甲○○及庚○○之行為，係被上訴人所受傷害之共同\n        原因，且被上訴人所受之傷害，與甲○○及庚○○之侵\n        權行為間，具有相當因果關係，堪以認定。\n      庚○○係限制行為能力人，其上揭侵權行為致被上訴人\n        受有傷害，與其法定代理人即己○○、辛○○應連帶負\n        損害賠償責任。則被上訴人因甲○○及庚○○之共同侵\n        權行為，致身體受有損害，請求上訴人應連帶賠償醫療\n        費用、增加生活上所需費用及精神慰撫金，於法即無不\n        合。另甲○○與己○○、辛○○各自對被上訴人負全部\n        之損害賠償責任，為不真正連帶債務，與民法第二百七\n        十二條第一項所定連帶債務人就同一債務對於債權人各\n        負全部給付責任之法理，並無二致。茲就被上訴人所得\n      請求損害賠償金額，分述如下：\n        (1)醫療費用：被上訴人主張支出醫療費用一萬九千五百\n          零五元，有相關收據在卷可稽，均屬治療上之必要費\n          用，則被上訴人請求上訴人賠償醫療費用一萬九千五\n          百零五元，應予准許。至上訴人以被上訴人提出之單\n          據金額僅一萬九千一百七十一元，似有誤會。另上訴\n          人以被上訴人九十七年八月二十九日及同年十月一日\n          就醫，有三筆金額均各為五十元，應有重複云云，然\n          據被上訴人陳稱，此乃因看一次門診，即可復健六次\n          ，診所作業係以掛號日期為準，並未重複等語在卷，\n          尚屬可採，自無加以函查必要，附此敘明。\n        (2)整形費用：被上訴人受傷後留下十一公分之疤痕，對\n          成長中之少年自我人格發展，及追求身心之完美，自\n          有重大影響，本院審酌被上訴人右手腕處三至四公分\n          呈肥厚疤痕，如進行Ｗ一整形手術可能可獲些許改善\n          ，有臺中榮民總醫院鑑定書存卷可考，是被上訴人請\n          求未來整形費用，核屬必要。本院參酌臺中榮民總醫\n          院鑑定估計整形費用約須一萬元至五萬元間，因認被\n          上訴人請求整形費用四萬元，尚屬適當，應予准許。\n        (3)增加生活上所需費用：\n          (甲)相當於看護之費用：被上訴人右手受傷，自九十六\n            年十月十二日起至同年月二十七日，日常生活無法\n            自理，乙○○負責照顧看護，以一天相當於二千元\n            看護費，尚屬合理。故被上訴人請求相當於看護之\n            費用三萬元，於法有據，應予准許。\n          (乙)赴醫治療之交通費：被上訴人請求赴醫治療之交通\n            費三萬一千五百元，固據提出二張收據為證，然該\n            收據並無日期，復未記載支出車資之人及用途，尚\n            難憑為被上訴人有支出交通費之證明。此外，被上\n            訴人並未提出其他證據，資以證明其確有支出交通\n            費之事實，則被上訴人請求此部分之交通費，尚屬\n            無據，不應准許。\n          (丙)乙○○陪同被上訴人就診需請假所損失之工資二萬\n            八千元，與系爭事故無涉，且非被上訴人因系爭事\n            故所受之損害，則其此部分之請求，尚屬無稽，不\n            應准許。\n          (丁)是被上訴人得請求增加生活上所需費用，即為三萬\n            元。至超過三萬元部分，即屬無據，不應准許。\n        (4)精神慰撫金部分：被上訴人於本件車禍發生時，年僅\n          十歲，因本件事故右手拇指及食指仍感麻木無力，需\n          作經常性之復健治療，且留下十一公分長之疤痕醜形\n          ，依臺中榮民總醫院鑑定意見，進行整形手術，整體\n          疤痕無法消失，顯然被上訴人身心受有極大之痛苦，\n          非筆墨所能形容。而甲○○身為補習班之負責人，庚\n          ○○則屬實質之侵權行為人，渠等於事故發生後，迄\n          未與被上訴人達成和解，爰併審酌其他一切情狀，認\n          被上訴人請求精神慰撫金四十萬元，尚屬適當，應予\n          准許。上訴人以被上訴人請求精神慰撫金尚屬過高置\n          辯，殊無足採。\n        (5)綜上，被上訴人因本件事故而請求上訴人連帶賠償其\n          已支出醫療費用一萬九千五百零五元、將來須支出醫\n          療相關費用即整形費用四萬元、增加生活上所需費用\n          三萬元及精神慰撫金四十萬元，合計四十八萬九千五\n          百零五元，洵屬有據，應予准許。\n    (二)又損害之發生或擴大，被害人與有過失者，法院得減輕賠\n      償金額或免除之。前開規定，於被害人之代理人或使用與\n      有過失者，準用之。民法第二百十七條第一項、第三項亦\n      著有明文。經查：\n      被上訴人為限制行為能力人，對於在教室內嬉笑玩鬧，\n        已有能力辨識四週環境安危，懂得保護自己之安全，乃\n        被上訴人疏未注意嬉鬧時之安全，亦應負部分過失責任\n        ，始得事理之平。本院認斟酌甲○○身為補習班負責人\n        ，未能提供安全設施，復疏於注意指定教師在場監督，\n        與庚○○出其不意自後推擠被上訴人，應連帶負較重之\n        過失責任等情，因認甲○○及庚○○應連帶負擔百分之\n        八十過失責任，被上訴人應負百分之二十之過失責任。\n        準此計算，上訴人應連帶賠償被上訴人之數額為三十九\n        萬一千六百零四元。\n      己○○、辛○○於事故發生後，已給付被上訴人一萬元\n        ，被上訴人並同意自賠償金扣除，則被上訴人得請求上\n        訴人連帶賠償損害之金額為三十八萬一千六百零四元。\n        逾此範圍之請求，為無理由，自難准許。\n    (三)綜上所述，被上訴人依侵權行為之法律關係，請求上訴人\n      連帶給付三十八萬一千六百零四元，及甲○○自九十八年\n      十一月十九日、其餘上訴人均自同年月二十一日起至清償\n      日止，按年息百分之五計算法定遲延利息部分，為有理由\n      ，應予准許。此部分被上訴人聲請供擔保為假執行之宣告\n      ，核無不合，應酌定相當之擔保金額併予宣告。至逾越前\n      開應准許之部分，被上訴人之請求為無理由，應予駁回。\n      原審就被上訴人之請求，超過前開應准許部分，為被上訴\n      人勝訴之判決，尚有未合。上訴論旨指摘原判決該部分不\n      當，聲明廢棄，為有理由，爰由本院將原判決該部分予以\n      廢棄，改判如主文第二項所示。至原判決關於命上訴人應\n      連帶給付被上訴人三十八萬一千六百零四元，及甲○○自\n      九十八年十一月十九日、其餘上訴人均自同年月二十一日\n      起至清償日止，按年息百分之五計算法定遲延利息，暨依\n      被上訴人之聲請而為供擔保宣告假執行部分，經核於法洵\n      無違誤。上訴論旨指摘原判決該部分不當，聲明廢棄，為\n      無理由，應予駁回。\n六、本件事證已臻明確，兩造其餘攻擊、防禦方法，與判決結果\n    不生影響，爰不一一論述。\n七、據上論結，本件上訴為一部有理由、一部無理由。依民事訴\n    訟法第四百五十條、第四百四十九條第一項、第七十八條、\n    第七十九條、第八十五條第二項，判決如主文。\n中    華    民    國    99    年    1     月    5     日\n                民事第四庭    審判長法  官  陳蘇宗\n                                    法  官  張浴美\n                                    法  官  李寶堂\n以上正本係照原本作成。\n不得上訴。\n                                    書記官  林振甫\n中    華    民    國    99    年    1     月    5     日\n                                                      Ｖ\n",
  "structure": {
    "main": "原判決關於命上訴人連帶給付超過新臺幣三十八萬一千六百零四\n元本息及該部分假執行之宣告暨訴訟費用之裁判均廢棄（確定部\n分除外）。\n上開廢棄部分，被上訴人在第一審之訴及假執行之聲請均駁回。\n其餘上訴駁回。\n第一、二審訴訟費用（確定部分除外），由上訴人連帶負擔百分\n之七十四，餘由被上訴人負擔。",
    "fact": "一、本件被上訴人主張：\n    (一)上訴人甲○○係彰化縣和美鎮○○路一六三號群勝美語短\n      期補習班之負責人，本應注意並防止補習班四週環境對就\n      讀兒童可能引起之危險，應有符合標準之安全設備，詎疏\n      於注意設置符合標準之安全設備，亦未指定老師在場監督\n      屬於幼齡之在班補習學生之作息，適於民國九十六年十月\n      十二日下午一時許，伊在補習班二樓玩跑步競賽遊戲，遭\n      上訴人庚○○因過失未注意安全，出其不意自後推擠，致\n      伊受有右手刺傷合併二條肌腱斷裂、兩指神經斷裂，一條\n      動脈斷裂合併十一公分長疤痕醜形傷害。\n    (二)庚○○係限制行為能力人，對侵權行為與其法定代理人即\n      上訴人己○○、辛○○應負共同責任，與甲○○對被上訴\n      人之侵權受損有共同之原因，茲依侵權行為損害賠償法則\n      ，就被上訴人得請求之項目及金額，分述如下：\n      醫療費用：新臺幣（下同）一萬九千五百零五元。\n      整形費用：伊受傷後，留有十一公分之疤痕醜形，估計\n        整形費用需四萬元。\n      增加生活上所需費用：\n        (1)赴醫治療之交通費：三萬一千五百元。\n        (2)伊母乙○○陪同就診需請假所損失之工資，以半日工\n          資五百元，醫療及復健約五十六次計，共二萬八千元\n          。\n        (3)相當於看護之費用：伊右手受傷，自受傷十五日內即\n          九十六年十月十二日起至同年月二十七日，日常生活\n          無法自理，乙○○負責照顧看護，以一天相當於二千\n          元看護費，共計三萬元。\n        (4)以上合計八萬九千五百元。\n      精神慰撫金：伊原有天真快樂之童年，因上開傷害經開\n        刀縫合傷口後，右手拇指及食指仍感麻木無力，需作經\n        常性之復健治療，且留下十一公分長之疤痕醜形，身心\n        受有極大之痛苦，請求精神慰撫金四十萬元。\n    (三)事故發生後，己○○、辛○○已給付慰問金一萬元，伊同\n      意扣除等情。爰求為命上訴人應連帶給付伊五十一萬九千\n      二百元，及加計甲○○自九十八年十一月十九日、其餘上\n      訴人均自同年月二十一日起算法定遲延利息，並願供擔保\n      請准為假執行宣告之判決（未繫屬本院者，不予贅論）。\n二、上訴人則以：\n    (一)被上訴人提出醫療費用單據，總金額為一萬九千一百七十\n      一元，與其主張一萬九千五百零五元不符，其中九十七年\n      八月二十九日及同年十月一日就醫，有三筆金額均各為五\n      十元，應有重複。至整形費用被上訴人尚未支出，不能為\n      請求。又被上訴人提出之交通費用單據，尚無法證明確有\n      支出交通費用三萬一千五百元，而被上訴人並未住院，實\n      無須看護費用，且乙○○並未證明其請假之工資損失。另\n      被上訴人請求精神慰撫金四十萬元，亦屬過高。\n    (二)己○○及辛○○業給付被上訴人慰問金一萬元，應就被上\n      訴人請求之金額中扣除。又被上訴人在不得嬉戲之教室任\n      意嬉戲跑步，應有過失，且其過失責任較重，依過失相抵\n      原則，應減輕伊百分之八十之責任等語，資為抗辯。\n三、原審判命上訴人應連帶給付被上訴人五十一萬九千二百元本\n    息，上訴人聲明不服，兩造於本院各聲明如下：\n    (一)上訴人方面：\n      原判決廢棄。\n      上開廢棄部分，被上訴人在第一審之訴及假執行之聲請\n        均駁回。\n      第一、二審訴訟費用由被上訴人負擔。\n    (二)被上訴人方面：\n      上訴駁回。\n      訴訟費用由上訴人負擔。\n四、兩造不爭執之事實：\n    (一)甲○○係彰化縣和美鎮○○路一六三號群勝美語短期補習\n      班之負責人，九十六年十月十二日下午一時許，被上訴人\n      在補習班二樓玩跑步競賽遊戲，遭庚○○自後推擠，致被\n      上訴人受有右手刺傷合併二條肌腱斷裂、兩指神經斷裂，\n      一條動脈斷裂合併十一公分長疤痕醜形傷害。\n    (二)庚○○係八十六年九月一日出生，己○○及辛○○為其法\n      定代理人。\n    (三)甲○○因本件業務過失傷害罪，經臺灣彰化地方法院以九\n      十七年度彰簡字第八二八號刑事簡易判決，判處拘役二十\n      日確定在案。\n    (四)事故發生後，己○○、辛○○已給付被上訴人慰問金一萬\n      元，被上訴人同意自請求金額中扣除。\n五、得心證之理由：\n    (一)按因故意或過失，不法侵害他人之權利者，負損害賠償責\n      任。數人共同不法侵害他人之權利者，連帶負損害賠償責\n      任。無行為能力人或限制行為能力人，不法侵害他人之權\n      利者，以行為時有識別能力為限，與其法定代理人連帶負\n      損害賠償責任。不法侵害他人之身體或健康者，對於被害\n      人因此喪失或減少勞動能力或增加生活上之需要時，應負\n      損害賠償責任。不法侵害他人之身體、健康、名譽、自由\n      、信用、隱私、貞操，或不法侵害其他人格法益而情節重\n      大者，被害人雖非財產上之損害，亦得請求賠償相當之金\n      額。民法第一百八十四條第一項前段、第一百八十五條第\n      一項前段、第一百八十七條第一項、第一百九十三條第一\n      項及第一百九十五條第一項分別定有明文。經查：\n      甲○○為上開補習班之負責人，本應注意並防止補習班\n        四週環境對就讀兒童可能引起之危險，應有符合標準之\n        安全設備，詎其疏於注意，未設置符合標準之安全設備\n        ，更未指定老師在場監督屬於幼齡之在班補習學生之作\n        息，則於前揭時、地，被上訴人玩跑步競賽遊戲，遭庚\n        ○○出其不意自後推擠，致被上訴人受有上述傷害，顯\n        然甲○○及庚○○之行為，係被上訴人所受傷害之共同\n        原因，且被上訴人所受之傷害，與甲○○及庚○○之侵\n        權行為間，具有相當因果關係，堪以認定。\n      庚○○係限制行為能力人，其上揭侵權行為致被上訴人\n        受有傷害，與其法定代理人即己○○、辛○○應連帶負\n        損害賠償責任。則被上訴人因甲○○及庚○○之共同侵\n        權行為，致身體受有損害，請求上訴人應連帶賠償醫療\n        費用、增加生活上所需費用及精神慰撫金，於法即無不\n        合。另甲○○與己○○、辛○○各自對被上訴人負全部\n        之損害賠償責任，為不真正連帶債務，與民法第二百七\n        十二條第一項所定連帶債務人就同一債務對於債權人各\n        負全部給付責任之法理，並無二致。茲就被上訴人所得\n      請求損害賠償金額，分述如下：\n        (1)醫療費用：被上訴人主張支出醫療費用一萬九千五百\n          零五元，有相關收據在卷可稽，均屬治療上之必要費\n          用，則被上訴人請求上訴人賠償醫療費用一萬九千五\n          百零五元，應予准許。至上訴人以被上訴人提出之單\n          據金額僅一萬九千一百七十一元，似有誤會。另上訴\n          人以被上訴人九十七年八月二十九日及同年十月一日\n          就醫，有三筆金額均各為五十元，應有重複云云，然\n          據被上訴人陳稱，此乃因看一次門診，即可復健六次\n          ，診所作業係以掛號日期為準，並未重複等語在卷，\n          尚屬可採，自無加以函查必要，附此敘明。\n        (2)整形費用：被上訴人受傷後留下十一公分之疤痕，對\n          成長中之少年自我人格發展，及追求身心之完美，自\n          有重大影響，本院審酌被上訴人右手腕處三至四公分\n          呈肥厚疤痕，如進行Ｗ一整形手術可能可獲些許改善\n          ，有臺中榮民總醫院鑑定書存卷可考，是被上訴人請\n          求未來整形費用，核屬必要。本院參酌臺中榮民總醫\n          院鑑定估計整形費用約須一萬元至五萬元間，因認被\n          上訴人請求整形費用四萬元，尚屬適當，應予准許。\n        (3)增加生活上所需費用：\n          (甲)相當於看護之費用：被上訴人右手受傷，自九十六\n            年十月十二日起至同年月二十七日，日常生活無法\n            自理，乙○○負責照顧看護，以一天相當於二千元\n            看護費，尚屬合理。故被上訴人請求相當於看護之\n            費用三萬元，於法有據，應予准許。\n          (乙)赴醫治療之交通費：被上訴人請求赴醫治療之交通\n            費三萬一千五百元，固據提出二張收據為證，然該\n            收據並無日期，復未記載支出車資之人及用途，尚\n            難憑為被上訴人有支出交通費之證明。此外，被上\n            訴人並未提出其他證據，資以證明其確有支出交通\n            費之事實，則被上訴人請求此部分之交通費，尚屬\n            無據，不應准許。\n          (丙)乙○○陪同被上訴人就診需請假所損失之工資二萬\n            八千元，與系爭事故無涉，且非被上訴人因系爭事\n            故所受之損害，則其此部分之請求，尚屬無稽，不\n            應准許。\n          (丁)是被上訴人得請求增加生活上所需費用，即為三萬\n            元。至超過三萬元部分，即屬無據，不應准許。\n        (4)精神慰撫金部分：被上訴人於本件車禍發生時，年僅\n          十歲，因本件事故右手拇指及食指仍感麻木無力，需\n          作經常性之復健治療，且留下十一公分長之疤痕醜形\n          ，依臺中榮民總醫院鑑定意見，進行整形手術，整體\n          疤痕無法消失，顯然被上訴人身心受有極大之痛苦，\n          非筆墨所能形容。而甲○○身為補習班之負責人，庚\n          ○○則屬實質之侵權行為人，渠等於事故發生後，迄\n          未與被上訴人達成和解，爰併審酌其他一切情狀，認\n          被上訴人請求精神慰撫金四十萬元，尚屬適當，應予\n          准許。上訴人以被上訴人請求精神慰撫金尚屬過高置\n          辯，殊無足採。\n        (5)綜上，被上訴人因本件事故而請求上訴人連帶賠償其\n          已支出醫療費用一萬九千五百零五元、將來須支出醫\n          療相關費用即整形費用四萬元、增加生活上所需費用\n          三萬元及精神慰撫金四十萬元，合計四十八萬九千五\n          百零五元，洵屬有據，應予准許。\n    (二)又損害之發生或擴大，被害人與有過失者，法院得減輕賠\n      償金額或免除之。前開規定，於被害人之代理人或使用與\n      有過失者，準用之。民法第二百十七條第一項、第三項亦\n      著有明文。經查：\n      被上訴人為限制行為能力人，對於在教室內嬉笑玩鬧，\n        已有能力辨識四週環境安危，懂得保護自己之安全，乃\n        被上訴人疏未注意嬉鬧時之安全，亦應負部分過失責任\n        ，始得事理之平。本院認斟酌甲○○身為補習班負責人\n        ，未能提供安全設施，復疏於注意指定教師在場監督，\n        與庚○○出其不意自後推擠被上訴人，應連帶負較重之\n        過失責任等情，因認甲○○及庚○○應連帶負擔百分之\n        八十過失責任，被上訴人應負百分之二十之過失責任。\n        準此計算，上訴人應連帶賠償被上訴人之數額為三十九\n        萬一千六百零四元。\n      己○○、辛○○於事故發生後，已給付被上訴人一萬元\n        ，被上訴人並同意自賠償金扣除，則被上訴人得請求上\n        訴人連帶賠償損害之金額為三十八萬一千六百零四元。\n        逾此範圍之請求，為無理由，自難准許。\n    (三)綜上所述，被上訴人依侵權行為之法律關係，請求上訴人\n      連帶給付三十八萬一千六百零四元，及甲○○自九十八年\n      十一月十九日、其餘上訴人均自同年月二十一日起至清償\n      日止，按年息百分之五計算法定遲延利息部分，為有理由\n      ，應予准許。此部分被上訴人聲請供擔保為假執行之宣告\n      ，核無不合，應酌定相當之擔保金額併予宣告。至逾越前\n      開應准許之部分，被上訴人之請求為無理由，應予駁回。\n      原審就被上訴人之請求，超過前開應准許部分，為被上訴\n      人勝訴之判決，尚有未合。上訴論旨指摘原判決該部分不\n      當，聲明廢棄，為有理由，爰由本院將原判決該部分予以\n      廢棄，改判如主文第二項所示。至原判決關於命上訴人應\n      連帶給付被上訴人三十八萬一千六百零四元，及甲○○自\n      九十八年十一月十九日、其餘上訴人均自同年月二十一日\n      起至清償日止，按年息百分之五計算法定遲延利息，暨依\n      被上訴人之聲請而為供擔保宣告假執行部分，經核於法洵\n      無違誤。上訴論旨指摘原判決該部分不當，聲明廢棄，為\n      無理由，應予駁回。\n六、本件事證已臻明確，兩造其餘攻擊、防禦方法，與判決結果\n    不生影響，爰不一一論述。\n七、據上論結，本件上訴為一部有理由、一部無理由。依民事訴\n    訟法第四百五十條、第四百四十九條第一項、第七十八條、\n    第七十九條、第八十五條第二項，判決如主文。",
    "reason": "一、本件被上訴人主張：\n    (一)上訴人甲○○係彰化縣和美鎮○○路一六三號群勝美語短\n      期補習班之負責人，本應注意並防止補習班四週環境對就\n      讀兒童可能引起之危險，應有符合標準之安全設備，詎疏\n      於注意設置符合標準之安全設備，亦未指定老師在場監督\n      屬於幼齡之在班補習學生之作息，適於民國九十六年十月\n      十二日下午一時許，伊在補習班二樓玩跑步競賽遊戲，遭\n      上訴人庚○○因過失未注意安全，出其不意自後推擠，致\n      伊受有右手刺傷合併二條肌腱斷裂、兩指神經斷裂，一條\n      動脈斷裂合併十一公分長疤痕醜形傷害。\n    (二)庚○○係限制行為能力人，對侵權行為與其法定代理人即\n      上訴人己○○、辛○○應負共同責任，與甲○○對被上訴\n      人之侵權受損有共同之原因，茲依侵權行為損害賠償法則\n      ，就被上訴人得請求之項目及金額，分述如下：\n      醫療費用：新臺幣（下同）一萬九千五百零五元。\n      整形費用：伊受傷後，留有十一公分之疤痕醜形，估計\n        整形費用需四萬元。\n      增加生活上所需費用：\n        (1)赴醫治療之交通費：三萬一千五百元。\n        (2)伊母乙○○陪同就診需請假所損失之工資，以半日工\n          資五百元，醫療及復健約五十六次計，共二萬八千元\n          。\n        (3)相當於看護之費用：伊右手受傷，自受傷十五日內即\n          九十六年十月十二日起至同年月二十七日，日常生活\n          無法自理，乙○○負責照顧看護，以一天相當於二千\n          元看護費，共計三萬元。\n        (4)以上合計八萬九千五百元。\n      精神慰撫金：伊原有天真快樂之童年，因上開傷害經開\n        刀縫合傷口後，右手拇指及食指仍感麻木無力，需作經\n        常性之復健治療，且留下十一公分長之疤痕醜形，身心\n        受有極大之痛苦，請求精神慰撫金四十萬元。\n    (三)事故發生後，己○○、辛○○已給付慰問金一萬元，伊同\n      意扣除等情。爰求為命上訴人應連帶給付伊五十一萬九千\n      二百元，及加計甲○○自九十八年十一月十九日、其餘上\n      訴人均自同年月二十一日起算法定遲延利息，並願供擔保\n      請准為假執行宣告之判決（未繫屬本院者，不予贅論）。\n二、上訴人則以：\n    (一)被上訴人提出醫療費用單據，總金額為一萬九千一百七十\n      一元，與其主張一萬九千五百零五元不符，其中九十七年\n      八月二十九日及同年十月一日就醫，有三筆金額均各為五\n      十元，應有重複。至整形費用被上訴人尚未支出，不能為\n      請求。又被上訴人提出之交通費用單據，尚無法證明確有\n      支出交通費用三萬一千五百元，而被上訴人並未住院，實\n      無須看護費用，且乙○○並未證明其請假之工資損失。另\n      被上訴人請求精神慰撫金四十萬元，亦屬過高。\n    (二)己○○及辛○○業給付被上訴人慰問金一萬元，應就被上\n      訴人請求之金額中扣除。又被上訴人在不得嬉戲之教室任\n      意嬉戲跑步，應有過失，且其過失責任較重，依過失相抵\n      原則，應減輕伊百分之八十之責任等語，資為抗辯。\n三、原審判命上訴人應連帶給付被上訴人五十一萬九千二百元本\n    息，上訴人聲明不服，兩造於本院各聲明如下：\n    (一)上訴人方面：\n      原判決廢棄。\n      上開廢棄部分，被上訴人在第一審之訴及假執行之聲請\n        均駁回。\n      第一、二審訴訟費用由被上訴人負擔。\n    (二)被上訴人方面：\n      上訴駁回。\n      訴訟費用由上訴人負擔。\n四、兩造不爭執之事實：\n    (一)甲○○係彰化縣和美鎮○○路一六三號群勝美語短期補習\n      班之負責人，九十六年十月十二日下午一時許，被上訴人\n      在補習班二樓玩跑步競賽遊戲，遭庚○○自後推擠，致被\n      上訴人受有右手刺傷合併二條肌腱斷裂、兩指神經斷裂，\n      一條動脈斷裂合併十一公分長疤痕醜形傷害。\n    (二)庚○○係八十六年九月一日出生，己○○及辛○○為其法\n      定代理人。\n    (三)甲○○因本件業務過失傷害罪，經臺灣彰化地方法院以九\n      十七年度彰簡字第八二八號刑事簡易判決，判處拘役二十\n      日確定在案。\n    (四)事故發生後，己○○、辛○○已給付被上訴人慰問金一萬\n      元，被上訴人同意自請求金額中扣除。\n五、得心證之理由：\n    (一)按因故意或過失，不法侵害他人之權利者，負損害賠償責\n      任。數人共同不法侵害他人之權利者，連帶負損害賠償責\n      任。無行為能力人或限制行為能力人，不法侵害他人之權\n      利者，以行為時有識別能力為限，與其法定代理人連帶負\n      損害賠償責任。不法侵害他人之身體或健康者，對於被害\n      人因此喪失或減少勞動能力或增加生活上之需要時，應負\n      損害賠償責任。不法侵害他人之身體、健康、名譽、自由\n      、信用、隱私、貞操，或不法侵害其他人格法益而情節重\n      大者，被害人雖非財產上之損害，亦得請求賠償相當之金\n      額。民法第一百八十四條第一項前段、第一百八十五條第\n      一項前段、第一百八十七條第一項、第一百九十三條第一\n      項及第一百九十五條第一項分別定有明文。經查：\n      甲○○為上開補習班之負責人，本應注意並防止補習班\n        四週環境對就讀兒童可能引起之危險，應有符合標準之\n        安全設備，詎其疏於注意，未設置符合標準之安全設備\n        ，更未指定老師在場監督屬於幼齡之在班補習學生之作\n        息，則於前揭時、地，被上訴人玩跑步競賽遊戲，遭庚\n        ○○出其不意自後推擠，致被上訴人受有上述傷害，顯\n        然甲○○及庚○○之行為，係被上訴人所受傷害之共同\n        原因，且被上訴人所受之傷害，與甲○○及庚○○之侵\n        權行為間，具有相當因果關係，堪以認定。\n      庚○○係限制行為能力人，其上揭侵權行為致被上訴人\n        受有傷害，與其法定代理人即己○○、辛○○應連帶負\n        損害賠償責任。則被上訴人因甲○○及庚○○之共同侵\n        權行為，致身體受有損害，請求上訴人應連帶賠償醫療\n        費用、增加生活上所需費用及精神慰撫金，於法即無不\n        合。另甲○○與己○○、辛○○各自對被上訴人負全部\n        之損害賠償責任，為不真正連帶債務，與民法第二百七\n        十二條第一項所定連帶債務人就同一債務對於債權人各\n        負全部給付責任之法理，並無二致。茲就被上訴人所得\n      請求損害賠償金額，分述如下：\n        (1)醫療費用：被上訴人主張支出醫療費用一萬九千五百\n          零五元，有相關收據在卷可稽，均屬治療上之必要費\n          用，則被上訴人請求上訴人賠償醫療費用一萬九千五\n          百零五元，應予准許。至上訴人以被上訴人提出之單\n          據金額僅一萬九千一百七十一元，似有誤會。另上訴\n          人以被上訴人九十七年八月二十九日及同年十月一日\n          就醫，有三筆金額均各為五十元，應有重複云云，然\n          據被上訴人陳稱，此乃因看一次門診，即可復健六次\n          ，診所作業係以掛號日期為準，並未重複等語在卷，\n          尚屬可採，自無加以函查必要，附此敘明。\n        (2)整形費用：被上訴人受傷後留下十一公分之疤痕，對\n          成長中之少年自我人格發展，及追求身心之完美，自\n          有重大影響，本院審酌被上訴人右手腕處三至四公分\n          呈肥厚疤痕，如進行Ｗ一整形手術可能可獲些許改善\n          ，有臺中榮民總醫院鑑定書存卷可考，是被上訴人請\n          求未來整形費用，核屬必要。本院參酌臺中榮民總醫\n          院鑑定估計整形費用約須一萬元至五萬元間，因認被\n          上訴人請求整形費用四萬元，尚屬適當，應予准許。\n        (3)增加生活上所需費用：\n          (甲)相當於看護之費用：被上訴人右手受傷，自九十六\n            年十月十二日起至同年月二十七日，日常生活無法\n            自理，乙○○負責照顧看護，以一天相當於二千元\n            看護費，尚屬合理。故被上訴人請求相當於看護之\n            費用三萬元，於法有據，應予准許。\n          (乙)赴醫治療之交通費：被上訴人請求赴醫治療之交通\n            費三萬一千五百元，固據提出二張收據為證，然該\n            收據並無日期，復未記載支出車資之人及用途，尚\n            難憑為被上訴人有支出交通費之證明。此外，被上\n            訴人並未提出其他證據，資以證明其確有支出交通\n            費之事實，則被上訴人請求此部分之交通費，尚屬\n            無據，不應准許。\n          (丙)乙○○陪同被上訴人就診需請假所損失之工資二萬\n            八千元，與系爭事故無涉，且非被上訴人因系爭事\n            故所受之損害，則其此部分之請求，尚屬無稽，不\n            應准許。\n          (丁)是被上訴人得請求增加生活上所需費用，即為三萬\n            元。至超過三萬元部分，即屬無據，不應准許。\n        (4)精神慰撫金部分：被上訴人於本件車禍發生時，年僅\n          十歲，因本件事故右手拇指及食指仍感麻木無力，需\n          作經常性之復健治療，且留下十一公分長之疤痕醜形\n          ，依臺中榮民總醫院鑑定意見，進行整形手術，整體\n          疤痕無法消失，顯然被上訴人身心受有極大之痛苦，\n          非筆墨所能形容。而甲○○身為補習班之負責人，庚\n          ○○則屬實質之侵權行為人，渠等於事故發生後，迄\n          未與被上訴人達成和解，爰併審酌其他一切情狀，認\n          被上訴人請求精神慰撫金四十萬元，尚屬適當，應予\n          准許。上訴人以被上訴人請求精神慰撫金尚屬過高置\n          辯，殊無足採。\n        (5)綜上，被上訴人因本件事故而請求上訴人連帶賠償其\n          已支出醫療費用一萬九千五百零五元、將來須支出醫\n          療相關費用即整形費用四萬元、增加生活上所需費用\n          三萬元及精神慰撫金四十萬元，合計四十八萬九千五\n          百零五元，洵屬有據，應予准許。\n    (二)又損害之發生或擴大，被害人與有過失者，法院得減輕賠\n      償金額或免除之。前開規定，於被害人之代理人或使用與\n      有過失者，準用之。民法第二百十七條第一項、第三項亦\n      著有明文。經查：\n      被上訴人為限制行為能力人，對於在教室內嬉笑玩鬧，\n        已有能力辨識四週環境安危，懂得保護自己之安全，乃\n        被上訴人疏未注意嬉鬧時之安全，亦應負部分過失責任\n        ，始得事理之平。本院認斟酌甲○○身為補習班負責人\n        ，未能提供安全設施，復疏於注意指定教師在場監督，\n        與庚○○出其不意自後推擠被上訴人，應連帶負較重之\n        過失責任等情，因認甲○○及庚○○應連帶負擔百分之\n        八十過失責任，被上訴人應負百分之二十之過失責任。\n        準此計算，上訴人應連帶賠償被上訴人之數額為三十九\n        萬一千六百零四元。\n      己○○、辛○○於事故發生後，已給付被上訴人一萬元\n        ，被上訴人並同意自賠償金扣除，則被上訴人得請求上\n        訴人連帶賠償損害之金額為三十八萬一千六百零四元。\n        逾此範圍之請求，為無理由，自難准許。\n    (三)綜上所述，被上訴人依侵權行為之法律關係，請求上訴人\n      連帶給付三十八萬一千六百零四元，及甲○○自九十八年\n      十一月十九日、其餘上訴人均自同年月二十一日起至清償\n      日止，按年息百分之五計算法定遲延利息部分，為有理由\n      ，應予准許。此部分被上訴人聲請供擔保為假執行之宣告\n      ，核無不合，應酌定相當之擔保金額併予宣告。至逾越前\n      開應准許之部分，被上訴人之請求為無理由，應予駁回。\n      原審就被上訴人之請求，超過前開應准許部分，為被上訴\n      人勝訴之判決，尚有未合。上訴論旨指摘原判決該部分不\n      當，聲明廢棄，為有理由，爰由本院將原判決該部分予以\n      廢棄，改判如主文第二項所示。至原判決關於命上訴人應\n      連帶給付被上訴人三十八萬一千六百零四元，及甲○○自\n      九十八年十一月十九日、其餘上訴人均自同年月二十一日\n      起至清償日止，按年息百分之五計算法定遲延利息，暨依\n      被上訴人之聲請而為供擔保宣告假執行部分，經核於法洵\n      無違誤。上訴論旨指摘原判決該部分不當，聲明廢棄，為\n      無理由，應予駁回。\n六、本件事證已臻明確，兩造其餘攻擊、防禦方法，與判決結果\n    不生影響，爰不一一論述。\n七、據上論結，本件上訴為一部有理由、一部無理由。依民事訴\n    訟法第四百五十條、第四百四十九條第一項、第七十八條、\n    第七十九條、第八十五條第二項，判決如主文。"
  },
  "characters": {
    "judges": [
      "陳蘇宗",
      "張浴美",
      "李寶堂"
    ],
    "prosecutors": [

    ],
    "lawyers": [
      "柯開運"
    ],
    "clerks": [
      "林振甫"
    ],
    "plaintiffs": [

    ],
    "defendants": [

    ],
    "prosecutor_office": [

    ],
    "creditors": [

    ],
    "debtors": [

    ],
    "judicial_associate_officer": [

    ]
  },
  "adjudged_at": "2010-01-05",
  "created_at": "2016-01-05 15:07:30",
  "updated_at": "2016-01-05 15:07:30"
}