{
  "identify": "TCH-98-上-301-20100105-1",
  "court": {
    "name": "臺灣高等法院",
    "code": "TCH"
  },
  "division": {
    "name": "民事",
    "code": "V"
  },
  "year": 98,
  "word": "上",
  "number": "301",
  "jcheck": "1",
  "reason": "塗銷所有權移轉登記等",
  "content": "臺灣高等法院臺中分院民事判決  98年度上字第301號\n上  訴  人  華南商業銀行股份有限公司\n法定代理人  王濬智\n訴訟代理人  林政德律師\n被  上訴人  江梅華\n訴訟代理人  黃英傑律師\n被  上訴人  周益之\n上列當事人間請求塗銷所有權移轉登記等事件，上訴人對於民國\n98年7月15日臺灣臺中地方法院98年度訴字第444號第一審判決提\n起上訴，本院於98年12月22日言詞辯論終結，判決如下：\n    主  文\n上訴駁回。\n第二審訴訟費用由上訴人負擔。\n    事實及理由\n一、被上訴人周益之經合法通知，未於言詞辯論期日到場，核無\n    民事訴訟法第 386條各款所列情形，爰依上訴人華南商業銀\n    行股份有限公司（下簡稱華南銀行）之聲請，由其一造辯論\n    而為判決。\n二、上訴人華南銀行主張：訴外人凡永有限公司（下稱凡永公司\n    ）邀被上訴人周益之為連帶保證人，擔保凡永公司對於華南\n    銀行之一切債務。華南銀行執有訴外人詠順冷凍實業有限公\n    司（下稱詠順公司）所簽發、凡永公司背書之發票日為民國\n    97年11月5日、票號AD0000000、付款人華信銀行左營分行、\n    面額新臺幣（下同） 115萬5000元之支票，經提示後退票，\n    周益之對華南銀行負有清償責任。華南銀行就上述支票，嗣\n    後已以臺灣高雄地方法院98年度雄簡字第 431號宣示判決筆\n    錄，對詠順公司及凡永公司取得執行名義。華南銀行恐周益\n    之隱匿財產，日後有難於執行之虞，於97年11月14日聲請臺\n    灣高雄地方法院97年度裁全字第 10647號假扣押裁定，於97\n    年11月27日聲請對周益之所有坐落臺中市○區○○○段第13\n    8 之74地號土地面積85平方公尺全部及其地上建物1041建號\n    門牌台中市○區○○街586之2號三層樓房全部（下稱系爭房\n    地）執行假扣押；執行法院於97年11月28日發函查封。卻發\n    現周益之於97年11月28日以97年11月14日買賣為原因，將系\n    爭房地所有權移轉登記予被上訴人江梅華。周益之與江梅華\n    間所訂不動產買賣契約書簽約款100萬元、用印款100萬元均\n    記載於97年11月14日付清，惟並無匯款記錄可資證明；而於\n    移轉登完畢後之97年12月10日周益之與江梅華間另訂更正買\n    賣約定書，簽約款100萬元、用印款100萬元均更正付款日期\n    為97年10月20日；又依地政事務所資料中建築土地所有權買\n    賣移轉契約書及改良物所有權買賣移轉契約書記載買賣價金\n    分別是 256萬5725元及43萬1800元皆低於市價一半；另江梅\n    華並未支付買賣價金予周益之，足見雙方並非真實之買賣行\n    為，係依民法第87條第 1項規定，應係無效，爰先位聲明請\n    求確認被上訴人兩人間於97年11月14日就系爭房地之買賣關\n    係不存在，再依民法第 242條規定請求江梅華應將系爭房地\n    於97年11月28日以買賣原因所為之所有權移轉登記塗銷。又\n    縱認被上訴人見買賣關係為真實，惟周益之明知將系爭房地\n    所有權移轉登記，江梅華亦知周益之有債務未清償，如將系\n    爭房地移轉登記，必影響債權人債權，因此，備位聲明主張\n    依民法第 244條規定，訴請撤銷被上訴人間之上開買賣行為\n    ，並請求江梅華塗銷上開所有權移轉登記。\n三、被上訴人江梅華辯以：\n    江梅華確有以 700萬元之價格向周益之購買系爭房地，江梅\n    華於97年12月10日繳清尾款後，至97年12月31日點交完畢。\n    江梅華購買系爭房地，為支付買賣價金尾款，乃於97年12月\n    8 日以系爭房地向合作金庫商業銀行股份有限公司（下稱合\n    作金庫銀行）朝馬分行設定本金最高限額 540萬元抵押權，\n    實際貸款450萬元，而以其中429萬0278元代周益之償還台新\n    國際商業銀行股份有限公司（下稱台新銀行）南京東路分行\n    之抵押貸款，以充作支付買賣價金尾款。前 3次款乃江梅華\n    委託廉喬公司匯給庚德公司（負責人為周益之），江梅華將\n    款項匯給庚德公司。又江梅華分別於97年3月7日110萬元、3\n    月11日50萬元、4月16日50萬元、4月24日43萬元、10月27日\n    35萬元共計貸與廉喬公司 288萬元，而周益之積欠廉喬公司\n    273 萬元，在廉喬公司居間促成本件系爭房地買賣，並以江\n    梅華對廉喬公司之債權，以債作價方式來抵充價金之一部分\n    ，江梅華確實付足全部價金，其付款方式與社會常情相符。\n    江梅華之夫江劍英自78年起即已開設祥園實業有限公司，資\n    本額600萬元，經營不動產租賃仲介事業，年收入約在200萬\n    元以上；江梅華在合作金庫精武、坪林、朝馬分行，均有存\n    款，且名下尚投資多家上市公司股票，並自84年間起經營華\n    倫美容髮廊，經營美容美髮事業，年收入約在80萬元左右，\n    加上名下不動產以公告現值計算已達 600萬元以上。夫妻擔\n    任企業主多年，資力足敷支付購買系爭房地之款項，顯見江\n    梅華根本不可能與周益之為任何假買賣之行為。又周益之根\n    本不是系爭支票之發票人亦非背書人，根本無票據上責任；\n    周益之於96年 6月13日簽署保證書及授信契約書時，華南銀\n    行並未證明凡永公司負有何主債務，周益之之保證債務即不\n    存在；至於保證書上雖有「對貴行將來於第一條所負之債務\n    範圍內．．．保證人願與主債務人負連帶清償之責。」惟此\n    部分約定違反民法第 739條規定（主債務未存在）且其擔保\n    將來債務金額未明確，依民法第 153條規定其保證契約應未\n    成立。是系爭不動產買賣時，華南銀行對周益之尚無合法債\n    權存在，自不得提起本件訴訟。\n四、周益之未於言詞辯論期日到場，亦未提出書狀為任何聲明或\n    陳述。\n五、兩造不爭執之事項：\n    系爭房地原屬於周益之所有，周益之於97年11月14日以買賣\n    為原因，於97年11月28日移轉登記予江梅華。\n六、本院之判斷：\n  (一)華南銀行主張凡永公司邀周益之為連帶保證人，擔保凡永公\n    司對於華南銀行之一切債務。華南銀行執有詠順公司所簽發\n    、凡永公司背書之發票日為97年11月5日、票號AD0000000、\n    付款人華信銀行左營分行、面額 115萬5000元之支票，經提\n    示後退票，周益之對華南銀行負有清償責任等語，業據其提\n    出支票正反面影本、退票理由單、保證書及授信契約書為證\n    （見原審卷第110至124頁）。華南銀行就該支票債權，嗣已\n    對詠順公司、凡永公司取得執行名義（臺灣高雄地方法院98\n    年度雄簡字第 431號判決），亦有其所提出之該判決在卷可\n    憑（見原審卷第183、184頁），堪信華南銀行此部分主張屬\n    實。而周益之為連帶保證人之保證書（見原審卷第 112頁）\n    上已載明「對  貴行將來於第一條所負之債務範圍內．．．\n    保證人願與主債務人負連帶清償之責。」，是周益之所負之\n    保證債務涵蓋凡永公司於簽立授信契約書（見原審卷第 113\n    頁）後之債務。至於保證債務於契約有特別約定時，本非不\n    得包括將來之債務，江梅華辯稱保證契約應未成立云云，並\n    無足採。又周益之雖非系爭支票之發票人或背書人，而不負\n    票據債務，但凡永公司為系爭支票之背書人，嗣後系爭支票\n    經華南銀行提示不獲兌現時，凡永公司即為華南銀行之票據\n    債務人，華南銀行依上開保證書及授信契約書之約定，自屬\n    周益之之債權人；且華南銀行對周益之另有借款債權，業據\n    其提出臺灣高雄地方法院98年度司執字第 40599號執行事件\n    之債權憑證為證（見原審卷第 168頁），足見華南銀行確為\n    周益之之債權人，要無可疑。江梅華上開所辯，核無足採。\n    至於民事訴訟法第 270條之1第3項前段固規定：當事人就其\n    主張之爭點，經依第1項第3款或前項為協議者，應受其拘束\n    。惟該條項所謂應受其拘束之爭點協議，係指當事人就其所\n    主張之爭點，經依同條第 1項第3款或第2項為協議者而言；\n    於協議前未經當事人主張之爭點，既不在協議範圍，即不受\n    協議之拘束（最高法院97年度第2421號判決參照）。本件華\n    南銀行於98年4月1日行爭點整理時，雖未主張其對周益之另\n    有前揭臺灣高雄地方法院98年度重訴字第35號民事判決所確\n    定之債權，依上揭說明，尚不受該協議之拘束。且原告於前\n    揭爭點整理及協議簡化之後提出該攻擊防禦方法，並無礙於\n    訴訟之終結，應許其提出，併予敘明。\n  (二)按表意人與相對人通謀而為虛偽意思表示者，其意思表示無\n    效，民法第87條第 1項前段定有明文。惟所謂通謀虛偽表示\n    ，係指表意人與相對人相互明知為非真意之表示而言，故表\n    意人之相對人不僅須知表意人非真意，並須就表意人非真意\n    之表示相與為非真意之合意，始為相當。在贈與或買賣契約\n    ，不能僅因契約當事人間有特殊親誼關係或價金之交付不實\n    ，即謂該贈與或買賣係通謀虛偽成立。且第三人主張表意人\n    與相對人通謀而為虛偽意思表示者，該第三人應負舉證之責\n    （最高法院51年台上字第 215號判例、86年度台上字第3865\n    號判決、48年台上字第29號判例參照）。又民事訴訟如係由\n    原告主張權利者，應先由原告負舉證之責，若原告先不能舉\n    證，以證實自己主張之事實為真實，則被告就其抗辯事實即\n    令不能舉證，或其所舉證據尚有疵累，亦應駁回原告之請求\n    （最高法院17年上字第 917號判例意旨參照）。華南銀行主\n    張江梅華與周益之就系爭房地所為之買賣，為通謀虛偽之意\n    思表示云云，為江梅華所否認，並辯稱：其與周益之間就系\n    爭房地所為之前揭買賣係屬真正，其亦付足全部價金等語。\n    依江梅華與周益之於97年11月13日所簽訂之不動產買賣契約\n    書（見原審卷第63至66頁）之記載，系爭房地之買賣價金為\n    700萬元，簽約款100萬元，約定簽約時給付、用印款 100萬\n    元，約定97年11月14日用印時給付、完稅款50萬元，預於97\n    年12月10日給付、尾款 450萬元，預於97年12月20日給付；\n    江梅華與周益之復於97年12月10日簽訂更正買賣契約書（見\n    原審卷第68頁），約定：「1.買方應付各期價金，由買方委\n    託廉喬公司或委託合作金庫以匯款方式支付之。2.賣方應收\n    各期價金，以匯款匯入賣方本人或賣方指定庚德公司（負責\n    人為賣方）方式收取之。3.付款期別（以下各期款，均因賣\n    方急用而提前支付）：簽約款100萬元，用印款100萬元，\n    以97年10月20日匯款 200萬元支付之。完稅款以97年11月\n    12日匯款48萬元、97年11月13日匯款25萬元支付之。尾款\n    以97年12月10日匯款 377萬0862元、24萬8046元、27萬1370\n    元支付之。雙方約定價金700萬元，買方已提前支付702萬\n    0278元完畢，其中 2萬0278元用以支付代書費，印花稅，契\n    稅，規費等，如有不足則由買方負擔」，其上並有買方委託\n    付款人廉喬公司、賣方委託人庚德公司蓋用之印文。至於華\n    南銀行雖主張江梅華與周益之於97年12月10日簽訂更正買賣\n    契約書時，系爭房地已辦妥所有權移轉登記，顯應係無法證\n    明有支付價金之情況下拼湊書立云云，但廉喬公司確分別於\n    97年10月20日匯款 200萬元、97年11月12日匯款48萬元、97\n    年11月13日匯款25萬元至庚德公司帳戶，有匯款單六紙在卷\n    足憑（見原審卷第69、70頁），核與更正買賣契約書記載付\n    款之情形相符。江梅華另抗辯：其借貸予廉喬公司 288萬元\n    以上，廉喬公司積欠江梅華 288萬元，周益之則積欠廉喬公\n    司 273萬元，在廉喬公司居間促成下，乃有本件買賣等語，\n    亦據其提出廉喬公司所簽發、面額合計288萬元之本票5張及\n    其合作金庫銀行活期儲蓄存款存摺明細為證（見原審卷第19\n    4至200頁），華南銀行雖否認本票之真正，但該本票確係廉\n    喬公司陳進教所簽發，業據證人陳進教於本院到庭證述明確\n    （見本院卷第77頁正面）；而廉喬公司向江梅華借款均係現\n    金（見本院卷第76頁反面），核與江梅華之合作金庫銀行活\n    期儲蓄存款存摺明細相符，足證上開本票及合作金庫銀行活\n    期儲蓄存款存摺明細均屬真正。至於證人陳進教雖證稱其是\n    以私人名義向江梅華借款，與廉喬公司簽發本票雖有未符之\n    處，但陳進教係廉喬公司負責人，其或不能確實分別公司與\n    個人間之差異，但無礙於廉喬公司所簽發之上開本票為真實\n    。是更正買賣契約書記載之付款情形，應確屬江梅華與周益\n    之間買賣價款交付之實情，華南銀行雖主張應係無法證明有\n    支付價金之情況下拼湊書立云云，尚無足採。另系爭房地原\n    由周益之設定 732萬元之最高限額抵押權予台新銀行，用以\n    擔保周益之與庚德公司向台新銀行之借款債權，此有系爭房\n    地之登記謄本在卷可憑（見原審卷第10、11頁）。江梅華另\n    辯稱：其向周益之購買系爭房地後，為給付向周益之購買系\n    爭房地之價款，分別於97年12月10日、97年12月19日以系爭\n    房屋向合作金庫銀行抵押貸款429萬元、21萬元，合計450萬\n    元，所貸得之款項由江梅華代償周益之及庚德公司向台新銀\n    行之借款，而由合作金庫銀行朝馬分行分別於97年12月10日\n    匯款24萬8046元、27萬1370元、 377萬0862元至台新銀行南\n    京東路分行，並塗銷周益之以系爭房地向台新銀行所設定之\n    抵押權等語，業據提出借款契約書、系爭房屋登記謄本等為\n    證，並有合作金庫銀行朝馬分行函文暨所檢附之放款支出傳\n    票、取款憑條等足證（見原審卷第93-98、157-164頁），應\n    堪信江梅華之上開抗辯為真實。至於江梅華匯款予合作金庫\n    銀行之時間雖在系爭房地所有權移轉予江梅華之後，但匯款\n    單上已載明「如不同意塗銷抵押權請退匯」文字，顯見該匯\n    款確係江梅華代償之事實。是合計江梅華代周益之償還以系\n    爭房地向台新銀行所為之抵押貸款金額達 429萬0278元。華\n    南銀行主張此部分還款，不能認為係由江梅華所有之資金支\n    付此不動產買賣價金云云，尚無足採。則江梅華既為合作金\n    庫銀行之債務人，日後如有不能清償貸款之情事，債權人合\n    作金庫銀行除可拍賣系爭房地外，尚可對江梅華其餘財產取\n    償，是江梅華辯稱系爭買賣並非通謀虛偽意思表示等語，並\n    非無足採信，此外華南銀行未能舉證證明系爭買賣為通謀虛\n    偽意思表示之事實，華南銀行主張江梅華與周益之間就系爭\n    房地之買賣為通謀虛偽意思表示云云，要非可採。從而華南\n    銀行先位聲明請求確認江梅華與周益之間於97年11月14日就\n    系爭房地之買賣關係不存在；暨江梅華應將系爭房地於97年\n    11月28日以買賣原因所為之所有權移轉登記塗銷，難認有據\n    ，無法准許。\n  (三)按債務人所為之有償行為，於行為時明知有損害於債權人之\n    權利者，以受益人於受益時亦知其情事者為限，債權人得聲\n    請法院撤銷之。債務人之行為非以財產為標的，或僅有害於\n    以給付特定物為標的之債權者，不適用前二項之規定。債權\n    人依第1項或第2項之規定聲請法院撤銷時，得並聲請命受益\n    人或轉得人回復原狀。但轉得人於轉得時不知有撤銷原因者\n    ，不在此限，民法第244條第2、3、4項定有明文。依此規定\n    ，債權人依民法第 244條規定，撤銷債務人所為之有償或無\n    償行為者，須為債務人所為之法律行為，而其法律行為有害\n    於債權人，且其法律行為係以財產權為目的，如為有償之法\n    律行為，債務人於行為時，須明知其行為有害於債權人，受\n    益人於受益時，亦明知其事情，始足當之（最高法院42年台\n    上字第 323號判例參照）。又債務人出賣其財產非必生減少\n    資力之結果，苟出賣之財產已獲得相當之對價，用以清償具\n    有優先受償權之債務，則一方面減少其財產，一方面減少其\n    債務，其對於普通債權人，即難謂為詐害行為；債務已屆清\n    償期，債務人就既存債務為清償者，固生減少積極財產之結\n    果，但同時亦減少其消極財產，於債務人之資力並無影響，\n    不得指為民法第 244條第1項或第2項之詐害行為（最高法院\n    51年台上字第 302號判例、55年台上字第2839號判例參照）\n    。江梅華與周益之間之買賣契約並非通謀虛偽之意思表示，\n    且江梅華與周益之間確有買賣價金之支付事實，已如上述。\n    則周益之將系爭土地移轉登記予江梅華，應屬有償行為。華\n    南銀行提出之支票退票理由單（見原審卷第 110頁）之支票\n    退票日期雖為97年11月 5日，惟華南銀行至98年間始就對凡\n    永公司行使追索權，經臺灣高雄地方法院98年 4月28日以98\n    年度雄簡字第 431號給付票款判決，此有臺灣高雄地方法院\n    98年度雄簡字第 431號給付票款宣示判決筆錄在卷足憑（見\n    原審卷第183、184頁）；且華南銀行訴請周益之、凡永公司\n    清償借款事件，臺灣高雄地方法院係於98年 2月27日以98年\n    度重訴字第35號判決華南銀行勝訴，此業經原審法院調取該\n    案卷宗無訛，則依該判決書之認定，華南銀行對周益之債權\n    為連帶保證債權，亦即周益之為凡永公司向華南銀行借款之\n    連帶保證人，而凡永公司向華南銀行所為之借款，係於97年\n    12月19日到期之本金 450萬元未為清償，全部債務始依約視\n    為到期，則江梅華不可能事先知悉周益之對華南銀行有前揭\n    債務存在。此外華南銀行並未舉證證明江梅華向周益之買受\n    系爭房地時，明知周益之積欠華南銀行債務，及周益之出售\n    系爭房地有害於華南銀行行使債權之情事。從而華南銀行備\n    位聲明以江梅華與周益之間就系爭房地之買賣損害其權利，\n    依民法第244條第2、3、4項規定請求判決撤銷江梅華與周益\n    之間於97年11月14日就系爭房地所為之買賣行為，且江梅華\n    應將系爭房地於97年11月28日以買賣原因所為之所有權移轉\n    登記塗銷，亦無理由，應予駁回。\n  (四)綜上所述，本件上訴人華南銀行主張被上訴人間買賣系爭房\n    地之行為為通謀虛偽意思表示，無效；及被上訴人間移轉系\n    爭房地所有權行為為無償行為，暨被上訴人間移轉系爭房地\n    所有權行為縱為有償行為，亦為江梅華所明知等，均不足採\n    ，被上訴人抗辯尚屬可信。是則上訴人執此主張確認江梅華\n    與周益之間於97年11月14日就系爭房地之買賣關係不存在；\n    暨江梅華應將系爭房地於97年11月28日以買賣原因所為之所\n    有權移轉登記塗銷；及請求判決撤銷江梅華與周益之間於97\n    年11月14日就系爭房地所為之買賣行為，且江梅華應將系爭\n    房地於97年11月28日以買賣原因所為之所有權移轉登記塗銷\n    云云，自屬無據，不應准許。原審為上訴人敗訴之判決，並\n    無不合。上訴意旨指摘原判決不當，求予廢棄改判，為無理\n    由，應予駁回。\n七、本件事證已臻明確，兩造其餘攻擊防禦方法，核與判決結果\n    不生影響，爰不逐一論述。\n八、據上論結，本件上訴為無理由，依民事訴訟法第449條第1項\n    、第78條，判決如主文。\n中    華    民    國    99    年    1     月    5     日\n              民事第三庭    審判長法  官  陳照德\n                                  法  官  朱樑\n                                  法  官  李平勳\n以上正本係照原本作成。\n如對本判決上訴，須於收受判決送達後20日內向本院提出上訴書\n狀，其未表明上訴理由者，應於提出上訴後20日內向本院提出上\n訴理由書（須按他造人數附具繕本）。上訴時應提出委任律師為\n訴訟代理人之委任狀。具有民事訴訟法第 466條之1第1項但書或\n第 2項之情形為訴訟代理人者，另應附具律師及格證書及釋明委\n任人與受任人有該條項所定關係之釋明文書影本。\n                                  書記官  江丞晏\n中    華    民    國    99    年    1     月    5     日",
  "structure": {
    "main": "上訴駁回。\n第二審訴訟費用由上訴人負擔。",
    "fact": "一、被上訴人周益之經合法通知，未於言詞辯論期日到場，核無\n    民事訴訟法第 386條各款所列情形，爰依上訴人華南商業銀\n    行股份有限公司（下簡稱華南銀行）之聲請，由其一造辯論\n    而為判決。\n二、上訴人華南銀行主張：訴外人凡永有限公司（下稱凡永公司\n    ）邀被上訴人周益之為連帶保證人，擔保凡永公司對於華南\n    銀行之一切債務。華南銀行執有訴外人詠順冷凍實業有限公\n    司（下稱詠順公司）所簽發、凡永公司背書之發票日為民國\n    97年11月5日、票號AD0000000、付款人華信銀行左營分行、\n    面額新臺幣（下同） 115萬5000元之支票，經提示後退票，\n    周益之對華南銀行負有清償責任。華南銀行就上述支票，嗣\n    後已以臺灣高雄地方法院98年度雄簡字第 431號宣示判決筆\n    錄，對詠順公司及凡永公司取得執行名義。華南銀行恐周益\n    之隱匿財產，日後有難於執行之虞，於97年11月14日聲請臺\n    灣高雄地方法院97年度裁全字第 10647號假扣押裁定，於97\n    年11月27日聲請對周益之所有坐落臺中市○區○○○段第13\n    8 之74地號土地面積85平方公尺全部及其地上建物1041建號\n    門牌台中市○區○○街586之2號三層樓房全部（下稱系爭房\n    地）執行假扣押；執行法院於97年11月28日發函查封。卻發\n    現周益之於97年11月28日以97年11月14日買賣為原因，將系\n    爭房地所有權移轉登記予被上訴人江梅華。周益之與江梅華\n    間所訂不動產買賣契約書簽約款100萬元、用印款100萬元均\n    記載於97年11月14日付清，惟並無匯款記錄可資證明；而於\n    移轉登完畢後之97年12月10日周益之與江梅華間另訂更正買\n    賣約定書，簽約款100萬元、用印款100萬元均更正付款日期\n    為97年10月20日；又依地政事務所資料中建築土地所有權買\n    賣移轉契約書及改良物所有權買賣移轉契約書記載買賣價金\n    分別是 256萬5725元及43萬1800元皆低於市價一半；另江梅\n    華並未支付買賣價金予周益之，足見雙方並非真實之買賣行\n    為，係依民法第87條第 1項規定，應係無效，爰先位聲明請\n    求確認被上訴人兩人間於97年11月14日就系爭房地之買賣關\n    係不存在，再依民法第 242條規定請求江梅華應將系爭房地\n    於97年11月28日以買賣原因所為之所有權移轉登記塗銷。又\n    縱認被上訴人見買賣關係為真實，惟周益之明知將系爭房地\n    所有權移轉登記，江梅華亦知周益之有債務未清償，如將系\n    爭房地移轉登記，必影響債權人債權，因此，備位聲明主張\n    依民法第 244條規定，訴請撤銷被上訴人間之上開買賣行為\n    ，並請求江梅華塗銷上開所有權移轉登記。\n三、被上訴人江梅華辯以：\n    江梅華確有以 700萬元之價格向周益之購買系爭房地，江梅\n    華於97年12月10日繳清尾款後，至97年12月31日點交完畢。\n    江梅華購買系爭房地，為支付買賣價金尾款，乃於97年12月\n    8 日以系爭房地向合作金庫商業銀行股份有限公司（下稱合\n    作金庫銀行）朝馬分行設定本金最高限額 540萬元抵押權，\n    實際貸款450萬元，而以其中429萬0278元代周益之償還台新\n    國際商業銀行股份有限公司（下稱台新銀行）南京東路分行\n    之抵押貸款，以充作支付買賣價金尾款。前 3次款乃江梅華\n    委託廉喬公司匯給庚德公司（負責人為周益之），江梅華將\n    款項匯給庚德公司。又江梅華分別於97年3月7日110萬元、3\n    月11日50萬元、4月16日50萬元、4月24日43萬元、10月27日\n    35萬元共計貸與廉喬公司 288萬元，而周益之積欠廉喬公司\n    273 萬元，在廉喬公司居間促成本件系爭房地買賣，並以江\n    梅華對廉喬公司之債權，以債作價方式來抵充價金之一部分\n    ，江梅華確實付足全部價金，其付款方式與社會常情相符。\n    江梅華之夫江劍英自78年起即已開設祥園實業有限公司，資\n    本額600萬元，經營不動產租賃仲介事業，年收入約在200萬\n    元以上；江梅華在合作金庫精武、坪林、朝馬分行，均有存\n    款，且名下尚投資多家上市公司股票，並自84年間起經營華\n    倫美容髮廊，經營美容美髮事業，年收入約在80萬元左右，\n    加上名下不動產以公告現值計算已達 600萬元以上。夫妻擔\n    任企業主多年，資力足敷支付購買系爭房地之款項，顯見江\n    梅華根本不可能與周益之為任何假買賣之行為。又周益之根\n    本不是系爭支票之發票人亦非背書人，根本無票據上責任；\n    周益之於96年 6月13日簽署保證書及授信契約書時，華南銀\n    行並未證明凡永公司負有何主債務，周益之之保證債務即不\n    存在；至於保證書上雖有「對貴行將來於第一條所負之債務\n    範圍內．．．保證人願與主債務人負連帶清償之責。」惟此\n    部分約定違反民法第 739條規定（主債務未存在）且其擔保\n    將來債務金額未明確，依民法第 153條規定其保證契約應未\n    成立。是系爭不動產買賣時，華南銀行對周益之尚無合法債\n    權存在，自不得提起本件訴訟。\n四、周益之未於言詞辯論期日到場，亦未提出書狀為任何聲明或\n    陳述。\n五、兩造不爭執之事項：\n    系爭房地原屬於周益之所有，周益之於97年11月14日以買賣\n    為原因，於97年11月28日移轉登記予江梅華。\n六、本院之判斷：\n  (一)華南銀行主張凡永公司邀周益之為連帶保證人，擔保凡永公\n    司對於華南銀行之一切債務。華南銀行執有詠順公司所簽發\n    、凡永公司背書之發票日為97年11月5日、票號AD0000000、\n    付款人華信銀行左營分行、面額 115萬5000元之支票，經提\n    示後退票，周益之對華南銀行負有清償責任等語，業據其提\n    出支票正反面影本、退票理由單、保證書及授信契約書為證\n    （見原審卷第110至124頁）。華南銀行就該支票債權，嗣已\n    對詠順公司、凡永公司取得執行名義（臺灣高雄地方法院98\n    年度雄簡字第 431號判決），亦有其所提出之該判決在卷可\n    憑（見原審卷第183、184頁），堪信華南銀行此部分主張屬\n    實。而周益之為連帶保證人之保證書（見原審卷第 112頁）\n    上已載明「對  貴行將來於第一條所負之債務範圍內．．．\n    保證人願與主債務人負連帶清償之責。」，是周益之所負之\n    保證債務涵蓋凡永公司於簽立授信契約書（見原審卷第 113\n    頁）後之債務。至於保證債務於契約有特別約定時，本非不\n    得包括將來之債務，江梅華辯稱保證契約應未成立云云，並\n    無足採。又周益之雖非系爭支票之發票人或背書人，而不負\n    票據債務，但凡永公司為系爭支票之背書人，嗣後系爭支票\n    經華南銀行提示不獲兌現時，凡永公司即為華南銀行之票據\n    債務人，華南銀行依上開保證書及授信契約書之約定，自屬\n    周益之之債權人；且華南銀行對周益之另有借款債權，業據\n    其提出臺灣高雄地方法院98年度司執字第 40599號執行事件\n    之債權憑證為證（見原審卷第 168頁），足見華南銀行確為\n    周益之之債權人，要無可疑。江梅華上開所辯，核無足採。\n    至於民事訴訟法第 270條之1第3項前段固規定：當事人就其\n    主張之爭點，經依第1項第3款或前項為協議者，應受其拘束\n    。惟該條項所謂應受其拘束之爭點協議，係指當事人就其所\n    主張之爭點，經依同條第 1項第3款或第2項為協議者而言；\n    於協議前未經當事人主張之爭點，既不在協議範圍，即不受\n    協議之拘束（最高法院97年度第2421號判決參照）。本件華\n    南銀行於98年4月1日行爭點整理時，雖未主張其對周益之另\n    有前揭臺灣高雄地方法院98年度重訴字第35號民事判決所確\n    定之債權，依上揭說明，尚不受該協議之拘束。且原告於前\n    揭爭點整理及協議簡化之後提出該攻擊防禦方法，並無礙於\n    訴訟之終結，應許其提出，併予敘明。\n  (二)按表意人與相對人通謀而為虛偽意思表示者，其意思表示無\n    效，民法第87條第 1項前段定有明文。惟所謂通謀虛偽表示\n    ，係指表意人與相對人相互明知為非真意之表示而言，故表\n    意人之相對人不僅須知表意人非真意，並須就表意人非真意\n    之表示相與為非真意之合意，始為相當。在贈與或買賣契約\n    ，不能僅因契約當事人間有特殊親誼關係或價金之交付不實\n    ，即謂該贈與或買賣係通謀虛偽成立。且第三人主張表意人\n    與相對人通謀而為虛偽意思表示者，該第三人應負舉證之責\n    （最高法院51年台上字第 215號判例、86年度台上字第3865\n    號判決、48年台上字第29號判例參照）。又民事訴訟如係由\n    原告主張權利者，應先由原告負舉證之責，若原告先不能舉\n    證，以證實自己主張之事實為真實，則被告就其抗辯事實即\n    令不能舉證，或其所舉證據尚有疵累，亦應駁回原告之請求\n    （最高法院17年上字第 917號判例意旨參照）。華南銀行主\n    張江梅華與周益之就系爭房地所為之買賣，為通謀虛偽之意\n    思表示云云，為江梅華所否認，並辯稱：其與周益之間就系\n    爭房地所為之前揭買賣係屬真正，其亦付足全部價金等語。\n    依江梅華與周益之於97年11月13日所簽訂之不動產買賣契約\n    書（見原審卷第63至66頁）之記載，系爭房地之買賣價金為\n    700萬元，簽約款100萬元，約定簽約時給付、用印款 100萬\n    元，約定97年11月14日用印時給付、完稅款50萬元，預於97\n    年12月10日給付、尾款 450萬元，預於97年12月20日給付；\n    江梅華與周益之復於97年12月10日簽訂更正買賣契約書（見\n    原審卷第68頁），約定：「1.買方應付各期價金，由買方委\n    託廉喬公司或委託合作金庫以匯款方式支付之。2.賣方應收\n    各期價金，以匯款匯入賣方本人或賣方指定庚德公司（負責\n    人為賣方）方式收取之。3.付款期別（以下各期款，均因賣\n    方急用而提前支付）：簽約款100萬元，用印款100萬元，\n    以97年10月20日匯款 200萬元支付之。完稅款以97年11月\n    12日匯款48萬元、97年11月13日匯款25萬元支付之。尾款\n    以97年12月10日匯款 377萬0862元、24萬8046元、27萬1370\n    元支付之。雙方約定價金700萬元，買方已提前支付702萬\n    0278元完畢，其中 2萬0278元用以支付代書費，印花稅，契\n    稅，規費等，如有不足則由買方負擔」，其上並有買方委託\n    付款人廉喬公司、賣方委託人庚德公司蓋用之印文。至於華\n    南銀行雖主張江梅華與周益之於97年12月10日簽訂更正買賣\n    契約書時，系爭房地已辦妥所有權移轉登記，顯應係無法證\n    明有支付價金之情況下拼湊書立云云，但廉喬公司確分別於\n    97年10月20日匯款 200萬元、97年11月12日匯款48萬元、97\n    年11月13日匯款25萬元至庚德公司帳戶，有匯款單六紙在卷\n    足憑（見原審卷第69、70頁），核與更正買賣契約書記載付\n    款之情形相符。江梅華另抗辯：其借貸予廉喬公司 288萬元\n    以上，廉喬公司積欠江梅華 288萬元，周益之則積欠廉喬公\n    司 273萬元，在廉喬公司居間促成下，乃有本件買賣等語，\n    亦據其提出廉喬公司所簽發、面額合計288萬元之本票5張及\n    其合作金庫銀行活期儲蓄存款存摺明細為證（見原審卷第19\n    4至200頁），華南銀行雖否認本票之真正，但該本票確係廉\n    喬公司陳進教所簽發，業據證人陳進教於本院到庭證述明確\n    （見本院卷第77頁正面）；而廉喬公司向江梅華借款均係現\n    金（見本院卷第76頁反面），核與江梅華之合作金庫銀行活\n    期儲蓄存款存摺明細相符，足證上開本票及合作金庫銀行活\n    期儲蓄存款存摺明細均屬真正。至於證人陳進教雖證稱其是\n    以私人名義向江梅華借款，與廉喬公司簽發本票雖有未符之\n    處，但陳進教係廉喬公司負責人，其或不能確實分別公司與\n    個人間之差異，但無礙於廉喬公司所簽發之上開本票為真實\n    。是更正買賣契約書記載之付款情形，應確屬江梅華與周益\n    之間買賣價款交付之實情，華南銀行雖主張應係無法證明有\n    支付價金之情況下拼湊書立云云，尚無足採。另系爭房地原\n    由周益之設定 732萬元之最高限額抵押權予台新銀行，用以\n    擔保周益之與庚德公司向台新銀行之借款債權，此有系爭房\n    地之登記謄本在卷可憑（見原審卷第10、11頁）。江梅華另\n    辯稱：其向周益之購買系爭房地後，為給付向周益之購買系\n    爭房地之價款，分別於97年12月10日、97年12月19日以系爭\n    房屋向合作金庫銀行抵押貸款429萬元、21萬元，合計450萬\n    元，所貸得之款項由江梅華代償周益之及庚德公司向台新銀\n    行之借款，而由合作金庫銀行朝馬分行分別於97年12月10日\n    匯款24萬8046元、27萬1370元、 377萬0862元至台新銀行南\n    京東路分行，並塗銷周益之以系爭房地向台新銀行所設定之\n    抵押權等語，業據提出借款契約書、系爭房屋登記謄本等為\n    證，並有合作金庫銀行朝馬分行函文暨所檢附之放款支出傳\n    票、取款憑條等足證（見原審卷第93-98、157-164頁），應\n    堪信江梅華之上開抗辯為真實。至於江梅華匯款予合作金庫\n    銀行之時間雖在系爭房地所有權移轉予江梅華之後，但匯款\n    單上已載明「如不同意塗銷抵押權請退匯」文字，顯見該匯\n    款確係江梅華代償之事實。是合計江梅華代周益之償還以系\n    爭房地向台新銀行所為之抵押貸款金額達 429萬0278元。華\n    南銀行主張此部分還款，不能認為係由江梅華所有之資金支\n    付此不動產買賣價金云云，尚無足採。則江梅華既為合作金\n    庫銀行之債務人，日後如有不能清償貸款之情事，債權人合\n    作金庫銀行除可拍賣系爭房地外，尚可對江梅華其餘財產取\n    償，是江梅華辯稱系爭買賣並非通謀虛偽意思表示等語，並\n    非無足採信，此外華南銀行未能舉證證明系爭買賣為通謀虛\n    偽意思表示之事實，華南銀行主張江梅華與周益之間就系爭\n    房地之買賣為通謀虛偽意思表示云云，要非可採。從而華南\n    銀行先位聲明請求確認江梅華與周益之間於97年11月14日就\n    系爭房地之買賣關係不存在；暨江梅華應將系爭房地於97年\n    11月28日以買賣原因所為之所有權移轉登記塗銷，難認有據\n    ，無法准許。\n  (三)按債務人所為之有償行為，於行為時明知有損害於債權人之\n    權利者，以受益人於受益時亦知其情事者為限，債權人得聲\n    請法院撤銷之。債務人之行為非以財產為標的，或僅有害於\n    以給付特定物為標的之債權者，不適用前二項之規定。債權\n    人依第1項或第2項之規定聲請法院撤銷時，得並聲請命受益\n    人或轉得人回復原狀。但轉得人於轉得時不知有撤銷原因者\n    ，不在此限，民法第244條第2、3、4項定有明文。依此規定\n    ，債權人依民法第 244條規定，撤銷債務人所為之有償或無\n    償行為者，須為債務人所為之法律行為，而其法律行為有害\n    於債權人，且其法律行為係以財產權為目的，如為有償之法\n    律行為，債務人於行為時，須明知其行為有害於債權人，受\n    益人於受益時，亦明知其事情，始足當之（最高法院42年台\n    上字第 323號判例參照）。又債務人出賣其財產非必生減少\n    資力之結果，苟出賣之財產已獲得相當之對價，用以清償具\n    有優先受償權之債務，則一方面減少其財產，一方面減少其\n    債務，其對於普通債權人，即難謂為詐害行為；債務已屆清\n    償期，債務人就既存債務為清償者，固生減少積極財產之結\n    果，但同時亦減少其消極財產，於債務人之資力並無影響，\n    不得指為民法第 244條第1項或第2項之詐害行為（最高法院\n    51年台上字第 302號判例、55年台上字第2839號判例參照）\n    。江梅華與周益之間之買賣契約並非通謀虛偽之意思表示，\n    且江梅華與周益之間確有買賣價金之支付事實，已如上述。\n    則周益之將系爭土地移轉登記予江梅華，應屬有償行為。華\n    南銀行提出之支票退票理由單（見原審卷第 110頁）之支票\n    退票日期雖為97年11月 5日，惟華南銀行至98年間始就對凡\n    永公司行使追索權，經臺灣高雄地方法院98年 4月28日以98\n    年度雄簡字第 431號給付票款判決，此有臺灣高雄地方法院\n    98年度雄簡字第 431號給付票款宣示判決筆錄在卷足憑（見\n    原審卷第183、184頁）；且華南銀行訴請周益之、凡永公司\n    清償借款事件，臺灣高雄地方法院係於98年 2月27日以98年\n    度重訴字第35號判決華南銀行勝訴，此業經原審法院調取該\n    案卷宗無訛，則依該判決書之認定，華南銀行對周益之債權\n    為連帶保證債權，亦即周益之為凡永公司向華南銀行借款之\n    連帶保證人，而凡永公司向華南銀行所為之借款，係於97年\n    12月19日到期之本金 450萬元未為清償，全部債務始依約視\n    為到期，則江梅華不可能事先知悉周益之對華南銀行有前揭\n    債務存在。此外華南銀行並未舉證證明江梅華向周益之買受\n    系爭房地時，明知周益之積欠華南銀行債務，及周益之出售\n    系爭房地有害於華南銀行行使債權之情事。從而華南銀行備\n    位聲明以江梅華與周益之間就系爭房地之買賣損害其權利，\n    依民法第244條第2、3、4項規定請求判決撤銷江梅華與周益\n    之間於97年11月14日就系爭房地所為之買賣行為，且江梅華\n    應將系爭房地於97年11月28日以買賣原因所為之所有權移轉\n    登記塗銷，亦無理由，應予駁回。\n  (四)綜上所述，本件上訴人華南銀行主張被上訴人間買賣系爭房\n    地之行為為通謀虛偽意思表示，無效；及被上訴人間移轉系\n    爭房地所有權行為為無償行為，暨被上訴人間移轉系爭房地\n    所有權行為縱為有償行為，亦為江梅華所明知等，均不足採\n    ，被上訴人抗辯尚屬可信。是則上訴人執此主張確認江梅華\n    與周益之間於97年11月14日就系爭房地之買賣關係不存在；\n    暨江梅華應將系爭房地於97年11月28日以買賣原因所為之所\n    有權移轉登記塗銷；及請求判決撤銷江梅華與周益之間於97\n    年11月14日就系爭房地所為之買賣行為，且江梅華應將系爭\n    房地於97年11月28日以買賣原因所為之所有權移轉登記塗銷\n    云云，自屬無據，不應准許。原審為上訴人敗訴之判決，並\n    無不合。上訴意旨指摘原判決不當，求予廢棄改判，為無理\n    由，應予駁回。\n七、本件事證已臻明確，兩造其餘攻擊防禦方法，核與判決結果\n    不生影響，爰不逐一論述。\n八、據上論結，本件上訴為無理由，依民事訴訟法第449條第1項\n    、第78條，判決如主文。",
    "reason": "一、被上訴人周益之經合法通知，未於言詞辯論期日到場，核無\n    民事訴訟法第 386條各款所列情形，爰依上訴人華南商業銀\n    行股份有限公司（下簡稱華南銀行）之聲請，由其一造辯論\n    而為判決。\n二、上訴人華南銀行主張：訴外人凡永有限公司（下稱凡永公司\n    ）邀被上訴人周益之為連帶保證人，擔保凡永公司對於華南\n    銀行之一切債務。華南銀行執有訴外人詠順冷凍實業有限公\n    司（下稱詠順公司）所簽發、凡永公司背書之發票日為民國\n    97年11月5日、票號AD0000000、付款人華信銀行左營分行、\n    面額新臺幣（下同） 115萬5000元之支票，經提示後退票，\n    周益之對華南銀行負有清償責任。華南銀行就上述支票，嗣\n    後已以臺灣高雄地方法院98年度雄簡字第 431號宣示判決筆\n    錄，對詠順公司及凡永公司取得執行名義。華南銀行恐周益\n    之隱匿財產，日後有難於執行之虞，於97年11月14日聲請臺\n    灣高雄地方法院97年度裁全字第 10647號假扣押裁定，於97\n    年11月27日聲請對周益之所有坐落臺中市○區○○○段第13\n    8 之74地號土地面積85平方公尺全部及其地上建物1041建號\n    門牌台中市○區○○街586之2號三層樓房全部（下稱系爭房\n    地）執行假扣押；執行法院於97年11月28日發函查封。卻發\n    現周益之於97年11月28日以97年11月14日買賣為原因，將系\n    爭房地所有權移轉登記予被上訴人江梅華。周益之與江梅華\n    間所訂不動產買賣契約書簽約款100萬元、用印款100萬元均\n    記載於97年11月14日付清，惟並無匯款記錄可資證明；而於\n    移轉登完畢後之97年12月10日周益之與江梅華間另訂更正買\n    賣約定書，簽約款100萬元、用印款100萬元均更正付款日期\n    為97年10月20日；又依地政事務所資料中建築土地所有權買\n    賣移轉契約書及改良物所有權買賣移轉契約書記載買賣價金\n    分別是 256萬5725元及43萬1800元皆低於市價一半；另江梅\n    華並未支付買賣價金予周益之，足見雙方並非真實之買賣行\n    為，係依民法第87條第 1項規定，應係無效，爰先位聲明請\n    求確認被上訴人兩人間於97年11月14日就系爭房地之買賣關\n    係不存在，再依民法第 242條規定請求江梅華應將系爭房地\n    於97年11月28日以買賣原因所為之所有權移轉登記塗銷。又\n    縱認被上訴人見買賣關係為真實，惟周益之明知將系爭房地\n    所有權移轉登記，江梅華亦知周益之有債務未清償，如將系\n    爭房地移轉登記，必影響債權人債權，因此，備位聲明主張\n    依民法第 244條規定，訴請撤銷被上訴人間之上開買賣行為\n    ，並請求江梅華塗銷上開所有權移轉登記。\n三、被上訴人江梅華辯以：\n    江梅華確有以 700萬元之價格向周益之購買系爭房地，江梅\n    華於97年12月10日繳清尾款後，至97年12月31日點交完畢。\n    江梅華購買系爭房地，為支付買賣價金尾款，乃於97年12月\n    8 日以系爭房地向合作金庫商業銀行股份有限公司（下稱合\n    作金庫銀行）朝馬分行設定本金最高限額 540萬元抵押權，\n    實際貸款450萬元，而以其中429萬0278元代周益之償還台新\n    國際商業銀行股份有限公司（下稱台新銀行）南京東路分行\n    之抵押貸款，以充作支付買賣價金尾款。前 3次款乃江梅華\n    委託廉喬公司匯給庚德公司（負責人為周益之），江梅華將\n    款項匯給庚德公司。又江梅華分別於97年3月7日110萬元、3\n    月11日50萬元、4月16日50萬元、4月24日43萬元、10月27日\n    35萬元共計貸與廉喬公司 288萬元，而周益之積欠廉喬公司\n    273 萬元，在廉喬公司居間促成本件系爭房地買賣，並以江\n    梅華對廉喬公司之債權，以債作價方式來抵充價金之一部分\n    ，江梅華確實付足全部價金，其付款方式與社會常情相符。\n    江梅華之夫江劍英自78年起即已開設祥園實業有限公司，資\n    本額600萬元，經營不動產租賃仲介事業，年收入約在200萬\n    元以上；江梅華在合作金庫精武、坪林、朝馬分行，均有存\n    款，且名下尚投資多家上市公司股票，並自84年間起經營華\n    倫美容髮廊，經營美容美髮事業，年收入約在80萬元左右，\n    加上名下不動產以公告現值計算已達 600萬元以上。夫妻擔\n    任企業主多年，資力足敷支付購買系爭房地之款項，顯見江\n    梅華根本不可能與周益之為任何假買賣之行為。又周益之根\n    本不是系爭支票之發票人亦非背書人，根本無票據上責任；\n    周益之於96年 6月13日簽署保證書及授信契約書時，華南銀\n    行並未證明凡永公司負有何主債務，周益之之保證債務即不\n    存在；至於保證書上雖有「對貴行將來於第一條所負之債務\n    範圍內．．．保證人願與主債務人負連帶清償之責。」惟此\n    部分約定違反民法第 739條規定（主債務未存在）且其擔保\n    將來債務金額未明確，依民法第 153條規定其保證契約應未\n    成立。是系爭不動產買賣時，華南銀行對周益之尚無合法債\n    權存在，自不得提起本件訴訟。\n四、周益之未於言詞辯論期日到場，亦未提出書狀為任何聲明或\n    陳述。\n五、兩造不爭執之事項：\n    系爭房地原屬於周益之所有，周益之於97年11月14日以買賣\n    為原因，於97年11月28日移轉登記予江梅華。\n六、本院之判斷：\n  (一)華南銀行主張凡永公司邀周益之為連帶保證人，擔保凡永公\n    司對於華南銀行之一切債務。華南銀行執有詠順公司所簽發\n    、凡永公司背書之發票日為97年11月5日、票號AD0000000、\n    付款人華信銀行左營分行、面額 115萬5000元之支票，經提\n    示後退票，周益之對華南銀行負有清償責任等語，業據其提\n    出支票正反面影本、退票理由單、保證書及授信契約書為證\n    （見原審卷第110至124頁）。華南銀行就該支票債權，嗣已\n    對詠順公司、凡永公司取得執行名義（臺灣高雄地方法院98\n    年度雄簡字第 431號判決），亦有其所提出之該判決在卷可\n    憑（見原審卷第183、184頁），堪信華南銀行此部分主張屬\n    實。而周益之為連帶保證人之保證書（見原審卷第 112頁）\n    上已載明「對  貴行將來於第一條所負之債務範圍內．．．\n    保證人願與主債務人負連帶清償之責。」，是周益之所負之\n    保證債務涵蓋凡永公司於簽立授信契約書（見原審卷第 113\n    頁）後之債務。至於保證債務於契約有特別約定時，本非不\n    得包括將來之債務，江梅華辯稱保證契約應未成立云云，並\n    無足採。又周益之雖非系爭支票之發票人或背書人，而不負\n    票據債務，但凡永公司為系爭支票之背書人，嗣後系爭支票\n    經華南銀行提示不獲兌現時，凡永公司即為華南銀行之票據\n    債務人，華南銀行依上開保證書及授信契約書之約定，自屬\n    周益之之債權人；且華南銀行對周益之另有借款債權，業據\n    其提出臺灣高雄地方法院98年度司執字第 40599號執行事件\n    之債權憑證為證（見原審卷第 168頁），足見華南銀行確為\n    周益之之債權人，要無可疑。江梅華上開所辯，核無足採。\n    至於民事訴訟法第 270條之1第3項前段固規定：當事人就其\n    主張之爭點，經依第1項第3款或前項為協議者，應受其拘束\n    。惟該條項所謂應受其拘束之爭點協議，係指當事人就其所\n    主張之爭點，經依同條第 1項第3款或第2項為協議者而言；\n    於協議前未經當事人主張之爭點，既不在協議範圍，即不受\n    協議之拘束（最高法院97年度第2421號判決參照）。本件華\n    南銀行於98年4月1日行爭點整理時，雖未主張其對周益之另\n    有前揭臺灣高雄地方法院98年度重訴字第35號民事判決所確\n    定之債權，依上揭說明，尚不受該協議之拘束。且原告於前\n    揭爭點整理及協議簡化之後提出該攻擊防禦方法，並無礙於\n    訴訟之終結，應許其提出，併予敘明。\n  (二)按表意人與相對人通謀而為虛偽意思表示者，其意思表示無\n    效，民法第87條第 1項前段定有明文。惟所謂通謀虛偽表示\n    ，係指表意人與相對人相互明知為非真意之表示而言，故表\n    意人之相對人不僅須知表意人非真意，並須就表意人非真意\n    之表示相與為非真意之合意，始為相當。在贈與或買賣契約\n    ，不能僅因契約當事人間有特殊親誼關係或價金之交付不實\n    ，即謂該贈與或買賣係通謀虛偽成立。且第三人主張表意人\n    與相對人通謀而為虛偽意思表示者，該第三人應負舉證之責\n    （最高法院51年台上字第 215號判例、86年度台上字第3865\n    號判決、48年台上字第29號判例參照）。又民事訴訟如係由\n    原告主張權利者，應先由原告負舉證之責，若原告先不能舉\n    證，以證實自己主張之事實為真實，則被告就其抗辯事實即\n    令不能舉證，或其所舉證據尚有疵累，亦應駁回原告之請求\n    （最高法院17年上字第 917號判例意旨參照）。華南銀行主\n    張江梅華與周益之就系爭房地所為之買賣，為通謀虛偽之意\n    思表示云云，為江梅華所否認，並辯稱：其與周益之間就系\n    爭房地所為之前揭買賣係屬真正，其亦付足全部價金等語。\n    依江梅華與周益之於97年11月13日所簽訂之不動產買賣契約\n    書（見原審卷第63至66頁）之記載，系爭房地之買賣價金為\n    700萬元，簽約款100萬元，約定簽約時給付、用印款 100萬\n    元，約定97年11月14日用印時給付、完稅款50萬元，預於97\n    年12月10日給付、尾款 450萬元，預於97年12月20日給付；\n    江梅華與周益之復於97年12月10日簽訂更正買賣契約書（見\n    原審卷第68頁），約定：「1.買方應付各期價金，由買方委\n    託廉喬公司或委託合作金庫以匯款方式支付之。2.賣方應收\n    各期價金，以匯款匯入賣方本人或賣方指定庚德公司（負責\n    人為賣方）方式收取之。3.付款期別（以下各期款，均因賣\n    方急用而提前支付）：簽約款100萬元，用印款100萬元，\n    以97年10月20日匯款 200萬元支付之。完稅款以97年11月\n    12日匯款48萬元、97年11月13日匯款25萬元支付之。尾款\n    以97年12月10日匯款 377萬0862元、24萬8046元、27萬1370\n    元支付之。雙方約定價金700萬元，買方已提前支付702萬\n    0278元完畢，其中 2萬0278元用以支付代書費，印花稅，契\n    稅，規費等，如有不足則由買方負擔」，其上並有買方委託\n    付款人廉喬公司、賣方委託人庚德公司蓋用之印文。至於華\n    南銀行雖主張江梅華與周益之於97年12月10日簽訂更正買賣\n    契約書時，系爭房地已辦妥所有權移轉登記，顯應係無法證\n    明有支付價金之情況下拼湊書立云云，但廉喬公司確分別於\n    97年10月20日匯款 200萬元、97年11月12日匯款48萬元、97\n    年11月13日匯款25萬元至庚德公司帳戶，有匯款單六紙在卷\n    足憑（見原審卷第69、70頁），核與更正買賣契約書記載付\n    款之情形相符。江梅華另抗辯：其借貸予廉喬公司 288萬元\n    以上，廉喬公司積欠江梅華 288萬元，周益之則積欠廉喬公\n    司 273萬元，在廉喬公司居間促成下，乃有本件買賣等語，\n    亦據其提出廉喬公司所簽發、面額合計288萬元之本票5張及\n    其合作金庫銀行活期儲蓄存款存摺明細為證（見原審卷第19\n    4至200頁），華南銀行雖否認本票之真正，但該本票確係廉\n    喬公司陳進教所簽發，業據證人陳進教於本院到庭證述明確\n    （見本院卷第77頁正面）；而廉喬公司向江梅華借款均係現\n    金（見本院卷第76頁反面），核與江梅華之合作金庫銀行活\n    期儲蓄存款存摺明細相符，足證上開本票及合作金庫銀行活\n    期儲蓄存款存摺明細均屬真正。至於證人陳進教雖證稱其是\n    以私人名義向江梅華借款，與廉喬公司簽發本票雖有未符之\n    處，但陳進教係廉喬公司負責人，其或不能確實分別公司與\n    個人間之差異，但無礙於廉喬公司所簽發之上開本票為真實\n    。是更正買賣契約書記載之付款情形，應確屬江梅華與周益\n    之間買賣價款交付之實情，華南銀行雖主張應係無法證明有\n    支付價金之情況下拼湊書立云云，尚無足採。另系爭房地原\n    由周益之設定 732萬元之最高限額抵押權予台新銀行，用以\n    擔保周益之與庚德公司向台新銀行之借款債權，此有系爭房\n    地之登記謄本在卷可憑（見原審卷第10、11頁）。江梅華另\n    辯稱：其向周益之購買系爭房地後，為給付向周益之購買系\n    爭房地之價款，分別於97年12月10日、97年12月19日以系爭\n    房屋向合作金庫銀行抵押貸款429萬元、21萬元，合計450萬\n    元，所貸得之款項由江梅華代償周益之及庚德公司向台新銀\n    行之借款，而由合作金庫銀行朝馬分行分別於97年12月10日\n    匯款24萬8046元、27萬1370元、 377萬0862元至台新銀行南\n    京東路分行，並塗銷周益之以系爭房地向台新銀行所設定之\n    抵押權等語，業據提出借款契約書、系爭房屋登記謄本等為\n    證，並有合作金庫銀行朝馬分行函文暨所檢附之放款支出傳\n    票、取款憑條等足證（見原審卷第93-98、157-164頁），應\n    堪信江梅華之上開抗辯為真實。至於江梅華匯款予合作金庫\n    銀行之時間雖在系爭房地所有權移轉予江梅華之後，但匯款\n    單上已載明「如不同意塗銷抵押權請退匯」文字，顯見該匯\n    款確係江梅華代償之事實。是合計江梅華代周益之償還以系\n    爭房地向台新銀行所為之抵押貸款金額達 429萬0278元。華\n    南銀行主張此部分還款，不能認為係由江梅華所有之資金支\n    付此不動產買賣價金云云，尚無足採。則江梅華既為合作金\n    庫銀行之債務人，日後如有不能清償貸款之情事，債權人合\n    作金庫銀行除可拍賣系爭房地外，尚可對江梅華其餘財產取\n    償，是江梅華辯稱系爭買賣並非通謀虛偽意思表示等語，並\n    非無足採信，此外華南銀行未能舉證證明系爭買賣為通謀虛\n    偽意思表示之事實，華南銀行主張江梅華與周益之間就系爭\n    房地之買賣為通謀虛偽意思表示云云，要非可採。從而華南\n    銀行先位聲明請求確認江梅華與周益之間於97年11月14日就\n    系爭房地之買賣關係不存在；暨江梅華應將系爭房地於97年\n    11月28日以買賣原因所為之所有權移轉登記塗銷，難認有據\n    ，無法准許。\n  (三)按債務人所為之有償行為，於行為時明知有損害於債權人之\n    權利者，以受益人於受益時亦知其情事者為限，債權人得聲\n    請法院撤銷之。債務人之行為非以財產為標的，或僅有害於\n    以給付特定物為標的之債權者，不適用前二項之規定。債權\n    人依第1項或第2項之規定聲請法院撤銷時，得並聲請命受益\n    人或轉得人回復原狀。但轉得人於轉得時不知有撤銷原因者\n    ，不在此限，民法第244條第2、3、4項定有明文。依此規定\n    ，債權人依民法第 244條規定，撤銷債務人所為之有償或無\n    償行為者，須為債務人所為之法律行為，而其法律行為有害\n    於債權人，且其法律行為係以財產權為目的，如為有償之法\n    律行為，債務人於行為時，須明知其行為有害於債權人，受\n    益人於受益時，亦明知其事情，始足當之（最高法院42年台\n    上字第 323號判例參照）。又債務人出賣其財產非必生減少\n    資力之結果，苟出賣之財產已獲得相當之對價，用以清償具\n    有優先受償權之債務，則一方面減少其財產，一方面減少其\n    債務，其對於普通債權人，即難謂為詐害行為；債務已屆清\n    償期，債務人就既存債務為清償者，固生減少積極財產之結\n    果，但同時亦減少其消極財產，於債務人之資力並無影響，\n    不得指為民法第 244條第1項或第2項之詐害行為（最高法院\n    51年台上字第 302號判例、55年台上字第2839號判例參照）\n    。江梅華與周益之間之買賣契約並非通謀虛偽之意思表示，\n    且江梅華與周益之間確有買賣價金之支付事實，已如上述。\n    則周益之將系爭土地移轉登記予江梅華，應屬有償行為。華\n    南銀行提出之支票退票理由單（見原審卷第 110頁）之支票\n    退票日期雖為97年11月 5日，惟華南銀行至98年間始就對凡\n    永公司行使追索權，經臺灣高雄地方法院98年 4月28日以98\n    年度雄簡字第 431號給付票款判決，此有臺灣高雄地方法院\n    98年度雄簡字第 431號給付票款宣示判決筆錄在卷足憑（見\n    原審卷第183、184頁）；且華南銀行訴請周益之、凡永公司\n    清償借款事件，臺灣高雄地方法院係於98年 2月27日以98年\n    度重訴字第35號判決華南銀行勝訴，此業經原審法院調取該\n    案卷宗無訛，則依該判決書之認定，華南銀行對周益之債權\n    為連帶保證債權，亦即周益之為凡永公司向華南銀行借款之\n    連帶保證人，而凡永公司向華南銀行所為之借款，係於97年\n    12月19日到期之本金 450萬元未為清償，全部債務始依約視\n    為到期，則江梅華不可能事先知悉周益之對華南銀行有前揭\n    債務存在。此外華南銀行並未舉證證明江梅華向周益之買受\n    系爭房地時，明知周益之積欠華南銀行債務，及周益之出售\n    系爭房地有害於華南銀行行使債權之情事。從而華南銀行備\n    位聲明以江梅華與周益之間就系爭房地之買賣損害其權利，\n    依民法第244條第2、3、4項規定請求判決撤銷江梅華與周益\n    之間於97年11月14日就系爭房地所為之買賣行為，且江梅華\n    應將系爭房地於97年11月28日以買賣原因所為之所有權移轉\n    登記塗銷，亦無理由，應予駁回。\n  (四)綜上所述，本件上訴人華南銀行主張被上訴人間買賣系爭房\n    地之行為為通謀虛偽意思表示，無效；及被上訴人間移轉系\n    爭房地所有權行為為無償行為，暨被上訴人間移轉系爭房地\n    所有權行為縱為有償行為，亦為江梅華所明知等，均不足採\n    ，被上訴人抗辯尚屬可信。是則上訴人執此主張確認江梅華\n    與周益之間於97年11月14日就系爭房地之買賣關係不存在；\n    暨江梅華應將系爭房地於97年11月28日以買賣原因所為之所\n    有權移轉登記塗銷；及請求判決撤銷江梅華與周益之間於97\n    年11月14日就系爭房地所為之買賣行為，且江梅華應將系爭\n    房地於97年11月28日以買賣原因所為之所有權移轉登記塗銷\n    云云，自屬無據，不應准許。原審為上訴人敗訴之判決，並\n    無不合。上訴意旨指摘原判決不當，求予廢棄改判，為無理\n    由，應予駁回。\n七、本件事證已臻明確，兩造其餘攻擊防禦方法，核與判決結果\n    不生影響，爰不逐一論述。\n八、據上論結，本件上訴為無理由，依民事訴訟法第449條第1項\n    、第78條，判決如主文。"
  },
  "characters": {
    "judges": [
      "陳照德",
      "朱樑",
      "李平勳"
    ],
    "prosecutors": [

    ],
    "lawyers": [
      "林政德",
      "黃英傑"
    ],
    "clerks": [
      "江丞晏"
    ],
    "plaintiffs": [

    ],
    "defendants": [

    ],
    "prosecutor_office": [

    ],
    "creditors": [

    ],
    "debtors": [

    ],
    "judicial_associate_officer": [

    ]
  },
  "adjudged_at": "2010-01-05",
  "created_at": "2016-01-05 15:07:47",
  "updated_at": "2016-01-05 15:07:47"
}