{
  "identify": "TNH-98-聲-1009-20100104-1",
  "court": {
    "name": "臺灣高等法院",
    "code": "TNH"
  },
  "division": {
    "name": "刑事",
    "code": "M"
  },
  "year": 98,
  "word": "聲",
  "number": "1009",
  "jcheck": "1",
  "reason": "假釋中付保護管束",
  "content": "臺灣高等法院臺南分院刑事裁定          98年度聲字第1009號\n聲  請  人  臺灣高等法院臺南分院檢察署檢察官\n受  刑  人  甲○○\n            （現於臺灣高雄女子監獄執行中）\n上列受刑人因假釋中付保護管束案件，聲請人聲請交付保護管束\n（聲請案號：98年度執聲字第981號），本院裁定如下：\n    主  文\n甲○○假釋中付保護管束。\n    理  由\n一、聲請意旨略以：受刑人甲○○前因偽造文書等案件，判決確\n    定後，移送執行。茲聲請人以受刑人業經法務部於民國98年\n    12 月25日以法矯司字第0980907649號核准假釋，爰聲請於\n    其假釋中付保護管束等情。\n二、本院審核有關文件，認聲請為正當，爰依刑事訴訟法第481\n    條第1項，刑法第93條第2項、第96條但書，裁定如主文。\n中    華    民    國    99    年    1     月    4     日\n                  刑事第三庭    審判長法  官    陳義仲\n                                      法  官    宋明中\n                                      法  官    蔡勝雄\n以上正本證明與原本無異。\n如不服本裁定，應於收受本裁定後五日內向本院提出抗告狀。\n                                      書記官    汪姿秀\n中    華    民    國    99    年    1     月    4     日",
  "structure": {
    "main": "甲○○假釋中付保護管束。",
    "reason": "一、聲請意旨略以：受刑人甲○○前因偽造文書等案件，判決確\n    定後，移送執行。茲聲請人以受刑人業經法務部於民國98年\n    12 月25日以法矯司字第0980907649號核准假釋，爰聲請於\n    其假釋中付保護管束等情。\n二、本院審核有關文件，認聲請為正當，爰依刑事訴訟法第481\n    條第1項，刑法第93條第2項、第96條但書，裁定如主文。"
  },
  "characters": {
    "judges": [
      "陳義仲",
      "宋明中",
      "蔡勝雄"
    ],
    "prosecutors": [

    ],
    "lawyers": [

    ],
    "clerks": [
      "汪姿秀"
    ],
    "plaintiffs": [

    ],
    "defendants": [

    ],
    "prosecutor_office": [
      "臺灣高等法院臺南分院檢察署檢察官"
    ],
    "creditors": [

    ],
    "debtors": [

    ],
    "judicial_associate_officer": [

    ]
  },
  "adjudged_at": "2010-01-04",
  "created_at": "2016-01-05 14:36:46",
  "updated_at": "2016-01-05 14:36:46"
}