{
  "identify": "TNH-98-上易-640-20100105-2",
  "court": {
    "name": "臺灣高等法院",
    "code": "TNH"
  },
  "division": {
    "name": "刑事",
    "code": "M"
  },
  "year": 98,
  "word": "上易",
  "number": "640",
  "jcheck": "2",
  "reason": "詐欺等",
  "content": "臺灣高等法院臺南分院刑事判決         98年度上易字第640號\n上  訴  人  臺灣雲林地方法院檢察署檢察官\n上  訴  人\n即  被  告  甲○○\n上列上訴人因被告詐欺等案件，不服臺灣雲林地方法院98年度易\n字第313號中華民國98年7月22日第一審判決（起訴案號：臺灣雲\n林地方法院檢察署97年度偵字第5704、98年度偵字第1757、1895\n、2345、2440、2481號），提起上訴，本院判決如下：\n    主  文\n上訴駁回。\n    事  實\n一、甲○○知悉金融機構開立存款帳戶並無積極資格之限制，且\n    收集人頭帳戶用以詐騙被害人匯款之社會現象層出不窮，因\n    此能預見若將金融機構帳戶存摺、金融卡及密碼交付他人使\n    用，極可能因此供不法詐騙集團份子施用詐術使他人受騙匯\n    入款項，再加以提領運用，猶基於幫助他人從事詐欺取財之\n    不確定故意，見報紙刊登收購帳戶廣告後，於民國97年5 月\n    18日某時許，在雲林縣國道1 號斗南交流道附近之「空軍1\n    號」客運站，將其不知情胞妹孫敏芳（69年10月4日生，另\n    經檢察官為不起訴處分確定）先前向華南商業銀行斗六分行\n    申辦帳號為000000000000號帳號之存摺、提款卡及密碼委由\n    不知情之「空軍1號」之已成年之司機交付與姓名年籍不詳\n    、綽號「張經理」之成年男子，而「張經理」取得上開存摺\n    等物後，旋於同日亦委由「空軍1號」客運某不知情之已成\n    年之司機，在斗南交流道附近，交付新臺幣（下同）6千元\n    與甲○○。嗣該詐騙集團成員取得本案帳戶資料後，即基於\n    意圖為自己不法所有之犯意聯絡，先由自稱為奇摩拍賣網站\n    賣家之人於97年5月19日18時46分許，撥打電話與乙○○（\n    76年4月9日生），佯稱誤將乙○○某次交易之付款方式設定\n    為按月定期扣款，必需依稍後之華南銀行人員指示，始能取\n    消設定，同日18時56分許，乃有自稱為華南銀行客服員之人\n    撥打電話與乙○○，要求乙○○需依指示至自動櫃員機操作\n    以解除設定，乙○○因此陷於錯誤，前往桃園縣龜山鄉○○\n    街2號之豐美郵局，依指示操作自動櫃員機，遂於同日19時\n    44分許、49 分許、21時40分許、47分許，先後匯款21,019\n    元、2,163元、9,983元、12,859元，合計46,024元入孫敏芳\n    上開帳戶。\n    嗣乙○○發覺有異，始悉受騙而報警循線查獲上情。\n二、甲○○為丙○○（71年11月27日生）之夫，2人間具有家庭\n    暴力防治法第3條第1款所定之家庭成員關係。甲○○前因家\n    庭暴力行為，經原審法院於96年12月27日以96年度家護字第\n    502號案件核發民事通常保護令，裁定甲○○不得對丙○○\n    實施身體或精神上不法侵害之行為；不得直接或間接對於丙\n    ○○為騷擾之行為。該保護令有效期間為1年，嗣由原審法\n    院於97年10月30日以97年度家護聲字第36號裁定延長該保護\n    令有效期間1年。詎甲○○於知悉上開保護令後，竟基於違\n    反保護令之個別犯意，而為下列行為：\n  (一)甲○○自97年12月18日16時許起至同年月20日16時許止，在\n    不詳處所，以其所有門號為0000000000號行動電話及00-000\n    0000號室內電話，多次撥打丙○○上班地點即雲林縣虎尾鎮\n    ○○路○ 段266 號「婦安婦產科」之00-0000000號室內電話\n    ，並以「幹你娘」（台語）等不雅言詞辱罵丙○○，藉此對\n    丙○○實施精神上不法之侵害及騷擾丙○○，而違反上開保\n    護令裁定。\n  (二)甲○○於98年1 月15日上午11時55分許及同日12時27分許，\n    以上開0000000000號行動電話，傳送內容為「我不怕你不接\n    不回，我就是不可能讓你安心上班」、「你不把事情講清楚\n    ，我是不可能善罷甘休」之簡訊，至丙○○所用之00000000\n    00號行動電話，以此方式對丙○○實施精神上不法之侵害及\n    騷擾丙○○，而違反上開保護令裁定。\n  (三)甲○○於98年4 月1 日15時30分許、同年月2 日，在不詳處\n    所，以公共電話密集撥打上開丙○○工作地點即「婦安婦產\n    科」電話，使丙○○同事廖敏秀不斷接聽，並要求廖敏秀喚\n    丙○○親自接聽；或由丙○○接聽後，向丙○○略稱：「幹\n    你娘，我叫你聽電話是給你亂喔」、「幹你娘雞歪，我若安\n    靜，我不就是卒仔，我不可能讓你平靜上班」、「你去給人\n    家幹」、「你是搬回來讓人幹啊」、「我不可能讓你平靜上\n    班，電話掛掉我會一直打，打到明天早上上班一直打，幹你\n    娘，你回來要相幹啊」、「我一定一直給你打，亂到讓人知\n    道」、「我電話卡買5 張500 元等你，我就是要讓你別做」\n    、「你娘雞歪，你放我一個人在家可以嗎，你不回來，我就\n    一直給你亂」、「你回去給人幹，你去用保護令啊，我不怕\n    」、「瘋雞歪，瘋女人，你準備接電話就沒錯」、「你這個\n    瘋女人去討客兄」等語，以此方式對丙○○實施精神上不法\n    之侵害及騷擾丙○○，而違反上開保護令裁定。\n  (四)甲○○於98年5 月6 日20時50分許，騎乘丙○○名下之車牌\n    號碼USV-808 號輕型機車，前往雲林縣虎尾鎮埒內250-1 號\n    丙○○住處，甲○○因欲變賣該部機車，欲向丙○○拿取機\n    車證件辦理過戶，丙○○未予應允，甲○○即在該住處外大\n    聲吵鬧，而以此方式對丙○○實施精神上不法之侵害及騷擾\n    丙○○，違反上開保護令裁定。\n  (五)甲○○於98年5 月14日凌晨零時40分許，前往丙○○上開住\n    處外，不斷呼喊丙○○名字、不願離去，並向丙○○表示要\n    在該處坐到天亮，以此方式對丙○○實施精神上不法之侵害\n    及騷擾丙○○，違反上開保護令裁定。\n三、案經乙○○訴由雲林縣警察局斗六分局及經丙○○訴由雲林\n    縣警察局虎尾分局報告臺灣雲林地方法院檢察署檢察官偵查\n    起訴。\n    理  由\n一、認定被告涉犯上開犯罪事實所憑之證據如下：\n  (一)事實一（即幫助詐欺取財罪）部分：\n  1.被告經合法通知未到庭，惟其於警詢、偵查中及原審審理對\n    於上揭事實已坦承不諱，核與證人即被害人丙○○於警詢及\n    偵查中證述之情節相符，復有郵政自動櫃員機交易明細表4\n    紙、華南商業銀行斗六分行97年6月11日（97）華斗字第204\n    號函暨所附孫敏芳開戶資料、華南商業銀行斗六分行97 年\n    11月28日（97）華斗字第423號函暨所附孫敏芳上開帳戶金\n    融卡發行登記事故資料查詢單、交易往來明細表在卷可稽。\n    足見被告於原審之自白，顯與上開積極證據相符，堪予採信\n    。\n  2.次按金融機構之帳戶存摺、提款卡等相關資料事關個人財產\n    權益之保障，其專有性甚高，除非本人或與本人親密關係者\n    ，難認有何理由可自由流通使用該存摺、提款卡，一般人均\n    有妥為保管及防止他人任意使用之認識，縱特殊情況偶需交\n    付他人使用，亦必深入瞭解用途及合理性，始予提供，且該\n    等專有物品如落入不明人士手中，而未加以闡明正常用途，\n    極易被利用為與財產有關之犯罪工具，此為吾人依一般生活\n    認知所易於體察之常識。況近年來新聞媒體，對於不肖犯罪\n    集團常利用人頭帳戶，作為財產犯罪工具，藉此逃避檢警查\n    緝之情事，亦多所報導，政府亦大力宣導，督促民眾注意，\n    主管機關甚至限制以提款卡轉帳之金額，是交付帳戶資料予\n    非親非故之人，該取得帳戶資料之人應係為謀非正當資金進\n    出，而隱瞞其資金流程及行為人身分曝光之不法使用，幾乎\n    已成為人盡皆知之犯罪手法。以被告當時近32歲及自承為國\n    中畢業之教育程度，對上開事項應知悉甚稔，卻仍執意將胞\n    妹孫敏芳之帳戶提供不詳之人使用而賺取對價，顯見其能預\n    見該帳戶將遭用之於詐欺取財犯罪，是其主觀上不乏幫助他\n    人詐欺取財犯罪之不確定故意甚明。\n  3.綜上所述，本件事證明確，被告確有幫助詐欺取財之犯行，\n    應堪認定。\n  (二)事實二（即違反保護令罪）部分：\n  1.被告經合法通知未到庭，惟其於警詢、偵查中原審審理時已\n    自承上揭事實，核與證人即被害人丙○○於警詢及偵查中之\n    證述、及證人即丙○○「婦安婦產科」同事廖敏秀於警詢中\n    之證述情節相符，另有雲林縣警察局虎尾分局處理家庭暴力\n    與兒少保護案件調查紀錄（通報表）、手機簡訊翻拍照片2\n    張、原審法院96年度家護字第502號、97年度家護聲字第36\n    號民事通常保護令裁定等在卷可稽，並經台灣雲林地方法院\n    檢察署檢察官勘驗被告98年4月1日、2日電話錄音查明屬實\n    ，有勘驗筆錄可參。足見被告於原審之自白，顯與上開積極\n    證據相符，堪予採信。\n  2.綜上所述，本件事證明確，被告有違反保護令罪之犯行，應\n    堪認定。\n二、論罪科刑之理由：\n  (一)\n  1.按刑法上之幫助犯，係對於犯罪與正犯有共同之認識，而以\n    幫助之意思，對於正犯資以助力，而未參與實施犯罪之行為\n    者而言（最高法院75年度台上字第1509號、88年度台上字第\n    1270號判決亦同此意旨）。是如未參與實施犯罪構成要件之\n    行為，而係出於幫助之意思提供助力，即屬幫助犯，而非共\n    同正犯。被告就事實一部分，將其胞妹孫敏芳所有前揭帳戶\n    之存摺、提款卡及密碼提供與「張經理」，致遭詐騙集團利\n    用作為詐取財物之匯款帳戶，乃屬基於幫助他人詐欺取財之\n    不確定故意，而為詐欺取財罪構成要件以外之幫助行為。核\n    其此部分之所為，係犯刑法第30條第1項前段、第339條第1\n    項之幫助詐欺取財罪。又被告所為係詐欺取財罪之幫助犯，\n    依刑法第30條第2項規定，按正犯之刑減輕之。又被告委由\n    不知情之已成年之「空軍1號」客運司機轉交前揭帳戶之存\n    摺、提款卡及密碼，為間接正犯。\n  2.按幫助犯係從犯，係從屬於正犯而成立。刑法第28條之共同\n    正犯，係指二人以上共同實行犯罪之行為者而言，幫助他人\n    犯罪，並非實施正犯，在事實上雖有二人以上共同幫助犯罪\n    ，要亦各負幫助罪責，而無適用該條之餘地。刑法上既無「\n    共同幫助」之情，當亦無「幫助共同」之可言。幫助一人為\n    幫助，幫助二人、三人仍為幫助（95年度台上字第6767號判\n    決意旨參照）。據此，本案爰不另於主文項下載明「幫助共\n    同」，併此敘明。\n  (二)\n  1.按家庭暴力防治法所稱家庭暴力，係指家庭成員間實施身體\n    或精神上不法侵害之行為；又騷擾，係指任何打擾、警告、\n    嘲弄或辱罵他人之言詞、動作或製造使人心生畏怖情境之行\n    為，家庭暴力防治法第2條第1、3款分別定有明文。又通常\n    保護令係依家庭暴力防治法第14條第1項規定所為之裁定，\n    雖有違反上開保護令依同法第61條第1款至第5款數款應處罰\n    之裁定情形，仍應認係1個違反保護令罪。查被告與丙○○\n    為夫妻，為被告及丙○○所是認，二人具有家庭暴力防治法\n    第3條第1款之家庭成員關係。故核被告就事實二部分之所為\n    ，係犯家庭暴力防治法第61條第1款、第2款之違反保護令罪\n    。公訴意旨認被告所為僅有同條第2款禁止騷擾之違反保護\n    令罪，惟被告以上開密集撥打電話或以言詞辱罵或在被害人\n    住處門外大聲吵鬧、不願離去方式騷擾被害人，依前揭說明\n    ，亦屬對家庭成員實施精神上不法侵害之行為，核屬同條第\n    1 款之禁止實施家庭暴力。公訴意旨雖漏未論列家庭暴力防\n    治法第61條第1款規定，而有未洽，惟其於犯罪事實欄既已\n    敘明，本院自得予以審理。\n  2.按接續犯係一個犯罪行為，接續不斷進行，而侵害同一法益\n    ，其各個動作，乃組成整個犯罪行為之一部，以促成其犯罪\n    結果之發生。被告於事實二(一)、(二)、(三)於同日、接連2日、3\n    日均多次撥打電話至「婦安婦產科」以不雅言詞辱罵丙○○\n    之行為，乃係於密切接近之時間內為之，侵害同一法益，此\n    部分均應係出於一個犯意下所為，為接續犯，應論以一罪。\n    而被告所犯事實二(一)至(五)部分犯行，均係經被害人報案後再\n    犯，顯見被告皆係另行起意，犯罪時間短者相距1個月，長\n    者相距3個月，雖侵害同一法益，惟每一前行為與次行為，\n    依一般社會健全觀念，在時間差距上，可以分開，而非同時\n    ，在刑法評價上，各具獨立性，皆可單獨成罪，與接續犯之\n    要件難謂相符，自應予分論併罰。公訴意旨認被告上揭數次\n    違反保護令之行為，時空密接，犯意單一，侵害同一法益，\n    為接續犯，應論以一罪，尚有未合。\n  (三)被告所犯幫助詐欺取財罪與5次違反保護令罪，犯意個別，\n    行為互異，應分論併罰。\n三、維持原判之理由\n  (一)原審以被告罪證明確，因予適用家庭暴力防治法第61條第1\n    款、第2款，刑法第30條第1項前段、第2項、第339條第1項\n    、第51條第5款、第41條第1項前段，刑法施行法第1條之1第\n    1項、第2項前段之規定，並審酌被告提供帳戶與他人作為不\n    法使用，助長犯罪之猖獗，影響社會正常經濟交易安全，增\n    加被害人尋求救濟及偵查犯罪之困難，又明知收受原審法院\n    民事通常保護令後，依該保護令不得對被害人為精神上不法\n    之侵害及騷擾行為，竟仍漠視上開保護令內容，多次以撥打\n    電話、傳送簡訊及前往被害人住處外等方式對被害人實施精\n    神上不法之侵害及騷擾，顯然漠視法律，甚者，被告前於97\n    年12月17日亦因傷害被害人之違反保護令案件，經原審法院\n    以98年度虎簡字第43號判處有期徒刑3 月，緩刑2年，緩刑\n    期間付保護管束（被告於97年12月17日經警查獲後，於翌日\n    即同年月18日再次違反保護令即事實二(一)部分，然被告前次\n    已因遭警查獲而阻絕其犯意，之後其違反保護令行為應認係\n    另行起意，核與前次無關，不為既判力所及），此有臺灣高\n    等法院被告前案紀錄表、聲請簡易判決處刑書附卷可稽，被\n    告卻不知珍惜機會，再次觸犯相同之罪，顯然被告法治觀念\n    欠缺，惟念其犯後坦承犯行，尚能即時知錯，因涉幫助詐欺\n    取財罪之犯罪所得為6千元等一切情狀，分別量處有期徒刑\n    肆月，並依司法院釋字第366號、第662號解釋意旨，就本案\n    被告所犯上開6罪之宣告刑定其應執行之刑有期徒刑1年2 月\n    ，另諭知易科罰金之折算標準。經核原判決認事用法，並無\n    不合，量刑亦稱妥適。\n  (二)\n  1.被告上訴意旨略以：伊將孫敏芳之帳戶販賣予他人，孫敏芳\n    均屬知情，另告訴人丙○○事後已原諒為由，請求減輕其刑\n    云云，其上訴並無理由，應予駁回。\n  2.檢察官上訴意旨略以：併辦之98年4月20日違反保護令犯行\n    ，因被告所為違反保護令之騷擾行為，係密切接近之時地實\n    施，侵害同一之法益，應屬接續犯，顯在起訴範圍內，被告\n    係接續於密接時、地，與起訴之事實顯屬接續犯關係而為實\n    質上一罪，應為起訴效力所及，原審未予一併審理，顯有已\n    受請求之事項未予判決之違法云云，因而指摘原判決認定事\n    實適用法律不當，惟查，檢察官聲請併辦之被告於98年4月\n    20 日違反保護令犯行，如後所述，與起訴之事實顯非屬接\n    續犯關係，並未在起訴範圍內，非起訴效力所及，原審未予\n    一併審理，並無不當，詳如後述，檢察官上開所指尚無足採\n    ，從而其上訴並無理由，應予駁回。\n四、另臺灣雲林地方法院檢察署98年度偵字第3739號聲請併辦意\n    旨略以：被告甲○○於98年4月20日上午11時許，在不詳處\n    所，以公共電話不斷撥打上開丙○○工作地點即「婦安婦產\n    科」電話，令丙○○無法繼續上班之方式，直接、間接騷擾\n    丙○○，迫使丙○○因而離職，而違反上開保護令裁定。此\n    部分與被告上揭經起訴之違反保護令罪，有接續犯之關係，\n    為法律上之同一案件，依審判不可分原則，應為起訴效力所\n    及，爰檢送案卷請求併案審理等語。經查：本案被告經起訴\n    判決有罪部分之犯罪時間，各為自97年12月18日起至同年月\n    20 日止、98年1月15日、同年4月1、2日、同年5月6日及同\n    年5 月14日，核與檢察官聲請併案審理部分之犯罪時間即98\n    年4 月20日，犯罪時間相差甚遠，在刑法評價上，各具獨立\n    性，皆可單獨成罪，且被告每次違反保護令後，被害人均報\n    警處理，有各該次警詢筆錄可佐，顯見被告為警查獲後已中\n    斷其犯意，該次應屬另行起意至明，核與起訴部分無實質上\n    一罪關係，即非本案起訴效力所及，本院自無從併予審理，\n    應退由檢察官另為適法之處理。\n五、被告經合法傳喚，無正當之理由未於審判期日到庭，爰不待\n    其陳述，逕行判決。\n六、據上論結，應依刑事訴訟法第368條、第371條，判決如主文\n    。\n本案經檢察官羅清溪到庭執行職務。\n中    華    民    國    99    年    1     月    5     日\n                  刑事第四庭    審判長法  官  吳志誠\n                                      法  官  彭喜有\n                                      法  官  羅心芳\n以上正本證明與原本無異。\n不得上訴。\n                                      書記官  蔡振豐\n中    華    民    國    99    年    1     月    6     日\n附錄本判決論罪科刑法條全文：\n家庭暴力防治法第61條：\n違反法院依第14條第1 項、第16條第3 項所為之下列裁定者，為\n本法所稱違反保護令罪，處3 年以下有期徒刑、拘役或科或併科\n新臺幣100,000元以下罰金：\n一、禁止實施家庭暴力。\n二、禁止騷擾、接觸、跟蹤、通話、通信或其他非必要之聯絡行\n    為。\n三、遷出住居所。\n四、遠離住居所、工作場所、學校或其他特定場所。\n五、完成加害人處遇計畫。\n中華民國刑法第339條\n意圖為自己或第三人不法之所有，以詐術使人將本人或第三人之\n物交付者，處5 年以下有期徒刑、拘役或科或併科1,000 元以下\n罰金。\n以前項方法得財產上不法之利益或使第三人得之者，亦同。\n前2 項之未遂犯罰之。",
  "structure": {
    "main": "上訴駁回。",
    "fact": "一、甲○○知悉金融機構開立存款帳戶並無積極資格之限制，且\n    收集人頭帳戶用以詐騙被害人匯款之社會現象層出不窮，因\n    此能預見若將金融機構帳戶存摺、金融卡及密碼交付他人使\n    用，極可能因此供不法詐騙集團份子施用詐術使他人受騙匯\n    入款項，再加以提領運用，猶基於幫助他人從事詐欺取財之\n    不確定故意，見報紙刊登收購帳戶廣告後，於民國97年5 月\n    18日某時許，在雲林縣國道1 號斗南交流道附近之「空軍1\n    號」客運站，將其不知情胞妹孫敏芳（69年10月4日生，另\n    經檢察官為不起訴處分確定）先前向華南商業銀行斗六分行\n    申辦帳號為000000000000號帳號之存摺、提款卡及密碼委由\n    不知情之「空軍1號」之已成年之司機交付與姓名年籍不詳\n    、綽號「張經理」之成年男子，而「張經理」取得上開存摺\n    等物後，旋於同日亦委由「空軍1號」客運某不知情之已成\n    年之司機，在斗南交流道附近，交付新臺幣（下同）6千元\n    與甲○○。嗣該詐騙集團成員取得本案帳戶資料後，即基於\n    意圖為自己不法所有之犯意聯絡，先由自稱為奇摩拍賣網站\n    賣家之人於97年5月19日18時46分許，撥打電話與乙○○（\n    76年4月9日生），佯稱誤將乙○○某次交易之付款方式設定\n    為按月定期扣款，必需依稍後之華南銀行人員指示，始能取\n    消設定，同日18時56分許，乃有自稱為華南銀行客服員之人\n    撥打電話與乙○○，要求乙○○需依指示至自動櫃員機操作\n    以解除設定，乙○○因此陷於錯誤，前往桃園縣龜山鄉○○\n    街2號之豐美郵局，依指示操作自動櫃員機，遂於同日19時\n    44分許、49 分許、21時40分許、47分許，先後匯款21,019\n    元、2,163元、9,983元、12,859元，合計46,024元入孫敏芳\n    上開帳戶。\n    嗣乙○○發覺有異，始悉受騙而報警循線查獲上情。\n二、甲○○為丙○○（71年11月27日生）之夫，2人間具有家庭\n    暴力防治法第3條第1款所定之家庭成員關係。甲○○前因家\n    庭暴力行為，經原審法院於96年12月27日以96年度家護字第\n    502號案件核發民事通常保護令，裁定甲○○不得對丙○○\n    實施身體或精神上不法侵害之行為；不得直接或間接對於丙\n    ○○為騷擾之行為。該保護令有效期間為1年，嗣由原審法\n    院於97年10月30日以97年度家護聲字第36號裁定延長該保護\n    令有效期間1年。詎甲○○於知悉上開保護令後，竟基於違\n    反保護令之個別犯意，而為下列行為：\n  (一)甲○○自97年12月18日16時許起至同年月20日16時許止，在\n    不詳處所，以其所有門號為0000000000號行動電話及00-000\n    0000號室內電話，多次撥打丙○○上班地點即雲林縣虎尾鎮\n    ○○路○ 段266 號「婦安婦產科」之00-0000000號室內電話\n    ，並以「幹你娘」（台語）等不雅言詞辱罵丙○○，藉此對\n    丙○○實施精神上不法之侵害及騷擾丙○○，而違反上開保\n    護令裁定。\n  (二)甲○○於98年1 月15日上午11時55分許及同日12時27分許，\n    以上開0000000000號行動電話，傳送內容為「我不怕你不接\n    不回，我就是不可能讓你安心上班」、「你不把事情講清楚\n    ，我是不可能善罷甘休」之簡訊，至丙○○所用之00000000\n    00號行動電話，以此方式對丙○○實施精神上不法之侵害及\n    騷擾丙○○，而違反上開保護令裁定。\n  (三)甲○○於98年4 月1 日15時30分許、同年月2 日，在不詳處\n    所，以公共電話密集撥打上開丙○○工作地點即「婦安婦產\n    科」電話，使丙○○同事廖敏秀不斷接聽，並要求廖敏秀喚\n    丙○○親自接聽；或由丙○○接聽後，向丙○○略稱：「幹\n    你娘，我叫你聽電話是給你亂喔」、「幹你娘雞歪，我若安\n    靜，我不就是卒仔，我不可能讓你平靜上班」、「你去給人\n    家幹」、「你是搬回來讓人幹啊」、「我不可能讓你平靜上\n    班，電話掛掉我會一直打，打到明天早上上班一直打，幹你\n    娘，你回來要相幹啊」、「我一定一直給你打，亂到讓人知\n    道」、「我電話卡買5 張500 元等你，我就是要讓你別做」\n    、「你娘雞歪，你放我一個人在家可以嗎，你不回來，我就\n    一直給你亂」、「你回去給人幹，你去用保護令啊，我不怕\n    」、「瘋雞歪，瘋女人，你準備接電話就沒錯」、「你這個\n    瘋女人去討客兄」等語，以此方式對丙○○實施精神上不法\n    之侵害及騷擾丙○○，而違反上開保護令裁定。\n  (四)甲○○於98年5 月6 日20時50分許，騎乘丙○○名下之車牌\n    號碼USV-808 號輕型機車，前往雲林縣虎尾鎮埒內250-1 號\n    丙○○住處，甲○○因欲變賣該部機車，欲向丙○○拿取機\n    車證件辦理過戶，丙○○未予應允，甲○○即在該住處外大\n    聲吵鬧，而以此方式對丙○○實施精神上不法之侵害及騷擾\n    丙○○，違反上開保護令裁定。\n  (五)甲○○於98年5 月14日凌晨零時40分許，前往丙○○上開住\n    處外，不斷呼喊丙○○名字、不願離去，並向丙○○表示要\n    在該處坐到天亮，以此方式對丙○○實施精神上不法之侵害\n    及騷擾丙○○，違反上開保護令裁定。\n三、案經乙○○訴由雲林縣警察局斗六分局及經丙○○訴由雲林\n    縣警察局虎尾分局報告臺灣雲林地方法院檢察署檢察官偵查\n    起訴。",
    "reason": "一、認定被告涉犯上開犯罪事實所憑之證據如下：\n  (一)事實一（即幫助詐欺取財罪）部分：\n  1.被告經合法通知未到庭，惟其於警詢、偵查中及原審審理對\n    於上揭事實已坦承不諱，核與證人即被害人丙○○於警詢及\n    偵查中證述之情節相符，復有郵政自動櫃員機交易明細表4\n    紙、華南商業銀行斗六分行97年6月11日（97）華斗字第204\n    號函暨所附孫敏芳開戶資料、華南商業銀行斗六分行97 年\n    11月28日（97）華斗字第423號函暨所附孫敏芳上開帳戶金\n    融卡發行登記事故資料查詢單、交易往來明細表在卷可稽。\n    足見被告於原審之自白，顯與上開積極證據相符，堪予採信\n    。\n  2.次按金融機構之帳戶存摺、提款卡等相關資料事關個人財產\n    權益之保障，其專有性甚高，除非本人或與本人親密關係者\n    ，難認有何理由可自由流通使用該存摺、提款卡，一般人均\n    有妥為保管及防止他人任意使用之認識，縱特殊情況偶需交\n    付他人使用，亦必深入瞭解用途及合理性，始予提供，且該\n    等專有物品如落入不明人士手中，而未加以闡明正常用途，\n    極易被利用為與財產有關之犯罪工具，此為吾人依一般生活\n    認知所易於體察之常識。況近年來新聞媒體，對於不肖犯罪\n    集團常利用人頭帳戶，作為財產犯罪工具，藉此逃避檢警查\n    緝之情事，亦多所報導，政府亦大力宣導，督促民眾注意，\n    主管機關甚至限制以提款卡轉帳之金額，是交付帳戶資料予\n    非親非故之人，該取得帳戶資料之人應係為謀非正當資金進\n    出，而隱瞞其資金流程及行為人身分曝光之不法使用，幾乎\n    已成為人盡皆知之犯罪手法。以被告當時近32歲及自承為國\n    中畢業之教育程度，對上開事項應知悉甚稔，卻仍執意將胞\n    妹孫敏芳之帳戶提供不詳之人使用而賺取對價，顯見其能預\n    見該帳戶將遭用之於詐欺取財犯罪，是其主觀上不乏幫助他\n    人詐欺取財犯罪之不確定故意甚明。\n  3.綜上所述，本件事證明確，被告確有幫助詐欺取財之犯行，\n    應堪認定。\n  (二)事實二（即違反保護令罪）部分：\n  1.被告經合法通知未到庭，惟其於警詢、偵查中原審審理時已\n    自承上揭事實，核與證人即被害人丙○○於警詢及偵查中之\n    證述、及證人即丙○○「婦安婦產科」同事廖敏秀於警詢中\n    之證述情節相符，另有雲林縣警察局虎尾分局處理家庭暴力\n    與兒少保護案件調查紀錄（通報表）、手機簡訊翻拍照片2\n    張、原審法院96年度家護字第502號、97年度家護聲字第36\n    號民事通常保護令裁定等在卷可稽，並經台灣雲林地方法院\n    檢察署檢察官勘驗被告98年4月1日、2日電話錄音查明屬實\n    ，有勘驗筆錄可參。足見被告於原審之自白，顯與上開積極\n    證據相符，堪予採信。\n  2.綜上所述，本件事證明確，被告有違反保護令罪之犯行，應\n    堪認定。\n二、論罪科刑之理由：\n  (一)\n  1.按刑法上之幫助犯，係對於犯罪與正犯有共同之認識，而以\n    幫助之意思，對於正犯資以助力，而未參與實施犯罪之行為\n    者而言（最高法院75年度台上字第1509號、88年度台上字第\n    1270號判決亦同此意旨）。是如未參與實施犯罪構成要件之\n    行為，而係出於幫助之意思提供助力，即屬幫助犯，而非共\n    同正犯。被告就事實一部分，將其胞妹孫敏芳所有前揭帳戶\n    之存摺、提款卡及密碼提供與「張經理」，致遭詐騙集團利\n    用作為詐取財物之匯款帳戶，乃屬基於幫助他人詐欺取財之\n    不確定故意，而為詐欺取財罪構成要件以外之幫助行為。核\n    其此部分之所為，係犯刑法第30條第1項前段、第339條第1\n    項之幫助詐欺取財罪。又被告所為係詐欺取財罪之幫助犯，\n    依刑法第30條第2項規定，按正犯之刑減輕之。又被告委由\n    不知情之已成年之「空軍1號」客運司機轉交前揭帳戶之存\n    摺、提款卡及密碼，為間接正犯。\n  2.按幫助犯係從犯，係從屬於正犯而成立。刑法第28條之共同\n    正犯，係指二人以上共同實行犯罪之行為者而言，幫助他人\n    犯罪，並非實施正犯，在事實上雖有二人以上共同幫助犯罪\n    ，要亦各負幫助罪責，而無適用該條之餘地。刑法上既無「\n    共同幫助」之情，當亦無「幫助共同」之可言。幫助一人為\n    幫助，幫助二人、三人仍為幫助（95年度台上字第6767號判\n    決意旨參照）。據此，本案爰不另於主文項下載明「幫助共\n    同」，併此敘明。\n  (二)\n  1.按家庭暴力防治法所稱家庭暴力，係指家庭成員間實施身體\n    或精神上不法侵害之行為；又騷擾，係指任何打擾、警告、\n    嘲弄或辱罵他人之言詞、動作或製造使人心生畏怖情境之行\n    為，家庭暴力防治法第2條第1、3款分別定有明文。又通常\n    保護令係依家庭暴力防治法第14條第1項規定所為之裁定，\n    雖有違反上開保護令依同法第61條第1款至第5款數款應處罰\n    之裁定情形，仍應認係1個違反保護令罪。查被告與丙○○\n    為夫妻，為被告及丙○○所是認，二人具有家庭暴力防治法\n    第3條第1款之家庭成員關係。故核被告就事實二部分之所為\n    ，係犯家庭暴力防治法第61條第1款、第2款之違反保護令罪\n    。公訴意旨認被告所為僅有同條第2款禁止騷擾之違反保護\n    令罪，惟被告以上開密集撥打電話或以言詞辱罵或在被害人\n    住處門外大聲吵鬧、不願離去方式騷擾被害人，依前揭說明\n    ，亦屬對家庭成員實施精神上不法侵害之行為，核屬同條第\n    1 款之禁止實施家庭暴力。公訴意旨雖漏未論列家庭暴力防\n    治法第61條第1款規定，而有未洽，惟其於犯罪事實欄既已\n    敘明，本院自得予以審理。\n  2.按接續犯係一個犯罪行為，接續不斷進行，而侵害同一法益\n    ，其各個動作，乃組成整個犯罪行為之一部，以促成其犯罪\n    結果之發生。被告於事實二(一)、(二)、(三)於同日、接連2日、3\n    日均多次撥打電話至「婦安婦產科」以不雅言詞辱罵丙○○\n    之行為，乃係於密切接近之時間內為之，侵害同一法益，此\n    部分均應係出於一個犯意下所為，為接續犯，應論以一罪。\n    而被告所犯事實二(一)至(五)部分犯行，均係經被害人報案後再\n    犯，顯見被告皆係另行起意，犯罪時間短者相距1個月，長\n    者相距3個月，雖侵害同一法益，惟每一前行為與次行為，\n    依一般社會健全觀念，在時間差距上，可以分開，而非同時\n    ，在刑法評價上，各具獨立性，皆可單獨成罪，與接續犯之\n    要件難謂相符，自應予分論併罰。公訴意旨認被告上揭數次\n    違反保護令之行為，時空密接，犯意單一，侵害同一法益，\n    為接續犯，應論以一罪，尚有未合。\n  (三)被告所犯幫助詐欺取財罪與5次違反保護令罪，犯意個別，\n    行為互異，應分論併罰。\n三、維持原判之理由\n  (一)原審以被告罪證明確，因予適用家庭暴力防治法第61條第1\n    款、第2款，刑法第30條第1項前段、第2項、第339條第1項\n    、第51條第5款、第41條第1項前段，刑法施行法第1條之1第\n    1項、第2項前段之規定，並審酌被告提供帳戶與他人作為不\n    法使用，助長犯罪之猖獗，影響社會正常經濟交易安全，增\n    加被害人尋求救濟及偵查犯罪之困難，又明知收受原審法院\n    民事通常保護令後，依該保護令不得對被害人為精神上不法\n    之侵害及騷擾行為，竟仍漠視上開保護令內容，多次以撥打\n    電話、傳送簡訊及前往被害人住處外等方式對被害人實施精\n    神上不法之侵害及騷擾，顯然漠視法律，甚者，被告前於97\n    年12月17日亦因傷害被害人之違反保護令案件，經原審法院\n    以98年度虎簡字第43號判處有期徒刑3 月，緩刑2年，緩刑\n    期間付保護管束（被告於97年12月17日經警查獲後，於翌日\n    即同年月18日再次違反保護令即事實二(一)部分，然被告前次\n    已因遭警查獲而阻絕其犯意，之後其違反保護令行為應認係\n    另行起意，核與前次無關，不為既判力所及），此有臺灣高\n    等法院被告前案紀錄表、聲請簡易判決處刑書附卷可稽，被\n    告卻不知珍惜機會，再次觸犯相同之罪，顯然被告法治觀念\n    欠缺，惟念其犯後坦承犯行，尚能即時知錯，因涉幫助詐欺\n    取財罪之犯罪所得為6千元等一切情狀，分別量處有期徒刑\n    肆月，並依司法院釋字第366號、第662號解釋意旨，就本案\n    被告所犯上開6罪之宣告刑定其應執行之刑有期徒刑1年2 月\n    ，另諭知易科罰金之折算標準。經核原判決認事用法，並無\n    不合，量刑亦稱妥適。\n  (二)\n  1.被告上訴意旨略以：伊將孫敏芳之帳戶販賣予他人，孫敏芳\n    均屬知情，另告訴人丙○○事後已原諒為由，請求減輕其刑\n    云云，其上訴並無理由，應予駁回。\n  2.檢察官上訴意旨略以：併辦之98年4月20日違反保護令犯行\n    ，因被告所為違反保護令之騷擾行為，係密切接近之時地實\n    施，侵害同一之法益，應屬接續犯，顯在起訴範圍內，被告\n    係接續於密接時、地，與起訴之事實顯屬接續犯關係而為實\n    質上一罪，應為起訴效力所及，原審未予一併審理，顯有已\n    受請求之事項未予判決之違法云云，因而指摘原判決認定事\n    實適用法律不當，惟查，檢察官聲請併辦之被告於98年4月\n    20 日違反保護令犯行，如後所述，與起訴之事實顯非屬接\n    續犯關係，並未在起訴範圍內，非起訴效力所及，原審未予\n    一併審理，並無不當，詳如後述，檢察官上開所指尚無足採\n    ，從而其上訴並無理由，應予駁回。\n四、另臺灣雲林地方法院檢察署98年度偵字第3739號聲請併辦意\n    旨略以：被告甲○○於98年4月20日上午11時許，在不詳處\n    所，以公共電話不斷撥打上開丙○○工作地點即「婦安婦產\n    科」電話，令丙○○無法繼續上班之方式，直接、間接騷擾\n    丙○○，迫使丙○○因而離職，而違反上開保護令裁定。此\n    部分與被告上揭經起訴之違反保護令罪，有接續犯之關係，\n    為法律上之同一案件，依審判不可分原則，應為起訴效力所\n    及，爰檢送案卷請求併案審理等語。經查：本案被告經起訴\n    判決有罪部分之犯罪時間，各為自97年12月18日起至同年月\n    20 日止、98年1月15日、同年4月1、2日、同年5月6日及同\n    年5 月14日，核與檢察官聲請併案審理部分之犯罪時間即98\n    年4 月20日，犯罪時間相差甚遠，在刑法評價上，各具獨立\n    性，皆可單獨成罪，且被告每次違反保護令後，被害人均報\n    警處理，有各該次警詢筆錄可佐，顯見被告為警查獲後已中\n    斷其犯意，該次應屬另行起意至明，核與起訴部分無實質上\n    一罪關係，即非本案起訴效力所及，本院自無從併予審理，\n    應退由檢察官另為適法之處理。\n五、被告經合法傳喚，無正當之理由未於審判期日到庭，爰不待\n    其陳述，逕行判決。\n六、據上論結，應依刑事訴訟法第368條、第371條，判決如主文\n    。\n本案經檢察官羅清溪到庭執行職務。\n中    華    民    國    99    年    1     月    5     日\n                  刑事第四庭    審判長法  官  吳志誠\n                                      法  官  彭喜有\n                                      法  官  羅心芳\n以上正本證明與原本無異。\n不得上訴。\n                                      書記官  蔡振豐"
  },
  "characters": {
    "judges": [
      "吳志誠",
      "彭喜有",
      "羅心芳"
    ],
    "prosecutors": [
      "羅清溪"
    ],
    "lawyers": [

    ],
    "clerks": [
      "蔡振豐"
    ],
    "plaintiffs": [

    ],
    "defendants": [
      "甲"
    ],
    "prosecutor_office": [

    ],
    "creditors": [

    ],
    "debtors": [

    ],
    "judicial_associate_officer": [

    ]
  },
  "adjudged_at": "2010-01-05",
  "created_at": "2016-01-05 15:07:52",
  "updated_at": "2016-01-05 15:07:52"
}