{
  "identify": "TNH-98-交上訴-1054-20100105-1",
  "court": {
    "name": "臺灣高等法院",
    "code": "TNH"
  },
  "division": {
    "name": "刑事",
    "code": "M"
  },
  "year": 98,
  "word": "交上訴",
  "number": "1054",
  "jcheck": "1",
  "reason": "公共危險等",
  "content": "臺灣高等法院臺南分院刑事判決      98年度交上訴字第1054號\n上  訴  人  臺灣臺南地方法院檢察署檢察官\n被      告  丙○○\n選任辯護人  許安德利律師\n            許世律師\n上列上訴人因被告公共危險等案件，不服臺灣臺南地方法院97年\n度交訴字第113號中華民國98年9月16日第一審判決（起訴案號：\n臺灣臺南地方法院檢察署97年度偵字第4808號），提起上訴，本\n院判決如下：\n    主  文\n上訴駁回。\n    理  由\n一、公訴意旨略以：被告丙○○於民國97年1月30日凌晨2時30分\n    許，駕駛車牌號碼ST -2478號自用小客車，沿臺南縣永康市\n    ○○路由北往南方向行駛，途經中華路433號前時，原應注\n    意車前狀況，並隨時採取必要之安全措施，而依當時天候晴\n    ，視距良好，且無障礙物，亦無不能注意之情事，竟疏未注\n    意車前狀況，擦撞同向前方由甲○騎乘之腳踏車後車尾，致\n    甲○人車倒地，受有頭部外傷之傷害。詎丙○○肇事後，竟\n    未對甲○為必要之救助即駕車逃逸，經警方調閱永康市○○\n    路與中華二路路口監視器及目擊證人乙○○指證後，進而查\n    知上情。因認被告丙○○涉犯刑法第185條之4肇事逃逸罪嫌\n    及同法第284條第1項之過失傷害罪嫌等語。\n二、按犯罪事實應依證據認定之，無證據不得認定犯罪事實；又\n    不能證明被告犯罪者，應諭知無罪之判決，刑事訴訟法第15\n    4條第2項、第301條第1項分別定有明文。又刑事訴訟法上所\n    謂認定犯罪事實之證據，係指足以認定被告確有犯罪行為之\n    積極證據而言，該項證據自須適合於被告犯罪事實之認定，\n    始得採為斷罪資料；認定犯罪事實所憑之證據，無論係直接\n    證據或間接證據，其為訴訟上之證明，須於通常一般之人均\n    不致有所懷疑，而得確信其為真實之程度者，始得據為有罪\n    之認定，倘其證明尚未達到此一程度，而有合理之懷疑存在\n    ，復無其他調查途徑可尋，法院即應為無罪之判決（最高法\n    院29年上字第3105號、76年台上字第4986號判例參照）。再\n    按刑事訴訟法第161條已於91年2月8日修正公布，其第1項規\n    定：檢察官就被告犯罪事實，應負舉證責任，並指出證明之\n    方法。因此，檢察官對於起訴之犯罪事實，應負提出證據及\n    說服之實質舉證責任。倘其所提出之證據，不足為被告有罪\n    之積極證明，或其指出證明之方法，無從說服法院以形成被\n    告有罪之心證，基於無罪推定之原則，自應為被告無罪判決\n    之諭知（最高法院92年台上字第128號判例參照）。\n三、本件公訴人認被告丙○○涉犯肇事逃逸及過失傷害罪嫌，係\n    以告訴人甲○於警詢及偵查中之指訴、及證人乙○○於警詢\n    及偵查中之證述，復有臺南縣警察局永康分局道路交通事故\n    現場圖1紙、交通事故調查報告表(一)、(二)各1份、道路交通事\n    故現場及腳踏車車損照片6張、肇事地點監視器翻拍畫面2張\n    、被告自小客車車損照片5張及財團法人奇美醫院診斷證明\n    書1紙等，為其憑據；訊據被告丙○○對於告訴人甲○於前\n    揭時間騎乘腳踏車沿臺南縣永康市○○路由北往南方向行駛\n    ，於行經中華路433號前時，遭自小客車撞擊腳踏車後車尾\n    ，致告訴人甲○人車倒地，並受有頭部外傷傷害之事實，並\n    不爭執，亦不否認伊於前揭時間有駕駛上開自小客車，沿臺\n    南縣永康市○○路由北往南方向行駛之事實，惟堅詞否認有\n    何肇事逃逸及過失傷害之不法犯行，並辯稱：當天其在中山\n    南路與中華路交岔路口的豆漿店喝豆漿，喝完後開車走中華\n    路要回去，開到本件交通事故附近的時候，就有看到地上有\n    一個黑黑的東西，閃燈後看起來像是一個人躺在地上，其就\n    把車子閃進內車道，過了不知幾公尺，看到有1台車子倒在\n    那個人的後面，還有2個騎機車的人在旁邊看，其就開內車\n    道回家去了等語。\n四、證據能力部分：\n    按被告以外之人於審判外之陳述，經當事人於審判程序同意\n    作為證據，法院審酌該言詞陳述或書面陳述作成時之情況，\n    認為適當者，亦得為證據。當事人、代理人或辯護人於法院\n    調查證據時，知有刑事訴訟法第159條第1項不得為證據之情\n    形，而未於言詞辯論終結前聲明異議，視為有前項之同意，\n    刑事訴訟法第159條之5定有明文。查公訴人所提出之臺南縣\n    警察局永康分局道路交通事故現場圖1紙、道路交通事故調\n    查報告表(一)、(二)各1份，及其他各項具傳聞性質之證據資料\n    ，公訴人、被告及選任辯護人於審判程序中對於前述具傳聞\n    性質之證據資料之證據能力，均表示無意見，且迄於言詞辯\n    論終結前亦未聲明異議。本院審酌上開各項證據資料作成之\n    情況，核無違法取證或其他瑕疵，且為證明本件犯罪事實所\n    必要之重要關係事項，認為以之作為證據為適當，上開其他\n    相關證據資料，自得採為證據。\n五、經查：\n  (一)告訴人甲○於警詢時供稱：「（你今（02）日因何事前來本\n    分局接受調查？）我於97年01月30日02時40分許，因駕駛腳\n    踏車在永康市○○路433號前，與一部車號不詳自小客車發\n    生碰撞後，該肇事自小客車沒有對我採取救護及報警處理，\n    就自行駕駛原車輛駛離現場逃逸，致我身體受傷，所以打電\n    話向警方報案並接受調查。」、「（請你將發生經過詳述？\n    ）我於97年01月30日02時40分許，因駕駛腳踏車沿永康市○\n    ○路由北向南方向直行行駛機慢車道，途經中華路433號前\n    ，與一部車號不詳自小客車沿中華路由北向南方向直行行駛\n    ，雙方至事故地點，我的車子後車尾與對方車子何處發生碰\n    撞我不知道，該肇事車輛沒有停下就駛離現場。」、「（你\n    或者現場有其他目擊證人記下肇事車輛車牌？）我沒有記下\n    肇事車輛車牌，是否有其他人目擊我不知道。」、「（該肇\n    事車輛為何種車輛？廠牌？顏色？）我不知道是何種車輛，\n    廠牌我不知道。何種顏色我不知道。」等語（見警卷第8-9\n    頁）；於檢察事務官偵查中陳稱：「（車禍時、地、行車方\n    向是否如警詢所示？（告知97年2月2日警詢筆錄））是的，\n    我是被該車從後方撞到，撞到後我撞到路邊的車，我清醒後\n    爬起來，因該車子很快的開走，所以我沒有看到撞我的車子\n    。」等語（見臺灣臺南地方法院檢察署97年度核交字第1400\n    號卷第7頁，下稱核交卷）。依據告訴人甲○上開陳述之內\n    容，堪認告訴人甲○並未看到肇事車輛，亦不知道該車輛之\n    廠牌及顏色，自難依告訴人甲○之指述即認被告所駕駛之自\n    小客車為本件之肇事車輛。\n    雖告訴人於本院審理中到院另供述：「係被告闖紅燈撞到伊\n    …我在車底下有看到被告之車子」云云（本院卷第78、79頁\n    ），然亦自承被告闖紅燈由後方撞到我等語，衡情被告既經\n    被告自後撞擊而摔倒，衡情應無可能看到後方來車至明，從\n    而告訴人於本院審理時之供述應係推測之詞，不足採信。\n  (二)證人乙○○固於原審結證稱：「（檢察官問：於97年1月30\n    日凌晨2時30分左右，有無目擊一起自小客車與腳踏車在永\n    康市○○路433號前的車禍？）有。」、「（檢察官問：目\n    擊當時你站在何處？）站在一家小吃店前面，我正好吃完要\n    出來。」、「（檢察官問：是否記得小吃店門牌？）門牌沒\n    有記。知道叫『惠成』小吃店。」、「（檢察官問：之前在\n    警局時有證述，你是從中華路405號走出店外，405號是否正\n    確？）我不知道該店門牌，那是警察跟我說的。」、「（檢\n    察官問：你有跟警察說小吃店名稱，警察去現場查詢後跟你\n    說的？）是的。」、「（檢察官問：當時看到與聽到的情形\n    如何？）當時要牽機車準備要走，我聽到巨響出去看有一台\n    轎車，那時候很遠，很暗，我看到小客車前輪車下拖著一個\n    東西，當時距離約有一百公尺左右，我確定小客車有撞到東\n    西，小客車好像正在甩開他壓到的東西，然後，我看到小客\n    車左右擺動之後有甩開那東西，當時他在外車道，他往內車\n    道之後就有甩開那物品，我就騎車過去看，發現有女士坐在\n    地上，腳踏車在旁邊。」、「（檢察官問：你在哪裡聽到巨\n    響？）聽到巨響時，我已經在小吃店的外面正準備牽機車。\n    」、「（檢察官問：所以聽到巨響抬起頭來就看到上述的畫\n    面？）是的。」、「（檢察官問：你方才證述小客車有左右\n    甩開，是否很大的動作？）輕輕的，輕輕的往左往右，然後\n    小客車有一個從外車道切到內車道的較大動作，因為這個動\n    作將該不明物體拖到路中間，脫離之後小客車就走掉了。」\n    、「（檢察官問：自小客車拖行腳踏車拖行多長？）大概幾\n    秒鐘的時間。」、「（檢察官問：拖行時候，小客車車速多\n    少？）大約十公里左右，很慢。」、「（檢察官問：本身是\n    否有開車？）有，十八歲就開始開車。」、「（檢察官問：\n    你看到該自小客車是什麼顏色、廠牌、車號？）車號我只記\n    得有個『7』，廠牌我只知道是ＢＭＷ，黑色。新舊沒有很\n    精確判斷。新舊我沒有辦法很明確的判斷，但是看的話，我\n    應該可以，當時警察有給我看監視錄影帶。」、「（檢察官\n    問：該逃逸的自小客車，是否有從你面前開過去？）有，這\n    點我可以很肯定。」、「（檢察官問：從你面前開過去，你\n    距離他多遠？）大約2公尺左右。」、「（檢察官問：他經\n    過你面前時，車速多少？）車速約30左右。」、「（檢察官\n    請法院提示警卷第22頁到27頁照片予證人。審判長諭知提示\n    警卷第22頁至27頁照片予證人乙○○。檢察官問：照片上的\n    自小客車與你當時目擊的自小客車，是否特徵均相同？）是\n    的。」等語（見原審卷第103- 105頁），於本院審理時亦證\n    稱：「（當時車禍發生，有無親眼目睹？）有親眼看到，但\n    有一段距離，約壹佰公尺左右。（你怎麼發生壹佰公尺之外\n    有發生車禍？）先聽到撞擊聲，探頭出去看，看到有一部車\n    子要擺脫壓到的異物。（壓到的異物係何物知否？）我後來\n    有騎機車過去看係一部腳踏車。（壓腳踏車的小客車係那一\n    部，你清楚？）我大概知道他的外觀，那部小客車是在我視\n    線不斷下從我前面離開。（可否描述所謂看到的外觀？）係\n    黑色舊款式的ＢＭＷ。（車牌有看到其中壹個『七』？）是\n    的，我本來有記得好幾個數目，後來因為處理現場事情，記\n    憶中只很清楚得有壹個『七』。」等語（見本院卷第54-55\n    頁），惟查：\n  1.依證人乙○○之證言以觀，於告訴人之腳踏車遭汽車撞及之\n    際證人乙○○並未目擊，僅係聽到撞擊聲，亦即證人乙○○\n    並未親眼看到被告車輛撞擊告訴人之腳踏車，且證人乙○○\n    當時所在之位置距離肇事地點有100公尺之遠，而當時時間\n    為凌晨2時許，證人乙○○亦陳稱光線很暗，且其後來僅記\n    得肇事車輛車牌號碼中之一個數字為「7」，實難認其當時\n    所看到的車輛即為被告所駕駛之自小客車。\n  2.次查，證人乙○○所述之事發時間（2時25分），與被告所\n    駕駛之車輛經監視器拍下之畫面上時間（2時29分31秒，見\n    原審卷第47頁背面勘驗筆錄）有4分多鐘之落差；且證人所\n    述之時間（2時25分）至被告所駕駛之車輛經監視器拍下之\n    畫面上時間（2時29分31秒）此段時間內，行駛在臺南縣永\n    康市○○路北往南方向之車輛亦不在少數，其中也不乏車牌\n    號碼中之有數字「7」的自小客車（見原審卷第47頁正、背\n    面之勘驗筆錄），堪認證人乙○○非無誤認其他車輛為被告\n    所駕駛之自小客車之可能性。\n  3.又依證人乙○○所證，被告車子在壓到東西後，有輕輕的將\n    車身左右擺動，之後有一個從外車道切到內車道的較大動作\n    將腳踏車拖到路中間，並因此甩開該東西，脫離之後被告車\n    輛走掉，被告拖行腳踏車時的車速大約十公里左右，很慢的\n    等語，經與核交卷第20頁背面至第23頁背面之腳踏車照片、\n    警卷第23頁之腳踏車照片以及警卷第18頁之現場圖相核對後\n    ，本院認有下列不合常理之處：\n    (1)從腳踏車照片觀之，告訴人腳踏車之損壞處乃在後車輪擋\n      泥板之位置，可見告訴人之腳踏車應係被自小客車從正後\n      方撞擊，又依告訴人所述其所騎乘之腳踏車後方載有一個\n      大的藍色塑膠箱，依該塑膠箱的大小、寬度、長度觀之，\n      被告自小客車應不易壓住告訴人腳踏車拖行。\n    (2)依證人乙○○所言，被告自小客車壓住告訴人腳踏車拖行\n      一段距離，則告訴人腳踏車之車輪或車身某處依理應會有\n      因擠壓而變形之處，但照片中未見腳踏車有何變形之情形\n      。又告訴人所騎乘之腳踏車如由被告所駕駛之自小客車壓\n      住並拖行一段距離，則告訴人之腳踏車亦應有一側車身與\n      地面摩擦而有嚴重擦痕及掉漆之情形，但照片中並未見到\n      腳踏車有此情形（如藍色塑膠箱未與腳踏車脫離，亦應有\n      嚴重擦痕，亦未見此情形）。\n    (3)又如被告之自小客車壓住告訴人腳踏車拖行一段距離，即\n      告訴人腳踏車被汽車保險桿或車身卡住而被拖行，揆諸常\n      情應非被告之自小客車慢慢開、左右甩動即能甩開；另參\n      酌現場圖上所繪之刮地痕觀之，該刮地痕係發生在機慢車\n      道上，而且是以近似直線之方式由機慢車道向右斜偏至路\n      旁停止，並非向左斜偏往汽車慢車道（即第二汽車道），\n      亦非左右甩擺之曲線，又被告自小客車壓住告訴人腳踏車\n      拖行一段距離，則刮地痕之終止處應與告訴人腳踏車被牽\n      起扶正處接近，但依現場圖所繪之距離，兩者間卻相距有\n      11.5公尺之遠。從而依證人乙○○證述被告自小客車往左\n      往右擺動將腳踏車拖到路中間甩開乙節即與前揭現場圖所\n      示之刮地痕顯不相符合。\n    (4)因此，依核交卷第20頁背面至第23頁背面之腳踏車照片以\n      及警卷第18頁之現場圖觀之，告訴人之腳踏車應係先被他\n      車自正後方撞擊，嗣後因被告恰亦駕駛自小客車到腳踏車\n      停止處前方，被告為閃避該腳踏車而自慢車道左閃駛入內\n      車道，故本院認被告辯稱其乃係看到前方有黑黑的東西，\n      就把車閃進內車道內等語，應為可信。而且證人乙○○在\n      光線昏暗之100公尺遠處看到被告之自小客車閃進內車道\n      ，亦有誤認被告之自小客車閃進內車道是要把告訴人腳踏\n      車甩開之可能。\n  4.經將證人乙○○之證言與上開相關事證相核，因證人乙○○\n    之證言與相關事證有上述不吻合之處，證人乙○○不無誤認\n    之可能，是證人乙○○之證言應不足採為不利被告之證據。\n  (三)再查，依公訴人將被告所駕駛之自小客車與告訴人之腳踏車\n    送請臺南縣警察局鑑識課比對二車受損情形是否相符合，經\n    鑑識後並未發現兩車間有可疑之轉移漆痕，有該勘查採證報\n    告在卷可稽（見核交卷第14至15頁），又本院審酌告訴人之\n    腳踏車被碰撞處為後輪檔泥板處，有該腳踏車照片在卷可稽\n    （見核交卷第23頁背面），該被碰撞處之高度經與被告所駕\n    駛之自小客車（含保險桿）之高度比對後，兩者間亦有所落\n    差，是難認二車有發生碰撞之情形。\n    雖公訴人認被告事後更換保險桿，有影響鑑定結果，惟查，\n    如前所述，舉證責任應由公訴人負擔，本件公訴人如認有鑑\n    定之必要，本應於事故發生後偵查之初立即請鑑定機關鑑定\n    ，至少也應立即扣押被告車輛或限制被告不可修理車輛，然\n    公訴人未立即鑑定，也未為扣押或限制修理之處分，而係遲\n    至6個月以後才請鑑定機關鑑定，因此，本院認即使因被告\n    更換保險桿而影響鑑定結果，亦係公訴人之消極偵查行為所\n    致，自不得嗣後據為被告確有肇事逃逸並卸責之情事而為不\n    利被告之主張。\n六、綜上所述，告訴人甲○之指述及證人乙○○之證述，尚不能\n    推認被告確有公訴意旨所指肇事逃逸及過失傷害之犯行。至\n    卷附之臺南縣警察局永康分局道路交通事故現場圖1紙、交\n    通事故調查報告表(一)、(二)各1份、道路交通事故現場及腳踏\n    車車損照片6張、肇事地點監視器翻拍畫面2張、被告自小客\n    車車損照片5張及財團法人奇美醫院診斷證明書1紙等件，僅\n    能證明被告於前揭時、地，確曾駕駛上開自小客車約於本件\n    案發時行經肇事地點，及告訴人甲○因車禍事故受有頭部外\n    傷之傷害而已，尚難據此等證據遽認被告確曾駕駛上開自小\n    客車，於前揭時、地自後追撞告訴人腳踏車而發生車禍，並\n    致告訴人甲○受有上揭傷害後逃逸，是自難以肇事逃逸罪及\n    過失傷害罪相繩。\n七、綜上，本件公訴意旨所提之證據均未達到於通常之人均不致\n    有所懷疑，而得確信其為真實之程度，尚不能遽為被告有罪\n    之判斷，故被告被訴涉犯公共危險及過失傷害犯行應屬不能\n    證明，此外，本院復查無其他積極證據足以證明被告確有公\n    訴人所指上揭犯行，自屬不能證明被告犯罪，揆諸上開說明\n    ，自應為被告無罪之諭知。原審以不能證明被告犯罪而諭知\n    無罪之判決，核無不合，檢察官上訴意旨略以：\n    (1)原審僅以證人乙○○所述之事發時間（2時25分）至被告\n    所駕駛之車輛經監視器拍下之畫面上時間（2時29分31秒）\n    之4分許期間內之自小客車行經數非少、其中亦不乏車牌號\n    碼中之有數字「7」的自小客車，而推認證人乙○○有所誤\n    認等情，非無研求之餘地。(2)依證人乙○○於聽聞巨響，並\n    見告訴人所騎腳踏車遭上開自小客車輕微拖行、甩動，隨即\n    騎車至事故現場察看，並見告訴人遭撞在地，時間過程緊接\n    ，益認被告為本件交通事故肇事者。(3)再者，認定犯罪事實\n    所憑之證據，並不以直接證據為限，而本件綜合以上所述之\n    間接證據，應已達通常一般之人均不致有所懷疑，而得確信\n    其為真實之程度。原判決置本案間接證據於不顧，與判例意\n    旨相違云云，指摘原判決認定事實適用法律不當，惟查，\n    本件依告訴人甲○之指述及證人乙○○之證述，參酌現場圖\n    中刮地痕位置及告訴人與被告車輛損害之各種跡證，尚不能\n    證明被告確有公訴意旨所指肇事逃逸及過失傷害之犯行，已\n    如上述，是檢察官上開所指尚無足採，其上訴並無理由，應\n    予駁回。\n八、據上論結，應依刑事訴訟法第368條，判決如主文。\n本案經檢察官羅清溪到庭執行職務。\n中    華    民    國    99    年     1    月    5    日\n                  刑事第四庭    審判長法  官  吳志誠\n                                      法  官  彭喜有\n                                      法  官  羅心芳\n以上正本證明與原本無異。\n肇事逃逸罪檢察官如不服本判決應於收受本判決後十日內向本院\n提出上訴書，其未敘述上訴理由者並得於提起上訴後十日內向本\n院補提理由書。\n                                      書記官  蔡振豐\n中    華    民    國    99    年     1    月    6    日",
  "structure": {
    "main": "上訴駁回。",
    "reason": "一、公訴意旨略以：被告丙○○於民國97年1月30日凌晨2時30分\n    許，駕駛車牌號碼ST -2478號自用小客車，沿臺南縣永康市\n    ○○路由北往南方向行駛，途經中華路433號前時，原應注\n    意車前狀況，並隨時採取必要之安全措施，而依當時天候晴\n    ，視距良好，且無障礙物，亦無不能注意之情事，竟疏未注\n    意車前狀況，擦撞同向前方由甲○騎乘之腳踏車後車尾，致\n    甲○人車倒地，受有頭部外傷之傷害。詎丙○○肇事後，竟\n    未對甲○為必要之救助即駕車逃逸，經警方調閱永康市○○\n    路與中華二路路口監視器及目擊證人乙○○指證後，進而查\n    知上情。因認被告丙○○涉犯刑法第185條之4肇事逃逸罪嫌\n    及同法第284條第1項之過失傷害罪嫌等語。\n二、按犯罪事實應依證據認定之，無證據不得認定犯罪事實；又\n    不能證明被告犯罪者，應諭知無罪之判決，刑事訴訟法第15\n    4條第2項、第301條第1項分別定有明文。又刑事訴訟法上所\n    謂認定犯罪事實之證據，係指足以認定被告確有犯罪行為之\n    積極證據而言，該項證據自須適合於被告犯罪事實之認定，\n    始得採為斷罪資料；認定犯罪事實所憑之證據，無論係直接\n    證據或間接證據，其為訴訟上之證明，須於通常一般之人均\n    不致有所懷疑，而得確信其為真實之程度者，始得據為有罪\n    之認定，倘其證明尚未達到此一程度，而有合理之懷疑存在\n    ，復無其他調查途徑可尋，法院即應為無罪之判決（最高法\n    院29年上字第3105號、76年台上字第4986號判例參照）。再\n    按刑事訴訟法第161條已於91年2月8日修正公布，其第1項規\n    定：檢察官就被告犯罪事實，應負舉證責任，並指出證明之\n    方法。因此，檢察官對於起訴之犯罪事實，應負提出證據及\n    說服之實質舉證責任。倘其所提出之證據，不足為被告有罪\n    之積極證明，或其指出證明之方法，無從說服法院以形成被\n    告有罪之心證，基於無罪推定之原則，自應為被告無罪判決\n    之諭知（最高法院92年台上字第128號判例參照）。\n三、本件公訴人認被告丙○○涉犯肇事逃逸及過失傷害罪嫌，係\n    以告訴人甲○於警詢及偵查中之指訴、及證人乙○○於警詢\n    及偵查中之證述，復有臺南縣警察局永康分局道路交通事故\n    現場圖1紙、交通事故調查報告表(一)、(二)各1份、道路交通事\n    故現場及腳踏車車損照片6張、肇事地點監視器翻拍畫面2張\n    、被告自小客車車損照片5張及財團法人奇美醫院診斷證明\n    書1紙等，為其憑據；訊據被告丙○○對於告訴人甲○於前\n    揭時間騎乘腳踏車沿臺南縣永康市○○路由北往南方向行駛\n    ，於行經中華路433號前時，遭自小客車撞擊腳踏車後車尾\n    ，致告訴人甲○人車倒地，並受有頭部外傷傷害之事實，並\n    不爭執，亦不否認伊於前揭時間有駕駛上開自小客車，沿臺\n    南縣永康市○○路由北往南方向行駛之事實，惟堅詞否認有\n    何肇事逃逸及過失傷害之不法犯行，並辯稱：當天其在中山\n    南路與中華路交岔路口的豆漿店喝豆漿，喝完後開車走中華\n    路要回去，開到本件交通事故附近的時候，就有看到地上有\n    一個黑黑的東西，閃燈後看起來像是一個人躺在地上，其就\n    把車子閃進內車道，過了不知幾公尺，看到有1台車子倒在\n    那個人的後面，還有2個騎機車的人在旁邊看，其就開內車\n    道回家去了等語。\n四、證據能力部分：\n    按被告以外之人於審判外之陳述，經當事人於審判程序同意\n    作為證據，法院審酌該言詞陳述或書面陳述作成時之情況，\n    認為適當者，亦得為證據。當事人、代理人或辯護人於法院\n    調查證據時，知有刑事訴訟法第159條第1項不得為證據之情\n    形，而未於言詞辯論終結前聲明異議，視為有前項之同意，\n    刑事訴訟法第159條之5定有明文。查公訴人所提出之臺南縣\n    警察局永康分局道路交通事故現場圖1紙、道路交通事故調\n    查報告表(一)、(二)各1份，及其他各項具傳聞性質之證據資料\n    ，公訴人、被告及選任辯護人於審判程序中對於前述具傳聞\n    性質之證據資料之證據能力，均表示無意見，且迄於言詞辯\n    論終結前亦未聲明異議。本院審酌上開各項證據資料作成之\n    情況，核無違法取證或其他瑕疵，且為證明本件犯罪事實所\n    必要之重要關係事項，認為以之作為證據為適當，上開其他\n    相關證據資料，自得採為證據。\n五、經查：\n  (一)告訴人甲○於警詢時供稱：「（你今（02）日因何事前來本\n    分局接受調查？）我於97年01月30日02時40分許，因駕駛腳\n    踏車在永康市○○路433號前，與一部車號不詳自小客車發\n    生碰撞後，該肇事自小客車沒有對我採取救護及報警處理，\n    就自行駕駛原車輛駛離現場逃逸，致我身體受傷，所以打電\n    話向警方報案並接受調查。」、「（請你將發生經過詳述？\n    ）我於97年01月30日02時40分許，因駕駛腳踏車沿永康市○\n    ○路由北向南方向直行行駛機慢車道，途經中華路433號前\n    ，與一部車號不詳自小客車沿中華路由北向南方向直行行駛\n    ，雙方至事故地點，我的車子後車尾與對方車子何處發生碰\n    撞我不知道，該肇事車輛沒有停下就駛離現場。」、「（你\n    或者現場有其他目擊證人記下肇事車輛車牌？）我沒有記下\n    肇事車輛車牌，是否有其他人目擊我不知道。」、「（該肇\n    事車輛為何種車輛？廠牌？顏色？）我不知道是何種車輛，\n    廠牌我不知道。何種顏色我不知道。」等語（見警卷第8-9\n    頁）；於檢察事務官偵查中陳稱：「（車禍時、地、行車方\n    向是否如警詢所示？（告知97年2月2日警詢筆錄））是的，\n    我是被該車從後方撞到，撞到後我撞到路邊的車，我清醒後\n    爬起來，因該車子很快的開走，所以我沒有看到撞我的車子\n    。」等語（見臺灣臺南地方法院檢察署97年度核交字第1400\n    號卷第7頁，下稱核交卷）。依據告訴人甲○上開陳述之內\n    容，堪認告訴人甲○並未看到肇事車輛，亦不知道該車輛之\n    廠牌及顏色，自難依告訴人甲○之指述即認被告所駕駛之自\n    小客車為本件之肇事車輛。\n    雖告訴人於本院審理中到院另供述：「係被告闖紅燈撞到伊\n    …我在車底下有看到被告之車子」云云（本院卷第78、79頁\n    ），然亦自承被告闖紅燈由後方撞到我等語，衡情被告既經\n    被告自後撞擊而摔倒，衡情應無可能看到後方來車至明，從\n    而告訴人於本院審理時之供述應係推測之詞，不足採信。\n  (二)證人乙○○固於原審結證稱：「（檢察官問：於97年1月30\n    日凌晨2時30分左右，有無目擊一起自小客車與腳踏車在永\n    康市○○路433號前的車禍？）有。」、「（檢察官問：目\n    擊當時你站在何處？）站在一家小吃店前面，我正好吃完要\n    出來。」、「（檢察官問：是否記得小吃店門牌？）門牌沒\n    有記。知道叫『惠成』小吃店。」、「（檢察官問：之前在\n    警局時有證述，你是從中華路405號走出店外，405號是否正\n    確？）我不知道該店門牌，那是警察跟我說的。」、「（檢\n    察官問：你有跟警察說小吃店名稱，警察去現場查詢後跟你\n    說的？）是的。」、「（檢察官問：當時看到與聽到的情形\n    如何？）當時要牽機車準備要走，我聽到巨響出去看有一台\n    轎車，那時候很遠，很暗，我看到小客車前輪車下拖著一個\n    東西，當時距離約有一百公尺左右，我確定小客車有撞到東\n    西，小客車好像正在甩開他壓到的東西，然後，我看到小客\n    車左右擺動之後有甩開那東西，當時他在外車道，他往內車\n    道之後就有甩開那物品，我就騎車過去看，發現有女士坐在\n    地上，腳踏車在旁邊。」、「（檢察官問：你在哪裡聽到巨\n    響？）聽到巨響時，我已經在小吃店的外面正準備牽機車。\n    」、「（檢察官問：所以聽到巨響抬起頭來就看到上述的畫\n    面？）是的。」、「（檢察官問：你方才證述小客車有左右\n    甩開，是否很大的動作？）輕輕的，輕輕的往左往右，然後\n    小客車有一個從外車道切到內車道的較大動作，因為這個動\n    作將該不明物體拖到路中間，脫離之後小客車就走掉了。」\n    、「（檢察官問：自小客車拖行腳踏車拖行多長？）大概幾\n    秒鐘的時間。」、「（檢察官問：拖行時候，小客車車速多\n    少？）大約十公里左右，很慢。」、「（檢察官問：本身是\n    否有開車？）有，十八歲就開始開車。」、「（檢察官問：\n    你看到該自小客車是什麼顏色、廠牌、車號？）車號我只記\n    得有個『7』，廠牌我只知道是ＢＭＷ，黑色。新舊沒有很\n    精確判斷。新舊我沒有辦法很明確的判斷，但是看的話，我\n    應該可以，當時警察有給我看監視錄影帶。」、「（檢察官\n    問：該逃逸的自小客車，是否有從你面前開過去？）有，這\n    點我可以很肯定。」、「（檢察官問：從你面前開過去，你\n    距離他多遠？）大約2公尺左右。」、「（檢察官問：他經\n    過你面前時，車速多少？）車速約30左右。」、「（檢察官\n    請法院提示警卷第22頁到27頁照片予證人。審判長諭知提示\n    警卷第22頁至27頁照片予證人乙○○。檢察官問：照片上的\n    自小客車與你當時目擊的自小客車，是否特徵均相同？）是\n    的。」等語（見原審卷第103- 105頁），於本院審理時亦證\n    稱：「（當時車禍發生，有無親眼目睹？）有親眼看到，但\n    有一段距離，約壹佰公尺左右。（你怎麼發生壹佰公尺之外\n    有發生車禍？）先聽到撞擊聲，探頭出去看，看到有一部車\n    子要擺脫壓到的異物。（壓到的異物係何物知否？）我後來\n    有騎機車過去看係一部腳踏車。（壓腳踏車的小客車係那一\n    部，你清楚？）我大概知道他的外觀，那部小客車是在我視\n    線不斷下從我前面離開。（可否描述所謂看到的外觀？）係\n    黑色舊款式的ＢＭＷ。（車牌有看到其中壹個『七』？）是\n    的，我本來有記得好幾個數目，後來因為處理現場事情，記\n    憶中只很清楚得有壹個『七』。」等語（見本院卷第54-55\n    頁），惟查：\n  1.依證人乙○○之證言以觀，於告訴人之腳踏車遭汽車撞及之\n    際證人乙○○並未目擊，僅係聽到撞擊聲，亦即證人乙○○\n    並未親眼看到被告車輛撞擊告訴人之腳踏車，且證人乙○○\n    當時所在之位置距離肇事地點有100公尺之遠，而當時時間\n    為凌晨2時許，證人乙○○亦陳稱光線很暗，且其後來僅記\n    得肇事車輛車牌號碼中之一個數字為「7」，實難認其當時\n    所看到的車輛即為被告所駕駛之自小客車。\n  2.次查，證人乙○○所述之事發時間（2時25分），與被告所\n    駕駛之車輛經監視器拍下之畫面上時間（2時29分31秒，見\n    原審卷第47頁背面勘驗筆錄）有4分多鐘之落差；且證人所\n    述之時間（2時25分）至被告所駕駛之車輛經監視器拍下之\n    畫面上時間（2時29分31秒）此段時間內，行駛在臺南縣永\n    康市○○路北往南方向之車輛亦不在少數，其中也不乏車牌\n    號碼中之有數字「7」的自小客車（見原審卷第47頁正、背\n    面之勘驗筆錄），堪認證人乙○○非無誤認其他車輛為被告\n    所駕駛之自小客車之可能性。\n  3.又依證人乙○○所證，被告車子在壓到東西後，有輕輕的將\n    車身左右擺動，之後有一個從外車道切到內車道的較大動作\n    將腳踏車拖到路中間，並因此甩開該東西，脫離之後被告車\n    輛走掉，被告拖行腳踏車時的車速大約十公里左右，很慢的\n    等語，經與核交卷第20頁背面至第23頁背面之腳踏車照片、\n    警卷第23頁之腳踏車照片以及警卷第18頁之現場圖相核對後\n    ，本院認有下列不合常理之處：\n    (1)從腳踏車照片觀之，告訴人腳踏車之損壞處乃在後車輪擋\n      泥板之位置，可見告訴人之腳踏車應係被自小客車從正後\n      方撞擊，又依告訴人所述其所騎乘之腳踏車後方載有一個\n      大的藍色塑膠箱，依該塑膠箱的大小、寬度、長度觀之，\n      被告自小客車應不易壓住告訴人腳踏車拖行。\n    (2)依證人乙○○所言，被告自小客車壓住告訴人腳踏車拖行\n      一段距離，則告訴人腳踏車之車輪或車身某處依理應會有\n      因擠壓而變形之處，但照片中未見腳踏車有何變形之情形\n      。又告訴人所騎乘之腳踏車如由被告所駕駛之自小客車壓\n      住並拖行一段距離，則告訴人之腳踏車亦應有一側車身與\n      地面摩擦而有嚴重擦痕及掉漆之情形，但照片中並未見到\n      腳踏車有此情形（如藍色塑膠箱未與腳踏車脫離，亦應有\n      嚴重擦痕，亦未見此情形）。\n    (3)又如被告之自小客車壓住告訴人腳踏車拖行一段距離，即\n      告訴人腳踏車被汽車保險桿或車身卡住而被拖行，揆諸常\n      情應非被告之自小客車慢慢開、左右甩動即能甩開；另參\n      酌現場圖上所繪之刮地痕觀之，該刮地痕係發生在機慢車\n      道上，而且是以近似直線之方式由機慢車道向右斜偏至路\n      旁停止，並非向左斜偏往汽車慢車道（即第二汽車道），\n      亦非左右甩擺之曲線，又被告自小客車壓住告訴人腳踏車\n      拖行一段距離，則刮地痕之終止處應與告訴人腳踏車被牽\n      起扶正處接近，但依現場圖所繪之距離，兩者間卻相距有\n      11.5公尺之遠。從而依證人乙○○證述被告自小客車往左\n      往右擺動將腳踏車拖到路中間甩開乙節即與前揭現場圖所\n      示之刮地痕顯不相符合。\n    (4)因此，依核交卷第20頁背面至第23頁背面之腳踏車照片以\n      及警卷第18頁之現場圖觀之，告訴人之腳踏車應係先被他\n      車自正後方撞擊，嗣後因被告恰亦駕駛自小客車到腳踏車\n      停止處前方，被告為閃避該腳踏車而自慢車道左閃駛入內\n      車道，故本院認被告辯稱其乃係看到前方有黑黑的東西，\n      就把車閃進內車道內等語，應為可信。而且證人乙○○在\n      光線昏暗之100公尺遠處看到被告之自小客車閃進內車道\n      ，亦有誤認被告之自小客車閃進內車道是要把告訴人腳踏\n      車甩開之可能。\n  4.經將證人乙○○之證言與上開相關事證相核，因證人乙○○\n    之證言與相關事證有上述不吻合之處，證人乙○○不無誤認\n    之可能，是證人乙○○之證言應不足採為不利被告之證據。\n  (三)再查，依公訴人將被告所駕駛之自小客車與告訴人之腳踏車\n    送請臺南縣警察局鑑識課比對二車受損情形是否相符合，經\n    鑑識後並未發現兩車間有可疑之轉移漆痕，有該勘查採證報\n    告在卷可稽（見核交卷第14至15頁），又本院審酌告訴人之\n    腳踏車被碰撞處為後輪檔泥板處，有該腳踏車照片在卷可稽\n    （見核交卷第23頁背面），該被碰撞處之高度經與被告所駕\n    駛之自小客車（含保險桿）之高度比對後，兩者間亦有所落\n    差，是難認二車有發生碰撞之情形。\n    雖公訴人認被告事後更換保險桿，有影響鑑定結果，惟查，\n    如前所述，舉證責任應由公訴人負擔，本件公訴人如認有鑑\n    定之必要，本應於事故發生後偵查之初立即請鑑定機關鑑定\n    ，至少也應立即扣押被告車輛或限制被告不可修理車輛，然\n    公訴人未立即鑑定，也未為扣押或限制修理之處分，而係遲\n    至6個月以後才請鑑定機關鑑定，因此，本院認即使因被告\n    更換保險桿而影響鑑定結果，亦係公訴人之消極偵查行為所\n    致，自不得嗣後據為被告確有肇事逃逸並卸責之情事而為不\n    利被告之主張。\n六、綜上所述，告訴人甲○之指述及證人乙○○之證述，尚不能\n    推認被告確有公訴意旨所指肇事逃逸及過失傷害之犯行。至\n    卷附之臺南縣警察局永康分局道路交通事故現場圖1紙、交\n    通事故調查報告表(一)、(二)各1份、道路交通事故現場及腳踏\n    車車損照片6張、肇事地點監視器翻拍畫面2張、被告自小客\n    車車損照片5張及財團法人奇美醫院診斷證明書1紙等件，僅\n    能證明被告於前揭時、地，確曾駕駛上開自小客車約於本件\n    案發時行經肇事地點，及告訴人甲○因車禍事故受有頭部外\n    傷之傷害而已，尚難據此等證據遽認被告確曾駕駛上開自小\n    客車，於前揭時、地自後追撞告訴人腳踏車而發生車禍，並\n    致告訴人甲○受有上揭傷害後逃逸，是自難以肇事逃逸罪及\n    過失傷害罪相繩。\n七、綜上，本件公訴意旨所提之證據均未達到於通常之人均不致\n    有所懷疑，而得確信其為真實之程度，尚不能遽為被告有罪\n    之判斷，故被告被訴涉犯公共危險及過失傷害犯行應屬不能\n    證明，此外，本院復查無其他積極證據足以證明被告確有公\n    訴人所指上揭犯行，自屬不能證明被告犯罪，揆諸上開說明\n    ，自應為被告無罪之諭知。原審以不能證明被告犯罪而諭知\n    無罪之判決，核無不合，檢察官上訴意旨略以：\n    (1)原審僅以證人乙○○所述之事發時間（2時25分）至被告\n    所駕駛之車輛經監視器拍下之畫面上時間（2時29分31秒）\n    之4分許期間內之自小客車行經數非少、其中亦不乏車牌號\n    碼中之有數字「7」的自小客車，而推認證人乙○○有所誤\n    認等情，非無研求之餘地。(2)依證人乙○○於聽聞巨響，並\n    見告訴人所騎腳踏車遭上開自小客車輕微拖行、甩動，隨即\n    騎車至事故現場察看，並見告訴人遭撞在地，時間過程緊接\n    ，益認被告為本件交通事故肇事者。(3)再者，認定犯罪事實\n    所憑之證據，並不以直接證據為限，而本件綜合以上所述之\n    間接證據，應已達通常一般之人均不致有所懷疑，而得確信\n    其為真實之程度。原判決置本案間接證據於不顧，與判例意\n    旨相違云云，指摘原判決認定事實適用法律不當，惟查，\n    本件依告訴人甲○之指述及證人乙○○之證述，參酌現場圖\n    中刮地痕位置及告訴人與被告車輛損害之各種跡證，尚不能\n    證明被告確有公訴意旨所指肇事逃逸及過失傷害之犯行，已\n    如上述，是檢察官上開所指尚無足採，其上訴並無理由，應\n    予駁回。\n八、據上論結，應依刑事訴訟法第368條，判決如主文。\n本案經檢察官羅清溪到庭執行職務。"
  },
  "characters": {
    "judges": [
      "吳志誠",
      "彭喜有",
      "羅心芳"
    ],
    "prosecutors": [
      "羅清溪"
    ],
    "lawyers": [
      "許安德利",
      "許世"
    ],
    "clerks": [
      "蔡振豐"
    ],
    "plaintiffs": [

    ],
    "defendants": [
      "丙○○"
    ],
    "prosecutor_office": [

    ],
    "creditors": [

    ],
    "debtors": [

    ],
    "judicial_associate_officer": [

    ]
  },
  "adjudged_at": "2010-01-05",
  "created_at": "2016-01-05 15:08:01",
  "updated_at": "2016-01-05 15:08:01"
}