{
  "identify": "TNH-99-上訴-274-20100512-1",
  "court": {
    "name": "臺灣高等法院",
    "code": "TNH"
  },
  "division": {
    "name": "刑事",
    "code": "M"
  },
  "year": 99,
  "word": "上訴",
  "number": "274",
  "jcheck": "1",
  "reason": "偽造文書等",
  "content": "臺灣高等法院臺南分院刑事判決         99年度上訴字第274號\n上  訴  人  臺灣嘉義地方法院檢察署檢察官\n被      告  乙○○\n上列上訴人因被告偽造文書等案件，不服臺灣嘉義地方法院九十\n八年度訴字第三六０號中華民國九十八年十二月三十一日第一審\n判決（起訴案號：臺灣嘉義地方法院檢察署九十七年度偵字第六\n三二八號），提起上訴，本院判決如下：\n    主  文\n上訴駁回。\n    理  由\n一、公訴意旨略以：被告乙○○明知於九十七年七月間，向丙○\n    ○（原審另案處理）所購買之扣案車身號碼Ｋ一一ＧＬＡ０\n    二五九四五號、引擎號碼Ｋ一一ＧＬＡ二六０七七號（屬車\n    牌號碼二九六三─ＵＬ號之車身及引擎號碼）、外觀為銀灰\n    色之日產自小客車，係來源不明之贓物（車牌號碼Ｓ六─一\n    八五五號自小客車之車主為甲○○，車身號碼Ｋ一一ＧＬＡ\n    ０四０一七七號、引擎號碼為Ｋ一一ＧＬＡ四０一三Ｙ號，\n    於九十七年七月二十四日下午五時四十五分許在嘉義市失竊\n    ），竟基於故買贓物之犯意，以新臺幣八萬元之價格收購之\n    ，因認被告涉有刑法第三百四十九條第二項之故買贓物罪嫌\n    等語（乙○○另犯贓物及偽造文書罪，業經原審分別判處有\n    期徒刑三月、三月，並定應執行刑為有期徒刑五月，未據上\n    訴，業已確定在案）。\n二、按犯罪事實應依證據認定之，無證據不得認定犯罪事實；不\n    能證明被告犯罪者，應諭知無罪之判決，刑事訴訟法第一百\n    五十四條第二項、第三百零一條第一項分別定有明文。又認\n    定不利於被告之事實，須依積極證據，苟積極證據不足為不\n    利於被告事實之認定時，即應為有利於被告之認定，更不必\n    有何有利之證據（最高法院著有三十年上字第八一六號判例\n    意旨參照）。再按事實之認定應憑證據，如未能發現相當證\n    據，或證據不足以證明，自不能以推測或擬制之方法，為裁\n    判基礎（最高法院四十年臺上字第八六號判例意旨參照）。\n    復按認定犯罪事實所憑之證據，雖不以直接證據為限，間接\n    證據亦包括在內；然而無論直接或間接證據，其為訴訟上之\n    證明，須於通常一般之人均不致有所懷疑，而得確信其為真\n    實之程度者，始得據為有罪之認定，倘其證明尚未達到此一\n    程度，而有合理之懷疑存在，無從使事實審法院得有罪之確\n    信時，即應由法院諭知被告無罪之判決（最高法院七十六年\n    臺上字第四九八六號判例意旨參照）。\n三、查本案所引用之下列供述及非供述證據，經本院依法踐行調\n    查證據程序時，檢察官、被告均不爭執各該證據之證據能力\n    ，且亦查無依法應予排除之情形，應認均具有證據能力，合\n    先敘明。\n四、公訴人認被告涉有上開故買贓物罪嫌，係以證人即告訴人甲\n    ○○於警詢及原審審理中之證述、搜索查獲車身號碼Ｋ一一\n    ＧＬＡ０二五九四五號、引擎號碼Ｋ一一ＧＬＡ二六０七七\n    號、外觀為銀灰色之日產自小客車1部為其論據。\n五、訊據被告堅決否認有公訴意旨所指之此部分故買贓物犯行，\n    辯稱：上開查扣之銀灰色自小客車是伊於九十七年一月間向\n    丙○○購入，後因難以賣出而一直停放在伊車行內，且於九\n    十七年三月間即向監理站辦理停駛，而告訴人甲○○之自小\n    客車係在伊過戶後之九十七年七月二十四日始遭竊，查獲之\n    銀灰色自小客車並非甲○○遭竊之贓車等語。經查：\n（一）被告前於九十七年一月三十一日將車牌號碼二九六三─Ｕ\n      Ｌ號、車身號碼Ｋ一一ＧＬＡ０二五九四五號、引擎號碼\n      Ｋ一一ＧＬＡ二六０七七號、顏色登記為銀色之自小客車\n      辦理過戶登記於其名下，復因自九十七年三月十二日辦理\n      停駛後，已逾一年，經交通部公路總局嘉義區監理所嘉義\n      市監理站（下稱嘉義市監理站）於九十八年四月六日通知\n      逾期註銷牌照等情，有車籍查詢資料、汽車過戶登記書、\n      嘉義市監理站九十八年九月十八日嘉監義一字第０九八０\n      一０七四六六號函及通知書影本在卷可稽（見偵查卷第二\n      十四頁、原審卷第七十七、八十八至八十九頁）；又經警\n      於九十七年九月三日在被告經營之「佳勝汽車商行」搜索\n      查獲之銀灰色自小客車，其車身號碼為Ｋ一一ＧＬＡ０二\n      五九四五號、引擎號碼Ｋ一一ＧＬＡ二六０七七號，有車\n      身號碼拓印資料及車身及引擎號碼照片在卷可稽（見警卷\n      第五十六頁、原審卷第六十三至六十五頁），而經警勘察\n      結果，除該車前後均無懸掛車牌外，其餘外觀大致完整，\n      且車身號碼經先已砂布磨過後，再以ＤＡＶＩＳ溶液電解\n      ，發現該車身號碼為「Ｋ一一ＧＬＡ０二五九四五號」，\n      有嘉義市政府警察局勘察報告一份在卷可稽（見原審卷第\n      六十至六十五頁）。上開自用小客車係被告向丙○○所買\n      ，買受當時之車況與原審審理卷第六十一頁至六十六頁所\n      附照片之情形相符等情，復據證人丙○○於本院審理時結\n      證在卷（見本院卷第五十四頁）。被告抗辯上開自用小客\n      車係登記伊名下之車牌號碼二九六三─ＵＬ號之自小客車\n      車身，應可採信。\n（二）證人甲○○雖於警詢及原審審理時證述：警察查獲當日伊\n      前往指認車輛，發現車子底漆為綠色、水箱有撞過矯正之\n      痕跡，且置物箱內有買車懸掛紅花布之塑膠屑、擋風玻璃\n      及電瓶等均與伊於九十七年七月二十四日在嘉義市○○○\n      路三九七巷轉角失竊之車牌號碼Ｓ六─一八五五號自小客\n      車相同等語（見原審卷第一百三十五至一百三十八頁）；\n      惟其於原審審理時亦證稱：因為警察當時查失竊紀錄，只\n      有伊之車輛符合，而且只有伊報案，所以才去指認，當時\n      伊有看該車之引擎，但不能確定引擎是不是伊車所有等語\n      （見原審卷第一百三十九至一百四十頁）；參以被告名下\n      亦登記有與告訴人甲○○相同廠牌款式之裕隆日產自小客\n      車；且經證人即原擔任被告車行之修車人員黃世谷於原審\n      審理時證述：被告於九十七年一月間購入銀灰色自小客車\n      後，伊與被告一同去將車牽回來至被查獲時，均放在工廠\n      內沒有使用，且伊有觀看該銀灰色自小客車車頭並無撞過\n      重新焊接、板金之痕跡，亦無變更過該車之顏色等語（見\n      原審卷第一百四十至一百四十五頁）；而告訴人甲○○指\n      認之車子底漆乃為該日產自小客車原產顏色，不具有特殊\n      性，另所指認之塑膠屑、擋風玻璃及電瓶，亦為可替代物\n      ，故本案查扣之車輛，尚難認係甲○○所失竊之車牌號碼\n      Ｓ六─一八五五號自小客車。\n（三）又車輛之車身號碼及引擎號碼如同人之身分證字號，係作\n      為判斷該車車籍是否同一之依據，除該車身號碼及引擎號\n      碼經偽造、變造外，其內裝配備是否拆換，並不影響車籍\n      同一之認定。依上開勘察報告可知，本案查獲銀灰色自小\n      客車，經以ＤＡＶＩＳ溶液電解結果，原車身號碼為「Ｋ\n      一一ＧＬＡ０二五九四五號」，與被告於九十七年一月三\n      十一日過戶登記之車牌號碼二九六三─ＵＬ號自小客車之\n      車身號碼顯屬相同；員警於九十七年九月三日搜索被告車\n      行現場，復查扣另案被告陳建興所駕駛懸掛車牌號碼九一\n      三五─ＧＫ號之自小客車，該車車身號碼處發現明顯焊接\n      過，即車身號碼處遭整片切割後焊接另一車身號碼等情，\n      亦有上開勘察報告及卷附照片可稽（見警卷第六十六頁、\n      原審卷第三十九至四十四頁）；而本案銀灰色自小客車之\n      車身號碼處之底漆確為綠色，且與該車車身連為一體，依\n      肉眼觀之亦無切割、焊接痕跡，有該車輛車身號碼處照片\n      可稽（見原審卷第六十三至六十四頁）；參酌該銀灰色自\n      小客車經警勘察結果，其外觀大致完整；且經證人黃世谷\n      於原審審理時亦證述該銀灰色自小客車並無重新焊接板金\n      之痕跡等語，均如前所述，足認該銀灰色之原車身號碼即\n      為Ｋ一一ＧＬＡ０二五九四五號無訛，並無以其他車身號\n      碼焊接為查獲銀灰色自小客車車身加以偽造之疑，復無證\n      據證明該引擎號碼Ｋ一一ＧＬＡ二六０七七號係經偽造或\n      更替。復查無其他積極證據足認扣案之自用小客車為甲○\n      ○失竊之自用小客車，或為警查扣之銀灰色自小客車之車\n      身號碼Ｋ一一ＧＬＡ０二五九四五號、引擎號碼Ｋ一一Ｇ\n      ＬＡ二六０七七號係經偽造，自不能遽認被告有公訴人所\n      指之此部分故買贓物犯行，揆諸上開說明，自應為無罪之\n      諭知。\n六、原審以被告犯罪不能證明，諭知被告無罪，核其認事用法均\n    無不合。檢察官上訴意旨並未提出積極證據以供本院審酌，\n    仍執陳詞，任意指摘原判決不當，為無理由，應予駁回。\n七、據上論斷，應依刑事訴訟法第三百六十八條，判決如主文。\n本案經檢察官謝錫和到庭執行職務。\n中    華    民    國    99    年    5     月    12    日\n                  刑事第二庭    審判長法  官  葉居正\n                                      法  官  洪碧雀\n                                      法  官  陳春長\n以上正本證明與原本無異。\n不得上訴。\n                                      書記官  林宛妮\n中    華    民    國    99    年    5     月    12    日",
  "structure": {
    "main": "上訴駁回。",
    "reason": "一、公訴意旨略以：被告乙○○明知於九十七年七月間，向丙○\n    ○（原審另案處理）所購買之扣案車身號碼Ｋ一一ＧＬＡ０\n    二五九四五號、引擎號碼Ｋ一一ＧＬＡ二六０七七號（屬車\n    牌號碼二九六三─ＵＬ號之車身及引擎號碼）、外觀為銀灰\n    色之日產自小客車，係來源不明之贓物（車牌號碼Ｓ六─一\n    八五五號自小客車之車主為甲○○，車身號碼Ｋ一一ＧＬＡ\n    ０四０一七七號、引擎號碼為Ｋ一一ＧＬＡ四０一三Ｙ號，\n    於九十七年七月二十四日下午五時四十五分許在嘉義市失竊\n    ），竟基於故買贓物之犯意，以新臺幣八萬元之價格收購之\n    ，因認被告涉有刑法第三百四十九條第二項之故買贓物罪嫌\n    等語（乙○○另犯贓物及偽造文書罪，業經原審分別判處有\n    期徒刑三月、三月，並定應執行刑為有期徒刑五月，未據上\n    訴，業已確定在案）。\n二、按犯罪事實應依證據認定之，無證據不得認定犯罪事實；不\n    能證明被告犯罪者，應諭知無罪之判決，刑事訴訟法第一百\n    五十四條第二項、第三百零一條第一項分別定有明文。又認\n    定不利於被告之事實，須依積極證據，苟積極證據不足為不\n    利於被告事實之認定時，即應為有利於被告之認定，更不必\n    有何有利之證據（最高法院著有三十年上字第八一六號判例\n    意旨參照）。再按事實之認定應憑證據，如未能發現相當證\n    據，或證據不足以證明，自不能以推測或擬制之方法，為裁\n    判基礎（最高法院四十年臺上字第八六號判例意旨參照）。\n    復按認定犯罪事實所憑之證據，雖不以直接證據為限，間接\n    證據亦包括在內；然而無論直接或間接證據，其為訴訟上之\n    證明，須於通常一般之人均不致有所懷疑，而得確信其為真\n    實之程度者，始得據為有罪之認定，倘其證明尚未達到此一\n    程度，而有合理之懷疑存在，無從使事實審法院得有罪之確\n    信時，即應由法院諭知被告無罪之判決（最高法院七十六年\n    臺上字第四九八六號判例意旨參照）。\n三、查本案所引用之下列供述及非供述證據，經本院依法踐行調\n    查證據程序時，檢察官、被告均不爭執各該證據之證據能力\n    ，且亦查無依法應予排除之情形，應認均具有證據能力，合\n    先敘明。\n四、公訴人認被告涉有上開故買贓物罪嫌，係以證人即告訴人甲\n    ○○於警詢及原審審理中之證述、搜索查獲車身號碼Ｋ一一\n    ＧＬＡ０二五九四五號、引擎號碼Ｋ一一ＧＬＡ二六０七七\n    號、外觀為銀灰色之日產自小客車1部為其論據。\n五、訊據被告堅決否認有公訴意旨所指之此部分故買贓物犯行，\n    辯稱：上開查扣之銀灰色自小客車是伊於九十七年一月間向\n    丙○○購入，後因難以賣出而一直停放在伊車行內，且於九\n    十七年三月間即向監理站辦理停駛，而告訴人甲○○之自小\n    客車係在伊過戶後之九十七年七月二十四日始遭竊，查獲之\n    銀灰色自小客車並非甲○○遭竊之贓車等語。經查：\n（一）被告前於九十七年一月三十一日將車牌號碼二九六三─Ｕ\n      Ｌ號、車身號碼Ｋ一一ＧＬＡ０二五九四五號、引擎號碼\n      Ｋ一一ＧＬＡ二六０七七號、顏色登記為銀色之自小客車\n      辦理過戶登記於其名下，復因自九十七年三月十二日辦理\n      停駛後，已逾一年，經交通部公路總局嘉義區監理所嘉義\n      市監理站（下稱嘉義市監理站）於九十八年四月六日通知\n      逾期註銷牌照等情，有車籍查詢資料、汽車過戶登記書、\n      嘉義市監理站九十八年九月十八日嘉監義一字第０九八０\n      一０七四六六號函及通知書影本在卷可稽（見偵查卷第二\n      十四頁、原審卷第七十七、八十八至八十九頁）；又經警\n      於九十七年九月三日在被告經營之「佳勝汽車商行」搜索\n      查獲之銀灰色自小客車，其車身號碼為Ｋ一一ＧＬＡ０二\n      五九四五號、引擎號碼Ｋ一一ＧＬＡ二六０七七號，有車\n      身號碼拓印資料及車身及引擎號碼照片在卷可稽（見警卷\n      第五十六頁、原審卷第六十三至六十五頁），而經警勘察\n      結果，除該車前後均無懸掛車牌外，其餘外觀大致完整，\n      且車身號碼經先已砂布磨過後，再以ＤＡＶＩＳ溶液電解\n      ，發現該車身號碼為「Ｋ一一ＧＬＡ０二五九四五號」，\n      有嘉義市政府警察局勘察報告一份在卷可稽（見原審卷第\n      六十至六十五頁）。上開自用小客車係被告向丙○○所買\n      ，買受當時之車況與原審審理卷第六十一頁至六十六頁所\n      附照片之情形相符等情，復據證人丙○○於本院審理時結\n      證在卷（見本院卷第五十四頁）。被告抗辯上開自用小客\n      車係登記伊名下之車牌號碼二九六三─ＵＬ號之自小客車\n      車身，應可採信。\n（二）證人甲○○雖於警詢及原審審理時證述：警察查獲當日伊\n      前往指認車輛，發現車子底漆為綠色、水箱有撞過矯正之\n      痕跡，且置物箱內有買車懸掛紅花布之塑膠屑、擋風玻璃\n      及電瓶等均與伊於九十七年七月二十四日在嘉義市○○○\n      路三九七巷轉角失竊之車牌號碼Ｓ六─一八五五號自小客\n      車相同等語（見原審卷第一百三十五至一百三十八頁）；\n      惟其於原審審理時亦證稱：因為警察當時查失竊紀錄，只\n      有伊之車輛符合，而且只有伊報案，所以才去指認，當時\n      伊有看該車之引擎，但不能確定引擎是不是伊車所有等語\n      （見原審卷第一百三十九至一百四十頁）；參以被告名下\n      亦登記有與告訴人甲○○相同廠牌款式之裕隆日產自小客\n      車；且經證人即原擔任被告車行之修車人員黃世谷於原審\n      審理時證述：被告於九十七年一月間購入銀灰色自小客車\n      後，伊與被告一同去將車牽回來至被查獲時，均放在工廠\n      內沒有使用，且伊有觀看該銀灰色自小客車車頭並無撞過\n      重新焊接、板金之痕跡，亦無變更過該車之顏色等語（見\n      原審卷第一百四十至一百四十五頁）；而告訴人甲○○指\n      認之車子底漆乃為該日產自小客車原產顏色，不具有特殊\n      性，另所指認之塑膠屑、擋風玻璃及電瓶，亦為可替代物\n      ，故本案查扣之車輛，尚難認係甲○○所失竊之車牌號碼\n      Ｓ六─一八五五號自小客車。\n（三）又車輛之車身號碼及引擎號碼如同人之身分證字號，係作\n      為判斷該車車籍是否同一之依據，除該車身號碼及引擎號\n      碼經偽造、變造外，其內裝配備是否拆換，並不影響車籍\n      同一之認定。依上開勘察報告可知，本案查獲銀灰色自小\n      客車，經以ＤＡＶＩＳ溶液電解結果，原車身號碼為「Ｋ\n      一一ＧＬＡ０二五九四五號」，與被告於九十七年一月三\n      十一日過戶登記之車牌號碼二九六三─ＵＬ號自小客車之\n      車身號碼顯屬相同；員警於九十七年九月三日搜索被告車\n      行現場，復查扣另案被告陳建興所駕駛懸掛車牌號碼九一\n      三五─ＧＫ號之自小客車，該車車身號碼處發現明顯焊接\n      過，即車身號碼處遭整片切割後焊接另一車身號碼等情，\n      亦有上開勘察報告及卷附照片可稽（見警卷第六十六頁、\n      原審卷第三十九至四十四頁）；而本案銀灰色自小客車之\n      車身號碼處之底漆確為綠色，且與該車車身連為一體，依\n      肉眼觀之亦無切割、焊接痕跡，有該車輛車身號碼處照片\n      可稽（見原審卷第六十三至六十四頁）；參酌該銀灰色自\n      小客車經警勘察結果，其外觀大致完整；且經證人黃世谷\n      於原審審理時亦證述該銀灰色自小客車並無重新焊接板金\n      之痕跡等語，均如前所述，足認該銀灰色之原車身號碼即\n      為Ｋ一一ＧＬＡ０二五九四五號無訛，並無以其他車身號\n      碼焊接為查獲銀灰色自小客車車身加以偽造之疑，復無證\n      據證明該引擎號碼Ｋ一一ＧＬＡ二六０七七號係經偽造或\n      更替。復查無其他積極證據足認扣案之自用小客車為甲○\n      ○失竊之自用小客車，或為警查扣之銀灰色自小客車之車\n      身號碼Ｋ一一ＧＬＡ０二五九四五號、引擎號碼Ｋ一一Ｇ\n      ＬＡ二六０七七號係經偽造，自不能遽認被告有公訴人所\n      指之此部分故買贓物犯行，揆諸上開說明，自應為無罪之\n      諭知。\n六、原審以被告犯罪不能證明，諭知被告無罪，核其認事用法均\n    無不合。檢察官上訴意旨並未提出積極證據以供本院審酌，\n    仍執陳詞，任意指摘原判決不當，為無理由，應予駁回。\n七、據上論斷，應依刑事訴訟法第三百六十八條，判決如主文。\n本案經檢察官謝錫和到庭執行職務。"
  },
  "characters": {
    "judges": [
      "葉居正",
      "洪碧雀",
      "陳春長"
    ],
    "prosecutors": [
      "謝錫和"
    ],
    "lawyers": [

    ],
    "clerks": [
      "林宛妮"
    ],
    "plaintiffs": [

    ],
    "defendants": [
      "乙○○"
    ],
    "prosecutor_office": [

    ],
    "creditors": [

    ],
    "debtors": [

    ],
    "judicial_associate_officer": [

    ]
  },
  "adjudged_at": "2010-05-12",
  "created_at": "2016-01-05 12:00:45",
  "updated_at": "2016-01-05 12:00:45"
}