{
  "identify": "TNH-99-上更(一)-45-20100512-1",
  "court": {
    "name": "臺灣高等法院",
    "code": "TNH"
  },
  "division": {
    "name": "刑事",
    "code": "M"
  },
  "year": 99,
  "word": "上更(一)",
  "number": "45",
  "jcheck": "1",
  "reason": "毒品危害防制條例",
  "content": "臺灣高等法院臺南分院刑事判決      99年度上更(一)字第45號\n上  訴  人  臺灣臺南地方法院檢察署檢察官\n被      告  甲○○\n選任辯護人  楊惠雯律師（法律扶助律師）\n上列上訴人因被告違反毒品危害防制條例案件，不服臺灣臺南地\n方法院97年度訴字第1885號中華民國98年4月23日第一審判決（\n起訴案號：臺灣臺南地方法院檢察署97年度偵字第2665號），提\n起上訴，判決後經最高法院發回更審，本院判決如下：\n    主  文\n上訴駁回。\n    理  由\n一、公訴意旨略以：甲○○與其同居男友李文毅（另案審理）基\n    於販賣第一級毒品海洛因之犯意聯絡，以0000000000號行動\n    電話為聯絡交易毒品之工具，於96年6月6日上午，由甲○○\n    接聽金志峰電話，並與金志峰約在臺南縣柳營鄉柳營橋下加\n    油站對面，由李文毅攜帶新臺幣（下同）500元之海洛因前\n    往販賣予金志峰（原檢察官起訴範圍如附表所示，其中編號\n    1.2.3.部分原審為無罪諭知，經本院上訴審駁回上訴確定；\n    編號5.部分經本院上訴審改判處有期徒刑七年六月，經最高\n    法院判決上訴駁回確定）。經實施通訊監察及於96年7月12\n    日13時27分許搜索其與李文毅臺南縣柳營鄉○○路○段275巷\n    2號同居處，扣得甲○○所有中型夾鏈袋5包、小型夾鏈袋1\n    包、NOKIA牌行動電話1支（門號0000000000、序號00000000\n    0000000）、UTEC牌行動電話1支（無SIM卡、序號000000000\n    000000），因認甲○○涉犯毒品危害防制條例第四條第一項\n    販賣第一級毒品罪嫌云云。\n二、按犯罪事實應依證據認定之，無證據不得認定犯罪事實；不\n    能證明被告犯罪者，應諭知無罪之判決，刑事訴訟法第一百\n    五十四條第二項、第三百零一條第一項，分別定有明文。又\n    按檢察官就被告犯罪事實，應負舉證責任，並指出證明之方\n    法，為刑事訴訟法第一百六十一條第一項所明定。因此，檢\n    察官對於起訴之犯罪事實，應負提出證據及說服之實質舉證\n    責任；倘其所提出之證據，不足為被告有罪之積極證明，或\n    其指出證明之方法，無從說服法院以形成被告有罪之心證，\n    基於無罪推定之原則，自應為被告無罪判決之諭知（最高法\n    院92年台上字第128號判例參照）。另按施用毒品者，其所\n    稱向某人購買之供述，須補強證據以擔保其供述之真實性。\n    良以施用毒品者，其供述之憑信性本不及於一般人，況施用\n    毒品者，其供出來源因而破獲者，法律復規定得減輕其刑，\n    其有為偵查機關誘導、或為邀輕典而為不實之陳述之可能，\n    其供述之真實性自有合理之懷疑。故認施用毒品者，關於其\n    向某人購買毒品之供述，必須補強證據佐證，以擔保其供述\n    之真實性，俾貫徹刑事訴訟無罪推定及嚴格證明之基本原則\n    。又關於毒品施用者其所稱向某人購買毒品之供述，必須補\n    強證據佐證，係指毒品購買者之供述縱使並無瑕疵，仍須補\n    強證據佐證而言，以擔保其供述之真實性。該所謂補強證據\n    ，必須與施用毒品者關於相關毒品交易之供述，具有相當程\n    度之關聯性，且足使一般人對於施用毒品者之供述無合理之\n    懷疑存在，而得確信其為真實，始足當之（最高法院96年台\n    上字第1029號判例參照）。\n三、本件公訴意旨認被告甲○○有上揭販賣第一級毒品之犯行，\n    無非係以(1)被告甲○○供述0000000000號行動電話為其所申\n    請，與李文毅交替使用；(2)證人金志峰於警詢證述有於上開\n    時地撥打0000000000號行動電話，由被告甲○○接聽並向伊\n    購買海洛因；(3)上開行動電話之通訊監聽譯文顯示被告甲○\n    ○有於上開時間與證人金志峰通話；(4)扣案之中型夾鏈袋5\n    個、小型夾鏈袋1個及行動電話手機2支間接證明被告甲○○\n    有販賣上開毒品等為其論據。惟訊據被告甲○○堅決否認有\n    上開販賣第一級毒品海洛因予金志峰之犯行，並辯稱：其未\n    販賣第一級毒品海洛因予證人金志峰，且電話監聽譯文之通\n    話者，非其聲音等語。\n四、經查：證人金志峰於警詢證稱：「我認識警方所提示綽號「\n    毅仔」男子與他女友，我持用0000000000號是我本人申請的\n    門號，也只有我個人在使用該門號。都稱呼我「黑狗」之綽\n    號。我以0000000000號打給毅仔及他女友（甲○○）二人共\n    同持用0000000000號門號取得連絡。我打電話給他們都是要\n    毅仔及他女友向他們買俗稱4號的海洛因毒品。就只有買毒\n    品才有金錢上的往來。我於96年4月間開始施打之海洛因毒\n    品是向警方偵辦對象之「毅仔」及他女友（即甲○○）二人\n    購得施用的，他們的連絡電話是「阿龍」給我的，我打0000\n    000000號電話連絡時，有時是「毅仔」接的，有時是他女友\n    （即甲○○）接的。我都講要「一」，「毅仔」他們就知道\n    了，之前他們會約臺南縣新營市○○路上有一家「明治釣蝦\n    場」旁的巷道、臺南縣新營市○○街「龍銀遊藝場」外面旁\n    ，後來這段時間就都約在臺南縣柳營鄉要過新營市○○○○\n    ○路邊或是橋下的上帝爺廟前交易，1小包海洛因是1000元\n    。我與「毅仔」及他女友（即甲○○）有當面交易過海洛因\n    毒品，在上述的地點都曾交易過，有時「毅仔」他與女友（\n    即甲○○）都在一起，有時他女友（即甲○○）自己拿毒品\n    出來賣給我，均是電話連絡約定交易地點。經我指認是編號\n    1號男子就是「毅仔」沒錯。經我指認是編號3號女子就是「\n    毅仔」他的女友（即甲○○）沒錯。李文毅及甲○○持毒品\n    前往與我交易時常會共乘一部豪邁重機車。（提示2007/06/\n    0610：48：19、06/0610：58：52之二次通話內容）我是打0\n    000000000號電話是「毅仔」女友（即甲○○）接的，我要\n    買海洛因毒品，她跟我約在臺南縣柳營鄉柳營橋要過新營市\n    橋下的紅綠燈，該處就是中油加油站的斜對面，第二通我向\n    她說我到達了，她回答我「毅仔」在那邊了，當時是「毅仔\n    」與我交易的，我買500元半小包海洛因」等語（見警卷第4\n    5至51頁）。惟證人金志峰經本院傳喚到庭結證：「（問：\n    為何你在警局跟警察說你在96年6月6日有買過毒品？）隨便\n    大約講的」；「（問：你在96年7月30日警詢中，你告訴警\n    察說你曾經向李文毅、甲○○購買二十多次海洛因毒品？）\n    有跟男生買，沒有跟女生買」；「（當時也指認李文毅的女\n    朋友就是在庭的甲○○）照片的臉不太一樣」（見本院更一\n    審卷第74、75頁）。證人金志峰上開警詢供述與到庭結證所\n    陳，顯不相同，自難依據未經具結之證人警詢供述，為認定\n    被告犯罪事實之證據。\n五、又證人金志峰於本院之結證與警詢所為供述，互不一致，宜\n    就被告對其警詢供述之彈劾或為補強證據予以調查，作為認\n    定事實之證據。依上開最高法院96年臺上字第1029號判例意\n    旨，證人金志峰警詢所述，尚須補強證據以擔保其供述之真\n    實性。而補強證據，必須與該施用毒品者關於相關毒品交易\n    之供述，具有相當程度之關連性，因該補強證據之佐證，足\n    使一般人對於施用毒品之供述無合理之懷疑存在，而得確信\n    其為真實，始足當之。本件96年6月6日之電話監聽錄音，經\n    被告甲○○否認為其聲音，本院依其聲請函送法務部調查局\n    為聲紋鑑定，據該局鑑定報告檢驗結果，認為錄音品質不佳\n    ，致聲紋共振峰圖譜特徵模糊，不符聲紋鑑定條件，無法作\n    聲紋比對鑑定，有法務部調查局99年4月6日調科參字第0990\n    0133600號聲紋鑑定報告書一紙在卷可參（見本院更一審卷\n    第56至58頁），是本案已無法藉由鑑定聲紋方式，確認卷附\n    96年6月6日之電話監聽錄音係被告甲○○之通話。復查卷附\n    之通聯紀錄（見警卷第210頁至230頁），更無96年6月6日上\n    午10時48分19秒及10時58分52秒，由證人金志峰以其持用之\n    0000000000號行動電話撥打被告甲○○與李文毅共同持用之\n    0000000000號行動電話之通聯紀錄，是被告否認卷附之96年\n    6月6日電話監聽錄音之通話，非其聲音，尚非不可採信。從\n    而，卷附之96年6月6日電話監聽錄音及譯文，無法作為補強\n    證人金志峰警詢所述為真實之證據。至扣案之中型夾鏈袋5\n    個、小型夾鏈袋1個等物，據被告甲○○到警詢供稱：中型\n    夾鏈袋5包、小型夾鏈袋1包是伊用來裝小飾品用的等語（見\n    警卷第30頁）。又被告甲○○有施用第一級毒品及第二級毒\n    品之行為，亦經其於警詢自承在卷（見警卷第31頁）。故扣\n    案中型夾鏈袋5個、小型夾鏈袋1個，不無可能為被告施用毒\n    品或包裝飾品所用，尚不足據為補強證人金志峰上揭證述之\n    證據。另扣案之手機僅足證明被告甲○○持有上開電話之事\n    實，而本件既無96年6月6日之通聯紀錄，則難僅憑被告甲○\n    ○持用上開手機之情，而認可補強證人金志峰於警詢之陳述\n    為真實。是證人金志峰於警詢供述之真實性與證明力均有所\n    不足。\n六、辯護人於本院審理時請求傳喚證人李文毅與證人金志峰對質\n    ，因證人李文毅已於原審到庭證述被告甲○○並未叫伊拿毒\n    品予金志峰（見原審卷第七一、七三頁），辯護人請求調查\n    之待證事實，業已調查，辦護人之聲請調查證據，係屬就同\n    一證據再行聲請調查者，核無調查必要，爰依刑事訴訟法第\n    一六三條之二第一項規定，駁回辯護人調查證據聲請，附此\n    敘明。\n七、綜上所述，本件依公訴意旨所提上開事證，尚不足據為認定\n    被告甲○○販賣第一級毒品予金志峰。此外，復無其他積極\n    證據可資證明被告甲○○有公訴人上開所指販賣第一級毒品\n    之事實。原判決就此部分為被告無罪之諭知，尚無違誤。檢\n    察官上訴意旨，指摘原審判決認事用法有所違誤，請求撤銷\n    原判決，為無理由，應予駁回。\n據上論斷，應依刑事訴訟法第三百六十八條，判決如主文。\n本案經檢察官范文豪到庭執行職務。\n中    華    民    國    99    年    5     月    12    日\n                  刑事第七庭    審判長法  官  李文福\n                                      法  官  顏基典\n                                      法  官  陳顯榮\n以上正本證明與原本無異。\n如不服本判決應於收受送達後10日內向本院提出上訴書狀，其未\n敘述上訴理由者，並得於提起上訴後10日內向本院補提理由書（\n均須按他造當事人之人數附繕本）「切勿逕送上級法院」。\n                                      書記官  李珍鳳\n中    華    民    國    99    年    5     月    12    日\n附表：\n┌──┬────┬─────┬────┬────┬─────┐\n│編號│販賣時間│販賣地點  │販賣對象│販賣數量│毒  品    │\n├──┼────┼─────┼────┼────┼─────┤\n│ １ │96年5月9│臺南縣柳營│金志峰  │新臺幣（│海洛因    │\n│    │日下午  │鄉柳營橋下│        │下同）1 │          │\n│    │        │紅綠燈    │        │千元    │          │\n├──┼────┼─────┼────┼────┼─────┤\n│ ２ │96年5月1│臺南縣新營│金志峰  │2千元   │海洛因    │\n│    │2日上午 │市○○街巷│        │        │          │\n│    │        │底        │        │        │          │\n├──┼────┼─────┼────┼────┼─────┤\n│ ３ │96年5月1│臺南縣新營│金志峰  │5百元   │海洛因    │\n│    │2日下午 │市○○街「│        │        │          │\n│    │        │銀龍電動玩│        │        │          │\n│    │        │具店」外  │        │        │          │\n│    │        │          │        │        │          │\n├──┼────┼─────┼────┼────┼─────┤\n│ ４ │96年6月6│甲○○接聽│金志峰  │5百元   │海洛因    │\n│    │日上午  │電金志峰電│        │        │          │\n│    │        │話，約在臺│        │        │          │\n│    │        │南縣柳營鄉│        │        │          │\n│    │        │柳營橋下加│        │        │          │\n│    │        │油站對面，│        │        │          │\n│    │        │由李文毅攜│        │        │          │\n│    │        │帶毒品前往│        │        │          │\n│    │        │交易      │        │        │          │\n├──┼────┼─────┼────┼────┼─────┤\n│ ５ │96年5月1│臺南縣新營│林士傑  │3千元   │安非他命  │\n│    │2日下午 │市南新國中│        │        │          │\n│    │        │附近      │        │        │          │\n└──┴────┴─────┴────┴────┴─────┘",
  "structure": {
    "main": "上訴駁回。",
    "reason": "一、公訴意旨略以：甲○○與其同居男友李文毅（另案審理）基\n    於販賣第一級毒品海洛因之犯意聯絡，以0000000000號行動\n    電話為聯絡交易毒品之工具，於96年6月6日上午，由甲○○\n    接聽金志峰電話，並與金志峰約在臺南縣柳營鄉柳營橋下加\n    油站對面，由李文毅攜帶新臺幣（下同）500元之海洛因前\n    往販賣予金志峰（原檢察官起訴範圍如附表所示，其中編號\n    1.2.3.部分原審為無罪諭知，經本院上訴審駁回上訴確定；\n    編號5.部分經本院上訴審改判處有期徒刑七年六月，經最高\n    法院判決上訴駁回確定）。經實施通訊監察及於96年7月12\n    日13時27分許搜索其與李文毅臺南縣柳營鄉○○路○段275巷\n    2號同居處，扣得甲○○所有中型夾鏈袋5包、小型夾鏈袋1\n    包、NOKIA牌行動電話1支（門號0000000000、序號00000000\n    0000000）、UTEC牌行動電話1支（無SIM卡、序號000000000\n    000000），因認甲○○涉犯毒品危害防制條例第四條第一項\n    販賣第一級毒品罪嫌云云。\n二、按犯罪事實應依證據認定之，無證據不得認定犯罪事實；不\n    能證明被告犯罪者，應諭知無罪之判決，刑事訴訟法第一百\n    五十四條第二項、第三百零一條第一項，分別定有明文。又\n    按檢察官就被告犯罪事實，應負舉證責任，並指出證明之方\n    法，為刑事訴訟法第一百六十一條第一項所明定。因此，檢\n    察官對於起訴之犯罪事實，應負提出證據及說服之實質舉證\n    責任；倘其所提出之證據，不足為被告有罪之積極證明，或\n    其指出證明之方法，無從說服法院以形成被告有罪之心證，\n    基於無罪推定之原則，自應為被告無罪判決之諭知（最高法\n    院92年台上字第128號判例參照）。另按施用毒品者，其所\n    稱向某人購買之供述，須補強證據以擔保其供述之真實性。\n    良以施用毒品者，其供述之憑信性本不及於一般人，況施用\n    毒品者，其供出來源因而破獲者，法律復規定得減輕其刑，\n    其有為偵查機關誘導、或為邀輕典而為不實之陳述之可能，\n    其供述之真實性自有合理之懷疑。故認施用毒品者，關於其\n    向某人購買毒品之供述，必須補強證據佐證，以擔保其供述\n    之真實性，俾貫徹刑事訴訟無罪推定及嚴格證明之基本原則\n    。又關於毒品施用者其所稱向某人購買毒品之供述，必須補\n    強證據佐證，係指毒品購買者之供述縱使並無瑕疵，仍須補\n    強證據佐證而言，以擔保其供述之真實性。該所謂補強證據\n    ，必須與施用毒品者關於相關毒品交易之供述，具有相當程\n    度之關聯性，且足使一般人對於施用毒品者之供述無合理之\n    懷疑存在，而得確信其為真實，始足當之（最高法院96年台\n    上字第1029號判例參照）。\n三、本件公訴意旨認被告甲○○有上揭販賣第一級毒品之犯行，\n    無非係以(1)被告甲○○供述0000000000號行動電話為其所申\n    請，與李文毅交替使用；(2)證人金志峰於警詢證述有於上開\n    時地撥打0000000000號行動電話，由被告甲○○接聽並向伊\n    購買海洛因；(3)上開行動電話之通訊監聽譯文顯示被告甲○\n    ○有於上開時間與證人金志峰通話；(4)扣案之中型夾鏈袋5\n    個、小型夾鏈袋1個及行動電話手機2支間接證明被告甲○○\n    有販賣上開毒品等為其論據。惟訊據被告甲○○堅決否認有\n    上開販賣第一級毒品海洛因予金志峰之犯行，並辯稱：其未\n    販賣第一級毒品海洛因予證人金志峰，且電話監聽譯文之通\n    話者，非其聲音等語。\n四、經查：證人金志峰於警詢證稱：「我認識警方所提示綽號「\n    毅仔」男子與他女友，我持用0000000000號是我本人申請的\n    門號，也只有我個人在使用該門號。都稱呼我「黑狗」之綽\n    號。我以0000000000號打給毅仔及他女友（甲○○）二人共\n    同持用0000000000號門號取得連絡。我打電話給他們都是要\n    毅仔及他女友向他們買俗稱4號的海洛因毒品。就只有買毒\n    品才有金錢上的往來。我於96年4月間開始施打之海洛因毒\n    品是向警方偵辦對象之「毅仔」及他女友（即甲○○）二人\n    購得施用的，他們的連絡電話是「阿龍」給我的，我打0000\n    000000號電話連絡時，有時是「毅仔」接的，有時是他女友\n    （即甲○○）接的。我都講要「一」，「毅仔」他們就知道\n    了，之前他們會約臺南縣新營市○○路上有一家「明治釣蝦\n    場」旁的巷道、臺南縣新營市○○街「龍銀遊藝場」外面旁\n    ，後來這段時間就都約在臺南縣柳營鄉要過新營市○○○○\n    ○路邊或是橋下的上帝爺廟前交易，1小包海洛因是1000元\n    。我與「毅仔」及他女友（即甲○○）有當面交易過海洛因\n    毒品，在上述的地點都曾交易過，有時「毅仔」他與女友（\n    即甲○○）都在一起，有時他女友（即甲○○）自己拿毒品\n    出來賣給我，均是電話連絡約定交易地點。經我指認是編號\n    1號男子就是「毅仔」沒錯。經我指認是編號3號女子就是「\n    毅仔」他的女友（即甲○○）沒錯。李文毅及甲○○持毒品\n    前往與我交易時常會共乘一部豪邁重機車。（提示2007/06/\n    0610：48：19、06/0610：58：52之二次通話內容）我是打0\n    000000000號電話是「毅仔」女友（即甲○○）接的，我要\n    買海洛因毒品，她跟我約在臺南縣柳營鄉柳營橋要過新營市\n    橋下的紅綠燈，該處就是中油加油站的斜對面，第二通我向\n    她說我到達了，她回答我「毅仔」在那邊了，當時是「毅仔\n    」與我交易的，我買500元半小包海洛因」等語（見警卷第4\n    5至51頁）。惟證人金志峰經本院傳喚到庭結證：「（問：\n    為何你在警局跟警察說你在96年6月6日有買過毒品？）隨便\n    大約講的」；「（問：你在96年7月30日警詢中，你告訴警\n    察說你曾經向李文毅、甲○○購買二十多次海洛因毒品？）\n    有跟男生買，沒有跟女生買」；「（當時也指認李文毅的女\n    朋友就是在庭的甲○○）照片的臉不太一樣」（見本院更一\n    審卷第74、75頁）。證人金志峰上開警詢供述與到庭結證所\n    陳，顯不相同，自難依據未經具結之證人警詢供述，為認定\n    被告犯罪事實之證據。\n五、又證人金志峰於本院之結證與警詢所為供述，互不一致，宜\n    就被告對其警詢供述之彈劾或為補強證據予以調查，作為認\n    定事實之證據。依上開最高法院96年臺上字第1029號判例意\n    旨，證人金志峰警詢所述，尚須補強證據以擔保其供述之真\n    實性。而補強證據，必須與該施用毒品者關於相關毒品交易\n    之供述，具有相當程度之關連性，因該補強證據之佐證，足\n    使一般人對於施用毒品之供述無合理之懷疑存在，而得確信\n    其為真實，始足當之。本件96年6月6日之電話監聽錄音，經\n    被告甲○○否認為其聲音，本院依其聲請函送法務部調查局\n    為聲紋鑑定，據該局鑑定報告檢驗結果，認為錄音品質不佳\n    ，致聲紋共振峰圖譜特徵模糊，不符聲紋鑑定條件，無法作\n    聲紋比對鑑定，有法務部調查局99年4月6日調科參字第0990\n    0133600號聲紋鑑定報告書一紙在卷可參（見本院更一審卷\n    第56至58頁），是本案已無法藉由鑑定聲紋方式，確認卷附\n    96年6月6日之電話監聽錄音係被告甲○○之通話。復查卷附\n    之通聯紀錄（見警卷第210頁至230頁），更無96年6月6日上\n    午10時48分19秒及10時58分52秒，由證人金志峰以其持用之\n    0000000000號行動電話撥打被告甲○○與李文毅共同持用之\n    0000000000號行動電話之通聯紀錄，是被告否認卷附之96年\n    6月6日電話監聽錄音之通話，非其聲音，尚非不可採信。從\n    而，卷附之96年6月6日電話監聽錄音及譯文，無法作為補強\n    證人金志峰警詢所述為真實之證據。至扣案之中型夾鏈袋5\n    個、小型夾鏈袋1個等物，據被告甲○○到警詢供稱：中型\n    夾鏈袋5包、小型夾鏈袋1包是伊用來裝小飾品用的等語（見\n    警卷第30頁）。又被告甲○○有施用第一級毒品及第二級毒\n    品之行為，亦經其於警詢自承在卷（見警卷第31頁）。故扣\n    案中型夾鏈袋5個、小型夾鏈袋1個，不無可能為被告施用毒\n    品或包裝飾品所用，尚不足據為補強證人金志峰上揭證述之\n    證據。另扣案之手機僅足證明被告甲○○持有上開電話之事\n    實，而本件既無96年6月6日之通聯紀錄，則難僅憑被告甲○\n    ○持用上開手機之情，而認可補強證人金志峰於警詢之陳述\n    為真實。是證人金志峰於警詢供述之真實性與證明力均有所\n    不足。\n六、辯護人於本院審理時請求傳喚證人李文毅與證人金志峰對質\n    ，因證人李文毅已於原審到庭證述被告甲○○並未叫伊拿毒\n    品予金志峰（見原審卷第七一、七三頁），辯護人請求調查\n    之待證事實，業已調查，辦護人之聲請調查證據，係屬就同\n    一證據再行聲請調查者，核無調查必要，爰依刑事訴訟法第\n    一六三條之二第一項規定，駁回辯護人調查證據聲請，附此\n    敘明。\n七、綜上所述，本件依公訴意旨所提上開事證，尚不足據為認定\n    被告甲○○販賣第一級毒品予金志峰。此外，復無其他積極\n    證據可資證明被告甲○○有公訴人上開所指販賣第一級毒品\n    之事實。原判決就此部分為被告無罪之諭知，尚無違誤。檢\n    察官上訴意旨，指摘原審判決認事用法有所違誤，請求撤銷\n    原判決，為無理由，應予駁回。\n據上論斷，應依刑事訴訟法第三百六十八條，判決如主文。\n本案經檢察官范文豪到庭執行職務。"
  },
  "characters": {
    "judges": [
      "李文福",
      "顏基典",
      "陳顯榮"
    ],
    "prosecutors": [
      "范文豪"
    ],
    "lawyers": [
      "楊惠雯"
    ],
    "clerks": [
      "李珍鳳"
    ],
    "plaintiffs": [

    ],
    "defendants": [
      "甲○○"
    ],
    "prosecutor_office": [

    ],
    "creditors": [

    ],
    "debtors": [

    ],
    "judicial_associate_officer": [

    ]
  },
  "adjudged_at": "2010-05-12",
  "created_at": "2016-01-05 12:00:59",
  "updated_at": "2016-01-05 12:00:59"
}