{
  "identify": "TNH-98-上易-710-20100105-1",
  "court": {
    "name": "臺灣高等法院",
    "code": "TNH"
  },
  "division": {
    "name": "刑事",
    "code": "M"
  },
  "year": 98,
  "word": "上易",
  "number": "710",
  "jcheck": "1",
  "reason": "侵占",
  "content": "臺灣高等法院臺南分院刑事判決         98年度上易字第710號\n上  訴  人\n即  被  告  甲○○\n上列上訴人因侵占案件，不服臺灣台南地方法院98年度易字第88\n9號中華民國98年9月2日第一審判決（起訴案號：臺灣台南地方\n法院檢察署98年度撤緩偵字第67號），提起上訴，本院判決如下\n：\n    主  文\n原判決撤銷。\n甲○○連續犯業務侵占罪，處有期徒刑拾月，減為有期徒刑伍月\n，如易科罰金，以銀元參佰元即新台幣玖佰元折算壹日。\n    事  實\n一、甲○○自民國（下同）81年起，任職國華人壽保險股份有限\n    公司（下稱：國華人壽公司）之業務員，負責向客戶招攬人\n    身保險及收取保險費用，為從事業務之人。甲○○明知其向\n    客戶收取保費後，應將款項交予國華人壽公司，竟因私人投\n    資失利，而基於為自己不法所有意圖之概括犯意，自94年2\n    月間起至94年6月間止，連續向如附表所示之客戶收取如附\n    表所示之保費共新臺幣（下同）2,648,853元後，未將收取\n    之現金繳交予國華人壽公司，而變易持有為所有之意思，將\n    款項全數侵占入己另行挪用，並開立發票人為王崑明、林基\n    耀之支票22張交予國華人壽公司抵交保費，詎上開支票屆期\n    均未獲兌現，始為國華人壽公司查悉上情。\n二、案經國華人壽公司告訴由臺灣台南地方法院檢察署檢察官偵\n    查後起訴。\n    理  由\n一、本件被告甲○○所犯並非死刑、無期徒刑或最輕本刑有期徒\n    刑3 年以上之罪，亦非高等法院管轄第一審案件，其於準備\n    程序中就被訴事實為有罪之陳述，經本院告知被告簡式審判\n    程序之旨，並聽取檢察官及被告之意見後，裁定以簡式審判\n    程序審理，是本案之證據調查，依刑事訴訟法第273條之2規\n    定，不受同法第159條第1項、第161條之2、第161條之3、第\n    163條之1及第164條至第170條之限制，合先敘明。\n二、查上揭事實業據被告甲○○坦承不諱，核與告訴人國華人壽\n    公司所指訴情節相符，復有被告親自書立之還款切結書影本\n    一紙、王崑明及林基耀所簽發之支票暨退票理由單影本二十\n    二紙及國華人壽公司保戶林素文等人之繳費情形聲明書二百\n    十六紙附卷可稽，互核相符，事證明確，被告犯行已堪認定\n    。\n三、查被告行為後，刑法業於94年2月2日修正公布，並定95 年7\n    月1日起施行，茲依刑法第2條第1項規定，就新舊法比較結\n    果，敘述如下：\n（一）刑法第336條第2項業務侵占罪規定，雖未經修正，但該條\n      併科罰金刑部分，依修正後刑法第33條第5款之規定，最\n      低額為新臺幣一千元，惟依被告行為時之刑法第33條第5\n      款規定，罰金之最低額僅新臺幣3元。比較修正前後之刑\n      罰法律，適用「修正前」之規定，對被告較為有利。\n（二）修正後刑法已刪除第56條連續犯之規定，則被告之犯行，\n      因行為後刑法業已刪除連續犯之規定，此刪除雖非犯罪構\n      成要件之變更，但顯已影響行為人刑罰之法律效果，自屬\n      法律有變更，比較修正前後之刑罰法律，如不以連續犯論\n      以一罪，即須適用數罪併罰規定，對被告較為不利，自以\n      適用「修正前」之規定，對被告較為有利\n（三）另按修正前刑法第41條第1項前段規定：「犯最重本刑為5\n      年以下有期徒刑之刑之罪，而受6個月以下有期徒刑或拘\n      役之宣告，因身體、教育、職業、家庭之關係或其他正當\n      理由，執行顯有困難者，得以1元以上3元以下折算1日，\n      易科罰金」。而刑法修正施行前之易科罰金折算標準，修\n      正前罰金罰鍰提高標準條例第2條前段規定（95年5月17日\n      修正刪除，95年7月1日施行），就其原定數額提高為100\n      倍折算1日，則刑法修正施行前易科罰金折算標準，應以\n      銀元300元即新臺幣900元折算1日；而修正後刑法第41條\n      第1項前段規定：「犯最重本刑為5年以下有期徒刑以下之\n      罪，而受6個月以下有期徒刑或拘役之宣告者，得以新臺\n      幣1千元、2千元或3千元折算1日，易科罰金」。比較新舊\n      法易科罰金之折算標準，亦以「修正前」之規定，較有利\n      於被告。\n（四）至「修正後刑法」施行前，「刑法分則編」有關「罰金刑\n      」之貨幣單位係銀元；且依刑法分則編應處罰金者，適用\n      現已廢止罰金罰鍰提高標準條例第1條、第4條之規定，亦\n      即應按各該具體條文制定或修正之時間先後，定其提高之\n      倍數。惟被告行為後，刑法施行法增訂第1條之1，於95年\n      6月14日經總統公布，並自同年7月1日起施行；該條規定\n      ：「中華民國94年1月7日刑法修正施行後，刑法分則編所\n      定罰金之貨幣單位為新臺幣。94年1月7日刑法修正時，刑\n      法分則編未修正之條文定有罰金者，自94年1月7日刑法修\n      正施行後，就其所定數額提高為30倍。但72年6月26日至\n      94年1月7日新增或修正之條文，就其所定數額提高為三倍\n      」。亦即自95年7月1日起，刑法分則編所定罰金之「貨幣\n      單位」，由銀元改為新臺幣。惟刑法施行法第1條之1係替\n      代罰金罰鍰提高標準條例部分條文，與經換算後，該條例\n      所定之罰金額度相同，僅係貨幣單位由銀元改為新臺幣，\n      其罰金刑之刑度並無變更，不發生有利、不利之問題，亦\n      非法律變更刑度之條文，是被告所犯刑法第336條第2項業\n      務侵占罪部分，並無比較新舊法之問題，併予敘明。\n（五）綜合上述刑法新舊法之比較適用，應依刑法第2條第1項前\n      段之規定，一體適用有利於行為人之「修正前」刑法規定\n      。\n四、核被告所為係犯刑法第三百三十六條第二項之業務侵占罪。\n    又被告所為數次業務侵占行為間，其時間緊接，觸犯犯罪構\n    成要件相同之罪名，顯係基於概括犯意而反覆為之，應依修\n    正前刑法第五十六條連續犯規定，論以一罪，並酌加重其刑\n    。\n五、原判決依據上開事證予以被告論罪科刑，固非無見。然查，\n    被告係經通緝而自行到案說明，並非經警緝獲，原判決未依\n    中華民國96年罪犯減刑條例規定予以減刑（詳如後述），自\n    屬違誤。被告據此提起上訴，為有理由，自應由本院撤銷改\n    判。爰審酌被告並無任何前科紀錄，顯見其素行尚佳、其因\n    自身投資失利，而侵占業務上所收取款項之犯罪動機、目的\n    ，犯罪後雖已與告訴人國華人壽公司成立和解，惟迄今僅償\n    還542,849元，尚欠2,106,004元等一切情狀，量處有期徒刑\n    十月。又本件被告犯罪時間在96年4月24日以前，所犯罪名\n    雖係中華民國96年罪犯減刑條例第3條第1項第15款所列罪名\n    ，然其宣告刑未逾有期徒刑一年六月，依該條例第3條反面\n    解釋，自應減其宣告刑2分之1，併諭知易科罰金之折算標準\n    。至於中華民國九十六年罪犯減刑條例施行（96年7月16日\n    ）前，經通緝而未於96年12月31日以前「自動歸案」接受偵\n    查、審判或執行者，不得依本條例減刑，上開條例第5條、\n    第16條固定有明文。查本件被告之業務侵占犯行，係於96年\n    4 月24日之前，且被告並因本案於95年8月21日，經台灣台\n    南地方法院檢察署發布通緝在案，然被告係於通緝當日，經\n    警聯絡策動告知，即自行至台南市警察局第六分局到案說明\n    ，並非經警緝獲等情，有被告95年8月21日警詢筆錄、該分\n    局解送人犯報告書（載明被告自行至台南市○區○○○路2\n    段241號）及該分局地址資料（該址即該分局地址）在卷可\n    證（偵緝字第1228號偵查卷第2-4頁、本院卷第26-28頁），\n    依據上開條例第5條之規定反面解釋，自應減刑，附此敘明\n    。\n據上論結，應依刑事訴訟法第369條第1項前段、第364條、第299\n條第1項前段，刑法第2條第1項前段、修正前刑法第56條、第41\n條第1項、刑法第336條第2項，刑法施刑法第1條之1，廢止前罰\n金罰鍰提高標準條例第2條，中華民國九十六年罪犯減刑條例第2\n條第1項第3款、第7條、第9條，判決如主文。\n本案經檢察官謝錫和到庭執行職務。\n中    華    民    國    99    年    1     月    5     日\n                  刑事第三庭    審判長法  官  陳義仲\n                                      法  官  楊清安\n                                      法  官  宋明中\n以上正本證明與原本無異。\n不得上訴。\n                                      書記官  王薇潔\n中    華    民    國    99    年    1     月    5     日\n附錄本案論罪科刑法條全文：\n中華民國刑法第336條\n對於公務上或因公益所持有之物，犯前條第 1 項之罪者，處 1\n年以上 7 年以下有期徒刑，得併科 5 千元以下罰金。\n對於業務上所持有之物，犯前條第 1 項之罪者，處 6 月以上\n5 年以下有期徒刑，得併科 3 千元以下罰金。\n前二項之未遂犯罰之。\n附表：\n┌────┬──┬────┬─────┬──┬────┬─────┬──────┬─────┬────┐\n│保單號碼│種類│要保人  │金額（新臺│繳別│支票號碼│票載發票日│支票金額（新│ 發票銀行 │ 發票人 │\n│        │    │        │幣/元）   │    │        │          │臺幣/元）   │          │        │\n├────┼──┼────┼─────┼──┼────┼─────┼──────┼─────┼────┤\n│H0000000│保費│蔡麗蘭  │  13914   │年  │        │          │            │          │        │\n├────┼──┼────┼─────┼──┤        │          │            │          │        │\n│AH002084│保費│陳聖慧  │  26823   │年  │        │          │            │          │        │\n├────┼──┼────┼─────┼──┤        │          │            │          │        │\n│G0000000│保費│郭靜芳  │   8860   │年  │        │          │            │          │        │\n├────┼──┼────┼─────┼──┤        │          │            │          │        │\n│H0000000│保費│陳龍泰  │  15714   │年  │        │          │            │          │        │\n├────┼──┼────┼─────┼──┤        │          │            │          │        │\n│J0000000│保費│房陳秀環│  42848   │年  │        │          │            │          │        │\n├────┼──┼────┼─────┼──┤        │          │            │          │        │\n│H0000000│保費│林榮耀  │  17175   │年  │        │          │            │          │        │\n├────┼──┼────┼─────┼──┤0000000 │940516    │218,240     │合作金庫台│王崑明  │\n│J0000000│保費│林榮耀  │  11324   │年  │        │          │            │南分行    │        │\n├────┼──┼────┼─────┼──┤        │          │            │          │        │\n│G0000000│保費│林潘牡丹│   7790   │年  │        │          │            │          │        │\n├────┼──┼────┼─────┼──┤        │          │            │          │        │\n│G0000000│保費│林潘牡丹│  15510   │年  │        │          │            │          │        │\n├────┼──┼────┼─────┼──┤        │          │            │          │        │\n│J0000000│保費│許石延  │  19171   │年  │        │          │            │          │        │\n├────┼──┼────┼─────┼──┤        │          │            │          │        │\n│A0000000│保費│許林芬蘭│  24476   │年  │        │          │            │          │        │\n├────┼──┼────┼─────┼──┤        │          │            │          │        │\n│J0000000│保費│郭寸桃  │  14635   │年  │        │          │            │          │        │\n├────┼──┼────┼─────┼──┼────┼─────┼──────┼─────┼────┤\n│A0000000│保費│郭再生  │  17600   │年  │        │          │            │          │        │\n├────┼──┼────┼─────┼──┤        │          │            │          │        │\n│G0000000│保費│郭再生  │   1633   │年  │        │          │            │          │        │\n├────┼──┼────┼─────┼──┤        │          │            │          │        │\n│A0000000│保費│林榮    │  63519   │年  │        │          │            │          │        │\n├────┼──┼────┼─────┼──┤        │          │            │          │        │\n│A0000000│保費│林美雲  │  30360   │年  │        │          │            │          │        │\n├────┼──┼────┼─────┼──┤0000000 │940524    │138,381     │合作金庫台│王崑明  │\n│J0000000│保費│林銹玲  │  11021   │年  │        │          │            │南分行    │        │\n├────┼──┼────┼─────┼──┤        │          │            │          │        │\n│A0000000│利息│林美雲  │    864   │    │        │          │            │          │        │\n├────┼──┼────┼─────┼──┤        │          │            │          │        │\n│A0000000│利息│林榮    │  10533   │    │        │          │            │          │        │\n├────┼──┼────┼─────┼──┤        │          │            │          │        │\n│A0000000│利息│郭再生  │   2851   │    │        │          │            │          │        │\n├────┼──┼────┼─────┼──┼────┼─────┼──────┼─────┼────┤\n│AI001123│保費│林永森  │  33641   │年  │        │          │            │          │        │\n├────┼──┼────┼─────┼──┤        │          │            │          │        │\n│AI000831│保費│郭靜芳  │  16740   │年  │        │          │            │          │        │\n├────┼──┼────┼─────┼──┤        │          │            │          │        │\n│AH005050│保費│郭靜芳  │  11077   │年  │        │          │            │          │        │\n├────┼──┼────┼─────┼──┤        │          │            │          │        │\n│AU000583│保費│林進傳  │  33733   │年  │        │          │            │          │        │\n├────┼──┼────┼─────┼──┤        │          │            │          │        │\n│J0000000│保費│林美鳳  │  10763   │半年│        │          │            │          │        │\n├────┼──┼────┼─────┼──┤        │          │            │          │        │\n│J0000000│保費│林美鳳  │   5997   │半年│        │          │            │          │        │\n├────┼──┼────┼─────┼──┤        │          │            │          │        │\n│F0000000│保費│林美華  │   1660   │年  │        │          │            │          │        │\n├────┼──┼────┼─────┼──┤        │          │            │          │        │\n│F0000000│保費│林水和  │  34265   │年  │        │          │            │          │        │\n├────┼──┼────┼─────┼──┤        │          │            │          │        │\n│H0000000│保費│吳瑞臨  │  14840   │年  │        │          │            │          │        │\n├────┼──┼────┼─────┼──┤        │          │            │          │        │\n│E0000000│保費│吳瑞臨  │  10387   │年  │0000000 │940616    │404,441     │合作金庫台│王崑明  │\n├────┼──┼────┼─────┼──┤        │          │            │南分行    │        │\n│00000000│保費│洪麗卿  │   1950   │年  │        │          │            │          │        │\n├────┼──┼────┼─────┼──┤        │          │            │          │        │\n│J0000000│保費│洪麗卿  │  14410   │年  │        │          │            │          │        │\n├────┼──┼────┼─────┼──┤        │          │            │          │        │\n│J0000000│保費│林健明  │  18764   │年  │        │          │            │          │        │\n├────┼──┼────┼─────┼──┤        │          │            │          │        │\n│J0000000│保費│陳嘉美  │  67797   │年  │        │          │            │          │        │\n├────┼──┼────┼─────┼──┤        │          │            │          │        │\n│J0000000│保費│吳石吉  │   9105   │年  │        │          │            │          │        │\n├────┼──┼────┼─────┼──┤        │          │            │          │        │\n│J0000000│保費│吳石吉  │  71157   │年  │        │          │            │          │        │\n├────┼──┼────┼─────┼──┤        │          │            │          │        │\n│J0000000│保費│陳嘉美  │   8109   │年  │        │          │            │          │        │\n├────┼──┼────┼─────┼──┤        │          │            │          │        │\n│00000000│保費│陳水    │  19576   │年  │        │          │            │          │        │\n├────┼──┼────┼─────┼──┤        │          │            │          │        │\n│00000000│保費│陳李晴  │  20470   │年  │        │          │            │          │        │\n├────┼──┼────┼─────┼──┼────┼─────┼──────┼─────┼────┤\n│H0000000│保費│陳淑芸  │   6278   │年  │        │          │            │          │        │\n├────┼──┼────┼─────┼──┤        │          │            │          │        │\n│H0000000│保費│陳淑芸  │  16341   │年  │0000000 │940630    │30,741      │合作金庫台│王崑明  │\n├────┼──┼────┼─────┼──┤        │          │            │南分行    │        │\n│H0000000│保費│陳淑芸  │   6354   │年  │        │          │            │          │        │\n├────┼──┼────┼─────┼──┼────┼─────┼──────┼─────┼────┤\n│A0000000│保費│史櫻蓮  │   8350   │年  │        │          │            │          │        │\n├────┼──┼────┼─────┼──┤        │          │            │          │        │\n│AW037482│保費│劉建鴻  │   7068   │半年│        │          │            │          │        │\n├────┼──┼────┼─────┼──┤        │          │            │          │        │\n│AW037481│保費│劉金樹  │   7999   │半年│        │          │            │          │        │\n├────┼──┼────┼─────┼──┤0000000 │940606    │100,564     │合作金庫台│王崑明  │\n│E0000000│保費│吳佳玲  │  27249   │年  │        │          │            │南分行    │        │\n├────┼──┼────┼─────┼──┤        │          │            │          │        │\n│J0000000│保費│吳佳玲  │  10819   │年  │        │          │            │          │        │\n├────┼──┼────┼─────┼──┤        │          │            │          │        │\n│A0000000│保費│薛銘江  │  39079   │年  │        │          │            │          │        │\n├────┼──┼────┼─────┼──┼────┼─────┼──────┼─────┼────┤\n│BT015224│保費│蘇雅惠  │   3591   │月  │        │          │            │          │        │\n├────┼──┼────┼─────┼──┤        │          │            │          │        │\n│AE002454│保費│蘇慶成  │   1952   │月  │0000000 │940531    │15,640      │合作金庫台│王崑明  │\n├────┼──┼────┼─────┼──┤        │          │            │南分行    │        │\n│H0000000│保費│吳佳玲  │  10097   │年  │        │          │            │          │        │\n├────┼──┼────┼─────┼──┼────┼─────┼──────┼─────┼────┤\n│BT015224│保費│蘇雅惠  │   3591   │月  │        │          │            │          │        │\n├────┼──┼────┼─────┼──┤        │          │            │          │        │\n│H0000000│保費│鄭清江  │   3514   │月  │        │          │            │          │        │\n├────┼──┼────┼─────┼──┤        │          │            │          │        │\n│J0000000│保費│盧建成  │   5949   │月  │0000000 │940531    │20,227      │合作金庫台│王崑明  │\n├────┼──┼────┼─────┼──┤        │          │            │南分行    │        │\n│G0000000│保費│楊秋娟  │   6208   │月  │        │          │            │          │        │\n├────┼──┼────┼─────┼──┤        │          │            │          │        │\n│H0000000│保費│楊秋娟  │    965   │月  │        │          │            │          │        │\n├────┼──┼────┼─────┼──┼────┼─────┼──────┼─────┼────┤\n│H0000000│保費│曾朝憲  │   3081   │月  │        │          │            │          │        │\n├────┼──┼────┼─────┼──┤        │          │            │          │        │\n│H0000000│保費│曾薛秀女│   2854   │月  │        │          │            │          │        │\n├────┼──┼────┼─────┼──┤        │          │            │          │        │\n│J0000000│保費│薛歐玉鳳│   2636   │月  │        │          │            │          │        │\n├────┼──┼────┼─────┼──┤        │          │            │          │        │\n│H0000000│保費│薛慶林  │   1488   │月  │        │          │            │          │        │\n├────┼──┼────┼─────┼──┤        │          │            │          │        │\n│BW029111│保費│歐明慶  │   1194   │月  │        │          │            │          │        │\n├────┼──┼────┼─────┼──┤        │          │            │          │        │\n│BL012897│保費│李秀里  │    523   │月  │        │          │            │          │        │\n├────┼──┼────┼─────┼──┤        │          │            │          │        │\n│H0000000│保費│林有志  │   1999   │月  │        │          │            │          │        │\n├────┼──┼────┼─────┼──┤        │          │            │          │        │\n│H0000000│保費│史民俊  │   4391   │月  │        │          │            │          │        │\n├────┼──┼────┼─────┼──┤        │          │            │          │        │\n│AH022240│保費│林素文  │   2955   │月  │        │          │            │          │        │\n├────┼──┼────┼─────┼──┤        │          │            │          │        │\n│H0000000│保費│鄭清江  │   3514   │月  │        │          │            │          │        │\n├────┼──┼────┼─────┼──┤        │          │            │          │        │\n│CQ000620│保費│陳彥佳  │   4206   │月  │        │          │            │          │        │\n├────┼──┼────┼─────┼──┤        │          │            │          │        │\n│CG000449│保費│陳彥佳  │   1121   │月  │        │          │            │          │        │\n├────┼──┼────┼─────┼──┤        │          │            │          │        │\n│H0000000│保費│曾朝政  │   4037   │月  │        │          │            │          │        │\n├────┼──┼────┼─────┼──┤        │          │            │          │        │\n│00000000│保費│周翌星  │   2613   │月  │        │          │            │          │        │\n├────┼──┼────┼─────┼──┤        │          │            │          │        │\n│J0000000│保費│薛林玉蘭│   2668   │月  │        │          │            │          │        │\n├────┼──┼────┼─────┼──┤        │          │            │          │        │\n│C0000000│保費│薛林玉蘭│   1787   │月  │        │          │            │          │        │\n├────┼──┼────┼─────┼──┤        │          │            │          │        │\n│H0000000│保費│薛文良  │    909   │月  │        │          │            │          │        │\n├────┼──┼────┼─────┼──┤        │          │            │          │        │\n│J0000000│保費│薛文良  │   1981   │月  │        │          │            │          │        │\n├────┼──┼────┼─────┼──┤        │          │            │          │        │\n│J0000000│保費│林宗慶  │   1405   │月  │        │          │            │          │        │\n├────┼──┼────┼─────┼──┤        │          │            │          │        │\n│BW028162│保費│李秀里  │   1088   │月  │0000000 │940630    │87,298      │合作金庫台│王崑明  │\n├────┼──┼────┼─────┼──┤        │          │            │南分行    │        │\n│F0000000│保費│陳曾不纏│   2859   │月  │        │          │            │          │        │\n├────┼──┼────┼─────┼──┤        │          │            │          │        │\n│F0000000│保費│薛邱阿鵠│   2561   │月  │        │          │            │          │        │\n├────┼──┼────┼─────┼──┤        │          │            │          │        │\n│F0000000│保費│陳順傭  │   2909   │月  │        │          │            │          │        │\n├────┼──┼────┼─────┼──┤        │          │            │          │        │\n│J0000000│保費│盧建成  │   5949   │月  │        │          │            │          │        │\n├────┼──┼────┼─────┼──┤        │          │            │          │        │\n│AH037271│保費│郭玉佩  │   3231   │月  │        │          │            │          │        │\n├────┼──┼────┼─────┼──┤        │          │            │          │        │\n│H0000000│保費│邱林秀枝│   3545   │月  │        │          │            │          │        │\n├────┼──┼────┼─────┼──┤        │          │            │          │        │\n│AW042833│保費│郭潘金桃│   2338   │月  │        │          │            │          │        │\n├────┼──┼────┼─────┼──┤        │          │            │          │        │\n│BL014914│保費│李秀里  │    522   │月  │        │          │            │          │        │\n├────┼──┼────┼─────┼──┤        │          │            │          │        │\n│BL012895│保費│李秀里  │    533   │月  │        │          │            │          │        │\n├────┼──┼────┼─────┼──┤        │          │            │          │        │\n│J0000000│保費│歐玉霞  │   1937   │月  │        │          │            │          │        │\n├────┼──┼────┼─────┼──┤        │          │            │          │        │\n│H0000000│保費│楊秋娟  │    965   │月  │        │          │            │          │        │\n├────┼──┼────┼─────┼──┤        │          │            │          │        │\n│00000000│保費│邱進於  │   1249   │月  │        │          │            │          │        │\n├────┼──┼────┼─────┼──┤        │          │            │          │        │\n│G0000000│保費│楊秋娟  │   6208   │月  │        │          │            │          │        │\n├────┼──┼────┼─────┼──┤        │          │            │          │        │\n│00000000│保費│李綢緞  │   1536   │月  │        │          │            │          │        │\n├────┼──┼────┼─────┼──┤        │          │            │          │        │\n│J0000000│保費│薛慶林  │   2204   │月  │        │          │            │          │        │\n├────┼──┼────┼─────┼──┤        │          │            │          │        │\n│J0000000│保費│周翌星  │    605   │月  │        │          │            │          │        │\n├────┼──┼────┼─────┼──┤        │          │            │          │        │\n│H0000000│利息│史民俊  │    446   │    │        │          │            │          │        │\n├────┼──┼────┼─────┼──┤        │          │            │          │        │\n│H0000000│利息│薛慶林  │    412   │    │        │          │            │          │        │\n├────┼──┼────┼─────┼──┤        │          │            │          │        │\n│J0000000│利息│歐玉霞  │    839   │    │        │          │            │          │        │\n├────┼──┼────┼─────┼──┼────┼─────┼──────┼─────┼────┤\n│G0000000│保費│陳冠銘  │  10805   │年  │        │          │            │          │        │\n├────┼──┼────┼─────┼──┤        │          │            │          │        │\n│E0000000│保費│陳啟鴻  │  34240   │年  │        │          │            │          │        │\n├────┼──┼────┼─────┼──┤        │          │            │          │        │\n│N0000000│保費│陳啟鴻  │   4306   │年  │        │          │            │          │        │\n├────┼──┼────┼─────┼──┤        │          │            │          │        │\n│G0000000│保費│陳啟鴻  │   2168   │年  │        │          │            │          │        │\n├────┼──┼────┼─────┼──┤        │          │            │          │        │\n│A0000000│保費│林潘牡丹│   7976   │年  │0000000 │940715    │121,667     │合作金庫台│王崑明  │\n├────┼──┼────┼─────┼──┤        │          │            │南分行    │        │\n│H0000000│保費│薛陳黃枝│   7508   │年  │        │          │            │          │        │\n├────┼──┼────┼─────┼──┤        │          │            │          │        │\n│J0000000│保費│薛陳黃枝│  12279   │年  │        │          │            │          │        │\n├────┼──┼────┼─────┼──┤        │          │            │          │        │\n│A0000000│利息│林潘牡丹│   2266   │    │        │          │            │          │        │\n├────┼──┼────┼─────┼──┤        │          │            │          │        │\n│F0000000│保費│郭美雲  │   6139   │年  │        │          │            │          │        │\n├────┼──┼────┼─────┼──┼────┼─────┼──────┼─────┼────┤\n│H0000000│保費│吳茂正  │  48579   │年  │        │          │            │          │        │\n├────┼──┼────┼─────┼──┤        │          │            │          │        │\n│H0000000│保費│吳薛鳳英│  11089   │年  │        │          │            │          │        │\n├────┼──┼────┼─────┼──┤        │          │            │          │        │\n│00000000│保費│林國火  │   7798   │半年│        │          │            │          │        │\n├────┼──┼────┼─────┼──┤        │          │            │          │        │\n│H0000000│保費│黃錦雲  │   7603   │半年│        │          │            │          │        │\n├────┼──┼────┼─────┼──┤        │          │            │          │        │\n│00000000│保費│薛全祥  │  15746   │半年│        │          │            │          │        │\n├────┼──┼────┼─────┼──┤        │          │            │          │        │\n│A0000000│保費│吳淑惠  │   2578   │月  │        │          │            │          │        │\n├────┼──┼────┼─────┼──┤        │          │            │          │        │\n│G0000000│保費│吳淑惠  │   1126   │月  │        │          │            │          │        │\n├────┼──┼────┼─────┼──┤        │          │            │          │        │\n│G0000000│保費│吳淑惠  │    946   │月  │        │          │            │          │        │\n├────┼──┼────┼─────┼──┤        │          │            │          │        │\n│H0000000│保費│許林芬蘭│  19338   │年  │        │          │            │          │        │\n├────┼──┼────┼─────┼──┤        │          │            │          │        │\n│J0000000│保費│薛陳黃枝│   6456   │年  │        │          │            │          │        │\n├────┼──┼────┼─────┼──┤        │          │            │          │        │\n│H0000000│保費│薛碧綢  │  25000   │年  │        │          │            │          │        │\n├────┼──┼────┼─────┼──┤        │          │            │          │        │\n│AW020129│保費│郭美雲  │  33318   │年  │        │          │            │          │        │\n├────┼──┼────┼─────┼──┤        │          │            │          │        │\n│H0000000│保費│吳志瞬  │  11389   │年  │        │          │            │          │        │\n├────┼──┼────┼─────┼──┤        │          │            │          │        │\n│F0000000│保費│吳志瞬  │   2453   │年  │        │          │            │          │        │\n├────┼──┼────┼─────┼──┤        │          │            │          │        │\n│J0000000│保費│戴志忠  │    290   │月  │        │          │            │          │        │\n├────┼──┼────┼─────┼──┤        │          │            │          │        │\n│AW020605│保費│歐林月珠│  26160   │年  │        │          │            │          │        │\n├────┼──┼────┼─────┼──┤        │          │            │          │        │\n│H0000000│保費│薛源堂  │   3009   │季  │        │          │            │          │        │\n├────┼──┼────┼─────┼──┤        │          │            │          │        │\n│F0000000│保費│陳真男  │  13961   │季  │        │          │            │          │        │\n├────┼──┼────┼─────┼──┤        │          │            │          │        │\n│J0000000│保費│林福全  │   7232   │季  │        │          │            │          │        │\n├────┼──┼────┼─────┼──┤0000000 │940630    │404,493     │合作金庫台│王崑明  │\n│J0000000│保費│薛寶柱  │  12602   │季  │        │          │            │南分行    │        │\n├────┼──┼────┼─────┼──┤        │          │            │          │        │\n│J0000000│保費│戴志忠  │   3080   │月  │        │          │            │          │        │\n├────┼──┼────┼─────┼──┤        │          │            │          │        │\n│J0000000│保費│戴志忠  │   1418   │月  │        │          │            │          │        │\n├────┼──┼────┼─────┼──┤        │          │            │          │        │\n│G0000000│保費│吳淑惠  │    875   │月  │        │          │            │          │        │\n├────┼──┼────┼─────┼──┤        │          │            │          │        │\n│J0000000│保費│林冬結  │   3140   │月  │        │          │            │          │        │\n├────┼──┼────┼─────┼──┤        │          │            │          │        │\n│J0000000│保費│林冬結  │    696   │月  │        │          │            │          │        │\n├────┼──┼────┼─────┼──┤        │          │            │          │        │\n│J0000000│保費│謝月綿  │   1820   │月  │        │          │            │          │        │\n├────┼──┼────┼─────┼──┤        │          │            │          │        │\n│J0000000│保費│謝月綿  │    570   │月  │        │          │            │          │        │\n├────┼──┼────┼─────┼──┤        │          │            │          │        │\n│F0000000│保費│吳志瞬  │  10540   │年  │        │          │            │          │        │\n├────┼──┼────┼─────┼──┤        │          │            │          │        │\n│G0000000│保費│吳志瞬  │  21081   │年  │        │          │            │          │        │\n├────┼──┼────┼─────┼──┤        │          │            │          │        │\n│F0000000│保費│林麗萍  │  54148   │年  │        │          │            │          │        │\n├────┼──┼────┼─────┼──┤        │          │            │          │        │\n│E0000000│保費│薛源堂  │  11619   │季  │        │          │            │          │        │\n├────┼──┼────┼─────┼──┤        │          │            │          │        │\n│J0000000│保費│薛源堂  │   6178   │季  │        │          │            │          │        │\n├────┼──┼────┼─────┼──┤        │          │            │          │        │\n│F0000000│利息│陳真男  │   1119   │    │        │          │            │          │        │\n├────┼──┼────┼─────┼──┤        │          │            │          │        │\n│00000000│利息│林國火  │   1062   │    │        │          │            │          │        │\n├────┼──┼────┼─────┼──┤        │          │            │          │        │\n│J0000000│利息│戴志忠  │   1170   │    │        │          │            │          │        │\n├────┼──┼────┼─────┼──┤        │          │            │          │        │\n│J0000000│利息│戴志忠  │    466   │    │        │          │            │          │        │\n├────┼──┼────┼─────┼──┤        │          │            │          │        │\n│E0000000│利息│薛源堂  │   1260   │    │        │          │            │          │        │\n├────┼──┼────┼─────┼──┤        │          │            │          │        │\n│A0000000│利息│吳淑惠  │    223   │    │        │          │            │          │        │\n├────┼──┼────┼─────┼──┼────┼─────┼──────┼─────┼────┤\n│AH000662│保費│柳丁發  │   1452   │月  │        │          │            │          │        │\n├────┼──┼────┼─────┼──┤        │          │            │          │        │\n│F0000000│保費│柳丁發  │   2012   │月  │        │          │            │          │        │\n├────┼──┼────┼─────┼──┤        │          │            │          │        │\n│AH000681│保費│柳劉秀玲│   2086   │月  │        │          │            │          │        │\n├────┼──┼────┼─────┼──┤        │          │            │          │        │\n│F0000000│保費│柳丁發  │    536   │月  │        │          │            │          │        │\n├────┼──┼────┼─────┼──┤        │          │            │          │        │\n│AH000656│保費│柳淑文  │   1673   │月  │        │          │            │          │        │\n├────┼──┼────┼─────┼──┤        │          │            │          │        │\n│H0000000│保費│盧安鎮  │   4572   │月  │        │          │            │          │        │\n├────┼──┼────┼─────┼──┤        │          │            │          │        │\n│AW031323│保費│盧立偉  │   1362   │月  │0000000 │940630    │33,031      │合作金庫台│王崑明  │\n├────┼──┼────┼─────┼──┤        │          │            │南分行    │        │\n│H0000000│保費│張好    │   2674   │月  │        │          │            │          │        │\n├────┼──┼────┼─────┼──┤        │          │            │          │        │\n│G0000000│保費│黃秋燕  │   2157   │月  │        │          │            │          │        │\n├────┼──┼────┼─────┼──┤        │          │            │          │        │\n│F0000000│保費│王鐸磐  │   5011   │月  │        │          │            │          │        │\n├────┼──┼────┼─────┼──┤        │          │            │          │        │\n│F0000000│保費│王鐸磐  │   3930   │月  │        │          │            │          │        │\n├────┼──┼────┼─────┼──┤        │          │            │          │        │\n│F0000000│保費│王貞懿  │   3608   │月  │        │          │            │          │        │\n├────┼──┼────┼─────┼──┤        │          │            │          │        │\n│AE002454│保費│蘇慶成  │   1952   │月  │        │          │            │          │        │\n├────┼──┼────┼─────┼──┼────┼─────┼──────┼─────┼────┤\n│CT003052│保費│王崑楠  │  26470   │年  │        │          │            │          │        │\n├────┼──┼────┼─────┼──┤        │          │            │          │        │\n│F0000000│保費│吳石崇  │  72981   │年  │0000000 │940723    │106,572     │合作金庫台│王崑明  │\n├────┼──┼────┼─────┼──┤        │          │            │南分行    │        │\n│F0000000│保費│吳石崇  │   7121   │年  │        │          │            │          │        │\n├────┼──┼────┼─────┼──┼────┼─────┼──────┼─────┼────┤\n│F0000000│保費│陳淑芸  │   3294   │年  │        │          │            │          │        │\n├────┼──┼────┼─────┼──┤        │          │            │          │        │\n│F0000000│保費│陳淑芸  │   1168   │年  │        │          │            │          │        │\n├────┼──┼────┼─────┼──┤        │          │            │          │        │\n│F0000000│保費│陳淑芸  │   1108   │年  │        │          │            │          │        │\n├────┼──┼────┼─────┼──┤        │          │            │          │        │\n│00000000│保費│林健明  │  49475   │年  │        │          │            │          │        │\n├────┼──┼────┼─────┼──┤0000000 │940712    │119,113     │合作金庫台│王崑明  │\n│G0000000│保費│杜麗美  │   2366   │年  │        │          │            │南分行    │        │\n├────┼──┼────┼─────┼──┤        │          │            │          │        │\n│G0000000│保費│林健明  │   4467   │年  │        │          │            │          │        │\n├────┼──┼────┼─────┼──┤        │          │            │          │        │\n│J0000000│保費│林鄭秀鑾│  43400   │年  │        │          │            │          │        │\n├────┼──┼────┼─────┼──┤        │          │            │          │        │\n│J0000000│利息│林鄭秀鑾│  13835   │    │        │          │            │          │        │\n├────┼──┼────┼─────┼──┼────┼─────┼──────┼─────┼────┤\n│AH037271│保費│郭玉佩  │   3231   │月  │        │          │            │          │        │\n├────┼──┼────┼─────┼──┤        │          │            │          │        │\n│AW042833│保費│郭潘金桃│   2338   │月  │        │          │            │          │        │\n├────┼──┼────┼─────┼──┤        │          │            │          │        │\n│J0000000│保費│戴志忠  │    290   │月  │        │          │            │          │        │\n├────┼──┼────┼─────┼──┤        │          │            │          │        │\n│J0000000│保費│戴志忠  │   3080   │月  │        │          │            │          │        │\n├────┼──┼────┼─────┼──┤        │          │            │          │        │\n│BL014914│保費│李秀里  │    522   │月  │        │          │            │          │        │\n├────┼──┼────┼─────┼──┤        │          │            │          │        │\n│G0000000│保費│楊秋娟  │   6208   │月  │        │          │            │          │        │\n├────┼──┼────┼─────┼──┤        │          │            │          │        │\n│H0000000│保費│楊秋娟  │    965   │月  │        │          │            │          │        │\n├────┼──┼────┼─────┼──┤        │          │            │          │        │\n│J0000000│保費│盧建成  │   5949   │月  │        │          │            │          │        │\n├────┼──┼────┼─────┼──┤        │          │            │          │        │\n│CQ000620│保費│陳彥佳  │   4206   │月  │        │          │            │          │        │\n├────┼──┼────┼─────┼──┤        │          │            │          │        │\n│CG000449│保費│陳彥佳  │   1121   │月  │        │          │            │          │        │\n├────┼──┼────┼─────┼──┤        │          │            │          │        │\n│H0000000│保費│林有志  │   1999   │月  │        │          │            │          │        │\n├────┼──┼────┼─────┼──┤        │          │            │          │        │\n│BL012897│保費│李秀里  │    523   │月  │        │          │            │          │        │\n├────┼──┼────┼─────┼──┤        │          │            │          │        │\n│BW029111│保費│歐明慶  │   1194   │月  │        │          │            │          │        │\n├────┼──┼────┼─────┼──┤        │          │            │          │        │\n│J0000000│保費│歐玉霞  │   1937   │月  │        │          │            │          │        │\n├────┼──┼────┼─────┼──┤        │          │            │          │        │\n│BL012895│保費│李秀里  │    533   │月  │        │          │            │          │        │\n├────┼──┼────┼─────┼──┤        │          │            │          │        │\n│BW028162│保費│李秀里  │   1088   │月  │0000000 │940731    │77,219      │合作金庫台│王崑明  │\n├────┼──┼────┼─────┼──┤        │          │            │南分行    │        │\n│F0000000│保費│陳順傭  │   2909   │月  │        │          │            │          │        │\n├────┼──┼────┼─────┼──┤        │          │            │          │        │\n│F0000000│保費│薛邱阿鵠│   2561   │月  │        │          │            │          │        │\n├────┼──┼────┼─────┼──┤        │          │            │          │        │\n│F0000000│保費│陳曾不纏│   2859   │月  │        │          │            │          │        │\n├────┼──┼────┼─────┼──┤        │          │            │          │        │\n│H0000000│保費│邱林秀枝│   3545   │月  │        │          │            │          │        │\n├────┼──┼────┼─────┼──┤        │          │            │          │        │\n│AH022240│保費│林素文  │   2955   │月  │        │          │            │          │        │\n├────┼──┼────┼─────┼──┤        │          │            │          │        │\n│AH021590│保費│鄭琳卉  │   1045   │月  │        │          │            │          │        │\n├────┼──┼────┼─────┼──┤        │          │            │          │        │\n│H0000000│保費│鄭清江  │   3514   │月  │        │          │            │          │        │\n├────┼──┼────┼─────┼──┤        │          │            │          │        │\n│H0000000│保費│史民俊  │   4391   │月  │        │          │            │          │        │\n├────┼──┼────┼─────┼──┤        │          │            │          │        │\n│H0000000│保費│曾薛秀女│   2854   │月  │        │          │            │          │        │\n├────┼──┼────┼─────┼──┤        │          │            │          │        │\n│H0000000│保費│曾朝憲  │   3081   │月  │        │          │            │          │        │\n├────┼──┼────┼─────┼──┤        │          │            │          │        │\n│H0000000│保費│曾朝政  │   4037   │月  │        │          │            │          │        │\n├────┼──┼────┼─────┼──┤        │          │            │          │        │\n│J0000000│保費│薛歐玉鳳│   2636   │月  │        │          │            │          │        │\n├────┼──┼────┼─────┼──┤        │          │            │          │        │\n│J0000000│保費│薛慶林  │   2204   │月  │        │          │            │          │        │\n├────┼──┼────┼─────┼──┤        │          │            │          │        │\n│H0000000│保費│薛慶林  │   1488   │月  │        │          │            │          │        │\n├────┼──┼────┼─────┼──┤        │          │            │          │        │\n│AH037271│利息│郭玉佩  │    126   │    │        │          │            │          │        │\n├────┼──┼────┼─────┼──┤        │          │            │          │        │\n│F0000000│利息│陳曾不纏│    176   │    │        │          │            │          │        │\n├────┼──┼────┼─────┼──┤        │          │            │          │        │\n│H0000000│利息│鄭清江  │    236   │    │        │          │            │          │        │\n├────┼──┼────┼─────┼──┼────┼─────┼──────┼─────┼────┤\n│J0000000│保費│蔡麗蘭  │  13259   │月  │        │          │            │          │        │\n├────┼──┼────┼─────┼──┤        │          │            │          │        │\n│C0000000│保費│薛林玉蘭│   1787   │月  │        │          │            │          │        │\n├────┼──┼────┼─────┼──┤        │          │            │          │        │\n│J0000000│保費│薛林玉蘭│   2668   │月  │        │          │            │          │        │\n├────┼──┼────┼─────┼──┤        │          │            │          │        │\n│J0000000│保費│周翌星  │    605   │月  │        │          │            │          │        │\n├────┼──┼────┼─────┼──┤        │          │            │          │        │\n│00000000│保費│周翌星  │   2613   │月  │        │          │            │          │        │\n├────┼──┼────┼─────┼──┤        │          │            │          │        │\n│J0000000│保費│謝月綿  │    570   │月  │        │          │            │          │        │\n├────┼──┼────┼─────┼──┤        │          │            │          │        │\n│J0000000│保費│謝月綿  │   1820   │月  │        │          │            │          │        │\n├────┼──┼────┼─────┼──┤        │          │            │          │        │\n│A0000000│保費│吳淑惠  │   2578   │月  │        │          │            │          │        │\n├────┼──┼────┼─────┼──┤        │          │            │          │        │\n│G0000000│保費│吳淑惠  │    946   │月  │        │          │            │          │        │\n├────┼──┼────┼─────┼──┤        │          │            │          │        │\n│G0000000│保費│吳淑惠  │   1126   │月  │        │          │            │          │        │\n├────┼──┼────┼─────┼──┤        │          │            │          │        │\n│G0000000│保費│吳淑惠  │    875   │月  │        │          │            │          │        │\n├────┼──┼────┼─────┼──┤        │          │            │          │        │\n│00000000│保費│李綢緞  │   1536   │月  │        │          │            │          │        │\n├────┼──┼────┼─────┼──┤        │          │            │          │        │\n│J0000000│保費│薛文良  │   1981   │月  │        │          │            │          │        │\n├────┼──┼────┼─────┼──┤        │          │            │          │        │\n│H0000000│保費│薛文良  │    909   │月  │        │          │            │          │        │\n├────┼──┼────┼─────┼──┤        │          │            │          │        │\n│J0000000│保費│林冬結  │    696   │月  │        │          │            │          │        │\n├────┼──┼────┼─────┼──┤        │          │            │          │        │\n│J0000000│保費│林冬結  │   3206   │月  │        │          │            │          │        │\n├────┼──┼────┼─────┼──┤        │          │            │          │        │\n│00000000│保費│邱進於  │   1249   │月  │0000000 │940731    │ 283,256    │合作金庫台│王崑明  │\n├────┼──┼────┼─────┼──┤        │          │            │南分行    │        │\n│J0000000│保費│薛順來  │   7723   │季  │        │          │            │          │        │\n├────┼──┼────┼─────┼──┤        │          │            │          │        │\n│J0000000│保費│楊德肥  │   9280   │季  │        │          │            │          │        │\n├────┼──┼────┼─────┼──┤        │          │            │          │        │\n│J0000000│保費│陳龍泰  │  20370   │季  │        │          │            │          │        │\n├────┼──┼────┼─────┼──┤        │          │            │          │        │\n│J0000000│保費│陳冠銘  │   6996   │半年│        │          │            │          │        │\n├────┼──┼────┼─────┼──┤        │          │            │          │        │\n│J0000000│保費│陳冠銘  │  10857   │半年│        │          │            │          │        │\n├────┼──┼────┼─────┼──┤        │          │            │          │        │\n│N0000000│保費│楊秋芬  │   9473   │年  │        │          │            │          │        │\n├────┼──┼────┼─────┼──┤        │          │            │          │        │\n│E0000000│保費│楊秋芬  │  54440   │年  │        │          │            │          │        │\n├────┼──┼────┼─────┼──┤        │          │            │          │        │\n│AE013341│保費│邱陳秀玉│  13379   │年  │        │          │            │          │        │\n├────┼──┼────┼─────┼──┤        │          │            │          │        │\n│J0000000│保費│鄭旻綺  │  24366   │年  │        │          │            │          │        │\n├────┼──┼────┼─────┼──┤        │          │            │          │        │\n│H0000000│保費│薛順安  │  17074   │年  │        │          │            │          │        │\n├────┼──┼────┼─────┼──┤        │          │            │          │        │\n│C0000000│保費│薛順安  │   6054   │年  │        │          │            │          │        │\n├────┼──┼────┼─────┼──┤        │          │            │          │        │\n│J0000000│利息│楊德肥  │    634   │    │        │          │            │          │        │\n├────┼──┼────┼─────┼──┤        │          │            │          │        │\n│00000000│利息│李綢緞  │  1394    │    │        │          │            │          │        │\n├────┼──┼────┼─────┼──┤        │          │            │          │        │\n│00000000│利息│邱進於  │    982   │    │        │          │            │          │        │\n├────┼──┼────┼─────┼──┤        │          │            │          │        │\n│J0000000│利息│鄭旻綺  │   4563   │    │        │          │            │          │        │\n├────┼──┼────┼─────┼──┤        │          │            │          │        │\n│J0000000│利息│薛順來  │    493   │    │        │          │            │          │        │\n├────┼──┼────┼─────┼──┼────┼─────┼──────┼─────┼────┤\n│H0000000│保費│林福泰  │  38430   │年  │        │          │            │          │        │\n├────┼──┼────┼─────┼──┤0000000 │940815    │165,895     │合作金庫台│王崑明  │\n│H0000000│保費│顏美環  │  24291   │年  │        │          │            │南分行    │        │\n├────┼──┼────┼─────┼──┼────┼─────┼──────┼─────┼────┤\n│H0000000│保費│張好    │   2674   │月  │        │          │            │          │        │\n├────┼──┼────┼─────┼──┤        │          │            │          │        │\n│H0000000│保費│盧安鎮  │   4572   │月  │        │          │            │          │        │\n├────┼──┼────┼─────┼──┤        │          │            │          │        │\n│AW031323│保費│盧立偉  │   1362   │月  │        │          │            │          │        │\n├────┼──┼────┼─────┼──┤        │          │            │          │        │\n│AE002454│保費│蘇慶成  │   1952   │月  │        │          │            │          │        │\n├────┼──┼────┼─────┼──┤        │          │            │          │        │\n│AH000662│保費│柳丁發  │   1452   │月  │        │          │            │          │        │\n├────┼──┼────┼─────┼──┤        │          │            │          │        │\n│AH000681│保費│柳劉秀玲│   2086   │月  │        │          │            │          │        │\n├────┼──┼────┼─────┼──┤        │          │            │          │        │\n│AH000656│保費│柳淑文  │   1673   │月  │        │          │            │          │        │\n├────┼──┼────┼─────┼──┤        │          │            │          │        │\n│F0000000│保費│柳丁發  │    536   │月  │        │          │            │          │        │\n├────┼──┼────┼─────┼──┤        │          │            │          │        │\n│F0000000│保費│柳丁發  │   2012   │月  │        │          │            │          │        │\n├────┼──┼────┼─────┼──┤        │          │            │          │        │\n│G0000000│保費│杜贊長  │    819   │季  │        │          │            │          │        │\n├────┼──┼────┼─────┼──┤        │          │            │          │        │\n│G0000000│保費│戴月花  │    707   │季  │0000000 │940731    │47,215      │合作金庫台│王崑明  │\n├────┼──┼────┼─────┼──┤        │          │            │南分行    │        │\n│J0000000│保費│杜贊長  │   6427   │季  │        │          │            │          │        │\n├────┼──┼────┼─────┼──┤        │          │            │          │        │\n│J0000000│保費│戴月花  │   4505   │季  │        │          │            │          │        │\n├────┼──┼────┼─────┼──┤        │          │            │          │        │\n│G0000000│保費│黃秋燕  │   2157   │月  │        │          │            │          │        │\n├────┼──┼────┼─────┼──┤        │          │            │          │        │\n│F0000000│保費│王鐸馨  │   3930   │月  │        │          │            │          │        │\n├────┼──┼────┼─────┼──┤        │          │            │          │        │\n│F0000000│保費│王貞懿  │   3608   │月  │        │          │            │          │        │\n├────┼──┼────┼─────┼──┤        │          │            │          │        │\n│F0000000│保費│王鐸馨  │   5011   │月  │        │          │            │          │        │\n├────┼──┼────┼─────┼──┤        │          │            │          │        │\n│AH000662│利息│柳丁發  │    221   │    │        │          │            │          │        │\n├────┼──┼────┼─────┼──┤        │          │            │          │        │\n│J0000000│利息│戴月花  │    669   │    │        │          │            │          │        │\n├────┼──┼────┼─────┼──┤        │          │            │          │        │\n│J0000000│利息│杜贊長  │    722   │    │        │          │            │          │        │\n├────┼──┼────┼─────┼──┤        │          │            │          │        │\n│AE002454│利息│蘇慶成  │    190   │    │        │          │            │          │        │\n├────┼──┼────┼─────┼──┼────┼─────┼──────┼─────┼────┤\n│J0000000│保費│郭月華  │  20524   │年  │        │          │            │          │        │\n├────┼──┼────┼─────┼──┤        │          │            │          │        │\n│J0000000│保費│郭月華  │  12289   │年  │        │          │            │          │        │\n├────┼──┼────┼─────┼──┤        │          │            │          │        │\n│J0000000│保費│郭月華  │   3398   │年  │0000000 │940820    │88,850      │合作金庫台│王崑明  │\n├────┼──┼────┼─────┼──┤        │          │            │南分行    │        │\n│J0000000│保費│郭鄭伯霞│  47307   │年  │        │          │            │          │        │\n├────┼──┼────┼─────┼──┤        │          │            │          │        │\n│H0000000│保費│林朝英  │   5332   │年  │        │          │            │          │        │\n├────┼──┼────┼─────┼──┼────┼─────┼──────┼─────┼────┤\n│CQ000620│保費│陳彥佳  │   4205   │月  │        │          │            │          │        │\n├────┼──┼────┼─────┼──┤        │          │            │          │        │\n│CG000449│保費│陳彥佳  │   1121   │月  │        │          │            │          │        │\n├────┼──┼────┼─────┼──┤        │          │            │          │        │\n│J0000000│保費│林宗慶  │   1405   │月  │        │          │            │          │        │\n├────┼──┼────┼─────┼──┤        │          │            │          │        │\n│BQ000917│保費│劉思慧  │   2352   │月  │        │          │            │          │        │\n├────┼──┼────┼─────┼──┤        │          │            │          │        │\n│CG001529│保費│許鈺喬  │   1676   │月  │        │          │            │          │        │\n├────┼──┼────┼─────┼──┤        │          │            │          │        │\n│AH022240│保費│林素文  │   2955   │月  │        │          │            │          │        │\n├────┼──┼────┼─────┼──┤        │          │            │          │        │\n│H0000000│保費│薛慶林  │   1488   │月  │        │          │            │          │        │\n├────┼──┼────┼─────┼──┤        │          │            │          │        │\n│J0000000│保費│薛慶林  │   2204   │月  │        │          │            │          │        │\n├────┼──┼────┼─────┼──┤        │          │            │          │        │\n│J0000000│保費│薛歐玉鳳│   2636   │月  │        │          │            │          │        │\n├────┼──┼────┼─────┼──┤        │          │            │          │        │\n│H0000000│保費│曾薛秀女│   2854   │月  │        │          │            │          │        │\n├────┼──┼────┼─────┼──┤        │          │            │          │        │\n│H0000000│保費│曾朝政  │   4037   │月  │        │          │            │          │        │\n├────┼──┼────┼─────┼──┤        │          │            │          │        │\n│H0000000│保費│曾朝憲  │   3081   │月  │        │          │            │          │        │\n├────┼──┼────┼─────┼──┤        │          │            │          │        │\n│H0000000│保費│史民俊  │   4391   │月  │        │          │            │          │        │\n├────┼──┼────┼─────┼──┤        │          │            │          │        │\n│H0000000│保費│林哲安  │  12923   │年  │        │          │            │          │        │\n├────┼──┼────┼─────┼──┤        │          │            │          │        │\n│G0000000│保費│邱吳秋霞│  62957   │年  │        │          │            │          │        │\n├────┼──┼────┼─────┼──┤        │          │            │          │        │\n│J0000000│保費│邱江凜  │  23057   │年  │        │          │            │          │        │\n├────┼──┼────┼─────┼──┤        │          │            │          │        │\n│A0000000│保費│薛王碧蘭│   2655   │季  │        │          │            │          │        │\n├────┼──┼────┼─────┼──┤        │          │            │          │        │\n│A0000000│保費│薛祈富  │   4550   │季  │        │          │            │          │        │\n├────┼──┼────┼─────┼──┤        │          │            │          │        │\n│H0000000│保費│史長青  │   8706   │季  │        │          │            │          │        │\n├────┼──┼────┼─────┼──┤        │          │            │          │        │\n│H0000000│保費│史斌一  │   6565   │季  │        │          │            │          │        │\n├────┼──┼────┼─────┼──┤ 0000000│940531    │236,283     │台北銀行台│林基耀  │\n│F0000000│保費│薛邱阿鵠│   2561   │月  │        │          │            │南分行    │        │\n├────┼──┼────┼─────┼──┤        │          │            │          │        │\n│H0000000│保費│史長青  │   3829   │季  │        │          │            │          │        │\n├────┼──┼────┼─────┼──┤        │          │            │          │        │\n│AH037271│保費│郭玉佩  │   3231   │月  │        │          │            │          │        │\n├────┼──┼────┼─────┼──┤        │          │            │          │        │\n│AW042833│保費│郭潘金桃│   2338   │月  │        │          │            │          │        │\n├────┼──┼────┼─────┼──┤        │          │            │          │        │\n│F0000000│保費│陳曾不纏│   2859   │月  │        │          │            │          │        │\n├────┼──┼────┼─────┼──┤        │          │            │          │        │\n│H0000000│保費│林欽崇  │  16353   │半年│        │          │            │          │        │\n├────┼──┼────┼─────┼──┤        │          │            │          │        │\n│H0000000│保費│蘇保安  │  12139   │半年│        │          │            │          │        │\n├────┼──┼────┼─────┼──┤        │          │            │          │        │\n│H0000000│保費│陳菱瑤  │  10032   │年  │        │          │            │          │        │\n├────┼──┼────┼─────┼──┤        │          │            │          │        │\n│H0000000│保費│林美鳳  │  13904   │年  │        │          │            │          │        │\n├────┼──┼────┼─────┼──┤        │          │            │          │        │\n│J0000000│保費│蔡元德  │   6400   │年  │        │          │            │          │        │\n├────┼──┼────┼─────┼──┤        │          │            │          │        │\n│BQ000917│利息│劉思慧  │    793   │    │        │          │            │          │        │\n├────┼──┼────┼─────┼──┤        │          │            │          │        │\n│AH022240│利息│林素文  │     96   │    │        │          │            │          │        │\n├────┼──┼────┼─────┼──┤        │          │            │          │        │\n│J0000000│利息│薛歐玉鳳│    642   │    │        │          │            │          │        │\n├────┼──┼────┼─────┼──┤        │          │            │          │        │\n│J0000000│利息│薛慶林  │    837   │    │        │          │            │          │        │\n├────┼──┼────┼─────┼──┤        │          │            │          │        │\n│H0000000│利息│史斌一  │     86   │    │        │          │            │          │        │\n├────┼──┼────┼─────┼──┤        │          │            │          │        │\n│H0000000│利息│史長青  │    725   │    │        │          │            │          │        │\n├────┼──┼────┼─────┼──┤        │          │            │          │        │\n│J0000000│利息│林宗慶  │    408   │    │        │          │            │          │        │\n├────┼──┼────┼─────┼──┤        │          │            │          │        │\n│A0000000│利息│薛王碧蘭│   1226   │    │        │          │            │          │        │\n├────┼──┼────┼─────┼──┤        │          │            │          │        │\n│A0000000│利息│薛祈富  │   2006   │    │        │          │            │          │        │\n├────┼──┼────┼─────┼──┼────┼─────┼──────┼─────┼────┤\n│H0000000│利息│邱林秀枝│    604   │    │        │          │            │          │        │\n├────┼──┼────┼─────┼──┤        │          │            │          │        │\n│H0000000│保費│邱林秀枝│   3545   │月  │        │          │            │          │        │\n├────┼──┼────┼─────┼──┤        │          │            │          │        │\n│00000000│保費│李綢緞  │   1536   │月  │        │          │            │          │        │\n├────┼──┼────┼─────┼──┤        │          │            │          │        │\n│BW028162│保費│李秀里  │   1088   │月  │        │          │            │          │        │\n├────┼──┼────┼─────┼──┤        │          │            │          │        │\n│BL014914│保費│李秀里  │    522   │月  │        │          │            │          │        │\n├────┼──┼────┼─────┼──┤        │          │            │          │        │\n│J0000000│保費│林冬結  │   3140   │月  │        │          │            │          │        │\n├────┼──┼────┼─────┼──┤        │          │            │          │        │\n│J0000000│保費│林冬結  │    696   │月  │        │          │            │          │        │\n├────┼──┼────┼─────┼──┤        │          │            │          │        │\n│J0000000│保費│謝月綿  │    570   │月  │        │          │            │          │        │\n├────┼──┼────┼─────┼──┤        │          │            │          │        │\n│J0000000│保費│謝月綿  │   1820   │月  │        │          │            │          │        │\n├────┼──┼────┼─────┼──┤        │          │            │          │        │\n│00000000│保費│邱進於  │   1249   │月  │        │          │            │          │        │\n├────┼──┼────┼─────┼──┤        │          │            │          │        │\n│BW029111│保費│歐明慶  │   1194   │月  │        │          │            │          │        │\n├────┼──┼────┼─────┼──┤        │          │            │          │        │\n│J0000000│保費│歐玉霞  │   1937   │月  │        │          │            │          │        │\n├────┼──┼────┼─────┼──┤        │          │            │          │        │\n│BL012897│保費│李秀里  │    523   │月  │        │          │            │          │        │\n├────┼──┼────┼─────┼──┤        │          │            │          │        │\n│BL012895│保費│李秀里  │    533   │月  │        │          │            │          │        │\n├────┼──┼────┼─────┼──┤        │          │            │          │        │\n│J0000000│保費│戴志忠  │   3080   │月  │        │          │            │          │        │\n├────┼──┼────┼─────┼──┤        │          │            │          │        │\n│J0000000│保費│戴志忠  │   1418   │月  │        │          │            │          │        │\n├────┼──┼────┼─────┼──┤        │          │            │          │        │\n│J0000000│保費│戴志忠  │    290   │月  │        │          │            │          │        │\n├────┼──┼────┼─────┼──┤00000000│940531    │ 61,394     │台北銀行台│林基耀  │\n│G0000000│保費│吳淑惠  │    946   │月  │        │          │            │南分行    │        │\n├────┼──┼────┼─────┼──┤        │          │            │          │        │\n│G0000000│保費│吳淑惠  │   1126   │月  │        │          │            │          │        │\n├────┼──┼────┼─────┼──┤        │          │            │          │        │\n│A0000000│保費│吳淑惠  │   2578   │月  │        │          │            │          │        │\n├────┼──┼────┼─────┼──┤        │          │            │          │        │\n│F0000000│利息│吳順傭  │   1674   │    │        │          │            │          │        │\n├────┼──┼────┼─────┼──┤        │          │            │          │        │\n│F0000000│保費│陳順傭  │   2909   │月  │        │          │            │          │        │\n├────┼──┼────┼─────┼──┤        │          │            │          │        │\n│J0000000│利息│周翌星  │    603   │    │        │          │            │          │        │\n├────┼──┼────┼─────┼──┤        │          │            │          │        │\n│00000000│利息│周翌星  │   2473   │    │        │          │            │          │        │\n├────┼──┼────┼─────┼──┤        │          │            │          │        │\n│J0000000│保費│周翌星  │    605   │月  │        │          │            │          │        │\n├────┼──┼────┼─────┼──┤        │          │            │          │        │\n│00000000│保費│周翌星  │   2613   │月  │        │          │            │          │        │\n├────┼──┼────┼─────┼──┤        │          │            │          │        │\n│J0000000│保費│薛林玉蘭│   2668   │月  │        │          │            │          │        │\n├────┼──┼────┼─────┼──┤        │          │            │          │        │\n│C0000000│保費│薛林玉蘭│   1787   │月  │        │          │            │          │        │\n├────┼──┼────┼─────┼──┤        │          │            │          │        │\n│G0000000│保費│吳淑惠  │    875   │月  │        │          │            │          │        │\n├────┼──┼────┼─────┼──┤        │          │            │          │        │\n│J0000000│保費│周翌星  │  11731   │季  │        │          │            │          │        │\n├────┼──┼────┼─────┼──┤        │          │            │          │        │\n│J0000000│保費│薛文良  │   1981   │月  │        │          │            │          │        │\n├────┼──┼────┼─────┼──┤        │          │            │          │        │\n│H0000000│保費│薛文良  │    909   │月  │        │          │            │          │        │\n├────┼──┼────┼─────┼──┤        │          │            │          │        │\n│H0000000│利息│林有志  │    172   │    │        │          │            │          │        │\n├────┼──┼────┼─────┼──┤        │          │            │          │        │\n│H0000000│保費│林有志  │   1999   │月  │        │          │            │          │        │\n├────┼──┼────┼─────┼──┼────┼─────┼──────┼─────┼────┤\n│F0000000│保費│柳丁發  │   2012   │月  │        │          │            │          │        │\n├────┼──┼────┼─────┼──┤        │          │            │          │        │\n│AH000656│保費│柳淑文  │   1673   │月  │        │          │            │          │        │\n├────┼──┼────┼─────┼──┤        │          │            │          │        │\n│AH000681│保費│柳劉秀玲│   2086   │月  │        │          │            │          │        │\n├────┼──┼────┼─────┼──┤        │          │            │          │        │\n│AH000662│保費│柳丁發  │   1452   │月  │        │          │            │          │        │\n├────┼──┼────┼─────┼──┤        │          │            │          │        │\n│G0000000│保費│陳淑芸  │   2869   │年  │        │          │            │          │        │\n├────┼──┼────┼─────┼──┤        │          │            │          │        │\n│H0000000│保費│呂麗紅  │   7652   │年  │        │          │            │          │        │\n├────┼──┼────┼─────┼──┤        │          │            │          │        │\n│H0000000│保費│呂麗紅  │   3369   │年  │        │          │            │          │        │\n├────┼──┼────┼─────┼──┤        │          │            │          │        │\n│G0000000│保費│黃秋燕  │   2157   │月  │        │          │            │          │        │\n├────┼──┼────┼─────┼──┤        │          │            │          │        │\n│H0000000│保費│戴月花  │   3049   │季  │        │          │            │          │        │\n├────┼──┼────┼─────┼──┤ 0000000│940531    │77,486      │台北銀行台│林基耀  │\n│H0000000│保費│杜贊長  │   2894   │季  │        │          │            │南分行    │        │\n├────┼──┼────┼─────┼──┤        │          │            │          │        │\n│G0000000│保費│魏翠薇  │   3706   │年  │        │          │            │          │        │\n├────┼──┼────┼─────┼──┤        │          │            │          │        │\n│F0000000│保費│柳丁發  │    536   │月  │        │          │            │          │        │\n├────┼──┼────┼─────┼──┤        │          │            │          │        │\n│00000000│保費│陳淑芸  │  29169   │年  │        │          │            │          │        │\n├────┼──┼────┼─────┼──┤        │          │            │          │        │\n│AW031323│保費│盧立偉  │   1362   │月  │        │          │            │          │        │\n├────┼──┼────┼─────┼──┤        │          │            │          │        │\n│H0000000│保費│張好    │   2674   │月  │        │          │            │          │        │\n├────┼──┼────┼─────┼──┤        │          │            │          │        │\n│H0000000│保費│盧安鎮  │   4572   │月  │        │          │            │          │        │\n├────┼──┼────┼─────┼──┤        │          │            │          │        │\n│F0000000│利息│柳丁發  │    699   │    │        │          │            │          │        │\n├────┼──┼────┼─────┼──┤        │          │            │          │        │\n│00000000│利息│陳淑芸  │   5555   │    │        │          │            │          │        │\n├────┼──┼────┼─────┼──┼────┼─────┼──────┼─────┼────┤\n│00000000│保費│張世宗  │  15670   │年  │        │          │            │          │        │\n├────┼──┼────┼─────┼──┤        │          │            │          │        │\n│F0000000│保費│楊敬業  │   3042   │年  │        │          │            │          │        │\n├────┼──┼────┼─────┼──┤0000000 │940612    │47,193      │合作金庫台│王崑明  │\n│F0000000│保費│楊樂群  │   2962   │年  │        │          │            │南分行    │        │\n├────┼──┼────┼─────┼──┤        │          │            │          │        │\n│00000000│保費│施金蓮  │  25519   │年  │        │          │            │          │        │\n└────┴──┴────┴─────┴──┴────┴─────┴──────┴─────┴────┘",
  "structure": {
    "main": "原判決撤銷。\n甲○○連續犯業務侵占罪，處有期徒刑拾月，減為有期徒刑伍月\n，如易科罰金，以銀元參佰元即新台幣玖佰元折算壹日。",
    "fact": "一、甲○○自民國（下同）81年起，任職國華人壽保險股份有限\n    公司（下稱：國華人壽公司）之業務員，負責向客戶招攬人\n    身保險及收取保險費用，為從事業務之人。甲○○明知其向\n    客戶收取保費後，應將款項交予國華人壽公司，竟因私人投\n    資失利，而基於為自己不法所有意圖之概括犯意，自94年2\n    月間起至94年6月間止，連續向如附表所示之客戶收取如附\n    表所示之保費共新臺幣（下同）2,648,853元後，未將收取\n    之現金繳交予國華人壽公司，而變易持有為所有之意思，將\n    款項全數侵占入己另行挪用，並開立發票人為王崑明、林基\n    耀之支票22張交予國華人壽公司抵交保費，詎上開支票屆期\n    均未獲兌現，始為國華人壽公司查悉上情。\n二、案經國華人壽公司告訴由臺灣台南地方法院檢察署檢察官偵\n    查後起訴。",
    "reason": "一、本件被告甲○○所犯並非死刑、無期徒刑或最輕本刑有期徒\n    刑3 年以上之罪，亦非高等法院管轄第一審案件，其於準備\n    程序中就被訴事實為有罪之陳述，經本院告知被告簡式審判\n    程序之旨，並聽取檢察官及被告之意見後，裁定以簡式審判\n    程序審理，是本案之證據調查，依刑事訴訟法第273條之2規\n    定，不受同法第159條第1項、第161條之2、第161條之3、第\n    163條之1及第164條至第170條之限制，合先敘明。\n二、查上揭事實業據被告甲○○坦承不諱，核與告訴人國華人壽\n    公司所指訴情節相符，復有被告親自書立之還款切結書影本\n    一紙、王崑明及林基耀所簽發之支票暨退票理由單影本二十\n    二紙及國華人壽公司保戶林素文等人之繳費情形聲明書二百\n    十六紙附卷可稽，互核相符，事證明確，被告犯行已堪認定\n    。\n三、查被告行為後，刑法業於94年2月2日修正公布，並定95 年7\n    月1日起施行，茲依刑法第2條第1項規定，就新舊法比較結\n    果，敘述如下：\n（一）刑法第336條第2項業務侵占罪規定，雖未經修正，但該條\n      併科罰金刑部分，依修正後刑法第33條第5款之規定，最\n      低額為新臺幣一千元，惟依被告行為時之刑法第33條第5\n      款規定，罰金之最低額僅新臺幣3元。比較修正前後之刑\n      罰法律，適用「修正前」之規定，對被告較為有利。\n（二）修正後刑法已刪除第56條連續犯之規定，則被告之犯行，\n      因行為後刑法業已刪除連續犯之規定，此刪除雖非犯罪構\n      成要件之變更，但顯已影響行為人刑罰之法律效果，自屬\n      法律有變更，比較修正前後之刑罰法律，如不以連續犯論\n      以一罪，即須適用數罪併罰規定，對被告較為不利，自以\n      適用「修正前」之規定，對被告較為有利\n（三）另按修正前刑法第41條第1項前段規定：「犯最重本刑為5\n      年以下有期徒刑之刑之罪，而受6個月以下有期徒刑或拘\n      役之宣告，因身體、教育、職業、家庭之關係或其他正當\n      理由，執行顯有困難者，得以1元以上3元以下折算1日，\n      易科罰金」。而刑法修正施行前之易科罰金折算標準，修\n      正前罰金罰鍰提高標準條例第2條前段規定（95年5月17日\n      修正刪除，95年7月1日施行），就其原定數額提高為100\n      倍折算1日，則刑法修正施行前易科罰金折算標準，應以\n      銀元300元即新臺幣900元折算1日；而修正後刑法第41條\n      第1項前段規定：「犯最重本刑為5年以下有期徒刑以下之\n      罪，而受6個月以下有期徒刑或拘役之宣告者，得以新臺\n      幣1千元、2千元或3千元折算1日，易科罰金」。比較新舊\n      法易科罰金之折算標準，亦以「修正前」之規定，較有利\n      於被告。\n（四）至「修正後刑法」施行前，「刑法分則編」有關「罰金刑\n      」之貨幣單位係銀元；且依刑法分則編應處罰金者，適用\n      現已廢止罰金罰鍰提高標準條例第1條、第4條之規定，亦\n      即應按各該具體條文制定或修正之時間先後，定其提高之\n      倍數。惟被告行為後，刑法施行法增訂第1條之1，於95年\n      6月14日經總統公布，並自同年7月1日起施行；該條規定\n      ：「中華民國94年1月7日刑法修正施行後，刑法分則編所\n      定罰金之貨幣單位為新臺幣。94年1月7日刑法修正時，刑\n      法分則編未修正之條文定有罰金者，自94年1月7日刑法修\n      正施行後，就其所定數額提高為30倍。但72年6月26日至\n      94年1月7日新增或修正之條文，就其所定數額提高為三倍\n      」。亦即自95年7月1日起，刑法分則編所定罰金之「貨幣\n      單位」，由銀元改為新臺幣。惟刑法施行法第1條之1係替\n      代罰金罰鍰提高標準條例部分條文，與經換算後，該條例\n      所定之罰金額度相同，僅係貨幣單位由銀元改為新臺幣，\n      其罰金刑之刑度並無變更，不發生有利、不利之問題，亦\n      非法律變更刑度之條文，是被告所犯刑法第336條第2項業\n      務侵占罪部分，並無比較新舊法之問題，併予敘明。\n（五）綜合上述刑法新舊法之比較適用，應依刑法第2條第1項前\n      段之規定，一體適用有利於行為人之「修正前」刑法規定\n      。\n四、核被告所為係犯刑法第三百三十六條第二項之業務侵占罪。\n    又被告所為數次業務侵占行為間，其時間緊接，觸犯犯罪構\n    成要件相同之罪名，顯係基於概括犯意而反覆為之，應依修\n    正前刑法第五十六條連續犯規定，論以一罪，並酌加重其刑\n    。\n五、原判決依據上開事證予以被告論罪科刑，固非無見。然查，\n    被告係經通緝而自行到案說明，並非經警緝獲，原判決未依\n    中華民國96年罪犯減刑條例規定予以減刑（詳如後述），自\n    屬違誤。被告據此提起上訴，為有理由，自應由本院撤銷改\n    判。爰審酌被告並無任何前科紀錄，顯見其素行尚佳、其因\n    自身投資失利，而侵占業務上所收取款項之犯罪動機、目的\n    ，犯罪後雖已與告訴人國華人壽公司成立和解，惟迄今僅償\n    還542,849元，尚欠2,106,004元等一切情狀，量處有期徒刑\n    十月。又本件被告犯罪時間在96年4月24日以前，所犯罪名\n    雖係中華民國96年罪犯減刑條例第3條第1項第15款所列罪名\n    ，然其宣告刑未逾有期徒刑一年六月，依該條例第3條反面\n    解釋，自應減其宣告刑2分之1，併諭知易科罰金之折算標準\n    。至於中華民國九十六年罪犯減刑條例施行（96年7月16日\n    ）前，經通緝而未於96年12月31日以前「自動歸案」接受偵\n    查、審判或執行者，不得依本條例減刑，上開條例第5條、\n    第16條固定有明文。查本件被告之業務侵占犯行，係於96年\n    4 月24日之前，且被告並因本案於95年8月21日，經台灣台\n    南地方法院檢察署發布通緝在案，然被告係於通緝當日，經\n    警聯絡策動告知，即自行至台南市警察局第六分局到案說明\n    ，並非經警緝獲等情，有被告95年8月21日警詢筆錄、該分\n    局解送人犯報告書（載明被告自行至台南市○區○○○路2\n    段241號）及該分局地址資料（該址即該分局地址）在卷可\n    證（偵緝字第1228號偵查卷第2-4頁、本院卷第26-28頁），\n    依據上開條例第5條之規定反面解釋，自應減刑，附此敘明\n    。\n據上論結，應依刑事訴訟法第369條第1項前段、第364條、第299\n條第1項前段，刑法第2條第1項前段、修正前刑法第56條、第41\n條第1項、刑法第336條第2項，刑法施刑法第1條之1，廢止前罰\n金罰鍰提高標準條例第2條，中華民國九十六年罪犯減刑條例第2\n條第1項第3款、第7條、第9條，判決如主文。\n本案經檢察官謝錫和到庭執行職務。\n中    華    民    國    99    年    1     月    5     日\n                  刑事第三庭    審判長法  官  陳義仲\n                                      法  官  楊清安\n                                      法  官  宋明中\n以上正本證明與原本無異。\n不得上訴。\n                                      書記官  王薇潔"
  },
  "characters": {
    "judges": [
      "陳義仲",
      "楊清安",
      "宋明中"
    ],
    "prosecutors": [
      "謝錫和"
    ],
    "lawyers": [

    ],
    "clerks": [
      "王薇潔"
    ],
    "plaintiffs": [

    ],
    "defendants": [
      "甲"
    ],
    "prosecutor_office": [

    ],
    "creditors": [

    ],
    "debtors": [

    ],
    "judicial_associate_officer": [

    ]
  },
  "adjudged_at": "2010-01-05",
  "created_at": "2016-01-05 15:08:15",
  "updated_at": "2016-01-05 15:08:15"
}