{
  "identify": "TNH-99-聲-1-20100105-1",
  "court": {
    "name": "臺灣高等法院",
    "code": "TNH"
  },
  "division": {
    "name": "刑事",
    "code": "M"
  },
  "year": 99,
  "word": "聲",
  "number": "1",
  "jcheck": "1",
  "reason": "假釋中付保護管束",
  "content": "臺灣高等法院臺南分院刑事裁定             99年度聲字第1號\n聲  請  人  臺灣高等法院臺南分院檢察署檢察官\n受  刑  人  甲○○\n上列受刑人因強盜案件，聲請人聲請交付保護管束（99年度執聲\n字第5號），本院裁定如下：\n    主  文\n甲○○假釋中付保護管束。\n    理  由\n一、聲請意旨略以：受刑人前因強盜案件，判決確定後，移送執\n    行。茲聲請人以受刑人業經法務部於民國（下同）98年12月\n    28日以法矯字第0980052760號函核准假釋，而縮短刑期後刑\n    期終了日期為100年12月14日，聲請於其假釋中付保護管束\n    等情。\n二、本院審核相關文件，認為聲請為正當，爰依修正後刑事訴訟\n    法第481條第1項，刑法第93條第2項、第96條但書，裁定如\n    主文。\n中    華    民    國    99    年    1     月    5     日\n                  刑事第三庭    審判長法  官  陳義仲\n                                      法  官  楊清安\n                                      法  官  宋明中\n以上正本證明與原本無異。\n如不服本裁定，應於收受本裁定後五日內向本院提出抗告狀。\n                                      書記官  王薇潔\n中    華    民    國    99    年    1     月    5     日",
  "structure": {
    "main": "甲○○假釋中付保護管束。",
    "reason": "一、聲請意旨略以：受刑人前因強盜案件，判決確定後，移送執\n    行。茲聲請人以受刑人業經法務部於民國（下同）98年12月\n    28日以法矯字第0980052760號函核准假釋，而縮短刑期後刑\n    期終了日期為100年12月14日，聲請於其假釋中付保護管束\n    等情。\n二、本院審核相關文件，認為聲請為正當，爰依修正後刑事訴訟\n    法第481條第1項，刑法第93條第2項、第96條但書，裁定如\n    主文。"
  },
  "characters": {
    "judges": [
      "陳義仲",
      "楊清安",
      "宋明中"
    ],
    "prosecutors": [

    ],
    "lawyers": [

    ],
    "clerks": [
      "王薇潔"
    ],
    "plaintiffs": [

    ],
    "defendants": [

    ],
    "prosecutor_office": [
      "臺灣高等法院臺南分院檢察署檢察官"
    ],
    "creditors": [

    ],
    "debtors": [

    ],
    "judicial_associate_officer": [

    ]
  },
  "adjudged_at": "2010-01-05",
  "created_at": "2016-01-05 15:08:03",
  "updated_at": "2016-01-05 15:08:03"
}