{
  "identify": "TNH-98-上易-63-20100105-1",
  "court": {
    "name": "臺灣高等法院",
    "code": "TNH"
  },
  "division": {
    "name": "刑事",
    "code": "M"
  },
  "year": 98,
  "word": "上易",
  "number": "63",
  "jcheck": "1",
  "reason": "詐欺",
  "content": "臺灣高等法院臺南分院刑事判決          98年度上易字第63號\n上  訴  人  臺灣臺南地方法院檢察署檢察官\n被      告  丁○○\n選任辯護人  江大寧律師\n被      告  乙○○\n上列上訴人因被告等詐欺案件，不服臺灣臺南地方法院97年度易\n字第994號中華民國97年12月2日第一審判決（起訴案號：臺灣臺\n南地方法院檢察署96年度偵緝字第1950、1951號），提起上訴，\n本院判決如下：\n    主  文\n上訴駁回。\n    理  由\n一、公訴意旨略稱：被告丁○○及乙○○二人係男女朋友，經扶\n    輪社活動而認識甲○○，二人竟共同基於意圖為自己不法所\n    有之犯意聯絡，於民國94年10月間，向甲○○謊稱欲邀甲○\n    ○共同開設中古車行，而投資方式是：購入車輛之費用由甲\n    ○○出資，中古車行之經營包含找店舖、找車子、僱用店員\n    等等事項均由丁○○負責，而獲利方式是：待車輛轉手售出\n    後，分予甲○○4成利潤云云，嗣後丁○○於臺南市○○區\n    ○○路236號1樓設立「懷特先生有限公司」（下稱懷特公司\n    ），並再遊說甲○○投資，丁○○及乙○○並開立附表所示\n    支票作為擔保，甲○○不疑有他，乃在臺南市○○路將購買\n    車輛之費用交付予丁○○及乙○○二人。嗣後丁○○為取信\n    甲○○，乃將所購入車輛之原始證件如行車執照及副鑰匙交\n    付予甲○○，甲○○因而陷於錯誤，方才同意繼續出資，並\n    多次交付合計新台幣（下同）559萬元予丁○○以購買車輛\n    ，惟丁○○竟於94年12月間，以需要將車輛建檔為由，向甲\n    ○○騙取上開車輛之原始證件及副鑰匙，嗣經甲○○前往懷\n    特公司查看，懷特公司內已空無一物、車輛已不翼而飛，且\n    丁○○及乙○○所開立之上開支票均未獲兌現，甲○○始發\n    覺受騙。因認被告二人共同涉有刑法第339條第1項之詐欺罪\n    嫌等語。\n二、按被告以外之人於審判外之陳述，雖不符刑事訴訟法第159\n    條之1至第159條之4之規定，而經當事人於審判程序同意作\n    為證據，法院審酌該言詞陳述或書面陳述作成時之情況，認\n    為適當者，亦得為證據刑事訴訟法第159條之5第1項定有明\n    文。本件公訴人、被告及辯護人對於本案全部證據資料之證\n    據能力均表示同意採為證據之意思，依前揭規定，應認均有\n    證據能力，合先敘明。\n三、次按犯罪事實應依證據認定之，無證據不得認定其犯罪事實\n    ；又不能證明被告犯罪者，即應諭知無罪之判決，刑事訴訟\n    法第154條第2項、第301條第1項分別定有明文。另按認定犯\n    罪所憑之證據，無論其為直接證據或間接證據，其為訴訟上\n    之證明時，均須達於一般通常之人均不致於有所懷疑，而得\n    確信其為真實之程度，始得據之為有罪之認定。倘其證明尚\n    未達到此一程度，而有合理性之懷疑存在，致使無從形成有\n    罪之確信時，根據「罪證有疑，利於被告」之證據法則，即\n    不得遽為不利被告之認定。又告訴人之告訴，係以使被告受\n    刑事訴追為目的，是其陳述是否與事實相符，仍應調查其他\n    證據以資審認；又認定犯罪事實之證據，係指得以認定被告\n    確有犯罪行為之積極證據而言，該項證據自須適合於被告犯\n    罪事實認定，始得採為斷罪資料，如未能發現相當證據，或\n    證據不足以證明，自不能以推測或擬制之方法，為裁判基礎\n    。苟積極證據不足為不利於被告事實之認定時，即應為有利\n    於被告之認定，更不必有何有利之證據（最高法院52年臺上\n    字第1300號、29年度上字第3105號、30年度上字第816號、\n    40年臺上字第86號判例意旨參照）。\n四、公訴意旨認被告二人涉犯刑法339條第1項之詐欺罪嫌，無非\n    以(1)告訴人甲○○於警詢及偵審之指訴；(2)被告丁○○、乙\n    ○○於偵查中供述；(3)證人黃雅萍於偵查中之證述；(4)證人\n    傅俊超於偵審之證述；(5)證人洪銘偉、王子堅、劉振東三人\n    於偵查中證述；(6)車號4522-KH、4415-KH、4413-KH號自小\n    客車之汽車燃料使用費繳納通知書及(7)如附表所示之支票11\n    張影本等為據。惟訊據被告丁○○、乙○○固坦承丁○○有\n    開設懷特公司及向告訴人甲○○拿取金錢，並開立如附表所\n    示支票為擔保，然迄未清償票款等情，惟均堅決否認有詐欺\n    之犯行，被告丁○○辯稱：我與甲○○單純是借款關係，我\n    並無邀甲○○投資中古車，只有提供我自己所有2、3台車之\n    車籍資料予甲○○擔保借款，另借過2、3台權利車予甲○○\n    使用，借款時並未指定要用來買權利車等語；被告乙○○則\n    以：我都在家照顧小孩，並未與丁○○一同邀甲○○投資中\n    古車，只有去甲○○店裡幫丁○○拿過1、2次錢知道他們之\n    間有債務往來，但不清楚細節等語，資為抗辯。\n五、經查被告丁○○、乙○○二人為同居未婚關係，被告丁○○\n    原為懷特公司（於92年12月24日設立）之負責人（現負責人\n    為李進爐）、被告乙○○為同旗股份有限公司（下稱同旗公\n    司，已命令解散）、群邵股份有限公司（下稱群邵公司，已\n    撤銷登記）之負責人。告訴人甲○○約於93年間加入扶輪社\n    而認識被告二人後，雙方即常有金錢往來。被告丁○○有從\n    事權利車之買賣及中古二手車之介紹業務，並曾提供車輛予\n    甲○○使用，其中一台鈴木SOLIO權利車為案外人洪銘偉所\n    有借予案外人劉振東向上林當舖借錢，經被告丁○○贖回後\n    借予甲○○使用，嗣遭銀行拖走。另被告丁○○曾交付車輛\n    之車籍資料予甲○○作為債務之擔保，然業經被告丁○○取\n    回。被告丁○○有以如附表所示支票為擔保向甲○○取得金\n    錢至少554萬元，然上開支票屆期經提示並未獲付款等事實\n    ，業經證人即告訴人甲○○迭於偵、審指訴明確，且為被告\n    二人所是認，並有證人洪銘偉、王子堅、劉振東三人於偵查\n    中證述屬實，並有懷特、同旗、群紹公司之營利事業登記資\n    料，以及車號4522-KH、4415-KH、4413-KH號自小客車之汽\n    車燃料使用費繳納通知書及如附表所示之支票影本11張等附\n    卷可參，此部分事實固無疑義。\n六、證人劉振東於偵查所證，僅足證明被告丁○○曾幫其向上林\n    當舖贖車，並將行照、車籍資料及上開汽車燃料稅繳納通知\n    單等物交予被告丁○○，至於被告與告訴人間之金錢往來，\n    及被告如何將車交予告訴人等情，亦非其所知。又證人洪銘\n    偉、王子堅均於偵查中證稱:「不認識丁○○、乙○○、甲\n    ○○」等語，自無從知悉並證明被告與告訴人間之財務糾紛\n    。另上開自小客車之汽車燃料使用費繳納通知書及附表所示\n    之支票11張等物，僅足證明，被告有交付車輛予告訴人使用\n    及開具支票擔保付款之事實，然均不足以證明被告有何詐騙\n    告訴人之事實。\n七、且查：\n  (一)告訴人甲○○就遭受被告二人詐騙，曾為以下之前後反覆不\n    一之陳述：\n    警詢：我與丁○○、乙○○原本不認識，是去年（94年）\n      我加入扶輪社的時候才認識的，94年7月左右我加入扶輪\n      社認識他們兩個，後來10月初的時候，丁○○告訴我要找\n      我一起投資開設中古車行的買賣，如果車輛有售出的話，\n      利潤我們兩個四、六分帳（我分利潤四成），後來丁○○\n      就到南市○○區○○路跟南華路口那邊開設一家懷特先生\n      有限公司，然後對我說有估到車輛的話，我先支付現金，\n      然後他會開立支票給我，等到車輛賣出的話，再將我該得\n      的利潤分給我，後來他前前後後總共估了12輛，而且每一\n      次將車取回的時候，他會將車輛的原始證件及副鑰匙交給\n      我，也分別以開立面額10萬元至92萬元不等之12張支票給\n      我」。\n    偵查：丁○○約定我先出資買車，車賣得的利潤我們七三\n      分，所以我前後共出資500多萬元，被告有交付給我幾輛\n      車的行車執照和備份車鑰匙，被告買車後就陸續開支票給\n      我，支票頭幾張有兌現，之後12月份的就跳票了。被告還\n      特地去租房子，擺了幾輛車在那裡，像是有在經營汽車買\n      賣，結果根本沒有在經營，他跟我說他要在永華路開設一\n      家懷特公司，結果他有設立，後來如果他有買到車，就拿\n      車籍資料給我看，我就給他該輛車等價的金錢，他就把車\n      籍資料及鑰匙給我。當初約定他六我四，因為才二個月，\n      因此並未有分紅，但是我從他處拿得約八、九輛車的車籍\n      資料及鑰匙。我給他七百多萬是要投資中古車買賣。他估\n      到車就來找我，要我出錢買車，我就交付現金給他，他買\n      車之後就將車鑰匙及行照給我，並且開立支票給我，支票\n      面額即我交給他的現金金額，當初約定買車錢由我負擔，\n      其餘的成本支出，包括找店面、經營店面、付租金，雇請\n      店員、發薪水實際經營事項均由被告丁○○負責，車子賣\n      掉之後，他會將本金及買車的錢還我並且會另外分給我四\n      成的利潤。被告買12台車的時間前後總共1個多月。懷特\n      公司有成立，我也有看過3台車，被告也有表示那是用我\n      的錢去買的。被告總共給我12台車的行照、鑰匙、汽車燃\n      料繳納通知書等，支票金額代表丁○○購車的錢，也同時\n      代表我所交付給丁○○之現金金額，交付現金的金額就與\n      支票的總額一樣，車子賣掉的錢，扣除先還我買車的錢，\n      剩下的我再分四成其中這四成還包括利息在內，利息我們\n      約定自我交付金錢那天開始算起，直到車子賣出，中間這\n      段期間以1分或1分半計算利息。五百多萬到底是買了多少\n      台車，詳細的數字我不確定，應該是12台，簽發支票的日\n      期與交付現金的日期應該是同一天，沒有一張支票兌現過\n      等語。\n    原審：「有利潤的分配，按照四六比例分配，他分六成，\n      我分四成。投資金額就是買車的價款，也就是支票的面額\n      。我提供給警察三輛車子的汽車燃料稅使用收據，那輛車\n      是由他買，然後留給我開，最後他也是把車子牽回去，汽\n      車燃料稅收據因為沒有一起放在袋子裡面，所以有留下來\n      ，那是跟車籍資料一起的。一開始設立懷特汽車中古買賣\n      到他要去租店鋪，這些錢都是我先支付的，租店鋪的錢是\n      我支付的。我投資的金額之前有兌現幾台，他有賣掉成交\n      應該有三、四台，借錢的部份是先扣除利息沒錯，可是投\n      資的部份沒有利息，投資的部份是賣之後才結算利息。（\n      問:你給付的金額就是他要買中古車的車款嗎？金額是一\n      致的嗎？）不一定是這金額，但他都會算整數拿錢。（問\n      ：總共估12輛車，開12張支票，這12張支票都是你投資買\n      車的錢？）對，12張都沒有兌現。（問：警卷中的第16頁\n      這張有無兌現？）這張應該不是車款。（問：所以他要你\n      估的車子是11台還是12台，開的票據是11張還是12張？）\n      應該是11台車，11張票。有3張有賣出去，不包括在這11\n      張裡面。（問：你方才說有賣出三台車，這三台車的獲利\n      ，除方才說的六、四比的分配之外，還有無算你出資買車\n      時的利息嗎？）有。他都算在我的40％中，我先出資買出\n      ，在賣掉之後給四成就是包括利息在裡面，就紅利沒利息\n      」；「我投資他買車子的數量是11台，所以被告也開了11\n      張支票給我，後來被牽走的那一台車，是我跟被告借的，\n      不是投資的車子。被告把我們投資的車輛拿來借給我使用\n      ，前後有3輛。最後被牽走的那一台，也是投資的車輛。\n      是一台一台車分別投資，被告進車之後，會放在府前路的\n      懷特公司，然後我會過去看車，我看了之後才決定要不要\n      投資，要投資才會給被告錢，被告才會把車籍資料交給我\n      ，且開立支票給我，支票的金額有時候就是車子買進的價\n      錢，有時候是加上前一台車賣出去的紅利，被告賣車之後\n      ，我才可以去兌領支票，差價的部分，再按我四他六的比\n      例分紅。（問：如果車子沒有賣出去的話怎麼辦？）沒有\n      談到這些，可是如果票到期，車子還沒有賣出去，可以再\n      換票。（問：你說之前有賣出3台，加上沒有賣出去的11\n      台，是否總共進14台車？）應該是。紅利是一台車一台車\n      算，分紅的錢，被告他會另外開票給我。我去店的時候都\n      會看到有車子擺在裡面，我有看過鈴木、裕隆及賓士的車\n      。他本來是有跟我說要買中古車，可是被告到後來有買權\n      利車，可是我覺得都可以接受。店裡面有擺車，所以可以\n      看得出來是在賣車的。賣出的三台車另外再開票的金額，\n      其中1台金額大概是是8萬元，另外兩台金額不一樣，我不\n      記得了」等語。\n    依上所述，告訴人甲○○前後所為不利於被告二人之指訴\n      ，就(1)分紅比例、(2)投資金額、(3)投資車輛之數量、(4)懷\n      特公司有無經營賣車業務、(5)投資後是否曾經分紅、(6)紅\n      利之外有無另計利息、(7)交付投資金額之日期是否即支票\n      之發票日、(8)投資之金額是否即支票面額、(9)為擔保投資\n      金額之支票曾否兌現以及(10)被牽走的的車輛究否為投資之\n      車輛等諸多情節之證述，均反覆不一多所歧異，且此等事\n      涉其所指訴被告如何施詐之過程，要非屬細節之些微不同\n      ，顯係重大瑕疵，自難憑信。\n  (二)告訴人甲○○所為指訴核與下列證據及經驗法則不相符合：\n    告訴人甲○○迭於警詢及偵審中指稱：我與被告等人投資\n      買賣汽車期間，被告有交付有幾輛車的行車執照和備份車\n      鑰匙，在被告丁○○消失的前二天，丁○○告訴我那些車\n      籍資料（包括行車執照和車鑰匙）需要再影印做建檔，所\n      以我就把行車執照和車鑰匙拿給被告丁○○指派前來之丙\n      ○○，當天我還打電話問他說可不可以拿回那些證件，丁\n      ○○推說影印機壞掉了，無法影印，結果隔天再聯絡他就\n      聯絡不上了等語。依其所述，上述「數輛汽車之行車執照\n      及備份鑰匙」，應係被告等交付告訴人以供擔保或取信於\n      告訴人之用。此事攸關數百萬元投資金額之去向或擔保，\n      依社會常情，債權人均會慎重保存或詳加記錄，若被告方\n      面需要記錄車籍，亦僅請告訴人抄錄告知或提供執照影本\n      即可，勿須交付執照原件並進而交付鑰匙。況告訴人甲○\n      ○陳稱其係扶輪社會員，而「扶輪社開放各行業及擁有各\n      項專業的人士加入，但從事某些特定職業的人會被限制不\n      得加入；通常並沒有年紀及經濟能力的限制，只要通過現\n      有社員們的同意即可加入。不過實際上參加扶輪社的社友\n      仍是以中年和富裕的人為主，這往往是因為年紀較長且經\n      濟狀況較佳的人才有較多的時間及心力參予扶輪社活動」\n      ，有維基百科全書網路查詢資料列印本在卷可按，由此可\n      知扶輪社之社友通常具有相當之社會經驗與能力。故告訴\n      人陳稱其僅被告丁○○所稱「需要影印建檔」，即將執照\n      原本連同鑰匙一併交付被告委派前來之人，且未記錄該等\n      車輛之型號或車號，殊與社會常情有違，而難採信。\n    告訴人請求傳訊之證人丙○○（即告訴人陳稱被告委託前\n      來拿取行車執照及鑰匙之人）則於本院審理時，到庭證述\n      ：伊前係因告訴人甲○○透過朋友之要求，而曾前往懷特\n      公司工作一個星期，當時伊有見到中古車，據伊所知，告\n      訴人是被告丁○○之金主，亦即借錢給被告丁○○之人，\n      且有固定之利息，當時告訴人要求伊前往懷特公司應該有\n      監督丁○○的意思。又被告丁○○不曾要求伊向告訴人拿\n      汽車之鑰匙與資料等語。是告訴人甲○○指稱：(1)其係投\n      資被告丁○○而非借貸款項及(2)被告丁○○曾經派遣丙○\n      ○以建檔為由拿回投資汽車之行車執照及鑰匙等情，即與\n      其所舉證人丙○○所述不相符合。\n    證人傅俊超雖於偵查中證述其曾聽聞被告二人邀請告訴人\n      入股參與汽車買賣事宜，然而該證人於偵查中所證之投資\n      時間為「94年初」，核與告訴人所述受詐時間為94年10月\n      之後明顯不符。而該證人復於原審證稱：「丁○○跟甲○\n      ○說要做投資中古車，大致的情形是說請甲○○做金主，\n      被告丁○○去主持公司，後來應該車子都有買進來，永華\n      路上的懷特先生公司裡都有車子....丁○○與甲○○一起\n      做車行，就看金主的意願，他（指甲○○）覺得這車子有\n      利益，就金主出錢，沒有利益的話，金主就借錢給被告丁\n      ○○。一台車金額應該都是上百萬，因為都是好車。被告\n      與告訴人間之情形實際上較不瞭解，被告丁○○後來有欠\n      甲○○錢....（問：投資跟借款你區分的出來嗎？）在雙\n      方交易的範圍之下，在交易之前去認定說這筆是借你，還\n      是你來投資，這很模糊，內部交易情形如何，我們不會很\n      清楚。像甲○○和被告丁○○這些事，可能就是案件對案\n      件，每個人眼光不一樣，也許丁○○覺得這車賣的出去，\n      但甲○○說這車子我不要，但被告丁○○堅持要買，這就\n      等於說向甲○○借錢買車，也許一台車，甲○○願意，被\n      告丁○○也願意，甲○○說我出錢，我們賺的一人分一半\n      ，那就是共資。（問：你的意思是說，被告丁○○邀甲○\n      ○有些借款，有些是投資？）是。（問：所謂的投資是指\n      他們二人由甲○○出資去買車，被告丁○○出人力去賣車\n      ？一起分享利潤）對。丁○○有在賣車，他也是跟我說他\n      在賣車，我確定他有在經營懷特中古車買賣。每個案件情\n      形不一定，譬如說10輛車，金主又不一定每台車都看的上\n      ，也許這台你喜歡，金主不一定喜歡。也許我們覺得這台\n      車好賣，但甲○○並不覺得好賣，要看他們每台車談的情\n      形如何。（問：以你當時在場的理解，是跟他借錢還是要\n      他一起投資？）先投資，我說是依每個案件的情況而定。\n      （問：你的意思是說，有可能這台車是用借錢的，另一台\n      車是用投資的嗎？）對，我就是記得四、六比例分配，應\n      該是投資。我有問過他店裡賓士車的價錢，確實是要賣的\n      沒錯」等語。核與告訴人堅稱其交付被告財物之原因係「\n      單純投資」乙節，亦不相同。\n    證人葉展嘉亦於原審證述：「被告丁○○和甲○○有私人\n      借貸關係，應該是他們私下有在互相週轉錢，有的情形我\n      不清楚，他們如何算利息我不清楚，他的錢怎麼處理的我\n      就不清楚，現金和票一定會有差，會加入利息。他們的往\n      來差不多從94年3月開始到12月....（問：懷特公司有從\n      事中古車買賣？）不算是中古車買賣，是權利車買賣。（\n      問：你方才說你有看到被告丁○○想甲○○周轉錢，你看\n      到週轉的意思是？）單純的借錢。（問：有無聽過他們討\n      論一起合夥投資買賣中古車的事情？）這我哪有可能聽到\n      ，我只是在那工作。（問：甲○○有無出錢給被告丁○○\n      作中古車的買賣？）我方才有說，幾乎都是權利車買賣較\n      多，借錢給被告丁○○，甲○○知道他的錢給被告丁○○\n      是去買權利車，車子是有進有出，甲○○也會借車去開。\n      （問：甲○○和你們去當舖挑車是先出錢再挑車，還是先\n      挑車再出錢？）是拿車回來再借」等語，亦證述被告丁○\n      ○與告訴人之間係付息借貸，而非告訴人所稱之投資合作\n      。\n    系爭懷特公司係於92年12月24日核准設立，有臺南市政府\n      營利事業登記證及經濟部公司登記資料影本及營利事業登\n      記資料查詢列印單在卷可按，故告訴人指稱該公司乃被告\n      於94年底為了從事中古車買賣而設立懷特公司云云，亦非\n      實情。\n  (三)被告確曾經於懷特公司從事其與告訴人甲○○所稱之「中古\n    車或權利車買賣」：\n    證人黃雅萍雖於偵查中證稱:「我進入懷特公司任職在92\n      年底，一直做到約94年初，我擺貨時沒有看過二手車，我\n      沒有做之後經過懷特公司有一台汽車停在店面，我沒有聽\n      過甲○○」等語，公訴人似欲藉此證明「被告謊稱開設中\n      古車行」之起訴事實。然而告訴人指訴遭被告以「偽稱開\n      設中古車行施詐」之時間為94年10月間，已如前述，該等\n      時間證人黃雅萍業已離職，自難依該證人之證詞，據為不\n      利於被告之認定。\n    證人丙○○及傅俊超均證稱被告丁○○確有以懷特公司經\n      營中古車買賣事宜，證人葉展嘉則證述被告丁○○曾在懷\n      特公司內經營權利車買賣，俱如前述。核與告訴人於原審\n      所證：「（懷特公司）租店鋪的錢是我支付的。我投資的\n      金額之前有兌現幾台，他有賣掉成交應該有三、四台....\n      」等語相符。足徵被告丁○○的確曾在懷特公司內經營中\n      古車或權利車買賣無訛。\n  (四)檢察官論告意旨及告訴人補充告訴意旨另認：(1)依陽信商業\n    銀行健康分行提供之懷特公司帳戶資料顯示，該公司於告訴\n    人受詐期間之94年全年並無資金往來資料，顯見懷特公司於\n    上述時間並無實際經營，而為一空頭公司。(2)依被告等提出\n    被告丁○○經營之懷特公司銷項發票所示，該公司有與被告\n    乙○○掛名為負責人之群邵及同旗公司互開發票方式進行假\n    交易，足認被告二人有利用未實際經營之懷特公司向外詐財\n    之事實。(3)縱認為被告二人所為「借貸關係」之辯解為真，\n    被告丁○○供稱其於94年週轉不靈，亦足認為被告等於借款\n    之時，財力已甚窘迫，被告等仍向告訴人為高額借款，亦足\n    認為有詐欺情事等語。惟查：\n  本件檢察官起訴被告之事實為「於94年10月間，向告訴人甲\n    ○○謊稱欲邀其共同開設中古車行，嗣後丁○○設立懷特公\n    司，並再遊說甲○○投資並開立支票作為擔保，使告訴人甲\n    ○○受詐而參與投資559萬元」，而非「藉未實際經營之懷\n    特公司以虛偽交易方式向他人詐欺財物」。故本案法院審查\n    之重點，厥為「被告二人有無向告訴人詐欺取財」、「被告\n    二人有無偽以懷特公司經營中古車或權利車買賣之事詐騙告\n    訴人」，至於懷特公司於設立經營期間，有無實際經營、有\n    無經營核准以外之事項、是否誠實開立統一發票、有無藉被\n    告掌控之各公司間對開發票而虛偽交易等事實，除非被告被\n    訴之犯罪已經嚴格證明而生起訴範圍擴張之效果，否則均非\n    本院所得實質審理之範圍。依上說明，本件雖有事證足認被\n    告存有藉懷特、群邵及同旗公司互開發票進行虛偽交易之高\n    度可能，尚無從憑此遽認被告二人有以懷特公司向告訴人施\n    詐之行為。\n  證人丙○○、傅俊超及葉展嘉均證稱被告丁○○確有以懷特\n    公司經營中古車或權利車買賣事宜，告訴人復於原審所證：\n    伊有支付懷特汽車租店鋪之費用，且被告過往的確有完成三\n    、四台汽車之交易等語，均如前述，自足認為被告丁○○確\n    曾以其經營之懷特公司經營中古車或權利車之買賣，而無從\n    認為被告等人曾以虛設之懷特公司作為向告訴人詐欺取財之\n    手段。至於懷特公司是否獲准經營中古車買賣、有無如實開\n    立發票誠實納稅、買賣所用之資金是否均存放於該公司申用\n    之陽信商業銀行健康分行帳戶，因非屬本案起訴之犯罪事實\n    ，自非本院所應審查之重點。\n  衡諸經驗法則，若非財務已陷窘迫，而無法以自己之財力支\n    應生活或事業所需，斷無支付利息向外舉債應急之必要，故\n    單純之「週轉不靈」或「財務情況窘迫」而向外借款，不能\n    遽而認定係詐欺之行為，必須證明行為人「於借款之初即存\n    不法所有之意圖而施用詐術」。本件依告訴人所陳「被告過\n    往的確有完成三、四台汽車之交易」，即足證明被告丁○○\n    的確曾以向告訴人借得之款項經營中古車或權利車買賣，參\n    以證人傅俊超證述被告丁○○無法繼續經營之原因為「後來\n    因為大環境的問題，汽車貸款、卡債的問題，不好成交，所\n    以沒有繼續做下去」；證人葉展嘉說明被告丁○○經商失敗\n    之原因為「懷特公司是因為台中那有一家塑膠工廠有在被告\n    丁○○這借錢，他被吵好幾天，受不了就去向地下錢莊借錢\n    ，借到受不了就倒閉，就呆帳拿不回」等語，顯見被告丁○\n    ○並非故意於財務窘迫之際基於不法所有之意圖而向告訴人\n    大量舉債之後避不見面，足認為被告丁○○並非出於詐欺之\n    目的而借款。\n八、綜合上情，本件被告二人就向告訴人借款之後，如何使用借\n    得之款項以及其所答辯之中古車買賣事宜，雖於偵審中多有\n    避重就輕、語焉不詳之情形，然依最高法院30年上字第482\n    號判例所闡示「積極證據不足證明犯罪事實時，被告之抗辯\n    或反證縱屬虛偽，仍不能以此資為積極證據應予採信之理由\n    」意旨，仍須有充份之積極證據，始足為不利於被告之認定\n    。本件告訴人所述各節非但存有一再反覆之顯著暇疵，復與\n    前述各項事證顯現之事實及經驗法則不相符合，自難憑信。\n    而被告二人所持「借款經營車輛買賣」之辯解，則經證人丙\n    ○○、傅俊超及葉展嘉分別證述屬實，自無從認為被告二人\n    有向告訴人施詐情事。且證人傅俊超及葉展嘉均說明被告丁\n    ○○經商係因景氣不佳及其他廠商之拖累而無以為繼，益徵\n    被告等並非惡意向告訴人舉債避不見面而詐取財物。此外復\n    查無「被告向告訴人詐財」之積極證據，應認為被告二人之\n    犯罪不能證明，揆諸首揭關於證據法則之說明，自應為其等\n    無罪判決之諭知。原審依調查證據之所得，認為不足以證明\n    被告二人有基於不法所有之意圖施用詐術使告訴人陷於錯誤\n    之事實，而為被告二人無罪判決之諭知，核無不合。檢察官\n    循告訴人聲請之上訴意旨徒以被告供述前後不一、且告訴人\n    之指訴僅有些許出入及被告於停業之前以詐術將汽車之行車\n    執照及鑰匙取回等節為由，而認原判決認事用法存有違誤據\n    以提起上訴，依前述說明，為無理由，應予駁回。\n據上論結，應依刑事訴訟法第368條，判決如主文。\n本案經檢察官蘇南桓到庭執行職務。\n中    華    民    國    99    年    1     月    5     日\n                  刑事第二庭    審判長法  官  葉居正\n                                      法  官  陳春長\n                                      法  官  陳欽賢\n以上正本證明與原本無異。\n不得上訴。\n                                      書記官  李良倩\n中    華    民    國    99    年    1     月    5     日\n附表\n┌──────┬─────┬────────┬───┐\n│到期日      │支票號碼  │發票人          │面額  │\n├──────┼─────┼────────┼───┤\n│94年12月11日│KS0000000 │丁○○懷特先生有│40萬元│\n│            │          │限公司          │      │\n├──────┼─────┼────────┼───┤\n│94年12月12日│KS0000000 │丁○○懷特先生有│10萬元│\n│            │          │限公司          │      │\n├──────┼─────┼────────┼───┤\n│94年12月13日│KS0000000 │乙○○郡邵股份有│30萬元│\n│            │          │限公司          │      │\n├──────┼─────┼────────┼───┤\n│94年12月17日│KS0000000 │乙○○郡邵股份有│45萬元│\n│            │          │限公司          │      │\n├──────┼─────┼────────┼───┤\n│94年12月18日│KS0000000 │丁○○懷特先生有│50萬元│\n│            │          │限公司          │      │\n├──────┼─────┼────────┼───┤\n│94年12月19日│KS0000000 │乙○○郡邵股份有│45萬元│\n│            │          │限公司          │      │\n├──────┼─────┼────────┼───┤\n│94年12月20日│KS0000000 │丁○○懷特先生有│50萬元│\n│            │          │限公司          │      │\n├──────┼─────┼────────┼───┤\n│94年12月27日│KS0000000 │丁○○懷特先生有│50萬元│\n│            │          │限公司          │      │\n├──────┼─────┼────────┼───┤\n│94年12月29日│KS0000000 │丁○○懷特先生有│50萬元│\n│            │          │限公司          │      │\n├──────┼─────┼────────┼───┤\n│95年2月15日 │KS0000000 │乙○○同旗股份有│92萬元│\n│            │          │限公司          │      │\n├──────┼─────┼────────┼───┤\n│95年2月17日 │KS0000000 │乙○○同旗股份有│92萬元│\n│            │          │限公司          │      │\n└──────┴─────┴────────┴───┘",
  "structure": {
    "main": "上訴駁回。",
    "reason": "一、公訴意旨略稱：被告丁○○及乙○○二人係男女朋友，經扶\n    輪社活動而認識甲○○，二人竟共同基於意圖為自己不法所\n    有之犯意聯絡，於民國94年10月間，向甲○○謊稱欲邀甲○\n    ○共同開設中古車行，而投資方式是：購入車輛之費用由甲\n    ○○出資，中古車行之經營包含找店舖、找車子、僱用店員\n    等等事項均由丁○○負責，而獲利方式是：待車輛轉手售出\n    後，分予甲○○4成利潤云云，嗣後丁○○於臺南市○○區\n    ○○路236號1樓設立「懷特先生有限公司」（下稱懷特公司\n    ），並再遊說甲○○投資，丁○○及乙○○並開立附表所示\n    支票作為擔保，甲○○不疑有他，乃在臺南市○○路將購買\n    車輛之費用交付予丁○○及乙○○二人。嗣後丁○○為取信\n    甲○○，乃將所購入車輛之原始證件如行車執照及副鑰匙交\n    付予甲○○，甲○○因而陷於錯誤，方才同意繼續出資，並\n    多次交付合計新台幣（下同）559萬元予丁○○以購買車輛\n    ，惟丁○○竟於94年12月間，以需要將車輛建檔為由，向甲\n    ○○騙取上開車輛之原始證件及副鑰匙，嗣經甲○○前往懷\n    特公司查看，懷特公司內已空無一物、車輛已不翼而飛，且\n    丁○○及乙○○所開立之上開支票均未獲兌現，甲○○始發\n    覺受騙。因認被告二人共同涉有刑法第339條第1項之詐欺罪\n    嫌等語。\n二、按被告以外之人於審判外之陳述，雖不符刑事訴訟法第159\n    條之1至第159條之4之規定，而經當事人於審判程序同意作\n    為證據，法院審酌該言詞陳述或書面陳述作成時之情況，認\n    為適當者，亦得為證據刑事訴訟法第159條之5第1項定有明\n    文。本件公訴人、被告及辯護人對於本案全部證據資料之證\n    據能力均表示同意採為證據之意思，依前揭規定，應認均有\n    證據能力，合先敘明。\n三、次按犯罪事實應依證據認定之，無證據不得認定其犯罪事實\n    ；又不能證明被告犯罪者，即應諭知無罪之判決，刑事訴訟\n    法第154條第2項、第301條第1項分別定有明文。另按認定犯\n    罪所憑之證據，無論其為直接證據或間接證據，其為訴訟上\n    之證明時，均須達於一般通常之人均不致於有所懷疑，而得\n    確信其為真實之程度，始得據之為有罪之認定。倘其證明尚\n    未達到此一程度，而有合理性之懷疑存在，致使無從形成有\n    罪之確信時，根據「罪證有疑，利於被告」之證據法則，即\n    不得遽為不利被告之認定。又告訴人之告訴，係以使被告受\n    刑事訴追為目的，是其陳述是否與事實相符，仍應調查其他\n    證據以資審認；又認定犯罪事實之證據，係指得以認定被告\n    確有犯罪行為之積極證據而言，該項證據自須適合於被告犯\n    罪事實認定，始得採為斷罪資料，如未能發現相當證據，或\n    證據不足以證明，自不能以推測或擬制之方法，為裁判基礎\n    。苟積極證據不足為不利於被告事實之認定時，即應為有利\n    於被告之認定，更不必有何有利之證據（最高法院52年臺上\n    字第1300號、29年度上字第3105號、30年度上字第816號、\n    40年臺上字第86號判例意旨參照）。\n四、公訴意旨認被告二人涉犯刑法339條第1項之詐欺罪嫌，無非\n    以(1)告訴人甲○○於警詢及偵審之指訴；(2)被告丁○○、乙\n    ○○於偵查中供述；(3)證人黃雅萍於偵查中之證述；(4)證人\n    傅俊超於偵審之證述；(5)證人洪銘偉、王子堅、劉振東三人\n    於偵查中證述；(6)車號4522-KH、4415-KH、4413-KH號自小\n    客車之汽車燃料使用費繳納通知書及(7)如附表所示之支票11\n    張影本等為據。惟訊據被告丁○○、乙○○固坦承丁○○有\n    開設懷特公司及向告訴人甲○○拿取金錢，並開立如附表所\n    示支票為擔保，然迄未清償票款等情，惟均堅決否認有詐欺\n    之犯行，被告丁○○辯稱：我與甲○○單純是借款關係，我\n    並無邀甲○○投資中古車，只有提供我自己所有2、3台車之\n    車籍資料予甲○○擔保借款，另借過2、3台權利車予甲○○\n    使用，借款時並未指定要用來買權利車等語；被告乙○○則\n    以：我都在家照顧小孩，並未與丁○○一同邀甲○○投資中\n    古車，只有去甲○○店裡幫丁○○拿過1、2次錢知道他們之\n    間有債務往來，但不清楚細節等語，資為抗辯。\n五、經查被告丁○○、乙○○二人為同居未婚關係，被告丁○○\n    原為懷特公司（於92年12月24日設立）之負責人（現負責人\n    為李進爐）、被告乙○○為同旗股份有限公司（下稱同旗公\n    司，已命令解散）、群邵股份有限公司（下稱群邵公司，已\n    撤銷登記）之負責人。告訴人甲○○約於93年間加入扶輪社\n    而認識被告二人後，雙方即常有金錢往來。被告丁○○有從\n    事權利車之買賣及中古二手車之介紹業務，並曾提供車輛予\n    甲○○使用，其中一台鈴木SOLIO權利車為案外人洪銘偉所\n    有借予案外人劉振東向上林當舖借錢，經被告丁○○贖回後\n    借予甲○○使用，嗣遭銀行拖走。另被告丁○○曾交付車輛\n    之車籍資料予甲○○作為債務之擔保，然業經被告丁○○取\n    回。被告丁○○有以如附表所示支票為擔保向甲○○取得金\n    錢至少554萬元，然上開支票屆期經提示並未獲付款等事實\n    ，業經證人即告訴人甲○○迭於偵、審指訴明確，且為被告\n    二人所是認，並有證人洪銘偉、王子堅、劉振東三人於偵查\n    中證述屬實，並有懷特、同旗、群紹公司之營利事業登記資\n    料，以及車號4522-KH、4415-KH、4413-KH號自小客車之汽\n    車燃料使用費繳納通知書及如附表所示之支票影本11張等附\n    卷可參，此部分事實固無疑義。\n六、證人劉振東於偵查所證，僅足證明被告丁○○曾幫其向上林\n    當舖贖車，並將行照、車籍資料及上開汽車燃料稅繳納通知\n    單等物交予被告丁○○，至於被告與告訴人間之金錢往來，\n    及被告如何將車交予告訴人等情，亦非其所知。又證人洪銘\n    偉、王子堅均於偵查中證稱:「不認識丁○○、乙○○、甲\n    ○○」等語，自無從知悉並證明被告與告訴人間之財務糾紛\n    。另上開自小客車之汽車燃料使用費繳納通知書及附表所示\n    之支票11張等物，僅足證明，被告有交付車輛予告訴人使用\n    及開具支票擔保付款之事實，然均不足以證明被告有何詐騙\n    告訴人之事實。\n七、且查：\n  (一)告訴人甲○○就遭受被告二人詐騙，曾為以下之前後反覆不\n    一之陳述：\n    警詢：我與丁○○、乙○○原本不認識，是去年（94年）\n      我加入扶輪社的時候才認識的，94年7月左右我加入扶輪\n      社認識他們兩個，後來10月初的時候，丁○○告訴我要找\n      我一起投資開設中古車行的買賣，如果車輛有售出的話，\n      利潤我們兩個四、六分帳（我分利潤四成），後來丁○○\n      就到南市○○區○○路跟南華路口那邊開設一家懷特先生\n      有限公司，然後對我說有估到車輛的話，我先支付現金，\n      然後他會開立支票給我，等到車輛賣出的話，再將我該得\n      的利潤分給我，後來他前前後後總共估了12輛，而且每一\n      次將車取回的時候，他會將車輛的原始證件及副鑰匙交給\n      我，也分別以開立面額10萬元至92萬元不等之12張支票給\n      我」。\n    偵查：丁○○約定我先出資買車，車賣得的利潤我們七三\n      分，所以我前後共出資500多萬元，被告有交付給我幾輛\n      車的行車執照和備份車鑰匙，被告買車後就陸續開支票給\n      我，支票頭幾張有兌現，之後12月份的就跳票了。被告還\n      特地去租房子，擺了幾輛車在那裡，像是有在經營汽車買\n      賣，結果根本沒有在經營，他跟我說他要在永華路開設一\n      家懷特公司，結果他有設立，後來如果他有買到車，就拿\n      車籍資料給我看，我就給他該輛車等價的金錢，他就把車\n      籍資料及鑰匙給我。當初約定他六我四，因為才二個月，\n      因此並未有分紅，但是我從他處拿得約八、九輛車的車籍\n      資料及鑰匙。我給他七百多萬是要投資中古車買賣。他估\n      到車就來找我，要我出錢買車，我就交付現金給他，他買\n      車之後就將車鑰匙及行照給我，並且開立支票給我，支票\n      面額即我交給他的現金金額，當初約定買車錢由我負擔，\n      其餘的成本支出，包括找店面、經營店面、付租金，雇請\n      店員、發薪水實際經營事項均由被告丁○○負責，車子賣\n      掉之後，他會將本金及買車的錢還我並且會另外分給我四\n      成的利潤。被告買12台車的時間前後總共1個多月。懷特\n      公司有成立，我也有看過3台車，被告也有表示那是用我\n      的錢去買的。被告總共給我12台車的行照、鑰匙、汽車燃\n      料繳納通知書等，支票金額代表丁○○購車的錢，也同時\n      代表我所交付給丁○○之現金金額，交付現金的金額就與\n      支票的總額一樣，車子賣掉的錢，扣除先還我買車的錢，\n      剩下的我再分四成其中這四成還包括利息在內，利息我們\n      約定自我交付金錢那天開始算起，直到車子賣出，中間這\n      段期間以1分或1分半計算利息。五百多萬到底是買了多少\n      台車，詳細的數字我不確定，應該是12台，簽發支票的日\n      期與交付現金的日期應該是同一天，沒有一張支票兌現過\n      等語。\n    原審：「有利潤的分配，按照四六比例分配，他分六成，\n      我分四成。投資金額就是買車的價款，也就是支票的面額\n      。我提供給警察三輛車子的汽車燃料稅使用收據，那輛車\n      是由他買，然後留給我開，最後他也是把車子牽回去，汽\n      車燃料稅收據因為沒有一起放在袋子裡面，所以有留下來\n      ，那是跟車籍資料一起的。一開始設立懷特汽車中古買賣\n      到他要去租店鋪，這些錢都是我先支付的，租店鋪的錢是\n      我支付的。我投資的金額之前有兌現幾台，他有賣掉成交\n      應該有三、四台，借錢的部份是先扣除利息沒錯，可是投\n      資的部份沒有利息，投資的部份是賣之後才結算利息。（\n      問:你給付的金額就是他要買中古車的車款嗎？金額是一\n      致的嗎？）不一定是這金額，但他都會算整數拿錢。（問\n      ：總共估12輛車，開12張支票，這12張支票都是你投資買\n      車的錢？）對，12張都沒有兌現。（問：警卷中的第16頁\n      這張有無兌現？）這張應該不是車款。（問：所以他要你\n      估的車子是11台還是12台，開的票據是11張還是12張？）\n      應該是11台車，11張票。有3張有賣出去，不包括在這11\n      張裡面。（問：你方才說有賣出三台車，這三台車的獲利\n      ，除方才說的六、四比的分配之外，還有無算你出資買車\n      時的利息嗎？）有。他都算在我的40％中，我先出資買出\n      ，在賣掉之後給四成就是包括利息在裡面，就紅利沒利息\n      」；「我投資他買車子的數量是11台，所以被告也開了11\n      張支票給我，後來被牽走的那一台車，是我跟被告借的，\n      不是投資的車子。被告把我們投資的車輛拿來借給我使用\n      ，前後有3輛。最後被牽走的那一台，也是投資的車輛。\n      是一台一台車分別投資，被告進車之後，會放在府前路的\n      懷特公司，然後我會過去看車，我看了之後才決定要不要\n      投資，要投資才會給被告錢，被告才會把車籍資料交給我\n      ，且開立支票給我，支票的金額有時候就是車子買進的價\n      錢，有時候是加上前一台車賣出去的紅利，被告賣車之後\n      ，我才可以去兌領支票，差價的部分，再按我四他六的比\n      例分紅。（問：如果車子沒有賣出去的話怎麼辦？）沒有\n      談到這些，可是如果票到期，車子還沒有賣出去，可以再\n      換票。（問：你說之前有賣出3台，加上沒有賣出去的11\n      台，是否總共進14台車？）應該是。紅利是一台車一台車\n      算，分紅的錢，被告他會另外開票給我。我去店的時候都\n      會看到有車子擺在裡面，我有看過鈴木、裕隆及賓士的車\n      。他本來是有跟我說要買中古車，可是被告到後來有買權\n      利車，可是我覺得都可以接受。店裡面有擺車，所以可以\n      看得出來是在賣車的。賣出的三台車另外再開票的金額，\n      其中1台金額大概是是8萬元，另外兩台金額不一樣，我不\n      記得了」等語。\n    依上所述，告訴人甲○○前後所為不利於被告二人之指訴\n      ，就(1)分紅比例、(2)投資金額、(3)投資車輛之數量、(4)懷\n      特公司有無經營賣車業務、(5)投資後是否曾經分紅、(6)紅\n      利之外有無另計利息、(7)交付投資金額之日期是否即支票\n      之發票日、(8)投資之金額是否即支票面額、(9)為擔保投資\n      金額之支票曾否兌現以及(10)被牽走的的車輛究否為投資之\n      車輛等諸多情節之證述，均反覆不一多所歧異，且此等事\n      涉其所指訴被告如何施詐之過程，要非屬細節之些微不同\n      ，顯係重大瑕疵，自難憑信。\n  (二)告訴人甲○○所為指訴核與下列證據及經驗法則不相符合：\n    告訴人甲○○迭於警詢及偵審中指稱：我與被告等人投資\n      買賣汽車期間，被告有交付有幾輛車的行車執照和備份車\n      鑰匙，在被告丁○○消失的前二天，丁○○告訴我那些車\n      籍資料（包括行車執照和車鑰匙）需要再影印做建檔，所\n      以我就把行車執照和車鑰匙拿給被告丁○○指派前來之丙\n      ○○，當天我還打電話問他說可不可以拿回那些證件，丁\n      ○○推說影印機壞掉了，無法影印，結果隔天再聯絡他就\n      聯絡不上了等語。依其所述，上述「數輛汽車之行車執照\n      及備份鑰匙」，應係被告等交付告訴人以供擔保或取信於\n      告訴人之用。此事攸關數百萬元投資金額之去向或擔保，\n      依社會常情，債權人均會慎重保存或詳加記錄，若被告方\n      面需要記錄車籍，亦僅請告訴人抄錄告知或提供執照影本\n      即可，勿須交付執照原件並進而交付鑰匙。況告訴人甲○\n      ○陳稱其係扶輪社會員，而「扶輪社開放各行業及擁有各\n      項專業的人士加入，但從事某些特定職業的人會被限制不\n      得加入；通常並沒有年紀及經濟能力的限制，只要通過現\n      有社員們的同意即可加入。不過實際上參加扶輪社的社友\n      仍是以中年和富裕的人為主，這往往是因為年紀較長且經\n      濟狀況較佳的人才有較多的時間及心力參予扶輪社活動」\n      ，有維基百科全書網路查詢資料列印本在卷可按，由此可\n      知扶輪社之社友通常具有相當之社會經驗與能力。故告訴\n      人陳稱其僅被告丁○○所稱「需要影印建檔」，即將執照\n      原本連同鑰匙一併交付被告委派前來之人，且未記錄該等\n      車輛之型號或車號，殊與社會常情有違，而難採信。\n    告訴人請求傳訊之證人丙○○（即告訴人陳稱被告委託前\n      來拿取行車執照及鑰匙之人）則於本院審理時，到庭證述\n      ：伊前係因告訴人甲○○透過朋友之要求，而曾前往懷特\n      公司工作一個星期，當時伊有見到中古車，據伊所知，告\n      訴人是被告丁○○之金主，亦即借錢給被告丁○○之人，\n      且有固定之利息，當時告訴人要求伊前往懷特公司應該有\n      監督丁○○的意思。又被告丁○○不曾要求伊向告訴人拿\n      汽車之鑰匙與資料等語。是告訴人甲○○指稱：(1)其係投\n      資被告丁○○而非借貸款項及(2)被告丁○○曾經派遣丙○\n      ○以建檔為由拿回投資汽車之行車執照及鑰匙等情，即與\n      其所舉證人丙○○所述不相符合。\n    證人傅俊超雖於偵查中證述其曾聽聞被告二人邀請告訴人\n      入股參與汽車買賣事宜，然而該證人於偵查中所證之投資\n      時間為「94年初」，核與告訴人所述受詐時間為94年10月\n      之後明顯不符。而該證人復於原審證稱：「丁○○跟甲○\n      ○說要做投資中古車，大致的情形是說請甲○○做金主，\n      被告丁○○去主持公司，後來應該車子都有買進來，永華\n      路上的懷特先生公司裡都有車子....丁○○與甲○○一起\n      做車行，就看金主的意願，他（指甲○○）覺得這車子有\n      利益，就金主出錢，沒有利益的話，金主就借錢給被告丁\n      ○○。一台車金額應該都是上百萬，因為都是好車。被告\n      與告訴人間之情形實際上較不瞭解，被告丁○○後來有欠\n      甲○○錢....（問：投資跟借款你區分的出來嗎？）在雙\n      方交易的範圍之下，在交易之前去認定說這筆是借你，還\n      是你來投資，這很模糊，內部交易情形如何，我們不會很\n      清楚。像甲○○和被告丁○○這些事，可能就是案件對案\n      件，每個人眼光不一樣，也許丁○○覺得這車賣的出去，\n      但甲○○說這車子我不要，但被告丁○○堅持要買，這就\n      等於說向甲○○借錢買車，也許一台車，甲○○願意，被\n      告丁○○也願意，甲○○說我出錢，我們賺的一人分一半\n      ，那就是共資。（問：你的意思是說，被告丁○○邀甲○\n      ○有些借款，有些是投資？）是。（問：所謂的投資是指\n      他們二人由甲○○出資去買車，被告丁○○出人力去賣車\n      ？一起分享利潤）對。丁○○有在賣車，他也是跟我說他\n      在賣車，我確定他有在經營懷特中古車買賣。每個案件情\n      形不一定，譬如說10輛車，金主又不一定每台車都看的上\n      ，也許這台你喜歡，金主不一定喜歡。也許我們覺得這台\n      車好賣，但甲○○並不覺得好賣，要看他們每台車談的情\n      形如何。（問：以你當時在場的理解，是跟他借錢還是要\n      他一起投資？）先投資，我說是依每個案件的情況而定。\n      （問：你的意思是說，有可能這台車是用借錢的，另一台\n      車是用投資的嗎？）對，我就是記得四、六比例分配，應\n      該是投資。我有問過他店裡賓士車的價錢，確實是要賣的\n      沒錯」等語。核與告訴人堅稱其交付被告財物之原因係「\n      單純投資」乙節，亦不相同。\n    證人葉展嘉亦於原審證述：「被告丁○○和甲○○有私人\n      借貸關係，應該是他們私下有在互相週轉錢，有的情形我\n      不清楚，他們如何算利息我不清楚，他的錢怎麼處理的我\n      就不清楚，現金和票一定會有差，會加入利息。他們的往\n      來差不多從94年3月開始到12月....（問：懷特公司有從\n      事中古車買賣？）不算是中古車買賣，是權利車買賣。（\n      問：你方才說你有看到被告丁○○想甲○○周轉錢，你看\n      到週轉的意思是？）單純的借錢。（問：有無聽過他們討\n      論一起合夥投資買賣中古車的事情？）這我哪有可能聽到\n      ，我只是在那工作。（問：甲○○有無出錢給被告丁○○\n      作中古車的買賣？）我方才有說，幾乎都是權利車買賣較\n      多，借錢給被告丁○○，甲○○知道他的錢給被告丁○○\n      是去買權利車，車子是有進有出，甲○○也會借車去開。\n      （問：甲○○和你們去當舖挑車是先出錢再挑車，還是先\n      挑車再出錢？）是拿車回來再借」等語，亦證述被告丁○\n      ○與告訴人之間係付息借貸，而非告訴人所稱之投資合作\n      。\n    系爭懷特公司係於92年12月24日核准設立，有臺南市政府\n      營利事業登記證及經濟部公司登記資料影本及營利事業登\n      記資料查詢列印單在卷可按，故告訴人指稱該公司乃被告\n      於94年底為了從事中古車買賣而設立懷特公司云云，亦非\n      實情。\n  (三)被告確曾經於懷特公司從事其與告訴人甲○○所稱之「中古\n    車或權利車買賣」：\n    證人黃雅萍雖於偵查中證稱:「我進入懷特公司任職在92\n      年底，一直做到約94年初，我擺貨時沒有看過二手車，我\n      沒有做之後經過懷特公司有一台汽車停在店面，我沒有聽\n      過甲○○」等語，公訴人似欲藉此證明「被告謊稱開設中\n      古車行」之起訴事實。然而告訴人指訴遭被告以「偽稱開\n      設中古車行施詐」之時間為94年10月間，已如前述，該等\n      時間證人黃雅萍業已離職，自難依該證人之證詞，據為不\n      利於被告之認定。\n    證人丙○○及傅俊超均證稱被告丁○○確有以懷特公司經\n      營中古車買賣事宜，證人葉展嘉則證述被告丁○○曾在懷\n      特公司內經營權利車買賣，俱如前述。核與告訴人於原審\n      所證：「（懷特公司）租店鋪的錢是我支付的。我投資的\n      金額之前有兌現幾台，他有賣掉成交應該有三、四台....\n      」等語相符。足徵被告丁○○的確曾在懷特公司內經營中\n      古車或權利車買賣無訛。\n  (四)檢察官論告意旨及告訴人補充告訴意旨另認：(1)依陽信商業\n    銀行健康分行提供之懷特公司帳戶資料顯示，該公司於告訴\n    人受詐期間之94年全年並無資金往來資料，顯見懷特公司於\n    上述時間並無實際經營，而為一空頭公司。(2)依被告等提出\n    被告丁○○經營之懷特公司銷項發票所示，該公司有與被告\n    乙○○掛名為負責人之群邵及同旗公司互開發票方式進行假\n    交易，足認被告二人有利用未實際經營之懷特公司向外詐財\n    之事實。(3)縱認為被告二人所為「借貸關係」之辯解為真，\n    被告丁○○供稱其於94年週轉不靈，亦足認為被告等於借款\n    之時，財力已甚窘迫，被告等仍向告訴人為高額借款，亦足\n    認為有詐欺情事等語。惟查：\n  本件檢察官起訴被告之事實為「於94年10月間，向告訴人甲\n    ○○謊稱欲邀其共同開設中古車行，嗣後丁○○設立懷特公\n    司，並再遊說甲○○投資並開立支票作為擔保，使告訴人甲\n    ○○受詐而參與投資559萬元」，而非「藉未實際經營之懷\n    特公司以虛偽交易方式向他人詐欺財物」。故本案法院審查\n    之重點，厥為「被告二人有無向告訴人詐欺取財」、「被告\n    二人有無偽以懷特公司經營中古車或權利車買賣之事詐騙告\n    訴人」，至於懷特公司於設立經營期間，有無實際經營、有\n    無經營核准以外之事項、是否誠實開立統一發票、有無藉被\n    告掌控之各公司間對開發票而虛偽交易等事實，除非被告被\n    訴之犯罪已經嚴格證明而生起訴範圍擴張之效果，否則均非\n    本院所得實質審理之範圍。依上說明，本件雖有事證足認被\n    告存有藉懷特、群邵及同旗公司互開發票進行虛偽交易之高\n    度可能，尚無從憑此遽認被告二人有以懷特公司向告訴人施\n    詐之行為。\n  證人丙○○、傅俊超及葉展嘉均證稱被告丁○○確有以懷特\n    公司經營中古車或權利車買賣事宜，告訴人復於原審所證：\n    伊有支付懷特汽車租店鋪之費用，且被告過往的確有完成三\n    、四台汽車之交易等語，均如前述，自足認為被告丁○○確\n    曾以其經營之懷特公司經營中古車或權利車之買賣，而無從\n    認為被告等人曾以虛設之懷特公司作為向告訴人詐欺取財之\n    手段。至於懷特公司是否獲准經營中古車買賣、有無如實開\n    立發票誠實納稅、買賣所用之資金是否均存放於該公司申用\n    之陽信商業銀行健康分行帳戶，因非屬本案起訴之犯罪事實\n    ，自非本院所應審查之重點。\n  衡諸經驗法則，若非財務已陷窘迫，而無法以自己之財力支\n    應生活或事業所需，斷無支付利息向外舉債應急之必要，故\n    單純之「週轉不靈」或「財務情況窘迫」而向外借款，不能\n    遽而認定係詐欺之行為，必須證明行為人「於借款之初即存\n    不法所有之意圖而施用詐術」。本件依告訴人所陳「被告過\n    往的確有完成三、四台汽車之交易」，即足證明被告丁○○\n    的確曾以向告訴人借得之款項經營中古車或權利車買賣，參\n    以證人傅俊超證述被告丁○○無法繼續經營之原因為「後來\n    因為大環境的問題，汽車貸款、卡債的問題，不好成交，所\n    以沒有繼續做下去」；證人葉展嘉說明被告丁○○經商失敗\n    之原因為「懷特公司是因為台中那有一家塑膠工廠有在被告\n    丁○○這借錢，他被吵好幾天，受不了就去向地下錢莊借錢\n    ，借到受不了就倒閉，就呆帳拿不回」等語，顯見被告丁○\n    ○並非故意於財務窘迫之際基於不法所有之意圖而向告訴人\n    大量舉債之後避不見面，足認為被告丁○○並非出於詐欺之\n    目的而借款。\n八、綜合上情，本件被告二人就向告訴人借款之後，如何使用借\n    得之款項以及其所答辯之中古車買賣事宜，雖於偵審中多有\n    避重就輕、語焉不詳之情形，然依最高法院30年上字第482\n    號判例所闡示「積極證據不足證明犯罪事實時，被告之抗辯\n    或反證縱屬虛偽，仍不能以此資為積極證據應予採信之理由\n    」意旨，仍須有充份之積極證據，始足為不利於被告之認定\n    。本件告訴人所述各節非但存有一再反覆之顯著暇疵，復與\n    前述各項事證顯現之事實及經驗法則不相符合，自難憑信。\n    而被告二人所持「借款經營車輛買賣」之辯解，則經證人丙\n    ○○、傅俊超及葉展嘉分別證述屬實，自無從認為被告二人\n    有向告訴人施詐情事。且證人傅俊超及葉展嘉均說明被告丁\n    ○○經商係因景氣不佳及其他廠商之拖累而無以為繼，益徵\n    被告等並非惡意向告訴人舉債避不見面而詐取財物。此外復\n    查無「被告向告訴人詐財」之積極證據，應認為被告二人之\n    犯罪不能證明，揆諸首揭關於證據法則之說明，自應為其等\n    無罪判決之諭知。原審依調查證據之所得，認為不足以證明\n    被告二人有基於不法所有之意圖施用詐術使告訴人陷於錯誤\n    之事實，而為被告二人無罪判決之諭知，核無不合。檢察官\n    循告訴人聲請之上訴意旨徒以被告供述前後不一、且告訴人\n    之指訴僅有些許出入及被告於停業之前以詐術將汽車之行車\n    執照及鑰匙取回等節為由，而認原判決認事用法存有違誤據\n    以提起上訴，依前述說明，為無理由，應予駁回。\n據上論結，應依刑事訴訟法第368條，判決如主文。\n本案經檢察官蘇南桓到庭執行職務。"
  },
  "characters": {
    "judges": [
      "葉居正",
      "陳春長",
      "陳欽賢"
    ],
    "prosecutors": [
      "蘇南桓"
    ],
    "lawyers": [
      "江大寧"
    ],
    "clerks": [
      "李良倩"
    ],
    "plaintiffs": [

    ],
    "defendants": [
      "丁○○",
      "乙○○"
    ],
    "prosecutor_office": [

    ],
    "creditors": [

    ],
    "debtors": [

    ],
    "judicial_associate_officer": [

    ]
  },
  "adjudged_at": "2010-01-05",
  "created_at": "2016-01-05 15:08:26",
  "updated_at": "2016-01-05 15:08:26"
}