{
  "identify": "TNH-99-上易-189-20100512-1",
  "court": {
    "name": "臺灣高等法院",
    "code": "TNH"
  },
  "division": {
    "name": "刑事",
    "code": "M"
  },
  "year": 99,
  "word": "上易",
  "number": "189",
  "jcheck": "1",
  "reason": "詐欺",
  "content": "臺灣高等法院臺南分院刑事判決      99年度上易字第189號\n上  訴  人  臺灣雲林地方法院檢察署檢察官\n被      告  甲○○\n選任辯護人  李進勇律師\n上列上訴人因詐欺案件，不服臺灣雲林地方法院九十八年度易字\n第三０四號中華民國九十九年二月四日第一審判決（起訴案號：\n臺灣雲林地方法院檢察署九十七年度偵字第五七二三號），提起\n上訴，本院判決如下：\n    主  文\n上訴駁回。\n    理  由\n一、公訴意旨略以：被告甲○○明知依一般社會生活之通常經驗\n    ，可預見提供金融帳戶予他人使用，可能幫助他人犯罪，且\n    詐騙集團經常施用詐術使被詐騙人將款項匯入其指定之人頭\n    帳戶，以掩飾其犯行，並藉此逃避檢警人員之追緝。詎被告\n    不惜發生上述結果，而基於幫助他人易於實現詐欺取財犯罪\n    之不確定故意，於民國九十五年六月間某日，在雲林縣某處\n    ，向不知情之大學同學陳楚寒商借其設於臺北富邦商業銀行\n    股份有限公司鳳山分公司（下稱富邦銀行鳳山分行）申辦之\n    帳號000000000000號電子帳戶（下稱本案電子\n    帳戶）及密碼，提供予不詳姓名年籍之成年女子，容任該名\n    女子使用。嗣該女子取得上開電子帳戶及密碼資料後，基於\n    意圖為自己不法所有之犯意，於九十五年六月三十日二十一\n    時許，透過ＳＫＹＰＥ網站聊天，謊稱：欲販售情趣用品按\n    摩棒，價格新臺幣（下同）一千元云云，致乙○○陷於錯誤\n    ，而於九十五年七月一日凌晨一時四十八分許，至設於臺北\n    市○○路與和平東路口之富邦商業銀行自動提款機匯款一千\n    元入本案帳戶內，嗣乙○○匯款完畢後始發覺受騙。因認被\n    告涉犯刑法第三十條第一項前段、第三百三十九條第三項、\n    第一項之幫助詐欺取財未遂罪嫌等語。\n二、按犯罪事實應依證據認定之，無證據不得認定犯罪事實；不\n    能證明被告犯罪者，應諭知無罪之判決，刑事訴訟法第一百\n    五十四條第二項、第三百零一條第一項分別定有明文。又認\n    定不利於被告之事實，須依積極證據，苟積極證據不足為不\n    利於被告事實之認定時，即應為有利於被告之認定，更不必\n    有何有利之證據（最高法院三十年度上字第八一六號判例意\n    旨參照）。再按事實之認定應憑證據，如未能發現相當證據\n    ，或證據不足以證明，自不能以推測或擬制之方法，為裁判\n    基礎（最高法院四十年臺上字第八六號判例意旨參照）。復\n    按認定犯罪事實所憑之證據，雖不以直接證據為限，間接證\n    據亦包括在內；然而無論直接或間接證據，其為訴訟上之證\n    明，須於通常一般之人均不致有所懷疑，而得確信其為真實\n    之程度者，始得據為有罪之認定，倘其證明尚未達到此一程\n    度，而有合理之懷疑存在，無從使事實審法院得有罪之確信\n    時，即應由法院諭知被告無罪之判決（最高法院七十六年臺\n    上字第四九八六號判例意旨參照）。\n三、關於證據能力之認定：\n（一）刑事訴訟法第一百五十八條之三規定：「證人、鑑定人依\n      法應具結而未具結者，其證言或鑑定意見，不得作為證據\n      。」其立法理由乃在擔保該證言或鑑定意見，係據實陳述\n      或公正誠實之可信性，故未依法具結者，依證據絕對排除\n      法則，當然無證據能力，而不得作為證據，自不得因當事\n      人於審判程序之同意，逕認該未經具結之證言或鑑定意見\n      ，亦得作為證據（最高法院九十七年度臺上字第四０九六\n      號判決意旨參照）。查陳楚寒於九十七年十二月三日日以\n      關係人身分在檢察官偵訊時所為之供述筆錄（見偵卷第九\n      至十頁），其中供述其將電子帳戶交給被告使用，而被告\n      又交給他人使用等情，對被告而言，屬證人之證述，但未\n      依法具結以擔保其憑信性，縱令被告於原審審理中同意作\n      為證據使用，依前揭說明，仍無證據能力。\n（二）被告以外之人於審判外之陳述，雖不符刑事訴訟法第一百\n      五十九條之一至第一百五十九條之四之規定，而經當事人\n      於審判程序同意作為證據，法院審酌該言詞陳述或書面陳\n      述作成時之情況，認為適當者，亦得為證據，刑事訴訟法\n      第一百五十九條之五第一項定有明文。經查，本件被告及\n      其辯護人對於下述供述及非供述證據（此部分不含上開陳\n      楚寒九十七年十二月三日之供述筆錄），均同意作為證據\n      ，本院審酌該等證據之取得過程並無瑕疵，與本案待證事\n      實間復具有相當之關聯性，以之為本案證據並無不當，自\n      得採為本件認定事實之基礎，合先敘明。\n四、公訴人認被告涉有前開罪嫌，無非係以被告之供述、被害人\n    乙○○於警詢之陳述、證人陳楚寒之證述、富邦銀行自動付\n    款機交易明細表一份、富邦銀行鳳山分行各類存款歷史對帳\n    單一份、富邦銀行鳳山分行九十七年十二月十六日（九七）\n    北富銀鳳字第二九六號函附之臺北富邦銀行高雄分行帳號0\n    00000000000號帳戶基本資料一份、被告褒忠郵\n    局帳戶客戶歷史交易清單及中華郵政股份有限公司金融卡申\n    請書各一份為據，訊據被告固坦承：陳楚寒於九十五年六\n    月十六日向富邦銀行鳳山分行申辦本案電子帳戶及密碼。\n    其於九十五年六月間某日，向陳楚寒商借使用本案電子帳戶\n    及密碼，並將上開電子帳戶及密碼提供予不詳姓名年籍之成\n    年女子。乙○○因受詐騙於九十五年七月一日匯款一千元\n    入本案電子帳戶；但上開帳戶因故受凍結而無法提領，且上\n    開款項已於九十五年七月二十六日返還乙○○。其與陳楚\n    寒因懷疑上開電子帳戶遭詐騙集團使用而於九十五年六月三\n    十日曾至高雄縣警察局仁武分局大社分駐所備案，當時不知\n    何故未製作筆錄也沒有製作報案三聯單，但事後警局函覆係\n    因資料不齊全所以沒有製作筆錄及三聯單，遲至九十五年八\n    月九日始至該分駐所製作筆錄等事實為真正（見原審卷第七\n    十三頁）；惟堅決否認有何幫助詐欺取財之犯行，辯稱：伊\n    因前遭詐騙近十六萬元，對方表示請其提供帳戶以利匯還上\n    開款項，才將電子帳戶及密碼告知對方，主觀上並無幫助詐\n    欺取財之未必故意等語。經查：\n（一）被告於九十五年六月間某日，向陳楚寒商借使用本案電子\n      帳戶及密碼，並將上開電子帳戶及密碼提供予不詳姓名年\n      籍之成年女子，嗣被害人乙○○因受詐騙而於九十五年七\n      月一日匯款一千元入陳楚寒上開電子帳戶；但上開電子帳\n      戶因故受凍結及上開款項已於九十五年七月二十六日返還\n      乙○○等事實，業據被告供述明確，核與被害人乙○○指\n      述情節及證人陳楚寒證述內容相符（見警卷第十頁至第十\n      二頁、偵卷第四十頁至第四十一頁），復有富邦銀行自動\n      付款機交易明細表、富邦銀行鳳山分行各類存款歷史對帳\n      單、被告褒忠郵局帳戶及中華郵政股份有限公司金融卡申\n      請書等各一份附卷可參（見警卷第十三頁、第十八頁至第\n      十九頁；偵卷第十七號頁至第二十二頁、第五十二頁至第\n      五十七頁、第六十三頁至第六十四頁），足認被告此部分\n      之自白為真實。\n（二）被告名義之褒忠郵局帳號00000000000000\n      號帳戶分別於九十五年六月十二日以ＡＴＭ跨行轉出五\n      十元、九十五年六月十三日以ＡＴＭ先跨行轉出十元後\n      再轉出二萬九千九百九十元、九十五年六月十四日先以\n      ＡＴＭ跨行轉出一萬三千五百二十六元後再轉出三十三元\n      。上開款項皆轉至兆豐國際商業銀行永康分行（下稱兆豐\n      銀行永康分行）楊順雄帳號00000000000號帳\n      戶內之事實，有中華郵政股份有限公司雲林郵局九十八年\n      七月二十日雲營字第０九八五０００八四八號函文及兆豐\n      銀行永康分行九十八年十月二十六日（九八）兆康業字第\n      二二三號函文各一份在卷可佐（見原審卷第二十六頁、第\n      一百三十四頁至第一百三十五頁）。被告上開之褒忠郵局\n      帳戶，於九十五年六月十四日以語音掛失停用，同年六月\n      二十二日由被告之母親即證人黃椒華代向該郵局重新申請\n      金融卡之事實，業據證人黃椒華證述明確（見原審卷第一\n      百零九頁至第一百一十頁），復有該郵局之「中華郵政股\n      份有限公司金融卡申請書」及「客戶歷史交易清單」各一\n      份附卷可參（見偵卷第五十二頁至第五十七頁、第六十三\n      頁至第六十四頁）。準此，被告於九十五年六月十六日向\n      陳楚寒借用本案帳戶時，被告之褒忠郵局帳戶尚未重新申\n      請金融卡（申請時間九十五年六月二十二日），更未領取\n      金融卡開卡啟用（領用時間九十五年七月十日），故被告\n      未提供其褒忠郵局帳戶，而提供本案電子帳戶給該名女子\n      ，尚無可議之處。況被告提供本案電子帳戶予該名女子之\n      同時，也告訴證人黃椒華，致證人黃椒華於九十五年六月\n      二十二日以被告名義匯入四萬元，除被告當日提領之一萬\n      元外，另三萬元於翌日即被轉出之事實，亦據證人黃椒華\n      證述綦詳（見原審卷第一百一十頁至第一百十一頁），並\n      有富邦銀行鳳山分行函送之「對帳單查詢／列印」一份在\n      卷可稽（見原審卷第三十二頁）。被告如預見本案電子帳\n      戶可能遭詐欺集團不法使用，或有幫助詐欺取財之犯意，\n      斷無請母親將錢匯入該電子帳戶而被轉出之理。此與一般\n      為詐欺取財之經驗法則有違。足認被告辯稱提供本案電子\n      帳戶給該名女子之目的，係請其匯還遭騙之金額乙節，應\n      可採信。\n（三）被告於九十五年六月二十二日以後，發現黃椒華匯入本案\n      電子帳戶之四萬元，除其當日提領之一萬元外，另三萬元\n      被轉出時，始驚覺有異而告知黃椒華，經黃椒華指示而與\n      陳楚寒於九十五年六月三十日前往銀行辦理關閉帳戶，及\n      向高雄縣政府警察局仁武分局大武分駐所報案，經富邦銀\n      行鳳山分行於九十五年七月三日接獲基隆市警察局刑警大\n      隊通報列為警示帳戶，惟已於九十五年六月二十九日即先\n      做暫時禁提（僅能存入）之註記等情，業據證人陳楚寒、\n      黃椒華證述明確（見原審卷第九十六頁、第一百十一頁至\n      第一百十二頁），並有高雄縣政府警察局仁武分局九十八\n      年八月二十日高縣仁警偵字第０九八００一七七０八號函\n      文暨其後附之陳楚寒、甲○○被詐欺案報案資料卷乙宗（\n      見原審卷第三十九頁至第五十頁）及富邦銀行鳳山分行九\n      十八年十月二十三日（九八）北富銀鳳字第一一一號函文\n      一份（見原審卷第一百三十二頁）在卷可憑。又被害人乙\n      ○○匯入本案帳戶內之一千元並未遭人提領且已於九十五\n      年七月二十六日返還之事實，已於上述。由此觀之，被告\n      醒覺遭詐騙後，旋即採取前往警局報案及要求銀行關閉帳\n      戶等舉動，益徵被告應無幫助他人犯罪之故意。\n（三）按幫助犯之成立，必須行為人主觀上具有幫助之故意，客\n      觀上具有幫助之行為。詳言之，必須行為人基於幫助正犯\n      犯罪之意思，於行為前或實施中給予正犯以精神上或物質\n      上之助力，而參與犯罪構成要件以外之積極或消極行為，\n      以助成正犯犯罪之實施為要件。查被告固將陳楚寒之電子\n      帳戶及密碼提供不詳姓名之女子使用，但依公訴人所提出\n      之證據，尚無法證明被告確係基於幫助詐欺取財之故意自\n      難逕以幫助詐欺取財罪相繩。此外，檢察官復未提出其他\n      積極證據足認被告有何起訴意旨所指之幫助他人詐欺取財\n      之犯行，是檢察官之證明尚難謂已達一般人可確信其為真\n      實之程度，自屬不能證明其犯罪，揆諸前揭規定及判例意\n      旨說明，依法自應為被告無罪之諭知。\n五、原判決以被告犯罪不能證明，依刑事訴訟法第三百零一條之\n    規定，諭知被告無罪。上訴意旨略以：(一)被告所有褒忠郵局\n    帳戶於九十五年六月十四日先後跨行轉出一萬三千五百四十\n    三元及五十元入兆豐銀行永康分行楊順雄帳號。上開一萬三\n    千五百四十三元係於中國信託商業銀行ＡＴＭ轉出；五十元\n    係於褒忠郵局ＡＴＭ跨行轉出等情，有中華郵政股份有限公\n    司雲林郵局雲營字第０九八五０００斗八號函在卷可憑；被\n    告於九十五年六月十三日、十四日均在高雄未回雲林等情，\n    復據證人即被告之母黃椒華於原審證述明確。被告之褒忠郵\n    局帳戶與兆豐銀行永康分行楊順雄帳號於九十五年六月十三\n    、十四日間不斷有匯款，且上開五十元之跨行轉帳者必非被\n    告所為，而係另有他人「持被告上開褒忠郵局之金融卡」至\n    褒忠郵局ＡＴＭ跨行轉出，且該他人知悉被告上開褒忠郵局\n    金融卡之密碼。以被告當時身為大學四年級生之知識，應知\n    匯款僅需提供帳號，而無需連同金融卡、密碼均交付予他人\n    之理。足見被告供稱交付本件電子帳戶、密碼予他人，係因\n    要取回受騙之款項云云，顯不足採等語。本院查：(一)被告如\n    預見本案電子帳戶可能遭詐欺集團不法使用，或有幫助詐欺\n    取財之犯意，斷無請母親將錢匯入該電子帳戶而被轉出，致\n    自己母親受害之理；更不可能報警凍結該帳戶致詐欺集團無\n    法順利領取被害人乙○○被騙款項。此與一般提供帳戶及密\n    碼予詐欺集團藉以幫助詐欺取財之經驗法則有違。足認被告\n    辯稱提供本案電子帳戶給該名女子之目的，係請其匯還遭騙\n    之金額乙節，應可採信。(二)被告是否將其所有褒忠郵局之金\n    融卡及密碼，提供他人使用，與本件被告將向陳楚寒商借之\n    電子帳戶及密碼提供不詳姓名女子使用，並無必然之因果關\n    係。尚不得以被告將郵局之金融卡及密碼交付他人使用，據\n    此推認被告將陳楚寒之富邦銀行鳳山分行電子帳戶及密碼，\n    提供予不詳女子使用，即具有幫助詐欺取財之犯意。又本件\n    公訴意旨係追訴被告將向陳楚寒商借其設於富邦銀行鳳山分\n    行申辦之電子帳戶及密碼，提供予不詳姓名年籍之成年女子\n    ，容任該名女子使用，涉有幫助詐欺取財罪嫌。被告縱將所\n    有之褒忠郵局金融卡及密碼，提供他人使用，而有幫助詐欺\n    取財犯行，亦非本件起訴效力所及。檢察官應另行偵查、起\n    訴，而非提起本件上訴。(三)被告於刑事訴訟程序中並無自證\n    己罪之義務，亦不負終局之「說服責任」。本件依檢察官所\n    舉之證據及其指出之證明方法，尚不足使本院就被告有上開\n    幫助詐欺取財之犯行產生確信之心證，基於無罪推定原則，\n    自應為被告無罪之諭知。從而，原審以被告之犯罪不能證明\n    為由，諭知被告無罪，其認事用法核無不合。上訴意旨仍執\n    陳詞，指摘原判決不當，為無理由，應予駁回。\n六、據上論斷，應依刑事訴訟法第三百六十八條，判決如主文。\n本案經檢察官謝錫和到庭執行職務。\n中    華    民    國    99    年    5     月    12    日\n                  刑事第二庭    審判長法  官  葉居正\n                                      法  官  洪碧雀\n                                      法  官  陳春長\n以上正本證明與原本無異。\n不得上訴。\n                                      書記官  林宛妮\n中    華    民    國    99    年    5     月    12    日",
  "structure": {
    "main": "上訴駁回。",
    "reason": "一、公訴意旨略以：被告甲○○明知依一般社會生活之通常經驗\n    ，可預見提供金融帳戶予他人使用，可能幫助他人犯罪，且\n    詐騙集團經常施用詐術使被詐騙人將款項匯入其指定之人頭\n    帳戶，以掩飾其犯行，並藉此逃避檢警人員之追緝。詎被告\n    不惜發生上述結果，而基於幫助他人易於實現詐欺取財犯罪\n    之不確定故意，於民國九十五年六月間某日，在雲林縣某處\n    ，向不知情之大學同學陳楚寒商借其設於臺北富邦商業銀行\n    股份有限公司鳳山分公司（下稱富邦銀行鳳山分行）申辦之\n    帳號000000000000號電子帳戶（下稱本案電子\n    帳戶）及密碼，提供予不詳姓名年籍之成年女子，容任該名\n    女子使用。嗣該女子取得上開電子帳戶及密碼資料後，基於\n    意圖為自己不法所有之犯意，於九十五年六月三十日二十一\n    時許，透過ＳＫＹＰＥ網站聊天，謊稱：欲販售情趣用品按\n    摩棒，價格新臺幣（下同）一千元云云，致乙○○陷於錯誤\n    ，而於九十五年七月一日凌晨一時四十八分許，至設於臺北\n    市○○路與和平東路口之富邦商業銀行自動提款機匯款一千\n    元入本案帳戶內，嗣乙○○匯款完畢後始發覺受騙。因認被\n    告涉犯刑法第三十條第一項前段、第三百三十九條第三項、\n    第一項之幫助詐欺取財未遂罪嫌等語。\n二、按犯罪事實應依證據認定之，無證據不得認定犯罪事實；不\n    能證明被告犯罪者，應諭知無罪之判決，刑事訴訟法第一百\n    五十四條第二項、第三百零一條第一項分別定有明文。又認\n    定不利於被告之事實，須依積極證據，苟積極證據不足為不\n    利於被告事實之認定時，即應為有利於被告之認定，更不必\n    有何有利之證據（最高法院三十年度上字第八一六號判例意\n    旨參照）。再按事實之認定應憑證據，如未能發現相當證據\n    ，或證據不足以證明，自不能以推測或擬制之方法，為裁判\n    基礎（最高法院四十年臺上字第八六號判例意旨參照）。復\n    按認定犯罪事實所憑之證據，雖不以直接證據為限，間接證\n    據亦包括在內；然而無論直接或間接證據，其為訴訟上之證\n    明，須於通常一般之人均不致有所懷疑，而得確信其為真實\n    之程度者，始得據為有罪之認定，倘其證明尚未達到此一程\n    度，而有合理之懷疑存在，無從使事實審法院得有罪之確信\n    時，即應由法院諭知被告無罪之判決（最高法院七十六年臺\n    上字第四九八六號判例意旨參照）。\n三、關於證據能力之認定：\n（一）刑事訴訟法第一百五十八條之三規定：「證人、鑑定人依\n      法應具結而未具結者，其證言或鑑定意見，不得作為證據\n      。」其立法理由乃在擔保該證言或鑑定意見，係據實陳述\n      或公正誠實之可信性，故未依法具結者，依證據絕對排除\n      法則，當然無證據能力，而不得作為證據，自不得因當事\n      人於審判程序之同意，逕認該未經具結之證言或鑑定意見\n      ，亦得作為證據（最高法院九十七年度臺上字第四０九六\n      號判決意旨參照）。查陳楚寒於九十七年十二月三日日以\n      關係人身分在檢察官偵訊時所為之供述筆錄（見偵卷第九\n      至十頁），其中供述其將電子帳戶交給被告使用，而被告\n      又交給他人使用等情，對被告而言，屬證人之證述，但未\n      依法具結以擔保其憑信性，縱令被告於原審審理中同意作\n      為證據使用，依前揭說明，仍無證據能力。\n（二）被告以外之人於審判外之陳述，雖不符刑事訴訟法第一百\n      五十九條之一至第一百五十九條之四之規定，而經當事人\n      於審判程序同意作為證據，法院審酌該言詞陳述或書面陳\n      述作成時之情況，認為適當者，亦得為證據，刑事訴訟法\n      第一百五十九條之五第一項定有明文。經查，本件被告及\n      其辯護人對於下述供述及非供述證據（此部分不含上開陳\n      楚寒九十七年十二月三日之供述筆錄），均同意作為證據\n      ，本院審酌該等證據之取得過程並無瑕疵，與本案待證事\n      實間復具有相當之關聯性，以之為本案證據並無不當，自\n      得採為本件認定事實之基礎，合先敘明。\n四、公訴人認被告涉有前開罪嫌，無非係以被告之供述、被害人\n    乙○○於警詢之陳述、證人陳楚寒之證述、富邦銀行自動付\n    款機交易明細表一份、富邦銀行鳳山分行各類存款歷史對帳\n    單一份、富邦銀行鳳山分行九十七年十二月十六日（九七）\n    北富銀鳳字第二九六號函附之臺北富邦銀行高雄分行帳號0\n    00000000000號帳戶基本資料一份、被告褒忠郵\n    局帳戶客戶歷史交易清單及中華郵政股份有限公司金融卡申\n    請書各一份為據，訊據被告固坦承：陳楚寒於九十五年六\n    月十六日向富邦銀行鳳山分行申辦本案電子帳戶及密碼。\n    其於九十五年六月間某日，向陳楚寒商借使用本案電子帳戶\n    及密碼，並將上開電子帳戶及密碼提供予不詳姓名年籍之成\n    年女子。乙○○因受詐騙於九十五年七月一日匯款一千元\n    入本案電子帳戶；但上開帳戶因故受凍結而無法提領，且上\n    開款項已於九十五年七月二十六日返還乙○○。其與陳楚\n    寒因懷疑上開電子帳戶遭詐騙集團使用而於九十五年六月三\n    十日曾至高雄縣警察局仁武分局大社分駐所備案，當時不知\n    何故未製作筆錄也沒有製作報案三聯單，但事後警局函覆係\n    因資料不齊全所以沒有製作筆錄及三聯單，遲至九十五年八\n    月九日始至該分駐所製作筆錄等事實為真正（見原審卷第七\n    十三頁）；惟堅決否認有何幫助詐欺取財之犯行，辯稱：伊\n    因前遭詐騙近十六萬元，對方表示請其提供帳戶以利匯還上\n    開款項，才將電子帳戶及密碼告知對方，主觀上並無幫助詐\n    欺取財之未必故意等語。經查：\n（一）被告於九十五年六月間某日，向陳楚寒商借使用本案電子\n      帳戶及密碼，並將上開電子帳戶及密碼提供予不詳姓名年\n      籍之成年女子，嗣被害人乙○○因受詐騙而於九十五年七\n      月一日匯款一千元入陳楚寒上開電子帳戶；但上開電子帳\n      戶因故受凍結及上開款項已於九十五年七月二十六日返還\n      乙○○等事實，業據被告供述明確，核與被害人乙○○指\n      述情節及證人陳楚寒證述內容相符（見警卷第十頁至第十\n      二頁、偵卷第四十頁至第四十一頁），復有富邦銀行自動\n      付款機交易明細表、富邦銀行鳳山分行各類存款歷史對帳\n      單、被告褒忠郵局帳戶及中華郵政股份有限公司金融卡申\n      請書等各一份附卷可參（見警卷第十三頁、第十八頁至第\n      十九頁；偵卷第十七號頁至第二十二頁、第五十二頁至第\n      五十七頁、第六十三頁至第六十四頁），足認被告此部分\n      之自白為真實。\n（二）被告名義之褒忠郵局帳號00000000000000\n      號帳戶分別於九十五年六月十二日以ＡＴＭ跨行轉出五\n      十元、九十五年六月十三日以ＡＴＭ先跨行轉出十元後\n      再轉出二萬九千九百九十元、九十五年六月十四日先以\n      ＡＴＭ跨行轉出一萬三千五百二十六元後再轉出三十三元\n      。上開款項皆轉至兆豐國際商業銀行永康分行（下稱兆豐\n      銀行永康分行）楊順雄帳號00000000000號帳\n      戶內之事實，有中華郵政股份有限公司雲林郵局九十八年\n      七月二十日雲營字第０九八五０００八四八號函文及兆豐\n      銀行永康分行九十八年十月二十六日（九八）兆康業字第\n      二二三號函文各一份在卷可佐（見原審卷第二十六頁、第\n      一百三十四頁至第一百三十五頁）。被告上開之褒忠郵局\n      帳戶，於九十五年六月十四日以語音掛失停用，同年六月\n      二十二日由被告之母親即證人黃椒華代向該郵局重新申請\n      金融卡之事實，業據證人黃椒華證述明確（見原審卷第一\n      百零九頁至第一百一十頁），復有該郵局之「中華郵政股\n      份有限公司金融卡申請書」及「客戶歷史交易清單」各一\n      份附卷可參（見偵卷第五十二頁至第五十七頁、第六十三\n      頁至第六十四頁）。準此，被告於九十五年六月十六日向\n      陳楚寒借用本案帳戶時，被告之褒忠郵局帳戶尚未重新申\n      請金融卡（申請時間九十五年六月二十二日），更未領取\n      金融卡開卡啟用（領用時間九十五年七月十日），故被告\n      未提供其褒忠郵局帳戶，而提供本案電子帳戶給該名女子\n      ，尚無可議之處。況被告提供本案電子帳戶予該名女子之\n      同時，也告訴證人黃椒華，致證人黃椒華於九十五年六月\n      二十二日以被告名義匯入四萬元，除被告當日提領之一萬\n      元外，另三萬元於翌日即被轉出之事實，亦據證人黃椒華\n      證述綦詳（見原審卷第一百一十頁至第一百十一頁），並\n      有富邦銀行鳳山分行函送之「對帳單查詢／列印」一份在\n      卷可稽（見原審卷第三十二頁）。被告如預見本案電子帳\n      戶可能遭詐欺集團不法使用，或有幫助詐欺取財之犯意，\n      斷無請母親將錢匯入該電子帳戶而被轉出之理。此與一般\n      為詐欺取財之經驗法則有違。足認被告辯稱提供本案電子\n      帳戶給該名女子之目的，係請其匯還遭騙之金額乙節，應\n      可採信。\n（三）被告於九十五年六月二十二日以後，發現黃椒華匯入本案\n      電子帳戶之四萬元，除其當日提領之一萬元外，另三萬元\n      被轉出時，始驚覺有異而告知黃椒華，經黃椒華指示而與\n      陳楚寒於九十五年六月三十日前往銀行辦理關閉帳戶，及\n      向高雄縣政府警察局仁武分局大武分駐所報案，經富邦銀\n      行鳳山分行於九十五年七月三日接獲基隆市警察局刑警大\n      隊通報列為警示帳戶，惟已於九十五年六月二十九日即先\n      做暫時禁提（僅能存入）之註記等情，業據證人陳楚寒、\n      黃椒華證述明確（見原審卷第九十六頁、第一百十一頁至\n      第一百十二頁），並有高雄縣政府警察局仁武分局九十八\n      年八月二十日高縣仁警偵字第０九八００一七七０八號函\n      文暨其後附之陳楚寒、甲○○被詐欺案報案資料卷乙宗（\n      見原審卷第三十九頁至第五十頁）及富邦銀行鳳山分行九\n      十八年十月二十三日（九八）北富銀鳳字第一一一號函文\n      一份（見原審卷第一百三十二頁）在卷可憑。又被害人乙\n      ○○匯入本案帳戶內之一千元並未遭人提領且已於九十五\n      年七月二十六日返還之事實，已於上述。由此觀之，被告\n      醒覺遭詐騙後，旋即採取前往警局報案及要求銀行關閉帳\n      戶等舉動，益徵被告應無幫助他人犯罪之故意。\n（三）按幫助犯之成立，必須行為人主觀上具有幫助之故意，客\n      觀上具有幫助之行為。詳言之，必須行為人基於幫助正犯\n      犯罪之意思，於行為前或實施中給予正犯以精神上或物質\n      上之助力，而參與犯罪構成要件以外之積極或消極行為，\n      以助成正犯犯罪之實施為要件。查被告固將陳楚寒之電子\n      帳戶及密碼提供不詳姓名之女子使用，但依公訴人所提出\n      之證據，尚無法證明被告確係基於幫助詐欺取財之故意自\n      難逕以幫助詐欺取財罪相繩。此外，檢察官復未提出其他\n      積極證據足認被告有何起訴意旨所指之幫助他人詐欺取財\n      之犯行，是檢察官之證明尚難謂已達一般人可確信其為真\n      實之程度，自屬不能證明其犯罪，揆諸前揭規定及判例意\n      旨說明，依法自應為被告無罪之諭知。\n五、原判決以被告犯罪不能證明，依刑事訴訟法第三百零一條之\n    規定，諭知被告無罪。上訴意旨略以：(一)被告所有褒忠郵局\n    帳戶於九十五年六月十四日先後跨行轉出一萬三千五百四十\n    三元及五十元入兆豐銀行永康分行楊順雄帳號。上開一萬三\n    千五百四十三元係於中國信託商業銀行ＡＴＭ轉出；五十元\n    係於褒忠郵局ＡＴＭ跨行轉出等情，有中華郵政股份有限公\n    司雲林郵局雲營字第０九八五０００斗八號函在卷可憑；被\n    告於九十五年六月十三日、十四日均在高雄未回雲林等情，\n    復據證人即被告之母黃椒華於原審證述明確。被告之褒忠郵\n    局帳戶與兆豐銀行永康分行楊順雄帳號於九十五年六月十三\n    、十四日間不斷有匯款，且上開五十元之跨行轉帳者必非被\n    告所為，而係另有他人「持被告上開褒忠郵局之金融卡」至\n    褒忠郵局ＡＴＭ跨行轉出，且該他人知悉被告上開褒忠郵局\n    金融卡之密碼。以被告當時身為大學四年級生之知識，應知\n    匯款僅需提供帳號，而無需連同金融卡、密碼均交付予他人\n    之理。足見被告供稱交付本件電子帳戶、密碼予他人，係因\n    要取回受騙之款項云云，顯不足採等語。本院查：(一)被告如\n    預見本案電子帳戶可能遭詐欺集團不法使用，或有幫助詐欺\n    取財之犯意，斷無請母親將錢匯入該電子帳戶而被轉出，致\n    自己母親受害之理；更不可能報警凍結該帳戶致詐欺集團無\n    法順利領取被害人乙○○被騙款項。此與一般提供帳戶及密\n    碼予詐欺集團藉以幫助詐欺取財之經驗法則有違。足認被告\n    辯稱提供本案電子帳戶給該名女子之目的，係請其匯還遭騙\n    之金額乙節，應可採信。(二)被告是否將其所有褒忠郵局之金\n    融卡及密碼，提供他人使用，與本件被告將向陳楚寒商借之\n    電子帳戶及密碼提供不詳姓名女子使用，並無必然之因果關\n    係。尚不得以被告將郵局之金融卡及密碼交付他人使用，據\n    此推認被告將陳楚寒之富邦銀行鳳山分行電子帳戶及密碼，\n    提供予不詳女子使用，即具有幫助詐欺取財之犯意。又本件\n    公訴意旨係追訴被告將向陳楚寒商借其設於富邦銀行鳳山分\n    行申辦之電子帳戶及密碼，提供予不詳姓名年籍之成年女子\n    ，容任該名女子使用，涉有幫助詐欺取財罪嫌。被告縱將所\n    有之褒忠郵局金融卡及密碼，提供他人使用，而有幫助詐欺\n    取財犯行，亦非本件起訴效力所及。檢察官應另行偵查、起\n    訴，而非提起本件上訴。(三)被告於刑事訴訟程序中並無自證\n    己罪之義務，亦不負終局之「說服責任」。本件依檢察官所\n    舉之證據及其指出之證明方法，尚不足使本院就被告有上開\n    幫助詐欺取財之犯行產生確信之心證，基於無罪推定原則，\n    自應為被告無罪之諭知。從而，原審以被告之犯罪不能證明\n    為由，諭知被告無罪，其認事用法核無不合。上訴意旨仍執\n    陳詞，指摘原判決不當，為無理由，應予駁回。\n六、據上論斷，應依刑事訴訟法第三百六十八條，判決如主文。\n本案經檢察官謝錫和到庭執行職務。"
  },
  "characters": {
    "judges": [
      "葉居正",
      "洪碧雀",
      "陳春長"
    ],
    "prosecutors": [
      "謝錫和"
    ],
    "lawyers": [
      "李進勇"
    ],
    "clerks": [
      "林宛妮"
    ],
    "plaintiffs": [

    ],
    "defendants": [
      "甲○○"
    ],
    "prosecutor_office": [

    ],
    "creditors": [

    ],
    "debtors": [

    ],
    "judicial_associate_officer": [

    ]
  },
  "adjudged_at": "2010-05-12",
  "created_at": "2016-01-05 12:00:33",
  "updated_at": "2016-01-05 12:00:33"
}