{
  "identify": "TNH-98-上更(一)-37-20100105-1",
  "court": {
    "name": "臺灣高等法院",
    "code": "TNH"
  },
  "division": {
    "name": "刑事",
    "code": "M"
  },
  "year": 98,
  "word": "上更(一)",
  "number": "37",
  "jcheck": "1",
  "reason": "毒品危害防制條例",
  "content": "臺灣高等法院臺南分院刑事判決      98年度上更(一)字第37號\n上  訴  人\n即  被  告  甲○○\n選任辯護人  涂欣成律師\n            洪梅芬律師\n上列上訴人因違反毒品危害防制條例案件，不服臺灣臺南地方法\n院97年度訴字第182號中華民國97年7月24日第一審判決（起訴案\n號：臺灣臺南地方法院檢察署96年度偵字第14993號），提起上\n訴，經本院判決後由最高法院發回更審，本院判決如下：\n    主  文\n原判決關於甲○○於九十六年九月間某日販賣第二級毒品安非他\n命予黃麗真一次部分撤銷。\n甲○○無罪（甲○○被訴另販賣第二級毒品安非他命予黃麗真四\n次之部分業經前審判決確定，不在本件審理範圍之內）\n    理  由\n一、公訴意旨略以：被告甲○○基於販賣第二級毒品安非他命之\n    概括犯意，於96年9月間某日，先由黃麗真以其0000000000\n    號行動電話撥打甲○○之0000000000號行動電話約定購買安\n    非他命之事宜後，雙方依約定在嘉義市火車站前之水瓶座遊\n    藝場，由甲○○以新臺幣（下同）7000元之價格販賣第二級\n    毒品安非他予黃麗真一次。因認被告涉犯毒品危害防制條例\n    第4條第2項之販賣第二級毒品罪嫌（檢察官另起訴被告販賣\n    安非他命予黃麗真四次部分，經前審判決無罪後，未據上訴\n    而告確定，不在本件審判範圍之內）。\n二、關於證據能力之說明：\n  (一)證人黃麗真於警詢之陳述與其於原審之證述不符，且被告不\n    同意黃麗真於警詢之陳述作為證據，而檢察官又未證明黃麗\n    真於警詢中之陳述，有何「較可信之特別情況」，則依刑事\n    訴訟法第159條之2規定，黃麗真於警詢之陳述即不得作為證\n    據。\n  (二)辯護人主張檢察官所引卷附黃麗真之驗尿報告，與被告販賣\n    第二級毒品犯行無關連性，無證據能力，然查證據是否與本\n    案待證事實相關，應係證明力有無之問題，況檢察官係以驗\n    尿報告證明購毒者自己本身施用毒品有購毒之可能，與本案\n    尚非無關連性，應有證據能力。\n  (三)按證人依法應具結而未具結者，其證言或鑑定意見，不得作\n    為證據，刑事訴訟法第158條之3亦有明文。證人黃麗真於臺\n    灣臺南地方法院檢察署98年度偵字第7536號偽證案件中，以\n    被告身分所為之陳述（見本院更一卷第197至199頁），因未\n    經具結，依前揭規定，應認對於被告而言並無證據能力。\n  (四)偵查卷第37頁之監聽譯文有證據能力：\n  按刑事訴訟法第158條之4規定：「除法律另有規定外，實施\n    刑事訴訟程序之公務員因違背法定程序取得之證據，其有無\n    證據能力之認定，應審酌人權保障及公共利益之均衡維護」\n    ；故為求得人權之保障及公共利益之均衡維護，實施刑事訴\n    訟程序之公務員，因違背法定程序取得之證據，是否具證據\n    能力？於個案權衡時，法院允宜斟酌：違背法定程序之情節\n    ，違背法定程序時之主觀意圖，侵害犯罪嫌疑人或被告權益\n    之種類及輕重，犯罪所生之危險或實害，禁止使用證據對於\n    預防將來違法取得證據之效果，偵審人員如依法定程序有無\n    發現該證據之必然性，證據取得之違法對被告訴訟上防禦不\n    利益之程度等各種情形決之，俾能兼顧理論與實際而因應需\n    要。\n  經查，本件臺南地檢署96南檢瑞明監（續）字第001532號通\n    訊監察書對0000000000號手機之監聽時間為96年8月2日至96\n    年8月31日，此有該監察書附於通訊監察卷內可考，則本件\n    偵查卷第37頁之監聽譯文其監聽時間為96年9月間，是上開\n    手機之通聯期間並不在通訊監察書之通訊監察期間內，該監\n    聽譯文，應屬違背法定程序取得證據，則揆諸前述說明，該\n    監聽譯文是否有證據能力？即應依刑事訴訟法第158條之4之\n    規定就個案具體權衡之。\n  查本件臺灣臺南地方法院檢察署96南檢瑞明監（續）字第00\n    1532號通訊監察書對0000000000行動電話門號之監聽時間為\n    96年8月2日至96年8月31日，而於此期間內監聽所得之對話\n    或簡訊譯文內容已有如：「（仁哥你有嗎？）有」、「（我\n    要向你拿1個）好ㄚ」、「…有小的半，妳先過來，我朋友\n    他聽錯了，我要大半，結果他叫人拿小半來，他晚點會再拿\n    過來，妳有需要就先拿去用」「有沒有要來俊柏這裡玩，要\n    記得帶尺『即指磅秤』來喔」等語（見通訊監察卷第34、35\n    頁），由其內容可知其間之通話多用暗語且略係涉及某物品\n    之交易等情形，監聽偵查機關可據之輕易判斷有續予監聽之\n    必要，且可據之輕易取得續予監聽之核可，而偵查機關竟未\n    續予聲請核發通訊監察書，再參酌本件共計聲請9件通訊監\n    察書，對23個手機進行監聽之情形，前述偵查機關未續予聲\n    請核發通訊監察書，應係一時疏忽所致，而非故意違反法律\n    規定，足認其違法之情節尚屬非重，且無禁止使用此證據以\n    預防偵查機關將來違法取證之必要。又門號0000000000手機\n    至少於96年8月2日起即被監聽，故於96年9月間偵查機關逾\n    越監聽期間所續為之監聽，並未明顯擴大對於被告權益之侵\n    害。另證人黃麗真於原審審理時亦明確證述，此監聽譯文是\n    其與甲○○間的通訊內容（見原審卷257頁），足認此監聽\n    譯文於形式上有可信賴之情況保證，自應容許此證據提出於\n    法院使用。再者，毒品對於個人身心、社會秩序之危害，甚\n    為鉅大，加以販賣毒品之隱密性，往往使偵查此類犯罪增添\n    其困難度，如逕予排除此項證據之使用，不免因之而有害於\n    公共利益之維護。是以，應認0000000000與黃麗真持用之00\n    00000000行動電話門號間，96年9月7日至96年9月12日之對\n    話監聽譯文（見通訊監察卷37頁），應有證據能力。\n三、按犯罪事實應依證據認定之，無證據不得認定犯罪事實，刑\n    事訴訟法第154條第2項定有明文。又不能證明被告犯罪者，\n    應諭知無罪之判決，刑事訴訟法第301條第1項亦定有明文。\n    又犯販賣第二級毒品之罪，供出毒品來源因而破獲者，得減\n    輕其刑，毒品危害防制條例第十七條定有明文，則涉嫌販賣\n    第二級毒品之人，如供出毒品之來源因而破獲者，既得獲邀\n    減輕其刑之寬典，為擔保其所為陳述之真實性，自應有足以\n    令人確信其陳述為真實之補強證據，始能資為販賣或轉讓毒\n    品等犯行論罪之依據。而所謂補強證據，則指除受讓者之供\n    述外，其他足以證明該陳述之事實確具有相當程度真實性之\n    證據而言，雖所補強者，非以事實之全部為必要，但亦須因\n    補強證據與該項陳述之相互利用，足使犯罪事實獲得確信者\n    ，始足當之，最高法院98年度臺上字第6601號判決意旨足資\n    參照。準此，刑事被告經指證販賣第二級毒品安非他命，若\n    別無其他補強證據擔保前開指證之真實性，於證據之評價上\n    應認為未能使法院獲得有罪之確信。此等關於證人指訴販賣\n    情事應有補強佐證之證據上要求，並不因證人曾否為反覆不\n    同之證述而遭論處偽證罪責而有所不同，合先敘明。\n四、檢察官認為被告涉有前述96年9月間某日販賣安非他命予黃\n    麗真之犯行，無非係以：證人黃麗真之指訴、卷附00000000\n    00行動電話門號監聽譯文及證人黃麗真於96年11月2日所採\n    尿液之驗尿報告，為其論據。訊據被告甲○○堅詞否認於上\n    開時地販賣安非他命予黃麗真之事實，並以：伊未曾使用00\n    00000000門號行動電話，96年9月8日與證人黃麗真以行動電\n    話簡訊約定買賣毒品者係另有其人，伊未曾販賣安非他命予\n    黃麗真等語，資為抗辯。\n五、經查：\n  (一)證人黃麗真雖於偵查中結證稱：96年9月份，伊在嘉義市水\n    瓶座遊藝場，跟甲○○買過安非他命五次，每次都買7000元\n    、重量一錢，是用伊的電話0000000000號打甲○○的000000\n    0000號電話，都約在水瓶座遊藝場交易，她每次都有當場把\n    錢給甲○○，甲○○也有交毒品給她等語（見偵查卷91頁）\n    。然而該證人又於原審證述：伊沒有向甲○○買安非他命，\n    是因為她知道甲○○被抓了，才證述甲○○賣安非他命給她\n    等語（見原審卷第254、255頁），故該證人就曾否向被告購\n    買安非他命，於偵查及審判程序曾為完全相反之供述。\n  (二)卷附監聽譯文雖可呈現證人黃麗真於96年9月8日下午及夜間\n    以其持用之0000000000行動電話門號，與持用0000000000行\n    動電話門號之人互通多次顯可疑為毒品交易之簡訊（見通訊\n    監察卷第37頁），且證人黃麗真於原審審理時亦證稱：上開\n    譯文確係其與被告之通訊內容（見原審卷第257頁），然而\n    ：\n  上開0000000000號行動電話門號自94年8月23日起即由居住\n    在臺南縣歸仁德鄉○○○街62號之乙○○申請使用，迄於98\n    年4月6日始停止使用，有和信電訊股份有限公司函覆查詢資\n    料在卷可稽（見本院更一卷第151、152頁）。而被告自97年\n    12月22日因本案遭受羈押於臺南看守所迄於98年2月5日始具\n    保停止羈押，亦有被告之臺灣高等法院被告全國前案紀錄表\n    及本院釋票附卷足憑（見本院更一卷第39、49頁）。上述門\n    號於被告羈押期間之98年1月5日至同年1月24日，尚有四次\n    通話使用紀錄，復有和信電訊股份有限公司98年2月16日和\n    信（企營）字第09820200907號函及通聯紀錄存卷可參（見\n    本院更一卷第54、55頁）。故該通門號是否確實曾為被告所\n    持用，已有可疑。\n  經本院將系爭0000000000行動電話門號，分別於96年8月20\n    日上午4時54分、96年8月31日下午5時8分、96年9月1日上午\n    1時44分三次與證人黃麗真持用之0000000000行動電話門號\n    通話錄音，連同被告於本院準備程序陳述之錄音送請法務部\n    調查局鑑定聲紋，但因待鑑字數不足或監聽錄音之錄音品質\n    不佳而無法比對鑑定，有該局98年7月17日調科參字第09800\n    387250聲紋鑑定報告書在卷可按（見本院更一卷第145至147\n    頁），故亦而無從自監聽之錄音以科學方法確認係被告與證\n    人黃麗真之對話。\n  證人乙○○（即0000000000行動電話門號之申請人）於本院\n    審理時到庭證述：0000000000門號係伊所申請之預付卡門號\n    ，伊於申請後約一個星期左右，即因與朋友合資所開設機車\n    行客戶之要求而出借SIM卡，嗣後伊結束機車行生意，但出\n    借之SIM卡並未獲歸還，伊因認為該門號係預付卡即不以為\n    意，該位借用SIM卡之客戶並非被告，伊亦不認識被告等語\n    （見本院更一卷第189至190頁）。是依系爭0000000000行動\n    電話門號之申請資料循線而為調查，亦無從確認被告曾經使\n    用上開門號。\n  司法警察於96年10月9日搜索被告設於嘉義縣水上鄉○○路\n    148巷38號住處時，係查獲0000000000號行動電話（見警卷\n    第5頁、偵卷第35頁）；警方搜索時，與被告同在現場之被\n    告女友黃郁珊所供曾經使用之門號為0000000000、000000\n    0000、0000000000及0000000000號（見警卷第34頁），該名\n    證人黃郁珊則於偵查中證述被告另曾使用0000000000號行動\n    電話（見偵卷第34頁）；本案另多指證被告曾經販賣毒品之\n    證人曾聰明則於警詢中證述曾以0000000000及0000000000號\n    門號與被告聯絡毒品交易之事（見警卷第19頁），各有該等\n    被告及證人筆錄附卷可按，上述曾經提及之行動電話門號，\n    均無系爭0000000000號行動電話，\n  據此，本件僅只證人黃麗真曾經供述被告曾經使用該只0000\n    000000行動電話門號。故卷附0000000000行動電話門號之監\n    聽譯文，亦無從據以補強證人黃麗真所為不利於被告之指訴\n    甚明。\n  (三)證人黃麗真經警採尿之日期既為96年11月2日，已在被告被\n    訴販賣安非他命予該證人之時間即96年9月8日之二個月後，\n    且證人黃麗真亦證述其於96年8、9月間另曾向案外人林坤祺\n    購買安非他命施用（見偵卷第92頁），故證人黃麗真之尿液\n    經檢驗結果雖呈安非他命陽性反應之驗尿報告尚難資為本件\n    被告被訴發生於96年9月間之販賣犯行。\n  (四)綜上所述，本件僅有證人黃麗真單一且曾反覆之證詞，指證\n    被告曾經販賣安非他命以及0000000000行動電話門號係被告\n    持用之門號等事實，此外別無其他不利之事證可資佐證，揆\n    諸前揭證據法則之說明，自難率認被告有此部分之販賣事實\n    。又證人黃麗真因於本案原審中證述被告未曾販賣安非他命\n    而經分案偵查，並於該偽證案件（臺灣臺南地方法院檢察署\n    98年度偵字第7536號）偵查中自白於本案原審審理時為虛偽\n    陳述，亦無從補強同一證人先前所為之不利於被告之陳述。\n    故上開事實認定之結果，亦不因證人黃麗真是否曾遭追訴偽\n    證罪責以及在被訴偽證案件中是否自白犯罪而有所不同，附\n    此敘明。原審未詳予審酌系爭0000000000行動電話門號能否\n    證明確係被告所持用，而依證人黃麗真之片面證述認定96年\n    9月8日之該門號監聽譯文係被告與證人黃麗真交易毒品之聯\n    絡過程，並據以佐證黃麗真所為被告販賣毒品之證言，形同\n    以同一證人之甲部分供述補強該證人所為之乙部分供述，而\n    為被告有罪之判決，自有未當，被告上訴否認犯罪，為有理\n    由，應由本院將原判決就此部分撤銷，另為無罪判決之諭知\n    。\n據上論斷，應依刑事訴訟法第369條第1項前段、第364條、第301\n條第1項，判決如主文。\n本案經檢察官蘇南桓到庭執行職務。\n中    華    民    國    99    年    1     月    5     日\n                  刑事第二庭    審判長法  官  葉居正\n                                      法  官  陳春長\n                                      法  官  陳欽賢\n以上正本證明與原本無異。\n如不服本判決應於收受送達後10日內向本院提出上訴書狀，其未\n敘述上訴理由者，並得於提起上訴後10日內向本院補提理由書（\n均須按他造當事人之人數附繕本）「切勿逕送上級法院」。\n                                      書記官  李良倩\n中    華    民    國    99    年    1     月    5     日",
  "structure": {
    "main": "原判決關於甲○○於九十六年九月間某日販賣第二級毒品安非他\n命予黃麗真一次部分撤銷。\n甲○○無罪（甲○○被訴另販賣第二級毒品安非他命予黃麗真四\n次之部分業經前審判決確定，不在本件審理範圍之內）",
    "reason": "一、公訴意旨略以：被告甲○○基於販賣第二級毒品安非他命之\n    概括犯意，於96年9月間某日，先由黃麗真以其0000000000\n    號行動電話撥打甲○○之0000000000號行動電話約定購買安\n    非他命之事宜後，雙方依約定在嘉義市火車站前之水瓶座遊\n    藝場，由甲○○以新臺幣（下同）7000元之價格販賣第二級\n    毒品安非他予黃麗真一次。因認被告涉犯毒品危害防制條例\n    第4條第2項之販賣第二級毒品罪嫌（檢察官另起訴被告販賣\n    安非他命予黃麗真四次部分，經前審判決無罪後，未據上訴\n    而告確定，不在本件審判範圍之內）。\n二、關於證據能力之說明：\n  (一)證人黃麗真於警詢之陳述與其於原審之證述不符，且被告不\n    同意黃麗真於警詢之陳述作為證據，而檢察官又未證明黃麗\n    真於警詢中之陳述，有何「較可信之特別情況」，則依刑事\n    訴訟法第159條之2規定，黃麗真於警詢之陳述即不得作為證\n    據。\n  (二)辯護人主張檢察官所引卷附黃麗真之驗尿報告，與被告販賣\n    第二級毒品犯行無關連性，無證據能力，然查證據是否與本\n    案待證事實相關，應係證明力有無之問題，況檢察官係以驗\n    尿報告證明購毒者自己本身施用毒品有購毒之可能，與本案\n    尚非無關連性，應有證據能力。\n  (三)按證人依法應具結而未具結者，其證言或鑑定意見，不得作\n    為證據，刑事訴訟法第158條之3亦有明文。證人黃麗真於臺\n    灣臺南地方法院檢察署98年度偵字第7536號偽證案件中，以\n    被告身分所為之陳述（見本院更一卷第197至199頁），因未\n    經具結，依前揭規定，應認對於被告而言並無證據能力。\n  (四)偵查卷第37頁之監聽譯文有證據能力：\n  按刑事訴訟法第158條之4規定：「除法律另有規定外，實施\n    刑事訴訟程序之公務員因違背法定程序取得之證據，其有無\n    證據能力之認定，應審酌人權保障及公共利益之均衡維護」\n    ；故為求得人權之保障及公共利益之均衡維護，實施刑事訴\n    訟程序之公務員，因違背法定程序取得之證據，是否具證據\n    能力？於個案權衡時，法院允宜斟酌：違背法定程序之情節\n    ，違背法定程序時之主觀意圖，侵害犯罪嫌疑人或被告權益\n    之種類及輕重，犯罪所生之危險或實害，禁止使用證據對於\n    預防將來違法取得證據之效果，偵審人員如依法定程序有無\n    發現該證據之必然性，證據取得之違法對被告訴訟上防禦不\n    利益之程度等各種情形決之，俾能兼顧理論與實際而因應需\n    要。\n  經查，本件臺南地檢署96南檢瑞明監（續）字第001532號通\n    訊監察書對0000000000號手機之監聽時間為96年8月2日至96\n    年8月31日，此有該監察書附於通訊監察卷內可考，則本件\n    偵查卷第37頁之監聽譯文其監聽時間為96年9月間，是上開\n    手機之通聯期間並不在通訊監察書之通訊監察期間內，該監\n    聽譯文，應屬違背法定程序取得證據，則揆諸前述說明，該\n    監聽譯文是否有證據能力？即應依刑事訴訟法第158條之4之\n    規定就個案具體權衡之。\n  查本件臺灣臺南地方法院檢察署96南檢瑞明監（續）字第00\n    1532號通訊監察書對0000000000行動電話門號之監聽時間為\n    96年8月2日至96年8月31日，而於此期間內監聽所得之對話\n    或簡訊譯文內容已有如：「（仁哥你有嗎？）有」、「（我\n    要向你拿1個）好ㄚ」、「…有小的半，妳先過來，我朋友\n    他聽錯了，我要大半，結果他叫人拿小半來，他晚點會再拿\n    過來，妳有需要就先拿去用」「有沒有要來俊柏這裡玩，要\n    記得帶尺『即指磅秤』來喔」等語（見通訊監察卷第34、35\n    頁），由其內容可知其間之通話多用暗語且略係涉及某物品\n    之交易等情形，監聽偵查機關可據之輕易判斷有續予監聽之\n    必要，且可據之輕易取得續予監聽之核可，而偵查機關竟未\n    續予聲請核發通訊監察書，再參酌本件共計聲請9件通訊監\n    察書，對23個手機進行監聽之情形，前述偵查機關未續予聲\n    請核發通訊監察書，應係一時疏忽所致，而非故意違反法律\n    規定，足認其違法之情節尚屬非重，且無禁止使用此證據以\n    預防偵查機關將來違法取證之必要。又門號0000000000手機\n    至少於96年8月2日起即被監聽，故於96年9月間偵查機關逾\n    越監聽期間所續為之監聽，並未明顯擴大對於被告權益之侵\n    害。另證人黃麗真於原審審理時亦明確證述，此監聽譯文是\n    其與甲○○間的通訊內容（見原審卷257頁），足認此監聽\n    譯文於形式上有可信賴之情況保證，自應容許此證據提出於\n    法院使用。再者，毒品對於個人身心、社會秩序之危害，甚\n    為鉅大，加以販賣毒品之隱密性，往往使偵查此類犯罪增添\n    其困難度，如逕予排除此項證據之使用，不免因之而有害於\n    公共利益之維護。是以，應認0000000000與黃麗真持用之00\n    00000000行動電話門號間，96年9月7日至96年9月12日之對\n    話監聽譯文（見通訊監察卷37頁），應有證據能力。\n三、按犯罪事實應依證據認定之，無證據不得認定犯罪事實，刑\n    事訴訟法第154條第2項定有明文。又不能證明被告犯罪者，\n    應諭知無罪之判決，刑事訴訟法第301條第1項亦定有明文。\n    又犯販賣第二級毒品之罪，供出毒品來源因而破獲者，得減\n    輕其刑，毒品危害防制條例第十七條定有明文，則涉嫌販賣\n    第二級毒品之人，如供出毒品之來源因而破獲者，既得獲邀\n    減輕其刑之寬典，為擔保其所為陳述之真實性，自應有足以\n    令人確信其陳述為真實之補強證據，始能資為販賣或轉讓毒\n    品等犯行論罪之依據。而所謂補強證據，則指除受讓者之供\n    述外，其他足以證明該陳述之事實確具有相當程度真實性之\n    證據而言，雖所補強者，非以事實之全部為必要，但亦須因\n    補強證據與該項陳述之相互利用，足使犯罪事實獲得確信者\n    ，始足當之，最高法院98年度臺上字第6601號判決意旨足資\n    參照。準此，刑事被告經指證販賣第二級毒品安非他命，若\n    別無其他補強證據擔保前開指證之真實性，於證據之評價上\n    應認為未能使法院獲得有罪之確信。此等關於證人指訴販賣\n    情事應有補強佐證之證據上要求，並不因證人曾否為反覆不\n    同之證述而遭論處偽證罪責而有所不同，合先敘明。\n四、檢察官認為被告涉有前述96年9月間某日販賣安非他命予黃\n    麗真之犯行，無非係以：證人黃麗真之指訴、卷附00000000\n    00行動電話門號監聽譯文及證人黃麗真於96年11月2日所採\n    尿液之驗尿報告，為其論據。訊據被告甲○○堅詞否認於上\n    開時地販賣安非他命予黃麗真之事實，並以：伊未曾使用00\n    00000000門號行動電話，96年9月8日與證人黃麗真以行動電\n    話簡訊約定買賣毒品者係另有其人，伊未曾販賣安非他命予\n    黃麗真等語，資為抗辯。\n五、經查：\n  (一)證人黃麗真雖於偵查中結證稱：96年9月份，伊在嘉義市水\n    瓶座遊藝場，跟甲○○買過安非他命五次，每次都買7000元\n    、重量一錢，是用伊的電話0000000000號打甲○○的000000\n    0000號電話，都約在水瓶座遊藝場交易，她每次都有當場把\n    錢給甲○○，甲○○也有交毒品給她等語（見偵查卷91頁）\n    。然而該證人又於原審證述：伊沒有向甲○○買安非他命，\n    是因為她知道甲○○被抓了，才證述甲○○賣安非他命給她\n    等語（見原審卷第254、255頁），故該證人就曾否向被告購\n    買安非他命，於偵查及審判程序曾為完全相反之供述。\n  (二)卷附監聽譯文雖可呈現證人黃麗真於96年9月8日下午及夜間\n    以其持用之0000000000行動電話門號，與持用0000000000行\n    動電話門號之人互通多次顯可疑為毒品交易之簡訊（見通訊\n    監察卷第37頁），且證人黃麗真於原審審理時亦證稱：上開\n    譯文確係其與被告之通訊內容（見原審卷第257頁），然而\n    ：\n  上開0000000000號行動電話門號自94年8月23日起即由居住\n    在臺南縣歸仁德鄉○○○街62號之乙○○申請使用，迄於98\n    年4月6日始停止使用，有和信電訊股份有限公司函覆查詢資\n    料在卷可稽（見本院更一卷第151、152頁）。而被告自97年\n    12月22日因本案遭受羈押於臺南看守所迄於98年2月5日始具\n    保停止羈押，亦有被告之臺灣高等法院被告全國前案紀錄表\n    及本院釋票附卷足憑（見本院更一卷第39、49頁）。上述門\n    號於被告羈押期間之98年1月5日至同年1月24日，尚有四次\n    通話使用紀錄，復有和信電訊股份有限公司98年2月16日和\n    信（企營）字第09820200907號函及通聯紀錄存卷可參（見\n    本院更一卷第54、55頁）。故該通門號是否確實曾為被告所\n    持用，已有可疑。\n  經本院將系爭0000000000行動電話門號，分別於96年8月20\n    日上午4時54分、96年8月31日下午5時8分、96年9月1日上午\n    1時44分三次與證人黃麗真持用之0000000000行動電話門號\n    通話錄音，連同被告於本院準備程序陳述之錄音送請法務部\n    調查局鑑定聲紋，但因待鑑字數不足或監聽錄音之錄音品質\n    不佳而無法比對鑑定，有該局98年7月17日調科參字第09800\n    387250聲紋鑑定報告書在卷可按（見本院更一卷第145至147\n    頁），故亦而無從自監聽之錄音以科學方法確認係被告與證\n    人黃麗真之對話。\n  證人乙○○（即0000000000行動電話門號之申請人）於本院\n    審理時到庭證述：0000000000門號係伊所申請之預付卡門號\n    ，伊於申請後約一個星期左右，即因與朋友合資所開設機車\n    行客戶之要求而出借SIM卡，嗣後伊結束機車行生意，但出\n    借之SIM卡並未獲歸還，伊因認為該門號係預付卡即不以為\n    意，該位借用SIM卡之客戶並非被告，伊亦不認識被告等語\n    （見本院更一卷第189至190頁）。是依系爭0000000000行動\n    電話門號之申請資料循線而為調查，亦無從確認被告曾經使\n    用上開門號。\n  司法警察於96年10月9日搜索被告設於嘉義縣水上鄉○○路\n    148巷38號住處時，係查獲0000000000號行動電話（見警卷\n    第5頁、偵卷第35頁）；警方搜索時，與被告同在現場之被\n    告女友黃郁珊所供曾經使用之門號為0000000000、000000\n    0000、0000000000及0000000000號（見警卷第34頁），該名\n    證人黃郁珊則於偵查中證述被告另曾使用0000000000號行動\n    電話（見偵卷第34頁）；本案另多指證被告曾經販賣毒品之\n    證人曾聰明則於警詢中證述曾以0000000000及0000000000號\n    門號與被告聯絡毒品交易之事（見警卷第19頁），各有該等\n    被告及證人筆錄附卷可按，上述曾經提及之行動電話門號，\n    均無系爭0000000000號行動電話，\n  據此，本件僅只證人黃麗真曾經供述被告曾經使用該只0000\n    000000行動電話門號。故卷附0000000000行動電話門號之監\n    聽譯文，亦無從據以補強證人黃麗真所為不利於被告之指訴\n    甚明。\n  (三)證人黃麗真經警採尿之日期既為96年11月2日，已在被告被\n    訴販賣安非他命予該證人之時間即96年9月8日之二個月後，\n    且證人黃麗真亦證述其於96年8、9月間另曾向案外人林坤祺\n    購買安非他命施用（見偵卷第92頁），故證人黃麗真之尿液\n    經檢驗結果雖呈安非他命陽性反應之驗尿報告尚難資為本件\n    被告被訴發生於96年9月間之販賣犯行。\n  (四)綜上所述，本件僅有證人黃麗真單一且曾反覆之證詞，指證\n    被告曾經販賣安非他命以及0000000000行動電話門號係被告\n    持用之門號等事實，此外別無其他不利之事證可資佐證，揆\n    諸前揭證據法則之說明，自難率認被告有此部分之販賣事實\n    。又證人黃麗真因於本案原審中證述被告未曾販賣安非他命\n    而經分案偵查，並於該偽證案件（臺灣臺南地方法院檢察署\n    98年度偵字第7536號）偵查中自白於本案原審審理時為虛偽\n    陳述，亦無從補強同一證人先前所為之不利於被告之陳述。\n    故上開事實認定之結果，亦不因證人黃麗真是否曾遭追訴偽\n    證罪責以及在被訴偽證案件中是否自白犯罪而有所不同，附\n    此敘明。原審未詳予審酌系爭0000000000行動電話門號能否\n    證明確係被告所持用，而依證人黃麗真之片面證述認定96年\n    9月8日之該門號監聽譯文係被告與證人黃麗真交易毒品之聯\n    絡過程，並據以佐證黃麗真所為被告販賣毒品之證言，形同\n    以同一證人之甲部分供述補強該證人所為之乙部分供述，而\n    為被告有罪之判決，自有未當，被告上訴否認犯罪，為有理\n    由，應由本院將原判決就此部分撤銷，另為無罪判決之諭知\n    。\n據上論斷，應依刑事訴訟法第369條第1項前段、第364條、第301\n條第1項，判決如主文。\n本案經檢察官蘇南桓到庭執行職務。"
  },
  "characters": {
    "judges": [
      "葉居正",
      "陳春長",
      "陳欽賢"
    ],
    "prosecutors": [
      "蘇南桓"
    ],
    "lawyers": [
      "涂欣成",
      "洪梅芬"
    ],
    "clerks": [
      "李良倩"
    ],
    "plaintiffs": [

    ],
    "defendants": [
      "甲"
    ],
    "prosecutor_office": [

    ],
    "creditors": [

    ],
    "debtors": [

    ],
    "judicial_associate_officer": [

    ]
  },
  "adjudged_at": "2010-01-05",
  "created_at": "2016-01-05 15:08:30",
  "updated_at": "2016-01-05 15:08:30"
}