{
  "identify": "TNH-98-聲-976-20100104-1",
  "court": {
    "name": "臺灣高等法院",
    "code": "TNH"
  },
  "division": {
    "name": "刑事",
    "code": "M"
  },
  "year": 98,
  "word": "聲",
  "number": "976",
  "jcheck": "1",
  "reason": "聲請定其應執行刑",
  "content": "臺灣高等法院臺南分院刑事裁定           98年度聲字第976號\n聲 請 人  臺灣高等法院臺南分院檢察署檢察官\n受 刑 人  甲○○\n上列聲請人因受刑人數罪併罰有二裁判以上，聲請定其應執行刑\n（聲請案號：98年度執聲字第943號），本院裁定如下：\n    主  文\n甲○○所犯如附表所示各罪，應執行有期徒刑壹年拾壹月。\n    理  由\n一、按數罪併罰中之一罪，依刑法規定得易科罰金，若因與不得\n    易科之他罪併合處罰結果而不得易科罰金時，原可易科部分\n    所處之刑，自亦無庸為易科折算標準之記載，業經司法院院\n    字2702號、釋字第144號解釋在案 ，最高法院40年台非字第\n    12號判例、87年台非字第4號判決亦有相同意旨。\n二、受刑人甲○○因違反毒品危害防制條例等罪，經臺灣臺南地\n    方法院及本院先後判處如附表所示之刑，且均確定在案。茲\n    檢察官聲請定其應執行之刑，本院審核認聲請為正當，應定\n    其應執行之刑。又受刑人所犯除附表編號２以外之罪所處之\n    徒刑，依法均不得為易科罰金之宣告，揆諸前開院字第2702\n    號解釋意旨，於定其應執行時，即不得再為宣告易科罰金。\n三、爰依刑事訴訟法第477條第1項、刑法第53條、第51條第5款\n    ，裁定如主文。\n中    華    民    國    99    年    1     月    4     日\n                  刑事第三庭    審判長法  官    陳義仲\n                                      法  官    宋明中\n                                      法  官    蔡勝雄\n以上正本證明與原本無異。\n如不服本裁定，應於收受本裁定後五日內向本院提出抗告狀。\n                                      書記官    汪姿秀\n中    華    民    國    99    年    1     月    4     日",
  "structure": {
    "main": "甲○○所犯如附表所示各罪，應執行有期徒刑壹年拾壹月。",
    "reason": "一、按數罪併罰中之一罪，依刑法規定得易科罰金，若因與不得\n    易科之他罪併合處罰結果而不得易科罰金時，原可易科部分\n    所處之刑，自亦無庸為易科折算標準之記載，業經司法院院\n    字2702號、釋字第144號解釋在案 ，最高法院40年台非字第\n    12號判例、87年台非字第4號判決亦有相同意旨。\n二、受刑人甲○○因違反毒品危害防制條例等罪，經臺灣臺南地\n    方法院及本院先後判處如附表所示之刑，且均確定在案。茲\n    檢察官聲請定其應執行之刑，本院審核認聲請為正當，應定\n    其應執行之刑。又受刑人所犯除附表編號２以外之罪所處之\n    徒刑，依法均不得為易科罰金之宣告，揆諸前開院字第2702\n    號解釋意旨，於定其應執行時，即不得再為宣告易科罰金。\n三、爰依刑事訴訟法第477條第1項、刑法第53條、第51條第5款\n    ，裁定如主文。"
  },
  "characters": {
    "judges": [
      "陳義仲",
      "宋明中",
      "蔡勝雄"
    ],
    "prosecutors": [

    ],
    "lawyers": [

    ],
    "clerks": [
      "汪姿秀"
    ],
    "plaintiffs": [

    ],
    "defendants": [

    ],
    "prosecutor_office": [
      "臺灣高等法院臺南分院檢察署檢察官"
    ],
    "creditors": [

    ],
    "debtors": [

    ],
    "judicial_associate_officer": [

    ]
  },
  "adjudged_at": "2010-01-04",
  "created_at": "2016-01-05 14:38:01",
  "updated_at": "2016-01-05 14:38:01"
}