{
  "identify": "TPB-99-訴-727-20100512-1",
  "court": {
    "name": "臺北高等行政法院",
    "code": "TPB"
  },
  "division": {
    "name": "行政",
    "code": "A"
  },
  "year": 99,
  "word": "訴",
  "number": "727",
  "jcheck": "1",
  "reason": "教師升等",
  "content": "臺北高等行政法院裁定\n                                       99年度訴字第727號\n原      告  甲○○\n被      告  義守大學\n代  表  人  丙○○○○○○\n上列當事人間教師升等事件，原告不服教育部中華民國99年2 月\n4 日台訴字第0990005868A 號訴願決定，提起行政訴訟，本院裁\n定如下：\n   主  文\n本件移送高雄高等行政法院。\n    理  由\n一、本件原告為被告學校助理教授，申請升等為副教授，遭被告\n    否准，循序提起訴願，遞遭駁回，遂提起行政訴訟。經查被\n    告為私立學校，惟其否准原告申請教師升等，係受託行使公\n    權力之行為，具機關地位，依行政訴訟法第13條第1 項規定\n    ，應由被告所在地之高雄高等行政法院管轄，本院並無管轄\n    權，應裁定移轉管轄。\n二、依行政訴訟法第18條、民事訴訟法第28條第1 項，裁定如主\n    文。\n中    華    民    國    99    年    5     月    12    日\n             台北高等行政法院第八庭\n                        審判長法  官  蔡進田\n                              法  官  黃清光\n                              法  官  闕銘富\n上為正本係照原本作成。\n如不服本裁定，應於送達後10日內向本院提出抗告狀（須按他造\n人數附繕本）。\n中    華    民    國    99    年    5     月    12    日\n                              書記官  黃倩鈺",
  "structure": {
    "main": "本件移送高雄高等行政法院。",
    "reason": "一、本件原告為被告學校助理教授，申請升等為副教授，遭被告\n    否准，循序提起訴願，遞遭駁回，遂提起行政訴訟。經查被\n    告為私立學校，惟其否准原告申請教師升等，係受託行使公\n    權力之行為，具機關地位，依行政訴訟法第13條第1 項規定\n    ，應由被告所在地之高雄高等行政法院管轄，本院並無管轄\n    權，應裁定移轉管轄。\n二、依行政訴訟法第18條、民事訴訟法第28條第1 項，裁定如主\n    文。"
  },
  "characters": {
    "judges": [
      "蔡進田",
      "黃清光",
      "闕銘富"
    ],
    "prosecutors": [

    ],
    "lawyers": [

    ],
    "clerks": [

    ],
    "plaintiffs": [
      "甲○○"
    ],
    "defendants": [
      "義守大學",
      "代  表  人  丙○○○○○○"
    ],
    "prosecutor_office": [

    ],
    "creditors": [

    ],
    "debtors": [

    ],
    "judicial_associate_officer": [

    ]
  },
  "adjudged_at": "2010-05-12",
  "created_at": "2016-01-05 11:57:55",
  "updated_at": "2016-01-05 11:57:55"
}