{
  "identify": "TPB-98-簡-656-20100105-1",
  "court": {
    "name": "臺北高等行政法院",
    "code": "TPB"
  },
  "division": {
    "name": "行政",
    "code": "A"
  },
  "year": 98,
  "word": "簡",
  "number": "656",
  "jcheck": "1",
  "reason": "綜合所得稅",
  "content": "臺北高等行政法院裁定\n                                       98年度簡字第656號\n原      告  甲○○\n被      告  財政部臺北市國稅局\n代  表  人  乙○○（局長）\n上列當事人間綜合所得稅事件，原告不服財政部中華民國98年9\n月21日台財訴字第09800441570 號訴願決定，提起行政訴訟，本\n院裁定如下：\n    主  文\n原告之訴駁回。\n訴訟費用由原告負擔。\n    理  由\n一、按訴願之提起，應自行政處分達到或公告期滿之次日起30日\n    內為之。提起訴願逾法定期間者，應為不受理之訴願決定。\n    參照訴願法第14條第1 項、第77條第2 款之規定甚明。訴願\n    逾期即未經合法之訴願程序，進而提起撤銷訴訟，不合撤銷\n    訴訟之訴願前置要件，又不能補正，應依行政訴訟法第107\n    條第1 項第10款裁定駁回之。依同法第236 條規定，簡易程\n    序適用上開通常程序之規定。\n二、本件原告因綜合所得稅事件，不服被告處罰鍰新台幣（下同\n    ）69,935元之處分，申請複查，遭被告98年6 月29日財北國\n    稅法二字第0980215666號複查決定駁回，循序提起撤銷訴訟\n    。查複查決定書係於98年7 月3 日送達於原告，此有掛號郵\n    件送達回執附訴願卷可稽。計其提起訴願之期間，應自98年\n    7 月4 日起算。原告住居受理訴願機關所在地台北市，無須\n    扣除在途期間。原至98年8 月2 日屆滿，該日適逢星期日，\n    以次（3 ）日代之。原告遲至98年8 月5 日始具狀提起訴願\n    ，此有訴願書上所載日期可考，早已逾訴願法定不變期間，\n    訴願決定不予受理，自無不合。原告復提起撤銷訴訟，參照\n    前述規定與說明，並非合法，應予駁回。本件爭訟之罰鍰金\n    額不逾20萬元，依簡易程序終結之。附予說明。\n三、依行政訴訟法第236 條、第107 條第1 項第10款、第104 條\n    、民事訴訟法第95條、第78條，裁定如主文。\n中    華    民    國    99    年    1     月     5   日\n      台北高等行政法院第八庭\n             台北高等行政法院第八庭\n                             法  官  蔡進田\n上為正本係照原本作成。\n本件以訴訟事件所涉及之法律見解具有原則性者為限，始得於本\n裁定送達後10日內向本院提出抗告狀（須按他造人數附繕本），\n並經最高行政法院許可後方得抗告。\n中    華    民    國    99    年    1     月    5     日\n                              書記官  黃倩鈺\n",
  "structure": {
    "main": "原告之訴駁回。\n訴訟費用由原告負擔。",
    "reason": "一、按訴願之提起，應自行政處分達到或公告期滿之次日起30日\n    內為之。提起訴願逾法定期間者，應為不受理之訴願決定。\n    參照訴願法第14條第1 項、第77條第2 款之規定甚明。訴願\n    逾期即未經合法之訴願程序，進而提起撤銷訴訟，不合撤銷\n    訴訟之訴願前置要件，又不能補正，應依行政訴訟法第107\n    條第1 項第10款裁定駁回之。依同法第236 條規定，簡易程\n    序適用上開通常程序之規定。\n二、本件原告因綜合所得稅事件，不服被告處罰鍰新台幣（下同\n    ）69,935元之處分，申請複查，遭被告98年6 月29日財北國\n    稅法二字第0980215666號複查決定駁回，循序提起撤銷訴訟\n    。查複查決定書係於98年7 月3 日送達於原告，此有掛號郵\n    件送達回執附訴願卷可稽。計其提起訴願之期間，應自98年\n    7 月4 日起算。原告住居受理訴願機關所在地台北市，無須\n    扣除在途期間。原至98年8 月2 日屆滿，該日適逢星期日，\n    以次（3 ）日代之。原告遲至98年8 月5 日始具狀提起訴願\n    ，此有訴願書上所載日期可考，早已逾訴願法定不變期間，\n    訴願決定不予受理，自無不合。原告復提起撤銷訴訟，參照\n    前述規定與說明，並非合法，應予駁回。本件爭訟之罰鍰金\n    額不逾20萬元，依簡易程序終結之。附予說明。\n三、依行政訴訟法第236 條、第107 條第1 項第10款、第104 條\n    、民事訴訟法第95條、第78條，裁定如主文。"
  },
  "characters": {
    "judges": [
      "蔡進田"
    ],
    "prosecutors": [

    ],
    "lawyers": [

    ],
    "clerks": [
      "黃倩鈺"
    ],
    "plaintiffs": [
      "甲○○"
    ],
    "defendants": [
      "財政部臺北市國稅局",
      "代  表  人  乙○○（局長）"
    ],
    "prosecutor_office": [

    ],
    "creditors": [

    ],
    "debtors": [

    ],
    "judicial_associate_officer": [

    ]
  },
  "adjudged_at": "2010-01-05",
  "created_at": "2016-01-05 15:05:38",
  "updated_at": "2016-01-05 15:05:38"
}