{
  "identify": "TPB-98-訴-1115-20100512-1",
  "court": {
    "name": "臺北高等行政法院",
    "code": "TPB"
  },
  "division": {
    "name": "行政",
    "code": "A"
  },
  "year": 98,
  "word": "訴",
  "number": "1115",
  "jcheck": "1",
  "reason": "房屋稅",
  "content": "臺北高等行政法院判決\n                                      98年度訴字第1115號\n                                     99年4月21日辯論終結\n原      告  財團法人世界宗教博物館發展基金會\n代  表  人  甲○○\n訴訟代理人  李永然  律師\n            葉建偉  律師\n            陳心儀  律師\n被      告  臺北縣政府稅捐稽徵處\n代  表  人  乙○○（代理處長）.\n訴訟代理人  丙○○\n            丁○○\n            戊○○\n上列當事人間房屋稅事件，原告不服臺北縣政府中華民國98年4\n月3日北府訴決字第0970959397號（案號：第00000000號）訴願\n決定，提起行政訴訟，本院判決如下：\n    主  文\n原告之訴駁回。\n訴訟費用由原告負擔。\n    事實及理由\n一、程序事項：本件原告起訴時，被告之代表人為黃毓彥，嗣於\n    訴訟中變更為乙○○，茲據新任代表人具狀聲明承受訴訟，\n    經核無不合，應予准許。\n二、事實概要：原告所有如附表所示門牌號碼臺北縣永和市○○\n    路○段236號6樓、7樓、永和市○○路2號6樓、永和市○○路\n    22巷12號6 樓、7 樓、中和市○○路○ 段344 號5 樓、中和\n    市○○路○ 段346 號5 樓、永和市○○路2 號7 樓等8 戶房\n    屋，經被告所屬中和分處於97年間派員至現場勘查結果，因\n    認上開房屋之使用情形，或供世界宗教博物館使用，或供道\n    饗養生蔬膳餐廳等營業使用，不符免徵房屋稅事由，乃對原\n    告發單課徵上開8 戶房屋之97年度房屋稅總計為新臺幣( 下\n    同)2,532,063 元 。原告不服，申請復查未獲變更，提起訴\n    願亦經決定駁回後，原告就被告對附表編號1-7 等7 戶房屋\n     (下稱系爭房屋) 課徵房屋稅之處分仍不服，遂提起本件行\n    政訴訟。\n三、本件原告主張：\n    (一)按文建會98年1月9日文壹字第0983100593號函釋規定，如\n      屬從事文化藝術獎助條例第2 條所稱文化藝術事業者，則\n      該從事者只要經其目的事業主管機關核准設立，即得適用\n      免徵房屋稅之租稅優惠。查原告興辦之「世界宗教博物館\n      」，為依該條例第2 條及同條例施行細則第4 條規定之文\n      化藝術事業；且自開館以來，即長期與臺北縣文化局、教\n      育部或文建會等互動頻繁，並多次參與文建會推動之計劃\n      ，確為有興辦博物館之文化機構，核與上開獎助條例所稱\n      「文化藝術事業」之內涵相符。而原告亦經目的事業主管\n      機關內政部核准設立之公益性財團法人，並有法人登記證\n      書，故依上開函釋意旨，原告符合上開獎助條例第26條「\n      經文教主管機關核准設立」規定，自得免徵房屋稅甚明。\n    (二)原告為不以營利為目的之公益社團，自有房屋稅條例第15\n      條第1項第5款規定之適用：\n      1.依財政部 87年6月8日臺財稅字第871947996號函釋及財\n        政部88年5 月1 日臺財稅字第881912937 號函意旨，房\n        屋稅條例第15條第1 項第5 款所指之「公益社團」，其\n        重點應在私有房屋是否供「公益使用」，殊不因該公益\n        性團體為社團或財團本質上即有不同。被告雖援引臺灣\n        省稅務局69.1.30 稅三字第19336 號函：「…本案○○\n        高爾夫俱樂部雖屬財團法人組織，並非屬房屋稅條例所\n        稱之『公益社團』，其供辦公使用房屋應無首揭法條免\n        徵房屋稅之適用。」之內容，稱財團法人組織非屬房屋\n        稅條例所稱「公益社團」云云。惟上開函釋係指稱該案\n        之稅捐主體並不具公益性，故雖屬財團法人組織，仍無\n        上開條例第15條第1 項第5 款之適用，並未認公益性之\n        財團法人不得適用房屋稅條例，被告顯有誤解，不值採\n        信。\n      2.而自原告法人登記證書、目的事業主管機關內政部之核\n        准設立函，及內政部93年10月28日內授中民字第093000\n        8261號函覆原告：「…貴法人係經本部許可設立登記有\n        案之宗教財團法人基金會，依章程其設立目的…確為促\n        進公眾利益成立之宗教財團法人。」皆足證原告係非以\n        營利為目的，而為促進公眾利益所設立之財團法人；且\n        所從事「籌設世界宗教博物館及國內外分館」、「興辦\n        宗教與生活之教育活動」及「興辦國內外各項宗教圖書\n        與資訊服務」，亦為達成其目的所須「非以營利為目的\n        」之活動；再依原告章程第23條規定，原告解散時財產\n        歸屬法人所在地之地方自治團體所有，非歸屬私人，益\n        證原告為非以營利為目的之財團法人，殆無疑義。\n      3.查系爭房屋所有人為原告，僅原告為納稅義務人，是房\n        屋稅條例第15條第1項第5款所定之公益社團，應就原告\n        之性質認定，方符房屋稅之課徵要件。詎被告以原告附\n        設機構「財團法人世界宗教博物館發展基金會附設臺北\n        館」有設稅籍及繳納營業稅，即認定該附設機構係以營\n        利為目的，進而否定系爭房屋得免徵房屋稅云云。惟查\n        ，原告附設台北館無法人格，並無得以獨立名義對外興\n        辦博物館、推廣宗教活動及對系爭房屋使用收益之可能\n        。房屋稅條例既規定納稅義務人為原告，即應就原告之\n        性質判斷方屬正確。原告既屬非以營利為目的之公益性\n        財團法人，所從事者皆為非營利為目的之活動，應得適\n        用房屋稅條例第15條第1項第5款規定無疑。\n      4.原告雖於86年間因興辦宗教博物館，有銷售貨物或勞務\n        之營業行為，乃由附設機構為營業登記。然依營業稅法\n        第2 條及第6 條第2 項規定可知，營業人非當然以營利\n        為目的，且營業稅之納稅義務人，容許同一人因其總機\n        構與分支機構不同而分別登記( 營業稅法第28條規定參\n        照)， 原告方得以附設機構單獨登記為營業人，惟營業\n        稅法與房屋稅條例之規範迥異，房屋稅條例規定之納稅\n        義務人，僅為所有人，並無就所有人及其附設機構分別\n        認定之可能，被告恣意割裂就原告及附設機構分別認定\n        性質，進而主張系爭房屋無房屋稅條例第15條第1 項第\n        5 款規定之適用，顯有認事用法之錯誤。\n      5.再按財政部88年7月29日臺財稅字第881929562號函釋意\n        ，原告之門票收入及租金收入，係屬酌收水電費用性質\n        ，並無營利性質。查附表項次1 、2 、3 之三戶房屋係\n        供世界宗教博物館展覽區使用，項次5 供兒童館展示使\n        用，雖有門票收入，惟該項收入僅供支付系爭房屋之電\n        費支出，總計該7 戶房屋97課稅年度之電費支出為4,07\n        0,521 元與門票收入2,932,497 元相較，尚不足1,138,\n        024 元，足見原告主要經費來源均仰賴大眾捐助，足見\n        原告主要經費來源均仰賴大眾捐助，酌收門票僅係酌收\n        水電茶水費用，非以營利為目的甚明。況該三戶房屋從\n        95年10月起，已無再提供場地租借服務，遑論當初原告\n        酌收費用僅係用以支應茶水、水電等費用，總計從94年\n        7 月至95年6 月僅4 萬餘元，即使將此場地租借費用計\n        入，原告仍舊入不敷出，何來具有營利目的可言？\n      6.再者，原告之性質係為財團法人，原告所有之盈餘均係\n        供維持會務運作所使用，縱原告如有收益多於支出之情\n        況（假設語，原告否認之），日後若依法解散時，依照\n        原告章程第23條規定，賸餘財產係歸於原告事務所所在\n        地之地方自治團體，而非歸於個人或私人企業，故原告\n        附屬機構世界宗教博物館雖有門票、場地費等收入，仍\n        與以營利為目的不同，其理甚明。\n    (三)系爭房屋皆屬供原告辦公使用之房屋，符合房屋稅條例第\n      15條第1項第5款「私有房屋供自有辦公室使用」之要件：\n      1.按財政部66.8.15臺財稅字第35449號函釋，上開條例規\n        定「供辦公室使用之房屋」，包含會議室、貯藏室、講\n        習室及文物儲藏室；另財政部60.9.23臺財稅字第37570\n        號函釋亦闡明供辦公使用之房屋，其認定標準，係就該\n        社團自有房屋之用途，在供其推廣公益業務或活動，核\n        實認定為「供辦公使用」之房屋，並免徵房屋稅即明。\n      2.查附表1、2之兩戶房屋，主要供世界宗教博物館展覽使\n        用，與原告設立之宗旨相符，符合上揭60年函釋意旨；\n        另項次3 之房屋主要供該博物館特展區展覽，並兼作講\n        習室使用；兼作講習室部份，亦與上揭66年函釋意旨相\n        符，均符合「自有供辦公使用」之要件，應得免稅。又\n        前述三戶房屋有部分面積曾對外提供作會議、教學之臨\n        時性活動用途並酌收場地費，然該部分面積於平時無外\n        借時，亦為原告內部舉辦會議之會議室，依上揭66年函\n        釋意旨，符合「自有供辦公室使用」要件，端不能僅憑\n        原告曾在網頁上列出場地費之標準，即認定該房屋作為\n        經常性租借用途，不可不辨。\n      3.附表項次4 之房屋係作辦公室使用，雖被告認係原告附\n        設機構使用，惟不應割裂原告及附設機構分別認定已如\n        前述，該房屋應得免稅甚明。另項次5 之房屋於94年2\n        月起則供世界宗教博物館兒童館展示使用，該部分期間\n        供展覽使用，依上揭60年函釋意旨，亦符合自有供辦公\n        使用之要件。另附表項次6 、7 兩戶房屋係供放置展覽\n        用文物之「文物儲藏室」使用，與上揭66年函釋「與辦\n        公有關之文物儲藏室」之意旨相符，雖被告認係供原告\n        附設機構使用，惟不應割裂原告及附設機構分別認定已\n        如前述，該房屋應得免稅甚明。\n    (四)又被告所提最高行政法院99年度判字第66號判決，原告已\n      於法定期間內提起再審之訴，更擬針對該判決所適用之法\n      規提起大法官解釋，以茲救濟，故該判決見解尚非的論等\n      語。並聲明請求判決訴願決定、原處分（含復查決定）關\n      於課徵房屋稅額超過263,139部分均撤銷。\n四、被告則以：\n    (一)按房屋稅條例第15條第1項第5款規定之適用，就免徵房屋\n      稅之主體而言，財政部87.6.8臺財稅字第871947996 號函\n      雖認為該「公益社團」包括財團法人及社團法人，惟依臺\n      灣省稅務局上揭69年函釋卻指出財團法人組織，並非屬房\n      屋稅條例所稱之「公益社團」；再就免徵房屋稅客體之用\n      途而言，所謂「供辦公使用」者，依財政部60年11月9 日\n      臺財稅字第38743 號令，房屋如用為營業非屬「供辦公使\n      用；另參諸財政部88年7 月29日臺財稅字第881929562 號\n      函釋，顯見公益社團所有之房屋，原則上供自己辦公使用\n      ，兼而提供各級政府機關、學校使用或偶有提供其他團體\n      辦理臨時性之活動使用而酌收或僅收取水電費者，亦得認\n      定為「供辦公使用」，此合先敘明。\n    (二)查系爭房屋前經被告所屬中和分處於93年4 月間及97年間\n      派員至現場勘查，其使用情形或供世界宗教博物館使用，\n      或供餐廳等營業使用，均非供原告自己辦公使用或供與其\n      辦公有關之會議廳等用途使用，此會勘結果為原告所不爭\n      ，核與前揭房屋稅條例第15條第1 項第5 款規定及上開函\n      釋規定不符，自無免徵房屋稅之適用。又系爭房屋為原告\n      所興辦之博物館使用。該博物館之正確名稱係「財團法人\n      世界宗教博物館發展基金會附設臺北館」，乃原告於86年\n      間增設之附屬機構，並於89年10月間辦理營業稅設籍登記\n      迄今；系爭博物館經營博物館業務，對外收取門票，經查\n      調其96年至97年營業稅申報書資料得知，該館96年申報銷\n      項總額為24,089,125元，進貨及費用總金額申報為13,548\n      ,885元；97年申報之銷項總額截至97年4 月為7,796,976\n      元，進貨及費用總金額為1,795,392 元，足證原告經營博\n      物館業務係屬常態性營業行為，此有原告96年至97年營業\n      稅課稅資料可稽，又原告93及94年房屋稅上訴審99年度判\n      字第66號判決理由五(二)載明：「揆諸…營業稅法第1 條：\n      …之規定可知，被上訴人興辦之世界宗教博物館為加值型\n      及非加值型營業稅法之營業人，必須繳納營業稅，其非屬\n      免徵營業稅範圍，因此被上訴人興辦之世界宗教博物館所\n      使用之系爭房屋尚非屬『不以營利為目的』，即不符行為\n      時房屋稅條例第15條第1 項第5 款免徵房屋稅之法定要件\n      ，…」是以，原告以其所有系爭房屋作博物館使用，其使\n      用情形乃原告設立營業稅籍從事包括販賣門票、場地租借\n      等常態性營業行為，依上揭60年11月9 日臺財稅字第3874\n      3 號令及改制前行政法院57年判字第431 號判例意旨，顯\n      非屬「供辦公使用」自明，是原告之主張尚難採憑。\n    (三)而有關已辦妥財團法人登記或其興辦之博物館，其房屋為\n      該財團法人所有者，該財團法人得否享受免徵房屋稅之租\n      稅優惠，其所應具備之要件，文化藝術獎助條例第26條定\n      有明文；而經調閱該條文之立法紀錄可知，該條文係於逐\n      條討論時，由立法委員提議修正為：「免徵房屋稅及土地\n      稅」，經核其立法過程既有財政部代表參與，其與房屋稅\n      條例第15條第1 項規定間當無疊床架屋之情形發生，亦即\n      文化藝術獎助條例第26條制定當時，倘已辦妥財團法人登\n      記或其興辦之博物館收取門票經營博物館業務使用之自有\n      房屋，符合房屋稅條例第15條第1 項第5 款規定，即得依\n      該規定免徵房屋稅，而收獎勵文化事業之實效，實毋須考\n      量該等財團法人興辦博物館等，雖有營業行為，然「光靠\n      門票收入，根本不敷所需」之問題，再於上開獎助條例中\n      增設免徵房屋稅之規定，顯然已辦妥財團法人登記或其所\n      興辦博物館使用之自有房屋，並不屬於行為時房屋稅條例\n      第15條第1 項第5 款規定所規範之情形，如此，文化獎助\n      條例第26條之規定，始不致成為具文。\n    (四)復查，系爭房屋稅之核課，被告均核定原告為納稅義務人\n      並非以系爭博物館為納稅義務人，再者，依房屋稅條例第\n      15條第1項第5款規定，享受免徵房屋稅之租稅優惠者，以\n      自有房屋「供辦公使用」為限，被告就原告之系爭房屋供\n      作系爭博物館使用之情形，認定是否合致上開條款所定「\n      供辦公使用」之要件，乃適用該條款規定之當然，原告所\n      謂將「基金會」與「博物館」割裂為兩個獨立之個體，而\n      各自承擔權利義務云云，顯與事實不符，並不可採。至原\n      告主張酌收費用僅係用以支應茶水、水電等費用一節，依\n      財政部85.7.5臺財稅字第851116753 號函規定，係指因提\n      供設施或服務而酌收之必要費用，須經目的事業主管機關\n      出具證明，其收費非以營利為目的且其不違反其設立之宗\n      旨目的，惟原告迄未提示，經其目的事業主管機關證明其\n      收費非以營利為目的且不違反其設立宗旨之相關文件，被\n      告自無從認定其屬慈善救濟事業，而有該函釋之適用。\n    (五)原告雖主張依營業稅法第6條第2款規定，營業人非當然以\n      營利為目的一節。查系爭博物館銷售書籍、販賣導覽手冊\n      、書法筆記書、收取租金、發行會員卡、設立咖啡廳及餐\n      廳、出售門票等營利行為，依宗教團體免辦理所得稅結算\n      申報認定要點及教育文化公益慈善機關或團體免納所得稅\n      適用標準及財政部78年6 月6 日臺財稅字第780649615 號\n      函釋規定，該等收入屬銷售貨物或勞務收入。則系爭博物\n      館既為原告之附屬作業組織，並有銷售貨物及勞務之收入\n      ，自無不符免辦理所得稅結算申報規定，原告亦依規定辦\n      理所得稅結算申報。顯見辦理營業登記課徵營業稅一事，\n      彰顯原告確有營利之行為及目的。原告雖不斷強調「利潤\n      」是判斷營利行為之重要指標云云，惟查組織機構賺錢與\n      否，需視其營運團隊之經營方針。以系爭博物館之課稅資\n      料來看，除禪一股份有限公司等之租金收入為大筆營運收\n      入外，其餘皆為零星的營運收入，不能因原告經營虧損，\n      即認定其無營利之事實。綜觀原告之經營營業組織策略，\n      實已具備營利之行為及目的等語置辯。並聲明求為判決駁\n      回原告之訴。\n五、本院判斷如下：\n  (一)關於原告主張適用房屋稅條例第15條第1項第5款部分：\n    1.按「房屋稅之徵收，依本條例之規定；本條例未規定者，\n      依其他有關法律之規定。」「房屋稅向房屋所有人徵收之\n      。……」「房屋稅依房屋現值，按左列稅率課徵之：……\n      二、非住家用房屋，其為營業用者，最低不得少於其房屋\n      現值3%，最高不得超過5%。其為私人醫院、診所、自由職\n      業事務所及人民團體等非營業用者，最低不得少於其房屋\n      現值1. 5% 」「私有房屋有左列情形之一者，免徵房屋稅\n      ：…5.不以營利為目的，並經政府核准之公益社團自有供\n      辦公使用之房屋。但以同業、同鄉、同學或宗親社團為受\n      益對象者，不在此限。…」行為時房屋稅條例第1 條、第\n      4 條第1 項前段、第5 條第2 款及第15條第1 項第5 款分\n      別定有明文。\n    2.次按，「憲法第19條規定『人民有依法律納稅之義務』，\n      係指人民有依法律所定要件負繳納稅捐之義務或享減免繳\n      納之優惠而言。」業經司法院釋字第369號及第496號解釋\n      揭櫫甚明。故上引行為時房屋稅條例第15條第1項第5款免\n      徵房屋稅規定之適用，其要件為：(1)經政府核准之公益社\n      團之自有房屋。(2)該公益社團非以營利為目的。(3)該公益\n      社團不得以同業、同鄉、同學或宗親社團為受益對象。(4)\n      該公益社團自有之房屋，其用途須供辦公使用，並須同時\n      具備上述四項要件，始得享有免徵房屋稅之租稅優惠。財\n      政部87年6 月8 日台財稅字第871947996 號函略以：「…\n      依房屋稅條例第15條第1 項第5 款規定，…本案財團法人\n      ＯＯ文教基金會，如係以公益為的目之社團（包括財團法\n      人組織及社團法人組織），其自有供基金會及其台中、台\n      南、高雄三地區分會辦公使用之房屋，准依上開條款規定\n      ，免徵房屋稅。」乃該部本於中央稅捐稽徵主管機關職權\n      ，就上引房屋稅條例第15條第1 項第5 款「公益社團」之\n      範圍所為之釋示，經核與該法條規範意旨無違，自得予援\n      用。因此，房屋稅條例第15條第1 項第5 款規定免徵房屋\n      稅之主體，包括社團法人組織及財團法人組織均屬之；況\n      被告就原告自有供其基金會辦公室使用之門牌號碼臺北縣\n      永和市○○路22巷8 號6 樓房屋，亦依上開條款規定准予\n      自93年5 月起免徵房屋稅在案，被告於本件訴訟中，卻改\n      稱原告為財團法人組織，非屬上開條款規定之「公益社團\n      」，並無該條款免徵所得稅之適用云云，洵無足採。\n    3.復按，上引房屋稅條例第15條第1項第5款係房屋稅條例於\n      59年7月8日修正增訂之規定，旨在於公益社團之自有房屋\n      多半供公益使用，乃明定對於公益社團自有「供辦公使用\n      」之房屋，給予免徵房屋稅之租稅優惠。另對照同法條同\n      項第2 款關於「業經立案之私立慈善救濟事業，……，其\n      『直接供辦理事業所使用』之房屋。」免徵房屋稅之規定\n      ，於59年7 月8 日修正前原規定：「業經立案之私立慈善\n      救濟事業，……其『供辦公使用』之房屋。」及參酌其修\n      正立法理由以：「慈善救濟事業房屋之免稅，應包括直接\n      供辦理事業所使用之一切房屋，如養老院、救濟院等，不\n      能單以辦公房屋為限，故予以修正。」可知，公益社團所\n      有房屋免徵房屋稅，依上引房屋稅條例第15條第1 項第5\n      款規定，應以其自有「供辦公使用」之房屋為限；至該公\n      益社團自有「供辦理事業使用」之房屋，既非屬「供辦公\n      使用」，自不得依該條款規定免徵房屋甚明。財政部60年\n      11月9 日台財稅字第38743 號函略以：「房屋稅條例第15\n      條第1項 第5 款所指之：『不以營利為目的，並經政府核\n      准之公益社團自有供辦公使用之房屋』免徵房屋稅，應以\n      經由主管目的事業機關核准登記有案之公益社團自有房屋\n      供作辦公使用者為準，如其房屋用為營業或供收益使用，\n      或該社團為謀社員經濟上之利益，而將所得利益分配於社\n      員者，均不在此限。」66年8 月15日台財稅字第35449 號\n      函：「查房屋稅條例第15條第1 項第5 款規定……免徵房\n      屋稅，其免徵範圍係包括與該社團辦公有關之會議廳、圖\n      書室、廚房、員工食堂、浴室、廁所、值日室、檔案室、\n      貯藏室、議習室、值夜室、禮堂、文物儲藏室等房屋。」\n      及88年7 月29日台財稅字第881929562 號函：「依房屋稅\n      條例第15條第1 項第5 款規定，…又依同條項第4 款規定\n      ，私有房屋無償供政府機關公用之房屋，免徵房屋稅。本\n      案中國青年反共救國團所有××市青年育樂中心禮堂兼球\n      場房屋，除供該團××市團務指導委員會及各區團委會集\n      會活動使用外，為配合貴市推展各項活動，並提供青少年\n      良好活動場所，無償或酌收水電費提供貴市各級政府機關\n      、學校使用，應有上開2 條款免徵房屋稅規定之適用。至\n      該房屋偶有提供其他團體辦理臨時性之活動使用，但僅收\n      取水電費，亦准比照房屋稅條例第15條第1 項第5 款規定\n      ，免徵房屋稅。」等關於房屋稅條例第15條第1 項第5 款\n      所稱公益社團自有「供辦公使用」房屋之範圍所為之釋示\n      ，與該條款規範目的並無抵觸，亦非增加人民法律所無之\n      稅賦負擔，自得予援用。故揆諸上揭說明可知，非以營利\n      為目的之公益社團，其自有房屋除供自己辦公使用外，如\n      「偶而」「無償」或「酌收水電費」提供予政府機關、學\n      校或其他團體使用者，因偶一為之，非屬繼續、固定性之\n      對外提供使用；且其收取費僅用以支付水電費用，與提供\n      房屋供他人使用間亦無對價關係，仍屬無償提供使用，則\n      系爭自有房屋仍具備提供予公益社團自己辦公使用之公益\n      性質，依房屋稅條例第15條第1 項第5 款規定意旨，應准\n      免徵房屋。惟若公益社團將自有房屋出租予他人使用而收\n      取租金；或用以從事銷售貨物、勞務而收取代價之營利行\n      為，既非供公益社團自己辦公使用，自無上揭條款規定免\n      徵房屋稅之適用甚明。申言之，判斷公益社團之自有房屋\n      是否供自己辦公使用或用以營業及收取利益之營利行為，\n      應以該自有房屋之實際使用用途認定之，與該公益社團是\n      否非以營利為目的，係屬二事；亦與公益社團就取自該自\n      有房屋之收益如何處分或是否用於公益及辦理目的事業無\n      關，否則，房屋稅條例第15條第1 項第5 款關於公益社團\n      自有房屋給予免徵房屋稅之規定，何須在「不以營利為目\n      的，並經政府核准之公益社團」之要件外，再加以「供辦\n      公使用」之要件，原告將二者混為一談，主張其為非以營\n      利目的之公益財團法人，系爭房屋供世界宗教博物館使用\n      之門票收入及場地租金收入，既均用於公益及原告之設立\n      目的，世界宗教博物館收取門票及場地租金，即非以營利\n      為目的，並無營利行為云云，委無憑採。\n    4.再按，「在中華民國境內銷售貨物或勞務及進口貨物，均\n      應依本法規定課徵加值型或非加值型之營業稅。」「將貨\n      物之所有權移轉與他人，以取得代價者，為銷售貨物。提\n      供勞務予他人，或提供貨物與他人使用、收益，以取得代\n      價者，為銷售勞務。…」及「有左列情形之一者，為營業\n      人：一、以營利為目的之公營、私營或公私合營之事業。\n      二、非以營利為目的之事業、機關、團體、組織，有銷售\n      貨物或勞務者。……」加值型及非加值型營業稅法第1 條\n      、第3 條第1 項、第2 項及第6 條分別定有明文。查原告\n      所有如附表編號1-7 所示之7 戶房屋均係供「世界宗教博\n      物館」使用，並非供原告基金會辦公使用，此有原告所不\n      爭如附表所載上開7 戶房屋之使用情形可按，其中附表編\n      號2 之房屋於95年6 月28日設立洋瀧股份有限公司宗博館\n      門市部( 見原處分卷第152 頁) ，而上開該博物館除常設\n      展覽、兒童展覽對外收取門票及發行宗博之友會員卡收取\n      會員費外，館內亦設有禮品中心及咖啡廳，分別販賣文物\n      禮品、音樂、書籍及咖啡、花茶、茶點、簡餐等營利行為\n      ，亦有該館所印製之參觀指引及世界宗教博物館架設之網\n      站資料在卷可稽( 見原處分卷(一)第135-143 頁) 。又原告\n      為上開博物館出售門票之營業行為，於86年間增設附屬機\n      構「財團法人世界宗教博物館發展基金會附設臺北館」（\n      下稱原告附設臺北館），再以原告附設台北館之名義於89\n      年10月間辦理營業稅設籍登記迄今，亦有內政部86年4 月\n      2 日臺(86)內民字第8602392 號函及營業稅稅籍資料可稽\n      （見本院卷第152 、153 頁、原處分卷(一)第154 頁) ，而\n      經被告調得原告附設台北館96年至97年營業稅申報書資料\n      得知，該館96年申報之銷項總額為24,089,125元，進貨及\n      費用總金額之申報為13,548,885元；97年申報之銷項總額\n      截至97年4 月為7,796,976 元，進貨及費用總金額為1,79\n      5,392 元( 見本院卷第330-348 頁) ；且依本院命原告提\n      出該附設台北館於本件97年度房屋稅課稅期間( 即96年7\n      月至97年6 月) 關於銷貨收入之總分類帳顯示，以原告附\n      設台北館名義經營上開「世界宗教博物館」之各項銷貨收\n      入，包括門票、宗博之友會員卡、禮品店、祥瀧禮品店抽\n      成金、舉辦教育推廣及各項活動等收入( 見本院卷300-31\n      0 頁) ，並非如原告所稱該博物館只有門票收入，亦足證\n      「世界宗教博物館」係從事經常性、繼續性提供展覽、場\n      地與他人使用收益以收取代價；及販賣貨物予他人以收取\n      代價之營業行為，均屬有對價關係之有償行為，並非「供\n      辦公使用」之性質甚明，亦與財政部上揭88年7 月29日函\n      釋所指「偶而」「無償」「酌收水費」提供予政府機關、\n      學校或其他使用之情形不同；且營業本有盈虧，與其是否\n      為營利性質無關，原告執「世界宗教博物館」成立以來均\n      屬虧損，主張該博物館之門票及場地租金收入，屬僅酌收\n      水電用支出，並非營利行為云云，亦無足取。\n    5.又所謂營業，應不以門市交易為限，營利事業內部之工作\n      ，亦不能謂非營業之行為( 改制前行政法院57年判字第43\n      1 號判例參照) ，如附表編號4 之房屋係供世界宗教博物\n      館之辦公室使用；另編號6 、7 之2 戶房屋供該博物館放\n      置展覽用文物之儲藏室使用，均屬該博物館營運不可或缺\n      之一環，自屬提供世界宗教博物館使用之範圍，故被告以\n      如附表編號1-7 所示系爭房屋係供世界宗教博物館使用，\n      不符行為時房屋稅條例第15條第1 項第5 款規定之要件，\n      課徵該等房屋97年度房屋稅，於法並無違誤。原告未詳究\n      上引房屋稅條例第15條第1 項第5 款之規範目的及適用範\n      圍，亦未區辨「供辦公使用」及「供目的事業使用」之差\n      異，徒執其設立宗旨及在國內外籌設宗教博物館、展覽文\n      物為其目的事業，故附表編號1 、2 、3 、5 之房屋供世\n      界宗教博物館展覽區、特展區及兒童館展示使用，符合其\n      設立宗旨，即符合「供辦公使用」之要件；另附表編號6\n      、7 之房屋供該博物館放置展覽文物之儲藏室，即與財政\n      部上揭66年8 月15日函釋「與辦公有關之文物儲室」相符\n      ，應得免徵房屋稅云云，均無足取。\n  (二)關於原告主張適用文化藝術獎助條例第26條部分：\n    1.按「經文教主管機關核准設立之私立圖書館、博物館、藝\n      術館、美術館、民俗文物館、實驗劇場等場所免徵土地稅\n      及房屋稅。但以已辦妥財團法人登記或係辦妥登記之財團\n      法人興辦，且其用地及建築物為該財團法人所有者為限。\n      」為文化藝術獎助條例第26條所明定。由上開規定可知，\n      已辦妥財團法人登記或係辦妥登記之財團法人興辦之博物\n      館，尚須「經文教主管機關核准設立」，始得免徵房屋稅\n      ；否則，若不問是否「經文教主管機關核准設立」之博物\n      館，均得依行為時房屋稅條例第15條第1項第5款規定免徵\n      房屋稅，則文化藝術獎助條例第26條有關免徵房屋稅之規\n      定，不啻成為具文，此當非其立法本旨所在，合先敘明。\n    2.而依文建會98年1月9日文壹字第0983100593號函釋謂：「\n      …二、有關『文教主管機關』是否包含地方政府等其他機\n      關乙節，鑑於經文教主管機關核准設立之文化藝術事業場\n      所之種類及態樣繁多。爰此，文化藝術獎助條例第26條所\n      稱之『文教主管機關』，係指經營或從事文化藝術獎助條\n      例第2 條所列相關文化藝術事業之各該目的事業主管機關\n      ，合先敘明；另第26條所定免徵土地稅及房屋稅之場所，\n      除所列舉之私立圖書館、博物館、藝術館、美術館、民俗\n      文物館、實驗劇場等場所外，仍以辦妥財團法人登記或係\n      辦妥登記之財團法人興辦，且其用地及建築物為該財團法\n      人所有者為限。」可知，文化藝術獎助條例第26條之「文\n      教主管機關」，係指經營或從事該條例第2 條所列相關文\n      化藝術事業之各該目的事業主管機關而言，核該函釋乃文\n      建會本於文化藝術事業獎勵、補助之主管機關職權，對於\n      文化藝術獎助條例第26條規定所為之解釋，符合該條例「\n      為扶植文化藝術事業，輔導藝文活動，保障文化藝術工作\n      者，促進國家文化建設，提昇國民文化水準」之立法意旨\n      ，自得予援用。\n    3.復按，「本條例所稱文化藝術事業，係指經營或從事下列\n      事務者：……四、關於文化機構或從事文化藝術活動場所\n      之管理及興辦。……」及「本條例第2條第4款所稱文化機\n      構，係指依法令設立之下列機構：……二、博物館或美術\n      館。……」分別為文化藝術獎助條例第2條第4款及同條例\n      施行細則第4條第2款所明定。是以，須依「法令」合法設\n      立之博物館，方屬於文化藝術獎助條例第2條第4款所稱之\n      「文化機構」，而依社會教育法第5條第2款：「各級政府\n      視其財力與社會需要，得設立或依權責核准設立左列各社\n      會教育機構：……二、博物館或文物陳列室。」第6條：\n      「社會教育機構由中央設立者為國立；……；由私人或團\n      體設立者為私立。」第7 條：「社會教育機構之設立、變\n      更或停辦：國立者，應由教育部審查全國情形決定之；…\n      …縣( 市) 立、鄉( 鎮、市、區) 立及私立者，應報請縣\n       (市) 政府或直轄市主管教育行政機關核准，並轉報教育\n      部備案。」第8 條：「私立社會教育機構應依前條規定核\n      准立案並辦理財團法人登記；其設立、變更、停辦、督導\n      、獎勵及其他應遵行事項之辦法，由教育部定之。」暨私\n      立社會教育機構設立及獎勵辦法第1 條：「本辦法依社會\n      教育法第8 條規定訂定之。」第3 條第2 款：「私立社會\n      教育機構種類如下：…二、博物館或文物陳列室。」第8\n      條：「私立社會教育機構得由私人或團體創辦，或經各級\n      主管教育行政機關許可設立之財團法人附設。」第9 條：\n      「設立私立社會教育機構，應由創辦人或所屬之財團法人\n      以申請書載明下列事項，並檢具有關證明文件，連同捐助\n      章程或遺囑影本，向直轄市主管教育行政機關或縣( 市)\n      政府申請籌設。……」第10條：「私立社會教育機構應設\n      董事會，但財團法人附設者，得不另設董事會。」第17條\n      ：「董事會經報准核備後，應於30日內辦理財團法人登記\n      ，逾期不辦理者，依第9 條之核准失其效力。…」第18條\n      ：私立社會教育機構於完成財團法人設立登記並領得財團\n      法人登記證書後，應由董事會於一年內開具第9 條所列事\n      項及有關文件，向直轄市主管教育行政機關或縣( 市) 政\n      府申請立案。凡經核准立案之私立社會教育機構，直轄市\n      主管教育行政機關或縣（市) 政府應轉報教育部備查。」\n      第19條：「私立社會教育機構經直轄市主管教育行政機關\n      或縣( 市) 政府核准立案後，始得開辦。」第20條：「財\n      團法人附設社會教育機構，得……依第9 條規定向直轄市\n      主管教育行政機關或縣( 市) 政府申請核准立案後開辦。\n      」「私立社會教育機構受直轄市主管教育行政機關或縣(\n      市) 政府之監督及輔導，其一切教育措施及其他事項應依\n      有關法令辦理。」等規定可知，博物館不僅為文化機構，\n      亦屬於社會教育機構，私立博物館之設立，如由私人或團\n      體設立者，應向直轄市主管教育行政機關或縣( 市) 政府\n      申請核准立案，並辦理財團法人登記，方得開辦；如由財\n      團法人附設私立博物館，亦須為主管教育行政機關許可設\n      立之財團法人始得申請之，並由直轄市主管教育行政機關\n      或縣( 市) 政府執行私立博物館之監督及輔導。足見，無\n      論是文化藝術獎助條例第26條所定「經文教主管機關核准\n      設立之博物館」，其所稱之「文教機關」；或依文建會上\n      開函釋所稱經營同條例第2 條第4 款所列博物館( 文化機\n      構) 之文化藝術事業之「目的事業主管機關」，依現行有\n      效之上揭法令規定，均係指直轄市主管教育行政機關或縣\n       (市) 政府等地方主管教育行政機關甚明。\n    4.惟查，原告係以從事宗教業務及服務為目的之宗教團體，\n      向內政部申請許可設立之宗教財團法人，其名稱為「財團\n      法人世界宗教博物館發展基金會」，設立宗旨為「一、重\n      建尊重、包容、博愛的社會、闡揚生命的智慧與健康的人\n      生觀。二、提昇華人社會的國際形象與地位。三、推展宗\n      教交流，促進世界和平。四、保護人類的宗教智慧與資產\n      。」此有原告經臺灣板橋地方法院登記處核發之法人登記\n      證書內容可稽( 見本院卷第146 頁) ，並非經主管教育行\n      政機關許可設立之財團法人，而原告之捐助及組織章程第\n      4 條第1 款規定：「本法人依有關法令規定辦理左列業務\n      ：「(一)籌設世界宗教博物館及國內外分館。……」( 見本\n      院卷第148 頁) ，亦係原告本於宗教財團法人所從事之目\n      的事業，仍屬於宗教業務之範圍；縱原告興辦之「世界宗\n      教博物館」已實質具備「博物館」之內涵，依上引社會教\n      育法暨私立社會教育機構設立及獎勵辦法之規定，亦應向\n      地方主管教育行政機關申請核准設立，方符合文化藝術獎\n      助條例第26條所稱「經文教主管核准設立」及同條例施行\n      細則第4 條第2 款規定「依法令設立」之要件，該博物館\n      始能謂屬於同條例第2 條第4 款所列文化機構( 博物館)\n      之文化藝術事業；況且，內政部以83年3 月22日台83內民\n      字第8301721 號函准予原告設立宗教財團法人，已於該函\n      說明欄載明：「…三、另依教育部82年12月22日(82)社字\n      第071180號函，該基金會設立後，若欲推展『博物館」業\n      務，須依『私立社會教育機構設立及獎勵辦法』辦理。」\n       (見原處分卷(一)第189 頁) ，原告亦不得諉為不知；然原\n      告卻係以附設機構台北館名義辦理營業登記而經營上開「\n      世界宗教博物館」，明顯與上揭法令規定不符。原告未細\n      究相關法令規定及文建會上開函釋意旨，徒言其為經目的\n      事業主管機關內政部核准設立之公益財團法人，其興辦之\n      「世界宗教博物館」亦為文化藝術獎助條例第2 條第4 款\n      之文化藝術事業，即符合該條例第26條「經文教主管機關\n      核准設立」之規定，其所有供該博物館使用之系爭房屋，\n      自得依該規定免徵房屋稅云云，委無足取。\n六、綜上所述，原告之主張，均無足採。被告對於原告所有如附\n    表編號1-7 等7 戶房屋所為課徵97年度房屋稅之處分，於法\n    並無違誤，訴願決定予以維持，亦無不合。原告訴請撤銷，\n    為無理由，應予駁回。\n七、據上論結，本件原告之訴為無理由，依行政訴訟法第98條第\n    1 項前段，判決如主文。\n中    華    民    國    99    年     5    月   12     日\n                    臺北高等行政法院第二庭\n                              審判長法  官  徐瑞晃\n                                    法  官  蔡紹良\n                                    法  官  蕭惠芳\n上為正本係照原本作成。\n如不服本判決，應於送達後20日內，向本院提出上訴狀並表明上\n訴理由，如於本判決宣示後送達前提起上訴者，應於判決送達後\n20日內補提上訴理由書（須按他造人數附繕本）。\n中    華    民    國    99    年     5    月   12     日\n                                    書記官  李淑貞\n",
  "structure": {
    "main": "原告之訴駁回。\n訴訟費用由原告負擔。",
    "fact": "一、程序事項：本件原告起訴時，被告之代表人為黃毓彥，嗣於\n    訴訟中變更為乙○○，茲據新任代表人具狀聲明承受訴訟，\n    經核無不合，應予准許。\n二、事實概要：原告所有如附表所示門牌號碼臺北縣永和市○○\n    路○段236號6樓、7樓、永和市○○路2號6樓、永和市○○路\n    22巷12號6 樓、7 樓、中和市○○路○ 段344 號5 樓、中和\n    市○○路○ 段346 號5 樓、永和市○○路2 號7 樓等8 戶房\n    屋，經被告所屬中和分處於97年間派員至現場勘查結果，因\n    認上開房屋之使用情形，或供世界宗教博物館使用，或供道\n    饗養生蔬膳餐廳等營業使用，不符免徵房屋稅事由，乃對原\n    告發單課徵上開8 戶房屋之97年度房屋稅總計為新臺幣( 下\n    同)2,532,063 元 。原告不服，申請復查未獲變更，提起訴\n    願亦經決定駁回後，原告就被告對附表編號1-7 等7 戶房屋\n     (下稱系爭房屋) 課徵房屋稅之處分仍不服，遂提起本件行\n    政訴訟。\n三、本件原告主張：\n    (一)按文建會98年1月9日文壹字第0983100593號函釋規定，如\n      屬從事文化藝術獎助條例第2 條所稱文化藝術事業者，則\n      該從事者只要經其目的事業主管機關核准設立，即得適用\n      免徵房屋稅之租稅優惠。查原告興辦之「世界宗教博物館\n      」，為依該條例第2 條及同條例施行細則第4 條規定之文\n      化藝術事業；且自開館以來，即長期與臺北縣文化局、教\n      育部或文建會等互動頻繁，並多次參與文建會推動之計劃\n      ，確為有興辦博物館之文化機構，核與上開獎助條例所稱\n      「文化藝術事業」之內涵相符。而原告亦經目的事業主管\n      機關內政部核准設立之公益性財團法人，並有法人登記證\n      書，故依上開函釋意旨，原告符合上開獎助條例第26條「\n      經文教主管機關核准設立」規定，自得免徵房屋稅甚明。\n    (二)原告為不以營利為目的之公益社團，自有房屋稅條例第15\n      條第1項第5款規定之適用：\n      1.依財政部 87年6月8日臺財稅字第871947996號函釋及財\n        政部88年5 月1 日臺財稅字第881912937 號函意旨，房\n        屋稅條例第15條第1 項第5 款所指之「公益社團」，其\n        重點應在私有房屋是否供「公益使用」，殊不因該公益\n        性團體為社團或財團本質上即有不同。被告雖援引臺灣\n        省稅務局69.1.30 稅三字第19336 號函：「…本案○○\n        高爾夫俱樂部雖屬財團法人組織，並非屬房屋稅條例所\n        稱之『公益社團』，其供辦公使用房屋應無首揭法條免\n        徵房屋稅之適用。」之內容，稱財團法人組織非屬房屋\n        稅條例所稱「公益社團」云云。惟上開函釋係指稱該案\n        之稅捐主體並不具公益性，故雖屬財團法人組織，仍無\n        上開條例第15條第1 項第5 款之適用，並未認公益性之\n        財團法人不得適用房屋稅條例，被告顯有誤解，不值採\n        信。\n      2.而自原告法人登記證書、目的事業主管機關內政部之核\n        准設立函，及內政部93年10月28日內授中民字第093000\n        8261號函覆原告：「…貴法人係經本部許可設立登記有\n        案之宗教財團法人基金會，依章程其設立目的…確為促\n        進公眾利益成立之宗教財團法人。」皆足證原告係非以\n        營利為目的，而為促進公眾利益所設立之財團法人；且\n        所從事「籌設世界宗教博物館及國內外分館」、「興辦\n        宗教與生活之教育活動」及「興辦國內外各項宗教圖書\n        與資訊服務」，亦為達成其目的所須「非以營利為目的\n        」之活動；再依原告章程第23條規定，原告解散時財產\n        歸屬法人所在地之地方自治團體所有，非歸屬私人，益\n        證原告為非以營利為目的之財團法人，殆無疑義。\n      3.查系爭房屋所有人為原告，僅原告為納稅義務人，是房\n        屋稅條例第15條第1項第5款所定之公益社團，應就原告\n        之性質認定，方符房屋稅之課徵要件。詎被告以原告附\n        設機構「財團法人世界宗教博物館發展基金會附設臺北\n        館」有設稅籍及繳納營業稅，即認定該附設機構係以營\n        利為目的，進而否定系爭房屋得免徵房屋稅云云。惟查\n        ，原告附設台北館無法人格，並無得以獨立名義對外興\n        辦博物館、推廣宗教活動及對系爭房屋使用收益之可能\n        。房屋稅條例既規定納稅義務人為原告，即應就原告之\n        性質判斷方屬正確。原告既屬非以營利為目的之公益性\n        財團法人，所從事者皆為非營利為目的之活動，應得適\n        用房屋稅條例第15條第1項第5款規定無疑。\n      4.原告雖於86年間因興辦宗教博物館，有銷售貨物或勞務\n        之營業行為，乃由附設機構為營業登記。然依營業稅法\n        第2 條及第6 條第2 項規定可知，營業人非當然以營利\n        為目的，且營業稅之納稅義務人，容許同一人因其總機\n        構與分支機構不同而分別登記( 營業稅法第28條規定參\n        照)， 原告方得以附設機構單獨登記為營業人，惟營業\n        稅法與房屋稅條例之規範迥異，房屋稅條例規定之納稅\n        義務人，僅為所有人，並無就所有人及其附設機構分別\n        認定之可能，被告恣意割裂就原告及附設機構分別認定\n        性質，進而主張系爭房屋無房屋稅條例第15條第1 項第\n        5 款規定之適用，顯有認事用法之錯誤。\n      5.再按財政部88年7月29日臺財稅字第881929562號函釋意\n        ，原告之門票收入及租金收入，係屬酌收水電費用性質\n        ，並無營利性質。查附表項次1 、2 、3 之三戶房屋係\n        供世界宗教博物館展覽區使用，項次5 供兒童館展示使\n        用，雖有門票收入，惟該項收入僅供支付系爭房屋之電\n        費支出，總計該7 戶房屋97課稅年度之電費支出為4,07\n        0,521 元與門票收入2,932,497 元相較，尚不足1,138,\n        024 元，足見原告主要經費來源均仰賴大眾捐助，足見\n        原告主要經費來源均仰賴大眾捐助，酌收門票僅係酌收\n        水電茶水費用，非以營利為目的甚明。況該三戶房屋從\n        95年10月起，已無再提供場地租借服務，遑論當初原告\n        酌收費用僅係用以支應茶水、水電等費用，總計從94年\n        7 月至95年6 月僅4 萬餘元，即使將此場地租借費用計\n        入，原告仍舊入不敷出，何來具有營利目的可言？\n      6.再者，原告之性質係為財團法人，原告所有之盈餘均係\n        供維持會務運作所使用，縱原告如有收益多於支出之情\n        況（假設語，原告否認之），日後若依法解散時，依照\n        原告章程第23條規定，賸餘財產係歸於原告事務所所在\n        地之地方自治團體，而非歸於個人或私人企業，故原告\n        附屬機構世界宗教博物館雖有門票、場地費等收入，仍\n        與以營利為目的不同，其理甚明。\n    (三)系爭房屋皆屬供原告辦公使用之房屋，符合房屋稅條例第\n      15條第1項第5款「私有房屋供自有辦公室使用」之要件：\n      1.按財政部66.8.15臺財稅字第35449號函釋，上開條例規\n        定「供辦公室使用之房屋」，包含會議室、貯藏室、講\n        習室及文物儲藏室；另財政部60.9.23臺財稅字第37570\n        號函釋亦闡明供辦公使用之房屋，其認定標準，係就該\n        社團自有房屋之用途，在供其推廣公益業務或活動，核\n        實認定為「供辦公使用」之房屋，並免徵房屋稅即明。\n      2.查附表1、2之兩戶房屋，主要供世界宗教博物館展覽使\n        用，與原告設立之宗旨相符，符合上揭60年函釋意旨；\n        另項次3 之房屋主要供該博物館特展區展覽，並兼作講\n        習室使用；兼作講習室部份，亦與上揭66年函釋意旨相\n        符，均符合「自有供辦公使用」之要件，應得免稅。又\n        前述三戶房屋有部分面積曾對外提供作會議、教學之臨\n        時性活動用途並酌收場地費，然該部分面積於平時無外\n        借時，亦為原告內部舉辦會議之會議室，依上揭66年函\n        釋意旨，符合「自有供辦公室使用」要件，端不能僅憑\n        原告曾在網頁上列出場地費之標準，即認定該房屋作為\n        經常性租借用途，不可不辨。\n      3.附表項次4 之房屋係作辦公室使用，雖被告認係原告附\n        設機構使用，惟不應割裂原告及附設機構分別認定已如\n        前述，該房屋應得免稅甚明。另項次5 之房屋於94年2\n        月起則供世界宗教博物館兒童館展示使用，該部分期間\n        供展覽使用，依上揭60年函釋意旨，亦符合自有供辦公\n        使用之要件。另附表項次6 、7 兩戶房屋係供放置展覽\n        用文物之「文物儲藏室」使用，與上揭66年函釋「與辦\n        公有關之文物儲藏室」之意旨相符，雖被告認係供原告\n        附設機構使用，惟不應割裂原告及附設機構分別認定已\n        如前述，該房屋應得免稅甚明。\n    (四)又被告所提最高行政法院99年度判字第66號判決，原告已\n      於法定期間內提起再審之訴，更擬針對該判決所適用之法\n      規提起大法官解釋，以茲救濟，故該判決見解尚非的論等\n      語。並聲明請求判決訴願決定、原處分（含復查決定）關\n      於課徵房屋稅額超過263,139部分均撤銷。\n四、被告則以：\n    (一)按房屋稅條例第15條第1項第5款規定之適用，就免徵房屋\n      稅之主體而言，財政部87.6.8臺財稅字第871947996 號函\n      雖認為該「公益社團」包括財團法人及社團法人，惟依臺\n      灣省稅務局上揭69年函釋卻指出財團法人組織，並非屬房\n      屋稅條例所稱之「公益社團」；再就免徵房屋稅客體之用\n      途而言，所謂「供辦公使用」者，依財政部60年11月9 日\n      臺財稅字第38743 號令，房屋如用為營業非屬「供辦公使\n      用；另參諸財政部88年7 月29日臺財稅字第881929562 號\n      函釋，顯見公益社團所有之房屋，原則上供自己辦公使用\n      ，兼而提供各級政府機關、學校使用或偶有提供其他團體\n      辦理臨時性之活動使用而酌收或僅收取水電費者，亦得認\n      定為「供辦公使用」，此合先敘明。\n    (二)查系爭房屋前經被告所屬中和分處於93年4 月間及97年間\n      派員至現場勘查，其使用情形或供世界宗教博物館使用，\n      或供餐廳等營業使用，均非供原告自己辦公使用或供與其\n      辦公有關之會議廳等用途使用，此會勘結果為原告所不爭\n      ，核與前揭房屋稅條例第15條第1 項第5 款規定及上開函\n      釋規定不符，自無免徵房屋稅之適用。又系爭房屋為原告\n      所興辦之博物館使用。該博物館之正確名稱係「財團法人\n      世界宗教博物館發展基金會附設臺北館」，乃原告於86年\n      間增設之附屬機構，並於89年10月間辦理營業稅設籍登記\n      迄今；系爭博物館經營博物館業務，對外收取門票，經查\n      調其96年至97年營業稅申報書資料得知，該館96年申報銷\n      項總額為24,089,125元，進貨及費用總金額申報為13,548\n      ,885元；97年申報之銷項總額截至97年4 月為7,796,976\n      元，進貨及費用總金額為1,795,392 元，足證原告經營博\n      物館業務係屬常態性營業行為，此有原告96年至97年營業\n      稅課稅資料可稽，又原告93及94年房屋稅上訴審99年度判\n      字第66號判決理由五(二)載明：「揆諸…營業稅法第1 條：\n      …之規定可知，被上訴人興辦之世界宗教博物館為加值型\n      及非加值型營業稅法之營業人，必須繳納營業稅，其非屬\n      免徵營業稅範圍，因此被上訴人興辦之世界宗教博物館所\n      使用之系爭房屋尚非屬『不以營利為目的』，即不符行為\n      時房屋稅條例第15條第1 項第5 款免徵房屋稅之法定要件\n      ，…」是以，原告以其所有系爭房屋作博物館使用，其使\n      用情形乃原告設立營業稅籍從事包括販賣門票、場地租借\n      等常態性營業行為，依上揭60年11月9 日臺財稅字第3874\n      3 號令及改制前行政法院57年判字第431 號判例意旨，顯\n      非屬「供辦公使用」自明，是原告之主張尚難採憑。\n    (三)而有關已辦妥財團法人登記或其興辦之博物館，其房屋為\n      該財團法人所有者，該財團法人得否享受免徵房屋稅之租\n      稅優惠，其所應具備之要件，文化藝術獎助條例第26條定\n      有明文；而經調閱該條文之立法紀錄可知，該條文係於逐\n      條討論時，由立法委員提議修正為：「免徵房屋稅及土地\n      稅」，經核其立法過程既有財政部代表參與，其與房屋稅\n      條例第15條第1 項規定間當無疊床架屋之情形發生，亦即\n      文化藝術獎助條例第26條制定當時，倘已辦妥財團法人登\n      記或其興辦之博物館收取門票經營博物館業務使用之自有\n      房屋，符合房屋稅條例第15條第1 項第5 款規定，即得依\n      該規定免徵房屋稅，而收獎勵文化事業之實效，實毋須考\n      量該等財團法人興辦博物館等，雖有營業行為，然「光靠\n      門票收入，根本不敷所需」之問題，再於上開獎助條例中\n      增設免徵房屋稅之規定，顯然已辦妥財團法人登記或其所\n      興辦博物館使用之自有房屋，並不屬於行為時房屋稅條例\n      第15條第1 項第5 款規定所規範之情形，如此，文化獎助\n      條例第26條之規定，始不致成為具文。\n    (四)復查，系爭房屋稅之核課，被告均核定原告為納稅義務人\n      並非以系爭博物館為納稅義務人，再者，依房屋稅條例第\n      15條第1項第5款規定，享受免徵房屋稅之租稅優惠者，以\n      自有房屋「供辦公使用」為限，被告就原告之系爭房屋供\n      作系爭博物館使用之情形，認定是否合致上開條款所定「\n      供辦公使用」之要件，乃適用該條款規定之當然，原告所\n      謂將「基金會」與「博物館」割裂為兩個獨立之個體，而\n      各自承擔權利義務云云，顯與事實不符，並不可採。至原\n      告主張酌收費用僅係用以支應茶水、水電等費用一節，依\n      財政部85.7.5臺財稅字第851116753 號函規定，係指因提\n      供設施或服務而酌收之必要費用，須經目的事業主管機關\n      出具證明，其收費非以營利為目的且其不違反其設立之宗\n      旨目的，惟原告迄未提示，經其目的事業主管機關證明其\n      收費非以營利為目的且不違反其設立宗旨之相關文件，被\n      告自無從認定其屬慈善救濟事業，而有該函釋之適用。\n    (五)原告雖主張依營業稅法第6條第2款規定，營業人非當然以\n      營利為目的一節。查系爭博物館銷售書籍、販賣導覽手冊\n      、書法筆記書、收取租金、發行會員卡、設立咖啡廳及餐\n      廳、出售門票等營利行為，依宗教團體免辦理所得稅結算\n      申報認定要點及教育文化公益慈善機關或團體免納所得稅\n      適用標準及財政部78年6 月6 日臺財稅字第780649615 號\n      函釋規定，該等收入屬銷售貨物或勞務收入。則系爭博物\n      館既為原告之附屬作業組織，並有銷售貨物及勞務之收入\n      ，自無不符免辦理所得稅結算申報規定，原告亦依規定辦\n      理所得稅結算申報。顯見辦理營業登記課徵營業稅一事，\n      彰顯原告確有營利之行為及目的。原告雖不斷強調「利潤\n      」是判斷營利行為之重要指標云云，惟查組織機構賺錢與\n      否，需視其營運團隊之經營方針。以系爭博物館之課稅資\n      料來看，除禪一股份有限公司等之租金收入為大筆營運收\n      入外，其餘皆為零星的營運收入，不能因原告經營虧損，\n      即認定其無營利之事實。綜觀原告之經營營業組織策略，\n      實已具備營利之行為及目的等語置辯。並聲明求為判決駁\n      回原告之訴。\n五、本院判斷如下：\n  (一)關於原告主張適用房屋稅條例第15條第1項第5款部分：\n    1.按「房屋稅之徵收，依本條例之規定；本條例未規定者，\n      依其他有關法律之規定。」「房屋稅向房屋所有人徵收之\n      。……」「房屋稅依房屋現值，按左列稅率課徵之：……\n      二、非住家用房屋，其為營業用者，最低不得少於其房屋\n      現值3%，最高不得超過5%。其為私人醫院、診所、自由職\n      業事務所及人民團體等非營業用者，最低不得少於其房屋\n      現值1. 5% 」「私有房屋有左列情形之一者，免徵房屋稅\n      ：…5.不以營利為目的，並經政府核准之公益社團自有供\n      辦公使用之房屋。但以同業、同鄉、同學或宗親社團為受\n      益對象者，不在此限。…」行為時房屋稅條例第1 條、第\n      4 條第1 項前段、第5 條第2 款及第15條第1 項第5 款分\n      別定有明文。\n    2.次按，「憲法第19條規定『人民有依法律納稅之義務』，\n      係指人民有依法律所定要件負繳納稅捐之義務或享減免繳\n      納之優惠而言。」業經司法院釋字第369號及第496號解釋\n      揭櫫甚明。故上引行為時房屋稅條例第15條第1項第5款免\n      徵房屋稅規定之適用，其要件為：(1)經政府核准之公益社\n      團之自有房屋。(2)該公益社團非以營利為目的。(3)該公益\n      社團不得以同業、同鄉、同學或宗親社團為受益對象。(4)\n      該公益社團自有之房屋，其用途須供辦公使用，並須同時\n      具備上述四項要件，始得享有免徵房屋稅之租稅優惠。財\n      政部87年6 月8 日台財稅字第871947996 號函略以：「…\n      依房屋稅條例第15條第1 項第5 款規定，…本案財團法人\n      ＯＯ文教基金會，如係以公益為的目之社團（包括財團法\n      人組織及社團法人組織），其自有供基金會及其台中、台\n      南、高雄三地區分會辦公使用之房屋，准依上開條款規定\n      ，免徵房屋稅。」乃該部本於中央稅捐稽徵主管機關職權\n      ，就上引房屋稅條例第15條第1 項第5 款「公益社團」之\n      範圍所為之釋示，經核與該法條規範意旨無違，自得予援\n      用。因此，房屋稅條例第15條第1 項第5 款規定免徵房屋\n      稅之主體，包括社團法人組織及財團法人組織均屬之；況\n      被告就原告自有供其基金會辦公室使用之門牌號碼臺北縣\n      永和市○○路22巷8 號6 樓房屋，亦依上開條款規定准予\n      自93年5 月起免徵房屋稅在案，被告於本件訴訟中，卻改\n      稱原告為財團法人組織，非屬上開條款規定之「公益社團\n      」，並無該條款免徵所得稅之適用云云，洵無足採。\n    3.復按，上引房屋稅條例第15條第1項第5款係房屋稅條例於\n      59年7月8日修正增訂之規定，旨在於公益社團之自有房屋\n      多半供公益使用，乃明定對於公益社團自有「供辦公使用\n      」之房屋，給予免徵房屋稅之租稅優惠。另對照同法條同\n      項第2 款關於「業經立案之私立慈善救濟事業，……，其\n      『直接供辦理事業所使用』之房屋。」免徵房屋稅之規定\n      ，於59年7 月8 日修正前原規定：「業經立案之私立慈善\n      救濟事業，……其『供辦公使用』之房屋。」及參酌其修\n      正立法理由以：「慈善救濟事業房屋之免稅，應包括直接\n      供辦理事業所使用之一切房屋，如養老院、救濟院等，不\n      能單以辦公房屋為限，故予以修正。」可知，公益社團所\n      有房屋免徵房屋稅，依上引房屋稅條例第15條第1 項第5\n      款規定，應以其自有「供辦公使用」之房屋為限；至該公\n      益社團自有「供辦理事業使用」之房屋，既非屬「供辦公\n      使用」，自不得依該條款規定免徵房屋甚明。財政部60年\n      11月9 日台財稅字第38743 號函略以：「房屋稅條例第15\n      條第1項 第5 款所指之：『不以營利為目的，並經政府核\n      准之公益社團自有供辦公使用之房屋』免徵房屋稅，應以\n      經由主管目的事業機關核准登記有案之公益社團自有房屋\n      供作辦公使用者為準，如其房屋用為營業或供收益使用，\n      或該社團為謀社員經濟上之利益，而將所得利益分配於社\n      員者，均不在此限。」66年8 月15日台財稅字第35449 號\n      函：「查房屋稅條例第15條第1 項第5 款規定……免徵房\n      屋稅，其免徵範圍係包括與該社團辦公有關之會議廳、圖\n      書室、廚房、員工食堂、浴室、廁所、值日室、檔案室、\n      貯藏室、議習室、值夜室、禮堂、文物儲藏室等房屋。」\n      及88年7 月29日台財稅字第881929562 號函：「依房屋稅\n      條例第15條第1 項第5 款規定，…又依同條項第4 款規定\n      ，私有房屋無償供政府機關公用之房屋，免徵房屋稅。本\n      案中國青年反共救國團所有××市青年育樂中心禮堂兼球\n      場房屋，除供該團××市團務指導委員會及各區團委會集\n      會活動使用外，為配合貴市推展各項活動，並提供青少年\n      良好活動場所，無償或酌收水電費提供貴市各級政府機關\n      、學校使用，應有上開2 條款免徵房屋稅規定之適用。至\n      該房屋偶有提供其他團體辦理臨時性之活動使用，但僅收\n      取水電費，亦准比照房屋稅條例第15條第1 項第5 款規定\n      ，免徵房屋稅。」等關於房屋稅條例第15條第1 項第5 款\n      所稱公益社團自有「供辦公使用」房屋之範圍所為之釋示\n      ，與該條款規範目的並無抵觸，亦非增加人民法律所無之\n      稅賦負擔，自得予援用。故揆諸上揭說明可知，非以營利\n      為目的之公益社團，其自有房屋除供自己辦公使用外，如\n      「偶而」「無償」或「酌收水電費」提供予政府機關、學\n      校或其他團體使用者，因偶一為之，非屬繼續、固定性之\n      對外提供使用；且其收取費僅用以支付水電費用，與提供\n      房屋供他人使用間亦無對價關係，仍屬無償提供使用，則\n      系爭自有房屋仍具備提供予公益社團自己辦公使用之公益\n      性質，依房屋稅條例第15條第1 項第5 款規定意旨，應准\n      免徵房屋。惟若公益社團將自有房屋出租予他人使用而收\n      取租金；或用以從事銷售貨物、勞務而收取代價之營利行\n      為，既非供公益社團自己辦公使用，自無上揭條款規定免\n      徵房屋稅之適用甚明。申言之，判斷公益社團之自有房屋\n      是否供自己辦公使用或用以營業及收取利益之營利行為，\n      應以該自有房屋之實際使用用途認定之，與該公益社團是\n      否非以營利為目的，係屬二事；亦與公益社團就取自該自\n      有房屋之收益如何處分或是否用於公益及辦理目的事業無\n      關，否則，房屋稅條例第15條第1 項第5 款關於公益社團\n      自有房屋給予免徵房屋稅之規定，何須在「不以營利為目\n      的，並經政府核准之公益社團」之要件外，再加以「供辦\n      公使用」之要件，原告將二者混為一談，主張其為非以營\n      利目的之公益財團法人，系爭房屋供世界宗教博物館使用\n      之門票收入及場地租金收入，既均用於公益及原告之設立\n      目的，世界宗教博物館收取門票及場地租金，即非以營利\n      為目的，並無營利行為云云，委無憑採。\n    4.再按，「在中華民國境內銷售貨物或勞務及進口貨物，均\n      應依本法規定課徵加值型或非加值型之營業稅。」「將貨\n      物之所有權移轉與他人，以取得代價者，為銷售貨物。提\n      供勞務予他人，或提供貨物與他人使用、收益，以取得代\n      價者，為銷售勞務。…」及「有左列情形之一者，為營業\n      人：一、以營利為目的之公營、私營或公私合營之事業。\n      二、非以營利為目的之事業、機關、團體、組織，有銷售\n      貨物或勞務者。……」加值型及非加值型營業稅法第1 條\n      、第3 條第1 項、第2 項及第6 條分別定有明文。查原告\n      所有如附表編號1-7 所示之7 戶房屋均係供「世界宗教博\n      物館」使用，並非供原告基金會辦公使用，此有原告所不\n      爭如附表所載上開7 戶房屋之使用情形可按，其中附表編\n      號2 之房屋於95年6 月28日設立洋瀧股份有限公司宗博館\n      門市部( 見原處分卷第152 頁) ，而上開該博物館除常設\n      展覽、兒童展覽對外收取門票及發行宗博之友會員卡收取\n      會員費外，館內亦設有禮品中心及咖啡廳，分別販賣文物\n      禮品、音樂、書籍及咖啡、花茶、茶點、簡餐等營利行為\n      ，亦有該館所印製之參觀指引及世界宗教博物館架設之網\n      站資料在卷可稽( 見原處分卷(一)第135-143 頁) 。又原告\n      為上開博物館出售門票之營業行為，於86年間增設附屬機\n      構「財團法人世界宗教博物館發展基金會附設臺北館」（\n      下稱原告附設臺北館），再以原告附設台北館之名義於89\n      年10月間辦理營業稅設籍登記迄今，亦有內政部86年4 月\n      2 日臺(86)內民字第8602392 號函及營業稅稅籍資料可稽\n      （見本院卷第152 、153 頁、原處分卷(一)第154 頁) ，而\n      經被告調得原告附設台北館96年至97年營業稅申報書資料\n      得知，該館96年申報之銷項總額為24,089,125元，進貨及\n      費用總金額之申報為13,548,885元；97年申報之銷項總額\n      截至97年4 月為7,796,976 元，進貨及費用總金額為1,79\n      5,392 元( 見本院卷第330-348 頁) ；且依本院命原告提\n      出該附設台北館於本件97年度房屋稅課稅期間( 即96年7\n      月至97年6 月) 關於銷貨收入之總分類帳顯示，以原告附\n      設台北館名義經營上開「世界宗教博物館」之各項銷貨收\n      入，包括門票、宗博之友會員卡、禮品店、祥瀧禮品店抽\n      成金、舉辦教育推廣及各項活動等收入( 見本院卷300-31\n      0 頁) ，並非如原告所稱該博物館只有門票收入，亦足證\n      「世界宗教博物館」係從事經常性、繼續性提供展覽、場\n      地與他人使用收益以收取代價；及販賣貨物予他人以收取\n      代價之營業行為，均屬有對價關係之有償行為，並非「供\n      辦公使用」之性質甚明，亦與財政部上揭88年7 月29日函\n      釋所指「偶而」「無償」「酌收水費」提供予政府機關、\n      學校或其他使用之情形不同；且營業本有盈虧，與其是否\n      為營利性質無關，原告執「世界宗教博物館」成立以來均\n      屬虧損，主張該博物館之門票及場地租金收入，屬僅酌收\n      水電用支出，並非營利行為云云，亦無足取。\n    5.又所謂營業，應不以門市交易為限，營利事業內部之工作\n      ，亦不能謂非營業之行為( 改制前行政法院57年判字第43\n      1 號判例參照) ，如附表編號4 之房屋係供世界宗教博物\n      館之辦公室使用；另編號6 、7 之2 戶房屋供該博物館放\n      置展覽用文物之儲藏室使用，均屬該博物館營運不可或缺\n      之一環，自屬提供世界宗教博物館使用之範圍，故被告以\n      如附表編號1-7 所示系爭房屋係供世界宗教博物館使用，\n      不符行為時房屋稅條例第15條第1 項第5 款規定之要件，\n      課徵該等房屋97年度房屋稅，於法並無違誤。原告未詳究\n      上引房屋稅條例第15條第1 項第5 款之規範目的及適用範\n      圍，亦未區辨「供辦公使用」及「供目的事業使用」之差\n      異，徒執其設立宗旨及在國內外籌設宗教博物館、展覽文\n      物為其目的事業，故附表編號1 、2 、3 、5 之房屋供世\n      界宗教博物館展覽區、特展區及兒童館展示使用，符合其\n      設立宗旨，即符合「供辦公使用」之要件；另附表編號6\n      、7 之房屋供該博物館放置展覽文物之儲藏室，即與財政\n      部上揭66年8 月15日函釋「與辦公有關之文物儲室」相符\n      ，應得免徵房屋稅云云，均無足取。\n  (二)關於原告主張適用文化藝術獎助條例第26條部分：\n    1.按「經文教主管機關核准設立之私立圖書館、博物館、藝\n      術館、美術館、民俗文物館、實驗劇場等場所免徵土地稅\n      及房屋稅。但以已辦妥財團法人登記或係辦妥登記之財團\n      法人興辦，且其用地及建築物為該財團法人所有者為限。\n      」為文化藝術獎助條例第26條所明定。由上開規定可知，\n      已辦妥財團法人登記或係辦妥登記之財團法人興辦之博物\n      館，尚須「經文教主管機關核准設立」，始得免徵房屋稅\n      ；否則，若不問是否「經文教主管機關核准設立」之博物\n      館，均得依行為時房屋稅條例第15條第1項第5款規定免徵\n      房屋稅，則文化藝術獎助條例第26條有關免徵房屋稅之規\n      定，不啻成為具文，此當非其立法本旨所在，合先敘明。\n    2.而依文建會98年1月9日文壹字第0983100593號函釋謂：「\n      …二、有關『文教主管機關』是否包含地方政府等其他機\n      關乙節，鑑於經文教主管機關核准設立之文化藝術事業場\n      所之種類及態樣繁多。爰此，文化藝術獎助條例第26條所\n      稱之『文教主管機關』，係指經營或從事文化藝術獎助條\n      例第2 條所列相關文化藝術事業之各該目的事業主管機關\n      ，合先敘明；另第26條所定免徵土地稅及房屋稅之場所，\n      除所列舉之私立圖書館、博物館、藝術館、美術館、民俗\n      文物館、實驗劇場等場所外，仍以辦妥財團法人登記或係\n      辦妥登記之財團法人興辦，且其用地及建築物為該財團法\n      人所有者為限。」可知，文化藝術獎助條例第26條之「文\n      教主管機關」，係指經營或從事該條例第2 條所列相關文\n      化藝術事業之各該目的事業主管機關而言，核該函釋乃文\n      建會本於文化藝術事業獎勵、補助之主管機關職權，對於\n      文化藝術獎助條例第26條規定所為之解釋，符合該條例「\n      為扶植文化藝術事業，輔導藝文活動，保障文化藝術工作\n      者，促進國家文化建設，提昇國民文化水準」之立法意旨\n      ，自得予援用。\n    3.復按，「本條例所稱文化藝術事業，係指經營或從事下列\n      事務者：……四、關於文化機構或從事文化藝術活動場所\n      之管理及興辦。……」及「本條例第2條第4款所稱文化機\n      構，係指依法令設立之下列機構：……二、博物館或美術\n      館。……」分別為文化藝術獎助條例第2條第4款及同條例\n      施行細則第4條第2款所明定。是以，須依「法令」合法設\n      立之博物館，方屬於文化藝術獎助條例第2條第4款所稱之\n      「文化機構」，而依社會教育法第5條第2款：「各級政府\n      視其財力與社會需要，得設立或依權責核准設立左列各社\n      會教育機構：……二、博物館或文物陳列室。」第6條：\n      「社會教育機構由中央設立者為國立；……；由私人或團\n      體設立者為私立。」第7 條：「社會教育機構之設立、變\n      更或停辦：國立者，應由教育部審查全國情形決定之；…\n      …縣( 市) 立、鄉( 鎮、市、區) 立及私立者，應報請縣\n       (市) 政府或直轄市主管教育行政機關核准，並轉報教育\n      部備案。」第8 條：「私立社會教育機構應依前條規定核\n      准立案並辦理財團法人登記；其設立、變更、停辦、督導\n      、獎勵及其他應遵行事項之辦法，由教育部定之。」暨私\n      立社會教育機構設立及獎勵辦法第1 條：「本辦法依社會\n      教育法第8 條規定訂定之。」第3 條第2 款：「私立社會\n      教育機構種類如下：…二、博物館或文物陳列室。」第8\n      條：「私立社會教育機構得由私人或團體創辦，或經各級\n      主管教育行政機關許可設立之財團法人附設。」第9 條：\n      「設立私立社會教育機構，應由創辦人或所屬之財團法人\n      以申請書載明下列事項，並檢具有關證明文件，連同捐助\n      章程或遺囑影本，向直轄市主管教育行政機關或縣( 市)\n      政府申請籌設。……」第10條：「私立社會教育機構應設\n      董事會，但財團法人附設者，得不另設董事會。」第17條\n      ：「董事會經報准核備後，應於30日內辦理財團法人登記\n      ，逾期不辦理者，依第9 條之核准失其效力。…」第18條\n      ：私立社會教育機構於完成財團法人設立登記並領得財團\n      法人登記證書後，應由董事會於一年內開具第9 條所列事\n      項及有關文件，向直轄市主管教育行政機關或縣( 市) 政\n      府申請立案。凡經核准立案之私立社會教育機構，直轄市\n      主管教育行政機關或縣（市) 政府應轉報教育部備查。」\n      第19條：「私立社會教育機構經直轄市主管教育行政機關\n      或縣( 市) 政府核准立案後，始得開辦。」第20條：「財\n      團法人附設社會教育機構，得……依第9 條規定向直轄市\n      主管教育行政機關或縣( 市) 政府申請核准立案後開辦。\n      」「私立社會教育機構受直轄市主管教育行政機關或縣(\n      市) 政府之監督及輔導，其一切教育措施及其他事項應依\n      有關法令辦理。」等規定可知，博物館不僅為文化機構，\n      亦屬於社會教育機構，私立博物館之設立，如由私人或團\n      體設立者，應向直轄市主管教育行政機關或縣( 市) 政府\n      申請核准立案，並辦理財團法人登記，方得開辦；如由財\n      團法人附設私立博物館，亦須為主管教育行政機關許可設\n      立之財團法人始得申請之，並由直轄市主管教育行政機關\n      或縣( 市) 政府執行私立博物館之監督及輔導。足見，無\n      論是文化藝術獎助條例第26條所定「經文教主管機關核准\n      設立之博物館」，其所稱之「文教機關」；或依文建會上\n      開函釋所稱經營同條例第2 條第4 款所列博物館( 文化機\n      構) 之文化藝術事業之「目的事業主管機關」，依現行有\n      效之上揭法令規定，均係指直轄市主管教育行政機關或縣\n       (市) 政府等地方主管教育行政機關甚明。\n    4.惟查，原告係以從事宗教業務及服務為目的之宗教團體，\n      向內政部申請許可設立之宗教財團法人，其名稱為「財團\n      法人世界宗教博物館發展基金會」，設立宗旨為「一、重\n      建尊重、包容、博愛的社會、闡揚生命的智慧與健康的人\n      生觀。二、提昇華人社會的國際形象與地位。三、推展宗\n      教交流，促進世界和平。四、保護人類的宗教智慧與資產\n      。」此有原告經臺灣板橋地方法院登記處核發之法人登記\n      證書內容可稽( 見本院卷第146 頁) ，並非經主管教育行\n      政機關許可設立之財團法人，而原告之捐助及組織章程第\n      4 條第1 款規定：「本法人依有關法令規定辦理左列業務\n      ：「(一)籌設世界宗教博物館及國內外分館。……」( 見本\n      院卷第148 頁) ，亦係原告本於宗教財團法人所從事之目\n      的事業，仍屬於宗教業務之範圍；縱原告興辦之「世界宗\n      教博物館」已實質具備「博物館」之內涵，依上引社會教\n      育法暨私立社會教育機構設立及獎勵辦法之規定，亦應向\n      地方主管教育行政機關申請核准設立，方符合文化藝術獎\n      助條例第26條所稱「經文教主管核准設立」及同條例施行\n      細則第4 條第2 款規定「依法令設立」之要件，該博物館\n      始能謂屬於同條例第2 條第4 款所列文化機構( 博物館)\n      之文化藝術事業；況且，內政部以83年3 月22日台83內民\n      字第8301721 號函准予原告設立宗教財團法人，已於該函\n      說明欄載明：「…三、另依教育部82年12月22日(82)社字\n      第071180號函，該基金會設立後，若欲推展『博物館」業\n      務，須依『私立社會教育機構設立及獎勵辦法』辦理。」\n       (見原處分卷(一)第189 頁) ，原告亦不得諉為不知；然原\n      告卻係以附設機構台北館名義辦理營業登記而經營上開「\n      世界宗教博物館」，明顯與上揭法令規定不符。原告未細\n      究相關法令規定及文建會上開函釋意旨，徒言其為經目的\n      事業主管機關內政部核准設立之公益財團法人，其興辦之\n      「世界宗教博物館」亦為文化藝術獎助條例第2 條第4 款\n      之文化藝術事業，即符合該條例第26條「經文教主管機關\n      核准設立」之規定，其所有供該博物館使用之系爭房屋，\n      自得依該規定免徵房屋稅云云，委無足取。\n六、綜上所述，原告之主張，均無足採。被告對於原告所有如附\n    表編號1-7 等7 戶房屋所為課徵97年度房屋稅之處分，於法\n    並無違誤，訴願決定予以維持，亦無不合。原告訴請撤銷，\n    為無理由，應予駁回。\n七、據上論結，本件原告之訴為無理由，依行政訴訟法第98條第\n    1 項前段，判決如主文。",
    "reason": "一、程序事項：本件原告起訴時，被告之代表人為黃毓彥，嗣於\n    訴訟中變更為乙○○，茲據新任代表人具狀聲明承受訴訟，\n    經核無不合，應予准許。\n二、事實概要：原告所有如附表所示門牌號碼臺北縣永和市○○\n    路○段236號6樓、7樓、永和市○○路2號6樓、永和市○○路\n    22巷12號6 樓、7 樓、中和市○○路○ 段344 號5 樓、中和\n    市○○路○ 段346 號5 樓、永和市○○路2 號7 樓等8 戶房\n    屋，經被告所屬中和分處於97年間派員至現場勘查結果，因\n    認上開房屋之使用情形，或供世界宗教博物館使用，或供道\n    饗養生蔬膳餐廳等營業使用，不符免徵房屋稅事由，乃對原\n    告發單課徵上開8 戶房屋之97年度房屋稅總計為新臺幣( 下\n    同)2,532,063 元 。原告不服，申請復查未獲變更，提起訴\n    願亦經決定駁回後，原告就被告對附表編號1-7 等7 戶房屋\n     (下稱系爭房屋) 課徵房屋稅之處分仍不服，遂提起本件行\n    政訴訟。\n三、本件原告主張：\n    (一)按文建會98年1月9日文壹字第0983100593號函釋規定，如\n      屬從事文化藝術獎助條例第2 條所稱文化藝術事業者，則\n      該從事者只要經其目的事業主管機關核准設立，即得適用\n      免徵房屋稅之租稅優惠。查原告興辦之「世界宗教博物館\n      」，為依該條例第2 條及同條例施行細則第4 條規定之文\n      化藝術事業；且自開館以來，即長期與臺北縣文化局、教\n      育部或文建會等互動頻繁，並多次參與文建會推動之計劃\n      ，確為有興辦博物館之文化機構，核與上開獎助條例所稱\n      「文化藝術事業」之內涵相符。而原告亦經目的事業主管\n      機關內政部核准設立之公益性財團法人，並有法人登記證\n      書，故依上開函釋意旨，原告符合上開獎助條例第26條「\n      經文教主管機關核准設立」規定，自得免徵房屋稅甚明。\n    (二)原告為不以營利為目的之公益社團，自有房屋稅條例第15\n      條第1項第5款規定之適用：\n      1.依財政部 87年6月8日臺財稅字第871947996號函釋及財\n        政部88年5 月1 日臺財稅字第881912937 號函意旨，房\n        屋稅條例第15條第1 項第5 款所指之「公益社團」，其\n        重點應在私有房屋是否供「公益使用」，殊不因該公益\n        性團體為社團或財團本質上即有不同。被告雖援引臺灣\n        省稅務局69.1.30 稅三字第19336 號函：「…本案○○\n        高爾夫俱樂部雖屬財團法人組織，並非屬房屋稅條例所\n        稱之『公益社團』，其供辦公使用房屋應無首揭法條免\n        徵房屋稅之適用。」之內容，稱財團法人組織非屬房屋\n        稅條例所稱「公益社團」云云。惟上開函釋係指稱該案\n        之稅捐主體並不具公益性，故雖屬財團法人組織，仍無\n        上開條例第15條第1 項第5 款之適用，並未認公益性之\n        財團法人不得適用房屋稅條例，被告顯有誤解，不值採\n        信。\n      2.而自原告法人登記證書、目的事業主管機關內政部之核\n        准設立函，及內政部93年10月28日內授中民字第093000\n        8261號函覆原告：「…貴法人係經本部許可設立登記有\n        案之宗教財團法人基金會，依章程其設立目的…確為促\n        進公眾利益成立之宗教財團法人。」皆足證原告係非以\n        營利為目的，而為促進公眾利益所設立之財團法人；且\n        所從事「籌設世界宗教博物館及國內外分館」、「興辦\n        宗教與生活之教育活動」及「興辦國內外各項宗教圖書\n        與資訊服務」，亦為達成其目的所須「非以營利為目的\n        」之活動；再依原告章程第23條規定，原告解散時財產\n        歸屬法人所在地之地方自治團體所有，非歸屬私人，益\n        證原告為非以營利為目的之財團法人，殆無疑義。\n      3.查系爭房屋所有人為原告，僅原告為納稅義務人，是房\n        屋稅條例第15條第1項第5款所定之公益社團，應就原告\n        之性質認定，方符房屋稅之課徵要件。詎被告以原告附\n        設機構「財團法人世界宗教博物館發展基金會附設臺北\n        館」有設稅籍及繳納營業稅，即認定該附設機構係以營\n        利為目的，進而否定系爭房屋得免徵房屋稅云云。惟查\n        ，原告附設台北館無法人格，並無得以獨立名義對外興\n        辦博物館、推廣宗教活動及對系爭房屋使用收益之可能\n        。房屋稅條例既規定納稅義務人為原告，即應就原告之\n        性質判斷方屬正確。原告既屬非以營利為目的之公益性\n        財團法人，所從事者皆為非營利為目的之活動，應得適\n        用房屋稅條例第15條第1項第5款規定無疑。\n      4.原告雖於86年間因興辦宗教博物館，有銷售貨物或勞務\n        之營業行為，乃由附設機構為營業登記。然依營業稅法\n        第2 條及第6 條第2 項規定可知，營業人非當然以營利\n        為目的，且營業稅之納稅義務人，容許同一人因其總機\n        構與分支機構不同而分別登記( 營業稅法第28條規定參\n        照)， 原告方得以附設機構單獨登記為營業人，惟營業\n        稅法與房屋稅條例之規範迥異，房屋稅條例規定之納稅\n        義務人，僅為所有人，並無就所有人及其附設機構分別\n        認定之可能，被告恣意割裂就原告及附設機構分別認定\n        性質，進而主張系爭房屋無房屋稅條例第15條第1 項第\n        5 款規定之適用，顯有認事用法之錯誤。\n      5.再按財政部88年7月29日臺財稅字第881929562號函釋意\n        ，原告之門票收入及租金收入，係屬酌收水電費用性質\n        ，並無營利性質。查附表項次1 、2 、3 之三戶房屋係\n        供世界宗教博物館展覽區使用，項次5 供兒童館展示使\n        用，雖有門票收入，惟該項收入僅供支付系爭房屋之電\n        費支出，總計該7 戶房屋97課稅年度之電費支出為4,07\n        0,521 元與門票收入2,932,497 元相較，尚不足1,138,\n        024 元，足見原告主要經費來源均仰賴大眾捐助，足見\n        原告主要經費來源均仰賴大眾捐助，酌收門票僅係酌收\n        水電茶水費用，非以營利為目的甚明。況該三戶房屋從\n        95年10月起，已無再提供場地租借服務，遑論當初原告\n        酌收費用僅係用以支應茶水、水電等費用，總計從94年\n        7 月至95年6 月僅4 萬餘元，即使將此場地租借費用計\n        入，原告仍舊入不敷出，何來具有營利目的可言？\n      6.再者，原告之性質係為財團法人，原告所有之盈餘均係\n        供維持會務運作所使用，縱原告如有收益多於支出之情\n        況（假設語，原告否認之），日後若依法解散時，依照\n        原告章程第23條規定，賸餘財產係歸於原告事務所所在\n        地之地方自治團體，而非歸於個人或私人企業，故原告\n        附屬機構世界宗教博物館雖有門票、場地費等收入，仍\n        與以營利為目的不同，其理甚明。\n    (三)系爭房屋皆屬供原告辦公使用之房屋，符合房屋稅條例第\n      15條第1項第5款「私有房屋供自有辦公室使用」之要件：\n      1.按財政部66.8.15臺財稅字第35449號函釋，上開條例規\n        定「供辦公室使用之房屋」，包含會議室、貯藏室、講\n        習室及文物儲藏室；另財政部60.9.23臺財稅字第37570\n        號函釋亦闡明供辦公使用之房屋，其認定標準，係就該\n        社團自有房屋之用途，在供其推廣公益業務或活動，核\n        實認定為「供辦公使用」之房屋，並免徵房屋稅即明。\n      2.查附表1、2之兩戶房屋，主要供世界宗教博物館展覽使\n        用，與原告設立之宗旨相符，符合上揭60年函釋意旨；\n        另項次3 之房屋主要供該博物館特展區展覽，並兼作講\n        習室使用；兼作講習室部份，亦與上揭66年函釋意旨相\n        符，均符合「自有供辦公使用」之要件，應得免稅。又\n        前述三戶房屋有部分面積曾對外提供作會議、教學之臨\n        時性活動用途並酌收場地費，然該部分面積於平時無外\n        借時，亦為原告內部舉辦會議之會議室，依上揭66年函\n        釋意旨，符合「自有供辦公室使用」要件，端不能僅憑\n        原告曾在網頁上列出場地費之標準，即認定該房屋作為\n        經常性租借用途，不可不辨。\n      3.附表項次4 之房屋係作辦公室使用，雖被告認係原告附\n        設機構使用，惟不應割裂原告及附設機構分別認定已如\n        前述，該房屋應得免稅甚明。另項次5 之房屋於94年2\n        月起則供世界宗教博物館兒童館展示使用，該部分期間\n        供展覽使用，依上揭60年函釋意旨，亦符合自有供辦公\n        使用之要件。另附表項次6 、7 兩戶房屋係供放置展覽\n        用文物之「文物儲藏室」使用，與上揭66年函釋「與辦\n        公有關之文物儲藏室」之意旨相符，雖被告認係供原告\n        附設機構使用，惟不應割裂原告及附設機構分別認定已\n        如前述，該房屋應得免稅甚明。\n    (四)又被告所提最高行政法院99年度判字第66號判決，原告已\n      於法定期間內提起再審之訴，更擬針對該判決所適用之法\n      規提起大法官解釋，以茲救濟，故該判決見解尚非的論等\n      語。並聲明請求判決訴願決定、原處分（含復查決定）關\n      於課徵房屋稅額超過263,139部分均撤銷。\n四、被告則以：\n    (一)按房屋稅條例第15條第1項第5款規定之適用，就免徵房屋\n      稅之主體而言，財政部87.6.8臺財稅字第871947996 號函\n      雖認為該「公益社團」包括財團法人及社團法人，惟依臺\n      灣省稅務局上揭69年函釋卻指出財團法人組織，並非屬房\n      屋稅條例所稱之「公益社團」；再就免徵房屋稅客體之用\n      途而言，所謂「供辦公使用」者，依財政部60年11月9 日\n      臺財稅字第38743 號令，房屋如用為營業非屬「供辦公使\n      用；另參諸財政部88年7 月29日臺財稅字第881929562 號\n      函釋，顯見公益社團所有之房屋，原則上供自己辦公使用\n      ，兼而提供各級政府機關、學校使用或偶有提供其他團體\n      辦理臨時性之活動使用而酌收或僅收取水電費者，亦得認\n      定為「供辦公使用」，此合先敘明。\n    (二)查系爭房屋前經被告所屬中和分處於93年4 月間及97年間\n      派員至現場勘查，其使用情形或供世界宗教博物館使用，\n      或供餐廳等營業使用，均非供原告自己辦公使用或供與其\n      辦公有關之會議廳等用途使用，此會勘結果為原告所不爭\n      ，核與前揭房屋稅條例第15條第1 項第5 款規定及上開函\n      釋規定不符，自無免徵房屋稅之適用。又系爭房屋為原告\n      所興辦之博物館使用。該博物館之正確名稱係「財團法人\n      世界宗教博物館發展基金會附設臺北館」，乃原告於86年\n      間增設之附屬機構，並於89年10月間辦理營業稅設籍登記\n      迄今；系爭博物館經營博物館業務，對外收取門票，經查\n      調其96年至97年營業稅申報書資料得知，該館96年申報銷\n      項總額為24,089,125元，進貨及費用總金額申報為13,548\n      ,885元；97年申報之銷項總額截至97年4 月為7,796,976\n      元，進貨及費用總金額為1,795,392 元，足證原告經營博\n      物館業務係屬常態性營業行為，此有原告96年至97年營業\n      稅課稅資料可稽，又原告93及94年房屋稅上訴審99年度判\n      字第66號判決理由五(二)載明：「揆諸…營業稅法第1 條：\n      …之規定可知，被上訴人興辦之世界宗教博物館為加值型\n      及非加值型營業稅法之營業人，必須繳納營業稅，其非屬\n      免徵營業稅範圍，因此被上訴人興辦之世界宗教博物館所\n      使用之系爭房屋尚非屬『不以營利為目的』，即不符行為\n      時房屋稅條例第15條第1 項第5 款免徵房屋稅之法定要件\n      ，…」是以，原告以其所有系爭房屋作博物館使用，其使\n      用情形乃原告設立營業稅籍從事包括販賣門票、場地租借\n      等常態性營業行為，依上揭60年11月9 日臺財稅字第3874\n      3 號令及改制前行政法院57年判字第431 號判例意旨，顯\n      非屬「供辦公使用」自明，是原告之主張尚難採憑。\n    (三)而有關已辦妥財團法人登記或其興辦之博物館，其房屋為\n      該財團法人所有者，該財團法人得否享受免徵房屋稅之租\n      稅優惠，其所應具備之要件，文化藝術獎助條例第26條定\n      有明文；而經調閱該條文之立法紀錄可知，該條文係於逐\n      條討論時，由立法委員提議修正為：「免徵房屋稅及土地\n      稅」，經核其立法過程既有財政部代表參與，其與房屋稅\n      條例第15條第1 項規定間當無疊床架屋之情形發生，亦即\n      文化藝術獎助條例第26條制定當時，倘已辦妥財團法人登\n      記或其興辦之博物館收取門票經營博物館業務使用之自有\n      房屋，符合房屋稅條例第15條第1 項第5 款規定，即得依\n      該規定免徵房屋稅，而收獎勵文化事業之實效，實毋須考\n      量該等財團法人興辦博物館等，雖有營業行為，然「光靠\n      門票收入，根本不敷所需」之問題，再於上開獎助條例中\n      增設免徵房屋稅之規定，顯然已辦妥財團法人登記或其所\n      興辦博物館使用之自有房屋，並不屬於行為時房屋稅條例\n      第15條第1 項第5 款規定所規範之情形，如此，文化獎助\n      條例第26條之規定，始不致成為具文。\n    (四)復查，系爭房屋稅之核課，被告均核定原告為納稅義務人\n      並非以系爭博物館為納稅義務人，再者，依房屋稅條例第\n      15條第1項第5款規定，享受免徵房屋稅之租稅優惠者，以\n      自有房屋「供辦公使用」為限，被告就原告之系爭房屋供\n      作系爭博物館使用之情形，認定是否合致上開條款所定「\n      供辦公使用」之要件，乃適用該條款規定之當然，原告所\n      謂將「基金會」與「博物館」割裂為兩個獨立之個體，而\n      各自承擔權利義務云云，顯與事實不符，並不可採。至原\n      告主張酌收費用僅係用以支應茶水、水電等費用一節，依\n      財政部85.7.5臺財稅字第851116753 號函規定，係指因提\n      供設施或服務而酌收之必要費用，須經目的事業主管機關\n      出具證明，其收費非以營利為目的且其不違反其設立之宗\n      旨目的，惟原告迄未提示，經其目的事業主管機關證明其\n      收費非以營利為目的且不違反其設立宗旨之相關文件，被\n      告自無從認定其屬慈善救濟事業，而有該函釋之適用。\n    (五)原告雖主張依營業稅法第6條第2款規定，營業人非當然以\n      營利為目的一節。查系爭博物館銷售書籍、販賣導覽手冊\n      、書法筆記書、收取租金、發行會員卡、設立咖啡廳及餐\n      廳、出售門票等營利行為，依宗教團體免辦理所得稅結算\n      申報認定要點及教育文化公益慈善機關或團體免納所得稅\n      適用標準及財政部78年6 月6 日臺財稅字第780649615 號\n      函釋規定，該等收入屬銷售貨物或勞務收入。則系爭博物\n      館既為原告之附屬作業組織，並有銷售貨物及勞務之收入\n      ，自無不符免辦理所得稅結算申報規定，原告亦依規定辦\n      理所得稅結算申報。顯見辦理營業登記課徵營業稅一事，\n      彰顯原告確有營利之行為及目的。原告雖不斷強調「利潤\n      」是判斷營利行為之重要指標云云，惟查組織機構賺錢與\n      否，需視其營運團隊之經營方針。以系爭博物館之課稅資\n      料來看，除禪一股份有限公司等之租金收入為大筆營運收\n      入外，其餘皆為零星的營運收入，不能因原告經營虧損，\n      即認定其無營利之事實。綜觀原告之經營營業組織策略，\n      實已具備營利之行為及目的等語置辯。並聲明求為判決駁\n      回原告之訴。\n五、本院判斷如下：\n  (一)關於原告主張適用房屋稅條例第15條第1項第5款部分：\n    1.按「房屋稅之徵收，依本條例之規定；本條例未規定者，\n      依其他有關法律之規定。」「房屋稅向房屋所有人徵收之\n      。……」「房屋稅依房屋現值，按左列稅率課徵之：……\n      二、非住家用房屋，其為營業用者，最低不得少於其房屋\n      現值3%，最高不得超過5%。其為私人醫院、診所、自由職\n      業事務所及人民團體等非營業用者，最低不得少於其房屋\n      現值1. 5% 」「私有房屋有左列情形之一者，免徵房屋稅\n      ：…5.不以營利為目的，並經政府核准之公益社團自有供\n      辦公使用之房屋。但以同業、同鄉、同學或宗親社團為受\n      益對象者，不在此限。…」行為時房屋稅條例第1 條、第\n      4 條第1 項前段、第5 條第2 款及第15條第1 項第5 款分\n      別定有明文。\n    2.次按，「憲法第19條規定『人民有依法律納稅之義務』，\n      係指人民有依法律所定要件負繳納稅捐之義務或享減免繳\n      納之優惠而言。」業經司法院釋字第369號及第496號解釋\n      揭櫫甚明。故上引行為時房屋稅條例第15條第1項第5款免\n      徵房屋稅規定之適用，其要件為：(1)經政府核准之公益社\n      團之自有房屋。(2)該公益社團非以營利為目的。(3)該公益\n      社團不得以同業、同鄉、同學或宗親社團為受益對象。(4)\n      該公益社團自有之房屋，其用途須供辦公使用，並須同時\n      具備上述四項要件，始得享有免徵房屋稅之租稅優惠。財\n      政部87年6 月8 日台財稅字第871947996 號函略以：「…\n      依房屋稅條例第15條第1 項第5 款規定，…本案財團法人\n      ＯＯ文教基金會，如係以公益為的目之社團（包括財團法\n      人組織及社團法人組織），其自有供基金會及其台中、台\n      南、高雄三地區分會辦公使用之房屋，准依上開條款規定\n      ，免徵房屋稅。」乃該部本於中央稅捐稽徵主管機關職權\n      ，就上引房屋稅條例第15條第1 項第5 款「公益社團」之\n      範圍所為之釋示，經核與該法條規範意旨無違，自得予援\n      用。因此，房屋稅條例第15條第1 項第5 款規定免徵房屋\n      稅之主體，包括社團法人組織及財團法人組織均屬之；況\n      被告就原告自有供其基金會辦公室使用之門牌號碼臺北縣\n      永和市○○路22巷8 號6 樓房屋，亦依上開條款規定准予\n      自93年5 月起免徵房屋稅在案，被告於本件訴訟中，卻改\n      稱原告為財團法人組織，非屬上開條款規定之「公益社團\n      」，並無該條款免徵所得稅之適用云云，洵無足採。\n    3.復按，上引房屋稅條例第15條第1項第5款係房屋稅條例於\n      59年7月8日修正增訂之規定，旨在於公益社團之自有房屋\n      多半供公益使用，乃明定對於公益社團自有「供辦公使用\n      」之房屋，給予免徵房屋稅之租稅優惠。另對照同法條同\n      項第2 款關於「業經立案之私立慈善救濟事業，……，其\n      『直接供辦理事業所使用』之房屋。」免徵房屋稅之規定\n      ，於59年7 月8 日修正前原規定：「業經立案之私立慈善\n      救濟事業，……其『供辦公使用』之房屋。」及參酌其修\n      正立法理由以：「慈善救濟事業房屋之免稅，應包括直接\n      供辦理事業所使用之一切房屋，如養老院、救濟院等，不\n      能單以辦公房屋為限，故予以修正。」可知，公益社團所\n      有房屋免徵房屋稅，依上引房屋稅條例第15條第1 項第5\n      款規定，應以其自有「供辦公使用」之房屋為限；至該公\n      益社團自有「供辦理事業使用」之房屋，既非屬「供辦公\n      使用」，自不得依該條款規定免徵房屋甚明。財政部60年\n      11月9 日台財稅字第38743 號函略以：「房屋稅條例第15\n      條第1項 第5 款所指之：『不以營利為目的，並經政府核\n      准之公益社團自有供辦公使用之房屋』免徵房屋稅，應以\n      經由主管目的事業機關核准登記有案之公益社團自有房屋\n      供作辦公使用者為準，如其房屋用為營業或供收益使用，\n      或該社團為謀社員經濟上之利益，而將所得利益分配於社\n      員者，均不在此限。」66年8 月15日台財稅字第35449 號\n      函：「查房屋稅條例第15條第1 項第5 款規定……免徵房\n      屋稅，其免徵範圍係包括與該社團辦公有關之會議廳、圖\n      書室、廚房、員工食堂、浴室、廁所、值日室、檔案室、\n      貯藏室、議習室、值夜室、禮堂、文物儲藏室等房屋。」\n      及88年7 月29日台財稅字第881929562 號函：「依房屋稅\n      條例第15條第1 項第5 款規定，…又依同條項第4 款規定\n      ，私有房屋無償供政府機關公用之房屋，免徵房屋稅。本\n      案中國青年反共救國團所有××市青年育樂中心禮堂兼球\n      場房屋，除供該團××市團務指導委員會及各區團委會集\n      會活動使用外，為配合貴市推展各項活動，並提供青少年\n      良好活動場所，無償或酌收水電費提供貴市各級政府機關\n      、學校使用，應有上開2 條款免徵房屋稅規定之適用。至\n      該房屋偶有提供其他團體辦理臨時性之活動使用，但僅收\n      取水電費，亦准比照房屋稅條例第15條第1 項第5 款規定\n      ，免徵房屋稅。」等關於房屋稅條例第15條第1 項第5 款\n      所稱公益社團自有「供辦公使用」房屋之範圍所為之釋示\n      ，與該條款規範目的並無抵觸，亦非增加人民法律所無之\n      稅賦負擔，自得予援用。故揆諸上揭說明可知，非以營利\n      為目的之公益社團，其自有房屋除供自己辦公使用外，如\n      「偶而」「無償」或「酌收水電費」提供予政府機關、學\n      校或其他團體使用者，因偶一為之，非屬繼續、固定性之\n      對外提供使用；且其收取費僅用以支付水電費用，與提供\n      房屋供他人使用間亦無對價關係，仍屬無償提供使用，則\n      系爭自有房屋仍具備提供予公益社團自己辦公使用之公益\n      性質，依房屋稅條例第15條第1 項第5 款規定意旨，應准\n      免徵房屋。惟若公益社團將自有房屋出租予他人使用而收\n      取租金；或用以從事銷售貨物、勞務而收取代價之營利行\n      為，既非供公益社團自己辦公使用，自無上揭條款規定免\n      徵房屋稅之適用甚明。申言之，判斷公益社團之自有房屋\n      是否供自己辦公使用或用以營業及收取利益之營利行為，\n      應以該自有房屋之實際使用用途認定之，與該公益社團是\n      否非以營利為目的，係屬二事；亦與公益社團就取自該自\n      有房屋之收益如何處分或是否用於公益及辦理目的事業無\n      關，否則，房屋稅條例第15條第1 項第5 款關於公益社團\n      自有房屋給予免徵房屋稅之規定，何須在「不以營利為目\n      的，並經政府核准之公益社團」之要件外，再加以「供辦\n      公使用」之要件，原告將二者混為一談，主張其為非以營\n      利目的之公益財團法人，系爭房屋供世界宗教博物館使用\n      之門票收入及場地租金收入，既均用於公益及原告之設立\n      目的，世界宗教博物館收取門票及場地租金，即非以營利\n      為目的，並無營利行為云云，委無憑採。\n    4.再按，「在中華民國境內銷售貨物或勞務及進口貨物，均\n      應依本法規定課徵加值型或非加值型之營業稅。」「將貨\n      物之所有權移轉與他人，以取得代價者，為銷售貨物。提\n      供勞務予他人，或提供貨物與他人使用、收益，以取得代\n      價者，為銷售勞務。…」及「有左列情形之一者，為營業\n      人：一、以營利為目的之公營、私營或公私合營之事業。\n      二、非以營利為目的之事業、機關、團體、組織，有銷售\n      貨物或勞務者。……」加值型及非加值型營業稅法第1 條\n      、第3 條第1 項、第2 項及第6 條分別定有明文。查原告\n      所有如附表編號1-7 所示之7 戶房屋均係供「世界宗教博\n      物館」使用，並非供原告基金會辦公使用，此有原告所不\n      爭如附表所載上開7 戶房屋之使用情形可按，其中附表編\n      號2 之房屋於95年6 月28日設立洋瀧股份有限公司宗博館\n      門市部( 見原處分卷第152 頁) ，而上開該博物館除常設\n      展覽、兒童展覽對外收取門票及發行宗博之友會員卡收取\n      會員費外，館內亦設有禮品中心及咖啡廳，分別販賣文物\n      禮品、音樂、書籍及咖啡、花茶、茶點、簡餐等營利行為\n      ，亦有該館所印製之參觀指引及世界宗教博物館架設之網\n      站資料在卷可稽( 見原處分卷(一)第135-143 頁) 。又原告\n      為上開博物館出售門票之營業行為，於86年間增設附屬機\n      構「財團法人世界宗教博物館發展基金會附設臺北館」（\n      下稱原告附設臺北館），再以原告附設台北館之名義於89\n      年10月間辦理營業稅設籍登記迄今，亦有內政部86年4 月\n      2 日臺(86)內民字第8602392 號函及營業稅稅籍資料可稽\n      （見本院卷第152 、153 頁、原處分卷(一)第154 頁) ，而\n      經被告調得原告附設台北館96年至97年營業稅申報書資料\n      得知，該館96年申報之銷項總額為24,089,125元，進貨及\n      費用總金額之申報為13,548,885元；97年申報之銷項總額\n      截至97年4 月為7,796,976 元，進貨及費用總金額為1,79\n      5,392 元( 見本院卷第330-348 頁) ；且依本院命原告提\n      出該附設台北館於本件97年度房屋稅課稅期間( 即96年7\n      月至97年6 月) 關於銷貨收入之總分類帳顯示，以原告附\n      設台北館名義經營上開「世界宗教博物館」之各項銷貨收\n      入，包括門票、宗博之友會員卡、禮品店、祥瀧禮品店抽\n      成金、舉辦教育推廣及各項活動等收入( 見本院卷300-31\n      0 頁) ，並非如原告所稱該博物館只有門票收入，亦足證\n      「世界宗教博物館」係從事經常性、繼續性提供展覽、場\n      地與他人使用收益以收取代價；及販賣貨物予他人以收取\n      代價之營業行為，均屬有對價關係之有償行為，並非「供\n      辦公使用」之性質甚明，亦與財政部上揭88年7 月29日函\n      釋所指「偶而」「無償」「酌收水費」提供予政府機關、\n      學校或其他使用之情形不同；且營業本有盈虧，與其是否\n      為營利性質無關，原告執「世界宗教博物館」成立以來均\n      屬虧損，主張該博物館之門票及場地租金收入，屬僅酌收\n      水電用支出，並非營利行為云云，亦無足取。\n    5.又所謂營業，應不以門市交易為限，營利事業內部之工作\n      ，亦不能謂非營業之行為( 改制前行政法院57年判字第43\n      1 號判例參照) ，如附表編號4 之房屋係供世界宗教博物\n      館之辦公室使用；另編號6 、7 之2 戶房屋供該博物館放\n      置展覽用文物之儲藏室使用，均屬該博物館營運不可或缺\n      之一環，自屬提供世界宗教博物館使用之範圍，故被告以\n      如附表編號1-7 所示系爭房屋係供世界宗教博物館使用，\n      不符行為時房屋稅條例第15條第1 項第5 款規定之要件，\n      課徵該等房屋97年度房屋稅，於法並無違誤。原告未詳究\n      上引房屋稅條例第15條第1 項第5 款之規範目的及適用範\n      圍，亦未區辨「供辦公使用」及「供目的事業使用」之差\n      異，徒執其設立宗旨及在國內外籌設宗教博物館、展覽文\n      物為其目的事業，故附表編號1 、2 、3 、5 之房屋供世\n      界宗教博物館展覽區、特展區及兒童館展示使用，符合其\n      設立宗旨，即符合「供辦公使用」之要件；另附表編號6\n      、7 之房屋供該博物館放置展覽文物之儲藏室，即與財政\n      部上揭66年8 月15日函釋「與辦公有關之文物儲室」相符\n      ，應得免徵房屋稅云云，均無足取。\n  (二)關於原告主張適用文化藝術獎助條例第26條部分：\n    1.按「經文教主管機關核准設立之私立圖書館、博物館、藝\n      術館、美術館、民俗文物館、實驗劇場等場所免徵土地稅\n      及房屋稅。但以已辦妥財團法人登記或係辦妥登記之財團\n      法人興辦，且其用地及建築物為該財團法人所有者為限。\n      」為文化藝術獎助條例第26條所明定。由上開規定可知，\n      已辦妥財團法人登記或係辦妥登記之財團法人興辦之博物\n      館，尚須「經文教主管機關核准設立」，始得免徵房屋稅\n      ；否則，若不問是否「經文教主管機關核准設立」之博物\n      館，均得依行為時房屋稅條例第15條第1項第5款規定免徵\n      房屋稅，則文化藝術獎助條例第26條有關免徵房屋稅之規\n      定，不啻成為具文，此當非其立法本旨所在，合先敘明。\n    2.而依文建會98年1月9日文壹字第0983100593號函釋謂：「\n      …二、有關『文教主管機關』是否包含地方政府等其他機\n      關乙節，鑑於經文教主管機關核准設立之文化藝術事業場\n      所之種類及態樣繁多。爰此，文化藝術獎助條例第26條所\n      稱之『文教主管機關』，係指經營或從事文化藝術獎助條\n      例第2 條所列相關文化藝術事業之各該目的事業主管機關\n      ，合先敘明；另第26條所定免徵土地稅及房屋稅之場所，\n      除所列舉之私立圖書館、博物館、藝術館、美術館、民俗\n      文物館、實驗劇場等場所外，仍以辦妥財團法人登記或係\n      辦妥登記之財團法人興辦，且其用地及建築物為該財團法\n      人所有者為限。」可知，文化藝術獎助條例第26條之「文\n      教主管機關」，係指經營或從事該條例第2 條所列相關文\n      化藝術事業之各該目的事業主管機關而言，核該函釋乃文\n      建會本於文化藝術事業獎勵、補助之主管機關職權，對於\n      文化藝術獎助條例第26條規定所為之解釋，符合該條例「\n      為扶植文化藝術事業，輔導藝文活動，保障文化藝術工作\n      者，促進國家文化建設，提昇國民文化水準」之立法意旨\n      ，自得予援用。\n    3.復按，「本條例所稱文化藝術事業，係指經營或從事下列\n      事務者：……四、關於文化機構或從事文化藝術活動場所\n      之管理及興辦。……」及「本條例第2條第4款所稱文化機\n      構，係指依法令設立之下列機構：……二、博物館或美術\n      館。……」分別為文化藝術獎助條例第2條第4款及同條例\n      施行細則第4條第2款所明定。是以，須依「法令」合法設\n      立之博物館，方屬於文化藝術獎助條例第2條第4款所稱之\n      「文化機構」，而依社會教育法第5條第2款：「各級政府\n      視其財力與社會需要，得設立或依權責核准設立左列各社\n      會教育機構：……二、博物館或文物陳列室。」第6條：\n      「社會教育機構由中央設立者為國立；……；由私人或團\n      體設立者為私立。」第7 條：「社會教育機構之設立、變\n      更或停辦：國立者，應由教育部審查全國情形決定之；…\n      …縣( 市) 立、鄉( 鎮、市、區) 立及私立者，應報請縣\n       (市) 政府或直轄市主管教育行政機關核准，並轉報教育\n      部備案。」第8 條：「私立社會教育機構應依前條規定核\n      准立案並辦理財團法人登記；其設立、變更、停辦、督導\n      、獎勵及其他應遵行事項之辦法，由教育部定之。」暨私\n      立社會教育機構設立及獎勵辦法第1 條：「本辦法依社會\n      教育法第8 條規定訂定之。」第3 條第2 款：「私立社會\n      教育機構種類如下：…二、博物館或文物陳列室。」第8\n      條：「私立社會教育機構得由私人或團體創辦，或經各級\n      主管教育行政機關許可設立之財團法人附設。」第9 條：\n      「設立私立社會教育機構，應由創辦人或所屬之財團法人\n      以申請書載明下列事項，並檢具有關證明文件，連同捐助\n      章程或遺囑影本，向直轄市主管教育行政機關或縣( 市)\n      政府申請籌設。……」第10條：「私立社會教育機構應設\n      董事會，但財團法人附設者，得不另設董事會。」第17條\n      ：「董事會經報准核備後，應於30日內辦理財團法人登記\n      ，逾期不辦理者，依第9 條之核准失其效力。…」第18條\n      ：私立社會教育機構於完成財團法人設立登記並領得財團\n      法人登記證書後，應由董事會於一年內開具第9 條所列事\n      項及有關文件，向直轄市主管教育行政機關或縣( 市) 政\n      府申請立案。凡經核准立案之私立社會教育機構，直轄市\n      主管教育行政機關或縣（市) 政府應轉報教育部備查。」\n      第19條：「私立社會教育機構經直轄市主管教育行政機關\n      或縣( 市) 政府核准立案後，始得開辦。」第20條：「財\n      團法人附設社會教育機構，得……依第9 條規定向直轄市\n      主管教育行政機關或縣( 市) 政府申請核准立案後開辦。\n      」「私立社會教育機構受直轄市主管教育行政機關或縣(\n      市) 政府之監督及輔導，其一切教育措施及其他事項應依\n      有關法令辦理。」等規定可知，博物館不僅為文化機構，\n      亦屬於社會教育機構，私立博物館之設立，如由私人或團\n      體設立者，應向直轄市主管教育行政機關或縣( 市) 政府\n      申請核准立案，並辦理財團法人登記，方得開辦；如由財\n      團法人附設私立博物館，亦須為主管教育行政機關許可設\n      立之財團法人始得申請之，並由直轄市主管教育行政機關\n      或縣( 市) 政府執行私立博物館之監督及輔導。足見，無\n      論是文化藝術獎助條例第26條所定「經文教主管機關核准\n      設立之博物館」，其所稱之「文教機關」；或依文建會上\n      開函釋所稱經營同條例第2 條第4 款所列博物館( 文化機\n      構) 之文化藝術事業之「目的事業主管機關」，依現行有\n      效之上揭法令規定，均係指直轄市主管教育行政機關或縣\n       (市) 政府等地方主管教育行政機關甚明。\n    4.惟查，原告係以從事宗教業務及服務為目的之宗教團體，\n      向內政部申請許可設立之宗教財團法人，其名稱為「財團\n      法人世界宗教博物館發展基金會」，設立宗旨為「一、重\n      建尊重、包容、博愛的社會、闡揚生命的智慧與健康的人\n      生觀。二、提昇華人社會的國際形象與地位。三、推展宗\n      教交流，促進世界和平。四、保護人類的宗教智慧與資產\n      。」此有原告經臺灣板橋地方法院登記處核發之法人登記\n      證書內容可稽( 見本院卷第146 頁) ，並非經主管教育行\n      政機關許可設立之財團法人，而原告之捐助及組織章程第\n      4 條第1 款規定：「本法人依有關法令規定辦理左列業務\n      ：「(一)籌設世界宗教博物館及國內外分館。……」( 見本\n      院卷第148 頁) ，亦係原告本於宗教財團法人所從事之目\n      的事業，仍屬於宗教業務之範圍；縱原告興辦之「世界宗\n      教博物館」已實質具備「博物館」之內涵，依上引社會教\n      育法暨私立社會教育機構設立及獎勵辦法之規定，亦應向\n      地方主管教育行政機關申請核准設立，方符合文化藝術獎\n      助條例第26條所稱「經文教主管核准設立」及同條例施行\n      細則第4 條第2 款規定「依法令設立」之要件，該博物館\n      始能謂屬於同條例第2 條第4 款所列文化機構( 博物館)\n      之文化藝術事業；況且，內政部以83年3 月22日台83內民\n      字第8301721 號函准予原告設立宗教財團法人，已於該函\n      說明欄載明：「…三、另依教育部82年12月22日(82)社字\n      第071180號函，該基金會設立後，若欲推展『博物館」業\n      務，須依『私立社會教育機構設立及獎勵辦法』辦理。」\n       (見原處分卷(一)第189 頁) ，原告亦不得諉為不知；然原\n      告卻係以附設機構台北館名義辦理營業登記而經營上開「\n      世界宗教博物館」，明顯與上揭法令規定不符。原告未細\n      究相關法令規定及文建會上開函釋意旨，徒言其為經目的\n      事業主管機關內政部核准設立之公益財團法人，其興辦之\n      「世界宗教博物館」亦為文化藝術獎助條例第2 條第4 款\n      之文化藝術事業，即符合該條例第26條「經文教主管機關\n      核准設立」之規定，其所有供該博物館使用之系爭房屋，\n      自得依該規定免徵房屋稅云云，委無足取。\n六、綜上所述，原告之主張，均無足採。被告對於原告所有如附\n    表編號1-7 等7 戶房屋所為課徵97年度房屋稅之處分，於法\n    並無違誤，訴願決定予以維持，亦無不合。原告訴請撤銷，\n    為無理由，應予駁回。\n七、據上論結，本件原告之訴為無理由，依行政訴訟法第98條第\n    1 項前段，判決如主文。"
  },
  "characters": {
    "judges": [
      "徐瑞晃",
      "蔡紹良",
      "蕭惠芳"
    ],
    "prosecutors": [

    ],
    "lawyers": [

    ],
    "clerks": [
      "李淑貞"
    ],
    "plaintiffs": [
      "財團法人世界宗教博物館發展基金會"
    ],
    "defendants": [
      "臺北縣政府稅捐稽徵處",
      "代  表  人  乙○○（代理處長）."
    ],
    "prosecutor_office": [

    ],
    "creditors": [

    ],
    "debtors": [

    ],
    "judicial_associate_officer": [

    ]
  },
  "adjudged_at": "2010-05-12",
  "created_at": "2016-01-05 11:57:09",
  "updated_at": "2016-01-05 11:57:09"
}