{
  "identify": "TPB-98-訴-2085-20100512-1",
  "court": {
    "name": "臺北高等行政法院",
    "code": "TPB"
  },
  "division": {
    "name": "行政",
    "code": "A"
  },
  "year": 98,
  "word": "訴",
  "number": "2085",
  "jcheck": "1",
  "reason": "考試",
  "content": "臺北高等行政法院判決\n                                      98年度訴字第2085號\n                                    99年 4月28日辯論終結\n原      告  甲○○\n            乙○○\n            丙○○\n            丁○○\n            戊○○\n            己○○\n            庚○○\n            辛○○\n            壬○○\n            癸○○\n            子○○\n            丑○○\n            寅○○\n            卯○○\n            辰○○\n            巳○○\n共      同\n訴訟代理人  呂偉誠  律師\n被      告  考選部\n代  表  人  午○○（部長）住同.\n訴訟代理人  未○○\n            申○○\n            林家祺  律師\n上列當事人間考試事件，原告提起行政訴訟，本院判決如下：\n    主  文\n原告之訴駁回。\n訴訟費用由原告負擔。\n    事實及理由\n一、程序事項：按當事人應就訴訟關係為事實上及法律上之陳述\n    ，行政訴訟法第122 條第2 項定有明文，又同法第132 條準\n    用民事訴訟法第195 條第1 項規定：「當事人就其提出之事\n    實，應為真實及完全之陳述。」即當事人對事實及法律上之\n    訴訟關係，有完全陳述之義務，此就行政訴訟在人民公權利\n    保障理念下，權利是否以及如何行使，自應委由權利人自主\n    決定，故有關訴訟程序之開始，訴訟標的之特定，訴訟程序\n    之終結等，自應賦與當事人即人民自主權，即人民對於訴訟\n    標的或訴訟中之訴之聲明有一定之處分權，從而審判長於訴\n    訟程序中行使闡明義務後，若原告即處分權人仍堅持己見，\n    參照上開說明，本院即已盡闡明義務。本件本院經闡明依司\n    法院釋字第546 號解釋，拒絕應考之決定，性質屬行政處分\n    ，系爭「考選部『暫准報考緩發及格證書』行政契約」第2\n    條、第3 條、第4 條是否為行政處分之附款（條件或負擔）\n    請原告確認，然原告仍稱上開「考選部『暫准報考緩發及格\n    證書』行政契約」性質為行政契約，且屬有對價關係之行政\n    契約，並非行政處分，故仍應提起本件確認之訴而無庸更改\n    其聲明及陳述；基於尊重當事人之處分權，本院仍就原告聲\n    明主張之範圍審認，並敘明理由，應先敘明。\n二、事實概要：原告等人分別波蘭國波茲南醫學大學、羅茲醫學\n    大學、西里西亞醫學大學之畢業生（詳如附件），欲參加被\n    告於民國（下同）98年8 月1 日至98年8 月2 日舉辦之「98\n    年第二次專門職業及技術人員高等暨普通考試醫事人員（不\n    含牙醫師、助產師、職能治療師）、中醫師、心理師、營養\n    師考試暨醫師考試分試考試」（下稱98年醫師考試）。原告\n    依據被告所制訂之應考須知第八頁第八點之規定，均於限定\n    期間內，提出經我國駐外使館驗證之波蘭各醫學院畢業證書\n    、歷年成績單、實習證明等文件，向被告提出報名。嗣被告\n    以98年6 月25日選專字第0983301258號函分別通知原告等，\n    略以：(一)、依據本部醫師牙醫師考試審議委員會第五次會議\n    決議辦理。(二)依專門職業及技術人員高等暨普通考試醫事人\n    員考試規則附表一醫師類科應考資格第1 款之規定，……畢\n    業，並經實習期滿成績及格，領有畢業證書者，……(三)依據\n    會議決議結果，原告應考資格證明文件未齊，所繳驗之實習\n    證明不予採認，應補繳自各該校畢業以後的一年實習證明。\n    (四)原告尚能補件，請於98年6 月30日通知傳真被告，並於98\n    年7 月10日前補繳相關實習證明文件之原本影印本及中文議\n    本……，憑以覆審，逾期不准報名，所繳報名費用，一律收\n    繳國庫，概不退還……等語。嗣原告接獲上開函件後分別於\n    98年6 月間陸續向被告提出回覆略以：原告申請准予暫時報\n    名，相關證明將於98年7 月10日前寄送被告等語；另由原告\n    等考生家長等向被告陳情，原告等亦陸續於98年6 月29日、\n    30日、7 月1 日陸續向被告提出申覆。嗣被告於98年7 月6\n    日、9 日再召開醫師牙醫師考試審議委員會第六、七次會議\n    ，其中第七次會議邀請波蘭國等醫學院畢業生之考生代表與\n    會說明有關實習情形後，認為原告等34人提出證明，因見習\n    與實習未區別，依國內學制其大多屬見習性質並非「實習」\n    ，與國內學制1 年完整實習有別，爰與醫師法第2 條「……\n    實習期滿成績及格……」之規定不相當，不予報考。原告除\n    再向被告繼續陳情外，亦曾陸續自98年7 月13日、14日起，\n    分別向本院具狀聲請假處分保全程序。嗣被告98年7 月16日\n    召開醫師牙醫師考試審議委員會第八次會議審議結果，同意\n    被告與波蘭國醫學院畢業生之原告等考生，簽定行政契約，\n    以「暫准報考緩發及格證書」方式，限報考本件98年第二次\n    專門職業及技術人員考試。而原告接獲通知後，於98年7 月\n    中旬後，簽訂被告寄發之「考選部『暫准報考緩發及格證書\n    』行政契約」（下稱系爭行政契約）一式三份，系爭行政契\n    約記載「……一、甲方在乙方應考資格中「實習期滿成績及\n    格」部分與國內醫學院實習期間及內容是否相當尚具爭議情\n    況下，……甲方暫准乙方報考98年第2 次專門職業及技術人\n    員高等考試醫師考試。二、乙方同意倘考試成績及格，願意\n    接受甲方暫不發給醫師考試及格證書之決定，俟自行聲請或\n    接受行政院衛生署安排於國內適當層級之醫療機構，完成與\n    國內醫學院相當期間與內容之實習，於實習期滿成績及格後\n    ，由相關醫療機構出具實習證明並由行政院……。三、乙方\n    倘於考試榜示及格三年內，未依上述方式，於國內實習期滿\n    成績及格或實習不及格，甲方將依專門職業及技術人員考試\n    法第23條規定，以自始不具備應考資格為由，報請考試院撤\n    銷考試及格資格，不發給考試及格證書。四、乙方同意未及\n    格，應依醫師法施行細則修正發佈之有關實習規定，經實習\n    期滿成績及格後，始得再行報考醫師考試分試第一試。……\n    」，原告於系爭行政契約上簽名後，陸續於98年7 月20日左\n    右寄回被告。被告於收到原告所簽署並繳回之系爭行政契約\n    書後，始將行政契約書一份及准考證併同寄給原告等，原告\n    等人陸續於98年7 月23日左右收到前述行政契約及准考證，\n    於98 年8月1 日參加該次醫師考試。而上開醫師考試業於98\n    年9 月30日榜示，原告甲○○、己○○、辛○○、癸○○及\n    子○○5 人醫師考試及格，同日被告亦依系爭行政契約約定\n    ，將甲○○等5 人及格人員名冊函送至行政院衛生署，請其\n    安排渠等至國內各醫療機構實習；行政院衛生署則以98年12\n    月1 日衛署醫字第0980 087896 號函，分發上開考試及格之\n    原告至各署立醫院實習。其餘未及格之原告業已由被告於98\n    年12月8 日以選專字第09 83302483 號函准其報考99年1 月\n    23 日 舉行之99年第一次專技高考醫師考試分試考試第一試\n    ，並已於99年1 月7 日寄發入場證在案。又本件原告於98年\n    10月9 日向本院提起本件確認公法上法律關係不存在之訴訟\n    。\n三、原告起訴主張略以：\n（一）程序方面：\n  １、本件原告提起之訴訟乃確認系爭行政契約中之第二、三、\n      四條約定之法律關係不存在，並非確認行政處分無效或違\n      法，應屬「確認法律關係存否之訴」。另被告98年6 月25\n      日選專字第0983301258號函文，主旨係載明要求原告等補\n      正文件，並未記載已否准原告等之報考等事實甚明；況且\n      原告等人亦已對被告上開函文均以書面提出申覆表示不服\n      ，然被告對於原告等上開申覆書並未再回函表示予以駁回\n      或否准原告等之報考，足證被告稱原告應對其98年6 月25\n      日否准處分提起撤銷之訴，並無理由；故本件原告就系爭\n      行政契約內容提起確認訴訟並無違反備位性原則。\n  ２、本件原告應考資格是否具備，應依醫師法第2 條第1 項第\n      1 款及依專門職業及技術人員考試法第5 條規定，所制定\n      之專門職業及技術人員高等考試醫師牙醫師考試分試考試\n      規則第六條之附表一、應考須知第6 頁亦明確規定，原告\n      等人報考系爭醫師考試之應考資格為「符合教育部採認之\n      國外大學、獨立學院醫學醫學系、科畢業，並經實習期滿\n      成績及格，領有畢業證書者」等規定認定。原告報考資格\n      符合上開法律規定，故並無被告所稱會將行政契約變成授\n      益行政處分之情形。另查系爭行政契約第4 條對本件醫師\n      考試未及格之原告11人言，顯違反法律不溯既往原則，且\n      剝奪此部分原告報考下次考試之應考資格，故就此次考試\n      未及格原告12人而言，當然具確認判決之法律上利益，而\n      得提起確認訴訟。\n  ３、關於已考試及格之原告甲○○、己○○、辛○○、子○○\n      、癸○○雖已分發至各署立醫院實習，然本件系爭醫師高\n      等考試及系爭行政契約簽立當時（98年8 月2 日），被告\n      系爭醫師考試分試考試規則尚未修訂，故被告於98年10月\n      14日修訂之上開考試規則，並無溯及效力，被告抗辯此部\n      分原告訴訟無保護必要云云，應屬無據。又本件訴訟獲致\n      勝訴判決時，原告等甲○○5人即可中止實習而要求被告\n      發給考試及格證書，故原告等5 人自仍有提起本件訴訟之\n      法律上利益及權利保護必要。\n  ４、被告98年6 月25日函文僅要求原告補正文件，並未記載已\n      否准原告之報考等，而原告對上開函文均已向被告提出申\n      覆書請求救濟，但被告對原告申覆書未為任何處置，亦未\n      作成駁回之決定，則原告亦無從進行後續行政訴訟之救濟\n      程序；且縱使撤銷上開被告98年6 月25日函文之處分，本\n      件系爭行政契約不當然因此失其效力，足見原告仍有提起\n      本件確認之訴之法律上利益及權利保護必要。是被告稱本\n      件訴訟之提起違反行政訴訟法第6 條第3 項規定云云，應\n      屬無理由。\n  ５、本件原告等人分別留學於波蘭國波茲南醫學大學、羅茲醫\n      學大學、西里西亞醫學大學畢業，並經實習期滿成績及格\n      ，已符合法定應考資格之要件，被告即應准予原告報考，\n      但原告竟以系爭行政契約，在未有法律明文授權下，課與\n      原告額外之實習義務，使原告須於考畢後再補為實習，否\n      則不發給證書或不得報名往後年度之考試，即屬侵害原告\n      之權利，是原告權利受侵害甚明確；原告在無其他救濟途\n      徑之情形下，為保障自身取得合格證書之權利，方先依照\n      該契約之內容補行實習，故本件確認之訴確認系爭行政契\n      約之第2條等該契約條款無效而該法律關係不成立，則原\n      告自可免於此等義務，被告稱無權利保護之必要云云，應\n      屬無理由。\n（二）實體部分：\n  １、被告要求原告等所簽訂之系爭行政契約其中第二、三、四\n      條約定應屬違法無效而不存在：\n      (1)依據醫師法第2 條第1 項第1 款規定及專門職業及技術\n        人員高等考試醫師牙醫師考試分試考試規則第6 條之附\n        表一、應考須知第6 頁亦明確規定，原告應考資格為「\n        符合教育部採認規定之國外大學畢、獨立學院醫學醫學\n        系、科畢業」並「經實習期滿成績及格」而「領有畢業\n        證書者」即具有應考資格；而被告卻於系爭「暫准報考\n        緩發及格證書」行政契約內容所示，顯係約定以被告為\n        准予原告參加考試受益行政處分，與原告需重新或補行\n        實習及接受暫緩發及格證書，為雙方對待給付義務，而\n        成立行政契約中之雙務契約。惟所謂應考資格之訂定須\n        符合公平、公開原則和保障人民權益之目的乃屬當然，\n        自不得依據雙方之契約約定而有所變更，故仍應以上開\n        醫師法、專門職業及技術人員高等考試醫師牙醫師考試\n        分試考試規則等相關規定之要件，決定原告等人之應考\n        資格，即原告如符合應考資格，被告即應准予應考，反\n        之則否，被告依法並無行政裁量空間，應屬行政程序法\n        第135 條規定但書規定，依其性質不得為行政契約之情\n        形。\n      (2)該雙務契約之內容係約定原告等人考試後應再實習，顯\n        與確保應考人能於一定期限內，提出考試前已經具備應\n        考資格之證明無關，故與為確保准予考試受益行政處分\n        法定要件履行，即考試前已經具備應考資格為准許應考\n        受益處分之法定要件無關，故依據行政程序法第137 條\n        第2 項規定不得作成行政契約。綜上，被告准許原告考\n        試之受益行政處分之性質或依法律規定應不得締結行政\n        契約，故被告「暫准報考緩發及格證書」行政契約，違\n        背禁止規定而應為無效而不存在。\n      (3)且系爭行政契約第2 、3 、4 條約定應屬無效違背行政\n        程序法第135 條但書已如前述，故被告以之作為行政契\n        約，依上開規定，應屬無效；況有關原告考試後依法應\n        否再為實習或如何實習之事項，應屬於醫師法相關法令\n        所規範，被告依法並非該事項之主管機關，被告依法顯\n        無訂定上開事項行政契約之權限，應屬違反行政程序法\n        第14 2條、第111 條第1 項第6 款規定，足證上開系爭\n        行政契約之約定應為違法無效而不存在。\n  ２、考試機關所訂定各類科之應考資格時，亦應受一般法律原\n      則之拘束。惟查：\n      (1)本件被告所單方制訂之系爭行政契約條款，顯違反依法\n        行政原則。即依憲法第18條及中央法規標準法第5 條第\n        1 項第2 款之規定，上開應考資格之標準或限制，應以\n        法律規定之。前開所稱法律規定，即為前述醫師法第2\n        條規定及依專門職業及技術人員考試法第5 條規定，所\n        制定之專門職業及技術人員高等考試醫師牙醫師考試分\n        試考試規則第六條之附表一。被告依據依行政程序法第\n        4 條規定「依法行政原則」，不得再以系爭行政契約另\n        行增定准予考試之條件，被告擅予增加法律所未有之限\n        制，應屬違法而無效。\n      (2)本件被告所訂系爭行政契約條款，違反行政程序法第6\n        條規定之「平等原則」。查原告於波蘭國各醫學院求學\n        過程，均依據該大學學制、課程內容之要求完成學業，\n        並經實習期滿成績及格，方取得畢業證書，而原告報考\n        本件醫師考試所提出之應考資格證明文件，均符合上開\n        應考須知之規定，亦與歷年被告機關辦理相同考試時，\n        所認定准予應考之波蘭國暨其他外國留學生學生之情形\n        皆無任何不同。且依被告91年3 月27日醫事人員考試審\n        議委員會第六次會議決議及醫師法第四條之一規定，原\n        告等人之實習資格即應予以採認，而符合醫師法第2條\n        第1 項第1 款「實習期滿成績及格」之要件，故原告之\n        應考資格應屬合法。原告信賴被告長久以來之慣行和法\n        令解釋，花費多年時間出國學習醫學，依同樣條件、方\n        式完成學業且實習期滿成績及格並取得證明文件，報考\n        本件醫師考試，自屬合理信賴被告應採取上開歷年相同\n        應考資格審查標準，豈料被告竟事後於審查時，先突然\n        來函通知，對於原告等人之實習期滿成績及格證明「不\n        予採認」，其後又於系爭行政契約中增加准予考試之條\n        件，顯然違反行政程序法第6 條之規定，足證上開系爭\n        行政契約條款之差別待遇違反平等原則又無正當原因，\n        應屬違法無效。\n      (3)本件被告所訂系爭行政契約條款，顯違反行政程序法不\n        當連結禁止原則：系爭行政契約性質應為「代替行政處\n        分」之行政契約，應受行政程序法第142 條之規範限制\n        。又該契約內容為規定原告有諸多義務需要履行，而上\n        述契約既為被告單方片面所制訂定之事實，且原告等又\n        係基於時間緊迫等因素，顯陷於無充分選擇自由，更無\n        參與契約條款討論商議之機會等等顯不公平情況下，故\n        對原告而言，應為顯失公平之負擔義務契約，該契約自\n        應受行政程序法第137 條規範之限制，同時雙方對待給\n        付顯不相當，亦顯失公平。又系爭行政契約雖記載，其\n        目的在於保障國人生命身體健康並兼顧原告等人應國家\n        考試之權利，然所謂「實習期滿成績及格」僅為應考資\n        格的標準，並非考試及格的標準，具備應考資格者仍須\n        參加考試成績及格，方有可能取得及格證書執行業務，\n        此時方與所謂國人生命身體健康產生正當且合理關聯性\n        ，然被告片面對原告等人不法增加法律所未規定之報考\n        資格限制，自屬違法不當。同時與被告91年決議或不同\n        於以往歷年採認標準；顯見被告之行為不僅違反前開行\n        政程序法第137 條第1 項第3 款禁止不當連結原則及第\n        137 條第2項，更屬違反同法第8 條規定之誠信原則及\n        同法第5條之明確性原則。\n      (4)系爭行政契約約定，顯違反法律優位原則：依據前開專\n        門執業及技術人員考試法第1 條、專門執業及技術人員\n        高等考試醫師牙醫師考試分試考試規則第14 條 、醫師\n        法第6 條之規定，原告等人若考試及格，對於被告即有\n        請領及格證書之權利，而被告亦有給予及格證書的法定\n        義務，被告依法應無裁量的空間。然今被告片面制定系\n        爭行政契約，顯然逾越其法定裁量範圍，且為違背法令\n        對原告增加法律所未規定限制之行為，應屬違反法律優\n        位原則而無效。\n      (5)再依行政程序法第141 條規定，可知法律行為的內容應\n        具備合法、妥當、可能、確定四項要件，且行政程序法\n        第5 條亦規定：「行政行為之內容應明確。」惟查：系\n        爭行政契約第2 條、第4 條所指外國醫學院畢業生能否\n        在國內醫院實習？如何實習？之相關規定，以及所指醫\n        師法施行細則修正發佈之有關實習規定等事項之內容為\n        何？何時實施？等事實，於系爭行政契約訂約當時，均\n        付之闕如，亦尚無從知悉，皆屬客觀上無法確定之情形\n        ，足見系爭行政契約顯違反行政程序法第5 條規定及顯\n        有法律行為標的欠缺確定性之無效情形。\n  ３、依據司法院釋字第348 號解釋之協同意見書揭示「公法契\n      約故應受行政主體與他造當事人就約定之內容自由達成協\n      議……人民僅有簽訂與否之自由，並無對其內容與行政主\n      體協商修改之餘地，故其契約內容首重公平合理，不得使\n      人民負不相當之對待給付義務。」是本件原告於系爭行政\n      契約中，最低限度仍應享有締約自由及承諾自由。查原告\n      等人於98年7 月17日左右，接獲被告人員表示須簽訂系爭\n      行政契約，才會核發准考證，當時距離考試不到10日之時\n      間，而原告等人向本院所聲請假處分案件，尚無具體結果\n      ，原告又無其他立即救濟途徑，如果原告等人拒絕簽訂系\n      爭行政契約，根本不可能有參加此次考試之機會，足證原\n      告係於毫無選擇餘地之情形下，被迫不得已而簽訂系爭行\n      政契約，顯見被告所稱「原告在自由意願下簽訂此一和解\n      契約云云」，顯與事實不合。\n  ４、被告雖主張系爭行政契約為行政程序法第136 條之和解契\n      約云云，惟查：縱認被告所稱，雙方對於波蘭醫學院之實\n      習課程是否與我國醫學院之實習相當存有爭義，而成立和\n      解契約，然系爭行政契約內容中記載，被告有「暫准原告\n      報考」、「原告考試及格並實習期滿，考試院發給考試及\n      格證書」義務及「原告考試及格然無實習或實習不及格時\n      ，撤銷考試及格資格不發給考試及格證書」之權利，而原\n      告等有「原告考試及格時，需完成與國內醫學院相當期間\n      與內容之實習」及「原告考試不及格時，需實習始得再行\n      報考」等義務，足見系爭行政契約原、被告間互負給付義\n      務，亦屬成立雙務契約之情形。況且被告於答辯狀自承「\n      第五次會議決議，通知補繳畢業後一年實習證明後再議。\n      ……嗣該審議委員會第6 次會議決議，以原告等均未提出\n      合乎規定之實習證明不准報考」、「第7 次會議同意應考\n      人（含原告）推派代表到場說明，惟決議仍以原告在學期\n      間之見習與實習未做明確區分……核與醫師法第2 條……\n      之規定不符，不准報考」等情，顯見被告係已明確認定原\n      告等不符報考資格而作成不准報考之決議，應非其現今所\n      稱原告等之報考資格認定尚有疑義而無法查明事實之情形\n      ，足見被告上開所稱系爭行政契約之簽定為「和解契約」\n      ，非無疑義。\n  ５、被告又主張對於外國醫學院之實習是否與國內醫學院實習\n      『相當』，為不確定法律概念，具有判斷餘地，本件經由\n      專業審議委員會本於專業權責加以判斷，作成先通過考試\n      後，補實習再執業決定之和解契約云云，惟查：被告係依\n      據醫師法第2 條第1 項第1 款、專門職業及技術人員考試\n      法第五條規定，所制定之專門職業及技術人員高等考試醫\n      師牙醫師考試分試考試規則第六條之附表一，辦理本件醫\n      師特考，應考人之資格要件明確，並無被告所稱「不確定\n      法律概念」而授予被告裁量權之情形；依被告之「應考資\n      格審查規則」第2 條、第3 條規定，被告於審核應考者符\n      合法定要件之情形，即應為准考之處分，換言之，係為羈\n      束處分，即同一申請於相同時點審查是否符合應考要件，\n      只有「符合」或「不符合」擇一之明確判定，顯見被告並\n      無一方面既已決議認定原告等「不符合應考資格不得考試\n      」，另方面卻又以行政契約准予原告等應考之法律上裁量\n      權。足證系爭行政契約應有行政程序法第135 條但書所規\n      定，依其性質或法律規定不得締約之違法無效情形。同理\n      系爭行政契約第2 、3 、4 條等約定，既無法律明文規定\n      ，亦與確保行政契約之法定要件之履行無關，則依行政程\n      序法第137 條第2 項規定適用同法第93條第1 項後段，被\n      告應不得為之。\n  ６、有關醫師法第2 條第1 項第1 款規定事項，主管機關應為\n      行政院衛生署，而非被告。且有關上開法律規定之應考資\n      格如有修改之必要時，亦須由主管機關依法定程序進行修\n      法，然本件系爭行政契約簽定當時，醫師法規定之應考資\n      格相關法令規定尚未修改，然被告卻已先於系爭行政契約\n      中，自行規定原告須補行有關國內實習事項，已屬逾越被\n      告之法定職權。依行政程序法第142 條第1 項第1 款及同\n      法第111 條第1 項第6 款規定，上開有關補行實習之契約\n      條款應屬無效。\n  ７、關於被告主張「原告違反禁反言、誠信原則，原告乃在自\n      由意願下簽訂此一合約，也獲得報考資格之實質利益且『\n      已經完考』，原告既然合意締結和解在前，事後即不得違\n      反其承諾。」等語云云。查被告為執掌國家考試之機關，\n      本件被告又係於臨考前始要求原告簽訂系爭行政契約，原\n      告當時基於時間緊迫且欠缺救濟途徑等情形，不得已而簽\n      定，實非出於自由意願，已如前述詳述，且所謂取得報考\n      資格之實質利益，本應為原告應有之法定權益，是原告提\n      起本件訴訟，並無違反禁反言或誠信原則。\n  ８、又原告分別留學於波蘭國波茲南醫學大學、羅茲醫學大學\n      、西里西亞醫學大學畢業，並經實習期滿成績及格，已滿\n      足本考試應考資格所定之要件，原告竟以系爭契約條款，\n      在未獲法律授權之情形下，課與原告考試後須另於國內額\n      外實習之義務，否則即不發給證書或不得報名下年度之考\n      試，該條款乃不合法且違反平等原則等一般法律原則，應\n      屬無效已如前述，原告自不受該無效條款之其拘束，系爭\n      行政契約之法律關係亦為不成立，被告主張原告應受拘束\n      ，要無理由。\n（三）綜上，系爭行政契約第2 條、第3 條及第4 條應有違反上\n      述法律規定、原則而無效情事而法律關係不存在，爰依行\n      政訴訟法第6 條第1 項等規定，得提起本件確認之訴，聲\n      明：１、確認原告等分別與被告所簽系爭行政契約所示「\n      考選部暫准報考緩發及格證書行政契約」，其中第2 條、\n      第3 條、第4 條約定之法律關係不存在。２、訴訟費用由\n      被告負擔。\n四、被告抗辯略以：\n（一）程序方面：\n  １、原告起訴違反確認訴訟之備位性原則：本件爭議實質上係\n      因原告對於被告認定其波蘭醫學院學歷無法取得報考醫師\n      資格之認定不服，但當時因考試即將舉行，且原告復一再\n      陳情，被告為保障其參與考試之機會，始在經協調行政院\n      衛生署同意配合辦理實習作業以及『雙方合意下』分別在\n      98年7 月18日至21日與原告簽訂系爭行政契約。核其實質\n      上所不服者乃係「被告」當初否准其具有專技人員醫師高\n      考報考資格之決議，依行政訴訟法第6 條第3 項之規定，\n      原告應在獲知其被認定不符報考資格之後依法提起訴願、\n      撤銷訴訟，亦即當時如對該行政決定有所不服原應對該「\n      否准」且退件報考資格之行政處分提出撤銷訴訟，而當時\n      原告等人對並未對該處分提出訴願而僅四處陳情，現否准\n      報考及退件之處分已確定之後始提出確認訴訟，應足認本\n      件起訴程式有違反確認訴訟之備位原則。\n  ２、原告訴之聲明不合法：如依原告之聲明將造成法院以判決\n      方式將『行政契約』變更為『授益行政處分』，此已自創\n      法律所無之訴訟類型，而屬誤用訴訟類型：細繹原告訴之\n      聲明係確認：「考選部暫准報考緩發及格證書行政契約其\n      中第二條、第三條、第四條約定之法律關係不存在」，惟\n      果真如依其聲明以判決方式確認行政契約之第二、三、四\n      條均無效而不存在之後，全份契約僅保留第一條「考選部\n      暫准原告等報考醫師高考」，而『准予報考之法律性質係\n      授益行政處分』，惟行政訴訟法並無法律依據可透過法院\n      之判決將行政契約變成授益行政處分之訴訟類型，蓋行政\n      契約與行政處分，本質上即為不同之行政行為，自無由法\n      院以判決之方式將行政契約以『判決方式』『變成』『行\n      政處分』餘地。如原告之目的係欲命被告作成「准予報考\n      之行政處分」應依行政訴訟法第5 條提起課予義務之訴。\n      惟不論以上何者，原告之訴訟類型均非適法當可確定。\n  ３、原告乙○○等11名未及格者並無即受確認判決之法律上利\n      益：本件醫師考試未及格者11人，已參加98年8 月1 日之\n      醫師考試而考試已於98年9 月30日榜示結束，所以被告已\n      完成行政契約之給付，因為原告乙○○等11名未及格，未\n      有後續實習問題，被告之義務已因履行完畢而消滅，故依\n      行政訴訟法第6 條之規定，原告乙○○等11名未及格者並\n      無即受確認判決之法律上利益。同時上開原告亦報名參加\n      99年1 月23日舉行之99年第一次專技高考醫師考試分試考\n      試第一試，並已於99年1 月7 日寄發入場證在案，是此部\n      分原告更無即受確認判決之法律上利益存在。\n  ５、原告之訴依其所訴之事實顯無理由，依法應不經言詞辯論\n      逕以判決駁回之：本件原告確認聲明係確認「考選部暫准\n      報考緩發及格證書行政契約第二、三、四條法律關係不存\n      在」，而依行政程序法第143 條之規定行政契約一部無效\n      者，全部無效；且明顯地如欠缺整份契約之二、三、四條\n      被告將不可能締結該行政契約，因此，本件無由透過行政\n      程序法第143 條但書之規定僅讓契約第一條『單獨』生效\n      ，原告之聲明主文僅依其形式上觀之已不合法，直接牴觸\n      行政程序法第143 條，故依行政訴訟法第107 條第3 項規\n      定，本院依法即應不經言詞辯論，逕以判決駁回原告之訴\n      。\n（二）實體方面：\n  １、系爭行政契約法律性質為行政程序法第136 條和解契約：\n      (1)依行政程序法第136 條之規定，機關負有職權調查事實\n        之義務，本件兩造間之爭執為波蘭醫學院之實習課程是\n        否與我國醫學院之實習『相當』（參照國外學歷採認辦\n        法第8 條），因簽訂契約之前已經即將舉行專技人員醫\n        師高考，具有時效性及急迫性，為避免侵害人民之權利\n        ，被告於已盡各種調查途徑仍不能查明該事實，為解決\n        爭執及達成行政目的始與原告依行政程序法第136 條規\n        定締結系爭和解契約，合先說明。\n      (2)本件所涉前開報考資格之「事實不明」爭議經過：\n        原告等係波蘭醫學院之畢業生，故其『學歷』部分經\n          認與醫師法第4 條之1 之學歷相符。所爭議者係其『\n          實習』部分，究竟是否符合醫師法第2 條第1 項第1\n          款其中所稱之『實習期滿』之內涵，蓋依據教育部大\n          學辦理國外學歷採認辦法第8 條規定：「國外學歷…\n          …修業期限、修習課程，應與國內同級同類學校規定\n          相當」。而本件原告等人在波蘭求學之『實習』過程\n          經被告機關邀集具各大醫學中心之醫師代表、行政院\n          衛生署……等召開醫師牙醫師考試審議委員會審議其\n          報考資格，並請原告等人到會陳述意見後，委員會一\n          致認為原告等人『波蘭醫學院之』『實習』僅相當於\n          『見習』，與我國醫學院之『實習』過程顯不相當，\n          而否准其報考資格。\n        醫師牙醫師考試審議委員會之組織合法、程序正當：\n          按考選部組織法第19條規定考試院爰訂定專門職業及\n          技術人員考試審議委員會組織規程，復按該組織規程\n          第2 條規定，該審議委員會成員由行政院衛生署副署\n          長、教育部醫事教育委員會執行秘書、醫學大學醫學\n          院院長、醫學系系主任、教學醫院院長、公會團體代\n          表及被告簡任以上高級人員組成，另邀請行政院衛生\n          署醫事處及教育部高等教育司派員列席，有關應考人\n          應考資格之疑義，均提該委員會審議，該組織嚴謹，\n          且程序正當，並將審議結果經被告核定後，始報請考\n          試院備查，以維應考人權益，可知過程至為審慎，依\n          此而做成之決定，即不容任意推翻。\n        原告接獲不符報考資格之通知後續處置：\n          嗣原告等多人接獲不符資格之通知後四處陳情謂其係\n          合法國外醫學院之畢業生竟不能報考醫師高考，當時\n          因考試在即且涉及在歐洲之波蘭醫學院其實習之『實\n          際狀況』調查非短期可能明確，因而涉及行政處分(\n          准否報告之決定) 之事實不明確下，乃為行政程序法\n          第136 條規定「行政處分所依據之事實，經依職權調\n          查仍不能確定者」之情況。基於確保醫師專業資格水\n          準與維護國民健康之行政目的，以及原告等援前例得\n          以報考之期待，並為解決爭執( 得否報考醫師高考)\n          ，被告遂依據行政程序法第136 條與原告等人簽訂和\n          解之行政契約，以代替行政處分。\n  ２、原告誤認本件行政契約係行政程序法第137 條之雙務契約\n      並據此為基礎所為契約無效之主張，均因契約是否有效之\n      前提「契約定性」錯誤而失其附麗：本件行政契約雙方並\n      未因約定「被告准予參加考試」與「原告須重新或補行實\n      習及接受暫緩發及格證書」而使雙方互負對待給付義務，\n      而係因為「原告在波蘭之實習狀況」是否與國內醫學院之\n      實習『相當』所為之專業判斷已如前述，因此雙方所訂立\n      者乃行政程序法第136 條之和解契約，迺原告竟執行政程\n      序法第137 條之行政契約大肆主張契約無效，核其有關行\n      政程序法第137 條之主張均因前提不存在，即「契約定性\n      」錯誤而失其附麗，顯不可採。\n  ３、被告（審議委員會）對於外國醫學院之實習與國內醫學院\n      實習是否『相當』具有判斷餘地：\n      (1)本件情形，就現存具體事實涵攝至法律之構成要件判斷\n        （原告等人之波蘭醫學院之「實習」是否符合醫師法第\n        2 條第1 項第1 款、教育部大學辦理國外學歷採認辦法\n        第8 條規定之「實習」「相當」）。由於本件所涉之法\n        令之構成要件用語係以不確定之法律概念『相當』貳字\n        來表現，究竟是否相當則由主管機關依法令所組成之專\n        業審議委員會，本於專業之權責加以判斷，應認其決定\n        具有判斷餘地不容原告以一己主觀之見解主張無效。\n      (2)況查，本件波蘭醫學生之應考資格「實習」部分之認定\n        是否與國內醫學院之實習相當，隨著時空環境的不同而\n        時移事轉，經考選部醫師牙醫師考試審議委員會第7 次\n        會議，詳細詢問原告等在波蘭修習醫學系課程與實習實\n        際之狀況。委員們從英語國際班實習互動與醫院值夜班\n        情況，審慎討論後認為與國內實習未完全相當，委員會\n        作此專業判斷後為了彌補原告等實習與國內實習之完整\n        性及確保國內執業前先行瞭解國內病人與本土流行病等\n        ，審議委員會作成先通過考試後，補實習再執業之決定\n        。此乃被告依據之醫師法及教育部大學辦理國外學歷採\n        認辦法，關於國外「實習」與國內醫學院之實習是否相\n        當，容有判斷餘地。\n  ４、機關辦理本次專技人員醫師高考之審查歷程：\n      (1)各種國家考試應考人之應考資格原則由考選部擬定、考\n        試院發布，惟醫師法及其他醫事人員等相關法規由行政\n        院衛生署主管。另依醫師法施行細則部分條文修正總說\n        明：「對持國外學歷回國參加考試者，其於國外使用之\n        語言及接觸之疾病型態，顯與國內各類醫學生有所不同\n        ，需要在其參加考試前，於國內醫療機構接受與國內醫\n        學生相當之臨床實作科別及週數或時數之訓練，以確認\n        其與我國的醫學院醫學系畢業生具有相似之臨床經驗。\n        」且依醫師法施行細則第1 條之2 規定，就實習期滿，\n        其臨床實作之科別及週數或時數，並無區分國內外，表\n        示國內外之「實習期滿」標準必須一致。\n      (2)被告經提98年6 月19日召開之醫師牙醫師考試審議委員\n        會第5 次會議審議決議，通知補繳畢業後1 年實習證明\n        後再議。被告即於同年月25日選專字第0983301258號書\n        函通知原告等人補件。原告等乃於同年6 月29日、30日\n        及7 月1 日陸續向被告提出申覆，被告為求慎重，即於\n        同年7 月3 、8 日及15日又分別召開醫師牙醫師考試審\n        議委員會第6 、7 、8 次會議。嗣該審議委員會第6 次\n        會議決議，以原告等均未提出合乎規定之實習證明不准\n        報考；第7 次會議同意應考人（含原告）推派代表到場\n        說明，惟決議仍以原告在學期間之見習與實習未作明確\n        區別，依國內學制其大多屬見習性質並非「實習」，與\n        國內學制1 年完整實習有別，核與醫師法第2 條「……\n        實習期滿成績及格……」之規定不符，不准報考。\n      (3)另經考選部醫師牙醫師考試審議委員會第8 次會議審議\n        通過，決議：「一、同意被告與波蘭波茲南等4 所醫學\n        大學及愛爾蘭都柏林大學醫學院畢業生簽訂行政契約以\n        「暫准報考緩發及格證書」方式，並對行政契約修正通\n        過。二、前述權宜措施，僅限報考98年第二次專門職業\n        及技術人員高等考試醫師、牙醫師考試、醫師考試分試\n        考試第一試。三、考試及格證書以實習期滿成績及格之\n        日為生效日期。四、經醫師考試第一試及格者，應先完\n        成實習後再考第二試。五、未簽署行政契約者不准應本\n        次考試。六、本案應報請考試院核定。七、本考試暫准\n        報考成績及格人員在醫療機構實習期間，請衛生署落實\n        督導考核。八、函請教育部儘速查明波蘭大量培養醫學\n        系學生原由，其學制包括課程、見習、實習情形是否與\n        國內學制相當，俾供本會審查相關案件參考」。\n      (4)本案原告等17名擬報考98年第二次專門職業及技術人員\n        高等考試醫師考試、醫師考試分試考試第一試一案，經\n        第8 次會議決議：「比照第一案決議，同意被告與巳○\n        ○等33名波蘭波茲南等4 所醫學大學及愛爾蘭都柏林大\n        學醫學院畢業生簽訂行政契約以『暫准報考緩發及格證\n        書』方式，僅限報考98年第二次專門職業及技術人員高\n        等考試醫師考試、醫師考試分試考試第一試。」\n  ５、被告先取得衛生署同意，而衛生署同意配合辦理考試及格\n      後之實習程序之後，被告始與原告等簽行政契約之過程及\n      行政契約之內容：\n      (1)由於原告等係「實習期滿成績及格」所生之爭議，審議\n        委員會作成「暫准報考緩發及格證書」決議前，由被告\n        以98年7 月14日選專字第0983301452號函徵求行政院衛\n        生署之同意，而行政院衛生署於同日衛署醫字第098020\n        8143號函覆被告同意略以：「……貴部函請本署配合辦\n        理國外醫學畢業生暫准參加專門職業及技術人員高等考\n        試醫師、牙醫師考試及格人員之實習，敬表同意。至實\n        習期滿成績及格之證書，將由各該醫療機構發給，另本\n        署將請各醫療機構列冊函報本署，俾彙整成冊函送貴部\n        ，作為核發考試及格證書之參考……。」\n      (2)依上開協調取得共識，決定於醫師法施行細則修正發布\n        前，經98年第二次專技高考醫師考試及格之應考人，由\n        行政院衛生署安排於國內適當層級之醫療機構實習期滿\n        成績及格後，再由衛生署加以彙整成冊，被告始報請考\n        試院發給考試及格證書。由於被告考試採測驗式試題，\n        無法考出其實作( 實務) ，是以，審議委員會作成「暫\n        准報考」實已兼顧應考人考試權益，並為其實習主動與\n        衛生署連絡，對實習之疑義提出補救措施。被告作成「\n        暫准報考緩發及格證書」之作法。\n      (3)監察院亦認暫准報考緩發及格證書作法兼顧法令與應考\n        權益尚稱允當：依監察院糾正文表示，「……相較於歐\n        盟其他國家之留學人數寥廖可數，留學波蘭人數之多，\n        顯非尋常，非但嚴重影響國內醫學系招生人數之管制總\n        量，且其入學管道與國內醫學系嚴格篩選學生素質相較\n        ，亦明顯寬鬆，甚至前往該國取得醫學系學歷者如循國\n        內升學管道，多數尚無法取得進入國內醫學系就讀之資\n        格，致國人對波蘭大學醫學系開設英語學程廣收外籍學\n        生之教育品質多存疑慮。」（詳被證十五）監察委員針\n        對「波蘭醫學系畢業生回國報考醫師考試相關問題」所\n        做調查報告指出，在行政院衛生署未針對國外醫學系學\n        歷報考者之實習發布明確規定前，考選部「暫准報考緩\n        發及格證書」之作法「尚屬允當」。\n      (4)依上開協商決議採暫准報考緩發及格證書之作法後，98\n        年7 月15日考選部醫師牙醫師考試審議委員會第8 次會\n        議審議通過，依原告等與被告簽訂之行政契約，雙方議\n        定行政契約條款如「考選部『暫准報考緩發及格證書』\n        行政契約」。\n      (5)本次考試及格原告5 人，被告『已依行政契約』函請衛\n        生署安排其至醫院實習：\n        本次考試業於98年9 月30日榜示，原告等計有甲○○\n          、己○○、辛○○、癸○○及子○○等5 人醫師考試\n          及格，醫師考試分試考試無人及格。\n        被告業於98年9 月30日檢送5 名及格人員名冊至行政\n          院衛生署，請其安排渠等至國內各醫療機構實習。至\n          實習期滿成績及格之證書，將由各該實習醫療機構發\n          給，各醫療機構並列冊函報行政院衛生署後，由該署\n          彙編成冊函送被告，渠等5 人業與被告簽訂行政契約\n          ，對雙方均發生拘束力，『被告亦已依約履行安排其\n          及格後實習已如前述』，原告等就議定內容，即須遵\n          守，不得「一面享有行政契約之利益卻另一面否定契\n          約之效力」。\n        另原告乙○○、丙○○、丁○○、戊○○、庚○○、\n          壬○○、丑○○、寅○○、卯○○、辰○○及巳○○\n          等11人該次考試並未及格，若要報考99年第一次專門\n          職業及技術人員高等考試醫師考試分試考試第一試，\n          應依98年10月14日考試院修正發布之專門職業及技術\n          人員高等考試醫師牙醫師考試分試考試規則之規定報\n          考。\n  ６、原告違反禁反言原則：本件情形原告在自由意願下簽訂此\n      一和解契約，也獲得報考資格之實質利益且「已經考完」\n      ，豈有在「既得利益」已實現後，復爭執其無效，亦即被\n      告已充分保障原告之應考資格，未料事後原告竟在獲准參\n      與本次考試後始主張和解契約無效，被告既已合意締結和\n      解在先，事後即不得違反其承諾，否則即有違行政法上禁\n      反言原則之法理。\n  ７、原告違反誠信原則：本件原告於簽訂行政契約之後已『享\n      有』契約第一條之授益行政處分之利益( 准予參加考試)\n      且也『已經參加完考試』並有原告甲○○、己○○、辛○\n      ○、癸○○及子○○等5 人醫師考試還經榜示錄取『並獲\n      被告依契約函請行政院衛生署安排其實習程序』，是原告\n      等人乃系爭行政契約之既得利益者於獲得其利益後( 參加\n      應試) 竟反執以主張「讓其得以順利參試」之行政契約無\n      效，顯自我矛盾不合誠信原則。\n  ８、行政先例須屬合法者，乃行政自我拘束之前提要件，憲法\n      之平等原則，並非賦予人民有要求行政機關重複錯誤之請\n      求權：最高行政法院93年判字第1392號判例之意旨：「憲\n      法之平等原則要求行政機關對於事物本質上相同之事件作\n      相同處理，乃形成行政自我拘束，惟憲法之平等原則係指\n      合法之平等，不包含違法之平等。故行政先例需屬合法者\n      ，乃行政自我拘束之前提要件，憲法之平等原則，並非賦\n      予人民有要求行政機關重複錯誤之請求權。」原告主張：\n      「考選部92年2 月函文中更載明，被告機關曾於91年3 月\n      27日醫事人員考試審議委員會第6 次會議作成決議，『有\n      關經國外醫學系畢業前往與取得學位不同之醫師法第4 條\n      之1 所列九大地區或國家實習，其實習資格予以採認』」\n      等語云云，即要求被告重複做成錯誤之決定，此部分應不\n      可採。\n  ９、原告主張違反行政法上之公益原則：貿然全面開放大量實\n      習訓練與國內醫學院有差異之波蘭醫學生資格，有違公共\n      利益與國民健康。本件根據駐波蘭台北經濟文化辦事處之\n      資料，截至97年度止，目前台灣學生就讀波蘭醫學系及牙\n      醫學系之人數已高達665 人，未來還將有更多台灣學生前\n      往就讀，因此若貿然全面性開放波蘭醫學生准予報考醫師\n      考試，而完全不去依法審查其『實習』是否與國內醫學院\n      相當，後續透過此管道取得醫師報考資格之人將因此暴增\n      ，對國人健康將有莫大之危害有違公共利益。\n（三）原告98年6 月30日申覆書之性質應為行政程序法上之「陳\n      情」，被告就原告之申覆即循陳情程序辦理：\n  １、按行政程序法第168 條、171 條規定，原告針對被告選專\n      字第0983301258號通知補件函所提起之申覆，性質核屬行\n      政程序法上之「陳情」，並非提起行政訴訟前應經之訴願\n      先行程序，蓋綜觀原告之申覆書全文，可知原告除指摘被\n      告所為「應補繳1 年實習證明」之認定及處分係違法不當\n      ，違反行政程序法等相關規定外，另表示被告違反憲法第\n      18條規定侵害人民考試權，因而提出申覆救濟，不但所涉\n      及之法令皆為抽象之原則且並未敘明所提起之訴願類型，\n      全文亦未見明確訴願意旨，故被告無法逕依訴願程序辦理\n      。\n  ２、被告對於原告之陳情，爰審慎召開第6 ～8 次醫師牙醫師\n      考試審議委員會，並通知原告指派代表到會陳述意見，於\n      綜整並獲取初步意見後，更主動向主管機關行政院衛生署\n      尋求協助與配合，被告決議透過簽訂行政契約「暫准報考\n      緩發及格證書」方式解決爭議之措施，亦獲得監察院之肯\n      認與贊同，可知被告對於原告之申覆，根據其申覆意旨，\n      依行政程序法第102 條邀請申覆人到場陳述意見後，始作\n      成「暫准報考緩發及格證書」之處分，為行政程序之一環\n      ，非行政救濟程序之內容。最後並與原告簽訂和解契約，\n      兼顧公益與原告之應考權益，如今原告欲切割主張部分和\n      解契約條文之法律關係不存在，實無理由。\n（四）設若原告於98年6 月30日所提申覆書之真意確為訴願，如\n      今仍可於法定一年期限內再行透過訴願救濟，惟本件確認\n      訴訟之提起並不合法：承被告99年1 月25日答辯（二）狀\n      所述，被告98年6 月25日選專字第0983301258號函之意旨\n      ，不僅止於通知受文者（即原告甲○○等17人）限期補正\n      文件，尚包含因渠等並未符合應考資格，告知原告「如逾\n      期未能補正」，即「不准報名」等意思表示在內，核已具\n      備行政程序法第92條第1項 行政處分之要件而對外生法律\n      上效果，即便系爭通知函未記載行政程序法第96條第1 項\n      第6 款之教示條款，惟依行政程序法第98條第3 項規定，\n      原告得自處分書送達後一年內聲明不服。基此，本件原告\n      若不服被告系爭函文「如逾期未能補正即不准報名」之行\n      政處分，自應依訴願法之規定提起撤銷訴願，如今原告提\n      起本件確認訴訟前並未經訴願前置程序，若依其主張所提\n      起者係「確認法律關係存否之訴」，則依行政訴訟法第6\n      條第3 項規定，自不得提起本件訴訟，而應依訴願法之規\n      定明確對於被告98年6 月25日選專字第0983301258號函進\n      行救濟，若有不服，再於完成訴願前置程序後，循行政訴\n      訟管道續行救濟。\n（五）本件原告並無權利保護必要：\n  １、本件原起訴之原告甲○○等16人，其中已及格之甲○○、\n      己○○、辛○○、癸○○、子○○等5 人業已分發至各署\n      立醫院實習，並已完成報到手續；未及格之11人已由被告\n      於98年12月8 日以選專字第0983302483號函准其報考99年\n      1 月23日舉行之99年第一次專技高考醫師考試分試考試第\n      一試，並已於99年1 月7 日寄發入場證，從而原告等並無\n      任何法律之權利或利益受侵害或有受侵害之虞而有立即以\n      行政訴訟確認判決予以除去之必要，其所提本件訴訟顯然\n      欠缺權利保護之必要而應予程序駁回。\n  ２、至於原告所謂「仍須補行實習成績及格始能應試之第二試\n      限制」，及「已及格之5 人可中止實習要求被告發給考試\n      及格證書」等訴之利益，依本件原告起訴前醫師法等相關\n      法規上針對報考資格早已既定之實質要件，即「學歷證明\n      」與「實習期滿成績及格」，無論本件訴訟之勝敗，原告\n      要不可能脫離法律明訂之應考資格要件，可「不用實習」\n      或「中止實習」而違反平等原則以特例方式取得考試及格\n      證書。是本件原告於新制考試制度下得應醫師考試分試第\n      一試，且已分發實習（及格者）或參加99年第一次專技高\n      考醫師考試分試考試第一試（未及格者）並無疑義，至於\n      醫師考試分試第二試所有應考人皆必須「實習期滿成績及\n      格」亦無不同，原告主張本件仍有權利保護必要即無理由\n      。\n（六）綜上所述，原告既基於自由意願合意與被告簽訂行政契約\n      ，且被告亦依約暫准原告參加考試以合理保障其考試權，\n      原告嗣經「參加」並「完成」考試不及格即應遵照契約之\n      規定正式取得資格再重新報考，不得再任意主張行政契約\n      無效，否則將嚴重違反禁反言原則、誠信原則、公益原則\n      等，為此答辯聲明求為判決：１、駁回原告之訴。２、訴\n      訟費用由原告負擔。\n五、本件應適用之法律：\n（一）按醫師法第2 條規定：「（第1 項）具有下列資格之一者\n      ，得應醫師考試：一、公立或立案之私立大學、獨立學院\n      或符合教育部採認規定之國外大學、獨立學院醫學系、科\n      畢業，並經實習期滿成績及格，領有畢業證書者。二、八\n      十四學年度以前入學之私立獨立學院七年制中醫學系畢業\n      ，經修習醫學必要課程及實習期滿成績及格，得有證明文\n      件，且經中醫師考試及格，領有中醫師證書者。三、中醫\n      學系選醫學系雙主修畢業，並經實習期滿成績及格，領有\n      畢業證書，且經中醫師考試及格，領有中醫師證書者。（\n      第2 項）前項第三款中醫學系選醫學系雙主修，除九十一\n      學年度以前入學者外，其人數連同醫學系人數，不得超過\n      教育部核定該校醫學生得招收人數。」次按專門職業技術\n      人員考試法第5 條規定：「各種考試，得單獨或合併舉行\n      ，並得分試、分地舉行。其考試類、科、地點、日期等，\n      由考選部於考試兩個月前公告之。應考人在學期間得視類\n      科之不同，參加前項所定分試考試最後一試以外之考試。\n      分試考試之類科及其考試規則，由考選部報請考試院定之\n      。」是得應專門職業醫師考試之資格者，必須符合經過國\n      內外大學醫學院畢業，並經實習期滿成績及格二要件。\n（二）依據醫師法第42條授權訂立之醫師法施行細則，經主管機\n      關行政院衛生署於98年9 月16衛署醫字第0980215591號令\n      增訂發布第 1之1條至第1之5 條規定如下：\n  １、第1 條之1 ：「（第1 項）本法（按醫師法）第二條至第\n      四條所稱實習期滿成績及格，指在經教學醫院評鑑通過，\n      得提供臨床實作訓練之醫療機構，於醫師指導下完成第一\n      條之二至第一條之四所定之科別及週數或時數之臨床實作\n      ，各科別考評成績均及格，且持有該醫療機構開立之證明\n      。（第2 項）中央主管機關得就前項實習，辦理臨床實作\n      訓練申請人與醫療機構間之選配分發，並得就該業務委託\n      民間專業機構或團體辦理。」\n  ２、第1 條之2 ：「本法第二條所稱實習期滿，其臨床實作之\n      科別及週數或時數如下：一、內科十二週或四百八十小時\n      以上。二、外科十二週或四百八十小時以上。三、婦產科\n      四週或一百六十小時以上。四、小兒科四週或一百六十小\n      時以上。五、其他選修科別至少三科，每科二週或八十小\n      時以上。前項週數或時數，合計應達四十八週或一千九百\n      二十小時以上。」\n  ３、第1 條之3 ：「本法第三條所稱實習期滿，其臨床實作之\n      科別及週數或時數如下：一、中醫內科十八週或七百二十\n      小時以上。二、中醫傷科八週或三百二十小時以上。\n      三、針灸學科九週或三百六十小時以上。四、中醫婦兒科\n      九週或三百六十小時以上。前項週數或時數，合計應達四\n      十五週或一千八百小時以上。」\n  ４、第1 條之4 ：「本法第四條所稱實習期滿，其臨床實作之\n      科別及週數或時數如下：一、兒童牙科二週或八十小時以\n      上。二、口腔顎面外科八週或三百二十小時以上。三、齒\n      顎矯正科二週或八十小時以上。四、膺復科八週或三百二\n      十小時以上。五、牙周病科四週或一百六十小時以上。六\n      、牙髓病科四週或一百六十小時以上。七、牙體復形科二\n      週或八十小時以上。八、其他選修科別至少三科，合計至\n      少十八週或七百二十小時以上。\n  ５、第1 條之5 ：「前三條所定之臨床實作時數，不包括夜間\n      與假日之值班。」\n      又上開規定，屬醫師法枝節性、技術性之規定，並未逾越\n      母法醫師法授權，未違反法律保留原則，主管機關據以訂\n      立以供認定醫師法第2 條規定之「實習期滿」之考試行政\n      ，本院予以尊重。\n（三）考試主管機關考試院依據上開專門職業技術人員考試法第\n      5 條授權，以96年5 月26日考試院考臺組壹一字第096000\n      38331 號令修正發布專門職業及技術人員高等考試醫師牙\n      醫師考試分試考試規則，第2 條規定：「（第1 項）專門\n      職業及技術人員高等考試醫師牙醫師考試分試考試（以下\n      簡稱本考試）分二試舉行。（第2 項）第一試未及格者，\n      不得應第二試。」第6 條規定：「（第1 項）中華民國國\n      民具有附表一醫師、牙醫師類科所列資格之一者，得分別\n      應本考試醫師、牙醫師類科第一試。（第2 項）具有前項\n      附表一醫師類科第一款至第三款規定資格之一者，於中華\n      民國九十九年一月一日前，得應專門職業及技術人員高等\n      考試醫師考試。（第3 項）具有第一項附表一牙醫師類科\n      第一款規定資格者，於中華民國一０一年一月一日前，得\n      應專門職業及技術人員高等考試牙醫師考試。」第7 條規\n      定：「（第1 項）中華民國國民具有附表一醫師應考資格\n      第一款、第二款、第三款資格之一，牙醫師應考資格第一\n      款，並分別經本考試醫師、牙醫師第一試及格者，得應本\n      考試醫師、牙醫師第二試。（第2 項）六年內第二試未及\n      格者，應重新應本考試第一試。」而上開考試規則附表一\n      應考資格第１點亦明確載明：「……但國外大學、獨立學\n      院醫學系、科畢業者，其實習滿成績及格之認定標準，依\n      行政院衛生中華民國九十八年九月十六日修正發布之醫師\n      法施行細則規定辦理。」上開考試規則，亦經法律授權主\n      管機關訂立，並未逾越母法，與其他法律相互配合，其中\n      就醫師法相關之醫師等考試改採第一試及第二試規定，又\n      訂立三年之過渡期間（自96年間起至98年12月31日止）兼\n      顧規範對象即應醫師考生之信賴利益之保護；從而被告據\n      以為考試行政，本院予以尊重。\n（四）再按考選部組織法第19條規定：「考選部為因應各種業務\n      或特殊需要，得設各種委員會，分別辦理各有關業務之審\n      議或研議等事項。」考試院據此訂定專門職業及技術人員\n      考試審議委員會組織規程，依該組織規程第2 條規定：「\n      （被告機關）為辦理專門職業及技術人員醫師牙醫師考試\n      政策、法規、制度之諮詢、應考資格疑義案件、應考人減\n      免應試科目案件之審議，設醫師牙醫師考試審議委員會，\n      審議應考資格初審不合格或疑義案件。」上開醫師牙醫師\n      考試審議委員會之委員，由行政院衛生署副署長、教育部\n      醫事教育委員會執行秘書、醫學大學醫學院院長、醫學系\n      系主任、教學醫院院長、公會團體代表及被告簡任以上職\n      員組成，並邀請行政院衛生署醫事處及教育部高等教育司\n      派員列席，針對醫師及牙醫師考試應考人應考資格之疑義\n      ，均由上開委員會審議。\n（五）另按「確認行政處分無效及確認公法上法律關係成立或不\n      成立之訴訟，非原告有即受確認判決之法律上利益者，不\n      得提起之。其確認已執行完畢或因其他事由而消滅之行政\n      處分為違法之訴訟，亦同。」行政訴訟法第6 條第1 項訂\n      有明文。因此：\n  １、前述「確認法律關係之成立或不成立」，因實務上早已擴\n      及於法律關係之存在或不存在，故於行政訴訟法修正時，\n      認不必嚴加區別，而未特別規定「存在或不存在」之文字\n      （參見學者陳計男著行政訴訟法釋論第188 頁）；且觀本\n      條規定之立法理由，其於公法上法律關係「成立或不成立\n      」文字下又特別註明包括「存在或不存在」，可知，本條\n      關於「確認公法上法律關係成立或不成立訴訟」之規範，\n      應包含「確認公法上法律關係存在或不存在之訴訟」。\n  ２、再按所謂公法上之法律關係，係指公法上之權利義務關係\n      ，即二以上之法律主體，就公法上具體事件，依法律規定\n      所成立之法律上關係而言；同時公法上之具體事件，亦必\n      須有特定生活事實之存在，因法規之規範效果，在兩個以\n      上之權利主體間所產生之公法上權利義務關係，或產生人\n      對權利客體間之公法上利用關係；又公法上法律關係之成\n      立有直接基於法規規定者，亦有因行政處分、行政契約或\n      事實行為而發生者，但法規、事實行為均非法律關係本身\n      ，故皆不得以其存否為確認訴訟之標的。\n  ３、又按所謂即受確認判決之法律上利益，須因法律關係之存\n      否不明確，致原告在公法上之地位有受侵害之危險，而此\n      項危險得以對於被告之確認判決除去之者，始足當之。故\n      原告提起確認公法上法律關係不存在之訴，若欠缺即受確\n      認判決之法律上利益，核屬欠缺權利保護之必要即無確認\n      訴訟訴之利益，在法律上為無理由，應以判決駁回之。\n六、兩造對事實概要之記載及下開其他事實、醫師考試制度之變\n    革等均不爭執，並有原告提出之系爭「考選部暫准報考緩發\n    及格證書行政契約」16件、原告等人畢業學校整理表、「98\n    年第二次專門職業及技術人員高等暨普通考試醫事人員（不\n    含牙醫師、助產師、職能治療師）、中醫師、心理師、營養\n    師考試暨醫師考試分試考試」應考須知、經我國駐外使館驗\n    證之原告等人於波蘭各醫學院畢業證書、歷年成績單、實習\n    證明文件16件、被告98年6 月25日選專字第0983301258號函\n    及原告之申覆書16件、被告98年7 月8 日召開醫師牙醫師考\n    試審議委員會第七次會議新聞稿；及被告提出原告等人及台\n    灣醫學生至被告處陳情紀要及相關報導、被告98年7 月14日\n    選專字第0983301452號函乙份、行政院衛生署98年7 月14日\n    衛署醫字第0980208143號函、監察院糾正案文節錄、監察院\n    通過對衛生署、教育部處理波蘭醫學系畢業生回國報考醫師\n    考試相關問題顯有違失之糾正案新聞稿及相關報導、被告98\n    年9 月30日選專字第09833020281 號函、被告98年6 月25日\n    選專字第0983301258號函、行政院衛生署98年12月1 日衛署\n    醫字第0980087896號函及原告己○○等五人實習分發一覽表\n    、被告98年12月8 日選專字第09833024 83 號函、「98年第\n    二次專門職業及技術人員高等暨普通考試醫事人員（不含牙\n    醫師、助產師、職能治療師）、中醫師、心理師、營養師考\n    試暨醫師考試分試考試」應考須知、原告15人（莊家順及羅\n    友祺兩人除外）所回傳被告98年6 月25日選專字第09833012\n    58號函附件1 之回覆通知15件、行政院衛生署99年3 月12號\n    令、被告提出之原告等人報名表件及學經歷證件、原告與被\n    告所簽訂之系爭行政契約、被告提出之被告醫師牙醫師考試\n    審議委員會第5 次、第6 次、第7 刺、第8 次會議記錄（不\n    可閱覽卷）、98年第二次專門職業及技術人員高等考試醫師\n    考試、醫師考試分試考試應考人員與考選部簽訂行政契約名\n    冊（均為影本）附本院卷及原處分卷可查，足認為真實。\n（一）本件其他事實：\n  １、本件98年醫師考試應考須知第6 頁「應考資格證明文件」\n      醫師部分，除需繳驗「畢業（學位）證書」外，於醫師（\n      應試全部科目6 科）之附註欄載明：「前開醫師（應試全\n      部科目6 科），依專門職業及技術人員高等考試醫師牙醫\n      師考試分試考試規則第6 條第2 項規定，辦理至民國99年\n      1 月1日前為止，凡符合報考資格之應考人，請及早規劃\n      因應。」醫師（一）（應醫師考試分試考試第一試）之附\n      註欄記載：「以外國學歷報考醫師（一）者：依專門職業\n      及技術人員高等考試醫師牙醫師考試分試考試規則第6 條\n      附表一規定，須為教育部採認之國外大學、獨立學院醫學\n      系、科畢業，並經實習期滿成績及格，領有畢業證書者，\n      繳驗證明文件另見8.」。\n  ２、被告因原告等波蘭國等大學醫學院畢業，有「實習期滿成\n      績及格」所生之爭議，由審議委員會作成「暫准報考緩發\n      及格證書」決議前，於98年7 月14日以選專字第09833014\n      52號函徵求行政院衛生署之同意，經行政院衛生署於同日\n      衛署醫字第0980208143號函覆被告同意略以：「……貴部\n      函請本署配合辦理國外醫學畢業生暫准參加專門職業及技\n      術人員高等考試醫師、牙醫師考試及格人員之實習，敬表\n      同意。至實習期滿成績及格之證書，將由各該醫療機構發\n      給，另本署將請各醫療機構列冊函報本署，俾彙整成冊函\n      送貴部，作為核發考試及格證書之參考……。」\n  ３、監察院98年10月中旬針對原告等波蘭國大學醫學院之學歷\n      報考資格等問題，糾正行政院衛生署、教育部略以：波蘭\n      93年加入歐盟以來迄今不過6 年期間，國人於當年即前往\n      該國就讀醫學系者，於96年及97年間已陸續畢業，2 年間\n      即有37名畢業生以該國學歷應考並通過醫師考試，目前尚\n      就學中之人數，亦約670 名，相較於歐盟其他國家之留學\n      人數寥廖可數，留學波蘭人數之多，顯非尋常，非但嚴重\n      影響國內醫學系招生人數之管制總量，且其入學管道與國\n      內醫學系嚴格篩選學生素質相較，亦明顯寬鬆，甚至前往\n      該國取得醫學系學歷者如循國內升學管道，多數尚無法取\n      得進入國內醫學系就讀之資格，致國人對波蘭大學醫學系\n      開設英語學程廣收外籍學生之教育品質多存疑慮等語。\n（二）醫師考試制度之變革：\n  １、醫師法第2 條第1 項第1 款規定（醫師法於91年1 月16日\n      總統（91）華總一義字第09100007520 號令修正公布全文\n      43條；並自公布日起施行）自公布施行迄今均未修正。\n  ２、專門職業及技術人員高等考試醫師牙醫師考試分試考試規\n      則，經主管機關考試院以94年12月22日考臺組壹一字第09\n      400112051 號令訂定發布全文17條；並自96年1 月1 日施\n      行。是有開上開考試規則第2條規定，醫師之專門職業及\n      技術人員高等考試，已明文規定自「民國96年」開始實施\n      分試，即改採二階段考試制度，且慮及制度變革，為保障\n      應考人信賴利益，始訂定3 年之過渡期間，自99年1 月1\n      日起始全面施行。\n  ３、為配合國內醫學教育改革，被告92年度考選制度研討會，\n      邀請學者專家就國家考試醫師考試分試之可行性進行研討\n      ，報告人何橈通院長建議參考國外制度，改為二階段分試\n      ，第一試於國內大學醫學系修畢基礎課程時考，第二階段\n      於第一試及格，經實習期滿取得畢業證書後考，建議之初\n      各界意見紛陳，後經被告邀請各界研商，始漸達成共識，\n      於93年8 月30日正式召開「高等考試醫師考試改進相關事\n      宜會議」決定醫師考試採行分試制度，考試院乃於94年12\n      月22日配合訂定發布上開「專門職業及技術人員高等考試\n      醫師考試分試考試規則」，明訂自「民國96年」開始實施\n      分試，但具有該規則附表一醫師類科第1 款至第3 款規定\n      資格之一者（舊制醫學院需實習一年始能畢業之畢業生）\n      ，於民國99年1 月1 日前，得應專門職業及技術人員高等\n      考試醫師考試（應試全部科目6 科），俾給予該等應考人\n      3 年之緩衝期，以維護其應考信賴保護利益權利，而99年\n      1 月1 日起即全面採行醫師考試分試考試制度（參見前開\n      規則第6 條、第7 條規定，第1 試及格後始可應考第2 試\n      ）。\n七、本件兩造主張之事實，相關法律詳如上述，是本件主要爭點\n    乃原告所提出之波蘭國醫學院畢業證書等文件，是否符合「\n    經實習期滿成績及格」之要件？又原告提起之確認之訴，是\n    否有即受確認判決法律上之利益？以下就原告之訴有無理由\n    ，依序論述爭點如下。\n（一）本件原告主張系爭行政契約之第2 條、第3 條、第4 條等\n      違反行政程序法等相關法律規定，致發生無效而自始不成\n      立，故提起本件確認公法上法律關係不存在之訴；參照上\n      開有關行政訴訟法第6 條確認公法上法律關係「成立或不\n      成立」之規範，應包含「確認公法上法律關係存在或不存\n      在之訴訟」之說明，本件原告聲明形式上觀察，與行政訴\n      訟法第6 條第1 項前段確認公法上法律關係成立不成立之\n      訴訟類型相符，應先敘明。次查原告主張其起訴之訴訟標\n      的法律關係的原因事實，並無行政處分之存在，即兩造間\n      行政法上之法律關係非因行政處分（而係有償之雙務行政\n      契約）而發生，依據本院前揭說明，在確認之訴部分，尊\n      重當事人之處分權，從而，從形式上原告提起本件確認之\n      訴並未違背行政訴訟法第6 條第3 項規定之「確認訴訟之\n      備位性原則」，亦應先予敘明。\n（二）兩造對本件訟爭之行之行政行為（即原告主張為雙務之行\n      政契約，被告主張之行政程序法第136 條替代行政處分之\n      和解行政契約；即前述之系爭行政契約）之內容及簽立過\n      程等事實均不爭執詳如上事實概要欄所載；從而縱認系爭\n      行政契約為原告主張之「行政契約」，然本件系爭行政契\n      約不論是第1 條及第2 、3 、4 條及其他條文整體始形成\n      一個公法上之法律關係，上開法律關係特別是第1 條使用\n      「爰暫准乙方（按原告）報告98年醫師考試」，與第2 條\n      「乙方同意倘考試成績及格，願意接受甲方（按被告）暫\n      不發給醫師考試及格證書之決定……」及第3 條「乙方倘\n      於考試榜示及格三年內，未依上述方式，於國內實習期滿\n      成績及格……」及其他條文規定，整體構成一個完整之公\n      法上法律關係，彼此互相依存，不能各自分開創設獨立之\n      公法上法律關係，換言之，本件系爭行政契約全部實屬一\n      完整不可分之公法上法律關係，原告切割完整之法律關係\n      ，僅認系爭行政契約第2 、3 、4 條規定可分且違反行政\n      程序法等法律，認屬無效，而僅留存第1 條暫准報考之被\n      告之行政處分權，認並不存在「行政契約」，提起本件確\n      認公法上法律關係不存在之訴，其主張及事實理由顯有矛\n      盾（本件系爭行政契約並不可分），本難認有理由。\n（三）原告所提出之波蘭國醫學院畢業證書等文件，並不符合前\n      開醫師法第2條之「經實習期滿成績及格」要件。\n  １、按前開98年9 月16日醫師法施行細則部分條文修正總說明\n      略以：「……對持國外學歷回國參加考試者，其於國外使\n      用之語言及接觸之疾病型態，顯與國內各類醫學生有所不\n      同，需要在其參加考試前，於國內醫療機構接受與國內醫\n      學生相當之臨床實作科別及週數或時數之訓練，以確認其\n      與我國的醫學院醫學系畢業生具有相似之臨床經驗。」另\n      依醫師法施行細則修正條文第1 條之2 之規定，就實習期\n      滿，其臨床實作之科別及週數或時數，並無區分國內外，\n      表示國內外之「實習期滿」標準必須一致，應先敘明。又\n      醫師法施行細則乃醫師法授權主管機關行政院衛生署訂立\n      之法規命令。而上開解釋醫師法第2 條「經實習期滿成績\n      及格」要件，並未逾越母法，本院應予尊重等情，詳如上\n      述，從而不論醫師法施行細則是否增修上開規定，均應為\n      相同解釋，應先敘明。\n  ２、次查本件原告報告98年度醫師考試後，被告認原告等人持\n      波蘭國學歷證件，有關是否「經實習期滿成績及格」要件\n      有疑義，乃送請醫師牙醫師考試審議委員會98年6 月19日\n      第5 次會議審議，經認為原告所提證件不符，乃決議通知\n      原告補繳畢業後1 年實習證明後再議，被告乃於同年月25\n      日選專字第0983301258號書函通知補件。原告陸續向被告\n      提出申覆，被告為求慎重，即於同年7 月3 、8 日及15日\n      又分別召開醫師牙醫師考試審議委員會第6 、7 、8 次會\n      議。其中第6 次會議決議，以原告等均未提出合乎規定之\n      實習證明不准報考，第7 次會議同意應考人（含原告）推\n      派代表到場說明，惟決議仍以原告在學期間之見習與實習\n      未作明確區別，依國內學制其大多屬見習性質並非「實習\n      」，與國內學制1 年完整實習有別，核與醫師法第2 條「\n      ……實習期滿成績及格……」之規定不符，不准報考。第\n      8 次會議經被告協議相關單位提出建議經審議後決議：「\n      一、同意被告與波蘭波茲南等4 所醫學大學及愛爾蘭都柏\n      林大學醫學院畢業生簽訂行政契約以「暫准報考緩發及格\n      證書」方式，並對行政契約修正通過」（即原處分卷不可\n      供閱覽部分卷），被告依上開第8 次會議議決，始有本件\n      原告主張之系爭行政契約。又參照上開法律說明可知，被\n      告醫師牙醫師考試審議委員會之組織合法、前述審議程序\n      正當合法，亦應先予敘明。\n  ３、又醫師法第2 條規定之「經實習期滿成績及格」構成要件\n      ，其所謂實習期滿，則屬不確定概念，而法規中不確定法\n      律概念，不論是要件或法律效果，或於多重解釋發生時，\n      由行政機詮釋或適用之結果，作成單一解釋與適用。行政\n      法院就此種行政機關所為不確定法律概念之判斷及選擇，\n      固得監督，惟體現憲法、立法、行政、司法權之作用，僅\n      為合法性監督，即對行政機關之裁量、判斷如認有逾越權\n      限或濫用、恣意情事，自應予以糾正；申言之，行政法院\n      監督及審查密度如何，自應事件不同而異，並應視組織及\n      程序是否完備，判斷之政策性及專業性高低等，而認行政\n      機關有一定之判斷餘地。是以，上開醫師法第2 條規定之\n      醫師應考資格之規定，涉及醫師專業技術性之實際需要，\n      與國民健康及生命之公益息息相關，並具有高度之屬人性\n      ，因此，辦理醫師考試機關，對上開「實習期滿」不確定\n      法律概念之解釋及適用，只要是非基於錯誤之事實，或基\n      於事件無關之考量、或組織不合法、未遵守法定程序，或\n      顯然違反平等原則、比例原則及一般公認之價值判斷標準\n      者外，行政法院應採取較低密度審查標準，並應尊重其判\n      斷餘地。查本件原告所提出之波蘭國醫學院之「實習」是\n      否符合醫師法第2 條第1 項第1 款、教育部大學辦理國外\n      學歷採認辦法第8 條規定之「實習」或「相當於實習」，\n      經被告所屬醫師牙醫師考試審議委員會之專業委員第5 、\n      6 次會議決議，認原告應考時提出之波蘭國醫師院之學歷\n      資料，與上開「實習期滿」要件不符，而不准報考，並通\n      知原告補提出實習一年之證據，亦有被告提出不可閱卷第\n      3-9 頁、第30-36 頁可證。而本件被告作成此部分決定所\n      依據之醫師牙醫師考試審議委員會審議過程合法正當又如\n      上述，同時被告不准原告報考98年醫師考試之決定（原告\n      提出之波蘭國醫師院之學歷資料，與上開「實習期滿」要\n      件不符）並非基於錯誤之事實或其他無關之考量，亦未違\n      反一般公認行政法價值判斷標準；參照上開說明，本院自\n      宜予尊重。\n  ４、綜上，本件原告之提出報考之學歷證件，不符實習期滿之\n      要件，從而被告抗辯系爭行政契約之第2 、3 、4 條規定\n      並無違法，即足認定。因此原告主張違法並提起本件確認\n      之訴並無理由。\n  ５、又如前述應適用之法律說明，原告提起本件訴訟（98年10\n      月9 日）前，醫師法施行細則業於98年9 月16日增訂第1\n      之1 條至第1 之5 條規定；而參考前述專門職業及技術人\n      員高等考試醫師牙醫師考試分試考試規則（考試院以94年\n      12月22日考臺組壹一字第09400112051 號令訂定發布）規\n      定及說明三，自98年9 月16日醫師法施行細則部分增訂條\n      文起，醫師考試應全面採行醫師考試分試考試制度（即專\n      門職業及技術人員高等考試醫師牙醫師考試分試考試規則\n      6 條、第7 條規定，第1 試及格後始可應考第2 試）；本\n      件原告訟爭「實習期滿」應考資格之爭議，因此而不續存\n      在，從而原告就系爭行政契約第4 條規定，退步言，姑不\n      論其是否具備法律關係性質，請求確認法律關係不存在，\n      即無確認之利益，應併敘明。\n  ６、再查原告雖陳稱98年以前持本件波蘭國原告畢業學校相同\n      證件報考醫師考試均獲准考，本件則不同意報考，是系爭\n      行政契約第2 、3 、4 條規定顯有違平等原則云云。惟：\n      (1)按憲法之平等原則要求行政機關對於事物本質上相同之\n        事件作相同處理，乃形成行政自我拘束，惟憲法之平等\n        原則係指合法之平等，不包含違法之平等。故行政先例\n        需屬合法者，乃行政自我拘束之前提要件，憲法之平等\n        原則，並非賦予人民有要求行政機關重複錯誤之請求權\n        。\n      (2)本件原告主張之波蘭國學歷證件等，與醫師法第2 條「\n        經實習期滿成績及格」要件不符如上述，是原告持98年\n        以前之被告准報考之不合法案例，主張被告應受行政自\n        我拘束云云，參照首開說明，本無理由。\n      (3)再查依被告統計，持波蘭醫學院學經歷之學生報考醫師\n        考試，已由95年1 人報考、96年17人報考急速擴增至98\n        年118 人報考) ，目前循相同管道在波蘭修習醫學之台\n        灣留學生已高達六百多人，且波蘭醫學院係針對外國學\n        生開設專班（絕大多數係台灣學生，其中亦有其他國家\n        學生）以英語開設的課程，而留學生本身在波蘭醫院實\n        習部分亦需透過翻譯與病人互動等語明確。而被告醫師\n        牙醫師考試審議委員會第7 次會議，亦邀請原告等派代\n        表到會陳述意見如前述，經審議委員等專家詳細詢問原\n        告等在波蘭修習醫學系課程與實習實際之狀況後，認為\n        從英語國際班實習互動與醫院值夜班情況，認為與國內\n        實習未完全相當等事實，亦有原處分卷不可供閱覽部分\n        第49～64頁可證，是本件被告經審慎調查後，為系爭行\n        政契約之第2 、3 、4 條規定，亦屬有據；綜上此部分\n        原告違反平等原則之主張云云，並不足採。況且，契約\n        之關係乃立於當事人自治原則，契約內容未違反法律之\n        強行規定（無效）或公序良俗外，均不應「禁反言」，\n        而本件原告對於被告拒絕報考，不以通常之行政救濟程\n        序，謀求救濟，卻以其他方式，以簽定「系爭行政契約\n        」取得報考資格後，反言被告違反平等原則，有失誠信\n        ，委無可取。\n（四）原告乙○○等11人（即除甲○○、己○○、辛○○、癸○\n      ○、子○○5 人以外），雖簽立系爭行政契約然參加本件\n      98年醫師考試但未獲及格評定之事實詳如上述。而醫師法\n      施行細則於原告起訴前亦增修第1 之1 條至第1 之5 條規\n      定亦如前述，是本件醫師法第2 條「經實習期滿成績及格\n      」之爭執，已有法令明確規定，且原告乙○○亦依照新修\n      正之規定檢附證件報考99年1 月23日舉行之99年第一次專\n      技高考醫師考試分試考試第一試，並經被告以98年12月8\n      日選專字第0983302483號函准予報考；是參照上開行政訴\n      訟法第6 條規定之法律說明，原告乙○○等11人有關報考\n      醫師考試之公法上法律關係未有不明確，而致原告在公法\n      上應醫師考試之之地位有受侵害之危險，更無從藉由原告\n      提起之本件確認之訴除去之，從而此部分原告之訴欠缺權\n      利保護之必要即無確認訴訟訴之利益，在法律上為無理由\n      ，應以判決駁回之。\n（五）原告甲○○、己○○、辛○○、癸○○、子○○5 人參加\n      98年醫師考試及格，並已分發至各署立醫院實習詳如上述\n      ，而本件系爭行政契約第2 、3 、4 條規定並無原告所指\n      之違法而不存在詳如上述，是此部分原告訴請確認法律關\n      係不存在云云，亦無理由，應予駁回。\n（六）本件應適用之法律及事實理由及本院見解詳如上述，兩造\n      其餘攻擊防禦方法，核與判斷結果無涉，爰不一一敘明。\n八、據上論結，本件原告之訴為無理由，依行政訴訟法第98條第\n    1項前段、第104 條，民事訴訟法第85條第1 項前段判決如\n    主文。\n中    華    民    國    99    年     5    月   12     日\n                  臺北高等行政法院第一庭\n                         審 判 長 法  官   王立杰\n                                  法  官   楊得君\n                                  法  官   洪遠亮\n上為正本係照原本作成。\n如不服本判決，應於送達後20日內，向本院提出上訴狀並表明上\n訴理由，如於本判決宣示後送達前提起上訴者，應於判決送達後\n20日內補提上訴理由書（須按他造人數附繕本）。\n中    華    民    國    99    年     5    月   12     日\n                                  書記官   陳德銘\n",
  "structure": {
    "main": "原告之訴駁回。\n訴訟費用由原告負擔。",
    "fact": "一、程序事項：按當事人應就訴訟關係為事實上及法律上之陳述\n    ，行政訴訟法第122 條第2 項定有明文，又同法第132 條準\n    用民事訴訟法第195 條第1 項規定：「當事人就其提出之事\n    實，應為真實及完全之陳述。」即當事人對事實及法律上之\n    訴訟關係，有完全陳述之義務，此就行政訴訟在人民公權利\n    保障理念下，權利是否以及如何行使，自應委由權利人自主\n    決定，故有關訴訟程序之開始，訴訟標的之特定，訴訟程序\n    之終結等，自應賦與當事人即人民自主權，即人民對於訴訟\n    標的或訴訟中之訴之聲明有一定之處分權，從而審判長於訴\n    訟程序中行使闡明義務後，若原告即處分權人仍堅持己見，\n    參照上開說明，本院即已盡闡明義務。本件本院經闡明依司\n    法院釋字第546 號解釋，拒絕應考之決定，性質屬行政處分\n    ，系爭「考選部『暫准報考緩發及格證書』行政契約」第2\n    條、第3 條、第4 條是否為行政處分之附款（條件或負擔）\n    請原告確認，然原告仍稱上開「考選部『暫准報考緩發及格\n    證書』行政契約」性質為行政契約，且屬有對價關係之行政\n    契約，並非行政處分，故仍應提起本件確認之訴而無庸更改\n    其聲明及陳述；基於尊重當事人之處分權，本院仍就原告聲\n    明主張之範圍審認，並敘明理由，應先敘明。\n二、事實概要：原告等人分別波蘭國波茲南醫學大學、羅茲醫學\n    大學、西里西亞醫學大學之畢業生（詳如附件），欲參加被\n    告於民國（下同）98年8 月1 日至98年8 月2 日舉辦之「98\n    年第二次專門職業及技術人員高等暨普通考試醫事人員（不\n    含牙醫師、助產師、職能治療師）、中醫師、心理師、營養\n    師考試暨醫師考試分試考試」（下稱98年醫師考試）。原告\n    依據被告所制訂之應考須知第八頁第八點之規定，均於限定\n    期間內，提出經我國駐外使館驗證之波蘭各醫學院畢業證書\n    、歷年成績單、實習證明等文件，向被告提出報名。嗣被告\n    以98年6 月25日選專字第0983301258號函分別通知原告等，\n    略以：(一)、依據本部醫師牙醫師考試審議委員會第五次會議\n    決議辦理。(二)依專門職業及技術人員高等暨普通考試醫事人\n    員考試規則附表一醫師類科應考資格第1 款之規定，……畢\n    業，並經實習期滿成績及格，領有畢業證書者，……(三)依據\n    會議決議結果，原告應考資格證明文件未齊，所繳驗之實習\n    證明不予採認，應補繳自各該校畢業以後的一年實習證明。\n    (四)原告尚能補件，請於98年6 月30日通知傳真被告，並於98\n    年7 月10日前補繳相關實習證明文件之原本影印本及中文議\n    本……，憑以覆審，逾期不准報名，所繳報名費用，一律收\n    繳國庫，概不退還……等語。嗣原告接獲上開函件後分別於\n    98年6 月間陸續向被告提出回覆略以：原告申請准予暫時報\n    名，相關證明將於98年7 月10日前寄送被告等語；另由原告\n    等考生家長等向被告陳情，原告等亦陸續於98年6 月29日、\n    30日、7 月1 日陸續向被告提出申覆。嗣被告於98年7 月6\n    日、9 日再召開醫師牙醫師考試審議委員會第六、七次會議\n    ，其中第七次會議邀請波蘭國等醫學院畢業生之考生代表與\n    會說明有關實習情形後，認為原告等34人提出證明，因見習\n    與實習未區別，依國內學制其大多屬見習性質並非「實習」\n    ，與國內學制1 年完整實習有別，爰與醫師法第2 條「……\n    實習期滿成績及格……」之規定不相當，不予報考。原告除\n    再向被告繼續陳情外，亦曾陸續自98年7 月13日、14日起，\n    分別向本院具狀聲請假處分保全程序。嗣被告98年7 月16日\n    召開醫師牙醫師考試審議委員會第八次會議審議結果，同意\n    被告與波蘭國醫學院畢業生之原告等考生，簽定行政契約，\n    以「暫准報考緩發及格證書」方式，限報考本件98年第二次\n    專門職業及技術人員考試。而原告接獲通知後，於98年7 月\n    中旬後，簽訂被告寄發之「考選部『暫准報考緩發及格證書\n    』行政契約」（下稱系爭行政契約）一式三份，系爭行政契\n    約記載「……一、甲方在乙方應考資格中「實習期滿成績及\n    格」部分與國內醫學院實習期間及內容是否相當尚具爭議情\n    況下，……甲方暫准乙方報考98年第2 次專門職業及技術人\n    員高等考試醫師考試。二、乙方同意倘考試成績及格，願意\n    接受甲方暫不發給醫師考試及格證書之決定，俟自行聲請或\n    接受行政院衛生署安排於國內適當層級之醫療機構，完成與\n    國內醫學院相當期間與內容之實習，於實習期滿成績及格後\n    ，由相關醫療機構出具實習證明並由行政院……。三、乙方\n    倘於考試榜示及格三年內，未依上述方式，於國內實習期滿\n    成績及格或實習不及格，甲方將依專門職業及技術人員考試\n    法第23條規定，以自始不具備應考資格為由，報請考試院撤\n    銷考試及格資格，不發給考試及格證書。四、乙方同意未及\n    格，應依醫師法施行細則修正發佈之有關實習規定，經實習\n    期滿成績及格後，始得再行報考醫師考試分試第一試。……\n    」，原告於系爭行政契約上簽名後，陸續於98年7 月20日左\n    右寄回被告。被告於收到原告所簽署並繳回之系爭行政契約\n    書後，始將行政契約書一份及准考證併同寄給原告等，原告\n    等人陸續於98年7 月23日左右收到前述行政契約及准考證，\n    於98 年8月1 日參加該次醫師考試。而上開醫師考試業於98\n    年9 月30日榜示，原告甲○○、己○○、辛○○、癸○○及\n    子○○5 人醫師考試及格，同日被告亦依系爭行政契約約定\n    ，將甲○○等5 人及格人員名冊函送至行政院衛生署，請其\n    安排渠等至國內各醫療機構實習；行政院衛生署則以98年12\n    月1 日衛署醫字第0980 087896 號函，分發上開考試及格之\n    原告至各署立醫院實習。其餘未及格之原告業已由被告於98\n    年12月8 日以選專字第09 83302483 號函准其報考99年1 月\n    23 日 舉行之99年第一次專技高考醫師考試分試考試第一試\n    ，並已於99年1 月7 日寄發入場證在案。又本件原告於98年\n    10月9 日向本院提起本件確認公法上法律關係不存在之訴訟\n    。\n三、原告起訴主張略以：\n（一）程序方面：\n  １、本件原告提起之訴訟乃確認系爭行政契約中之第二、三、\n      四條約定之法律關係不存在，並非確認行政處分無效或違\n      法，應屬「確認法律關係存否之訴」。另被告98年6 月25\n      日選專字第0983301258號函文，主旨係載明要求原告等補\n      正文件，並未記載已否准原告等之報考等事實甚明；況且\n      原告等人亦已對被告上開函文均以書面提出申覆表示不服\n      ，然被告對於原告等上開申覆書並未再回函表示予以駁回\n      或否准原告等之報考，足證被告稱原告應對其98年6 月25\n      日否准處分提起撤銷之訴，並無理由；故本件原告就系爭\n      行政契約內容提起確認訴訟並無違反備位性原則。\n  ２、本件原告應考資格是否具備，應依醫師法第2 條第1 項第\n      1 款及依專門職業及技術人員考試法第5 條規定，所制定\n      之專門職業及技術人員高等考試醫師牙醫師考試分試考試\n      規則第六條之附表一、應考須知第6 頁亦明確規定，原告\n      等人報考系爭醫師考試之應考資格為「符合教育部採認之\n      國外大學、獨立學院醫學醫學系、科畢業，並經實習期滿\n      成績及格，領有畢業證書者」等規定認定。原告報考資格\n      符合上開法律規定，故並無被告所稱會將行政契約變成授\n      益行政處分之情形。另查系爭行政契約第4 條對本件醫師\n      考試未及格之原告11人言，顯違反法律不溯既往原則，且\n      剝奪此部分原告報考下次考試之應考資格，故就此次考試\n      未及格原告12人而言，當然具確認判決之法律上利益，而\n      得提起確認訴訟。\n  ３、關於已考試及格之原告甲○○、己○○、辛○○、子○○\n      、癸○○雖已分發至各署立醫院實習，然本件系爭醫師高\n      等考試及系爭行政契約簽立當時（98年8 月2 日），被告\n      系爭醫師考試分試考試規則尚未修訂，故被告於98年10月\n      14日修訂之上開考試規則，並無溯及效力，被告抗辯此部\n      分原告訴訟無保護必要云云，應屬無據。又本件訴訟獲致\n      勝訴判決時，原告等甲○○5人即可中止實習而要求被告\n      發給考試及格證書，故原告等5 人自仍有提起本件訴訟之\n      法律上利益及權利保護必要。\n  ４、被告98年6 月25日函文僅要求原告補正文件，並未記載已\n      否准原告之報考等，而原告對上開函文均已向被告提出申\n      覆書請求救濟，但被告對原告申覆書未為任何處置，亦未\n      作成駁回之決定，則原告亦無從進行後續行政訴訟之救濟\n      程序；且縱使撤銷上開被告98年6 月25日函文之處分，本\n      件系爭行政契約不當然因此失其效力，足見原告仍有提起\n      本件確認之訴之法律上利益及權利保護必要。是被告稱本\n      件訴訟之提起違反行政訴訟法第6 條第3 項規定云云，應\n      屬無理由。\n  ５、本件原告等人分別留學於波蘭國波茲南醫學大學、羅茲醫\n      學大學、西里西亞醫學大學畢業，並經實習期滿成績及格\n      ，已符合法定應考資格之要件，被告即應准予原告報考，\n      但原告竟以系爭行政契約，在未有法律明文授權下，課與\n      原告額外之實習義務，使原告須於考畢後再補為實習，否\n      則不發給證書或不得報名往後年度之考試，即屬侵害原告\n      之權利，是原告權利受侵害甚明確；原告在無其他救濟途\n      徑之情形下，為保障自身取得合格證書之權利，方先依照\n      該契約之內容補行實習，故本件確認之訴確認系爭行政契\n      約之第2條等該契約條款無效而該法律關係不成立，則原\n      告自可免於此等義務，被告稱無權利保護之必要云云，應\n      屬無理由。\n（二）實體部分：\n  １、被告要求原告等所簽訂之系爭行政契約其中第二、三、四\n      條約定應屬違法無效而不存在：\n      (1)依據醫師法第2 條第1 項第1 款規定及專門職業及技術\n        人員高等考試醫師牙醫師考試分試考試規則第6 條之附\n        表一、應考須知第6 頁亦明確規定，原告應考資格為「\n        符合教育部採認規定之國外大學畢、獨立學院醫學醫學\n        系、科畢業」並「經實習期滿成績及格」而「領有畢業\n        證書者」即具有應考資格；而被告卻於系爭「暫准報考\n        緩發及格證書」行政契約內容所示，顯係約定以被告為\n        准予原告參加考試受益行政處分，與原告需重新或補行\n        實習及接受暫緩發及格證書，為雙方對待給付義務，而\n        成立行政契約中之雙務契約。惟所謂應考資格之訂定須\n        符合公平、公開原則和保障人民權益之目的乃屬當然，\n        自不得依據雙方之契約約定而有所變更，故仍應以上開\n        醫師法、專門職業及技術人員高等考試醫師牙醫師考試\n        分試考試規則等相關規定之要件，決定原告等人之應考\n        資格，即原告如符合應考資格，被告即應准予應考，反\n        之則否，被告依法並無行政裁量空間，應屬行政程序法\n        第135 條規定但書規定，依其性質不得為行政契約之情\n        形。\n      (2)該雙務契約之內容係約定原告等人考試後應再實習，顯\n        與確保應考人能於一定期限內，提出考試前已經具備應\n        考資格之證明無關，故與為確保准予考試受益行政處分\n        法定要件履行，即考試前已經具備應考資格為准許應考\n        受益處分之法定要件無關，故依據行政程序法第137 條\n        第2 項規定不得作成行政契約。綜上，被告准許原告考\n        試之受益行政處分之性質或依法律規定應不得締結行政\n        契約，故被告「暫准報考緩發及格證書」行政契約，違\n        背禁止規定而應為無效而不存在。\n      (3)且系爭行政契約第2 、3 、4 條約定應屬無效違背行政\n        程序法第135 條但書已如前述，故被告以之作為行政契\n        約，依上開規定，應屬無效；況有關原告考試後依法應\n        否再為實習或如何實習之事項，應屬於醫師法相關法令\n        所規範，被告依法並非該事項之主管機關，被告依法顯\n        無訂定上開事項行政契約之權限，應屬違反行政程序法\n        第14 2條、第111 條第1 項第6 款規定，足證上開系爭\n        行政契約之約定應為違法無效而不存在。\n  ２、考試機關所訂定各類科之應考資格時，亦應受一般法律原\n      則之拘束。惟查：\n      (1)本件被告所單方制訂之系爭行政契約條款，顯違反依法\n        行政原則。即依憲法第18條及中央法規標準法第5 條第\n        1 項第2 款之規定，上開應考資格之標準或限制，應以\n        法律規定之。前開所稱法律規定，即為前述醫師法第2\n        條規定及依專門職業及技術人員考試法第5 條規定，所\n        制定之專門職業及技術人員高等考試醫師牙醫師考試分\n        試考試規則第六條之附表一。被告依據依行政程序法第\n        4 條規定「依法行政原則」，不得再以系爭行政契約另\n        行增定准予考試之條件，被告擅予增加法律所未有之限\n        制，應屬違法而無效。\n      (2)本件被告所訂系爭行政契約條款，違反行政程序法第6\n        條規定之「平等原則」。查原告於波蘭國各醫學院求學\n        過程，均依據該大學學制、課程內容之要求完成學業，\n        並經實習期滿成績及格，方取得畢業證書，而原告報考\n        本件醫師考試所提出之應考資格證明文件，均符合上開\n        應考須知之規定，亦與歷年被告機關辦理相同考試時，\n        所認定准予應考之波蘭國暨其他外國留學生學生之情形\n        皆無任何不同。且依被告91年3 月27日醫事人員考試審\n        議委員會第六次會議決議及醫師法第四條之一規定，原\n        告等人之實習資格即應予以採認，而符合醫師法第2條\n        第1 項第1 款「實習期滿成績及格」之要件，故原告之\n        應考資格應屬合法。原告信賴被告長久以來之慣行和法\n        令解釋，花費多年時間出國學習醫學，依同樣條件、方\n        式完成學業且實習期滿成績及格並取得證明文件，報考\n        本件醫師考試，自屬合理信賴被告應採取上開歷年相同\n        應考資格審查標準，豈料被告竟事後於審查時，先突然\n        來函通知，對於原告等人之實習期滿成績及格證明「不\n        予採認」，其後又於系爭行政契約中增加准予考試之條\n        件，顯然違反行政程序法第6 條之規定，足證上開系爭\n        行政契約條款之差別待遇違反平等原則又無正當原因，\n        應屬違法無效。\n      (3)本件被告所訂系爭行政契約條款，顯違反行政程序法不\n        當連結禁止原則：系爭行政契約性質應為「代替行政處\n        分」之行政契約，應受行政程序法第142 條之規範限制\n        。又該契約內容為規定原告有諸多義務需要履行，而上\n        述契約既為被告單方片面所制訂定之事實，且原告等又\n        係基於時間緊迫等因素，顯陷於無充分選擇自由，更無\n        參與契約條款討論商議之機會等等顯不公平情況下，故\n        對原告而言，應為顯失公平之負擔義務契約，該契約自\n        應受行政程序法第137 條規範之限制，同時雙方對待給\n        付顯不相當，亦顯失公平。又系爭行政契約雖記載，其\n        目的在於保障國人生命身體健康並兼顧原告等人應國家\n        考試之權利，然所謂「實習期滿成績及格」僅為應考資\n        格的標準，並非考試及格的標準，具備應考資格者仍須\n        參加考試成績及格，方有可能取得及格證書執行業務，\n        此時方與所謂國人生命身體健康產生正當且合理關聯性\n        ，然被告片面對原告等人不法增加法律所未規定之報考\n        資格限制，自屬違法不當。同時與被告91年決議或不同\n        於以往歷年採認標準；顯見被告之行為不僅違反前開行\n        政程序法第137 條第1 項第3 款禁止不當連結原則及第\n        137 條第2項，更屬違反同法第8 條規定之誠信原則及\n        同法第5條之明確性原則。\n      (4)系爭行政契約約定，顯違反法律優位原則：依據前開專\n        門執業及技術人員考試法第1 條、專門執業及技術人員\n        高等考試醫師牙醫師考試分試考試規則第14 條 、醫師\n        法第6 條之規定，原告等人若考試及格，對於被告即有\n        請領及格證書之權利，而被告亦有給予及格證書的法定\n        義務，被告依法應無裁量的空間。然今被告片面制定系\n        爭行政契約，顯然逾越其法定裁量範圍，且為違背法令\n        對原告增加法律所未規定限制之行為，應屬違反法律優\n        位原則而無效。\n      (5)再依行政程序法第141 條規定，可知法律行為的內容應\n        具備合法、妥當、可能、確定四項要件，且行政程序法\n        第5 條亦規定：「行政行為之內容應明確。」惟查：系\n        爭行政契約第2 條、第4 條所指外國醫學院畢業生能否\n        在國內醫院實習？如何實習？之相關規定，以及所指醫\n        師法施行細則修正發佈之有關實習規定等事項之內容為\n        何？何時實施？等事實，於系爭行政契約訂約當時，均\n        付之闕如，亦尚無從知悉，皆屬客觀上無法確定之情形\n        ，足見系爭行政契約顯違反行政程序法第5 條規定及顯\n        有法律行為標的欠缺確定性之無效情形。\n  ３、依據司法院釋字第348 號解釋之協同意見書揭示「公法契\n      約故應受行政主體與他造當事人就約定之內容自由達成協\n      議……人民僅有簽訂與否之自由，並無對其內容與行政主\n      體協商修改之餘地，故其契約內容首重公平合理，不得使\n      人民負不相當之對待給付義務。」是本件原告於系爭行政\n      契約中，最低限度仍應享有締約自由及承諾自由。查原告\n      等人於98年7 月17日左右，接獲被告人員表示須簽訂系爭\n      行政契約，才會核發准考證，當時距離考試不到10日之時\n      間，而原告等人向本院所聲請假處分案件，尚無具體結果\n      ，原告又無其他立即救濟途徑，如果原告等人拒絕簽訂系\n      爭行政契約，根本不可能有參加此次考試之機會，足證原\n      告係於毫無選擇餘地之情形下，被迫不得已而簽訂系爭行\n      政契約，顯見被告所稱「原告在自由意願下簽訂此一和解\n      契約云云」，顯與事實不合。\n  ４、被告雖主張系爭行政契約為行政程序法第136 條之和解契\n      約云云，惟查：縱認被告所稱，雙方對於波蘭醫學院之實\n      習課程是否與我國醫學院之實習相當存有爭義，而成立和\n      解契約，然系爭行政契約內容中記載，被告有「暫准原告\n      報考」、「原告考試及格並實習期滿，考試院發給考試及\n      格證書」義務及「原告考試及格然無實習或實習不及格時\n      ，撤銷考試及格資格不發給考試及格證書」之權利，而原\n      告等有「原告考試及格時，需完成與國內醫學院相當期間\n      與內容之實習」及「原告考試不及格時，需實習始得再行\n      報考」等義務，足見系爭行政契約原、被告間互負給付義\n      務，亦屬成立雙務契約之情形。況且被告於答辯狀自承「\n      第五次會議決議，通知補繳畢業後一年實習證明後再議。\n      ……嗣該審議委員會第6 次會議決議，以原告等均未提出\n      合乎規定之實習證明不准報考」、「第7 次會議同意應考\n      人（含原告）推派代表到場說明，惟決議仍以原告在學期\n      間之見習與實習未做明確區分……核與醫師法第2 條……\n      之規定不符，不准報考」等情，顯見被告係已明確認定原\n      告等不符報考資格而作成不准報考之決議，應非其現今所\n      稱原告等之報考資格認定尚有疑義而無法查明事實之情形\n      ，足見被告上開所稱系爭行政契約之簽定為「和解契約」\n      ，非無疑義。\n  ５、被告又主張對於外國醫學院之實習是否與國內醫學院實習\n      『相當』，為不確定法律概念，具有判斷餘地，本件經由\n      專業審議委員會本於專業權責加以判斷，作成先通過考試\n      後，補實習再執業決定之和解契約云云，惟查：被告係依\n      據醫師法第2 條第1 項第1 款、專門職業及技術人員考試\n      法第五條規定，所制定之專門職業及技術人員高等考試醫\n      師牙醫師考試分試考試規則第六條之附表一，辦理本件醫\n      師特考，應考人之資格要件明確，並無被告所稱「不確定\n      法律概念」而授予被告裁量權之情形；依被告之「應考資\n      格審查規則」第2 條、第3 條規定，被告於審核應考者符\n      合法定要件之情形，即應為准考之處分，換言之，係為羈\n      束處分，即同一申請於相同時點審查是否符合應考要件，\n      只有「符合」或「不符合」擇一之明確判定，顯見被告並\n      無一方面既已決議認定原告等「不符合應考資格不得考試\n      」，另方面卻又以行政契約准予原告等應考之法律上裁量\n      權。足證系爭行政契約應有行政程序法第135 條但書所規\n      定，依其性質或法律規定不得締約之違法無效情形。同理\n      系爭行政契約第2 、3 、4 條等約定，既無法律明文規定\n      ，亦與確保行政契約之法定要件之履行無關，則依行政程\n      序法第137 條第2 項規定適用同法第93條第1 項後段，被\n      告應不得為之。\n  ６、有關醫師法第2 條第1 項第1 款規定事項，主管機關應為\n      行政院衛生署，而非被告。且有關上開法律規定之應考資\n      格如有修改之必要時，亦須由主管機關依法定程序進行修\n      法，然本件系爭行政契約簽定當時，醫師法規定之應考資\n      格相關法令規定尚未修改，然被告卻已先於系爭行政契約\n      中，自行規定原告須補行有關國內實習事項，已屬逾越被\n      告之法定職權。依行政程序法第142 條第1 項第1 款及同\n      法第111 條第1 項第6 款規定，上開有關補行實習之契約\n      條款應屬無效。\n  ７、關於被告主張「原告違反禁反言、誠信原則，原告乃在自\n      由意願下簽訂此一合約，也獲得報考資格之實質利益且『\n      已經完考』，原告既然合意締結和解在前，事後即不得違\n      反其承諾。」等語云云。查被告為執掌國家考試之機關，\n      本件被告又係於臨考前始要求原告簽訂系爭行政契約，原\n      告當時基於時間緊迫且欠缺救濟途徑等情形，不得已而簽\n      定，實非出於自由意願，已如前述詳述，且所謂取得報考\n      資格之實質利益，本應為原告應有之法定權益，是原告提\n      起本件訴訟，並無違反禁反言或誠信原則。\n  ８、又原告分別留學於波蘭國波茲南醫學大學、羅茲醫學大學\n      、西里西亞醫學大學畢業，並經實習期滿成績及格，已滿\n      足本考試應考資格所定之要件，原告竟以系爭契約條款，\n      在未獲法律授權之情形下，課與原告考試後須另於國內額\n      外實習之義務，否則即不發給證書或不得報名下年度之考\n      試，該條款乃不合法且違反平等原則等一般法律原則，應\n      屬無效已如前述，原告自不受該無效條款之其拘束，系爭\n      行政契約之法律關係亦為不成立，被告主張原告應受拘束\n      ，要無理由。\n（三）綜上，系爭行政契約第2 條、第3 條及第4 條應有違反上\n      述法律規定、原則而無效情事而法律關係不存在，爰依行\n      政訴訟法第6 條第1 項等規定，得提起本件確認之訴，聲\n      明：１、確認原告等分別與被告所簽系爭行政契約所示「\n      考選部暫准報考緩發及格證書行政契約」，其中第2 條、\n      第3 條、第4 條約定之法律關係不存在。２、訴訟費用由\n      被告負擔。\n四、被告抗辯略以：\n（一）程序方面：\n  １、原告起訴違反確認訴訟之備位性原則：本件爭議實質上係\n      因原告對於被告認定其波蘭醫學院學歷無法取得報考醫師\n      資格之認定不服，但當時因考試即將舉行，且原告復一再\n      陳情，被告為保障其參與考試之機會，始在經協調行政院\n      衛生署同意配合辦理實習作業以及『雙方合意下』分別在\n      98年7 月18日至21日與原告簽訂系爭行政契約。核其實質\n      上所不服者乃係「被告」當初否准其具有專技人員醫師高\n      考報考資格之決議，依行政訴訟法第6 條第3 項之規定，\n      原告應在獲知其被認定不符報考資格之後依法提起訴願、\n      撤銷訴訟，亦即當時如對該行政決定有所不服原應對該「\n      否准」且退件報考資格之行政處分提出撤銷訴訟，而當時\n      原告等人對並未對該處分提出訴願而僅四處陳情，現否准\n      報考及退件之處分已確定之後始提出確認訴訟，應足認本\n      件起訴程式有違反確認訴訟之備位原則。\n  ２、原告訴之聲明不合法：如依原告之聲明將造成法院以判決\n      方式將『行政契約』變更為『授益行政處分』，此已自創\n      法律所無之訴訟類型，而屬誤用訴訟類型：細繹原告訴之\n      聲明係確認：「考選部暫准報考緩發及格證書行政契約其\n      中第二條、第三條、第四條約定之法律關係不存在」，惟\n      果真如依其聲明以判決方式確認行政契約之第二、三、四\n      條均無效而不存在之後，全份契約僅保留第一條「考選部\n      暫准原告等報考醫師高考」，而『准予報考之法律性質係\n      授益行政處分』，惟行政訴訟法並無法律依據可透過法院\n      之判決將行政契約變成授益行政處分之訴訟類型，蓋行政\n      契約與行政處分，本質上即為不同之行政行為，自無由法\n      院以判決之方式將行政契約以『判決方式』『變成』『行\n      政處分』餘地。如原告之目的係欲命被告作成「准予報考\n      之行政處分」應依行政訴訟法第5 條提起課予義務之訴。\n      惟不論以上何者，原告之訴訟類型均非適法當可確定。\n  ３、原告乙○○等11名未及格者並無即受確認判決之法律上利\n      益：本件醫師考試未及格者11人，已參加98年8 月1 日之\n      醫師考試而考試已於98年9 月30日榜示結束，所以被告已\n      完成行政契約之給付，因為原告乙○○等11名未及格，未\n      有後續實習問題，被告之義務已因履行完畢而消滅，故依\n      行政訴訟法第6 條之規定，原告乙○○等11名未及格者並\n      無即受確認判決之法律上利益。同時上開原告亦報名參加\n      99年1 月23日舉行之99年第一次專技高考醫師考試分試考\n      試第一試，並已於99年1 月7 日寄發入場證在案，是此部\n      分原告更無即受確認判決之法律上利益存在。\n  ５、原告之訴依其所訴之事實顯無理由，依法應不經言詞辯論\n      逕以判決駁回之：本件原告確認聲明係確認「考選部暫准\n      報考緩發及格證書行政契約第二、三、四條法律關係不存\n      在」，而依行政程序法第143 條之規定行政契約一部無效\n      者，全部無效；且明顯地如欠缺整份契約之二、三、四條\n      被告將不可能締結該行政契約，因此，本件無由透過行政\n      程序法第143 條但書之規定僅讓契約第一條『單獨』生效\n      ，原告之聲明主文僅依其形式上觀之已不合法，直接牴觸\n      行政程序法第143 條，故依行政訴訟法第107 條第3 項規\n      定，本院依法即應不經言詞辯論，逕以判決駁回原告之訴\n      。\n（二）實體方面：\n  １、系爭行政契約法律性質為行政程序法第136 條和解契約：\n      (1)依行政程序法第136 條之規定，機關負有職權調查事實\n        之義務，本件兩造間之爭執為波蘭醫學院之實習課程是\n        否與我國醫學院之實習『相當』（參照國外學歷採認辦\n        法第8 條），因簽訂契約之前已經即將舉行專技人員醫\n        師高考，具有時效性及急迫性，為避免侵害人民之權利\n        ，被告於已盡各種調查途徑仍不能查明該事實，為解決\n        爭執及達成行政目的始與原告依行政程序法第136 條規\n        定締結系爭和解契約，合先說明。\n      (2)本件所涉前開報考資格之「事實不明」爭議經過：\n        原告等係波蘭醫學院之畢業生，故其『學歷』部分經\n          認與醫師法第4 條之1 之學歷相符。所爭議者係其『\n          實習』部分，究竟是否符合醫師法第2 條第1 項第1\n          款其中所稱之『實習期滿』之內涵，蓋依據教育部大\n          學辦理國外學歷採認辦法第8 條規定：「國外學歷…\n          …修業期限、修習課程，應與國內同級同類學校規定\n          相當」。而本件原告等人在波蘭求學之『實習』過程\n          經被告機關邀集具各大醫學中心之醫師代表、行政院\n          衛生署……等召開醫師牙醫師考試審議委員會審議其\n          報考資格，並請原告等人到會陳述意見後，委員會一\n          致認為原告等人『波蘭醫學院之』『實習』僅相當於\n          『見習』，與我國醫學院之『實習』過程顯不相當，\n          而否准其報考資格。\n        醫師牙醫師考試審議委員會之組織合法、程序正當：\n          按考選部組織法第19條規定考試院爰訂定專門職業及\n          技術人員考試審議委員會組織規程，復按該組織規程\n          第2 條規定，該審議委員會成員由行政院衛生署副署\n          長、教育部醫事教育委員會執行秘書、醫學大學醫學\n          院院長、醫學系系主任、教學醫院院長、公會團體代\n          表及被告簡任以上高級人員組成，另邀請行政院衛生\n          署醫事處及教育部高等教育司派員列席，有關應考人\n          應考資格之疑義，均提該委員會審議，該組織嚴謹，\n          且程序正當，並將審議結果經被告核定後，始報請考\n          試院備查，以維應考人權益，可知過程至為審慎，依\n          此而做成之決定，即不容任意推翻。\n        原告接獲不符報考資格之通知後續處置：\n          嗣原告等多人接獲不符資格之通知後四處陳情謂其係\n          合法國外醫學院之畢業生竟不能報考醫師高考，當時\n          因考試在即且涉及在歐洲之波蘭醫學院其實習之『實\n          際狀況』調查非短期可能明確，因而涉及行政處分(\n          准否報告之決定) 之事實不明確下，乃為行政程序法\n          第136 條規定「行政處分所依據之事實，經依職權調\n          查仍不能確定者」之情況。基於確保醫師專業資格水\n          準與維護國民健康之行政目的，以及原告等援前例得\n          以報考之期待，並為解決爭執( 得否報考醫師高考)\n          ，被告遂依據行政程序法第136 條與原告等人簽訂和\n          解之行政契約，以代替行政處分。\n  ２、原告誤認本件行政契約係行政程序法第137 條之雙務契約\n      並據此為基礎所為契約無效之主張，均因契約是否有效之\n      前提「契約定性」錯誤而失其附麗：本件行政契約雙方並\n      未因約定「被告准予參加考試」與「原告須重新或補行實\n      習及接受暫緩發及格證書」而使雙方互負對待給付義務，\n      而係因為「原告在波蘭之實習狀況」是否與國內醫學院之\n      實習『相當』所為之專業判斷已如前述，因此雙方所訂立\n      者乃行政程序法第136 條之和解契約，迺原告竟執行政程\n      序法第137 條之行政契約大肆主張契約無效，核其有關行\n      政程序法第137 條之主張均因前提不存在，即「契約定性\n      」錯誤而失其附麗，顯不可採。\n  ３、被告（審議委員會）對於外國醫學院之實習與國內醫學院\n      實習是否『相當』具有判斷餘地：\n      (1)本件情形，就現存具體事實涵攝至法律之構成要件判斷\n        （原告等人之波蘭醫學院之「實習」是否符合醫師法第\n        2 條第1 項第1 款、教育部大學辦理國外學歷採認辦法\n        第8 條規定之「實習」「相當」）。由於本件所涉之法\n        令之構成要件用語係以不確定之法律概念『相當』貳字\n        來表現，究竟是否相當則由主管機關依法令所組成之專\n        業審議委員會，本於專業之權責加以判斷，應認其決定\n        具有判斷餘地不容原告以一己主觀之見解主張無效。\n      (2)況查，本件波蘭醫學生之應考資格「實習」部分之認定\n        是否與國內醫學院之實習相當，隨著時空環境的不同而\n        時移事轉，經考選部醫師牙醫師考試審議委員會第7 次\n        會議，詳細詢問原告等在波蘭修習醫學系課程與實習實\n        際之狀況。委員們從英語國際班實習互動與醫院值夜班\n        情況，審慎討論後認為與國內實習未完全相當，委員會\n        作此專業判斷後為了彌補原告等實習與國內實習之完整\n        性及確保國內執業前先行瞭解國內病人與本土流行病等\n        ，審議委員會作成先通過考試後，補實習再執業之決定\n        。此乃被告依據之醫師法及教育部大學辦理國外學歷採\n        認辦法，關於國外「實習」與國內醫學院之實習是否相\n        當，容有判斷餘地。\n  ４、機關辦理本次專技人員醫師高考之審查歷程：\n      (1)各種國家考試應考人之應考資格原則由考選部擬定、考\n        試院發布，惟醫師法及其他醫事人員等相關法規由行政\n        院衛生署主管。另依醫師法施行細則部分條文修正總說\n        明：「對持國外學歷回國參加考試者，其於國外使用之\n        語言及接觸之疾病型態，顯與國內各類醫學生有所不同\n        ，需要在其參加考試前，於國內醫療機構接受與國內醫\n        學生相當之臨床實作科別及週數或時數之訓練，以確認\n        其與我國的醫學院醫學系畢業生具有相似之臨床經驗。\n        」且依醫師法施行細則第1 條之2 規定，就實習期滿，\n        其臨床實作之科別及週數或時數，並無區分國內外，表\n        示國內外之「實習期滿」標準必須一致。\n      (2)被告經提98年6 月19日召開之醫師牙醫師考試審議委員\n        會第5 次會議審議決議，通知補繳畢業後1 年實習證明\n        後再議。被告即於同年月25日選專字第0983301258號書\n        函通知原告等人補件。原告等乃於同年6 月29日、30日\n        及7 月1 日陸續向被告提出申覆，被告為求慎重，即於\n        同年7 月3 、8 日及15日又分別召開醫師牙醫師考試審\n        議委員會第6 、7 、8 次會議。嗣該審議委員會第6 次\n        會議決議，以原告等均未提出合乎規定之實習證明不准\n        報考；第7 次會議同意應考人（含原告）推派代表到場\n        說明，惟決議仍以原告在學期間之見習與實習未作明確\n        區別，依國內學制其大多屬見習性質並非「實習」，與\n        國內學制1 年完整實習有別，核與醫師法第2 條「……\n        實習期滿成績及格……」之規定不符，不准報考。\n      (3)另經考選部醫師牙醫師考試審議委員會第8 次會議審議\n        通過，決議：「一、同意被告與波蘭波茲南等4 所醫學\n        大學及愛爾蘭都柏林大學醫學院畢業生簽訂行政契約以\n        「暫准報考緩發及格證書」方式，並對行政契約修正通\n        過。二、前述權宜措施，僅限報考98年第二次專門職業\n        及技術人員高等考試醫師、牙醫師考試、醫師考試分試\n        考試第一試。三、考試及格證書以實習期滿成績及格之\n        日為生效日期。四、經醫師考試第一試及格者，應先完\n        成實習後再考第二試。五、未簽署行政契約者不准應本\n        次考試。六、本案應報請考試院核定。七、本考試暫准\n        報考成績及格人員在醫療機構實習期間，請衛生署落實\n        督導考核。八、函請教育部儘速查明波蘭大量培養醫學\n        系學生原由，其學制包括課程、見習、實習情形是否與\n        國內學制相當，俾供本會審查相關案件參考」。\n      (4)本案原告等17名擬報考98年第二次專門職業及技術人員\n        高等考試醫師考試、醫師考試分試考試第一試一案，經\n        第8 次會議決議：「比照第一案決議，同意被告與巳○\n        ○等33名波蘭波茲南等4 所醫學大學及愛爾蘭都柏林大\n        學醫學院畢業生簽訂行政契約以『暫准報考緩發及格證\n        書』方式，僅限報考98年第二次專門職業及技術人員高\n        等考試醫師考試、醫師考試分試考試第一試。」\n  ５、被告先取得衛生署同意，而衛生署同意配合辦理考試及格\n      後之實習程序之後，被告始與原告等簽行政契約之過程及\n      行政契約之內容：\n      (1)由於原告等係「實習期滿成績及格」所生之爭議，審議\n        委員會作成「暫准報考緩發及格證書」決議前，由被告\n        以98年7 月14日選專字第0983301452號函徵求行政院衛\n        生署之同意，而行政院衛生署於同日衛署醫字第098020\n        8143號函覆被告同意略以：「……貴部函請本署配合辦\n        理國外醫學畢業生暫准參加專門職業及技術人員高等考\n        試醫師、牙醫師考試及格人員之實習，敬表同意。至實\n        習期滿成績及格之證書，將由各該醫療機構發給，另本\n        署將請各醫療機構列冊函報本署，俾彙整成冊函送貴部\n        ，作為核發考試及格證書之參考……。」\n      (2)依上開協調取得共識，決定於醫師法施行細則修正發布\n        前，經98年第二次專技高考醫師考試及格之應考人，由\n        行政院衛生署安排於國內適當層級之醫療機構實習期滿\n        成績及格後，再由衛生署加以彙整成冊，被告始報請考\n        試院發給考試及格證書。由於被告考試採測驗式試題，\n        無法考出其實作( 實務) ，是以，審議委員會作成「暫\n        准報考」實已兼顧應考人考試權益，並為其實習主動與\n        衛生署連絡，對實習之疑義提出補救措施。被告作成「\n        暫准報考緩發及格證書」之作法。\n      (3)監察院亦認暫准報考緩發及格證書作法兼顧法令與應考\n        權益尚稱允當：依監察院糾正文表示，「……相較於歐\n        盟其他國家之留學人數寥廖可數，留學波蘭人數之多，\n        顯非尋常，非但嚴重影響國內醫學系招生人數之管制總\n        量，且其入學管道與國內醫學系嚴格篩選學生素質相較\n        ，亦明顯寬鬆，甚至前往該國取得醫學系學歷者如循國\n        內升學管道，多數尚無法取得進入國內醫學系就讀之資\n        格，致國人對波蘭大學醫學系開設英語學程廣收外籍學\n        生之教育品質多存疑慮。」（詳被證十五）監察委員針\n        對「波蘭醫學系畢業生回國報考醫師考試相關問題」所\n        做調查報告指出，在行政院衛生署未針對國外醫學系學\n        歷報考者之實習發布明確規定前，考選部「暫准報考緩\n        發及格證書」之作法「尚屬允當」。\n      (4)依上開協商決議採暫准報考緩發及格證書之作法後，98\n        年7 月15日考選部醫師牙醫師考試審議委員會第8 次會\n        議審議通過，依原告等與被告簽訂之行政契約，雙方議\n        定行政契約條款如「考選部『暫准報考緩發及格證書』\n        行政契約」。\n      (5)本次考試及格原告5 人，被告『已依行政契約』函請衛\n        生署安排其至醫院實習：\n        本次考試業於98年9 月30日榜示，原告等計有甲○○\n          、己○○、辛○○、癸○○及子○○等5 人醫師考試\n          及格，醫師考試分試考試無人及格。\n        被告業於98年9 月30日檢送5 名及格人員名冊至行政\n          院衛生署，請其安排渠等至國內各醫療機構實習。至\n          實習期滿成績及格之證書，將由各該實習醫療機構發\n          給，各醫療機構並列冊函報行政院衛生署後，由該署\n          彙編成冊函送被告，渠等5 人業與被告簽訂行政契約\n          ，對雙方均發生拘束力，『被告亦已依約履行安排其\n          及格後實習已如前述』，原告等就議定內容，即須遵\n          守，不得「一面享有行政契約之利益卻另一面否定契\n          約之效力」。\n        另原告乙○○、丙○○、丁○○、戊○○、庚○○、\n          壬○○、丑○○、寅○○、卯○○、辰○○及巳○○\n          等11人該次考試並未及格，若要報考99年第一次專門\n          職業及技術人員高等考試醫師考試分試考試第一試，\n          應依98年10月14日考試院修正發布之專門職業及技術\n          人員高等考試醫師牙醫師考試分試考試規則之規定報\n          考。\n  ６、原告違反禁反言原則：本件情形原告在自由意願下簽訂此\n      一和解契約，也獲得報考資格之實質利益且「已經考完」\n      ，豈有在「既得利益」已實現後，復爭執其無效，亦即被\n      告已充分保障原告之應考資格，未料事後原告竟在獲准參\n      與本次考試後始主張和解契約無效，被告既已合意締結和\n      解在先，事後即不得違反其承諾，否則即有違行政法上禁\n      反言原則之法理。\n  ７、原告違反誠信原則：本件原告於簽訂行政契約之後已『享\n      有』契約第一條之授益行政處分之利益( 准予參加考試)\n      且也『已經參加完考試』並有原告甲○○、己○○、辛○\n      ○、癸○○及子○○等5 人醫師考試還經榜示錄取『並獲\n      被告依契約函請行政院衛生署安排其實習程序』，是原告\n      等人乃系爭行政契約之既得利益者於獲得其利益後( 參加\n      應試) 竟反執以主張「讓其得以順利參試」之行政契約無\n      效，顯自我矛盾不合誠信原則。\n  ８、行政先例須屬合法者，乃行政自我拘束之前提要件，憲法\n      之平等原則，並非賦予人民有要求行政機關重複錯誤之請\n      求權：最高行政法院93年判字第1392號判例之意旨：「憲\n      法之平等原則要求行政機關對於事物本質上相同之事件作\n      相同處理，乃形成行政自我拘束，惟憲法之平等原則係指\n      合法之平等，不包含違法之平等。故行政先例需屬合法者\n      ，乃行政自我拘束之前提要件，憲法之平等原則，並非賦\n      予人民有要求行政機關重複錯誤之請求權。」原告主張：\n      「考選部92年2 月函文中更載明，被告機關曾於91年3 月\n      27日醫事人員考試審議委員會第6 次會議作成決議，『有\n      關經國外醫學系畢業前往與取得學位不同之醫師法第4 條\n      之1 所列九大地區或國家實習，其實習資格予以採認』」\n      等語云云，即要求被告重複做成錯誤之決定，此部分應不\n      可採。\n  ９、原告主張違反行政法上之公益原則：貿然全面開放大量實\n      習訓練與國內醫學院有差異之波蘭醫學生資格，有違公共\n      利益與國民健康。本件根據駐波蘭台北經濟文化辦事處之\n      資料，截至97年度止，目前台灣學生就讀波蘭醫學系及牙\n      醫學系之人數已高達665 人，未來還將有更多台灣學生前\n      往就讀，因此若貿然全面性開放波蘭醫學生准予報考醫師\n      考試，而完全不去依法審查其『實習』是否與國內醫學院\n      相當，後續透過此管道取得醫師報考資格之人將因此暴增\n      ，對國人健康將有莫大之危害有違公共利益。\n（三）原告98年6 月30日申覆書之性質應為行政程序法上之「陳\n      情」，被告就原告之申覆即循陳情程序辦理：\n  １、按行政程序法第168 條、171 條規定，原告針對被告選專\n      字第0983301258號通知補件函所提起之申覆，性質核屬行\n      政程序法上之「陳情」，並非提起行政訴訟前應經之訴願\n      先行程序，蓋綜觀原告之申覆書全文，可知原告除指摘被\n      告所為「應補繳1 年實習證明」之認定及處分係違法不當\n      ，違反行政程序法等相關規定外，另表示被告違反憲法第\n      18條規定侵害人民考試權，因而提出申覆救濟，不但所涉\n      及之法令皆為抽象之原則且並未敘明所提起之訴願類型，\n      全文亦未見明確訴願意旨，故被告無法逕依訴願程序辦理\n      。\n  ２、被告對於原告之陳情，爰審慎召開第6 ～8 次醫師牙醫師\n      考試審議委員會，並通知原告指派代表到會陳述意見，於\n      綜整並獲取初步意見後，更主動向主管機關行政院衛生署\n      尋求協助與配合，被告決議透過簽訂行政契約「暫准報考\n      緩發及格證書」方式解決爭議之措施，亦獲得監察院之肯\n      認與贊同，可知被告對於原告之申覆，根據其申覆意旨，\n      依行政程序法第102 條邀請申覆人到場陳述意見後，始作\n      成「暫准報考緩發及格證書」之處分，為行政程序之一環\n      ，非行政救濟程序之內容。最後並與原告簽訂和解契約，\n      兼顧公益與原告之應考權益，如今原告欲切割主張部分和\n      解契約條文之法律關係不存在，實無理由。\n（四）設若原告於98年6 月30日所提申覆書之真意確為訴願，如\n      今仍可於法定一年期限內再行透過訴願救濟，惟本件確認\n      訴訟之提起並不合法：承被告99年1 月25日答辯（二）狀\n      所述，被告98年6 月25日選專字第0983301258號函之意旨\n      ，不僅止於通知受文者（即原告甲○○等17人）限期補正\n      文件，尚包含因渠等並未符合應考資格，告知原告「如逾\n      期未能補正」，即「不准報名」等意思表示在內，核已具\n      備行政程序法第92條第1項 行政處分之要件而對外生法律\n      上效果，即便系爭通知函未記載行政程序法第96條第1 項\n      第6 款之教示條款，惟依行政程序法第98條第3 項規定，\n      原告得自處分書送達後一年內聲明不服。基此，本件原告\n      若不服被告系爭函文「如逾期未能補正即不准報名」之行\n      政處分，自應依訴願法之規定提起撤銷訴願，如今原告提\n      起本件確認訴訟前並未經訴願前置程序，若依其主張所提\n      起者係「確認法律關係存否之訴」，則依行政訴訟法第6\n      條第3 項規定，自不得提起本件訴訟，而應依訴願法之規\n      定明確對於被告98年6 月25日選專字第0983301258號函進\n      行救濟，若有不服，再於完成訴願前置程序後，循行政訴\n      訟管道續行救濟。\n（五）本件原告並無權利保護必要：\n  １、本件原起訴之原告甲○○等16人，其中已及格之甲○○、\n      己○○、辛○○、癸○○、子○○等5 人業已分發至各署\n      立醫院實習，並已完成報到手續；未及格之11人已由被告\n      於98年12月8 日以選專字第0983302483號函准其報考99年\n      1 月23日舉行之99年第一次專技高考醫師考試分試考試第\n      一試，並已於99年1 月7 日寄發入場證，從而原告等並無\n      任何法律之權利或利益受侵害或有受侵害之虞而有立即以\n      行政訴訟確認判決予以除去之必要，其所提本件訴訟顯然\n      欠缺權利保護之必要而應予程序駁回。\n  ２、至於原告所謂「仍須補行實習成績及格始能應試之第二試\n      限制」，及「已及格之5 人可中止實習要求被告發給考試\n      及格證書」等訴之利益，依本件原告起訴前醫師法等相關\n      法規上針對報考資格早已既定之實質要件，即「學歷證明\n      」與「實習期滿成績及格」，無論本件訴訟之勝敗，原告\n      要不可能脫離法律明訂之應考資格要件，可「不用實習」\n      或「中止實習」而違反平等原則以特例方式取得考試及格\n      證書。是本件原告於新制考試制度下得應醫師考試分試第\n      一試，且已分發實習（及格者）或參加99年第一次專技高\n      考醫師考試分試考試第一試（未及格者）並無疑義，至於\n      醫師考試分試第二試所有應考人皆必須「實習期滿成績及\n      格」亦無不同，原告主張本件仍有權利保護必要即無理由\n      。\n（六）綜上所述，原告既基於自由意願合意與被告簽訂行政契約\n      ，且被告亦依約暫准原告參加考試以合理保障其考試權，\n      原告嗣經「參加」並「完成」考試不及格即應遵照契約之\n      規定正式取得資格再重新報考，不得再任意主張行政契約\n      無效，否則將嚴重違反禁反言原則、誠信原則、公益原則\n      等，為此答辯聲明求為判決：１、駁回原告之訴。２、訴\n      訟費用由原告負擔。\n五、本件應適用之法律：\n（一）按醫師法第2 條規定：「（第1 項）具有下列資格之一者\n      ，得應醫師考試：一、公立或立案之私立大學、獨立學院\n      或符合教育部採認規定之國外大學、獨立學院醫學系、科\n      畢業，並經實習期滿成績及格，領有畢業證書者。二、八\n      十四學年度以前入學之私立獨立學院七年制中醫學系畢業\n      ，經修習醫學必要課程及實習期滿成績及格，得有證明文\n      件，且經中醫師考試及格，領有中醫師證書者。三、中醫\n      學系選醫學系雙主修畢業，並經實習期滿成績及格，領有\n      畢業證書，且經中醫師考試及格，領有中醫師證書者。（\n      第2 項）前項第三款中醫學系選醫學系雙主修，除九十一\n      學年度以前入學者外，其人數連同醫學系人數，不得超過\n      教育部核定該校醫學生得招收人數。」次按專門職業技術\n      人員考試法第5 條規定：「各種考試，得單獨或合併舉行\n      ，並得分試、分地舉行。其考試類、科、地點、日期等，\n      由考選部於考試兩個月前公告之。應考人在學期間得視類\n      科之不同，參加前項所定分試考試最後一試以外之考試。\n      分試考試之類科及其考試規則，由考選部報請考試院定之\n      。」是得應專門職業醫師考試之資格者，必須符合經過國\n      內外大學醫學院畢業，並經實習期滿成績及格二要件。\n（二）依據醫師法第42條授權訂立之醫師法施行細則，經主管機\n      關行政院衛生署於98年9 月16衛署醫字第0980215591號令\n      增訂發布第 1之1條至第1之5 條規定如下：\n  １、第1 條之1 ：「（第1 項）本法（按醫師法）第二條至第\n      四條所稱實習期滿成績及格，指在經教學醫院評鑑通過，\n      得提供臨床實作訓練之醫療機構，於醫師指導下完成第一\n      條之二至第一條之四所定之科別及週數或時數之臨床實作\n      ，各科別考評成績均及格，且持有該醫療機構開立之證明\n      。（第2 項）中央主管機關得就前項實習，辦理臨床實作\n      訓練申請人與醫療機構間之選配分發，並得就該業務委託\n      民間專業機構或團體辦理。」\n  ２、第1 條之2 ：「本法第二條所稱實習期滿，其臨床實作之\n      科別及週數或時數如下：一、內科十二週或四百八十小時\n      以上。二、外科十二週或四百八十小時以上。三、婦產科\n      四週或一百六十小時以上。四、小兒科四週或一百六十小\n      時以上。五、其他選修科別至少三科，每科二週或八十小\n      時以上。前項週數或時數，合計應達四十八週或一千九百\n      二十小時以上。」\n  ３、第1 條之3 ：「本法第三條所稱實習期滿，其臨床實作之\n      科別及週數或時數如下：一、中醫內科十八週或七百二十\n      小時以上。二、中醫傷科八週或三百二十小時以上。\n      三、針灸學科九週或三百六十小時以上。四、中醫婦兒科\n      九週或三百六十小時以上。前項週數或時數，合計應達四\n      十五週或一千八百小時以上。」\n  ４、第1 條之4 ：「本法第四條所稱實習期滿，其臨床實作之\n      科別及週數或時數如下：一、兒童牙科二週或八十小時以\n      上。二、口腔顎面外科八週或三百二十小時以上。三、齒\n      顎矯正科二週或八十小時以上。四、膺復科八週或三百二\n      十小時以上。五、牙周病科四週或一百六十小時以上。六\n      、牙髓病科四週或一百六十小時以上。七、牙體復形科二\n      週或八十小時以上。八、其他選修科別至少三科，合計至\n      少十八週或七百二十小時以上。\n  ５、第1 條之5 ：「前三條所定之臨床實作時數，不包括夜間\n      與假日之值班。」\n      又上開規定，屬醫師法枝節性、技術性之規定，並未逾越\n      母法醫師法授權，未違反法律保留原則，主管機關據以訂\n      立以供認定醫師法第2 條規定之「實習期滿」之考試行政\n      ，本院予以尊重。\n（三）考試主管機關考試院依據上開專門職業技術人員考試法第\n      5 條授權，以96年5 月26日考試院考臺組壹一字第096000\n      38331 號令修正發布專門職業及技術人員高等考試醫師牙\n      醫師考試分試考試規則，第2 條規定：「（第1 項）專門\n      職業及技術人員高等考試醫師牙醫師考試分試考試（以下\n      簡稱本考試）分二試舉行。（第2 項）第一試未及格者，\n      不得應第二試。」第6 條規定：「（第1 項）中華民國國\n      民具有附表一醫師、牙醫師類科所列資格之一者，得分別\n      應本考試醫師、牙醫師類科第一試。（第2 項）具有前項\n      附表一醫師類科第一款至第三款規定資格之一者，於中華\n      民國九十九年一月一日前，得應專門職業及技術人員高等\n      考試醫師考試。（第3 項）具有第一項附表一牙醫師類科\n      第一款規定資格者，於中華民國一０一年一月一日前，得\n      應專門職業及技術人員高等考試牙醫師考試。」第7 條規\n      定：「（第1 項）中華民國國民具有附表一醫師應考資格\n      第一款、第二款、第三款資格之一，牙醫師應考資格第一\n      款，並分別經本考試醫師、牙醫師第一試及格者，得應本\n      考試醫師、牙醫師第二試。（第2 項）六年內第二試未及\n      格者，應重新應本考試第一試。」而上開考試規則附表一\n      應考資格第１點亦明確載明：「……但國外大學、獨立學\n      院醫學系、科畢業者，其實習滿成績及格之認定標準，依\n      行政院衛生中華民國九十八年九月十六日修正發布之醫師\n      法施行細則規定辦理。」上開考試規則，亦經法律授權主\n      管機關訂立，並未逾越母法，與其他法律相互配合，其中\n      就醫師法相關之醫師等考試改採第一試及第二試規定，又\n      訂立三年之過渡期間（自96年間起至98年12月31日止）兼\n      顧規範對象即應醫師考生之信賴利益之保護；從而被告據\n      以為考試行政，本院予以尊重。\n（四）再按考選部組織法第19條規定：「考選部為因應各種業務\n      或特殊需要，得設各種委員會，分別辦理各有關業務之審\n      議或研議等事項。」考試院據此訂定專門職業及技術人員\n      考試審議委員會組織規程，依該組織規程第2 條規定：「\n      （被告機關）為辦理專門職業及技術人員醫師牙醫師考試\n      政策、法規、制度之諮詢、應考資格疑義案件、應考人減\n      免應試科目案件之審議，設醫師牙醫師考試審議委員會，\n      審議應考資格初審不合格或疑義案件。」上開醫師牙醫師\n      考試審議委員會之委員，由行政院衛生署副署長、教育部\n      醫事教育委員會執行秘書、醫學大學醫學院院長、醫學系\n      系主任、教學醫院院長、公會團體代表及被告簡任以上職\n      員組成，並邀請行政院衛生署醫事處及教育部高等教育司\n      派員列席，針對醫師及牙醫師考試應考人應考資格之疑義\n      ，均由上開委員會審議。\n（五）另按「確認行政處分無效及確認公法上法律關係成立或不\n      成立之訴訟，非原告有即受確認判決之法律上利益者，不\n      得提起之。其確認已執行完畢或因其他事由而消滅之行政\n      處分為違法之訴訟，亦同。」行政訴訟法第6 條第1 項訂\n      有明文。因此：\n  １、前述「確認法律關係之成立或不成立」，因實務上早已擴\n      及於法律關係之存在或不存在，故於行政訴訟法修正時，\n      認不必嚴加區別，而未特別規定「存在或不存在」之文字\n      （參見學者陳計男著行政訴訟法釋論第188 頁）；且觀本\n      條規定之立法理由，其於公法上法律關係「成立或不成立\n      」文字下又特別註明包括「存在或不存在」，可知，本條\n      關於「確認公法上法律關係成立或不成立訴訟」之規範，\n      應包含「確認公法上法律關係存在或不存在之訴訟」。\n  ２、再按所謂公法上之法律關係，係指公法上之權利義務關係\n      ，即二以上之法律主體，就公法上具體事件，依法律規定\n      所成立之法律上關係而言；同時公法上之具體事件，亦必\n      須有特定生活事實之存在，因法規之規範效果，在兩個以\n      上之權利主體間所產生之公法上權利義務關係，或產生人\n      對權利客體間之公法上利用關係；又公法上法律關係之成\n      立有直接基於法規規定者，亦有因行政處分、行政契約或\n      事實行為而發生者，但法規、事實行為均非法律關係本身\n      ，故皆不得以其存否為確認訴訟之標的。\n  ３、又按所謂即受確認判決之法律上利益，須因法律關係之存\n      否不明確，致原告在公法上之地位有受侵害之危險，而此\n      項危險得以對於被告之確認判決除去之者，始足當之。故\n      原告提起確認公法上法律關係不存在之訴，若欠缺即受確\n      認判決之法律上利益，核屬欠缺權利保護之必要即無確認\n      訴訟訴之利益，在法律上為無理由，應以判決駁回之。\n六、兩造對事實概要之記載及下開其他事實、醫師考試制度之變\n    革等均不爭執，並有原告提出之系爭「考選部暫准報考緩發\n    及格證書行政契約」16件、原告等人畢業學校整理表、「98\n    年第二次專門職業及技術人員高等暨普通考試醫事人員（不\n    含牙醫師、助產師、職能治療師）、中醫師、心理師、營養\n    師考試暨醫師考試分試考試」應考須知、經我國駐外使館驗\n    證之原告等人於波蘭各醫學院畢業證書、歷年成績單、實習\n    證明文件16件、被告98年6 月25日選專字第0983301258號函\n    及原告之申覆書16件、被告98年7 月8 日召開醫師牙醫師考\n    試審議委員會第七次會議新聞稿；及被告提出原告等人及台\n    灣醫學生至被告處陳情紀要及相關報導、被告98年7 月14日\n    選專字第0983301452號函乙份、行政院衛生署98年7 月14日\n    衛署醫字第0980208143號函、監察院糾正案文節錄、監察院\n    通過對衛生署、教育部處理波蘭醫學系畢業生回國報考醫師\n    考試相關問題顯有違失之糾正案新聞稿及相關報導、被告98\n    年9 月30日選專字第09833020281 號函、被告98年6 月25日\n    選專字第0983301258號函、行政院衛生署98年12月1 日衛署\n    醫字第0980087896號函及原告己○○等五人實習分發一覽表\n    、被告98年12月8 日選專字第09833024 83 號函、「98年第\n    二次專門職業及技術人員高等暨普通考試醫事人員（不含牙\n    醫師、助產師、職能治療師）、中醫師、心理師、營養師考\n    試暨醫師考試分試考試」應考須知、原告15人（莊家順及羅\n    友祺兩人除外）所回傳被告98年6 月25日選專字第09833012\n    58號函附件1 之回覆通知15件、行政院衛生署99年3 月12號\n    令、被告提出之原告等人報名表件及學經歷證件、原告與被\n    告所簽訂之系爭行政契約、被告提出之被告醫師牙醫師考試\n    審議委員會第5 次、第6 次、第7 刺、第8 次會議記錄（不\n    可閱覽卷）、98年第二次專門職業及技術人員高等考試醫師\n    考試、醫師考試分試考試應考人員與考選部簽訂行政契約名\n    冊（均為影本）附本院卷及原處分卷可查，足認為真實。\n（一）本件其他事實：\n  １、本件98年醫師考試應考須知第6 頁「應考資格證明文件」\n      醫師部分，除需繳驗「畢業（學位）證書」外，於醫師（\n      應試全部科目6 科）之附註欄載明：「前開醫師（應試全\n      部科目6 科），依專門職業及技術人員高等考試醫師牙醫\n      師考試分試考試規則第6 條第2 項規定，辦理至民國99年\n      1 月1日前為止，凡符合報考資格之應考人，請及早規劃\n      因應。」醫師（一）（應醫師考試分試考試第一試）之附\n      註欄記載：「以外國學歷報考醫師（一）者：依專門職業\n      及技術人員高等考試醫師牙醫師考試分試考試規則第6 條\n      附表一規定，須為教育部採認之國外大學、獨立學院醫學\n      系、科畢業，並經實習期滿成績及格，領有畢業證書者，\n      繳驗證明文件另見8.」。\n  ２、被告因原告等波蘭國等大學醫學院畢業，有「實習期滿成\n      績及格」所生之爭議，由審議委員會作成「暫准報考緩發\n      及格證書」決議前，於98年7 月14日以選專字第09833014\n      52號函徵求行政院衛生署之同意，經行政院衛生署於同日\n      衛署醫字第0980208143號函覆被告同意略以：「……貴部\n      函請本署配合辦理國外醫學畢業生暫准參加專門職業及技\n      術人員高等考試醫師、牙醫師考試及格人員之實習，敬表\n      同意。至實習期滿成績及格之證書，將由各該醫療機構發\n      給，另本署將請各醫療機構列冊函報本署，俾彙整成冊函\n      送貴部，作為核發考試及格證書之參考……。」\n  ３、監察院98年10月中旬針對原告等波蘭國大學醫學院之學歷\n      報考資格等問題，糾正行政院衛生署、教育部略以：波蘭\n      93年加入歐盟以來迄今不過6 年期間，國人於當年即前往\n      該國就讀醫學系者，於96年及97年間已陸續畢業，2 年間\n      即有37名畢業生以該國學歷應考並通過醫師考試，目前尚\n      就學中之人數，亦約670 名，相較於歐盟其他國家之留學\n      人數寥廖可數，留學波蘭人數之多，顯非尋常，非但嚴重\n      影響國內醫學系招生人數之管制總量，且其入學管道與國\n      內醫學系嚴格篩選學生素質相較，亦明顯寬鬆，甚至前往\n      該國取得醫學系學歷者如循國內升學管道，多數尚無法取\n      得進入國內醫學系就讀之資格，致國人對波蘭大學醫學系\n      開設英語學程廣收外籍學生之教育品質多存疑慮等語。\n（二）醫師考試制度之變革：\n  １、醫師法第2 條第1 項第1 款規定（醫師法於91年1 月16日\n      總統（91）華總一義字第09100007520 號令修正公布全文\n      43條；並自公布日起施行）自公布施行迄今均未修正。\n  ２、專門職業及技術人員高等考試醫師牙醫師考試分試考試規\n      則，經主管機關考試院以94年12月22日考臺組壹一字第09\n      400112051 號令訂定發布全文17條；並自96年1 月1 日施\n      行。是有開上開考試規則第2條規定，醫師之專門職業及\n      技術人員高等考試，已明文規定自「民國96年」開始實施\n      分試，即改採二階段考試制度，且慮及制度變革，為保障\n      應考人信賴利益，始訂定3 年之過渡期間，自99年1 月1\n      日起始全面施行。\n  ３、為配合國內醫學教育改革，被告92年度考選制度研討會，\n      邀請學者專家就國家考試醫師考試分試之可行性進行研討\n      ，報告人何橈通院長建議參考國外制度，改為二階段分試\n      ，第一試於國內大學醫學系修畢基礎課程時考，第二階段\n      於第一試及格，經實習期滿取得畢業證書後考，建議之初\n      各界意見紛陳，後經被告邀請各界研商，始漸達成共識，\n      於93年8 月30日正式召開「高等考試醫師考試改進相關事\n      宜會議」決定醫師考試採行分試制度，考試院乃於94年12\n      月22日配合訂定發布上開「專門職業及技術人員高等考試\n      醫師考試分試考試規則」，明訂自「民國96年」開始實施\n      分試，但具有該規則附表一醫師類科第1 款至第3 款規定\n      資格之一者（舊制醫學院需實習一年始能畢業之畢業生）\n      ，於民國99年1 月1 日前，得應專門職業及技術人員高等\n      考試醫師考試（應試全部科目6 科），俾給予該等應考人\n      3 年之緩衝期，以維護其應考信賴保護利益權利，而99年\n      1 月1 日起即全面採行醫師考試分試考試制度（參見前開\n      規則第6 條、第7 條規定，第1 試及格後始可應考第2 試\n      ）。\n七、本件兩造主張之事實，相關法律詳如上述，是本件主要爭點\n    乃原告所提出之波蘭國醫學院畢業證書等文件，是否符合「\n    經實習期滿成績及格」之要件？又原告提起之確認之訴，是\n    否有即受確認判決法律上之利益？以下就原告之訴有無理由\n    ，依序論述爭點如下。\n（一）本件原告主張系爭行政契約之第2 條、第3 條、第4 條等\n      違反行政程序法等相關法律規定，致發生無效而自始不成\n      立，故提起本件確認公法上法律關係不存在之訴；參照上\n      開有關行政訴訟法第6 條確認公法上法律關係「成立或不\n      成立」之規範，應包含「確認公法上法律關係存在或不存\n      在之訴訟」之說明，本件原告聲明形式上觀察，與行政訴\n      訟法第6 條第1 項前段確認公法上法律關係成立不成立之\n      訴訟類型相符，應先敘明。次查原告主張其起訴之訴訟標\n      的法律關係的原因事實，並無行政處分之存在，即兩造間\n      行政法上之法律關係非因行政處分（而係有償之雙務行政\n      契約）而發生，依據本院前揭說明，在確認之訴部分，尊\n      重當事人之處分權，從而，從形式上原告提起本件確認之\n      訴並未違背行政訴訟法第6 條第3 項規定之「確認訴訟之\n      備位性原則」，亦應先予敘明。\n（二）兩造對本件訟爭之行之行政行為（即原告主張為雙務之行\n      政契約，被告主張之行政程序法第136 條替代行政處分之\n      和解行政契約；即前述之系爭行政契約）之內容及簽立過\n      程等事實均不爭執詳如上事實概要欄所載；從而縱認系爭\n      行政契約為原告主張之「行政契約」，然本件系爭行政契\n      約不論是第1 條及第2 、3 、4 條及其他條文整體始形成\n      一個公法上之法律關係，上開法律關係特別是第1 條使用\n      「爰暫准乙方（按原告）報告98年醫師考試」，與第2 條\n      「乙方同意倘考試成績及格，願意接受甲方（按被告）暫\n      不發給醫師考試及格證書之決定……」及第3 條「乙方倘\n      於考試榜示及格三年內，未依上述方式，於國內實習期滿\n      成績及格……」及其他條文規定，整體構成一個完整之公\n      法上法律關係，彼此互相依存，不能各自分開創設獨立之\n      公法上法律關係，換言之，本件系爭行政契約全部實屬一\n      完整不可分之公法上法律關係，原告切割完整之法律關係\n      ，僅認系爭行政契約第2 、3 、4 條規定可分且違反行政\n      程序法等法律，認屬無效，而僅留存第1 條暫准報考之被\n      告之行政處分權，認並不存在「行政契約」，提起本件確\n      認公法上法律關係不存在之訴，其主張及事實理由顯有矛\n      盾（本件系爭行政契約並不可分），本難認有理由。\n（三）原告所提出之波蘭國醫學院畢業證書等文件，並不符合前\n      開醫師法第2條之「經實習期滿成績及格」要件。\n  １、按前開98年9 月16日醫師法施行細則部分條文修正總說明\n      略以：「……對持國外學歷回國參加考試者，其於國外使\n      用之語言及接觸之疾病型態，顯與國內各類醫學生有所不\n      同，需要在其參加考試前，於國內醫療機構接受與國內醫\n      學生相當之臨床實作科別及週數或時數之訓練，以確認其\n      與我國的醫學院醫學系畢業生具有相似之臨床經驗。」另\n      依醫師法施行細則修正條文第1 條之2 之規定，就實習期\n      滿，其臨床實作之科別及週數或時數，並無區分國內外，\n      表示國內外之「實習期滿」標準必須一致，應先敘明。又\n      醫師法施行細則乃醫師法授權主管機關行政院衛生署訂立\n      之法規命令。而上開解釋醫師法第2 條「經實習期滿成績\n      及格」要件，並未逾越母法，本院應予尊重等情，詳如上\n      述，從而不論醫師法施行細則是否增修上開規定，均應為\n      相同解釋，應先敘明。\n  ２、次查本件原告報告98年度醫師考試後，被告認原告等人持\n      波蘭國學歷證件，有關是否「經實習期滿成績及格」要件\n      有疑義，乃送請醫師牙醫師考試審議委員會98年6 月19日\n      第5 次會議審議，經認為原告所提證件不符，乃決議通知\n      原告補繳畢業後1 年實習證明後再議，被告乃於同年月25\n      日選專字第0983301258號書函通知補件。原告陸續向被告\n      提出申覆，被告為求慎重，即於同年7 月3 、8 日及15日\n      又分別召開醫師牙醫師考試審議委員會第6 、7 、8 次會\n      議。其中第6 次會議決議，以原告等均未提出合乎規定之\n      實習證明不准報考，第7 次會議同意應考人（含原告）推\n      派代表到場說明，惟決議仍以原告在學期間之見習與實習\n      未作明確區別，依國內學制其大多屬見習性質並非「實習\n      」，與國內學制1 年完整實習有別，核與醫師法第2 條「\n      ……實習期滿成績及格……」之規定不符，不准報考。第\n      8 次會議經被告協議相關單位提出建議經審議後決議：「\n      一、同意被告與波蘭波茲南等4 所醫學大學及愛爾蘭都柏\n      林大學醫學院畢業生簽訂行政契約以「暫准報考緩發及格\n      證書」方式，並對行政契約修正通過」（即原處分卷不可\n      供閱覽部分卷），被告依上開第8 次會議議決，始有本件\n      原告主張之系爭行政契約。又參照上開法律說明可知，被\n      告醫師牙醫師考試審議委員會之組織合法、前述審議程序\n      正當合法，亦應先予敘明。\n  ３、又醫師法第2 條規定之「經實習期滿成績及格」構成要件\n      ，其所謂實習期滿，則屬不確定概念，而法規中不確定法\n      律概念，不論是要件或法律效果，或於多重解釋發生時，\n      由行政機詮釋或適用之結果，作成單一解釋與適用。行政\n      法院就此種行政機關所為不確定法律概念之判斷及選擇，\n      固得監督，惟體現憲法、立法、行政、司法權之作用，僅\n      為合法性監督，即對行政機關之裁量、判斷如認有逾越權\n      限或濫用、恣意情事，自應予以糾正；申言之，行政法院\n      監督及審查密度如何，自應事件不同而異，並應視組織及\n      程序是否完備，判斷之政策性及專業性高低等，而認行政\n      機關有一定之判斷餘地。是以，上開醫師法第2 條規定之\n      醫師應考資格之規定，涉及醫師專業技術性之實際需要，\n      與國民健康及生命之公益息息相關，並具有高度之屬人性\n      ，因此，辦理醫師考試機關，對上開「實習期滿」不確定\n      法律概念之解釋及適用，只要是非基於錯誤之事實，或基\n      於事件無關之考量、或組織不合法、未遵守法定程序，或\n      顯然違反平等原則、比例原則及一般公認之價值判斷標準\n      者外，行政法院應採取較低密度審查標準，並應尊重其判\n      斷餘地。查本件原告所提出之波蘭國醫學院之「實習」是\n      否符合醫師法第2 條第1 項第1 款、教育部大學辦理國外\n      學歷採認辦法第8 條規定之「實習」或「相當於實習」，\n      經被告所屬醫師牙醫師考試審議委員會之專業委員第5 、\n      6 次會議決議，認原告應考時提出之波蘭國醫師院之學歷\n      資料，與上開「實習期滿」要件不符，而不准報考，並通\n      知原告補提出實習一年之證據，亦有被告提出不可閱卷第\n      3-9 頁、第30-36 頁可證。而本件被告作成此部分決定所\n      依據之醫師牙醫師考試審議委員會審議過程合法正當又如\n      上述，同時被告不准原告報考98年醫師考試之決定（原告\n      提出之波蘭國醫師院之學歷資料，與上開「實習期滿」要\n      件不符）並非基於錯誤之事實或其他無關之考量，亦未違\n      反一般公認行政法價值判斷標準；參照上開說明，本院自\n      宜予尊重。\n  ４、綜上，本件原告之提出報考之學歷證件，不符實習期滿之\n      要件，從而被告抗辯系爭行政契約之第2 、3 、4 條規定\n      並無違法，即足認定。因此原告主張違法並提起本件確認\n      之訴並無理由。\n  ５、又如前述應適用之法律說明，原告提起本件訴訟（98年10\n      月9 日）前，醫師法施行細則業於98年9 月16日增訂第1\n      之1 條至第1 之5 條規定；而參考前述專門職業及技術人\n      員高等考試醫師牙醫師考試分試考試規則（考試院以94年\n      12月22日考臺組壹一字第09400112051 號令訂定發布）規\n      定及說明三，自98年9 月16日醫師法施行細則部分增訂條\n      文起，醫師考試應全面採行醫師考試分試考試制度（即專\n      門職業及技術人員高等考試醫師牙醫師考試分試考試規則\n      6 條、第7 條規定，第1 試及格後始可應考第2 試）；本\n      件原告訟爭「實習期滿」應考資格之爭議，因此而不續存\n      在，從而原告就系爭行政契約第4 條規定，退步言，姑不\n      論其是否具備法律關係性質，請求確認法律關係不存在，\n      即無確認之利益，應併敘明。\n  ６、再查原告雖陳稱98年以前持本件波蘭國原告畢業學校相同\n      證件報考醫師考試均獲准考，本件則不同意報考，是系爭\n      行政契約第2 、3 、4 條規定顯有違平等原則云云。惟：\n      (1)按憲法之平等原則要求行政機關對於事物本質上相同之\n        事件作相同處理，乃形成行政自我拘束，惟憲法之平等\n        原則係指合法之平等，不包含違法之平等。故行政先例\n        需屬合法者，乃行政自我拘束之前提要件，憲法之平等\n        原則，並非賦予人民有要求行政機關重複錯誤之請求權\n        。\n      (2)本件原告主張之波蘭國學歷證件等，與醫師法第2 條「\n        經實習期滿成績及格」要件不符如上述，是原告持98年\n        以前之被告准報考之不合法案例，主張被告應受行政自\n        我拘束云云，參照首開說明，本無理由。\n      (3)再查依被告統計，持波蘭醫學院學經歷之學生報考醫師\n        考試，已由95年1 人報考、96年17人報考急速擴增至98\n        年118 人報考) ，目前循相同管道在波蘭修習醫學之台\n        灣留學生已高達六百多人，且波蘭醫學院係針對外國學\n        生開設專班（絕大多數係台灣學生，其中亦有其他國家\n        學生）以英語開設的課程，而留學生本身在波蘭醫院實\n        習部分亦需透過翻譯與病人互動等語明確。而被告醫師\n        牙醫師考試審議委員會第7 次會議，亦邀請原告等派代\n        表到會陳述意見如前述，經審議委員等專家詳細詢問原\n        告等在波蘭修習醫學系課程與實習實際之狀況後，認為\n        從英語國際班實習互動與醫院值夜班情況，認為與國內\n        實習未完全相當等事實，亦有原處分卷不可供閱覽部分\n        第49～64頁可證，是本件被告經審慎調查後，為系爭行\n        政契約之第2 、3 、4 條規定，亦屬有據；綜上此部分\n        原告違反平等原則之主張云云，並不足採。況且，契約\n        之關係乃立於當事人自治原則，契約內容未違反法律之\n        強行規定（無效）或公序良俗外，均不應「禁反言」，\n        而本件原告對於被告拒絕報考，不以通常之行政救濟程\n        序，謀求救濟，卻以其他方式，以簽定「系爭行政契約\n        」取得報考資格後，反言被告違反平等原則，有失誠信\n        ，委無可取。\n（四）原告乙○○等11人（即除甲○○、己○○、辛○○、癸○\n      ○、子○○5 人以外），雖簽立系爭行政契約然參加本件\n      98年醫師考試但未獲及格評定之事實詳如上述。而醫師法\n      施行細則於原告起訴前亦增修第1 之1 條至第1 之5 條規\n      定亦如前述，是本件醫師法第2 條「經實習期滿成績及格\n      」之爭執，已有法令明確規定，且原告乙○○亦依照新修\n      正之規定檢附證件報考99年1 月23日舉行之99年第一次專\n      技高考醫師考試分試考試第一試，並經被告以98年12月8\n      日選專字第0983302483號函准予報考；是參照上開行政訴\n      訟法第6 條規定之法律說明，原告乙○○等11人有關報考\n      醫師考試之公法上法律關係未有不明確，而致原告在公法\n      上應醫師考試之之地位有受侵害之危險，更無從藉由原告\n      提起之本件確認之訴除去之，從而此部分原告之訴欠缺權\n      利保護之必要即無確認訴訟訴之利益，在法律上為無理由\n      ，應以判決駁回之。\n（五）原告甲○○、己○○、辛○○、癸○○、子○○5 人參加\n      98年醫師考試及格，並已分發至各署立醫院實習詳如上述\n      ，而本件系爭行政契約第2 、3 、4 條規定並無原告所指\n      之違法而不存在詳如上述，是此部分原告訴請確認法律關\n      係不存在云云，亦無理由，應予駁回。\n（六）本件應適用之法律及事實理由及本院見解詳如上述，兩造\n      其餘攻擊防禦方法，核與判斷結果無涉，爰不一一敘明。\n八、據上論結，本件原告之訴為無理由，依行政訴訟法第98條第\n    1項前段、第104 條，民事訴訟法第85條第1 項前段判決如\n    主文。",
    "reason": "一、程序事項：按當事人應就訴訟關係為事實上及法律上之陳述\n    ，行政訴訟法第122 條第2 項定有明文，又同法第132 條準\n    用民事訴訟法第195 條第1 項規定：「當事人就其提出之事\n    實，應為真實及完全之陳述。」即當事人對事實及法律上之\n    訴訟關係，有完全陳述之義務，此就行政訴訟在人民公權利\n    保障理念下，權利是否以及如何行使，自應委由權利人自主\n    決定，故有關訴訟程序之開始，訴訟標的之特定，訴訟程序\n    之終結等，自應賦與當事人即人民自主權，即人民對於訴訟\n    標的或訴訟中之訴之聲明有一定之處分權，從而審判長於訴\n    訟程序中行使闡明義務後，若原告即處分權人仍堅持己見，\n    參照上開說明，本院即已盡闡明義務。本件本院經闡明依司\n    法院釋字第546 號解釋，拒絕應考之決定，性質屬行政處分\n    ，系爭「考選部『暫准報考緩發及格證書』行政契約」第2\n    條、第3 條、第4 條是否為行政處分之附款（條件或負擔）\n    請原告確認，然原告仍稱上開「考選部『暫准報考緩發及格\n    證書』行政契約」性質為行政契約，且屬有對價關係之行政\n    契約，並非行政處分，故仍應提起本件確認之訴而無庸更改\n    其聲明及陳述；基於尊重當事人之處分權，本院仍就原告聲\n    明主張之範圍審認，並敘明理由，應先敘明。\n二、事實概要：原告等人分別波蘭國波茲南醫學大學、羅茲醫學\n    大學、西里西亞醫學大學之畢業生（詳如附件），欲參加被\n    告於民國（下同）98年8 月1 日至98年8 月2 日舉辦之「98\n    年第二次專門職業及技術人員高等暨普通考試醫事人員（不\n    含牙醫師、助產師、職能治療師）、中醫師、心理師、營養\n    師考試暨醫師考試分試考試」（下稱98年醫師考試）。原告\n    依據被告所制訂之應考須知第八頁第八點之規定，均於限定\n    期間內，提出經我國駐外使館驗證之波蘭各醫學院畢業證書\n    、歷年成績單、實習證明等文件，向被告提出報名。嗣被告\n    以98年6 月25日選專字第0983301258號函分別通知原告等，\n    略以：(一)、依據本部醫師牙醫師考試審議委員會第五次會議\n    決議辦理。(二)依專門職業及技術人員高等暨普通考試醫事人\n    員考試規則附表一醫師類科應考資格第1 款之規定，……畢\n    業，並經實習期滿成績及格，領有畢業證書者，……(三)依據\n    會議決議結果，原告應考資格證明文件未齊，所繳驗之實習\n    證明不予採認，應補繳自各該校畢業以後的一年實習證明。\n    (四)原告尚能補件，請於98年6 月30日通知傳真被告，並於98\n    年7 月10日前補繳相關實習證明文件之原本影印本及中文議\n    本……，憑以覆審，逾期不准報名，所繳報名費用，一律收\n    繳國庫，概不退還……等語。嗣原告接獲上開函件後分別於\n    98年6 月間陸續向被告提出回覆略以：原告申請准予暫時報\n    名，相關證明將於98年7 月10日前寄送被告等語；另由原告\n    等考生家長等向被告陳情，原告等亦陸續於98年6 月29日、\n    30日、7 月1 日陸續向被告提出申覆。嗣被告於98年7 月6\n    日、9 日再召開醫師牙醫師考試審議委員會第六、七次會議\n    ，其中第七次會議邀請波蘭國等醫學院畢業生之考生代表與\n    會說明有關實習情形後，認為原告等34人提出證明，因見習\n    與實習未區別，依國內學制其大多屬見習性質並非「實習」\n    ，與國內學制1 年完整實習有別，爰與醫師法第2 條「……\n    實習期滿成績及格……」之規定不相當，不予報考。原告除\n    再向被告繼續陳情外，亦曾陸續自98年7 月13日、14日起，\n    分別向本院具狀聲請假處分保全程序。嗣被告98年7 月16日\n    召開醫師牙醫師考試審議委員會第八次會議審議結果，同意\n    被告與波蘭國醫學院畢業生之原告等考生，簽定行政契約，\n    以「暫准報考緩發及格證書」方式，限報考本件98年第二次\n    專門職業及技術人員考試。而原告接獲通知後，於98年7 月\n    中旬後，簽訂被告寄發之「考選部『暫准報考緩發及格證書\n    』行政契約」（下稱系爭行政契約）一式三份，系爭行政契\n    約記載「……一、甲方在乙方應考資格中「實習期滿成績及\n    格」部分與國內醫學院實習期間及內容是否相當尚具爭議情\n    況下，……甲方暫准乙方報考98年第2 次專門職業及技術人\n    員高等考試醫師考試。二、乙方同意倘考試成績及格，願意\n    接受甲方暫不發給醫師考試及格證書之決定，俟自行聲請或\n    接受行政院衛生署安排於國內適當層級之醫療機構，完成與\n    國內醫學院相當期間與內容之實習，於實習期滿成績及格後\n    ，由相關醫療機構出具實習證明並由行政院……。三、乙方\n    倘於考試榜示及格三年內，未依上述方式，於國內實習期滿\n    成績及格或實習不及格，甲方將依專門職業及技術人員考試\n    法第23條規定，以自始不具備應考資格為由，報請考試院撤\n    銷考試及格資格，不發給考試及格證書。四、乙方同意未及\n    格，應依醫師法施行細則修正發佈之有關實習規定，經實習\n    期滿成績及格後，始得再行報考醫師考試分試第一試。……\n    」，原告於系爭行政契約上簽名後，陸續於98年7 月20日左\n    右寄回被告。被告於收到原告所簽署並繳回之系爭行政契約\n    書後，始將行政契約書一份及准考證併同寄給原告等，原告\n    等人陸續於98年7 月23日左右收到前述行政契約及准考證，\n    於98 年8月1 日參加該次醫師考試。而上開醫師考試業於98\n    年9 月30日榜示，原告甲○○、己○○、辛○○、癸○○及\n    子○○5 人醫師考試及格，同日被告亦依系爭行政契約約定\n    ，將甲○○等5 人及格人員名冊函送至行政院衛生署，請其\n    安排渠等至國內各醫療機構實習；行政院衛生署則以98年12\n    月1 日衛署醫字第0980 087896 號函，分發上開考試及格之\n    原告至各署立醫院實習。其餘未及格之原告業已由被告於98\n    年12月8 日以選專字第09 83302483 號函准其報考99年1 月\n    23 日 舉行之99年第一次專技高考醫師考試分試考試第一試\n    ，並已於99年1 月7 日寄發入場證在案。又本件原告於98年\n    10月9 日向本院提起本件確認公法上法律關係不存在之訴訟\n    。\n三、原告起訴主張略以：\n（一）程序方面：\n  １、本件原告提起之訴訟乃確認系爭行政契約中之第二、三、\n      四條約定之法律關係不存在，並非確認行政處分無效或違\n      法，應屬「確認法律關係存否之訴」。另被告98年6 月25\n      日選專字第0983301258號函文，主旨係載明要求原告等補\n      正文件，並未記載已否准原告等之報考等事實甚明；況且\n      原告等人亦已對被告上開函文均以書面提出申覆表示不服\n      ，然被告對於原告等上開申覆書並未再回函表示予以駁回\n      或否准原告等之報考，足證被告稱原告應對其98年6 月25\n      日否准處分提起撤銷之訴，並無理由；故本件原告就系爭\n      行政契約內容提起確認訴訟並無違反備位性原則。\n  ２、本件原告應考資格是否具備，應依醫師法第2 條第1 項第\n      1 款及依專門職業及技術人員考試法第5 條規定，所制定\n      之專門職業及技術人員高等考試醫師牙醫師考試分試考試\n      規則第六條之附表一、應考須知第6 頁亦明確規定，原告\n      等人報考系爭醫師考試之應考資格為「符合教育部採認之\n      國外大學、獨立學院醫學醫學系、科畢業，並經實習期滿\n      成績及格，領有畢業證書者」等規定認定。原告報考資格\n      符合上開法律規定，故並無被告所稱會將行政契約變成授\n      益行政處分之情形。另查系爭行政契約第4 條對本件醫師\n      考試未及格之原告11人言，顯違反法律不溯既往原則，且\n      剝奪此部分原告報考下次考試之應考資格，故就此次考試\n      未及格原告12人而言，當然具確認判決之法律上利益，而\n      得提起確認訴訟。\n  ３、關於已考試及格之原告甲○○、己○○、辛○○、子○○\n      、癸○○雖已分發至各署立醫院實習，然本件系爭醫師高\n      等考試及系爭行政契約簽立當時（98年8 月2 日），被告\n      系爭醫師考試分試考試規則尚未修訂，故被告於98年10月\n      14日修訂之上開考試規則，並無溯及效力，被告抗辯此部\n      分原告訴訟無保護必要云云，應屬無據。又本件訴訟獲致\n      勝訴判決時，原告等甲○○5人即可中止實習而要求被告\n      發給考試及格證書，故原告等5 人自仍有提起本件訴訟之\n      法律上利益及權利保護必要。\n  ４、被告98年6 月25日函文僅要求原告補正文件，並未記載已\n      否准原告之報考等，而原告對上開函文均已向被告提出申\n      覆書請求救濟，但被告對原告申覆書未為任何處置，亦未\n      作成駁回之決定，則原告亦無從進行後續行政訴訟之救濟\n      程序；且縱使撤銷上開被告98年6 月25日函文之處分，本\n      件系爭行政契約不當然因此失其效力，足見原告仍有提起\n      本件確認之訴之法律上利益及權利保護必要。是被告稱本\n      件訴訟之提起違反行政訴訟法第6 條第3 項規定云云，應\n      屬無理由。\n  ５、本件原告等人分別留學於波蘭國波茲南醫學大學、羅茲醫\n      學大學、西里西亞醫學大學畢業，並經實習期滿成績及格\n      ，已符合法定應考資格之要件，被告即應准予原告報考，\n      但原告竟以系爭行政契約，在未有法律明文授權下，課與\n      原告額外之實習義務，使原告須於考畢後再補為實習，否\n      則不發給證書或不得報名往後年度之考試，即屬侵害原告\n      之權利，是原告權利受侵害甚明確；原告在無其他救濟途\n      徑之情形下，為保障自身取得合格證書之權利，方先依照\n      該契約之內容補行實習，故本件確認之訴確認系爭行政契\n      約之第2條等該契約條款無效而該法律關係不成立，則原\n      告自可免於此等義務，被告稱無權利保護之必要云云，應\n      屬無理由。\n（二）實體部分：\n  １、被告要求原告等所簽訂之系爭行政契約其中第二、三、四\n      條約定應屬違法無效而不存在：\n      (1)依據醫師法第2 條第1 項第1 款規定及專門職業及技術\n        人員高等考試醫師牙醫師考試分試考試規則第6 條之附\n        表一、應考須知第6 頁亦明確規定，原告應考資格為「\n        符合教育部採認規定之國外大學畢、獨立學院醫學醫學\n        系、科畢業」並「經實習期滿成績及格」而「領有畢業\n        證書者」即具有應考資格；而被告卻於系爭「暫准報考\n        緩發及格證書」行政契約內容所示，顯係約定以被告為\n        准予原告參加考試受益行政處分，與原告需重新或補行\n        實習及接受暫緩發及格證書，為雙方對待給付義務，而\n        成立行政契約中之雙務契約。惟所謂應考資格之訂定須\n        符合公平、公開原則和保障人民權益之目的乃屬當然，\n        自不得依據雙方之契約約定而有所變更，故仍應以上開\n        醫師法、專門職業及技術人員高等考試醫師牙醫師考試\n        分試考試規則等相關規定之要件，決定原告等人之應考\n        資格，即原告如符合應考資格，被告即應准予應考，反\n        之則否，被告依法並無行政裁量空間，應屬行政程序法\n        第135 條規定但書規定，依其性質不得為行政契約之情\n        形。\n      (2)該雙務契約之內容係約定原告等人考試後應再實習，顯\n        與確保應考人能於一定期限內，提出考試前已經具備應\n        考資格之證明無關，故與為確保准予考試受益行政處分\n        法定要件履行，即考試前已經具備應考資格為准許應考\n        受益處分之法定要件無關，故依據行政程序法第137 條\n        第2 項規定不得作成行政契約。綜上，被告准許原告考\n        試之受益行政處分之性質或依法律規定應不得締結行政\n        契約，故被告「暫准報考緩發及格證書」行政契約，違\n        背禁止規定而應為無效而不存在。\n      (3)且系爭行政契約第2 、3 、4 條約定應屬無效違背行政\n        程序法第135 條但書已如前述，故被告以之作為行政契\n        約，依上開規定，應屬無效；況有關原告考試後依法應\n        否再為實習或如何實習之事項，應屬於醫師法相關法令\n        所規範，被告依法並非該事項之主管機關，被告依法顯\n        無訂定上開事項行政契約之權限，應屬違反行政程序法\n        第14 2條、第111 條第1 項第6 款規定，足證上開系爭\n        行政契約之約定應為違法無效而不存在。\n  ２、考試機關所訂定各類科之應考資格時，亦應受一般法律原\n      則之拘束。惟查：\n      (1)本件被告所單方制訂之系爭行政契約條款，顯違反依法\n        行政原則。即依憲法第18條及中央法規標準法第5 條第\n        1 項第2 款之規定，上開應考資格之標準或限制，應以\n        法律規定之。前開所稱法律規定，即為前述醫師法第2\n        條規定及依專門職業及技術人員考試法第5 條規定，所\n        制定之專門職業及技術人員高等考試醫師牙醫師考試分\n        試考試規則第六條之附表一。被告依據依行政程序法第\n        4 條規定「依法行政原則」，不得再以系爭行政契約另\n        行增定准予考試之條件，被告擅予增加法律所未有之限\n        制，應屬違法而無效。\n      (2)本件被告所訂系爭行政契約條款，違反行政程序法第6\n        條規定之「平等原則」。查原告於波蘭國各醫學院求學\n        過程，均依據該大學學制、課程內容之要求完成學業，\n        並經實習期滿成績及格，方取得畢業證書，而原告報考\n        本件醫師考試所提出之應考資格證明文件，均符合上開\n        應考須知之規定，亦與歷年被告機關辦理相同考試時，\n        所認定准予應考之波蘭國暨其他外國留學生學生之情形\n        皆無任何不同。且依被告91年3 月27日醫事人員考試審\n        議委員會第六次會議決議及醫師法第四條之一規定，原\n        告等人之實習資格即應予以採認，而符合醫師法第2條\n        第1 項第1 款「實習期滿成績及格」之要件，故原告之\n        應考資格應屬合法。原告信賴被告長久以來之慣行和法\n        令解釋，花費多年時間出國學習醫學，依同樣條件、方\n        式完成學業且實習期滿成績及格並取得證明文件，報考\n        本件醫師考試，自屬合理信賴被告應採取上開歷年相同\n        應考資格審查標準，豈料被告竟事後於審查時，先突然\n        來函通知，對於原告等人之實習期滿成績及格證明「不\n        予採認」，其後又於系爭行政契約中增加准予考試之條\n        件，顯然違反行政程序法第6 條之規定，足證上開系爭\n        行政契約條款之差別待遇違反平等原則又無正當原因，\n        應屬違法無效。\n      (3)本件被告所訂系爭行政契約條款，顯違反行政程序法不\n        當連結禁止原則：系爭行政契約性質應為「代替行政處\n        分」之行政契約，應受行政程序法第142 條之規範限制\n        。又該契約內容為規定原告有諸多義務需要履行，而上\n        述契約既為被告單方片面所制訂定之事實，且原告等又\n        係基於時間緊迫等因素，顯陷於無充分選擇自由，更無\n        參與契約條款討論商議之機會等等顯不公平情況下，故\n        對原告而言，應為顯失公平之負擔義務契約，該契約自\n        應受行政程序法第137 條規範之限制，同時雙方對待給\n        付顯不相當，亦顯失公平。又系爭行政契約雖記載，其\n        目的在於保障國人生命身體健康並兼顧原告等人應國家\n        考試之權利，然所謂「實習期滿成績及格」僅為應考資\n        格的標準，並非考試及格的標準，具備應考資格者仍須\n        參加考試成績及格，方有可能取得及格證書執行業務，\n        此時方與所謂國人生命身體健康產生正當且合理關聯性\n        ，然被告片面對原告等人不法增加法律所未規定之報考\n        資格限制，自屬違法不當。同時與被告91年決議或不同\n        於以往歷年採認標準；顯見被告之行為不僅違反前開行\n        政程序法第137 條第1 項第3 款禁止不當連結原則及第\n        137 條第2項，更屬違反同法第8 條規定之誠信原則及\n        同法第5條之明確性原則。\n      (4)系爭行政契約約定，顯違反法律優位原則：依據前開專\n        門執業及技術人員考試法第1 條、專門執業及技術人員\n        高等考試醫師牙醫師考試分試考試規則第14 條 、醫師\n        法第6 條之規定，原告等人若考試及格，對於被告即有\n        請領及格證書之權利，而被告亦有給予及格證書的法定\n        義務，被告依法應無裁量的空間。然今被告片面制定系\n        爭行政契約，顯然逾越其法定裁量範圍，且為違背法令\n        對原告增加法律所未規定限制之行為，應屬違反法律優\n        位原則而無效。\n      (5)再依行政程序法第141 條規定，可知法律行為的內容應\n        具備合法、妥當、可能、確定四項要件，且行政程序法\n        第5 條亦規定：「行政行為之內容應明確。」惟查：系\n        爭行政契約第2 條、第4 條所指外國醫學院畢業生能否\n        在國內醫院實習？如何實習？之相關規定，以及所指醫\n        師法施行細則修正發佈之有關實習規定等事項之內容為\n        何？何時實施？等事實，於系爭行政契約訂約當時，均\n        付之闕如，亦尚無從知悉，皆屬客觀上無法確定之情形\n        ，足見系爭行政契約顯違反行政程序法第5 條規定及顯\n        有法律行為標的欠缺確定性之無效情形。\n  ３、依據司法院釋字第348 號解釋之協同意見書揭示「公法契\n      約故應受行政主體與他造當事人就約定之內容自由達成協\n      議……人民僅有簽訂與否之自由，並無對其內容與行政主\n      體協商修改之餘地，故其契約內容首重公平合理，不得使\n      人民負不相當之對待給付義務。」是本件原告於系爭行政\n      契約中，最低限度仍應享有締約自由及承諾自由。查原告\n      等人於98年7 月17日左右，接獲被告人員表示須簽訂系爭\n      行政契約，才會核發准考證，當時距離考試不到10日之時\n      間，而原告等人向本院所聲請假處分案件，尚無具體結果\n      ，原告又無其他立即救濟途徑，如果原告等人拒絕簽訂系\n      爭行政契約，根本不可能有參加此次考試之機會，足證原\n      告係於毫無選擇餘地之情形下，被迫不得已而簽訂系爭行\n      政契約，顯見被告所稱「原告在自由意願下簽訂此一和解\n      契約云云」，顯與事實不合。\n  ４、被告雖主張系爭行政契約為行政程序法第136 條之和解契\n      約云云，惟查：縱認被告所稱，雙方對於波蘭醫學院之實\n      習課程是否與我國醫學院之實習相當存有爭義，而成立和\n      解契約，然系爭行政契約內容中記載，被告有「暫准原告\n      報考」、「原告考試及格並實習期滿，考試院發給考試及\n      格證書」義務及「原告考試及格然無實習或實習不及格時\n      ，撤銷考試及格資格不發給考試及格證書」之權利，而原\n      告等有「原告考試及格時，需完成與國內醫學院相當期間\n      與內容之實習」及「原告考試不及格時，需實習始得再行\n      報考」等義務，足見系爭行政契約原、被告間互負給付義\n      務，亦屬成立雙務契約之情形。況且被告於答辯狀自承「\n      第五次會議決議，通知補繳畢業後一年實習證明後再議。\n      ……嗣該審議委員會第6 次會議決議，以原告等均未提出\n      合乎規定之實習證明不准報考」、「第7 次會議同意應考\n      人（含原告）推派代表到場說明，惟決議仍以原告在學期\n      間之見習與實習未做明確區分……核與醫師法第2 條……\n      之規定不符，不准報考」等情，顯見被告係已明確認定原\n      告等不符報考資格而作成不准報考之決議，應非其現今所\n      稱原告等之報考資格認定尚有疑義而無法查明事實之情形\n      ，足見被告上開所稱系爭行政契約之簽定為「和解契約」\n      ，非無疑義。\n  ５、被告又主張對於外國醫學院之實習是否與國內醫學院實習\n      『相當』，為不確定法律概念，具有判斷餘地，本件經由\n      專業審議委員會本於專業權責加以判斷，作成先通過考試\n      後，補實習再執業決定之和解契約云云，惟查：被告係依\n      據醫師法第2 條第1 項第1 款、專門職業及技術人員考試\n      法第五條規定，所制定之專門職業及技術人員高等考試醫\n      師牙醫師考試分試考試規則第六條之附表一，辦理本件醫\n      師特考，應考人之資格要件明確，並無被告所稱「不確定\n      法律概念」而授予被告裁量權之情形；依被告之「應考資\n      格審查規則」第2 條、第3 條規定，被告於審核應考者符\n      合法定要件之情形，即應為准考之處分，換言之，係為羈\n      束處分，即同一申請於相同時點審查是否符合應考要件，\n      只有「符合」或「不符合」擇一之明確判定，顯見被告並\n      無一方面既已決議認定原告等「不符合應考資格不得考試\n      」，另方面卻又以行政契約准予原告等應考之法律上裁量\n      權。足證系爭行政契約應有行政程序法第135 條但書所規\n      定，依其性質或法律規定不得締約之違法無效情形。同理\n      系爭行政契約第2 、3 、4 條等約定，既無法律明文規定\n      ，亦與確保行政契約之法定要件之履行無關，則依行政程\n      序法第137 條第2 項規定適用同法第93條第1 項後段，被\n      告應不得為之。\n  ６、有關醫師法第2 條第1 項第1 款規定事項，主管機關應為\n      行政院衛生署，而非被告。且有關上開法律規定之應考資\n      格如有修改之必要時，亦須由主管機關依法定程序進行修\n      法，然本件系爭行政契約簽定當時，醫師法規定之應考資\n      格相關法令規定尚未修改，然被告卻已先於系爭行政契約\n      中，自行規定原告須補行有關國內實習事項，已屬逾越被\n      告之法定職權。依行政程序法第142 條第1 項第1 款及同\n      法第111 條第1 項第6 款規定，上開有關補行實習之契約\n      條款應屬無效。\n  ７、關於被告主張「原告違反禁反言、誠信原則，原告乃在自\n      由意願下簽訂此一合約，也獲得報考資格之實質利益且『\n      已經完考』，原告既然合意締結和解在前，事後即不得違\n      反其承諾。」等語云云。查被告為執掌國家考試之機關，\n      本件被告又係於臨考前始要求原告簽訂系爭行政契約，原\n      告當時基於時間緊迫且欠缺救濟途徑等情形，不得已而簽\n      定，實非出於自由意願，已如前述詳述，且所謂取得報考\n      資格之實質利益，本應為原告應有之法定權益，是原告提\n      起本件訴訟，並無違反禁反言或誠信原則。\n  ８、又原告分別留學於波蘭國波茲南醫學大學、羅茲醫學大學\n      、西里西亞醫學大學畢業，並經實習期滿成績及格，已滿\n      足本考試應考資格所定之要件，原告竟以系爭契約條款，\n      在未獲法律授權之情形下，課與原告考試後須另於國內額\n      外實習之義務，否則即不發給證書或不得報名下年度之考\n      試，該條款乃不合法且違反平等原則等一般法律原則，應\n      屬無效已如前述，原告自不受該無效條款之其拘束，系爭\n      行政契約之法律關係亦為不成立，被告主張原告應受拘束\n      ，要無理由。\n（三）綜上，系爭行政契約第2 條、第3 條及第4 條應有違反上\n      述法律規定、原則而無效情事而法律關係不存在，爰依行\n      政訴訟法第6 條第1 項等規定，得提起本件確認之訴，聲\n      明：１、確認原告等分別與被告所簽系爭行政契約所示「\n      考選部暫准報考緩發及格證書行政契約」，其中第2 條、\n      第3 條、第4 條約定之法律關係不存在。２、訴訟費用由\n      被告負擔。\n四、被告抗辯略以：\n（一）程序方面：\n  １、原告起訴違反確認訴訟之備位性原則：本件爭議實質上係\n      因原告對於被告認定其波蘭醫學院學歷無法取得報考醫師\n      資格之認定不服，但當時因考試即將舉行，且原告復一再\n      陳情，被告為保障其參與考試之機會，始在經協調行政院\n      衛生署同意配合辦理實習作業以及『雙方合意下』分別在\n      98年7 月18日至21日與原告簽訂系爭行政契約。核其實質\n      上所不服者乃係「被告」當初否准其具有專技人員醫師高\n      考報考資格之決議，依行政訴訟法第6 條第3 項之規定，\n      原告應在獲知其被認定不符報考資格之後依法提起訴願、\n      撤銷訴訟，亦即當時如對該行政決定有所不服原應對該「\n      否准」且退件報考資格之行政處分提出撤銷訴訟，而當時\n      原告等人對並未對該處分提出訴願而僅四處陳情，現否准\n      報考及退件之處分已確定之後始提出確認訴訟，應足認本\n      件起訴程式有違反確認訴訟之備位原則。\n  ２、原告訴之聲明不合法：如依原告之聲明將造成法院以判決\n      方式將『行政契約』變更為『授益行政處分』，此已自創\n      法律所無之訴訟類型，而屬誤用訴訟類型：細繹原告訴之\n      聲明係確認：「考選部暫准報考緩發及格證書行政契約其\n      中第二條、第三條、第四條約定之法律關係不存在」，惟\n      果真如依其聲明以判決方式確認行政契約之第二、三、四\n      條均無效而不存在之後，全份契約僅保留第一條「考選部\n      暫准原告等報考醫師高考」，而『准予報考之法律性質係\n      授益行政處分』，惟行政訴訟法並無法律依據可透過法院\n      之判決將行政契約變成授益行政處分之訴訟類型，蓋行政\n      契約與行政處分，本質上即為不同之行政行為，自無由法\n      院以判決之方式將行政契約以『判決方式』『變成』『行\n      政處分』餘地。如原告之目的係欲命被告作成「准予報考\n      之行政處分」應依行政訴訟法第5 條提起課予義務之訴。\n      惟不論以上何者，原告之訴訟類型均非適法當可確定。\n  ３、原告乙○○等11名未及格者並無即受確認判決之法律上利\n      益：本件醫師考試未及格者11人，已參加98年8 月1 日之\n      醫師考試而考試已於98年9 月30日榜示結束，所以被告已\n      完成行政契約之給付，因為原告乙○○等11名未及格，未\n      有後續實習問題，被告之義務已因履行完畢而消滅，故依\n      行政訴訟法第6 條之規定，原告乙○○等11名未及格者並\n      無即受確認判決之法律上利益。同時上開原告亦報名參加\n      99年1 月23日舉行之99年第一次專技高考醫師考試分試考\n      試第一試，並已於99年1 月7 日寄發入場證在案，是此部\n      分原告更無即受確認判決之法律上利益存在。\n  ５、原告之訴依其所訴之事實顯無理由，依法應不經言詞辯論\n      逕以判決駁回之：本件原告確認聲明係確認「考選部暫准\n      報考緩發及格證書行政契約第二、三、四條法律關係不存\n      在」，而依行政程序法第143 條之規定行政契約一部無效\n      者，全部無效；且明顯地如欠缺整份契約之二、三、四條\n      被告將不可能締結該行政契約，因此，本件無由透過行政\n      程序法第143 條但書之規定僅讓契約第一條『單獨』生效\n      ，原告之聲明主文僅依其形式上觀之已不合法，直接牴觸\n      行政程序法第143 條，故依行政訴訟法第107 條第3 項規\n      定，本院依法即應不經言詞辯論，逕以判決駁回原告之訴\n      。\n（二）實體方面：\n  １、系爭行政契約法律性質為行政程序法第136 條和解契約：\n      (1)依行政程序法第136 條之規定，機關負有職權調查事實\n        之義務，本件兩造間之爭執為波蘭醫學院之實習課程是\n        否與我國醫學院之實習『相當』（參照國外學歷採認辦\n        法第8 條），因簽訂契約之前已經即將舉行專技人員醫\n        師高考，具有時效性及急迫性，為避免侵害人民之權利\n        ，被告於已盡各種調查途徑仍不能查明該事實，為解決\n        爭執及達成行政目的始與原告依行政程序法第136 條規\n        定締結系爭和解契約，合先說明。\n      (2)本件所涉前開報考資格之「事實不明」爭議經過：\n        原告等係波蘭醫學院之畢業生，故其『學歷』部分經\n          認與醫師法第4 條之1 之學歷相符。所爭議者係其『\n          實習』部分，究竟是否符合醫師法第2 條第1 項第1\n          款其中所稱之『實習期滿』之內涵，蓋依據教育部大\n          學辦理國外學歷採認辦法第8 條規定：「國外學歷…\n          …修業期限、修習課程，應與國內同級同類學校規定\n          相當」。而本件原告等人在波蘭求學之『實習』過程\n          經被告機關邀集具各大醫學中心之醫師代表、行政院\n          衛生署……等召開醫師牙醫師考試審議委員會審議其\n          報考資格，並請原告等人到會陳述意見後，委員會一\n          致認為原告等人『波蘭醫學院之』『實習』僅相當於\n          『見習』，與我國醫學院之『實習』過程顯不相當，\n          而否准其報考資格。\n        醫師牙醫師考試審議委員會之組織合法、程序正當：\n          按考選部組織法第19條規定考試院爰訂定專門職業及\n          技術人員考試審議委員會組織規程，復按該組織規程\n          第2 條規定，該審議委員會成員由行政院衛生署副署\n          長、教育部醫事教育委員會執行秘書、醫學大學醫學\n          院院長、醫學系系主任、教學醫院院長、公會團體代\n          表及被告簡任以上高級人員組成，另邀請行政院衛生\n          署醫事處及教育部高等教育司派員列席，有關應考人\n          應考資格之疑義，均提該委員會審議，該組織嚴謹，\n          且程序正當，並將審議結果經被告核定後，始報請考\n          試院備查，以維應考人權益，可知過程至為審慎，依\n          此而做成之決定，即不容任意推翻。\n        原告接獲不符報考資格之通知後續處置：\n          嗣原告等多人接獲不符資格之通知後四處陳情謂其係\n          合法國外醫學院之畢業生竟不能報考醫師高考，當時\n          因考試在即且涉及在歐洲之波蘭醫學院其實習之『實\n          際狀況』調查非短期可能明確，因而涉及行政處分(\n          准否報告之決定) 之事實不明確下，乃為行政程序法\n          第136 條規定「行政處分所依據之事實，經依職權調\n          查仍不能確定者」之情況。基於確保醫師專業資格水\n          準與維護國民健康之行政目的，以及原告等援前例得\n          以報考之期待，並為解決爭執( 得否報考醫師高考)\n          ，被告遂依據行政程序法第136 條與原告等人簽訂和\n          解之行政契約，以代替行政處分。\n  ２、原告誤認本件行政契約係行政程序法第137 條之雙務契約\n      並據此為基礎所為契約無效之主張，均因契約是否有效之\n      前提「契約定性」錯誤而失其附麗：本件行政契約雙方並\n      未因約定「被告准予參加考試」與「原告須重新或補行實\n      習及接受暫緩發及格證書」而使雙方互負對待給付義務，\n      而係因為「原告在波蘭之實習狀況」是否與國內醫學院之\n      實習『相當』所為之專業判斷已如前述，因此雙方所訂立\n      者乃行政程序法第136 條之和解契約，迺原告竟執行政程\n      序法第137 條之行政契約大肆主張契約無效，核其有關行\n      政程序法第137 條之主張均因前提不存在，即「契約定性\n      」錯誤而失其附麗，顯不可採。\n  ３、被告（審議委員會）對於外國醫學院之實習與國內醫學院\n      實習是否『相當』具有判斷餘地：\n      (1)本件情形，就現存具體事實涵攝至法律之構成要件判斷\n        （原告等人之波蘭醫學院之「實習」是否符合醫師法第\n        2 條第1 項第1 款、教育部大學辦理國外學歷採認辦法\n        第8 條規定之「實習」「相當」）。由於本件所涉之法\n        令之構成要件用語係以不確定之法律概念『相當』貳字\n        來表現，究竟是否相當則由主管機關依法令所組成之專\n        業審議委員會，本於專業之權責加以判斷，應認其決定\n        具有判斷餘地不容原告以一己主觀之見解主張無效。\n      (2)況查，本件波蘭醫學生之應考資格「實習」部分之認定\n        是否與國內醫學院之實習相當，隨著時空環境的不同而\n        時移事轉，經考選部醫師牙醫師考試審議委員會第7 次\n        會議，詳細詢問原告等在波蘭修習醫學系課程與實習實\n        際之狀況。委員們從英語國際班實習互動與醫院值夜班\n        情況，審慎討論後認為與國內實習未完全相當，委員會\n        作此專業判斷後為了彌補原告等實習與國內實習之完整\n        性及確保國內執業前先行瞭解國內病人與本土流行病等\n        ，審議委員會作成先通過考試後，補實習再執業之決定\n        。此乃被告依據之醫師法及教育部大學辦理國外學歷採\n        認辦法，關於國外「實習」與國內醫學院之實習是否相\n        當，容有判斷餘地。\n  ４、機關辦理本次專技人員醫師高考之審查歷程：\n      (1)各種國家考試應考人之應考資格原則由考選部擬定、考\n        試院發布，惟醫師法及其他醫事人員等相關法規由行政\n        院衛生署主管。另依醫師法施行細則部分條文修正總說\n        明：「對持國外學歷回國參加考試者，其於國外使用之\n        語言及接觸之疾病型態，顯與國內各類醫學生有所不同\n        ，需要在其參加考試前，於國內醫療機構接受與國內醫\n        學生相當之臨床實作科別及週數或時數之訓練，以確認\n        其與我國的醫學院醫學系畢業生具有相似之臨床經驗。\n        」且依醫師法施行細則第1 條之2 規定，就實習期滿，\n        其臨床實作之科別及週數或時數，並無區分國內外，表\n        示國內外之「實習期滿」標準必須一致。\n      (2)被告經提98年6 月19日召開之醫師牙醫師考試審議委員\n        會第5 次會議審議決議，通知補繳畢業後1 年實習證明\n        後再議。被告即於同年月25日選專字第0983301258號書\n        函通知原告等人補件。原告等乃於同年6 月29日、30日\n        及7 月1 日陸續向被告提出申覆，被告為求慎重，即於\n        同年7 月3 、8 日及15日又分別召開醫師牙醫師考試審\n        議委員會第6 、7 、8 次會議。嗣該審議委員會第6 次\n        會議決議，以原告等均未提出合乎規定之實習證明不准\n        報考；第7 次會議同意應考人（含原告）推派代表到場\n        說明，惟決議仍以原告在學期間之見習與實習未作明確\n        區別，依國內學制其大多屬見習性質並非「實習」，與\n        國內學制1 年完整實習有別，核與醫師法第2 條「……\n        實習期滿成績及格……」之規定不符，不准報考。\n      (3)另經考選部醫師牙醫師考試審議委員會第8 次會議審議\n        通過，決議：「一、同意被告與波蘭波茲南等4 所醫學\n        大學及愛爾蘭都柏林大學醫學院畢業生簽訂行政契約以\n        「暫准報考緩發及格證書」方式，並對行政契約修正通\n        過。二、前述權宜措施，僅限報考98年第二次專門職業\n        及技術人員高等考試醫師、牙醫師考試、醫師考試分試\n        考試第一試。三、考試及格證書以實習期滿成績及格之\n        日為生效日期。四、經醫師考試第一試及格者，應先完\n        成實習後再考第二試。五、未簽署行政契約者不准應本\n        次考試。六、本案應報請考試院核定。七、本考試暫准\n        報考成績及格人員在醫療機構實習期間，請衛生署落實\n        督導考核。八、函請教育部儘速查明波蘭大量培養醫學\n        系學生原由，其學制包括課程、見習、實習情形是否與\n        國內學制相當，俾供本會審查相關案件參考」。\n      (4)本案原告等17名擬報考98年第二次專門職業及技術人員\n        高等考試醫師考試、醫師考試分試考試第一試一案，經\n        第8 次會議決議：「比照第一案決議，同意被告與巳○\n        ○等33名波蘭波茲南等4 所醫學大學及愛爾蘭都柏林大\n        學醫學院畢業生簽訂行政契約以『暫准報考緩發及格證\n        書』方式，僅限報考98年第二次專門職業及技術人員高\n        等考試醫師考試、醫師考試分試考試第一試。」\n  ５、被告先取得衛生署同意，而衛生署同意配合辦理考試及格\n      後之實習程序之後，被告始與原告等簽行政契約之過程及\n      行政契約之內容：\n      (1)由於原告等係「實習期滿成績及格」所生之爭議，審議\n        委員會作成「暫准報考緩發及格證書」決議前，由被告\n        以98年7 月14日選專字第0983301452號函徵求行政院衛\n        生署之同意，而行政院衛生署於同日衛署醫字第098020\n        8143號函覆被告同意略以：「……貴部函請本署配合辦\n        理國外醫學畢業生暫准參加專門職業及技術人員高等考\n        試醫師、牙醫師考試及格人員之實習，敬表同意。至實\n        習期滿成績及格之證書，將由各該醫療機構發給，另本\n        署將請各醫療機構列冊函報本署，俾彙整成冊函送貴部\n        ，作為核發考試及格證書之參考……。」\n      (2)依上開協調取得共識，決定於醫師法施行細則修正發布\n        前，經98年第二次專技高考醫師考試及格之應考人，由\n        行政院衛生署安排於國內適當層級之醫療機構實習期滿\n        成績及格後，再由衛生署加以彙整成冊，被告始報請考\n        試院發給考試及格證書。由於被告考試採測驗式試題，\n        無法考出其實作( 實務) ，是以，審議委員會作成「暫\n        准報考」實已兼顧應考人考試權益，並為其實習主動與\n        衛生署連絡，對實習之疑義提出補救措施。被告作成「\n        暫准報考緩發及格證書」之作法。\n      (3)監察院亦認暫准報考緩發及格證書作法兼顧法令與應考\n        權益尚稱允當：依監察院糾正文表示，「……相較於歐\n        盟其他國家之留學人數寥廖可數，留學波蘭人數之多，\n        顯非尋常，非但嚴重影響國內醫學系招生人數之管制總\n        量，且其入學管道與國內醫學系嚴格篩選學生素質相較\n        ，亦明顯寬鬆，甚至前往該國取得醫學系學歷者如循國\n        內升學管道，多數尚無法取得進入國內醫學系就讀之資\n        格，致國人對波蘭大學醫學系開設英語學程廣收外籍學\n        生之教育品質多存疑慮。」（詳被證十五）監察委員針\n        對「波蘭醫學系畢業生回國報考醫師考試相關問題」所\n        做調查報告指出，在行政院衛生署未針對國外醫學系學\n        歷報考者之實習發布明確規定前，考選部「暫准報考緩\n        發及格證書」之作法「尚屬允當」。\n      (4)依上開協商決議採暫准報考緩發及格證書之作法後，98\n        年7 月15日考選部醫師牙醫師考試審議委員會第8 次會\n        議審議通過，依原告等與被告簽訂之行政契約，雙方議\n        定行政契約條款如「考選部『暫准報考緩發及格證書』\n        行政契約」。\n      (5)本次考試及格原告5 人，被告『已依行政契約』函請衛\n        生署安排其至醫院實習：\n        本次考試業於98年9 月30日榜示，原告等計有甲○○\n          、己○○、辛○○、癸○○及子○○等5 人醫師考試\n          及格，醫師考試分試考試無人及格。\n        被告業於98年9 月30日檢送5 名及格人員名冊至行政\n          院衛生署，請其安排渠等至國內各醫療機構實習。至\n          實習期滿成績及格之證書，將由各該實習醫療機構發\n          給，各醫療機構並列冊函報行政院衛生署後，由該署\n          彙編成冊函送被告，渠等5 人業與被告簽訂行政契約\n          ，對雙方均發生拘束力，『被告亦已依約履行安排其\n          及格後實習已如前述』，原告等就議定內容，即須遵\n          守，不得「一面享有行政契約之利益卻另一面否定契\n          約之效力」。\n        另原告乙○○、丙○○、丁○○、戊○○、庚○○、\n          壬○○、丑○○、寅○○、卯○○、辰○○及巳○○\n          等11人該次考試並未及格，若要報考99年第一次專門\n          職業及技術人員高等考試醫師考試分試考試第一試，\n          應依98年10月14日考試院修正發布之專門職業及技術\n          人員高等考試醫師牙醫師考試分試考試規則之規定報\n          考。\n  ６、原告違反禁反言原則：本件情形原告在自由意願下簽訂此\n      一和解契約，也獲得報考資格之實質利益且「已經考完」\n      ，豈有在「既得利益」已實現後，復爭執其無效，亦即被\n      告已充分保障原告之應考資格，未料事後原告竟在獲准參\n      與本次考試後始主張和解契約無效，被告既已合意締結和\n      解在先，事後即不得違反其承諾，否則即有違行政法上禁\n      反言原則之法理。\n  ７、原告違反誠信原則：本件原告於簽訂行政契約之後已『享\n      有』契約第一條之授益行政處分之利益( 准予參加考試)\n      且也『已經參加完考試』並有原告甲○○、己○○、辛○\n      ○、癸○○及子○○等5 人醫師考試還經榜示錄取『並獲\n      被告依契約函請行政院衛生署安排其實習程序』，是原告\n      等人乃系爭行政契約之既得利益者於獲得其利益後( 參加\n      應試) 竟反執以主張「讓其得以順利參試」之行政契約無\n      效，顯自我矛盾不合誠信原則。\n  ８、行政先例須屬合法者，乃行政自我拘束之前提要件，憲法\n      之平等原則，並非賦予人民有要求行政機關重複錯誤之請\n      求權：最高行政法院93年判字第1392號判例之意旨：「憲\n      法之平等原則要求行政機關對於事物本質上相同之事件作\n      相同處理，乃形成行政自我拘束，惟憲法之平等原則係指\n      合法之平等，不包含違法之平等。故行政先例需屬合法者\n      ，乃行政自我拘束之前提要件，憲法之平等原則，並非賦\n      予人民有要求行政機關重複錯誤之請求權。」原告主張：\n      「考選部92年2 月函文中更載明，被告機關曾於91年3 月\n      27日醫事人員考試審議委員會第6 次會議作成決議，『有\n      關經國外醫學系畢業前往與取得學位不同之醫師法第4 條\n      之1 所列九大地區或國家實習，其實習資格予以採認』」\n      等語云云，即要求被告重複做成錯誤之決定，此部分應不\n      可採。\n  ９、原告主張違反行政法上之公益原則：貿然全面開放大量實\n      習訓練與國內醫學院有差異之波蘭醫學生資格，有違公共\n      利益與國民健康。本件根據駐波蘭台北經濟文化辦事處之\n      資料，截至97年度止，目前台灣學生就讀波蘭醫學系及牙\n      醫學系之人數已高達665 人，未來還將有更多台灣學生前\n      往就讀，因此若貿然全面性開放波蘭醫學生准予報考醫師\n      考試，而完全不去依法審查其『實習』是否與國內醫學院\n      相當，後續透過此管道取得醫師報考資格之人將因此暴增\n      ，對國人健康將有莫大之危害有違公共利益。\n（三）原告98年6 月30日申覆書之性質應為行政程序法上之「陳\n      情」，被告就原告之申覆即循陳情程序辦理：\n  １、按行政程序法第168 條、171 條規定，原告針對被告選專\n      字第0983301258號通知補件函所提起之申覆，性質核屬行\n      政程序法上之「陳情」，並非提起行政訴訟前應經之訴願\n      先行程序，蓋綜觀原告之申覆書全文，可知原告除指摘被\n      告所為「應補繳1 年實習證明」之認定及處分係違法不當\n      ，違反行政程序法等相關規定外，另表示被告違反憲法第\n      18條規定侵害人民考試權，因而提出申覆救濟，不但所涉\n      及之法令皆為抽象之原則且並未敘明所提起之訴願類型，\n      全文亦未見明確訴願意旨，故被告無法逕依訴願程序辦理\n      。\n  ２、被告對於原告之陳情，爰審慎召開第6 ～8 次醫師牙醫師\n      考試審議委員會，並通知原告指派代表到會陳述意見，於\n      綜整並獲取初步意見後，更主動向主管機關行政院衛生署\n      尋求協助與配合，被告決議透過簽訂行政契約「暫准報考\n      緩發及格證書」方式解決爭議之措施，亦獲得監察院之肯\n      認與贊同，可知被告對於原告之申覆，根據其申覆意旨，\n      依行政程序法第102 條邀請申覆人到場陳述意見後，始作\n      成「暫准報考緩發及格證書」之處分，為行政程序之一環\n      ，非行政救濟程序之內容。最後並與原告簽訂和解契約，\n      兼顧公益與原告之應考權益，如今原告欲切割主張部分和\n      解契約條文之法律關係不存在，實無理由。\n（四）設若原告於98年6 月30日所提申覆書之真意確為訴願，如\n      今仍可於法定一年期限內再行透過訴願救濟，惟本件確認\n      訴訟之提起並不合法：承被告99年1 月25日答辯（二）狀\n      所述，被告98年6 月25日選專字第0983301258號函之意旨\n      ，不僅止於通知受文者（即原告甲○○等17人）限期補正\n      文件，尚包含因渠等並未符合應考資格，告知原告「如逾\n      期未能補正」，即「不准報名」等意思表示在內，核已具\n      備行政程序法第92條第1項 行政處分之要件而對外生法律\n      上效果，即便系爭通知函未記載行政程序法第96條第1 項\n      第6 款之教示條款，惟依行政程序法第98條第3 項規定，\n      原告得自處分書送達後一年內聲明不服。基此，本件原告\n      若不服被告系爭函文「如逾期未能補正即不准報名」之行\n      政處分，自應依訴願法之規定提起撤銷訴願，如今原告提\n      起本件確認訴訟前並未經訴願前置程序，若依其主張所提\n      起者係「確認法律關係存否之訴」，則依行政訴訟法第6\n      條第3 項規定，自不得提起本件訴訟，而應依訴願法之規\n      定明確對於被告98年6 月25日選專字第0983301258號函進\n      行救濟，若有不服，再於完成訴願前置程序後，循行政訴\n      訟管道續行救濟。\n（五）本件原告並無權利保護必要：\n  １、本件原起訴之原告甲○○等16人，其中已及格之甲○○、\n      己○○、辛○○、癸○○、子○○等5 人業已分發至各署\n      立醫院實習，並已完成報到手續；未及格之11人已由被告\n      於98年12月8 日以選專字第0983302483號函准其報考99年\n      1 月23日舉行之99年第一次專技高考醫師考試分試考試第\n      一試，並已於99年1 月7 日寄發入場證，從而原告等並無\n      任何法律之權利或利益受侵害或有受侵害之虞而有立即以\n      行政訴訟確認判決予以除去之必要，其所提本件訴訟顯然\n      欠缺權利保護之必要而應予程序駁回。\n  ２、至於原告所謂「仍須補行實習成績及格始能應試之第二試\n      限制」，及「已及格之5 人可中止實習要求被告發給考試\n      及格證書」等訴之利益，依本件原告起訴前醫師法等相關\n      法規上針對報考資格早已既定之實質要件，即「學歷證明\n      」與「實習期滿成績及格」，無論本件訴訟之勝敗，原告\n      要不可能脫離法律明訂之應考資格要件，可「不用實習」\n      或「中止實習」而違反平等原則以特例方式取得考試及格\n      證書。是本件原告於新制考試制度下得應醫師考試分試第\n      一試，且已分發實習（及格者）或參加99年第一次專技高\n      考醫師考試分試考試第一試（未及格者）並無疑義，至於\n      醫師考試分試第二試所有應考人皆必須「實習期滿成績及\n      格」亦無不同，原告主張本件仍有權利保護必要即無理由\n      。\n（六）綜上所述，原告既基於自由意願合意與被告簽訂行政契約\n      ，且被告亦依約暫准原告參加考試以合理保障其考試權，\n      原告嗣經「參加」並「完成」考試不及格即應遵照契約之\n      規定正式取得資格再重新報考，不得再任意主張行政契約\n      無效，否則將嚴重違反禁反言原則、誠信原則、公益原則\n      等，為此答辯聲明求為判決：１、駁回原告之訴。２、訴\n      訟費用由原告負擔。\n五、本件應適用之法律：\n（一）按醫師法第2 條規定：「（第1 項）具有下列資格之一者\n      ，得應醫師考試：一、公立或立案之私立大學、獨立學院\n      或符合教育部採認規定之國外大學、獨立學院醫學系、科\n      畢業，並經實習期滿成績及格，領有畢業證書者。二、八\n      十四學年度以前入學之私立獨立學院七年制中醫學系畢業\n      ，經修習醫學必要課程及實習期滿成績及格，得有證明文\n      件，且經中醫師考試及格，領有中醫師證書者。三、中醫\n      學系選醫學系雙主修畢業，並經實習期滿成績及格，領有\n      畢業證書，且經中醫師考試及格，領有中醫師證書者。（\n      第2 項）前項第三款中醫學系選醫學系雙主修，除九十一\n      學年度以前入學者外，其人數連同醫學系人數，不得超過\n      教育部核定該校醫學生得招收人數。」次按專門職業技術\n      人員考試法第5 條規定：「各種考試，得單獨或合併舉行\n      ，並得分試、分地舉行。其考試類、科、地點、日期等，\n      由考選部於考試兩個月前公告之。應考人在學期間得視類\n      科之不同，參加前項所定分試考試最後一試以外之考試。\n      分試考試之類科及其考試規則，由考選部報請考試院定之\n      。」是得應專門職業醫師考試之資格者，必須符合經過國\n      內外大學醫學院畢業，並經實習期滿成績及格二要件。\n（二）依據醫師法第42條授權訂立之醫師法施行細則，經主管機\n      關行政院衛生署於98年9 月16衛署醫字第0980215591號令\n      增訂發布第 1之1條至第1之5 條規定如下：\n  １、第1 條之1 ：「（第1 項）本法（按醫師法）第二條至第\n      四條所稱實習期滿成績及格，指在經教學醫院評鑑通過，\n      得提供臨床實作訓練之醫療機構，於醫師指導下完成第一\n      條之二至第一條之四所定之科別及週數或時數之臨床實作\n      ，各科別考評成績均及格，且持有該醫療機構開立之證明\n      。（第2 項）中央主管機關得就前項實習，辦理臨床實作\n      訓練申請人與醫療機構間之選配分發，並得就該業務委託\n      民間專業機構或團體辦理。」\n  ２、第1 條之2 ：「本法第二條所稱實習期滿，其臨床實作之\n      科別及週數或時數如下：一、內科十二週或四百八十小時\n      以上。二、外科十二週或四百八十小時以上。三、婦產科\n      四週或一百六十小時以上。四、小兒科四週或一百六十小\n      時以上。五、其他選修科別至少三科，每科二週或八十小\n      時以上。前項週數或時數，合計應達四十八週或一千九百\n      二十小時以上。」\n  ３、第1 條之3 ：「本法第三條所稱實習期滿，其臨床實作之\n      科別及週數或時數如下：一、中醫內科十八週或七百二十\n      小時以上。二、中醫傷科八週或三百二十小時以上。\n      三、針灸學科九週或三百六十小時以上。四、中醫婦兒科\n      九週或三百六十小時以上。前項週數或時數，合計應達四\n      十五週或一千八百小時以上。」\n  ４、第1 條之4 ：「本法第四條所稱實習期滿，其臨床實作之\n      科別及週數或時數如下：一、兒童牙科二週或八十小時以\n      上。二、口腔顎面外科八週或三百二十小時以上。三、齒\n      顎矯正科二週或八十小時以上。四、膺復科八週或三百二\n      十小時以上。五、牙周病科四週或一百六十小時以上。六\n      、牙髓病科四週或一百六十小時以上。七、牙體復形科二\n      週或八十小時以上。八、其他選修科別至少三科，合計至\n      少十八週或七百二十小時以上。\n  ５、第1 條之5 ：「前三條所定之臨床實作時數，不包括夜間\n      與假日之值班。」\n      又上開規定，屬醫師法枝節性、技術性之規定，並未逾越\n      母法醫師法授權，未違反法律保留原則，主管機關據以訂\n      立以供認定醫師法第2 條規定之「實習期滿」之考試行政\n      ，本院予以尊重。\n（三）考試主管機關考試院依據上開專門職業技術人員考試法第\n      5 條授權，以96年5 月26日考試院考臺組壹一字第096000\n      38331 號令修正發布專門職業及技術人員高等考試醫師牙\n      醫師考試分試考試規則，第2 條規定：「（第1 項）專門\n      職業及技術人員高等考試醫師牙醫師考試分試考試（以下\n      簡稱本考試）分二試舉行。（第2 項）第一試未及格者，\n      不得應第二試。」第6 條規定：「（第1 項）中華民國國\n      民具有附表一醫師、牙醫師類科所列資格之一者，得分別\n      應本考試醫師、牙醫師類科第一試。（第2 項）具有前項\n      附表一醫師類科第一款至第三款規定資格之一者，於中華\n      民國九十九年一月一日前，得應專門職業及技術人員高等\n      考試醫師考試。（第3 項）具有第一項附表一牙醫師類科\n      第一款規定資格者，於中華民國一０一年一月一日前，得\n      應專門職業及技術人員高等考試牙醫師考試。」第7 條規\n      定：「（第1 項）中華民國國民具有附表一醫師應考資格\n      第一款、第二款、第三款資格之一，牙醫師應考資格第一\n      款，並分別經本考試醫師、牙醫師第一試及格者，得應本\n      考試醫師、牙醫師第二試。（第2 項）六年內第二試未及\n      格者，應重新應本考試第一試。」而上開考試規則附表一\n      應考資格第１點亦明確載明：「……但國外大學、獨立學\n      院醫學系、科畢業者，其實習滿成績及格之認定標準，依\n      行政院衛生中華民國九十八年九月十六日修正發布之醫師\n      法施行細則規定辦理。」上開考試規則，亦經法律授權主\n      管機關訂立，並未逾越母法，與其他法律相互配合，其中\n      就醫師法相關之醫師等考試改採第一試及第二試規定，又\n      訂立三年之過渡期間（自96年間起至98年12月31日止）兼\n      顧規範對象即應醫師考生之信賴利益之保護；從而被告據\n      以為考試行政，本院予以尊重。\n（四）再按考選部組織法第19條規定：「考選部為因應各種業務\n      或特殊需要，得設各種委員會，分別辦理各有關業務之審\n      議或研議等事項。」考試院據此訂定專門職業及技術人員\n      考試審議委員會組織規程，依該組織規程第2 條規定：「\n      （被告機關）為辦理專門職業及技術人員醫師牙醫師考試\n      政策、法規、制度之諮詢、應考資格疑義案件、應考人減\n      免應試科目案件之審議，設醫師牙醫師考試審議委員會，\n      審議應考資格初審不合格或疑義案件。」上開醫師牙醫師\n      考試審議委員會之委員，由行政院衛生署副署長、教育部\n      醫事教育委員會執行秘書、醫學大學醫學院院長、醫學系\n      系主任、教學醫院院長、公會團體代表及被告簡任以上職\n      員組成，並邀請行政院衛生署醫事處及教育部高等教育司\n      派員列席，針對醫師及牙醫師考試應考人應考資格之疑義\n      ，均由上開委員會審議。\n（五）另按「確認行政處分無效及確認公法上法律關係成立或不\n      成立之訴訟，非原告有即受確認判決之法律上利益者，不\n      得提起之。其確認已執行完畢或因其他事由而消滅之行政\n      處分為違法之訴訟，亦同。」行政訴訟法第6 條第1 項訂\n      有明文。因此：\n  １、前述「確認法律關係之成立或不成立」，因實務上早已擴\n      及於法律關係之存在或不存在，故於行政訴訟法修正時，\n      認不必嚴加區別，而未特別規定「存在或不存在」之文字\n      （參見學者陳計男著行政訴訟法釋論第188 頁）；且觀本\n      條規定之立法理由，其於公法上法律關係「成立或不成立\n      」文字下又特別註明包括「存在或不存在」，可知，本條\n      關於「確認公法上法律關係成立或不成立訴訟」之規範，\n      應包含「確認公法上法律關係存在或不存在之訴訟」。\n  ２、再按所謂公法上之法律關係，係指公法上之權利義務關係\n      ，即二以上之法律主體，就公法上具體事件，依法律規定\n      所成立之法律上關係而言；同時公法上之具體事件，亦必\n      須有特定生活事實之存在，因法規之規範效果，在兩個以\n      上之權利主體間所產生之公法上權利義務關係，或產生人\n      對權利客體間之公法上利用關係；又公法上法律關係之成\n      立有直接基於法規規定者，亦有因行政處分、行政契約或\n      事實行為而發生者，但法規、事實行為均非法律關係本身\n      ，故皆不得以其存否為確認訴訟之標的。\n  ３、又按所謂即受確認判決之法律上利益，須因法律關係之存\n      否不明確，致原告在公法上之地位有受侵害之危險，而此\n      項危險得以對於被告之確認判決除去之者，始足當之。故\n      原告提起確認公法上法律關係不存在之訴，若欠缺即受確\n      認判決之法律上利益，核屬欠缺權利保護之必要即無確認\n      訴訟訴之利益，在法律上為無理由，應以判決駁回之。\n六、兩造對事實概要之記載及下開其他事實、醫師考試制度之變\n    革等均不爭執，並有原告提出之系爭「考選部暫准報考緩發\n    及格證書行政契約」16件、原告等人畢業學校整理表、「98\n    年第二次專門職業及技術人員高等暨普通考試醫事人員（不\n    含牙醫師、助產師、職能治療師）、中醫師、心理師、營養\n    師考試暨醫師考試分試考試」應考須知、經我國駐外使館驗\n    證之原告等人於波蘭各醫學院畢業證書、歷年成績單、實習\n    證明文件16件、被告98年6 月25日選專字第0983301258號函\n    及原告之申覆書16件、被告98年7 月8 日召開醫師牙醫師考\n    試審議委員會第七次會議新聞稿；及被告提出原告等人及台\n    灣醫學生至被告處陳情紀要及相關報導、被告98年7 月14日\n    選專字第0983301452號函乙份、行政院衛生署98年7 月14日\n    衛署醫字第0980208143號函、監察院糾正案文節錄、監察院\n    通過對衛生署、教育部處理波蘭醫學系畢業生回國報考醫師\n    考試相關問題顯有違失之糾正案新聞稿及相關報導、被告98\n    年9 月30日選專字第09833020281 號函、被告98年6 月25日\n    選專字第0983301258號函、行政院衛生署98年12月1 日衛署\n    醫字第0980087896號函及原告己○○等五人實習分發一覽表\n    、被告98年12月8 日選專字第09833024 83 號函、「98年第\n    二次專門職業及技術人員高等暨普通考試醫事人員（不含牙\n    醫師、助產師、職能治療師）、中醫師、心理師、營養師考\n    試暨醫師考試分試考試」應考須知、原告15人（莊家順及羅\n    友祺兩人除外）所回傳被告98年6 月25日選專字第09833012\n    58號函附件1 之回覆通知15件、行政院衛生署99年3 月12號\n    令、被告提出之原告等人報名表件及學經歷證件、原告與被\n    告所簽訂之系爭行政契約、被告提出之被告醫師牙醫師考試\n    審議委員會第5 次、第6 次、第7 刺、第8 次會議記錄（不\n    可閱覽卷）、98年第二次專門職業及技術人員高等考試醫師\n    考試、醫師考試分試考試應考人員與考選部簽訂行政契約名\n    冊（均為影本）附本院卷及原處分卷可查，足認為真實。\n（一）本件其他事實：\n  １、本件98年醫師考試應考須知第6 頁「應考資格證明文件」\n      醫師部分，除需繳驗「畢業（學位）證書」外，於醫師（\n      應試全部科目6 科）之附註欄載明：「前開醫師（應試全\n      部科目6 科），依專門職業及技術人員高等考試醫師牙醫\n      師考試分試考試規則第6 條第2 項規定，辦理至民國99年\n      1 月1日前為止，凡符合報考資格之應考人，請及早規劃\n      因應。」醫師（一）（應醫師考試分試考試第一試）之附\n      註欄記載：「以外國學歷報考醫師（一）者：依專門職業\n      及技術人員高等考試醫師牙醫師考試分試考試規則第6 條\n      附表一規定，須為教育部採認之國外大學、獨立學院醫學\n      系、科畢業，並經實習期滿成績及格，領有畢業證書者，\n      繳驗證明文件另見8.」。\n  ２、被告因原告等波蘭國等大學醫學院畢業，有「實習期滿成\n      績及格」所生之爭議，由審議委員會作成「暫准報考緩發\n      及格證書」決議前，於98年7 月14日以選專字第09833014\n      52號函徵求行政院衛生署之同意，經行政院衛生署於同日\n      衛署醫字第0980208143號函覆被告同意略以：「……貴部\n      函請本署配合辦理國外醫學畢業生暫准參加專門職業及技\n      術人員高等考試醫師、牙醫師考試及格人員之實習，敬表\n      同意。至實習期滿成績及格之證書，將由各該醫療機構發\n      給，另本署將請各醫療機構列冊函報本署，俾彙整成冊函\n      送貴部，作為核發考試及格證書之參考……。」\n  ３、監察院98年10月中旬針對原告等波蘭國大學醫學院之學歷\n      報考資格等問題，糾正行政院衛生署、教育部略以：波蘭\n      93年加入歐盟以來迄今不過6 年期間，國人於當年即前往\n      該國就讀醫學系者，於96年及97年間已陸續畢業，2 年間\n      即有37名畢業生以該國學歷應考並通過醫師考試，目前尚\n      就學中之人數，亦約670 名，相較於歐盟其他國家之留學\n      人數寥廖可數，留學波蘭人數之多，顯非尋常，非但嚴重\n      影響國內醫學系招生人數之管制總量，且其入學管道與國\n      內醫學系嚴格篩選學生素質相較，亦明顯寬鬆，甚至前往\n      該國取得醫學系學歷者如循國內升學管道，多數尚無法取\n      得進入國內醫學系就讀之資格，致國人對波蘭大學醫學系\n      開設英語學程廣收外籍學生之教育品質多存疑慮等語。\n（二）醫師考試制度之變革：\n  １、醫師法第2 條第1 項第1 款規定（醫師法於91年1 月16日\n      總統（91）華總一義字第09100007520 號令修正公布全文\n      43條；並自公布日起施行）自公布施行迄今均未修正。\n  ２、專門職業及技術人員高等考試醫師牙醫師考試分試考試規\n      則，經主管機關考試院以94年12月22日考臺組壹一字第09\n      400112051 號令訂定發布全文17條；並自96年1 月1 日施\n      行。是有開上開考試規則第2條規定，醫師之專門職業及\n      技術人員高等考試，已明文規定自「民國96年」開始實施\n      分試，即改採二階段考試制度，且慮及制度變革，為保障\n      應考人信賴利益，始訂定3 年之過渡期間，自99年1 月1\n      日起始全面施行。\n  ３、為配合國內醫學教育改革，被告92年度考選制度研討會，\n      邀請學者專家就國家考試醫師考試分試之可行性進行研討\n      ，報告人何橈通院長建議參考國外制度，改為二階段分試\n      ，第一試於國內大學醫學系修畢基礎課程時考，第二階段\n      於第一試及格，經實習期滿取得畢業證書後考，建議之初\n      各界意見紛陳，後經被告邀請各界研商，始漸達成共識，\n      於93年8 月30日正式召開「高等考試醫師考試改進相關事\n      宜會議」決定醫師考試採行分試制度，考試院乃於94年12\n      月22日配合訂定發布上開「專門職業及技術人員高等考試\n      醫師考試分試考試規則」，明訂自「民國96年」開始實施\n      分試，但具有該規則附表一醫師類科第1 款至第3 款規定\n      資格之一者（舊制醫學院需實習一年始能畢業之畢業生）\n      ，於民國99年1 月1 日前，得應專門職業及技術人員高等\n      考試醫師考試（應試全部科目6 科），俾給予該等應考人\n      3 年之緩衝期，以維護其應考信賴保護利益權利，而99年\n      1 月1 日起即全面採行醫師考試分試考試制度（參見前開\n      規則第6 條、第7 條規定，第1 試及格後始可應考第2 試\n      ）。\n七、本件兩造主張之事實，相關法律詳如上述，是本件主要爭點\n    乃原告所提出之波蘭國醫學院畢業證書等文件，是否符合「\n    經實習期滿成績及格」之要件？又原告提起之確認之訴，是\n    否有即受確認判決法律上之利益？以下就原告之訴有無理由\n    ，依序論述爭點如下。\n（一）本件原告主張系爭行政契約之第2 條、第3 條、第4 條等\n      違反行政程序法等相關法律規定，致發生無效而自始不成\n      立，故提起本件確認公法上法律關係不存在之訴；參照上\n      開有關行政訴訟法第6 條確認公法上法律關係「成立或不\n      成立」之規範，應包含「確認公法上法律關係存在或不存\n      在之訴訟」之說明，本件原告聲明形式上觀察，與行政訴\n      訟法第6 條第1 項前段確認公法上法律關係成立不成立之\n      訴訟類型相符，應先敘明。次查原告主張其起訴之訴訟標\n      的法律關係的原因事實，並無行政處分之存在，即兩造間\n      行政法上之法律關係非因行政處分（而係有償之雙務行政\n      契約）而發生，依據本院前揭說明，在確認之訴部分，尊\n      重當事人之處分權，從而，從形式上原告提起本件確認之\n      訴並未違背行政訴訟法第6 條第3 項規定之「確認訴訟之\n      備位性原則」，亦應先予敘明。\n（二）兩造對本件訟爭之行之行政行為（即原告主張為雙務之行\n      政契約，被告主張之行政程序法第136 條替代行政處分之\n      和解行政契約；即前述之系爭行政契約）之內容及簽立過\n      程等事實均不爭執詳如上事實概要欄所載；從而縱認系爭\n      行政契約為原告主張之「行政契約」，然本件系爭行政契\n      約不論是第1 條及第2 、3 、4 條及其他條文整體始形成\n      一個公法上之法律關係，上開法律關係特別是第1 條使用\n      「爰暫准乙方（按原告）報告98年醫師考試」，與第2 條\n      「乙方同意倘考試成績及格，願意接受甲方（按被告）暫\n      不發給醫師考試及格證書之決定……」及第3 條「乙方倘\n      於考試榜示及格三年內，未依上述方式，於國內實習期滿\n      成績及格……」及其他條文規定，整體構成一個完整之公\n      法上法律關係，彼此互相依存，不能各自分開創設獨立之\n      公法上法律關係，換言之，本件系爭行政契約全部實屬一\n      完整不可分之公法上法律關係，原告切割完整之法律關係\n      ，僅認系爭行政契約第2 、3 、4 條規定可分且違反行政\n      程序法等法律，認屬無效，而僅留存第1 條暫准報考之被\n      告之行政處分權，認並不存在「行政契約」，提起本件確\n      認公法上法律關係不存在之訴，其主張及事實理由顯有矛\n      盾（本件系爭行政契約並不可分），本難認有理由。\n（三）原告所提出之波蘭國醫學院畢業證書等文件，並不符合前\n      開醫師法第2條之「經實習期滿成績及格」要件。\n  １、按前開98年9 月16日醫師法施行細則部分條文修正總說明\n      略以：「……對持國外學歷回國參加考試者，其於國外使\n      用之語言及接觸之疾病型態，顯與國內各類醫學生有所不\n      同，需要在其參加考試前，於國內醫療機構接受與國內醫\n      學生相當之臨床實作科別及週數或時數之訓練，以確認其\n      與我國的醫學院醫學系畢業生具有相似之臨床經驗。」另\n      依醫師法施行細則修正條文第1 條之2 之規定，就實習期\n      滿，其臨床實作之科別及週數或時數，並無區分國內外，\n      表示國內外之「實習期滿」標準必須一致，應先敘明。又\n      醫師法施行細則乃醫師法授權主管機關行政院衛生署訂立\n      之法規命令。而上開解釋醫師法第2 條「經實習期滿成績\n      及格」要件，並未逾越母法，本院應予尊重等情，詳如上\n      述，從而不論醫師法施行細則是否增修上開規定，均應為\n      相同解釋，應先敘明。\n  ２、次查本件原告報告98年度醫師考試後，被告認原告等人持\n      波蘭國學歷證件，有關是否「經實習期滿成績及格」要件\n      有疑義，乃送請醫師牙醫師考試審議委員會98年6 月19日\n      第5 次會議審議，經認為原告所提證件不符，乃決議通知\n      原告補繳畢業後1 年實習證明後再議，被告乃於同年月25\n      日選專字第0983301258號書函通知補件。原告陸續向被告\n      提出申覆，被告為求慎重，即於同年7 月3 、8 日及15日\n      又分別召開醫師牙醫師考試審議委員會第6 、7 、8 次會\n      議。其中第6 次會議決議，以原告等均未提出合乎規定之\n      實習證明不准報考，第7 次會議同意應考人（含原告）推\n      派代表到場說明，惟決議仍以原告在學期間之見習與實習\n      未作明確區別，依國內學制其大多屬見習性質並非「實習\n      」，與國內學制1 年完整實習有別，核與醫師法第2 條「\n      ……實習期滿成績及格……」之規定不符，不准報考。第\n      8 次會議經被告協議相關單位提出建議經審議後決議：「\n      一、同意被告與波蘭波茲南等4 所醫學大學及愛爾蘭都柏\n      林大學醫學院畢業生簽訂行政契約以「暫准報考緩發及格\n      證書」方式，並對行政契約修正通過」（即原處分卷不可\n      供閱覽部分卷），被告依上開第8 次會議議決，始有本件\n      原告主張之系爭行政契約。又參照上開法律說明可知，被\n      告醫師牙醫師考試審議委員會之組織合法、前述審議程序\n      正當合法，亦應先予敘明。\n  ３、又醫師法第2 條規定之「經實習期滿成績及格」構成要件\n      ，其所謂實習期滿，則屬不確定概念，而法規中不確定法\n      律概念，不論是要件或法律效果，或於多重解釋發生時，\n      由行政機詮釋或適用之結果，作成單一解釋與適用。行政\n      法院就此種行政機關所為不確定法律概念之判斷及選擇，\n      固得監督，惟體現憲法、立法、行政、司法權之作用，僅\n      為合法性監督，即對行政機關之裁量、判斷如認有逾越權\n      限或濫用、恣意情事，自應予以糾正；申言之，行政法院\n      監督及審查密度如何，自應事件不同而異，並應視組織及\n      程序是否完備，判斷之政策性及專業性高低等，而認行政\n      機關有一定之判斷餘地。是以，上開醫師法第2 條規定之\n      醫師應考資格之規定，涉及醫師專業技術性之實際需要，\n      與國民健康及生命之公益息息相關，並具有高度之屬人性\n      ，因此，辦理醫師考試機關，對上開「實習期滿」不確定\n      法律概念之解釋及適用，只要是非基於錯誤之事實，或基\n      於事件無關之考量、或組織不合法、未遵守法定程序，或\n      顯然違反平等原則、比例原則及一般公認之價值判斷標準\n      者外，行政法院應採取較低密度審查標準，並應尊重其判\n      斷餘地。查本件原告所提出之波蘭國醫學院之「實習」是\n      否符合醫師法第2 條第1 項第1 款、教育部大學辦理國外\n      學歷採認辦法第8 條規定之「實習」或「相當於實習」，\n      經被告所屬醫師牙醫師考試審議委員會之專業委員第5 、\n      6 次會議決議，認原告應考時提出之波蘭國醫師院之學歷\n      資料，與上開「實習期滿」要件不符，而不准報考，並通\n      知原告補提出實習一年之證據，亦有被告提出不可閱卷第\n      3-9 頁、第30-36 頁可證。而本件被告作成此部分決定所\n      依據之醫師牙醫師考試審議委員會審議過程合法正當又如\n      上述，同時被告不准原告報考98年醫師考試之決定（原告\n      提出之波蘭國醫師院之學歷資料，與上開「實習期滿」要\n      件不符）並非基於錯誤之事實或其他無關之考量，亦未違\n      反一般公認行政法價值判斷標準；參照上開說明，本院自\n      宜予尊重。\n  ４、綜上，本件原告之提出報考之學歷證件，不符實習期滿之\n      要件，從而被告抗辯系爭行政契約之第2 、3 、4 條規定\n      並無違法，即足認定。因此原告主張違法並提起本件確認\n      之訴並無理由。\n  ５、又如前述應適用之法律說明，原告提起本件訴訟（98年10\n      月9 日）前，醫師法施行細則業於98年9 月16日增訂第1\n      之1 條至第1 之5 條規定；而參考前述專門職業及技術人\n      員高等考試醫師牙醫師考試分試考試規則（考試院以94年\n      12月22日考臺組壹一字第09400112051 號令訂定發布）規\n      定及說明三，自98年9 月16日醫師法施行細則部分增訂條\n      文起，醫師考試應全面採行醫師考試分試考試制度（即專\n      門職業及技術人員高等考試醫師牙醫師考試分試考試規則\n      6 條、第7 條規定，第1 試及格後始可應考第2 試）；本\n      件原告訟爭「實習期滿」應考資格之爭議，因此而不續存\n      在，從而原告就系爭行政契約第4 條規定，退步言，姑不\n      論其是否具備法律關係性質，請求確認法律關係不存在，\n      即無確認之利益，應併敘明。\n  ６、再查原告雖陳稱98年以前持本件波蘭國原告畢業學校相同\n      證件報考醫師考試均獲准考，本件則不同意報考，是系爭\n      行政契約第2 、3 、4 條規定顯有違平等原則云云。惟：\n      (1)按憲法之平等原則要求行政機關對於事物本質上相同之\n        事件作相同處理，乃形成行政自我拘束，惟憲法之平等\n        原則係指合法之平等，不包含違法之平等。故行政先例\n        需屬合法者，乃行政自我拘束之前提要件，憲法之平等\n        原則，並非賦予人民有要求行政機關重複錯誤之請求權\n        。\n      (2)本件原告主張之波蘭國學歷證件等，與醫師法第2 條「\n        經實習期滿成績及格」要件不符如上述，是原告持98年\n        以前之被告准報考之不合法案例，主張被告應受行政自\n        我拘束云云，參照首開說明，本無理由。\n      (3)再查依被告統計，持波蘭醫學院學經歷之學生報考醫師\n        考試，已由95年1 人報考、96年17人報考急速擴增至98\n        年118 人報考) ，目前循相同管道在波蘭修習醫學之台\n        灣留學生已高達六百多人，且波蘭醫學院係針對外國學\n        生開設專班（絕大多數係台灣學生，其中亦有其他國家\n        學生）以英語開設的課程，而留學生本身在波蘭醫院實\n        習部分亦需透過翻譯與病人互動等語明確。而被告醫師\n        牙醫師考試審議委員會第7 次會議，亦邀請原告等派代\n        表到會陳述意見如前述，經審議委員等專家詳細詢問原\n        告等在波蘭修習醫學系課程與實習實際之狀況後，認為\n        從英語國際班實習互動與醫院值夜班情況，認為與國內\n        實習未完全相當等事實，亦有原處分卷不可供閱覽部分\n        第49～64頁可證，是本件被告經審慎調查後，為系爭行\n        政契約之第2 、3 、4 條規定，亦屬有據；綜上此部分\n        原告違反平等原則之主張云云，並不足採。況且，契約\n        之關係乃立於當事人自治原則，契約內容未違反法律之\n        強行規定（無效）或公序良俗外，均不應「禁反言」，\n        而本件原告對於被告拒絕報考，不以通常之行政救濟程\n        序，謀求救濟，卻以其他方式，以簽定「系爭行政契約\n        」取得報考資格後，反言被告違反平等原則，有失誠信\n        ，委無可取。\n（四）原告乙○○等11人（即除甲○○、己○○、辛○○、癸○\n      ○、子○○5 人以外），雖簽立系爭行政契約然參加本件\n      98年醫師考試但未獲及格評定之事實詳如上述。而醫師法\n      施行細則於原告起訴前亦增修第1 之1 條至第1 之5 條規\n      定亦如前述，是本件醫師法第2 條「經實習期滿成績及格\n      」之爭執，已有法令明確規定，且原告乙○○亦依照新修\n      正之規定檢附證件報考99年1 月23日舉行之99年第一次專\n      技高考醫師考試分試考試第一試，並經被告以98年12月8\n      日選專字第0983302483號函准予報考；是參照上開行政訴\n      訟法第6 條規定之法律說明，原告乙○○等11人有關報考\n      醫師考試之公法上法律關係未有不明確，而致原告在公法\n      上應醫師考試之之地位有受侵害之危險，更無從藉由原告\n      提起之本件確認之訴除去之，從而此部分原告之訴欠缺權\n      利保護之必要即無確認訴訟訴之利益，在法律上為無理由\n      ，應以判決駁回之。\n（五）原告甲○○、己○○、辛○○、癸○○、子○○5 人參加\n      98年醫師考試及格，並已分發至各署立醫院實習詳如上述\n      ，而本件系爭行政契約第2 、3 、4 條規定並無原告所指\n      之違法而不存在詳如上述，是此部分原告訴請確認法律關\n      係不存在云云，亦無理由，應予駁回。\n（六）本件應適用之法律及事實理由及本院見解詳如上述，兩造\n      其餘攻擊防禦方法，核與判斷結果無涉，爰不一一敘明。\n八、據上論結，本件原告之訴為無理由，依行政訴訟法第98條第\n    1項前段、第104 條，民事訴訟法第85條第1 項前段判決如\n    主文。"
  },
  "characters": {
    "judges": [
      "王立杰",
      "楊得君",
      "洪遠亮"
    ],
    "prosecutors": [

    ],
    "lawyers": [

    ],
    "clerks": [
      "陳德銘"
    ],
    "plaintiffs": [
      "甲"
    ],
    "defendants": [
      "考選部",
      "代  表  人  午○○（部長）住同."
    ],
    "prosecutor_office": [

    ],
    "creditors": [

    ],
    "debtors": [

    ],
    "judicial_associate_officer": [

    ]
  },
  "adjudged_at": "2010-05-12",
  "created_at": "2016-01-05 11:57:23",
  "updated_at": "2016-01-05 11:57:23"
}