{
  "identify": "TPD-99-易-935-20100512-1",
  "court": {
    "name": "臺灣臺北地方法院",
    "code": "TPD"
  },
  "division": {
    "name": "刑事",
    "code": "M"
  },
  "year": 99,
  "word": "易",
  "number": "935",
  "jcheck": "1",
  "reason": "毒品危害防制條例",
  "content": "臺灣臺北地方法院刑事判決               99年度易字第935號\n公  訴  人  臺灣臺北地方法院檢察署檢察官\n被      告  甲○○\n上列被告因違反毒品危害防制條例案件，經檢察官提起公訴（九\n十九年度毒偵字第九九七號），嗣於本院準備程序進行中，被告\n就被訴事實為有罪之陳述，經本院裁定進行簡式審判程序，判決\n如下：\n    主    文\n甲○○施用第二級毒品，累犯，處有期徒刑陸月，如易科罰金，\n以新臺幣壹仟元折算壹日。\n    犯罪事實\n一、甲○○前（一）於民國九十五年間因施用毒品案件，經本院\n    依臺灣臺北地方法院檢察署檢察官之聲請，於九十五年九月\n    二十九日以九十五年度毒聲字第七○四號裁定送勒戒處所觀\n    察、勒戒，於九十六年三月二日入臺灣臺北看守所附設觀察\n    勒戒處所觀察、勒戒後，因認無繼續施用毒品之傾向，於九\n    十六年四月十八日釋放出所，並經臺灣臺北地方法院檢察署\n    檢察官於九十六年四月二十日以九十六年度毒偵緝字第五八\n    號為不起訴處分確定。（二）於九十七年間因犯加重竊盜罪\n    ，經本院於九十七年一月三十一日以九十七年度簡字第四○\n    ○號判決判處有期徒刑六月，於九十七年四月七日確定；復\n    於九十七年間因犯加重竊盜等罪，經本院於九十七年二月二\n    十五日以九十七年度易字第五○一號判決分別判處有期徒刑\n    七月、七月，應執行有期徒刑十月，於九十七年三月十七日\n    確定；又於九十七年間因施用第二級毒品等案件，經本院於\n    九十七年四月九日以九十七年度簡字第一○九九號判決分別\n    判處有期徒刑二月、二月，應執行有期徒刑三月，於九十七\n    年四月二十八日確定；上開五罪，經本院於九十七年五月二\n    十日以九十七年度聲字第一一七四號裁定應執行有期徒刑一\n    年六月確定，於九十七年三月二十八日入監執行，於九十八\n    年六月四日因縮短刑期假釋出監，假釋中付保護管束，於九\n    十八年六月二十八日保護管束期滿，假釋未經撤銷，以已執\n    行論。（三）於九十八年間因施用第二級毒品案件，經本院\n    於九十八年九月三十日以九十八年度簡字第三七四二號判決\n    判處有期徒刑五月，於九十八年十月二十六日確定；復於九\n    十八年間因犯竊盜罪，經本院於九十八年十二月七日以九十\n    八年度易字第二九一六號判決判處有期徒刑六月，於九十九\n    年一月四日確定；又於九十八年間因施用第二級毒品案件，\n    經本院於九十八年十二月二十一日以九十八年度易字第三二\n    六七號判決判處有期徒刑五月，於九十九年三月五日確定；\n    並於九十八年間因犯竊盜罪，經本院於九十八年十二月二十\n    一日以九十八年度易字第二九二九號判決分別判處有期徒刑\n    八月、四月，應執行有期徒刑十月，於九十九年三月五日確\n    定；再於九十八年間因犯竊盜罪，經本院於九十八年十二月\n    十一日以九十八年度易字第三二○八號判決分別判處有期徒\n    刑三月、四月，應執行有期徒刑六月，於九十九年一月十一\n    日確定；且於九十八年間因犯施用第二級毒品案件，經本院\n    於九十八年十二月十六日以九十八年度簡字第四八○六號判\n    決判處有期徒刑五月，於九十九年一月十一日確定；上開八\n    罪，經本院於九十九年四月三十日以九十九年度聲字第七五\n    七號裁定應執行有期徒刑二年十月（此部分不構成累犯）。\n    詎猶不知悔改，明知安非他命、甲基安非他命均為毒品危害\n    防制條例第二條第二項第二款所定之第二級毒品，不得施用\n    ，竟基於施用第二級毒品甲基安非他命之犯意，於九十八年\n    十二月八日深夜零時許，在其斯時位在臺北市○○區○○路\n    二段三二○巷五五弄三六號五樓住處內，以不詳方式，施用\n    第二級毒品甲基安非他命一次。嗣於九十八年十二月十日深\n    夜二時十分許，在臺北縣土城市○○路二六號前，甲○○因\n    持螺絲起子一支竊取沈子竣所有停放在該處車牌號碼六七九\n    七─ＶＫ號自用小客車內現金新臺幣一百五十七元，為警當\n    場查獲（甲○○涉犯加重竊盜罪嫌部分，業經臺灣板橋地方\n    法院於九十九年四月二十三日以九十九年度易字第四九七號\n    判決判處有期徒刑八月），並經甲○○同意採集其尿液經送\n    請臺灣檢驗科技股份有限公司檢驗結果，呈安非他命及甲基\n    安非他命陽性反應，始知上情。\n二、案經臺北縣政府警察局土城分局報請臺灣板橋地方法院檢察\n    署檢察官呈請臺灣高等法院檢察署檢察長令轉臺灣臺北地方\n    法院檢察署檢察官偵查起訴。\n    理    由\n一、上開犯罪事實，業據被告甲○○於偵查及本院審理時供承不\n    諱，而被告於九十八年十二月十日為警採集之尿液經送臺灣\n    檢驗科技股份有限公司以ＥＩＡ酵素免疫分析法初步檢驗，\n    再以ＧＣ／ＭＳ氣相層析／質譜儀法確認檢驗結果，呈安非\n    他命及甲基安非他命陽性反應，此有臺灣檢驗科技股份有限\n    公司九十八年十二月二十一日濫用藥物檢驗報告一份在卷可\n    稽，是被告任意性自白核與事實相符，應堪採信。再被告於\n    於九十五年間因施用毒品案件，經本院依臺灣臺北地方法院\n    檢察署檢察官之聲請，於九十五年九月二十九日以九十五年\n    度毒聲字第七○四號裁定送勒戒處所觀察、勒戒，於九十六\n    年三月二日入臺灣臺北看守所附設觀察勒戒處所觀察、勒戒\n    後，因認無繼續施用毒品之傾向，於九十六年四月十八日釋\n    放出所，並經臺灣臺北地方法院檢察署檢察官於九十六年四\n    月二十日以九十六年度毒偵緝字第五八號為不起訴處分確定\n    ；復於九十七年間因施用第二級毒品等案件，經本院於九十\n    七年四月九日以九十七年度簡字第一○九九號判決分別判處\n    有期徒刑二月、二月，應執行有期徒刑三月，於九十七年四\n    月二十八日確定；又於九十八年間因施用第二級毒品案件，\n    經本院於九十八年九月三十日以九十八年度簡字第三七四二\n    號判決判處有期徒刑五月，於九十八年十月二十六日確定；\n    並於九十八年間因施用第二級毒品案件，經本院於九十八年\n    十二月二十一日以九十八年度易字第三二六七號判決判處有\n    期徒刑五月，於九十九年三月五日確定；再於九十八年間因\n    犯施用第二級毒品案件，經本院於九十八年十二月十六日以\n    九十八年度簡字第四八○六號判決判處有期徒刑五月，於九\n    十九年一月十一日確定等情，有臺灣高等法院被告前案紀錄\n    表、刑案資料查註紀錄表及本院九十八年度易字第三二六七\n    號刑事判決各一份在卷可按，足認被告係於觀察、勒戒執行\n    完畢釋放後，五年內再施用第二級毒品安非他命。綜上所述\n    ，本件事證明確，被告犯行堪以認定，應依法論科。\n二、按安非他命、甲基安非他命均係屬毒品危害防制條例第二條\n    第二項第二款所規定之第二級毒品，均不得施用。核被告所\n    為，係違反毒品危害防制條例第十條第二項之施用第二級毒\n    品罪。查被告前於九十七年間因犯加重竊盜罪，經本院於九\n    十七年一月三十一日以九十七年度簡字第四○○號判決判處\n    有期徒刑六月，於九十七年四月七日確定；又於九十七年間\n    因犯加重竊盜等罪，經本院於九十七年二月二十五日以九十\n    七年度易字第五○一號判決分別判處有期徒刑七月、七月，\n    應執行有期徒刑十月，於九十七年三月十七日確定；並於九\n    十七年間因施用第二級毒品等案件，經本院於九十七年四月\n    九日以九十七年度簡字第一○九九號判決分別判處有期徒刑\n    二月、二月，應執行有期徒刑三月，於九十七年四月二十八\n    日確定；上開五罪，經本院於九十七年五月二十日以九十七\n    年度聲字第一一七四號裁定應執行有期徒刑一年六月確定，\n    於九十七年三月二十八日入監執行，於九十八年六月四日因\n    縮短刑期假釋出監，假釋中付保護管束，於九十八年六月二\n    十八日保護管束期滿，假釋未經撤銷，以已執行論，此有臺\n    灣高等法院被告前案紀錄表一份在卷可參，被告受有期徒刑\n    之執行完畢，五年以內故意再犯本件最重本刑有期徒刑以上\n    之罪，為累犯，應依刑法第四十七條第一項規定，加重本刑\n    至二分之一。爰審酌被告前有犯加重竊盜、施用第二級毒品\n    等前科，素行不佳，竟不思悛悔，前於勒戒處所施以觀察、\n    勒戒後，未把握自新機會，又再次施用足以導致人體機能發\n    生依賴性、成癮性及抗藥性等障礙之第二級毒品甲基安非他\n    命，對個人身心戕害甚鉅，惟犯後坦承犯行，態度良好，兼\n    衡其犯罪之動機、目的、手段、方法、品行及智識程度等一\n    切情狀，爰量處如主文所示之刑，並諭知易科罰金之折算標\n    準。\n據上論斷，應依刑事訴訟法第二百七十三條之一第一項、第二百\n八十四條之一、第二百九十九條第一項前段，毒品危害防制條例\n第十條第二項，刑法第十一條前段、第四十七條第一項、第四十\n一條第一項前段，判決如主文。\n本件經檢察官申心蓓到庭執行職務\n中    華    民    國    99    年    5     月    12    日\n                  臺灣臺北地方法院刑事第六庭\n                      法      官  雷淑雯\n以上正本證明與原本無異。\n如不服本判決，應於判決送達後十日內，向本院提出上訴狀。\n                      書  記  官  胡詩唯\n中    華    民    國    99    年    5     月    12    日\n附錄本案論罪科刑法條全文\n毒品危害防制條例第十條：\n施用第一級毒品者，處六月以上五年以下有期徒刑。\n施用第二級毒品者，處三年以下有期徒刑。",
  "structure": {
    "main": "甲○○施用第二級毒品，累犯，處有期徒刑陸月，如易科罰金，\n以新臺幣壹仟元折算壹日。",
    "fact": "一、甲○○前（一）於民國九十五年間因施用毒品案件，經本院\n    依臺灣臺北地方法院檢察署檢察官之聲請，於九十五年九月\n    二十九日以九十五年度毒聲字第七○四號裁定送勒戒處所觀\n    察、勒戒，於九十六年三月二日入臺灣臺北看守所附設觀察\n    勒戒處所觀察、勒戒後，因認無繼續施用毒品之傾向，於九\n    十六年四月十八日釋放出所，並經臺灣臺北地方法院檢察署\n    檢察官於九十六年四月二十日以九十六年度毒偵緝字第五八\n    號為不起訴處分確定。（二）於九十七年間因犯加重竊盜罪\n    ，經本院於九十七年一月三十一日以九十七年度簡字第四○\n    ○號判決判處有期徒刑六月，於九十七年四月七日確定；復\n    於九十七年間因犯加重竊盜等罪，經本院於九十七年二月二\n    十五日以九十七年度易字第五○一號判決分別判處有期徒刑\n    七月、七月，應執行有期徒刑十月，於九十七年三月十七日\n    確定；又於九十七年間因施用第二級毒品等案件，經本院於\n    九十七年四月九日以九十七年度簡字第一○九九號判決分別\n    判處有期徒刑二月、二月，應執行有期徒刑三月，於九十七\n    年四月二十八日確定；上開五罪，經本院於九十七年五月二\n    十日以九十七年度聲字第一一七四號裁定應執行有期徒刑一\n    年六月確定，於九十七年三月二十八日入監執行，於九十八\n    年六月四日因縮短刑期假釋出監，假釋中付保護管束，於九\n    十八年六月二十八日保護管束期滿，假釋未經撤銷，以已執\n    行論。（三）於九十八年間因施用第二級毒品案件，經本院\n    於九十八年九月三十日以九十八年度簡字第三七四二號判決\n    判處有期徒刑五月，於九十八年十月二十六日確定；復於九\n    十八年間因犯竊盜罪，經本院於九十八年十二月七日以九十\n    八年度易字第二九一六號判決判處有期徒刑六月，於九十九\n    年一月四日確定；又於九十八年間因施用第二級毒品案件，\n    經本院於九十八年十二月二十一日以九十八年度易字第三二\n    六七號判決判處有期徒刑五月，於九十九年三月五日確定；\n    並於九十八年間因犯竊盜罪，經本院於九十八年十二月二十\n    一日以九十八年度易字第二九二九號判決分別判處有期徒刑\n    八月、四月，應執行有期徒刑十月，於九十九年三月五日確\n    定；再於九十八年間因犯竊盜罪，經本院於九十八年十二月\n    十一日以九十八年度易字第三二○八號判決分別判處有期徒\n    刑三月、四月，應執行有期徒刑六月，於九十九年一月十一\n    日確定；且於九十八年間因犯施用第二級毒品案件，經本院\n    於九十八年十二月十六日以九十八年度簡字第四八○六號判\n    決判處有期徒刑五月，於九十九年一月十一日確定；上開八\n    罪，經本院於九十九年四月三十日以九十九年度聲字第七五\n    七號裁定應執行有期徒刑二年十月（此部分不構成累犯）。\n    詎猶不知悔改，明知安非他命、甲基安非他命均為毒品危害\n    防制條例第二條第二項第二款所定之第二級毒品，不得施用\n    ，竟基於施用第二級毒品甲基安非他命之犯意，於九十八年\n    十二月八日深夜零時許，在其斯時位在臺北市○○區○○路\n    二段三二○巷五五弄三六號五樓住處內，以不詳方式，施用\n    第二級毒品甲基安非他命一次。嗣於九十八年十二月十日深\n    夜二時十分許，在臺北縣土城市○○路二六號前，甲○○因\n    持螺絲起子一支竊取沈子竣所有停放在該處車牌號碼六七九\n    七─ＶＫ號自用小客車內現金新臺幣一百五十七元，為警當\n    場查獲（甲○○涉犯加重竊盜罪嫌部分，業經臺灣板橋地方\n    法院於九十九年四月二十三日以九十九年度易字第四九七號\n    判決判處有期徒刑八月），並經甲○○同意採集其尿液經送\n    請臺灣檢驗科技股份有限公司檢驗結果，呈安非他命及甲基\n    安非他命陽性反應，始知上情。\n二、案經臺北縣政府警察局土城分局報請臺灣板橋地方法院檢察\n    署檢察官呈請臺灣高等法院檢察署檢察長令轉臺灣臺北地方\n    法院檢察署檢察官偵查起訴。\n    理    由\n一、上開犯罪事實，業據被告甲○○於偵查及本院審理時供承不\n    諱，而被告於九十八年十二月十日為警採集之尿液經送臺灣\n    檢驗科技股份有限公司以ＥＩＡ酵素免疫分析法初步檢驗，\n    再以ＧＣ／ＭＳ氣相層析／質譜儀法確認檢驗結果，呈安非\n    他命及甲基安非他命陽性反應，此有臺灣檢驗科技股份有限\n    公司九十八年十二月二十一日濫用藥物檢驗報告一份在卷可\n    稽，是被告任意性自白核與事實相符，應堪採信。再被告於\n    於九十五年間因施用毒品案件，經本院依臺灣臺北地方法院\n    檢察署檢察官之聲請，於九十五年九月二十九日以九十五年\n    度毒聲字第七○四號裁定送勒戒處所觀察、勒戒，於九十六\n    年三月二日入臺灣臺北看守所附設觀察勒戒處所觀察、勒戒\n    後，因認無繼續施用毒品之傾向，於九十六年四月十八日釋\n    放出所，並經臺灣臺北地方法院檢察署檢察官於九十六年四\n    月二十日以九十六年度毒偵緝字第五八號為不起訴處分確定\n    ；復於九十七年間因施用第二級毒品等案件，經本院於九十\n    七年四月九日以九十七年度簡字第一○九九號判決分別判處\n    有期徒刑二月、二月，應執行有期徒刑三月，於九十七年四\n    月二十八日確定；又於九十八年間因施用第二級毒品案件，\n    經本院於九十八年九月三十日以九十八年度簡字第三七四二\n    號判決判處有期徒刑五月，於九十八年十月二十六日確定；\n    並於九十八年間因施用第二級毒品案件，經本院於九十八年\n    十二月二十一日以九十八年度易字第三二六七號判決判處有\n    期徒刑五月，於九十九年三月五日確定；再於九十八年間因\n    犯施用第二級毒品案件，經本院於九十八年十二月十六日以\n    九十八年度簡字第四八○六號判決判處有期徒刑五月，於九\n    十九年一月十一日確定等情，有臺灣高等法院被告前案紀錄\n    表、刑案資料查註紀錄表及本院九十八年度易字第三二六七\n    號刑事判決各一份在卷可按，足認被告係於觀察、勒戒執行\n    完畢釋放後，五年內再施用第二級毒品安非他命。綜上所述\n    ，本件事證明確，被告犯行堪以認定，應依法論科。\n二、按安非他命、甲基安非他命均係屬毒品危害防制條例第二條\n    第二項第二款所規定之第二級毒品，均不得施用。核被告所\n    為，係違反毒品危害防制條例第十條第二項之施用第二級毒\n    品罪。查被告前於九十七年間因犯加重竊盜罪，經本院於九\n    十七年一月三十一日以九十七年度簡字第四○○號判決判處\n    有期徒刑六月，於九十七年四月七日確定；又於九十七年間\n    因犯加重竊盜等罪，經本院於九十七年二月二十五日以九十\n    七年度易字第五○一號判決分別判處有期徒刑七月、七月，\n    應執行有期徒刑十月，於九十七年三月十七日確定；並於九\n    十七年間因施用第二級毒品等案件，經本院於九十七年四月\n    九日以九十七年度簡字第一○九九號判決分別判處有期徒刑\n    二月、二月，應執行有期徒刑三月，於九十七年四月二十八\n    日確定；上開五罪，經本院於九十七年五月二十日以九十七\n    年度聲字第一一七四號裁定應執行有期徒刑一年六月確定，\n    於九十七年三月二十八日入監執行，於九十八年六月四日因\n    縮短刑期假釋出監，假釋中付保護管束，於九十八年六月二\n    十八日保護管束期滿，假釋未經撤銷，以已執行論，此有臺\n    灣高等法院被告前案紀錄表一份在卷可參，被告受有期徒刑\n    之執行完畢，五年以內故意再犯本件最重本刑有期徒刑以上\n    之罪，為累犯，應依刑法第四十七條第一項規定，加重本刑\n    至二分之一。爰審酌被告前有犯加重竊盜、施用第二級毒品\n    等前科，素行不佳，竟不思悛悔，前於勒戒處所施以觀察、\n    勒戒後，未把握自新機會，又再次施用足以導致人體機能發\n    生依賴性、成癮性及抗藥性等障礙之第二級毒品甲基安非他\n    命，對個人身心戕害甚鉅，惟犯後坦承犯行，態度良好，兼\n    衡其犯罪之動機、目的、手段、方法、品行及智識程度等一\n    切情狀，爰量處如主文所示之刑，並諭知易科罰金之折算標\n    準。\n據上論斷，應依刑事訴訟法第二百七十三條之一第一項、第二百\n八十四條之一、第二百九十九條第一項前段，毒品危害防制條例\n第十條第二項，刑法第十一條前段、第四十七條第一項、第四十\n一條第一項前段，判決如主文。\n本件經檢察官申心蓓到庭執行職務"
  },
  "characters": {
    "judges": [
      "雷淑雯"
    ],
    "prosecutors": [
      "申心蓓"
    ],
    "lawyers": [

    ],
    "clerks": [

    ],
    "plaintiffs": [

    ],
    "defendants": [
      "甲○○"
    ],
    "prosecutor_office": [
      "臺灣臺北地方法院檢察署檢察官"
    ],
    "creditors": [

    ],
    "debtors": [

    ],
    "judicial_associate_officer": [

    ]
  },
  "adjudged_at": "2010-05-12",
  "created_at": "2016-01-05 12:05:24",
  "updated_at": "2016-01-05 12:05:24"
}