{
  "identify": "TPD-98-聲判-147-20100102-1",
  "court": {
    "name": "臺灣臺北地方法院",
    "code": "TPD"
  },
  "division": {
    "name": "刑事",
    "code": "M"
  },
  "year": 98,
  "word": "聲判",
  "number": "147",
  "jcheck": "1",
  "reason": "聲請交付審判",
  "content": "臺灣臺北地方法院刑事裁定             98年度聲判字第147號\n聲  請  人  甲○○\n代  理  人  顧定軒律師\n被      告  乙○○\n上列聲請人因被告誣告案件，不服臺灣高等法院檢察署檢察長中\n華民國98年7月9日98年度上聲議字第4249號駁回聲請再議之處分\n（原不起訴處分案號：臺灣臺北地方法院檢察署97年度偵字第\n25225號），聲請交付審判，本院裁定如下：\n    主  文\n聲請駁回。\n    理  由\n一、按聲請人不服上級法院檢察署檢察長或檢察總長認再議為無\n    理由而駁回之處分者，得於接受處分書後10日內委任律師提\n    出理由狀，向該管第一審法院聲請交付審判；法院認為交付\n    審判之聲請不合法或無理由者，應駁回之，刑事訴訟法第\n    258 條之1 第1 項、第258 條之3 第2 項前段，分別定有明\n    文。\n二、本件聲請人甲○○以被告乙○○涉犯誣告罪提出告訴，經臺\n    灣臺北地方法院檢察署（下稱臺北地檢）檢察官偵查終結，\n    以罪嫌不足為不起訴處分（97年度偵字第25255號，下稱不\n    起訴處分書），聲請人不服，聲請再議亦經臺灣高等法院檢\n    察署（下稱臺高檢）檢察長認再議無理由，於民國98年7月9\n    日以98年度上聲議字第4249號駁回再議（下稱原處分書），\n    經聲請人於同年7月20日收受，並於同年7月30日向本院聲請\n    交付審判，合先敘明。\n三、聲請交付審判意旨略以：\n    (一)聲請人與被告係夫妻關係，被告前於94年間對聲請人提起\n      確認兩造間婚姻不存在之訴，經判決敗訴確定，詎被告自\n      始知悉世界經貿資訊股份有限公司（下稱「世界經貿公司\n      」）之存在，且交付身分證件及印章給被告與聲請人之女\n      陳思庭（原名陳佳玲），授權陳思庭使用，竟於上開民事\n      訴訟期間，以陳思庭與聲請人未得被告之同意，偽造被告\n      署名及印文，而偽造世界經貿資訊股份有限公司（下稱「\n      世界經貿公司」）之董事願任同意書等私文書後，於92年\n      4 月21日向臺北市政府申請設立登記而行使；及明知92年\n      6 月3日，被告並未出席參與世界經貿公司之股東臨時會\n      議，竟於該會議事錄紀錄欄內，偽造被告署名及印文；另\n      聲請人及陳思庭明知被告於93年4月15日，並未參加世界\n      經貿公司之董事會，竟冒用被告名義，於世界經貿公司董\n      事會董事出席簽到簿、董事願任同意書上，偽造渠署押及\n      印文而偽造上開文書後，於93年4月23日持向臺北市政府\n      商業管理處辦理世界經貿公司變更登記而行使等虛偽之事\n      實，對聲請人及陳思庭提出偽造文書之不實告訴。惟此部\n      分業經臺北地檢以96年度偵字第12912號、第18573號不另\n      為不起訴處分，是聲請人等並無被告上開不實指述之行為\n      應已明確。聲請人因而對被告提起誣告之告訴。詎竟遭臺\n      北地檢為不起訴處分，經提起再議後，復經臺高檢以原處\n      分書駁回再議。\n    (二)然查，上開不起訴處分書及原處分書竟忽略下述證據而有\n      違誤：\n      1.臺北地檢竟於不起訴處分書認「被告曾授權簽署文件」\n        乙節乃屬「推論」，惟此部分應屬事實，並經本院於96\n        年度簡字第4036號、97年度簡上字第27號判決理由中加\n        以認定「被告並無不知世界經貿公司」及「被告確已授\n        權陳思庭辦理相關登記」之情事，亦有被告與陳思庭及\n        聲請人在內華達州參加臺灣商會舉辦之活動（背後掛有\n        「世界經濟貿易資訊股份有限公司」等字樣之布簾）之\n        照片在卷，則被告已該當誣告犯行，要屬無疑。此由被\n        告先稱「不知道世界經貿公司」，後改稱「當時人在美\n        國不可能簽署相關文件」而就知悉世界經貿公司部分說\n        謊即可認定。\n      2.由被告早已知悉世界經貿公司，卻謊稱其迄96年2月收\n        到臺北市國稅局94年度總合所得稅核定通知書時，始知\n        悉世界經貿公司，益見其確有虛構事實之情。\n      3.被告另謊稱「不知陳思庭如何取得其身分證影本」云云\n        ，然實則被告已曾自承「曾交付身分證彩本及印章給二\n        女兒」等語，當時陳思庭與聲請人正籌備世界經貿公司\n        設立事宜，自可證被告提供其身分證影本等文件確係為\n        授權由陳思庭處理設立經貿公司事宜。\n      4.被告又曾在本案中謊稱「其所參加之活動，乃係「美國\n        內華達州布達儀式」，而非世界經貿公司活動」云云，\n        就此，由我國外交部92年8月21日外北美二字第0922004\n        0970號函，即可證明被告上開均屬謊言。\n    (三)綜上，原處分書及不起訴處分書，有上述未洽之處，爰聲\n      請交付審判。\n四、經查：\n    (一)被告與聲請人係夫妻關係，陳思庭係被告與聲請人之長女\n      ，聲請人為名義負責人之世界經貿資訊股份有限公司（址\n      設臺北市○○區○○街72號1樓），經檢附日期為92年4月\n      11日上午10時，記錄為被告之發起人會議事錄（蓋印有被\n      告之印文1枚）、日期為同日下午2時，記錄為被告之董事\n      會議事錄（蓋印有被告之印文1枚）、日期為同日下午2時\n      之董事會出席董事簽到簿（有被告之署名及印文各1枚\n      ）、董事願任同意書（有被告之署名及印文各1枚）、乙\n      ○○身分證正反面影本及印文1枚等資料，向臺北市政府\n      申請設立登記，並經臺北市政府於92年5月2日核准；嗣檢\n      附日期為92年6月3日上午10時，記錄為被告之股東臨時（\n      常）會議事錄（蓋印有被告之印文1枚）等資料，向臺北\n      市政府申請變更登記，並經臺北市政府於92年6月9日核准\n      ；再檢附日期為93年4月15日上午10時，記錄為被告之股\n      東臨時（常）會議事錄（蓋印有被告之印文1枚）、日期\n      為同日下午2時，記錄為被告之董事會議事錄（蓋印有被\n      告之印文1枚）、日期為同日下午2時之董事會出席董事簽\n      到簿（有被告之署名及印文各1枚）、董事願任同意書（\n      有被告之署名及印文各1枚），向臺北市政府聲請變更登\n      記，因不符規定，臺北市政府於93年4月28日函覆不予受\n      理；末於94年7月11日經申請解散登記核准，上開發起人\n      會議事錄、董事會議事錄、董事會出席董事簽到簿、董事\n      願任同意書、股東臨時（常）會議事錄上被告之署名及印\n      文均非被告所為，被告於91年12月8日出境後迄95年2月18\n      日始入境，被告於96年3月29日以聲請人為被告向臺北地\n      檢提起告訴，控告聲請人未經其同意，冒用其名義，於上\n      開發起人會議事錄、董事會議事錄、董事會出席董事簽到\n      簿、董事願任同意書、股東臨時（常）會議事錄上偽造其\n      署名、印文而偽造私文書並進而行使，經臺北地檢於96年\n      10月17日以96年度偵字第12912號、第18573號就此部分不\n      另為不起訴處分之事實，業據被告、聲請人及陳思庭陳稱\n      在卷，並有最高法院97年度臺上字第702號民事裁定（被\n      告對聲請人提起確認婚姻關係不存在訴訟三審敗訴確定，\n      歷審：臺灣高等法院96年度家上字第78號、本院94年度家\n      訴字第146號判決）、臺北地檢96年度偵字第12912號、第\n      18573號起訴書（係針對聲請人及陳思庭違反公司法部分\n      提起公訴）、法務部入出境資訊連結作業、全戶戶籍資料\n      查詢結果各1份、臺北市商業管理處世界經貿資訊股份有\n      限公司案卷（96年度他字第3485號卷第85頁至第124頁）1\n      宗在卷可稽，可以認定。\n    (二)被告是否交付身分證、印章並授權陳思庭使用以擔任世界\n      經貿公司董事乙事，難以證明：\n      1.被告於91年12月8日至95年2月18日間均不在我國境內，\n        於92年4月11日至93年4月15日間在我國境內作成之上開\n        發起人會議事錄、董事會議事錄、董事會出席董事簽到\n        簿、董事願任同意書、股東臨時（常）會議事錄上被告\n        之署名及印文均非被告所為，業如前述，則上開署名及\n        印文是否經被告授權同意，非無疑問。\n      2.無法認定被告是否交付身分證、印章並授權陳思庭使用\n        ：\n        (1)固然，被告於96年3月29日在前案對聲請人提起偽造\n          文書之告訴時，指稱其不知有世界經貿公司存在，迄\n          96年2月接獲財政部臺北市國稅局94年度綜合所得稅\n          核定通知書後才察覺有異（96年度他字第3485號卷第\n          1頁）云云，惟經陳思庭提出有被告、陳思庭、聲請\n          人等人入鏡，背後懸掛有「世界經貿資訊股份有限公\n          司南內華達臺灣商會」等字樣紅布條之照片2張（96\n          年度偵字第12912號卷第23頁），被告則於96年10月\n          15日改稱：「（問：《提示陳思庭陳述狀所附相片》\n          這些相片上面的人是不是你？）是。這個場合是我介\n          紹陳思庭並推薦她成為內華達州的駐臺北經貿代表。\n          」、「（問：這些相片照相時間為何？）應該是2003\n          或2004年，她到美國告我之前。」（同上卷第27至28\n          頁）等語，而由被告等人背景即為上開紅布條，可以\n          看出被告等人係特地在該字樣紅布條前面拍照，而該\n          紅布條上面寫有字體甚大且非常明顯的「世界經貿資\n          訊股份有限公司南內華達臺灣商會」等字樣，被告又\n          在該紅布條前面刻意拍了2張照片，就上開文字實難\n          諉為不知，也就是被告至遲於拍照當時，即2003或\n          2004年間，就已經知道世界經貿公司之存在，但被告\n          卻於前開告訴狀中表示迄96年2月間才知悉，顯有不\n          符，則其刻意隱瞞其前已知悉世界經貿公司之存在，\n          動機為何，確實有可疑之處，這也正是臺北地檢96年\n          度偵字第12912號、第18573號起訴書理由中認定聲請\n          人及陳思庭所涉偽造文書罪嫌不足的主要原因，並因\n          而就此部分不另為不起訴處分，復為本院97年度簡上\n          字第27號判決理由認定檢察官以聲請人及陳思庭另涉\n          偽造文書部分未一併審理而提起上訴部分無理由之主\n          要論據。\n        (2)然而，被告刻意隱瞞其前已知悉世界經貿公司之存在\n          ，因認聲請人及陳思庭所涉上開偽造文書部分罪嫌不\n          足，並不代表被告實際上必然有授權予聲請人及陳思\n          庭，也難以據此推論被告明知有授權給聲請人及陳思\n          庭卻故意誣告之犯意，仍應審認其他證據以為認定。\n        (3)就上開發起人會議事錄、董事會議事錄、董事會出席\n          董事簽到簿、董事願任同意書、股東臨時（常）會議\n          事錄上被告之署名及印文係何人所為，陳思庭於96年\n          7 月23日檢察官訊問時供稱：「（問：《提示公司會\n          議記錄》上面乙○○的印章誰蓋的？）我爸爸給我的\n          印章，我給會計師蓋的。」、「（問：《提示92年4\n          月11日董事會出席董事簽到簿、董事願任同意書》簽\n          名是誰簽的？印章是誰蓋的？）我忘記了，蠻久了。\n          印章是我爸爸給我的，我好像是拿給會計師事務所。\n          」、「（問：你父親乙○○同意擔任該公司之董事，\n          是否有簽下任何文件證明？）因為我和他是家人，所\n          以沒有寫。我爸爸是說因為我是女生開公司，所以要\n          有男生。這家公司沒有借貸。」（96年度他字第5049\n          號卷第6至7頁）；甲○○於同日檢察官訊問時供稱：\n          「（問：你有在公司裡面擔任任何職務？）我沒有去\n          過。但是乙○○有去過。」、「（問：《提示董事願\n          任同意書、董事會出席董事簽到簿》上面簽名是否是\n          你簽的？）這個不是我簽的，我寫的沒有這麼漂亮。\n          」（同上卷第7頁）等語。依據陳思庭及聲請人上開\n          供述，均否認係其等簽署被告之名字及蓋印被告的印\n          文，這是非常奇怪的，聲請人既為被告之妻，陳思庭\n          復為被告之長女，如經被告授權使用其身分證及印章\n          擔任董事，應該會由聲請人或陳思庭代為簽署被告的\n          名字並蓋印其印文，何以均稱非其等所為、會計師蓋\n          的、忘記是誰簽被告的名字云云，實啟人疑竇。再者\n          ，被告於世界經貿公司成立之92年5月2日迄解散之94\n          年7月11日為止，均於境外（被告於91年12月8日出境\n          後迄95年2月18日始入境），如何能「參加」世界經\n          貿公司於92年4月11日、92年6月9日、93年4月15日之\n          發起人會議、董事會議、股東臨時（常）會議，並擔\n          任「記錄」，甚至如聲請人甲○○所言之「被告有去\n          過公司」，也是殊難想像。何況，被告如果真參加世\n          界經貿公司之董事，需負擔法律上之義務，何以在世\n          界經貿公司成立至解散之2年餘間，均不聞不問，未\n          曾入境，亦與常情不符。\n        (4)此外，被告固於97年11月26日檢察官訊問時供稱「（\n          問：你是否有將你的身分證影本及印章交給你女兒？\n          ）時間久遠，我忘記了，我曾將印章交給第二個女兒\n          ，至於身分證影本，我不記得我有將身分證影本交給\n          他們。」（97年度偵字第25255號卷第5頁）等語，惟\n          查陳思庭係被告之長女而非次女，是難認被告即已交\n          付印章給陳思庭並授權其用以擔任世界經貿公司之董\n          事乙情。\n        (5)從而，固然被告知悉世界經貿公司，卻否認上開情事\n          ，實屬可疑，但由聲請人及陳思庭前開與常情不符之\n          行為，亦難以認定被告確實有授權陳思庭及聲請人使\n          用被告之身分證件及印章以擔任世界經貿公司之董事\n          。\n      (三)準此，既然無法認定被告確實授權陳思庭及聲請人使用\n        被告之身分證件及印章以擔任世界經貿公司之董事，則\n        被告向臺北地檢提起偽造文書之告訴，自非故意捏造事\n        實，即難認與誣告之構成要件相符。\n五、綜上所述，聲請人所指被告有誣告嫌疑等情，缺乏積極證據\n    ，不起訴處分書及原處分書中既已詳為調查說明，認無積極\n    證據足資證明被告有何聲請人所指訴之犯行，因認被告犯罪\n    嫌疑不足，依刑事訴訟法第252條第10款之規定，由臺北地\n    檢原檢察官及臺高檢檢察長分別予以不起訴處分及駁回再議\n    聲請之處分，於法並無違誤，本件聲請交付審判意旨，對於\n    原處分加以指摘認定事實悖於常理，並無理由，應予駁回。\n六、依刑事訴訟法第258條之3第2項前段，裁定如主文。\n中    華    民    國    99    年    1     月    2     日\n                  刑事第十三庭  審判長法  官  許泰誠\n\n                                      法  官  林瑋桓\n\n                                      法  官  李貞瑩\n以上正本證明與原本無異。\n本裁定不得抗告\n                                      書記官  陳鳳瀴\n中    華    民    國    99    年    1    月     4    日",
  "structure": {
    "main": "聲請駁回。",
    "reason": "一、按聲請人不服上級法院檢察署檢察長或檢察總長認再議為無\n    理由而駁回之處分者，得於接受處分書後10日內委任律師提\n    出理由狀，向該管第一審法院聲請交付審判；法院認為交付\n    審判之聲請不合法或無理由者，應駁回之，刑事訴訟法第\n    258 條之1 第1 項、第258 條之3 第2 項前段，分別定有明\n    文。\n二、本件聲請人甲○○以被告乙○○涉犯誣告罪提出告訴，經臺\n    灣臺北地方法院檢察署（下稱臺北地檢）檢察官偵查終結，\n    以罪嫌不足為不起訴處分（97年度偵字第25255號，下稱不\n    起訴處分書），聲請人不服，聲請再議亦經臺灣高等法院檢\n    察署（下稱臺高檢）檢察長認再議無理由，於民國98年7月9\n    日以98年度上聲議字第4249號駁回再議（下稱原處分書），\n    經聲請人於同年7月20日收受，並於同年7月30日向本院聲請\n    交付審判，合先敘明。\n三、聲請交付審判意旨略以：\n    (一)聲請人與被告係夫妻關係，被告前於94年間對聲請人提起\n      確認兩造間婚姻不存在之訴，經判決敗訴確定，詎被告自\n      始知悉世界經貿資訊股份有限公司（下稱「世界經貿公司\n      」）之存在，且交付身分證件及印章給被告與聲請人之女\n      陳思庭（原名陳佳玲），授權陳思庭使用，竟於上開民事\n      訴訟期間，以陳思庭與聲請人未得被告之同意，偽造被告\n      署名及印文，而偽造世界經貿資訊股份有限公司（下稱「\n      世界經貿公司」）之董事願任同意書等私文書後，於92年\n      4 月21日向臺北市政府申請設立登記而行使；及明知92年\n      6 月3日，被告並未出席參與世界經貿公司之股東臨時會\n      議，竟於該會議事錄紀錄欄內，偽造被告署名及印文；另\n      聲請人及陳思庭明知被告於93年4月15日，並未參加世界\n      經貿公司之董事會，竟冒用被告名義，於世界經貿公司董\n      事會董事出席簽到簿、董事願任同意書上，偽造渠署押及\n      印文而偽造上開文書後，於93年4月23日持向臺北市政府\n      商業管理處辦理世界經貿公司變更登記而行使等虛偽之事\n      實，對聲請人及陳思庭提出偽造文書之不實告訴。惟此部\n      分業經臺北地檢以96年度偵字第12912號、第18573號不另\n      為不起訴處分，是聲請人等並無被告上開不實指述之行為\n      應已明確。聲請人因而對被告提起誣告之告訴。詎竟遭臺\n      北地檢為不起訴處分，經提起再議後，復經臺高檢以原處\n      分書駁回再議。\n    (二)然查，上開不起訴處分書及原處分書竟忽略下述證據而有\n      違誤：\n      1.臺北地檢竟於不起訴處分書認「被告曾授權簽署文件」\n        乙節乃屬「推論」，惟此部分應屬事實，並經本院於96\n        年度簡字第4036號、97年度簡上字第27號判決理由中加\n        以認定「被告並無不知世界經貿公司」及「被告確已授\n        權陳思庭辦理相關登記」之情事，亦有被告與陳思庭及\n        聲請人在內華達州參加臺灣商會舉辦之活動（背後掛有\n        「世界經濟貿易資訊股份有限公司」等字樣之布簾）之\n        照片在卷，則被告已該當誣告犯行，要屬無疑。此由被\n        告先稱「不知道世界經貿公司」，後改稱「當時人在美\n        國不可能簽署相關文件」而就知悉世界經貿公司部分說\n        謊即可認定。\n      2.由被告早已知悉世界經貿公司，卻謊稱其迄96年2月收\n        到臺北市國稅局94年度總合所得稅核定通知書時，始知\n        悉世界經貿公司，益見其確有虛構事實之情。\n      3.被告另謊稱「不知陳思庭如何取得其身分證影本」云云\n        ，然實則被告已曾自承「曾交付身分證彩本及印章給二\n        女兒」等語，當時陳思庭與聲請人正籌備世界經貿公司\n        設立事宜，自可證被告提供其身分證影本等文件確係為\n        授權由陳思庭處理設立經貿公司事宜。\n      4.被告又曾在本案中謊稱「其所參加之活動，乃係「美國\n        內華達州布達儀式」，而非世界經貿公司活動」云云，\n        就此，由我國外交部92年8月21日外北美二字第0922004\n        0970號函，即可證明被告上開均屬謊言。\n    (三)綜上，原處分書及不起訴處分書，有上述未洽之處，爰聲\n      請交付審判。\n四、經查：\n    (一)被告與聲請人係夫妻關係，陳思庭係被告與聲請人之長女\n      ，聲請人為名義負責人之世界經貿資訊股份有限公司（址\n      設臺北市○○區○○街72號1樓），經檢附日期為92年4月\n      11日上午10時，記錄為被告之發起人會議事錄（蓋印有被\n      告之印文1枚）、日期為同日下午2時，記錄為被告之董事\n      會議事錄（蓋印有被告之印文1枚）、日期為同日下午2時\n      之董事會出席董事簽到簿（有被告之署名及印文各1枚\n      ）、董事願任同意書（有被告之署名及印文各1枚）、乙\n      ○○身分證正反面影本及印文1枚等資料，向臺北市政府\n      申請設立登記，並經臺北市政府於92年5月2日核准；嗣檢\n      附日期為92年6月3日上午10時，記錄為被告之股東臨時（\n      常）會議事錄（蓋印有被告之印文1枚）等資料，向臺北\n      市政府申請變更登記，並經臺北市政府於92年6月9日核准\n      ；再檢附日期為93年4月15日上午10時，記錄為被告之股\n      東臨時（常）會議事錄（蓋印有被告之印文1枚）、日期\n      為同日下午2時，記錄為被告之董事會議事錄（蓋印有被\n      告之印文1枚）、日期為同日下午2時之董事會出席董事簽\n      到簿（有被告之署名及印文各1枚）、董事願任同意書（\n      有被告之署名及印文各1枚），向臺北市政府聲請變更登\n      記，因不符規定，臺北市政府於93年4月28日函覆不予受\n      理；末於94年7月11日經申請解散登記核准，上開發起人\n      會議事錄、董事會議事錄、董事會出席董事簽到簿、董事\n      願任同意書、股東臨時（常）會議事錄上被告之署名及印\n      文均非被告所為，被告於91年12月8日出境後迄95年2月18\n      日始入境，被告於96年3月29日以聲請人為被告向臺北地\n      檢提起告訴，控告聲請人未經其同意，冒用其名義，於上\n      開發起人會議事錄、董事會議事錄、董事會出席董事簽到\n      簿、董事願任同意書、股東臨時（常）會議事錄上偽造其\n      署名、印文而偽造私文書並進而行使，經臺北地檢於96年\n      10月17日以96年度偵字第12912號、第18573號就此部分不\n      另為不起訴處分之事實，業據被告、聲請人及陳思庭陳稱\n      在卷，並有最高法院97年度臺上字第702號民事裁定（被\n      告對聲請人提起確認婚姻關係不存在訴訟三審敗訴確定，\n      歷審：臺灣高等法院96年度家上字第78號、本院94年度家\n      訴字第146號判決）、臺北地檢96年度偵字第12912號、第\n      18573號起訴書（係針對聲請人及陳思庭違反公司法部分\n      提起公訴）、法務部入出境資訊連結作業、全戶戶籍資料\n      查詢結果各1份、臺北市商業管理處世界經貿資訊股份有\n      限公司案卷（96年度他字第3485號卷第85頁至第124頁）1\n      宗在卷可稽，可以認定。\n    (二)被告是否交付身分證、印章並授權陳思庭使用以擔任世界\n      經貿公司董事乙事，難以證明：\n      1.被告於91年12月8日至95年2月18日間均不在我國境內，\n        於92年4月11日至93年4月15日間在我國境內作成之上開\n        發起人會議事錄、董事會議事錄、董事會出席董事簽到\n        簿、董事願任同意書、股東臨時（常）會議事錄上被告\n        之署名及印文均非被告所為，業如前述，則上開署名及\n        印文是否經被告授權同意，非無疑問。\n      2.無法認定被告是否交付身分證、印章並授權陳思庭使用\n        ：\n        (1)固然，被告於96年3月29日在前案對聲請人提起偽造\n          文書之告訴時，指稱其不知有世界經貿公司存在，迄\n          96年2月接獲財政部臺北市國稅局94年度綜合所得稅\n          核定通知書後才察覺有異（96年度他字第3485號卷第\n          1頁）云云，惟經陳思庭提出有被告、陳思庭、聲請\n          人等人入鏡，背後懸掛有「世界經貿資訊股份有限公\n          司南內華達臺灣商會」等字樣紅布條之照片2張（96\n          年度偵字第12912號卷第23頁），被告則於96年10月\n          15日改稱：「（問：《提示陳思庭陳述狀所附相片》\n          這些相片上面的人是不是你？）是。這個場合是我介\n          紹陳思庭並推薦她成為內華達州的駐臺北經貿代表。\n          」、「（問：這些相片照相時間為何？）應該是2003\n          或2004年，她到美國告我之前。」（同上卷第27至28\n          頁）等語，而由被告等人背景即為上開紅布條，可以\n          看出被告等人係特地在該字樣紅布條前面拍照，而該\n          紅布條上面寫有字體甚大且非常明顯的「世界經貿資\n          訊股份有限公司南內華達臺灣商會」等字樣，被告又\n          在該紅布條前面刻意拍了2張照片，就上開文字實難\n          諉為不知，也就是被告至遲於拍照當時，即2003或\n          2004年間，就已經知道世界經貿公司之存在，但被告\n          卻於前開告訴狀中表示迄96年2月間才知悉，顯有不\n          符，則其刻意隱瞞其前已知悉世界經貿公司之存在，\n          動機為何，確實有可疑之處，這也正是臺北地檢96年\n          度偵字第12912號、第18573號起訴書理由中認定聲請\n          人及陳思庭所涉偽造文書罪嫌不足的主要原因，並因\n          而就此部分不另為不起訴處分，復為本院97年度簡上\n          字第27號判決理由認定檢察官以聲請人及陳思庭另涉\n          偽造文書部分未一併審理而提起上訴部分無理由之主\n          要論據。\n        (2)然而，被告刻意隱瞞其前已知悉世界經貿公司之存在\n          ，因認聲請人及陳思庭所涉上開偽造文書部分罪嫌不\n          足，並不代表被告實際上必然有授權予聲請人及陳思\n          庭，也難以據此推論被告明知有授權給聲請人及陳思\n          庭卻故意誣告之犯意，仍應審認其他證據以為認定。\n        (3)就上開發起人會議事錄、董事會議事錄、董事會出席\n          董事簽到簿、董事願任同意書、股東臨時（常）會議\n          事錄上被告之署名及印文係何人所為，陳思庭於96年\n          7 月23日檢察官訊問時供稱：「（問：《提示公司會\n          議記錄》上面乙○○的印章誰蓋的？）我爸爸給我的\n          印章，我給會計師蓋的。」、「（問：《提示92年4\n          月11日董事會出席董事簽到簿、董事願任同意書》簽\n          名是誰簽的？印章是誰蓋的？）我忘記了，蠻久了。\n          印章是我爸爸給我的，我好像是拿給會計師事務所。\n          」、「（問：你父親乙○○同意擔任該公司之董事，\n          是否有簽下任何文件證明？）因為我和他是家人，所\n          以沒有寫。我爸爸是說因為我是女生開公司，所以要\n          有男生。這家公司沒有借貸。」（96年度他字第5049\n          號卷第6至7頁）；甲○○於同日檢察官訊問時供稱：\n          「（問：你有在公司裡面擔任任何職務？）我沒有去\n          過。但是乙○○有去過。」、「（問：《提示董事願\n          任同意書、董事會出席董事簽到簿》上面簽名是否是\n          你簽的？）這個不是我簽的，我寫的沒有這麼漂亮。\n          」（同上卷第7頁）等語。依據陳思庭及聲請人上開\n          供述，均否認係其等簽署被告之名字及蓋印被告的印\n          文，這是非常奇怪的，聲請人既為被告之妻，陳思庭\n          復為被告之長女，如經被告授權使用其身分證及印章\n          擔任董事，應該會由聲請人或陳思庭代為簽署被告的\n          名字並蓋印其印文，何以均稱非其等所為、會計師蓋\n          的、忘記是誰簽被告的名字云云，實啟人疑竇。再者\n          ，被告於世界經貿公司成立之92年5月2日迄解散之94\n          年7月11日為止，均於境外（被告於91年12月8日出境\n          後迄95年2月18日始入境），如何能「參加」世界經\n          貿公司於92年4月11日、92年6月9日、93年4月15日之\n          發起人會議、董事會議、股東臨時（常）會議，並擔\n          任「記錄」，甚至如聲請人甲○○所言之「被告有去\n          過公司」，也是殊難想像。何況，被告如果真參加世\n          界經貿公司之董事，需負擔法律上之義務，何以在世\n          界經貿公司成立至解散之2年餘間，均不聞不問，未\n          曾入境，亦與常情不符。\n        (4)此外，被告固於97年11月26日檢察官訊問時供稱「（\n          問：你是否有將你的身分證影本及印章交給你女兒？\n          ）時間久遠，我忘記了，我曾將印章交給第二個女兒\n          ，至於身分證影本，我不記得我有將身分證影本交給\n          他們。」（97年度偵字第25255號卷第5頁）等語，惟\n          查陳思庭係被告之長女而非次女，是難認被告即已交\n          付印章給陳思庭並授權其用以擔任世界經貿公司之董\n          事乙情。\n        (5)從而，固然被告知悉世界經貿公司，卻否認上開情事\n          ，實屬可疑，但由聲請人及陳思庭前開與常情不符之\n          行為，亦難以認定被告確實有授權陳思庭及聲請人使\n          用被告之身分證件及印章以擔任世界經貿公司之董事\n          。\n      (三)準此，既然無法認定被告確實授權陳思庭及聲請人使用\n        被告之身分證件及印章以擔任世界經貿公司之董事，則\n        被告向臺北地檢提起偽造文書之告訴，自非故意捏造事\n        實，即難認與誣告之構成要件相符。\n五、綜上所述，聲請人所指被告有誣告嫌疑等情，缺乏積極證據\n    ，不起訴處分書及原處分書中既已詳為調查說明，認無積極\n    證據足資證明被告有何聲請人所指訴之犯行，因認被告犯罪\n    嫌疑不足，依刑事訴訟法第252條第10款之規定，由臺北地\n    檢原檢察官及臺高檢檢察長分別予以不起訴處分及駁回再議\n    聲請之處分，於法並無違誤，本件聲請交付審判意旨，對於\n    原處分加以指摘認定事實悖於常理，並無理由，應予駁回。\n六、依刑事訴訟法第258條之3第2項前段，裁定如主文。"
  },
  "characters": {
    "judges": [
      "許泰誠",
      "林瑋桓",
      "李貞瑩"
    ],
    "prosecutors": [

    ],
    "lawyers": [
      "顧定軒"
    ],
    "clerks": [
      "陳鳳瀴"
    ],
    "plaintiffs": [

    ],
    "defendants": [
      "乙○○"
    ],
    "prosecutor_office": [
      "甲"
    ],
    "creditors": [

    ],
    "debtors": [

    ],
    "judicial_associate_officer": [

    ]
  },
  "adjudged_at": "2010-01-02",
  "created_at": "2016-01-05 14:28:09",
  "updated_at": "2016-01-05 14:28:09"
}