{
  "identify": "TPD-99-簡-1433-20100512-1",
  "court": {
    "name": "臺灣臺北地方法院",
    "code": "TPD"
  },
  "division": {
    "name": "刑事",
    "code": "M"
  },
  "year": 99,
  "word": "簡",
  "number": "1433",
  "jcheck": "1",
  "reason": "毒品危害防制條例",
  "content": "臺灣臺北地方法院刑事簡易判決          99年度簡字第1433號\n聲  請  人  臺灣臺北地方法院檢察署檢察官\n被      告  甲○○\n上列被告因毒品危害防制條例案件，經檢察官聲請以簡易判決處\n刑（99年度毒偵字第914號），本院判決如下：\n    主  文\n甲○○持有第二級毒品，處有期徒刑貳月，如易科罰金，以新臺\n幣壹仟元折算壹日。扣案之含第二級毒品MDA、MDMA、MDEA成分\n之藥錠伍顆（驗餘淨重壹點肆壹公克）及含第二級毒品MDMA成分\n之藥錠參顆（驗餘淨重零點玖肆公克）均沒收銷燬之，包裝上開\n毒品之包裝袋貳個沒收之。\n    事實及理由\n一、本件犯罪事實及證據，均引用檢察官聲請簡易判決處刑書之\n    記載（如附件）。\n二、按MDA、MDMA及MDEA為毒品危害防制條例第2條第2項第2款所\n    列之第二級毒品，未經許可，不得非法持有。故核被告甲○\n    ○所為，係犯毒品危害防制條例第11條第2項之持有第二級\n    毒品罪。被告一行為持有MDA、MDMA及MDEA 3種第二級毒品\n    ，為同種想像競合犯，應依刑法第55條前段規定從一重處斷\n    。爰審酌被告購入毒品持有之目的係為施用，尚未施用即為\n    查獲，且扣案毒品數量僅8顆錠劑，數量非多，犯後已坦承\n    犯行之態度，又其並無前科，素行尚佳及其生活狀況、教育\n    程度等一切情狀，量處如主文所示之刑，並諭知易科罰金之\n    折算標準。又扣案之MDA、MDMA、MDEA成分藥錠5顆及MDMA成\n    分藥錠3顆，為查獲之第二級毒品，應依毒品危害防制條例\n    第18條第1項前段規定，併予以宣告沒收銷燬之。至於鑑驗\n    耗損之毒品既已滅失，爰不再行諭知沒收銷燬。又包裝上開\n    毒品之外包裝袋2個，為被告所有供本案犯罪所用之物，爰\n    均依刑法第38條第1項第2款之規定，併予宣告沒收。\n三、依刑事訴訟法第449條第1項前段、第3項、第454條第2項、\n    第450條第1項，毒品危害防制條例第11條第2項、第18條第1\n    項前段，刑法第11條、第55條前段、第41條第1項前段、第\n    38條第1項第2款，逕以簡易判決處刑如主文。\n中    華    民    國    99    年    5     月    12    日\n                  刑事第十三庭  法  官  林瑋桓\n以上正本證明與原本無異。\n如不服本判決應於收受送達後10日內向本院提出上訴書狀，並應\n敘述具體理由；其未敘述上訴理由者，應於上訴期間屆滿後20日\n內向本院補提理由書（均須按他造當事人之人數附繕）「切勿逕\n送上級法院」。\n中    華    民    國    99    年    5     月    12    日\n                                書記官  鄭伊芸\n附錄本件判決論罪科刑法條：\n毒品危害防制條例第11條第2 項\n持有第二級毒品者，處2 年以下有期徒刑、拘役或新臺幣3 萬元\n以下罰金。",
  "structure": {
    "main": "甲○○持有第二級毒品，處有期徒刑貳月，如易科罰金，以新臺\n幣壹仟元折算壹日。扣案之含第二級毒品MDA、MDMA、MDEA成分\n之藥錠伍顆（驗餘淨重壹點肆壹公克）及含第二級毒品MDMA成分\n之藥錠參顆（驗餘淨重零點玖肆公克）均沒收銷燬之，包裝上開\n毒品之包裝袋貳個沒收之。",
    "fact": "一、本件犯罪事實及證據，均引用檢察官聲請簡易判決處刑書之\n    記載（如附件）。\n二、按MDA、MDMA及MDEA為毒品危害防制條例第2條第2項第2款所\n    列之第二級毒品，未經許可，不得非法持有。故核被告甲○\n    ○所為，係犯毒品危害防制條例第11條第2項之持有第二級\n    毒品罪。被告一行為持有MDA、MDMA及MDEA 3種第二級毒品\n    ，為同種想像競合犯，應依刑法第55條前段規定從一重處斷\n    。爰審酌被告購入毒品持有之目的係為施用，尚未施用即為\n    查獲，且扣案毒品數量僅8顆錠劑，數量非多，犯後已坦承\n    犯行之態度，又其並無前科，素行尚佳及其生活狀況、教育\n    程度等一切情狀，量處如主文所示之刑，並諭知易科罰金之\n    折算標準。又扣案之MDA、MDMA、MDEA成分藥錠5顆及MDMA成\n    分藥錠3顆，為查獲之第二級毒品，應依毒品危害防制條例\n    第18條第1項前段規定，併予以宣告沒收銷燬之。至於鑑驗\n    耗損之毒品既已滅失，爰不再行諭知沒收銷燬。又包裝上開\n    毒品之外包裝袋2個，為被告所有供本案犯罪所用之物，爰\n    均依刑法第38條第1項第2款之規定，併予宣告沒收。\n三、依刑事訴訟法第449條第1項前段、第3項、第454條第2項、\n    第450條第1項，毒品危害防制條例第11條第2項、第18條第1\n    項前段，刑法第11條、第55條前段、第41條第1項前段、第\n    38條第1項第2款，逕以簡易判決處刑如主文。",
    "reason": "一、本件犯罪事實及證據，均引用檢察官聲請簡易判決處刑書之\n    記載（如附件）。\n二、按MDA、MDMA及MDEA為毒品危害防制條例第2條第2項第2款所\n    列之第二級毒品，未經許可，不得非法持有。故核被告甲○\n    ○所為，係犯毒品危害防制條例第11條第2項之持有第二級\n    毒品罪。被告一行為持有MDA、MDMA及MDEA 3種第二級毒品\n    ，為同種想像競合犯，應依刑法第55條前段規定從一重處斷\n    。爰審酌被告購入毒品持有之目的係為施用，尚未施用即為\n    查獲，且扣案毒品數量僅8顆錠劑，數量非多，犯後已坦承\n    犯行之態度，又其並無前科，素行尚佳及其生活狀況、教育\n    程度等一切情狀，量處如主文所示之刑，並諭知易科罰金之\n    折算標準。又扣案之MDA、MDMA、MDEA成分藥錠5顆及MDMA成\n    分藥錠3顆，為查獲之第二級毒品，應依毒品危害防制條例\n    第18條第1項前段規定，併予以宣告沒收銷燬之。至於鑑驗\n    耗損之毒品既已滅失，爰不再行諭知沒收銷燬。又包裝上開\n    毒品之外包裝袋2個，為被告所有供本案犯罪所用之物，爰\n    均依刑法第38條第1項第2款之規定，併予宣告沒收。\n三、依刑事訴訟法第449條第1項前段、第3項、第454條第2項、\n    第450條第1項，毒品危害防制條例第11條第2項、第18條第1\n    項前段，刑法第11條、第55條前段、第41條第1項前段、第\n    38條第1項第2款，逕以簡易判決處刑如主文。"
  },
  "characters": {
    "judges": [
      "林瑋桓"
    ],
    "prosecutors": [

    ],
    "lawyers": [

    ],
    "clerks": [
      "鄭伊芸"
    ],
    "plaintiffs": [

    ],
    "defendants": [
      "甲○○"
    ],
    "prosecutor_office": [
      "臺灣臺北地方法院檢察署檢察官"
    ],
    "creditors": [

    ],
    "debtors": [

    ],
    "judicial_associate_officer": [

    ]
  },
  "adjudged_at": "2010-05-12",
  "created_at": "2016-01-05 12:06:06",
  "updated_at": "2016-01-05 12:06:06"
}