{
  "identify": "TPD-99-除-862-20100512-1",
  "court": {
    "name": "臺灣臺北地方法院",
    "code": "TPD"
  },
  "division": {
    "name": "民事",
    "code": "V"
  },
  "year": 99,
  "word": "除",
  "number": "862",
  "jcheck": "1",
  "reason": "除權判決",
  "content": "臺灣臺北地方法院民事判決               99年度除字第862號\n聲  請  人  立昌紙業股份有限公司\n法定代理人  甲○○\n代  理  人  乙○○\n上列聲請人聲請除權判決事件，本院判決如下：\n    主  文\n如附表所示之證券無效。\n訴訟費用由聲請人負擔。\n    理  由\n一、上開證券，經本院以98年度司催字第2932號公示催告。\n二、所定申報權利期間，已於民國99年3月25日屆滿，迄今無人\n    申報權利。\n三、依民事訴訟法第564條第1項，判決如主文。\n中    華    民    國    99    年    5     月    12    日\n                  民事第三庭  審判長法  官  丁蓓蓓\n                                    法  官  魏式瑜\n                                    法  官  周玉琦\n以上正本證明係照原本作成。\n本判決不得上訴。\n中    華    民    國    99    年    5     月     12   日\n                                    書記官  劉英權\n┌────────────────────────────────┐\n│附表：                                       99年度除字第862號  │\n├──┬─────┬────┬──────┬─────┬─────┤\n│編號│發票人    │付款人  │發票日      │票面金額  │支票號碼  │\n│    │          │        │            │（新臺幣）│          │\n├──┼─────┼────┼──────┼─────┼─────┤\n│001 │廣興印刷廠│台北富邦│98年10月20日│55,196元  │AU0000000 │\n│    │股份有限  │商業銀行│            │          │          │\n│    │公司      │仁愛分行│            │          │          │\n└──┴─────┴────┴──────┴─────┴─────┘",
  "structure": {
    "main": "如附表所示之證券無效。\n訴訟費用由聲請人負擔。",
    "reason": "一、上開證券，經本院以98年度司催字第2932號公示催告。\n二、所定申報權利期間，已於民國99年3月25日屆滿，迄今無人\n    申報權利。\n三、依民事訴訟法第564條第1項，判決如主文。"
  },
  "characters": {
    "judges": [
      "丁蓓蓓",
      "魏式瑜",
      "周玉琦"
    ],
    "prosecutors": [

    ],
    "lawyers": [

    ],
    "clerks": [
      "劉英權"
    ],
    "plaintiffs": [

    ],
    "defendants": [

    ],
    "prosecutor_office": [
      "立昌紙業股份有限公司"
    ],
    "creditors": [

    ],
    "debtors": [

    ],
    "judicial_associate_officer": [

    ]
  },
  "adjudged_at": "2010-05-12",
  "created_at": "2016-01-05 12:12:49",
  "updated_at": "2016-01-05 12:12:49"
}