{
  "identify": "TPD-98-聲-3408-20100105-1",
  "court": {
    "name": "臺灣臺北地方法院",
    "code": "TPD"
  },
  "division": {
    "name": "刑事",
    "code": "M"
  },
  "year": 98,
  "word": "聲",
  "number": "3408",
  "jcheck": "1",
  "reason": "聲請單獨宣告沒收違禁物",
  "content": "臺灣臺北地方法院刑事裁定              98年度聲字第3408號\n聲  請  人  臺灣臺北地方法院檢察署檢察官\n被      告  甲○○\n上列聲請人聲請單獨宣告沒收違禁物(98年度聲沒字第393號)案\n件，本院裁定如下：\n    主  文\n扣案如附表所示之物沒收銷燬。\n    理  由\n一、本件聲請意旨略以：臺灣臺北地方法院檢察署九十七年度毒\n    偵字第三００一號被告甲○○違反毒品危害防制條例案件，\n    業經該署檢察官為不起訴處分確定，惟查扣案之磚紅色圓形\n    錠劑一粒，經交通部民用航空局航空醫務中心檢驗結果，確\n    認檢出第二級毒品ＭＤＭＡ、ＭＤＡ、甲基安非他命等成分\n    （不含空包裝袋，驗餘淨重零點二一０三公克），有該局鑑\n    定通知書一紙附卷可稽，依毒品危害防制條例第二條第二項\n    第一款及第十一條第二項之規定，係屬違禁物，爰依刑法第\n    三十八條第一項第一款、第二項、第四十條第二項及毒品危\n    害防制條例第十八條第一項前段之規定聲請單獨宣告沒收銷\n    燬等語。\n二、按持有第二級毒品，係犯毒品危害防制條例第十一條第二項\n    之罪，故第一級毒品係屬違禁物。次按違禁物，不問屬於犯\n    人與否，均沒收之，且得單獨宣告沒收，而查獲之毒品及專\n    供製造或施用毒品之器具，不問屬於犯人與否，均沒收銷燬\n    之，刑法第三十八條第一項第一款、第二項、第四十條第二\n    項及毒品危害防制條例第十八條第一項前段分別定有明文。\n    經查，本件被告基於施用第二級毒品安非他命、ＭＤＭＡ之\n    犯意，於民國九十七年八月二十九日為警採尿送驗前之九十\n    六小時之某時，在不詳地點，施用第二級毒品安非他命、Ｍ\n    ＤＭＡ，嗣於同年月二十九日十八時三十五分許為警在臺北\n    市中山區○○○路五二０號前攔撿查獲，並扣得第二級毒品\n    ＭＤＭＡ一顆（不含空包裝袋，驗餘淨重零點二一０三公克\n    ）之案件，經本院以九十七年度毒聲字第八八四號裁定送觀\n    察、勒戒後，因無繼續施用之傾向，復經臺灣臺北地方法院\n    檢察署檢察官以九十七年度毒偵字第三００一為不起訴處分\n    確定，惟查，扣案之磚紅色圓形錠劑一粒，經交通部民用航\n    空局航空醫務中心檢驗結果，確認檢出第二級毒品ＭＤＭＡ\n    、ＭＤＡ、甲基安非他命等成分（不含空包裝袋，驗餘淨重\n    零點二一０三公克），有該局鑑定通知書一紙附卷可稽，是\n    檢察官所提單獨宣告沒收之聲請，核與前揭規定，並無不合\n    ，爰依刑法第四十條第二項，毒品危害防制條例第十八條第\n    一項前段之規定，裁定如主文。\n中    華    民    國    99    年     1    月    5     日\n                       刑事第五庭   法  官  鄭昱仁\n上正本證明與原本無異。\n如不服本裁定，應於裁定送達後5 日內向本院提出抗告狀。\n                                    書記官  宋德華\n中    華    民    國    99    年     1    月    5     日\n附表：\n一、磚紅色圓形錠劑壹粒，不含空包裝袋，驗餘淨重零點貳壹零\n    公克。",
  "structure": {
    "main": "扣案如附表所示之物沒收銷燬。",
    "reason": "一、本件聲請意旨略以：臺灣臺北地方法院檢察署九十七年度毒\n    偵字第三００一號被告甲○○違反毒品危害防制條例案件，\n    業經該署檢察官為不起訴處分確定，惟查扣案之磚紅色圓形\n    錠劑一粒，經交通部民用航空局航空醫務中心檢驗結果，確\n    認檢出第二級毒品ＭＤＭＡ、ＭＤＡ、甲基安非他命等成分\n    （不含空包裝袋，驗餘淨重零點二一０三公克），有該局鑑\n    定通知書一紙附卷可稽，依毒品危害防制條例第二條第二項\n    第一款及第十一條第二項之規定，係屬違禁物，爰依刑法第\n    三十八條第一項第一款、第二項、第四十條第二項及毒品危\n    害防制條例第十八條第一項前段之規定聲請單獨宣告沒收銷\n    燬等語。\n二、按持有第二級毒品，係犯毒品危害防制條例第十一條第二項\n    之罪，故第一級毒品係屬違禁物。次按違禁物，不問屬於犯\n    人與否，均沒收之，且得單獨宣告沒收，而查獲之毒品及專\n    供製造或施用毒品之器具，不問屬於犯人與否，均沒收銷燬\n    之，刑法第三十八條第一項第一款、第二項、第四十條第二\n    項及毒品危害防制條例第十八條第一項前段分別定有明文。\n    經查，本件被告基於施用第二級毒品安非他命、ＭＤＭＡ之\n    犯意，於民國九十七年八月二十九日為警採尿送驗前之九十\n    六小時之某時，在不詳地點，施用第二級毒品安非他命、Ｍ\n    ＤＭＡ，嗣於同年月二十九日十八時三十五分許為警在臺北\n    市中山區○○○路五二０號前攔撿查獲，並扣得第二級毒品\n    ＭＤＭＡ一顆（不含空包裝袋，驗餘淨重零點二一０三公克\n    ）之案件，經本院以九十七年度毒聲字第八八四號裁定送觀\n    察、勒戒後，因無繼續施用之傾向，復經臺灣臺北地方法院\n    檢察署檢察官以九十七年度毒偵字第三００一為不起訴處分\n    確定，惟查，扣案之磚紅色圓形錠劑一粒，經交通部民用航\n    空局航空醫務中心檢驗結果，確認檢出第二級毒品ＭＤＭＡ\n    、ＭＤＡ、甲基安非他命等成分（不含空包裝袋，驗餘淨重\n    零點二一０三公克），有該局鑑定通知書一紙附卷可稽，是\n    檢察官所提單獨宣告沒收之聲請，核與前揭規定，並無不合\n    ，爰依刑法第四十條第二項，毒品危害防制條例第十八條第\n    一項前段之規定，裁定如主文。"
  },
  "characters": {
    "judges": [
      "鄭昱仁"
    ],
    "prosecutors": [

    ],
    "lawyers": [

    ],
    "clerks": [
      "宋德華"
    ],
    "plaintiffs": [

    ],
    "defendants": [
      "甲○○"
    ],
    "prosecutor_office": [
      "臺灣臺北地方法院檢察署檢察官"
    ],
    "creditors": [

    ],
    "debtors": [

    ],
    "judicial_associate_officer": [

    ]
  },
  "adjudged_at": "2010-01-05",
  "created_at": "2016-01-05 15:12:09",
  "updated_at": "2016-01-05 15:12:09"
}