{
  "identify": "TPD-99-簡-1408-20100512-1",
  "court": {
    "name": "臺灣臺北地方法院",
    "code": "TPD"
  },
  "division": {
    "name": "刑事",
    "code": "M"
  },
  "year": 99,
  "word": "簡",
  "number": "1408",
  "jcheck": "1",
  "reason": "竊盜",
  "content": "臺灣臺北地方法院刑事簡易判決          99年度簡字第1408號\n聲  請  人  臺灣臺北地方法院檢察署檢察官\n被      告  甲○○\n上列被告因竊盜案件，經檢察官聲請以簡易判決處刑（99年度偵\n字第5904號），本院判決如下：\n    主  文\n甲○○竊盜，處拘役貳拾日，如易科罰金，以新臺幣壹仟元折算\n壹日；又竊盜，處拘役參拾日，如易科罰金，以新臺幣壹仟元折\n算壹日；又竊盜，處拘役肆拾日，如易科罰金，以新臺幣壹仟元\n折算壹日。應執行拘役柒拾日，如易科罰金，以新臺幣壹仟元折\n算壹日。\n    事實及理由\n一、本件犯罪事實及證據，均引用檢察官聲請簡易判決處刑書之\n    記載（如附件）。\n二、核被告甲○○所為，係犯刑法第320條第1項之竊盜罪。又被\n    告所犯3次竊盜犯行間，犯意各別，行為互殊，應分論併罰\n    。爰審酌被告為滿足自身性慾，竟徒手竊取陌生女性內衣褲\n    ，影響被害人財產權益，造成生活不便，行為殊值非難，惟\n    其犯後坦承犯行，尚有悔意，其所竊物品價值非鉅，且已返\n    還部分財物予被害人領回，另其犯罪手段與情節尚屬平和輕\n    微暨其年齡、智識程度等一切情狀，各量處如主文所示之刑\n    及定其應執行之刑，並均諭知易科罰金之折算標準。\n三、依刑事訴訟法第449條第1項前段、第3項、第454條第2項，\n    刑法第320條第1項、第51條第6款、第41條第1項前段，逕以\n    簡易判決處刑如主文。\n中    華    民    國    99    年    5    月    12    日\n                  刑事第十三庭  法  官  林瑋桓\n以上正本證明與原本無異。\n如不服本判決應於收受送達後10日內向本院提出上訴書狀，並應\n敘述具體理由；其未敘述上訴理由者，應於上訴期間屆滿後20日\n內向本院補提理由書（均須按他造當事人之人數附繕）「切勿逕\n送上級法院」。\n中    華    民    國    99    年    5     月    12    日\n                                書記官  鄭伊芸\n附錄法條\n中華民國刑法第320條\n（普通竊盜罪、竊佔罪）\n意圖為自己或第三人不法之所有，而竊取他人之動產者，為竊盜\n罪，處5  年以下有期徒刑、拘役或 5 百元以下罰金。\n意圖為自己或第三人不法之利益，而竊佔他人之不動產者，依前\n項之規定處斷。\n前二項之未遂犯罰之。",
  "structure": {
    "main": "甲○○竊盜，處拘役貳拾日，如易科罰金，以新臺幣壹仟元折算\n壹日；又竊盜，處拘役參拾日，如易科罰金，以新臺幣壹仟元折\n算壹日；又竊盜，處拘役肆拾日，如易科罰金，以新臺幣壹仟元\n折算壹日。應執行拘役柒拾日，如易科罰金，以新臺幣壹仟元折\n算壹日。",
    "fact": "一、本件犯罪事實及證據，均引用檢察官聲請簡易判決處刑書之\n    記載（如附件）。\n二、核被告甲○○所為，係犯刑法第320條第1項之竊盜罪。又被\n    告所犯3次竊盜犯行間，犯意各別，行為互殊，應分論併罰\n    。爰審酌被告為滿足自身性慾，竟徒手竊取陌生女性內衣褲\n    ，影響被害人財產權益，造成生活不便，行為殊值非難，惟\n    其犯後坦承犯行，尚有悔意，其所竊物品價值非鉅，且已返\n    還部分財物予被害人領回，另其犯罪手段與情節尚屬平和輕\n    微暨其年齡、智識程度等一切情狀，各量處如主文所示之刑\n    及定其應執行之刑，並均諭知易科罰金之折算標準。\n三、依刑事訴訟法第449條第1項前段、第3項、第454條第2項，\n    刑法第320條第1項、第51條第6款、第41條第1項前段，逕以\n    簡易判決處刑如主文。",
    "reason": "一、本件犯罪事實及證據，均引用檢察官聲請簡易判決處刑書之\n    記載（如附件）。\n二、核被告甲○○所為，係犯刑法第320條第1項之竊盜罪。又被\n    告所犯3次竊盜犯行間，犯意各別，行為互殊，應分論併罰\n    。爰審酌被告為滿足自身性慾，竟徒手竊取陌生女性內衣褲\n    ，影響被害人財產權益，造成生活不便，行為殊值非難，惟\n    其犯後坦承犯行，尚有悔意，其所竊物品價值非鉅，且已返\n    還部分財物予被害人領回，另其犯罪手段與情節尚屬平和輕\n    微暨其年齡、智識程度等一切情狀，各量處如主文所示之刑\n    及定其應執行之刑，並均諭知易科罰金之折算標準。\n三、依刑事訴訟法第449條第1項前段、第3項、第454條第2項，\n    刑法第320條第1項、第51條第6款、第41條第1項前段，逕以\n    簡易判決處刑如主文。"
  },
  "characters": {
    "judges": [
      "林瑋桓"
    ],
    "prosecutors": [

    ],
    "lawyers": [

    ],
    "clerks": [
      "鄭伊芸"
    ],
    "plaintiffs": [

    ],
    "defendants": [
      "甲○○"
    ],
    "prosecutor_office": [
      "臺灣臺北地方法院檢察署檢察官"
    ],
    "creditors": [

    ],
    "debtors": [

    ],
    "judicial_associate_officer": [

    ]
  },
  "adjudged_at": "2010-05-12",
  "created_at": "2016-01-05 12:06:04",
  "updated_at": "2016-01-05 12:06:04"
}