{
  "identify": "TPD-98-簡-5131-20100105-1",
  "court": {
    "name": "臺灣臺北地方法院",
    "code": "TPD"
  },
  "division": {
    "name": "刑事",
    "code": "M"
  },
  "year": 98,
  "word": "簡",
  "number": "5131",
  "jcheck": "1",
  "reason": "偽造文書",
  "content": "臺灣臺北地方法院刑事簡易判決          98年度簡字第5131號\n聲  請  人  臺灣臺北地方法院檢察署檢察官\n被      告  甲○○\n上列被告因偽造文書案件，經檢察官聲請以簡易判決處刑（98年\n度偵字第26900號），本院判決如下：\n    主  文\n甲○○共同犯行使偽造私文書罪，處有期徒刑月，如易科罰金\n，以新臺幣壹仟元折算壹日。\n威寶電信股份有限公司門號申請書上申請人簽章欄之偽造「乙○\n○」署名壹枚沒收。\n    事實及理由\n一、本件犯罪事實除將「基於共同行使偽造文書及不法所有之犯\n    意聯絡」補充為「基於共同行使偽造、變造文書及意圖為自\n    己不法所有之犯意聯絡」外，其餘犯罪事實及證據均引用檢\n    察官聲請簡易判決處刑書之記載（如附件所示）。\n二、核被告甲○○所為，係犯刑法第216條、第210條行使偽造私\n    文書罪，刑法第216條、第212條之行使特種文書罪及刑法第\n    339條第1項之詐欺取財罪、同條第2項詐欺得利罪。被告與\n    同案被告李明信（另由檢察官為緩起訴處分）就前述犯行，\n    有犯意聯絡及行為分擔，為共同正犯。被告於取得被害人乙\n    ○○之身分證、健保卡等證件影本後，變造乙○○之身分證\n    父母欄，再由同案被告李明信在申請書申請人簽章欄內偽造\n    「乙○○」署名1枚，並在該申請書上各欄位填載乙○○之\n    基本資料而偽造該申請書，繼而持以申請行動電話門號而行\n    使之，其中偽造署名係偽造私文書之部分行為，而偽造私文\n    書及變造特種文書之低度行為復為行使偽造私文書及行使變\n    造特種文書之高度行為所吸收，均不另論罪。被告以一個申\n    請行為同時觸犯行使偽造私文書罪、詐欺取財及詐欺得利罪\n    ，為想像競合犯，應從較重之行使偽造私文書罪論處。爰審\n    酌：被告之前科素行，於取得被害人之證件影本後，明知未\n    經被害人同意，竟變造被害人身分證影本且冒名申辦行動電\n    話門號，並詐得手機1支、SIM卡1張、補助費新台幣（下同\n    ）7000元及通話費利益1780元，造成被害人乙○○及威寶電\n    信股份有限公司之損害及該電信公司對於門號使用人之管理\n    正確。惟被告犯罪後，於偵查中坦承全部犯行，並已由同案\n    被告李明信賠償威寶電信股份有限公司8780元（偵查卷第42\n    頁至44頁），犯後態度尚可。且被告因貪圖小利，致為本件\n    犯行等一切情狀，量處有期徒刑3月，並諭知易科罰金之折\n    算標準。至於由共同被告李明信在98年3月28日門號申請書\n    申請人簽章欄內偽造「乙○○」之署名1枚，雖未扣案，但\n    無證據證明已滅失，依刑法第219條規定，不問屬於被告與\n    否，均應宣告沒收。至於被告所偽造之門號申請書，因已交\n    付威寶電信股份有限公司行使，而非被告所有之物，爰不為\n    沒收之諭知。\n三、適用法條：刑事訴訟法第449條第1項前段、第3項、第450條\n    第1項、第454條第2項，刑法第28條、第216條、第210條、\n    第212條、第339條第1項、第2項、第55條、第41條第1項前\n    段、第219條，刑法施行法第1條之1，逕以簡易判決處刑如\n    主文。\n如不服本判決，應於收受判決正本送達之翌日起10日內向本庭提\n出上訴狀，上訴於本院合議庭（須附繕本）。\n中    華    民    國    99    年     1    月    5     日\n                  刑事第十庭  法  官  蔡坤湖\n上正本證明與原本無異。\n                              書記官  林妙穗\n中    華    民    國    99    年     1    月    5     日\n附錄論罪法條：\n中華民國刑法第210條\n（偽造變造私文書罪）\n偽造、變造私文書，足以生損害於公眾或他人者，處 5 年以下\n有期徒刑。\n中華民國刑法第212條\n（偽造變造特種文書罪）\n偽造、變造護照、旅券、免許證、特許證及關於品行、能力服務\n或其他相類之證書、介紹書，足以生損害於公眾或他人者，處\n1年以下有期徒刑、拘役或3百元以下罰金。\n中華民國刑法第216條\n（行使偽造變造或登載不實之文書罪）\n行使第 210 條至第 215 條之文書者，依偽造、變造文書或登載\n不實事項或使登載不實事項之規定處斷。\n中華民國刑法第339條\n（普通詐欺罪）\n意圖為自己或第三人不法之所有，以詐術使人將本人或第三人之\n物交付者，處 5 年以下有期徒刑、拘役或科或併科 1 千元以下\n罰金。\n以前項方法得財產上不法之利益或使第三人得之者，亦同。\n前二項之未遂犯罰之。\n臺灣臺北地方法院檢察署檢察官聲請簡易判決處刑書      附件\n                                     98年度偵字第26900號\n    被      告  甲○○  男  35歲（民國○○年○○月○○日生）\n                        住臺南縣仁德鄉○○路240巷31弄9號\n                        國民身份證統一編號：Ｚ000000000號\n上列被告因詐欺等案件，業經偵查終結，認為宜聲請以簡易判決\n處刑，茲將犯罪事實及證據並所犯法條分敘如下：\n        犯罪事實\n一、甲○○係徵信業者，因而取得委託人乙○○所交付之身份證\n    影本（該身份證影本上之父母欄名字部分，為乙○○將中間\n    一字挖空）及健保卡影本。甲○○為申辦電話及門號，基於\n    行使變偽造特種文書之犯意，於民國98年3月某日，在某處\n    ，將乙○○所交付之身份證影本父母欄挖空部分，將它處所\n    剪下「德」與「金」黏上後影印，以此方式變造身份證影本\n    ，再於98年3月28日，持以向李明信所經營之豐霸通信行（\n    設臺北市○○區○○路177號），申辦門號以行使之，李明\n    信亦明知未經過乙○○之授權或同意（李明信涉嫌行使偽造\n    私文書部分，另為緩起訴處分），竟與甲○○基於共同行使\n    偽造文書及不法所有之犯意聯絡，由李明信在威寶電信股份\n    有限公司（下稱威寶電信）行動電話服務申請書上，偽簽乙\n    ○○之名於其上，表示願依該服務申請書內容向威寶電信申\n    請行動電話電信服務，而已領得贈送之行動電話等意思表示\n    ，偽造完成屬於私文書之服務申請書、服務契約、代辦授權\n    書後，再連同乙○○之國民身份證、健保卡影本向威寶電信\n    申請，使威寶電信為誤認係乙○○本人欲申辦門號且承諾將\n    來願依約定支付電信費用，而將威寶電信公司專案手機（即\n    三星牌行動電話1具）連同門號「0000000000」號之SIM卡1\n    枚交給甲○○，以此方式詐得上開門號SIM卡1枚，上開專案\n    手機，李明信並亦詐得威電信公司補助專案手機之費用7000\n    元，足以生損害於乙○○、威寶電信對行動電話申請者之審\n    核權及使用者帳務管理之正確性。而甲○○取得上開行動電\n    話SIM卡之日起至98年5月間，另基於詐欺得利之犯意，接續\n    撥打、使用上述門號與人聯絡通話，致不知情之威寶電信因\n    陷於錯誤而接續提供相關通信服務，其因使用上開門號而獲\n    得相當於1780元通話費用之不法利益。嗣因乙○○接獲威寶\n    電信催繳通話費用之帳單，循線查悉上情。\n二、案經乙○○及威寶電信告訴及國家通訊傳播委員會函送偵辦\n    。\n        證據並所犯法條\n一、證據：（一）被告甲○○之自白；（二）同案被告李明信於\n    偵查中之自白（三）告訴人乙○○及威寶電信之代理人丙○\n    ○之指訴；（四）告訴人乙○○所提出之未辦門號聲明書、\n    、威寶電信服務申請書及電信帳單。被告犯嫌應堪認定。\n二、核被告甲○○所為，係犯刑法第216條、第212條行使偽造特\n    種文書、第216條、210條行使偽造私文書及第339條第1項、\n    詐欺取財、第2項詐欺得利罪嫌。其偽造署押所涉之刑法第\n    217條第1項偽造署押罪為偽造私文書罪所吸收，偽造私文書\n    及偽造特種文書之低度行為，復為高度之行使偽造私文書及\n    特種文書所吸收，均不另論罪。而被告甲○○撥打號行動電\n    話累計通信費用1780元，係基於概括犯意且在時間場所密接\n    下侵害同一法益，屬接續犯，請論以一個詐欺得利罪。被告\n    甲○○與李明信，有犯意聯絡及行為分擔，請依共同正犯論\n    處。\n三、依刑事訴訟法第451條第1項聲請逕以簡易判決處刑。\n    此  致\n臺灣臺北地方法院\n中    華    民    國    98    年    12    月    15    日\n                              檢  察  官  侯  靜  雯\n本件正本證明與原本無異\n中    華    民    國    98    年    12    月    21    日\n                              書  記  官  胡  漢  光\n本件係依刑事訴訟法簡易程式辦理，法院簡易庭得不傳喚被告、\n輔佐人、告訴人、告發人等出庭即以簡易判決處刑；被告、被害\n人、告訴人等對告訴乃論案件如已達成民事和解而要撤回告訴或\n對非告訴乃論案件認有受傳喚到庭陳述意見之必要時，請即另以\n書狀向簡易法庭陳述或請求傳訊。\n附錄本案所犯法條全文\n中華民國刑法第210條\n偽造、變造私文書，足以生損害於公眾或他人者，處5年以下有\n期徒刑。\n中華民國刑法第212條\n偽造、變造護照、旅券、免許證、特許證及關於品行、能力服務\n或其他相類之證書、介紹書，足以生損害於公眾或他人者，處1\n年以下有期徒刑、拘役或3百元以下罰金。\n中華民國刑法第216條\n行使第210條至第215條之文書者，依偽造、變造文書或登載不實\n事項或使登載不實事項之規定處斷。\n中華民國刑法第217條\n偽造印章、印文或署押，足以生損害於公眾或他人者，處3年以\n下有期徒刑。\n盜用印章、印文或署押，足以生損害於公眾或他人者，亦同。\n中華民國刑法第339條\n意圖為自己或第三人不法之所有，以詐術使人將本人或第三人之\n物交付者，處5年以下有期徒刑、拘役或科或併科1千元以下罰金\n。\n以前項方法得財產上不法之利益或使第三人得之者，亦同。\n前二項之未遂犯罰之。",
  "structure": {
    "main": "甲○○共同犯行使偽造私文書罪，處有期徒刑月，如易科罰金\n，以新臺幣壹仟元折算壹日。\n威寶電信股份有限公司門號申請書上申請人簽章欄之偽造「乙○\n○」署名壹枚沒收。",
    "fact": "一、本件犯罪事實除將「基於共同行使偽造文書及不法所有之犯\n    意聯絡」補充為「基於共同行使偽造、變造文書及意圖為自\n    己不法所有之犯意聯絡」外，其餘犯罪事實及證據均引用檢\n    察官聲請簡易判決處刑書之記載（如附件所示）。\n二、核被告甲○○所為，係犯刑法第216條、第210條行使偽造私\n    文書罪，刑法第216條、第212條之行使特種文書罪及刑法第\n    339條第1項之詐欺取財罪、同條第2項詐欺得利罪。被告與\n    同案被告李明信（另由檢察官為緩起訴處分）就前述犯行，\n    有犯意聯絡及行為分擔，為共同正犯。被告於取得被害人乙\n    ○○之身分證、健保卡等證件影本後，變造乙○○之身分證\n    父母欄，再由同案被告李明信在申請書申請人簽章欄內偽造\n    「乙○○」署名1枚，並在該申請書上各欄位填載乙○○之\n    基本資料而偽造該申請書，繼而持以申請行動電話門號而行\n    使之，其中偽造署名係偽造私文書之部分行為，而偽造私文\n    書及變造特種文書之低度行為復為行使偽造私文書及行使變\n    造特種文書之高度行為所吸收，均不另論罪。被告以一個申\n    請行為同時觸犯行使偽造私文書罪、詐欺取財及詐欺得利罪\n    ，為想像競合犯，應從較重之行使偽造私文書罪論處。爰審\n    酌：被告之前科素行，於取得被害人之證件影本後，明知未\n    經被害人同意，竟變造被害人身分證影本且冒名申辦行動電\n    話門號，並詐得手機1支、SIM卡1張、補助費新台幣（下同\n    ）7000元及通話費利益1780元，造成被害人乙○○及威寶電\n    信股份有限公司之損害及該電信公司對於門號使用人之管理\n    正確。惟被告犯罪後，於偵查中坦承全部犯行，並已由同案\n    被告李明信賠償威寶電信股份有限公司8780元（偵查卷第42\n    頁至44頁），犯後態度尚可。且被告因貪圖小利，致為本件\n    犯行等一切情狀，量處有期徒刑3月，並諭知易科罰金之折\n    算標準。至於由共同被告李明信在98年3月28日門號申請書\n    申請人簽章欄內偽造「乙○○」之署名1枚，雖未扣案，但\n    無證據證明已滅失，依刑法第219條規定，不問屬於被告與\n    否，均應宣告沒收。至於被告所偽造之門號申請書，因已交\n    付威寶電信股份有限公司行使，而非被告所有之物，爰不為\n    沒收之諭知。\n三、適用法條：刑事訴訟法第449條第1項前段、第3項、第450條\n    第1項、第454條第2項，刑法第28條、第216條、第210條、\n    第212條、第339條第1項、第2項、第55條、第41條第1項前\n    段、第219條，刑法施行法第1條之1，逕以簡易判決處刑如\n    主文。\n如不服本判決，應於收受判決正本送達之翌日起10日內向本庭提\n出上訴狀，上訴於本院合議庭（須附繕本）。",
    "reason": "一、本件犯罪事實除將「基於共同行使偽造文書及不法所有之犯\n    意聯絡」補充為「基於共同行使偽造、變造文書及意圖為自\n    己不法所有之犯意聯絡」外，其餘犯罪事實及證據均引用檢\n    察官聲請簡易判決處刑書之記載（如附件所示）。\n二、核被告甲○○所為，係犯刑法第216條、第210條行使偽造私\n    文書罪，刑法第216條、第212條之行使特種文書罪及刑法第\n    339條第1項之詐欺取財罪、同條第2項詐欺得利罪。被告與\n    同案被告李明信（另由檢察官為緩起訴處分）就前述犯行，\n    有犯意聯絡及行為分擔，為共同正犯。被告於取得被害人乙\n    ○○之身分證、健保卡等證件影本後，變造乙○○之身分證\n    父母欄，再由同案被告李明信在申請書申請人簽章欄內偽造\n    「乙○○」署名1枚，並在該申請書上各欄位填載乙○○之\n    基本資料而偽造該申請書，繼而持以申請行動電話門號而行\n    使之，其中偽造署名係偽造私文書之部分行為，而偽造私文\n    書及變造特種文書之低度行為復為行使偽造私文書及行使變\n    造特種文書之高度行為所吸收，均不另論罪。被告以一個申\n    請行為同時觸犯行使偽造私文書罪、詐欺取財及詐欺得利罪\n    ，為想像競合犯，應從較重之行使偽造私文書罪論處。爰審\n    酌：被告之前科素行，於取得被害人之證件影本後，明知未\n    經被害人同意，竟變造被害人身分證影本且冒名申辦行動電\n    話門號，並詐得手機1支、SIM卡1張、補助費新台幣（下同\n    ）7000元及通話費利益1780元，造成被害人乙○○及威寶電\n    信股份有限公司之損害及該電信公司對於門號使用人之管理\n    正確。惟被告犯罪後，於偵查中坦承全部犯行，並已由同案\n    被告李明信賠償威寶電信股份有限公司8780元（偵查卷第42\n    頁至44頁），犯後態度尚可。且被告因貪圖小利，致為本件\n    犯行等一切情狀，量處有期徒刑3月，並諭知易科罰金之折\n    算標準。至於由共同被告李明信在98年3月28日門號申請書\n    申請人簽章欄內偽造「乙○○」之署名1枚，雖未扣案，但\n    無證據證明已滅失，依刑法第219條規定，不問屬於被告與\n    否，均應宣告沒收。至於被告所偽造之門號申請書，因已交\n    付威寶電信股份有限公司行使，而非被告所有之物，爰不為\n    沒收之諭知。\n三、適用法條：刑事訴訟法第449條第1項前段、第3項、第450條\n    第1項、第454條第2項，刑法第28條、第216條、第210條、\n    第212條、第339條第1項、第2項、第55條、第41條第1項前\n    段、第219條，刑法施行法第1條之1，逕以簡易判決處刑如\n    主文。\n如不服本判決，應於收受判決正本送達之翌日起10日內向本庭提\n出上訴狀，上訴於本院合議庭（須附繕本）。"
  },
  "characters": {
    "judges": [
      "蔡坤湖"
    ],
    "prosecutors": [

    ],
    "lawyers": [

    ],
    "clerks": [
      "林妙穗"
    ],
    "plaintiffs": [

    ],
    "defendants": [
      "甲○○",
      "甲○○  男  35歲（民國○○年○○月○○日生）"
    ],
    "prosecutor_office": [
      "臺灣臺北地方法院檢察署檢察官"
    ],
    "creditors": [

    ],
    "debtors": [

    ],
    "judicial_associate_officer": [

    ]
  },
  "adjudged_at": "2010-01-05",
  "created_at": "2016-01-05 15:14:12",
  "updated_at": "2016-01-05 15:14:12"
}