{
  "identify": "TPD-99-除-924-20100512-1",
  "court": {
    "name": "臺灣臺北地方法院",
    "code": "TPD"
  },
  "division": {
    "name": "民事",
    "code": "V"
  },
  "year": 99,
  "word": "除",
  "number": "924",
  "jcheck": "1",
  "reason": "除權判決",
  "content": "臺灣臺北地方法院民事判決               99年度除字第924號\n聲  請  人  貝斯特國際貿易有限公司\n法定代理人  甲○○\n代  理  人  乙○○\n上列聲請人聲請除權判決事件，本院判決如下：\n    主  文\n如附表所示之證券無效。\n訴訟費用由聲請人負擔。\n    理  由\n一、上開證券，經本院以98年度司催字第2798號公示催告。\n二、所定申報權利期間，已於民國99年2月26日屆滿，迄今無人\n    申報權利。\n三、依民事訴訟法第564條第1項，判決如主文。\n中    華    民    國    99    年     5    月    12    日\n                  民事第一庭        法  官  熊志強\n本判決不得上訴。\n以上正本證明係照原本作成。\n中    華    民    國    99    年     5    月    12    日\n                                    書記官  謝盈敏\n┌─────────────────────────────────────────┐\n│附表：                                                           99年度除字第924號│\n├──┬─────────┬─────────┬──────┬─────┬─────┤\n│編號│ 發    票    人   │  付    款    人  │發  票  日  │ 票面金額 │支票號碼  │\n│    │                  │                  │            │（新台幣）│          │\n├──┼─────────┼─────────┼──────┼─────┼─────┤\n│001 │台北市牙醫師公會  │安泰商業銀行松江分│98年4月27日 │21,000元  │AQ0000000 │\n│    │陳彥廷            │行                │            │          │          │\n└──┴─────────┴─────────┴──────┴─────┴─────┘",
  "structure": {
    "main": "如附表所示之證券無效。\n訴訟費用由聲請人負擔。",
    "reason": "一、上開證券，經本院以98年度司催字第2798號公示催告。\n二、所定申報權利期間，已於民國99年2月26日屆滿，迄今無人\n    申報權利。\n三、依民事訴訟法第564條第1項，判決如主文。"
  },
  "characters": {
    "judges": [
      "熊志強"
    ],
    "prosecutors": [

    ],
    "lawyers": [

    ],
    "clerks": [
      "謝盈敏"
    ],
    "plaintiffs": [

    ],
    "defendants": [

    ],
    "prosecutor_office": [
      "貝斯特國際貿易有限公司"
    ],
    "creditors": [

    ],
    "debtors": [

    ],
    "judicial_associate_officer": [

    ]
  },
  "adjudged_at": "2010-05-12",
  "created_at": "2016-01-05 12:10:09",
  "updated_at": "2016-01-05 12:10:09"
}