{
  "identify": "TPD-98-交訴-111-20100105-1",
  "court": {
    "name": "臺灣臺北地方法院",
    "code": "TPD"
  },
  "division": {
    "name": "刑事",
    "code": "M"
  },
  "year": 98,
  "word": "交訴",
  "number": "111",
  "jcheck": "1",
  "reason": "公共危險等",
  "content": "臺灣臺北地方法院刑事裁定             98年度交訴字第111號\n公  訴  人  臺灣臺北地方法院檢察署檢察官\n上  訴  人\n即  被  告  甲○○\n上列上訴人因公共危險等案件，不服本院中華民國九十八年十月\n三十日第一審判決，提起上訴，本院裁定如下：\n    主  文\n上訴人甲○○應於上訴期間屆滿後二十日內補正敘述具體上訴理\n由。\n    理  由\n一、按刑事訴訟法第三百六十一條規定：「不服地方法院之第一\n    審判決而上訴者，應向管轄第二審之高等法院為之。上訴書\n    狀應敘述具體理由。上訴書狀未敘述上訴理由者，應於上訴\n    期間屆滿後二十日內補提理由書於原審法院。逾期未補提者\n    ，原審法院應定期間先命補正。」又同法第三百六十二條復\n    規定：「原審法院認為上訴不合法律上之程式或法律上不應\n    准許或其上訴權已經喪失者，應以裁定駁回之。但其不合法\n    律上之程式可補正者，應定期間先命補正。」合先敘明。\n二、查本件上訴人即被告甲○○不服本院民國九十八年十月三十\n    日九十八年度交訴字第一一一號第一審判決，於同年十一月\n    十三日提起上訴，惟上訴狀內並未敘述具體理由，有該上訴\n    狀附卷可稽，爰依刑事訴訟法第三百六十一條第二項之規定\n    ，裁定如主文所示。\n中    華    民    國    99    年    1     月    5     日\n                  刑事第八庭    審判長法  官  林鳳珠\n                                      法  官  陳芃宇\n                                      法  官  詹慶堂\n以上正本證明與原本無異。\n如不服本裁定，應於裁定送達後5日內向本院提出抗告狀。\n                                      書記官  蔡易霖\n中    華    民    國    99    年    1     月    5     日",
  "structure": {
    "main": "上訴人甲○○應於上訴期間屆滿後二十日內補正敘述具體上訴理\n由。",
    "reason": "一、按刑事訴訟法第三百六十一條規定：「不服地方法院之第一\n    審判決而上訴者，應向管轄第二審之高等法院為之。上訴書\n    狀應敘述具體理由。上訴書狀未敘述上訴理由者，應於上訴\n    期間屆滿後二十日內補提理由書於原審法院。逾期未補提者\n    ，原審法院應定期間先命補正。」又同法第三百六十二條復\n    規定：「原審法院認為上訴不合法律上之程式或法律上不應\n    准許或其上訴權已經喪失者，應以裁定駁回之。但其不合法\n    律上之程式可補正者，應定期間先命補正。」合先敘明。\n二、查本件上訴人即被告甲○○不服本院民國九十八年十月三十\n    日九十八年度交訴字第一一一號第一審判決，於同年十一月\n    十三日提起上訴，惟上訴狀內並未敘述具體理由，有該上訴\n    狀附卷可稽，爰依刑事訴訟法第三百六十一條第二項之規定\n    ，裁定如主文所示。"
  },
  "characters": {
    "judges": [
      "林鳳珠",
      "陳芃宇",
      "詹慶堂"
    ],
    "prosecutors": [

    ],
    "lawyers": [

    ],
    "clerks": [
      "蔡易霖"
    ],
    "plaintiffs": [

    ],
    "defendants": [
      "甲"
    ],
    "prosecutor_office": [
      "臺灣臺北地方法院檢察署檢察官"
    ],
    "creditors": [

    ],
    "debtors": [

    ],
    "judicial_associate_officer": [

    ]
  },
  "adjudged_at": "2010-01-05",
  "created_at": "2016-01-05 15:11:50",
  "updated_at": "2016-01-05 15:11:50"
}