{
  "identify": "TPD-99-簡-28-20100105-1",
  "court": {
    "name": "臺灣臺北地方法院",
    "code": "TPD"
  },
  "division": {
    "name": "刑事",
    "code": "M"
  },
  "year": 99,
  "word": "簡",
  "number": "28",
  "jcheck": "1",
  "reason": "詐欺",
  "content": "臺灣臺北地方法院刑事簡易判決            99年度簡字第28號\n聲  請  人  臺灣臺北地方法院檢察署檢察官\n被      告  乙○○\n上列被告因詐欺案件，經檢察官聲請以簡易判決處刑（98年度偵\n字第24938 號），本院受理後（案號：98年度簡字第4897號），\n認不宜逕以簡易判決處刑，經改依通常程序審理（原案號：98年\n度易字第3594號），而被告自白犯罪，本院合議庭認宜以簡易判\n決處刑，裁定逕以簡易判決處刑，判決如下︰\n    主      文\n乙○○幫助共同意圖為自己不法之所有，以詐術使人將本人之物\n交付，處拘役伍拾日，如易科罰金，以新台幣壹仟元折算壹日。\n緩刑貳年，並應向被害人甲○○支付如附表所示之金額。\n    事實及理由\n一、本件犯罪事實、證據及所引應適用之法條，除犯罪事實部分\n    應記載為：「乙○○依其社會經驗，雖預見其提供自己或他\n    人之金融帳戶與第三人使用，常與財產犯罪密切相關，極可\n    能被犯罪集團所使用以遂行詐欺取財而達收取贓款，並避免\n    遭到檢警單位追查之目的，仍不違背其本意，基於幫助詐欺\n    之未必故意，於民國98年8 月20日15時許，在臺北縣板橋市\n    板橋車站，將其所申辦之中華信託商業銀行城北分行帳戶（\n    帳號0000000000000000號）之提款卡、密碼交給姓名年籍不\n    詳之人。嗣上開帳戶即輾轉流至某詐騙集團（無證據證明集\n    團成員中有兒童或少年，依罪疑有利於被告之原則，應認詐\n    騙集團成員均屬18歲以上之人）手中，該詐騙集團成員即基\n    於意圖為自己不法所有之犯意聯絡，由某成員於98年8 月21\n    日17時15分許撥打電話給甲○○，佯稱係快樂購客服人員，\n    因甲○○多刷一筆分期付款金額，將把資料傳真至聯邦銀行\n    云云，甲○○旋即接獲該集團另一成員之電話，佯稱係聯邦\n    銀行專員，甲○○需至自動櫃員機查詢餘額，看有無遭到扣\n    款，並聽其指示取消分期云云，致甲○○陷於錯誤，於98年\n    8月22日凌晨零時22分至25分間，接續匯款新台幣【下同】3\n    萬元、3萬元、3萬元、1 萬元至前開乙○○帳戶內，嗣因甲\n    ○○察覺有異，始知受騙」；證據部分應加列「被告乙○○\n    於本院行準備程序時坦承犯行」外，餘均引用檢察官聲請簡\n    易判決處刑書之記載（如附件）。\n二、被告乙○○前未曾因故意犯罪受有期徒刑以上刑之宣告，此\n    有臺灣高等法院被告前案紀錄表可憑，本院考量被告因一時\n    失慮而觸犯刑章，犯後尚知所悔悟，並有意分期賠償被害人\n    甲○○之損失，被告經此教訓，應已知警惕，而無再犯之虞\n    ，惟本院為期被告能確實按期給付，免僥倖利用分期之利，\n    得法院寬判，於給付數期款後即不再履行，故依刑法第74條\n    第1項第1款、第2項第3款之規定，認被告所宣告之刑以暫不\n    執行為適當，併諭知緩刑2 年，並命被告應依如附表所示之\n    支付方式，向被害人甲○○支付如附表所示之金額。此部分\n    依刑法第74條第4 項規定得為民事強制執行名義，又依同法\n    第75條之1 第1項第4款規定，受緩刑之宣告而違反上開本院\n    所定負擔情節重大，足認原宣告之緩刑難收其預期效果，而\n    有執行刑罰之必要者，得撤銷其宣告，併為說明。\n三、依刑事訴訟法第449條第1 項前段、第3項、第454條第2項，\n    刑法第339條第1項、第30條第2項、第41條第1項前段、第74\n    條第1項第1款、第2項第3款，刑法施行法第1條之1，逕以簡\n    易判決處如主文所示之刑。\n四、如不服本判決，得於判決書送達之翌日起10日內，以書狀敘\n    述理由，向本庭提出上訴。\n中    華    民    國    99    年    1     月    5     日\n                  刑事第四庭    法  官  李明益\n以上正本證明與原本無異。\n如不服本判決應於收受送達後10日內向本院提出上訴書狀，並應\n敘述具體理由；其未敘述上訴理由者，應於上訴期間屆滿後20日\n內向本院補提理由書（均須按他造當事人之人數附繕本）「切勿\n逕送上級法院」。告訴人或被害人如對於本判決不服者，應具備\n理由請求檢察官上訴，其上訴期間之計算係以檢察官收受判決正\n本之日期為準。\n                                書記官  劉穗筠\n中    華    民    國    99    年    1     月    5     日\n附錄本案論罪科刑法條\n中華民國刑法第339條\n（普通詐欺罪）\n意圖為自己或第三人不法之所有，以詐術使人將本人或第三人之\n物交付者，處 5 年以下有期徒刑、拘役或科或併科 1 千元以下\n罰金。\n以前項方法得財產上不法之利益或使第三人得之者，亦同。\n前二項之未遂犯罰之。\n附表\n┌────┬─────────┬────────────┐\n│被 害 人│應 支 付 之 金 額 │支     付     方     式 │\n│        │（新    台    幣）│                        │\n├────┼─────────┼────────────┤\n│甲○○  │100,000元         │自民國99年1 月20日起至99│\n│        │                  │年10月20日止分10期，於每│\n│        │                  │月20日給付一期款10,000元│\n│        │                  │，至全部清償完畢止，如有│\n│        │                  │一期未履行，視為全部到期│\n│        │                  │。                      │\n└────┴─────────┴────────────┘\n臺灣臺北地方法院檢察署檢察官聲請簡易判決處刑書\n                                     98年度偵字第24938號\n    被      告  乙○○  男  31歲（民國○○年○月○日生）\n                        住臺北市○○區○○路161巷17號\n                        國民身份證統一編號：Ｚ000000000號\n上列被告因詐欺案件，業經偵查終結，認為宜聲請以簡易判決處\n刑，茲將犯罪事實及證據並所犯法條分敘如下：\n        犯罪事實\n一、乙○○明知申請帳戶使用係輕而易舉之事，一般人無故取得\n    他人金融帳戶使用之行徑常與財產犯罪之需要密切相關，而\n    可預見該名不自行申辦帳戶之人，可能係遂行不法所有意圖\n    用以詐騙、恐嚇取財等不法財產犯罪行為，又對於提供帳戶\n    予他人使用雖無必然引發他人萌生犯罪之確信，但仍以縱若\n    有人持以犯罪亦不違反其本意，而基於幫助他人詐欺取財之\n    犯意，於民國98年8月20日下午3時許，在臺北縣板橋車站西\n    門站，將其所於之中國信託商業銀行城北分行帳號00000000\n    00000000號之提款卡、提款卡密碼，以不詳代價，交與詐欺\n    集團之成員。嗣同詐騙集團之成員間，共同基於詐欺之犯意\n    聯絡，於98年8月21日，由當中1人撥打甲○○之電話，並對\n    甲○○詐稱其為快樂購客服人員，甲○○於網路購物時，多\n    刷一筆分期付款，需至自動櫃員機取消，致甲○○陷於錯誤\n    ，依詐欺集團成員之指示，操作自動櫃員機，遂於同年月22\n    日4次分別匯款新臺幣（下同）3萬元、3萬元、3萬元及1萬\n    元至上述帳戶，並旋遭詐欺集團成員所提領，因而詐欺得手\n    。\n二、案經臺北縣政府警察局新店分局報告偵辦。\n        證據並所犯法條\n一、證據\n1、被告供述。被告辯稱係為找工作而將提款卡及密碼交予陳經\n   理所指派之外勤人員，伊後來察覺有異，於星期一辦理掛失\n   ，因中間有隔六、日等語。然經函詢中國信託商業銀行，被\n   告於98年8月25日始以電話辦理掛失，而8月25日為星期二，\n   且被告既知可以電話辦理掛失，何以未於察覺有異之際，立\n   即辦理過失，被告所辯，尚不足採。並依一般人之日常生活\n   經驗可知，應徵工作並不需要交付提款卡及密碼，而金融機\n   構之帳戶存摺等相關資料事關個人財產權益之保障，其專有\n   性甚高，除非本人或與本人親密關係者，難認有何理由可自\n   由流通使用該存摺，一般人均有妥為保管及防止他人任意使\n   用之認識，縱特殊情況偶需交付他人使用，亦必深入瞭解用\n   途及合理性，始予提供，且該等專有物品如落入不明人士手\n   中，而未加以闡明正常用途，極易被利用為與財產有關之犯\n   罪工具，此為吾人依一般生活認知所易於體察之常識。況近\n   年來新聞媒體，對於不肖犯罪集團常利用人頭帳戶，作為詐\n   騙錢財等犯罪工具，藉此逃避檢警查緝之情事，亦多所報導\n   ，政府亦大力宣導，督促民眾注意，主管機關甚至限制以提\n   款卡轉帳之金額，是交付帳戶資料予非親非故之人，該取得\n   帳戶資料之人應係為謀非正當資金進出，而隱瞞其資金流程\n   及行為人身份曝光之不法使用，幾乎已成為人盡皆知之犯罪\n   手法，被告為智識正常且具社會經驗之成年人，對此自無不\n   知之理。綜上所述，被告所辯尚難採信，本案事證明確，被\n   告犯行，應堪認定。\n2、被害人邱春英於警詢時證述遭詐欺及匯款等情。\n3、被告上述帳戶之交易明細。\n4、客戶交易明細表影本4紙。\n二、被告交付本案帳戶不詳年籍之成年人，雖可預見其人與其他\n    集團成員係從事詐欺等不法行為且縱如此亦不違背本意，然\n    此僅係對該集團之詐欺犯行提供助力，並非有何共同正犯之\n    犯意聯絡及行為分擔，而提供金融帳戶予他人之行為亦非屬\n    刑法詐欺罪構成要件之行為，其既以幫助他人犯罪之意思而\n    參與犯罪構成要件以外之行為，是核被告所為，係犯刑法第\n    30條第1項前段、第339條第1項之幫助詐欺取財之罪嫌。被\n    告之犯行係屬幫助犯，請依刑法第30條第2項之規定減輕其\n    刑。\n三、至報告意指另謂被告上揭犯行涉嫌刑法第339條第1項之詐欺\n    取財罪之罪嫌。惟查，本件並無證據足認被告與上開犯罪集\n    團成員間有犯意聯絡及行為分擔之共同正犯關係。而被告提\n    供他人之帳戶予不明人土使用之行為，係詐欺取財罪之構成\n    要件以外行為，故尚難以刑法詐欺取財罪相繩。報告意旨容\n    有誤會，併此敘明。\n四、依刑事訴訟法第451條第1項聲請簡易判決處刑。\n    此    致\n臺灣臺北地方法院\n中    華    民    國    98    年    11    月    30    日\n                        檢  察  官   王  惟  琪\n本件正本證明與原本無異\n中    華    民    國    98    年    12    月    8     日\n                        書  記  官\n本件係依刑事訴訟法簡易程式辦理，法院簡易庭得不傳喚被告、\n輔佐人、告訴人、告發人等出庭即以簡易判決處刑；被告、被害\n人、告訴人等對告訴乃論案件如已達成民事和解而要撤回告訴或\n對非告訴乃論案件認有受傳喚到庭陳述意見之必要時，請即另以\n書狀向簡易庭陳述或請求傳訊。\n附錄本案所犯法條全文\n刑法第339條第1項（普通詐欺罪）\n意圖為自己或第三人不法之所有，以詐術使人將本人或第三人之\n物交付者，處5年以下有期徒刑、拘役或科或併科1千元以下罰金\n。\n刑法第30條第1項（幫助犯及其處罰）\n幫助他人實行犯罪行為者，為幫助犯。雖他人不知幫助之情者，\n亦同。",
  "structure": {
    "main": "乙○○幫助共同意圖為自己不法之所有，以詐術使人將本人之物\n交付，處拘役伍拾日，如易科罰金，以新台幣壹仟元折算壹日。\n緩刑貳年，並應向被害人甲○○支付如附表所示之金額。",
    "fact": "一、本件犯罪事實、證據及所引應適用之法條，除犯罪事實部分\n    應記載為：「乙○○依其社會經驗，雖預見其提供自己或他\n    人之金融帳戶與第三人使用，常與財產犯罪密切相關，極可\n    能被犯罪集團所使用以遂行詐欺取財而達收取贓款，並避免\n    遭到檢警單位追查之目的，仍不違背其本意，基於幫助詐欺\n    之未必故意，於民國98年8 月20日15時許，在臺北縣板橋市\n    板橋車站，將其所申辦之中華信託商業銀行城北分行帳戶（\n    帳號0000000000000000號）之提款卡、密碼交給姓名年籍不\n    詳之人。嗣上開帳戶即輾轉流至某詐騙集團（無證據證明集\n    團成員中有兒童或少年，依罪疑有利於被告之原則，應認詐\n    騙集團成員均屬18歲以上之人）手中，該詐騙集團成員即基\n    於意圖為自己不法所有之犯意聯絡，由某成員於98年8 月21\n    日17時15分許撥打電話給甲○○，佯稱係快樂購客服人員，\n    因甲○○多刷一筆分期付款金額，將把資料傳真至聯邦銀行\n    云云，甲○○旋即接獲該集團另一成員之電話，佯稱係聯邦\n    銀行專員，甲○○需至自動櫃員機查詢餘額，看有無遭到扣\n    款，並聽其指示取消分期云云，致甲○○陷於錯誤，於98年\n    8月22日凌晨零時22分至25分間，接續匯款新台幣【下同】3\n    萬元、3萬元、3萬元、1 萬元至前開乙○○帳戶內，嗣因甲\n    ○○察覺有異，始知受騙」；證據部分應加列「被告乙○○\n    於本院行準備程序時坦承犯行」外，餘均引用檢察官聲請簡\n    易判決處刑書之記載（如附件）。\n二、被告乙○○前未曾因故意犯罪受有期徒刑以上刑之宣告，此\n    有臺灣高等法院被告前案紀錄表可憑，本院考量被告因一時\n    失慮而觸犯刑章，犯後尚知所悔悟，並有意分期賠償被害人\n    甲○○之損失，被告經此教訓，應已知警惕，而無再犯之虞\n    ，惟本院為期被告能確實按期給付，免僥倖利用分期之利，\n    得法院寬判，於給付數期款後即不再履行，故依刑法第74條\n    第1項第1款、第2項第3款之規定，認被告所宣告之刑以暫不\n    執行為適當，併諭知緩刑2 年，並命被告應依如附表所示之\n    支付方式，向被害人甲○○支付如附表所示之金額。此部分\n    依刑法第74條第4 項規定得為民事強制執行名義，又依同法\n    第75條之1 第1項第4款規定，受緩刑之宣告而違反上開本院\n    所定負擔情節重大，足認原宣告之緩刑難收其預期效果，而\n    有執行刑罰之必要者，得撤銷其宣告，併為說明。\n三、依刑事訴訟法第449條第1 項前段、第3項、第454條第2項，\n    刑法第339條第1項、第30條第2項、第41條第1項前段、第74\n    條第1項第1款、第2項第3款，刑法施行法第1條之1，逕以簡\n    易判決處如主文所示之刑。\n四、如不服本判決，得於判決書送達之翌日起10日內，以書狀敘\n    述理由，向本庭提出上訴。",
    "reason": "一、本件犯罪事實、證據及所引應適用之法條，除犯罪事實部分\n    應記載為：「乙○○依其社會經驗，雖預見其提供自己或他\n    人之金融帳戶與第三人使用，常與財產犯罪密切相關，極可\n    能被犯罪集團所使用以遂行詐欺取財而達收取贓款，並避免\n    遭到檢警單位追查之目的，仍不違背其本意，基於幫助詐欺\n    之未必故意，於民國98年8 月20日15時許，在臺北縣板橋市\n    板橋車站，將其所申辦之中華信託商業銀行城北分行帳戶（\n    帳號0000000000000000號）之提款卡、密碼交給姓名年籍不\n    詳之人。嗣上開帳戶即輾轉流至某詐騙集團（無證據證明集\n    團成員中有兒童或少年，依罪疑有利於被告之原則，應認詐\n    騙集團成員均屬18歲以上之人）手中，該詐騙集團成員即基\n    於意圖為自己不法所有之犯意聯絡，由某成員於98年8 月21\n    日17時15分許撥打電話給甲○○，佯稱係快樂購客服人員，\n    因甲○○多刷一筆分期付款金額，將把資料傳真至聯邦銀行\n    云云，甲○○旋即接獲該集團另一成員之電話，佯稱係聯邦\n    銀行專員，甲○○需至自動櫃員機查詢餘額，看有無遭到扣\n    款，並聽其指示取消分期云云，致甲○○陷於錯誤，於98年\n    8月22日凌晨零時22分至25分間，接續匯款新台幣【下同】3\n    萬元、3萬元、3萬元、1 萬元至前開乙○○帳戶內，嗣因甲\n    ○○察覺有異，始知受騙」；證據部分應加列「被告乙○○\n    於本院行準備程序時坦承犯行」外，餘均引用檢察官聲請簡\n    易判決處刑書之記載（如附件）。\n二、被告乙○○前未曾因故意犯罪受有期徒刑以上刑之宣告，此\n    有臺灣高等法院被告前案紀錄表可憑，本院考量被告因一時\n    失慮而觸犯刑章，犯後尚知所悔悟，並有意分期賠償被害人\n    甲○○之損失，被告經此教訓，應已知警惕，而無再犯之虞\n    ，惟本院為期被告能確實按期給付，免僥倖利用分期之利，\n    得法院寬判，於給付數期款後即不再履行，故依刑法第74條\n    第1項第1款、第2項第3款之規定，認被告所宣告之刑以暫不\n    執行為適當，併諭知緩刑2 年，並命被告應依如附表所示之\n    支付方式，向被害人甲○○支付如附表所示之金額。此部分\n    依刑法第74條第4 項規定得為民事強制執行名義，又依同法\n    第75條之1 第1項第4款規定，受緩刑之宣告而違反上開本院\n    所定負擔情節重大，足認原宣告之緩刑難收其預期效果，而\n    有執行刑罰之必要者，得撤銷其宣告，併為說明。\n三、依刑事訴訟法第449條第1 項前段、第3項、第454條第2項，\n    刑法第339條第1項、第30條第2項、第41條第1項前段、第74\n    條第1項第1款、第2項第3款，刑法施行法第1條之1，逕以簡\n    易判決處如主文所示之刑。\n四、如不服本判決，得於判決書送達之翌日起10日內，以書狀敘\n    述理由，向本庭提出上訴。"
  },
  "characters": {
    "judges": [
      "李明益"
    ],
    "prosecutors": [

    ],
    "lawyers": [

    ],
    "clerks": [
      "劉穗筠"
    ],
    "plaintiffs": [

    ],
    "defendants": [
      "乙○○",
      "乙○○  男  31歲（民國○○年○月○日生）"
    ],
    "prosecutor_office": [
      "臺灣臺北地方法院檢察署檢察官"
    ],
    "creditors": [

    ],
    "debtors": [

    ],
    "judicial_associate_officer": [

    ]
  },
  "adjudged_at": "2010-01-05",
  "created_at": "2016-01-05 15:13:42",
  "updated_at": "2016-01-05 15:13:42"
}