{
  "identify": "TPD-99-金簡-1-20100105-1",
  "court": {
    "name": "臺灣臺北地方法院",
    "code": "TPD"
  },
  "division": {
    "name": "刑事",
    "code": "M"
  },
  "year": 99,
  "word": "金簡",
  "number": "1",
  "jcheck": "1",
  "reason": "違反期貨交易法等",
  "content": "臺灣臺北地方法院刑事簡易判決    99年度金簡字第1號\n公  訴  人  臺灣臺北地方法院檢察署檢察官\n被      告  己○○\n選任辯護人  曾允斌律師\n            林文鵬律師\n被      告  丙○○\n選任辯護人  陳德峰律師\n            林奕秀律師\n            周建才律師\n上列被告等因違反期貨交易法等案件，經檢察官提起公訴（97年\n度偵字第26253 號），經本院訊問後被告等均自白犯罪，認為宜\n以簡易判決處刑，逕以簡易判決處刑如下：\n    主      文\n己○○未經許可，擅自經營期貨顧問事業，處有期徒刑貳年，併\n科罰金新臺幣貳佰伍拾萬元，罰金如易服勞役，以罰金總額與壹\n年之日數比例折算。緩刑伍年，並應向公庫支付新台幣壹佰伍拾\n萬元。\n丙○○未經許可，擅自經營期貨顧問事業，處有期徒刑拾月，併\n科罰金新臺幣貳佰萬元，罰金如易服勞役，以罰金總額與壹年之\n日數比例折算。緩刑參年，並應於本案丙○○部分判決確定後壹\n年內，向公庫支付新臺幣伍拾萬元。\n    事實及理由\n一、按刑事訴訟法第449 條第1 項規定之案件，檢察官依通常程\n    序起訴，被告自白犯罪，認為宜以簡易判決處刑者，得不經\n    通常審判程序，逕以簡易判決處刑；又依此簡易判決所科之\n    刑以宣告緩刑、得易科罰金之有期徒刑及拘役或罰金為限。\n    刑事訴訟法第449 條第2 項、第3 項分別定有明文。查本案\n    被告己○○、丙○○2 人雖經公訴人依通常程序起訴，本院\n    依通常程序審理（本院98年度金訴字第37號），經本院訊問\n    被告2 人後，認本案被告2 人合於以簡易判決處刑之要件，\n    依前述刑事訴訟法之規定，得不經通常審判程序，對被告2\n    人逕以簡易判決處刑，本件爰依簡易判決程序審理，合先敘\n    明。\n二、本件犯罪事實及證據均引用檢察官起訴書之記載（如附件）\n    ，另增列被告2 人於審理中之自白為證據。\n三、論罪科刑部分：\n  (一)核被告己○○所為，係犯期貨交易法第112 條第5 款之未經\n    許可經營期貨顧問事業罪、證券投資信託及顧問法第107 條\n    第1 款之未經許可經營證券投資顧問業務罪；被告己○○所\n    為，係犯期貨交易法第112 條第5 款之未經許可經營期貨顧\n    問事業罪、證券投資信託及顧問法第107 條第1 款之未經許\n    可經營證券投資顧問業務罪及刑法第339 條第1 項之詐欺罪\n    。\n  (二)按在犯罪構成要件中，本即預定有數個同種類之行為將反覆\n    實行，而具有職業性、營業性或收集性等具有重複之特質。\n    此等反覆實行之犯罪行為，於自然意義上雖係數行為，但依\n    社會通念應為一總括之評價，故在法律評價上，則應將之視\n    為包括一罪。本案被告2 人所犯期貨交易法第112 條第5 款\n    之未經許可經營期貨顧問事業罪、證券投資信託及顧問法第\n    107 條第1 款之未經許可經營證券投資顧問業務罪，均係以\n    未經許可而持續從事一定業務之經營為其犯罪構成要件，本\n    質上具有預定數個同種類行為將反覆實行之犯罪，且本案被\n    告2 人又係在密切接近之一定時間及空間內反覆為之，均屬\n    集合犯，應均為包括一罪。\n  (三)復按刑法上一行為而觸犯數罪名之想像競合犯存在之目的，\n    在於避免對於同一不法要素予以過度評價，其所謂「同一行\n    為」係指所實行者為完全或局部同一之行為而言。因此刑法\n    修正刪除牽連犯之規定後，於修正前原認屬於方法目的或原\n    因結果之不同犯罪，其間果有實行之行為完全或局部同一之\n    情形，應得依想像競合犯論擬（最高法院97年度台上字第\n    3494號判決意旨參照）。被告己○○所犯上開2 罪名、被告\n    丙○○所犯上開3 罪名，其間實行之行為均有局部同一之情\n    形，均應依刑法第55條想像競合犯之規定，從一重之未經許\n    可經營期貨顧問事業罪處斷。起訴書所犯法條欄，就被告丙\n    ○○部分雖記載：「被告丙○○於同一時地，一行為而觸犯\n    上開二罪名，為想像競合犯，請從一重之罪處斷」，惟檢察\n    官於本院審理時，亦已當庭更正為：「被告丙○○於同一時\n    地，一行為而觸犯上開數罪名，為想像競合犯，請從一重之\n    罪處斷」（見本院98年度金訴字第37號卷第72頁反面），在\n    此敘明。\n  (四)爰審酌被告己○○前於79年間因違反醫師法案件，經臺灣高\n    等法院判處有期徒刑7 月，緩刑4 年確定，緩刑期滿後未再\n    有其他刑事犯罪前案紀錄，被告丙○○則未有其他刑案紀錄\n    ，此有被告2 人之臺灣高等法院被告前案紀錄表在卷可按，\n    足認被告2 人素行尚可，而被告2 人未經主管機關許可而擅\n    自從事期貨顧問事業及證券投資顧問業務，影響國家對於金\n    融交易秩序之管理，對於社會大眾投資理財有所影響，被告\n    己○○犯案期間長達約8 年，被告丙○○犯案期間則達1 年\n    3 月，惟念及被告2 人於本院審理時皆業已自白犯行，深表\n    悔悟，另被告丙○○於本院審理期間已賠償被害人丁○○、\n    庚○○、乙○○、甲○○、戊○○共新臺幣（下同）51萬6\n    千元，此有被告提出之和解書5 紙在卷可稽，且考量被告2\n    人之犯罪動機、犯罪手段等一切情狀，分別量處如主文所示\n    之刑，併就被告2 人所處罰金部分，各諭知罰金如易服勞役\n    折算之標準，以示警惕。末查，被告己○○前曾於79年間因\n    違反醫師法案件經判處有期徒刑7 月，緩刑4 年確定，緩刑\n    期滿，緩刑之宣告未經撤銷，其刑之宣告已失其效力，此外\n    ，被告2 人均未曾因故意犯罪受有期徒刑以上刑之宣告，此\n    有被告2 人之臺灣高等法院被告前案紀錄表在卷可稽，被告\n    2 人因短於思慮，致罹刑章，犯後均尚知所悔悟，其等經此\n    偵審程序，當應已知警惕，信無再犯之虞，被告2 人所宣告\n    之刑以暫不執行為適當，惟為確實督促被告2 人保持善良品\n    行及正確法律觀念，爰依刑法第74條第1 項第1 款、第2 項\n    第4 款之規定，分別併諭知緩刑期間及應向公庫支付之金額\n    如主文所示，以啟自新。\n  (五)被告2 人應向公庫支付如主文所示之金額，此部分依刑法第\n    74條第3 項規定得為民事強制執行名義，又依同法第75條之\n    1 第1 項第4 款規定，受緩刑之宣告而違反上開本院所定負\n    擔情節重大，足認原宣告之緩刑難收其預期效果，而有執行\n    刑罰之必要者，得撤銷其宣告，在此敘明。\n四、據上論斷，依刑事訴訟法第449 條第2 項、第3 項、第454\n    條第2 項，期貨交易法第112 條第5 款，證券投資信託及顧\n    問法第107 條第1 款，刑法第11條前段、第339 條第1 項、\n    第55條、第42條第3 項、第5 項、第74條第1 項第1 款、第\n    2 項第4 款，刑法施行法第1 條之1 ，逕以簡易判決處刑如\n    主文。\n五、如不服本判決，得於判決書送達之翌日起10日內，以書狀敘\n    述理由（須附繕本），向本院合議庭提出上訴。\n中    華    民    國    99    年    1     月    5     日\n                  刑事第二庭    法  官  江俊彥\n以上正本證明與原本無異。\n                                書記官  王聖婷\n中    華    民    國    99    年    1     月    5     日\n附錄本判決論罪科刑依據之法條：\n證券投資信託及顧問法第107條\n有下列情事之一者，處5 年以下有期徒刑，併科新臺幣1 百萬元\n以上5 千萬元以下罰金：\n一、未經主管機關許可，經營證券投資信託業務、證券投資顧問\n    業務、全權委託投資業務或其他應經主管機關核准之業務。\n二、違反第16條第1 項規定，在中華民國境內從事或代理募集、\n    銷售境外基金。\n期貨交易法第112條\n有下列情事之一者，處7 年以下有期徒刑，得併科新臺幣3 百萬\n元以下罰金：\n一、未經許可，擅自經營期貨交易所或期貨交易所業務者。\n二、未經許可，擅自經營期貨結算機構者。\n三  違反第 56 條第 1 項之規定者。\n四、未經許可，擅自經營槓桿交易商者。\n五、未經許可，擅自經營期貨信託事業、期貨經理事業、期貨顧\n    問事業或其他期貨服務事業者。\n六、期貨信託事業違反第84條第1 項規定募集期貨信託基金者。\n七、違反第 106 條、第 107 條或第 108 條第 1 項之規定者。\n中華民國刑法第339條（普通詐欺罪）\n意圖為自己或第三人不法之所有，以詐術使人將本人或第三人之\n物交付者，處5年以下有期徒刑、拘役或科或併科1千元以下罰金\n。\n以前項方法得財產上不法之利益或使第三人得之者，亦同。\n前二項之未遂犯罰之。",
  "structure": {
    "main": "己○○未經許可，擅自經營期貨顧問事業，處有期徒刑貳年，併\n科罰金新臺幣貳佰伍拾萬元，罰金如易服勞役，以罰金總額與壹\n年之日數比例折算。緩刑伍年，並應向公庫支付新台幣壹佰伍拾\n萬元。\n丙○○未經許可，擅自經營期貨顧問事業，處有期徒刑拾月，併\n科罰金新臺幣貳佰萬元，罰金如易服勞役，以罰金總額與壹年之\n日數比例折算。緩刑參年，並應於本案丙○○部分判決確定後壹\n年內，向公庫支付新臺幣伍拾萬元。",
    "fact": "一、按刑事訴訟法第449 條第1 項規定之案件，檢察官依通常程\n    序起訴，被告自白犯罪，認為宜以簡易判決處刑者，得不經\n    通常審判程序，逕以簡易判決處刑；又依此簡易判決所科之\n    刑以宣告緩刑、得易科罰金之有期徒刑及拘役或罰金為限。\n    刑事訴訟法第449 條第2 項、第3 項分別定有明文。查本案\n    被告己○○、丙○○2 人雖經公訴人依通常程序起訴，本院\n    依通常程序審理（本院98年度金訴字第37號），經本院訊問\n    被告2 人後，認本案被告2 人合於以簡易判決處刑之要件，\n    依前述刑事訴訟法之規定，得不經通常審判程序，對被告2\n    人逕以簡易判決處刑，本件爰依簡易判決程序審理，合先敘\n    明。\n二、本件犯罪事實及證據均引用檢察官起訴書之記載（如附件）\n    ，另增列被告2 人於審理中之自白為證據。\n三、論罪科刑部分：\n  (一)核被告己○○所為，係犯期貨交易法第112 條第5 款之未經\n    許可經營期貨顧問事業罪、證券投資信託及顧問法第107 條\n    第1 款之未經許可經營證券投資顧問業務罪；被告己○○所\n    為，係犯期貨交易法第112 條第5 款之未經許可經營期貨顧\n    問事業罪、證券投資信託及顧問法第107 條第1 款之未經許\n    可經營證券投資顧問業務罪及刑法第339 條第1 項之詐欺罪\n    。\n  (二)按在犯罪構成要件中，本即預定有數個同種類之行為將反覆\n    實行，而具有職業性、營業性或收集性等具有重複之特質。\n    此等反覆實行之犯罪行為，於自然意義上雖係數行為，但依\n    社會通念應為一總括之評價，故在法律評價上，則應將之視\n    為包括一罪。本案被告2 人所犯期貨交易法第112 條第5 款\n    之未經許可經營期貨顧問事業罪、證券投資信託及顧問法第\n    107 條第1 款之未經許可經營證券投資顧問業務罪，均係以\n    未經許可而持續從事一定業務之經營為其犯罪構成要件，本\n    質上具有預定數個同種類行為將反覆實行之犯罪，且本案被\n    告2 人又係在密切接近之一定時間及空間內反覆為之，均屬\n    集合犯，應均為包括一罪。\n  (三)復按刑法上一行為而觸犯數罪名之想像競合犯存在之目的，\n    在於避免對於同一不法要素予以過度評價，其所謂「同一行\n    為」係指所實行者為完全或局部同一之行為而言。因此刑法\n    修正刪除牽連犯之規定後，於修正前原認屬於方法目的或原\n    因結果之不同犯罪，其間果有實行之行為完全或局部同一之\n    情形，應得依想像競合犯論擬（最高法院97年度台上字第\n    3494號判決意旨參照）。被告己○○所犯上開2 罪名、被告\n    丙○○所犯上開3 罪名，其間實行之行為均有局部同一之情\n    形，均應依刑法第55條想像競合犯之規定，從一重之未經許\n    可經營期貨顧問事業罪處斷。起訴書所犯法條欄，就被告丙\n    ○○部分雖記載：「被告丙○○於同一時地，一行為而觸犯\n    上開二罪名，為想像競合犯，請從一重之罪處斷」，惟檢察\n    官於本院審理時，亦已當庭更正為：「被告丙○○於同一時\n    地，一行為而觸犯上開數罪名，為想像競合犯，請從一重之\n    罪處斷」（見本院98年度金訴字第37號卷第72頁反面），在\n    此敘明。\n  (四)爰審酌被告己○○前於79年間因違反醫師法案件，經臺灣高\n    等法院判處有期徒刑7 月，緩刑4 年確定，緩刑期滿後未再\n    有其他刑事犯罪前案紀錄，被告丙○○則未有其他刑案紀錄\n    ，此有被告2 人之臺灣高等法院被告前案紀錄表在卷可按，\n    足認被告2 人素行尚可，而被告2 人未經主管機關許可而擅\n    自從事期貨顧問事業及證券投資顧問業務，影響國家對於金\n    融交易秩序之管理，對於社會大眾投資理財有所影響，被告\n    己○○犯案期間長達約8 年，被告丙○○犯案期間則達1 年\n    3 月，惟念及被告2 人於本院審理時皆業已自白犯行，深表\n    悔悟，另被告丙○○於本院審理期間已賠償被害人丁○○、\n    庚○○、乙○○、甲○○、戊○○共新臺幣（下同）51萬6\n    千元，此有被告提出之和解書5 紙在卷可稽，且考量被告2\n    人之犯罪動機、犯罪手段等一切情狀，分別量處如主文所示\n    之刑，併就被告2 人所處罰金部分，各諭知罰金如易服勞役\n    折算之標準，以示警惕。末查，被告己○○前曾於79年間因\n    違反醫師法案件經判處有期徒刑7 月，緩刑4 年確定，緩刑\n    期滿，緩刑之宣告未經撤銷，其刑之宣告已失其效力，此外\n    ，被告2 人均未曾因故意犯罪受有期徒刑以上刑之宣告，此\n    有被告2 人之臺灣高等法院被告前案紀錄表在卷可稽，被告\n    2 人因短於思慮，致罹刑章，犯後均尚知所悔悟，其等經此\n    偵審程序，當應已知警惕，信無再犯之虞，被告2 人所宣告\n    之刑以暫不執行為適當，惟為確實督促被告2 人保持善良品\n    行及正確法律觀念，爰依刑法第74條第1 項第1 款、第2 項\n    第4 款之規定，分別併諭知緩刑期間及應向公庫支付之金額\n    如主文所示，以啟自新。\n  (五)被告2 人應向公庫支付如主文所示之金額，此部分依刑法第\n    74條第3 項規定得為民事強制執行名義，又依同法第75條之\n    1 第1 項第4 款規定，受緩刑之宣告而違反上開本院所定負\n    擔情節重大，足認原宣告之緩刑難收其預期效果，而有執行\n    刑罰之必要者，得撤銷其宣告，在此敘明。\n四、據上論斷，依刑事訴訟法第449 條第2 項、第3 項、第454\n    條第2 項，期貨交易法第112 條第5 款，證券投資信託及顧\n    問法第107 條第1 款，刑法第11條前段、第339 條第1 項、\n    第55條、第42條第3 項、第5 項、第74條第1 項第1 款、第\n    2 項第4 款，刑法施行法第1 條之1 ，逕以簡易判決處刑如\n    主文。\n五、如不服本判決，得於判決書送達之翌日起10日內，以書狀敘\n    述理由（須附繕本），向本院合議庭提出上訴。",
    "reason": "一、按刑事訴訟法第449 條第1 項規定之案件，檢察官依通常程\n    序起訴，被告自白犯罪，認為宜以簡易判決處刑者，得不經\n    通常審判程序，逕以簡易判決處刑；又依此簡易判決所科之\n    刑以宣告緩刑、得易科罰金之有期徒刑及拘役或罰金為限。\n    刑事訴訟法第449 條第2 項、第3 項分別定有明文。查本案\n    被告己○○、丙○○2 人雖經公訴人依通常程序起訴，本院\n    依通常程序審理（本院98年度金訴字第37號），經本院訊問\n    被告2 人後，認本案被告2 人合於以簡易判決處刑之要件，\n    依前述刑事訴訟法之規定，得不經通常審判程序，對被告2\n    人逕以簡易判決處刑，本件爰依簡易判決程序審理，合先敘\n    明。\n二、本件犯罪事實及證據均引用檢察官起訴書之記載（如附件）\n    ，另增列被告2 人於審理中之自白為證據。\n三、論罪科刑部分：\n  (一)核被告己○○所為，係犯期貨交易法第112 條第5 款之未經\n    許可經營期貨顧問事業罪、證券投資信託及顧問法第107 條\n    第1 款之未經許可經營證券投資顧問業務罪；被告己○○所\n    為，係犯期貨交易法第112 條第5 款之未經許可經營期貨顧\n    問事業罪、證券投資信託及顧問法第107 條第1 款之未經許\n    可經營證券投資顧問業務罪及刑法第339 條第1 項之詐欺罪\n    。\n  (二)按在犯罪構成要件中，本即預定有數個同種類之行為將反覆\n    實行，而具有職業性、營業性或收集性等具有重複之特質。\n    此等反覆實行之犯罪行為，於自然意義上雖係數行為，但依\n    社會通念應為一總括之評價，故在法律評價上，則應將之視\n    為包括一罪。本案被告2 人所犯期貨交易法第112 條第5 款\n    之未經許可經營期貨顧問事業罪、證券投資信託及顧問法第\n    107 條第1 款之未經許可經營證券投資顧問業務罪，均係以\n    未經許可而持續從事一定業務之經營為其犯罪構成要件，本\n    質上具有預定數個同種類行為將反覆實行之犯罪，且本案被\n    告2 人又係在密切接近之一定時間及空間內反覆為之，均屬\n    集合犯，應均為包括一罪。\n  (三)復按刑法上一行為而觸犯數罪名之想像競合犯存在之目的，\n    在於避免對於同一不法要素予以過度評價，其所謂「同一行\n    為」係指所實行者為完全或局部同一之行為而言。因此刑法\n    修正刪除牽連犯之規定後，於修正前原認屬於方法目的或原\n    因結果之不同犯罪，其間果有實行之行為完全或局部同一之\n    情形，應得依想像競合犯論擬（最高法院97年度台上字第\n    3494號判決意旨參照）。被告己○○所犯上開2 罪名、被告\n    丙○○所犯上開3 罪名，其間實行之行為均有局部同一之情\n    形，均應依刑法第55條想像競合犯之規定，從一重之未經許\n    可經營期貨顧問事業罪處斷。起訴書所犯法條欄，就被告丙\n    ○○部分雖記載：「被告丙○○於同一時地，一行為而觸犯\n    上開二罪名，為想像競合犯，請從一重之罪處斷」，惟檢察\n    官於本院審理時，亦已當庭更正為：「被告丙○○於同一時\n    地，一行為而觸犯上開數罪名，為想像競合犯，請從一重之\n    罪處斷」（見本院98年度金訴字第37號卷第72頁反面），在\n    此敘明。\n  (四)爰審酌被告己○○前於79年間因違反醫師法案件，經臺灣高\n    等法院判處有期徒刑7 月，緩刑4 年確定，緩刑期滿後未再\n    有其他刑事犯罪前案紀錄，被告丙○○則未有其他刑案紀錄\n    ，此有被告2 人之臺灣高等法院被告前案紀錄表在卷可按，\n    足認被告2 人素行尚可，而被告2 人未經主管機關許可而擅\n    自從事期貨顧問事業及證券投資顧問業務，影響國家對於金\n    融交易秩序之管理，對於社會大眾投資理財有所影響，被告\n    己○○犯案期間長達約8 年，被告丙○○犯案期間則達1 年\n    3 月，惟念及被告2 人於本院審理時皆業已自白犯行，深表\n    悔悟，另被告丙○○於本院審理期間已賠償被害人丁○○、\n    庚○○、乙○○、甲○○、戊○○共新臺幣（下同）51萬6\n    千元，此有被告提出之和解書5 紙在卷可稽，且考量被告2\n    人之犯罪動機、犯罪手段等一切情狀，分別量處如主文所示\n    之刑，併就被告2 人所處罰金部分，各諭知罰金如易服勞役\n    折算之標準，以示警惕。末查，被告己○○前曾於79年間因\n    違反醫師法案件經判處有期徒刑7 月，緩刑4 年確定，緩刑\n    期滿，緩刑之宣告未經撤銷，其刑之宣告已失其效力，此外\n    ，被告2 人均未曾因故意犯罪受有期徒刑以上刑之宣告，此\n    有被告2 人之臺灣高等法院被告前案紀錄表在卷可稽，被告\n    2 人因短於思慮，致罹刑章，犯後均尚知所悔悟，其等經此\n    偵審程序，當應已知警惕，信無再犯之虞，被告2 人所宣告\n    之刑以暫不執行為適當，惟為確實督促被告2 人保持善良品\n    行及正確法律觀念，爰依刑法第74條第1 項第1 款、第2 項\n    第4 款之規定，分別併諭知緩刑期間及應向公庫支付之金額\n    如主文所示，以啟自新。\n  (五)被告2 人應向公庫支付如主文所示之金額，此部分依刑法第\n    74條第3 項規定得為民事強制執行名義，又依同法第75條之\n    1 第1 項第4 款規定，受緩刑之宣告而違反上開本院所定負\n    擔情節重大，足認原宣告之緩刑難收其預期效果，而有執行\n    刑罰之必要者，得撤銷其宣告，在此敘明。\n四、據上論斷，依刑事訴訟法第449 條第2 項、第3 項、第454\n    條第2 項，期貨交易法第112 條第5 款，證券投資信託及顧\n    問法第107 條第1 款，刑法第11條前段、第339 條第1 項、\n    第55條、第42條第3 項、第5 項、第74條第1 項第1 款、第\n    2 項第4 款，刑法施行法第1 條之1 ，逕以簡易判決處刑如\n    主文。\n五、如不服本判決，得於判決書送達之翌日起10日內，以書狀敘\n    述理由（須附繕本），向本院合議庭提出上訴。"
  },
  "characters": {
    "judges": [
      "江俊彥"
    ],
    "prosecutors": [

    ],
    "lawyers": [
      "曾允斌",
      "林文鵬",
      "陳德峰",
      "林奕秀",
      "周建才"
    ],
    "clerks": [
      "王聖婷"
    ],
    "plaintiffs": [

    ],
    "defendants": [
      "己○○",
      "丙○○"
    ],
    "prosecutor_office": [
      "臺灣臺北地方法院檢察署檢察官"
    ],
    "creditors": [

    ],
    "debtors": [

    ],
    "judicial_associate_officer": [

    ]
  },
  "adjudged_at": "2010-01-05",
  "created_at": "2016-01-05 15:12:25",
  "updated_at": "2016-01-05 15:12:25"
}