{
  "identify": "TPD-97-訴緝-136-20100105-3",
  "court": {
    "name": "臺灣臺北地方法院",
    "code": "TPD"
  },
  "division": {
    "name": "刑事",
    "code": "M"
  },
  "year": 97,
  "word": "訴緝",
  "number": "136",
  "jcheck": "3",
  "reason": "偽造文書等",
  "content": "臺灣臺北地方法院刑事裁定             97年度訴緝字第136號\n公  訴  人  臺灣臺北地方法院檢察署檢察官\n被      告  甲○○\n上列被告因偽造文書等案件，不服中華民國98年9 月29日本院98\n年度訴緝字第136號第一審判決，提起上訴，本院裁定如下：\n    主  文\n上訴駁回。\n    理  由\n一、按「不服地方法院之第一審判決而上訴者，應向管轄第二審\n    之高等法院為之。上訴書狀應敘述具體理由。上訴書狀未敘\n    述上訴理由者，應於上訴期間屆滿後20日內補提理由書於原\n    審法院。逾期未補提者，原審法院應定期間先命補正」；「\n    原審法院認為上訴不合法律上之程式或法律上不應准許或其\n    上訴權已經喪失者，應以裁定駁回之」，刑事訴訟法第361\n    條、第362 條前段分別定有明文。\n二、本件上訴人即被告甲○○因偽造文書等案件，不服本院98年\n    度訴緝字第136 號第一審判決，於法定期間內提起上訴，經\n    核其上訴狀並未敘述上訴理由，亦未於上訴期間屆滿後20日\n    內補提上訴理由書，經本院依刑事訴訟法第361 條第3 項規\n    定，於民國98年12月4 日命其於裁定送達後5 日內補正。該\n    項命補正之裁定所訂期限業已屆滿，惟上訴人迄今仍未補正\n    上訴理由，參照前揭法條規定，本件上訴即不符合法律上之\n    程式，自應予駁回。\n三、依刑事訴訟法第362 條前段，裁定如主文。\n中    華    民    國    99    年    1     月    5     日\n                  刑事第六庭審判長  法  官  張永宏\n                                    法  官  林孟皇\n                                    法  官  林晏如\n上正本與原本無異。\n如不服本裁定，應於送達後5 日內向本院提出抗告狀。\n                                    書記官  楊盈茹\n中    華    民    國    99    年    1     月    5     日",
  "structure": {
    "main": "上訴駁回。",
    "reason": "一、按「不服地方法院之第一審判決而上訴者，應向管轄第二審\n    之高等法院為之。上訴書狀應敘述具體理由。上訴書狀未敘\n    述上訴理由者，應於上訴期間屆滿後20日內補提理由書於原\n    審法院。逾期未補提者，原審法院應定期間先命補正」；「\n    原審法院認為上訴不合法律上之程式或法律上不應准許或其\n    上訴權已經喪失者，應以裁定駁回之」，刑事訴訟法第361\n    條、第362 條前段分別定有明文。\n二、本件上訴人即被告甲○○因偽造文書等案件，不服本院98年\n    度訴緝字第136 號第一審判決，於法定期間內提起上訴，經\n    核其上訴狀並未敘述上訴理由，亦未於上訴期間屆滿後20日\n    內補提上訴理由書，經本院依刑事訴訟法第361 條第3 項規\n    定，於民國98年12月4 日命其於裁定送達後5 日內補正。該\n    項命補正之裁定所訂期限業已屆滿，惟上訴人迄今仍未補正\n    上訴理由，參照前揭法條規定，本件上訴即不符合法律上之\n    程式，自應予駁回。\n三、依刑事訴訟法第362 條前段，裁定如主文。"
  },
  "characters": {
    "judges": [
      "張永宏",
      "林孟皇",
      "林晏如"
    ],
    "prosecutors": [

    ],
    "lawyers": [

    ],
    "clerks": [
      "楊盈茹"
    ],
    "plaintiffs": [

    ],
    "defendants": [
      "甲○○"
    ],
    "prosecutor_office": [
      "臺灣臺北地方法院檢察署檢察官"
    ],
    "creditors": [

    ],
    "debtors": [

    ],
    "judicial_associate_officer": [

    ]
  },
  "adjudged_at": "2010-01-05",
  "created_at": "2016-01-05 15:12:02",
  "updated_at": "2016-01-05 15:12:02"
}