{
  "identify": "TPD-99-消債清-49-20100512-1",
  "court": {
    "name": "臺灣臺北地方法院",
    "code": "TPD"
  },
  "division": {
    "name": "民事",
    "code": "V"
  },
  "year": 99,
  "word": "消債清",
  "number": "49",
  "jcheck": "1",
  "reason": "清算事件",
  "content": "臺灣臺北地方法院民事裁定            99年度消債清字第49號\n聲  請  人\n即債務人    乙○○\n代  理  人  郭至卓律師\n上列當事人聲請消費者債務清理清算事件，本院裁定如下：\n    主  文\n聲請人應於本裁定送達後二十日內，補提如附表所示文件到院，\n逾期未補正，則駁回清算之聲請。\n    理  由\n一、按聲請更生或清算不合程式或不備其他要件者，法院應以裁\n    定駁回之，但其情形可以補正者，法院應定期間先命補正，\n    消費者債務清理條例第8條定有明文。\n二、查本件聲請人具狀聲請清算，主張有該條例第151條第6項不\n    可歸責之事由，其漏未提出如附表所示之說明及文件到院，\n    爰定期命補正，如逾期未補正，則駁回其聲請。\n中    華    民    國    99    年    5     月    12    日\n              民事第三庭    法      官  郭美杏\n上為正本係照原本作成\n本件不得抗告\n中    華    民    國    99    年    5     月    12    日\n                            書  記  官  馮姿蓉\n附表：\n一、聲請人自中國人壽保險股份有限公司辭職後迄本裁定送達之\n    日止，有無從事任何工作？若有，請列明公司名稱及每月收\n    入薪資，並提出相關證明文件。\n二、聲請人陳報前夫甲○○自民國97年8月19日起至98年12月21\n    日止有給付女兒之扶養費17筆共新臺幣（下同）61,723元，\n    除此之外，甲○○有無為其他任何給付？若有，請提出給付\n    之金額、日期，以及證明文件。\n三、聲請人自99年1月1日起迄本裁定送達之日止，有無任何收入\n    ？若有，請列明各項收入明細，並提出相關證明文件。\n四、請提出自98年1月1日起迄本裁定送達之日止，聲請人與受扶\n    養人每月各項必要支出明細表，並提出證明文件。",
  "structure": {
    "main": "聲請人應於本裁定送達後二十日內，補提如附表所示文件到院，\n逾期未補正，則駁回清算之聲請。",
    "reason": "一、按聲請更生或清算不合程式或不備其他要件者，法院應以裁\n    定駁回之，但其情形可以補正者，法院應定期間先命補正，\n    消費者債務清理條例第8條定有明文。\n二、查本件聲請人具狀聲請清算，主張有該條例第151條第6項不\n    可歸責之事由，其漏未提出如附表所示之說明及文件到院，\n    爰定期命補正，如逾期未補正，則駁回其聲請。"
  },
  "characters": {
    "judges": [
      "郭美杏"
    ],
    "prosecutors": [

    ],
    "lawyers": [
      "郭至卓"
    ],
    "clerks": [

    ],
    "plaintiffs": [

    ],
    "defendants": [

    ],
    "prosecutor_office": [
      "即債務人"
    ],
    "creditors": [

    ],
    "debtors": [

    ],
    "judicial_associate_officer": [

    ]
  },
  "adjudged_at": "2010-05-12",
  "created_at": "2016-01-05 12:10:07",
  "updated_at": "2016-01-05 12:10:07"
}