{
  "identify": "TPD-99-簡上-1-20100512-1",
  "court": {
    "name": "臺灣臺北地方法院",
    "code": "TPD"
  },
  "division": {
    "name": "民事",
    "code": "V"
  },
  "year": 99,
  "word": "簡上",
  "number": "1",
  "jcheck": "1",
  "reason": "給付管理費等",
  "content": "臺灣臺北地方法院民事裁定               99年度簡上字第1號\n上  訴  人  丙○○\n            丁○○\n共      同\n訴訟代理人  楊揚律師\n被  上訴人\n即追加原告  福久產物管理有限公司\n法定代理人  甲○○\n訴訟代理人  徐偉峰律師\n追加被  告  樺達哲興業有限公司\n法定代理人  乙○○\n訴訟代理人  楊揚律師\n上列當事人間請求給付管理費等事件，被上訴人所為訴之追加，\n本院裁定如下：\n    主  文\n被上訴人追加之訴駁回。\n追加之訴訴訟費用由被上訴人負擔。\n    理  由\n一、按於第二審為訴之變更或追加，非經他造同意，不得為之。\n    但請求之基礎事實同一者，或該訴訟標的對於數人必須合一\n    確定時，追加其原非當事人之人為當事人者，不在此限，民\n    事訴訟法第446條第1項但書、第255條第1項第2、5款規定自\n    明。而上開普通訴訟程序第二審程序之規定，依同法第436\n    條之1第3項規定，於簡易訴訟程序之第二審程序準用之。此\n    所謂「該訴訟標的對於數人必須合一確定」者，係指依法律\n    之規定必須數人一同起訴或一同被訴，否則其當事人之適格\n    即有欠缺，原告即因此不能獲得本案之勝訴判決而言；或數\n    人在法律上各有獨立實施訴訟之權能，而其中一人起訴或一\n    人被訴時，所受之本案判決依法律之規定對於他人亦有效力\n    者而言（最高法院87年度台抗字137 號裁判可供參照）。惟\n    若無上開情事，則非經他方當事人之同意，尚不容許原告於\n    訴狀送達後任意追加原非當事人之他人為當事人，此觀前開\n    民事訴訟法第446條第1項規定自明。又合於民事訴訟法第25\n    5 條第1項第2款規定而准予追加之訴，並不包括當事人之追\n    加，此乃因訴訟標的對於數人必須合一確定時，其基礎事實\n    並無不同一，如「請求之基礎事實同一」，尚包括追加當事\n    人在內者，則於追加當事人之情形，逕予適用第255條第1項\n    第2款規定即足，自無另設第255條第1項第5款規定之必要（\n    最高法院89年台抗字第54號裁判可資參照）。況在第二審追\n    加原非當事人之人為他造當事人，涉及被追加者之審級利益\n    ，亦不能因原為他造當事人之人表示同意而認為合法（最高\n    法院29年上字第1767號判例參照）。\n二、查，被上訴人於原審以上訴人為被告，主張上訴人丙○○於\n    民國94年4月4日向被上訴人承租坐落臺北市○○區○○路1\n    段144號2樓及3 樓之全部房屋（下稱系爭房屋），雙方並簽\n    訂房屋租賃契約（下稱系爭租約），依系爭租約第13條約定\n    ，上訴人同意就其承租範圍，依西門大樓管理委員會規定標\n    準，向該管委員會繳納管理費，上訴人丁○○則為系爭租賃\n    契約上訴人丙○○之連帶保證人。詎上訴人丙○○於承租期\n    間，自96年1月起至97年12月止短繳合計管理費75萬6,684元\n    ，經被上訴人於98年2月20日繳清，且上訴人丙○○於96年2\n    月份之租金短繳24萬元，而依系爭租約約定及民法第281 條\n    第1 項規定，請求上訴人連帶償還上開款項及遲延利息等語\n    。經原審判決上訴人應連帶給付被上訴人80萬3,200元及自9\n    8年9月15日起算之法定遲延利息，並駁回被上訴人其餘之訴\n    。上訴人不服前開判決而提起本件上訴後，被上訴人始於99\n    年2月5日提出民事上訴答辯暨訴之追加狀，抗辯系爭房屋係\n    由上訴人與被告樺達哲興業有限公司（下稱樺達哲公司）共\n    同承租，而請求上訴人與被告樺達哲公司連帶負給付之責等\n    語。惟被上訴人於原審從未為此主張，且被告樺達哲公司既\n    未同意上訴人之追加，亦否認被上訴人上開主張（見本院卷\n    第67頁），況原列上訴人丙○○、丁○○與被告樺達哲公司\n    間，並非依法律之規定必須一同起訴或一同被訴者，亦非依\n    法律規定，其中一人所受之本案判決效力所及之他人，意即\n    渠等間訴訟標的並非必須合一確定，則被上訴人於本院所為\n    訴之追加即不合民事訴訟法第255條第1項2、5款之情形，復\n    不符合同條其餘各款規定；再參酌被上訴人於二審程序始追\n    加當事人，被告樺達哲公司全無參與第一審程序，若允許其\n    追加當事人，顯有害於被追加當事人之審級利益。從而，揆\n    諸首揭說明，被上訴人於簡易程序第二審始追加被告樺達哲\n    公司為當事人，不符民事訴訟法第446條、第255條第1 項各\n    款之規定，故本院認不應准許追加，以裁定駁回為當。\n三、據上論結，本件訴之追加為不合法，依民事訴訟法第436 條\n    之1第3項、第463條、第249條第1項第6款、第95條、第78條\n    ，裁定如主文。\n中    華    民    國    99    年    5     月    12    日\n                  民事第三庭  審判長法  官  丁蓓蓓\n                                    法  官  魏式瑜\n                                    法  官  周玉琦\n以上正本係照原本作成。\n本裁定不得抗告。\n中    華    民    國    99    年    5     月    12    日\n                                    書記官  劉英權",
  "structure": {
    "main": "被上訴人追加之訴駁回。\n追加之訴訴訟費用由被上訴人負擔。",
    "reason": "一、按於第二審為訴之變更或追加，非經他造同意，不得為之。\n    但請求之基礎事實同一者，或該訴訟標的對於數人必須合一\n    確定時，追加其原非當事人之人為當事人者，不在此限，民\n    事訴訟法第446條第1項但書、第255條第1項第2、5款規定自\n    明。而上開普通訴訟程序第二審程序之規定，依同法第436\n    條之1第3項規定，於簡易訴訟程序之第二審程序準用之。此\n    所謂「該訴訟標的對於數人必須合一確定」者，係指依法律\n    之規定必須數人一同起訴或一同被訴，否則其當事人之適格\n    即有欠缺，原告即因此不能獲得本案之勝訴判決而言；或數\n    人在法律上各有獨立實施訴訟之權能，而其中一人起訴或一\n    人被訴時，所受之本案判決依法律之規定對於他人亦有效力\n    者而言（最高法院87年度台抗字137 號裁判可供參照）。惟\n    若無上開情事，則非經他方當事人之同意，尚不容許原告於\n    訴狀送達後任意追加原非當事人之他人為當事人，此觀前開\n    民事訴訟法第446條第1項規定自明。又合於民事訴訟法第25\n    5 條第1項第2款規定而准予追加之訴，並不包括當事人之追\n    加，此乃因訴訟標的對於數人必須合一確定時，其基礎事實\n    並無不同一，如「請求之基礎事實同一」，尚包括追加當事\n    人在內者，則於追加當事人之情形，逕予適用第255條第1項\n    第2款規定即足，自無另設第255條第1項第5款規定之必要（\n    最高法院89年台抗字第54號裁判可資參照）。況在第二審追\n    加原非當事人之人為他造當事人，涉及被追加者之審級利益\n    ，亦不能因原為他造當事人之人表示同意而認為合法（最高\n    法院29年上字第1767號判例參照）。\n二、查，被上訴人於原審以上訴人為被告，主張上訴人丙○○於\n    民國94年4月4日向被上訴人承租坐落臺北市○○區○○路1\n    段144號2樓及3 樓之全部房屋（下稱系爭房屋），雙方並簽\n    訂房屋租賃契約（下稱系爭租約），依系爭租約第13條約定\n    ，上訴人同意就其承租範圍，依西門大樓管理委員會規定標\n    準，向該管委員會繳納管理費，上訴人丁○○則為系爭租賃\n    契約上訴人丙○○之連帶保證人。詎上訴人丙○○於承租期\n    間，自96年1月起至97年12月止短繳合計管理費75萬6,684元\n    ，經被上訴人於98年2月20日繳清，且上訴人丙○○於96年2\n    月份之租金短繳24萬元，而依系爭租約約定及民法第281 條\n    第1 項規定，請求上訴人連帶償還上開款項及遲延利息等語\n    。經原審判決上訴人應連帶給付被上訴人80萬3,200元及自9\n    8年9月15日起算之法定遲延利息，並駁回被上訴人其餘之訴\n    。上訴人不服前開判決而提起本件上訴後，被上訴人始於99\n    年2月5日提出民事上訴答辯暨訴之追加狀，抗辯系爭房屋係\n    由上訴人與被告樺達哲興業有限公司（下稱樺達哲公司）共\n    同承租，而請求上訴人與被告樺達哲公司連帶負給付之責等\n    語。惟被上訴人於原審從未為此主張，且被告樺達哲公司既\n    未同意上訴人之追加，亦否認被上訴人上開主張（見本院卷\n    第67頁），況原列上訴人丙○○、丁○○與被告樺達哲公司\n    間，並非依法律之規定必須一同起訴或一同被訴者，亦非依\n    法律規定，其中一人所受之本案判決效力所及之他人，意即\n    渠等間訴訟標的並非必須合一確定，則被上訴人於本院所為\n    訴之追加即不合民事訴訟法第255條第1項2、5款之情形，復\n    不符合同條其餘各款規定；再參酌被上訴人於二審程序始追\n    加當事人，被告樺達哲公司全無參與第一審程序，若允許其\n    追加當事人，顯有害於被追加當事人之審級利益。從而，揆\n    諸首揭說明，被上訴人於簡易程序第二審始追加被告樺達哲\n    公司為當事人，不符民事訴訟法第446條、第255條第1 項各\n    款之規定，故本院認不應准許追加，以裁定駁回為當。\n三、據上論結，本件訴之追加為不合法，依民事訴訟法第436 條\n    之1第3項、第463條、第249條第1項第6款、第95條、第78條\n    ，裁定如主文。"
  },
  "characters": {
    "judges": [
      "丁蓓蓓",
      "魏式瑜",
      "周玉琦"
    ],
    "prosecutors": [

    ],
    "lawyers": [
      "楊揚",
      "徐偉峰",
      "楊揚"
    ],
    "clerks": [

    ],
    "plaintiffs": [

    ],
    "defendants": [
      "樺達哲興業有限公司"
    ],
    "prosecutor_office": [

    ],
    "creditors": [

    ],
    "debtors": [

    ],
    "judicial_associate_officer": [

    ]
  },
  "adjudged_at": "2010-05-12",
  "created_at": "2016-01-05 12:19:16",
  "updated_at": "2016-01-05 12:19:16"
}