{
  "identify": "TPD-97-重訴-318-20100512-7",
  "court": {
    "name": "臺灣臺北地方法院",
    "code": "TPD"
  },
  "division": {
    "name": "民事",
    "code": "V"
  },
  "year": 97,
  "word": "重訴",
  "number": "318",
  "jcheck": "7",
  "reason": "拆屋還地等",
  "content": "臺灣臺北地方法院民事裁定             97年度重訴字第318號\n原      告    國防部總政治作戰局（國防部軍備局之承受訴訟\n法定代理人    甲○○\n訴訟代理人    林志宏律師\n被      告    酉○○\n              午○○\n兼上一人\n法定代理人    申○○\n              壬○○\n被      告    丁○○○○○○○.\n法定代理人    申○○\n上列五人共同\n訴訟代理人    沈宏裕律師\n被      告    巳○○    住臺北市松山區○○○路○段191巷7\n                          弄4號\n                        居臺北市松山區○○○路○段36巷8弄\n                          12號5樓\n訴訟代理人    王昧爽律師\n複代理人      李初東律師\n被      告    阿發視覺特效股份有限公司\n                        設臺北市○○○路○段81號1樓\n                        設臺北市松山區○○○路○段191巷7\n                          弄4號\n法定代理人    辛○○    住同上\n                        居臺北市○○區○○路3段210號4樓\n被      告    戊○○    住臺北市松山區○○○路○段191巷13\n                          弄3號\n                        居臺北縣三峽鎮嘉添里12鄰白雞127號\n              己○○    住臺北市松山區○○○路○段191巷13\n                          弄3號\n              庚○○    住同上\n              子○○    住同上\n              癸○○    住同上\n上列二人共同\n兼法定代理人  丑○○    住同上\n上列二人共同\n法定代理人    乙○      住同上\n被      告    辰○○    住同上\n兼法定代理    丙○○    住同上\n人\n法定代理人    卯○○    住同上\n上列四人共同\n訴訟代理人    丑○○    住同上\n被      告    寅○○    住臺北市松山區○○○路○段191巷21\n                          號\n訴訟代理人    王義光律師\n被      告    奧美達國際室內裝修有限公司\n                        設臺北市○○○路○段138-1號4樓\n法定代理人    未○○    住桃園市○○○路87號10樓之1\n                        居臺北市○○路288號2樓之1\n上列當事人間請求拆屋還地等事件，本院裁定如下：\n    主  文\n本件准由原告國防部總政治作戰局為國防部軍備局承受訴訟人，\n續行訴訟。\n    理  由\n一、按當事人喪失訴訟能力或法定代理人死亡或其代理權消滅者\n    ，訴訟程序在有法定代理人或取得訴訟能力之本人承受其訴\n    訟以前當然停止；又本於一定資格以自己名義為他人任訴訟\n    當事人之人，喪失其資格或死亡者，訴訟程序在有同一資格\n    之人承受其訴訟以前當然停止。承受訴訟之聲明有無理由，\n    法院應依職權調查之；訴訟程序於裁判送達後當然停止者，\n    其承受訴訟之聲明，由為裁判之原法院裁定之，民事訴訟法\n    第170 條、第172 條第1 項、第177 條第1 項及第3 項分別\n    定有明文。\n二、本院97年度重訴字第318 號拆屋還地等事件，業於民國98年\n    10月22日言詞辯論終結，於同年10月30日宣判，嗣原告對該\n    判決提起上訴。查系爭土地之管理機關起訴時，原為國防部\n    軍備局，嗣改為國防部總政治作戰局，並聲明承受訴訟，有\n    系爭土地之土地登記謄本及聲明承受訴訟暨部分撤回狀各在\n    卷可稽，揆前說明，核無不合，應予准許，爰裁定如主文所\n    示。\n中    華    民    國    99    年    5     月    12    日\n                    民事第五庭  法  官  陳靜茹\n以上正本係照原本作成。\n如對本裁定抗告，須於裁定送達後10日內，向本院提出抗告狀。\n中    華    民    國    99    年    5     月    12    日\n                                書記官  鄭雅雲",
  "structure": {
    "main": "本件准由原告國防部總政治作戰局為國防部軍備局承受訴訟人，\n續行訴訟。",
    "reason": "一、按當事人喪失訴訟能力或法定代理人死亡或其代理權消滅者\n    ，訴訟程序在有法定代理人或取得訴訟能力之本人承受其訴\n    訟以前當然停止；又本於一定資格以自己名義為他人任訴訟\n    當事人之人，喪失其資格或死亡者，訴訟程序在有同一資格\n    之人承受其訴訟以前當然停止。承受訴訟之聲明有無理由，\n    法院應依職權調查之；訴訟程序於裁判送達後當然停止者，\n    其承受訴訟之聲明，由為裁判之原法院裁定之，民事訴訟法\n    第170 條、第172 條第1 項、第177 條第1 項及第3 項分別\n    定有明文。\n二、本院97年度重訴字第318 號拆屋還地等事件，業於民國98年\n    10月22日言詞辯論終結，於同年10月30日宣判，嗣原告對該\n    判決提起上訴。查系爭土地之管理機關起訴時，原為國防部\n    軍備局，嗣改為國防部總政治作戰局，並聲明承受訴訟，有\n    系爭土地之土地登記謄本及聲明承受訴訟暨部分撤回狀各在\n    卷可稽，揆前說明，核無不合，應予准許，爰裁定如主文所\n    示。"
  },
  "characters": {
    "judges": [
      "陳靜茹"
    ],
    "prosecutors": [

    ],
    "lawyers": [
      "林志宏",
      "沈宏裕",
      "王昧爽",
      "李初東",
      "王義光"
    ],
    "clerks": [

    ],
    "plaintiffs": [
      "國防部總政治作戰局"
    ],
    "defendants": [
      "酉○○",
      "丁○○○○○○○.",
      "巳○○    住臺北市松山區○○○路○段191巷7",
      "阿發視覺特效股份有限公司",
      "戊○○    住臺北市松山區○○○路○段191巷13",
      "辰○○    住同上",
      "兼法定代理    丙○○    住同上",
      "寅○○    住臺北市松山區○○○路○段191巷21",
      "奧美達國際室內裝修有限公司"
    ],
    "prosecutor_office": [

    ],
    "creditors": [

    ],
    "debtors": [

    ],
    "judicial_associate_officer": [

    ]
  },
  "adjudged_at": "2010-05-12",
  "created_at": "2016-01-05 12:10:49",
  "updated_at": "2016-01-05 12:10:49"
}