{
  "identify": "TPD-99-簡上-89-20100512-1",
  "court": {
    "name": "臺灣臺北地方法院",
    "code": "TPD"
  },
  "division": {
    "name": "刑事",
    "code": "M"
  },
  "year": 99,
  "word": "簡上",
  "number": "89",
  "jcheck": "1",
  "reason": "妨害名譽",
  "content": "臺灣臺北地方法院刑事判決            99年度簡上字第89號\n上  訴  人\n即  被  告  甲○○\n上列上訴人即被告因妨害名譽案件，不服本院於中華民國99年1\n月20日所為之99年度簡字第90號第一審簡易判決（聲請案號：臺\n灣臺北地方法院檢察署98年度偵字第27244號），提起上訴，本\n院管轄之第二審合議庭判決如下：\n    主      文\n上訴駁回。\n甲○○緩刑貳年。\n    事實及理由\n一、本案經本院審理結果，認第一審簡易判決認事用法及量刑均\n    無不當，應予維持，並引用第一審判決書記載之事實、證據\n    及理由（如附件）。\n二、上訴意旨略以：上訴人即被告甲○○對原審判決所認定之事\n    實及適用法律均無爭執，僅表示已與被害人和解，希望可以\n    給予緩刑之機會（見99年度簡上字第89號卷第27至29頁）等\n    語。經查：\n（一）原審經審理結果，認被告犯罪事證明確，因而適用刑法第\n      310第2項、第1項、第41條第1項前段，刑法施行法第1條\n      之1等規定，處被告拘役40日，並諭知以新臺幣1000元折\n      算1日為易科罰金之折算標準。經核其認事用法，均無違\n      誤，量刑亦屬妥適，上訴人上訴尚無理由，應予駁回。\n（二）末查，被告前未曾受有期徒刑以上刑之宣告，有臺灣高等\n      法院被告全國前案紀錄表在卷可稽，其於本院審理時坦認\n      犯行，並與告訴人和解，且已履行和解條件完畢，有臺北\n      市內湖區調解委員會調解書1份在卷可參（見同上審卷第\n      30頁），其因一時失慮，致罹刑章，本院認被告經此偵審\n      程序，應知警惕而無再犯之虞，前開所宣告之刑以暫不執\n      行為適當，併予宣告緩刑2年，以啟自新。\n三、據上論結，應依刑事訴訟法第455條之1第1項、第3項、第36\n    8條、第373條，刑法第74條第1項第1款，判決如主文。\n本案經檢察官蘇維達到庭執行職務。\n中    華    民    國    99    年    5     月    12    日\n                  刑事第十一庭  審判長法  官  劉方慈\n                                      法  官  黃紹紘\n                                      法  官  顧正德\n上正本證明與原本無異。\n不得上訴。\n                                      書記官  郭錦賢\n中    華    民    國    99    年    5     月    13    日",
  "structure": {
    "main": "上訴駁回。\n甲○○緩刑貳年。",
    "fact": "一、本案經本院審理結果，認第一審簡易判決認事用法及量刑均\n    無不當，應予維持，並引用第一審判決書記載之事實、證據\n    及理由（如附件）。\n二、上訴意旨略以：上訴人即被告甲○○對原審判決所認定之事\n    實及適用法律均無爭執，僅表示已與被害人和解，希望可以\n    給予緩刑之機會（見99年度簡上字第89號卷第27至29頁）等\n    語。經查：\n（一）原審經審理結果，認被告犯罪事證明確，因而適用刑法第\n      310第2項、第1項、第41條第1項前段，刑法施行法第1條\n      之1等規定，處被告拘役40日，並諭知以新臺幣1000元折\n      算1日為易科罰金之折算標準。經核其認事用法，均無違\n      誤，量刑亦屬妥適，上訴人上訴尚無理由，應予駁回。\n（二）末查，被告前未曾受有期徒刑以上刑之宣告，有臺灣高等\n      法院被告全國前案紀錄表在卷可稽，其於本院審理時坦認\n      犯行，並與告訴人和解，且已履行和解條件完畢，有臺北\n      市內湖區調解委員會調解書1份在卷可參（見同上審卷第\n      30頁），其因一時失慮，致罹刑章，本院認被告經此偵審\n      程序，應知警惕而無再犯之虞，前開所宣告之刑以暫不執\n      行為適當，併予宣告緩刑2年，以啟自新。\n三、據上論結，應依刑事訴訟法第455條之1第1項、第3項、第36\n    8條、第373條，刑法第74條第1項第1款，判決如主文。\n本案經檢察官蘇維達到庭執行職務。",
    "reason": "一、本案經本院審理結果，認第一審簡易判決認事用法及量刑均\n    無不當，應予維持，並引用第一審判決書記載之事實、證據\n    及理由（如附件）。\n二、上訴意旨略以：上訴人即被告甲○○對原審判決所認定之事\n    實及適用法律均無爭執，僅表示已與被害人和解，希望可以\n    給予緩刑之機會（見99年度簡上字第89號卷第27至29頁）等\n    語。經查：\n（一）原審經審理結果，認被告犯罪事證明確，因而適用刑法第\n      310第2項、第1項、第41條第1項前段，刑法施行法第1條\n      之1等規定，處被告拘役40日，並諭知以新臺幣1000元折\n      算1日為易科罰金之折算標準。經核其認事用法，均無違\n      誤，量刑亦屬妥適，上訴人上訴尚無理由，應予駁回。\n（二）末查，被告前未曾受有期徒刑以上刑之宣告，有臺灣高等\n      法院被告全國前案紀錄表在卷可稽，其於本院審理時坦認\n      犯行，並與告訴人和解，且已履行和解條件完畢，有臺北\n      市內湖區調解委員會調解書1份在卷可參（見同上審卷第\n      30頁），其因一時失慮，致罹刑章，本院認被告經此偵審\n      程序，應知警惕而無再犯之虞，前開所宣告之刑以暫不執\n      行為適當，併予宣告緩刑2年，以啟自新。\n三、據上論結，應依刑事訴訟法第455條之1第1項、第3項、第36\n    8條、第373條，刑法第74條第1項第1款，判決如主文。\n本案經檢察官蘇維達到庭執行職務。"
  },
  "characters": {
    "judges": [
      "劉方慈",
      "黃紹紘",
      "顧正德"
    ],
    "prosecutors": [
      "蘇維達"
    ],
    "lawyers": [

    ],
    "clerks": [
      "郭錦賢"
    ],
    "plaintiffs": [

    ],
    "defendants": [
      "甲"
    ],
    "prosecutor_office": [

    ],
    "creditors": [

    ],
    "debtors": [

    ],
    "judicial_associate_officer": [

    ]
  },
  "adjudged_at": "2010-05-12",
  "created_at": "2016-01-05 12:05:53",
  "updated_at": "2016-01-05 12:05:53"
}