{
  "identify": "TPD-99-訴-373-20100512-1",
  "court": {
    "name": "臺灣臺北地方法院",
    "code": "TPD"
  },
  "division": {
    "name": "民事",
    "code": "V"
  },
  "year": 99,
  "word": "訴",
  "number": "373",
  "jcheck": "1",
  "reason": "損害賠償",
  "content": "臺灣臺北地方法院民事判決               99年度訴字第373號\n原      告  甲○○\n被      告  乙○○\n上列當事人間請求損害賠償事件，本院於民國99年4月21日言詞\n辯論終結，判決如下：\n    主      文\n被告應給付原告新臺幣貳萬元，及自民國九十九年一月四日起至\n清償日止，按週年利率百分之五計算之利息。\n原告其餘之訴駁回。\n訴訟費用由被告負擔五十九分之二，餘由原告負擔。\n    事實及理由\n一、原告主張：被告於民國97年間任臺北市國興國宅社區（下稱\n    國興社區）管理委員會主任委員，原告為國興社區之住戶，\n    原告等人因不滿管理委員會要求住戶繳交身分證及產權證明\n    影本予管理委員會後始得受領福利金，乃向臺北市萬華區調\n    解委員會聲請調解。於97年6 月10日下午某時許，在臺北市\n    萬華區行政中心大禮堂之公共場所內，由訴外人即調解委員\n    李成光進行調解事宜時，被告稱：「有繳交身分證和產權證\n    明影本予管委會之住戶難道都是傻瓜。」等語，原告遂提出\n    臺北市政府消防局於97年3 月31日就國興社區所為之消防安\n    全檢（複）查不合規定限期改善通知單質疑稱：「一張消防\n    缺失改善通知單上，你為什麼要把身分證字號塗抹掉再公告\n    呢？你是不是區分所有權人？」等語，被告竟立即打斷原告\n    問語，當眾向原告辱罵稱：「你去告啊！你不敢告，你就是\n    ㄋㄠ種，他媽的，幹！」等語。被告在大庭廣眾中辱罵原告\n    ，侵害原告名譽，使原告人格受辱並精神上蒙受重大痛苦，\n    經本院刑事庭以98年度易字第279號判決認定被告犯刑法第3\n    09條第1項之公然侮辱罪確定。爰依民法第184條第1項、第1\n    95條第1 項之規定請求被告負損害賠償之責等語，並聲明：\n    被告應給付原告新臺幣（下同）59萬元及自起訴狀繕本送達\n    翌日起至清償日止，按年息5％計算之利息。\n二、被告則以：被告於97年6 月10日調解時並無口出不雅言語，\n    被告因當時人在大陸而未提起上訴，但被告係因社區公共事\n    務與原告發生糾紛，且願意以書面公開方式向原告道歉，然\n    為原告所拒，被告目前失業中，經濟狀況非常窘困，原告請\n    求之金額，實不合理等語資為抗辯，並聲明：原告之訴駁回\n    。\n三、兩造不爭執之事實（見本院98年度審訴字第6354號卷，下稱\n    審訴卷，第36頁反面）：\n  (一)被告於97年至98年12月31日為臺北市國興國宅社區管理委員\n    會主任委員。\n  (二)原告以：其因社區領取福利金問題之爭議，向臺北市萬華區\n    調解委員會聲請調解，經該調解委員會於97年6月10日下午\n    在臺北市萬華區行政中心大禮堂之公共場所內，由調解委員\n    即訴外人李成光進行調解時，被告當場對原告為：「你去告\n    啊！你不敢告，你就是ㄋㄠ種，他媽的，幹！」之言語一事\n    ，向被告提出刑事告訴，經本院刑事庭以98年度易字第279\n    號判決認定被告犯刑法第309條第1項之公然侮辱罪，處拘役\n    35日，得易科罰金。\n四、原告主張被告於97年6 月10日下午某時許，在臺北市萬華區\n    行政中心大禮堂之公共場所內由調解委員即訴外人李成光進\n    行調解事宜時，當眾向原告辱罵稱：「你去告啊！你不敢告\n    ，你就是ㄋㄠ種，他媽的，幹！」等語，侵害原告名譽，使\n    原告人格受辱並精神上蒙受重大痛苦，而請求被告賠償原告\n    非財產上損害59萬元及遲延利息等語，則為被告所否認，並\n    以前揭情詞置辯。是本件主要爭點厥為：被告有無於上開時\n    地為前揭言語？被告應否對原告負侵權行為損害賠償之責？\n    原告請求被告賠償若干金額之慰撫金為適當？茲論述如下：\n  (一)經查，被告對於其曾於97年6 月10日下午某時許，至臺北市\n    萬華區行政大禮堂，就國興社區管理委員會發放福利金問題\n    與原告進行調解之事實，並不爭執。又被告係於97年6月10\n    日下午某時許，以國興社區管理委員會主任委員身分帶同其\n    他委員即訴外人陳水官、張堂治及陳秀鳳前往臺北市萬華區\n    行政中心大禮堂進行調解，而被告在調解委員李成光進行調\n    解事宜時，因不滿原告就其所述：「有繳交身分證和產權證\n    明影本予管委會之住戶難道都是傻瓜。」等語，提出臺北市\n    政府消防局於97年3月31日就國興社區所為之消防安全檢（\n    複）查不合規定限期改善通知單質疑稱：「一張消防缺失改\n    善通知單上，你為什麼要把身分證字號塗抹掉再公告呢？你\n    是不是區分所有權人？」等語，即憤而向原告辱罵稱：「你\n    去告啊！你不敢告，你就是ㄋㄠ種，他媽的，幹！」等語，\n    站立於原告及陳錦後方之鄭澄江隨即出言向被告制止稱：「\n    你怎麼可以罵人。」等語，調解委員李成光見狀即告稱：「\n    不要做人身攻擊。」等語，其後因陳錦與陳水官、張堂治就\n    前屆管理委員會委員侵占3 個月管理費之事另起爭執，該次\n    調解即無法繼續而調解不成立等情，業據原告於偵查及本院\n    刑事庭審理時結證明確，核與訴外人趙麗雲、陳錦及鄭澄江\n    於偵查及本院刑事庭審理時之證述相符（見臺灣臺北地方法\n    院檢察署97年度他字第6829號卷第12頁至第18頁，下稱他字\n    卷、本院刑事庭98年度易字第279號卷，下稱刑事一審卷第3\n    5 頁至第40頁、第42頁反面至第46頁、第58頁至第65頁），\n    並有國興社區管理委員會94年5月3日國興（選）字第940502\n    號公告、臺北市政府消防局消防安全檢（複）查不合規定限\n    期改善通知單、臺北市萬華區調解委員會97年民調字第207\n    號調解不成立證明書（見審訴卷第3頁至第4頁、他字卷第8\n    頁）附卷可佐，且被告所為上開言語，業經本院刑事庭以98\n    年度易字第279號判決認定被告犯刑法第309條第1 項之公然\n    侮辱罪，處拘役35日，得易科罰金。被告不服提起上訴後，\n    旋於98年9 月29日撤回其上訴等事實，有上開刑事判決（見\n    審訴卷第5 頁至第10頁）在卷足憑，並經本院職權調閱上開\n    刑事卷查明無訛。是堪認原告主張被告於97年6 月10日下午\n    某時許，在臺北市萬華區行政中心大禮堂之公共場所內由調\n    解委員李成光進行調解事宜時，當眾向原告辱罵稱：「你去\n    告啊！你不敢告，你就是ㄋㄠ種，他媽的，幹！」等語，應\n    為可採。被告空言抗辯其於97年6 月10日調解時並無口出不\n    雅言語云云，要非足取。\n  (二)按因故意或過失，不法侵害他人之權利者，負損害賠償責任\n    ；不法侵害他人之身體、健康、名譽、自由、信用、隱私、\n    貞操，或不法侵害其他人格法益而情節重大者，被害人雖非\n    財產上之損害，亦得請求賠償相當之金額，民法第184條第1\n    項前段、第195條第1項前段分別定有明文。又按慰藉金之賠\n    償須以人格權遭遇侵害，使精神上受有痛苦為必要，其核給\n    之標準，則可斟酌雙方身分、資力與加害程度，及其他各種\n    情形核定相當之數額（最高法院51年台上字第223 號判例意\n    旨參照）。查被告有於97年6 月10日下午某時許，在臺北市\n    萬華區行政中心大禮堂之公共場所內由調解委員李成光進行\n    調解事宜時，當眾向原告辱罵稱：「你去告啊！你不敢告，\n    你就是ㄋㄠ種，他媽的，幹！」等語之事實，已於前述，而\n    「ㄋㄠ種」一詞，本含有貶抑他人之意涵，且被告辱罵之際\n    ，參與該次調解委員會人員在場、聽聞，亦使渠等人員知悉\n    其事，衡諸一般社會通念，足認原告主張被告所為上開言語\n    係屬故意不法侵害原告之名譽，使原告人格受辱並精神上感\n    受痛苦等語，應為可採。是原告依侵權行為法則請求被告賠\n    償其非財產上損害，洵屬有據。本院審酌原告為屏東初中畢\n    業，97年財產所得資料顯示其名下有房屋、土地多筆，及薪\n    資所得12萬元，財產總額527萬7,074元。被告高中畢業，從\n    事設計工作，自98年7 月間起失業，於97年財產所得資料顯\n    示其名下有房地各1筆、投資8萬元，財產總額213萬3,030元\n    。此經兩造陳明在案（見本院審訴卷第29頁、本院卷第37頁\n    ），且有原告97年度綜合所得稅各類所得資料清單、兩造稅\n    務電子閘門財產所得調件明細表（見審訴卷第30頁、本院卷\n    第6頁至第30頁）附卷可考；另參酌被告固以「ㄋㄠ種」、\n    「他媽的」、「幹」等詞等語辱罵原告而侵害原告名譽，惟\n    在場聽聞之人僅為參與該次調解委員會會議之人員，原告名\n    譽遭受侵害程度尚非嚴重，且被告係因國興社區公共事務與\n    原告發生爭執，及被告於本件訴訟中已向原告表示歉意，欲\n    與原告和解，顯見其已深感悔悟（詳本院卷第36頁）等情，\n    認原告請求被告賠償59萬元，猶嫌過高，應以2 萬元始屬允\n    當，逾此部分之請求，即非可採，應予駁回。\n五、綜上所述，原告依侵權行為法律關係請求被告給付原告2 萬\n    元，及自起訴狀繕本送達翌日即99年1月4日起至清償日止，\n    按年息5％ 計算之利息為有理由，應予准許；逾此部分即無\n    理由，應予駁回。\n六、本件事證已明，兩造其餘攻擊防禦方法及所提之證據，核與\n    判決結果無影響，毋庸再予一一論述，附此敘明。\n七、據上論結，原告之訴為一部有理由，一部無理由，依民事訴\n    訟法第79條，判決如主文。\n中    華    民    國    99    年    5     月    12    日\n                  民事第三庭  審判長法  官  丁蓓蓓\n                                    法  官  黃書苑\n                                    法  官  周玉琦\n以上正本係照原本作成。\n如對本判決上訴，須於判決送達後20日內向本院提出上訴狀。\n中    華    民    國    99    年    5     月    12    日\n                                    書記官  劉英權",
  "structure": {
    "main": "被告應給付原告新臺幣貳萬元，及自民國九十九年一月四日起至\n清償日止，按週年利率百分之五計算之利息。\n原告其餘之訴駁回。\n訴訟費用由被告負擔五十九分之二，餘由原告負擔。",
    "fact": "一、原告主張：被告於民國97年間任臺北市國興國宅社區（下稱\n    國興社區）管理委員會主任委員，原告為國興社區之住戶，\n    原告等人因不滿管理委員會要求住戶繳交身分證及產權證明\n    影本予管理委員會後始得受領福利金，乃向臺北市萬華區調\n    解委員會聲請調解。於97年6 月10日下午某時許，在臺北市\n    萬華區行政中心大禮堂之公共場所內，由訴外人即調解委員\n    李成光進行調解事宜時，被告稱：「有繳交身分證和產權證\n    明影本予管委會之住戶難道都是傻瓜。」等語，原告遂提出\n    臺北市政府消防局於97年3 月31日就國興社區所為之消防安\n    全檢（複）查不合規定限期改善通知單質疑稱：「一張消防\n    缺失改善通知單上，你為什麼要把身分證字號塗抹掉再公告\n    呢？你是不是區分所有權人？」等語，被告竟立即打斷原告\n    問語，當眾向原告辱罵稱：「你去告啊！你不敢告，你就是\n    ㄋㄠ種，他媽的，幹！」等語。被告在大庭廣眾中辱罵原告\n    ，侵害原告名譽，使原告人格受辱並精神上蒙受重大痛苦，\n    經本院刑事庭以98年度易字第279號判決認定被告犯刑法第3\n    09條第1項之公然侮辱罪確定。爰依民法第184條第1項、第1\n    95條第1 項之規定請求被告負損害賠償之責等語，並聲明：\n    被告應給付原告新臺幣（下同）59萬元及自起訴狀繕本送達\n    翌日起至清償日止，按年息5％計算之利息。\n二、被告則以：被告於97年6 月10日調解時並無口出不雅言語，\n    被告因當時人在大陸而未提起上訴，但被告係因社區公共事\n    務與原告發生糾紛，且願意以書面公開方式向原告道歉，然\n    為原告所拒，被告目前失業中，經濟狀況非常窘困，原告請\n    求之金額，實不合理等語資為抗辯，並聲明：原告之訴駁回\n    。\n三、兩造不爭執之事實（見本院98年度審訴字第6354號卷，下稱\n    審訴卷，第36頁反面）：\n  (一)被告於97年至98年12月31日為臺北市國興國宅社區管理委員\n    會主任委員。\n  (二)原告以：其因社區領取福利金問題之爭議，向臺北市萬華區\n    調解委員會聲請調解，經該調解委員會於97年6月10日下午\n    在臺北市萬華區行政中心大禮堂之公共場所內，由調解委員\n    即訴外人李成光進行調解時，被告當場對原告為：「你去告\n    啊！你不敢告，你就是ㄋㄠ種，他媽的，幹！」之言語一事\n    ，向被告提出刑事告訴，經本院刑事庭以98年度易字第279\n    號判決認定被告犯刑法第309條第1項之公然侮辱罪，處拘役\n    35日，得易科罰金。\n四、原告主張被告於97年6 月10日下午某時許，在臺北市萬華區\n    行政中心大禮堂之公共場所內由調解委員即訴外人李成光進\n    行調解事宜時，當眾向原告辱罵稱：「你去告啊！你不敢告\n    ，你就是ㄋㄠ種，他媽的，幹！」等語，侵害原告名譽，使\n    原告人格受辱並精神上蒙受重大痛苦，而請求被告賠償原告\n    非財產上損害59萬元及遲延利息等語，則為被告所否認，並\n    以前揭情詞置辯。是本件主要爭點厥為：被告有無於上開時\n    地為前揭言語？被告應否對原告負侵權行為損害賠償之責？\n    原告請求被告賠償若干金額之慰撫金為適當？茲論述如下：\n  (一)經查，被告對於其曾於97年6 月10日下午某時許，至臺北市\n    萬華區行政大禮堂，就國興社區管理委員會發放福利金問題\n    與原告進行調解之事實，並不爭執。又被告係於97年6月10\n    日下午某時許，以國興社區管理委員會主任委員身分帶同其\n    他委員即訴外人陳水官、張堂治及陳秀鳳前往臺北市萬華區\n    行政中心大禮堂進行調解，而被告在調解委員李成光進行調\n    解事宜時，因不滿原告就其所述：「有繳交身分證和產權證\n    明影本予管委會之住戶難道都是傻瓜。」等語，提出臺北市\n    政府消防局於97年3月31日就國興社區所為之消防安全檢（\n    複）查不合規定限期改善通知單質疑稱：「一張消防缺失改\n    善通知單上，你為什麼要把身分證字號塗抹掉再公告呢？你\n    是不是區分所有權人？」等語，即憤而向原告辱罵稱：「你\n    去告啊！你不敢告，你就是ㄋㄠ種，他媽的，幹！」等語，\n    站立於原告及陳錦後方之鄭澄江隨即出言向被告制止稱：「\n    你怎麼可以罵人。」等語，調解委員李成光見狀即告稱：「\n    不要做人身攻擊。」等語，其後因陳錦與陳水官、張堂治就\n    前屆管理委員會委員侵占3 個月管理費之事另起爭執，該次\n    調解即無法繼續而調解不成立等情，業據原告於偵查及本院\n    刑事庭審理時結證明確，核與訴外人趙麗雲、陳錦及鄭澄江\n    於偵查及本院刑事庭審理時之證述相符（見臺灣臺北地方法\n    院檢察署97年度他字第6829號卷第12頁至第18頁，下稱他字\n    卷、本院刑事庭98年度易字第279號卷，下稱刑事一審卷第3\n    5 頁至第40頁、第42頁反面至第46頁、第58頁至第65頁），\n    並有國興社區管理委員會94年5月3日國興（選）字第940502\n    號公告、臺北市政府消防局消防安全檢（複）查不合規定限\n    期改善通知單、臺北市萬華區調解委員會97年民調字第207\n    號調解不成立證明書（見審訴卷第3頁至第4頁、他字卷第8\n    頁）附卷可佐，且被告所為上開言語，業經本院刑事庭以98\n    年度易字第279號判決認定被告犯刑法第309條第1 項之公然\n    侮辱罪，處拘役35日，得易科罰金。被告不服提起上訴後，\n    旋於98年9 月29日撤回其上訴等事實，有上開刑事判決（見\n    審訴卷第5 頁至第10頁）在卷足憑，並經本院職權調閱上開\n    刑事卷查明無訛。是堪認原告主張被告於97年6 月10日下午\n    某時許，在臺北市萬華區行政中心大禮堂之公共場所內由調\n    解委員李成光進行調解事宜時，當眾向原告辱罵稱：「你去\n    告啊！你不敢告，你就是ㄋㄠ種，他媽的，幹！」等語，應\n    為可採。被告空言抗辯其於97年6 月10日調解時並無口出不\n    雅言語云云，要非足取。\n  (二)按因故意或過失，不法侵害他人之權利者，負損害賠償責任\n    ；不法侵害他人之身體、健康、名譽、自由、信用、隱私、\n    貞操，或不法侵害其他人格法益而情節重大者，被害人雖非\n    財產上之損害，亦得請求賠償相當之金額，民法第184條第1\n    項前段、第195條第1項前段分別定有明文。又按慰藉金之賠\n    償須以人格權遭遇侵害，使精神上受有痛苦為必要，其核給\n    之標準，則可斟酌雙方身分、資力與加害程度，及其他各種\n    情形核定相當之數額（最高法院51年台上字第223 號判例意\n    旨參照）。查被告有於97年6 月10日下午某時許，在臺北市\n    萬華區行政中心大禮堂之公共場所內由調解委員李成光進行\n    調解事宜時，當眾向原告辱罵稱：「你去告啊！你不敢告，\n    你就是ㄋㄠ種，他媽的，幹！」等語之事實，已於前述，而\n    「ㄋㄠ種」一詞，本含有貶抑他人之意涵，且被告辱罵之際\n    ，參與該次調解委員會人員在場、聽聞，亦使渠等人員知悉\n    其事，衡諸一般社會通念，足認原告主張被告所為上開言語\n    係屬故意不法侵害原告之名譽，使原告人格受辱並精神上感\n    受痛苦等語，應為可採。是原告依侵權行為法則請求被告賠\n    償其非財產上損害，洵屬有據。本院審酌原告為屏東初中畢\n    業，97年財產所得資料顯示其名下有房屋、土地多筆，及薪\n    資所得12萬元，財產總額527萬7,074元。被告高中畢業，從\n    事設計工作，自98年7 月間起失業，於97年財產所得資料顯\n    示其名下有房地各1筆、投資8萬元，財產總額213萬3,030元\n    。此經兩造陳明在案（見本院審訴卷第29頁、本院卷第37頁\n    ），且有原告97年度綜合所得稅各類所得資料清單、兩造稅\n    務電子閘門財產所得調件明細表（見審訴卷第30頁、本院卷\n    第6頁至第30頁）附卷可考；另參酌被告固以「ㄋㄠ種」、\n    「他媽的」、「幹」等詞等語辱罵原告而侵害原告名譽，惟\n    在場聽聞之人僅為參與該次調解委員會會議之人員，原告名\n    譽遭受侵害程度尚非嚴重，且被告係因國興社區公共事務與\n    原告發生爭執，及被告於本件訴訟中已向原告表示歉意，欲\n    與原告和解，顯見其已深感悔悟（詳本院卷第36頁）等情，\n    認原告請求被告賠償59萬元，猶嫌過高，應以2 萬元始屬允\n    當，逾此部分之請求，即非可採，應予駁回。\n五、綜上所述，原告依侵權行為法律關係請求被告給付原告2 萬\n    元，及自起訴狀繕本送達翌日即99年1月4日起至清償日止，\n    按年息5％ 計算之利息為有理由，應予准許；逾此部分即無\n    理由，應予駁回。\n六、本件事證已明，兩造其餘攻擊防禦方法及所提之證據，核與\n    判決結果無影響，毋庸再予一一論述，附此敘明。\n七、據上論結，原告之訴為一部有理由，一部無理由，依民事訴\n    訟法第79條，判決如主文。",
    "reason": "一、原告主張：被告於民國97年間任臺北市國興國宅社區（下稱\n    國興社區）管理委員會主任委員，原告為國興社區之住戶，\n    原告等人因不滿管理委員會要求住戶繳交身分證及產權證明\n    影本予管理委員會後始得受領福利金，乃向臺北市萬華區調\n    解委員會聲請調解。於97年6 月10日下午某時許，在臺北市\n    萬華區行政中心大禮堂之公共場所內，由訴外人即調解委員\n    李成光進行調解事宜時，被告稱：「有繳交身分證和產權證\n    明影本予管委會之住戶難道都是傻瓜。」等語，原告遂提出\n    臺北市政府消防局於97年3 月31日就國興社區所為之消防安\n    全檢（複）查不合規定限期改善通知單質疑稱：「一張消防\n    缺失改善通知單上，你為什麼要把身分證字號塗抹掉再公告\n    呢？你是不是區分所有權人？」等語，被告竟立即打斷原告\n    問語，當眾向原告辱罵稱：「你去告啊！你不敢告，你就是\n    ㄋㄠ種，他媽的，幹！」等語。被告在大庭廣眾中辱罵原告\n    ，侵害原告名譽，使原告人格受辱並精神上蒙受重大痛苦，\n    經本院刑事庭以98年度易字第279號判決認定被告犯刑法第3\n    09條第1項之公然侮辱罪確定。爰依民法第184條第1項、第1\n    95條第1 項之規定請求被告負損害賠償之責等語，並聲明：\n    被告應給付原告新臺幣（下同）59萬元及自起訴狀繕本送達\n    翌日起至清償日止，按年息5％計算之利息。\n二、被告則以：被告於97年6 月10日調解時並無口出不雅言語，\n    被告因當時人在大陸而未提起上訴，但被告係因社區公共事\n    務與原告發生糾紛，且願意以書面公開方式向原告道歉，然\n    為原告所拒，被告目前失業中，經濟狀況非常窘困，原告請\n    求之金額，實不合理等語資為抗辯，並聲明：原告之訴駁回\n    。\n三、兩造不爭執之事實（見本院98年度審訴字第6354號卷，下稱\n    審訴卷，第36頁反面）：\n  (一)被告於97年至98年12月31日為臺北市國興國宅社區管理委員\n    會主任委員。\n  (二)原告以：其因社區領取福利金問題之爭議，向臺北市萬華區\n    調解委員會聲請調解，經該調解委員會於97年6月10日下午\n    在臺北市萬華區行政中心大禮堂之公共場所內，由調解委員\n    即訴外人李成光進行調解時，被告當場對原告為：「你去告\n    啊！你不敢告，你就是ㄋㄠ種，他媽的，幹！」之言語一事\n    ，向被告提出刑事告訴，經本院刑事庭以98年度易字第279\n    號判決認定被告犯刑法第309條第1項之公然侮辱罪，處拘役\n    35日，得易科罰金。\n四、原告主張被告於97年6 月10日下午某時許，在臺北市萬華區\n    行政中心大禮堂之公共場所內由調解委員即訴外人李成光進\n    行調解事宜時，當眾向原告辱罵稱：「你去告啊！你不敢告\n    ，你就是ㄋㄠ種，他媽的，幹！」等語，侵害原告名譽，使\n    原告人格受辱並精神上蒙受重大痛苦，而請求被告賠償原告\n    非財產上損害59萬元及遲延利息等語，則為被告所否認，並\n    以前揭情詞置辯。是本件主要爭點厥為：被告有無於上開時\n    地為前揭言語？被告應否對原告負侵權行為損害賠償之責？\n    原告請求被告賠償若干金額之慰撫金為適當？茲論述如下：\n  (一)經查，被告對於其曾於97年6 月10日下午某時許，至臺北市\n    萬華區行政大禮堂，就國興社區管理委員會發放福利金問題\n    與原告進行調解之事實，並不爭執。又被告係於97年6月10\n    日下午某時許，以國興社區管理委員會主任委員身分帶同其\n    他委員即訴外人陳水官、張堂治及陳秀鳳前往臺北市萬華區\n    行政中心大禮堂進行調解，而被告在調解委員李成光進行調\n    解事宜時，因不滿原告就其所述：「有繳交身分證和產權證\n    明影本予管委會之住戶難道都是傻瓜。」等語，提出臺北市\n    政府消防局於97年3月31日就國興社區所為之消防安全檢（\n    複）查不合規定限期改善通知單質疑稱：「一張消防缺失改\n    善通知單上，你為什麼要把身分證字號塗抹掉再公告呢？你\n    是不是區分所有權人？」等語，即憤而向原告辱罵稱：「你\n    去告啊！你不敢告，你就是ㄋㄠ種，他媽的，幹！」等語，\n    站立於原告及陳錦後方之鄭澄江隨即出言向被告制止稱：「\n    你怎麼可以罵人。」等語，調解委員李成光見狀即告稱：「\n    不要做人身攻擊。」等語，其後因陳錦與陳水官、張堂治就\n    前屆管理委員會委員侵占3 個月管理費之事另起爭執，該次\n    調解即無法繼續而調解不成立等情，業據原告於偵查及本院\n    刑事庭審理時結證明確，核與訴外人趙麗雲、陳錦及鄭澄江\n    於偵查及本院刑事庭審理時之證述相符（見臺灣臺北地方法\n    院檢察署97年度他字第6829號卷第12頁至第18頁，下稱他字\n    卷、本院刑事庭98年度易字第279號卷，下稱刑事一審卷第3\n    5 頁至第40頁、第42頁反面至第46頁、第58頁至第65頁），\n    並有國興社區管理委員會94年5月3日國興（選）字第940502\n    號公告、臺北市政府消防局消防安全檢（複）查不合規定限\n    期改善通知單、臺北市萬華區調解委員會97年民調字第207\n    號調解不成立證明書（見審訴卷第3頁至第4頁、他字卷第8\n    頁）附卷可佐，且被告所為上開言語，業經本院刑事庭以98\n    年度易字第279號判決認定被告犯刑法第309條第1 項之公然\n    侮辱罪，處拘役35日，得易科罰金。被告不服提起上訴後，\n    旋於98年9 月29日撤回其上訴等事實，有上開刑事判決（見\n    審訴卷第5 頁至第10頁）在卷足憑，並經本院職權調閱上開\n    刑事卷查明無訛。是堪認原告主張被告於97年6 月10日下午\n    某時許，在臺北市萬華區行政中心大禮堂之公共場所內由調\n    解委員李成光進行調解事宜時，當眾向原告辱罵稱：「你去\n    告啊！你不敢告，你就是ㄋㄠ種，他媽的，幹！」等語，應\n    為可採。被告空言抗辯其於97年6 月10日調解時並無口出不\n    雅言語云云，要非足取。\n  (二)按因故意或過失，不法侵害他人之權利者，負損害賠償責任\n    ；不法侵害他人之身體、健康、名譽、自由、信用、隱私、\n    貞操，或不法侵害其他人格法益而情節重大者，被害人雖非\n    財產上之損害，亦得請求賠償相當之金額，民法第184條第1\n    項前段、第195條第1項前段分別定有明文。又按慰藉金之賠\n    償須以人格權遭遇侵害，使精神上受有痛苦為必要，其核給\n    之標準，則可斟酌雙方身分、資力與加害程度，及其他各種\n    情形核定相當之數額（最高法院51年台上字第223 號判例意\n    旨參照）。查被告有於97年6 月10日下午某時許，在臺北市\n    萬華區行政中心大禮堂之公共場所內由調解委員李成光進行\n    調解事宜時，當眾向原告辱罵稱：「你去告啊！你不敢告，\n    你就是ㄋㄠ種，他媽的，幹！」等語之事實，已於前述，而\n    「ㄋㄠ種」一詞，本含有貶抑他人之意涵，且被告辱罵之際\n    ，參與該次調解委員會人員在場、聽聞，亦使渠等人員知悉\n    其事，衡諸一般社會通念，足認原告主張被告所為上開言語\n    係屬故意不法侵害原告之名譽，使原告人格受辱並精神上感\n    受痛苦等語，應為可採。是原告依侵權行為法則請求被告賠\n    償其非財產上損害，洵屬有據。本院審酌原告為屏東初中畢\n    業，97年財產所得資料顯示其名下有房屋、土地多筆，及薪\n    資所得12萬元，財產總額527萬7,074元。被告高中畢業，從\n    事設計工作，自98年7 月間起失業，於97年財產所得資料顯\n    示其名下有房地各1筆、投資8萬元，財產總額213萬3,030元\n    。此經兩造陳明在案（見本院審訴卷第29頁、本院卷第37頁\n    ），且有原告97年度綜合所得稅各類所得資料清單、兩造稅\n    務電子閘門財產所得調件明細表（見審訴卷第30頁、本院卷\n    第6頁至第30頁）附卷可考；另參酌被告固以「ㄋㄠ種」、\n    「他媽的」、「幹」等詞等語辱罵原告而侵害原告名譽，惟\n    在場聽聞之人僅為參與該次調解委員會會議之人員，原告名\n    譽遭受侵害程度尚非嚴重，且被告係因國興社區公共事務與\n    原告發生爭執，及被告於本件訴訟中已向原告表示歉意，欲\n    與原告和解，顯見其已深感悔悟（詳本院卷第36頁）等情，\n    認原告請求被告賠償59萬元，猶嫌過高，應以2 萬元始屬允\n    當，逾此部分之請求，即非可採，應予駁回。\n五、綜上所述，原告依侵權行為法律關係請求被告給付原告2 萬\n    元，及自起訴狀繕本送達翌日即99年1月4日起至清償日止，\n    按年息5％ 計算之利息為有理由，應予准許；逾此部分即無\n    理由，應予駁回。\n六、本件事證已明，兩造其餘攻擊防禦方法及所提之證據，核與\n    判決結果無影響，毋庸再予一一論述，附此敘明。\n七、據上論結，原告之訴為一部有理由，一部無理由，依民事訴\n    訟法第79條，判決如主文。"
  },
  "characters": {
    "judges": [
      "丁蓓蓓",
      "黃書苑",
      "周玉琦"
    ],
    "prosecutors": [

    ],
    "lawyers": [

    ],
    "clerks": [

    ],
    "plaintiffs": [
      "甲○○"
    ],
    "defendants": [
      "乙○○"
    ],
    "prosecutor_office": [

    ],
    "creditors": [

    ],
    "debtors": [

    ],
    "judicial_associate_officer": [

    ]
  },
  "adjudged_at": "2010-05-12",
  "created_at": "2016-01-05 12:16:12",
  "updated_at": "2016-01-05 12:16:12"
}