{
  "identify": "TPD-99-交簡上-16-20100512-1",
  "court": {
    "name": "臺灣臺北地方法院",
    "code": "TPD"
  },
  "division": {
    "name": "刑事",
    "code": "M"
  },
  "year": 99,
  "word": "交簡上",
  "number": "16",
  "jcheck": "1",
  "reason": "公共危險",
  "content": "臺灣臺北地方法院刑事判決            99年度交簡上字第16號\n上  訴  人  臺灣臺北地方法院檢察署檢察官\n上  訴  人\n即  被  告  甲○○\n選任辯護人  高鳳英律師\n上列上訴人因被告過失傷害案件，不服本院於中華民國98年12月\n23日所為之98年度交簡字第118號第一審簡易判決（起訴案號：\n臺灣臺北地方法院檢察署98年度調偵字第1170號），提起上訴，\n本院管轄之第二審合議庭判決如下：\n    主      文\n上訴駁回。\n甲○○緩刑貳年。\n    事實及理由\n一、本案經本院審理結果，認第一審簡易判決認事用法及量刑均\n    無不當，應予維持，並引用第一審判決書記載之事實、證據\n    及理由（如附件）。\n二、上訴意旨略以：上訴人即檢察官以告訴人因車禍受有頸椎第\n    6、7節左側神經孔狹窄併頸部疼痛、脊髓病變等傷害，需長\n    期復健及門診追蹤治療，造成告訴人身體上、精神上之損害\n    甚巨，本件被告雖願賠償新台幣（下同）275,000元，但尚\n    不足賠償告訴人所受損害，是原審以被告院以上揭金額與告\n    訴人和解，為告訴人所拒，認被告犯後態度尚稱良好，僅量\n    處拘役40日之刑，實非允當等理由，認量刑過輕，提起上訴\n    ；上訴人即被告甲○○則對原審判決所認定之事實及適用法\n    律均無爭執，僅表示已與被害人成立和解，希望可以給予緩\n    刑之機會（見99年度交簡上字第16號卷第157至159頁）等語\n    。經查：\n（一）原審經審理結果，認被告犯罪事證明確，因而適用刑法第\n      284條第1項前段、第62條前段、第41條第1項前段，刑法\n      施行法第1條之1等規定，本院併審酌被告因一時過失而罹\n      本件犯行，雖造成告訴人受有左第一指末端指骨折、雙側\n      上下肢多處挫傷及頸部扭傷（頸椎第6、7節左側神經孔狹\n      窄併頸部疼痛、脊髓病變）等傷害，然於本院審理時坦承\n      犯行（見本院卷第158頁），並以343,890元與告訴人和解\n      ，履行和解條件（見本院卷第73頁調解筆錄1紙、本院卷\n      第84頁告訴人陳報狀），犯罪後態度良好，原審之認事用\n      法，均無違誤，量刑亦屬妥適，檢察官上訴意旨以原審量\n      刑過輕，指摘原判決不當，實無理由，應予駁回。被告上\n      訴亦無理由，應予駁回。\n（二）末查，被告前未曾受有期徒刑以上刑之宣告，有臺灣高等\n      法院被告全國前案紀錄表在卷可稽，其於本院審理時坦認\n      犯行，並與告訴人和解，且已履行和解條件完畢。經告訴\n      人表示原諒並同意給予其緩刑之意（見本院卷第67頁背面\n      ），其因一時失慮，致罹刑章，本院認被告經此偵審程序\n      ，應知警惕而無再犯之虞，前開所宣告之刑以暫不執行為\n      適當，併予宣告緩刑2年，以啟自新。\n三、應適用之法律依據：\n    刑事訴訟法第455條之1第1項、第3項、第368條、第373條，\n    刑法第74條第1項第1款。\n本案經檢察官蘇維達到庭執行職務。\n中    華    民    國    99    年    5     月    12    日\n                  刑事第十一庭  審判長法  官  劉方慈\n                                      法  官  黃紹紘\n                                      法  官  顧正德\n上正本證明與原本無異。\n不得上訴。\n                                      書記官  郭錦賢\n中    華    民    國    99    年    5     月    13    日",
  "structure": {
    "main": "上訴駁回。\n甲○○緩刑貳年。",
    "fact": "一、本案經本院審理結果，認第一審簡易判決認事用法及量刑均\n    無不當，應予維持，並引用第一審判決書記載之事實、證據\n    及理由（如附件）。\n二、上訴意旨略以：上訴人即檢察官以告訴人因車禍受有頸椎第\n    6、7節左側神經孔狹窄併頸部疼痛、脊髓病變等傷害，需長\n    期復健及門診追蹤治療，造成告訴人身體上、精神上之損害\n    甚巨，本件被告雖願賠償新台幣（下同）275,000元，但尚\n    不足賠償告訴人所受損害，是原審以被告院以上揭金額與告\n    訴人和解，為告訴人所拒，認被告犯後態度尚稱良好，僅量\n    處拘役40日之刑，實非允當等理由，認量刑過輕，提起上訴\n    ；上訴人即被告甲○○則對原審判決所認定之事實及適用法\n    律均無爭執，僅表示已與被害人成立和解，希望可以給予緩\n    刑之機會（見99年度交簡上字第16號卷第157至159頁）等語\n    。經查：\n（一）原審經審理結果，認被告犯罪事證明確，因而適用刑法第\n      284條第1項前段、第62條前段、第41條第1項前段，刑法\n      施行法第1條之1等規定，本院併審酌被告因一時過失而罹\n      本件犯行，雖造成告訴人受有左第一指末端指骨折、雙側\n      上下肢多處挫傷及頸部扭傷（頸椎第6、7節左側神經孔狹\n      窄併頸部疼痛、脊髓病變）等傷害，然於本院審理時坦承\n      犯行（見本院卷第158頁），並以343,890元與告訴人和解\n      ，履行和解條件（見本院卷第73頁調解筆錄1紙、本院卷\n      第84頁告訴人陳報狀），犯罪後態度良好，原審之認事用\n      法，均無違誤，量刑亦屬妥適，檢察官上訴意旨以原審量\n      刑過輕，指摘原判決不當，實無理由，應予駁回。被告上\n      訴亦無理由，應予駁回。\n（二）末查，被告前未曾受有期徒刑以上刑之宣告，有臺灣高等\n      法院被告全國前案紀錄表在卷可稽，其於本院審理時坦認\n      犯行，並與告訴人和解，且已履行和解條件完畢。經告訴\n      人表示原諒並同意給予其緩刑之意（見本院卷第67頁背面\n      ），其因一時失慮，致罹刑章，本院認被告經此偵審程序\n      ，應知警惕而無再犯之虞，前開所宣告之刑以暫不執行為\n      適當，併予宣告緩刑2年，以啟自新。\n三、應適用之法律依據：\n    刑事訴訟法第455條之1第1項、第3項、第368條、第373條，\n    刑法第74條第1項第1款。\n本案經檢察官蘇維達到庭執行職務。",
    "reason": "一、本案經本院審理結果，認第一審簡易判決認事用法及量刑均\n    無不當，應予維持，並引用第一審判決書記載之事實、證據\n    及理由（如附件）。\n二、上訴意旨略以：上訴人即檢察官以告訴人因車禍受有頸椎第\n    6、7節左側神經孔狹窄併頸部疼痛、脊髓病變等傷害，需長\n    期復健及門診追蹤治療，造成告訴人身體上、精神上之損害\n    甚巨，本件被告雖願賠償新台幣（下同）275,000元，但尚\n    不足賠償告訴人所受損害，是原審以被告院以上揭金額與告\n    訴人和解，為告訴人所拒，認被告犯後態度尚稱良好，僅量\n    處拘役40日之刑，實非允當等理由，認量刑過輕，提起上訴\n    ；上訴人即被告甲○○則對原審判決所認定之事實及適用法\n    律均無爭執，僅表示已與被害人成立和解，希望可以給予緩\n    刑之機會（見99年度交簡上字第16號卷第157至159頁）等語\n    。經查：\n（一）原審經審理結果，認被告犯罪事證明確，因而適用刑法第\n      284條第1項前段、第62條前段、第41條第1項前段，刑法\n      施行法第1條之1等規定，本院併審酌被告因一時過失而罹\n      本件犯行，雖造成告訴人受有左第一指末端指骨折、雙側\n      上下肢多處挫傷及頸部扭傷（頸椎第6、7節左側神經孔狹\n      窄併頸部疼痛、脊髓病變）等傷害，然於本院審理時坦承\n      犯行（見本院卷第158頁），並以343,890元與告訴人和解\n      ，履行和解條件（見本院卷第73頁調解筆錄1紙、本院卷\n      第84頁告訴人陳報狀），犯罪後態度良好，原審之認事用\n      法，均無違誤，量刑亦屬妥適，檢察官上訴意旨以原審量\n      刑過輕，指摘原判決不當，實無理由，應予駁回。被告上\n      訴亦無理由，應予駁回。\n（二）末查，被告前未曾受有期徒刑以上刑之宣告，有臺灣高等\n      法院被告全國前案紀錄表在卷可稽，其於本院審理時坦認\n      犯行，並與告訴人和解，且已履行和解條件完畢。經告訴\n      人表示原諒並同意給予其緩刑之意（見本院卷第67頁背面\n      ），其因一時失慮，致罹刑章，本院認被告經此偵審程序\n      ，應知警惕而無再犯之虞，前開所宣告之刑以暫不執行為\n      適當，併予宣告緩刑2年，以啟自新。\n三、應適用之法律依據：\n    刑事訴訟法第455條之1第1項、第3項、第368條、第373條，\n    刑法第74條第1項第1款。\n本案經檢察官蘇維達到庭執行職務。"
  },
  "characters": {
    "judges": [
      "劉方慈",
      "黃紹紘",
      "顧正德"
    ],
    "prosecutors": [
      "蘇維達"
    ],
    "lawyers": [
      "高鳳英"
    ],
    "clerks": [
      "郭錦賢"
    ],
    "plaintiffs": [

    ],
    "defendants": [
      "甲"
    ],
    "prosecutor_office": [

    ],
    "creditors": [

    ],
    "debtors": [

    ],
    "judicial_associate_officer": [

    ]
  },
  "adjudged_at": "2010-05-12",
  "created_at": "2016-01-05 12:05:48",
  "updated_at": "2016-01-05 12:05:48"
}