{
  "identify": "TPD-98-交易-589-20100512-1",
  "court": {
    "name": "臺灣臺北地方法院",
    "code": "TPD"
  },
  "division": {
    "name": "刑事",
    "code": "M"
  },
  "year": 98,
  "word": "交易",
  "number": "589",
  "jcheck": "1",
  "reason": "業務過失傷害",
  "content": "臺灣臺北地方法院刑事判決            98年度交易字第589 號\n公  訴  人  臺灣臺北地方法院檢察署檢察官\n被      告  乙○○\n上列被告因業務過失傷害案件，經檢察官提起公訴（98年度調偵\n字第1039號），本院判決如下：\n    主  文\n本件公訴不受理。\n    理  由\n一、公訴意旨略以：被告乙○○係計程車司機，為從事駕駛業務\n    之人，其於民國98年6月29日下午3時許，駕駛車牌號碼2E-7\n    02號營業用小客車，沿臺北市○○區○○路，由東向西方向\n    行駛，行經上開濟南路與紹興南街口左轉至紹興南街時，本\n    應注意左轉彎時，應先顯示車輛前後之左邊方向燈光，或由\n    駕駛人表示左臂平伸，手掌向下之手勢，且應注意車前狀況\n    ，並隨時採取必要之安全措施，而依當時並無不能注意之情\n    事，竟疏未注意而貿然左轉，適有訴外人劉佳峰騎乘車牌號\n    碼57 5-EWL號機車，其上搭載告訴人甲○○，沿濟南路由西\n    往東方向行駛，行至上開濟南路與紹興南街口處，劉佳峰因\n    未見被告駕駛之前揭小客車顯示左轉燈光，遂閃避不及而煞\n    車打滑，致該機車車尾及後座之告訴人甲○○撞及被告所駕\n    駛之上揭小客車右後方，致告訴人受有肝臟撕裂傷、左側肩\n    胛骨折、右側肋骨骨折、骨盆骨折等處之傷害，因認被告涉\n    犯刑法第284條第2項前段之業務過失傷害罪嫌。\n二、按告訴乃論之罪，告訴人於第一審辯論終結前，得撤回其告\n    訴；又告訴經撤回者，法院應諭知不受理之判決，並得不經\n    言詞辯論為之，刑事訴訟法第238條第1項，及第303條第3款\n    、第307條分別定有明文。\n三、查，被告涉犯刑法第284條第2項前段業務過失傷害案件，經\n    檢察官提起公訴，並有起訴書在卷可稽。惟按刑法第284 條\n    第2項前段業務過失傷害罪，依同法第287條前段規定須告訴\n    乃論，而被告及告訴人經本院勸導息訟，並均同意由本院轉\n    介至財團法人保險事業發展中心（址設臺北市○○區○○路\n    三號六樓）協調成立，而告訴人於第一審辯論終結前之99年\n    4 月21日撤回告訴，並有刑事撤回告訴狀、和解書、財團法\n    人保險事業發展中心99年4 月21日99保調字第0935號函及其\n    檢附資料在卷可稽（見本院卷第12至22頁）。因此，揆諸上\n    開規定及說明，本件爰不經言詞辯論，逕為諭知不受理之判\n    決。\n四、據上論斷，應依刑事訴訟法第284條之1、第303條第3款、第\n    307條，判決如主文。\n中    華    民    國    99    年    5     月    12    日\n                  交通法庭法  官  施添寶\n以上正本證明與原本無異。\n如不服本判決應於收受本判決後10日內向本院提出上訴書狀，並\n應敘述具體理由，如未敘述上訴理由者，應於上訴期間屆滿後20\n日內補提理由書狀於本院（均須按他造當事人之人數附繕本）「\n切勿逕送上級法院」。告訴人或被害人如對於本判決不服者，應\n具備理由請求檢察官上訴，其上訴期間之計算係以檢察官收受判\n決正本之日期為準。\n                          書記官  陳弘文\n中    華    民    國    99    年    5     月    12    日",
  "structure": {
    "main": "本件公訴不受理。",
    "reason": "一、公訴意旨略以：被告乙○○係計程車司機，為從事駕駛業務\n    之人，其於民國98年6月29日下午3時許，駕駛車牌號碼2E-7\n    02號營業用小客車，沿臺北市○○區○○路，由東向西方向\n    行駛，行經上開濟南路與紹興南街口左轉至紹興南街時，本\n    應注意左轉彎時，應先顯示車輛前後之左邊方向燈光，或由\n    駕駛人表示左臂平伸，手掌向下之手勢，且應注意車前狀況\n    ，並隨時採取必要之安全措施，而依當時並無不能注意之情\n    事，竟疏未注意而貿然左轉，適有訴外人劉佳峰騎乘車牌號\n    碼57 5-EWL號機車，其上搭載告訴人甲○○，沿濟南路由西\n    往東方向行駛，行至上開濟南路與紹興南街口處，劉佳峰因\n    未見被告駕駛之前揭小客車顯示左轉燈光，遂閃避不及而煞\n    車打滑，致該機車車尾及後座之告訴人甲○○撞及被告所駕\n    駛之上揭小客車右後方，致告訴人受有肝臟撕裂傷、左側肩\n    胛骨折、右側肋骨骨折、骨盆骨折等處之傷害，因認被告涉\n    犯刑法第284條第2項前段之業務過失傷害罪嫌。\n二、按告訴乃論之罪，告訴人於第一審辯論終結前，得撤回其告\n    訴；又告訴經撤回者，法院應諭知不受理之判決，並得不經\n    言詞辯論為之，刑事訴訟法第238條第1項，及第303條第3款\n    、第307條分別定有明文。\n三、查，被告涉犯刑法第284條第2項前段業務過失傷害案件，經\n    檢察官提起公訴，並有起訴書在卷可稽。惟按刑法第284 條\n    第2項前段業務過失傷害罪，依同法第287條前段規定須告訴\n    乃論，而被告及告訴人經本院勸導息訟，並均同意由本院轉\n    介至財團法人保險事業發展中心（址設臺北市○○區○○路\n    三號六樓）協調成立，而告訴人於第一審辯論終結前之99年\n    4 月21日撤回告訴，並有刑事撤回告訴狀、和解書、財團法\n    人保險事業發展中心99年4 月21日99保調字第0935號函及其\n    檢附資料在卷可稽（見本院卷第12至22頁）。因此，揆諸上\n    開規定及說明，本件爰不經言詞辯論，逕為諭知不受理之判\n    決。\n四、據上論斷，應依刑事訴訟法第284條之1、第303條第3款、第\n    307條，判決如主文。"
  },
  "characters": {
    "judges": [
      "施添寶"
    ],
    "prosecutors": [

    ],
    "lawyers": [

    ],
    "clerks": [
      "陳弘文"
    ],
    "plaintiffs": [

    ],
    "defendants": [
      "乙○○"
    ],
    "prosecutor_office": [
      "臺灣臺北地方法院檢察署檢察官"
    ],
    "creditors": [

    ],
    "debtors": [

    ],
    "judicial_associate_officer": [

    ]
  },
  "adjudged_at": "2010-05-12",
  "created_at": "2016-01-05 12:06:09",
  "updated_at": "2016-01-05 12:06:09"
}