{
  "identify": "TPD-98-聲-3409-20100104-1",
  "court": {
    "name": "臺灣臺北地方法院",
    "code": "TPD"
  },
  "division": {
    "name": "刑事",
    "code": "M"
  },
  "year": 98,
  "word": "聲",
  "number": "3409",
  "jcheck": "1",
  "reason": "聲請單獨宣告沒收違禁物",
  "content": "臺灣臺北地方法院刑事裁定              98年度聲字第3409號\n聲  請  人  臺灣臺北地方法院檢察署檢察官\n被      告  甲○○\n上列聲請人聲請單獨宣告沒收違禁物案件（98年度聲沒字第400\n號），本院裁定如下：\n    主  文\n扣案之第一級毒品海洛因壹包（驗餘淨重零點壹捌壹柒公克）沒\n收銷燬之。\n    理  由\n一、按違禁物不問屬於犯人所有與否，得單獨宣告沒收，刑法第\n    38條第1項第1款、第2項及第40條第2項分別定有明文。另依\n    毒品危害防制條例第18條第1 項前段之規定，查獲之毒品，\n    不論屬於犯人與否，均沒收銷燬之。\n二、聲請意旨略以：被告甲○○前因違反毒品危害防制條例案件\n    ，業經臺灣臺北地方法院檢察署檢察官以98年度毒偵字第19\n    17號為不起訴處分確定，其於民國98年5月2日在台中市南屯\n    區樂田巷15號之1，經警查獲而扣押之第一級毒品海洛因1\n    包（驗餘淨重0.1817公克），係屬違禁物，爰依首揭法律規\n    定，聲請宣告沒收銷燬等語。\n三、經查，扣案之白色粉末1包，經送鑑驗結果檢出第一級毒品\n    海洛因（Heroin）成分（驗餘淨重0.1817公克），有98年5\n    月7日行政院衛生署草屯療養院鑑定書1紙附卷可稽，是聲請\n    意旨確與上開法條之規定，尚無不合。爰依刑事訴訟法第22\n    0條、刑法第40條第2項、毒品危害防制條例第18條第1項前\n    段之規定，裁定如主文。\n中    華    民    國    99    年    1     月    4     日\n                  刑事第八庭    法  官  林鳳珠\n以上正本證明與原本無異\n如不服本裁定應於送達後5日內向本院提出抗告狀\n                                書記官  黃鈴容\n中    華    民    國    99    年    1     月    4     日",
  "structure": {
    "main": "扣案之第一級毒品海洛因壹包（驗餘淨重零點壹捌壹柒公克）沒\n收銷燬之。",
    "reason": "一、按違禁物不問屬於犯人所有與否，得單獨宣告沒收，刑法第\n    38條第1項第1款、第2項及第40條第2項分別定有明文。另依\n    毒品危害防制條例第18條第1 項前段之規定，查獲之毒品，\n    不論屬於犯人與否，均沒收銷燬之。\n二、聲請意旨略以：被告甲○○前因違反毒品危害防制條例案件\n    ，業經臺灣臺北地方法院檢察署檢察官以98年度毒偵字第19\n    17號為不起訴處分確定，其於民國98年5月2日在台中市南屯\n    區樂田巷15號之1，經警查獲而扣押之第一級毒品海洛因1\n    包（驗餘淨重0.1817公克），係屬違禁物，爰依首揭法律規\n    定，聲請宣告沒收銷燬等語。\n三、經查，扣案之白色粉末1包，經送鑑驗結果檢出第一級毒品\n    海洛因（Heroin）成分（驗餘淨重0.1817公克），有98年5\n    月7日行政院衛生署草屯療養院鑑定書1紙附卷可稽，是聲請\n    意旨確與上開法條之規定，尚無不合。爰依刑事訴訟法第22\n    0條、刑法第40條第2項、毒品危害防制條例第18條第1項前\n    段之規定，裁定如主文。"
  },
  "characters": {
    "judges": [
      "林鳳珠"
    ],
    "prosecutors": [

    ],
    "lawyers": [

    ],
    "clerks": [
      "黃鈴容"
    ],
    "plaintiffs": [

    ],
    "defendants": [
      "甲○○"
    ],
    "prosecutor_office": [
      "臺灣臺北地方法院檢察署檢察官"
    ],
    "creditors": [

    ],
    "debtors": [

    ],
    "judicial_associate_officer": [

    ]
  },
  "adjudged_at": "2010-01-04",
  "created_at": "2016-01-05 14:41:06",
  "updated_at": "2016-01-05 14:41:06"
}