{
  "identify": "TPD-99-除-920-20100512-1",
  "court": {
    "name": "臺灣臺北地方法院",
    "code": "TPD"
  },
  "division": {
    "name": "民事",
    "code": "V"
  },
  "year": 99,
  "word": "除",
  "number": "920",
  "jcheck": "1",
  "reason": "除權判決",
  "content": "臺灣臺北地方法院民事判決               99年度除字第920號\n聲  請  人  甲○○\n上列聲請人聲請除權判決事件，本院判決如下：\n    主  文\n如附表所示之證券無效。\n訴訟費用由聲請人負擔。\n    理  由\n一、上開證券，經本院以99年度司催字第13號公示催告。\n二、所定申報權利期間，已於民國99年4月13日屆滿，迄今無人\n    申報權利。\n三、依民事訴訟法第564條第1項，判決如主文。\n中    華    民    國    99    年    5     月    12    日\n                  民事第三庭  審判長法  官  丁蓓蓓\n                                    法  官  魏式瑜\n                                    法  官  周玉琦\n以上正本證明係照原本作成。\n本判決不得上訴。\n中    華    民    國    99    年    5     月     12   日\n                                    書記官  劉英權\n┌───────────────────────────────────┐\n│附表：                                              99年度除字第920號 │\n├──┬─────────┬─────────┬───┬────┬───┤\n│編號│ 發  行  公  司   │股  票  號  碼    │張  數│股    數│備  考│\n├──┼─────────┼─────────┼───┼────┼───┤\n│001 │台橡股份有限公司  │0088-NX-0000000-0 │1     │672     │      │\n└──┴─────────┴─────────┴───┴────┴───┘",
  "structure": {
    "main": "如附表所示之證券無效。\n訴訟費用由聲請人負擔。",
    "reason": "一、上開證券，經本院以99年度司催字第13號公示催告。\n二、所定申報權利期間，已於民國99年4月13日屆滿，迄今無人\n    申報權利。\n三、依民事訴訟法第564條第1項，判決如主文。"
  },
  "characters": {
    "judges": [
      "丁蓓蓓",
      "魏式瑜",
      "周玉琦"
    ],
    "prosecutors": [

    ],
    "lawyers": [

    ],
    "clerks": [
      "劉英權"
    ],
    "plaintiffs": [

    ],
    "defendants": [

    ],
    "prosecutor_office": [
      "甲"
    ],
    "creditors": [

    ],
    "debtors": [

    ],
    "judicial_associate_officer": [

    ]
  },
  "adjudged_at": "2010-05-12",
  "created_at": "2016-01-05 12:12:52",
  "updated_at": "2016-01-05 12:12:52"
}