{
  "identify": "TPD-98-重勞訴-2-20100512-1",
  "court": {
    "name": "臺灣臺北地方法院",
    "code": "TPD"
  },
  "division": {
    "name": "民事",
    "code": "V"
  },
  "year": 98,
  "word": "重勞訴",
  "number": "2",
  "jcheck": "1",
  "reason": "給付資遣費",
  "content": "臺灣臺北地方法院民事判決             98年度重勞訴字第2號\n原      告  林瑞宗\n訴訟代理人  黃翎芳律師\n複代理人    何新琦\n複代理人    鄧翊鴻律師\n被      告  富邦人壽保險股份有限公司\n法定代理人  蔡明興\n訴訟代理人  謝佩圜\n            黃杉睿\n上列當事人間給付資遣費事件，本院於民國99年4月26日言詞辯\n論終結，判決如下：\n    主  文\n原告之訴及假執行之聲請均駁回。\n訴訟費用由原告負擔。\n    事實及理由\n壹、程序方面：\n一、本件被告富邦人壽保險股份有限公司於民國98年6月1日與安\n    泰人壽保險股份公司合併，安泰人壽保險股份有限公司為存\n    續公司，合併後，安泰人壽保險股份有限公司變更名稱為富\n    邦人壽保險股份有限公司。被告於98年6月22日聲明書狀承\n    受訴訟，並提出經濟部98年6月1日經授商字第09801100490\n    號函及公司變更登記表影本在卷可稽，先予敘明。\n二、按訴狀送達後，原告不得將原訴變更或追加他訴，但擴張或\n    減縮應受判決事項之聲明者，不在此限，民事訴訟法第255\n    條第1項第3款定有明文。原告起訴時原聲明請求被告給付\n    新臺幣（下同）8,556,640元及自起訴狀繕本送達翌日起至\n    清償日止按年息5%計算之利息，並願供擔保請准宣告假執行\n    （見本院北勞調卷第3頁）；嗣於本院審理中，於97年8月22\n    日具狀減縮訴之聲明第一項為：被告應給付原告7,479,232\n    元及自起訴狀繕本送達翌日起至清償日止按年息5%計算之利\n    息（見本院卷(一)第5頁）；又於97年9月1日具狀減縮訴之聲\n    明第一項為：被告應給付原告7,086,440元及自起訴狀繕本\n    送達翌日起至清償日止按年息5%計算之利息（見本院卷(一)第\n    14頁）；後於98年8月3日具狀減縮訴之聲明第一項為被告應\n    給付原告6,097,935元及自起訴狀繕本送達翌日起至清償日\n    止按年息5%計算之利息（見本院卷(三)第66頁）。經核原告所\n    為均係基於同一訴訟事實減縮應受判決事項之聲明，依前揭\n    規定，自應准許。\n貳、實體方面：\n一、原告主張：\n  (一)原告自85年7月1日起受僱於被告公司，由業務員晉升至總監\n    ，然被告公司卻於97年5月30日，以原告藉職權對同仁多項\n    管理領導不當引發爭議為由，將原告由中央通訊處總監一職\n    降為業務經理，並取消相關應屬原告之工資，然原告任職於\n    被告公司之期間並未有任何失職之處，被告除卻未經詳查，\n    亦未給原告任何申訴之機會，亦未召開人評會，即原告予以\n    降職減薪，核被告所為已違反勞動基準法（下稱勞基法）第\n    14條第1項第5款前段、第6款規定，原告遂於97年6月25日以\n    臺中市英才郵局01345號存證信函終止兩造間勞動契約，並\n    要求被告給付資遣費。\n  (二)原告任職被告公司期間自85年8月1日到職受僱於被告公司後\n    ，至97年6月25日終止兩造勞動契約之日之97年1月至97年6\n    月之工資，其中97年1月之薪資為432,612元（不含被告所主\n    張之承攬契約報酬）、97年2月之薪資為321,408元、97年3\n    月之薪資為403,687元、97年4月之薪資為373,058元、97年5\n    月之薪資為455,594元，97年6月之薪資為101,109元，再加\n    計如仍任總監所得增領之97年6月薪資151﹐833元，合計原\n    告任職於公司97年1月至97年6月之薪資總額為2,239,301元\n    ，則被告終止勞動契約前六個之平均工資為373﹐217元。又\n    原告自85年8月1日到職受僱於被告公司後，至97年6月25日\n    終止兩造勞動契約之日，合計年資原應為12年，惟原告自95\n    年12月1日起，就資遣費部分已改由新制勞工保險條例而提\n    撥退休金於勞保年金，故逾95年12月1日之年資部分，依勞\n    工退休金條例，原告得請求之資遣費為每滿一年後被告公司\n    應發給2分之1個月之平均工資，故被告應給付原告10年又4\n    個月之一個月平均工資之資遣費，及1年又7個月之2分之1個\n    月平均工資之資遣費；以原告終止兩造間之勞動契約之日前\n    之六個月平均工資為373,217元，每日之平均薪資為12,446\n    元【計算式：373,217元÷30天=12,446元/日，小數點以下\n    捨去】，故被告公司應給付原告之資遣費為4,152,039元【\n    計算式：（373,217元/月×10又4/12月）＋（373,217元/月\n    ×1/2×1又7/12月）＝4,152,039元】。\n  (三)原告受雇被告公司已12年，以原告終止兩造間之勞動契約之\n    日前之六個月平均工資為373,217元，每日之平均薪資為12,\n    446元，原告終止勞動契約時前5年應休特別休假之日數為76\n    日，故計算兩造契約終止時之前五年之特別休假之工資，被\n    告應給付原告之特別休假之工資945,896元【計算式：76日\n    ×12,446元＝945,896元】。\n  (四)被告以原告藉職權對業務同仁多項管理、領導為不當，並影\n    響團隊士氣為由，將原告降職及減薪，係不實之事實指述，\n    且被告懲處函文係發函予被告公司之內勤人員、各區部公號\n    、各通訊處公號、業務同仁等，已使特定人或不特定人置於\n    隨時可見聞之狀態；另被告97年6月30日於淡水教育中心之\n    處經理組訊會議中，以原告多項管理行為不善引發爭議之不\n    實事項，公開指名道姓，並據以引為被告公司組訓之案例，\n    被告顯有意圖侵害原告之名譽，致原告名譽受損害及產生精\n    神上痛苦，爰依民法第195條規定請求被告賠償100萬元之非\n    財產之損害。\n  (五)綜上，原告請求被告給付資遺費4,152,039元、特別休假之\n    工資945,896元及非財產上之損害賠償100萬元，合計6,097,\n    935元。並聲明：被告應給付原告6,097,935元及自起訴狀繕\n    本送達之翌日起至清償日止按年息5%計算之利息，並願供擔\n    保請准宣告假執行。\n二、被告則以：(一)原告於85年8月1日與被告簽訂聘用保險業務員\n    契約書而任職於被告公司，兩造間並於87年4月1日簽訂僱傭\n    契約與承攬契約，約定原告應遵守被告所頒布之工作相關規\n    範。因原告對同仁有不當職場言語及肢體行為，復因原告對\n    被告公司之財務管理交代不清、違反公司規定私聘業務助理\n    、宣導不當之招攬保險方式等影響金融專業形象之行為，經\n    被告公司稽核單位查證屬實後，原告已不適任管理職務，基\n    於企業經營之必要性及合理性，由被告管理單位於97年5月\n    30日以「藉職權對業務同仁多項管理、領導行為不當，引發\n    爭議，並影響團隊士氣」為由，將原告停止主管職務，調整\n    為非管理職之業務經理，被告並未侵害原告之工作權，亦未\n    侵害其直轄業務員部分，一切業務運作回歸總公司暫為監管\n    。原告於97年6月25日以存證信函通知被告終止系爭勞動契\n    約，被告公司於97年7月11日同意終止系爭勞動契約，系爭\n    勞動契約係經兩造合意終止，原告主張資遣費並無依據；(二)\n    縱被告應給付資遣費，原告平均工資之計算不應包括承攬契\n    約之報酬，且原告於97年6月1日已調整為非管理職，其平均\n    工資之計算，自當不應包含管理職之部分，原告之平均工資\n    應為薪資表冊列計之347,911元。又行政院勞工委員會函公\n    告保險業自87年4月1日納入勞基法適用，在適用勞基法前，\n    兩造間並無約定資遣費及退休金給予標準，故適用勞基法前\n    之期間，不應列計給付年資計算，則依勞基法第84-2條規定\n    ，原告資遣費之給付年資應自87年4月1日起至97年7月11日\n    止，其年資基數之計算應為自87年4月1日至95年11月30日共\n    計8年8個月，年資基數為8.67（計算式：8.67×1＝8.67）\n    ；自95年12月1日至97年7月11日共計1年8個月，年資基數為\n    0.83（計算式：1.66×0.5＝0.83），共計為9.5，故原告之\n    資遣費應為3,305,155元（計算式：347,911×9.5＝3,305,\n    155）；(三)原告任職於被告公司期間，給假均正常，又因其\n    業務性質自主性強，與勞基法上之勞工特性不同，除了每日\n    早上約一小時之教育訓練課程及業務宣導外，均得自由活動\n    ，原告得充分安排其工作時間，此由原告94年請假23日，而\n    被告並未計以事假而扣其薪資足證之。另被告每日早上之會\n    議係由各業務單位主管、組訓輪流主持，並進行主題之報告\n    ，並非必須由原告親自主持，被告亦無此項規範，如原告遇\n    有配合客戶或其他私事待辦，仍得辦理請假手續而由職務代\n    理人代為處理事務，故原告有充分的權利與機會安排每年度\n    的特別休假。原告自身認知上的誤謬、安排不當以及其自請\n    離職致特別休假未休完，屬可歸責於己之事由，被告可不發\n    給未休日數之工資；若本院認責任制之管理適用勞基法之特\n    別休假獎金計算，且原告未休完特休假係不可歸責於原告而\n    可請求特別休假獎金，則原告每日平均工資為11,597元，其\n    93年至97年未休假天數應為25日（計算式：給假總天數76－\n    請假天數42－缺席天數9＝25），特別休假獎金應為289,925\n    元（計算式：11,597×25＝289,925）；其97年未休假天數\n    為5日（計算式：給假總天數17－請假天數6－缺席天數6＝5\n    ），特別休假獎金應為57,985元（計算式：11,597×5＝\n    57,985）；(四)被告並未以原告作為討論之議題引發不當之爭\n    議，或意圖侵害原告名譽之情形，對於原告所懲處之事實情\n    形，僅以概括之文字記載公告之，且僅於被告企業內部網站\n    得觀看，並無侵害原告之名譽。而原告自請離職後，仍於同\n    業就職，被告對於其他單位人員詢問原告之工作表現時，均\n    未有任何不利於原告之言詞，原告主張被告侵害其名譽權，\n    須就被告有使原告社會上對其個人評價有貶損之故意或過失\n    負舉證責任等語資為抗辯，並聲明：原告之訴駁回，如受不\n    利判決，願供擔保請准宣告免為假執行。\n三、兩造不爭執之事實：\n  (一)原告自85年8月1日其任職被告公司，97年間離職時為總監。\n    業務經理。\n  (三)原告於97年6月25日以台中英才路郵局第1345號存證信函，\n    通知被告終止勞動契約。\n  (四)被告於97年7月11日發函給原告。\n四、原告請求被告給付資遺費4,152,039元、特別休假之工資945\n    ,896元及非財產上之損害賠償100萬元，合計6,097,935元，\n    被告則以前揭情詞置辯，是本件爭點厥為：(一)原告主張被告\n    公司之行為違反勞基法第14條第1項第5款前段、第6款規定\n    ，而終止勞動契約，並請求資遺費，有無理由；(二)原告請求\n    終止勞動契約時前5年應休特別休假之日數為76日之特別休\n    假之工資，有無理由；(三)原告主張被告侵害其名譽權，而請\n    求精神上之損害賠償，有無理由。茲分述如下：\n  (一)按雇主為達成營業目的，具有指揮監督勞工之權限，即雇主\n    有人事權為勞動契約之核心內容之一，是雇主對勞工之調動\n    升已有一定準則，且其調動升遷非以專損害勞工權益為目的\n    ，自應尊重雇主之人事自主權。經查，原告於離職時，係被\n    告公司總監，為被告公司中區業務部之最高主管等情，為原\n    告陳明在卷（見本院卷(一)第103頁），原告既身為最高主管\n    人員，首要者需有各組織之認同，並能引導士氣、形成向心\n    力之人員，以凝結合作團隊之精神。查證人即被告公司業務\n    部協理黃傑到庭證稱：「……原告後來又變成業務部經理是\n    因為原告在通訊處期間有很多同事反應原告有很多缺失的狀\n    況，我們有委請稽核瞭解，請這些反應的人出具書面資料說\n    明，根據這些資料說明我們就做一些懲處決議，我們是認為\n    原告在管理上有缺失，包含與業務同仁收取不當款項，帳目\n    不清楚，我們確實有去查帳，因為公司有規定帳目要依基金\n    管理辦法製作帳目，我們有去調帳目來看，覺得帳目不清，\n    相關細節我不清楚，另同仁的抱怨有很多，主要抱怨原告不\n    公平，例如對某些同仁比較好，比較多是針對劉淑芬與他帶\n    進來的人，原告之所以對劉淑芬與他帶進來的人比較不好我\n    們有去瞭解原因可能是他與劉淑芬之間有私人金錢往來而產\n    生不愉快。處理過程中我們有要求他們提出相關借據等等資\n    料，但都沒有提出。我們調查的過程認為原告在領導管理有\n    出嚴重的問題，所以我們將他調整為業務經理只管自己轄下\n    的業務員」、「……有很多關於系爭通訊處人員不合跟財物\n    不清的傳言，我們有去訪談其他諸如部長、組訓（就是中央\n    派駐地方作組織訓練、政令宣導的人），他們確實反應有這\n    些問題」等語（見本院卷(一)第191頁反面、第192頁）；證人\n    即被告公司稽核室經理黃文正到庭證稱：「（法官問：稽核\n    室從事何事？）負責公司業務查核，包含人員違失的查核，\n    本件原告的查核是部門的稽核人員負責，當初查核原告的原\n    因是業務部門接到業務人員的申訴書，會請我們去求證，我\n    們才派員去原告的通訊處查核，97年3月時我稽核室有派員\n    去台中作這10個申訴人員的訪談，願意作訪談的人有5位，\n    我們主要是確認申訴內容是否真正，及確認是否為申訴人的\n    原意，5位申訴者有告知我們申訴函確實是他們表達的意思\n    ，申訴者有反應不能認同主管的管理方法，覺得不公平，有\n    個人不妥當的行為。其中壹份申訴函中有提到主管對於獎勵\n    金的運用有問題，我們有用電話與業務人員查證，業務人員\n    也表達當初處經理提到的獎勵是由業務人員提供發票領取，\n    但最後是由主管統籌運用，與當初業務人員獲悉的不一樣，\n    也沒有領到這筆獎勵金。我們主要是針對人員管理、獎勵金\n    的部分，我們有去訪查，及用電話查獎勵金的分配，之後是\n    將稽核的結果業務部處理。申訴的人是否都是劉淑芬轄下的\n    人員我不清楚。在稽核的過程中我們有拜訪原告，也有請他\n    就申訴人提到的問題作陳述，原告事後有寫一個報告，我們\n    對於這個報告書沒有作判斷，我們全部移交業務部門決定。\n    」等語（見本院卷(一)192頁反面、第193頁）；證人王大維證\n    稱：「……被證十八就是我調查的結論，調查期間也有很多\n    不合公司內部規定的情形，所以我有寫類似請示案，看是否\n    可以做工作的適當調整。」（見本院卷(三)第62頁），顯見被\n    告公司對於原告之行為，提交稽核單位查證，認其行為確實\n    不適合擔任主管職務，被告公司基於原告不當之管理、領導\n    能力而為組織調整，屬被告公司基於企業營運管理考量所做\n    之必要調整，而被告公司之業務組織中，非管理職最高職務\n    即為「業務經理」等情，業據被告陳明在卷可按（見卷(三)第\n    197頁），原告既有不當之管理行為，已不適合擔任主管職\n    務，被告公司將原告調整為非管理職之最高職務「業務經理\n    」，並不構成勞基法第14條第1項第6款「雇主違反勞動契約\n    或勞工法令，致有損害勞工權益之虞」之事由。又原告亦自\n    承其主張被告取消其相關原屬工資，係計算報酬之方式由總\n    監職務改依業務經理之職務計算等語（見本院卷(三)第169頁\n    ），參諸擔任不同之工作，其受領之工資當有所不同之理，\n    是被告公司依據原告之職務而計算其薪資，亦不構成勞基法\n    第14條第5款前段「雇主不依勞動契約給付工作報酬」之事\n    由，是原告主張依勞基法第14條第1項第5款前段、第6款規\n    定終止勞動契約，尚屬無據。原告既不得依勞基法第14條第\n    1項第5款前段、第6款之規定終止系爭勞動契約，則其依同\n    法第14條第4項準用第17條之規定請求被告給付資遣費，即\n    屬無據，故原告請求被告給付資遣費4,152,039元，並無理\n    由。\n  (二)按勞基法第38條規定，雇主經徵得勞工同意於休假日工作者\n    ，工資應加倍發給。因季節性關係有趕工必要，經勞工或工\n    會同意照常工作者，亦同；勞動基準法施行細則第24條則規\n    定，本法第38條之特別休假，特別休假日期應由勞雇雙方協\n    商排定之。特別休假因年度終結或終止契約而未休者，其應\n    休未休之日數，雇主應發給工資。據此，可知特別休假雇主\n    加倍發給工資，須以該休假日工作係出於雇主之需求要求勞\n    工加班為要件。若勞工並未表示欲休特別休假，雇主自無從\n    表示同意，縱因而導致年度終了或契約終止時仍有未休畢之\n    特別休假，亦無從遽認係屬雇主徵得勞工同意於特別休假日\n    工作。是以勞工應休之特別休假日於年度終結時，如有未休\n    完日數，如係可歸責於雇主之原因，雇主應發給未休完日數\n    之工資。至於特別休假未休完之日數，如係勞工個人之原因\n    而自行未休時，則雇主可不發給未休日數之工資（行政院勞\n    工委員會79年9月15日台勞動二字第21827號函釋參照）。是\n    勞工應休之特別休假日於年度終結時，如有未休完日數，雇\n    主非必發給勞工未休完日數之工資，端視其原因而定。則原\n    告請求被告給付不休假工資，即應就其債權發生之事實，即\n    不休假原因之所在，負舉證之責。原告雖主張其終止勞動契\n    約時前5年應休特別休假之日數為76日，被告應給付原告之\n    特別休假之工資945,896元，原告擔任被告公司中央通訊處\n    總監一職，須每日早上進行約一小時教育訓練課程及業務宣\n    導，是原告未能於每年度終了前休特別休假，實屬可歸責於\n    被告之原因云云，惟原告主張其須每日早上「親自」進行約\n    一小時教育訓練課程及業務宣導等情，為被告所否認，且勞\n    基法明文對員工工作時間與休息時間、特別休假之規範，企\n    業主有遵守之義務；而請假亦有職務代理人之設置，得由代\n    理人代為處理事務，故原告有充分之權利與機會安排每年度\n    的特別休假，參諸被告公司之工作規則第42條即對於特別休\n    假核予之計算為規定，且工作規則第43條亦規範原告可就核\n    予之特別休假先行排定，有被告提出之工作規則在卷可佐（\n    見本院卷(三)第164頁反面），是原告於93年至96年未排定休\n    假，而致有未休完之假，自為可歸責於己之事由。至原告於\n    97 年未休之特別休假，係因原告於97年6月25日以存證信函\n    通知終止雙方契約之行為，非屬於可歸責於被告之事由所致\n    ，自無從僅以原告未休畢休假之事實，逕行課被告以給付不\n    休假獎金之義務。從而，原告依勞基法第38條請求被告給付\n    終止勞動契約時前5年應休特別休假之工資945,896元，亦屬\n    無據。\n  (三)按侵權行為以故意或過失不法侵害他人之權利為成立要件，\n    民法第184條第1項前段定有明文。故主張應負侵權行為責任\n    者，應就其有故意或過失負舉證責任。又名譽權，係指個人\n    在社會上享有一般人對其品德、聲望或信譽等所加之評價，\n    屬於個人在社會上所受之價值判斷（最高法院90年度台上字\n    第1814號判決要旨參照）。是原告主張被告侵害其名譽權，\n    自必須證明被告公司有使原告社會上對其個人評價有貶損之\n    故意或過失。經查，被告係依其所調查之事實，認原告不適\n    合擔任主管職，而於97年5月30日以「藉職對業務同仁多項\n    管理、領導行為不當，引發爭議、並影響團隊士氣」為由，\n    將原告調職，已如前述，被告既主觀上認原告係有不適合擔\n    任管理職之事由而將之調任非主管職，縱因此造成原告難堪\n    之結果，亦難認被告有何故意或過失侵害原告名譽可言，是\n    原告主張被告侵害其名譽權，而請求精神上之損害賠償100\n    萬元，亦無理由。\n五、綜上所述，原告之請求均無理由。從而，原告提起本件訴訟\n    ，請求被告給付6,097,935元，及自起訴狀繕本送達之翌日\n    起至清償日止按年息5%計算之利息，為無理由，應予駁回。\n    又原告之訴既經駁回，其假執行之聲請即失所附麗，應併予\n    駁回。\n六、本件事證已臻明確，兩造其餘之攻擊、防禦方法，核與判決\n    結果不生影響，爰毋庸一一論述，併此敘明。\n七、結論：原告之訴為無理由，依民事訴訟法第78條判決如主文\n    。\n中    華    民    國    99    年    5     月    12    日\n                    勞工法庭    法  官  郭美杏\n以上正本係照原本作成\n如對本判決上訴，須於判決送達後20日內向本院提出上訴狀\n中    華    民    國    99    年    5     月    12    日\n                                書記官  馮姿蓉",
  "structure": {
    "main": "原告之訴及假執行之聲請均駁回。\n訴訟費用由原告負擔。",
    "fact": "壹、程序方面：\n一、本件被告富邦人壽保險股份有限公司於民國98年6月1日與安\n    泰人壽保險股份公司合併，安泰人壽保險股份有限公司為存\n    續公司，合併後，安泰人壽保險股份有限公司變更名稱為富\n    邦人壽保險股份有限公司。被告於98年6月22日聲明書狀承\n    受訴訟，並提出經濟部98年6月1日經授商字第09801100490\n    號函及公司變更登記表影本在卷可稽，先予敘明。\n二、按訴狀送達後，原告不得將原訴變更或追加他訴，但擴張或\n    減縮應受判決事項之聲明者，不在此限，民事訴訟法第255\n    條第1項第3款定有明文。原告起訴時原聲明請求被告給付\n    新臺幣（下同）8,556,640元及自起訴狀繕本送達翌日起至\n    清償日止按年息5%計算之利息，並願供擔保請准宣告假執行\n    （見本院北勞調卷第3頁）；嗣於本院審理中，於97年8月22\n    日具狀減縮訴之聲明第一項為：被告應給付原告7,479,232\n    元及自起訴狀繕本送達翌日起至清償日止按年息5%計算之利\n    息（見本院卷(一)第5頁）；又於97年9月1日具狀減縮訴之聲\n    明第一項為：被告應給付原告7,086,440元及自起訴狀繕本\n    送達翌日起至清償日止按年息5%計算之利息（見本院卷(一)第\n    14頁）；後於98年8月3日具狀減縮訴之聲明第一項為被告應\n    給付原告6,097,935元及自起訴狀繕本送達翌日起至清償日\n    止按年息5%計算之利息（見本院卷(三)第66頁）。經核原告所\n    為均係基於同一訴訟事實減縮應受判決事項之聲明，依前揭\n    規定，自應准許。\n貳、實體方面：\n一、原告主張：\n  (一)原告自85年7月1日起受僱於被告公司，由業務員晉升至總監\n    ，然被告公司卻於97年5月30日，以原告藉職權對同仁多項\n    管理領導不當引發爭議為由，將原告由中央通訊處總監一職\n    降為業務經理，並取消相關應屬原告之工資，然原告任職於\n    被告公司之期間並未有任何失職之處，被告除卻未經詳查，\n    亦未給原告任何申訴之機會，亦未召開人評會，即原告予以\n    降職減薪，核被告所為已違反勞動基準法（下稱勞基法）第\n    14條第1項第5款前段、第6款規定，原告遂於97年6月25日以\n    臺中市英才郵局01345號存證信函終止兩造間勞動契約，並\n    要求被告給付資遣費。\n  (二)原告任職被告公司期間自85年8月1日到職受僱於被告公司後\n    ，至97年6月25日終止兩造勞動契約之日之97年1月至97年6\n    月之工資，其中97年1月之薪資為432,612元（不含被告所主\n    張之承攬契約報酬）、97年2月之薪資為321,408元、97年3\n    月之薪資為403,687元、97年4月之薪資為373,058元、97年5\n    月之薪資為455,594元，97年6月之薪資為101,109元，再加\n    計如仍任總監所得增領之97年6月薪資151﹐833元，合計原\n    告任職於公司97年1月至97年6月之薪資總額為2,239,301元\n    ，則被告終止勞動契約前六個之平均工資為373﹐217元。又\n    原告自85年8月1日到職受僱於被告公司後，至97年6月25日\n    終止兩造勞動契約之日，合計年資原應為12年，惟原告自95\n    年12月1日起，就資遣費部分已改由新制勞工保險條例而提\n    撥退休金於勞保年金，故逾95年12月1日之年資部分，依勞\n    工退休金條例，原告得請求之資遣費為每滿一年後被告公司\n    應發給2分之1個月之平均工資，故被告應給付原告10年又4\n    個月之一個月平均工資之資遣費，及1年又7個月之2分之1個\n    月平均工資之資遣費；以原告終止兩造間之勞動契約之日前\n    之六個月平均工資為373,217元，每日之平均薪資為12,446\n    元【計算式：373,217元÷30天=12,446元/日，小數點以下\n    捨去】，故被告公司應給付原告之資遣費為4,152,039元【\n    計算式：（373,217元/月×10又4/12月）＋（373,217元/月\n    ×1/2×1又7/12月）＝4,152,039元】。\n  (三)原告受雇被告公司已12年，以原告終止兩造間之勞動契約之\n    日前之六個月平均工資為373,217元，每日之平均薪資為12,\n    446元，原告終止勞動契約時前5年應休特別休假之日數為76\n    日，故計算兩造契約終止時之前五年之特別休假之工資，被\n    告應給付原告之特別休假之工資945,896元【計算式：76日\n    ×12,446元＝945,896元】。\n  (四)被告以原告藉職權對業務同仁多項管理、領導為不當，並影\n    響團隊士氣為由，將原告降職及減薪，係不實之事實指述，\n    且被告懲處函文係發函予被告公司之內勤人員、各區部公號\n    、各通訊處公號、業務同仁等，已使特定人或不特定人置於\n    隨時可見聞之狀態；另被告97年6月30日於淡水教育中心之\n    處經理組訊會議中，以原告多項管理行為不善引發爭議之不\n    實事項，公開指名道姓，並據以引為被告公司組訓之案例，\n    被告顯有意圖侵害原告之名譽，致原告名譽受損害及產生精\n    神上痛苦，爰依民法第195條規定請求被告賠償100萬元之非\n    財產之損害。\n  (五)綜上，原告請求被告給付資遺費4,152,039元、特別休假之\n    工資945,896元及非財產上之損害賠償100萬元，合計6,097,\n    935元。並聲明：被告應給付原告6,097,935元及自起訴狀繕\n    本送達之翌日起至清償日止按年息5%計算之利息，並願供擔\n    保請准宣告假執行。\n二、被告則以：(一)原告於85年8月1日與被告簽訂聘用保險業務員\n    契約書而任職於被告公司，兩造間並於87年4月1日簽訂僱傭\n    契約與承攬契約，約定原告應遵守被告所頒布之工作相關規\n    範。因原告對同仁有不當職場言語及肢體行為，復因原告對\n    被告公司之財務管理交代不清、違反公司規定私聘業務助理\n    、宣導不當之招攬保險方式等影響金融專業形象之行為，經\n    被告公司稽核單位查證屬實後，原告已不適任管理職務，基\n    於企業經營之必要性及合理性，由被告管理單位於97年5月\n    30日以「藉職權對業務同仁多項管理、領導行為不當，引發\n    爭議，並影響團隊士氣」為由，將原告停止主管職務，調整\n    為非管理職之業務經理，被告並未侵害原告之工作權，亦未\n    侵害其直轄業務員部分，一切業務運作回歸總公司暫為監管\n    。原告於97年6月25日以存證信函通知被告終止系爭勞動契\n    約，被告公司於97年7月11日同意終止系爭勞動契約，系爭\n    勞動契約係經兩造合意終止，原告主張資遣費並無依據；(二)\n    縱被告應給付資遣費，原告平均工資之計算不應包括承攬契\n    約之報酬，且原告於97年6月1日已調整為非管理職，其平均\n    工資之計算，自當不應包含管理職之部分，原告之平均工資\n    應為薪資表冊列計之347,911元。又行政院勞工委員會函公\n    告保險業自87年4月1日納入勞基法適用，在適用勞基法前，\n    兩造間並無約定資遣費及退休金給予標準，故適用勞基法前\n    之期間，不應列計給付年資計算，則依勞基法第84-2條規定\n    ，原告資遣費之給付年資應自87年4月1日起至97年7月11日\n    止，其年資基數之計算應為自87年4月1日至95年11月30日共\n    計8年8個月，年資基數為8.67（計算式：8.67×1＝8.67）\n    ；自95年12月1日至97年7月11日共計1年8個月，年資基數為\n    0.83（計算式：1.66×0.5＝0.83），共計為9.5，故原告之\n    資遣費應為3,305,155元（計算式：347,911×9.5＝3,305,\n    155）；(三)原告任職於被告公司期間，給假均正常，又因其\n    業務性質自主性強，與勞基法上之勞工特性不同，除了每日\n    早上約一小時之教育訓練課程及業務宣導外，均得自由活動\n    ，原告得充分安排其工作時間，此由原告94年請假23日，而\n    被告並未計以事假而扣其薪資足證之。另被告每日早上之會\n    議係由各業務單位主管、組訓輪流主持，並進行主題之報告\n    ，並非必須由原告親自主持，被告亦無此項規範，如原告遇\n    有配合客戶或其他私事待辦，仍得辦理請假手續而由職務代\n    理人代為處理事務，故原告有充分的權利與機會安排每年度\n    的特別休假。原告自身認知上的誤謬、安排不當以及其自請\n    離職致特別休假未休完，屬可歸責於己之事由，被告可不發\n    給未休日數之工資；若本院認責任制之管理適用勞基法之特\n    別休假獎金計算，且原告未休完特休假係不可歸責於原告而\n    可請求特別休假獎金，則原告每日平均工資為11,597元，其\n    93年至97年未休假天數應為25日（計算式：給假總天數76－\n    請假天數42－缺席天數9＝25），特別休假獎金應為289,925\n    元（計算式：11,597×25＝289,925）；其97年未休假天數\n    為5日（計算式：給假總天數17－請假天數6－缺席天數6＝5\n    ），特別休假獎金應為57,985元（計算式：11,597×5＝\n    57,985）；(四)被告並未以原告作為討論之議題引發不當之爭\n    議，或意圖侵害原告名譽之情形，對於原告所懲處之事實情\n    形，僅以概括之文字記載公告之，且僅於被告企業內部網站\n    得觀看，並無侵害原告之名譽。而原告自請離職後，仍於同\n    業就職，被告對於其他單位人員詢問原告之工作表現時，均\n    未有任何不利於原告之言詞，原告主張被告侵害其名譽權，\n    須就被告有使原告社會上對其個人評價有貶損之故意或過失\n    負舉證責任等語資為抗辯，並聲明：原告之訴駁回，如受不\n    利判決，願供擔保請准宣告免為假執行。\n三、兩造不爭執之事實：\n  (一)原告自85年8月1日其任職被告公司，97年間離職時為總監。\n    業務經理。\n  (三)原告於97年6月25日以台中英才路郵局第1345號存證信函，\n    通知被告終止勞動契約。\n  (四)被告於97年7月11日發函給原告。\n四、原告請求被告給付資遺費4,152,039元、特別休假之工資945\n    ,896元及非財產上之損害賠償100萬元，合計6,097,935元，\n    被告則以前揭情詞置辯，是本件爭點厥為：(一)原告主張被告\n    公司之行為違反勞基法第14條第1項第5款前段、第6款規定\n    ，而終止勞動契約，並請求資遺費，有無理由；(二)原告請求\n    終止勞動契約時前5年應休特別休假之日數為76日之特別休\n    假之工資，有無理由；(三)原告主張被告侵害其名譽權，而請\n    求精神上之損害賠償，有無理由。茲分述如下：\n  (一)按雇主為達成營業目的，具有指揮監督勞工之權限，即雇主\n    有人事權為勞動契約之核心內容之一，是雇主對勞工之調動\n    升已有一定準則，且其調動升遷非以專損害勞工權益為目的\n    ，自應尊重雇主之人事自主權。經查，原告於離職時，係被\n    告公司總監，為被告公司中區業務部之最高主管等情，為原\n    告陳明在卷（見本院卷(一)第103頁），原告既身為最高主管\n    人員，首要者需有各組織之認同，並能引導士氣、形成向心\n    力之人員，以凝結合作團隊之精神。查證人即被告公司業務\n    部協理黃傑到庭證稱：「……原告後來又變成業務部經理是\n    因為原告在通訊處期間有很多同事反應原告有很多缺失的狀\n    況，我們有委請稽核瞭解，請這些反應的人出具書面資料說\n    明，根據這些資料說明我們就做一些懲處決議，我們是認為\n    原告在管理上有缺失，包含與業務同仁收取不當款項，帳目\n    不清楚，我們確實有去查帳，因為公司有規定帳目要依基金\n    管理辦法製作帳目，我們有去調帳目來看，覺得帳目不清，\n    相關細節我不清楚，另同仁的抱怨有很多，主要抱怨原告不\n    公平，例如對某些同仁比較好，比較多是針對劉淑芬與他帶\n    進來的人，原告之所以對劉淑芬與他帶進來的人比較不好我\n    們有去瞭解原因可能是他與劉淑芬之間有私人金錢往來而產\n    生不愉快。處理過程中我們有要求他們提出相關借據等等資\n    料，但都沒有提出。我們調查的過程認為原告在領導管理有\n    出嚴重的問題，所以我們將他調整為業務經理只管自己轄下\n    的業務員」、「……有很多關於系爭通訊處人員不合跟財物\n    不清的傳言，我們有去訪談其他諸如部長、組訓（就是中央\n    派駐地方作組織訓練、政令宣導的人），他們確實反應有這\n    些問題」等語（見本院卷(一)第191頁反面、第192頁）；證人\n    即被告公司稽核室經理黃文正到庭證稱：「（法官問：稽核\n    室從事何事？）負責公司業務查核，包含人員違失的查核，\n    本件原告的查核是部門的稽核人員負責，當初查核原告的原\n    因是業務部門接到業務人員的申訴書，會請我們去求證，我\n    們才派員去原告的通訊處查核，97年3月時我稽核室有派員\n    去台中作這10個申訴人員的訪談，願意作訪談的人有5位，\n    我們主要是確認申訴內容是否真正，及確認是否為申訴人的\n    原意，5位申訴者有告知我們申訴函確實是他們表達的意思\n    ，申訴者有反應不能認同主管的管理方法，覺得不公平，有\n    個人不妥當的行為。其中壹份申訴函中有提到主管對於獎勵\n    金的運用有問題，我們有用電話與業務人員查證，業務人員\n    也表達當初處經理提到的獎勵是由業務人員提供發票領取，\n    但最後是由主管統籌運用，與當初業務人員獲悉的不一樣，\n    也沒有領到這筆獎勵金。我們主要是針對人員管理、獎勵金\n    的部分，我們有去訪查，及用電話查獎勵金的分配，之後是\n    將稽核的結果業務部處理。申訴的人是否都是劉淑芬轄下的\n    人員我不清楚。在稽核的過程中我們有拜訪原告，也有請他\n    就申訴人提到的問題作陳述，原告事後有寫一個報告，我們\n    對於這個報告書沒有作判斷，我們全部移交業務部門決定。\n    」等語（見本院卷(一)192頁反面、第193頁）；證人王大維證\n    稱：「……被證十八就是我調查的結論，調查期間也有很多\n    不合公司內部規定的情形，所以我有寫類似請示案，看是否\n    可以做工作的適當調整。」（見本院卷(三)第62頁），顯見被\n    告公司對於原告之行為，提交稽核單位查證，認其行為確實\n    不適合擔任主管職務，被告公司基於原告不當之管理、領導\n    能力而為組織調整，屬被告公司基於企業營運管理考量所做\n    之必要調整，而被告公司之業務組織中，非管理職最高職務\n    即為「業務經理」等情，業據被告陳明在卷可按（見卷(三)第\n    197頁），原告既有不當之管理行為，已不適合擔任主管職\n    務，被告公司將原告調整為非管理職之最高職務「業務經理\n    」，並不構成勞基法第14條第1項第6款「雇主違反勞動契約\n    或勞工法令，致有損害勞工權益之虞」之事由。又原告亦自\n    承其主張被告取消其相關原屬工資，係計算報酬之方式由總\n    監職務改依業務經理之職務計算等語（見本院卷(三)第169頁\n    ），參諸擔任不同之工作，其受領之工資當有所不同之理，\n    是被告公司依據原告之職務而計算其薪資，亦不構成勞基法\n    第14條第5款前段「雇主不依勞動契約給付工作報酬」之事\n    由，是原告主張依勞基法第14條第1項第5款前段、第6款規\n    定終止勞動契約，尚屬無據。原告既不得依勞基法第14條第\n    1項第5款前段、第6款之規定終止系爭勞動契約，則其依同\n    法第14條第4項準用第17條之規定請求被告給付資遣費，即\n    屬無據，故原告請求被告給付資遣費4,152,039元，並無理\n    由。\n  (二)按勞基法第38條規定，雇主經徵得勞工同意於休假日工作者\n    ，工資應加倍發給。因季節性關係有趕工必要，經勞工或工\n    會同意照常工作者，亦同；勞動基準法施行細則第24條則規\n    定，本法第38條之特別休假，特別休假日期應由勞雇雙方協\n    商排定之。特別休假因年度終結或終止契約而未休者，其應\n    休未休之日數，雇主應發給工資。據此，可知特別休假雇主\n    加倍發給工資，須以該休假日工作係出於雇主之需求要求勞\n    工加班為要件。若勞工並未表示欲休特別休假，雇主自無從\n    表示同意，縱因而導致年度終了或契約終止時仍有未休畢之\n    特別休假，亦無從遽認係屬雇主徵得勞工同意於特別休假日\n    工作。是以勞工應休之特別休假日於年度終結時，如有未休\n    完日數，如係可歸責於雇主之原因，雇主應發給未休完日數\n    之工資。至於特別休假未休完之日數，如係勞工個人之原因\n    而自行未休時，則雇主可不發給未休日數之工資（行政院勞\n    工委員會79年9月15日台勞動二字第21827號函釋參照）。是\n    勞工應休之特別休假日於年度終結時，如有未休完日數，雇\n    主非必發給勞工未休完日數之工資，端視其原因而定。則原\n    告請求被告給付不休假工資，即應就其債權發生之事實，即\n    不休假原因之所在，負舉證之責。原告雖主張其終止勞動契\n    約時前5年應休特別休假之日數為76日，被告應給付原告之\n    特別休假之工資945,896元，原告擔任被告公司中央通訊處\n    總監一職，須每日早上進行約一小時教育訓練課程及業務宣\n    導，是原告未能於每年度終了前休特別休假，實屬可歸責於\n    被告之原因云云，惟原告主張其須每日早上「親自」進行約\n    一小時教育訓練課程及業務宣導等情，為被告所否認，且勞\n    基法明文對員工工作時間與休息時間、特別休假之規範，企\n    業主有遵守之義務；而請假亦有職務代理人之設置，得由代\n    理人代為處理事務，故原告有充分之權利與機會安排每年度\n    的特別休假，參諸被告公司之工作規則第42條即對於特別休\n    假核予之計算為規定，且工作規則第43條亦規範原告可就核\n    予之特別休假先行排定，有被告提出之工作規則在卷可佐（\n    見本院卷(三)第164頁反面），是原告於93年至96年未排定休\n    假，而致有未休完之假，自為可歸責於己之事由。至原告於\n    97 年未休之特別休假，係因原告於97年6月25日以存證信函\n    通知終止雙方契約之行為，非屬於可歸責於被告之事由所致\n    ，自無從僅以原告未休畢休假之事實，逕行課被告以給付不\n    休假獎金之義務。從而，原告依勞基法第38條請求被告給付\n    終止勞動契約時前5年應休特別休假之工資945,896元，亦屬\n    無據。\n  (三)按侵權行為以故意或過失不法侵害他人之權利為成立要件，\n    民法第184條第1項前段定有明文。故主張應負侵權行為責任\n    者，應就其有故意或過失負舉證責任。又名譽權，係指個人\n    在社會上享有一般人對其品德、聲望或信譽等所加之評價，\n    屬於個人在社會上所受之價值判斷（最高法院90年度台上字\n    第1814號判決要旨參照）。是原告主張被告侵害其名譽權，\n    自必須證明被告公司有使原告社會上對其個人評價有貶損之\n    故意或過失。經查，被告係依其所調查之事實，認原告不適\n    合擔任主管職，而於97年5月30日以「藉職對業務同仁多項\n    管理、領導行為不當，引發爭議、並影響團隊士氣」為由，\n    將原告調職，已如前述，被告既主觀上認原告係有不適合擔\n    任管理職之事由而將之調任非主管職，縱因此造成原告難堪\n    之結果，亦難認被告有何故意或過失侵害原告名譽可言，是\n    原告主張被告侵害其名譽權，而請求精神上之損害賠償100\n    萬元，亦無理由。\n五、綜上所述，原告之請求均無理由。從而，原告提起本件訴訟\n    ，請求被告給付6,097,935元，及自起訴狀繕本送達之翌日\n    起至清償日止按年息5%計算之利息，為無理由，應予駁回。\n    又原告之訴既經駁回，其假執行之聲請即失所附麗，應併予\n    駁回。\n六、本件事證已臻明確，兩造其餘之攻擊、防禦方法，核與判決\n    結果不生影響，爰毋庸一一論述，併此敘明。\n七、結論：原告之訴為無理由，依民事訴訟法第78條判決如主文\n    。",
    "reason": "壹、程序方面：\n一、本件被告富邦人壽保險股份有限公司於民國98年6月1日與安\n    泰人壽保險股份公司合併，安泰人壽保險股份有限公司為存\n    續公司，合併後，安泰人壽保險股份有限公司變更名稱為富\n    邦人壽保險股份有限公司。被告於98年6月22日聲明書狀承\n    受訴訟，並提出經濟部98年6月1日經授商字第09801100490\n    號函及公司變更登記表影本在卷可稽，先予敘明。\n二、按訴狀送達後，原告不得將原訴變更或追加他訴，但擴張或\n    減縮應受判決事項之聲明者，不在此限，民事訴訟法第255\n    條第1項第3款定有明文。原告起訴時原聲明請求被告給付\n    新臺幣（下同）8,556,640元及自起訴狀繕本送達翌日起至\n    清償日止按年息5%計算之利息，並願供擔保請准宣告假執行\n    （見本院北勞調卷第3頁）；嗣於本院審理中，於97年8月22\n    日具狀減縮訴之聲明第一項為：被告應給付原告7,479,232\n    元及自起訴狀繕本送達翌日起至清償日止按年息5%計算之利\n    息（見本院卷(一)第5頁）；又於97年9月1日具狀減縮訴之聲\n    明第一項為：被告應給付原告7,086,440元及自起訴狀繕本\n    送達翌日起至清償日止按年息5%計算之利息（見本院卷(一)第\n    14頁）；後於98年8月3日具狀減縮訴之聲明第一項為被告應\n    給付原告6,097,935元及自起訴狀繕本送達翌日起至清償日\n    止按年息5%計算之利息（見本院卷(三)第66頁）。經核原告所\n    為均係基於同一訴訟事實減縮應受判決事項之聲明，依前揭\n    規定，自應准許。\n貳、實體方面：\n一、原告主張：\n  (一)原告自85年7月1日起受僱於被告公司，由業務員晉升至總監\n    ，然被告公司卻於97年5月30日，以原告藉職權對同仁多項\n    管理領導不當引發爭議為由，將原告由中央通訊處總監一職\n    降為業務經理，並取消相關應屬原告之工資，然原告任職於\n    被告公司之期間並未有任何失職之處，被告除卻未經詳查，\n    亦未給原告任何申訴之機會，亦未召開人評會，即原告予以\n    降職減薪，核被告所為已違反勞動基準法（下稱勞基法）第\n    14條第1項第5款前段、第6款規定，原告遂於97年6月25日以\n    臺中市英才郵局01345號存證信函終止兩造間勞動契約，並\n    要求被告給付資遣費。\n  (二)原告任職被告公司期間自85年8月1日到職受僱於被告公司後\n    ，至97年6月25日終止兩造勞動契約之日之97年1月至97年6\n    月之工資，其中97年1月之薪資為432,612元（不含被告所主\n    張之承攬契約報酬）、97年2月之薪資為321,408元、97年3\n    月之薪資為403,687元、97年4月之薪資為373,058元、97年5\n    月之薪資為455,594元，97年6月之薪資為101,109元，再加\n    計如仍任總監所得增領之97年6月薪資151﹐833元，合計原\n    告任職於公司97年1月至97年6月之薪資總額為2,239,301元\n    ，則被告終止勞動契約前六個之平均工資為373﹐217元。又\n    原告自85年8月1日到職受僱於被告公司後，至97年6月25日\n    終止兩造勞動契約之日，合計年資原應為12年，惟原告自95\n    年12月1日起，就資遣費部分已改由新制勞工保險條例而提\n    撥退休金於勞保年金，故逾95年12月1日之年資部分，依勞\n    工退休金條例，原告得請求之資遣費為每滿一年後被告公司\n    應發給2分之1個月之平均工資，故被告應給付原告10年又4\n    個月之一個月平均工資之資遣費，及1年又7個月之2分之1個\n    月平均工資之資遣費；以原告終止兩造間之勞動契約之日前\n    之六個月平均工資為373,217元，每日之平均薪資為12,446\n    元【計算式：373,217元÷30天=12,446元/日，小數點以下\n    捨去】，故被告公司應給付原告之資遣費為4,152,039元【\n    計算式：（373,217元/月×10又4/12月）＋（373,217元/月\n    ×1/2×1又7/12月）＝4,152,039元】。\n  (三)原告受雇被告公司已12年，以原告終止兩造間之勞動契約之\n    日前之六個月平均工資為373,217元，每日之平均薪資為12,\n    446元，原告終止勞動契約時前5年應休特別休假之日數為76\n    日，故計算兩造契約終止時之前五年之特別休假之工資，被\n    告應給付原告之特別休假之工資945,896元【計算式：76日\n    ×12,446元＝945,896元】。\n  (四)被告以原告藉職權對業務同仁多項管理、領導為不當，並影\n    響團隊士氣為由，將原告降職及減薪，係不實之事實指述，\n    且被告懲處函文係發函予被告公司之內勤人員、各區部公號\n    、各通訊處公號、業務同仁等，已使特定人或不特定人置於\n    隨時可見聞之狀態；另被告97年6月30日於淡水教育中心之\n    處經理組訊會議中，以原告多項管理行為不善引發爭議之不\n    實事項，公開指名道姓，並據以引為被告公司組訓之案例，\n    被告顯有意圖侵害原告之名譽，致原告名譽受損害及產生精\n    神上痛苦，爰依民法第195條規定請求被告賠償100萬元之非\n    財產之損害。\n  (五)綜上，原告請求被告給付資遺費4,152,039元、特別休假之\n    工資945,896元及非財產上之損害賠償100萬元，合計6,097,\n    935元。並聲明：被告應給付原告6,097,935元及自起訴狀繕\n    本送達之翌日起至清償日止按年息5%計算之利息，並願供擔\n    保請准宣告假執行。\n二、被告則以：(一)原告於85年8月1日與被告簽訂聘用保險業務員\n    契約書而任職於被告公司，兩造間並於87年4月1日簽訂僱傭\n    契約與承攬契約，約定原告應遵守被告所頒布之工作相關規\n    範。因原告對同仁有不當職場言語及肢體行為，復因原告對\n    被告公司之財務管理交代不清、違反公司規定私聘業務助理\n    、宣導不當之招攬保險方式等影響金融專業形象之行為，經\n    被告公司稽核單位查證屬實後，原告已不適任管理職務，基\n    於企業經營之必要性及合理性，由被告管理單位於97年5月\n    30日以「藉職權對業務同仁多項管理、領導行為不當，引發\n    爭議，並影響團隊士氣」為由，將原告停止主管職務，調整\n    為非管理職之業務經理，被告並未侵害原告之工作權，亦未\n    侵害其直轄業務員部分，一切業務運作回歸總公司暫為監管\n    。原告於97年6月25日以存證信函通知被告終止系爭勞動契\n    約，被告公司於97年7月11日同意終止系爭勞動契約，系爭\n    勞動契約係經兩造合意終止，原告主張資遣費並無依據；(二)\n    縱被告應給付資遣費，原告平均工資之計算不應包括承攬契\n    約之報酬，且原告於97年6月1日已調整為非管理職，其平均\n    工資之計算，自當不應包含管理職之部分，原告之平均工資\n    應為薪資表冊列計之347,911元。又行政院勞工委員會函公\n    告保險業自87年4月1日納入勞基法適用，在適用勞基法前，\n    兩造間並無約定資遣費及退休金給予標準，故適用勞基法前\n    之期間，不應列計給付年資計算，則依勞基法第84-2條規定\n    ，原告資遣費之給付年資應自87年4月1日起至97年7月11日\n    止，其年資基數之計算應為自87年4月1日至95年11月30日共\n    計8年8個月，年資基數為8.67（計算式：8.67×1＝8.67）\n    ；自95年12月1日至97年7月11日共計1年8個月，年資基數為\n    0.83（計算式：1.66×0.5＝0.83），共計為9.5，故原告之\n    資遣費應為3,305,155元（計算式：347,911×9.5＝3,305,\n    155）；(三)原告任職於被告公司期間，給假均正常，又因其\n    業務性質自主性強，與勞基法上之勞工特性不同，除了每日\n    早上約一小時之教育訓練課程及業務宣導外，均得自由活動\n    ，原告得充分安排其工作時間，此由原告94年請假23日，而\n    被告並未計以事假而扣其薪資足證之。另被告每日早上之會\n    議係由各業務單位主管、組訓輪流主持，並進行主題之報告\n    ，並非必須由原告親自主持，被告亦無此項規範，如原告遇\n    有配合客戶或其他私事待辦，仍得辦理請假手續而由職務代\n    理人代為處理事務，故原告有充分的權利與機會安排每年度\n    的特別休假。原告自身認知上的誤謬、安排不當以及其自請\n    離職致特別休假未休完，屬可歸責於己之事由，被告可不發\n    給未休日數之工資；若本院認責任制之管理適用勞基法之特\n    別休假獎金計算，且原告未休完特休假係不可歸責於原告而\n    可請求特別休假獎金，則原告每日平均工資為11,597元，其\n    93年至97年未休假天數應為25日（計算式：給假總天數76－\n    請假天數42－缺席天數9＝25），特別休假獎金應為289,925\n    元（計算式：11,597×25＝289,925）；其97年未休假天數\n    為5日（計算式：給假總天數17－請假天數6－缺席天數6＝5\n    ），特別休假獎金應為57,985元（計算式：11,597×5＝\n    57,985）；(四)被告並未以原告作為討論之議題引發不當之爭\n    議，或意圖侵害原告名譽之情形，對於原告所懲處之事實情\n    形，僅以概括之文字記載公告之，且僅於被告企業內部網站\n    得觀看，並無侵害原告之名譽。而原告自請離職後，仍於同\n    業就職，被告對於其他單位人員詢問原告之工作表現時，均\n    未有任何不利於原告之言詞，原告主張被告侵害其名譽權，\n    須就被告有使原告社會上對其個人評價有貶損之故意或過失\n    負舉證責任等語資為抗辯，並聲明：原告之訴駁回，如受不\n    利判決，願供擔保請准宣告免為假執行。\n三、兩造不爭執之事實：\n  (一)原告自85年8月1日其任職被告公司，97年間離職時為總監。\n    業務經理。\n  (三)原告於97年6月25日以台中英才路郵局第1345號存證信函，\n    通知被告終止勞動契約。\n  (四)被告於97年7月11日發函給原告。\n四、原告請求被告給付資遺費4,152,039元、特別休假之工資945\n    ,896元及非財產上之損害賠償100萬元，合計6,097,935元，\n    被告則以前揭情詞置辯，是本件爭點厥為：(一)原告主張被告\n    公司之行為違反勞基法第14條第1項第5款前段、第6款規定\n    ，而終止勞動契約，並請求資遺費，有無理由；(二)原告請求\n    終止勞動契約時前5年應休特別休假之日數為76日之特別休\n    假之工資，有無理由；(三)原告主張被告侵害其名譽權，而請\n    求精神上之損害賠償，有無理由。茲分述如下：\n  (一)按雇主為達成營業目的，具有指揮監督勞工之權限，即雇主\n    有人事權為勞動契約之核心內容之一，是雇主對勞工之調動\n    升已有一定準則，且其調動升遷非以專損害勞工權益為目的\n    ，自應尊重雇主之人事自主權。經查，原告於離職時，係被\n    告公司總監，為被告公司中區業務部之最高主管等情，為原\n    告陳明在卷（見本院卷(一)第103頁），原告既身為最高主管\n    人員，首要者需有各組織之認同，並能引導士氣、形成向心\n    力之人員，以凝結合作團隊之精神。查證人即被告公司業務\n    部協理黃傑到庭證稱：「……原告後來又變成業務部經理是\n    因為原告在通訊處期間有很多同事反應原告有很多缺失的狀\n    況，我們有委請稽核瞭解，請這些反應的人出具書面資料說\n    明，根據這些資料說明我們就做一些懲處決議，我們是認為\n    原告在管理上有缺失，包含與業務同仁收取不當款項，帳目\n    不清楚，我們確實有去查帳，因為公司有規定帳目要依基金\n    管理辦法製作帳目，我們有去調帳目來看，覺得帳目不清，\n    相關細節我不清楚，另同仁的抱怨有很多，主要抱怨原告不\n    公平，例如對某些同仁比較好，比較多是針對劉淑芬與他帶\n    進來的人，原告之所以對劉淑芬與他帶進來的人比較不好我\n    們有去瞭解原因可能是他與劉淑芬之間有私人金錢往來而產\n    生不愉快。處理過程中我們有要求他們提出相關借據等等資\n    料，但都沒有提出。我們調查的過程認為原告在領導管理有\n    出嚴重的問題，所以我們將他調整為業務經理只管自己轄下\n    的業務員」、「……有很多關於系爭通訊處人員不合跟財物\n    不清的傳言，我們有去訪談其他諸如部長、組訓（就是中央\n    派駐地方作組織訓練、政令宣導的人），他們確實反應有這\n    些問題」等語（見本院卷(一)第191頁反面、第192頁）；證人\n    即被告公司稽核室經理黃文正到庭證稱：「（法官問：稽核\n    室從事何事？）負責公司業務查核，包含人員違失的查核，\n    本件原告的查核是部門的稽核人員負責，當初查核原告的原\n    因是業務部門接到業務人員的申訴書，會請我們去求證，我\n    們才派員去原告的通訊處查核，97年3月時我稽核室有派員\n    去台中作這10個申訴人員的訪談，願意作訪談的人有5位，\n    我們主要是確認申訴內容是否真正，及確認是否為申訴人的\n    原意，5位申訴者有告知我們申訴函確實是他們表達的意思\n    ，申訴者有反應不能認同主管的管理方法，覺得不公平，有\n    個人不妥當的行為。其中壹份申訴函中有提到主管對於獎勵\n    金的運用有問題，我們有用電話與業務人員查證，業務人員\n    也表達當初處經理提到的獎勵是由業務人員提供發票領取，\n    但最後是由主管統籌運用，與當初業務人員獲悉的不一樣，\n    也沒有領到這筆獎勵金。我們主要是針對人員管理、獎勵金\n    的部分，我們有去訪查，及用電話查獎勵金的分配，之後是\n    將稽核的結果業務部處理。申訴的人是否都是劉淑芬轄下的\n    人員我不清楚。在稽核的過程中我們有拜訪原告，也有請他\n    就申訴人提到的問題作陳述，原告事後有寫一個報告，我們\n    對於這個報告書沒有作判斷，我們全部移交業務部門決定。\n    」等語（見本院卷(一)192頁反面、第193頁）；證人王大維證\n    稱：「……被證十八就是我調查的結論，調查期間也有很多\n    不合公司內部規定的情形，所以我有寫類似請示案，看是否\n    可以做工作的適當調整。」（見本院卷(三)第62頁），顯見被\n    告公司對於原告之行為，提交稽核單位查證，認其行為確實\n    不適合擔任主管職務，被告公司基於原告不當之管理、領導\n    能力而為組織調整，屬被告公司基於企業營運管理考量所做\n    之必要調整，而被告公司之業務組織中，非管理職最高職務\n    即為「業務經理」等情，業據被告陳明在卷可按（見卷(三)第\n    197頁），原告既有不當之管理行為，已不適合擔任主管職\n    務，被告公司將原告調整為非管理職之最高職務「業務經理\n    」，並不構成勞基法第14條第1項第6款「雇主違反勞動契約\n    或勞工法令，致有損害勞工權益之虞」之事由。又原告亦自\n    承其主張被告取消其相關原屬工資，係計算報酬之方式由總\n    監職務改依業務經理之職務計算等語（見本院卷(三)第169頁\n    ），參諸擔任不同之工作，其受領之工資當有所不同之理，\n    是被告公司依據原告之職務而計算其薪資，亦不構成勞基法\n    第14條第5款前段「雇主不依勞動契約給付工作報酬」之事\n    由，是原告主張依勞基法第14條第1項第5款前段、第6款規\n    定終止勞動契約，尚屬無據。原告既不得依勞基法第14條第\n    1項第5款前段、第6款之規定終止系爭勞動契約，則其依同\n    法第14條第4項準用第17條之規定請求被告給付資遣費，即\n    屬無據，故原告請求被告給付資遣費4,152,039元，並無理\n    由。\n  (二)按勞基法第38條規定，雇主經徵得勞工同意於休假日工作者\n    ，工資應加倍發給。因季節性關係有趕工必要，經勞工或工\n    會同意照常工作者，亦同；勞動基準法施行細則第24條則規\n    定，本法第38條之特別休假，特別休假日期應由勞雇雙方協\n    商排定之。特別休假因年度終結或終止契約而未休者，其應\n    休未休之日數，雇主應發給工資。據此，可知特別休假雇主\n    加倍發給工資，須以該休假日工作係出於雇主之需求要求勞\n    工加班為要件。若勞工並未表示欲休特別休假，雇主自無從\n    表示同意，縱因而導致年度終了或契約終止時仍有未休畢之\n    特別休假，亦無從遽認係屬雇主徵得勞工同意於特別休假日\n    工作。是以勞工應休之特別休假日於年度終結時，如有未休\n    完日數，如係可歸責於雇主之原因，雇主應發給未休完日數\n    之工資。至於特別休假未休完之日數，如係勞工個人之原因\n    而自行未休時，則雇主可不發給未休日數之工資（行政院勞\n    工委員會79年9月15日台勞動二字第21827號函釋參照）。是\n    勞工應休之特別休假日於年度終結時，如有未休完日數，雇\n    主非必發給勞工未休完日數之工資，端視其原因而定。則原\n    告請求被告給付不休假工資，即應就其債權發生之事實，即\n    不休假原因之所在，負舉證之責。原告雖主張其終止勞動契\n    約時前5年應休特別休假之日數為76日，被告應給付原告之\n    特別休假之工資945,896元，原告擔任被告公司中央通訊處\n    總監一職，須每日早上進行約一小時教育訓練課程及業務宣\n    導，是原告未能於每年度終了前休特別休假，實屬可歸責於\n    被告之原因云云，惟原告主張其須每日早上「親自」進行約\n    一小時教育訓練課程及業務宣導等情，為被告所否認，且勞\n    基法明文對員工工作時間與休息時間、特別休假之規範，企\n    業主有遵守之義務；而請假亦有職務代理人之設置，得由代\n    理人代為處理事務，故原告有充分之權利與機會安排每年度\n    的特別休假，參諸被告公司之工作規則第42條即對於特別休\n    假核予之計算為規定，且工作規則第43條亦規範原告可就核\n    予之特別休假先行排定，有被告提出之工作規則在卷可佐（\n    見本院卷(三)第164頁反面），是原告於93年至96年未排定休\n    假，而致有未休完之假，自為可歸責於己之事由。至原告於\n    97 年未休之特別休假，係因原告於97年6月25日以存證信函\n    通知終止雙方契約之行為，非屬於可歸責於被告之事由所致\n    ，自無從僅以原告未休畢休假之事實，逕行課被告以給付不\n    休假獎金之義務。從而，原告依勞基法第38條請求被告給付\n    終止勞動契約時前5年應休特別休假之工資945,896元，亦屬\n    無據。\n  (三)按侵權行為以故意或過失不法侵害他人之權利為成立要件，\n    民法第184條第1項前段定有明文。故主張應負侵權行為責任\n    者，應就其有故意或過失負舉證責任。又名譽權，係指個人\n    在社會上享有一般人對其品德、聲望或信譽等所加之評價，\n    屬於個人在社會上所受之價值判斷（最高法院90年度台上字\n    第1814號判決要旨參照）。是原告主張被告侵害其名譽權，\n    自必須證明被告公司有使原告社會上對其個人評價有貶損之\n    故意或過失。經查，被告係依其所調查之事實，認原告不適\n    合擔任主管職，而於97年5月30日以「藉職對業務同仁多項\n    管理、領導行為不當，引發爭議、並影響團隊士氣」為由，\n    將原告調職，已如前述，被告既主觀上認原告係有不適合擔\n    任管理職之事由而將之調任非主管職，縱因此造成原告難堪\n    之結果，亦難認被告有何故意或過失侵害原告名譽可言，是\n    原告主張被告侵害其名譽權，而請求精神上之損害賠償100\n    萬元，亦無理由。\n五、綜上所述，原告之請求均無理由。從而，原告提起本件訴訟\n    ，請求被告給付6,097,935元，及自起訴狀繕本送達之翌日\n    起至清償日止按年息5%計算之利息，為無理由，應予駁回。\n    又原告之訴既經駁回，其假執行之聲請即失所附麗，應併予\n    駁回。\n六、本件事證已臻明確，兩造其餘之攻擊、防禦方法，核與判決\n    結果不生影響，爰毋庸一一論述，併此敘明。\n七、結論：原告之訴為無理由，依民事訴訟法第78條判決如主文\n    。"
  },
  "characters": {
    "judges": [
      "郭美杏"
    ],
    "prosecutors": [

    ],
    "lawyers": [
      "黃翎芳",
      "鄧翊鴻"
    ],
    "clerks": [

    ],
    "plaintiffs": [
      "林瑞宗"
    ],
    "defendants": [
      "富邦人壽保險股份有限公司"
    ],
    "prosecutor_office": [

    ],
    "creditors": [

    ],
    "debtors": [

    ],
    "judicial_associate_officer": [

    ]
  },
  "adjudged_at": "2010-05-12",
  "created_at": "2016-01-05 12:19:32",
  "updated_at": "2016-01-05 12:19:32"
}