{
  "identify": "TPD-98-勞訴-117-20100104-2",
  "court": {
    "name": "臺灣臺北地方法院",
    "code": "TPD"
  },
  "division": {
    "name": "民事",
    "code": "V"
  },
  "year": 98,
  "word": "勞訴",
  "number": "117",
  "jcheck": "2",
  "reason": "給付退休金差額",
  "content": "臺灣臺北地方法院民事裁定             98年度勞訴字第117號\n原      告  卯○○\n            丙○○\n            丁○○\n            丑○○\n            庚○○\n            壬○○\n            己○○\n            寅○○\n            癸○○\n            戊○○\n前列十人共同\n訴訟代理人  劉思龍律師\n複代理人    江大寧律師\n被      告  台灣中油股份有限公司\n法定代理人  朱少華\n訴訟代理人  子○○\n            乙○○\n            薛進坤律師\n複代理人    甲○○\n上列當事人間給付退休金差額事件本院裁定如下：\n    主  文\n本件應由被告台灣中油股份有限公司法定代理人朱少華為承受訴\n訟人，續行訴訟。\n    理  由\n一、按訴訟程序於裁判送達後當然停止者，其承受訴訟之聲明，\n    由為裁判之原法院裁定之，民事訴訟法第177條第3項有明文\n    之規定。\n二、查本件被告之法定代理人原為辛○○，嗣因其於民國98年9\n    月10日升任經濟部部長，由被告總經理朱少華暫代董事長之\n    職，有被告98年10月19日油人發字第09810433140號函影本\n    乙紙附臺灣高等法院98年度勞上易字第125號卷可稽，現據\n    新任法定代理人朱少華具狀聲明承受訴訟，經核無不合，應\n    准其承受訴訟並續為訴訟行為。\n三、爰依民事訴訟法第177條第3項，裁定如主文。\n中    華    民    國    99    年    1     月    4     日\n                    勞工法庭    法  官  郭美杏\n以上正本係照原本作成\n如對本裁定抗告須於裁定送達後10日內向本院提出抗告狀，並繳\n納抗告費新臺幣1,000元\n中    華    民    國    99    年    1     月    4     日\n                                書記官  馮姿蓉",
  "structure": {
    "main": "本件應由被告台灣中油股份有限公司法定代理人朱少華為承受訴\n訟人，續行訴訟。",
    "reason": "一、按訴訟程序於裁判送達後當然停止者，其承受訴訟之聲明，\n    由為裁判之原法院裁定之，民事訴訟法第177條第3項有明文\n    之規定。\n二、查本件被告之法定代理人原為辛○○，嗣因其於民國98年9\n    月10日升任經濟部部長，由被告總經理朱少華暫代董事長之\n    職，有被告98年10月19日油人發字第09810433140號函影本\n    乙紙附臺灣高等法院98年度勞上易字第125號卷可稽，現據\n    新任法定代理人朱少華具狀聲明承受訴訟，經核無不合，應\n    准其承受訴訟並續為訴訟行為。\n三、爰依民事訴訟法第177條第3項，裁定如主文。"
  },
  "characters": {
    "judges": [
      "郭美杏"
    ],
    "prosecutors": [

    ],
    "lawyers": [
      "劉思龍",
      "江大寧",
      "薛進坤"
    ],
    "clerks": [

    ],
    "plaintiffs": [
      "卯"
    ],
    "defendants": [
      "台灣中油股份有限公司"
    ],
    "prosecutor_office": [

    ],
    "creditors": [

    ],
    "debtors": [

    ],
    "judicial_associate_officer": [

    ]
  },
  "adjudged_at": "2010-01-04",
  "created_at": "2016-01-05 14:54:26",
  "updated_at": "2016-01-05 14:54:26"
}