{
  "identify": "TPD-98-簡-5213-20100105-1",
  "court": {
    "name": "臺灣臺北地方法院",
    "code": "TPD"
  },
  "division": {
    "name": "刑事",
    "code": "M"
  },
  "year": 98,
  "word": "簡",
  "number": "5213",
  "jcheck": "1",
  "reason": "竊盜",
  "content": "臺灣臺北地方法院刑事簡易判決          98年度簡字第5213號\n聲  請  人  臺灣臺北地方法院檢察署檢察官\n被      告  甲○○\n上列被告因竊盜案件，經檢察官聲請以簡易判決處刑（九十八年\n度速偵字第二二八號），本院判決如下：\n    主  文\n甲○○竊盜，累犯，處有期徒刑肆月，如易科罰金，以新臺幣壹\n仟元折算壹日；又竊盜，累犯，處有期徒刑肆月，如易科罰金，\n以新臺幣壹仟元折算壹日。應執行有期徒刑陸月，如易科罰金，\n以新臺幣壹仟元折算壹日。\n    事實及理由\n一、本件犯罪事實及證據，除犯罪事實第四行補充並更正為於民\n    國97年10月18日假釋期滿執行完畢外，餘均引用檢察官聲請\n    簡易判決處刑書所載（如附件）。\n二、核被告甲○○所為均係犯刑法第三百二十條第一項之普通竊\n    盜罪。被告所犯上開二罪間，犯意各別、行為分殊，應予分\n    論併罰。又被告有上開犯罪事實欄之前案紀錄等情，有臺灣\n    高等法院被告前案紀錄表在卷可證，其於五年內再故意犯本\n    案有期徒刑以上之罪，為累犯，爰審酌被告前已有竊盜、搶\n    奪等前科，素行非佳有臺灣高等法院被告前案紀錄表在卷可\n    考，素行非佳，其徒手竊取財物，危害他人財產及社會治安\n    ，惟念諸其犯後尚知坦認犯行，態度良好，並斟酌被害人財\n    產損失程度，暨被告犯罪動機、手段、目的、所得利益等一\n    切情狀，分別量處如主文所示之刑，並定其應執行之刑，且\n    均併諭知易科罰金之折算標準，以示懲儆。\n三、依刑事訴訟法第四百四十九條第一項前段、第三項、第四百\n    五十四條第二項，刑法第三百二十條第一項、第四十七條第\n    一項、刑法第四十一條第一項前段、第八項、第五十一條第\n    一項第五款，，刑法施行法第一條之一第一項、第二項前段\n    ，逕以簡易判決處如主文所示之刑。\n四、如不服本件判決，得自收受送達之日起十日內，向本院提起\n    上訴。\n中    華    民    國   九十九   年    一   月    五   日\n                  刑事第五庭    法  官  鄭昱仁\n\n上正本證明與原本無異。\n                                書記官  宋德華\n中    華    民    國   九十九   年    一   月    五   日\n附錄本案論罪科刑法條：\n中華民國刑法第320條\n（普通竊盜罪、竊佔罪）\n意圖為自己或第三人不法之所有，而竊取他人之動產者，為竊盜\n罪，處5  年以下有期徒刑、拘役或 5 百元以下罰金。\n意圖為自己或第三人不法之利益，而竊佔他人之不動產者，依前\n項之規定處斷。\n前二項之未遂犯罰之。",
  "structure": {
    "main": "甲○○竊盜，累犯，處有期徒刑肆月，如易科罰金，以新臺幣壹\n仟元折算壹日；又竊盜，累犯，處有期徒刑肆月，如易科罰金，\n以新臺幣壹仟元折算壹日。應執行有期徒刑陸月，如易科罰金，\n以新臺幣壹仟元折算壹日。",
    "fact": "一、本件犯罪事實及證據，除犯罪事實第四行補充並更正為於民\n    國97年10月18日假釋期滿執行完畢外，餘均引用檢察官聲請\n    簡易判決處刑書所載（如附件）。\n二、核被告甲○○所為均係犯刑法第三百二十條第一項之普通竊\n    盜罪。被告所犯上開二罪間，犯意各別、行為分殊，應予分\n    論併罰。又被告有上開犯罪事實欄之前案紀錄等情，有臺灣\n    高等法院被告前案紀錄表在卷可證，其於五年內再故意犯本\n    案有期徒刑以上之罪，為累犯，爰審酌被告前已有竊盜、搶\n    奪等前科，素行非佳有臺灣高等法院被告前案紀錄表在卷可\n    考，素行非佳，其徒手竊取財物，危害他人財產及社會治安\n    ，惟念諸其犯後尚知坦認犯行，態度良好，並斟酌被害人財\n    產損失程度，暨被告犯罪動機、手段、目的、所得利益等一\n    切情狀，分別量處如主文所示之刑，並定其應執行之刑，且\n    均併諭知易科罰金之折算標準，以示懲儆。\n三、依刑事訴訟法第四百四十九條第一項前段、第三項、第四百\n    五十四條第二項，刑法第三百二十條第一項、第四十七條第\n    一項、刑法第四十一條第一項前段、第八項、第五十一條第\n    一項第五款，，刑法施行法第一條之一第一項、第二項前段\n    ，逕以簡易判決處如主文所示之刑。\n四、如不服本件判決，得自收受送達之日起十日內，向本院提起\n    上訴。",
    "reason": "一、本件犯罪事實及證據，除犯罪事實第四行補充並更正為於民\n    國97年10月18日假釋期滿執行完畢外，餘均引用檢察官聲請\n    簡易判決處刑書所載（如附件）。\n二、核被告甲○○所為均係犯刑法第三百二十條第一項之普通竊\n    盜罪。被告所犯上開二罪間，犯意各別、行為分殊，應予分\n    論併罰。又被告有上開犯罪事實欄之前案紀錄等情，有臺灣\n    高等法院被告前案紀錄表在卷可證，其於五年內再故意犯本\n    案有期徒刑以上之罪，為累犯，爰審酌被告前已有竊盜、搶\n    奪等前科，素行非佳有臺灣高等法院被告前案紀錄表在卷可\n    考，素行非佳，其徒手竊取財物，危害他人財產及社會治安\n    ，惟念諸其犯後尚知坦認犯行，態度良好，並斟酌被害人財\n    產損失程度，暨被告犯罪動機、手段、目的、所得利益等一\n    切情狀，分別量處如主文所示之刑，並定其應執行之刑，且\n    均併諭知易科罰金之折算標準，以示懲儆。\n三、依刑事訴訟法第四百四十九條第一項前段、第三項、第四百\n    五十四條第二項，刑法第三百二十條第一項、第四十七條第\n    一項、刑法第四十一條第一項前段、第八項、第五十一條第\n    一項第五款，，刑法施行法第一條之一第一項、第二項前段\n    ，逕以簡易判決處如主文所示之刑。\n四、如不服本件判決，得自收受送達之日起十日內，向本院提起\n    上訴。"
  },
  "characters": {
    "judges": [
      "鄭昱仁"
    ],
    "prosecutors": [

    ],
    "lawyers": [

    ],
    "clerks": [
      "宋德華"
    ],
    "plaintiffs": [

    ],
    "defendants": [
      "甲○○"
    ],
    "prosecutor_office": [
      "臺灣臺北地方法院檢察署檢察官"
    ],
    "creditors": [

    ],
    "debtors": [

    ],
    "judicial_associate_officer": [

    ]
  },
  "adjudged_at": "2010-01-05",
  "created_at": "2016-01-05 15:12:16",
  "updated_at": "2016-01-05 15:12:16"
}