{
  "identify": "TPD-99-簡-993-20100512-1",
  "court": {
    "name": "臺灣臺北地方法院",
    "code": "TPD"
  },
  "division": {
    "name": "刑事",
    "code": "M"
  },
  "year": 99,
  "word": "簡",
  "number": "993",
  "jcheck": "1",
  "reason": "詐欺等",
  "content": "臺灣臺北地方法院刑事簡易判決           99年度簡字第993號\n聲  請  人  臺灣臺北地方法院檢察署檢察官\n被      告  甲○○\n上列被告因詐欺等案件，經檢察官聲請以簡易判決處刑（99年度\n撤緩偵字第61號），本院判決如下：\n    主  文\n甲○○連續犯行使偽造準私文書罪，處有期徒刑陸月，如易科罰\n金，以銀元參佰元即新臺幣玖佰元折算壹日。\n    事實及理由\n一、本件犯罪事實及證據，均引用檢察官聲請簡易判決處刑書之\n    記載（如附件）。\n二、查被告甲○○行為後，刑法部分條文於94年2月2日經總統公\n    布修正，並自95年7月1日起施行。又刑法施行法增訂第1條\n    之1，亦於95年6月14日經總統公布，並自同年7月1日起施行\n    。按行為後法律有變更者，適用行為時之法律，但行為後之\n    法律有利於行為人者，適用最有利於行為人之法律，現行刑\n    法第2條第1項定有明文。此條規定係規範行為後法律變更所\n    生新舊法律比較適用之準據法，是刑法第2條本身雖經修正\n    ，但刑法第2條既屬適用法律之準據法，本身尚無比較新舊\n    法之問題，於新法施行後，應一律適用裁判時之現行刑法第\n    2 條之規定，為「從舊從輕」之比較，合先敘明。次按，本\n    次刑法修正之比較新舊法，應就罪刑有關之共犯、未遂犯、\n    想像競合犯、牽連犯、連續犯、結合犯，以及累犯加重、自\n    首減輕暨其他法定加減原因（如身分加減）與加減例等一切\n    情形，綜其全部罪刑之結果而為比較，最高法院95年5月23\n    日95年度第8次刑庭會議著有決議可資參照。經查：\n  (一)刑法第339 條第1 項詐欺取財罪，法定刑得科或併科銀元1\n    千元、1 萬元以下罰金，據修正後刑法施行法增訂第1 條之\n    1 ：「中華民國94年1 月7 日刑法修正施行後，刑法分則編\n    所定罰金之貨幣單位為新臺幣。94年1 月7 日刑法修正時，\n    刑法分則編未修正之條文定有罰金者，自94年1 月7 日刑法\n    修正施行後，就其所定數額提高為30倍。但72年6 月26日至\n    94年1 月7 日新增或修正之條文，就其所定數額提高為3倍\n    」及刑法第33條第5 款修正為：「主刑之種類如下：五、罰\n    金：新臺幣千1 元以上，以百元計算之」等規定，是依修正\n    後之法律，刑法第339 條第1 項詐欺取財罪所得科處之罰金\n    刑最高為新臺幣3 萬元、最低為新臺幣1 千元；然依被告行\n    為時之刑罰法律，即罰金罰鍰提高標準條例第1 條前段規定\n    之提高倍數10倍及刑法第33條第5 款規定之罰金最低額1 元\n    計算，該罪之罰金刑最高為銀元1 萬元，最低額為銀元10元\n    ，換算為新臺幣，最高額雖與新法同為新臺幣3 萬元，然最\n    低額僅為新臺幣30元。因此，比較上述修正前、後之刑罰法\n    律，自以被告修正施行前即行為時關於科處罰金刑之法律較\n    有利於被告。\n  (二)修正施行前刑法第55條之牽連犯、刑法第56條連續犯之規定\n    業經修正公佈刪除，則被告之犯行，因行為後新法已刪除牽\n    連犯、連續犯之規定，此刪除雖非犯罪構成要件之變更，但\n    顯已影響行為人刑罰之法律效果，自屬法律有變更。修正前\n    刑法第55條牽連犯，第56條連續犯規定，前者加重其刑至二\n    分之一，後者從一重罪處斷；而上開規定於修正刪除後，刑\n    法就行為罪數，除接續犯、想像競合犯、結合犯等實質上或\n    裁判上一罪，以一罪論處原則上採取一罪一罰及數罪併罰，\n    故修正前之處罰結果，顯較修正刑法規定一罪一罰或數罪併\n    罰對被告有利。\n  (三)又修正後刑法第41條第1 項前段關於得易科罰金之折算標準\n    規定，由「得以1 元以上3 元以下折算1 日」（按：此規定\n    配合修正前罰金罰鍰提高標準條例第2 條（現已刪除）規定\n    ，就其原定數額提高為100 倍折算1 日，則最高應以銀元\n    300 元折算1 日，經折算為新臺幣後，應以新臺幣900 元折\n    算為1 日），提高為「以新臺幣1 千元、2 千元或3 千元折\n    算1 日」，並刪除「因身體、教育、職業、家庭之關係或其\n    他正當事由，執行顯有困難」之條件。是以修正前刑法第41\n    條第1 項前段關於易科罰金之折算標準對被告較為有利。\n  (四)綜合上述之比較，揆諸前揭最高法院決議及修正後刑法第2\n    條第1 項規定之「從舊、從輕」原則，自應適用被告行為時\n    之舊法較有利於被告。\n  (五)刑法第220條就「在紙上或物品上之文字、符號，依習慣或\n    特約足以為表示其用意之證明者，以文書論」，於修正後雖\n    移列為同條第1項，惟法文字並無變動，即非犯罪構成要件\n    之變更；為此，均不影響行為人刑罰之法律效果，即無有利\n    或不利之情形，自無新舊法比較問題。\n三、按刑法第220條以文書論之文書，指在紙上或物品上之文字\n    、符號，依習慣或特約足以表示其用意之證明者而言，故凡\n    以虛偽之文字、符號或在物品或紙上表示一定用意之證明者\n    ，即屬偽造。再民間互助會之標會會單，而必須依據習慣或\n    特約，始足以表示該一定之金額即為標取會款之利息，如未\n    書寫標會者之姓名或代號，致無從辨別或表示係某一會員參\n    與標會，固不具文書之形式，然若經投標者（或代為投標者\n    或冒標者）表明其係某人之標單，因在場之其他投標者或會\n    員已能辨別係某一會員參與標會者，縱標單上未書寫姓名或\n    代號，依其習慣或特約，仍認為係標取會款之會員出單競標\n    ，且係在該標單出標金額最高會員標取會款，故偽造該未書\n    姓名之標單，應認為偽造同法第220條以文書論之私文書（\n    參最高法院53年台上字第2905號判例、74年度台上字第5612\n    號、94年度台上字第1439號判決意旨），故核被告所為，係\n    犯刑法第216條、第220條、第210條之行使偽造準私文書罪\n    及第339條第1項之詐欺取財罪。被告偽造準私文書而後行使\n    ，偽造之低度行為應為行使之高度行為所吸收，不另成罪。\n    另被告其每次冒標詐取會款之行為，係同時侵害多數活會會\n    員之權益，乃一行為觸犯數罪名，應依刑法第55條想像競合\n    犯規定，從一重論處。被告先後多次犯行，時間緊接，犯意\n    概括，構成要件亦復相同，應依修正前刑法第56條連續犯規\n    定，就行使偽造準私文書罪及詐欺取財罪，分別論以一罪，\n    並均加重其刑。另被告行使偽造準私文書及與詐欺取財二罪\n    之間，有方法與結果牽連關係，應依修正前刑法第55條牽連\n    犯規定，從一重行使偽造準私文書罪論處。爰審酌被告未循\n    正當途徑獲取財物，竟冒標詐得合會款項，侵害活會會員之\n    權益，且犯後雖與被害人和解，然未能依約履行和解條件，\n    實有不該，惟念被告並無前科，有前案紀錄表在卷可按，素\n    行尚佳，又犯後坦承犯行，態度尚可，兼衡其智識程度、犯\n    罪動機、目的、手段、生活狀況、被害人所受損害金額及檢\n    察官聲請簡易判決處刑意旨等一切情狀，量處如主文所示之\n    刑。又96年7月16日施行之中華民國九十六年罪犯減刑條例\n    第5條規定：「本條例施行前，經通緝而未於中華民國96年\n    12月31日以前自動歸案接受偵查、審判或執行者，不得依本\n    條例減刑」，查本件被告於偵查中經通緝，嗣於96年9月10\n    日被警方緝獲到案，有卷附通緝書及臺北市政府警察局內湖\n    分局通緝案件移送書各1份附卷可稽（見96年度偵緝字第\n    2194 號卷），是被告雖於上開減刑條例施行前經通緝，但\n    並未依同條例第5條規定於96年12月31日前自動歸案接受偵\n    查，而係於同年9月10日遭警方緝獲到案，自不得依前開減\n    刑條例予以減刑。末查，被告所偽造之標單並未扣案，衡一\n    般互助會開標宣布得標人後，均會扔棄該無用標單，況此係\n    犯罪證據，為免遭察，被告顯無留存之理，應認均遭被告丟\n    棄滅失，故不予宣告沒收，附此敘明。\n四、依刑事訴訟法第449條第1項、第3項、第454條第2項，刑法\n    第2條第1項前段、第216條、第210條、第220條第1項、第55\n    條前段，修正前刑法第56條、第339條第1項、第55條後段、\n    第41條第1項前段，修正前罰金罰鍰提高標準條例第1條前段\n    、第2條，逕以簡易判決處刑如主文。\n中    華    民    國    99    年    5     月    12    日\n                  刑事第十三庭  法  官  林瑋桓\n以上正本證明與原本無異。\n如不服本判決應於收受送達後10日內向本院提出上訴書狀，並應\n敘述具體理由；其未敘述上訴理由者，應於上訴期間屆滿後20日\n內向本院補提理由書（均須按他造當事人之人數附繕）「切勿逕\n送上級法院」。\n中    華    民    國    99    年    5     月    12    日\n                                書記官  鄭伊芸\n附錄本件判決論罪科刑法條：\n中華民國刑法第210條\n偽造、變造私文書，足以生損害於公眾或他人者，處5 年以下有\n期徒刑。\n中華民國刑法第220條第1項\n在紙上或物品上之文字、符號、圖畫、照像，依習慣或特約，足\n以為表示其用意之證明者，關於本章及本章以外各罪，以文書論\n。\n中華民國刑法第216條\n行使第210 條至第215 條之文書者，依偽造、變造文書或登載不\n實事項或使登載不實事項之規定處斷。\n中華民國刑法第339條\n意圖為自己或第三人不法之所有，以詐術使人將本人或第三人之\n物交付者，處5 年以下有期徒刑、拘役或科或併科1 千元以下罰\n金。\n以前項方法得財產上不法之利益或使第三人得之者，亦同。\n前二項之未遂犯罰之。",
  "structure": {
    "main": "甲○○連續犯行使偽造準私文書罪，處有期徒刑陸月，如易科罰\n金，以銀元參佰元即新臺幣玖佰元折算壹日。",
    "fact": "一、本件犯罪事實及證據，均引用檢察官聲請簡易判決處刑書之\n    記載（如附件）。\n二、查被告甲○○行為後，刑法部分條文於94年2月2日經總統公\n    布修正，並自95年7月1日起施行。又刑法施行法增訂第1條\n    之1，亦於95年6月14日經總統公布，並自同年7月1日起施行\n    。按行為後法律有變更者，適用行為時之法律，但行為後之\n    法律有利於行為人者，適用最有利於行為人之法律，現行刑\n    法第2條第1項定有明文。此條規定係規範行為後法律變更所\n    生新舊法律比較適用之準據法，是刑法第2條本身雖經修正\n    ，但刑法第2條既屬適用法律之準據法，本身尚無比較新舊\n    法之問題，於新法施行後，應一律適用裁判時之現行刑法第\n    2 條之規定，為「從舊從輕」之比較，合先敘明。次按，本\n    次刑法修正之比較新舊法，應就罪刑有關之共犯、未遂犯、\n    想像競合犯、牽連犯、連續犯、結合犯，以及累犯加重、自\n    首減輕暨其他法定加減原因（如身分加減）與加減例等一切\n    情形，綜其全部罪刑之結果而為比較，最高法院95年5月23\n    日95年度第8次刑庭會議著有決議可資參照。經查：\n  (一)刑法第339 條第1 項詐欺取財罪，法定刑得科或併科銀元1\n    千元、1 萬元以下罰金，據修正後刑法施行法增訂第1 條之\n    1 ：「中華民國94年1 月7 日刑法修正施行後，刑法分則編\n    所定罰金之貨幣單位為新臺幣。94年1 月7 日刑法修正時，\n    刑法分則編未修正之條文定有罰金者，自94年1 月7 日刑法\n    修正施行後，就其所定數額提高為30倍。但72年6 月26日至\n    94年1 月7 日新增或修正之條文，就其所定數額提高為3倍\n    」及刑法第33條第5 款修正為：「主刑之種類如下：五、罰\n    金：新臺幣千1 元以上，以百元計算之」等規定，是依修正\n    後之法律，刑法第339 條第1 項詐欺取財罪所得科處之罰金\n    刑最高為新臺幣3 萬元、最低為新臺幣1 千元；然依被告行\n    為時之刑罰法律，即罰金罰鍰提高標準條例第1 條前段規定\n    之提高倍數10倍及刑法第33條第5 款規定之罰金最低額1 元\n    計算，該罪之罰金刑最高為銀元1 萬元，最低額為銀元10元\n    ，換算為新臺幣，最高額雖與新法同為新臺幣3 萬元，然最\n    低額僅為新臺幣30元。因此，比較上述修正前、後之刑罰法\n    律，自以被告修正施行前即行為時關於科處罰金刑之法律較\n    有利於被告。\n  (二)修正施行前刑法第55條之牽連犯、刑法第56條連續犯之規定\n    業經修正公佈刪除，則被告之犯行，因行為後新法已刪除牽\n    連犯、連續犯之規定，此刪除雖非犯罪構成要件之變更，但\n    顯已影響行為人刑罰之法律效果，自屬法律有變更。修正前\n    刑法第55條牽連犯，第56條連續犯規定，前者加重其刑至二\n    分之一，後者從一重罪處斷；而上開規定於修正刪除後，刑\n    法就行為罪數，除接續犯、想像競合犯、結合犯等實質上或\n    裁判上一罪，以一罪論處原則上採取一罪一罰及數罪併罰，\n    故修正前之處罰結果，顯較修正刑法規定一罪一罰或數罪併\n    罰對被告有利。\n  (三)又修正後刑法第41條第1 項前段關於得易科罰金之折算標準\n    規定，由「得以1 元以上3 元以下折算1 日」（按：此規定\n    配合修正前罰金罰鍰提高標準條例第2 條（現已刪除）規定\n    ，就其原定數額提高為100 倍折算1 日，則最高應以銀元\n    300 元折算1 日，經折算為新臺幣後，應以新臺幣900 元折\n    算為1 日），提高為「以新臺幣1 千元、2 千元或3 千元折\n    算1 日」，並刪除「因身體、教育、職業、家庭之關係或其\n    他正當事由，執行顯有困難」之條件。是以修正前刑法第41\n    條第1 項前段關於易科罰金之折算標準對被告較為有利。\n  (四)綜合上述之比較，揆諸前揭最高法院決議及修正後刑法第2\n    條第1 項規定之「從舊、從輕」原則，自應適用被告行為時\n    之舊法較有利於被告。\n  (五)刑法第220條就「在紙上或物品上之文字、符號，依習慣或\n    特約足以為表示其用意之證明者，以文書論」，於修正後雖\n    移列為同條第1項，惟法文字並無變動，即非犯罪構成要件\n    之變更；為此，均不影響行為人刑罰之法律效果，即無有利\n    或不利之情形，自無新舊法比較問題。\n三、按刑法第220條以文書論之文書，指在紙上或物品上之文字\n    、符號，依習慣或特約足以表示其用意之證明者而言，故凡\n    以虛偽之文字、符號或在物品或紙上表示一定用意之證明者\n    ，即屬偽造。再民間互助會之標會會單，而必須依據習慣或\n    特約，始足以表示該一定之金額即為標取會款之利息，如未\n    書寫標會者之姓名或代號，致無從辨別或表示係某一會員參\n    與標會，固不具文書之形式，然若經投標者（或代為投標者\n    或冒標者）表明其係某人之標單，因在場之其他投標者或會\n    員已能辨別係某一會員參與標會者，縱標單上未書寫姓名或\n    代號，依其習慣或特約，仍認為係標取會款之會員出單競標\n    ，且係在該標單出標金額最高會員標取會款，故偽造該未書\n    姓名之標單，應認為偽造同法第220條以文書論之私文書（\n    參最高法院53年台上字第2905號判例、74年度台上字第5612\n    號、94年度台上字第1439號判決意旨），故核被告所為，係\n    犯刑法第216條、第220條、第210條之行使偽造準私文書罪\n    及第339條第1項之詐欺取財罪。被告偽造準私文書而後行使\n    ，偽造之低度行為應為行使之高度行為所吸收，不另成罪。\n    另被告其每次冒標詐取會款之行為，係同時侵害多數活會會\n    員之權益，乃一行為觸犯數罪名，應依刑法第55條想像競合\n    犯規定，從一重論處。被告先後多次犯行，時間緊接，犯意\n    概括，構成要件亦復相同，應依修正前刑法第56條連續犯規\n    定，就行使偽造準私文書罪及詐欺取財罪，分別論以一罪，\n    並均加重其刑。另被告行使偽造準私文書及與詐欺取財二罪\n    之間，有方法與結果牽連關係，應依修正前刑法第55條牽連\n    犯規定，從一重行使偽造準私文書罪論處。爰審酌被告未循\n    正當途徑獲取財物，竟冒標詐得合會款項，侵害活會會員之\n    權益，且犯後雖與被害人和解，然未能依約履行和解條件，\n    實有不該，惟念被告並無前科，有前案紀錄表在卷可按，素\n    行尚佳，又犯後坦承犯行，態度尚可，兼衡其智識程度、犯\n    罪動機、目的、手段、生活狀況、被害人所受損害金額及檢\n    察官聲請簡易判決處刑意旨等一切情狀，量處如主文所示之\n    刑。又96年7月16日施行之中華民國九十六年罪犯減刑條例\n    第5條規定：「本條例施行前，經通緝而未於中華民國96年\n    12月31日以前自動歸案接受偵查、審判或執行者，不得依本\n    條例減刑」，查本件被告於偵查中經通緝，嗣於96年9月10\n    日被警方緝獲到案，有卷附通緝書及臺北市政府警察局內湖\n    分局通緝案件移送書各1份附卷可稽（見96年度偵緝字第\n    2194 號卷），是被告雖於上開減刑條例施行前經通緝，但\n    並未依同條例第5條規定於96年12月31日前自動歸案接受偵\n    查，而係於同年9月10日遭警方緝獲到案，自不得依前開減\n    刑條例予以減刑。末查，被告所偽造之標單並未扣案，衡一\n    般互助會開標宣布得標人後，均會扔棄該無用標單，況此係\n    犯罪證據，為免遭察，被告顯無留存之理，應認均遭被告丟\n    棄滅失，故不予宣告沒收，附此敘明。\n四、依刑事訴訟法第449條第1項、第3項、第454條第2項，刑法\n    第2條第1項前段、第216條、第210條、第220條第1項、第55\n    條前段，修正前刑法第56條、第339條第1項、第55條後段、\n    第41條第1項前段，修正前罰金罰鍰提高標準條例第1條前段\n    、第2條，逕以簡易判決處刑如主文。",
    "reason": "一、本件犯罪事實及證據，均引用檢察官聲請簡易判決處刑書之\n    記載（如附件）。\n二、查被告甲○○行為後，刑法部分條文於94年2月2日經總統公\n    布修正，並自95年7月1日起施行。又刑法施行法增訂第1條\n    之1，亦於95年6月14日經總統公布，並自同年7月1日起施行\n    。按行為後法律有變更者，適用行為時之法律，但行為後之\n    法律有利於行為人者，適用最有利於行為人之法律，現行刑\n    法第2條第1項定有明文。此條規定係規範行為後法律變更所\n    生新舊法律比較適用之準據法，是刑法第2條本身雖經修正\n    ，但刑法第2條既屬適用法律之準據法，本身尚無比較新舊\n    法之問題，於新法施行後，應一律適用裁判時之現行刑法第\n    2 條之規定，為「從舊從輕」之比較，合先敘明。次按，本\n    次刑法修正之比較新舊法，應就罪刑有關之共犯、未遂犯、\n    想像競合犯、牽連犯、連續犯、結合犯，以及累犯加重、自\n    首減輕暨其他法定加減原因（如身分加減）與加減例等一切\n    情形，綜其全部罪刑之結果而為比較，最高法院95年5月23\n    日95年度第8次刑庭會議著有決議可資參照。經查：\n  (一)刑法第339 條第1 項詐欺取財罪，法定刑得科或併科銀元1\n    千元、1 萬元以下罰金，據修正後刑法施行法增訂第1 條之\n    1 ：「中華民國94年1 月7 日刑法修正施行後，刑法分則編\n    所定罰金之貨幣單位為新臺幣。94年1 月7 日刑法修正時，\n    刑法分則編未修正之條文定有罰金者，自94年1 月7 日刑法\n    修正施行後，就其所定數額提高為30倍。但72年6 月26日至\n    94年1 月7 日新增或修正之條文，就其所定數額提高為3倍\n    」及刑法第33條第5 款修正為：「主刑之種類如下：五、罰\n    金：新臺幣千1 元以上，以百元計算之」等規定，是依修正\n    後之法律，刑法第339 條第1 項詐欺取財罪所得科處之罰金\n    刑最高為新臺幣3 萬元、最低為新臺幣1 千元；然依被告行\n    為時之刑罰法律，即罰金罰鍰提高標準條例第1 條前段規定\n    之提高倍數10倍及刑法第33條第5 款規定之罰金最低額1 元\n    計算，該罪之罰金刑最高為銀元1 萬元，最低額為銀元10元\n    ，換算為新臺幣，最高額雖與新法同為新臺幣3 萬元，然最\n    低額僅為新臺幣30元。因此，比較上述修正前、後之刑罰法\n    律，自以被告修正施行前即行為時關於科處罰金刑之法律較\n    有利於被告。\n  (二)修正施行前刑法第55條之牽連犯、刑法第56條連續犯之規定\n    業經修正公佈刪除，則被告之犯行，因行為後新法已刪除牽\n    連犯、連續犯之規定，此刪除雖非犯罪構成要件之變更，但\n    顯已影響行為人刑罰之法律效果，自屬法律有變更。修正前\n    刑法第55條牽連犯，第56條連續犯規定，前者加重其刑至二\n    分之一，後者從一重罪處斷；而上開規定於修正刪除後，刑\n    法就行為罪數，除接續犯、想像競合犯、結合犯等實質上或\n    裁判上一罪，以一罪論處原則上採取一罪一罰及數罪併罰，\n    故修正前之處罰結果，顯較修正刑法規定一罪一罰或數罪併\n    罰對被告有利。\n  (三)又修正後刑法第41條第1 項前段關於得易科罰金之折算標準\n    規定，由「得以1 元以上3 元以下折算1 日」（按：此規定\n    配合修正前罰金罰鍰提高標準條例第2 條（現已刪除）規定\n    ，就其原定數額提高為100 倍折算1 日，則最高應以銀元\n    300 元折算1 日，經折算為新臺幣後，應以新臺幣900 元折\n    算為1 日），提高為「以新臺幣1 千元、2 千元或3 千元折\n    算1 日」，並刪除「因身體、教育、職業、家庭之關係或其\n    他正當事由，執行顯有困難」之條件。是以修正前刑法第41\n    條第1 項前段關於易科罰金之折算標準對被告較為有利。\n  (四)綜合上述之比較，揆諸前揭最高法院決議及修正後刑法第2\n    條第1 項規定之「從舊、從輕」原則，自應適用被告行為時\n    之舊法較有利於被告。\n  (五)刑法第220條就「在紙上或物品上之文字、符號，依習慣或\n    特約足以為表示其用意之證明者，以文書論」，於修正後雖\n    移列為同條第1項，惟法文字並無變動，即非犯罪構成要件\n    之變更；為此，均不影響行為人刑罰之法律效果，即無有利\n    或不利之情形，自無新舊法比較問題。\n三、按刑法第220條以文書論之文書，指在紙上或物品上之文字\n    、符號，依習慣或特約足以表示其用意之證明者而言，故凡\n    以虛偽之文字、符號或在物品或紙上表示一定用意之證明者\n    ，即屬偽造。再民間互助會之標會會單，而必須依據習慣或\n    特約，始足以表示該一定之金額即為標取會款之利息，如未\n    書寫標會者之姓名或代號，致無從辨別或表示係某一會員參\n    與標會，固不具文書之形式，然若經投標者（或代為投標者\n    或冒標者）表明其係某人之標單，因在場之其他投標者或會\n    員已能辨別係某一會員參與標會者，縱標單上未書寫姓名或\n    代號，依其習慣或特約，仍認為係標取會款之會員出單競標\n    ，且係在該標單出標金額最高會員標取會款，故偽造該未書\n    姓名之標單，應認為偽造同法第220條以文書論之私文書（\n    參最高法院53年台上字第2905號判例、74年度台上字第5612\n    號、94年度台上字第1439號判決意旨），故核被告所為，係\n    犯刑法第216條、第220條、第210條之行使偽造準私文書罪\n    及第339條第1項之詐欺取財罪。被告偽造準私文書而後行使\n    ，偽造之低度行為應為行使之高度行為所吸收，不另成罪。\n    另被告其每次冒標詐取會款之行為，係同時侵害多數活會會\n    員之權益，乃一行為觸犯數罪名，應依刑法第55條想像競合\n    犯規定，從一重論處。被告先後多次犯行，時間緊接，犯意\n    概括，構成要件亦復相同，應依修正前刑法第56條連續犯規\n    定，就行使偽造準私文書罪及詐欺取財罪，分別論以一罪，\n    並均加重其刑。另被告行使偽造準私文書及與詐欺取財二罪\n    之間，有方法與結果牽連關係，應依修正前刑法第55條牽連\n    犯規定，從一重行使偽造準私文書罪論處。爰審酌被告未循\n    正當途徑獲取財物，竟冒標詐得合會款項，侵害活會會員之\n    權益，且犯後雖與被害人和解，然未能依約履行和解條件，\n    實有不該，惟念被告並無前科，有前案紀錄表在卷可按，素\n    行尚佳，又犯後坦承犯行，態度尚可，兼衡其智識程度、犯\n    罪動機、目的、手段、生活狀況、被害人所受損害金額及檢\n    察官聲請簡易判決處刑意旨等一切情狀，量處如主文所示之\n    刑。又96年7月16日施行之中華民國九十六年罪犯減刑條例\n    第5條規定：「本條例施行前，經通緝而未於中華民國96年\n    12月31日以前自動歸案接受偵查、審判或執行者，不得依本\n    條例減刑」，查本件被告於偵查中經通緝，嗣於96年9月10\n    日被警方緝獲到案，有卷附通緝書及臺北市政府警察局內湖\n    分局通緝案件移送書各1份附卷可稽（見96年度偵緝字第\n    2194 號卷），是被告雖於上開減刑條例施行前經通緝，但\n    並未依同條例第5條規定於96年12月31日前自動歸案接受偵\n    查，而係於同年9月10日遭警方緝獲到案，自不得依前開減\n    刑條例予以減刑。末查，被告所偽造之標單並未扣案，衡一\n    般互助會開標宣布得標人後，均會扔棄該無用標單，況此係\n    犯罪證據，為免遭察，被告顯無留存之理，應認均遭被告丟\n    棄滅失，故不予宣告沒收，附此敘明。\n四、依刑事訴訟法第449條第1項、第3項、第454條第2項，刑法\n    第2條第1項前段、第216條、第210條、第220條第1項、第55\n    條前段，修正前刑法第56條、第339條第1項、第55條後段、\n    第41條第1項前段，修正前罰金罰鍰提高標準條例第1條前段\n    、第2條，逕以簡易判決處刑如主文。"
  },
  "characters": {
    "judges": [
      "林瑋桓"
    ],
    "prosecutors": [

    ],
    "lawyers": [

    ],
    "clerks": [
      "鄭伊芸"
    ],
    "plaintiffs": [

    ],
    "defendants": [
      "甲○○"
    ],
    "prosecutor_office": [
      "臺灣臺北地方法院檢察署檢察官"
    ],
    "creditors": [

    ],
    "debtors": [

    ],
    "judicial_associate_officer": [

    ]
  },
  "adjudged_at": "2010-05-12",
  "created_at": "2016-01-05 12:06:18",
  "updated_at": "2016-01-05 12:06:18"
}