{
  "identify": "TPD-99-簡-1695-20100512-1",
  "court": {
    "name": "臺灣臺北地方法院",
    "code": "TPD"
  },
  "division": {
    "name": "刑事",
    "code": "M"
  },
  "year": 99,
  "word": "簡",
  "number": "1695",
  "jcheck": "1",
  "reason": "毒品危害防制條例",
  "content": "臺灣臺北地方法院刑事簡易判決          99年度簡字第1695號\n聲  請  人  臺灣臺北地方法院檢察署檢察官\n被      告  甲○○\n上列被告因毒品危害防制條例案件，經檢察官聲請以簡易判決處\n刑（99年度毒偵字第1483號），本院判決如下：\n    主  文\n甲○○施用第二級毒品，處有期徒刑參月，如易科罰金，以新臺\n幣壹仟元折算壹日。扣案之第二級毒品甲基安非他命壹包（驗餘\n淨重零點陸伍捌捌公克）沒收銷燬。\n    事實及理由\n一、本件犯罪事實及證明犯罪事實之證據方法並其證據均引用檢\n    察官聲請簡易判決處刑書之記載（如附件）。\n二、核被告甲○○所為，係犯毒品危害防制條例第10條第2 項施\n    用第2級毒品罪；而其持有扣案之第2級毒品甲基安非他命之\n    行為，既意在供己施用，為施用第2 級毒品甲基安非他命之\n    高度行為所吸收，不另論罪。爰審酌被告之生活狀況、智識\n    程度及犯罪後態度等一切情狀，量處有期徒刑3 月，並諭知\n    得易科罰金併其折算標準。至扣案之第2 級毒品甲基安非他\n    命（驗餘淨重0.6588公克)，依毒品危害防制條例第18條第1\n    項前段之規定，沒收銷燬。\n三、依刑事訴訟法第449條第1 項前段、第3項、第454條第2項，\n    毒品危害防制條例第10條第2項、第18條第1項前段，刑法第\n    11條前段、第41條第1 項前段，逕以簡易判決處如主文所示\n    之刑。\n如不服本判決應於收受送達後10日內向本院提出上訴書狀，並應\n敘述具體理由；其未敘述上訴理由者，應於上訴期間屆滿後20日\n內向本院補提理由書（均須按他造當事人之人數附繕）「切勿逕\n送上級法院」。\n中    華    民    國    99    年    5     月    12    日\n                  刑事第四庭    法  官  呂政燁\n以上正本證明與原本無異。\n如不服本判決應於收受送達後10日內向本院提出上訴書狀，並應\n敘述具體理由；其未敘述上訴理由者，應於上訴期間屆滿後20日\n內向本院補提理由書（均須按他造當事人之人數附繕本）「切勿\n逕送上級法院」。\n                                書記官  呂欣穎\n中    華    民    國    99    年    5     月    12    日\n附錄本案所犯法條全文：\n毒品危害防制條例第10條\n施用第一級毒品者，處6月以上5年以下有期徒刑。\n施用第二級毒品者，處3年以下有期徒刑。",
  "structure": {
    "main": "甲○○施用第二級毒品，處有期徒刑參月，如易科罰金，以新臺\n幣壹仟元折算壹日。扣案之第二級毒品甲基安非他命壹包（驗餘\n淨重零點陸伍捌捌公克）沒收銷燬。",
    "fact": "一、本件犯罪事實及證明犯罪事實之證據方法並其證據均引用檢\n    察官聲請簡易判決處刑書之記載（如附件）。\n二、核被告甲○○所為，係犯毒品危害防制條例第10條第2 項施\n    用第2級毒品罪；而其持有扣案之第2級毒品甲基安非他命之\n    行為，既意在供己施用，為施用第2 級毒品甲基安非他命之\n    高度行為所吸收，不另論罪。爰審酌被告之生活狀況、智識\n    程度及犯罪後態度等一切情狀，量處有期徒刑3 月，並諭知\n    得易科罰金併其折算標準。至扣案之第2 級毒品甲基安非他\n    命（驗餘淨重0.6588公克)，依毒品危害防制條例第18條第1\n    項前段之規定，沒收銷燬。\n三、依刑事訴訟法第449條第1 項前段、第3項、第454條第2項，\n    毒品危害防制條例第10條第2項、第18條第1項前段，刑法第\n    11條前段、第41條第1 項前段，逕以簡易判決處如主文所示\n    之刑。\n如不服本判決應於收受送達後10日內向本院提出上訴書狀，並應\n敘述具體理由；其未敘述上訴理由者，應於上訴期間屆滿後20日\n內向本院補提理由書（均須按他造當事人之人數附繕）「切勿逕\n送上級法院」。",
    "reason": "一、本件犯罪事實及證明犯罪事實之證據方法並其證據均引用檢\n    察官聲請簡易判決處刑書之記載（如附件）。\n二、核被告甲○○所為，係犯毒品危害防制條例第10條第2 項施\n    用第2級毒品罪；而其持有扣案之第2級毒品甲基安非他命之\n    行為，既意在供己施用，為施用第2 級毒品甲基安非他命之\n    高度行為所吸收，不另論罪。爰審酌被告之生活狀況、智識\n    程度及犯罪後態度等一切情狀，量處有期徒刑3 月，並諭知\n    得易科罰金併其折算標準。至扣案之第2 級毒品甲基安非他\n    命（驗餘淨重0.6588公克)，依毒品危害防制條例第18條第1\n    項前段之規定，沒收銷燬。\n三、依刑事訴訟法第449條第1 項前段、第3項、第454條第2項，\n    毒品危害防制條例第10條第2項、第18條第1項前段，刑法第\n    11條前段、第41條第1 項前段，逕以簡易判決處如主文所示\n    之刑。\n如不服本判決應於收受送達後10日內向本院提出上訴書狀，並應\n敘述具體理由；其未敘述上訴理由者，應於上訴期間屆滿後20日\n內向本院補提理由書（均須按他造當事人之人數附繕）「切勿逕\n送上級法院」。"
  },
  "characters": {
    "judges": [
      "呂政燁"
    ],
    "prosecutors": [

    ],
    "lawyers": [

    ],
    "clerks": [
      "呂欣穎"
    ],
    "plaintiffs": [

    ],
    "defendants": [
      "甲○○"
    ],
    "prosecutor_office": [
      "臺灣臺北地方法院檢察署檢察官"
    ],
    "creditors": [

    ],
    "debtors": [

    ],
    "judicial_associate_officer": [

    ]
  },
  "adjudged_at": "2010-05-12",
  "created_at": "2016-01-05 12:05:17",
  "updated_at": "2016-01-05 12:05:17"
}