{
  "identify": "TPD-99-簡-1-20100105-1",
  "court": {
    "name": "臺灣臺北地方法院",
    "code": "TPD"
  },
  "division": {
    "name": "刑事",
    "code": "M"
  },
  "year": 99,
  "word": "簡",
  "number": "1",
  "jcheck": "1",
  "reason": "贓物",
  "content": "臺灣臺北地方法院刑事簡易判決             99年度簡字第1號\n聲  請  人  臺灣臺北地方法院檢察署檢察官\n被      告  甲○○\n上列被告因贓物案件，經檢察官聲請以簡易判決處刑（98年度調\n偵字第1132號），本院判決如下：\n    主  文\n甲○○故買贓物，累犯，處有期徒刑月，如易科罰金，以新臺\n幣壹仟元折算壹日。\n    事實及理由\n一、本案犯罪事實及證據除引用如附件所示之聲請簡易判決處刑\n    書之記載外，另補充記載如下：甲○○前於民國95年間因贓\n    物案件，經本院以95年度簡字第1927號判決判處有期徒刑4\n    月確定，於95年11月13日易科罰金執行完畢。\n二、核被告甲○○所為，係犯刑法第349 條第2 項之故買贓物罪\n    。被告前於95年間因贓物案件，經本院以95年度簡字第1927\n    號判決判處有期徒刑4 月確定，於95年11月13日易科罰金執\n    行完畢，此有臺灣高等法院被告前案紀錄表在卷可按，是被\n    告受前開徒刑執行完畢後，5 年以內故意再犯本案有期徒刑\n    以上之罪，為累犯，應依刑法第47條第1 項之規定，加重其\n    刑。爰審酌被告前有贓物罪前科之素行，猶不知悛悔，為貪\n    小便宜而向姓名年籍不詳綽號「小吳」之成年男子買受來源\n    不明之車輛，足以助長竊盜歪風，致使贓物追索困難，所為\n    誠屬可議，惟念及被告犯後坦承犯行，並於98年10月13日賠\n    償車主乙○○所受損失，有臺北縣新店市調解委員會98年民\n    調字第476 號調解書在卷可佐，態度尚佳，暨其犯罪之動機\n    、目的、手段、智識程度、生活狀況等一切情狀，量處如主\n    文所示之刑，並諭知易科罰金之折算標準，以示懲儆。\n三、依刑事訴訟法第449 條第1 項前段、第3 項、第454 條第1\n    項，刑法第349 條第2 項、第47條第1 項、第41條第1 項前\n    段，刑法施行法第1 條之1 ，逕以簡易判決處刑如主文。\n四、如不服本判決，得自收受送達之日起10日內，向本院提起上\n    訴。\n中    華    民    國    99    年    1     月    5     日\n                  刑事第十八庭  法  官  林芳華\n以上正本證明與原本無異。\n                                書記官  林鈴芬\n中    華    民    國    99    年    1     月    5     日\n附錄本案論罪科刑法條\n刑法第349條\n收受贓物者，處3 年以下有期徒刑、拘役或5 百元以下罰金。\n搬運、寄藏、故買贓物或為牙保者，處5 年以下有期徒刑、拘役\n或科或併科1 千元以下罰金。\n因贓物變得之財物，以贓物論。",
  "structure": {
    "main": "甲○○故買贓物，累犯，處有期徒刑月，如易科罰金，以新臺\n幣壹仟元折算壹日。",
    "fact": "一、本案犯罪事實及證據除引用如附件所示之聲請簡易判決處刑\n    書之記載外，另補充記載如下：甲○○前於民國95年間因贓\n    物案件，經本院以95年度簡字第1927號判決判處有期徒刑4\n    月確定，於95年11月13日易科罰金執行完畢。\n二、核被告甲○○所為，係犯刑法第349 條第2 項之故買贓物罪\n    。被告前於95年間因贓物案件，經本院以95年度簡字第1927\n    號判決判處有期徒刑4 月確定，於95年11月13日易科罰金執\n    行完畢，此有臺灣高等法院被告前案紀錄表在卷可按，是被\n    告受前開徒刑執行完畢後，5 年以內故意再犯本案有期徒刑\n    以上之罪，為累犯，應依刑法第47條第1 項之規定，加重其\n    刑。爰審酌被告前有贓物罪前科之素行，猶不知悛悔，為貪\n    小便宜而向姓名年籍不詳綽號「小吳」之成年男子買受來源\n    不明之車輛，足以助長竊盜歪風，致使贓物追索困難，所為\n    誠屬可議，惟念及被告犯後坦承犯行，並於98年10月13日賠\n    償車主乙○○所受損失，有臺北縣新店市調解委員會98年民\n    調字第476 號調解書在卷可佐，態度尚佳，暨其犯罪之動機\n    、目的、手段、智識程度、生活狀況等一切情狀，量處如主\n    文所示之刑，並諭知易科罰金之折算標準，以示懲儆。\n三、依刑事訴訟法第449 條第1 項前段、第3 項、第454 條第1\n    項，刑法第349 條第2 項、第47條第1 項、第41條第1 項前\n    段，刑法施行法第1 條之1 ，逕以簡易判決處刑如主文。\n四、如不服本判決，得自收受送達之日起10日內，向本院提起上\n    訴。",
    "reason": "一、本案犯罪事實及證據除引用如附件所示之聲請簡易判決處刑\n    書之記載外，另補充記載如下：甲○○前於民國95年間因贓\n    物案件，經本院以95年度簡字第1927號判決判處有期徒刑4\n    月確定，於95年11月13日易科罰金執行完畢。\n二、核被告甲○○所為，係犯刑法第349 條第2 項之故買贓物罪\n    。被告前於95年間因贓物案件，經本院以95年度簡字第1927\n    號判決判處有期徒刑4 月確定，於95年11月13日易科罰金執\n    行完畢，此有臺灣高等法院被告前案紀錄表在卷可按，是被\n    告受前開徒刑執行完畢後，5 年以內故意再犯本案有期徒刑\n    以上之罪，為累犯，應依刑法第47條第1 項之規定，加重其\n    刑。爰審酌被告前有贓物罪前科之素行，猶不知悛悔，為貪\n    小便宜而向姓名年籍不詳綽號「小吳」之成年男子買受來源\n    不明之車輛，足以助長竊盜歪風，致使贓物追索困難，所為\n    誠屬可議，惟念及被告犯後坦承犯行，並於98年10月13日賠\n    償車主乙○○所受損失，有臺北縣新店市調解委員會98年民\n    調字第476 號調解書在卷可佐，態度尚佳，暨其犯罪之動機\n    、目的、手段、智識程度、生活狀況等一切情狀，量處如主\n    文所示之刑，並諭知易科罰金之折算標準，以示懲儆。\n三、依刑事訴訟法第449 條第1 項前段、第3 項、第454 條第1\n    項，刑法第349 條第2 項、第47條第1 項、第41條第1 項前\n    段，刑法施行法第1 條之1 ，逕以簡易判決處刑如主文。\n四、如不服本判決，得自收受送達之日起10日內，向本院提起上\n    訴。"
  },
  "characters": {
    "judges": [
      "林芳華"
    ],
    "prosecutors": [

    ],
    "lawyers": [

    ],
    "clerks": [
      "林鈴芬"
    ],
    "plaintiffs": [

    ],
    "defendants": [
      "甲○○"
    ],
    "prosecutor_office": [
      "臺灣臺北地方法院檢察署檢察官"
    ],
    "creditors": [

    ],
    "debtors": [

    ],
    "judicial_associate_officer": [

    ]
  },
  "adjudged_at": "2010-01-05",
  "created_at": "2016-01-05 15:12:31",
  "updated_at": "2016-01-05 15:12:31"
}