{
  "identify": "TPD-99-智易-16-20100512-1",
  "court": {
    "name": "臺灣臺北地方法院",
    "code": "TPD"
  },
  "division": {
    "name": "刑事",
    "code": "M"
  },
  "year": 99,
  "word": "智易",
  "number": "16",
  "jcheck": "1",
  "reason": "違反著作權法",
  "content": "臺灣臺北地方法院刑事判決              99年度智易字第16號\n公  訴  人  臺灣臺北地方法院檢察署檢察官\n被      告  皕富興有限公司\n代  表  人\n兼  被  告  乙○○\n選任辯護人  陳昆明律師\n上列被告因違反著作權法案件，經檢察官聲請簡易判決處刑（98\n年度偵字第26221 號），而本院認不應以簡易判決處刑（98年度\n簡字第5156號），而改依通常審判程序（99年度智易字第16號）\n審理、判決如下：\n    主  文\n本件公訴不受理。\n    理  由\n一、公訴意旨略以：被告乙○○為被告皕富興有限公司負責人，\n    明知如附圖所示之「TAIWAN」書法字樣，係甲○○擁有著作\n    權之美術著作，未經甲○○之許可或授權，不得非法重製或\n    散布，竟仍於民國97年12月間，擅自重製如附圖所示之書法\n    字樣為鋁燙片及絨布商品，意圖販售予不特定人。嗣為甲○\n    ○之子徐浩登，於97年12月11日查知，始悉獲上情，因認被\n    告乙○○涉犯違反著作權法第91條第1 項擅自以重製方法侵\n    害他人之著作財產權及同法第91條之1第2項之明知係侵害著\n    作財產權之物而散布等罪嫌，且被告皕富興業有限公司，因\n    法人之代表人執行業務，犯著作權法第91條第1 項及第91條\n    之1第2項罪名者，對該法人依著作權第101條第1項規定亦科\n    各該條之罰金刑罪嫌。\n二、按告訴乃論之罪，未經告訴者，應諭知不受理之判決，並得\n    不經言詞辯論為之，刑事訴訟法第303條第3款、第307 條分\n    別定有明文。又犯罪之被害人得為告訴，固為刑事訴訟法第\n    232 條所明定，但此之所謂犯罪之被害人，係指因犯罪而直\n    接受損害之人而言，其間接或附帶受害之人不與焉。再按著\n    作權法第100條規定：「本章之罪，須告訴乃論。但犯第91\n    條第3 項及第91條之1第3項之罪，不在此限」。是本案被告\n    等上開所犯既屬違反著作權法第91條第1項，及第91條之1第\n    2項之規定，依同法第100條之規定，自屬告訴乃論之罪，合\n    先敘明。\n三、證據能力部分：\n    按被告以外之人於審判外之言詞或書面陳述，除法律有規定\n    者外，不得作為證據。又被告以外之人於審判外之陳述，雖\n    不符前4 條之規定，而經當事人於審判程序同意作為證據，\n    法院審酌該言詞陳述或書面陳述作成時之情況，認為適當者\n    ，亦得為證據。當事人、代理人或辯護人於法院調查證據時\n    ，知有第159 條第1 項不得為證據之情形，而未於言詞辯論\n    終結前聲明異議者，視為有前項同意，刑事訴訟法159 條第\n    1 項、第159 條之5 分別定有明文。查除告訴代理人陳玉玲\n    於98年7月9日於警詢之指述、告訴代理人徐浩登於98年7 月\n    9 日警詢之指述、告訴代理人徐浩登於98年10月9 日檢察官\n    偵查時之指述，為被告以外之人於審判外之陳述，不得作為\n    證據外，其餘本院認定事實所引用之下列證據資料（包含供\n    述證據、文書證據等），並無證據證明係公務員違背法定程\n    序所取得。又被告等人及檢察官於本院審判期日中對本院所\n    提示有關被告以外之人審判外之供述，包括供述證據、文書\n    證據等證據，就證據能力均未表示爭執，而迄至言詞辯論終\n    結前亦未再聲明異議，經核亦無顯有不可信之情況與不得作\n    為證據之情形，本院審酌上開證據資料製作時之情況，尚無\n    違法不當及證明力明顯過低之瑕疵，認為以之作為證據應屬\n    適當，是依刑事訴訟法第159條至第159條之5 規定，本院所\n    引用之供述證據及文書證據等，如下揭示均有證據能力，玆\n    分述之。\n四、訊據被告乙○○固不否認並未享有「島型台灣」及「TAIWAN\n    」圖樣之著作權，亦未有他人授權使用，而將上揭圖案製作\n    我愛臺灣─鋁燙片及絨布商品等於網路中販賣之事實，惟堅\n    決否認有何前揭違反著作權法之犯行，並辯稱：(1)被告乙○\n    ○認為「TAIWAN」圖樣是觀光局的ＣＩＳ標誌，應屬公共財\n    ，且從雅虎奇摩網站都可以列印，應是可供公眾分享之圖樣\n    ，遂採為衣服彩飾設計圖樣，被告並無侵害任何人著作權之\n    認知，當然亦不知該「TAIWAN」圖樣係告訴人甲○○之著作\n    （事實上不全是甲○○之書法），被告乙○○並無侵害告訴\n    人所有之著作權犯意；(2)直至被告乙○○接獲告訴人所委託\n    之律師信函後，上網以「甲○○」名字作關鍵字搜尋，始得\n    知甲○○敘述其書寫「TAIWAN」之歷程，被告因此認為係侵\n    害甲○○之著作權，立刻向甲○○道歉，但甲○○之家人卻\n    不接受道歉，反要求被告購買使用權，但因被告只設計一件\n    衣服，反應並不理想，所以不想買其使用權；(3)自本件卷附\n    之臺灣士林地方法院91年度訴字第727 號民事確定判決以觀\n    ，交通部觀光局之企業識別系統（ＣＩＳ）標誌之「TAIWAN\n    」六個英文字係案外人元平設計有限公司由告訴人之多張「\n    TAIWAN」之書法中分別挑選其中「Ｔ」、「Ａ」、「Ｉ」、\n    「Ｎ」，然後加上蕭元平自己書寫之「Ｗ」，編輯而成，因\n    此系爭「TAIWAN」圖樣並非告訴人所稱侵權之書法著作。況\n    被告所引用觀光局之ＣＩＳ標誌係案外人永平設計有限公司\n    之編輯著作，並以將其編輯著作財產權讓與案外人聯旭國際\n    股份有限公司，聯旭公司則全部轉讓予交通部觀光局。因此\n    ，本件包括「TAIWAN」圖樣在內之觀光局ＣＩＳ標誌之著作\n    財產權應為交通部觀光局所有，足證被告並未侵害告訴人之\n    著作財產權；(4)至於交通部觀光局之ＣＩＳ標誌，基於政府\n    大力發展觀光事業之目的，當然希望廣為宣傳，甚至將ＣＩ\n    Ｓ標誌介紹推廣至海內外，被告引用交通部觀光局ＣＩＳ標\n    誌中之部分圖樣，設計作為衣服圖飾，實無侵害交通部觀光\n    局著作財產權可言；(5)綜上，本件被告乙○○使用交通部觀\n    光局之ＣＩＳ標誌，其著作財產權屬於交通部觀光局，本件\n    既未經告訴權人交通部觀光局告訴，應依刑事訴訟法第303\n    條第3款規定，諭知不受理之判決等語。\n五、本院查：\n(一)、上開本件交通部觀光局使用於ＣＩＳ標誌中之「TAIWAN」圖\n    樣之著作財產權歸屬於交通部觀光局或告訴人甲○○，首應\n    究明：\n  1.按書法為著作權法第5條第1項各款著作內容例示第4 款所稱\n    之美術著作，又按，「出資聘請他人完成之著作，除前條情\n    形外，以該受聘人為著作人。但契約約定以出資人為著作人\n    者，從其約定。依前項規定，以受聘人為著作人者，其著作\n    財產權依契約約定歸受聘人或出資人享有。未約定著作財產\n    權之歸屬者，其著作財產權歸受聘人享有。依前項規定著作\n    財產權歸受聘人享有者，出資人得利用該著作」，著作權法\n    第12條定有明文。查，案外人聯旭國際股份有限公司（下稱\n    聯旭公司）於90年7 月間某日，聘請告訴人甲○○揮毫書法\n    作品，告訴人亦明知聯旭公司聘請其創作之目的在於作為參\n    與交通部觀光局競圖之用，雙方未進一步為著作權歸屬之約\n    定等情，應認雙方係出資聘請他人完成著作之關係，依前揭\n    法條規定，該等書法作品以受聘人即告訴人為著作人，享有\n    著作人格權與財產權，但依著作權法第12條第3 項規定，聯\n    旭公司自得在出資目的範圍內，將上開書法作品利用為製作\n    ＣＩＳ標誌之素材，並進行利用行為所必須之修改、增刪，\n    且該等利用行為並不影響告訴人書法作品之著作財產權之事\n    實，迭經臺灣士林地方法院91年度訴字第727 號民事判決確\n    定在案，亦有該判決書附卷可稽。\n  2.本件上開「TAIWAN」圖樣之著作財產權歸屬於交通部觀光局\n    ，且使用於ＣＩＳ標誌中之「TAIWAN」圖樣：\n  (1)按「就資料之選擇及編排具有創作性者為編輯著作，以獨立\n    之著作保護之。編輯著作之保護，對其所收編著作之著作權\n    不生影響」，著作權法第7 條定有明文。經查，案外人聯旭\n    公司以60萬元之價格，委託案外人元平設計有限公司（下稱\n    元平公司）設計ＣＩＳ識別標誌及整體運用方式，並將上開\n    告訴人甲○○書寫之毛筆字交由元平公司利用，元平公司挑\n    選其適用之「Ｔ」、「Ａ」、「Ｉ」、「Ｎ」、「臺灣」等\n    字體，各別掃描入電腦中，以電腦略作修改，加上臺灣島形\n    電腦繪圖、「Touch Your Heart」標語等其他元素，以及元\n    平公司總經理蕭元平所書寫之「Ｗ」，重新組合成交通部觀\n    光局之ＣＩＳ標誌，再由元平公司將上開著作財產權移轉予\n    聯旭公司等情，業據另案證人蕭元平（見臺灣臺北地方法院\n    91年度訴字第727號之證人蕭元平於91年8月28日言詞辯論筆\n    錄）證述綦詳，並有告訴人所書寫之毛筆字影本9 張（見臺\n    灣臺北地方法院91年度訴字第727號卷一，以下簡稱本院727\n    號卷一，第87至95頁）、聯旭公司於90年7 月16日向交通部\n    觀光局提案之初稿（見本院727 號卷一第99頁）、另案證人\n    蕭元平書寫之「Ｗ」原稿（見本院727 號卷一第78頁）、以\n    及被告所提供之交通部觀光局ＣＩＳ標誌之最後成品（見臺\n    灣臺北地方法院99年度智易字第16號編號A，以下簡稱A卷，\n    第28至52頁）在卷可稽，核與本件之案外人聯旭公司創作情\n    形，係將另案證人蕭元平自行創作之「Ｗ」等部分與利用告\n    訴人著作物之部分加以編輯，再本於自己獨立之思維、智巧\n    、技匠完成最後交通部觀光局ＣＩＳ標誌成品，聯旭公司就\n    資料之選取及編排具有原創性，可認為是獨立之編輯著作，\n    而享有著作權。再者，另聯旭公司於另案中自承與案外人元\n    平公司未簽約書面契約（參見臺灣臺北地方法院91年度訴字\n    第727號之91年9月25日言詞辯論筆錄），不能證明雙方有特\n    別約定，依著作權法第12條第1 項規定，受聘人元平設計有\n    限公司原始取得該編輯著作之著作人格權及著作財產權，並\n    得依著作權法第36條規定，將著作財產權讓與聯旭公司，且\n    該編輯著作之保護，與告訴人前揭書法作品之著作權各自獨\n    立，為不同之著作，互不影響，此部分可參照卷附由告訴人\n    自行提供之臺灣士林地方法院91年度訴字第727 號民事確定\n    判決（見臺灣臺北地方法院檢察署98年度他字第6049號編號\n    B1 ，以下簡稱B1卷，第13至15頁）可佐。\n  (2)再按「著作財產權得全部或部分讓與他人或與他人共有。著\n    作財產權之受讓人，在其受讓範圍內，取得著作財產權。著\n    作財產權讓與之範圍依當事人之約定；其約定不明之部分，\n    推定為未讓與」，又「著作財產權人得授權他人利用著作，\n    其授權利用之地域、時間、內容、利用方法或其他事項，依\n    當事人之約定；其約定不明之部分，推定為未授權」，著作\n    權法第36條、第37條第1 項分別定有明文。查本件案外人元\n    平設計有限公司完成前揭ＣＩＳ標誌後，將著作財產權讓與\n    聯旭公司，已如前述，聯旭公司取得前揭ＣＩＳ標誌之著作\n    財產權，自得再依著作權法第36條、第37條規定，將該著作\n    財產權讓與他人或授權他人利用著作。再觀諸聯旭公司與交\n    通部觀光局於90年10月8 日簽訂之「90年度國際觀光宣傳推\n    廣工作計畫契約書」第14條第2 項約定：「乙方（即聯旭公\n    司）履約結果涉及智慧財產權者：（一）甲方（即交通部觀\n    光局）有權永久保存及無償使用，乙方放棄行使著作人格權\n    。（二）甲方取得全部權利。（三）乙方因履行契約所完成\n    之著作，其著作財產權之全部於著作完成之同時讓與甲方，\n    乙方放棄行使著作人格權。（四）乙方保證對其人員因履行\n    契約所完成之著作，與其人員約定以乙方為著作人，享有著\n    作財產權及著作人格權，並依前款規定辦理」等語，已明確\n    約定聯旭公司將前揭ＣＩＳ標誌之著作財產權全部讓與交通\n    部觀光局，由交通部觀光局永久取得全部權利。是以，前揭\n    ＣＩＳ標誌現在之著作財產權人為交通部觀光局，應屬無疑\n    ，亦有臺灣士林地方法院91年度訴字第727 號民事判決書在\n    卷可徵（見B1卷，第16頁）。\n  (3)末查，案外人聯旭公司出資聘請告訴人甲○○揮毫「TAIWAN\n    」書法字體，雙方無特別約定，其書法作品之著作人格權及\n    著作財產權屬於告訴人，但聯旭公司依著作權法第12條第3\n    項規定得利用該著作。嗣後聯旭公司又出資聘請案外人元平\n    公司完成ＣＩＳ標誌，並利用告訴人上開書法作品為素材，\n    元平公司所創作之ＣＩＳ標誌依著作權法第7 條亦以獨立著\n    作保護之，然對於收編為素材之告訴人書法作品之著作權並\n    不生影響，告訴人對於其所書寫之「TAIWAN」仍具有獨立之\n    著作權。惟案外人元平公司雖有利用告訴人所書寫之毛筆字\n    ，但在製作ＣＩＳ標誌時所使用之「Ｔ」、「Ａ」、「Ｉ」\n    、「Ｎ」係自告訴人所書寫毛筆字中之九張，分別挑選適合\n    之字體，並略加修改，其中「Ｗ」之部分更由另案證人蕭元\n    平所書寫，即便該「Ｗ」字體係仿告訴人書體所寫，然而著\n    作權法所保護者，乃觀念之表達，至於觀念本身，並非著作\n    權法保護之對象，筆跡、繪畫或書法之風格，亦非著作權法\n    保護之對象，元平公司基此重新組合成ＣＩＳ標誌中之「TA\n    IWAN」字體。因此，案外人元平公司原始取得ＣＩＳ標誌（\n    含ＣＩＳ標誌中之「TAIWAN」字體）之著作人格權及著作財\n    產權。案外人元平公司將ＣＩＳ標誌（含ＣＩＳ標誌中之「\n    TAIWAN」字體）之著作財產權讓與案外人聯旭公司，聯旭公\n    司再將著作財產權讓與交通部觀光局，則交通部觀光局應係\n    現在為該ＣＩＳ標誌（含ＣＩＳ標誌中之「TAIWAN」字體）\n    之著作財產權人無訛。\n(二)、綜上以觀，本件被告所辯與事實相符，應屬有據，上開交通\n    部觀光局使用於ＣＩＳ標誌中之「TAIWAN」圖樣之著作財產\n    權應歸屬於交通部觀光局，職是，本件告訴人甲○○既非因\n    犯罪受直接損害之人，其所提出之告訴係不合法，爰揆諸上\n    開規定及說明，就此部分爰不經言詞辯論，逕為諭知公訴不\n    受理之判決。\n六、據上論斷，應依刑事訴訟法第452條、第303條第3款、第307\n    條，判決如主文。\n中    華    民    國    99    年  5   月      12      日\n                  刑事第十九庭法  官  施添寶\n以上正本證明與原本無異。\n如不服本判決應於收受本判決後10日內向本院提出上訴書狀，並\n應敘述具體理由，如未敘述上訴理由者，應於上訴期間屆滿後20\n日內補提理由書狀於本院（均須按他造當事人之人數附繕本）「\n切勿逕送上級法院」。告訴人或被害人如對於本判決不服者，應\n具備理由請求檢察官上訴，其上訴期間之計算係以檢察官收受判\n決正本之日期為準。\n                              書記官  陳弘文\n中    華    民    國    99    年  5   月      12      日",
  "structure": {
    "main": "本件公訴不受理。",
    "reason": "一、公訴意旨略以：被告乙○○為被告皕富興有限公司負責人，\n    明知如附圖所示之「TAIWAN」書法字樣，係甲○○擁有著作\n    權之美術著作，未經甲○○之許可或授權，不得非法重製或\n    散布，竟仍於民國97年12月間，擅自重製如附圖所示之書法\n    字樣為鋁燙片及絨布商品，意圖販售予不特定人。嗣為甲○\n    ○之子徐浩登，於97年12月11日查知，始悉獲上情，因認被\n    告乙○○涉犯違反著作權法第91條第1 項擅自以重製方法侵\n    害他人之著作財產權及同法第91條之1第2項之明知係侵害著\n    作財產權之物而散布等罪嫌，且被告皕富興業有限公司，因\n    法人之代表人執行業務，犯著作權法第91條第1 項及第91條\n    之1第2項罪名者，對該法人依著作權第101條第1項規定亦科\n    各該條之罰金刑罪嫌。\n二、按告訴乃論之罪，未經告訴者，應諭知不受理之判決，並得\n    不經言詞辯論為之，刑事訴訟法第303條第3款、第307 條分\n    別定有明文。又犯罪之被害人得為告訴，固為刑事訴訟法第\n    232 條所明定，但此之所謂犯罪之被害人，係指因犯罪而直\n    接受損害之人而言，其間接或附帶受害之人不與焉。再按著\n    作權法第100條規定：「本章之罪，須告訴乃論。但犯第91\n    條第3 項及第91條之1第3項之罪，不在此限」。是本案被告\n    等上開所犯既屬違反著作權法第91條第1項，及第91條之1第\n    2項之規定，依同法第100條之規定，自屬告訴乃論之罪，合\n    先敘明。\n三、證據能力部分：\n    按被告以外之人於審判外之言詞或書面陳述，除法律有規定\n    者外，不得作為證據。又被告以外之人於審判外之陳述，雖\n    不符前4 條之規定，而經當事人於審判程序同意作為證據，\n    法院審酌該言詞陳述或書面陳述作成時之情況，認為適當者\n    ，亦得為證據。當事人、代理人或辯護人於法院調查證據時\n    ，知有第159 條第1 項不得為證據之情形，而未於言詞辯論\n    終結前聲明異議者，視為有前項同意，刑事訴訟法159 條第\n    1 項、第159 條之5 分別定有明文。查除告訴代理人陳玉玲\n    於98年7月9日於警詢之指述、告訴代理人徐浩登於98年7 月\n    9 日警詢之指述、告訴代理人徐浩登於98年10月9 日檢察官\n    偵查時之指述，為被告以外之人於審判外之陳述，不得作為\n    證據外，其餘本院認定事實所引用之下列證據資料（包含供\n    述證據、文書證據等），並無證據證明係公務員違背法定程\n    序所取得。又被告等人及檢察官於本院審判期日中對本院所\n    提示有關被告以外之人審判外之供述，包括供述證據、文書\n    證據等證據，就證據能力均未表示爭執，而迄至言詞辯論終\n    結前亦未再聲明異議，經核亦無顯有不可信之情況與不得作\n    為證據之情形，本院審酌上開證據資料製作時之情況，尚無\n    違法不當及證明力明顯過低之瑕疵，認為以之作為證據應屬\n    適當，是依刑事訴訟法第159條至第159條之5 規定，本院所\n    引用之供述證據及文書證據等，如下揭示均有證據能力，玆\n    分述之。\n四、訊據被告乙○○固不否認並未享有「島型台灣」及「TAIWAN\n    」圖樣之著作權，亦未有他人授權使用，而將上揭圖案製作\n    我愛臺灣─鋁燙片及絨布商品等於網路中販賣之事實，惟堅\n    決否認有何前揭違反著作權法之犯行，並辯稱：(1)被告乙○\n    ○認為「TAIWAN」圖樣是觀光局的ＣＩＳ標誌，應屬公共財\n    ，且從雅虎奇摩網站都可以列印，應是可供公眾分享之圖樣\n    ，遂採為衣服彩飾設計圖樣，被告並無侵害任何人著作權之\n    認知，當然亦不知該「TAIWAN」圖樣係告訴人甲○○之著作\n    （事實上不全是甲○○之書法），被告乙○○並無侵害告訴\n    人所有之著作權犯意；(2)直至被告乙○○接獲告訴人所委託\n    之律師信函後，上網以「甲○○」名字作關鍵字搜尋，始得\n    知甲○○敘述其書寫「TAIWAN」之歷程，被告因此認為係侵\n    害甲○○之著作權，立刻向甲○○道歉，但甲○○之家人卻\n    不接受道歉，反要求被告購買使用權，但因被告只設計一件\n    衣服，反應並不理想，所以不想買其使用權；(3)自本件卷附\n    之臺灣士林地方法院91年度訴字第727 號民事確定判決以觀\n    ，交通部觀光局之企業識別系統（ＣＩＳ）標誌之「TAIWAN\n    」六個英文字係案外人元平設計有限公司由告訴人之多張「\n    TAIWAN」之書法中分別挑選其中「Ｔ」、「Ａ」、「Ｉ」、\n    「Ｎ」，然後加上蕭元平自己書寫之「Ｗ」，編輯而成，因\n    此系爭「TAIWAN」圖樣並非告訴人所稱侵權之書法著作。況\n    被告所引用觀光局之ＣＩＳ標誌係案外人永平設計有限公司\n    之編輯著作，並以將其編輯著作財產權讓與案外人聯旭國際\n    股份有限公司，聯旭公司則全部轉讓予交通部觀光局。因此\n    ，本件包括「TAIWAN」圖樣在內之觀光局ＣＩＳ標誌之著作\n    財產權應為交通部觀光局所有，足證被告並未侵害告訴人之\n    著作財產權；(4)至於交通部觀光局之ＣＩＳ標誌，基於政府\n    大力發展觀光事業之目的，當然希望廣為宣傳，甚至將ＣＩ\n    Ｓ標誌介紹推廣至海內外，被告引用交通部觀光局ＣＩＳ標\n    誌中之部分圖樣，設計作為衣服圖飾，實無侵害交通部觀光\n    局著作財產權可言；(5)綜上，本件被告乙○○使用交通部觀\n    光局之ＣＩＳ標誌，其著作財產權屬於交通部觀光局，本件\n    既未經告訴權人交通部觀光局告訴，應依刑事訴訟法第303\n    條第3款規定，諭知不受理之判決等語。\n五、本院查：\n(一)、上開本件交通部觀光局使用於ＣＩＳ標誌中之「TAIWAN」圖\n    樣之著作財產權歸屬於交通部觀光局或告訴人甲○○，首應\n    究明：\n  1.按書法為著作權法第5條第1項各款著作內容例示第4 款所稱\n    之美術著作，又按，「出資聘請他人完成之著作，除前條情\n    形外，以該受聘人為著作人。但契約約定以出資人為著作人\n    者，從其約定。依前項規定，以受聘人為著作人者，其著作\n    財產權依契約約定歸受聘人或出資人享有。未約定著作財產\n    權之歸屬者，其著作財產權歸受聘人享有。依前項規定著作\n    財產權歸受聘人享有者，出資人得利用該著作」，著作權法\n    第12條定有明文。查，案外人聯旭國際股份有限公司（下稱\n    聯旭公司）於90年7 月間某日，聘請告訴人甲○○揮毫書法\n    作品，告訴人亦明知聯旭公司聘請其創作之目的在於作為參\n    與交通部觀光局競圖之用，雙方未進一步為著作權歸屬之約\n    定等情，應認雙方係出資聘請他人完成著作之關係，依前揭\n    法條規定，該等書法作品以受聘人即告訴人為著作人，享有\n    著作人格權與財產權，但依著作權法第12條第3 項規定，聯\n    旭公司自得在出資目的範圍內，將上開書法作品利用為製作\n    ＣＩＳ標誌之素材，並進行利用行為所必須之修改、增刪，\n    且該等利用行為並不影響告訴人書法作品之著作財產權之事\n    實，迭經臺灣士林地方法院91年度訴字第727 號民事判決確\n    定在案，亦有該判決書附卷可稽。\n  2.本件上開「TAIWAN」圖樣之著作財產權歸屬於交通部觀光局\n    ，且使用於ＣＩＳ標誌中之「TAIWAN」圖樣：\n  (1)按「就資料之選擇及編排具有創作性者為編輯著作，以獨立\n    之著作保護之。編輯著作之保護，對其所收編著作之著作權\n    不生影響」，著作權法第7 條定有明文。經查，案外人聯旭\n    公司以60萬元之價格，委託案外人元平設計有限公司（下稱\n    元平公司）設計ＣＩＳ識別標誌及整體運用方式，並將上開\n    告訴人甲○○書寫之毛筆字交由元平公司利用，元平公司挑\n    選其適用之「Ｔ」、「Ａ」、「Ｉ」、「Ｎ」、「臺灣」等\n    字體，各別掃描入電腦中，以電腦略作修改，加上臺灣島形\n    電腦繪圖、「Touch Your Heart」標語等其他元素，以及元\n    平公司總經理蕭元平所書寫之「Ｗ」，重新組合成交通部觀\n    光局之ＣＩＳ標誌，再由元平公司將上開著作財產權移轉予\n    聯旭公司等情，業據另案證人蕭元平（見臺灣臺北地方法院\n    91年度訴字第727號之證人蕭元平於91年8月28日言詞辯論筆\n    錄）證述綦詳，並有告訴人所書寫之毛筆字影本9 張（見臺\n    灣臺北地方法院91年度訴字第727號卷一，以下簡稱本院727\n    號卷一，第87至95頁）、聯旭公司於90年7 月16日向交通部\n    觀光局提案之初稿（見本院727 號卷一第99頁）、另案證人\n    蕭元平書寫之「Ｗ」原稿（見本院727 號卷一第78頁）、以\n    及被告所提供之交通部觀光局ＣＩＳ標誌之最後成品（見臺\n    灣臺北地方法院99年度智易字第16號編號A，以下簡稱A卷，\n    第28至52頁）在卷可稽，核與本件之案外人聯旭公司創作情\n    形，係將另案證人蕭元平自行創作之「Ｗ」等部分與利用告\n    訴人著作物之部分加以編輯，再本於自己獨立之思維、智巧\n    、技匠完成最後交通部觀光局ＣＩＳ標誌成品，聯旭公司就\n    資料之選取及編排具有原創性，可認為是獨立之編輯著作，\n    而享有著作權。再者，另聯旭公司於另案中自承與案外人元\n    平公司未簽約書面契約（參見臺灣臺北地方法院91年度訴字\n    第727號之91年9月25日言詞辯論筆錄），不能證明雙方有特\n    別約定，依著作權法第12條第1 項規定，受聘人元平設計有\n    限公司原始取得該編輯著作之著作人格權及著作財產權，並\n    得依著作權法第36條規定，將著作財產權讓與聯旭公司，且\n    該編輯著作之保護，與告訴人前揭書法作品之著作權各自獨\n    立，為不同之著作，互不影響，此部分可參照卷附由告訴人\n    自行提供之臺灣士林地方法院91年度訴字第727 號民事確定\n    判決（見臺灣臺北地方法院檢察署98年度他字第6049號編號\n    B1 ，以下簡稱B1卷，第13至15頁）可佐。\n  (2)再按「著作財產權得全部或部分讓與他人或與他人共有。著\n    作財產權之受讓人，在其受讓範圍內，取得著作財產權。著\n    作財產權讓與之範圍依當事人之約定；其約定不明之部分，\n    推定為未讓與」，又「著作財產權人得授權他人利用著作，\n    其授權利用之地域、時間、內容、利用方法或其他事項，依\n    當事人之約定；其約定不明之部分，推定為未授權」，著作\n    權法第36條、第37條第1 項分別定有明文。查本件案外人元\n    平設計有限公司完成前揭ＣＩＳ標誌後，將著作財產權讓與\n    聯旭公司，已如前述，聯旭公司取得前揭ＣＩＳ標誌之著作\n    財產權，自得再依著作權法第36條、第37條規定，將該著作\n    財產權讓與他人或授權他人利用著作。再觀諸聯旭公司與交\n    通部觀光局於90年10月8 日簽訂之「90年度國際觀光宣傳推\n    廣工作計畫契約書」第14條第2 項約定：「乙方（即聯旭公\n    司）履約結果涉及智慧財產權者：（一）甲方（即交通部觀\n    光局）有權永久保存及無償使用，乙方放棄行使著作人格權\n    。（二）甲方取得全部權利。（三）乙方因履行契約所完成\n    之著作，其著作財產權之全部於著作完成之同時讓與甲方，\n    乙方放棄行使著作人格權。（四）乙方保證對其人員因履行\n    契約所完成之著作，與其人員約定以乙方為著作人，享有著\n    作財產權及著作人格權，並依前款規定辦理」等語，已明確\n    約定聯旭公司將前揭ＣＩＳ標誌之著作財產權全部讓與交通\n    部觀光局，由交通部觀光局永久取得全部權利。是以，前揭\n    ＣＩＳ標誌現在之著作財產權人為交通部觀光局，應屬無疑\n    ，亦有臺灣士林地方法院91年度訴字第727 號民事判決書在\n    卷可徵（見B1卷，第16頁）。\n  (3)末查，案外人聯旭公司出資聘請告訴人甲○○揮毫「TAIWAN\n    」書法字體，雙方無特別約定，其書法作品之著作人格權及\n    著作財產權屬於告訴人，但聯旭公司依著作權法第12條第3\n    項規定得利用該著作。嗣後聯旭公司又出資聘請案外人元平\n    公司完成ＣＩＳ標誌，並利用告訴人上開書法作品為素材，\n    元平公司所創作之ＣＩＳ標誌依著作權法第7 條亦以獨立著\n    作保護之，然對於收編為素材之告訴人書法作品之著作權並\n    不生影響，告訴人對於其所書寫之「TAIWAN」仍具有獨立之\n    著作權。惟案外人元平公司雖有利用告訴人所書寫之毛筆字\n    ，但在製作ＣＩＳ標誌時所使用之「Ｔ」、「Ａ」、「Ｉ」\n    、「Ｎ」係自告訴人所書寫毛筆字中之九張，分別挑選適合\n    之字體，並略加修改，其中「Ｗ」之部分更由另案證人蕭元\n    平所書寫，即便該「Ｗ」字體係仿告訴人書體所寫，然而著\n    作權法所保護者，乃觀念之表達，至於觀念本身，並非著作\n    權法保護之對象，筆跡、繪畫或書法之風格，亦非著作權法\n    保護之對象，元平公司基此重新組合成ＣＩＳ標誌中之「TA\n    IWAN」字體。因此，案外人元平公司原始取得ＣＩＳ標誌（\n    含ＣＩＳ標誌中之「TAIWAN」字體）之著作人格權及著作財\n    產權。案外人元平公司將ＣＩＳ標誌（含ＣＩＳ標誌中之「\n    TAIWAN」字體）之著作財產權讓與案外人聯旭公司，聯旭公\n    司再將著作財產權讓與交通部觀光局，則交通部觀光局應係\n    現在為該ＣＩＳ標誌（含ＣＩＳ標誌中之「TAIWAN」字體）\n    之著作財產權人無訛。\n(二)、綜上以觀，本件被告所辯與事實相符，應屬有據，上開交通\n    部觀光局使用於ＣＩＳ標誌中之「TAIWAN」圖樣之著作財產\n    權應歸屬於交通部觀光局，職是，本件告訴人甲○○既非因\n    犯罪受直接損害之人，其所提出之告訴係不合法，爰揆諸上\n    開規定及說明，就此部分爰不經言詞辯論，逕為諭知公訴不\n    受理之判決。\n六、據上論斷，應依刑事訴訟法第452條、第303條第3款、第307\n    條，判決如主文。"
  },
  "characters": {
    "judges": [
      "施添寶"
    ],
    "prosecutors": [

    ],
    "lawyers": [
      "陳昆明",
      "之"
    ],
    "clerks": [
      "陳弘文"
    ],
    "plaintiffs": [

    ],
    "defendants": [
      "皕富興有限公司",
      "代  表  人",
      "兼  被  告  乙○○"
    ],
    "prosecutor_office": [
      "臺灣臺北地方法院檢察署檢察官"
    ],
    "creditors": [

    ],
    "debtors": [

    ],
    "judicial_associate_officer": [

    ]
  },
  "adjudged_at": "2010-05-12",
  "created_at": "2016-01-05 12:06:27",
  "updated_at": "2016-01-05 12:06:27"
}