{
  "identify": "TPD-99-交簡-1-20100105-1",
  "court": {
    "name": "臺灣臺北地方法院",
    "code": "TPD"
  },
  "division": {
    "name": "刑事",
    "code": "M"
  },
  "year": 99,
  "word": "交簡",
  "number": "1",
  "jcheck": "1",
  "reason": "公共危險等",
  "content": "臺灣臺北地方法院刑事簡易判決           99年度交簡字第1號\n聲  請  人  臺灣臺北地方法院檢察署檢察官\n被      告  甲○○\n上列被告因公共危險等案件，經檢察官提起公訴（98年度偵字第\n24895號），因被告自白犯罪，本院改依簡易判決逕行處刑如下\n：\n    主  文\n甲○○犯不能安全駕駛動力交通工具罪，處罰金新臺幣捌萬元，\n如易服勞役，以新臺幣壹仟元折算壹日。又犯傷害罪，處有期徒\n刑參月，如易科罰金，以新臺幣壹仟元折算壹日。\n    事實及理由\n一、本件除證據部分應刪除臺北市政府警察局舉發違反道路交通\n    管理事件通知單，及應補充被告於檢察官訊問時之自白（參\n    見偵卷98年10月15日訊問筆錄）外，其餘犯罪事實及證據均\n    引用檢察官起訴書之記載（如附件）。\n二、核被告所為，係犯刑法第185 條之3 之不能安全駕駛動力交\n    通工具罪及刑法第277條第1項之傷害罪。爰審酌酒醉駕車之\n    危害及酒後不應駕車之觀念，已透過學校教育、政令宣導及\n    各類媒體廣為介紹傳達各界週知多年，被告就此應有相當之\n    認識，詎其明知飲酒後已不能安全駕駛，猶騎乘機車，心存\n    僥倖，並缺乏尊重其他用路人生命、財產安全之觀念，所為\n    實不足取。又其於訪友不遇之際，僅因猜疑被害人等可能於\n    其背後說其壞話，即遽持刀械傷害被害人之犯罪動機，及參\n    酌其於犯後已坦承犯行，犯後態度尚稱良好，兼衡其測得之\n    酒精濃度、素行、智識程度、生活狀況及被害人所受傷害等\n    一切情狀，分別就其所犯上開2罪，量處如主文所示之刑，\n    並分別諭知易服勞役及易科罰金之折算標準。至扣案被告持\n    以傷害被害人之西瓜刀1把，被告迭於警詢及檢察官偵訊時\n    否認為其所有，亦無證據足資證明該把西瓜刀係被告所有之\n    物，爰不另為沒收之諭知，併此敘明。\n三、依刑事訴訟法第449條第2項、第3項、第454條第2項，刑法\n    第185條之3、第277條第1項、第41條第1項前段、第42條第3\n    項前段，刑法施行法第1之1條第1項，逕以簡易判決處刑如\n    主文。\n四、如不服本判決，得自收受送達之日起10日內向本院提起上訴\n    。\n中    華    民    國    99     年    1    月     5    日\n                    刑事第十五庭  法  官  黃桂興\n上正本證明與原本無異。\n如不服本判決應於收受送達後10日內向本院提出上訴書狀，並應\n敘述具體理由；其未敘述上訴理由者，應於上訴期間屆滿後20日\n內向本院補提理由書（均須按他造當事人之人數附繕本）「切勿\n逕送上級法院」。告訴人或被害人如對於本判決不服者，應具備\n理由請求檢察官上訴，其上訴期間之計算係以檢察官收受判決正\n本之日期為準。\n                                  書記官  陳品潔\n中    華    民    國    99     年    1    月     5    日\n附錄本件論罪科刑法條：\n中華民國刑法第185條之3\n服用毒品、麻醉藥品、酒類或其他相類之物，不能安全駕駛動力\n交通工具而駕駛者，處一年以下有期徒刑、拘役或科或併科十五\n萬元以下罰金。\n中華民國刑法第277條\n傷害人之身體或健康者，處3年以下有期徒刑、拘役或1千元以下\n罰金。\n犯前項之罪因而致人於死者，處無期徒刑或 7 年以上有期徒刑\n；致重傷者，處 3 年以上 10 年以下有期徒刑。",
  "structure": {
    "main": "甲○○犯不能安全駕駛動力交通工具罪，處罰金新臺幣捌萬元，\n如易服勞役，以新臺幣壹仟元折算壹日。又犯傷害罪，處有期徒\n刑參月，如易科罰金，以新臺幣壹仟元折算壹日。",
    "fact": "一、本件除證據部分應刪除臺北市政府警察局舉發違反道路交通\n    管理事件通知單，及應補充被告於檢察官訊問時之自白（參\n    見偵卷98年10月15日訊問筆錄）外，其餘犯罪事實及證據均\n    引用檢察官起訴書之記載（如附件）。\n二、核被告所為，係犯刑法第185 條之3 之不能安全駕駛動力交\n    通工具罪及刑法第277條第1項之傷害罪。爰審酌酒醉駕車之\n    危害及酒後不應駕車之觀念，已透過學校教育、政令宣導及\n    各類媒體廣為介紹傳達各界週知多年，被告就此應有相當之\n    認識，詎其明知飲酒後已不能安全駕駛，猶騎乘機車，心存\n    僥倖，並缺乏尊重其他用路人生命、財產安全之觀念，所為\n    實不足取。又其於訪友不遇之際，僅因猜疑被害人等可能於\n    其背後說其壞話，即遽持刀械傷害被害人之犯罪動機，及參\n    酌其於犯後已坦承犯行，犯後態度尚稱良好，兼衡其測得之\n    酒精濃度、素行、智識程度、生活狀況及被害人所受傷害等\n    一切情狀，分別就其所犯上開2罪，量處如主文所示之刑，\n    並分別諭知易服勞役及易科罰金之折算標準。至扣案被告持\n    以傷害被害人之西瓜刀1把，被告迭於警詢及檢察官偵訊時\n    否認為其所有，亦無證據足資證明該把西瓜刀係被告所有之\n    物，爰不另為沒收之諭知，併此敘明。\n三、依刑事訴訟法第449條第2項、第3項、第454條第2項，刑法\n    第185條之3、第277條第1項、第41條第1項前段、第42條第3\n    項前段，刑法施行法第1之1條第1項，逕以簡易判決處刑如\n    主文。\n四、如不服本判決，得自收受送達之日起10日內向本院提起上訴\n    。",
    "reason": "一、本件除證據部分應刪除臺北市政府警察局舉發違反道路交通\n    管理事件通知單，及應補充被告於檢察官訊問時之自白（參\n    見偵卷98年10月15日訊問筆錄）外，其餘犯罪事實及證據均\n    引用檢察官起訴書之記載（如附件）。\n二、核被告所為，係犯刑法第185 條之3 之不能安全駕駛動力交\n    通工具罪及刑法第277條第1項之傷害罪。爰審酌酒醉駕車之\n    危害及酒後不應駕車之觀念，已透過學校教育、政令宣導及\n    各類媒體廣為介紹傳達各界週知多年，被告就此應有相當之\n    認識，詎其明知飲酒後已不能安全駕駛，猶騎乘機車，心存\n    僥倖，並缺乏尊重其他用路人生命、財產安全之觀念，所為\n    實不足取。又其於訪友不遇之際，僅因猜疑被害人等可能於\n    其背後說其壞話，即遽持刀械傷害被害人之犯罪動機，及參\n    酌其於犯後已坦承犯行，犯後態度尚稱良好，兼衡其測得之\n    酒精濃度、素行、智識程度、生活狀況及被害人所受傷害等\n    一切情狀，分別就其所犯上開2罪，量處如主文所示之刑，\n    並分別諭知易服勞役及易科罰金之折算標準。至扣案被告持\n    以傷害被害人之西瓜刀1把，被告迭於警詢及檢察官偵訊時\n    否認為其所有，亦無證據足資證明該把西瓜刀係被告所有之\n    物，爰不另為沒收之諭知，併此敘明。\n三、依刑事訴訟法第449條第2項、第3項、第454條第2項，刑法\n    第185條之3、第277條第1項、第41條第1項前段、第42條第3\n    項前段，刑法施行法第1之1條第1項，逕以簡易判決處刑如\n    主文。\n四、如不服本判決，得自收受送達之日起10日內向本院提起上訴\n    。"
  },
  "characters": {
    "judges": [
      "黃桂興"
    ],
    "prosecutors": [

    ],
    "lawyers": [

    ],
    "clerks": [
      "陳品潔"
    ],
    "plaintiffs": [

    ],
    "defendants": [
      "甲○○"
    ],
    "prosecutor_office": [
      "臺灣臺北地方法院檢察署檢察官"
    ],
    "creditors": [

    ],
    "debtors": [

    ],
    "judicial_associate_officer": [

    ]
  },
  "adjudged_at": "2010-01-05",
  "created_at": "2016-01-05 15:12:39",
  "updated_at": "2016-01-05 15:12:39"
}