{
  "identify": "TPD-98-交訴-99-20100512-1",
  "court": {
    "name": "臺灣臺北地方法院",
    "code": "TPD"
  },
  "division": {
    "name": "刑事",
    "code": "M"
  },
  "year": 98,
  "word": "交訴",
  "number": "99",
  "jcheck": "1",
  "reason": "公共危險等",
  "content": "臺灣臺北地方法院刑事判決              98年度交訴字第99號\n公  訴  人  臺灣臺北地方法院檢察署檢察官\n被      告  甲○○\n上列被告因公共危險等案件，經檢察官提起公訴（98年度偵字第\n14797 號），本院判決如下：\n    主  文\n甲○○從事業務之人，因業務上之過失傷害人，處有期徒刑參月\n，如易科罰金，以新臺幣壹仟元折算壹日。又駕駛動力交通工具\n肇事，致人受傷而逃逸，處有期徒刑陸月，如易科罰金，以新臺\n幣壹仟元折算壹日。應執行有期徒刑柒月，如易科罰金，以新臺\n幣壹仟元折算壹日。\n    事  實\n一甲○○於民國98年4 月間為營業小客車職業駕駛，負責運送不\n  特定之乘客，為從事駕駛業務之人，其於98年4 月7 日下午1\n  點20分左右，駕駛568-YG號營業小客車，沿臺北市○○路由東\n  向西方向行駛，行經臺北市○○路811 號前第3 車道時，原應\n  注意汽車駕駛人在變換車道時，應讓直行車先行，並注意安全\n  距離，且依當時情形，日間光線充足、路面乾燥無缺陷、視距\n  良好，無不能注意之情形，竟疏未注意，未與沿同向第4 車道\n  直行，由張亞平（已於98年11月16日死亡）騎乘之AZR-610 重\n  型機車保持安全距離，貿然向右變換車道至第4 車道，前述營\n  業小客車右後方遂擦撞前述重型機車左側，致該機車失控倒地\n  滑行，張亞平因此受有胸壁挫傷，及上肢、下肢多處挫傷等傷\n  害。詎甲○○於肇事後未停車救護傷患，逕行往自強隧道駛去\n  逃逸。嗣經路人魏早平在後追趕，於自強隧道內記下前述營業\n  小客車之車號，為警循線查獲，始知上情。\n二案經張亞平訴由臺北市政府警察局中山分局報請臺灣臺北地方\n  法院檢察署檢察官偵查起訴。\n    理  由\n一按被告以外之人於審判外之言詞或書面陳述，除法律有規定者\n  外，不得作為證據，刑事訴訟法第159 條第1 項固有明文；惟\n  被告以外之人於審判外之陳述，雖不符同法第159 條之1 至之\n  4 規定，而經當事人於審判程序同意作為證據，法院審酌該言\n  詞陳述或書面陳述作成時之情況，認為適當者，亦得為證據。\n  又當事人、代理人或辯護人於法院調查證據時，知有第159 條\n  第1 項不得為證據之情形，而未於言詞辯論終結前聲明異議者\n  ，視為有前項之同意，同法第159 條之5 亦定有明文。本件公\n  訴人及被告甲○○於本院準備程序及審判程序中對於本院所引\n  用之供述及非供述證據之證據能力均表示沒有爭執，且迄於言\n  詞辯論終結前未聲明異議。經審酌本院所引用之供述及非供述\n  證據資料作成時之情況，核無違法取證或其他瑕疵，認為以之\n  作為證據為適當，均得做為證據。\n二認定犯罪事實所憑之證據及理由：被告雖坦承於98年4 月7 日\n  下午1 點20分左右，駕駛568-YG號營業小客車，沿臺北市○○\n  路由東向西方向行駛，行經臺北市○○路811 號前第3 車道後\n  ，繼續往自強隧道駛去，並未停車之事實，但否認有過失傷害\n  及肇事逃逸等犯行，辯稱：其沒有撞到告訴人張亞平，從後視\n  鏡只能看到汽車，是汽車撞到右邊，往前開約50公尺有停下來\n  看，看到右側後方被撞到一點黑黑的，沒有看到告訴人，以為\n  沒事就走了，當時很多車（本院卷1 第33至34頁）云云。本院\n  認為：\n(一)過失傷害部分\n(1)依臺北市政府警察局交通警察大隊中山交通分隊道路交通事故\n  現場圖、道路交通事故補充資料表（偵卷第28、29頁），道路\n  交通事故調查報告表（同卷第31、32頁），現場、車損及告訴\n  人受傷之照片（同卷第36至40頁），國防醫學院三軍總醫院附\n  設民眾診療服務處於98年6 月10日所出具告訴人張亞平之診斷\n  證明書（同卷第46頁），及證人即告訴人張亞平於警員詢問時\n  之證言，及證人魏早平於檢察官訊問時結證稱：其於98年4 月\n  下午1 點多，在臺北市○○路811 號前看到1 部計程車擦撞1\n  部機車，計程車保險桿有一半脫落，晃著晃著，然後很明顯就\n  加速開走，往自強隧道跑。計程車是右後方擦撞機車，計程車\n  向右往外線切出去，機車就倒下去，其距離肇事地點大約50公\n  尺，依其所見是計程車後面撞到機車，機車倒地滑行，往圍籬\n  摔進去，應該是鉤到機車，有「轟轟轟」的聲音，蠻大聲的，\n  應該聽的到。其從後面追計程車，追到自強隧道，剛好自強隧\n  道塞車，無法再前進，就記下車號交給警察，因為計程車是休\n  旅式的，而且保險桿掉一半，所以可以確定就是所記車號的該\n  部計程車，不會追錯（本院卷2 第15至19頁勘驗筆錄）等語可\n  知，告訴人於98年4 月7 日下午1 點20分左右，騎乘AZR-610\n  重型機車沿臺北市○○路由東向西方向行駛，行經臺北市○○\n  路811 號前第4 車道時，機車左側遭1 部計程車擦撞倒地滑行\n  ，告訴人因此受有胸壁挫傷，及上肢、下肢多處挫傷等傷害，\n  且該部計程車於肇事後未停車救護傷患，逕行往自強隧道駛去\n  逃逸等情，堪認屬實。\n(2)由證人魏早平前述證言可知，其見肇事營業小客車逃逸後，在\n  後追趕至自強隧道，因隧道內擁塞，始能追上該車，且其辨認\n  肇事車輛之依據，除肇事車輛係休旅式之營業小客車外，尚有\n  肇事車輛後方保險桿掉落一半，在地上拖行之客觀狀態，而此\n  客觀狀態並非一般車輛通常具有之條件，證人魏早平應無誤認\n  肇事車輛之可能，參以被告前述營業小客車確屬休旅式（偵卷\n  第20至22頁），及被告坦承於98年4 月7 日下午1 點多行經臺\n  北市○○路811 號前，並於警詢時自承行駛至自強隧道時，發\n  現後保險桿在地拖行並發出聲音，遂下車將保險桿扶正（同卷\n  第13頁），且知悉車後與他人發生碰撞（本院卷1 第33頁）等\n  情，益證告訴人及證人魏早平所指於98年4 月7 日下午1 點多\n  在臺北市○○路811 號前擦撞告訴人之肇事車輛，確係被告所\n  駕駛之568-YG號營業小客車無疑。\n(3)按汽車在同向二車道以上之道路（車道數計算，不含車種專用\n  車道、機車優先道及慢車道），除應依標誌或標線之指示行駛\n  外，並應遵守下列規定：六變換車道時，應讓直行車先行，並\n  注意安全距離，道路交通安全規則第98條第1 項第6 款定有明\n  文。依證人魏早平前述證言可知，被告駕駛568-YG號營業小客\n  車行駛於臺北市○○路○ ○道之道路，於變換車道時，疏未注\n  意與告訴人之AZR-610 重型機車保持安全距離，即貿然自第3\n  車道向右變換車道至第4 車道，而違反前述規定，致右側後方\n  撞及前述機車左側，告訴人並因而受傷，其過失行為與告訴人\n  受傷之結果自有相當因果關係，此部分證據明確，已可認定被\n  告有事實欄所載過失傷害犯行，應依法論科。\n(二)肇事逃逸部分：依證人魏早平前述證言可知，被告駕駛之568-\n  YG號營業小客車於擦撞告訴人之AZR-610 重型機車後，不僅機\n  車倒地後發出「轟轟轟」之聲響，並非細微，且被告之前述營\n  業小客車後保險桿在地拖行，被告應無不知與他人發生擦撞之\n  可能，參以被告於本院行準備程序時自承當時知悉車後與他人\n  發生碰撞之事實，以為沒事就走了（本院卷1 第33頁）等語，\n  及證人魏早平關於被告於肇事後加速離去之證言，足證被告雖\n  知悉其前述營業小客車後方與他車發生擦撞之事實，且主觀上\n  對於他人可能因此擦撞而受有傷害一節，亦有認識，卻未停車\n  察看告訴人之傷勢，採取救護或其他必要措施，亦未向警察機\n  關報告，即逕行駕車離去現場，被告駕駛動力交通工具肇事致\n  人受傷而逃逸之證據明確，已可認定被告有事實欄所載肇事逃\n  逸犯行，應依法論科。\n三論罪科刑之依據：核被告所為，係犯刑法第284 條第2 項前段\n  業務過失傷害、第185 條之4 肇事逃逸等罪。前述2 行為間之\n  犯意各別，罪名不同，應分論併罰之。本院審酌過失傷害部分\n  ，告訴人所受傷勢雖非嚴重，但被告至今仍否認犯行，亦未賠\n  償；肇事逃逸部分則審酌被告雖否認犯行，但情節非重等一切\n  情狀，分別量處如主文所示之刑。又被告行為後，刑法第41條\n  於98年6 月10日修正，將原條文第2 項「前項規定於數罪併罰\n  ，其應執行之刑未逾6 個月者，亦適用之。」移列第8 項，並\n  修正為「第1 項至第3 項規定於數罪併罰，其應執行之刑未逾\n  6 個月者，亦適用之。」。嗣於98年12月30日再度修正，並自\n  99年1 月1 日施行，將原條文第8 項修正為「第1 項至第4 項\n  及第7 項之規定，於數罪併罰之數罪均得易科罰金或易服社會\n  勞動，其應執行之刑逾6 月者，亦適用之。」是數罪併罰之案\n  件，且數宣告刑均得易科罰金之情形，依98年12月30日修正後\n  刑法第41條第8 項之規定，縱所定應執行之刑逾6 個月，仍得\n  易科罰金。本件被告所犯2 罪經本院定其應執行刑有期徒刑7\n  月，自以適用新法得易科罰金之規定較有利於被告，茲依刑法\n  第41條第1 項前段諭知易科罰金之折算標準，及定其應執行之\n  刑。\n四適用之法條：刑事訴訟法第299 條第1 項前段，刑法第2 條第\n  1 項後段，284 條第2 項前段、第185 之4 條、第51條第5 款\n  、第41條第1 項前段，98年12月30日修正後刑法第41條第8 項\n  ，刑法施行法第1 條之1 。\n本案經檢察官文家倩到庭執行職務\n中    華    民    國    99    年    5     月    12    日\n                    刑事第15庭  審判長法  官   廖紋妤\n                                      法  官   黃桂興\n                                      法  官   邱蓮華\n上正本證明與原本無異。\n如不服本判決應於收受送達後10日內向本院提出上訴書狀，並應\n敘述具體理由；其未敘述上訴理由者，應於上訴期間屆滿後20日\n內向本院補提理由書（均須按他造當事人之人數附繕本）「切勿\n逕送上級法院」。告訴人或被害人如對於本判決不服者，應具備\n理由請求檢察官上訴，其上訴期間之計算係以檢察官收受判決正\n本之日期為準。\n                                      書記官   葉宜玲\n中    華    民    國    99    年    5     月    12    日\n附錄論罪科刑法條\n刑法第284條第2項\n從事業務之人，因業務上之過失傷害人者，處1 年以下有期徒刑\n、拘役或1000元以下罰金，致重傷者，處3 年以下有期徒刑、拘\n役或2000元以下罰金。\n刑法第185條之4\n駕駛動力交通工具肇事，致人死傷而逃逸者，處6 月以上5 年以\n有期徒刑。",
  "structure": {
    "main": "甲○○從事業務之人，因業務上之過失傷害人，處有期徒刑參月\n，如易科罰金，以新臺幣壹仟元折算壹日。又駕駛動力交通工具\n肇事，致人受傷而逃逸，處有期徒刑陸月，如易科罰金，以新臺\n幣壹仟元折算壹日。應執行有期徒刑柒月，如易科罰金，以新臺\n幣壹仟元折算壹日。",
    "fact": "一甲○○於民國98年4 月間為營業小客車職業駕駛，負責運送不\n  特定之乘客，為從事駕駛業務之人，其於98年4 月7 日下午1\n  點20分左右，駕駛568-YG號營業小客車，沿臺北市○○路由東\n  向西方向行駛，行經臺北市○○路811 號前第3 車道時，原應\n  注意汽車駕駛人在變換車道時，應讓直行車先行，並注意安全\n  距離，且依當時情形，日間光線充足、路面乾燥無缺陷、視距\n  良好，無不能注意之情形，竟疏未注意，未與沿同向第4 車道\n  直行，由張亞平（已於98年11月16日死亡）騎乘之AZR-610 重\n  型機車保持安全距離，貿然向右變換車道至第4 車道，前述營\n  業小客車右後方遂擦撞前述重型機車左側，致該機車失控倒地\n  滑行，張亞平因此受有胸壁挫傷，及上肢、下肢多處挫傷等傷\n  害。詎甲○○於肇事後未停車救護傷患，逕行往自強隧道駛去\n  逃逸。嗣經路人魏早平在後追趕，於自強隧道內記下前述營業\n  小客車之車號，為警循線查獲，始知上情。\n二案經張亞平訴由臺北市政府警察局中山分局報請臺灣臺北地方\n  法院檢察署檢察官偵查起訴。",
    "reason": "一按被告以外之人於審判外之言詞或書面陳述，除法律有規定者\n  外，不得作為證據，刑事訴訟法第159 條第1 項固有明文；惟\n  被告以外之人於審判外之陳述，雖不符同法第159 條之1 至之\n  4 規定，而經當事人於審判程序同意作為證據，法院審酌該言\n  詞陳述或書面陳述作成時之情況，認為適當者，亦得為證據。\n  又當事人、代理人或辯護人於法院調查證據時，知有第159 條\n  第1 項不得為證據之情形，而未於言詞辯論終結前聲明異議者\n  ，視為有前項之同意，同法第159 條之5 亦定有明文。本件公\n  訴人及被告甲○○於本院準備程序及審判程序中對於本院所引\n  用之供述及非供述證據之證據能力均表示沒有爭執，且迄於言\n  詞辯論終結前未聲明異議。經審酌本院所引用之供述及非供述\n  證據資料作成時之情況，核無違法取證或其他瑕疵，認為以之\n  作為證據為適當，均得做為證據。\n二認定犯罪事實所憑之證據及理由：被告雖坦承於98年4 月7 日\n  下午1 點20分左右，駕駛568-YG號營業小客車，沿臺北市○○\n  路由東向西方向行駛，行經臺北市○○路811 號前第3 車道後\n  ，繼續往自強隧道駛去，並未停車之事實，但否認有過失傷害\n  及肇事逃逸等犯行，辯稱：其沒有撞到告訴人張亞平，從後視\n  鏡只能看到汽車，是汽車撞到右邊，往前開約50公尺有停下來\n  看，看到右側後方被撞到一點黑黑的，沒有看到告訴人，以為\n  沒事就走了，當時很多車（本院卷1 第33至34頁）云云。本院\n  認為：\n(一)過失傷害部分\n(1)依臺北市政府警察局交通警察大隊中山交通分隊道路交通事故\n  現場圖、道路交通事故補充資料表（偵卷第28、29頁），道路\n  交通事故調查報告表（同卷第31、32頁），現場、車損及告訴\n  人受傷之照片（同卷第36至40頁），國防醫學院三軍總醫院附\n  設民眾診療服務處於98年6 月10日所出具告訴人張亞平之診斷\n  證明書（同卷第46頁），及證人即告訴人張亞平於警員詢問時\n  之證言，及證人魏早平於檢察官訊問時結證稱：其於98年4 月\n  下午1 點多，在臺北市○○路811 號前看到1 部計程車擦撞1\n  部機車，計程車保險桿有一半脫落，晃著晃著，然後很明顯就\n  加速開走，往自強隧道跑。計程車是右後方擦撞機車，計程車\n  向右往外線切出去，機車就倒下去，其距離肇事地點大約50公\n  尺，依其所見是計程車後面撞到機車，機車倒地滑行，往圍籬\n  摔進去，應該是鉤到機車，有「轟轟轟」的聲音，蠻大聲的，\n  應該聽的到。其從後面追計程車，追到自強隧道，剛好自強隧\n  道塞車，無法再前進，就記下車號交給警察，因為計程車是休\n  旅式的，而且保險桿掉一半，所以可以確定就是所記車號的該\n  部計程車，不會追錯（本院卷2 第15至19頁勘驗筆錄）等語可\n  知，告訴人於98年4 月7 日下午1 點20分左右，騎乘AZR-610\n  重型機車沿臺北市○○路由東向西方向行駛，行經臺北市○○\n  路811 號前第4 車道時，機車左側遭1 部計程車擦撞倒地滑行\n  ，告訴人因此受有胸壁挫傷，及上肢、下肢多處挫傷等傷害，\n  且該部計程車於肇事後未停車救護傷患，逕行往自強隧道駛去\n  逃逸等情，堪認屬實。\n(2)由證人魏早平前述證言可知，其見肇事營業小客車逃逸後，在\n  後追趕至自強隧道，因隧道內擁塞，始能追上該車，且其辨認\n  肇事車輛之依據，除肇事車輛係休旅式之營業小客車外，尚有\n  肇事車輛後方保險桿掉落一半，在地上拖行之客觀狀態，而此\n  客觀狀態並非一般車輛通常具有之條件，證人魏早平應無誤認\n  肇事車輛之可能，參以被告前述營業小客車確屬休旅式（偵卷\n  第20至22頁），及被告坦承於98年4 月7 日下午1 點多行經臺\n  北市○○路811 號前，並於警詢時自承行駛至自強隧道時，發\n  現後保險桿在地拖行並發出聲音，遂下車將保險桿扶正（同卷\n  第13頁），且知悉車後與他人發生碰撞（本院卷1 第33頁）等\n  情，益證告訴人及證人魏早平所指於98年4 月7 日下午1 點多\n  在臺北市○○路811 號前擦撞告訴人之肇事車輛，確係被告所\n  駕駛之568-YG號營業小客車無疑。\n(3)按汽車在同向二車道以上之道路（車道數計算，不含車種專用\n  車道、機車優先道及慢車道），除應依標誌或標線之指示行駛\n  外，並應遵守下列規定：六變換車道時，應讓直行車先行，並\n  注意安全距離，道路交通安全規則第98條第1 項第6 款定有明\n  文。依證人魏早平前述證言可知，被告駕駛568-YG號營業小客\n  車行駛於臺北市○○路○ ○道之道路，於變換車道時，疏未注\n  意與告訴人之AZR-610 重型機車保持安全距離，即貿然自第3\n  車道向右變換車道至第4 車道，而違反前述規定，致右側後方\n  撞及前述機車左側，告訴人並因而受傷，其過失行為與告訴人\n  受傷之結果自有相當因果關係，此部分證據明確，已可認定被\n  告有事實欄所載過失傷害犯行，應依法論科。\n(二)肇事逃逸部分：依證人魏早平前述證言可知，被告駕駛之568-\n  YG號營業小客車於擦撞告訴人之AZR-610 重型機車後，不僅機\n  車倒地後發出「轟轟轟」之聲響，並非細微，且被告之前述營\n  業小客車後保險桿在地拖行，被告應無不知與他人發生擦撞之\n  可能，參以被告於本院行準備程序時自承當時知悉車後與他人\n  發生碰撞之事實，以為沒事就走了（本院卷1 第33頁）等語，\n  及證人魏早平關於被告於肇事後加速離去之證言，足證被告雖\n  知悉其前述營業小客車後方與他車發生擦撞之事實，且主觀上\n  對於他人可能因此擦撞而受有傷害一節，亦有認識，卻未停車\n  察看告訴人之傷勢，採取救護或其他必要措施，亦未向警察機\n  關報告，即逕行駕車離去現場，被告駕駛動力交通工具肇事致\n  人受傷而逃逸之證據明確，已可認定被告有事實欄所載肇事逃\n  逸犯行，應依法論科。\n三論罪科刑之依據：核被告所為，係犯刑法第284 條第2 項前段\n  業務過失傷害、第185 條之4 肇事逃逸等罪。前述2 行為間之\n  犯意各別，罪名不同，應分論併罰之。本院審酌過失傷害部分\n  ，告訴人所受傷勢雖非嚴重，但被告至今仍否認犯行，亦未賠\n  償；肇事逃逸部分則審酌被告雖否認犯行，但情節非重等一切\n  情狀，分別量處如主文所示之刑。又被告行為後，刑法第41條\n  於98年6 月10日修正，將原條文第2 項「前項規定於數罪併罰\n  ，其應執行之刑未逾6 個月者，亦適用之。」移列第8 項，並\n  修正為「第1 項至第3 項規定於數罪併罰，其應執行之刑未逾\n  6 個月者，亦適用之。」。嗣於98年12月30日再度修正，並自\n  99年1 月1 日施行，將原條文第8 項修正為「第1 項至第4 項\n  及第7 項之規定，於數罪併罰之數罪均得易科罰金或易服社會\n  勞動，其應執行之刑逾6 月者，亦適用之。」是數罪併罰之案\n  件，且數宣告刑均得易科罰金之情形，依98年12月30日修正後\n  刑法第41條第8 項之規定，縱所定應執行之刑逾6 個月，仍得\n  易科罰金。本件被告所犯2 罪經本院定其應執行刑有期徒刑7\n  月，自以適用新法得易科罰金之規定較有利於被告，茲依刑法\n  第41條第1 項前段諭知易科罰金之折算標準，及定其應執行之\n  刑。\n四適用之法條：刑事訴訟法第299 條第1 項前段，刑法第2 條第\n  1 項後段，284 條第2 項前段、第185 之4 條、第51條第5 款\n  、第41條第1 項前段，98年12月30日修正後刑法第41條第8 項\n  ，刑法施行法第1 條之1 。\n本案經檢察官文家倩到庭執行職務\n中    華    民    國    99    年    5     月    12    日\n                    刑事第15庭  審判長法  官   廖紋妤\n                                      法  官   黃桂興\n                                      法  官   邱蓮華\n上正本證明與原本無異。\n如不服本判決應於收受送達後10日內向本院提出上訴書狀，並應\n敘述具體理由；其未敘述上訴理由者，應於上訴期間屆滿後20日\n內向本院補提理由書（均須按他造當事人之人數附繕本）「切勿\n逕送上級法院」。告訴人或被害人如對於本判決不服者，應具備\n理由請求檢察官上訴，其上訴期間之計算係以檢察官收受判決正\n本之日期為準。\n                                      書記官   葉宜玲"
  },
  "characters": {
    "judges": [
      "廖紋妤",
      "黃桂興",
      "邱蓮華"
    ],
    "prosecutors": [
      "文家倩"
    ],
    "lawyers": [

    ],
    "clerks": [
      "葉宜玲"
    ],
    "plaintiffs": [

    ],
    "defendants": [
      "甲○○"
    ],
    "prosecutor_office": [
      "臺灣臺北地方法院檢察署檢察官"
    ],
    "creditors": [

    ],
    "debtors": [

    ],
    "judicial_associate_officer": [

    ]
  },
  "adjudged_at": "2010-05-12",
  "created_at": "2016-01-05 12:05:46",
  "updated_at": "2016-01-05 12:05:46"
}