{
  "identify": "TPD-98-易-3726-20100104-1",
  "court": {
    "name": "臺灣臺北地方法院",
    "code": "TPD"
  },
  "division": {
    "name": "刑事",
    "code": "M"
  },
  "year": 98,
  "word": "易",
  "number": "3726",
  "jcheck": "1",
  "reason": "傷害",
  "content": "臺灣臺北地方法院刑事判決              98年度易字第3726號\n聲  請  人  臺灣臺北地方法院檢察署檢察官\n被      告  乙○○\n上列被告因傷害案件，經檢察官聲請簡易判決（98年度偵字第\n27245號），由本院改以通常程序審理，本院判決如下：\n    主  文\n本件公訴不受理。\n    理  由\n一、聲請簡易判決處刑書意旨略以：被告乙○○於民國98年9月1\n    8日晚上7時許，在臺北市○○區○○路517巷8弄，見告訴人\n    甲○○與其女友林宣岑交談，心生不快，乃與告訴人發生爭\n    吵，竟基於傷害人身體之犯意，徒手毆打告訴人頭部，並以\n    頭撞擊告訴人頭部，致告訴人受有鼻部鈍傷、流鼻血、頭皮\n    多處、左耳、左臉鈍傷之傷害，因認被告涉有刑法第277 條\n    第1 項之普通傷害罪嫌等語。\n二、按告訴乃論之罪，告訴人於第一審辯論終結前得撤回其告訴\n    ，又告訴經撤回者，應諭知不受理之判決，刑事訴訟法第23\n    8 條第1 項、第303 條第3 款定有明文。\n三、查本件告訴人告訴被告普通傷害案件，起訴書認被告係犯刑\n    法第277 條第1 項之普通傷害罪，依同法第287 條前段之規\n    定，須告訴乃論。茲據告訴人於本院98年12月29日庭訊表明\n    撤回告訴之意旨，並當庭提出撤回告訴狀，有其撤回告訴狀\n    、本院前開筆錄附卷可稽，依照上開說明，爰不經言詞辯論\n    ，逕為諭知不受理之判決。\n據上論斷，應依刑事訴訟法第452 條、第303 條第3 款、第307\n條判決如主文。\n中    華    民    國    99    年    1     月    4     日\n                  刑事第四庭  法  官  郭惠玲\n以上正本證明與原本無異\n如不服本判決，應於判決送達後10日內向本院提出上訴狀（應抄\n附繕本）。告訴人或被害人如對於本判決不服者，應具備理由請\n求檢察官上訴，其上訴期間之計算係以檢察官收受判決正本之日\n期為準。\n                              書記官  江虹儀\n中    華    民    國    99    年    1     月    4     日",
  "structure": {
    "main": "本件公訴不受理。",
    "reason": "一、聲請簡易判決處刑書意旨略以：被告乙○○於民國98年9月1\n    8日晚上7時許，在臺北市○○區○○路517巷8弄，見告訴人\n    甲○○與其女友林宣岑交談，心生不快，乃與告訴人發生爭\n    吵，竟基於傷害人身體之犯意，徒手毆打告訴人頭部，並以\n    頭撞擊告訴人頭部，致告訴人受有鼻部鈍傷、流鼻血、頭皮\n    多處、左耳、左臉鈍傷之傷害，因認被告涉有刑法第277 條\n    第1 項之普通傷害罪嫌等語。\n二、按告訴乃論之罪，告訴人於第一審辯論終結前得撤回其告訴\n    ，又告訴經撤回者，應諭知不受理之判決，刑事訴訟法第23\n    8 條第1 項、第303 條第3 款定有明文。\n三、查本件告訴人告訴被告普通傷害案件，起訴書認被告係犯刑\n    法第277 條第1 項之普通傷害罪，依同法第287 條前段之規\n    定，須告訴乃論。茲據告訴人於本院98年12月29日庭訊表明\n    撤回告訴之意旨，並當庭提出撤回告訴狀，有其撤回告訴狀\n    、本院前開筆錄附卷可稽，依照上開說明，爰不經言詞辯論\n    ，逕為諭知不受理之判決。\n據上論斷，應依刑事訴訟法第452 條、第303 條第3 款、第307\n條判決如主文。"
  },
  "characters": {
    "judges": [
      "郭惠玲"
    ],
    "prosecutors": [

    ],
    "lawyers": [

    ],
    "clerks": [
      "江虹儀"
    ],
    "plaintiffs": [

    ],
    "defendants": [
      "乙○○"
    ],
    "prosecutor_office": [
      "臺灣臺北地方法院檢察署檢察官"
    ],
    "creditors": [

    ],
    "debtors": [

    ],
    "judicial_associate_officer": [

    ]
  },
  "adjudged_at": "2010-01-04",
  "created_at": "2016-01-05 14:41:13",
  "updated_at": "2016-01-05 14:41:13"
}