{
  "identify": "TPD-98-建-35-20100512-1",
  "court": {
    "name": "臺灣臺北地方法院",
    "code": "TPD"
  },
  "division": {
    "name": "民事",
    "code": "V"
  },
  "year": 98,
  "word": "建",
  "number": "35",
  "jcheck": "1",
  "reason": "給付工程款",
  "content": "臺灣臺北地方法院民事判決                98年度建字第35號\n原      告  大築營造工程有限公司\n法定代理人  乙○○\n訴訟代理人  戊○○\n            丁○○\n            阮祺祥律師\n被      告  甲○○\n訴訟代理人  徐志明律師\n            孫寅律師\n上列當事人間給付工程款事件，本院於民國99年4月28日言詞辯\n論終結，判決如下：\n    主  文\n被告應給付原告新台幣壹佰柒拾貳萬柒仟肆佰捌拾貳元及自民國\n九十七年九月二十五日起至清償日止，按年息百分之五計算之利\n息。\n原告其餘之訴駁回。\n訴訟費用由被告負擔百分之九十九，其餘由原告負擔。\n本判決第一項於原告以新台幣伍拾柒萬伍仟捌佰貳拾柒元供擔保\n後，得為假執行，但被告如於假執行實施前，以新台幣壹佰柒拾\n貳萬柒仟肆佰捌拾貳元為原告預供擔保後，得免為假執行。\n原告其餘假執行之聲請駁回。\n    事實及理由\n壹、程序部分：\n一、按當事人得以合意定第一審管轄法院。但以關於由一定法律\n    關係而生之訴訟為限。前項合意，應以文書證之。民事訴訟\n    法第24條定有明文。依據兩造所不爭執之工程契約第64條第\n    2項約定：「因本契約之履行所引起之爭端，雙方之任何一\n    方，如提起民事訴訟，以中華民國臺灣臺北地方法院為第一\n    審管轄法院」，是兩造就系爭工程合約履行之紛爭，既已書\n    面合意由本院管轄，原告起訴請求系爭工程之工程款，本院\n    自有管轄權，合先敘明。\n二、又按訴狀送達後，原告不得將原訴變更或追加他訴，但擴張\n    或減縮應受判決事項之聲明者，不在此限。民事訴訟法第25\n    5條第1項第3款定有明文。查原告起訴時訴之聲明為請求被\n    告應給付原告新臺幣（下同）1,771,331元，並自民國96年\n    12月3日起至清償日止，按年息5％計算之利息，嗣於本院99\n    年4月28日言詞辯論期日具狀變更聲明為被告應給付原告1,7\n    71,331元及自起訴狀送達之翌日起至清償日止，按年息5％\n    計算之利息；原告就訴之聲明變更部分，核屬減縮應受判決\n    事項之聲明，揆諸前開說明，尚無不合，應予准許。\n貳、實體部分：\n一、原告起訴主張：\n（一）原告與被告於95年8月14日簽訂工程契約（下稱系爭契約\n      ），雙方合意就坐落臺北市○○區○○段4小段215地號、\n      216地號2筆土地上（門牌號碼臺北市○○區○○路1段166\n      巷44號，以下稱系爭建築物），興建地上七層地下一層之\n      住宅大樓一棟，以原告為該住宅大樓興建工程之承造人；\n      惟承造期間被告因個人好惡，恣意要求原告需依其指示更\n      改施工及建築方式，不僅延宕工程進度徒增原告工程的施\n      工成本，又與建築法規相左，原告雖婉言規勸，被告仍一\n      意孤行，若原告據理力爭，被告即以解約要脅；另原告請\n      求撥發每屆各期工程結算款項時，被告則藉故拖延、苛扣\n      ，原告為維持營運及商業信用，不得已付息借款，購料、\n      支付包商請款，以及支付薪資，經多次促請原告依合約規\n      定協助結算以及撥發每期工程款，以利工程之進行，惟被\n      告仍藉詞拖延；詎料，被告逕於96年7月8日以北投實踐郵\n      局（臺北139支局）第2259號存證信函通知原告：「本工\n      程結構部分已完成，本人甲○○及陽信信託銀行無意與貴\n      公司再續合約，即日起與貴公司終止合約關係，並請貴公\n      司立即派員結算工程之工程款項，另有必要履行之未完成\n      部分之合約工程，請在一星期內完成，如在期限內未完成\n      的工作，本人即將代為處理，延生的費用則由貴公司保留\n      款中扣除。」原告經多次請被告考量該大樓興建工程已近\n      竣工，如雙方終止合約，工期又將延宕，雙方均將受有嚴\n      重損失，惟被告仍堅持解除合約，原告只得依被告之指示\n      提送結算資料辦理結案事宜；原告與被告所委任之現場工\n      地主任即訴外人丙○○於96年10月3日完成彙算結案之事\n      宜，經雙方結算後同意：原告得請求被告撥發工程款項\n      2,704,440元，但原告就本工程需扣減933,109元款項，兩\n      相抵銷，被告應再給付原告1,771,331元；被告並據此交\n      付發票日為96年12月3日，票面金額為909,000元，發票人\n      為曜先營造有限公司，支票號碼為EA0000000號之支票1紙\n      ；餘款則約定於96年11月份給付；然事後被告避不見面，\n      而上開發票日為96年12月3日之支票屆期提示亦遭退票，\n      雖經原告多次請求被告給付前述款項，被告均置之不理，\n      爰依兩造工程契約第48條之承攬關係及兩造96年10月3日\n      結算約定，提起本件訴訟。\n（二）對於被告抗辯之陳述：\n （1）被告於96年8月7日所寄發之上述存證信函通知原告，就系\n      爭工程與被告之工地主任丙○○為結算，故丙○○於系爭\n      工程之結算部分內均在被告授權範圍內，自不需再經被告\n      同意；況被告於97年11月25日之民事答辯狀第1頁表示：\n      「被告與原告結算工程款項並簽立結案工程款項單」，是\n      被告業已承認該結算；依上，該結算對被告已生效力；且\n      該次結算除對原告得請領之工程款為討論外，並有再就系\n      爭工程建物結構體、地下室、鄰損、保固金等各項爭執併\n      予討論，而由兩造互相讓步達成合意；上情由起訴狀附證\n      三大築營造結案工程款項，內容確有記載前開項目自明；\n      兩造間所為結算性質，為就終止承攬契約後之權利義務互\n      相讓步達成合意，具有和解之效力。兩造應受結算內容之\n      拘束。\n （2）被告所指建築結構偏差造成之敲除填補等之瑕疵，業經被\n      告扣款，有兩造結算之書面即大築營造結案工程款項影本\n      第2頁第2點業已載明。至被告之其餘主張，原告否認之。\n      是被告之主張並不可採。\n （3）地下室部分業經被告扣款，有大築營造結案工程款項影本\n      第2頁第4點業已載明。至其餘部分屬裝修工程，並非原告\n      所承包之範圍。再者，被告所提支出費用之96年11月7日\n      之估價單，係裝修工程部分之防水處理，與原告無關。\n （4）鄰損部分，被告之主張，原告否認之，原告所提出裂縫照\n      片，原告否認真正；卡拉OK部分業經被告修理完畢，且經\n      結算扣款；至於致遠一路部分，當初有與屋主張洪林協議\n      ，幫忙其作門口地坪，業已施作完畢，原告所花費用共4\n      萬餘元，被告同意補貼原告1萬元，有大築營造結案工程\n      款項影本第1頁b可稽。被告之主張並不可採。\n （5）工程管理費部分，原告均有派人管理，已盡監督管理責任\n      ，被告之主張，並不可採。況被告所稱之管理費之金額係\n      含利潤，益足證被告之主張並不可採。被告主張原告在施\n      工期間未盡監督管理責任而應比例退還管理費157,809元\n      予被告，原告否認之。又所謂管理費係因被告之工地交由\n      原告進場管理維護之費用，亦即就工地內工程、材料、人\n      員等之管理維護、設立明顯標示等費用，工地內若有材料\n      遺失、人員損傷等風險均由原告負擔，亦即雙方契約第23\n      條約定施工管理之費用，而原告就該工程確有管理維護，\n      已盡監督管理責任，被告之主張，並不可採。況雙方並未\n      約定原告需派工地主任日夜駐守，是被告之抗辯主張並無\n      理由。\n （6）保固金部分，雙方結算時，已約定無保固金。\n （7）原告施工並無窗框、門框等尺寸不合之情形，就窗框等部\n      分，原告之施工方式為請吊車將窗戶吊起，自結構體外面\n      往內裝設，尺寸並無不合；就門框部分，因於結構體完成\n      ，後續尚有裝潢工程，故需預留推車可通行之寬度，而預\n      留部分之修補費用，因請款係已施作面積計算，故被告於\n      原告之前請款時已預先扣除，被告之主張，亦不可採。\n      被告雖提出估價單為證，但查兩造就系爭工程之施工位置\n      為臺北市○○路○段166巷44號，若欲變更上開門牌號碼，\n      需待全部工程完工後，始能請領新的門牌號碼，而被告所\n      提估價單，其上所載施工位置為臺北市○○路○段166巷46\n      號，為系爭工程完工後新領之門牌號碼，足見該估價單已\n      明顯不實。又依系爭建物之建物謄本之記載，系爭建物於\n      97年7月11日建築完成，而被告所提之估價單竟有98年3月\n      30日估價單，益見該估價單已明顯不實。再者，如依被告\n      所提估價單所示，則幾乎每一層樓均有瑕疵，而估價單所\n      列瑕疵又係明顯可見，則被告之工地主任丙○○結算時焉\n      有不發現之理，益足證該估價單顯有不實。另外，被告對\n      於98年9月29日準備程序筆錄所載：「（受命法官）第31\n      頁第2點部分有（5％已扣）的部分，是何意思？（原告訴\n      訟代理人）這部分是指因為灌漿上面有瑕疵已經被被告扣\n      除5％的價金，所以新台幣909060元已經扣除後的金額。\n      」並不爭執，是就灌漿上面有瑕疵已經被告扣除，現被告\n      再為主張，並不可採。再退言之，本件係因被告中途終止\n      契約，是應依兩造所訂立工程合約第48條最後一項約定：\n      「甲方（指被告）因業務之考量，得終止或解除部分或全\n      部契約，乙方（指原告）於接獲甲方通知後，應立即停工\n      並負責遣散工人，清理現場，其已完成之工程及已進場之\n      材料機具設備，由甲方依契約或準用前項第二款工程開工\n      後無法繼續施工之約定，核實給付。…所有相關憑證單據\n      及工人機具遣散費用，甲方無條件支付。」處理；而原告\n      既應立即停工，自無兩造合約第41條減價收受之適用，其\n      理至明，被告之主張，顯不可採。\n （8）原告就系爭工程之建物結構體完工並無遲延達83日之事實\n      ；本件係因被告與原承包商正良泰公司遲未解除合約、被\n      告遲遲無法交付土方證明予原告，且被告有變更工程，故\n      本件工程係因可歸責於被告之事由，未能於合約所定之時\n      間完成結構體，自不可歸責於原告。又依民法第504條規\n      定，工作遲延後，定作人受領工作時，不為保留者，承攬\n      人對於遲延之結果不負責任。本件縱法院仍認原告有遲延\n      ，然因被告於結算受領工作時，未為保留，則依上規定，\n      原告對於遲延之結果亦不負責任。\n（三）聲明：（1）被告應給付原告1,771,331元及自起送狀送達\n      翌日起至清償日止按年息百分之5計算之延滯利息。（2）\n      訴訟費用由被告負擔。（3）願供擔保請准予宣告假執行\n      。\n二、被告則抗辯：\n（一）原告所提出之被告之工地主任丙○○與原告於96年10月3\n      日所為之結算約定，僅係兩造就系爭工程加減帳所為之估\n      算，並非最終結果，須經兩造確認無誤後，始得作為最終\n      結論，此亦可由證人丙○○到庭之證詞益證此點。且系爭\n      工程諸多瑕疵係於上開結算書簽立後，始陸續發現，被告\n      才始終未於結算書上簽名確認，該結算書之效力不應拘束\n      被告。雖有被告工地主任丙○○簽名其上，然丙○○與原\n      告簽訂結算約定時，亦未有附上被告委任狀，該結算約定\n      不可拘束被告至明。\n（二）被告雖與原告間有訂立系爭工程契約並不爭執，然原告因\n      有下列施工不良之情形，造成其所建築之該棟大樓有重大\n      瑕疵，致被告有損失，原告所發生之瑕疵如下：\n （1）系爭建物結構體部分，因混凝土未搗實，造成建物多處產\n      生孔洞，並有鋼筋外露、漏水之情形，另放樣及模板精準\n      度偏差，需打除重新修補，另屋突三水箱漏水亦需修補，\n      至於修補金額，需鑑定後方可確定。\n （2）地下室蓄水池、污水坑及電梯機漏水至多處積水及產生水\n      漬痕跡，此部分係因原告施工不善所產生之瑕疵，理應由\n      原告負修繕義務，惟原告置之不理，被告已委由廣修企業\n      有限公司修補並支出140,394元工程修補金，此部份支出\n      原告應予以返還。\n （3）因本件建物施工不當，致隔鄰致遠一路二段112巷20號之\n      一張家（屋主為張洪林、林麗珠）房舍有磁磚、天花板龜\n      裂及漏水、地面隆起，建物變形龜裂達20公分，此部分因\n      原告施工不當所致，應由原告負責修繕，惟尚未修繕完畢\n      ，且其金額須經鑑定後始得確定。\n （4）另依據原告施工期間之施工日報表所示，原告所設之工地\n      主任自95年7月25日至96年6月28日共11個月施工期間，僅\n      有5個月有於日報表上簽名，顯見原告於6個月期間並未確\n      實負起監督施工之管理責任，是原告就被告所給付之管理\n      費289,317元，應扣除未實地監工管理之日數，即返還157\n      ,809元（289,317×6/11＝157,809）。\n （5）又依系爭工程合約第44條規定，縱然兩造解除系爭契約，\n      乙方（即原告）就系爭工程提供裝修、機電、防水（屋頂\n      防水除外）、壁癌、交通設施、自來水工程…等保固工作\n      且按系爭契約第45條約定，保固金應按總價千分之6計算\n      ，本件總工程款為7,308,132元，故原告尚應提供43,849\n      元保固金（7,308,132×6/1000＝43,849）予被告。\n （6）再依系爭契約第41條之約定，原告施工時，若尺寸不合規\n      定，按契約單價比例扣減，並處以扣減額五倍之違約金。\n      今原告施工品質為如契約所定，致模板偏差過大致被告額\n      外施工支出223,450元，則原告除應將上開價金返還予被\n      告外，並依約應給付1,117,250元（223,450×5＝1,117,2\n      50）。\n （7）末依系爭工程契約之附件即工程進度表之約定，系爭建物\n      結構體應於96年4月5日完工，原告卻遲至96年6月28日結\n      構體才完成，共遲延83日，依系爭契約第27條、46條之約\n      定，原告應對被告負遲延責任，計606,575元（7308,132\n      ×83/1000＝606,575）\n （8）綜上所述，原告需給付被告2,065,877元（計算式：140,3\n      94＋157,809＋43,849＋1,117,250＋606,575＝2,065,877\n      ），以及原告積欠被告上述鋼筋款項、施工造成鄰損、防\n      水工程等扣款1,008,109元（其中鋼筋670,000元、結構偏\n      差126,800元、鄰損5,000元、止漏38,409元、防水37,900\n      元、臨時用電50,000元、模板借款50,000、補空洞30,000\n      元）。系爭工程被告原應給付原告8,563,313元，已給付7\n      ,308,132元，尚欠1,255,181元。然因原告尚須給付被告\n      3,073,986（2,065,877＋1,008,109＝3,043,986），兩相\n      抵銷，原告尚應給付被告1,818,805元，是被告已不具給\n      付義務。\n（三）並聲明：（1）原告之訴駁回。（2）訴訟費用由原告負擔\n      。（3）如受不利判決，願供擔保請准免為假執行。\n三、兩造不爭執事實：\n（1）兩造於95年8月14日簽訂工程契約，雙方合意就臺北市○○\n     區○○段4小段215地號、216地號2筆土地上（門牌號碼臺\n     北市○○區○○路1段166巷44號），興建地上七層地下一\n     層之住宅大樓一棟，以原告為該住宅大樓興建工程之承造\n     人，被告為系爭契約之定作人。\n（2）被告於96年7月18日以存證信函通知原告自即日起終止兩造\n     間工程契約關係，並請求原告派員結算工程款，及就有必\n     要履行之未完工工程部分在一週內完成。\n（3）被告之工地主任丙○○與原告於96年10月3日完成結算，結\n     算結果為：系爭工程原告實際請領之工程款為7,308,132元\n     ，原告得請求被告給付之承攬報酬為2,704,440元,，但原\n     告就系爭工程部分應扣減款項為933,109元，故核計後被告\n     尚應給付原告承攬報酬1,771,331元。\n（4）被告交付原告1紙發票人為曜先營造有限公司、支票號碼為\n     EA0000000、票面金額909,000元、受款人為原告、發票日\n     為96年12月3日之支票1紙以為報酬之給付，經原告於發票\n     日提示後遭退票，未獲付款。\n四、得心證之理由：\n（一）上述不爭執事實，有兩造所不爭執之系爭工程契約書、大\n      築營造結案工程款項影本、支票及退票理由單、存證信函\n      在卷可證，自可信為真實。\n（二）被告於96年7月18日以存證信函通知原告終止兩造間工程\n      契約關係，依據兩造所訂系爭工程合約第48條最後一項約\n      定：「甲方（指被告）因業務之考量，得終止或解除部分\n      或全部契約，乙方（指原告）於接獲甲方通知後，應立即\n      停工並負責遣散工人，清理現場，其已完成之工程及已進\n      場之材料機具設備，由甲方依契約或準用前項第二款工程\n      開工後無法繼續施工之約定，核實給付。但不包括所失利\n      益，所有相關憑證單據及工人機具遣散費用，甲方無條件\n      支付。」及系爭工程合約第48條第1項第二款第2目約定：\n      「已施工之工程，依本契約約定估驗計價」內容，被告於\n      終止系爭工程契約後，就原告已施工之工程，應負給付該\n      部分工程款之義務。\n（三）而原告主張兩造間已就系爭契約終止後之工程款曾為結算\n      ，且該結算之效力應及於被告，並據其提出大築營造結案\n      工程款項書面記錄在卷為證。被告雖不否認上述大築營造\n      結案工程款項書面係由被告之工地主任丙○○與原告所為\n      結算，但否認上述結算之效力及於被告，不生拘束被告之\n      效力，並為前揭抗辯。而查，上述原告所提出之大築營造\n      結案工程款項書面，雖有被告之工地主任丙○○為簽名，\n      但並未有被告之簽名，且被告雖曾於96年8月7日寄發存證\n      信函予被告，通知被告應於96年8月15日前會同丙○○丈\n      量工程計價款項數量，有原告所提出之存證信函1紙在卷\n      可證，但該存證信函內容，並無被告授權丙○○得以被告\n      之代理人名義全權處理與原告間之終止契約結算工程款事\n      宜，此有原告所提出上述存證信函在卷可據；又證人丙○\n      ○曾於本院準備程序中到庭證述：「被告有沒有說去原告\n      結算，被告即會依結算結果付款，不記得了，但我離開前\n      確實有做結算；當時因我要離職，原告叫我將該算的算一\n      算；因為被告找來新來的監工不知道狀況，所以理所當然\n      我經手的部分就要算清楚才走，我是就我經手的部分，我\n      認為該付多少錢，我就與原告算清楚；我跟被告報告後，\n      被告還會親自去看，確定後才會付款」等語（見本院98\n      年8月14日準備程序筆錄）；依據證人丙○○之上述證詞\n      可知，被告係因證人即將離職，叫證人去核算工程款，以\n      備新來之工地主任進行交接瞭解，被告當時並未授權證人\n      丙○○得全權與原告結算工程款之事實，可資確認；另外\n      ，被告雖曾交付上述支票1紙以為支付第十一次工程款909\n      ,000元，但各期之工程款係按施工進度給付之工程款，是\n      約定多少就給多少之事實，業據證人丙○○於上述準備程\n      序證述在卷，況且原告亦不否認系爭工程係按期給付工程\n      款之情，顯見系爭工程之各期工程款係依據施工進度施工\n      ，與結算無關，故被告所抗辯上述第十一期工程款本來就\n      是要由被告給付，與結算無關等語應屬事實，自不因被告\n      已交付支票給付第十一期工程款，而謂被告曾授權證人丙\n      ○○全權負責工程結算且被告已經承認結算之效力。故原\n      告主張兩造已經就系爭工程完成結算，兩造所為結算即大\n      築營造結案工程款項書面紀錄對被告亦生效力等語，即尚\n      無可據。\n（四）而依據兩造所訂系爭工程合約第48條第2項、第1項第二款\n      第2目之約定，被告應就終止契約時原告已施作之工程核\n      實給付工程，已如上述；而原告所請求之工程款給付標準\n      ，係依據原告所提出與被告之工地主任丙○○所結算之大\n      築營造結案工程款項書面為依據。本院審酌被告並不否認\n      上述書面係由被告之工地主任丙○○於被告終止系爭工程\n      合約後與原告所為之結算，且上述結算書面內容明確載明\n      應給付之工程款、扣款款項、工程施作內容之日期、工數\n      、工作內容、金額，甚且包括結算書，均有載明工程項目\n      、單位、數量、單價、總價、備註等，顯見被告之工地主\n      任丙○○於被告終止系爭工程合約後，確實就系爭工程曾\n      進行結算，而進行結算人丙○○於結算當時既任職被告之\n      工地主任，主管系爭工程現場之施工監督，當就系爭工程\n      之施作內容有相當之瞭解，故其與原告所進行之結算，就\n      工程施作項目、金額及應扣款金額等，應最能反應結算當\n      時原告就系爭工程之實際施作內容、數量、工程款及應扣\n      款事實，故原告提出大築營造結案工程款項之結算結果，\n      主張上述結算書面所載為原告於結算當時已施作工程內容\n      ，自可認為真實；另外，被告並未提出反證證明兩造於事\n      後曾另行結算，或上述結算，有何不符合事實之處。故原\n      告以上述大築營造結案工程款項之書面，主張被告應負上\n      述大築營造結案工程款項書面所載工程款之給付責任，自\n      屬有據。\n（五）至於被告上述所抗辯系爭工程施作有瑕疵及遲延，應進行\n      扣款部分，經查：\n （1）被告抗辯系爭工程有關建物結構體之部分，有因混凝土未\n      搗實，造成建物多處產生孔洞，並有鋼筋外露之情形，另\n      放樣及模板精準度偏差，需打除重新修補之建築結構偏差\n      之瑕疵，致被告支出223,450元修補之情，固據被告提出\n      現場照片、估價單在卷為證。然被告之上述抗辯，為原告\n      所否認在卷，且依據兩造所不爭執之卷附大築營造結案工\n      程款項結算書面，已記載「因建築結構偏差造成之敲除或\n      填補之工資及材料」字樣內容，且有記載扣款之金額，顯\n      然於上述結算當時，被告之工地主任丙○○曾經就此部分\n      結構體偏差之扣款為結算處理；又檢視被告所提出之估價\n      單，不僅記載系爭工程之施工位置為臺北市○○路○段166\n      巷46號，與系爭工程所在之44號不符，且依系爭建物之建\n      物謄本之記載，系爭工程之建物係於97年7月11日建築完\n      成，然上述估價單中竟有1張之日期為98年3月30日，係在\n      上述建物建築完工之後，顯示估價單之真正，乃有可疑；\n      另外，依上述估價單內容，原告所施作工程之瑕疵甚多，\n      幾乎每一層樓均有瑕疵，且所列瑕疵又係明顯可見，何以\n      被告之工地主任丙○○結算時均未發現而未以處理，此與\n      常情不符；另外，系爭工程施作之建物已經完工，且已有\n      出賣他人之事實，為被告所不否認在卷，則如被告確實支\n      出上述修補費用，應有確實之支出明細、支出記錄，不應\n      僅有如估價性質之估價單為證；上述估價單實不足以為支\n      出瑕疵修補之依據；故被告以上述證據，證明系爭工程所\n      施作之建物於結算當時有結構體偏差之瑕疵，舉證尚屬不\n      足，而不足採信。\n （2）有關被告所抗辯地下室蓄水池、污水坑及電梯機漏水等多\n      處積水及產生水漬痕跡之瑕疵，致被告支出140,394元之\n      修補費用之情，固據被告提出照片、廣修企業有限公司之\n      計價單為證。然被告之上述抗辯，亦為原告所否認，且本\n      院檢視卷附大築營造結案工程款項之結算書面，已有電梯\n      及污水坑止漏灌漿之扣款紀錄，工作內容亦有堵漏、電梯\n      機坑及污水坑、B1牆等止漏灌漿、水箱漏水處敲除等工作\n      項目之記載，顯示結算當時，被告之工地主任丙○○亦就\n      此部分有所結算處理；又被告亦不爭執上述結算書面所載\n      （廣修帳單）38,409元之部分，就是被告所提出廣修企業\n      有限公司之計價單中之一部份（見本院98年12月22日準備\n      程序筆錄），可見結算當時確實就漏水部分有所處理。另\n      外，本院再審酌被告所提出之96年11月7日計價單，工作\n      之時間自96年10月4日至96年10月27日，係在96年10月3日\n      結算翌日起進行，如於96年10月4日真有進行上述單純漏\n      水修補之需要，何以96年10月3日結算記錄並未處理，況\n      且比對被告所提出96年9月28日、96年11月7日之計價單，\n      96年11月7日記價單所載之工作項目較多（如多出環氧樹\n      脂、陶瓷粉、石英砂等，與96年9月28日帳單僅止漏劑、\n      黃油嘴、止水針頭不同），又原告陳述上述估價單不是單\n      純防漏工程要用等語，被告則未舉證證明上述計價單所載\n      確係為原告所施作工程漏水部分之單純防漏施作工程；故\n      被告以上述計價單證據，欲證明系爭工程所施作之建物於\n      結算當時有漏水等之瑕疵，舉證亦屬不足，而不足採信。\n （3）有關原告施作工程造成鄰損部分，被告之抗辯，為原告所\n      否認在卷；且原告所提出大築營造結案工程款項之書面記\n      錄，已記載有「鄰損、卡拉ＯＫ、水電修理」等之處理文\n      字，顯示結算當時，亦曾就鄰損部分為處理；另被告所抗\n      辯鄰損部分，被告迄今未提出賠償鄰損部分之證明，此部\n      分被告之抗辯，亦不能證明。\n （4）而有關被告抗辯系爭工程有關建物結構體之部分，有因混\n      凝土未搗實，造成建物多處產生孔洞，並有鋼筋外露之情\n      形，另放樣及模板精準度偏差，需打除重新修補之建築結\n      構偏差之瑕疵之事實，既未可信，則被告主張依據系爭契\n      約第41條之約定，原告施工時，若尺寸不合規定，按契約\n      單價比例扣減，並處以扣減額五倍之違約金，原告施工品\n      質未如契約所定，致模板偏差過大致被告額外施工支出22\n      3,450元，則原告除應將上開價金返還予被告外，並依約\n      應給付1,117,250元（223,450×5＝1,117,250）之違約金\n      部分，則屬無據。\n （5）被告抗辯原告施作系爭工程遲延之部分，原告並不否認完\n      工日期有所遲延，但主張係因被告與原承包商正良泰公司\n      遲未解除合約、被告遲遲無法交付土方證明予原告，且被\n      告有變更工程，故本件工程係因可歸責於被告之事由，未\n      能於合約所定之時間完成結構體，自不可歸責於原告等語\n      。查依據原告所提出大築營造結案工程款項之書面記錄，\n      並未就原告之工程施作遲延部分為處理，已顯示被告之工\n      地主任丙○○於結算當時，確實並未就原告施作遲延部分\n      為處理，因此，原告主張未因可歸責於原告之情，已非無\n      據，否則何以訴外人丙○○於結算當時曾就數項扣款項目\n      為扣款，但並未就遲延部分為計算；又被告亦不爭執系爭\n      工程之承攬施作過程，有原告所陳述與原承包商正良泰公\n      司之爭執及土方問題之處理之情（見本院99年3月23日準\n      備程序筆錄）；因此，原告主張非可歸責於原告等語，應\n      可採信。而遲延事由既非可歸責於原告，且結算當時未做\n      處理，顯見兩造就系爭工程之完成期限，於工程進行中應\n      有完工日期展延之合意存在，因此，原告未依期限完工，\n      自不應認為仍有遲延；故被告此部分之抗辯，亦屬無據。\n （6）綜上所述，被告上述所抗辯系爭工程瑕疵及遲延部分，自\n      屬未能證明。\n（六）被告另抗辯原告於6個月期間並未確實負起監督施工之管\n      理責任，是原告就被告所給付之管理費289,317元，應扣\n      除未實地監工管理之日數，即返還157,809元（289,317\n      ×6/11＝157,809）等語。然被告之此部分抗辯，已為原\n      告所否認在卷；且本院審酌兩造所簽訂之系爭工程契約就\n      管理費部分並無明文，僅在工程項目表為約定，而其項目\n      名稱為工程利潤及管理費，其計算方式，係以原告所能請\n      求之工程款百分之5計算，而該原告所能請求之工程款，\n      係指扣除原告應負之瑕疵、遲延等應扣款事項所計算之工\n      程款，顯見被告主張原告施作工程有所疏失，如有構成違\n      約事由，應於計算工程款時扣除，而非在計算管理費時為\n      扣除；故有關被告所抗辯原告未負監督施工責任，如有造\n      成系爭工程應扣款事由，即由該部分處理，而非於工程管\n      理費部分為扣除；另被告所提出日報表，未經原告人員簽\n      名之事實，雖為原告所不爭執，但兩造間並未約定日報表\n      未簽名即構成扣款事實，且此部分尚不足以證明原告施作\n      系爭工程已構成應扣款之事由；故被告抗辯應扣除管理費\n      ，亦無理由。\n（七）而依據原告所提出「大築營造結案工程款項」書面記錄，\n      原告所能向被告請求之金額，包括第十次前計價之保留款\n      876,135元、第十一次之工程款909,000元、零星工程款\n      919,245元，共計2,704,440元，扣除應扣款933,109元，\n      被告應給付原告1,771,331元，而原告所提出之上述結算\n      記錄，可資作為兩造計算被告應給付工程款之證據，已如\n      前述，故原告主張被告尚有工程款共計1,771,331元應給\n      付原告，自屬有據。\n（八）另依據系爭工程契約第44條之約定，原告就系爭工程應負\n      保固責任，而就結構體之部分，其保固期間為5年，雙方\n      契約經終止者，於點驗完成之次日起計算。另依據系爭工\n      程契約第45條第1項、第2項、第3項約定，保固保證金應\n      按結算總價千分之6計算。保固保證金，由工程款及保留\n      款、或乙方（原告）得領回之履約保證金優先抵充，或另\n      由乙方以同於繳納履約保證金方式繳交之。保固保證金未\n      經動用之部分，於保固期滿後且無瑕疵待改善情事時，返\n      還之。是依據兩造之約定，保固保證金應由承攬人以其能\n      領回之工程款優先抵充，且應待約定時間即保固期屆滿後\n      ，原告所承作之工程無瑕疵待改善情事，原告方能向被告\n      領回。而兩造並不爭執系爭契約結算總價為7,308,132元\n      ，則依據上述契約約定，原告應提供43,849元保固金（7,\n      30 8,132×6/1000＝43,849，元以下四捨五入）作為保固\n      保證金。故被告抗辯原告所得向被告請求之工程款應扣除\n      43,849元，依法有據，應予准許。\n（九）故原告得向被告請求之工程款1,771,331元，應扣除保固\n      保證金43,849元，原告所能請求被告給付之工程款應為1,\n      727,482元。從而，原告請求被告應給付原告1,727,482\n      元及自起訴狀繕本送達被告之翌日起（即97年9月25日）\n      至清償日止，按年息百分之5計算之遲延利息，為有理由\n      ，應予准許。逾此部分之請求，則無理由，應予駁回。\n五、原告陳明願供擔保以代釋明，聲請宣告假執行，經核原告勝\n    訴部分，合於法律規定，爰酌定相當之擔保金額宣告之；原\n    告其餘假執行之聲請，因訴之駁回而失所依據，應併予駁回\n    ；另被告敗訴部分，本院並依被告聲請，宣告被告得預供擔\n    保，免為假執行。\n六、本件判決基礎已臻明確，兩造其餘攻擊防禦方法及舉證，於\n    判決結果無影響，毋庸一一論列，附此敘明。\n七、結論：本件原告之訴部分有理由，部分無理由，依民事訴訟\n    法第79條，判決如主文。\n中    華    民    國    99    年    5     月    12    日\n                 民事第五庭    審判長法  官  薛中興\n                                     法  官  陳靜茹\n                                     法  官  陳杰正\n以上正本係照原本作成\n如對本判決上訴，須於判決送達後20日內向本院提出上訴狀\n中    華    民    國    99    年    5     月    12    日\n                                     書記官  王怡屏",
  "structure": {
    "main": "被告應給付原告新台幣壹佰柒拾貳萬柒仟肆佰捌拾貳元及自民國\n九十七年九月二十五日起至清償日止，按年息百分之五計算之利\n息。\n原告其餘之訴駁回。\n訴訟費用由被告負擔百分之九十九，其餘由原告負擔。\n本判決第一項於原告以新台幣伍拾柒萬伍仟捌佰貳拾柒元供擔保\n後，得為假執行，但被告如於假執行實施前，以新台幣壹佰柒拾\n貳萬柒仟肆佰捌拾貳元為原告預供擔保後，得免為假執行。\n原告其餘假執行之聲請駁回。",
    "fact": "壹、程序部分：\n一、按當事人得以合意定第一審管轄法院。但以關於由一定法律\n    關係而生之訴訟為限。前項合意，應以文書證之。民事訴訟\n    法第24條定有明文。依據兩造所不爭執之工程契約第64條第\n    2項約定：「因本契約之履行所引起之爭端，雙方之任何一\n    方，如提起民事訴訟，以中華民國臺灣臺北地方法院為第一\n    審管轄法院」，是兩造就系爭工程合約履行之紛爭，既已書\n    面合意由本院管轄，原告起訴請求系爭工程之工程款，本院\n    自有管轄權，合先敘明。\n二、又按訴狀送達後，原告不得將原訴變更或追加他訴，但擴張\n    或減縮應受判決事項之聲明者，不在此限。民事訴訟法第25\n    5條第1項第3款定有明文。查原告起訴時訴之聲明為請求被\n    告應給付原告新臺幣（下同）1,771,331元，並自民國96年\n    12月3日起至清償日止，按年息5％計算之利息，嗣於本院99\n    年4月28日言詞辯論期日具狀變更聲明為被告應給付原告1,7\n    71,331元及自起訴狀送達之翌日起至清償日止，按年息5％\n    計算之利息；原告就訴之聲明變更部分，核屬減縮應受判決\n    事項之聲明，揆諸前開說明，尚無不合，應予准許。\n貳、實體部分：\n一、原告起訴主張：\n（一）原告與被告於95年8月14日簽訂工程契約（下稱系爭契約\n      ），雙方合意就坐落臺北市○○區○○段4小段215地號、\n      216地號2筆土地上（門牌號碼臺北市○○區○○路1段166\n      巷44號，以下稱系爭建築物），興建地上七層地下一層之\n      住宅大樓一棟，以原告為該住宅大樓興建工程之承造人；\n      惟承造期間被告因個人好惡，恣意要求原告需依其指示更\n      改施工及建築方式，不僅延宕工程進度徒增原告工程的施\n      工成本，又與建築法規相左，原告雖婉言規勸，被告仍一\n      意孤行，若原告據理力爭，被告即以解約要脅；另原告請\n      求撥發每屆各期工程結算款項時，被告則藉故拖延、苛扣\n      ，原告為維持營運及商業信用，不得已付息借款，購料、\n      支付包商請款，以及支付薪資，經多次促請原告依合約規\n      定協助結算以及撥發每期工程款，以利工程之進行，惟被\n      告仍藉詞拖延；詎料，被告逕於96年7月8日以北投實踐郵\n      局（臺北139支局）第2259號存證信函通知原告：「本工\n      程結構部分已完成，本人甲○○及陽信信託銀行無意與貴\n      公司再續合約，即日起與貴公司終止合約關係，並請貴公\n      司立即派員結算工程之工程款項，另有必要履行之未完成\n      部分之合約工程，請在一星期內完成，如在期限內未完成\n      的工作，本人即將代為處理，延生的費用則由貴公司保留\n      款中扣除。」原告經多次請被告考量該大樓興建工程已近\n      竣工，如雙方終止合約，工期又將延宕，雙方均將受有嚴\n      重損失，惟被告仍堅持解除合約，原告只得依被告之指示\n      提送結算資料辦理結案事宜；原告與被告所委任之現場工\n      地主任即訴外人丙○○於96年10月3日完成彙算結案之事\n      宜，經雙方結算後同意：原告得請求被告撥發工程款項\n      2,704,440元，但原告就本工程需扣減933,109元款項，兩\n      相抵銷，被告應再給付原告1,771,331元；被告並據此交\n      付發票日為96年12月3日，票面金額為909,000元，發票人\n      為曜先營造有限公司，支票號碼為EA0000000號之支票1紙\n      ；餘款則約定於96年11月份給付；然事後被告避不見面，\n      而上開發票日為96年12月3日之支票屆期提示亦遭退票，\n      雖經原告多次請求被告給付前述款項，被告均置之不理，\n      爰依兩造工程契約第48條之承攬關係及兩造96年10月3日\n      結算約定，提起本件訴訟。\n（二）對於被告抗辯之陳述：\n （1）被告於96年8月7日所寄發之上述存證信函通知原告，就系\n      爭工程與被告之工地主任丙○○為結算，故丙○○於系爭\n      工程之結算部分內均在被告授權範圍內，自不需再經被告\n      同意；況被告於97年11月25日之民事答辯狀第1頁表示：\n      「被告與原告結算工程款項並簽立結案工程款項單」，是\n      被告業已承認該結算；依上，該結算對被告已生效力；且\n      該次結算除對原告得請領之工程款為討論外，並有再就系\n      爭工程建物結構體、地下室、鄰損、保固金等各項爭執併\n      予討論，而由兩造互相讓步達成合意；上情由起訴狀附證\n      三大築營造結案工程款項，內容確有記載前開項目自明；\n      兩造間所為結算性質，為就終止承攬契約後之權利義務互\n      相讓步達成合意，具有和解之效力。兩造應受結算內容之\n      拘束。\n （2）被告所指建築結構偏差造成之敲除填補等之瑕疵，業經被\n      告扣款，有兩造結算之書面即大築營造結案工程款項影本\n      第2頁第2點業已載明。至被告之其餘主張，原告否認之。\n      是被告之主張並不可採。\n （3）地下室部分業經被告扣款，有大築營造結案工程款項影本\n      第2頁第4點業已載明。至其餘部分屬裝修工程，並非原告\n      所承包之範圍。再者，被告所提支出費用之96年11月7日\n      之估價單，係裝修工程部分之防水處理，與原告無關。\n （4）鄰損部分，被告之主張，原告否認之，原告所提出裂縫照\n      片，原告否認真正；卡拉OK部分業經被告修理完畢，且經\n      結算扣款；至於致遠一路部分，當初有與屋主張洪林協議\n      ，幫忙其作門口地坪，業已施作完畢，原告所花費用共4\n      萬餘元，被告同意補貼原告1萬元，有大築營造結案工程\n      款項影本第1頁b可稽。被告之主張並不可採。\n （5）工程管理費部分，原告均有派人管理，已盡監督管理責任\n      ，被告之主張，並不可採。況被告所稱之管理費之金額係\n      含利潤，益足證被告之主張並不可採。被告主張原告在施\n      工期間未盡監督管理責任而應比例退還管理費157,809元\n      予被告，原告否認之。又所謂管理費係因被告之工地交由\n      原告進場管理維護之費用，亦即就工地內工程、材料、人\n      員等之管理維護、設立明顯標示等費用，工地內若有材料\n      遺失、人員損傷等風險均由原告負擔，亦即雙方契約第23\n      條約定施工管理之費用，而原告就該工程確有管理維護，\n      已盡監督管理責任，被告之主張，並不可採。況雙方並未\n      約定原告需派工地主任日夜駐守，是被告之抗辯主張並無\n      理由。\n （6）保固金部分，雙方結算時，已約定無保固金。\n （7）原告施工並無窗框、門框等尺寸不合之情形，就窗框等部\n      分，原告之施工方式為請吊車將窗戶吊起，自結構體外面\n      往內裝設，尺寸並無不合；就門框部分，因於結構體完成\n      ，後續尚有裝潢工程，故需預留推車可通行之寬度，而預\n      留部分之修補費用，因請款係已施作面積計算，故被告於\n      原告之前請款時已預先扣除，被告之主張，亦不可採。\n      被告雖提出估價單為證，但查兩造就系爭工程之施工位置\n      為臺北市○○路○段166巷44號，若欲變更上開門牌號碼，\n      需待全部工程完工後，始能請領新的門牌號碼，而被告所\n      提估價單，其上所載施工位置為臺北市○○路○段166巷46\n      號，為系爭工程完工後新領之門牌號碼，足見該估價單已\n      明顯不實。又依系爭建物之建物謄本之記載，系爭建物於\n      97年7月11日建築完成，而被告所提之估價單竟有98年3月\n      30日估價單，益見該估價單已明顯不實。再者，如依被告\n      所提估價單所示，則幾乎每一層樓均有瑕疵，而估價單所\n      列瑕疵又係明顯可見，則被告之工地主任丙○○結算時焉\n      有不發現之理，益足證該估價單顯有不實。另外，被告對\n      於98年9月29日準備程序筆錄所載：「（受命法官）第31\n      頁第2點部分有（5％已扣）的部分，是何意思？（原告訴\n      訟代理人）這部分是指因為灌漿上面有瑕疵已經被被告扣\n      除5％的價金，所以新台幣909060元已經扣除後的金額。\n      」並不爭執，是就灌漿上面有瑕疵已經被告扣除，現被告\n      再為主張，並不可採。再退言之，本件係因被告中途終止\n      契約，是應依兩造所訂立工程合約第48條最後一項約定：\n      「甲方（指被告）因業務之考量，得終止或解除部分或全\n      部契約，乙方（指原告）於接獲甲方通知後，應立即停工\n      並負責遣散工人，清理現場，其已完成之工程及已進場之\n      材料機具設備，由甲方依契約或準用前項第二款工程開工\n      後無法繼續施工之約定，核實給付。…所有相關憑證單據\n      及工人機具遣散費用，甲方無條件支付。」處理；而原告\n      既應立即停工，自無兩造合約第41條減價收受之適用，其\n      理至明，被告之主張，顯不可採。\n （8）原告就系爭工程之建物結構體完工並無遲延達83日之事實\n      ；本件係因被告與原承包商正良泰公司遲未解除合約、被\n      告遲遲無法交付土方證明予原告，且被告有變更工程，故\n      本件工程係因可歸責於被告之事由，未能於合約所定之時\n      間完成結構體，自不可歸責於原告。又依民法第504條規\n      定，工作遲延後，定作人受領工作時，不為保留者，承攬\n      人對於遲延之結果不負責任。本件縱法院仍認原告有遲延\n      ，然因被告於結算受領工作時，未為保留，則依上規定，\n      原告對於遲延之結果亦不負責任。\n（三）聲明：（1）被告應給付原告1,771,331元及自起送狀送達\n      翌日起至清償日止按年息百分之5計算之延滯利息。（2）\n      訴訟費用由被告負擔。（3）願供擔保請准予宣告假執行\n      。\n二、被告則抗辯：\n（一）原告所提出之被告之工地主任丙○○與原告於96年10月3\n      日所為之結算約定，僅係兩造就系爭工程加減帳所為之估\n      算，並非最終結果，須經兩造確認無誤後，始得作為最終\n      結論，此亦可由證人丙○○到庭之證詞益證此點。且系爭\n      工程諸多瑕疵係於上開結算書簽立後，始陸續發現，被告\n      才始終未於結算書上簽名確認，該結算書之效力不應拘束\n      被告。雖有被告工地主任丙○○簽名其上，然丙○○與原\n      告簽訂結算約定時，亦未有附上被告委任狀，該結算約定\n      不可拘束被告至明。\n（二）被告雖與原告間有訂立系爭工程契約並不爭執，然原告因\n      有下列施工不良之情形，造成其所建築之該棟大樓有重大\n      瑕疵，致被告有損失，原告所發生之瑕疵如下：\n （1）系爭建物結構體部分，因混凝土未搗實，造成建物多處產\n      生孔洞，並有鋼筋外露、漏水之情形，另放樣及模板精準\n      度偏差，需打除重新修補，另屋突三水箱漏水亦需修補，\n      至於修補金額，需鑑定後方可確定。\n （2）地下室蓄水池、污水坑及電梯機漏水至多處積水及產生水\n      漬痕跡，此部分係因原告施工不善所產生之瑕疵，理應由\n      原告負修繕義務，惟原告置之不理，被告已委由廣修企業\n      有限公司修補並支出140,394元工程修補金，此部份支出\n      原告應予以返還。\n （3）因本件建物施工不當，致隔鄰致遠一路二段112巷20號之\n      一張家（屋主為張洪林、林麗珠）房舍有磁磚、天花板龜\n      裂及漏水、地面隆起，建物變形龜裂達20公分，此部分因\n      原告施工不當所致，應由原告負責修繕，惟尚未修繕完畢\n      ，且其金額須經鑑定後始得確定。\n （4）另依據原告施工期間之施工日報表所示，原告所設之工地\n      主任自95年7月25日至96年6月28日共11個月施工期間，僅\n      有5個月有於日報表上簽名，顯見原告於6個月期間並未確\n      實負起監督施工之管理責任，是原告就被告所給付之管理\n      費289,317元，應扣除未實地監工管理之日數，即返還157\n      ,809元（289,317×6/11＝157,809）。\n （5）又依系爭工程合約第44條規定，縱然兩造解除系爭契約，\n      乙方（即原告）就系爭工程提供裝修、機電、防水（屋頂\n      防水除外）、壁癌、交通設施、自來水工程…等保固工作\n      且按系爭契約第45條約定，保固金應按總價千分之6計算\n      ，本件總工程款為7,308,132元，故原告尚應提供43,849\n      元保固金（7,308,132×6/1000＝43,849）予被告。\n （6）再依系爭契約第41條之約定，原告施工時，若尺寸不合規\n      定，按契約單價比例扣減，並處以扣減額五倍之違約金。\n      今原告施工品質為如契約所定，致模板偏差過大致被告額\n      外施工支出223,450元，則原告除應將上開價金返還予被\n      告外，並依約應給付1,117,250元（223,450×5＝1,117,2\n      50）。\n （7）末依系爭工程契約之附件即工程進度表之約定，系爭建物\n      結構體應於96年4月5日完工，原告卻遲至96年6月28日結\n      構體才完成，共遲延83日，依系爭契約第27條、46條之約\n      定，原告應對被告負遲延責任，計606,575元（7308,132\n      ×83/1000＝606,575）\n （8）綜上所述，原告需給付被告2,065,877元（計算式：140,3\n      94＋157,809＋43,849＋1,117,250＋606,575＝2,065,877\n      ），以及原告積欠被告上述鋼筋款項、施工造成鄰損、防\n      水工程等扣款1,008,109元（其中鋼筋670,000元、結構偏\n      差126,800元、鄰損5,000元、止漏38,409元、防水37,900\n      元、臨時用電50,000元、模板借款50,000、補空洞30,000\n      元）。系爭工程被告原應給付原告8,563,313元，已給付7\n      ,308,132元，尚欠1,255,181元。然因原告尚須給付被告\n      3,073,986（2,065,877＋1,008,109＝3,043,986），兩相\n      抵銷，原告尚應給付被告1,818,805元，是被告已不具給\n      付義務。\n（三）並聲明：（1）原告之訴駁回。（2）訴訟費用由原告負擔\n      。（3）如受不利判決，願供擔保請准免為假執行。\n三、兩造不爭執事實：\n（1）兩造於95年8月14日簽訂工程契約，雙方合意就臺北市○○\n     區○○段4小段215地號、216地號2筆土地上（門牌號碼臺\n     北市○○區○○路1段166巷44號），興建地上七層地下一\n     層之住宅大樓一棟，以原告為該住宅大樓興建工程之承造\n     人，被告為系爭契約之定作人。\n（2）被告於96年7月18日以存證信函通知原告自即日起終止兩造\n     間工程契約關係，並請求原告派員結算工程款，及就有必\n     要履行之未完工工程部分在一週內完成。\n（3）被告之工地主任丙○○與原告於96年10月3日完成結算，結\n     算結果為：系爭工程原告實際請領之工程款為7,308,132元\n     ，原告得請求被告給付之承攬報酬為2,704,440元,，但原\n     告就系爭工程部分應扣減款項為933,109元，故核計後被告\n     尚應給付原告承攬報酬1,771,331元。\n（4）被告交付原告1紙發票人為曜先營造有限公司、支票號碼為\n     EA0000000、票面金額909,000元、受款人為原告、發票日\n     為96年12月3日之支票1紙以為報酬之給付，經原告於發票\n     日提示後遭退票，未獲付款。\n四、得心證之理由：\n（一）上述不爭執事實，有兩造所不爭執之系爭工程契約書、大\n      築營造結案工程款項影本、支票及退票理由單、存證信函\n      在卷可證，自可信為真實。\n（二）被告於96年7月18日以存證信函通知原告終止兩造間工程\n      契約關係，依據兩造所訂系爭工程合約第48條最後一項約\n      定：「甲方（指被告）因業務之考量，得終止或解除部分\n      或全部契約，乙方（指原告）於接獲甲方通知後，應立即\n      停工並負責遣散工人，清理現場，其已完成之工程及已進\n      場之材料機具設備，由甲方依契約或準用前項第二款工程\n      開工後無法繼續施工之約定，核實給付。但不包括所失利\n      益，所有相關憑證單據及工人機具遣散費用，甲方無條件\n      支付。」及系爭工程合約第48條第1項第二款第2目約定：\n      「已施工之工程，依本契約約定估驗計價」內容，被告於\n      終止系爭工程契約後，就原告已施工之工程，應負給付該\n      部分工程款之義務。\n（三）而原告主張兩造間已就系爭契約終止後之工程款曾為結算\n      ，且該結算之效力應及於被告，並據其提出大築營造結案\n      工程款項書面記錄在卷為證。被告雖不否認上述大築營造\n      結案工程款項書面係由被告之工地主任丙○○與原告所為\n      結算，但否認上述結算之效力及於被告，不生拘束被告之\n      效力，並為前揭抗辯。而查，上述原告所提出之大築營造\n      結案工程款項書面，雖有被告之工地主任丙○○為簽名，\n      但並未有被告之簽名，且被告雖曾於96年8月7日寄發存證\n      信函予被告，通知被告應於96年8月15日前會同丙○○丈\n      量工程計價款項數量，有原告所提出之存證信函1紙在卷\n      可證，但該存證信函內容，並無被告授權丙○○得以被告\n      之代理人名義全權處理與原告間之終止契約結算工程款事\n      宜，此有原告所提出上述存證信函在卷可據；又證人丙○\n      ○曾於本院準備程序中到庭證述：「被告有沒有說去原告\n      結算，被告即會依結算結果付款，不記得了，但我離開前\n      確實有做結算；當時因我要離職，原告叫我將該算的算一\n      算；因為被告找來新來的監工不知道狀況，所以理所當然\n      我經手的部分就要算清楚才走，我是就我經手的部分，我\n      認為該付多少錢，我就與原告算清楚；我跟被告報告後，\n      被告還會親自去看，確定後才會付款」等語（見本院98\n      年8月14日準備程序筆錄）；依據證人丙○○之上述證詞\n      可知，被告係因證人即將離職，叫證人去核算工程款，以\n      備新來之工地主任進行交接瞭解，被告當時並未授權證人\n      丙○○得全權與原告結算工程款之事實，可資確認；另外\n      ，被告雖曾交付上述支票1紙以為支付第十一次工程款909\n      ,000元，但各期之工程款係按施工進度給付之工程款，是\n      約定多少就給多少之事實，業據證人丙○○於上述準備程\n      序證述在卷，況且原告亦不否認系爭工程係按期給付工程\n      款之情，顯見系爭工程之各期工程款係依據施工進度施工\n      ，與結算無關，故被告所抗辯上述第十一期工程款本來就\n      是要由被告給付，與結算無關等語應屬事實，自不因被告\n      已交付支票給付第十一期工程款，而謂被告曾授權證人丙\n      ○○全權負責工程結算且被告已經承認結算之效力。故原\n      告主張兩造已經就系爭工程完成結算，兩造所為結算即大\n      築營造結案工程款項書面紀錄對被告亦生效力等語，即尚\n      無可據。\n（四）而依據兩造所訂系爭工程合約第48條第2項、第1項第二款\n      第2目之約定，被告應就終止契約時原告已施作之工程核\n      實給付工程，已如上述；而原告所請求之工程款給付標準\n      ，係依據原告所提出與被告之工地主任丙○○所結算之大\n      築營造結案工程款項書面為依據。本院審酌被告並不否認\n      上述書面係由被告之工地主任丙○○於被告終止系爭工程\n      合約後與原告所為之結算，且上述結算書面內容明確載明\n      應給付之工程款、扣款款項、工程施作內容之日期、工數\n      、工作內容、金額，甚且包括結算書，均有載明工程項目\n      、單位、數量、單價、總價、備註等，顯見被告之工地主\n      任丙○○於被告終止系爭工程合約後，確實就系爭工程曾\n      進行結算，而進行結算人丙○○於結算當時既任職被告之\n      工地主任，主管系爭工程現場之施工監督，當就系爭工程\n      之施作內容有相當之瞭解，故其與原告所進行之結算，就\n      工程施作項目、金額及應扣款金額等，應最能反應結算當\n      時原告就系爭工程之實際施作內容、數量、工程款及應扣\n      款事實，故原告提出大築營造結案工程款項之結算結果，\n      主張上述結算書面所載為原告於結算當時已施作工程內容\n      ，自可認為真實；另外，被告並未提出反證證明兩造於事\n      後曾另行結算，或上述結算，有何不符合事實之處。故原\n      告以上述大築營造結案工程款項之書面，主張被告應負上\n      述大築營造結案工程款項書面所載工程款之給付責任，自\n      屬有據。\n（五）至於被告上述所抗辯系爭工程施作有瑕疵及遲延，應進行\n      扣款部分，經查：\n （1）被告抗辯系爭工程有關建物結構體之部分，有因混凝土未\n      搗實，造成建物多處產生孔洞，並有鋼筋外露之情形，另\n      放樣及模板精準度偏差，需打除重新修補之建築結構偏差\n      之瑕疵，致被告支出223,450元修補之情，固據被告提出\n      現場照片、估價單在卷為證。然被告之上述抗辯，為原告\n      所否認在卷，且依據兩造所不爭執之卷附大築營造結案工\n      程款項結算書面，已記載「因建築結構偏差造成之敲除或\n      填補之工資及材料」字樣內容，且有記載扣款之金額，顯\n      然於上述結算當時，被告之工地主任丙○○曾經就此部分\n      結構體偏差之扣款為結算處理；又檢視被告所提出之估價\n      單，不僅記載系爭工程之施工位置為臺北市○○路○段166\n      巷46號，與系爭工程所在之44號不符，且依系爭建物之建\n      物謄本之記載，系爭工程之建物係於97年7月11日建築完\n      成，然上述估價單中竟有1張之日期為98年3月30日，係在\n      上述建物建築完工之後，顯示估價單之真正，乃有可疑；\n      另外，依上述估價單內容，原告所施作工程之瑕疵甚多，\n      幾乎每一層樓均有瑕疵，且所列瑕疵又係明顯可見，何以\n      被告之工地主任丙○○結算時均未發現而未以處理，此與\n      常情不符；另外，系爭工程施作之建物已經完工，且已有\n      出賣他人之事實，為被告所不否認在卷，則如被告確實支\n      出上述修補費用，應有確實之支出明細、支出記錄，不應\n      僅有如估價性質之估價單為證；上述估價單實不足以為支\n      出瑕疵修補之依據；故被告以上述證據，證明系爭工程所\n      施作之建物於結算當時有結構體偏差之瑕疵，舉證尚屬不\n      足，而不足採信。\n （2）有關被告所抗辯地下室蓄水池、污水坑及電梯機漏水等多\n      處積水及產生水漬痕跡之瑕疵，致被告支出140,394元之\n      修補費用之情，固據被告提出照片、廣修企業有限公司之\n      計價單為證。然被告之上述抗辯，亦為原告所否認，且本\n      院檢視卷附大築營造結案工程款項之結算書面，已有電梯\n      及污水坑止漏灌漿之扣款紀錄，工作內容亦有堵漏、電梯\n      機坑及污水坑、B1牆等止漏灌漿、水箱漏水處敲除等工作\n      項目之記載，顯示結算當時，被告之工地主任丙○○亦就\n      此部分有所結算處理；又被告亦不爭執上述結算書面所載\n      （廣修帳單）38,409元之部分，就是被告所提出廣修企業\n      有限公司之計價單中之一部份（見本院98年12月22日準備\n      程序筆錄），可見結算當時確實就漏水部分有所處理。另\n      外，本院再審酌被告所提出之96年11月7日計價單，工作\n      之時間自96年10月4日至96年10月27日，係在96年10月3日\n      結算翌日起進行，如於96年10月4日真有進行上述單純漏\n      水修補之需要，何以96年10月3日結算記錄並未處理，況\n      且比對被告所提出96年9月28日、96年11月7日之計價單，\n      96年11月7日記價單所載之工作項目較多（如多出環氧樹\n      脂、陶瓷粉、石英砂等，與96年9月28日帳單僅止漏劑、\n      黃油嘴、止水針頭不同），又原告陳述上述估價單不是單\n      純防漏工程要用等語，被告則未舉證證明上述計價單所載\n      確係為原告所施作工程漏水部分之單純防漏施作工程；故\n      被告以上述計價單證據，欲證明系爭工程所施作之建物於\n      結算當時有漏水等之瑕疵，舉證亦屬不足，而不足採信。\n （3）有關原告施作工程造成鄰損部分，被告之抗辯，為原告所\n      否認在卷；且原告所提出大築營造結案工程款項之書面記\n      錄，已記載有「鄰損、卡拉ＯＫ、水電修理」等之處理文\n      字，顯示結算當時，亦曾就鄰損部分為處理；另被告所抗\n      辯鄰損部分，被告迄今未提出賠償鄰損部分之證明，此部\n      分被告之抗辯，亦不能證明。\n （4）而有關被告抗辯系爭工程有關建物結構體之部分，有因混\n      凝土未搗實，造成建物多處產生孔洞，並有鋼筋外露之情\n      形，另放樣及模板精準度偏差，需打除重新修補之建築結\n      構偏差之瑕疵之事實，既未可信，則被告主張依據系爭契\n      約第41條之約定，原告施工時，若尺寸不合規定，按契約\n      單價比例扣減，並處以扣減額五倍之違約金，原告施工品\n      質未如契約所定，致模板偏差過大致被告額外施工支出22\n      3,450元，則原告除應將上開價金返還予被告外，並依約\n      應給付1,117,250元（223,450×5＝1,117,250）之違約金\n      部分，則屬無據。\n （5）被告抗辯原告施作系爭工程遲延之部分，原告並不否認完\n      工日期有所遲延，但主張係因被告與原承包商正良泰公司\n      遲未解除合約、被告遲遲無法交付土方證明予原告，且被\n      告有變更工程，故本件工程係因可歸責於被告之事由，未\n      能於合約所定之時間完成結構體，自不可歸責於原告等語\n      。查依據原告所提出大築營造結案工程款項之書面記錄，\n      並未就原告之工程施作遲延部分為處理，已顯示被告之工\n      地主任丙○○於結算當時，確實並未就原告施作遲延部分\n      為處理，因此，原告主張未因可歸責於原告之情，已非無\n      據，否則何以訴外人丙○○於結算當時曾就數項扣款項目\n      為扣款，但並未就遲延部分為計算；又被告亦不爭執系爭\n      工程之承攬施作過程，有原告所陳述與原承包商正良泰公\n      司之爭執及土方問題之處理之情（見本院99年3月23日準\n      備程序筆錄）；因此，原告主張非可歸責於原告等語，應\n      可採信。而遲延事由既非可歸責於原告，且結算當時未做\n      處理，顯見兩造就系爭工程之完成期限，於工程進行中應\n      有完工日期展延之合意存在，因此，原告未依期限完工，\n      自不應認為仍有遲延；故被告此部分之抗辯，亦屬無據。\n （6）綜上所述，被告上述所抗辯系爭工程瑕疵及遲延部分，自\n      屬未能證明。\n（六）被告另抗辯原告於6個月期間並未確實負起監督施工之管\n      理責任，是原告就被告所給付之管理費289,317元，應扣\n      除未實地監工管理之日數，即返還157,809元（289,317\n      ×6/11＝157,809）等語。然被告之此部分抗辯，已為原\n      告所否認在卷；且本院審酌兩造所簽訂之系爭工程契約就\n      管理費部分並無明文，僅在工程項目表為約定，而其項目\n      名稱為工程利潤及管理費，其計算方式，係以原告所能請\n      求之工程款百分之5計算，而該原告所能請求之工程款，\n      係指扣除原告應負之瑕疵、遲延等應扣款事項所計算之工\n      程款，顯見被告主張原告施作工程有所疏失，如有構成違\n      約事由，應於計算工程款時扣除，而非在計算管理費時為\n      扣除；故有關被告所抗辯原告未負監督施工責任，如有造\n      成系爭工程應扣款事由，即由該部分處理，而非於工程管\n      理費部分為扣除；另被告所提出日報表，未經原告人員簽\n      名之事實，雖為原告所不爭執，但兩造間並未約定日報表\n      未簽名即構成扣款事實，且此部分尚不足以證明原告施作\n      系爭工程已構成應扣款之事由；故被告抗辯應扣除管理費\n      ，亦無理由。\n（七）而依據原告所提出「大築營造結案工程款項」書面記錄，\n      原告所能向被告請求之金額，包括第十次前計價之保留款\n      876,135元、第十一次之工程款909,000元、零星工程款\n      919,245元，共計2,704,440元，扣除應扣款933,109元，\n      被告應給付原告1,771,331元，而原告所提出之上述結算\n      記錄，可資作為兩造計算被告應給付工程款之證據，已如\n      前述，故原告主張被告尚有工程款共計1,771,331元應給\n      付原告，自屬有據。\n（八）另依據系爭工程契約第44條之約定，原告就系爭工程應負\n      保固責任，而就結構體之部分，其保固期間為5年，雙方\n      契約經終止者，於點驗完成之次日起計算。另依據系爭工\n      程契約第45條第1項、第2項、第3項約定，保固保證金應\n      按結算總價千分之6計算。保固保證金，由工程款及保留\n      款、或乙方（原告）得領回之履約保證金優先抵充，或另\n      由乙方以同於繳納履約保證金方式繳交之。保固保證金未\n      經動用之部分，於保固期滿後且無瑕疵待改善情事時，返\n      還之。是依據兩造之約定，保固保證金應由承攬人以其能\n      領回之工程款優先抵充，且應待約定時間即保固期屆滿後\n      ，原告所承作之工程無瑕疵待改善情事，原告方能向被告\n      領回。而兩造並不爭執系爭契約結算總價為7,308,132元\n      ，則依據上述契約約定，原告應提供43,849元保固金（7,\n      30 8,132×6/1000＝43,849，元以下四捨五入）作為保固\n      保證金。故被告抗辯原告所得向被告請求之工程款應扣除\n      43,849元，依法有據，應予准許。\n（九）故原告得向被告請求之工程款1,771,331元，應扣除保固\n      保證金43,849元，原告所能請求被告給付之工程款應為1,\n      727,482元。從而，原告請求被告應給付原告1,727,482\n      元及自起訴狀繕本送達被告之翌日起（即97年9月25日）\n      至清償日止，按年息百分之5計算之遲延利息，為有理由\n      ，應予准許。逾此部分之請求，則無理由，應予駁回。\n五、原告陳明願供擔保以代釋明，聲請宣告假執行，經核原告勝\n    訴部分，合於法律規定，爰酌定相當之擔保金額宣告之；原\n    告其餘假執行之聲請，因訴之駁回而失所依據，應併予駁回\n    ；另被告敗訴部分，本院並依被告聲請，宣告被告得預供擔\n    保，免為假執行。\n六、本件判決基礎已臻明確，兩造其餘攻擊防禦方法及舉證，於\n    判決結果無影響，毋庸一一論列，附此敘明。\n七、結論：本件原告之訴部分有理由，部分無理由，依民事訴訟\n    法第79條，判決如主文。",
    "reason": "壹、程序部分：\n一、按當事人得以合意定第一審管轄法院。但以關於由一定法律\n    關係而生之訴訟為限。前項合意，應以文書證之。民事訴訟\n    法第24條定有明文。依據兩造所不爭執之工程契約第64條第\n    2項約定：「因本契約之履行所引起之爭端，雙方之任何一\n    方，如提起民事訴訟，以中華民國臺灣臺北地方法院為第一\n    審管轄法院」，是兩造就系爭工程合約履行之紛爭，既已書\n    面合意由本院管轄，原告起訴請求系爭工程之工程款，本院\n    自有管轄權，合先敘明。\n二、又按訴狀送達後，原告不得將原訴變更或追加他訴，但擴張\n    或減縮應受判決事項之聲明者，不在此限。民事訴訟法第25\n    5條第1項第3款定有明文。查原告起訴時訴之聲明為請求被\n    告應給付原告新臺幣（下同）1,771,331元，並自民國96年\n    12月3日起至清償日止，按年息5％計算之利息，嗣於本院99\n    年4月28日言詞辯論期日具狀變更聲明為被告應給付原告1,7\n    71,331元及自起訴狀送達之翌日起至清償日止，按年息5％\n    計算之利息；原告就訴之聲明變更部分，核屬減縮應受判決\n    事項之聲明，揆諸前開說明，尚無不合，應予准許。\n貳、實體部分：\n一、原告起訴主張：\n（一）原告與被告於95年8月14日簽訂工程契約（下稱系爭契約\n      ），雙方合意就坐落臺北市○○區○○段4小段215地號、\n      216地號2筆土地上（門牌號碼臺北市○○區○○路1段166\n      巷44號，以下稱系爭建築物），興建地上七層地下一層之\n      住宅大樓一棟，以原告為該住宅大樓興建工程之承造人；\n      惟承造期間被告因個人好惡，恣意要求原告需依其指示更\n      改施工及建築方式，不僅延宕工程進度徒增原告工程的施\n      工成本，又與建築法規相左，原告雖婉言規勸，被告仍一\n      意孤行，若原告據理力爭，被告即以解約要脅；另原告請\n      求撥發每屆各期工程結算款項時，被告則藉故拖延、苛扣\n      ，原告為維持營運及商業信用，不得已付息借款，購料、\n      支付包商請款，以及支付薪資，經多次促請原告依合約規\n      定協助結算以及撥發每期工程款，以利工程之進行，惟被\n      告仍藉詞拖延；詎料，被告逕於96年7月8日以北投實踐郵\n      局（臺北139支局）第2259號存證信函通知原告：「本工\n      程結構部分已完成，本人甲○○及陽信信託銀行無意與貴\n      公司再續合約，即日起與貴公司終止合約關係，並請貴公\n      司立即派員結算工程之工程款項，另有必要履行之未完成\n      部分之合約工程，請在一星期內完成，如在期限內未完成\n      的工作，本人即將代為處理，延生的費用則由貴公司保留\n      款中扣除。」原告經多次請被告考量該大樓興建工程已近\n      竣工，如雙方終止合約，工期又將延宕，雙方均將受有嚴\n      重損失，惟被告仍堅持解除合約，原告只得依被告之指示\n      提送結算資料辦理結案事宜；原告與被告所委任之現場工\n      地主任即訴外人丙○○於96年10月3日完成彙算結案之事\n      宜，經雙方結算後同意：原告得請求被告撥發工程款項\n      2,704,440元，但原告就本工程需扣減933,109元款項，兩\n      相抵銷，被告應再給付原告1,771,331元；被告並據此交\n      付發票日為96年12月3日，票面金額為909,000元，發票人\n      為曜先營造有限公司，支票號碼為EA0000000號之支票1紙\n      ；餘款則約定於96年11月份給付；然事後被告避不見面，\n      而上開發票日為96年12月3日之支票屆期提示亦遭退票，\n      雖經原告多次請求被告給付前述款項，被告均置之不理，\n      爰依兩造工程契約第48條之承攬關係及兩造96年10月3日\n      結算約定，提起本件訴訟。\n（二）對於被告抗辯之陳述：\n （1）被告於96年8月7日所寄發之上述存證信函通知原告，就系\n      爭工程與被告之工地主任丙○○為結算，故丙○○於系爭\n      工程之結算部分內均在被告授權範圍內，自不需再經被告\n      同意；況被告於97年11月25日之民事答辯狀第1頁表示：\n      「被告與原告結算工程款項並簽立結案工程款項單」，是\n      被告業已承認該結算；依上，該結算對被告已生效力；且\n      該次結算除對原告得請領之工程款為討論外，並有再就系\n      爭工程建物結構體、地下室、鄰損、保固金等各項爭執併\n      予討論，而由兩造互相讓步達成合意；上情由起訴狀附證\n      三大築營造結案工程款項，內容確有記載前開項目自明；\n      兩造間所為結算性質，為就終止承攬契約後之權利義務互\n      相讓步達成合意，具有和解之效力。兩造應受結算內容之\n      拘束。\n （2）被告所指建築結構偏差造成之敲除填補等之瑕疵，業經被\n      告扣款，有兩造結算之書面即大築營造結案工程款項影本\n      第2頁第2點業已載明。至被告之其餘主張，原告否認之。\n      是被告之主張並不可採。\n （3）地下室部分業經被告扣款，有大築營造結案工程款項影本\n      第2頁第4點業已載明。至其餘部分屬裝修工程，並非原告\n      所承包之範圍。再者，被告所提支出費用之96年11月7日\n      之估價單，係裝修工程部分之防水處理，與原告無關。\n （4）鄰損部分，被告之主張，原告否認之，原告所提出裂縫照\n      片，原告否認真正；卡拉OK部分業經被告修理完畢，且經\n      結算扣款；至於致遠一路部分，當初有與屋主張洪林協議\n      ，幫忙其作門口地坪，業已施作完畢，原告所花費用共4\n      萬餘元，被告同意補貼原告1萬元，有大築營造結案工程\n      款項影本第1頁b可稽。被告之主張並不可採。\n （5）工程管理費部分，原告均有派人管理，已盡監督管理責任\n      ，被告之主張，並不可採。況被告所稱之管理費之金額係\n      含利潤，益足證被告之主張並不可採。被告主張原告在施\n      工期間未盡監督管理責任而應比例退還管理費157,809元\n      予被告，原告否認之。又所謂管理費係因被告之工地交由\n      原告進場管理維護之費用，亦即就工地內工程、材料、人\n      員等之管理維護、設立明顯標示等費用，工地內若有材料\n      遺失、人員損傷等風險均由原告負擔，亦即雙方契約第23\n      條約定施工管理之費用，而原告就該工程確有管理維護，\n      已盡監督管理責任，被告之主張，並不可採。況雙方並未\n      約定原告需派工地主任日夜駐守，是被告之抗辯主張並無\n      理由。\n （6）保固金部分，雙方結算時，已約定無保固金。\n （7）原告施工並無窗框、門框等尺寸不合之情形，就窗框等部\n      分，原告之施工方式為請吊車將窗戶吊起，自結構體外面\n      往內裝設，尺寸並無不合；就門框部分，因於結構體完成\n      ，後續尚有裝潢工程，故需預留推車可通行之寬度，而預\n      留部分之修補費用，因請款係已施作面積計算，故被告於\n      原告之前請款時已預先扣除，被告之主張，亦不可採。\n      被告雖提出估價單為證，但查兩造就系爭工程之施工位置\n      為臺北市○○路○段166巷44號，若欲變更上開門牌號碼，\n      需待全部工程完工後，始能請領新的門牌號碼，而被告所\n      提估價單，其上所載施工位置為臺北市○○路○段166巷46\n      號，為系爭工程完工後新領之門牌號碼，足見該估價單已\n      明顯不實。又依系爭建物之建物謄本之記載，系爭建物於\n      97年7月11日建築完成，而被告所提之估價單竟有98年3月\n      30日估價單，益見該估價單已明顯不實。再者，如依被告\n      所提估價單所示，則幾乎每一層樓均有瑕疵，而估價單所\n      列瑕疵又係明顯可見，則被告之工地主任丙○○結算時焉\n      有不發現之理，益足證該估價單顯有不實。另外，被告對\n      於98年9月29日準備程序筆錄所載：「（受命法官）第31\n      頁第2點部分有（5％已扣）的部分，是何意思？（原告訴\n      訟代理人）這部分是指因為灌漿上面有瑕疵已經被被告扣\n      除5％的價金，所以新台幣909060元已經扣除後的金額。\n      」並不爭執，是就灌漿上面有瑕疵已經被告扣除，現被告\n      再為主張，並不可採。再退言之，本件係因被告中途終止\n      契約，是應依兩造所訂立工程合約第48條最後一項約定：\n      「甲方（指被告）因業務之考量，得終止或解除部分或全\n      部契約，乙方（指原告）於接獲甲方通知後，應立即停工\n      並負責遣散工人，清理現場，其已完成之工程及已進場之\n      材料機具設備，由甲方依契約或準用前項第二款工程開工\n      後無法繼續施工之約定，核實給付。…所有相關憑證單據\n      及工人機具遣散費用，甲方無條件支付。」處理；而原告\n      既應立即停工，自無兩造合約第41條減價收受之適用，其\n      理至明，被告之主張，顯不可採。\n （8）原告就系爭工程之建物結構體完工並無遲延達83日之事實\n      ；本件係因被告與原承包商正良泰公司遲未解除合約、被\n      告遲遲無法交付土方證明予原告，且被告有變更工程，故\n      本件工程係因可歸責於被告之事由，未能於合約所定之時\n      間完成結構體，自不可歸責於原告。又依民法第504條規\n      定，工作遲延後，定作人受領工作時，不為保留者，承攬\n      人對於遲延之結果不負責任。本件縱法院仍認原告有遲延\n      ，然因被告於結算受領工作時，未為保留，則依上規定，\n      原告對於遲延之結果亦不負責任。\n（三）聲明：（1）被告應給付原告1,771,331元及自起送狀送達\n      翌日起至清償日止按年息百分之5計算之延滯利息。（2）\n      訴訟費用由被告負擔。（3）願供擔保請准予宣告假執行\n      。\n二、被告則抗辯：\n（一）原告所提出之被告之工地主任丙○○與原告於96年10月3\n      日所為之結算約定，僅係兩造就系爭工程加減帳所為之估\n      算，並非最終結果，須經兩造確認無誤後，始得作為最終\n      結論，此亦可由證人丙○○到庭之證詞益證此點。且系爭\n      工程諸多瑕疵係於上開結算書簽立後，始陸續發現，被告\n      才始終未於結算書上簽名確認，該結算書之效力不應拘束\n      被告。雖有被告工地主任丙○○簽名其上，然丙○○與原\n      告簽訂結算約定時，亦未有附上被告委任狀，該結算約定\n      不可拘束被告至明。\n（二）被告雖與原告間有訂立系爭工程契約並不爭執，然原告因\n      有下列施工不良之情形，造成其所建築之該棟大樓有重大\n      瑕疵，致被告有損失，原告所發生之瑕疵如下：\n （1）系爭建物結構體部分，因混凝土未搗實，造成建物多處產\n      生孔洞，並有鋼筋外露、漏水之情形，另放樣及模板精準\n      度偏差，需打除重新修補，另屋突三水箱漏水亦需修補，\n      至於修補金額，需鑑定後方可確定。\n （2）地下室蓄水池、污水坑及電梯機漏水至多處積水及產生水\n      漬痕跡，此部分係因原告施工不善所產生之瑕疵，理應由\n      原告負修繕義務，惟原告置之不理，被告已委由廣修企業\n      有限公司修補並支出140,394元工程修補金，此部份支出\n      原告應予以返還。\n （3）因本件建物施工不當，致隔鄰致遠一路二段112巷20號之\n      一張家（屋主為張洪林、林麗珠）房舍有磁磚、天花板龜\n      裂及漏水、地面隆起，建物變形龜裂達20公分，此部分因\n      原告施工不當所致，應由原告負責修繕，惟尚未修繕完畢\n      ，且其金額須經鑑定後始得確定。\n （4）另依據原告施工期間之施工日報表所示，原告所設之工地\n      主任自95年7月25日至96年6月28日共11個月施工期間，僅\n      有5個月有於日報表上簽名，顯見原告於6個月期間並未確\n      實負起監督施工之管理責任，是原告就被告所給付之管理\n      費289,317元，應扣除未實地監工管理之日數，即返還157\n      ,809元（289,317×6/11＝157,809）。\n （5）又依系爭工程合約第44條規定，縱然兩造解除系爭契約，\n      乙方（即原告）就系爭工程提供裝修、機電、防水（屋頂\n      防水除外）、壁癌、交通設施、自來水工程…等保固工作\n      且按系爭契約第45條約定，保固金應按總價千分之6計算\n      ，本件總工程款為7,308,132元，故原告尚應提供43,849\n      元保固金（7,308,132×6/1000＝43,849）予被告。\n （6）再依系爭契約第41條之約定，原告施工時，若尺寸不合規\n      定，按契約單價比例扣減，並處以扣減額五倍之違約金。\n      今原告施工品質為如契約所定，致模板偏差過大致被告額\n      外施工支出223,450元，則原告除應將上開價金返還予被\n      告外，並依約應給付1,117,250元（223,450×5＝1,117,2\n      50）。\n （7）末依系爭工程契約之附件即工程進度表之約定，系爭建物\n      結構體應於96年4月5日完工，原告卻遲至96年6月28日結\n      構體才完成，共遲延83日，依系爭契約第27條、46條之約\n      定，原告應對被告負遲延責任，計606,575元（7308,132\n      ×83/1000＝606,575）\n （8）綜上所述，原告需給付被告2,065,877元（計算式：140,3\n      94＋157,809＋43,849＋1,117,250＋606,575＝2,065,877\n      ），以及原告積欠被告上述鋼筋款項、施工造成鄰損、防\n      水工程等扣款1,008,109元（其中鋼筋670,000元、結構偏\n      差126,800元、鄰損5,000元、止漏38,409元、防水37,900\n      元、臨時用電50,000元、模板借款50,000、補空洞30,000\n      元）。系爭工程被告原應給付原告8,563,313元，已給付7\n      ,308,132元，尚欠1,255,181元。然因原告尚須給付被告\n      3,073,986（2,065,877＋1,008,109＝3,043,986），兩相\n      抵銷，原告尚應給付被告1,818,805元，是被告已不具給\n      付義務。\n（三）並聲明：（1）原告之訴駁回。（2）訴訟費用由原告負擔\n      。（3）如受不利判決，願供擔保請准免為假執行。\n三、兩造不爭執事實：\n（1）兩造於95年8月14日簽訂工程契約，雙方合意就臺北市○○\n     區○○段4小段215地號、216地號2筆土地上（門牌號碼臺\n     北市○○區○○路1段166巷44號），興建地上七層地下一\n     層之住宅大樓一棟，以原告為該住宅大樓興建工程之承造\n     人，被告為系爭契約之定作人。\n（2）被告於96年7月18日以存證信函通知原告自即日起終止兩造\n     間工程契約關係，並請求原告派員結算工程款，及就有必\n     要履行之未完工工程部分在一週內完成。\n（3）被告之工地主任丙○○與原告於96年10月3日完成結算，結\n     算結果為：系爭工程原告實際請領之工程款為7,308,132元\n     ，原告得請求被告給付之承攬報酬為2,704,440元,，但原\n     告就系爭工程部分應扣減款項為933,109元，故核計後被告\n     尚應給付原告承攬報酬1,771,331元。\n（4）被告交付原告1紙發票人為曜先營造有限公司、支票號碼為\n     EA0000000、票面金額909,000元、受款人為原告、發票日\n     為96年12月3日之支票1紙以為報酬之給付，經原告於發票\n     日提示後遭退票，未獲付款。\n四、得心證之理由：\n（一）上述不爭執事實，有兩造所不爭執之系爭工程契約書、大\n      築營造結案工程款項影本、支票及退票理由單、存證信函\n      在卷可證，自可信為真實。\n（二）被告於96年7月18日以存證信函通知原告終止兩造間工程\n      契約關係，依據兩造所訂系爭工程合約第48條最後一項約\n      定：「甲方（指被告）因業務之考量，得終止或解除部分\n      或全部契約，乙方（指原告）於接獲甲方通知後，應立即\n      停工並負責遣散工人，清理現場，其已完成之工程及已進\n      場之材料機具設備，由甲方依契約或準用前項第二款工程\n      開工後無法繼續施工之約定，核實給付。但不包括所失利\n      益，所有相關憑證單據及工人機具遣散費用，甲方無條件\n      支付。」及系爭工程合約第48條第1項第二款第2目約定：\n      「已施工之工程，依本契約約定估驗計價」內容，被告於\n      終止系爭工程契約後，就原告已施工之工程，應負給付該\n      部分工程款之義務。\n（三）而原告主張兩造間已就系爭契約終止後之工程款曾為結算\n      ，且該結算之效力應及於被告，並據其提出大築營造結案\n      工程款項書面記錄在卷為證。被告雖不否認上述大築營造\n      結案工程款項書面係由被告之工地主任丙○○與原告所為\n      結算，但否認上述結算之效力及於被告，不生拘束被告之\n      效力，並為前揭抗辯。而查，上述原告所提出之大築營造\n      結案工程款項書面，雖有被告之工地主任丙○○為簽名，\n      但並未有被告之簽名，且被告雖曾於96年8月7日寄發存證\n      信函予被告，通知被告應於96年8月15日前會同丙○○丈\n      量工程計價款項數量，有原告所提出之存證信函1紙在卷\n      可證，但該存證信函內容，並無被告授權丙○○得以被告\n      之代理人名義全權處理與原告間之終止契約結算工程款事\n      宜，此有原告所提出上述存證信函在卷可據；又證人丙○\n      ○曾於本院準備程序中到庭證述：「被告有沒有說去原告\n      結算，被告即會依結算結果付款，不記得了，但我離開前\n      確實有做結算；當時因我要離職，原告叫我將該算的算一\n      算；因為被告找來新來的監工不知道狀況，所以理所當然\n      我經手的部分就要算清楚才走，我是就我經手的部分，我\n      認為該付多少錢，我就與原告算清楚；我跟被告報告後，\n      被告還會親自去看，確定後才會付款」等語（見本院98\n      年8月14日準備程序筆錄）；依據證人丙○○之上述證詞\n      可知，被告係因證人即將離職，叫證人去核算工程款，以\n      備新來之工地主任進行交接瞭解，被告當時並未授權證人\n      丙○○得全權與原告結算工程款之事實，可資確認；另外\n      ，被告雖曾交付上述支票1紙以為支付第十一次工程款909\n      ,000元，但各期之工程款係按施工進度給付之工程款，是\n      約定多少就給多少之事實，業據證人丙○○於上述準備程\n      序證述在卷，況且原告亦不否認系爭工程係按期給付工程\n      款之情，顯見系爭工程之各期工程款係依據施工進度施工\n      ，與結算無關，故被告所抗辯上述第十一期工程款本來就\n      是要由被告給付，與結算無關等語應屬事實，自不因被告\n      已交付支票給付第十一期工程款，而謂被告曾授權證人丙\n      ○○全權負責工程結算且被告已經承認結算之效力。故原\n      告主張兩造已經就系爭工程完成結算，兩造所為結算即大\n      築營造結案工程款項書面紀錄對被告亦生效力等語，即尚\n      無可據。\n（四）而依據兩造所訂系爭工程合約第48條第2項、第1項第二款\n      第2目之約定，被告應就終止契約時原告已施作之工程核\n      實給付工程，已如上述；而原告所請求之工程款給付標準\n      ，係依據原告所提出與被告之工地主任丙○○所結算之大\n      築營造結案工程款項書面為依據。本院審酌被告並不否認\n      上述書面係由被告之工地主任丙○○於被告終止系爭工程\n      合約後與原告所為之結算，且上述結算書面內容明確載明\n      應給付之工程款、扣款款項、工程施作內容之日期、工數\n      、工作內容、金額，甚且包括結算書，均有載明工程項目\n      、單位、數量、單價、總價、備註等，顯見被告之工地主\n      任丙○○於被告終止系爭工程合約後，確實就系爭工程曾\n      進行結算，而進行結算人丙○○於結算當時既任職被告之\n      工地主任，主管系爭工程現場之施工監督，當就系爭工程\n      之施作內容有相當之瞭解，故其與原告所進行之結算，就\n      工程施作項目、金額及應扣款金額等，應最能反應結算當\n      時原告就系爭工程之實際施作內容、數量、工程款及應扣\n      款事實，故原告提出大築營造結案工程款項之結算結果，\n      主張上述結算書面所載為原告於結算當時已施作工程內容\n      ，自可認為真實；另外，被告並未提出反證證明兩造於事\n      後曾另行結算，或上述結算，有何不符合事實之處。故原\n      告以上述大築營造結案工程款項之書面，主張被告應負上\n      述大築營造結案工程款項書面所載工程款之給付責任，自\n      屬有據。\n（五）至於被告上述所抗辯系爭工程施作有瑕疵及遲延，應進行\n      扣款部分，經查：\n （1）被告抗辯系爭工程有關建物結構體之部分，有因混凝土未\n      搗實，造成建物多處產生孔洞，並有鋼筋外露之情形，另\n      放樣及模板精準度偏差，需打除重新修補之建築結構偏差\n      之瑕疵，致被告支出223,450元修補之情，固據被告提出\n      現場照片、估價單在卷為證。然被告之上述抗辯，為原告\n      所否認在卷，且依據兩造所不爭執之卷附大築營造結案工\n      程款項結算書面，已記載「因建築結構偏差造成之敲除或\n      填補之工資及材料」字樣內容，且有記載扣款之金額，顯\n      然於上述結算當時，被告之工地主任丙○○曾經就此部分\n      結構體偏差之扣款為結算處理；又檢視被告所提出之估價\n      單，不僅記載系爭工程之施工位置為臺北市○○路○段166\n      巷46號，與系爭工程所在之44號不符，且依系爭建物之建\n      物謄本之記載，系爭工程之建物係於97年7月11日建築完\n      成，然上述估價單中竟有1張之日期為98年3月30日，係在\n      上述建物建築完工之後，顯示估價單之真正，乃有可疑；\n      另外，依上述估價單內容，原告所施作工程之瑕疵甚多，\n      幾乎每一層樓均有瑕疵，且所列瑕疵又係明顯可見，何以\n      被告之工地主任丙○○結算時均未發現而未以處理，此與\n      常情不符；另外，系爭工程施作之建物已經完工，且已有\n      出賣他人之事實，為被告所不否認在卷，則如被告確實支\n      出上述修補費用，應有確實之支出明細、支出記錄，不應\n      僅有如估價性質之估價單為證；上述估價單實不足以為支\n      出瑕疵修補之依據；故被告以上述證據，證明系爭工程所\n      施作之建物於結算當時有結構體偏差之瑕疵，舉證尚屬不\n      足，而不足採信。\n （2）有關被告所抗辯地下室蓄水池、污水坑及電梯機漏水等多\n      處積水及產生水漬痕跡之瑕疵，致被告支出140,394元之\n      修補費用之情，固據被告提出照片、廣修企業有限公司之\n      計價單為證。然被告之上述抗辯，亦為原告所否認，且本\n      院檢視卷附大築營造結案工程款項之結算書面，已有電梯\n      及污水坑止漏灌漿之扣款紀錄，工作內容亦有堵漏、電梯\n      機坑及污水坑、B1牆等止漏灌漿、水箱漏水處敲除等工作\n      項目之記載，顯示結算當時，被告之工地主任丙○○亦就\n      此部分有所結算處理；又被告亦不爭執上述結算書面所載\n      （廣修帳單）38,409元之部分，就是被告所提出廣修企業\n      有限公司之計價單中之一部份（見本院98年12月22日準備\n      程序筆錄），可見結算當時確實就漏水部分有所處理。另\n      外，本院再審酌被告所提出之96年11月7日計價單，工作\n      之時間自96年10月4日至96年10月27日，係在96年10月3日\n      結算翌日起進行，如於96年10月4日真有進行上述單純漏\n      水修補之需要，何以96年10月3日結算記錄並未處理，況\n      且比對被告所提出96年9月28日、96年11月7日之計價單，\n      96年11月7日記價單所載之工作項目較多（如多出環氧樹\n      脂、陶瓷粉、石英砂等，與96年9月28日帳單僅止漏劑、\n      黃油嘴、止水針頭不同），又原告陳述上述估價單不是單\n      純防漏工程要用等語，被告則未舉證證明上述計價單所載\n      確係為原告所施作工程漏水部分之單純防漏施作工程；故\n      被告以上述計價單證據，欲證明系爭工程所施作之建物於\n      結算當時有漏水等之瑕疵，舉證亦屬不足，而不足採信。\n （3）有關原告施作工程造成鄰損部分，被告之抗辯，為原告所\n      否認在卷；且原告所提出大築營造結案工程款項之書面記\n      錄，已記載有「鄰損、卡拉ＯＫ、水電修理」等之處理文\n      字，顯示結算當時，亦曾就鄰損部分為處理；另被告所抗\n      辯鄰損部分，被告迄今未提出賠償鄰損部分之證明，此部\n      分被告之抗辯，亦不能證明。\n （4）而有關被告抗辯系爭工程有關建物結構體之部分，有因混\n      凝土未搗實，造成建物多處產生孔洞，並有鋼筋外露之情\n      形，另放樣及模板精準度偏差，需打除重新修補之建築結\n      構偏差之瑕疵之事實，既未可信，則被告主張依據系爭契\n      約第41條之約定，原告施工時，若尺寸不合規定，按契約\n      單價比例扣減，並處以扣減額五倍之違約金，原告施工品\n      質未如契約所定，致模板偏差過大致被告額外施工支出22\n      3,450元，則原告除應將上開價金返還予被告外，並依約\n      應給付1,117,250元（223,450×5＝1,117,250）之違約金\n      部分，則屬無據。\n （5）被告抗辯原告施作系爭工程遲延之部分，原告並不否認完\n      工日期有所遲延，但主張係因被告與原承包商正良泰公司\n      遲未解除合約、被告遲遲無法交付土方證明予原告，且被\n      告有變更工程，故本件工程係因可歸責於被告之事由，未\n      能於合約所定之時間完成結構體，自不可歸責於原告等語\n      。查依據原告所提出大築營造結案工程款項之書面記錄，\n      並未就原告之工程施作遲延部分為處理，已顯示被告之工\n      地主任丙○○於結算當時，確實並未就原告施作遲延部分\n      為處理，因此，原告主張未因可歸責於原告之情，已非無\n      據，否則何以訴外人丙○○於結算當時曾就數項扣款項目\n      為扣款，但並未就遲延部分為計算；又被告亦不爭執系爭\n      工程之承攬施作過程，有原告所陳述與原承包商正良泰公\n      司之爭執及土方問題之處理之情（見本院99年3月23日準\n      備程序筆錄）；因此，原告主張非可歸責於原告等語，應\n      可採信。而遲延事由既非可歸責於原告，且結算當時未做\n      處理，顯見兩造就系爭工程之完成期限，於工程進行中應\n      有完工日期展延之合意存在，因此，原告未依期限完工，\n      自不應認為仍有遲延；故被告此部分之抗辯，亦屬無據。\n （6）綜上所述，被告上述所抗辯系爭工程瑕疵及遲延部分，自\n      屬未能證明。\n（六）被告另抗辯原告於6個月期間並未確實負起監督施工之管\n      理責任，是原告就被告所給付之管理費289,317元，應扣\n      除未實地監工管理之日數，即返還157,809元（289,317\n      ×6/11＝157,809）等語。然被告之此部分抗辯，已為原\n      告所否認在卷；且本院審酌兩造所簽訂之系爭工程契約就\n      管理費部分並無明文，僅在工程項目表為約定，而其項目\n      名稱為工程利潤及管理費，其計算方式，係以原告所能請\n      求之工程款百分之5計算，而該原告所能請求之工程款，\n      係指扣除原告應負之瑕疵、遲延等應扣款事項所計算之工\n      程款，顯見被告主張原告施作工程有所疏失，如有構成違\n      約事由，應於計算工程款時扣除，而非在計算管理費時為\n      扣除；故有關被告所抗辯原告未負監督施工責任，如有造\n      成系爭工程應扣款事由，即由該部分處理，而非於工程管\n      理費部分為扣除；另被告所提出日報表，未經原告人員簽\n      名之事實，雖為原告所不爭執，但兩造間並未約定日報表\n      未簽名即構成扣款事實，且此部分尚不足以證明原告施作\n      系爭工程已構成應扣款之事由；故被告抗辯應扣除管理費\n      ，亦無理由。\n（七）而依據原告所提出「大築營造結案工程款項」書面記錄，\n      原告所能向被告請求之金額，包括第十次前計價之保留款\n      876,135元、第十一次之工程款909,000元、零星工程款\n      919,245元，共計2,704,440元，扣除應扣款933,109元，\n      被告應給付原告1,771,331元，而原告所提出之上述結算\n      記錄，可資作為兩造計算被告應給付工程款之證據，已如\n      前述，故原告主張被告尚有工程款共計1,771,331元應給\n      付原告，自屬有據。\n（八）另依據系爭工程契約第44條之約定，原告就系爭工程應負\n      保固責任，而就結構體之部分，其保固期間為5年，雙方\n      契約經終止者，於點驗完成之次日起計算。另依據系爭工\n      程契約第45條第1項、第2項、第3項約定，保固保證金應\n      按結算總價千分之6計算。保固保證金，由工程款及保留\n      款、或乙方（原告）得領回之履約保證金優先抵充，或另\n      由乙方以同於繳納履約保證金方式繳交之。保固保證金未\n      經動用之部分，於保固期滿後且無瑕疵待改善情事時，返\n      還之。是依據兩造之約定，保固保證金應由承攬人以其能\n      領回之工程款優先抵充，且應待約定時間即保固期屆滿後\n      ，原告所承作之工程無瑕疵待改善情事，原告方能向被告\n      領回。而兩造並不爭執系爭契約結算總價為7,308,132元\n      ，則依據上述契約約定，原告應提供43,849元保固金（7,\n      30 8,132×6/1000＝43,849，元以下四捨五入）作為保固\n      保證金。故被告抗辯原告所得向被告請求之工程款應扣除\n      43,849元，依法有據，應予准許。\n（九）故原告得向被告請求之工程款1,771,331元，應扣除保固\n      保證金43,849元，原告所能請求被告給付之工程款應為1,\n      727,482元。從而，原告請求被告應給付原告1,727,482\n      元及自起訴狀繕本送達被告之翌日起（即97年9月25日）\n      至清償日止，按年息百分之5計算之遲延利息，為有理由\n      ，應予准許。逾此部分之請求，則無理由，應予駁回。\n五、原告陳明願供擔保以代釋明，聲請宣告假執行，經核原告勝\n    訴部分，合於法律規定，爰酌定相當之擔保金額宣告之；原\n    告其餘假執行之聲請，因訴之駁回而失所依據，應併予駁回\n    ；另被告敗訴部分，本院並依被告聲請，宣告被告得預供擔\n    保，免為假執行。\n六、本件判決基礎已臻明確，兩造其餘攻擊防禦方法及舉證，於\n    判決結果無影響，毋庸一一論列，附此敘明。\n七、結論：本件原告之訴部分有理由，部分無理由，依民事訴訟\n    法第79條，判決如主文。"
  },
  "characters": {
    "judges": [
      "薛中興",
      "陳靜茹",
      "陳杰正"
    ],
    "prosecutors": [

    ],
    "lawyers": [
      "阮祺祥",
      "徐志明",
      "孫寅"
    ],
    "clerks": [

    ],
    "plaintiffs": [
      "大築營造工程有限公司"
    ],
    "defendants": [
      "甲○○"
    ],
    "prosecutor_office": [

    ],
    "creditors": [

    ],
    "debtors": [

    ],
    "judicial_associate_officer": [

    ]
  },
  "adjudged_at": "2010-05-12",
  "created_at": "2016-01-05 12:10:53",
  "updated_at": "2016-01-05 12:10:53"
}