{
  "identify": "TPD-99-易-100-20100512-1",
  "court": {
    "name": "臺灣臺北地方法院",
    "code": "TPD"
  },
  "division": {
    "name": "刑事",
    "code": "M"
  },
  "year": 99,
  "word": "易",
  "number": "100",
  "jcheck": "1",
  "reason": "竊盜",
  "content": "臺灣臺北地方法院刑事判決               99年度易字第100號\n公  訴  人  臺灣臺北地方法院檢察署檢察官\n被      告  甲○○\n            乙○○\n上列被告因竊盜案件，經檢察官提起公訴（98年度偵字第12542\n號），本院判決如下：\n    主  文\n甲○○、乙○○共同犯踰越牆垣竊盜罪，均累犯，各處有期徒刑\n柒月。\n    事  實\n一、甲○○於民國94年12月間，因犯施用第二級毒品罪，經本院\n    以94年度易字第1552號判決判處有期徒刑4月確定；於95 年\n    3月間，因犯搶奪罪，經本院以94年度訴字第1744號判決判\n    處有期徒刑7月確定；於95年7月間，因犯詐欺罪，經本院以\n    95年度簡字第2007號簡易判決判處有期徒刑6月確定，此三\n    案件再經本院以95年度聲字第1622號裁定定應執行刑有期徒\n    刑1年3月確定。於95年6月間，因犯竊盜罪，經本院以95 年\n    度易字第1097號判決各判處有期徒刑8月、8月、8月（共三\n    罪），應執行有期徒刑1年6月確定，嗣經本院以96年度聲減\n    字第252號裁定減刑並定應執行刑有期徒刑9月確定，上開案\n    件接續執行，於97年1月20日縮刑期滿執行完畢；乙○○前\n    因竊盜案件，經臺灣高等法院於93年10月26日以93年度上易\n    字第1458號判處有期徒刑6月確定，於95年3月10日易科罰金\n    執行完畢。\n二、甲○○於98年4月29日前後住在友人戊○○位於台北縣新店\n    市○○街167號住處，平日並向戊○○借用LA-5290號自小客\n    車使用。甲○○見附近之裕合街181號屋主甚少返家，與乙\n    ○○竟共同基於意圖為自己不法所有之犯意聯絡，於98年4\n    月29日下午5時許，由乙○○駕駛上開車號LA-5290號自小客\n    車載甲○○前往裕合街181號丙○○屋前，因乙○○跛腳而\n    行動不便，由甲○○翻牆進入屋內（侵入住宅部分未經告訴\n    ），徒手竊取藍色外殼電腦1台，得手後將電腦搬入車內，\n    由乙○○駕車一同離去。而上開甲○○自屋內搬電腦入車內\n    ，由乙○○開車離去之過程，適為上址鄰居丁○○於2樓所\n    目擊，並以電話通知丙○○，嗣丙○○趕回家中，發現家中\n    物品遭竊並報警處理，經警由丁○○所提供上開車號及竊嫌\n    之一有跛腳特徵，循線查獲上情。\n三、案經臺北縣政府警察局新店分局報請臺灣臺北地方法院檢察\n    署檢察官偵查起訴。\n    理  由\n一、證據能力部分：本判決所引用認定被告2人犯罪之證人於審\n    判外之陳述及卷內之書面證據資料，因被告2人於本院審理\n    中並未爭執該等證據之證據能力，復未於言詞辯論終結前聲\n    明異議，本院審酌該等證據作成時之情況，並無不宜作為證\n    據之情事，依刑事訴訟法第159條之5第2項之規定，均得作\n    為證據。\n二、認定事實所憑之證據及理由：\n    訊據被告甲○○於審理時對於前揭犯罪事實坦承不諱，另被\n    告乙○○固供認其有跛腳，惟矢口否認與被告甲○○共犯前\n    揭竊盜犯行，辯稱：伊當天在家睡覺，沒有去行竊云云（見\n    本院卷第49頁反面）。經查：\n（一）上揭竊盜犯行，業據被告甲○○於本院審理時供承不諱（\n      見本院卷第49頁背面），並據證人丁○○於警詢、偵訊及\n      審理中證述目擊被告甲○○自屋內搬電腦至車上並由被告\n      乙○○開車離去之過程等語明確（見偵卷第16至20頁、97\n      、98頁，本院卷第56頁以下），且證人即被害人丙○○於\n      警詢中證述其家中藍色外殼之電腦遭竊之事實等語明確（\n      見偵卷第13至15頁），復經警於丙○○住處2樓臥室地上\n      採集竊嫌鞋印比對結果，與被告甲○○當日所穿著之拖鞋\n      鞋底拓印紋痕型態、大小、間距類相同乙節，有內政部警\n      政署刑事警察局98年6月8日刑鑑字第0980068257號函在卷\n      可稽（見偵卷第63至70頁）。是被告甲○○任意性之自白\n      ，有前揭各項證據足資佐證，堪以採信。被告甲○○前揭\n      竊盜犯行，已臻明確，應堪認定。\n（二）被告乙○○固否認與被告甲○○共同行竊云云，惟查：\n    1.證人丁○○先後於警詢、偵訊及本院審理時證稱：伊於98\n      年4月29日17時許，發現竊嫌自裕合街181號搬一台藍色外\n      殼之電腦，搬運至一台黑色喜美之自小客車內，該車車號\n      為LA-5290號，由另一竊嫌駕駛該自小客車離去，經指認\n      係被告甲○○搬運電腦行竊，被告乙○○負責駕駛等語（\n      見偵卷第16至20頁）、伊係在樓上看到搬東西的人腳是好\n      的，在車子旁邊的那個人是跛腳，嗣警方發現被告2人跑\n      到街尾涼亭，叫伊去指認，伊騎摩托車去看，確定是被告\n      2 人等語（見偵卷第97、98頁）、伊沒有看到屋子行竊之\n      過程，伊是隔壁間從二樓往下看，看到被告甲○○從門口\n      搬東西出去放在車上，被告乙○○則是站在駕駛座門旁邊\n      ，有跛腳等語（見審卷第56頁背面以下）。本院審酌證人\n      丁○○與被告2人並不認識，素無恩怨仇隙，其經具結作\n      證，擔保其陳述之真正，衡情應無誣陷被告2人之理。而\n      證人係遭竊地點之隔壁鄰居，其在2樓目擊被告2人，並可\n      清楚而正確地目視上開行竊用車輛之車牌、顏色、廠牌，\n      以及被告乙○○有跛腳及被告甲○○搬東西之事實，足見\n      其視力及觀察力均佳，應無誤認之可能。參以證人丁○○\n      於案發後當日尚應警方要求騎機車至裕合街巷口附近，再\n      次確認案發時行為人確係被告2人乙節，業據證人丁○○\n      於警詢、偵訊及審理證述明確（見偵卷第20頁、98頁、本\n      院卷第57頁），由此足認案發當日被告並非僅藉由照片指\n      認被告2人，故其指認之正確性應相當高，應堪採信。綜\n      上，被告甲○○既爬牆進入181號，嗣又自屋內搬電腦至\n      汽車上，而被告乙○○在車旁等候嗣又開車離去，足認其\n      與被告甲○○間確有竊盜之犯意聯絡及行為分擔，是被告\n      乙○○上開竊盜犯行，洵堪認定。\n    2.被告甲○○固於審理時以證人身份證稱：伊案發當時係駕\n      駛向戊○○借用之LA-5690號車去行竊，伊係自己一人去\n      偷電腦，並沒有跟乙○○去偷，證人丁○○有可能看錯，\n      因為伊常常在那邊出入，有時候伊載戊○○，有時候也會\n      載乙○○，伊平日開車出去時，有時停在失竊地點住家門\n      口，而戊○○會站在車子旁邊，且戊○○也是跛腳云云（\n      見本院卷第73頁背面）。惟查，證人甲○○之上開證詞，\n      不惟與其於偵訊中以證人身份證稱：案發時伊係爬牆進去\n      18 1號這間偷，當時伊與乙○○要去戊○○家中，我叫乙\n      ○○停一下，說要拿一下東西，乙○○問伊這邊沒有人住\n      ，要停下來幹嘛，伊說伊撿人家不要的主機云云（見偵卷\n      第111頁、112頁）內容迥異，且經本院再次命證人丁○○\n      當庭指認案發當日所目擊站在車旁及開車者究竟係戊○○\n      或丁○○之結果，其證稱：伊確認案發當時看到在車旁邊\n      的那位是乙○○，而非戊○○，當時乙○○有走動，伊才\n      知道他跛腳等語（見審卷第112頁以下），而戊○○經本\n      院命其走動當庭勘驗結果，並未觀察出有明顯跛腳之情形\n      乙節，業經本院勘驗在卷（見本院卷第110頁背面），由\n      此足認證人丁○○應無誤戊○○為乙○○之可能。況證人\n      丁○○明確目擊被告甲○○從屋內搬電腦至車上後，由原\n      站在車旁邊之乙○○開車一同離去，已如前述，證人丁○\n      ○殊無將一人行竊誤認為兩人行竊之可能。參以證人甲○\n      ○上開於偵訊中證述乙○○案發當時有在車旁之證詞，與\n      證人丁○○之證詞相符，應可採信。是證人甲○○上開審\n      理中證述，與事實不符，尚難憑採。\n    3.綜上，本案被告乙○○上開竊盜犯行，已臻明確，應依法\n      論科。其空言否認犯行，與事實不符，尚難憑採。\n三、論罪科刑之理由：\n（一）按刑法第321條第1項第2款所謂「毀越門扇牆垣」，係指\n      毀損或超越、踰越門扇牆垣而言，本件被告甲○○當時係\n      踰越圍牆而進入該住處內竊盜，已如前述，是核被告2人\n      所為，均係犯刑法第321條第1項第2款之踰越牆垣竊盜罪\n      。被告2人有犯意聯絡及行為分擔，為共同正犯。另被告2\n      人有事實欄一所載前案執行情形，有臺灣高等法院被告前\n      案紀錄表1份在卷可參，其受有期徒刑易科罰金執行完畢\n      後，5年內故意再犯有期徒刑以上之本罪，均為累犯，均\n      應依刑法第47條第1項之規定加重其刑。\n（二）量刑理由之說明：\n      爰審酌被告2人翻越牆垣進入他人屋內行竊，被告乙○○\n      犯後否認犯行，且被告2人均有竊盜之前案紀錄，有臺灣\n      高等法院被告前案紀錄表在卷可稽，素行不良，其等未知\n      悛悔，再犯本案，本應重懲，念及被告甲○○犯後坦承犯\n      行，態度尚可，且其等所竊取之電腦主機，價值非鉅，而\n      被告乙○○行動不便，謀生能力受影響，併參酌其等犯罪\n      之動機、目的、手段等一切情狀，分別量處如主文所示之\n      刑，以示懲儆。\n四、證人即被告甲○○於審理中證述本案係其一人所犯，被告乙\n    ○○當時並未在場云云（見審卷第73頁以下），不惟與事實\n    不符，且與其偵訊中之證述矛盾（見偵卷第112頁），此部\n    分是否涉及偽證罪嫌，應由檢察官另行偵辦，併此敘明。\n五、適用之法律：刑事訴訟法第299條第1項前段，刑法第28條、\n    第321條第1項第2款、第47條。\n本案經檢察官蘇維達到庭執行職務。\n中    華    民    國    99    年    5     月    12    日\n                  刑事第十一庭  法  官  顧正德\n上正本證明與原本無異。\n如不服本判決應於收受送達後10日內向本院提出上訴書狀，並應\n敘述具體理由；其未敘述上訴理由者，應於上訴期間屆滿後20日\n內向本院補提理由書（均須按他造當事人之人數附繕本）「切勿\n逕送上級法院」。告訴人或被害人如對於本判決不服者，應具備\n理由請求檢察官上訴，其上訴期間之計算係以檢察官收受判決正\n本之日期為準。\n                                書記官  郭錦賢\n中    華    民    國    99    年    5     月    17    日\n中華民國刑法第321條\n（加重竊盜罪）\n犯竊盜罪而有左列情形之一者，處 6 月以上、 5 年以下有期徒\n刑：\n一、於夜間侵入住宅或有人居住之建築物、船艦或隱匿其內而犯\n    之者。\n二、毀越門扇、牆垣或其他安全設備而犯之者。\n三、攜帶兇器而犯之者。\n四、結夥三人以上而犯之者。\n五、乘火災、水災或其他災害之際而犯之者。\n六、在車站或埠頭而犯之者。\n前項之未遂犯罰之。",
  "structure": {
    "main": "甲○○、乙○○共同犯踰越牆垣竊盜罪，均累犯，各處有期徒刑\n柒月。",
    "fact": "一、甲○○於民國94年12月間，因犯施用第二級毒品罪，經本院\n    以94年度易字第1552號判決判處有期徒刑4月確定；於95 年\n    3月間，因犯搶奪罪，經本院以94年度訴字第1744號判決判\n    處有期徒刑7月確定；於95年7月間，因犯詐欺罪，經本院以\n    95年度簡字第2007號簡易判決判處有期徒刑6月確定，此三\n    案件再經本院以95年度聲字第1622號裁定定應執行刑有期徒\n    刑1年3月確定。於95年6月間，因犯竊盜罪，經本院以95 年\n    度易字第1097號判決各判處有期徒刑8月、8月、8月（共三\n    罪），應執行有期徒刑1年6月確定，嗣經本院以96年度聲減\n    字第252號裁定減刑並定應執行刑有期徒刑9月確定，上開案\n    件接續執行，於97年1月20日縮刑期滿執行完畢；乙○○前\n    因竊盜案件，經臺灣高等法院於93年10月26日以93年度上易\n    字第1458號判處有期徒刑6月確定，於95年3月10日易科罰金\n    執行完畢。\n二、甲○○於98年4月29日前後住在友人戊○○位於台北縣新店\n    市○○街167號住處，平日並向戊○○借用LA-5290號自小客\n    車使用。甲○○見附近之裕合街181號屋主甚少返家，與乙\n    ○○竟共同基於意圖為自己不法所有之犯意聯絡，於98年4\n    月29日下午5時許，由乙○○駕駛上開車號LA-5290號自小客\n    車載甲○○前往裕合街181號丙○○屋前，因乙○○跛腳而\n    行動不便，由甲○○翻牆進入屋內（侵入住宅部分未經告訴\n    ），徒手竊取藍色外殼電腦1台，得手後將電腦搬入車內，\n    由乙○○駕車一同離去。而上開甲○○自屋內搬電腦入車內\n    ，由乙○○開車離去之過程，適為上址鄰居丁○○於2樓所\n    目擊，並以電話通知丙○○，嗣丙○○趕回家中，發現家中\n    物品遭竊並報警處理，經警由丁○○所提供上開車號及竊嫌\n    之一有跛腳特徵，循線查獲上情。\n三、案經臺北縣政府警察局新店分局報請臺灣臺北地方法院檢察\n    署檢察官偵查起訴。",
    "reason": "一、證據能力部分：本判決所引用認定被告2人犯罪之證人於審\n    判外之陳述及卷內之書面證據資料，因被告2人於本院審理\n    中並未爭執該等證據之證據能力，復未於言詞辯論終結前聲\n    明異議，本院審酌該等證據作成時之情況，並無不宜作為證\n    據之情事，依刑事訴訟法第159條之5第2項之規定，均得作\n    為證據。\n二、認定事實所憑之證據及理由：\n    訊據被告甲○○於審理時對於前揭犯罪事實坦承不諱，另被\n    告乙○○固供認其有跛腳，惟矢口否認與被告甲○○共犯前\n    揭竊盜犯行，辯稱：伊當天在家睡覺，沒有去行竊云云（見\n    本院卷第49頁反面）。經查：\n（一）上揭竊盜犯行，業據被告甲○○於本院審理時供承不諱（\n      見本院卷第49頁背面），並據證人丁○○於警詢、偵訊及\n      審理中證述目擊被告甲○○自屋內搬電腦至車上並由被告\n      乙○○開車離去之過程等語明確（見偵卷第16至20頁、97\n      、98頁，本院卷第56頁以下），且證人即被害人丙○○於\n      警詢中證述其家中藍色外殼之電腦遭竊之事實等語明確（\n      見偵卷第13至15頁），復經警於丙○○住處2樓臥室地上\n      採集竊嫌鞋印比對結果，與被告甲○○當日所穿著之拖鞋\n      鞋底拓印紋痕型態、大小、間距類相同乙節，有內政部警\n      政署刑事警察局98年6月8日刑鑑字第0980068257號函在卷\n      可稽（見偵卷第63至70頁）。是被告甲○○任意性之自白\n      ，有前揭各項證據足資佐證，堪以採信。被告甲○○前揭\n      竊盜犯行，已臻明確，應堪認定。\n（二）被告乙○○固否認與被告甲○○共同行竊云云，惟查：\n    1.證人丁○○先後於警詢、偵訊及本院審理時證稱：伊於98\n      年4月29日17時許，發現竊嫌自裕合街181號搬一台藍色外\n      殼之電腦，搬運至一台黑色喜美之自小客車內，該車車號\n      為LA-5290號，由另一竊嫌駕駛該自小客車離去，經指認\n      係被告甲○○搬運電腦行竊，被告乙○○負責駕駛等語（\n      見偵卷第16至20頁）、伊係在樓上看到搬東西的人腳是好\n      的，在車子旁邊的那個人是跛腳，嗣警方發現被告2人跑\n      到街尾涼亭，叫伊去指認，伊騎摩托車去看，確定是被告\n      2 人等語（見偵卷第97、98頁）、伊沒有看到屋子行竊之\n      過程，伊是隔壁間從二樓往下看，看到被告甲○○從門口\n      搬東西出去放在車上，被告乙○○則是站在駕駛座門旁邊\n      ，有跛腳等語（見審卷第56頁背面以下）。本院審酌證人\n      丁○○與被告2人並不認識，素無恩怨仇隙，其經具結作\n      證，擔保其陳述之真正，衡情應無誣陷被告2人之理。而\n      證人係遭竊地點之隔壁鄰居，其在2樓目擊被告2人，並可\n      清楚而正確地目視上開行竊用車輛之車牌、顏色、廠牌，\n      以及被告乙○○有跛腳及被告甲○○搬東西之事實，足見\n      其視力及觀察力均佳，應無誤認之可能。參以證人丁○○\n      於案發後當日尚應警方要求騎機車至裕合街巷口附近，再\n      次確認案發時行為人確係被告2人乙節，業據證人丁○○\n      於警詢、偵訊及審理證述明確（見偵卷第20頁、98頁、本\n      院卷第57頁），由此足認案發當日被告並非僅藉由照片指\n      認被告2人，故其指認之正確性應相當高，應堪採信。綜\n      上，被告甲○○既爬牆進入181號，嗣又自屋內搬電腦至\n      汽車上，而被告乙○○在車旁等候嗣又開車離去，足認其\n      與被告甲○○間確有竊盜之犯意聯絡及行為分擔，是被告\n      乙○○上開竊盜犯行，洵堪認定。\n    2.被告甲○○固於審理時以證人身份證稱：伊案發當時係駕\n      駛向戊○○借用之LA-5690號車去行竊，伊係自己一人去\n      偷電腦，並沒有跟乙○○去偷，證人丁○○有可能看錯，\n      因為伊常常在那邊出入，有時候伊載戊○○，有時候也會\n      載乙○○，伊平日開車出去時，有時停在失竊地點住家門\n      口，而戊○○會站在車子旁邊，且戊○○也是跛腳云云（\n      見本院卷第73頁背面）。惟查，證人甲○○之上開證詞，\n      不惟與其於偵訊中以證人身份證稱：案發時伊係爬牆進去\n      18 1號這間偷，當時伊與乙○○要去戊○○家中，我叫乙\n      ○○停一下，說要拿一下東西，乙○○問伊這邊沒有人住\n      ，要停下來幹嘛，伊說伊撿人家不要的主機云云（見偵卷\n      第111頁、112頁）內容迥異，且經本院再次命證人丁○○\n      當庭指認案發當日所目擊站在車旁及開車者究竟係戊○○\n      或丁○○之結果，其證稱：伊確認案發當時看到在車旁邊\n      的那位是乙○○，而非戊○○，當時乙○○有走動，伊才\n      知道他跛腳等語（見審卷第112頁以下），而戊○○經本\n      院命其走動當庭勘驗結果，並未觀察出有明顯跛腳之情形\n      乙節，業經本院勘驗在卷（見本院卷第110頁背面），由\n      此足認證人丁○○應無誤戊○○為乙○○之可能。況證人\n      丁○○明確目擊被告甲○○從屋內搬電腦至車上後，由原\n      站在車旁邊之乙○○開車一同離去，已如前述，證人丁○\n      ○殊無將一人行竊誤認為兩人行竊之可能。參以證人甲○\n      ○上開於偵訊中證述乙○○案發當時有在車旁之證詞，與\n      證人丁○○之證詞相符，應可採信。是證人甲○○上開審\n      理中證述，與事實不符，尚難憑採。\n    3.綜上，本案被告乙○○上開竊盜犯行，已臻明確，應依法\n      論科。其空言否認犯行，與事實不符，尚難憑採。\n三、論罪科刑之理由：\n（一）按刑法第321條第1項第2款所謂「毀越門扇牆垣」，係指\n      毀損或超越、踰越門扇牆垣而言，本件被告甲○○當時係\n      踰越圍牆而進入該住處內竊盜，已如前述，是核被告2人\n      所為，均係犯刑法第321條第1項第2款之踰越牆垣竊盜罪\n      。被告2人有犯意聯絡及行為分擔，為共同正犯。另被告2\n      人有事實欄一所載前案執行情形，有臺灣高等法院被告前\n      案紀錄表1份在卷可參，其受有期徒刑易科罰金執行完畢\n      後，5年內故意再犯有期徒刑以上之本罪，均為累犯，均\n      應依刑法第47條第1項之規定加重其刑。\n（二）量刑理由之說明：\n      爰審酌被告2人翻越牆垣進入他人屋內行竊，被告乙○○\n      犯後否認犯行，且被告2人均有竊盜之前案紀錄，有臺灣\n      高等法院被告前案紀錄表在卷可稽，素行不良，其等未知\n      悛悔，再犯本案，本應重懲，念及被告甲○○犯後坦承犯\n      行，態度尚可，且其等所竊取之電腦主機，價值非鉅，而\n      被告乙○○行動不便，謀生能力受影響，併參酌其等犯罪\n      之動機、目的、手段等一切情狀，分別量處如主文所示之\n      刑，以示懲儆。\n四、證人即被告甲○○於審理中證述本案係其一人所犯，被告乙\n    ○○當時並未在場云云（見審卷第73頁以下），不惟與事實\n    不符，且與其偵訊中之證述矛盾（見偵卷第112頁），此部\n    分是否涉及偽證罪嫌，應由檢察官另行偵辦，併此敘明。\n五、適用之法律：刑事訴訟法第299條第1項前段，刑法第28條、\n    第321條第1項第2款、第47條。\n本案經檢察官蘇維達到庭執行職務。\n中    華    民    國    99    年    5     月    12    日\n                  刑事第十一庭  法  官  顧正德\n上正本證明與原本無異。\n如不服本判決應於收受送達後10日內向本院提出上訴書狀，並應\n敘述具體理由；其未敘述上訴理由者，應於上訴期間屆滿後20日\n內向本院補提理由書（均須按他造當事人之人數附繕本）「切勿\n逕送上級法院」。告訴人或被害人如對於本判決不服者，應具備\n理由請求檢察官上訴，其上訴期間之計算係以檢察官收受判決正\n本之日期為準。\n                                書記官  郭錦賢"
  },
  "characters": {
    "judges": [
      "顧正德"
    ],
    "prosecutors": [
      "蘇維達"
    ],
    "lawyers": [

    ],
    "clerks": [
      "郭錦賢"
    ],
    "plaintiffs": [

    ],
    "defendants": [
      "甲○○"
    ],
    "prosecutor_office": [
      "臺灣臺北地方法院檢察署檢察官"
    ],
    "creditors": [

    ],
    "debtors": [

    ],
    "judicial_associate_officer": [

    ]
  },
  "adjudged_at": "2010-05-12",
  "created_at": "2016-01-05 12:05:50",
  "updated_at": "2016-01-05 12:05:50"
}