{
  "identify": "TPD-99-聲-4-20100104-1",
  "court": {
    "name": "臺灣臺北地方法院",
    "code": "TPD"
  },
  "division": {
    "name": "刑事",
    "code": "M"
  },
  "year": 99,
  "word": "聲",
  "number": "4",
  "jcheck": "1",
  "reason": "聲請單獨宣告沒收違禁物",
  "content": "臺灣臺北地方法院刑事裁定                 99年度聲字第4號\n聲  請  人  臺灣臺北地方法院檢察署檢察官\n被      告  甲○○\n上列聲請人聲請單獨宣告沒收違禁物案件，本院裁定如下：\n    主  文\n扣案之甲基安非他命壹袋（驗餘淨重零點零玖貳陸公克）沒收銷\n燬。\n    理  由\n一、本件聲請意旨略以：臺灣臺北地方法院檢察署九十八年度毒\n    偵字第一五二號被告甲○○違反毒品危害防制條例案件，因\n    被告經觀察、勒戒完畢後無施用毒品傾向，而經該署檢察官\n    為不起訴處分，惟查扣案之白色透明結晶及結晶塊一袋（驗\n    餘淨重０點０九二六公克），經鑑驗結果含第二級毒品甲基\n    安非他命成分，有交通部民用航空局航空醫務中心毒品鑑定\n    書一紙附卷可稽，依毒品危害防制條例第二條第二項第二款\n    及第十一條第二項之規定，係屬違禁物，爰依刑法第三十八\n    條第一項第一款、第二項、第四十條第二項及毒品危害防制\n    條例第十八條第一項前段之規定聲請單獨宣告沒收銷燬等語\n    。\n二、按持有第二級毒品，係犯毒品危害防制條例第十一條第二項\n    之罪，故第二級毒品係屬違禁物。次按違禁物，不問屬於犯\n    人與否，均沒收之，且得單獨宣告沒收，而查獲之毒品及專\n    供製造或施用毒品之器具，不問屬於犯人與否，均沒收銷燬\n    之，刑法第三十八條第一項第一款、第二項、第四十條第二\n    項及毒品危害防制條例第十八條第一項前段分別定有明文。\n    經查，被告甲○○施用第二級毒品犯行，經依臺灣臺北地方\n    法院以九十八年度毒聲字第九七號裁定送觀察、勒戒後，因\n    無繼續施用毒品之傾向，復經臺灣臺北地方法院檢察署檢察\n    官以九十八年度毒偵字第一五二號為不起訴處分確定等情，\n    有上開裁定、不起訴處分書附卷可證。惟查扣案之白色透明\n    結晶及結晶塊一袋，業經交通部民用航空局航空醫務中心鑑\n    定為含第二級毒品甲基安非他命成份，驗餘淨重０點０九二\n    六公克，有該中心毒品鑑定書一紙附卷可稽，是檢察官所提\n    單獨宣告沒收之聲請，核與前揭規定，並無不合，爰依刑法\n    第四十條第二項，毒品危害防制條例第十八條第一項前段之\n    規定，裁定如主文。\n中    華    民    國    99    年    1     月    4     日\n                        刑事第九庭  法  官  劉素如\n上正本證明與原本無異。\n如不服本裁定，應於裁定送達後5 日內向本院提出抗告狀。\n                                    書記官  陳育君\n中    華    民    國    99    年    1     月    4     日",
  "structure": {
    "main": "扣案之甲基安非他命壹袋（驗餘淨重零點零玖貳陸公克）沒收銷\n燬。",
    "reason": "一、本件聲請意旨略以：臺灣臺北地方法院檢察署九十八年度毒\n    偵字第一五二號被告甲○○違反毒品危害防制條例案件，因\n    被告經觀察、勒戒完畢後無施用毒品傾向，而經該署檢察官\n    為不起訴處分，惟查扣案之白色透明結晶及結晶塊一袋（驗\n    餘淨重０點０九二六公克），經鑑驗結果含第二級毒品甲基\n    安非他命成分，有交通部民用航空局航空醫務中心毒品鑑定\n    書一紙附卷可稽，依毒品危害防制條例第二條第二項第二款\n    及第十一條第二項之規定，係屬違禁物，爰依刑法第三十八\n    條第一項第一款、第二項、第四十條第二項及毒品危害防制\n    條例第十八條第一項前段之規定聲請單獨宣告沒收銷燬等語\n    。\n二、按持有第二級毒品，係犯毒品危害防制條例第十一條第二項\n    之罪，故第二級毒品係屬違禁物。次按違禁物，不問屬於犯\n    人與否，均沒收之，且得單獨宣告沒收，而查獲之毒品及專\n    供製造或施用毒品之器具，不問屬於犯人與否，均沒收銷燬\n    之，刑法第三十八條第一項第一款、第二項、第四十條第二\n    項及毒品危害防制條例第十八條第一項前段分別定有明文。\n    經查，被告甲○○施用第二級毒品犯行，經依臺灣臺北地方\n    法院以九十八年度毒聲字第九七號裁定送觀察、勒戒後，因\n    無繼續施用毒品之傾向，復經臺灣臺北地方法院檢察署檢察\n    官以九十八年度毒偵字第一五二號為不起訴處分確定等情，\n    有上開裁定、不起訴處分書附卷可證。惟查扣案之白色透明\n    結晶及結晶塊一袋，業經交通部民用航空局航空醫務中心鑑\n    定為含第二級毒品甲基安非他命成份，驗餘淨重０點０九二\n    六公克，有該中心毒品鑑定書一紙附卷可稽，是檢察官所提\n    單獨宣告沒收之聲請，核與前揭規定，並無不合，爰依刑法\n    第四十條第二項，毒品危害防制條例第十八條第一項前段之\n    規定，裁定如主文。"
  },
  "characters": {
    "judges": [
      "劉素如"
    ],
    "prosecutors": [

    ],
    "lawyers": [

    ],
    "clerks": [
      "陳育君"
    ],
    "plaintiffs": [

    ],
    "defendants": [
      "甲○○"
    ],
    "prosecutor_office": [
      "臺灣臺北地方法院檢察署檢察官"
    ],
    "creditors": [

    ],
    "debtors": [

    ],
    "judicial_associate_officer": [

    ]
  },
  "adjudged_at": "2010-01-04",
  "created_at": "2016-01-05 14:40:58",
  "updated_at": "2016-01-05 14:40:58"
}