{
  "identify": "TPD-98-簡-5207-20100105-1",
  "court": {
    "name": "臺灣臺北地方法院",
    "code": "TPD"
  },
  "division": {
    "name": "刑事",
    "code": "M"
  },
  "year": 98,
  "word": "簡",
  "number": "5207",
  "jcheck": "1",
  "reason": "毒品危害防制條例",
  "content": "臺灣臺北地方法院刑事簡易判決          98年度簡字第5207號\n聲  請  人  臺灣臺北地方法院檢察署檢察官\n被      告  甲○○\n上列被告因毒品危害防制條例案件，經檢察官聲請以簡易判決處\n刑（98年度偵字第29001號），本院判決如下：\n    主  文\n甲○○持有第二級毒品，處拘役貳拾日，如易科罰金，以新臺幣\n壹仟元折算壹日。扣案之安非他命壹粒（淨重零點壹陸柒零公克\n，餘重零點壹貳捌壹公克），沒收銷燬之。\n    事實及理由\n一、本件犯罪事實及證據均引用檢察官聲請簡易判決處刑書所載\n    之內容，另於犯罪事實欄補充「甲○○在偵查機關未發覺其\n    上開持有安非他命犯行前，主動坦承上開犯行，而願接受裁\n    判」。\n二、核被告所為，係犯毒品危害防制條例第11條第2項持有第二\n    級毒品罪。又被告係於98年8月28日下午8時40分許，因形跡\n    可疑，為警盤查時，在偵查機關未發覺其持有第二級毒品犯\n    行前，主動坦承上開犯行，而願接受裁判，有被告警詢筆錄\n    1 份在卷可稽（見偵卷第9頁），堪認符合刑法第62條之自\n    首要件，而被告於警方發現其竊盜犯行前，即主動供出前揭\n    犯行，以利偵查，足見其已有悔意，爰依刑法第62條前段之\n    規定，減輕其刑。爰審酌被告素行尚可，本件持有第二級毒\n    品數量甚微，犯後復坦承犯行，態度良好，被告為國中畢業\n    之智識程度，家庭經濟勉強維持之生活狀況等一切情狀，量\n    處如主文所示之刑，並諭知易科罰金之折算標準。扣案之珊\n    瑚紅色圓形藥錠1粒，經送鑑定檢出安非他命成分，為毒品\n    危害防制條例規定之第二級毒品，應依同條例第18條第1項\n    前段規定，宣告沒收銷燬。\n據上論斷，應依刑事訴訟法第449條第1項前段、第3項、第450條\n第1項、第454條第2項，毒品危害防制條例第11條第2項、第18條\n第1項前段，刑法第11條前段、第41條第1項前段、第62條前段，\n逕以簡易判決處刑如主文。\n中    華    民    國    99    年    1     月    5     日\n                  刑事第八庭    法  官  楊蕙芬\n以上正本證明與原本無異。\n如不服本判決應於收受送達後10日內向本院提出上訴書狀，並應\n敘述具體理由；其未敘述上訴理由者，應於上訴期間屆滿後20日\n內向本院補提理由書（均須按他造當事人之人數附繕）「切勿逕\n送上級法院」。\n                                書記官  馬正道\n中    華    民    國    99    年    1     月    12    日\n附錄法條：\n毒品危害防制條例第11條\n持有第一級毒品者，處 3 年以下有期徒刑、拘役或新臺幣 5 萬\n元以下罰金。\n持有第二級毒品者，處 2 年以下有期徒刑、拘役或新臺幣 3 萬\n元以下罰金。\n持有第一級毒品純質淨重十公克以上者，處 1 年以上 7 年以下\n有期徒刑，得併科新臺幣 1 百萬元以下罰金。\n持有第二級毒品純質淨重二十公克以上者，處 6 月以上 5 年以\n下有期徒刑，得併科新臺幣 70 萬元以下罰金。\n持有第三級毒品純質淨重二十公克以上者，處 3 年以下有期徒\n刑，得併科新臺幣 30 萬元以下罰金。\n持有第四級毒品純質淨重二十公克以上者，處 1 年以下有期徒\n刑，得併科新臺幣 10 萬元以下罰金。\n持有專供製造或施用第一級、第二級毒品之器具者，處 1 年以\n下有期徒刑、拘役或新臺幣 1 萬元以下罰金。",
  "structure": {
    "main": "甲○○持有第二級毒品，處拘役貳拾日，如易科罰金，以新臺幣\n壹仟元折算壹日。扣案之安非他命壹粒（淨重零點壹陸柒零公克\n，餘重零點壹貳捌壹公克），沒收銷燬之。",
    "fact": "一、本件犯罪事實及證據均引用檢察官聲請簡易判決處刑書所載\n    之內容，另於犯罪事實欄補充「甲○○在偵查機關未發覺其\n    上開持有安非他命犯行前，主動坦承上開犯行，而願接受裁\n    判」。\n二、核被告所為，係犯毒品危害防制條例第11條第2項持有第二\n    級毒品罪。又被告係於98年8月28日下午8時40分許，因形跡\n    可疑，為警盤查時，在偵查機關未發覺其持有第二級毒品犯\n    行前，主動坦承上開犯行，而願接受裁判，有被告警詢筆錄\n    1 份在卷可稽（見偵卷第9頁），堪認符合刑法第62條之自\n    首要件，而被告於警方發現其竊盜犯行前，即主動供出前揭\n    犯行，以利偵查，足見其已有悔意，爰依刑法第62條前段之\n    規定，減輕其刑。爰審酌被告素行尚可，本件持有第二級毒\n    品數量甚微，犯後復坦承犯行，態度良好，被告為國中畢業\n    之智識程度，家庭經濟勉強維持之生活狀況等一切情狀，量\n    處如主文所示之刑，並諭知易科罰金之折算標準。扣案之珊\n    瑚紅色圓形藥錠1粒，經送鑑定檢出安非他命成分，為毒品\n    危害防制條例規定之第二級毒品，應依同條例第18條第1項\n    前段規定，宣告沒收銷燬。\n據上論斷，應依刑事訴訟法第449條第1項前段、第3項、第450條\n第1項、第454條第2項，毒品危害防制條例第11條第2項、第18條\n第1項前段，刑法第11條前段、第41條第1項前段、第62條前段，\n逕以簡易判決處刑如主文。",
    "reason": "一、本件犯罪事實及證據均引用檢察官聲請簡易判決處刑書所載\n    之內容，另於犯罪事實欄補充「甲○○在偵查機關未發覺其\n    上開持有安非他命犯行前，主動坦承上開犯行，而願接受裁\n    判」。\n二、核被告所為，係犯毒品危害防制條例第11條第2項持有第二\n    級毒品罪。又被告係於98年8月28日下午8時40分許，因形跡\n    可疑，為警盤查時，在偵查機關未發覺其持有第二級毒品犯\n    行前，主動坦承上開犯行，而願接受裁判，有被告警詢筆錄\n    1 份在卷可稽（見偵卷第9頁），堪認符合刑法第62條之自\n    首要件，而被告於警方發現其竊盜犯行前，即主動供出前揭\n    犯行，以利偵查，足見其已有悔意，爰依刑法第62條前段之\n    規定，減輕其刑。爰審酌被告素行尚可，本件持有第二級毒\n    品數量甚微，犯後復坦承犯行，態度良好，被告為國中畢業\n    之智識程度，家庭經濟勉強維持之生活狀況等一切情狀，量\n    處如主文所示之刑，並諭知易科罰金之折算標準。扣案之珊\n    瑚紅色圓形藥錠1粒，經送鑑定檢出安非他命成分，為毒品\n    危害防制條例規定之第二級毒品，應依同條例第18條第1項\n    前段規定，宣告沒收銷燬。\n據上論斷，應依刑事訴訟法第449條第1項前段、第3項、第450條\n第1項、第454條第2項，毒品危害防制條例第11條第2項、第18條\n第1項前段，刑法第11條前段、第41條第1項前段、第62條前段，\n逕以簡易判決處刑如主文。"
  },
  "characters": {
    "judges": [
      "楊蕙芬"
    ],
    "prosecutors": [

    ],
    "lawyers": [

    ],
    "clerks": [
      "馬正道"
    ],
    "plaintiffs": [

    ],
    "defendants": [
      "甲○○"
    ],
    "prosecutor_office": [
      "臺灣臺北地方法院檢察署檢察官"
    ],
    "creditors": [

    ],
    "debtors": [

    ],
    "judicial_associate_officer": [

    ]
  },
  "adjudged_at": "2010-01-05",
  "created_at": "2016-01-05 15:12:47",
  "updated_at": "2016-01-05 15:12:47"
}