{
  "identify": "TPD-99-自-20-20100512-1",
  "court": {
    "name": "臺灣臺北地方法院",
    "code": "TPD"
  },
  "division": {
    "name": "刑事",
    "code": "M"
  },
  "year": 99,
  "word": "自",
  "number": "20",
  "jcheck": "1",
  "reason": "誣告",
  "content": "臺灣臺北地方法院刑事裁定                99年度自字第20號\n自  訴  人  乙○○\n上列自訴人自訴被告丙○○、甲○○誣告案件，本院裁定如下：\n    主    文\n自訴人應於本裁定送達後五日內委任律師為代理人並提出委任書\n狀。\n    理    由\n一、按自訴之提起應委任律師行之；又自訴人未委任代理人，法\n    院應定期間以裁定命其委任代理人，逾期仍不委任者，應諭\n    知不受理之判決，刑事訴訟法第319條第2項及第329第2項分\n    別定有明文。\n二、查本件自訴人乙○○對被告丙○○、甲○○提起誣告自訴案\n    ，前雖經委任廖克明、王昭婷為代理人，惟嗣經自訴人代理\n    人具狀陳報已合意解除委任，此有刑事解除委任狀在卷可稽\n    ，是本件自訴程序於解除原自訴代理人委任後，已與法定要\n    件顯有未合，揆諸前揭之說明，自訴人提起本件自訴其起訴\n    之程式顯有未備，爰依刑事訴訟法第329條第2項之規定，命\n    自訴人於本裁定送達後5日內補正如主文所示事項，以資憑\n    辦。\n中    華    民    國    99    年    5     月    12    日\n                 刑事第十五庭   審判長法  官  廖紋妤\n                                      法  官  吳麗英\n                                      法  官  邱蓮華\n上正本證明與原本無異。\n本裁定不得抗告。\n                                      書記官  周小玲\n中    華    民    國    99    年    5     月    14    日",
  "structure": {
    "main": "自訴人應於本裁定送達後五日內委任律師為代理人並提出委任書\n狀。",
    "reason": "一、按自訴之提起應委任律師行之；又自訴人未委任代理人，法\n    院應定期間以裁定命其委任代理人，逾期仍不委任者，應諭\n    知不受理之判決，刑事訴訟法第319條第2項及第329第2項分\n    別定有明文。\n二、查本件自訴人乙○○對被告丙○○、甲○○提起誣告自訴案\n    ，前雖經委任廖克明、王昭婷為代理人，惟嗣經自訴人代理\n    人具狀陳報已合意解除委任，此有刑事解除委任狀在卷可稽\n    ，是本件自訴程序於解除原自訴代理人委任後，已與法定要\n    件顯有未合，揆諸前揭之說明，自訴人提起本件自訴其起訴\n    之程式顯有未備，爰依刑事訴訟法第329條第2項之規定，命\n    自訴人於本裁定送達後5日內補正如主文所示事項，以資憑\n    辦。"
  },
  "characters": {
    "judges": [
      "廖紋妤",
      "吳麗英",
      "邱蓮華"
    ],
    "prosecutors": [

    ],
    "lawyers": [
      "自訴人應於本裁定送達後五日內委任"
    ],
    "clerks": [
      "周小玲"
    ],
    "plaintiffs": [

    ],
    "defendants": [

    ],
    "prosecutor_office": [

    ],
    "creditors": [

    ],
    "debtors": [

    ],
    "judicial_associate_officer": [

    ]
  },
  "adjudged_at": "2010-05-12",
  "created_at": "2016-01-05 12:05:36",
  "updated_at": "2016-01-05 12:05:36"
}