{
  "identify": "TPD-99-簡-1301-20100512-2",
  "court": {
    "name": "臺灣臺北地方法院",
    "code": "TPD"
  },
  "division": {
    "name": "刑事",
    "code": "M"
  },
  "year": 99,
  "word": "簡",
  "number": "1301",
  "jcheck": "2",
  "reason": "偽造文書",
  "content": "臺灣臺北地方法院刑事裁定              99年度簡字第1301號\n聲  請  人  臺灣臺北地方法院檢察署檢察官\n被      告  甲○○\n上列被告因偽造文書案件，本院於中華民國99年4月20日所為之\n判決之原本及其正本有誤寫，應裁定更正如下：\n    主  文\n原判決之原本及其正本當事人欄內關於「受處分人」之記載應更\n正為「被告」。\n    理  由\n一、按刑事判決文字，顯係誤寫，而不影響於全案情節與判決之\n    本旨者，參照民事訴訟法第232條規定，原審法院得以裁定\n    更正之，業經司法院大法官會議釋字第四三號解釋在案。\n二、本件原判決之原本及其正本當事人欄內關於「受處分人」甲\n    ○○，係「被告」甲○○之誤，此觀之同判決事實及理由欄\n    內所為甲○○身分之記載亦明。是前開「受處分人」之文字\n    顯係誤寫，而不影響於全案情節與判決本旨，茲更正之。\n三、依刑事訴訟法第220條，裁定如主文。\n中    華    民    國    99    年    5     月    12    日\n                 刑事第十一庭  法  官  劉方慈\n以上正本證明與原本無異\n如不服本裁定應於送達後5日內向本院提出抗告狀\n                               書記官  林妙穗\n中    華    民    國    99    年    5     月    12    日",
  "structure": {
    "main": "原判決之原本及其正本當事人欄內關於「受處分人」之記載應更\n正為「被告」。",
    "reason": "一、按刑事判決文字，顯係誤寫，而不影響於全案情節與判決之\n    本旨者，參照民事訴訟法第232條規定，原審法院得以裁定\n    更正之，業經司法院大法官會議釋字第四三號解釋在案。\n二、本件原判決之原本及其正本當事人欄內關於「受處分人」甲\n    ○○，係「被告」甲○○之誤，此觀之同判決事實及理由欄\n    內所為甲○○身分之記載亦明。是前開「受處分人」之文字\n    顯係誤寫，而不影響於全案情節與判決本旨，茲更正之。\n三、依刑事訴訟法第220條，裁定如主文。"
  },
  "characters": {
    "judges": [
      "劉方慈"
    ],
    "prosecutors": [

    ],
    "lawyers": [

    ],
    "clerks": [
      "林妙穗"
    ],
    "plaintiffs": [

    ],
    "defendants": [
      "甲○○"
    ],
    "prosecutor_office": [
      "臺灣臺北地方法院檢察署檢察官"
    ],
    "creditors": [

    ],
    "debtors": [

    ],
    "judicial_associate_officer": [

    ]
  },
  "adjudged_at": "2010-05-12",
  "created_at": "2016-01-05 12:04:35",
  "updated_at": "2016-01-05 12:04:35"
}