{
  "identify": "TPD-95-訴-6194-20100104-2",
  "court": {
    "name": "臺灣臺北地方法院",
    "code": "TPD"
  },
  "division": {
    "name": "民事",
    "code": "V"
  },
  "year": 95,
  "word": "訴",
  "number": "6194",
  "jcheck": "2",
  "reason": "損害賠償",
  "content": "臺灣臺北地方法院民事裁定              95年度訴字第6194號\n原      告  丁○○\n被      告  澤登有限公司\n法定代理人  甲○○\n被      告  戊○○\n兼上列二人\n訴訟代理人  乙○○\n被      告  丙○○原名馬芝霖.\n上列當事人間損害賠償事件，本院裁定如下：\n    主  文\n本院於民國九十六年十月二十二日所為停止訴訟程序之裁定撤銷\n。\n    理  由\n一、本院前以前開被告戊○○、乙○○、丙○○涉涉有詐欺罪嫌\n    ，經臺灣台北地方法院檢察署偵檢察官以96年度偵續一字第\n    171號偵查中，茲經兩造陳述上開刑事案件確有影響於本件\n    民事訴訟之裁判，經本院裁定命在刑事訴訟終結以前停止訴\n    訟程序。\n二、茲查明上開刑事案件業經提起公訴，並經本院以97年度易字\n    第814號、台灣高等法院98年上易字937號判決確定在案，有\n    上開判決書在卷可稽。\n三、依民事訴訟法第186條規定，裁定如主文。\n中    華    民    國    99    年    1     月    4     日\n                民事第五庭  審判長  法  官  薛中興\n                                    法  官  胡宏文\n                                    法  官  莊書雯\n以上正本係照原本作成\n如對本裁定抗告須於裁定送達後10日內向本院提出抗告狀，並繳\n納抗告費新臺幣1,000元\n中    華    民    國    99    年    1     月    5     日\n                                    書記官  謝梅琴",
  "structure": {
    "main": "本院於民國九十六年十月二十二日所為停止訴訟程序之裁定撤銷\n。",
    "reason": "一、本院前以前開被告戊○○、乙○○、丙○○涉涉有詐欺罪嫌\n    ，經臺灣台北地方法院檢察署偵檢察官以96年度偵續一字第\n    171號偵查中，茲經兩造陳述上開刑事案件確有影響於本件\n    民事訴訟之裁判，經本院裁定命在刑事訴訟終結以前停止訴\n    訟程序。\n二、茲查明上開刑事案件業經提起公訴，並經本院以97年度易字\n    第814號、台灣高等法院98年上易字937號判決確定在案，有\n    上開判決書在卷可稽。\n三、依民事訴訟法第186條規定，裁定如主文。"
  },
  "characters": {
    "judges": [
      "薛中興",
      "胡宏文",
      "莊書雯"
    ],
    "prosecutors": [

    ],
    "lawyers": [

    ],
    "clerks": [

    ],
    "plaintiffs": [
      "丁○○"
    ],
    "defendants": [
      "澤登有限公司",
      "戊○○",
      "兼上列二人",
      "丙○○原名馬芝霖."
    ],
    "prosecutor_office": [

    ],
    "creditors": [

    ],
    "debtors": [

    ],
    "judicial_associate_officer": [

    ]
  },
  "adjudged_at": "2010-01-04",
  "created_at": "2016-01-05 14:55:28",
  "updated_at": "2016-01-05 14:55:28"
}