{
  "identify": "TPD-99-易-1196-20100512-1",
  "court": {
    "name": "臺灣臺北地方法院",
    "code": "TPD"
  },
  "division": {
    "name": "刑事",
    "code": "M"
  },
  "year": 99,
  "word": "易",
  "number": "1196",
  "jcheck": "1",
  "reason": "詐欺",
  "content": "臺灣臺北地方法院刑事判決              99年度易字第1196號\n公  訴  人  臺灣臺北地方法院檢察署檢察官\n被      告  甲○○\n上列被告因詐欺案件，經檢察官提起公訴（99年度偵字第3760號\n），因被告於準備程序中為有罪之陳述，經本院裁定由受命法官\n獨任以簡式審判程序審理，本院判決如下：\n    主  文\n甲○○幫助犯詐欺取財罪，處拘役參拾日，如易科罰金，以新臺\n幣壹仟元折算壹日。\n    事實及理由\n一、本件犯罪事實及證明犯罪事實之證據方法並其證據均引用檢\n    察官起訴書之記載（如附件）。\n二、核被告甲○○所為，係幫助犯刑法第339條第1項詐欺取財罪\n    ，而依刑法第30條第2 項規定，幫助犯得減輕其刑。爰審酌\n    被告已坦承犯行，犯後態度尚佳，且斟酌本案所犯造成被害\n    人實際損害之程度等一切情狀，量處拘役30日，並依刑法第\n    41條第1項前段規定諭知得易科罰金併其折算標準。\n三、依刑事訴訟法第273條之1第1項、第299條第1項前段、第310\n    條之2、第454條第2項，刑法第30條、第339條第1 項、第41\n    條第1項前段、刑法施行法第1條之1，判決如主文。\n本案經檢察官林冠佑到庭執行職務。\n中    華    民    國    99    年    5     月    12    日\n                  刑事第四庭    法  官  呂政燁\n以上正本證明與原本無異。\n如不服本判決應於收受送達後10日內向本院提出上訴書狀，並應\n敘述具體理由；其未敘述上訴理由者，應於上訴期間屆滿後20日\n內向本院補提理由書（均須按他造當事人之人數附繕）「切勿逕\n送上級法院」。\n                                書記官  呂欣穎\n中    華    民    國    99    年    5     月    12    日\n附錄本案論罪科刑法條全文：\n中華民國刑法第339條（普通詐欺罪）\n意圖為自己或第三人不法之所有，以詐術使人將本人或第三人之\n物交付者，處 5 年以下有期徒刑、拘役或科或併科 1 千元以下\n罰金。\n以前項方法得財產上不法之利益或使第三人得之者，亦同。\n前二項之未遂犯罰之。",
  "structure": {
    "main": "甲○○幫助犯詐欺取財罪，處拘役參拾日，如易科罰金，以新臺\n幣壹仟元折算壹日。",
    "fact": "一、本件犯罪事實及證明犯罪事實之證據方法並其證據均引用檢\n    察官起訴書之記載（如附件）。\n二、核被告甲○○所為，係幫助犯刑法第339條第1項詐欺取財罪\n    ，而依刑法第30條第2 項規定，幫助犯得減輕其刑。爰審酌\n    被告已坦承犯行，犯後態度尚佳，且斟酌本案所犯造成被害\n    人實際損害之程度等一切情狀，量處拘役30日，並依刑法第\n    41條第1項前段規定諭知得易科罰金併其折算標準。\n三、依刑事訴訟法第273條之1第1項、第299條第1項前段、第310\n    條之2、第454條第2項，刑法第30條、第339條第1 項、第41\n    條第1項前段、刑法施行法第1條之1，判決如主文。\n本案經檢察官林冠佑到庭執行職務。",
    "reason": "一、本件犯罪事實及證明犯罪事實之證據方法並其證據均引用檢\n    察官起訴書之記載（如附件）。\n二、核被告甲○○所為，係幫助犯刑法第339條第1項詐欺取財罪\n    ，而依刑法第30條第2 項規定，幫助犯得減輕其刑。爰審酌\n    被告已坦承犯行，犯後態度尚佳，且斟酌本案所犯造成被害\n    人實際損害之程度等一切情狀，量處拘役30日，並依刑法第\n    41條第1項前段規定諭知得易科罰金併其折算標準。\n三、依刑事訴訟法第273條之1第1項、第299條第1項前段、第310\n    條之2、第454條第2項，刑法第30條、第339條第1 項、第41\n    條第1項前段、刑法施行法第1條之1，判決如主文。\n本案經檢察官林冠佑到庭執行職務。"
  },
  "characters": {
    "judges": [
      "呂政燁"
    ],
    "prosecutors": [
      "林冠佑"
    ],
    "lawyers": [

    ],
    "clerks": [
      "呂欣穎"
    ],
    "plaintiffs": [

    ],
    "defendants": [
      "甲○○"
    ],
    "prosecutor_office": [
      "臺灣臺北地方法院檢察署檢察官"
    ],
    "creditors": [

    ],
    "debtors": [

    ],
    "judicial_associate_officer": [

    ]
  },
  "adjudged_at": "2010-05-12",
  "created_at": "2016-01-05 12:04:49",
  "updated_at": "2016-01-05 12:04:49"
}