{
  "identify": "TPD-98-重訴-427-20100512-3",
  "court": {
    "name": "臺灣臺北地方法院",
    "code": "TPD"
  },
  "division": {
    "name": "民事",
    "code": "V"
  },
  "year": 98,
  "word": "重訴",
  "number": "427",
  "jcheck": "3",
  "reason": "不動產所有權移轉登記",
  "content": "臺灣臺北地方法院民事裁定             98年度重訴字第427號\n上  訴  人\n即  原  告  乙○○\n訴訟代理人  孫世群律師\n被上訴人\n即  被  告  甲○○\n訴訟代理人  鄭世脩律師\n上列當事人間請求不動產所有權移轉登記事件，上訴人對於民國\n九十九年二月九日本院第一審判決提起上訴，本院裁定如下：\n    主  文\n上訴駁回。\n第二審訴訟費用由上訴人負擔。\n    理  由\n一、按提起民事第二審上訴，應依民事訴訟法第七十七條之十六\n    第一項規定繳納裁判費，為必須具備之程式。\n二、本件上訴人提起第二審上訴，未據繳納裁判費，經本院於九\n    十九年四月十三日裁定命於送達後十日內補正，此項裁定已\n    於九十九年四月十九日送達，有送達證書在卷可稽。\n三、上訴人逾期迄今仍未補正，其上訴自非合法，應予駁回。\n四、依民事訴訟法第四百四十二條第二項、第九十五條、第七十\n    八條，裁定如主文。\n中    華    民    國    99    年    5     月    12    日\n                  民事第五庭    法  官  高偉文\n以上正本係照原本作成\n如不服本裁定應於送達後10日內向本院提出抗告狀，並繳納抗告\n費新臺幣1,000元\n中    華    民    國    99    年    5     月    12    日\n                                書記官  駱俊勳",
  "structure": {
    "main": "上訴駁回。\n第二審訴訟費用由上訴人負擔。",
    "reason": "一、按提起民事第二審上訴，應依民事訴訟法第七十七條之十六\n    第一項規定繳納裁判費，為必須具備之程式。\n二、本件上訴人提起第二審上訴，未據繳納裁判費，經本院於九\n    十九年四月十三日裁定命於送達後十日內補正，此項裁定已\n    於九十九年四月十九日送達，有送達證書在卷可稽。\n三、上訴人逾期迄今仍未補正，其上訴自非合法，應予駁回。\n四、依民事訴訟法第四百四十二條第二項、第九十五條、第七十\n    八條，裁定如主文。"
  },
  "characters": {
    "judges": [
      "高偉文"
    ],
    "prosecutors": [

    ],
    "lawyers": [
      "孫世群",
      "鄭世脩"
    ],
    "clerks": [

    ],
    "plaintiffs": [
      "乙"
    ],
    "defendants": [
      "甲"
    ],
    "prosecutor_office": [

    ],
    "creditors": [

    ],
    "debtors": [

    ],
    "judicial_associate_officer": [

    ]
  },
  "adjudged_at": "2010-05-12",
  "created_at": "2016-01-05 12:10:56",
  "updated_at": "2016-01-05 12:10:56"
}