{
  "identify": "TPH-99-聲-1242-20100512-1",
  "court": {
    "name": "臺灣高等法院",
    "code": "TPH"
  },
  "division": {
    "name": "刑事",
    "code": "M"
  },
  "year": 99,
  "word": "聲",
  "number": "1242",
  "jcheck": "1",
  "reason": "聲請定其應執行刑",
  "content": "臺灣高等法院刑事裁定                  99年度聲字第1242號\n聲  請  人  臺灣高等法院檢察署檢察官\n受  刑  人  甲○○\n上列聲請人因受刑人數罪併罰有二裁判以上，聲請定其應執行之\n刑（99年度執聲字第576 號），本院裁定如下：\n    主  文\n甲○○因犯如附表所示各罪，所處之刑，應執行有期徒刑拾柒年\n柒月。\n    理  由\n一、聲請意旨略以：受刑人甲○○因毒品危害防制條例等數罪，\n    先後判決確定如附表所示，應依刑法第53 條、第51 條第5\n    款定其應執行之刑，爰依刑事訴訟法第477 條第1 項聲請裁\n    定等語。\n二、本院查：受刑人甲○○因犯如附表所示各罪，經本院先後判\n    處如附表所示之刑，均經分別確定在案。茲檢察官聲請定其\n    應執行之刑，本院審核認聲請為正當，應定其應執行之刑。\n    爰依刑事訴訟法第477條第1項、第220條，刑法第53條，第\n    51 條第5款，裁定如主文。\n中    華    民    國    99    年    5    月    12    日\n                  刑事第九庭    審判長法  官  陳貽男\n                                      法  官  詹駿鴻\n                                      法  官  楊炳禎\n以上正本證明與原本無異。\n如不服本裁定，應於收受送達後五日內向本院提出抗告狀。\n                                      書記官  林月蓉\n中    華    民    國    99    年    5    月    13    日",
  "structure": {
    "main": "甲○○因犯如附表所示各罪，所處之刑，應執行有期徒刑拾柒年\n柒月。",
    "reason": "一、聲請意旨略以：受刑人甲○○因毒品危害防制條例等數罪，\n    先後判決確定如附表所示，應依刑法第53 條、第51 條第5\n    款定其應執行之刑，爰依刑事訴訟法第477 條第1 項聲請裁\n    定等語。\n二、本院查：受刑人甲○○因犯如附表所示各罪，經本院先後判\n    處如附表所示之刑，均經分別確定在案。茲檢察官聲請定其\n    應執行之刑，本院審核認聲請為正當，應定其應執行之刑。\n    爰依刑事訴訟法第477條第1項、第220條，刑法第53條，第\n    51 條第5款，裁定如主文。"
  },
  "characters": {
    "judges": [
      "陳貽男",
      "詹駿鴻",
      "楊炳禎"
    ],
    "prosecutors": [

    ],
    "lawyers": [

    ],
    "clerks": [
      "林月蓉"
    ],
    "plaintiffs": [

    ],
    "defendants": [

    ],
    "prosecutor_office": [
      "臺灣高等法院檢察署檢察官"
    ],
    "creditors": [

    ],
    "debtors": [

    ],
    "judicial_associate_officer": [

    ]
  },
  "adjudged_at": "2010-05-12",
  "created_at": "2016-01-05 11:53:55",
  "updated_at": "2016-01-05 11:53:55"
}