{
  "identify": "TPH-98-上-279-20100105-2",
  "court": {
    "name": "臺灣高等法院",
    "code": "TPH"
  },
  "division": {
    "name": "民事",
    "code": "V"
  },
  "year": 98,
  "word": "上",
  "number": "279",
  "jcheck": "2",
  "reason": "遷讓房屋",
  "content": "臺灣高等法院民事判決                   98年度上字第279號\n上  訴  人  甲○○\n            丙○○\n            丁○○\n共      同\n訴訟代理人  周燦雄律師\n            蔡炳楠律師\n被上訴人    乙○○\n                        號3樓\n訴訟代理人  曾郁智律師\n上列當事人間遷讓房屋事件，上訴人對於中華民國98年2月18日\n臺灣臺北地方法院97年度訴字第5491號第一審判決提起上訴，\n本院於98年12月29日言詞辯論終結，判決如下：\n    主  文\n原判決除確定部分外廢棄。\n上開廢棄部分，被上訴人在第一審之訴及該部分假執行之聲請均\n駁回。\n第一、二審訴訟費用除確定部分外，由被上訴人負擔。\n    事實及理由\n一、本件被上訴人主張：伊於民國68年間向時代大飯店股份有限\n    公司（下稱時代大飯店）購買位於臺北市中山區○○○路○\n    段108號9樓之8房屋（下稱系爭不動產），並於96年4月間完\n    成辦理過戶移轉登記；嗣因時代大飯店先前以系爭不動產向\n    合作金庫抵押之貸款未按時清償，使系爭不動產遭查封拍賣\n    ，惟並未賣出，上訴人丙○○與他人繼受合作金庫之債權，\n    為系爭不動產之抵押債權人，聲請執行拍賣無效後，竟於94\n    年11月1日將系爭不動產出租於上訴人甲○○及丁○○，再\n    於97年10月12日出租於原審共同被告高佩靖，上訴人甲○○\n    則於96年7月18日將系爭不動產轉租予原審共同被告賴正剛\n    。又上訴人丙○○於數年前已聲請臺灣臺北地方法院（下稱\n    臺北地院）查封執行拍賣系爭不動產在案，於此強制執行程\n    序中，無權藉口保全抵押物而逕自出租系爭不動產，上訴人\n    無權處分擅自出租系爭不動產，構成對伊所有權之損害。又\n    伊從未參加上訴人所謂「時代大廈套房業主代表會」，更遑\n    論同意由該代表會管理伊所有系爭不動產。上訴人丁○○、\n    甲○○非適法承租人，無權轉租系爭不動產；原審共同被告\n    賴正剛、高佩靖非適法承租人，均係無權占有系爭不動產等\n    情，爰依民法第767條之規定，求為命上訴人及原審共同被\n    告賴正剛、高佩靖應將系爭不動產全部遷空返還被上訴人之\n    判決（原審為被上訴人勝訴之判決，上訴人聲明不服，提起\n    上訴。原審共同被告賴正剛、高佩靖均未提起上訴，則該部\n    分已確定在案。是本件僅甲○○、丙○○、丁○○三人提起\n    上訴）。並答辯聲明：上訴駁回。\n二、上訴人則以：上訴人丙○○繼受合作金庫之債權而為系爭不\n    動產之抵押權人，並未有意圖為自己不法之利益。被上訴人\n    購買系爭不動產後，曾出具委託書委託時代大飯店向合作金\n    庫貸款，並提供時代大廈及919號土地為擔保設定抵押權。\n    惟時代大飯店之貸款未按時清償，被上訴人亦不願繳款，而\n    由「時代大廈套房業主代表會」所屬全體業主代償，合作金\n    庫將債權及抵押權移轉於業主代表會所指定之代表，並辦理\n    抵押權設定登記手續。85年間系爭不動產遭縱火毀損，上訴\n    人丙○○自88年起受時代大廈（嗣改名錦新大樓）管委會之\n    委託，為全體大樓業主之利益管理，已收取之租金抵付被上\n    訴人所積欠之代償合作金庫貸款、火災重建費用、大樓管理\n    費等。被上訴人既不還款、又疏於管理，上訴人丙○○為抵\n    押權人，出租管理系爭不動產係基於委任管理契約，為有權\n    占有。上訴人丙○○為業主代表與上訴人甲○○、丁○○間\n    所訂定之房屋租賃契約有效成立，上訴人甲○○為適法承租\n    人，有權占有及轉租。若要上訴人返還系爭不動產，被上訴\n    人應支付上訴人丙○○已支出之裝修費用、購買家具費用及\n    租金收入、所生利息等費用，何況系爭不動產現仍為法院查\n    封中，查封當時被上訴人不在場，執行法院將查封之該不動\n    產命上訴人甲○○保管占有，被上訴人不得任意排除變更執\n    行命令，上訴人並非無權占有等語，資為抗辯。並上訴聲明\n    ：(一)原判決關於上訴人部分廢棄。(二)上開廢棄部分，被上訴\n    人在第一審之訴及假執行之聲請均駁回。\n三、兩造不爭執事項：\n    系爭不動產（臺北市中山區○○○路○段108號9樓之8房屋\n    ）為被上訴人所有，現仍查封中。上訴人丙○○繼受合作金\n    庫對時代大飯店之債權而為系爭不動產之抵押權人，該抵押\n    權之債務人及設定義務人均為時代大飯店等事實，為兩造所\n    不爭執（見本院卷第62頁之筆錄、第63頁之書狀），且有系\n    爭不動產買賣所有權移轉契約書、建物所有權狀、建物登記\n    謄本、本院檢察署97年度上聲議字第1283號處分書、房屋稅\n    單可證（見原審補字卷第7頁至第18頁），固堪信為真實。\n四、本件經依民事訴訟法第463條準用同法第270條之1第1項第3\n    款規定，整理爭點並協議簡化爭點後，兩造同意就本院98年\n    7月13日準備程序中，兩造協議簡化之爭點為辯論範圍（見\n    本院卷第73頁之筆錄）。茲就兩造之爭執點及本院判斷，分\n    述如下：\n    (一)經查，時代大飯店抵押之貸款未能按時清償，業主（被上\n      訴人亦為業主之一）亦不願繳款，而由「時代大廈套房業\n      主代表會」所屬業主代表代償，合作金庫遂將債權及抵押\n      權移轉於業主代表會所指定之代表（上訴人丙○○為代表\n      之一），並辦理抵押權移轉登記手續等情，有該函文可考\n      （見本院卷第27頁之函文）。再參以錦新大樓（原時代大\n      廈）業主代表會曾於88年12月1日出具委託管理契約，該\n      契約內容為：「查時代大廈（嗣經改名錦新大樓）套房業\n      主代表，於七十二年間因代償附表所列業主應負擔之物保\n      範圍，而取得彼等所購套房之抵押權，並成立代表會（下\n      稱本會）。由於該等業主既不還款，又疏於套房之管理，\n      且歷經災變，房屋受損，為維護抵押權人權益，對於附表\n      所列套房，亟需維修管理，茲經本會委員協商，同意委由\n      丙○○先生管理，並以租金收入，優先抵付管理維修及相\n      關費用，恐口無憑，特立此契約為據。」而附表業主列有\n      被上訴人「乙○○」之姓名（見本院卷第25頁之契約及第\n      26頁之附表）。且上訴人丙○○繼受合作金庫對時代大飯\n      店之債權而為系爭不動產之抵押權人，該抵押權之債務人\n      及設定義務人均為時代大飯店之事實，為兩造所不爭執。\n      是上訴人辯稱於85年間系爭不動產遭縱火毀損，上訴人丙\n      ○○自88年起受時代大廈（嗣改名錦新大樓）管委會之委\n      託，為全體大樓業主之利益管理，以收取之租金抵付被上\n      訴人所積欠之代償合作金庫貸款、火災重建費用、大樓管\n      理費等語，自屬可採。\n    (二)又上訴人辯稱「時代大廈套房業主代表會」（下稱代表會\n      ）於受讓上開債權及抵押權後，即委託孫建揚律師發函包\n      括被上訴人在內之17戶套房業主催告償還所欠債務本息（\n      見本院卷第41頁之存證信函），詎彼等均置之不理，代表\n      會逼不得已，乃聲請拍賣抵押物求償，經臺北地院以74年\n      度民執地字第6097號強制執行，原已由債權人聲明承受，\n      嗣因承受爭議，纏訟多年，於85年間，改以85年度執地字\n      第6097號續行拍賣，又於同年重新分案改為85年度民執更\n      一荒字第23號，其間一度為試行和解而撤回，因和解不成\n      ，又於90年11月間聲請強制執行，先以90年度民執平字第\n      24669號進行，嗣又改以95年度執更一字第11號（未股）\n      繼續查封執行，迄今仍未結案等情，被上訴人亦未爭執，\n      且經本院調取該執行卷，經核閱屬實。再參以被上訴人曾\n      對上訴人丙○○、甲○○提出竊占之告訴，經本院檢察署\n      以97年度上聲議字第1283號處分書，駁回被上訴人之再議\n      ；該處分書認定：「…卷查，觀之被告（即上訴人丙○○\n      、甲○○）所提出之房屋租賃契約書、主任委員丙○○函\n      及錦新大樓管理委員會函各2份、委託管理契約、合庫函\n      等等卷附資料，足見被告丙○○係受錦新大樓管理委員會\n      之委託，為全體大樓業主之利益管理包含聲請人（即被上\n      訴人，下同）在內之15戶套房，以租金收益抵付聲請人所\n      積欠之代償合庫貸款、火災重建費用、大樓管理費等；被\n      告甲○○則係基於與被告丙○○之租賃關係，合法承租該\n      15戶受託管理之套房等情無訛。又聲請人代理人於原署亦\n      陳稱聲請人長年旅居國外，被告丙○○係民法上無因管理\n      ，聲請人亦很感激，聲請人本無意提出刑事告訴，係因聲\n      請人於96年8月10日會同警察要進入系爭聲請人所有之套\n      房遭被告甲○○出面阻止，因而提出刑事告訴，以促使被\n      告2人出面解決，聲請人亦希望和解處理等語。…」等情\n      （見原審補字卷第16、17頁之處分書）。足見上訴人丙○\n      ○係受時代大飯店（即錦新大樓）管理委員會委託，為全\n      體大樓業主之利益管理包含被上訴人在內之套房業主，以\n      租金收益抵付業主所積欠之代償合作金庫貸款、火災重建\n      費用、大樓管理費等；而上訴人甲○○、丁○○則係基於\n      與上訴人丙○○之租賃關係，合法承租受託管理之套房。\n    (三)又系爭不動產自查封後，執行法院即經由債權人同意交由\n      上訴人甲○○負責保管，且該執行案尚未執行完畢，目前\n      系爭不動產仍在查封中，亦為兩造所不爭執（見本院卷第\n      106頁之筆錄），且經本院調取該查封卷，經核屬實，有\n      查封筆錄可考（見本院卷第102、103頁之筆錄），足見被\n      上訴人對系爭不動產並無管理使用權限；而上訴人丙○○\n      自始即代表債權人管理該房屋，則其將系爭不動產出租予\n      上訴人甲○○及丁○○，執行法院將查封物交由上訴人甲\n      ○○保管，上訴人等人自屬有權占有系爭不動產，而非無\n      權占有（本院95年度上字第1039號、最高法院96年度台上\n      字第1825號裁判參照）。是上訴人辯稱上訴人丙○○代表\n      業主代表會出面處理後續重建事宜，並以系爭不動產租金\n      收益抵付被上訴人所積欠之代償貸款、火災重建費用，而\n      出租予上訴人甲○○、丁○○，自屬可信。又債務人之不\n      動產經查封，並交由他人保管中，在啟封前，債務人已不\n      得任意取回管理處分。是被上訴人主張上訴人無權占有系\n      爭不動產，自不足取。從而，被上訴人請求上訴人將系爭\n      不動產全部遷空返還被上訴人，自屬無據。\n五、綜上所述，被上訴人訴請上訴人將系爭不動產全部遷空返還\n    被上訴人部分，非屬正當，自屬不應准許。從而原審就此部\n    分所為上訴人敗訴之判決，自有未洽，上訴論旨指摘原判決\n    此部分不當，求予廢棄改判，為有理由。\n六、兩造其餘之攻擊或防禦方法及所用之證據，經本院斟酌後，\n    認為均不足以影響本判決之結果，無庸逐一論列。\n七、據上論結，本件上訴為有理由，依民事訴訟法第450條、第\n    78 條，判決如主文。\n中    華    民    國    99    年     1    月     5     日\n                    民事第十六庭\n                        審判長法  官  王聖惠\n                              法  官  邱瑞祥\n                              法  官  呂淑玲\n正本係照原本作成。\n被上訴人如不服本判決，應於收受送達後20日內向本院提出上訴\n書狀，其未表明上訴理由者，應於提出上訴後20日內向本院補提\n理由書狀（均須按他造當事人之人數附繕本）上訴時應提出委任\n律師或具有律師資格之人之委任狀；委任有律師資格者，另應附\n具律師資格證書及釋明委任人與受任人有民事訴訟法第466條之1\n第1項但書或第2項（詳附註）所定關係之釋明文書影本。\n中    華    民    國    99    年    1     月    5     日\n                              書記官  詹麗珠\n附註：\n民事訴訟法第466條之1（第1項、第2項）：\n對於第二審判決上訴，上訴人應委任律師為訴訟代理人。但上訴\n人或其他法定代理人具有律師資格者，不在此限。\n上訴人之配偶、三親等內之血親、二親等內之姻親，或上訴人為\n法人、中央或地方機關時，其所屬專任人員具有律師資格並經法\n院認為適當者，亦得為第三審訴訟代理人。",
  "structure": {
    "main": "原判決除確定部分外廢棄。\n上開廢棄部分，被上訴人在第一審之訴及該部分假執行之聲請均\n駁回。\n第一、二審訴訟費用除確定部分外，由被上訴人負擔。",
    "fact": "一、本件被上訴人主張：伊於民國68年間向時代大飯店股份有限\n    公司（下稱時代大飯店）購買位於臺北市中山區○○○路○\n    段108號9樓之8房屋（下稱系爭不動產），並於96年4月間完\n    成辦理過戶移轉登記；嗣因時代大飯店先前以系爭不動產向\n    合作金庫抵押之貸款未按時清償，使系爭不動產遭查封拍賣\n    ，惟並未賣出，上訴人丙○○與他人繼受合作金庫之債權，\n    為系爭不動產之抵押債權人，聲請執行拍賣無效後，竟於94\n    年11月1日將系爭不動產出租於上訴人甲○○及丁○○，再\n    於97年10月12日出租於原審共同被告高佩靖，上訴人甲○○\n    則於96年7月18日將系爭不動產轉租予原審共同被告賴正剛\n    。又上訴人丙○○於數年前已聲請臺灣臺北地方法院（下稱\n    臺北地院）查封執行拍賣系爭不動產在案，於此強制執行程\n    序中，無權藉口保全抵押物而逕自出租系爭不動產，上訴人\n    無權處分擅自出租系爭不動產，構成對伊所有權之損害。又\n    伊從未參加上訴人所謂「時代大廈套房業主代表會」，更遑\n    論同意由該代表會管理伊所有系爭不動產。上訴人丁○○、\n    甲○○非適法承租人，無權轉租系爭不動產；原審共同被告\n    賴正剛、高佩靖非適法承租人，均係無權占有系爭不動產等\n    情，爰依民法第767條之規定，求為命上訴人及原審共同被\n    告賴正剛、高佩靖應將系爭不動產全部遷空返還被上訴人之\n    判決（原審為被上訴人勝訴之判決，上訴人聲明不服，提起\n    上訴。原審共同被告賴正剛、高佩靖均未提起上訴，則該部\n    分已確定在案。是本件僅甲○○、丙○○、丁○○三人提起\n    上訴）。並答辯聲明：上訴駁回。\n二、上訴人則以：上訴人丙○○繼受合作金庫之債權而為系爭不\n    動產之抵押權人，並未有意圖為自己不法之利益。被上訴人\n    購買系爭不動產後，曾出具委託書委託時代大飯店向合作金\n    庫貸款，並提供時代大廈及919號土地為擔保設定抵押權。\n    惟時代大飯店之貸款未按時清償，被上訴人亦不願繳款，而\n    由「時代大廈套房業主代表會」所屬全體業主代償，合作金\n    庫將債權及抵押權移轉於業主代表會所指定之代表，並辦理\n    抵押權設定登記手續。85年間系爭不動產遭縱火毀損，上訴\n    人丙○○自88年起受時代大廈（嗣改名錦新大樓）管委會之\n    委託，為全體大樓業主之利益管理，已收取之租金抵付被上\n    訴人所積欠之代償合作金庫貸款、火災重建費用、大樓管理\n    費等。被上訴人既不還款、又疏於管理，上訴人丙○○為抵\n    押權人，出租管理系爭不動產係基於委任管理契約，為有權\n    占有。上訴人丙○○為業主代表與上訴人甲○○、丁○○間\n    所訂定之房屋租賃契約有效成立，上訴人甲○○為適法承租\n    人，有權占有及轉租。若要上訴人返還系爭不動產，被上訴\n    人應支付上訴人丙○○已支出之裝修費用、購買家具費用及\n    租金收入、所生利息等費用，何況系爭不動產現仍為法院查\n    封中，查封當時被上訴人不在場，執行法院將查封之該不動\n    產命上訴人甲○○保管占有，被上訴人不得任意排除變更執\n    行命令，上訴人並非無權占有等語，資為抗辯。並上訴聲明\n    ：(一)原判決關於上訴人部分廢棄。(二)上開廢棄部分，被上訴\n    人在第一審之訴及假執行之聲請均駁回。\n三、兩造不爭執事項：\n    系爭不動產（臺北市中山區○○○路○段108號9樓之8房屋\n    ）為被上訴人所有，現仍查封中。上訴人丙○○繼受合作金\n    庫對時代大飯店之債權而為系爭不動產之抵押權人，該抵押\n    權之債務人及設定義務人均為時代大飯店等事實，為兩造所\n    不爭執（見本院卷第62頁之筆錄、第63頁之書狀），且有系\n    爭不動產買賣所有權移轉契約書、建物所有權狀、建物登記\n    謄本、本院檢察署97年度上聲議字第1283號處分書、房屋稅\n    單可證（見原審補字卷第7頁至第18頁），固堪信為真實。\n四、本件經依民事訴訟法第463條準用同法第270條之1第1項第3\n    款規定，整理爭點並協議簡化爭點後，兩造同意就本院98年\n    7月13日準備程序中，兩造協議簡化之爭點為辯論範圍（見\n    本院卷第73頁之筆錄）。茲就兩造之爭執點及本院判斷，分\n    述如下：\n    (一)經查，時代大飯店抵押之貸款未能按時清償，業主（被上\n      訴人亦為業主之一）亦不願繳款，而由「時代大廈套房業\n      主代表會」所屬業主代表代償，合作金庫遂將債權及抵押\n      權移轉於業主代表會所指定之代表（上訴人丙○○為代表\n      之一），並辦理抵押權移轉登記手續等情，有該函文可考\n      （見本院卷第27頁之函文）。再參以錦新大樓（原時代大\n      廈）業主代表會曾於88年12月1日出具委託管理契約，該\n      契約內容為：「查時代大廈（嗣經改名錦新大樓）套房業\n      主代表，於七十二年間因代償附表所列業主應負擔之物保\n      範圍，而取得彼等所購套房之抵押權，並成立代表會（下\n      稱本會）。由於該等業主既不還款，又疏於套房之管理，\n      且歷經災變，房屋受損，為維護抵押權人權益，對於附表\n      所列套房，亟需維修管理，茲經本會委員協商，同意委由\n      丙○○先生管理，並以租金收入，優先抵付管理維修及相\n      關費用，恐口無憑，特立此契約為據。」而附表業主列有\n      被上訴人「乙○○」之姓名（見本院卷第25頁之契約及第\n      26頁之附表）。且上訴人丙○○繼受合作金庫對時代大飯\n      店之債權而為系爭不動產之抵押權人，該抵押權之債務人\n      及設定義務人均為時代大飯店之事實，為兩造所不爭執。\n      是上訴人辯稱於85年間系爭不動產遭縱火毀損，上訴人丙\n      ○○自88年起受時代大廈（嗣改名錦新大樓）管委會之委\n      託，為全體大樓業主之利益管理，以收取之租金抵付被上\n      訴人所積欠之代償合作金庫貸款、火災重建費用、大樓管\n      理費等語，自屬可採。\n    (二)又上訴人辯稱「時代大廈套房業主代表會」（下稱代表會\n      ）於受讓上開債權及抵押權後，即委託孫建揚律師發函包\n      括被上訴人在內之17戶套房業主催告償還所欠債務本息（\n      見本院卷第41頁之存證信函），詎彼等均置之不理，代表\n      會逼不得已，乃聲請拍賣抵押物求償，經臺北地院以74年\n      度民執地字第6097號強制執行，原已由債權人聲明承受，\n      嗣因承受爭議，纏訟多年，於85年間，改以85年度執地字\n      第6097號續行拍賣，又於同年重新分案改為85年度民執更\n      一荒字第23號，其間一度為試行和解而撤回，因和解不成\n      ，又於90年11月間聲請強制執行，先以90年度民執平字第\n      24669號進行，嗣又改以95年度執更一字第11號（未股）\n      繼續查封執行，迄今仍未結案等情，被上訴人亦未爭執，\n      且經本院調取該執行卷，經核閱屬實。再參以被上訴人曾\n      對上訴人丙○○、甲○○提出竊占之告訴，經本院檢察署\n      以97年度上聲議字第1283號處分書，駁回被上訴人之再議\n      ；該處分書認定：「…卷查，觀之被告（即上訴人丙○○\n      、甲○○）所提出之房屋租賃契約書、主任委員丙○○函\n      及錦新大樓管理委員會函各2份、委託管理契約、合庫函\n      等等卷附資料，足見被告丙○○係受錦新大樓管理委員會\n      之委託，為全體大樓業主之利益管理包含聲請人（即被上\n      訴人，下同）在內之15戶套房，以租金收益抵付聲請人所\n      積欠之代償合庫貸款、火災重建費用、大樓管理費等；被\n      告甲○○則係基於與被告丙○○之租賃關係，合法承租該\n      15戶受託管理之套房等情無訛。又聲請人代理人於原署亦\n      陳稱聲請人長年旅居國外，被告丙○○係民法上無因管理\n      ，聲請人亦很感激，聲請人本無意提出刑事告訴，係因聲\n      請人於96年8月10日會同警察要進入系爭聲請人所有之套\n      房遭被告甲○○出面阻止，因而提出刑事告訴，以促使被\n      告2人出面解決，聲請人亦希望和解處理等語。…」等情\n      （見原審補字卷第16、17頁之處分書）。足見上訴人丙○\n      ○係受時代大飯店（即錦新大樓）管理委員會委託，為全\n      體大樓業主之利益管理包含被上訴人在內之套房業主，以\n      租金收益抵付業主所積欠之代償合作金庫貸款、火災重建\n      費用、大樓管理費等；而上訴人甲○○、丁○○則係基於\n      與上訴人丙○○之租賃關係，合法承租受託管理之套房。\n    (三)又系爭不動產自查封後，執行法院即經由債權人同意交由\n      上訴人甲○○負責保管，且該執行案尚未執行完畢，目前\n      系爭不動產仍在查封中，亦為兩造所不爭執（見本院卷第\n      106頁之筆錄），且經本院調取該查封卷，經核屬實，有\n      查封筆錄可考（見本院卷第102、103頁之筆錄），足見被\n      上訴人對系爭不動產並無管理使用權限；而上訴人丙○○\n      自始即代表債權人管理該房屋，則其將系爭不動產出租予\n      上訴人甲○○及丁○○，執行法院將查封物交由上訴人甲\n      ○○保管，上訴人等人自屬有權占有系爭不動產，而非無\n      權占有（本院95年度上字第1039號、最高法院96年度台上\n      字第1825號裁判參照）。是上訴人辯稱上訴人丙○○代表\n      業主代表會出面處理後續重建事宜，並以系爭不動產租金\n      收益抵付被上訴人所積欠之代償貸款、火災重建費用，而\n      出租予上訴人甲○○、丁○○，自屬可信。又債務人之不\n      動產經查封，並交由他人保管中，在啟封前，債務人已不\n      得任意取回管理處分。是被上訴人主張上訴人無權占有系\n      爭不動產，自不足取。從而，被上訴人請求上訴人將系爭\n      不動產全部遷空返還被上訴人，自屬無據。\n五、綜上所述，被上訴人訴請上訴人將系爭不動產全部遷空返還\n    被上訴人部分，非屬正當，自屬不應准許。從而原審就此部\n    分所為上訴人敗訴之判決，自有未洽，上訴論旨指摘原判決\n    此部分不當，求予廢棄改判，為有理由。\n六、兩造其餘之攻擊或防禦方法及所用之證據，經本院斟酌後，\n    認為均不足以影響本判決之結果，無庸逐一論列。\n七、據上論結，本件上訴為有理由，依民事訴訟法第450條、第\n    78 條，判決如主文。",
    "reason": "一、本件被上訴人主張：伊於民國68年間向時代大飯店股份有限\n    公司（下稱時代大飯店）購買位於臺北市中山區○○○路○\n    段108號9樓之8房屋（下稱系爭不動產），並於96年4月間完\n    成辦理過戶移轉登記；嗣因時代大飯店先前以系爭不動產向\n    合作金庫抵押之貸款未按時清償，使系爭不動產遭查封拍賣\n    ，惟並未賣出，上訴人丙○○與他人繼受合作金庫之債權，\n    為系爭不動產之抵押債權人，聲請執行拍賣無效後，竟於94\n    年11月1日將系爭不動產出租於上訴人甲○○及丁○○，再\n    於97年10月12日出租於原審共同被告高佩靖，上訴人甲○○\n    則於96年7月18日將系爭不動產轉租予原審共同被告賴正剛\n    。又上訴人丙○○於數年前已聲請臺灣臺北地方法院（下稱\n    臺北地院）查封執行拍賣系爭不動產在案，於此強制執行程\n    序中，無權藉口保全抵押物而逕自出租系爭不動產，上訴人\n    無權處分擅自出租系爭不動產，構成對伊所有權之損害。又\n    伊從未參加上訴人所謂「時代大廈套房業主代表會」，更遑\n    論同意由該代表會管理伊所有系爭不動產。上訴人丁○○、\n    甲○○非適法承租人，無權轉租系爭不動產；原審共同被告\n    賴正剛、高佩靖非適法承租人，均係無權占有系爭不動產等\n    情，爰依民法第767條之規定，求為命上訴人及原審共同被\n    告賴正剛、高佩靖應將系爭不動產全部遷空返還被上訴人之\n    判決（原審為被上訴人勝訴之判決，上訴人聲明不服，提起\n    上訴。原審共同被告賴正剛、高佩靖均未提起上訴，則該部\n    分已確定在案。是本件僅甲○○、丙○○、丁○○三人提起\n    上訴）。並答辯聲明：上訴駁回。\n二、上訴人則以：上訴人丙○○繼受合作金庫之債權而為系爭不\n    動產之抵押權人，並未有意圖為自己不法之利益。被上訴人\n    購買系爭不動產後，曾出具委託書委託時代大飯店向合作金\n    庫貸款，並提供時代大廈及919號土地為擔保設定抵押權。\n    惟時代大飯店之貸款未按時清償，被上訴人亦不願繳款，而\n    由「時代大廈套房業主代表會」所屬全體業主代償，合作金\n    庫將債權及抵押權移轉於業主代表會所指定之代表，並辦理\n    抵押權設定登記手續。85年間系爭不動產遭縱火毀損，上訴\n    人丙○○自88年起受時代大廈（嗣改名錦新大樓）管委會之\n    委託，為全體大樓業主之利益管理，已收取之租金抵付被上\n    訴人所積欠之代償合作金庫貸款、火災重建費用、大樓管理\n    費等。被上訴人既不還款、又疏於管理，上訴人丙○○為抵\n    押權人，出租管理系爭不動產係基於委任管理契約，為有權\n    占有。上訴人丙○○為業主代表與上訴人甲○○、丁○○間\n    所訂定之房屋租賃契約有效成立，上訴人甲○○為適法承租\n    人，有權占有及轉租。若要上訴人返還系爭不動產，被上訴\n    人應支付上訴人丙○○已支出之裝修費用、購買家具費用及\n    租金收入、所生利息等費用，何況系爭不動產現仍為法院查\n    封中，查封當時被上訴人不在場，執行法院將查封之該不動\n    產命上訴人甲○○保管占有，被上訴人不得任意排除變更執\n    行命令，上訴人並非無權占有等語，資為抗辯。並上訴聲明\n    ：(一)原判決關於上訴人部分廢棄。(二)上開廢棄部分，被上訴\n    人在第一審之訴及假執行之聲請均駁回。\n三、兩造不爭執事項：\n    系爭不動產（臺北市中山區○○○路○段108號9樓之8房屋\n    ）為被上訴人所有，現仍查封中。上訴人丙○○繼受合作金\n    庫對時代大飯店之債權而為系爭不動產之抵押權人，該抵押\n    權之債務人及設定義務人均為時代大飯店等事實，為兩造所\n    不爭執（見本院卷第62頁之筆錄、第63頁之書狀），且有系\n    爭不動產買賣所有權移轉契約書、建物所有權狀、建物登記\n    謄本、本院檢察署97年度上聲議字第1283號處分書、房屋稅\n    單可證（見原審補字卷第7頁至第18頁），固堪信為真實。\n四、本件經依民事訴訟法第463條準用同法第270條之1第1項第3\n    款規定，整理爭點並協議簡化爭點後，兩造同意就本院98年\n    7月13日準備程序中，兩造協議簡化之爭點為辯論範圍（見\n    本院卷第73頁之筆錄）。茲就兩造之爭執點及本院判斷，分\n    述如下：\n    (一)經查，時代大飯店抵押之貸款未能按時清償，業主（被上\n      訴人亦為業主之一）亦不願繳款，而由「時代大廈套房業\n      主代表會」所屬業主代表代償，合作金庫遂將債權及抵押\n      權移轉於業主代表會所指定之代表（上訴人丙○○為代表\n      之一），並辦理抵押權移轉登記手續等情，有該函文可考\n      （見本院卷第27頁之函文）。再參以錦新大樓（原時代大\n      廈）業主代表會曾於88年12月1日出具委託管理契約，該\n      契約內容為：「查時代大廈（嗣經改名錦新大樓）套房業\n      主代表，於七十二年間因代償附表所列業主應負擔之物保\n      範圍，而取得彼等所購套房之抵押權，並成立代表會（下\n      稱本會）。由於該等業主既不還款，又疏於套房之管理，\n      且歷經災變，房屋受損，為維護抵押權人權益，對於附表\n      所列套房，亟需維修管理，茲經本會委員協商，同意委由\n      丙○○先生管理，並以租金收入，優先抵付管理維修及相\n      關費用，恐口無憑，特立此契約為據。」而附表業主列有\n      被上訴人「乙○○」之姓名（見本院卷第25頁之契約及第\n      26頁之附表）。且上訴人丙○○繼受合作金庫對時代大飯\n      店之債權而為系爭不動產之抵押權人，該抵押權之債務人\n      及設定義務人均為時代大飯店之事實，為兩造所不爭執。\n      是上訴人辯稱於85年間系爭不動產遭縱火毀損，上訴人丙\n      ○○自88年起受時代大廈（嗣改名錦新大樓）管委會之委\n      託，為全體大樓業主之利益管理，以收取之租金抵付被上\n      訴人所積欠之代償合作金庫貸款、火災重建費用、大樓管\n      理費等語，自屬可採。\n    (二)又上訴人辯稱「時代大廈套房業主代表會」（下稱代表會\n      ）於受讓上開債權及抵押權後，即委託孫建揚律師發函包\n      括被上訴人在內之17戶套房業主催告償還所欠債務本息（\n      見本院卷第41頁之存證信函），詎彼等均置之不理，代表\n      會逼不得已，乃聲請拍賣抵押物求償，經臺北地院以74年\n      度民執地字第6097號強制執行，原已由債權人聲明承受，\n      嗣因承受爭議，纏訟多年，於85年間，改以85年度執地字\n      第6097號續行拍賣，又於同年重新分案改為85年度民執更\n      一荒字第23號，其間一度為試行和解而撤回，因和解不成\n      ，又於90年11月間聲請強制執行，先以90年度民執平字第\n      24669號進行，嗣又改以95年度執更一字第11號（未股）\n      繼續查封執行，迄今仍未結案等情，被上訴人亦未爭執，\n      且經本院調取該執行卷，經核閱屬實。再參以被上訴人曾\n      對上訴人丙○○、甲○○提出竊占之告訴，經本院檢察署\n      以97年度上聲議字第1283號處分書，駁回被上訴人之再議\n      ；該處分書認定：「…卷查，觀之被告（即上訴人丙○○\n      、甲○○）所提出之房屋租賃契約書、主任委員丙○○函\n      及錦新大樓管理委員會函各2份、委託管理契約、合庫函\n      等等卷附資料，足見被告丙○○係受錦新大樓管理委員會\n      之委託，為全體大樓業主之利益管理包含聲請人（即被上\n      訴人，下同）在內之15戶套房，以租金收益抵付聲請人所\n      積欠之代償合庫貸款、火災重建費用、大樓管理費等；被\n      告甲○○則係基於與被告丙○○之租賃關係，合法承租該\n      15戶受託管理之套房等情無訛。又聲請人代理人於原署亦\n      陳稱聲請人長年旅居國外，被告丙○○係民法上無因管理\n      ，聲請人亦很感激，聲請人本無意提出刑事告訴，係因聲\n      請人於96年8月10日會同警察要進入系爭聲請人所有之套\n      房遭被告甲○○出面阻止，因而提出刑事告訴，以促使被\n      告2人出面解決，聲請人亦希望和解處理等語。…」等情\n      （見原審補字卷第16、17頁之處分書）。足見上訴人丙○\n      ○係受時代大飯店（即錦新大樓）管理委員會委託，為全\n      體大樓業主之利益管理包含被上訴人在內之套房業主，以\n      租金收益抵付業主所積欠之代償合作金庫貸款、火災重建\n      費用、大樓管理費等；而上訴人甲○○、丁○○則係基於\n      與上訴人丙○○之租賃關係，合法承租受託管理之套房。\n    (三)又系爭不動產自查封後，執行法院即經由債權人同意交由\n      上訴人甲○○負責保管，且該執行案尚未執行完畢，目前\n      系爭不動產仍在查封中，亦為兩造所不爭執（見本院卷第\n      106頁之筆錄），且經本院調取該查封卷，經核屬實，有\n      查封筆錄可考（見本院卷第102、103頁之筆錄），足見被\n      上訴人對系爭不動產並無管理使用權限；而上訴人丙○○\n      自始即代表債權人管理該房屋，則其將系爭不動產出租予\n      上訴人甲○○及丁○○，執行法院將查封物交由上訴人甲\n      ○○保管，上訴人等人自屬有權占有系爭不動產，而非無\n      權占有（本院95年度上字第1039號、最高法院96年度台上\n      字第1825號裁判參照）。是上訴人辯稱上訴人丙○○代表\n      業主代表會出面處理後續重建事宜，並以系爭不動產租金\n      收益抵付被上訴人所積欠之代償貸款、火災重建費用，而\n      出租予上訴人甲○○、丁○○，自屬可信。又債務人之不\n      動產經查封，並交由他人保管中，在啟封前，債務人已不\n      得任意取回管理處分。是被上訴人主張上訴人無權占有系\n      爭不動產，自不足取。從而，被上訴人請求上訴人將系爭\n      不動產全部遷空返還被上訴人，自屬無據。\n五、綜上所述，被上訴人訴請上訴人將系爭不動產全部遷空返還\n    被上訴人部分，非屬正當，自屬不應准許。從而原審就此部\n    分所為上訴人敗訴之判決，自有未洽，上訴論旨指摘原判決\n    此部分不當，求予廢棄改判，為有理由。\n六、兩造其餘之攻擊或防禦方法及所用之證據，經本院斟酌後，\n    認為均不足以影響本判決之結果，無庸逐一論列。\n七、據上論結，本件上訴為有理由，依民事訴訟法第450條、第\n    78 條，判決如主文。"
  },
  "characters": {
    "judges": [
      "王聖惠",
      "邱瑞祥",
      "呂淑玲"
    ],
    "prosecutors": [

    ],
    "lawyers": [
      "周燦雄",
      "蔡炳楠",
      "曾郁智",
      "律師或具有",
      "具",
      "人或其他法定代理人具有"
    ],
    "clerks": [
      "詹麗珠"
    ],
    "plaintiffs": [

    ],
    "defendants": [

    ],
    "prosecutor_office": [

    ],
    "creditors": [

    ],
    "debtors": [

    ],
    "judicial_associate_officer": [

    ]
  },
  "adjudged_at": "2010-01-05",
  "created_at": "2016-01-05 15:02:26",
  "updated_at": "2016-01-05 15:02:26"
}