{
  "identify": "TPH-98-上更(一)-597-20100512-3",
  "court": {
    "name": "臺灣高等法院",
    "code": "TPH"
  },
  "division": {
    "name": "刑事",
    "code": "M"
  },
  "year": 98,
  "word": "上更(一)",
  "number": "597",
  "jcheck": "3",
  "reason": "毒品危害防制條例",
  "content": "臺灣高等法院刑事裁定             98年度上更(一)字第597號\n上  訴  人\n即  被  告  甲○○\n指定辯護人  法律扶助舒建中律師\n上列被告因毒品危害防制條例上訴案件，本院裁定如下：\n    主  文\n甲○○羈押期間自民國九十九年五月二十四日起延長二月。\n    理  由\n一、上訴人即被告甲○○前經本院認為犯毒品危害防制條例第 4\n    條第1 項之販賣第一級毒品罪，犯罪嫌疑重大，所犯為最輕\n    本刑為五年以上有期徒刑之罪，且有逃亡之虞，有刑事訴訟\n    法第101條第1項第1款、第3款之情形，非予羈押，顯難進行\n    審判或執行，於民國98年12 月24日起執行羈押，並自99年3\n    月24日延長羈押二月，至99 年5月23日止羈押期間即將屆滿\n    。\n二、茲本院以前項原因依然存在，認有繼續羈押之必要，應自99\n    年5月24日起延長羈押二月。\n三、依刑事訴訟法第108條第1項、第5項，裁定如主文。\n中    華    民    國    99    年    5     月    12    日\n                  刑事第二十庭審判長法  官  楊貴雄\n                                    法  官  許必奇\n                                    法  官  周明鴻\n以上正本證明與原本無異。\n如不服本裁定，應於收受送達後五日內向本院提出抗告狀。\n                                    書記官  郭彥琪\n中    華    民    國    99    年    5     月    12    日",
  "structure": {
    "main": "甲○○羈押期間自民國九十九年五月二十四日起延長二月。",
    "reason": "一、上訴人即被告甲○○前經本院認為犯毒品危害防制條例第 4\n    條第1 項之販賣第一級毒品罪，犯罪嫌疑重大，所犯為最輕\n    本刑為五年以上有期徒刑之罪，且有逃亡之虞，有刑事訴訟\n    法第101條第1項第1款、第3款之情形，非予羈押，顯難進行\n    審判或執行，於民國98年12 月24日起執行羈押，並自99年3\n    月24日延長羈押二月，至99 年5月23日止羈押期間即將屆滿\n    。\n二、茲本院以前項原因依然存在，認有繼續羈押之必要，應自99\n    年5月24日起延長羈押二月。\n三、依刑事訴訟法第108條第1項、第5項，裁定如主文。"
  },
  "characters": {
    "judges": [
      "楊貴雄",
      "許必奇",
      "周明鴻"
    ],
    "prosecutors": [

    ],
    "lawyers": [
      "法律扶助舒建中"
    ],
    "clerks": [
      "郭彥琪"
    ],
    "plaintiffs": [

    ],
    "defendants": [
      "甲"
    ],
    "prosecutor_office": [

    ],
    "creditors": [

    ],
    "debtors": [

    ],
    "judicial_associate_officer": [

    ]
  },
  "adjudged_at": "2010-05-12",
  "created_at": "2016-01-05 11:52:16",
  "updated_at": "2016-01-05 11:52:16"
}