{
  "identify": "TPH-99-聲-157-20100512-1",
  "court": {
    "name": "臺灣高等法院",
    "code": "TPH"
  },
  "division": {
    "name": "民事",
    "code": "V"
  },
  "year": 99,
  "word": "聲",
  "number": "157",
  "jcheck": "1",
  "reason": "停止執行",
  "content": "臺灣高等法院民事裁定                   99年度聲字第157號\n聲  請  人  捷盛聯運有限公司\n法定代理人  乙○\n代  理  人  張慧婷律師\n相  對  人  亞加倍工業股份有限公司\n法定代理人  甲○○\n上列聲請人因與相對人亞加倍工業股份有限公司間返還溢收運費\n強制執行事件，聲請停止執行，本院裁定如下：\n    主      文\n聲請駁回。\n聲請費用由聲請人負擔。\n    理      由\n一、聲請意旨略以：相對人執本院98年度海商上更(一)字第2號返\n    還溢收運費事件確定判決（下稱系爭確定判決）向臺灣高雄\n    地方法院民事執行處（下稱高雄地院執行處）聲請就伊與第\n    三人第一商業銀行股份有限公司苓雅分行之存款債權為強制\n    執行，高雄地院執行處亦已囑託臺灣臺北地方法院進行執行\n    ，惟伊已對系爭確定判決提起再審之訴，爰依強制執行法第\n    18條第2項之規定，請求准予供擔保後停止上開執行程序等\n    語。\n二、按債務人提起再審時，法院因必要情形或依聲請定相當並確\n    實之擔保，得為停止強制執行之裁定，強制執行第18條第2\n    項固定有明文。惟「再審以不停止強制執行為原則，非有特\n    別必要情形，法院不得為停止執行之裁判（最高法院18年抗\n    字第85號判例意旨參照）。是債務人聲請再審或提起再審之\n    訴，如經法院判決或裁定駁回，則法院對債務人所為停止強\n    制執行之聲請，即應予駁回，殆無疑義。\n三、經查，聲請人向本院提起再審之訴，業經本院於民國99年5\n    月11日以99年度再易字第35號判決駁回其再審之訴，且本件\n    再審之訴之訴訟標的金額為新臺幣（下同）116萬1,610元，\n    因未逾150萬元，而不得上訴第三審，於本院判決後即告確\n    定。揆諸上開說明，聲請人提起再審之訴，既經本院判決駁\n    回，則其聲請停止強制執行，自屬無理由，應予駁回。\n據上論結，本件聲請為無理由，爰裁定如主文。\n中    華    民    國    99    年    5     月    12    日\n                    民事第三庭\n                        審判長法  官  林敬修\n                              法  官  吳青蓉\n                              法  官  黃騰耀\n正本係照原本作成。\n不得抗告。\n中    華    民    國    99    年    5     月    12    日\n                              書記官  潘大鵬",
  "structure": {
    "main": "聲請駁回。\n聲請費用由聲請人負擔。",
    "reason": "一、聲請意旨略以：相對人執本院98年度海商上更(一)字第2號返\n    還溢收運費事件確定判決（下稱系爭確定判決）向臺灣高雄\n    地方法院民事執行處（下稱高雄地院執行處）聲請就伊與第\n    三人第一商業銀行股份有限公司苓雅分行之存款債權為強制\n    執行，高雄地院執行處亦已囑託臺灣臺北地方法院進行執行\n    ，惟伊已對系爭確定判決提起再審之訴，爰依強制執行法第\n    18條第2項之規定，請求准予供擔保後停止上開執行程序等\n    語。\n二、按債務人提起再審時，法院因必要情形或依聲請定相當並確\n    實之擔保，得為停止強制執行之裁定，強制執行第18條第2\n    項固定有明文。惟「再審以不停止強制執行為原則，非有特\n    別必要情形，法院不得為停止執行之裁判（最高法院18年抗\n    字第85號判例意旨參照）。是債務人聲請再審或提起再審之\n    訴，如經法院判決或裁定駁回，則法院對債務人所為停止強\n    制執行之聲請，即應予駁回，殆無疑義。\n三、經查，聲請人向本院提起再審之訴，業經本院於民國99年5\n    月11日以99年度再易字第35號判決駁回其再審之訴，且本件\n    再審之訴之訴訟標的金額為新臺幣（下同）116萬1,610元，\n    因未逾150萬元，而不得上訴第三審，於本院判決後即告確\n    定。揆諸上開說明，聲請人提起再審之訴，既經本院判決駁\n    回，則其聲請停止強制執行，自屬無理由，應予駁回。\n據上論結，本件聲請為無理由，爰裁定如主文。"
  },
  "characters": {
    "judges": [
      "林敬修",
      "吳青蓉",
      "黃騰耀"
    ],
    "prosecutors": [

    ],
    "lawyers": [
      "張慧婷"
    ],
    "clerks": [

    ],
    "plaintiffs": [

    ],
    "defendants": [

    ],
    "prosecutor_office": [
      "捷盛聯運有限公司"
    ],
    "creditors": [

    ],
    "debtors": [

    ],
    "judicial_associate_officer": [

    ]
  },
  "adjudged_at": "2010-05-12",
  "created_at": "2016-01-05 11:56:17",
  "updated_at": "2016-01-05 11:56:17"
}