{
  "identify": "TPH-98-聲-3814-20100105-1",
  "court": {
    "name": "臺灣高等法院",
    "code": "TPH"
  },
  "division": {
    "name": "刑事",
    "code": "M"
  },
  "year": 98,
  "word": "聲",
  "number": "3814",
  "jcheck": "1",
  "reason": "聲請定其應執行刑",
  "content": "臺灣高等法院刑事裁定                  98年度聲字第3814號\n聲  請  人  臺灣高等法院檢察署檢察官\n受  刑  人  甲○○\n上列聲請人因受刑人數罪併罰有二裁判以上，聲請定其應執行刑\n，本院裁定如下：\n    主  文\n甲○○因犯如附表所示各罪所處之刑，應執行有期徒刑捌月，如\n易科罰金，以銀元佰元即新臺幣玖佰元折算壹日。\n    理  由\n一、按依司法院釋字第662號解釋：「中華民國（下同）94年2月\n    2日修正公布之現行刑法第41條第2項，關於數罪併罰，數宣\n    告刑均得易科罰金，而定應執行刑之刑逾6個月者，排除適\n    用同條第1項得易科罰金之規定部分，與憲法第23條規定有\n    違，並與本院釋字第366號解釋意旨不符，應自本解釋公布\n    之日起失其效力。」故對於數罪併罰，數宣告刑均得易科罰\n    金，而定應執行之刑超過6個月之案件，依司法院釋字第366\n    號、662號解釋意旨，仍得易科罰金。\n二、刑法第2條第1項規定：「行為後法律有變更者，適用行為時\n    之法律。但行為後之法律有利於行為人者，適用最有利於行\n    為人之法律」。按95年7月1日新刑法施行前刑法第41條第1\n    項前段關於易科罰金之折算標準原規定：「犯最重本刑為5\n    年以下有期徒刑以下之刑之罪，而受6個月以下有期徒刑或\n    拘役之宣告，因身體、教育、職業、家庭之關係或其他正當\n    事由，執行顯有困難者，得以1元以上3元以下折算1日，易\n    科罰金。」，經依已廢止之罰金罰鍰提高標準條例第2條前\n    段及現行法規所定貨幣單位折算新臺幣條例第2條之規定提\n    高並折算後，為新臺幣900元折算為1日；而修正後公布施行\n    的刑法第41條第1項前段則規定：「犯最重本刑為5年以下有\n    期徒刑以下之刑之罪，而受6個月以下有期徒刑或拘役之宣\n    告者，得以新臺幣1千元、2千元或3千元折算1日，易科罰金\n    。」，比較修正前後刑法第41條第1項，以95年7月1日修正\n    公布施行前之規定，較有利於受刑人，應適用修正前刑法第\n    41 條第1項前段規定，諭知易科罰金之折算標準。又被告於\n    裁判確定前犯數罪，其行為後，刑法第51條第5款業於民國\n    94 年2月2日修正公布，並於95年7月1日施行，修正後之規\n    定，將宣告多數有期徒刑定執行刑之上限，由修正前之不得\n    逾20 年，提高為不得逾30年，其餘則無不同，比較結果，\n    修正後規定並未較有利於行為人，依刑法第2條第1項前段之\n    規定，仍應依修正前刑法，定其應執行之刑。\n三、受刑人甲○○所犯醫師法等罪，分別經本院先後各判處如附\n    表所示之刑，並依中華民國96年罪犯減刑條例之規定，減為\n    如附表所示之刑確定在案。茲聲請人聲請定其應執行之刑，\n    本院審核認聲請為正當，應定其應執行之刑，而附表所示二\n    罪，原確定判決宣告之刑期均未逾有期徒刑6月，揆諸上揭\n    說明，附表所示二罪所定之應執行刑，仍得易科罰金。\n四、爰依刑事訴訟法第477條第1項、刑法第2條第1項、第53條、\n    修正前第51條第5款、第41條第1項前段，已廢止之罰金罰鍰\n    提高標準條例第2條前段，現行法規所定貨幣單位折算新臺\n    幣條例第2條，裁定如主文。\n中    華    民    國    99    年     1    月     5    日\n                    刑事第一庭審判長法  官  葉騰瑞\n                                    法  官  王炳梁\n                                    法  官  莊明彰\n以上正本證明與原本無異。\n如不服本裁定，應於收受送達後五日內向本院提出抗告狀。\n                                    書記官  王韻雅\n中    華    民    國    99    年    1     月    5     日\n",
  "structure": {
    "main": "甲○○因犯如附表所示各罪所處之刑，應執行有期徒刑捌月，如\n易科罰金，以銀元佰元即新臺幣玖佰元折算壹日。",
    "reason": "一、按依司法院釋字第662號解釋：「中華民國（下同）94年2月\n    2日修正公布之現行刑法第41條第2項，關於數罪併罰，數宣\n    告刑均得易科罰金，而定應執行刑之刑逾6個月者，排除適\n    用同條第1項得易科罰金之規定部分，與憲法第23條規定有\n    違，並與本院釋字第366號解釋意旨不符，應自本解釋公布\n    之日起失其效力。」故對於數罪併罰，數宣告刑均得易科罰\n    金，而定應執行之刑超過6個月之案件，依司法院釋字第366\n    號、662號解釋意旨，仍得易科罰金。\n二、刑法第2條第1項規定：「行為後法律有變更者，適用行為時\n    之法律。但行為後之法律有利於行為人者，適用最有利於行\n    為人之法律」。按95年7月1日新刑法施行前刑法第41條第1\n    項前段關於易科罰金之折算標準原規定：「犯最重本刑為5\n    年以下有期徒刑以下之刑之罪，而受6個月以下有期徒刑或\n    拘役之宣告，因身體、教育、職業、家庭之關係或其他正當\n    事由，執行顯有困難者，得以1元以上3元以下折算1日，易\n    科罰金。」，經依已廢止之罰金罰鍰提高標準條例第2條前\n    段及現行法規所定貨幣單位折算新臺幣條例第2條之規定提\n    高並折算後，為新臺幣900元折算為1日；而修正後公布施行\n    的刑法第41條第1項前段則規定：「犯最重本刑為5年以下有\n    期徒刑以下之刑之罪，而受6個月以下有期徒刑或拘役之宣\n    告者，得以新臺幣1千元、2千元或3千元折算1日，易科罰金\n    。」，比較修正前後刑法第41條第1項，以95年7月1日修正\n    公布施行前之規定，較有利於受刑人，應適用修正前刑法第\n    41 條第1項前段規定，諭知易科罰金之折算標準。又被告於\n    裁判確定前犯數罪，其行為後，刑法第51條第5款業於民國\n    94 年2月2日修正公布，並於95年7月1日施行，修正後之規\n    定，將宣告多數有期徒刑定執行刑之上限，由修正前之不得\n    逾20 年，提高為不得逾30年，其餘則無不同，比較結果，\n    修正後規定並未較有利於行為人，依刑法第2條第1項前段之\n    規定，仍應依修正前刑法，定其應執行之刑。\n三、受刑人甲○○所犯醫師法等罪，分別經本院先後各判處如附\n    表所示之刑，並依中華民國96年罪犯減刑條例之規定，減為\n    如附表所示之刑確定在案。茲聲請人聲請定其應執行之刑，\n    本院審核認聲請為正當，應定其應執行之刑，而附表所示二\n    罪，原確定判決宣告之刑期均未逾有期徒刑6月，揆諸上揭\n    說明，附表所示二罪所定之應執行刑，仍得易科罰金。\n四、爰依刑事訴訟法第477條第1項、刑法第2條第1項、第53條、\n    修正前第51條第5款、第41條第1項前段，已廢止之罰金罰鍰\n    提高標準條例第2條前段，現行法規所定貨幣單位折算新臺\n    幣條例第2條，裁定如主文。"
  },
  "characters": {
    "judges": [
      "葉騰瑞",
      "王炳梁",
      "莊明彰"
    ],
    "prosecutors": [

    ],
    "lawyers": [

    ],
    "clerks": [
      "王韻雅"
    ],
    "plaintiffs": [

    ],
    "defendants": [

    ],
    "prosecutor_office": [
      "臺灣高等法院檢察署檢察官"
    ],
    "creditors": [

    ],
    "debtors": [

    ],
    "judicial_associate_officer": [

    ]
  },
  "adjudged_at": "2010-01-05",
  "created_at": "2016-01-05 15:00:48",
  "updated_at": "2016-01-05 15:00:48"
}