{
  "identify": "TPH-98-聲-3728-20100104-1",
  "court": {
    "name": "臺灣高等法院",
    "code": "TPH"
  },
  "division": {
    "name": "刑事",
    "code": "M"
  },
  "year": 98,
  "word": "聲",
  "number": "3728",
  "jcheck": "1",
  "reason": "聲請定其應執行刑",
  "content": "臺灣高等法院刑事裁定                  98年度聲字第3728號\n聲  請  人  臺灣高等法院檢察署檢察官\n受  刑  人  甲○○\n上列聲請人因受刑人數罪併罰有二裁判以上，聲請定其應執行之\n刑（聲請案號：九十八年度執聲字第一六六九號），本院裁定如\n下：\n    主  文\n甲○○因犯如附表所示各罪所處之刑，應執行有期徒刑玖月，如\n易科罰金，以銀元參佰元即新臺幣玖佰元折算壹日。\n    理  由\n一、聲請意旨略以：受刑人甲○○因贓物等數罪，先後經判決確\n    定如附表，應依刑法第五十三條、第五十一條第五款規定，\n    定其應執行之刑，爰依刑事訴訟法第四百七十七條第一項聲\n    請裁定等語。\n二、按刑法有關定應執行刑及易科罰金之規定均於九十四年二月\n    二日修正，並自九十五年七月一日起施行。依刑法第二條第\n    一項規定：「行為後法律有變更者，適用行為時之法律。但\n    行為後之法律有利於行為人者，適用最有利於行為人之法律\n    」，且依刑法第五十一條定應執行刑時，「裁判確定前犯數\n    罪，其中一罪在新法施行前者，亦同（即亦應為新舊法比較\n    ）」（最高法院九十五年五月二十三日第八次刑事庭會議決\n    議參照）。本件如附表編號 1所示之罪，係於九十五年七月\n    一日新法施行前所犯，且於新法施行後裁判確定，故附表所\n    示各罪定其應執行刑時，自應比較新舊法。茲就本件新舊法\n    之比較如下：(一)修正前刑法第五十一條規定：「數罪併罰，\n    分別宣告其罪之刑，依左列各款定其應執行者：」其中第五\n    款規定：「宣告多數有期徒刑者，於各刑中之最長期以上，\n    各刑合併之刑期以下，定其刑期。但不得逾二十年。」；修\n    正後刑法第五十一條第五款規定：「宣告多數有期徒刑者，\n    於各刑中之最長期以上，各刑合併之刑期以下，定其刑期。\n    但不得逾三十年。」，比較修正前後之規定，以修正前之規\n    定較有利於行為人，應依修正前刑法第五十一條第五款規定\n    ，定應執行之刑。(二)修正前刑法第四十一條第一項前段關於\n    易科罰金之折算標準原規定：「犯最重本刑為五年以下有期\n    徒刑以下之刑之罪，而受六個月以下有期徒刑或拘役之宣告\n    ，因身體、教育、職業、家庭之關係或其他正當事由，執行\n    顯有困難者，得以一元以上三元以下折算一日，易科罰金。\n    」，經依已廢止之罰金罰鍰提高標準條例第二條前段及現行\n    法規所定貨幣單位折算新臺幣條例第二條之規定提高並折算\n    後，為新臺幣九百元折算為一日；而修正後之刑法第四十一\n    條第一項前段則規定：「犯最重本刑為五年以下有期徒刑以\n    下之刑之罪，而受六個月以下有期徒刑或拘役之宣告者，得\n    以新臺幣一千元、二千元或三千元折算一日，易科罰金。」\n    ，比較修正前後之規定，以修正前之規定較有利於受刑人，\n    應適用修正前刑法第四十一條第一項前段規定，諭知易科罰\n    金之折算標準。\n三、次按法律上屬於自由裁量之事項，有其外部性界限及內部性\n    界限，並非概無拘束。依據法律之具體規定，法院應在其範\n    圍選擇為適當之裁判者，為外部性界限；而法院為裁判時，\n    應考量法律之目的，及法律秩序之理念所在者，為內部性界\n    限。法院為裁判時，二者均不得有所踰越。在數罪併罰，有\n    二裁判以上，定其應執行之刑時，固屬於法院自由裁量之事\n    項，然仍應受前揭外部性界限及內部性界限之拘束（最高法\n    院九十四年度台非字第二三三號判決意旨參照）。本件受刑\n    人甲○○所犯如附表編號1至5所示之罪，經臺灣桃園地方法\n    院以九十七年度審簡字第一八○號判決定其應執行之刑為有\n    期徒刑四月確定在案；又受刑人所犯如附表編號 6所示四罪\n    ，經臺灣桃園地方法院以九十七年度易字第八三一、九四一\n    號判決定其應執行之刑為有期徒刑六月，嗣經本院以九十八\n    年度上易字第八三五號判決上訴駁回確定在案，有上開判決\n    書正本及影本附卷可按，本院於定應執行刑時，自應審酌該\n    外部性界限及內部性界限決定之。\n四、復按司法院釋字第六六二號解釋：「中華民國九十四年二月\n    二日修正公布之現行刑法第四十一條第二項，關於數罪併罰\n    ，數宣告刑均得易科罰金，而定應執行刑之刑逾六個月者，\n    排除適用同條第一項得易科罰金之規定部分，與憲法第二十\n    三條規定有違，並與本院釋字第三六六號解釋意旨不符，應\n    自本解釋公布之日起失其效力。」故對於數罪併罰，數宣告\n    刑均得易科罰金，而定應執行之刑超過六個月之案件，依司\n    法院釋字第三六六號、第六六二號解釋意旨，仍得易科罰金\n    。本件受刑人甲○○所犯如附表所示之贓物等數罪之法定本\n    刑，係最重本刑五年以下有期徒刑之罪，且各罪均受六個月\n    以下有期徒刑之宣告，雖定執行刑後，其應執行之刑已逾六\n    月，仍得易科罰金。茲聲請人雖未一併聲請諭知易科罰金之\n    折算標準，本院參酌上開司法院釋字第六六二號解釋意旨及\n    刑法第二條第一項、修正前刑法第四十一條第一項規定，仍\n    應諭知易科罰金之折算標準，併此敘明。\n五、經查，本件受刑人甲○○因贓物等數罪，經臺灣桃園地方法\n    院及本院分別判處如附表所示之刑，均經分別確定在案。茲\n    檢察官聲請定其應執行之刑，本院審核認聲請為正當，應定\n    其應執行之刑，並諭知易科罰金之折算標準。爰依刑事訴訟\n    法第四百七十七條第一項，刑法第二條第一項、第五十三條\n    ，修正前刑法第五十一條第五款、第四十一條第一項前段、\n    第二項，廢止前罰金罰鍰提高標準條例第二條前段，現行法\n    規所定貨幣單位折算新臺幣條例第二條，裁定如主文。\n中    華    民    國    99    年    1     月    4     日\n                  刑事第二庭審判長法  官  洪光燦\n                                  法  官  林恆吉\n                                  法  官  宋明蒼\n以上正本證明與原本無異。\n如不服本裁定，應於收受送達後五日內向本院提出抗告狀。\n                                  書記官  駱麗君\n中    華    民    國    99    年    1     月    4     日\n",
  "structure": {
    "main": "甲○○因犯如附表所示各罪所處之刑，應執行有期徒刑玖月，如\n易科罰金，以銀元參佰元即新臺幣玖佰元折算壹日。",
    "reason": "一、聲請意旨略以：受刑人甲○○因贓物等數罪，先後經判決確\n    定如附表，應依刑法第五十三條、第五十一條第五款規定，\n    定其應執行之刑，爰依刑事訴訟法第四百七十七條第一項聲\n    請裁定等語。\n二、按刑法有關定應執行刑及易科罰金之規定均於九十四年二月\n    二日修正，並自九十五年七月一日起施行。依刑法第二條第\n    一項規定：「行為後法律有變更者，適用行為時之法律。但\n    行為後之法律有利於行為人者，適用最有利於行為人之法律\n    」，且依刑法第五十一條定應執行刑時，「裁判確定前犯數\n    罪，其中一罪在新法施行前者，亦同（即亦應為新舊法比較\n    ）」（最高法院九十五年五月二十三日第八次刑事庭會議決\n    議參照）。本件如附表編號 1所示之罪，係於九十五年七月\n    一日新法施行前所犯，且於新法施行後裁判確定，故附表所\n    示各罪定其應執行刑時，自應比較新舊法。茲就本件新舊法\n    之比較如下：(一)修正前刑法第五十一條規定：「數罪併罰，\n    分別宣告其罪之刑，依左列各款定其應執行者：」其中第五\n    款規定：「宣告多數有期徒刑者，於各刑中之最長期以上，\n    各刑合併之刑期以下，定其刑期。但不得逾二十年。」；修\n    正後刑法第五十一條第五款規定：「宣告多數有期徒刑者，\n    於各刑中之最長期以上，各刑合併之刑期以下，定其刑期。\n    但不得逾三十年。」，比較修正前後之規定，以修正前之規\n    定較有利於行為人，應依修正前刑法第五十一條第五款規定\n    ，定應執行之刑。(二)修正前刑法第四十一條第一項前段關於\n    易科罰金之折算標準原規定：「犯最重本刑為五年以下有期\n    徒刑以下之刑之罪，而受六個月以下有期徒刑或拘役之宣告\n    ，因身體、教育、職業、家庭之關係或其他正當事由，執行\n    顯有困難者，得以一元以上三元以下折算一日，易科罰金。\n    」，經依已廢止之罰金罰鍰提高標準條例第二條前段及現行\n    法規所定貨幣單位折算新臺幣條例第二條之規定提高並折算\n    後，為新臺幣九百元折算為一日；而修正後之刑法第四十一\n    條第一項前段則規定：「犯最重本刑為五年以下有期徒刑以\n    下之刑之罪，而受六個月以下有期徒刑或拘役之宣告者，得\n    以新臺幣一千元、二千元或三千元折算一日，易科罰金。」\n    ，比較修正前後之規定，以修正前之規定較有利於受刑人，\n    應適用修正前刑法第四十一條第一項前段規定，諭知易科罰\n    金之折算標準。\n三、次按法律上屬於自由裁量之事項，有其外部性界限及內部性\n    界限，並非概無拘束。依據法律之具體規定，法院應在其範\n    圍選擇為適當之裁判者，為外部性界限；而法院為裁判時，\n    應考量法律之目的，及法律秩序之理念所在者，為內部性界\n    限。法院為裁判時，二者均不得有所踰越。在數罪併罰，有\n    二裁判以上，定其應執行之刑時，固屬於法院自由裁量之事\n    項，然仍應受前揭外部性界限及內部性界限之拘束（最高法\n    院九十四年度台非字第二三三號判決意旨參照）。本件受刑\n    人甲○○所犯如附表編號1至5所示之罪，經臺灣桃園地方法\n    院以九十七年度審簡字第一八○號判決定其應執行之刑為有\n    期徒刑四月確定在案；又受刑人所犯如附表編號 6所示四罪\n    ，經臺灣桃園地方法院以九十七年度易字第八三一、九四一\n    號判決定其應執行之刑為有期徒刑六月，嗣經本院以九十八\n    年度上易字第八三五號判決上訴駁回確定在案，有上開判決\n    書正本及影本附卷可按，本院於定應執行刑時，自應審酌該\n    外部性界限及內部性界限決定之。\n四、復按司法院釋字第六六二號解釋：「中華民國九十四年二月\n    二日修正公布之現行刑法第四十一條第二項，關於數罪併罰\n    ，數宣告刑均得易科罰金，而定應執行刑之刑逾六個月者，\n    排除適用同條第一項得易科罰金之規定部分，與憲法第二十\n    三條規定有違，並與本院釋字第三六六號解釋意旨不符，應\n    自本解釋公布之日起失其效力。」故對於數罪併罰，數宣告\n    刑均得易科罰金，而定應執行之刑超過六個月之案件，依司\n    法院釋字第三六六號、第六六二號解釋意旨，仍得易科罰金\n    。本件受刑人甲○○所犯如附表所示之贓物等數罪之法定本\n    刑，係最重本刑五年以下有期徒刑之罪，且各罪均受六個月\n    以下有期徒刑之宣告，雖定執行刑後，其應執行之刑已逾六\n    月，仍得易科罰金。茲聲請人雖未一併聲請諭知易科罰金之\n    折算標準，本院參酌上開司法院釋字第六六二號解釋意旨及\n    刑法第二條第一項、修正前刑法第四十一條第一項規定，仍\n    應諭知易科罰金之折算標準，併此敘明。\n五、經查，本件受刑人甲○○因贓物等數罪，經臺灣桃園地方法\n    院及本院分別判處如附表所示之刑，均經分別確定在案。茲\n    檢察官聲請定其應執行之刑，本院審核認聲請為正當，應定\n    其應執行之刑，並諭知易科罰金之折算標準。爰依刑事訴訟\n    法第四百七十七條第一項，刑法第二條第一項、第五十三條\n    ，修正前刑法第五十一條第五款、第四十一條第一項前段、\n    第二項，廢止前罰金罰鍰提高標準條例第二條前段，現行法\n    規所定貨幣單位折算新臺幣條例第二條，裁定如主文。"
  },
  "characters": {
    "judges": [
      "洪光燦",
      "林恆吉",
      "宋明蒼"
    ],
    "prosecutors": [

    ],
    "lawyers": [

    ],
    "clerks": [
      "駱麗君"
    ],
    "plaintiffs": [

    ],
    "defendants": [

    ],
    "prosecutor_office": [
      "臺灣高等法院檢察署檢察官"
    ],
    "creditors": [

    ],
    "debtors": [

    ],
    "judicial_associate_officer": [

    ]
  },
  "adjudged_at": "2010-01-04",
  "created_at": "2016-01-05 14:34:37",
  "updated_at": "2016-01-05 14:34:37"
}