{
  "identify": "TPH-98-上訴-2372-20100104-3",
  "court": {
    "name": "臺灣高等法院",
    "code": "TPH"
  },
  "division": {
    "name": "刑事",
    "code": "M"
  },
  "year": 98,
  "word": "上訴",
  "number": "2372",
  "jcheck": "3",
  "reason": "毒品危害防制條例",
  "content": "臺灣高等法院刑事裁定                98年度上訴字第2372號\n上  訴  人  臺灣桃園地方法院檢察署檢察官\n上  訴  人\n即  被  告  甲○○\n                    樓(\n選任辯護人  邱鎮北律師\n上列被告因毒品危害防制條例上訴案件，本院裁定如下：\n    主  文\n甲○○羈押期間，自民國九十九年一月十日起，延長二月。\n    理  由\n一、上訴人即被告甲○○前經本院認為犯毒品危害防制條例罪嫌\n    疑重大，有刑事訴訟法第101條第1項第2款、第3款情形，非\n    予羈押，顯難進行審判，於民國98年6月10日執行羈押，嗣\n    經第2次延長羈押，至民國99年1月9日延長羈押期間即將屆\n    滿。\n二、茲本院以前項原因依然存在，認有繼續羈押之必要，應自\n    民國99年1月10日起，第3次延長羈押2月，爰依刑事訴訟法\n    第108條第1項、第5項，裁定如主文。\n中    華    民    國    99    年    1    月    4    日\n                  刑事第十七庭  審判長法  官  王聰明\n                                      法  官  黃雅芬\n                                      法  官  陳世宗\n以上正本證明與原本無異。\n如不服本裁定，應於收受送達後五日內向本院提出抗告狀。\n                                      書記官  魏汝萍\n中    華    民    國    99    年    1    月    4    日\n",
  "structure": {
    "main": "甲○○羈押期間，自民國九十九年一月十日起，延長二月。",
    "reason": "一、上訴人即被告甲○○前經本院認為犯毒品危害防制條例罪嫌\n    疑重大，有刑事訴訟法第101條第1項第2款、第3款情形，非\n    予羈押，顯難進行審判，於民國98年6月10日執行羈押，嗣\n    經第2次延長羈押，至民國99年1月9日延長羈押期間即將屆\n    滿。\n二、茲本院以前項原因依然存在，認有繼續羈押之必要，應自\n    民國99年1月10日起，第3次延長羈押2月，爰依刑事訴訟法\n    第108條第1項、第5項，裁定如主文。"
  },
  "characters": {
    "judges": [
      "王聰明",
      "黃雅芬",
      "陳世宗"
    ],
    "prosecutors": [

    ],
    "lawyers": [
      "邱鎮北"
    ],
    "clerks": [
      "魏汝萍"
    ],
    "plaintiffs": [

    ],
    "defendants": [
      "甲"
    ],
    "prosecutor_office": [

    ],
    "creditors": [

    ],
    "debtors": [

    ],
    "judicial_associate_officer": [

    ]
  },
  "adjudged_at": "2010-01-04",
  "created_at": "2016-01-05 14:34:06",
  "updated_at": "2016-01-05 14:34:06"
}