{
  "identify": "TPH-99-重上更(三)-80-20100512-1",
  "court": {
    "name": "臺灣高等法院",
    "code": "TPH"
  },
  "division": {
    "name": "刑事",
    "code": "M"
  },
  "year": 99,
  "word": "重上更(三)",
  "number": "80",
  "jcheck": "1",
  "reason": "毒品危害防制條例",
  "content": "臺灣高等法院刑事判決            99年度重上更(三)字第80號\n上  訴  人\n即  被  告  乙○○\n選任辯護人  吳磺慶律師\n上列上訴人因違反毒品危害防制條例案件，不服臺灣板橋地方法\n院95年度訴字第2975號，中華民國96年6月13日第一審判決（起\n訴案號：臺灣板橋地方法院檢察署95年度偵緝字第2045號），提\n起上訴，經判決後，最高法院第三次發回更審，本院判決如下：\n    主  文\n原判決撤銷。\n乙○○共同販賣第二級毒品未遂，處有期徒刑壹年拾月。扣案之\n第二級毒品甲基安非他命壹小包（驗餘含袋重零點伍捌玖公克）\n沒收銷燬之。門號0000000000號行動電話壹支（含SIM卡），沒\n收。\n    事  實\n一、乙○○明知甲基安非他命係毒品危害防制條例第二條第二項\n    第二款所稱之第二級毒品，不得販賣、持有。緣王明輝於民\n    國95年1月13日上午10時50分許，在臺北縣新莊市○○街20\n    號前，遭警查獲，警方並當場在其身上查得第二級毒品甲基\n    安非他命1小包，王明輝即向警方供稱其均係撥打門號00000\n    00000號行動電話向自稱「阿彬」之男子購買毒品（即甲○\n    ○，甲○○販賣第二級毒品部分，已經法院判處有期徒刑8\n    年確定），並配合警方以電話與甲○○聯絡，佯稱欲再購買\n    甲基安非他命1包，並約定於同日稍晚在臺北縣三重市○○\n    ○路224巷旁商店內交易。而乙○○亦明知甲○○有在販賣\n    第二級毒品甲基安非他命予不特定人牟利，猶與甲○○基於\n    共同販賣第二級毒品甲基安非他命圖利之犯意聯絡，於同日\n    上午11時40分許，由甲○○將甲基安非他命1小包（含袋重\n    0.6公克，驗餘含袋重0.589公克）及所有之門號0000000000\n    號行動電話1支（該門號係甲○○以其女友何佳妮名義申請\n    辦理，惟實際使用支配之人為甲○○）交予乙○○，指示乙\n    ○○前往上開地點以該0000000000號行動電話為聯絡工具，\n    將甲基安非他命1小包交付予買毒之人並收取價金2千元。迨\n    乙○○持上開毒品及行動電話抵達上開商店內後，於同日下\n    午1時30分許，已埋伏在店內之員警即撥打0000000000號行\n    動電話，見現場之乙○○接起電話應答，即上前將之逮捕，\n    並扣得上開甲基安非他命1包及行動電話1支。\n二、案經臺北縣政府警察局新莊分局報請臺灣板橋地方法院檢察\n    署檢察官偵查起訴。\n    理    由\n一、訊據被告乙○○對於上開販賣第二級毒品犯行坦承不諱（本\n    院卷第32頁背面、33頁正面、第49頁正面），核與證人王明\n    輝所證相符，王明輝於原審證稱：「（你被警察查獲的安非\n    他命一包，是否你撥打0000000000號買到的？）電話是，但\n    是人不是。對方是叫阿彬．．．我之前都是向持有00000000\n    00號電話的人購買安非他命，已經和這支電話交易2、3次，\n    但是每次來的人都不一樣，．．．（每次約見面地方的時候\n    ，要交付錢及毒品時，如何再確認？）都是我再打00000000\n    00號的電話確認的」等語（原審卷第90、91頁）。另證人即\n    臺北縣政府警察局新莊分局江明南、蕭博森於偵查中亦結證\n    稱：查獲王明輝時即追問王明輝向何人購買甲基安非他命，\n    王明輝稱係打0000000000號行動電話向藥頭購買，讓王明輝\n    在偵防車上撥打電話連絡，藥頭先與王明輝約在三重市，到\n    了三重市藥頭便與王明輝約在三重市○○○路224巷口旁之\n    便利超商，藥頭稱到了該處再打電話給他，到了約定的便利\n    超商內，其即按重播鍵播打0000000000號碼，看到被告拿起\n    該行動電話一直喂喂喂，被告並把該行動電話拿在手中走回\n    店內娃娃機彈珠檯座位上，我們確認被告是藥頭後，即一起\n    上前並要求被告主動交出甲基安非他命，被告指著娃娃機彈\n    珠檯取物口，其將取物口的小門推開即看到1包甲基安非他\n    命等語（2016號偵卷第70、71頁）。且扣案透明晶體1包，\n    經送請台灣檢驗科技股份有限公司鑑驗結果，毛重0.6公克\n    ，取其中0.011公克鑑定用罄，為甲基安非他命，有95年3\n    月9日濫用藥物檢驗報告在卷可稽（2016號偵卷第78頁），\n    並有該毒品甲基安非他命1包及前述之0000000000號行動電\n    話扣案可資佐證。被告上開任意性之自白，應為事實，可以\n    採信。又本案係因警方先查到王明輝，王明輝供稱係向「阿\n    彬」男子購毒，警方進而查獲持毒品前來進行交易之被告等\n    事實經過，已如前述。而被告於本院更一審時即供稱「阿彬\n    」男子之真實姓名身分即為甲○○（更一審卷第33頁背面）\n    ，且查扣案0000000000號行動電話亦係甲○○女友何佳妮名\n    義所申請，有大眾電信資料查詢紀錄一份可稽（2016號偵卷\n    第55頁），甲○○並於本院更一審98年5月27日審理時到庭\n    證稱其即係本案之「阿彬」男子（更一審卷第105頁背面）\n    ，及本院96年度上更(一)字第634號刑事判決亦認定該案被告\n    甲○○有與本案被告乙○○共犯本件販賣第二級毒品犯行，\n    並判處罪刑確定，迭經本院依職權調取該刑事案卷核閱無誤\n    ，故本院即據此認定本案「阿彬」男子即係甲○○。又本件\n    雖係證人王明輝之配合，於警方授意下撥打0000000000號行\n    動電話予甲○○，進而查獲被告，除甲○○先前即已有販賣\n    甲基安非他命之犯意，並非因員警或王明輝之教唆而生外（\n    甲○○除本案以外，尚另有其他多次販賣第二級毒品犯行，\n    詳見本院96年度上更(一)字第634號刑事判決），而被告係依\n    甲○○之指示而犯本案，更非係受員警或王明輝之教唆而來\n    ，故本件警方經由王明輝而查獲被告所為本件販賣第二級毒\n    品甲基安非他命之犯行，並無違法之處，警方因而取得之證\n    據（即查扣毒品），自得作為證據，無陷害教唆之問題，併\n    說明之。\n二、至公訴意旨以被告係基於幫助之犯意而為本案販賣第二級毒\n    品犯行，及被告於本院審理時亦辯稱：伊當時是和甲○○一\n    起去的，也知道甲○○要賣毒品，但伊不認識買毒的王明輝\n    ，只是幫忙甲○○接電話，伊是幫助犯云云。惟查：被告於\n    警詢中已承稱其係依「阿彬」（甲○○）指示至現場與買毒\n    之人進行毒品交易不諱，被告供稱：「（警方現場查獲何物\n    ？係何人所有？有何用途？）安非他命1小包毛重0.6公克、\n    是我所有、是綽號阿彬之男子要我帶到該處賣給王明輝的。\n    」、「（警方查獲安非他命1小包毛重0.6公克之情形為何？\n    ）是我主動將放在商店內娃娃販賣機取物口內之安非他命1\n    小包交給警方。（你今日被警方查獲之安非他命係向何人購\n    買？年籍資料為何？）是綽號阿彬之男子，叫我帶安非他命\n    到該處，以新台幣2千元之價格要賣給王明輝所用的，．．\n    ．是阿彬在95年1月13日11時40分許，在自強路跟重陽路口\n    ，將安非他命交給我，叫我帶到臺北縣三重市○○○路224\n    巷旁商店內賣給王明輝。（你如何聯絡綽號阿彬之人？他共\n    叫你販賣幾次之毒品安非他命？幫他販賣安毒每次代價為何\n    ？）我無法聯絡他，都是他聯絡我，只有今天被查獲這次、\n    沒有代價。（警方查獲之行動電話0000000000號是何人所有\n    ？）是阿彬交安毒交給我時，一同拿給我使用。」、「（你\n    今日被警方查獲之安毒0.6公克是否要賣給王明輝所用？販\n    賣之價格為何？）是的，要以新台幣2千元賣給他。．．．\n    查獲的行動電話是阿彬交給我使用的」等語（2016號偵卷第\n    12 、13頁）。再參以前述王明輝及警員江明南、蕭博森等\n    人證言，可查知，當天員警查獲被告時，甲○○並未在現場\n    ，且衡情，若甲○○在場，焉有不親自接電話之理？且依警\n    員所證，扣案毒品甲基安非他命1小包亦係由被告告知警方\n    ，警方始在娃娃機彈珠檯取物口查得，是被告於上開時地即\n    依甲○○指示攜帶毒品及行動電話欲與買毒之王明輝進行毒\n    品交易，迨可認定。則被告就本件毒品交易，依出賣人甲○\n    ○之指示實際進行交付毒品及收取價金等行為，自已達「販\n    賣」行為之構成要件程度，其與甲○○間當有犯意聯絡、行\n    為分擔，應為共同正犯，猶辯稱只是幫助犯云云，係避重就\n    輕之詞，不可採信。至證人甲○○於本院更一審時曾證稱：\n    伊當天有一起去，電話是放在我電動玩具抬旁邊，電話響我\n    沒有接，是被告幫我接云云（更一審卷第106頁背面），然\n    證人甲○○此部分所證並非事實，已如前述，認係迴護被告\n    之詞，不足採信。又證人王明輝雖非直接向被告購買毒品，\n    惟被告為甲○○送交毒品及收取價金，二人間就本次販賣第\n    二級毒品互有犯意聯絡、行為分擔，已如前述，且被告於本\n    院審理時承稱其知悉甲○○當日確係在販賣毒品（本院卷第\n    33、49頁），而甲○○亦因本件販賣第二級毒品犯行經法院\n    判處罪刑確定，有本院甲○○之被告前案紀錄表1份在卷可\n    稽，並經本院調取該案卷核閱無誤，被告當亦知悉甲○○係\n    販售毒品予不特定人圖利，應為合理推認。綜上所述，被告\n    有本案共同販賣第二級毒品犯行，堪以認定，應依法論科。\n三、論罪理由\n  (一)法律修正之比較\n    1.刑法部分\n      被告行為後，於94年2月2日修正公布之刑法，已自95年7\n      月1日起施行，修正後刑法第28條關於成立共同正犯之標\n      準，將原來共同正犯之共同「實施」犯罪，改為共同「實\n      行」犯罪，剔除完全未參與犯罪相關行為「實行」之「陰\n      謀共同正犯」及「預備共同正犯」，是修正後之共同正犯\n      之可罰性要件之範圍業已限縮，乃屬行為可罰性要件之變\n      更，自應比較新舊法。惟不論適用修正前、修正後之刑法\n      第28條規定，被告與甲○○間均成立共同正犯，故修正後\n      之刑法並非較有利於被告，依據刑法第2條第1項前段規定\n      ，應適用修正前刑法28條關於共犯之規定。\n    2.毒品危害防制條例部分\n      按甲基安非他命係毒品危害防制條例第2條第2項第2款規\n      定第二級毒品。又被告行為後，毒品危害防制條例於98年\n      5月20日經總統華總一義字第09800125141號令修正公布第\n      4、11、11-1、17、20、25條條文；並自公布後6個月施行\n      （參98年6月8日法務部法檢字第0980802279號函依同條例\n      第36條規定，修正條文自公布後6個月施行）。再按行為\n      後法律有變更者，適用行為時之法律，但行為後之法律有\n      利於行為人者，適用最有利於行為人之法律，刑法第2條\n      第1項定有明文。毒品危害防制條例第4條第2項關於販賣\n      第二級毒品罪，於本次修正時將原法定刑：「處無期徒刑\n      或七年以上有期徒刑，得併科新臺幣七百萬元以下罰金。\n      」提高為：「處無期徒刑或七年以上有期徒刑，得併科新\n      臺幣一千萬元以下罰金。」比較新舊法之結果，因舊法之\n      法定刑較輕，適用修正前毒品危害防制條例第4條第2項規\n      定對被告較為有利。惟毒品危害防制條例第17條原規定：\n      「犯第四條第一項至第四項、第五條第一項至第四項前段\n      、第六條第一項至第四項、第七條第一項至第四項、第八\n      條第一項至第四項、第十條或第十一條第一項、第二項之\n      罪，供出毒品來源，因而破獲者，得減輕其刑。」修正為\n      ：「犯第四條至第八條、第十條或第十一條之罪，供出毒\n      品來源，因而查獲其他正犯或共犯者，減輕或免除其刑（\n      第一項）。犯第四條至第八條之罪於偵查及審判中均自白\n      者，減輕其刑（第二項）。」查被告於警詢及本院審理時\n      均自白所犯之本案販賣第二級毒品犯行，符合修正後毒品\n      危害防制條例第17條第2項減輕其刑之規定，故綜合比較\n      結果，被告應整體適用修正後毒品危害防制條例規定較為\n      有利。\n  (二)法律之適用\n    按甲基安非他命係毒品危害防制條例第2條第2項第2款規定\n    第二級毒品。核被告所為，係犯修正後毒品危害防制條例第\n    4條第6項、第2項之販賣第二級毒品未遂罪。被告與甲○○\n    間，有犯意聯絡、行為分擔，為共同正犯。公訴意旨雖認被\n    告所犯係幫助販賣第二級毒品未遂罪，惟被告已參與本案「\n    販賣」毒品之構成要件行為，應論以共同正犯，已如前述，\n    公訴意旨此部分所指即有誤認，應予更正。又被告已著手本\n    案販賣第二級毒品行為，惟未發生犯罪之結果，屬未遂犯，\n    依刑法第25條第2項規定減輕其刑。又被告於警詢及本院審\n    理時均自白所犯之本案販賣第二級毒品犯行，已如前述（\n    2016號偵卷第12、13頁，本院卷第32頁背面、第33頁正面、\n    第49頁正面），應依修正後毒品危害防制條例第17條第2項\n    規定減輕其刑，並遞減之。\n四、撤銷改判及科刑理由\n    原審認被告犯罪事證明確，據予論罪科刑，固非無見。惟查\n    ：(1)、被告應適用修正後毒品危害防制條例之規定，原審未\n    及比較適用，即有未合。(2)、扣案第二級毒品甲基安非他命\n    1小包經鑑驗結果，驗餘毛重之正確重量應為0.589公克，原\n    審竟於主文中宣告沒收之扣案毒品數量為「驗餘淨重零點參\n    玖公克」，自有疏漏。(3)、本案嗣後有查出共犯「阿彬」男\n    子之真實身分即為甲○○，原審未詳加比對卷證而認定，亦\n    欠妥適。被告上訴請求從輕量刑，尚非全無理由，且原判決\n    亦有上開可議，自應由本院撤銷改判。爰審酌被告品行、明\n    知友人甲○○販賣第二級毒品危害他人，猶為其送貨及收取\n    價金，實屬非是，惟犯罪情節尚非重大，併其犯罪之動機、\n    目的，及於本院審理時已坦認犯行，非全無悔改之意等一切\n    情狀，量處如主文第二項所示之刑。扣案之第二級毒品甲基\n    安非他命1小包，毛重0.6公克，經送台灣檢驗科技股份有限\n    公司鑑驗時取其中0.011公克鑑定用罄，已如前述，故尚餘\n    毒品之數量應為毛重0.589公克，而該毒品包裝袋於鑑驗時\n    既無與毒品分別鑑秤重量，即難以析離而無法個別宣告沒收\n    ，該毒品包裝袋應視為毒品之一部分，應依毒品危害防制條\n    例第18條第1項前段之規定，沒收銷燬之。扣案門號0000000\n    000號行動電話1支，係共犯甲○○以其女友何佳妮名義申請\n    而由甲○○使用一節，迭據甲○○於本院更一審時到庭證述\n    明確（更一審卷第105頁正面），並有大眾電信資料查詢紀\n    錄一份可稽（2016號偵卷第55頁），且依證人王明輝所證，\n    其均係向門號0000000000號行動電話之「阿彬」男子連絡購\n    買毒品事宜，甲○○所證扣案電話為其所有一節應為事實，\n    故扣案0000000000號之行動電話（含SIM卡）為共犯甲○○\n    所有，且供被告及共犯甲○○犯本罪所用之物，應依毒品危\n    害防制條例第19條第1項規定，併宣告沒收。\n據上論斷，應依刑事訴訟法第369條第1項前段、第364條、第299\n條第1項前段，毒品危害防制條例第4條第2項、第6項、第17條第\n2項、第18條第1項前段、第19條第1項前段，刑法第2條第1項、\n第11條、第25條第2項，修正前刑法第28條，判決如主文。\n本案經檢察官李叔芬到庭執行職務。\n中     華     民    國    99    年    5    月   12    日\n                  刑事第四庭審判長法  官  陳筱珮\n                                  法  官  邱滋杉\n                                  法  官  孫惠琳\n以上正本證明與原本無異。\n如不服本判決，應於收受送達後十日內向本院提出上訴書狀，其\n未敘述上訴之理由者並得於提起上訴後十日內向本院補提理由書\n（均須按他造當事人之人數附繕本）。「切勿逕送上級法院」。\n                                  書記官  陶宇晨\n中    華    民    國    99    年    5     月    12    日\n附錄：本案論罪科刑法條全文\n毒品危害防制條例第4條\n製造、運輸、販賣第一級毒品者，處死刑或無期徒刑；處無期徒\n刑者，得併科新臺幣 2 千萬元以下罰金。\n製造、運輸、販賣第二級毒品者，處無期徒刑或 7 年以上有期\n徒刑，得併科新臺幣 1 千萬元以下罰金。\n製造、運輸、販賣第三級毒品者，處 5 年以上有期徒刑，得併\n科新臺幣 7 百萬元以下罰金。\n製造、運輸、販賣第四級毒品者，處 3 年以上 10 年以下有期\n徒刑，得併科新臺幣 3 百萬元以下罰金。\n製造、運輸、販賣專供製造或施用毒品之器具者，處 1 年以上\n7 年以下有期徒刑，得併科新臺幣 1 百萬元以下罰金。\n前五項之未遂犯罰之。",
  "structure": {
    "main": "原判決撤銷。\n乙○○共同販賣第二級毒品未遂，處有期徒刑壹年拾月。扣案之\n第二級毒品甲基安非他命壹小包（驗餘含袋重零點伍捌玖公克）\n沒收銷燬之。門號0000000000號行動電話壹支（含SIM卡），沒\n收。",
    "fact": "一、乙○○明知甲基安非他命係毒品危害防制條例第二條第二項\n    第二款所稱之第二級毒品，不得販賣、持有。緣王明輝於民\n    國95年1月13日上午10時50分許，在臺北縣新莊市○○街20\n    號前，遭警查獲，警方並當場在其身上查得第二級毒品甲基\n    安非他命1小包，王明輝即向警方供稱其均係撥打門號00000\n    00000號行動電話向自稱「阿彬」之男子購買毒品（即甲○\n    ○，甲○○販賣第二級毒品部分，已經法院判處有期徒刑8\n    年確定），並配合警方以電話與甲○○聯絡，佯稱欲再購買\n    甲基安非他命1包，並約定於同日稍晚在臺北縣三重市○○\n    ○路224巷旁商店內交易。而乙○○亦明知甲○○有在販賣\n    第二級毒品甲基安非他命予不特定人牟利，猶與甲○○基於\n    共同販賣第二級毒品甲基安非他命圖利之犯意聯絡，於同日\n    上午11時40分許，由甲○○將甲基安非他命1小包（含袋重\n    0.6公克，驗餘含袋重0.589公克）及所有之門號0000000000\n    號行動電話1支（該門號係甲○○以其女友何佳妮名義申請\n    辦理，惟實際使用支配之人為甲○○）交予乙○○，指示乙\n    ○○前往上開地點以該0000000000號行動電話為聯絡工具，\n    將甲基安非他命1小包交付予買毒之人並收取價金2千元。迨\n    乙○○持上開毒品及行動電話抵達上開商店內後，於同日下\n    午1時30分許，已埋伏在店內之員警即撥打0000000000號行\n    動電話，見現場之乙○○接起電話應答，即上前將之逮捕，\n    並扣得上開甲基安非他命1包及行動電話1支。\n二、案經臺北縣政府警察局新莊分局報請臺灣板橋地方法院檢察\n    署檢察官偵查起訴。",
    "reason": "一、訊據被告乙○○對於上開販賣第二級毒品犯行坦承不諱（本\n    院卷第32頁背面、33頁正面、第49頁正面），核與證人王明\n    輝所證相符，王明輝於原審證稱：「（你被警察查獲的安非\n    他命一包，是否你撥打0000000000號買到的？）電話是，但\n    是人不是。對方是叫阿彬．．．我之前都是向持有00000000\n    00號電話的人購買安非他命，已經和這支電話交易2、3次，\n    但是每次來的人都不一樣，．．．（每次約見面地方的時候\n    ，要交付錢及毒品時，如何再確認？）都是我再打00000000\n    00號的電話確認的」等語（原審卷第90、91頁）。另證人即\n    臺北縣政府警察局新莊分局江明南、蕭博森於偵查中亦結證\n    稱：查獲王明輝時即追問王明輝向何人購買甲基安非他命，\n    王明輝稱係打0000000000號行動電話向藥頭購買，讓王明輝\n    在偵防車上撥打電話連絡，藥頭先與王明輝約在三重市，到\n    了三重市藥頭便與王明輝約在三重市○○○路224巷口旁之\n    便利超商，藥頭稱到了該處再打電話給他，到了約定的便利\n    超商內，其即按重播鍵播打0000000000號碼，看到被告拿起\n    該行動電話一直喂喂喂，被告並把該行動電話拿在手中走回\n    店內娃娃機彈珠檯座位上，我們確認被告是藥頭後，即一起\n    上前並要求被告主動交出甲基安非他命，被告指著娃娃機彈\n    珠檯取物口，其將取物口的小門推開即看到1包甲基安非他\n    命等語（2016號偵卷第70、71頁）。且扣案透明晶體1包，\n    經送請台灣檢驗科技股份有限公司鑑驗結果，毛重0.6公克\n    ，取其中0.011公克鑑定用罄，為甲基安非他命，有95年3\n    月9日濫用藥物檢驗報告在卷可稽（2016號偵卷第78頁），\n    並有該毒品甲基安非他命1包及前述之0000000000號行動電\n    話扣案可資佐證。被告上開任意性之自白，應為事實，可以\n    採信。又本案係因警方先查到王明輝，王明輝供稱係向「阿\n    彬」男子購毒，警方進而查獲持毒品前來進行交易之被告等\n    事實經過，已如前述。而被告於本院更一審時即供稱「阿彬\n    」男子之真實姓名身分即為甲○○（更一審卷第33頁背面）\n    ，且查扣案0000000000號行動電話亦係甲○○女友何佳妮名\n    義所申請，有大眾電信資料查詢紀錄一份可稽（2016號偵卷\n    第55頁），甲○○並於本院更一審98年5月27日審理時到庭\n    證稱其即係本案之「阿彬」男子（更一審卷第105頁背面）\n    ，及本院96年度上更(一)字第634號刑事判決亦認定該案被告\n    甲○○有與本案被告乙○○共犯本件販賣第二級毒品犯行，\n    並判處罪刑確定，迭經本院依職權調取該刑事案卷核閱無誤\n    ，故本院即據此認定本案「阿彬」男子即係甲○○。又本件\n    雖係證人王明輝之配合，於警方授意下撥打0000000000號行\n    動電話予甲○○，進而查獲被告，除甲○○先前即已有販賣\n    甲基安非他命之犯意，並非因員警或王明輝之教唆而生外（\n    甲○○除本案以外，尚另有其他多次販賣第二級毒品犯行，\n    詳見本院96年度上更(一)字第634號刑事判決），而被告係依\n    甲○○之指示而犯本案，更非係受員警或王明輝之教唆而來\n    ，故本件警方經由王明輝而查獲被告所為本件販賣第二級毒\n    品甲基安非他命之犯行，並無違法之處，警方因而取得之證\n    據（即查扣毒品），自得作為證據，無陷害教唆之問題，併\n    說明之。\n二、至公訴意旨以被告係基於幫助之犯意而為本案販賣第二級毒\n    品犯行，及被告於本院審理時亦辯稱：伊當時是和甲○○一\n    起去的，也知道甲○○要賣毒品，但伊不認識買毒的王明輝\n    ，只是幫忙甲○○接電話，伊是幫助犯云云。惟查：被告於\n    警詢中已承稱其係依「阿彬」（甲○○）指示至現場與買毒\n    之人進行毒品交易不諱，被告供稱：「（警方現場查獲何物\n    ？係何人所有？有何用途？）安非他命1小包毛重0.6公克、\n    是我所有、是綽號阿彬之男子要我帶到該處賣給王明輝的。\n    」、「（警方查獲安非他命1小包毛重0.6公克之情形為何？\n    ）是我主動將放在商店內娃娃販賣機取物口內之安非他命1\n    小包交給警方。（你今日被警方查獲之安非他命係向何人購\n    買？年籍資料為何？）是綽號阿彬之男子，叫我帶安非他命\n    到該處，以新台幣2千元之價格要賣給王明輝所用的，．．\n    ．是阿彬在95年1月13日11時40分許，在自強路跟重陽路口\n    ，將安非他命交給我，叫我帶到臺北縣三重市○○○路224\n    巷旁商店內賣給王明輝。（你如何聯絡綽號阿彬之人？他共\n    叫你販賣幾次之毒品安非他命？幫他販賣安毒每次代價為何\n    ？）我無法聯絡他，都是他聯絡我，只有今天被查獲這次、\n    沒有代價。（警方查獲之行動電話0000000000號是何人所有\n    ？）是阿彬交安毒交給我時，一同拿給我使用。」、「（你\n    今日被警方查獲之安毒0.6公克是否要賣給王明輝所用？販\n    賣之價格為何？）是的，要以新台幣2千元賣給他。．．．\n    查獲的行動電話是阿彬交給我使用的」等語（2016號偵卷第\n    12 、13頁）。再參以前述王明輝及警員江明南、蕭博森等\n    人證言，可查知，當天員警查獲被告時，甲○○並未在現場\n    ，且衡情，若甲○○在場，焉有不親自接電話之理？且依警\n    員所證，扣案毒品甲基安非他命1小包亦係由被告告知警方\n    ，警方始在娃娃機彈珠檯取物口查得，是被告於上開時地即\n    依甲○○指示攜帶毒品及行動電話欲與買毒之王明輝進行毒\n    品交易，迨可認定。則被告就本件毒品交易，依出賣人甲○\n    ○之指示實際進行交付毒品及收取價金等行為，自已達「販\n    賣」行為之構成要件程度，其與甲○○間當有犯意聯絡、行\n    為分擔，應為共同正犯，猶辯稱只是幫助犯云云，係避重就\n    輕之詞，不可採信。至證人甲○○於本院更一審時曾證稱：\n    伊當天有一起去，電話是放在我電動玩具抬旁邊，電話響我\n    沒有接，是被告幫我接云云（更一審卷第106頁背面），然\n    證人甲○○此部分所證並非事實，已如前述，認係迴護被告\n    之詞，不足採信。又證人王明輝雖非直接向被告購買毒品，\n    惟被告為甲○○送交毒品及收取價金，二人間就本次販賣第\n    二級毒品互有犯意聯絡、行為分擔，已如前述，且被告於本\n    院審理時承稱其知悉甲○○當日確係在販賣毒品（本院卷第\n    33、49頁），而甲○○亦因本件販賣第二級毒品犯行經法院\n    判處罪刑確定，有本院甲○○之被告前案紀錄表1份在卷可\n    稽，並經本院調取該案卷核閱無誤，被告當亦知悉甲○○係\n    販售毒品予不特定人圖利，應為合理推認。綜上所述，被告\n    有本案共同販賣第二級毒品犯行，堪以認定，應依法論科。\n三、論罪理由\n  (一)法律修正之比較\n    1.刑法部分\n      被告行為後，於94年2月2日修正公布之刑法，已自95年7\n      月1日起施行，修正後刑法第28條關於成立共同正犯之標\n      準，將原來共同正犯之共同「實施」犯罪，改為共同「實\n      行」犯罪，剔除完全未參與犯罪相關行為「實行」之「陰\n      謀共同正犯」及「預備共同正犯」，是修正後之共同正犯\n      之可罰性要件之範圍業已限縮，乃屬行為可罰性要件之變\n      更，自應比較新舊法。惟不論適用修正前、修正後之刑法\n      第28條規定，被告與甲○○間均成立共同正犯，故修正後\n      之刑法並非較有利於被告，依據刑法第2條第1項前段規定\n      ，應適用修正前刑法28條關於共犯之規定。\n    2.毒品危害防制條例部分\n      按甲基安非他命係毒品危害防制條例第2條第2項第2款規\n      定第二級毒品。又被告行為後，毒品危害防制條例於98年\n      5月20日經總統華總一義字第09800125141號令修正公布第\n      4、11、11-1、17、20、25條條文；並自公布後6個月施行\n      （參98年6月8日法務部法檢字第0980802279號函依同條例\n      第36條規定，修正條文自公布後6個月施行）。再按行為\n      後法律有變更者，適用行為時之法律，但行為後之法律有\n      利於行為人者，適用最有利於行為人之法律，刑法第2條\n      第1項定有明文。毒品危害防制條例第4條第2項關於販賣\n      第二級毒品罪，於本次修正時將原法定刑：「處無期徒刑\n      或七年以上有期徒刑，得併科新臺幣七百萬元以下罰金。\n      」提高為：「處無期徒刑或七年以上有期徒刑，得併科新\n      臺幣一千萬元以下罰金。」比較新舊法之結果，因舊法之\n      法定刑較輕，適用修正前毒品危害防制條例第4條第2項規\n      定對被告較為有利。惟毒品危害防制條例第17條原規定：\n      「犯第四條第一項至第四項、第五條第一項至第四項前段\n      、第六條第一項至第四項、第七條第一項至第四項、第八\n      條第一項至第四項、第十條或第十一條第一項、第二項之\n      罪，供出毒品來源，因而破獲者，得減輕其刑。」修正為\n      ：「犯第四條至第八條、第十條或第十一條之罪，供出毒\n      品來源，因而查獲其他正犯或共犯者，減輕或免除其刑（\n      第一項）。犯第四條至第八條之罪於偵查及審判中均自白\n      者，減輕其刑（第二項）。」查被告於警詢及本院審理時\n      均自白所犯之本案販賣第二級毒品犯行，符合修正後毒品\n      危害防制條例第17條第2項減輕其刑之規定，故綜合比較\n      結果，被告應整體適用修正後毒品危害防制條例規定較為\n      有利。\n  (二)法律之適用\n    按甲基安非他命係毒品危害防制條例第2條第2項第2款規定\n    第二級毒品。核被告所為，係犯修正後毒品危害防制條例第\n    4條第6項、第2項之販賣第二級毒品未遂罪。被告與甲○○\n    間，有犯意聯絡、行為分擔，為共同正犯。公訴意旨雖認被\n    告所犯係幫助販賣第二級毒品未遂罪，惟被告已參與本案「\n    販賣」毒品之構成要件行為，應論以共同正犯，已如前述，\n    公訴意旨此部分所指即有誤認，應予更正。又被告已著手本\n    案販賣第二級毒品行為，惟未發生犯罪之結果，屬未遂犯，\n    依刑法第25條第2項規定減輕其刑。又被告於警詢及本院審\n    理時均自白所犯之本案販賣第二級毒品犯行，已如前述（\n    2016號偵卷第12、13頁，本院卷第32頁背面、第33頁正面、\n    第49頁正面），應依修正後毒品危害防制條例第17條第2項\n    規定減輕其刑，並遞減之。\n四、撤銷改判及科刑理由\n    原審認被告犯罪事證明確，據予論罪科刑，固非無見。惟查\n    ：(1)、被告應適用修正後毒品危害防制條例之規定，原審未\n    及比較適用，即有未合。(2)、扣案第二級毒品甲基安非他命\n    1小包經鑑驗結果，驗餘毛重之正確重量應為0.589公克，原\n    審竟於主文中宣告沒收之扣案毒品數量為「驗餘淨重零點參\n    玖公克」，自有疏漏。(3)、本案嗣後有查出共犯「阿彬」男\n    子之真實身分即為甲○○，原審未詳加比對卷證而認定，亦\n    欠妥適。被告上訴請求從輕量刑，尚非全無理由，且原判決\n    亦有上開可議，自應由本院撤銷改判。爰審酌被告品行、明\n    知友人甲○○販賣第二級毒品危害他人，猶為其送貨及收取\n    價金，實屬非是，惟犯罪情節尚非重大，併其犯罪之動機、\n    目的，及於本院審理時已坦認犯行，非全無悔改之意等一切\n    情狀，量處如主文第二項所示之刑。扣案之第二級毒品甲基\n    安非他命1小包，毛重0.6公克，經送台灣檢驗科技股份有限\n    公司鑑驗時取其中0.011公克鑑定用罄，已如前述，故尚餘\n    毒品之數量應為毛重0.589公克，而該毒品包裝袋於鑑驗時\n    既無與毒品分別鑑秤重量，即難以析離而無法個別宣告沒收\n    ，該毒品包裝袋應視為毒品之一部分，應依毒品危害防制條\n    例第18條第1項前段之規定，沒收銷燬之。扣案門號0000000\n    000號行動電話1支，係共犯甲○○以其女友何佳妮名義申請\n    而由甲○○使用一節，迭據甲○○於本院更一審時到庭證述\n    明確（更一審卷第105頁正面），並有大眾電信資料查詢紀\n    錄一份可稽（2016號偵卷第55頁），且依證人王明輝所證，\n    其均係向門號0000000000號行動電話之「阿彬」男子連絡購\n    買毒品事宜，甲○○所證扣案電話為其所有一節應為事實，\n    故扣案0000000000號之行動電話（含SIM卡）為共犯甲○○\n    所有，且供被告及共犯甲○○犯本罪所用之物，應依毒品危\n    害防制條例第19條第1項規定，併宣告沒收。\n據上論斷，應依刑事訴訟法第369條第1項前段、第364條、第299\n條第1項前段，毒品危害防制條例第4條第2項、第6項、第17條第\n2項、第18條第1項前段、第19條第1項前段，刑法第2條第1項、\n第11條、第25條第2項，修正前刑法第28條，判決如主文。\n本案經檢察官李叔芬到庭執行職務。\n中     華     民    國    99    年    5    月   12    日\n                  刑事第四庭審判長法  官  陳筱珮\n                                  法  官  邱滋杉\n                                  法  官  孫惠琳\n以上正本證明與原本無異。\n如不服本判決，應於收受送達後十日內向本院提出上訴書狀，其\n未敘述上訴之理由者並得於提起上訴後十日內向本院補提理由書\n（均須按他造當事人之人數附繕本）。「切勿逕送上級法院」。\n                                  書記官  陶宇晨"
  },
  "characters": {
    "judges": [
      "陳筱珮",
      "邱滋杉",
      "孫惠琳"
    ],
    "prosecutors": [
      "李叔芬"
    ],
    "lawyers": [
      "吳磺慶"
    ],
    "clerks": [
      "陶宇晨"
    ],
    "plaintiffs": [

    ],
    "defendants": [
      "乙"
    ],
    "prosecutor_office": [

    ],
    "creditors": [

    ],
    "debtors": [

    ],
    "judicial_associate_officer": [

    ]
  },
  "adjudged_at": "2010-05-12",
  "created_at": "2016-01-05 11:54:33",
  "updated_at": "2016-01-05 11:54:33"
}