{
  "identify": "TPH-98-上-876-20100105-1",
  "court": {
    "name": "臺灣高等法院",
    "code": "TPH"
  },
  "division": {
    "name": "民事",
    "code": "V"
  },
  "year": 98,
  "word": "上",
  "number": "876",
  "jcheck": "1",
  "reason": "清償借款",
  "content": "臺灣高等法院民事判決           98年度上字第876號\n上  訴  人  甲○○○\n            丁○○○\n            戊○○\n            己○○\n共      同\n訴訟代理人  楊志航律師\n被 上訴 人  富邦資產管理股份有限公司（即合作金庫商業銀行\n            股份有限公司訴訟承當人）\n法定代理人  丙○○\n訴訟代理人  乙○○\n            庚○○\n上列當事人間清償借款事件，上訴人對於中華民國98年7月8日臺\n灣宜蘭地方法院98年度訴字第8號第一審判決提起上訴，經本院\n於98年12月22日言詞辯論終結，判決如下：\n    主      文\n原判決關於命上訴人連帶給付本息超過上訴人因繼承被繼承人偉\n浪黑玳所得遺產限度部分，及訴訟費用之裁判均廢棄。\n上開廢棄部分，被上訴人在第一審之訴駁回。\n其餘上訴駁回。\n第一、二審訴訟費用由上訴人於因繼承被繼承人偉浪黑玳所得遺\n產限度內連帶負擔，餘由被上訴人負擔。\n    事實及理由\n甲、程序方面：按訴訟繫屬中為訴訟標的之法律關係，雖移轉於\n    第三人，於訴訟無影響。但第三人如經兩造同意，得聲請代\n    當事人承當訴訟。前項但書情形，僅他造不同意者，移轉之\n    當事人或第三人得聲請法院裁定許第三人承當訴訟，民事訴\n    訟法第254條第1、2項分別定有明文。查被上訴人（即原審\n    原告）原為合作金庫商業銀行（下稱合作金庫），於原審訴\n    訟程序進行中之98年3月11日，將其對上訴人之債權讓與被\n    上訴人，並將債權讓與之事實公告於報紙，被上訴人為債權\n    受讓人等情，有債權讓與證明書及債權讓與公告可稽（見原\n    審卷第65、66頁），是本債權讓與對債務人已發生效力，訴\n    訟標的法律關係已移轉於被上訴人，被上訴人並於原審98\n    年4月22日言詞辯論期日聲明承當訴訟，且徵得上訴人之同\n    意（見原審訴字卷第58頁），經核於法並無不合，自應准許\n    。\n乙、實體方面：\n一、被上訴人起訴主張：被繼承人（即借款人）偉浪黑玳於95年\n    12月18日向合作金庫借款新台幣（下同）380萬元，期限為\n    20年，利率前2年按定儲指數利率2.11%加碼年息0.33%即以\n    2.44%浮動計息，第3年起按指標利率2.11加碼年息0.93%即\n    以3.04 %浮動計息，第一年繳息，第二年起按月平均攤還本\n    息，如遲延履行時，除仍按上開利率計息外，逾期在6個月\n    以內者，另按上開利率之10%，逾期在6個月以上，按上開利\n    率20%加計違約金（下稱系爭貸款）。詎被繼承人偉浪黑玳\n    自96年6月18日起未依約繳息，尚欠380萬元未清償，依約全\n    部借款已喪失期限利益，視為全部到期。嗣被繼承人偉浪黑\n    玳於96年12月1日死亡，上訴人為其法定繼承人，應繼承被\n    繼承人偉浪黑玳之債務，且上訴人均無聲明拋棄或限定繼承\n    之情事，依法應負連帶清償責任，又上開債權經合作金庫讓\n    與伊，爰依消費借貸及繼承之法律關係，求為命上訴人應連\n    帶給付380萬元，及自96年6月18日起至清償日止，按年息\n    2.57%計算利息，並自96年7月18日起至清償日止，其逾期在\n    6個月以內者，另按上開利率10%，逾期超過6個月以上部分\n    ，按上開利率20%計付違約金之判決。並答辯聲明：上訴駁\n    回。\n二、上訴人則以：依被繼承人偉浪黑玳之消費者貸款申請書所載\n    ，被繼承人偉浪黑玳工作職務擔任保全員，全年收入卻記載\n    100萬元，顯然被上訴人之徵信調查不實，則被上訴人辦理\n    系爭貸款業務既有重大過失，且又以顯不實資料通過被繼承\n    人偉浪黑玳之申請，應自負此授信不實之呆帳之風險；又上\n    訴人與被繼承人偉浪黑玳未同財共居，依民法繼承篇施行法\n    第1條之3第4項規定，上訴人自得主張以所得遺產為限，負\n    清償責任等語，資為抗辯。並上訴聲明：(一)原判決廢棄。\n    (二)被上訴人在第一審之訴及假執行之聲請均駁回。或請判決\n    就上訴人於繼承被繼承人偉浪黑玳之遺產限度內，應給付被\n    上訴人380萬元本息。\n三、被上訴人主張被繼承人（即借款人）偉浪黑玳於95年12月18\n    日向合作金庫借款380萬元，期限為20年，利率前2年按定儲\n    指數利率2.11%加碼年息0.33%即以2.44%浮動計息，第3年起\n    按指標利率2.11加碼年息0.93%即以3.04%浮動計息，第一年\n    繳息，第二年起按月平均攤還本息，如遲延履行時，除仍按\n    上開利率計息外，逾期在6個月以內者，另按上開利率之10%\n    ，逾期在6個月以上，按上開利率20%加計違約金，詎被繼承\n    人偉浪黑玳自96年6月18日起未依約繳息，尚欠380萬元未清\n    償，依約全部借款已喪失期限利益，視為全部到期，又被繼\n    承人偉浪黑玳於96年12月1日死亡，上訴人為其法定繼承人\n    ，且均未聲明拋棄或限定繼承之事實，業經被上訴人提出借\n    貸、其他約定事項、消費者貸款申請書、客戶全部往來帳戶\n    查詢單、印鑑卡、偉浪黑玳之身分證及健保卡影本、銀行分\n    戶交易明細表、預定土地房屋買賣契約書、銀行撥款協議書\n    、戶籍謄本、臺灣高雄地方法院家事庭函、繼承系統表為證\n    （見原審支付命令卷第5至17頁，原審訴字卷第25至45頁）\n    ，上訴人對此並不爭執（見本院卷第28頁背面至29頁），自\n    堪信為真實。\n四、至被上訴人主張上訴人應就被繼承人偉浪黑玳所負系爭貸款\n    380萬元本息及違約金債務，負連帶清償責任等情，則為被\n    上訴人所否認，並以前開情詞置辯。經查：\n（一）上訴人辯稱被上訴人以不實資料通過被繼承人偉浪黑玳之\n      申請，系爭貸款業務顯有重大過失，應自負此授信不實之\n      呆帳風險等情。惟為被上訴人所否認，並主張被繼承人偉\n      浪黑玳因購屋需求，向合作金庫公司借貸，按當時評估計\n      市價價值491萬358元，貸予偉浪黑玳380萬元，購屋成數\n      為77.38%，合乎當時合作金庫內部估定之放款值成數8成\n      以內及銀行法第12條之1自用住宅放款規定，另偉浪黑玳\n      當時向合作金庫申請貸款時所填之申請書經銀行人員確認\n      後，再向財團法人金融聯合徵信中心取得其個人信用資料\n      ，因偉浪黑玳並無不良記錄等，故依當時合作金庫內部房\n      屋貸款相關規範辦理等語。依被上訴人提出系爭貸款申請\n      書所附預定土地買賣契約書、預定房屋買賣契約書觀之（\n      見原審卷25、33至42頁），系爭房地總價為500萬元（土\n      地275萬元、房屋225萬元），被上訴人評估市價後，貸予\n      被繼承人偉浪黑玳380萬元，尚難認有何授信不實情事。\n      上訴人所提出之高雄市三民區歷年行情走勢圖（見本院卷\n      第81頁），為高雄市三民區平均單價，並未針對系爭房屋\n      所在地段、結構、年限等條件做評估，自難遽此認為被上\n      訴人有授信不實情事。上訴人執此主張被上訴人應自負呆\n      帳風險，不得向繼承人求償云云，自不足取。\n（二）次按「繼承在民法繼承編中華民國98年5月22日修正施行\n      前開始，繼承人因不可歸責於己之事由或未同居共財者，\n      於繼承開始時無法知悉繼承債務之存在，致未能於修正施\n      行前之法定期間為限定或拋棄繼承，且由其繼續履行繼承\n      債務顯失公平者，於修正施行後，以所得遺產為限，負清\n      償責任。」民法繼承篇施行法第1之3條第4項定有明文。\n      又上述規定係於98年6月10日配合民法第1148條以下有關\n      概括繼承改採限定繼承而增訂，考民法第1148條以下改採\n      限定繼承之目的，係在於避免繼承人因不知法律而未於法\n      定期間內為限定或拋棄繼承之聲請，致背負繼承債務而影\n      響生計之不合理現象；且如強令繼承人須負無限責任，以\n      其本身固有財產清償，將使繼承人因天外飛來之債務，代\n      代不能脫卸負累，實有違民法公平正義之精神。又因民法\n      修正後之第1148條以下僅適用於修正公布後之繼承案件，\n      對於修正公布前者，固有溯及適用之必要，但為求維護債\n      權人之信賴、法安定性及避免有害交易安全，故於施行法\n      增訂本條並限縮其溯及之範圍，僅適用於98年5月22日前\n      在適用概括繼承舊制下，因不可歸責於繼承人之事由，或\n      未同財共居者，未能在法定期間內為限定或拋棄繼承等原\n      因，致繼承人受其所不知債務拘束，而顯失公平之案件。\n（三）上訴人主張與被繼承人偉浪黑玳長久以來未同財共居，且\n      未自被繼承人取得任何財產，依民法繼承篇施行法第1條\n      之3第4項規定，上訴人得主張以因繼承所得遺產限度負責\n      等情，固為被上訴人所否認。惟查被繼承人偉浪黑玳原住\n      宜蘭縣大同鄉寒溪村寒溪巷35號，於85年10月18日出境，\n      於86年5月10日遷出登記，於86年7月23日入境，於90年5\n      月18日遷入高雄市○○○路185號8樓之2，於96年1月18日\n      遷至高雄市○○○路312巷32號14樓之2；而上訴人甲○○\n      ○於59年1月11日結婚後，於63年11月23日即與戶長辦理\n      分炊，嗣遷至宜蘭縣羅東鎮○○街64之15號，復遷至宜蘭\n      縣大同鄉寒溪村寒溪巷58之2號迄今；上訴人丁○○○於\n      65 年1月1日結婚後，即遷至台北縣烏來鄉忠治村金堰96\n      號迄今；上訴人戊○○於71年10月6日結婚後遷出，於87\n      年8月20日離婚後遷至宜蘭縣羅東鎮○○街180巷15弄23號\n      ，復遷至桃園縣桃園市○○○街263號12樓之4迄今；上訴\n      人己○○則於70年1月8日結婚後，於同年12月7日另立新\n      戶等情；均有上訴人及被繼承人偉浪黑玳之戶籍資料可稽\n      （見本院卷第32、38至43頁）。上訴人主張分別於63年、\n      65年、71年、70年各自嫁娶後，即與被繼承人偉浪黑玳未\n      同居共財，致於96年12月1日繼承開始時，無法知悉被上\n      訴人有繼承債務存在，核與我國習俗，各自成家之手足咸\n      少過問彼此財務情況相符，應堪採信。又除系爭貸款購買\n      之房地外，上訴人並未取得被繼承人偉浪黑玳任何財產，\n      亦未申報被繼承人偉浪黑玳之遺產，而係由被上訴人代位\n      申報，亦有財政部國稅局函附被繼承人偉浪黑玳之遺產稅\n      申報書可稽（見本院卷第50至55頁）。則上訴人因各自嫁\n      娶，已有二、三十年，與被繼承人偉浪黑玳未同居共財，\n      致於繼承開始時無法知悉被上訴人有繼承債務存在；且除\n      系爭貸款購買之房地外，上訴人並未取得被繼承人偉浪黑\n      玳之任何財產，應認被繼承人偉浪黑玳之債務，除由被繼\n      承人偉浪黑玳之遺產清償外，由上訴人繼續履行繼承債務\n      ，顯與前述繼承編修正之精神相違，而顯然有失公平。從\n      而，上訴人主張僅以因繼承被繼承人偉浪黑玳所得遺產限\n      度內，對債權人即被上訴人負清償責任，自屬有據。\n五、綜上所陳，被上訴人請求上訴人應連帶給付380萬元及自96\n    年6月18日起至清償日止，按年息2.57％計算利息，並自96\n    年7月18日起至清償日止，其逾期在6個月以內者，另按上開\n    利率10％，逾期超過6個月以上部分，按上開利率20％計付\n    違約金，於上訴人因繼承被繼承人偉浪黑玳所得遺產限度內\n    ，洵屬有據，應予准許。逾此部分之請求，為無理由，應予\n    駁回。原審就被上訴人之請求不應准許之部分，命上訴人給\n    付超過因繼承被繼承人偉浪黑玳所得遺產限度部分，尚有未\n    洽。上訴意旨指摘原判決此部分不當，為有理由，爰由本院\n    將此部分廢棄，並改判如主文第1、2項所示。原審就被上訴\n    人之請求應准許部分，所為上訴人敗訴判決，核無違誤，上\n    訴意旨，就此部分指摘原判決不當，求予廢棄，為無理由，\n    應駁回其此部分之上訴。\n六、本件事證已臻明確，兩造其餘攻擊防禦方法及立論之證據資\n    料，均經本院審酌後，對判決結果不生影響，爰無庸逐一論\n    述，併此敘明。\n七、據上論結，本件上訴為一部有理由，一部無理由，依民事訴\n    訟法第450條、第449條第1項、第79條、第85條第2項，判決\n    如主文。\n中    華    民    國    99    年    1     月    5     日\n                    民事第十四庭\n                        審判長法  官 林金村\n                              法  官 王麗莉\n                              法  官 李慈惠\n正本係照原本作成。\n如不服本判決，應於收受送達後20日內向本院提出上訴書狀，其\n未表明上訴理由者，應於提出上訴後20日內向本院補提理由書狀\n（均須按他造當事人之人數附繕本）上訴時應提出委任律師或具\n有律師資格之人之委任狀；委任有律師資格者，另應附具律師資\n格證書及釋明委任人與受任人有民事訴訟法第466條之1第1項但\n書或第2項（詳附註）所定關係之釋明文書影本。\n中    華    民    國    99    年    1     月    6     日\n                              書記官 王敬端\n附註：\n民事訴訟法第466條之1（第1項、第2項）：\n對於第二審判決上訴，上訴人應委任律師為訴訟代理人。但上訴\n人或其他法定代理人具有律師資格者，不在此限。\n上訴人之配偶、三親等內之血親、二親等內之姻親，或上訴人為\n法人、中央或地方機關時，其所屬專任人員具有律師資格並經法\n院認為適當者，亦得為第三審訴訟代理人。",
  "structure": {
    "main": "原判決關於命上訴人連帶給付本息超過上訴人因繼承被繼承人偉\n浪黑玳所得遺產限度部分，及訴訟費用之裁判均廢棄。\n上開廢棄部分，被上訴人在第一審之訴駁回。\n其餘上訴駁回。\n第一、二審訴訟費用由上訴人於因繼承被繼承人偉浪黑玳所得遺\n產限度內連帶負擔，餘由被上訴人負擔。",
    "fact": "甲、程序方面：按訴訟繫屬中為訴訟標的之法律關係，雖移轉於\n    第三人，於訴訟無影響。但第三人如經兩造同意，得聲請代\n    當事人承當訴訟。前項但書情形，僅他造不同意者，移轉之\n    當事人或第三人得聲請法院裁定許第三人承當訴訟，民事訴\n    訟法第254條第1、2項分別定有明文。查被上訴人（即原審\n    原告）原為合作金庫商業銀行（下稱合作金庫），於原審訴\n    訟程序進行中之98年3月11日，將其對上訴人之債權讓與被\n    上訴人，並將債權讓與之事實公告於報紙，被上訴人為債權\n    受讓人等情，有債權讓與證明書及債權讓與公告可稽（見原\n    審卷第65、66頁），是本債權讓與對債務人已發生效力，訴\n    訟標的法律關係已移轉於被上訴人，被上訴人並於原審98\n    年4月22日言詞辯論期日聲明承當訴訟，且徵得上訴人之同\n    意（見原審訴字卷第58頁），經核於法並無不合，自應准許\n    。\n乙、實體方面：\n一、被上訴人起訴主張：被繼承人（即借款人）偉浪黑玳於95年\n    12月18日向合作金庫借款新台幣（下同）380萬元，期限為\n    20年，利率前2年按定儲指數利率2.11%加碼年息0.33%即以\n    2.44%浮動計息，第3年起按指標利率2.11加碼年息0.93%即\n    以3.04 %浮動計息，第一年繳息，第二年起按月平均攤還本\n    息，如遲延履行時，除仍按上開利率計息外，逾期在6個月\n    以內者，另按上開利率之10%，逾期在6個月以上，按上開利\n    率20%加計違約金（下稱系爭貸款）。詎被繼承人偉浪黑玳\n    自96年6月18日起未依約繳息，尚欠380萬元未清償，依約全\n    部借款已喪失期限利益，視為全部到期。嗣被繼承人偉浪黑\n    玳於96年12月1日死亡，上訴人為其法定繼承人，應繼承被\n    繼承人偉浪黑玳之債務，且上訴人均無聲明拋棄或限定繼承\n    之情事，依法應負連帶清償責任，又上開債權經合作金庫讓\n    與伊，爰依消費借貸及繼承之法律關係，求為命上訴人應連\n    帶給付380萬元，及自96年6月18日起至清償日止，按年息\n    2.57%計算利息，並自96年7月18日起至清償日止，其逾期在\n    6個月以內者，另按上開利率10%，逾期超過6個月以上部分\n    ，按上開利率20%計付違約金之判決。並答辯聲明：上訴駁\n    回。\n二、上訴人則以：依被繼承人偉浪黑玳之消費者貸款申請書所載\n    ，被繼承人偉浪黑玳工作職務擔任保全員，全年收入卻記載\n    100萬元，顯然被上訴人之徵信調查不實，則被上訴人辦理\n    系爭貸款業務既有重大過失，且又以顯不實資料通過被繼承\n    人偉浪黑玳之申請，應自負此授信不實之呆帳之風險；又上\n    訴人與被繼承人偉浪黑玳未同財共居，依民法繼承篇施行法\n    第1條之3第4項規定，上訴人自得主張以所得遺產為限，負\n    清償責任等語，資為抗辯。並上訴聲明：(一)原判決廢棄。\n    (二)被上訴人在第一審之訴及假執行之聲請均駁回。或請判決\n    就上訴人於繼承被繼承人偉浪黑玳之遺產限度內，應給付被\n    上訴人380萬元本息。\n三、被上訴人主張被繼承人（即借款人）偉浪黑玳於95年12月18\n    日向合作金庫借款380萬元，期限為20年，利率前2年按定儲\n    指數利率2.11%加碼年息0.33%即以2.44%浮動計息，第3年起\n    按指標利率2.11加碼年息0.93%即以3.04%浮動計息，第一年\n    繳息，第二年起按月平均攤還本息，如遲延履行時，除仍按\n    上開利率計息外，逾期在6個月以內者，另按上開利率之10%\n    ，逾期在6個月以上，按上開利率20%加計違約金，詎被繼承\n    人偉浪黑玳自96年6月18日起未依約繳息，尚欠380萬元未清\n    償，依約全部借款已喪失期限利益，視為全部到期，又被繼\n    承人偉浪黑玳於96年12月1日死亡，上訴人為其法定繼承人\n    ，且均未聲明拋棄或限定繼承之事實，業經被上訴人提出借\n    貸、其他約定事項、消費者貸款申請書、客戶全部往來帳戶\n    查詢單、印鑑卡、偉浪黑玳之身分證及健保卡影本、銀行分\n    戶交易明細表、預定土地房屋買賣契約書、銀行撥款協議書\n    、戶籍謄本、臺灣高雄地方法院家事庭函、繼承系統表為證\n    （見原審支付命令卷第5至17頁，原審訴字卷第25至45頁）\n    ，上訴人對此並不爭執（見本院卷第28頁背面至29頁），自\n    堪信為真實。\n四、至被上訴人主張上訴人應就被繼承人偉浪黑玳所負系爭貸款\n    380萬元本息及違約金債務，負連帶清償責任等情，則為被\n    上訴人所否認，並以前開情詞置辯。經查：\n（一）上訴人辯稱被上訴人以不實資料通過被繼承人偉浪黑玳之\n      申請，系爭貸款業務顯有重大過失，應自負此授信不實之\n      呆帳風險等情。惟為被上訴人所否認，並主張被繼承人偉\n      浪黑玳因購屋需求，向合作金庫公司借貸，按當時評估計\n      市價價值491萬358元，貸予偉浪黑玳380萬元，購屋成數\n      為77.38%，合乎當時合作金庫內部估定之放款值成數8成\n      以內及銀行法第12條之1自用住宅放款規定，另偉浪黑玳\n      當時向合作金庫申請貸款時所填之申請書經銀行人員確認\n      後，再向財團法人金融聯合徵信中心取得其個人信用資料\n      ，因偉浪黑玳並無不良記錄等，故依當時合作金庫內部房\n      屋貸款相關規範辦理等語。依被上訴人提出系爭貸款申請\n      書所附預定土地買賣契約書、預定房屋買賣契約書觀之（\n      見原審卷25、33至42頁），系爭房地總價為500萬元（土\n      地275萬元、房屋225萬元），被上訴人評估市價後，貸予\n      被繼承人偉浪黑玳380萬元，尚難認有何授信不實情事。\n      上訴人所提出之高雄市三民區歷年行情走勢圖（見本院卷\n      第81頁），為高雄市三民區平均單價，並未針對系爭房屋\n      所在地段、結構、年限等條件做評估，自難遽此認為被上\n      訴人有授信不實情事。上訴人執此主張被上訴人應自負呆\n      帳風險，不得向繼承人求償云云，自不足取。\n（二）次按「繼承在民法繼承編中華民國98年5月22日修正施行\n      前開始，繼承人因不可歸責於己之事由或未同居共財者，\n      於繼承開始時無法知悉繼承債務之存在，致未能於修正施\n      行前之法定期間為限定或拋棄繼承，且由其繼續履行繼承\n      債務顯失公平者，於修正施行後，以所得遺產為限，負清\n      償責任。」民法繼承篇施行法第1之3條第4項定有明文。\n      又上述規定係於98年6月10日配合民法第1148條以下有關\n      概括繼承改採限定繼承而增訂，考民法第1148條以下改採\n      限定繼承之目的，係在於避免繼承人因不知法律而未於法\n      定期間內為限定或拋棄繼承之聲請，致背負繼承債務而影\n      響生計之不合理現象；且如強令繼承人須負無限責任，以\n      其本身固有財產清償，將使繼承人因天外飛來之債務，代\n      代不能脫卸負累，實有違民法公平正義之精神。又因民法\n      修正後之第1148條以下僅適用於修正公布後之繼承案件，\n      對於修正公布前者，固有溯及適用之必要，但為求維護債\n      權人之信賴、法安定性及避免有害交易安全，故於施行法\n      增訂本條並限縮其溯及之範圍，僅適用於98年5月22日前\n      在適用概括繼承舊制下，因不可歸責於繼承人之事由，或\n      未同財共居者，未能在法定期間內為限定或拋棄繼承等原\n      因，致繼承人受其所不知債務拘束，而顯失公平之案件。\n（三）上訴人主張與被繼承人偉浪黑玳長久以來未同財共居，且\n      未自被繼承人取得任何財產，依民法繼承篇施行法第1條\n      之3第4項規定，上訴人得主張以因繼承所得遺產限度負責\n      等情，固為被上訴人所否認。惟查被繼承人偉浪黑玳原住\n      宜蘭縣大同鄉寒溪村寒溪巷35號，於85年10月18日出境，\n      於86年5月10日遷出登記，於86年7月23日入境，於90年5\n      月18日遷入高雄市○○○路185號8樓之2，於96年1月18日\n      遷至高雄市○○○路312巷32號14樓之2；而上訴人甲○○\n      ○於59年1月11日結婚後，於63年11月23日即與戶長辦理\n      分炊，嗣遷至宜蘭縣羅東鎮○○街64之15號，復遷至宜蘭\n      縣大同鄉寒溪村寒溪巷58之2號迄今；上訴人丁○○○於\n      65 年1月1日結婚後，即遷至台北縣烏來鄉忠治村金堰96\n      號迄今；上訴人戊○○於71年10月6日結婚後遷出，於87\n      年8月20日離婚後遷至宜蘭縣羅東鎮○○街180巷15弄23號\n      ，復遷至桃園縣桃園市○○○街263號12樓之4迄今；上訴\n      人己○○則於70年1月8日結婚後，於同年12月7日另立新\n      戶等情；均有上訴人及被繼承人偉浪黑玳之戶籍資料可稽\n      （見本院卷第32、38至43頁）。上訴人主張分別於63年、\n      65年、71年、70年各自嫁娶後，即與被繼承人偉浪黑玳未\n      同居共財，致於96年12月1日繼承開始時，無法知悉被上\n      訴人有繼承債務存在，核與我國習俗，各自成家之手足咸\n      少過問彼此財務情況相符，應堪採信。又除系爭貸款購買\n      之房地外，上訴人並未取得被繼承人偉浪黑玳任何財產，\n      亦未申報被繼承人偉浪黑玳之遺產，而係由被上訴人代位\n      申報，亦有財政部國稅局函附被繼承人偉浪黑玳之遺產稅\n      申報書可稽（見本院卷第50至55頁）。則上訴人因各自嫁\n      娶，已有二、三十年，與被繼承人偉浪黑玳未同居共財，\n      致於繼承開始時無法知悉被上訴人有繼承債務存在；且除\n      系爭貸款購買之房地外，上訴人並未取得被繼承人偉浪黑\n      玳之任何財產，應認被繼承人偉浪黑玳之債務，除由被繼\n      承人偉浪黑玳之遺產清償外，由上訴人繼續履行繼承債務\n      ，顯與前述繼承編修正之精神相違，而顯然有失公平。從\n      而，上訴人主張僅以因繼承被繼承人偉浪黑玳所得遺產限\n      度內，對債權人即被上訴人負清償責任，自屬有據。\n五、綜上所陳，被上訴人請求上訴人應連帶給付380萬元及自96\n    年6月18日起至清償日止，按年息2.57％計算利息，並自96\n    年7月18日起至清償日止，其逾期在6個月以內者，另按上開\n    利率10％，逾期超過6個月以上部分，按上開利率20％計付\n    違約金，於上訴人因繼承被繼承人偉浪黑玳所得遺產限度內\n    ，洵屬有據，應予准許。逾此部分之請求，為無理由，應予\n    駁回。原審就被上訴人之請求不應准許之部分，命上訴人給\n    付超過因繼承被繼承人偉浪黑玳所得遺產限度部分，尚有未\n    洽。上訴意旨指摘原判決此部分不當，為有理由，爰由本院\n    將此部分廢棄，並改判如主文第1、2項所示。原審就被上訴\n    人之請求應准許部分，所為上訴人敗訴判決，核無違誤，上\n    訴意旨，就此部分指摘原判決不當，求予廢棄，為無理由，\n    應駁回其此部分之上訴。\n六、本件事證已臻明確，兩造其餘攻擊防禦方法及立論之證據資\n    料，均經本院審酌後，對判決結果不生影響，爰無庸逐一論\n    述，併此敘明。\n七、據上論結，本件上訴為一部有理由，一部無理由，依民事訴\n    訟法第450條、第449條第1項、第79條、第85條第2項，判決\n    如主文。",
    "reason": "甲、程序方面：按訴訟繫屬中為訴訟標的之法律關係，雖移轉於\n    第三人，於訴訟無影響。但第三人如經兩造同意，得聲請代\n    當事人承當訴訟。前項但書情形，僅他造不同意者，移轉之\n    當事人或第三人得聲請法院裁定許第三人承當訴訟，民事訴\n    訟法第254條第1、2項分別定有明文。查被上訴人（即原審\n    原告）原為合作金庫商業銀行（下稱合作金庫），於原審訴\n    訟程序進行中之98年3月11日，將其對上訴人之債權讓與被\n    上訴人，並將債權讓與之事實公告於報紙，被上訴人為債權\n    受讓人等情，有債權讓與證明書及債權讓與公告可稽（見原\n    審卷第65、66頁），是本債權讓與對債務人已發生效力，訴\n    訟標的法律關係已移轉於被上訴人，被上訴人並於原審98\n    年4月22日言詞辯論期日聲明承當訴訟，且徵得上訴人之同\n    意（見原審訴字卷第58頁），經核於法並無不合，自應准許\n    。\n乙、實體方面：\n一、被上訴人起訴主張：被繼承人（即借款人）偉浪黑玳於95年\n    12月18日向合作金庫借款新台幣（下同）380萬元，期限為\n    20年，利率前2年按定儲指數利率2.11%加碼年息0.33%即以\n    2.44%浮動計息，第3年起按指標利率2.11加碼年息0.93%即\n    以3.04 %浮動計息，第一年繳息，第二年起按月平均攤還本\n    息，如遲延履行時，除仍按上開利率計息外，逾期在6個月\n    以內者，另按上開利率之10%，逾期在6個月以上，按上開利\n    率20%加計違約金（下稱系爭貸款）。詎被繼承人偉浪黑玳\n    自96年6月18日起未依約繳息，尚欠380萬元未清償，依約全\n    部借款已喪失期限利益，視為全部到期。嗣被繼承人偉浪黑\n    玳於96年12月1日死亡，上訴人為其法定繼承人，應繼承被\n    繼承人偉浪黑玳之債務，且上訴人均無聲明拋棄或限定繼承\n    之情事，依法應負連帶清償責任，又上開債權經合作金庫讓\n    與伊，爰依消費借貸及繼承之法律關係，求為命上訴人應連\n    帶給付380萬元，及自96年6月18日起至清償日止，按年息\n    2.57%計算利息，並自96年7月18日起至清償日止，其逾期在\n    6個月以內者，另按上開利率10%，逾期超過6個月以上部分\n    ，按上開利率20%計付違約金之判決。並答辯聲明：上訴駁\n    回。\n二、上訴人則以：依被繼承人偉浪黑玳之消費者貸款申請書所載\n    ，被繼承人偉浪黑玳工作職務擔任保全員，全年收入卻記載\n    100萬元，顯然被上訴人之徵信調查不實，則被上訴人辦理\n    系爭貸款業務既有重大過失，且又以顯不實資料通過被繼承\n    人偉浪黑玳之申請，應自負此授信不實之呆帳之風險；又上\n    訴人與被繼承人偉浪黑玳未同財共居，依民法繼承篇施行法\n    第1條之3第4項規定，上訴人自得主張以所得遺產為限，負\n    清償責任等語，資為抗辯。並上訴聲明：(一)原判決廢棄。\n    (二)被上訴人在第一審之訴及假執行之聲請均駁回。或請判決\n    就上訴人於繼承被繼承人偉浪黑玳之遺產限度內，應給付被\n    上訴人380萬元本息。\n三、被上訴人主張被繼承人（即借款人）偉浪黑玳於95年12月18\n    日向合作金庫借款380萬元，期限為20年，利率前2年按定儲\n    指數利率2.11%加碼年息0.33%即以2.44%浮動計息，第3年起\n    按指標利率2.11加碼年息0.93%即以3.04%浮動計息，第一年\n    繳息，第二年起按月平均攤還本息，如遲延履行時，除仍按\n    上開利率計息外，逾期在6個月以內者，另按上開利率之10%\n    ，逾期在6個月以上，按上開利率20%加計違約金，詎被繼承\n    人偉浪黑玳自96年6月18日起未依約繳息，尚欠380萬元未清\n    償，依約全部借款已喪失期限利益，視為全部到期，又被繼\n    承人偉浪黑玳於96年12月1日死亡，上訴人為其法定繼承人\n    ，且均未聲明拋棄或限定繼承之事實，業經被上訴人提出借\n    貸、其他約定事項、消費者貸款申請書、客戶全部往來帳戶\n    查詢單、印鑑卡、偉浪黑玳之身分證及健保卡影本、銀行分\n    戶交易明細表、預定土地房屋買賣契約書、銀行撥款協議書\n    、戶籍謄本、臺灣高雄地方法院家事庭函、繼承系統表為證\n    （見原審支付命令卷第5至17頁，原審訴字卷第25至45頁）\n    ，上訴人對此並不爭執（見本院卷第28頁背面至29頁），自\n    堪信為真實。\n四、至被上訴人主張上訴人應就被繼承人偉浪黑玳所負系爭貸款\n    380萬元本息及違約金債務，負連帶清償責任等情，則為被\n    上訴人所否認，並以前開情詞置辯。經查：\n（一）上訴人辯稱被上訴人以不實資料通過被繼承人偉浪黑玳之\n      申請，系爭貸款業務顯有重大過失，應自負此授信不實之\n      呆帳風險等情。惟為被上訴人所否認，並主張被繼承人偉\n      浪黑玳因購屋需求，向合作金庫公司借貸，按當時評估計\n      市價價值491萬358元，貸予偉浪黑玳380萬元，購屋成數\n      為77.38%，合乎當時合作金庫內部估定之放款值成數8成\n      以內及銀行法第12條之1自用住宅放款規定，另偉浪黑玳\n      當時向合作金庫申請貸款時所填之申請書經銀行人員確認\n      後，再向財團法人金融聯合徵信中心取得其個人信用資料\n      ，因偉浪黑玳並無不良記錄等，故依當時合作金庫內部房\n      屋貸款相關規範辦理等語。依被上訴人提出系爭貸款申請\n      書所附預定土地買賣契約書、預定房屋買賣契約書觀之（\n      見原審卷25、33至42頁），系爭房地總價為500萬元（土\n      地275萬元、房屋225萬元），被上訴人評估市價後，貸予\n      被繼承人偉浪黑玳380萬元，尚難認有何授信不實情事。\n      上訴人所提出之高雄市三民區歷年行情走勢圖（見本院卷\n      第81頁），為高雄市三民區平均單價，並未針對系爭房屋\n      所在地段、結構、年限等條件做評估，自難遽此認為被上\n      訴人有授信不實情事。上訴人執此主張被上訴人應自負呆\n      帳風險，不得向繼承人求償云云，自不足取。\n（二）次按「繼承在民法繼承編中華民國98年5月22日修正施行\n      前開始，繼承人因不可歸責於己之事由或未同居共財者，\n      於繼承開始時無法知悉繼承債務之存在，致未能於修正施\n      行前之法定期間為限定或拋棄繼承，且由其繼續履行繼承\n      債務顯失公平者，於修正施行後，以所得遺產為限，負清\n      償責任。」民法繼承篇施行法第1之3條第4項定有明文。\n      又上述規定係於98年6月10日配合民法第1148條以下有關\n      概括繼承改採限定繼承而增訂，考民法第1148條以下改採\n      限定繼承之目的，係在於避免繼承人因不知法律而未於法\n      定期間內為限定或拋棄繼承之聲請，致背負繼承債務而影\n      響生計之不合理現象；且如強令繼承人須負無限責任，以\n      其本身固有財產清償，將使繼承人因天外飛來之債務，代\n      代不能脫卸負累，實有違民法公平正義之精神。又因民法\n      修正後之第1148條以下僅適用於修正公布後之繼承案件，\n      對於修正公布前者，固有溯及適用之必要，但為求維護債\n      權人之信賴、法安定性及避免有害交易安全，故於施行法\n      增訂本條並限縮其溯及之範圍，僅適用於98年5月22日前\n      在適用概括繼承舊制下，因不可歸責於繼承人之事由，或\n      未同財共居者，未能在法定期間內為限定或拋棄繼承等原\n      因，致繼承人受其所不知債務拘束，而顯失公平之案件。\n（三）上訴人主張與被繼承人偉浪黑玳長久以來未同財共居，且\n      未自被繼承人取得任何財產，依民法繼承篇施行法第1條\n      之3第4項規定，上訴人得主張以因繼承所得遺產限度負責\n      等情，固為被上訴人所否認。惟查被繼承人偉浪黑玳原住\n      宜蘭縣大同鄉寒溪村寒溪巷35號，於85年10月18日出境，\n      於86年5月10日遷出登記，於86年7月23日入境，於90年5\n      月18日遷入高雄市○○○路185號8樓之2，於96年1月18日\n      遷至高雄市○○○路312巷32號14樓之2；而上訴人甲○○\n      ○於59年1月11日結婚後，於63年11月23日即與戶長辦理\n      分炊，嗣遷至宜蘭縣羅東鎮○○街64之15號，復遷至宜蘭\n      縣大同鄉寒溪村寒溪巷58之2號迄今；上訴人丁○○○於\n      65 年1月1日結婚後，即遷至台北縣烏來鄉忠治村金堰96\n      號迄今；上訴人戊○○於71年10月6日結婚後遷出，於87\n      年8月20日離婚後遷至宜蘭縣羅東鎮○○街180巷15弄23號\n      ，復遷至桃園縣桃園市○○○街263號12樓之4迄今；上訴\n      人己○○則於70年1月8日結婚後，於同年12月7日另立新\n      戶等情；均有上訴人及被繼承人偉浪黑玳之戶籍資料可稽\n      （見本院卷第32、38至43頁）。上訴人主張分別於63年、\n      65年、71年、70年各自嫁娶後，即與被繼承人偉浪黑玳未\n      同居共財，致於96年12月1日繼承開始時，無法知悉被上\n      訴人有繼承債務存在，核與我國習俗，各自成家之手足咸\n      少過問彼此財務情況相符，應堪採信。又除系爭貸款購買\n      之房地外，上訴人並未取得被繼承人偉浪黑玳任何財產，\n      亦未申報被繼承人偉浪黑玳之遺產，而係由被上訴人代位\n      申報，亦有財政部國稅局函附被繼承人偉浪黑玳之遺產稅\n      申報書可稽（見本院卷第50至55頁）。則上訴人因各自嫁\n      娶，已有二、三十年，與被繼承人偉浪黑玳未同居共財，\n      致於繼承開始時無法知悉被上訴人有繼承債務存在；且除\n      系爭貸款購買之房地外，上訴人並未取得被繼承人偉浪黑\n      玳之任何財產，應認被繼承人偉浪黑玳之債務，除由被繼\n      承人偉浪黑玳之遺產清償外，由上訴人繼續履行繼承債務\n      ，顯與前述繼承編修正之精神相違，而顯然有失公平。從\n      而，上訴人主張僅以因繼承被繼承人偉浪黑玳所得遺產限\n      度內，對債權人即被上訴人負清償責任，自屬有據。\n五、綜上所陳，被上訴人請求上訴人應連帶給付380萬元及自96\n    年6月18日起至清償日止，按年息2.57％計算利息，並自96\n    年7月18日起至清償日止，其逾期在6個月以內者，另按上開\n    利率10％，逾期超過6個月以上部分，按上開利率20％計付\n    違約金，於上訴人因繼承被繼承人偉浪黑玳所得遺產限度內\n    ，洵屬有據，應予准許。逾此部分之請求，為無理由，應予\n    駁回。原審就被上訴人之請求不應准許之部分，命上訴人給\n    付超過因繼承被繼承人偉浪黑玳所得遺產限度部分，尚有未\n    洽。上訴意旨指摘原判決此部分不當，為有理由，爰由本院\n    將此部分廢棄，並改判如主文第1、2項所示。原審就被上訴\n    人之請求應准許部分，所為上訴人敗訴判決，核無違誤，上\n    訴意旨，就此部分指摘原判決不當，求予廢棄，為無理由，\n    應駁回其此部分之上訴。\n六、本件事證已臻明確，兩造其餘攻擊防禦方法及立論之證據資\n    料，均經本院審酌後，對判決結果不生影響，爰無庸逐一論\n    述，併此敘明。\n七、據上論結，本件上訴為一部有理由，一部無理由，依民事訴\n    訟法第450條、第449條第1項、第79條、第85條第2項，判決\n    如主文。"
  },
  "characters": {
    "judges": [
      "林金村",
      "王麗莉",
      "李慈惠"
    ],
    "prosecutors": [

    ],
    "lawyers": [
      "楊志航",
      "有",
      "人或其他法定代理人具有"
    ],
    "clerks": [
      "王敬端"
    ],
    "plaintiffs": [

    ],
    "defendants": [

    ],
    "prosecutor_office": [

    ],
    "creditors": [

    ],
    "debtors": [

    ],
    "judicial_associate_officer": [

    ]
  },
  "adjudged_at": "2010-01-05",
  "created_at": "2016-01-05 15:04:40",
  "updated_at": "2016-01-05 15:04:40"
}