{
  "identify": "TPH-98-重上-248-20100105-2",
  "court": {
    "name": "臺灣高等法院",
    "code": "TPH"
  },
  "division": {
    "name": "民事",
    "code": "V"
  },
  "year": 98,
  "word": "重上",
  "number": "248",
  "jcheck": "2",
  "reason": "返還不當得利",
  "content": "臺灣高等法院民事判決                 98年度重上字第248號\n上  訴  人  乙○○\n            辛○\n            戊○○\n            丁○○\n上  三  人\n訴訟代理人  吳宜財律師\n上  訴  人  甲○○\n            庚○○\n上  六  人\n訴訟代理人  游朝義律師\n            林佳穎律師\n被上  訴人  丙○○\n            壬○○\n共      同\n訴訟代理人  李璧合律師\n            陳志雄律師\n上列當事人間返還不當得利事件，上訴人對於中華民國98年3 月\n30日臺灣士林地方法院97年度重訴字第86號第一審判決提起上訴\n，被上訴人並為訴之追加，本院於98年12月22日言詞辯論終結，\n判決如下：\n    主  文\n上訴駁回。\n第二審訴訟費用由上訴人乙○○負擔百分之一，餘由上訴人連帶\n負擔。\n    事實及理由\n一、按在第二審為訴之變更或追加，非經他造同意不得為之。但\n    請求之基礎事實同一者，不在此限，民事訴訟法第446條第1\n    項、第255條第1項第2 款分別定有明文。所謂請求之基礎事\n    實同一，係指變更或追加之訴與原訴之主要爭點有其共同性\n    ，各請求利益之主張在社會生活上可認為同一或關連，而就\n    原請求之訴訟及證據資料，於審理繼續進行在相當程度範圍\n    內具有同一性或一體性，得期待於後請求之審理予以利用，\n    俾先後兩請求在同一程序得加以解決，避免重複審理，進而\n    為統一解決紛爭者，即屬之。本件被上訴人原起訴主張依信\n    託物返還請求權、民法第184條、179條、225條、226條請求\n    上訴人給付，嗣於本院審理中追加借名登記財產返還請求權\n    及民法第541條規定為請求權基礎（見本院卷296頁背面），\n    核其追加之訴與原訴之主要爭點均在於被上訴人與訴外人李\n    清江間之聯名同意承配家產契約書性質為何，且原請求所主\n    張之事實及證據資料得以利用，避免被上訴人於原訴敗訴後\n    再行提起，重複審理，而得於本訴中統一解決紛爭，徵諸前\n    開說明，應許被上訴人為訴之追加，合先敘明。\n二、被上訴人主張：伊等與訴外人己○○、蘇達夫及上訴人辛○\n    、戊○○、丁○○、甲○○、庚○○（以下稱辛○等5 人）\n    之父李清江5 人為兄弟，上訴人乙○○係李清江之妻。民國\n    56年4月15日伊等兄弟5人於母親李張蔥主持下召開「承配家\n    產會議」，將當時全部家產分配予伊等5 人，其中坐落臺北\n    縣汐止鎮北峰里之土地（下稱系爭土地，即臺北縣汐止市○\n    ○段社后頂小段189、195、195-1、196地號土地，嗣分割為\n    如原判決附表所示24筆地號土地）約定承配6 份聯名共業，\n    李清江得1/3，伊等與己○○、蘇達夫4人各得1/6，兄弟5人\n    並簽訂「聯名同意承配家產契約書」（以下稱系爭承配家產\n    契約書）。因系爭土地當時為農地，兄弟乃同意共同委由父\n    母管理耕種，並口頭約定仍繼續登記於李清江名下，暫不為\n    移轉登記，俟將來土地較有價值時再行分配，故伊等就系爭\n    土地應各有1/6 共有權，並與李清江就系爭土地成立信託或\n    借名登記關係。嗣李清江於88年4 月11日死亡，伊等始發現\n    86年間，李清江因與上圓建設股份有限公司（以下稱上圓公\n    司）於系爭土地合建住宅大樓，而領取該公司支付之「道路\n    用地」（即系爭189-5、189-6、195-3、196-2地號土地）之\n    用路權利金2,400 萬元，及88年及92年間，上訴人又因基隆\n    河整治工程，政府徵收系爭189-8、189-16及189-18 地號土\n    地，而分別領取之徵收補償費新臺幣（下同）1億2,790萬7,\n    640元及1,365萬3,644 元，上開金額均尚未分配予伊等。而\n    前開信託或借名登記法律關係已因李清江死亡或伊等以起訴\n    狀繕本送達表示終止時消滅，伊等自得請求上訴人連帶給付\n    上開金額各1/ 6予伊。又上訴人未經伊等之同意，將系爭18\n    9-5、189-6、189-8、195-3及195-2 地號土地，逕行抵繳上\n    訴人應繳之遺產稅9,941萬4,400元，使該部分土地移轉登記\n    於財政部國有財產局，伊等自得以該抵繳之稅額作為該部分\n    土地之價額，請求上訴人連帶返還伊等該土地價額各1/6 。\n    另上訴人擅將系爭195-4、195-6地號土地辦理繼承登記予乙\n    ○○，伊等亦得請求乙○○將系爭195-4、195-6地號土地之\n    所有權應有部分各1/6移轉登記予伊等，依信託或借名登記\n    財產返還請求權、民法第225條、226條、541條、1148條及1\n    153條第1項之規定，求為命上訴人乙○○應將系爭195-4及1\n    95-6地號土地之所有權應有部分各1/6 移轉登記予伊等；上\n    訴人應連帶給付伊等各4,416萬2,614元，及自起訴狀繕本送\n    達翌日起至清償日止，按年息5%計算之利息。原審為被上訴\n    人勝訴之判決，上訴人不服，提起上訴，被上訴人於本院答\n    辯聲明：上訴駁回。\n三、上訴人則以：系爭土地係李清江獨自出資購得，並非被上訴\n    人父母所購買，縱認系爭土地係被上訴人父母購買而登記於\n    李清江名下，惟被上訴人既從未取得系爭土地之所有權，渠\n    等與李清江間自無成立信託或借名登記關係之可能，且系爭\n    土地於系爭家產承配契約書簽立後，仍由李清江之父母耕種\n    使用，並非由李清江代為管理處分，縱認系爭土地有信託或\n    借名登記關係存在，亦係存在於李清江與其父母間。又依系\n    爭承配家產契約書約定，系爭土地本應於系爭承配家產契約\n    書簽約之日，即56年4 月28日即行分配，然被上訴人卻於近\n    40年後始主張權利，其請求權顯已罹於15年之消滅時效期間\n    。李清江於86年間所領取上圓公司支付之2,400 萬元係該公\n    司使用計畫道路（即系爭189-5、189-6、195-3、196-2地號\n    土地）之用路權利金，惟上開金額乃上圓公司就盜刻李清江\n    印章乙事，與李清江達成和解時所給付之損害賠償金，與系\n    爭土地無涉。又抵稅係依法所為之繳稅行為，並非法律上交\n    易所得之對價，抵稅行為並未使上訴人對國稅局產生損害賠\n    償請求權、更未受領任何賠償物，則被上訴人亦無從以請求\n    上訴人讓與或請求交付賠償物為由，請求抵稅之金額。再者\n    ，縱認上訴人因抵繳稅款而受有利益，惟其中超過系爭土地\n    市價之利益，與被上訴人所受損害間並無因果關係，被上訴\n    人至多僅得就系爭土地之市價請求賠償等語，資為抗辯。並\n    上訴聲明：(一)原判決廢棄。(二)上開廢棄部分，被上訴人在第\n    一審之訴及假執行之聲請均駁回。\n四、查被上訴人與訴外人己○○、蘇達夫及上訴人辛○等5 人之\n    父李清江為兄弟關係，上訴人乙○○則係李清江之妻，李清\n    江於88年4 月11日死亡，上訴人為其繼承人，被上訴人與李\n    清江於56年4 月15日，由其母李張蔥主持召開承配家產會議\n    ，決議「社后村北峰里田地（約一甲七分）承配六份聯名共\n    業。一清江得其三分之一地積（係大孫份量在內）二定國、\n    朝圳、達夫、保定各得六分之一地積。」等情。嗣被上訴人\n    與李清江、己○○、蘇達夫於同年月28日簽署系爭承配家產\n    契約書約定：「北峰里之一甲七分之土地承配按六個份量計\n    開：清江兄得其六份之二，其餘六份之四，由定國、朝圳、\n    達夫、保定等四名各得其六份之一為五名聯名之共有地產。\n    」等語。系爭土地中臺北縣汐止市○○段社后頂小段189-8\n    、189-16地號土地於88年間被徵收，補償費1億2,790萬7,6\n    40元；同段189-18地號土地於92年間徵收，補償費1,365萬\n    3,644元，分別由上訴人於88年9月29日、93年12月14日領訖\n    ；另上訴人以坐落同小段189-5、189-6、189-8、195-3、19\n    6-2 地號土地抵繳李清江遺產稅共9,941萬4,400元，復由上\n    訴人乙○○辦理同小段195-4、195-6地號土地之繼承登記等\n    事實，為兩造所不爭，復有戶籍謄本、繼承系統表、會議錄\n    、承配家產契約書、土地登記簿謄本、臺北縣政府地政局函\n    、財政部臺北市國稅局函等件附卷足稽，堪信為真實。\n五、被上訴人主張，依系爭承配家產契約書約定，系爭土地為伊\n    等及己○○、蘇達夫與李清江所共有，僅信託或借名登記予\n    李清江，李清江死亡後，該信託或借名登記契約即終止，或\n    於以訴狀繕本送達上訴人之日終止，上訴人應負返還前開受\n    領之補償費、和解金及抵稅利益之義務，另上訴人乙○○則\n    應將系爭195-4、195-6地號土地應有部分各1/6 移轉登記予\n    伊等等情，為上訴人所否認，並以前揭情詞置辯。經查：\n  (一)依前開承配家產會議錄記載「社后村北峰里田地（約一甲七\n    分）承配六份聯名共業。一清江得其三分之一地積（係大孫\n    份量在內）二定國、朝圳、達夫、保定各得其三分之一地積\n    。」等語（見原審卷第21頁），嗣被上訴人與李清江、己○\n    ○、蘇達夫再簽署系爭聯名同意承配家產契約書約定：「北\n    峰里之一甲七分之土地承配按六個份量計開：清江兄得其六\n    份之二，其餘六份之四，由定國、朝圳、達夫、保定等四名\n    各得其六份之一為五名聯名之共有地產。…田地管理由雙親\n    司事。…三納稅：田賦由五兄弟共同分擔。」等語，再證人\n    即李清江與被上訴人兄弟蘇達夫於原審證稱：「（土地何時\n    買的？）我父母買的，我們兄弟大家約定給哥哥那時候開工\n    廠，工廠招標要用錢，可以週轉資金方便。」、「我們兄弟\n    約定用哥哥李清江的名字登記，以後看田地的價值，再看是\n    否要賣出，這個土地也是父母在耕作的。」、「父母親有表\n    示用大哥名義登記就可以，以後兄弟共分，大哥向父母表示\n    不會侵占兄弟的持分。」、「（一甲七分的農地你有無繳過\n    田賦？）我二哥丙○○在處理，有時候是我去繳，單子就交\n    給我二哥。」、「（70年住宅區土地你們如何分配？）是以\n    贈與方式處理。」、「（李清江78年徵收補償費是否有分配\n    給你們？）有，是他主動分配給我們。」等語（見原審卷第\n    386-389 頁），另證人己○○則於本院證稱：「（當時為何\n    會簽這份承諾書、契約書？）是父母親的意思。」、「（財\n    產是誰的？）父母親的。」、「（父母親有跟你說，地是父\n    母買的？）有。聯名同意承配家產契約書寫多少錢，只有不\n    夠的錢，李清江貼六萬元，那時候李清江有一間鐵工廠，也\n    是父母出錢，估價大約十萬多元，他出六萬元就與十萬元抵\n    掉了。」、「（社后的地，都是誰在管理使用？）都是我父\n    母親，那時候種水稻，割稻後我父母自己去曬穀，一直種到\n    父母親過世。」、「（社后的地，稅都是誰在繳？）大家在\n    繳，我也有繳。大家把錢拿給丙○○去繳，丙○○當時在父\n    母身邊，我也有出錢。」等語（見本院卷第248頁背面-250\n    頁），參以被上訴人所提56年至70年之農地田賦實物繳納單\n    及水利會會費繳納單計54紙（見原審卷第21-24頁、第26-\n    53頁），堪認系爭土地連同其他家產於前開分配家產會議中\n    為分配並作成決議後，再由上訴人與前開證人、李清江簽署\n    同意書，約定系爭土地分予上訴人與前開證人各1/6 之應有\n    部分，嗣雖未即為移轉登記，惟本於兄弟間之約定，仍以李\n    清江名義登記，實際則交由父母耕作，核與當事人約定一方\n    （借名者）經他方（出名者）同意，就屬於一方現在或將來\n    之財產，以他方名義登記為所有人，但無使他方取得實質所\n    有權之借名登記契約相符。是被上訴人主張，伊等就系爭土\n    地各有1/6 權利，並與李清江就系爭土地成立借名登記關係\n    一節，應可採信。徵以系爭土地嗣分割為如原判決附表所示\n    之24筆土地，李清江於70年6月間，將其中189、184-1、189\n    -7 地號土地中之4/6，以贈與名義移轉登記予被上訴人及己\n    ○○、蘇達夫，每人各1/6；又於78年6月15日領取臺北縣汐\n    止市公所發放同小段195-8、195-15地號土地之徵收補償費3\n    ,437,828元及70,000元後，以臺灣省公共建設土地債券（面\n    額50,000元）、支票（面額2,288,552元）分配予其他兄弟4\n    人（含上訴人）等事實，為上訴人所不爭執，並有土地增值\n    稅繳納通知書、贈與稅繳納通知書、臺灣土地銀行新店分行\n    補償費計算單、臺灣省公共建設土地債券、支票等影本（見\n    原審卷第54-57頁、第60-64頁）在卷可按。另被上訴人、\n    己○○、蘇達夫及李清江共同與上圓公司，於79年10月22日\n    就系爭臺北縣汐止市○○段社后頂小段189 地號簽署土地使\n    用權同意書，亦有同意書可稽（見原審卷第402 頁），亦\n    證被上訴人、己○○、蘇達夫與李清江間，確實就系爭土地\n    約定登記於李清江名下，而有借名登記關係存在，否則何須\n    分配前開土地之徵收補償費及聯名與上圓公司簽署土地使用\n    權同意書。而系爭土地既係連同其他家產共同分配，則購買\n    系爭土地者究為李清江或其父母，均無礙李清江與被上訴人\n    等其餘兄弟間前開借名登記契約之成立，上訴人以系爭土地\n    原不動產買賣契約書買受人載明李清江，辯稱系爭土地係李\n    清江單獨出資購得，與被上訴人間無借名登記關係存在云云\n    ，不足憑採。\n  (二)按委任關係，因當事人一方死亡而消滅，但契約另有訂定，\n    或因委任事務之性質，不能消滅者，不在此限；繼承人自繼\n    承開始時，承受被繼承人財產上之一切權利、義務，民法第\n    550 條、第1148條前段分別定有明文。又消滅時效，自請求\n    權可行使時起算，民法第128 條亦有明定。而借名登記契約\n    當事人約定一方將自己財產以他方名義登記，他方允就該財\n    產為出名登記之契約，側重於借名者與出名者間之信任關係\n    ，應類推適用有關民法委任之規定。訴外人李清江已於88年\n    4月11日死亡，類推適用前開民法第550條規定，其與上訴人\n    間之借名登記契約即已消滅。斯時被上訴人本於該契約消滅\n    後之返還請求權始能行使，迄被上訴人於96年3 月28日提起\n    本訴之日止，尚未罹於15年之時效期間，上訴人為時效抗辯\n    ，自不可採。至上訴人稱，被上訴人所提出之稅單，其與李\n    清江共同繳納系爭土地稅賦直至71年為止，此一時點洽與兄\n    弟間召開建地移轉決定之會議時間相同，顯見71年之會議結\n    束後，李清江除將建地分配與兄弟外，兄弟間亦不再共同負\n    擔系爭土地稅賦，顯見該會議之結論除約定建地分配外，應\n    尚有其餘兄弟放棄尚未分配之土地權利之結論云云，未見其\n    舉證證明之，核屬推論之詞，委無可採。\n  (三)查李清江死亡後，上訴人就系爭土地中坐落臺北縣汐止市○\n    ○段社后頂小段195-4及195-6地號土地分割登記予乙○○，\n    已如前述，被上訴人主張，依借名登記財產返還請求權請求\n    上訴人乙○○將前開土地所有權應有部分各1/6 移轉登記予\n    被上訴人，即屬有據，應予准許。\n  (四)次按，受任人因處理委任事務，所收取之金錢、物品及孳息\n    ，應交付於委任人；繼承人對於被繼承人之債務，負連帶責\n    任；解釋意思表示，應探求當事人之真意，不得拘泥於所用\n    之辭句，民法第541條前段、修正前第1153條第1項、第98條\n    分別定有明文。又解釋私人之契約應通觀全文，並斟酌立約\n    當時之情形，及其他一切證據資料為其判斷之標準，不能拘\n    泥字面或截取書句中一二語，任意推解致失真意。被上訴人\n    主張，李清江於86年間領取上圓公司給付2,400 萬元，乃上\n    圓公司使用系爭臺北縣汐止市○○段社后頂小段189-5、189\n    -6、195-3、196-2地號土地作為社區○○道路之用地權利金\n    等情，固為上訴人所否認。惟查，上訴人所提之和解書前言\n    雖記載：「茲因利用李清江私章事宜成立和解」等語，內容\n    則謂：「一上圓建設股份有限公司由於他人傳話錯誤，致誤\n    刻李清江私章一顆使用於汐止市○○段社后頂小段189、189\n    -7地號土地使用權同意書上…二茲經雙方協議結果，上圓建\n    設股份有限公司保證該印章僅使用於上述土地使用權同意書\n    上請領執照外，未曾使用於其他文件…三李清江同意不究追\n    刑事責任，…」等語，可見李清江同意上圓公司得使用其印\n    章於申領執照，並繼續使用系爭土地做為社區道路使用。又\n    上圓公司董事長王光祥、總經理謝魁奮、管理部經理郭文傑\n    及董事陳浴生，於85年7 月間，因規劃興建臺北縣汐止市○\n    ○○路「凱旋大地No.2」電梯大廈（下簡稱凱旋大地），遭\n    住戶聯名以其公共設施占用既成巷道，非該大廈住戶所有，\n    對渠等提出詐欺告訴，案經臺灣士林地方法院檢察署檢察官\n    提起公訴後，王光祥於該刑事詐欺案件審理中供稱：「（中\n    庭是否佔用既成巷道？）中庭及巷道是分開的，既成巷道是\n    地主的，我們有買權利，以後徵收費仍由地主領取。…有向\n    地主買使用權，有付錢給地主李清江買使用權，由陳浴生出\n    面，但地主怕稅捐負擔，所以沒有契約，但有支票。…（到\n    底有無付錢給李清江？何時？共多少？）支付支票已兌現，\n    共七張，當時是由謝魁奮將支票交付給李清江的兒子辛○收\n    取。」等語（見原審卷第417、419、420 頁）。上訴人辛\n    ○復於該案證稱：「（凱旋大地No.2羽球場土地有無同意被\n    告使用？）地是我父親的，有同意被告通行，我收到二千四\n    百萬元。」等語（見原審卷第423 頁），王光祥另於原審\n    到庭證稱：「（提示和解書，是否有和李清江簽署系爭和解\n    書？）確實是我的簽名，…（9 紙支票之和解金和系爭臺北\n    縣汐止市○○段社后頂小段189、189-7地號土地使用權利是\n    否有對價關係？）因為我已經使用這兩筆土地，取得道路使\n    用的權利，他同意我繼續使用，但需要支付他賠償金，連同\n    使用權及賠償金是有對價關係。…（取得臺北縣汐止市○○\n    段社后頂小段189、189-7地號土地使用，沒有誤刻李清江印\n    章蓋在同意書上，需要賠償24,000,000元嗎？）其實也不是\n    誤刻，雙方認知有差距，要使用該地號土地，需要補24,0\n    00,000元給他。（提示辛○證詞，辛○所述是否實在？）依\n    照和解書，當時確實是因為要取得土地使用權利才簽立和解\n    書，但有無接到律師函已經不記得了。…（依照和解書第三\n    條，內容沒有說要取得臺北縣汐止市○○段社后頂小段189\n    、189-7地號土地使用權利，而是就你誤刻李清江印章蓋在\n    土地使用同意書上，李清江同意不追究刑事責任，何以你剛\n    才說系爭24,000,000元是作為取得土地使用的對價？）根本\n    不用提到，因為他不再追究，表示同意我使用。…（當時李\n    清江和你談和解時，是否賠償24,000,000元給李清江後，李\n    清江就不再追究刑事責任，李清江免費給你使用土地？）支\n    付24,000,000元是為了取得土地使用權。」等語（見原審卷\n    第4-8頁），堪認李清江所收取之2,400萬元係上圓公司使\n    用系爭道路之通行費用。且僅盜刻印章，即獲取高達2,400\n    萬元之賠償款，亦與常情不符。觀諸前揭和解書內容，李清\n    江既同意上圓公司使用自行刻用之印章以申請執照，業已補\n    正上開瑕疵，是上訴人辯稱2,400萬元純係上圓公司盜刻李\n    清江印章之賠償款云云，顯不足採。李清江以前開土地供上\n    圓公司做為道路通行使用而取得之補償費2,400萬元，乃受\n    任人受託登記上開土地所收取之金錢，應按被上訴人應有部\n    分比例交付被上訴人，被上訴人本於前開規定請求上訴人等\n    連帶給付各1/6即400萬元，洵屬有據。\n  (五)復按，因不可歸責於債務人之事由，致給付不能者，債務人\n    免給付義務。債務人因前項給付不能之事由，對第三人有損\n    害賠償請求權者，債權人得向債務人請求讓與其損害賠償請\n    求權，或交付其所受領之賠償物，民法第225條第1項、第2\n    項定有明文。又政府基於公權力徵收土地而給予債務人之補\n    償費，雖非侵權行為之賠償，惟係債務人於其所負債務陷於\n    給付不能發生之一種代替利益，此項補償費，債權人非不得\n    類推適用民法第225條第2項之規定，請求讓與或交付其所受\n    領之補償費。上訴人為李清江之共同繼承人，於李清江死亡\n    後負有返還借名登記物之責任，惟依前所述，系爭臺北縣汐\n    止市○○段社后頂小段189-8、189-16 地號土地於88年間被\n    政府徵收，補償費1億2,790萬7,640元；同段189-18 地號土\n    地於92年間被政府徵收，補償費1,365萬3,644元，分別由上\n    訴人於88年9 月29日、93年12月14日領訖，此部分上訴人之\n    返還義務因不可歸責於上訴人之事由致給付不能，被上訴人\n    主張，依前開規定，請求上訴人連帶給付該代替利益各1/6\n    ，即2,359萬3,547元（〈127,907,640＋13,653,644〉×1/6\n    ），自屬正當。\n  (六)再按，因可歸責於債務人之事由，致給付不能者，債權人得\n    請求賠償損害，民法第226條第1項定有明文。上訴人於借名\n    登記關係消滅後，因繼承李清江遺產而被課徵遺產稅，將系\n    爭臺北縣汐止市○○段社后頂小段189-5、189-6、189-8、\n    195-3、196-2地號土地用以抵繳部分遺產稅共9,941萬4,400\n    元，已如前述，則上訴人應連帶返還借名登記物之義務即因\n    可歸責上訴人之事由致給付不能，上訴人自應負連帶賠償義\n    務。查前開土地經國稅局評估而同意上訴人等抵繳其應納之\n    部分遺產稅額9,941萬4,400元，堪認前開土地客觀上有該交\n    易價值，上訴人辯稱，前開土地價值僅抵稅時公告現值之1/\n    10云云，未舉證以明之，尚不可採，是此部分被上訴人各得\n    請求之金額為1,656萬9,067元（99,414,400×1/6，元以下\n    四捨五入），即非無據。\n六、綜上所述，被上訴人主張，其與李清江間之借名登記關係已\n    因李清江死亡而消滅，上訴人負有返還借名登記物及連帶給\n    付補償費、權利金並賠償抵稅款等情，應為可採。從而，被\n    上訴人依借名登記之法律關係、民法第541條、第225第2 項\n    、第226條第1項規定，請求上訴人乙○○將系爭坐落臺北縣\n    汐止市○○段社后頂小段195-4及195-6地號土地之所有權應\n    有部分各1/6 移轉登記予被上訴人，並請求上訴人連帶給付\n    被上訴人各4,416萬2,614元（400萬＋2,359萬3,547＋1,656\n    萬9,067元），及自起訴狀繕本送達翌日即97年4月15日起至\n    清償日止，按年息5%計算之利息，洵屬有據，應予准許。是\n    則原審判命上訴人給付，並為假執行之宣告，經核於法並無\n    不合。上訴論旨，聲明廢棄改判，為無理由，應予駁回。\n七、兩造其餘攻擊防禦方法及未經援用之證據，經本院審酌後認\n    與本判決之論斷不生影響，爰不一一論駁。另前開和解書內\n    容業據辛○、王光祥證述明確，上訴人聲請訊問林清江律師\n    ，核無必要，附此敘明。\n八、據上論結，本件上訴為無理由。依民事訴訟法第449條第1項\n    、第78條、第85條第1項但書、第2項，判決如主文。\n中    華    民    國    99    年    1     月    5     日\n                    民事第十一庭\n                        審判長法  官  鄭雅萍\n                              法  官  徐福晉\n                              法  官  詹文馨\n正本係照原本作成。\n如不服本判決，應於收受送達後20日內向本院提出上訴書狀，其\n未表明上訴理由者，應於提出上訴後20日內向本院補提理由書狀\n（均須按他造當事人之人數附繕本）上訴時應提出委任律師或具\n有律師資格之人之委任狀；委任有律師資格者，另應附具律師資\n格證書及釋明委任人與受任人有民事訴訟法第466 條之1第1項但\n書或第2項（詳附註）所定關係之釋明文書影本。\n中    華    民    國    99    年    1     月    6     日\n                              書記官  洪秋帆\n附註：\n民事訴訟法第466條之1（第1項、第2項）：\n對於第二審判決上訴，上訴人應委任律師為訴訟代理人。但上訴\n人或其他法定代理人具有律師資格者，不在此限。\n上訴人之配偶、三親等內之血親、二親等內之姻親，或上訴人為\n法人、中央或地方機關時，其所屬專任人員具有律師資格並經法\n院認為適當者，亦得為第三審訴訟代理人。",
  "structure": {
    "main": "上訴駁回。\n第二審訴訟費用由上訴人乙○○負擔百分之一，餘由上訴人連帶\n負擔。",
    "fact": "一、按在第二審為訴之變更或追加，非經他造同意不得為之。但\n    請求之基礎事實同一者，不在此限，民事訴訟法第446條第1\n    項、第255條第1項第2 款分別定有明文。所謂請求之基礎事\n    實同一，係指變更或追加之訴與原訴之主要爭點有其共同性\n    ，各請求利益之主張在社會生活上可認為同一或關連，而就\n    原請求之訴訟及證據資料，於審理繼續進行在相當程度範圍\n    內具有同一性或一體性，得期待於後請求之審理予以利用，\n    俾先後兩請求在同一程序得加以解決，避免重複審理，進而\n    為統一解決紛爭者，即屬之。本件被上訴人原起訴主張依信\n    託物返還請求權、民法第184條、179條、225條、226條請求\n    上訴人給付，嗣於本院審理中追加借名登記財產返還請求權\n    及民法第541條規定為請求權基礎（見本院卷296頁背面），\n    核其追加之訴與原訴之主要爭點均在於被上訴人與訴外人李\n    清江間之聯名同意承配家產契約書性質為何，且原請求所主\n    張之事實及證據資料得以利用，避免被上訴人於原訴敗訴後\n    再行提起，重複審理，而得於本訴中統一解決紛爭，徵諸前\n    開說明，應許被上訴人為訴之追加，合先敘明。\n二、被上訴人主張：伊等與訴外人己○○、蘇達夫及上訴人辛○\n    、戊○○、丁○○、甲○○、庚○○（以下稱辛○等5 人）\n    之父李清江5 人為兄弟，上訴人乙○○係李清江之妻。民國\n    56年4月15日伊等兄弟5人於母親李張蔥主持下召開「承配家\n    產會議」，將當時全部家產分配予伊等5 人，其中坐落臺北\n    縣汐止鎮北峰里之土地（下稱系爭土地，即臺北縣汐止市○\n    ○段社后頂小段189、195、195-1、196地號土地，嗣分割為\n    如原判決附表所示24筆地號土地）約定承配6 份聯名共業，\n    李清江得1/3，伊等與己○○、蘇達夫4人各得1/6，兄弟5人\n    並簽訂「聯名同意承配家產契約書」（以下稱系爭承配家產\n    契約書）。因系爭土地當時為農地，兄弟乃同意共同委由父\n    母管理耕種，並口頭約定仍繼續登記於李清江名下，暫不為\n    移轉登記，俟將來土地較有價值時再行分配，故伊等就系爭\n    土地應各有1/6 共有權，並與李清江就系爭土地成立信託或\n    借名登記關係。嗣李清江於88年4 月11日死亡，伊等始發現\n    86年間，李清江因與上圓建設股份有限公司（以下稱上圓公\n    司）於系爭土地合建住宅大樓，而領取該公司支付之「道路\n    用地」（即系爭189-5、189-6、195-3、196-2地號土地）之\n    用路權利金2,400 萬元，及88年及92年間，上訴人又因基隆\n    河整治工程，政府徵收系爭189-8、189-16及189-18 地號土\n    地，而分別領取之徵收補償費新臺幣（下同）1億2,790萬7,\n    640元及1,365萬3,644 元，上開金額均尚未分配予伊等。而\n    前開信託或借名登記法律關係已因李清江死亡或伊等以起訴\n    狀繕本送達表示終止時消滅，伊等自得請求上訴人連帶給付\n    上開金額各1/ 6予伊。又上訴人未經伊等之同意，將系爭18\n    9-5、189-6、189-8、195-3及195-2 地號土地，逕行抵繳上\n    訴人應繳之遺產稅9,941萬4,400元，使該部分土地移轉登記\n    於財政部國有財產局，伊等自得以該抵繳之稅額作為該部分\n    土地之價額，請求上訴人連帶返還伊等該土地價額各1/6 。\n    另上訴人擅將系爭195-4、195-6地號土地辦理繼承登記予乙\n    ○○，伊等亦得請求乙○○將系爭195-4、195-6地號土地之\n    所有權應有部分各1/6移轉登記予伊等，依信託或借名登記\n    財產返還請求權、民法第225條、226條、541條、1148條及1\n    153條第1項之規定，求為命上訴人乙○○應將系爭195-4及1\n    95-6地號土地之所有權應有部分各1/6 移轉登記予伊等；上\n    訴人應連帶給付伊等各4,416萬2,614元，及自起訴狀繕本送\n    達翌日起至清償日止，按年息5%計算之利息。原審為被上訴\n    人勝訴之判決，上訴人不服，提起上訴，被上訴人於本院答\n    辯聲明：上訴駁回。\n三、上訴人則以：系爭土地係李清江獨自出資購得，並非被上訴\n    人父母所購買，縱認系爭土地係被上訴人父母購買而登記於\n    李清江名下，惟被上訴人既從未取得系爭土地之所有權，渠\n    等與李清江間自無成立信託或借名登記關係之可能，且系爭\n    土地於系爭家產承配契約書簽立後，仍由李清江之父母耕種\n    使用，並非由李清江代為管理處分，縱認系爭土地有信託或\n    借名登記關係存在，亦係存在於李清江與其父母間。又依系\n    爭承配家產契約書約定，系爭土地本應於系爭承配家產契約\n    書簽約之日，即56年4 月28日即行分配，然被上訴人卻於近\n    40年後始主張權利，其請求權顯已罹於15年之消滅時效期間\n    。李清江於86年間所領取上圓公司支付之2,400 萬元係該公\n    司使用計畫道路（即系爭189-5、189-6、195-3、196-2地號\n    土地）之用路權利金，惟上開金額乃上圓公司就盜刻李清江\n    印章乙事，與李清江達成和解時所給付之損害賠償金，與系\n    爭土地無涉。又抵稅係依法所為之繳稅行為，並非法律上交\n    易所得之對價，抵稅行為並未使上訴人對國稅局產生損害賠\n    償請求權、更未受領任何賠償物，則被上訴人亦無從以請求\n    上訴人讓與或請求交付賠償物為由，請求抵稅之金額。再者\n    ，縱認上訴人因抵繳稅款而受有利益，惟其中超過系爭土地\n    市價之利益，與被上訴人所受損害間並無因果關係，被上訴\n    人至多僅得就系爭土地之市價請求賠償等語，資為抗辯。並\n    上訴聲明：(一)原判決廢棄。(二)上開廢棄部分，被上訴人在第\n    一審之訴及假執行之聲請均駁回。\n四、查被上訴人與訴外人己○○、蘇達夫及上訴人辛○等5 人之\n    父李清江為兄弟關係，上訴人乙○○則係李清江之妻，李清\n    江於88年4 月11日死亡，上訴人為其繼承人，被上訴人與李\n    清江於56年4 月15日，由其母李張蔥主持召開承配家產會議\n    ，決議「社后村北峰里田地（約一甲七分）承配六份聯名共\n    業。一清江得其三分之一地積（係大孫份量在內）二定國、\n    朝圳、達夫、保定各得六分之一地積。」等情。嗣被上訴人\n    與李清江、己○○、蘇達夫於同年月28日簽署系爭承配家產\n    契約書約定：「北峰里之一甲七分之土地承配按六個份量計\n    開：清江兄得其六份之二，其餘六份之四，由定國、朝圳、\n    達夫、保定等四名各得其六份之一為五名聯名之共有地產。\n    」等語。系爭土地中臺北縣汐止市○○段社后頂小段189-8\n    、189-16地號土地於88年間被徵收，補償費1億2,790萬7,6\n    40元；同段189-18地號土地於92年間徵收，補償費1,365萬\n    3,644元，分別由上訴人於88年9月29日、93年12月14日領訖\n    ；另上訴人以坐落同小段189-5、189-6、189-8、195-3、19\n    6-2 地號土地抵繳李清江遺產稅共9,941萬4,400元，復由上\n    訴人乙○○辦理同小段195-4、195-6地號土地之繼承登記等\n    事實，為兩造所不爭，復有戶籍謄本、繼承系統表、會議錄\n    、承配家產契約書、土地登記簿謄本、臺北縣政府地政局函\n    、財政部臺北市國稅局函等件附卷足稽，堪信為真實。\n五、被上訴人主張，依系爭承配家產契約書約定，系爭土地為伊\n    等及己○○、蘇達夫與李清江所共有，僅信託或借名登記予\n    李清江，李清江死亡後，該信託或借名登記契約即終止，或\n    於以訴狀繕本送達上訴人之日終止，上訴人應負返還前開受\n    領之補償費、和解金及抵稅利益之義務，另上訴人乙○○則\n    應將系爭195-4、195-6地號土地應有部分各1/6 移轉登記予\n    伊等等情，為上訴人所否認，並以前揭情詞置辯。經查：\n  (一)依前開承配家產會議錄記載「社后村北峰里田地（約一甲七\n    分）承配六份聯名共業。一清江得其三分之一地積（係大孫\n    份量在內）二定國、朝圳、達夫、保定各得其三分之一地積\n    。」等語（見原審卷第21頁），嗣被上訴人與李清江、己○\n    ○、蘇達夫再簽署系爭聯名同意承配家產契約書約定：「北\n    峰里之一甲七分之土地承配按六個份量計開：清江兄得其六\n    份之二，其餘六份之四，由定國、朝圳、達夫、保定等四名\n    各得其六份之一為五名聯名之共有地產。…田地管理由雙親\n    司事。…三納稅：田賦由五兄弟共同分擔。」等語，再證人\n    即李清江與被上訴人兄弟蘇達夫於原審證稱：「（土地何時\n    買的？）我父母買的，我們兄弟大家約定給哥哥那時候開工\n    廠，工廠招標要用錢，可以週轉資金方便。」、「我們兄弟\n    約定用哥哥李清江的名字登記，以後看田地的價值，再看是\n    否要賣出，這個土地也是父母在耕作的。」、「父母親有表\n    示用大哥名義登記就可以，以後兄弟共分，大哥向父母表示\n    不會侵占兄弟的持分。」、「（一甲七分的農地你有無繳過\n    田賦？）我二哥丙○○在處理，有時候是我去繳，單子就交\n    給我二哥。」、「（70年住宅區土地你們如何分配？）是以\n    贈與方式處理。」、「（李清江78年徵收補償費是否有分配\n    給你們？）有，是他主動分配給我們。」等語（見原審卷第\n    386-389 頁），另證人己○○則於本院證稱：「（當時為何\n    會簽這份承諾書、契約書？）是父母親的意思。」、「（財\n    產是誰的？）父母親的。」、「（父母親有跟你說，地是父\n    母買的？）有。聯名同意承配家產契約書寫多少錢，只有不\n    夠的錢，李清江貼六萬元，那時候李清江有一間鐵工廠，也\n    是父母出錢，估價大約十萬多元，他出六萬元就與十萬元抵\n    掉了。」、「（社后的地，都是誰在管理使用？）都是我父\n    母親，那時候種水稻，割稻後我父母自己去曬穀，一直種到\n    父母親過世。」、「（社后的地，稅都是誰在繳？）大家在\n    繳，我也有繳。大家把錢拿給丙○○去繳，丙○○當時在父\n    母身邊，我也有出錢。」等語（見本院卷第248頁背面-250\n    頁），參以被上訴人所提56年至70年之農地田賦實物繳納單\n    及水利會會費繳納單計54紙（見原審卷第21-24頁、第26-\n    53頁），堪認系爭土地連同其他家產於前開分配家產會議中\n    為分配並作成決議後，再由上訴人與前開證人、李清江簽署\n    同意書，約定系爭土地分予上訴人與前開證人各1/6 之應有\n    部分，嗣雖未即為移轉登記，惟本於兄弟間之約定，仍以李\n    清江名義登記，實際則交由父母耕作，核與當事人約定一方\n    （借名者）經他方（出名者）同意，就屬於一方現在或將來\n    之財產，以他方名義登記為所有人，但無使他方取得實質所\n    有權之借名登記契約相符。是被上訴人主張，伊等就系爭土\n    地各有1/6 權利，並與李清江就系爭土地成立借名登記關係\n    一節，應可採信。徵以系爭土地嗣分割為如原判決附表所示\n    之24筆土地，李清江於70年6月間，將其中189、184-1、189\n    -7 地號土地中之4/6，以贈與名義移轉登記予被上訴人及己\n    ○○、蘇達夫，每人各1/6；又於78年6月15日領取臺北縣汐\n    止市公所發放同小段195-8、195-15地號土地之徵收補償費3\n    ,437,828元及70,000元後，以臺灣省公共建設土地債券（面\n    額50,000元）、支票（面額2,288,552元）分配予其他兄弟4\n    人（含上訴人）等事實，為上訴人所不爭執，並有土地增值\n    稅繳納通知書、贈與稅繳納通知書、臺灣土地銀行新店分行\n    補償費計算單、臺灣省公共建設土地債券、支票等影本（見\n    原審卷第54-57頁、第60-64頁）在卷可按。另被上訴人、\n    己○○、蘇達夫及李清江共同與上圓公司，於79年10月22日\n    就系爭臺北縣汐止市○○段社后頂小段189 地號簽署土地使\n    用權同意書，亦有同意書可稽（見原審卷第402 頁），亦\n    證被上訴人、己○○、蘇達夫與李清江間，確實就系爭土地\n    約定登記於李清江名下，而有借名登記關係存在，否則何須\n    分配前開土地之徵收補償費及聯名與上圓公司簽署土地使用\n    權同意書。而系爭土地既係連同其他家產共同分配，則購買\n    系爭土地者究為李清江或其父母，均無礙李清江與被上訴人\n    等其餘兄弟間前開借名登記契約之成立，上訴人以系爭土地\n    原不動產買賣契約書買受人載明李清江，辯稱系爭土地係李\n    清江單獨出資購得，與被上訴人間無借名登記關係存在云云\n    ，不足憑採。\n  (二)按委任關係，因當事人一方死亡而消滅，但契約另有訂定，\n    或因委任事務之性質，不能消滅者，不在此限；繼承人自繼\n    承開始時，承受被繼承人財產上之一切權利、義務，民法第\n    550 條、第1148條前段分別定有明文。又消滅時效，自請求\n    權可行使時起算，民法第128 條亦有明定。而借名登記契約\n    當事人約定一方將自己財產以他方名義登記，他方允就該財\n    產為出名登記之契約，側重於借名者與出名者間之信任關係\n    ，應類推適用有關民法委任之規定。訴外人李清江已於88年\n    4月11日死亡，類推適用前開民法第550條規定，其與上訴人\n    間之借名登記契約即已消滅。斯時被上訴人本於該契約消滅\n    後之返還請求權始能行使，迄被上訴人於96年3 月28日提起\n    本訴之日止，尚未罹於15年之時效期間，上訴人為時效抗辯\n    ，自不可採。至上訴人稱，被上訴人所提出之稅單，其與李\n    清江共同繳納系爭土地稅賦直至71年為止，此一時點洽與兄\n    弟間召開建地移轉決定之會議時間相同，顯見71年之會議結\n    束後，李清江除將建地分配與兄弟外，兄弟間亦不再共同負\n    擔系爭土地稅賦，顯見該會議之結論除約定建地分配外，應\n    尚有其餘兄弟放棄尚未分配之土地權利之結論云云，未見其\n    舉證證明之，核屬推論之詞，委無可採。\n  (三)查李清江死亡後，上訴人就系爭土地中坐落臺北縣汐止市○\n    ○段社后頂小段195-4及195-6地號土地分割登記予乙○○，\n    已如前述，被上訴人主張，依借名登記財產返還請求權請求\n    上訴人乙○○將前開土地所有權應有部分各1/6 移轉登記予\n    被上訴人，即屬有據，應予准許。\n  (四)次按，受任人因處理委任事務，所收取之金錢、物品及孳息\n    ，應交付於委任人；繼承人對於被繼承人之債務，負連帶責\n    任；解釋意思表示，應探求當事人之真意，不得拘泥於所用\n    之辭句，民法第541條前段、修正前第1153條第1項、第98條\n    分別定有明文。又解釋私人之契約應通觀全文，並斟酌立約\n    當時之情形，及其他一切證據資料為其判斷之標準，不能拘\n    泥字面或截取書句中一二語，任意推解致失真意。被上訴人\n    主張，李清江於86年間領取上圓公司給付2,400 萬元，乃上\n    圓公司使用系爭臺北縣汐止市○○段社后頂小段189-5、189\n    -6、195-3、196-2地號土地作為社區○○道路之用地權利金\n    等情，固為上訴人所否認。惟查，上訴人所提之和解書前言\n    雖記載：「茲因利用李清江私章事宜成立和解」等語，內容\n    則謂：「一上圓建設股份有限公司由於他人傳話錯誤，致誤\n    刻李清江私章一顆使用於汐止市○○段社后頂小段189、189\n    -7地號土地使用權同意書上…二茲經雙方協議結果，上圓建\n    設股份有限公司保證該印章僅使用於上述土地使用權同意書\n    上請領執照外，未曾使用於其他文件…三李清江同意不究追\n    刑事責任，…」等語，可見李清江同意上圓公司得使用其印\n    章於申領執照，並繼續使用系爭土地做為社區道路使用。又\n    上圓公司董事長王光祥、總經理謝魁奮、管理部經理郭文傑\n    及董事陳浴生，於85年7 月間，因規劃興建臺北縣汐止市○\n    ○○路「凱旋大地No.2」電梯大廈（下簡稱凱旋大地），遭\n    住戶聯名以其公共設施占用既成巷道，非該大廈住戶所有，\n    對渠等提出詐欺告訴，案經臺灣士林地方法院檢察署檢察官\n    提起公訴後，王光祥於該刑事詐欺案件審理中供稱：「（中\n    庭是否佔用既成巷道？）中庭及巷道是分開的，既成巷道是\n    地主的，我們有買權利，以後徵收費仍由地主領取。…有向\n    地主買使用權，有付錢給地主李清江買使用權，由陳浴生出\n    面，但地主怕稅捐負擔，所以沒有契約，但有支票。…（到\n    底有無付錢給李清江？何時？共多少？）支付支票已兌現，\n    共七張，當時是由謝魁奮將支票交付給李清江的兒子辛○收\n    取。」等語（見原審卷第417、419、420 頁）。上訴人辛\n    ○復於該案證稱：「（凱旋大地No.2羽球場土地有無同意被\n    告使用？）地是我父親的，有同意被告通行，我收到二千四\n    百萬元。」等語（見原審卷第423 頁），王光祥另於原審\n    到庭證稱：「（提示和解書，是否有和李清江簽署系爭和解\n    書？）確實是我的簽名，…（9 紙支票之和解金和系爭臺北\n    縣汐止市○○段社后頂小段189、189-7地號土地使用權利是\n    否有對價關係？）因為我已經使用這兩筆土地，取得道路使\n    用的權利，他同意我繼續使用，但需要支付他賠償金，連同\n    使用權及賠償金是有對價關係。…（取得臺北縣汐止市○○\n    段社后頂小段189、189-7地號土地使用，沒有誤刻李清江印\n    章蓋在同意書上，需要賠償24,000,000元嗎？）其實也不是\n    誤刻，雙方認知有差距，要使用該地號土地，需要補24,0\n    00,000元給他。（提示辛○證詞，辛○所述是否實在？）依\n    照和解書，當時確實是因為要取得土地使用權利才簽立和解\n    書，但有無接到律師函已經不記得了。…（依照和解書第三\n    條，內容沒有說要取得臺北縣汐止市○○段社后頂小段189\n    、189-7地號土地使用權利，而是就你誤刻李清江印章蓋在\n    土地使用同意書上，李清江同意不追究刑事責任，何以你剛\n    才說系爭24,000,000元是作為取得土地使用的對價？）根本\n    不用提到，因為他不再追究，表示同意我使用。…（當時李\n    清江和你談和解時，是否賠償24,000,000元給李清江後，李\n    清江就不再追究刑事責任，李清江免費給你使用土地？）支\n    付24,000,000元是為了取得土地使用權。」等語（見原審卷\n    第4-8頁），堪認李清江所收取之2,400萬元係上圓公司使\n    用系爭道路之通行費用。且僅盜刻印章，即獲取高達2,400\n    萬元之賠償款，亦與常情不符。觀諸前揭和解書內容，李清\n    江既同意上圓公司使用自行刻用之印章以申請執照，業已補\n    正上開瑕疵，是上訴人辯稱2,400萬元純係上圓公司盜刻李\n    清江印章之賠償款云云，顯不足採。李清江以前開土地供上\n    圓公司做為道路通行使用而取得之補償費2,400萬元，乃受\n    任人受託登記上開土地所收取之金錢，應按被上訴人應有部\n    分比例交付被上訴人，被上訴人本於前開規定請求上訴人等\n    連帶給付各1/6即400萬元，洵屬有據。\n  (五)復按，因不可歸責於債務人之事由，致給付不能者，債務人\n    免給付義務。債務人因前項給付不能之事由，對第三人有損\n    害賠償請求權者，債權人得向債務人請求讓與其損害賠償請\n    求權，或交付其所受領之賠償物，民法第225條第1項、第2\n    項定有明文。又政府基於公權力徵收土地而給予債務人之補\n    償費，雖非侵權行為之賠償，惟係債務人於其所負債務陷於\n    給付不能發生之一種代替利益，此項補償費，債權人非不得\n    類推適用民法第225條第2項之規定，請求讓與或交付其所受\n    領之補償費。上訴人為李清江之共同繼承人，於李清江死亡\n    後負有返還借名登記物之責任，惟依前所述，系爭臺北縣汐\n    止市○○段社后頂小段189-8、189-16 地號土地於88年間被\n    政府徵收，補償費1億2,790萬7,640元；同段189-18 地號土\n    地於92年間被政府徵收，補償費1,365萬3,644元，分別由上\n    訴人於88年9 月29日、93年12月14日領訖，此部分上訴人之\n    返還義務因不可歸責於上訴人之事由致給付不能，被上訴人\n    主張，依前開規定，請求上訴人連帶給付該代替利益各1/6\n    ，即2,359萬3,547元（〈127,907,640＋13,653,644〉×1/6\n    ），自屬正當。\n  (六)再按，因可歸責於債務人之事由，致給付不能者，債權人得\n    請求賠償損害，民法第226條第1項定有明文。上訴人於借名\n    登記關係消滅後，因繼承李清江遺產而被課徵遺產稅，將系\n    爭臺北縣汐止市○○段社后頂小段189-5、189-6、189-8、\n    195-3、196-2地號土地用以抵繳部分遺產稅共9,941萬4,400\n    元，已如前述，則上訴人應連帶返還借名登記物之義務即因\n    可歸責上訴人之事由致給付不能，上訴人自應負連帶賠償義\n    務。查前開土地經國稅局評估而同意上訴人等抵繳其應納之\n    部分遺產稅額9,941萬4,400元，堪認前開土地客觀上有該交\n    易價值，上訴人辯稱，前開土地價值僅抵稅時公告現值之1/\n    10云云，未舉證以明之，尚不可採，是此部分被上訴人各得\n    請求之金額為1,656萬9,067元（99,414,400×1/6，元以下\n    四捨五入），即非無據。\n六、綜上所述，被上訴人主張，其與李清江間之借名登記關係已\n    因李清江死亡而消滅，上訴人負有返還借名登記物及連帶給\n    付補償費、權利金並賠償抵稅款等情，應為可採。從而，被\n    上訴人依借名登記之法律關係、民法第541條、第225第2 項\n    、第226條第1項規定，請求上訴人乙○○將系爭坐落臺北縣\n    汐止市○○段社后頂小段195-4及195-6地號土地之所有權應\n    有部分各1/6 移轉登記予被上訴人，並請求上訴人連帶給付\n    被上訴人各4,416萬2,614元（400萬＋2,359萬3,547＋1,656\n    萬9,067元），及自起訴狀繕本送達翌日即97年4月15日起至\n    清償日止，按年息5%計算之利息，洵屬有據，應予准許。是\n    則原審判命上訴人給付，並為假執行之宣告，經核於法並無\n    不合。上訴論旨，聲明廢棄改判，為無理由，應予駁回。\n七、兩造其餘攻擊防禦方法及未經援用之證據，經本院審酌後認\n    與本判決之論斷不生影響，爰不一一論駁。另前開和解書內\n    容業據辛○、王光祥證述明確，上訴人聲請訊問林清江律師\n    ，核無必要，附此敘明。\n八、據上論結，本件上訴為無理由。依民事訴訟法第449條第1項\n    、第78條、第85條第1項但書、第2項，判決如主文。",
    "reason": "一、按在第二審為訴之變更或追加，非經他造同意不得為之。但\n    請求之基礎事實同一者，不在此限，民事訴訟法第446條第1\n    項、第255條第1項第2 款分別定有明文。所謂請求之基礎事\n    實同一，係指變更或追加之訴與原訴之主要爭點有其共同性\n    ，各請求利益之主張在社會生活上可認為同一或關連，而就\n    原請求之訴訟及證據資料，於審理繼續進行在相當程度範圍\n    內具有同一性或一體性，得期待於後請求之審理予以利用，\n    俾先後兩請求在同一程序得加以解決，避免重複審理，進而\n    為統一解決紛爭者，即屬之。本件被上訴人原起訴主張依信\n    託物返還請求權、民法第184條、179條、225條、226條請求\n    上訴人給付，嗣於本院審理中追加借名登記財產返還請求權\n    及民法第541條規定為請求權基礎（見本院卷296頁背面），\n    核其追加之訴與原訴之主要爭點均在於被上訴人與訴外人李\n    清江間之聯名同意承配家產契約書性質為何，且原請求所主\n    張之事實及證據資料得以利用，避免被上訴人於原訴敗訴後\n    再行提起，重複審理，而得於本訴中統一解決紛爭，徵諸前\n    開說明，應許被上訴人為訴之追加，合先敘明。\n二、被上訴人主張：伊等與訴外人己○○、蘇達夫及上訴人辛○\n    、戊○○、丁○○、甲○○、庚○○（以下稱辛○等5 人）\n    之父李清江5 人為兄弟，上訴人乙○○係李清江之妻。民國\n    56年4月15日伊等兄弟5人於母親李張蔥主持下召開「承配家\n    產會議」，將當時全部家產分配予伊等5 人，其中坐落臺北\n    縣汐止鎮北峰里之土地（下稱系爭土地，即臺北縣汐止市○\n    ○段社后頂小段189、195、195-1、196地號土地，嗣分割為\n    如原判決附表所示24筆地號土地）約定承配6 份聯名共業，\n    李清江得1/3，伊等與己○○、蘇達夫4人各得1/6，兄弟5人\n    並簽訂「聯名同意承配家產契約書」（以下稱系爭承配家產\n    契約書）。因系爭土地當時為農地，兄弟乃同意共同委由父\n    母管理耕種，並口頭約定仍繼續登記於李清江名下，暫不為\n    移轉登記，俟將來土地較有價值時再行分配，故伊等就系爭\n    土地應各有1/6 共有權，並與李清江就系爭土地成立信託或\n    借名登記關係。嗣李清江於88年4 月11日死亡，伊等始發現\n    86年間，李清江因與上圓建設股份有限公司（以下稱上圓公\n    司）於系爭土地合建住宅大樓，而領取該公司支付之「道路\n    用地」（即系爭189-5、189-6、195-3、196-2地號土地）之\n    用路權利金2,400 萬元，及88年及92年間，上訴人又因基隆\n    河整治工程，政府徵收系爭189-8、189-16及189-18 地號土\n    地，而分別領取之徵收補償費新臺幣（下同）1億2,790萬7,\n    640元及1,365萬3,644 元，上開金額均尚未分配予伊等。而\n    前開信託或借名登記法律關係已因李清江死亡或伊等以起訴\n    狀繕本送達表示終止時消滅，伊等自得請求上訴人連帶給付\n    上開金額各1/ 6予伊。又上訴人未經伊等之同意，將系爭18\n    9-5、189-6、189-8、195-3及195-2 地號土地，逕行抵繳上\n    訴人應繳之遺產稅9,941萬4,400元，使該部分土地移轉登記\n    於財政部國有財產局，伊等自得以該抵繳之稅額作為該部分\n    土地之價額，請求上訴人連帶返還伊等該土地價額各1/6 。\n    另上訴人擅將系爭195-4、195-6地號土地辦理繼承登記予乙\n    ○○，伊等亦得請求乙○○將系爭195-4、195-6地號土地之\n    所有權應有部分各1/6移轉登記予伊等，依信託或借名登記\n    財產返還請求權、民法第225條、226條、541條、1148條及1\n    153條第1項之規定，求為命上訴人乙○○應將系爭195-4及1\n    95-6地號土地之所有權應有部分各1/6 移轉登記予伊等；上\n    訴人應連帶給付伊等各4,416萬2,614元，及自起訴狀繕本送\n    達翌日起至清償日止，按年息5%計算之利息。原審為被上訴\n    人勝訴之判決，上訴人不服，提起上訴，被上訴人於本院答\n    辯聲明：上訴駁回。\n三、上訴人則以：系爭土地係李清江獨自出資購得，並非被上訴\n    人父母所購買，縱認系爭土地係被上訴人父母購買而登記於\n    李清江名下，惟被上訴人既從未取得系爭土地之所有權，渠\n    等與李清江間自無成立信託或借名登記關係之可能，且系爭\n    土地於系爭家產承配契約書簽立後，仍由李清江之父母耕種\n    使用，並非由李清江代為管理處分，縱認系爭土地有信託或\n    借名登記關係存在，亦係存在於李清江與其父母間。又依系\n    爭承配家產契約書約定，系爭土地本應於系爭承配家產契約\n    書簽約之日，即56年4 月28日即行分配，然被上訴人卻於近\n    40年後始主張權利，其請求權顯已罹於15年之消滅時效期間\n    。李清江於86年間所領取上圓公司支付之2,400 萬元係該公\n    司使用計畫道路（即系爭189-5、189-6、195-3、196-2地號\n    土地）之用路權利金，惟上開金額乃上圓公司就盜刻李清江\n    印章乙事，與李清江達成和解時所給付之損害賠償金，與系\n    爭土地無涉。又抵稅係依法所為之繳稅行為，並非法律上交\n    易所得之對價，抵稅行為並未使上訴人對國稅局產生損害賠\n    償請求權、更未受領任何賠償物，則被上訴人亦無從以請求\n    上訴人讓與或請求交付賠償物為由，請求抵稅之金額。再者\n    ，縱認上訴人因抵繳稅款而受有利益，惟其中超過系爭土地\n    市價之利益，與被上訴人所受損害間並無因果關係，被上訴\n    人至多僅得就系爭土地之市價請求賠償等語，資為抗辯。並\n    上訴聲明：(一)原判決廢棄。(二)上開廢棄部分，被上訴人在第\n    一審之訴及假執行之聲請均駁回。\n四、查被上訴人與訴外人己○○、蘇達夫及上訴人辛○等5 人之\n    父李清江為兄弟關係，上訴人乙○○則係李清江之妻，李清\n    江於88年4 月11日死亡，上訴人為其繼承人，被上訴人與李\n    清江於56年4 月15日，由其母李張蔥主持召開承配家產會議\n    ，決議「社后村北峰里田地（約一甲七分）承配六份聯名共\n    業。一清江得其三分之一地積（係大孫份量在內）二定國、\n    朝圳、達夫、保定各得六分之一地積。」等情。嗣被上訴人\n    與李清江、己○○、蘇達夫於同年月28日簽署系爭承配家產\n    契約書約定：「北峰里之一甲七分之土地承配按六個份量計\n    開：清江兄得其六份之二，其餘六份之四，由定國、朝圳、\n    達夫、保定等四名各得其六份之一為五名聯名之共有地產。\n    」等語。系爭土地中臺北縣汐止市○○段社后頂小段189-8\n    、189-16地號土地於88年間被徵收，補償費1億2,790萬7,6\n    40元；同段189-18地號土地於92年間徵收，補償費1,365萬\n    3,644元，分別由上訴人於88年9月29日、93年12月14日領訖\n    ；另上訴人以坐落同小段189-5、189-6、189-8、195-3、19\n    6-2 地號土地抵繳李清江遺產稅共9,941萬4,400元，復由上\n    訴人乙○○辦理同小段195-4、195-6地號土地之繼承登記等\n    事實，為兩造所不爭，復有戶籍謄本、繼承系統表、會議錄\n    、承配家產契約書、土地登記簿謄本、臺北縣政府地政局函\n    、財政部臺北市國稅局函等件附卷足稽，堪信為真實。\n五、被上訴人主張，依系爭承配家產契約書約定，系爭土地為伊\n    等及己○○、蘇達夫與李清江所共有，僅信託或借名登記予\n    李清江，李清江死亡後，該信託或借名登記契約即終止，或\n    於以訴狀繕本送達上訴人之日終止，上訴人應負返還前開受\n    領之補償費、和解金及抵稅利益之義務，另上訴人乙○○則\n    應將系爭195-4、195-6地號土地應有部分各1/6 移轉登記予\n    伊等等情，為上訴人所否認，並以前揭情詞置辯。經查：\n  (一)依前開承配家產會議錄記載「社后村北峰里田地（約一甲七\n    分）承配六份聯名共業。一清江得其三分之一地積（係大孫\n    份量在內）二定國、朝圳、達夫、保定各得其三分之一地積\n    。」等語（見原審卷第21頁），嗣被上訴人與李清江、己○\n    ○、蘇達夫再簽署系爭聯名同意承配家產契約書約定：「北\n    峰里之一甲七分之土地承配按六個份量計開：清江兄得其六\n    份之二，其餘六份之四，由定國、朝圳、達夫、保定等四名\n    各得其六份之一為五名聯名之共有地產。…田地管理由雙親\n    司事。…三納稅：田賦由五兄弟共同分擔。」等語，再證人\n    即李清江與被上訴人兄弟蘇達夫於原審證稱：「（土地何時\n    買的？）我父母買的，我們兄弟大家約定給哥哥那時候開工\n    廠，工廠招標要用錢，可以週轉資金方便。」、「我們兄弟\n    約定用哥哥李清江的名字登記，以後看田地的價值，再看是\n    否要賣出，這個土地也是父母在耕作的。」、「父母親有表\n    示用大哥名義登記就可以，以後兄弟共分，大哥向父母表示\n    不會侵占兄弟的持分。」、「（一甲七分的農地你有無繳過\n    田賦？）我二哥丙○○在處理，有時候是我去繳，單子就交\n    給我二哥。」、「（70年住宅區土地你們如何分配？）是以\n    贈與方式處理。」、「（李清江78年徵收補償費是否有分配\n    給你們？）有，是他主動分配給我們。」等語（見原審卷第\n    386-389 頁），另證人己○○則於本院證稱：「（當時為何\n    會簽這份承諾書、契約書？）是父母親的意思。」、「（財\n    產是誰的？）父母親的。」、「（父母親有跟你說，地是父\n    母買的？）有。聯名同意承配家產契約書寫多少錢，只有不\n    夠的錢，李清江貼六萬元，那時候李清江有一間鐵工廠，也\n    是父母出錢，估價大約十萬多元，他出六萬元就與十萬元抵\n    掉了。」、「（社后的地，都是誰在管理使用？）都是我父\n    母親，那時候種水稻，割稻後我父母自己去曬穀，一直種到\n    父母親過世。」、「（社后的地，稅都是誰在繳？）大家在\n    繳，我也有繳。大家把錢拿給丙○○去繳，丙○○當時在父\n    母身邊，我也有出錢。」等語（見本院卷第248頁背面-250\n    頁），參以被上訴人所提56年至70年之農地田賦實物繳納單\n    及水利會會費繳納單計54紙（見原審卷第21-24頁、第26-\n    53頁），堪認系爭土地連同其他家產於前開分配家產會議中\n    為分配並作成決議後，再由上訴人與前開證人、李清江簽署\n    同意書，約定系爭土地分予上訴人與前開證人各1/6 之應有\n    部分，嗣雖未即為移轉登記，惟本於兄弟間之約定，仍以李\n    清江名義登記，實際則交由父母耕作，核與當事人約定一方\n    （借名者）經他方（出名者）同意，就屬於一方現在或將來\n    之財產，以他方名義登記為所有人，但無使他方取得實質所\n    有權之借名登記契約相符。是被上訴人主張，伊等就系爭土\n    地各有1/6 權利，並與李清江就系爭土地成立借名登記關係\n    一節，應可採信。徵以系爭土地嗣分割為如原判決附表所示\n    之24筆土地，李清江於70年6月間，將其中189、184-1、189\n    -7 地號土地中之4/6，以贈與名義移轉登記予被上訴人及己\n    ○○、蘇達夫，每人各1/6；又於78年6月15日領取臺北縣汐\n    止市公所發放同小段195-8、195-15地號土地之徵收補償費3\n    ,437,828元及70,000元後，以臺灣省公共建設土地債券（面\n    額50,000元）、支票（面額2,288,552元）分配予其他兄弟4\n    人（含上訴人）等事實，為上訴人所不爭執，並有土地增值\n    稅繳納通知書、贈與稅繳納通知書、臺灣土地銀行新店分行\n    補償費計算單、臺灣省公共建設土地債券、支票等影本（見\n    原審卷第54-57頁、第60-64頁）在卷可按。另被上訴人、\n    己○○、蘇達夫及李清江共同與上圓公司，於79年10月22日\n    就系爭臺北縣汐止市○○段社后頂小段189 地號簽署土地使\n    用權同意書，亦有同意書可稽（見原審卷第402 頁），亦\n    證被上訴人、己○○、蘇達夫與李清江間，確實就系爭土地\n    約定登記於李清江名下，而有借名登記關係存在，否則何須\n    分配前開土地之徵收補償費及聯名與上圓公司簽署土地使用\n    權同意書。而系爭土地既係連同其他家產共同分配，則購買\n    系爭土地者究為李清江或其父母，均無礙李清江與被上訴人\n    等其餘兄弟間前開借名登記契約之成立，上訴人以系爭土地\n    原不動產買賣契約書買受人載明李清江，辯稱系爭土地係李\n    清江單獨出資購得，與被上訴人間無借名登記關係存在云云\n    ，不足憑採。\n  (二)按委任關係，因當事人一方死亡而消滅，但契約另有訂定，\n    或因委任事務之性質，不能消滅者，不在此限；繼承人自繼\n    承開始時，承受被繼承人財產上之一切權利、義務，民法第\n    550 條、第1148條前段分別定有明文。又消滅時效，自請求\n    權可行使時起算，民法第128 條亦有明定。而借名登記契約\n    當事人約定一方將自己財產以他方名義登記，他方允就該財\n    產為出名登記之契約，側重於借名者與出名者間之信任關係\n    ，應類推適用有關民法委任之規定。訴外人李清江已於88年\n    4月11日死亡，類推適用前開民法第550條規定，其與上訴人\n    間之借名登記契約即已消滅。斯時被上訴人本於該契約消滅\n    後之返還請求權始能行使，迄被上訴人於96年3 月28日提起\n    本訴之日止，尚未罹於15年之時效期間，上訴人為時效抗辯\n    ，自不可採。至上訴人稱，被上訴人所提出之稅單，其與李\n    清江共同繳納系爭土地稅賦直至71年為止，此一時點洽與兄\n    弟間召開建地移轉決定之會議時間相同，顯見71年之會議結\n    束後，李清江除將建地分配與兄弟外，兄弟間亦不再共同負\n    擔系爭土地稅賦，顯見該會議之結論除約定建地分配外，應\n    尚有其餘兄弟放棄尚未分配之土地權利之結論云云，未見其\n    舉證證明之，核屬推論之詞，委無可採。\n  (三)查李清江死亡後，上訴人就系爭土地中坐落臺北縣汐止市○\n    ○段社后頂小段195-4及195-6地號土地分割登記予乙○○，\n    已如前述，被上訴人主張，依借名登記財產返還請求權請求\n    上訴人乙○○將前開土地所有權應有部分各1/6 移轉登記予\n    被上訴人，即屬有據，應予准許。\n  (四)次按，受任人因處理委任事務，所收取之金錢、物品及孳息\n    ，應交付於委任人；繼承人對於被繼承人之債務，負連帶責\n    任；解釋意思表示，應探求當事人之真意，不得拘泥於所用\n    之辭句，民法第541條前段、修正前第1153條第1項、第98條\n    分別定有明文。又解釋私人之契約應通觀全文，並斟酌立約\n    當時之情形，及其他一切證據資料為其判斷之標準，不能拘\n    泥字面或截取書句中一二語，任意推解致失真意。被上訴人\n    主張，李清江於86年間領取上圓公司給付2,400 萬元，乃上\n    圓公司使用系爭臺北縣汐止市○○段社后頂小段189-5、189\n    -6、195-3、196-2地號土地作為社區○○道路之用地權利金\n    等情，固為上訴人所否認。惟查，上訴人所提之和解書前言\n    雖記載：「茲因利用李清江私章事宜成立和解」等語，內容\n    則謂：「一上圓建設股份有限公司由於他人傳話錯誤，致誤\n    刻李清江私章一顆使用於汐止市○○段社后頂小段189、189\n    -7地號土地使用權同意書上…二茲經雙方協議結果，上圓建\n    設股份有限公司保證該印章僅使用於上述土地使用權同意書\n    上請領執照外，未曾使用於其他文件…三李清江同意不究追\n    刑事責任，…」等語，可見李清江同意上圓公司得使用其印\n    章於申領執照，並繼續使用系爭土地做為社區道路使用。又\n    上圓公司董事長王光祥、總經理謝魁奮、管理部經理郭文傑\n    及董事陳浴生，於85年7 月間，因規劃興建臺北縣汐止市○\n    ○○路「凱旋大地No.2」電梯大廈（下簡稱凱旋大地），遭\n    住戶聯名以其公共設施占用既成巷道，非該大廈住戶所有，\n    對渠等提出詐欺告訴，案經臺灣士林地方法院檢察署檢察官\n    提起公訴後，王光祥於該刑事詐欺案件審理中供稱：「（中\n    庭是否佔用既成巷道？）中庭及巷道是分開的，既成巷道是\n    地主的，我們有買權利，以後徵收費仍由地主領取。…有向\n    地主買使用權，有付錢給地主李清江買使用權，由陳浴生出\n    面，但地主怕稅捐負擔，所以沒有契約，但有支票。…（到\n    底有無付錢給李清江？何時？共多少？）支付支票已兌現，\n    共七張，當時是由謝魁奮將支票交付給李清江的兒子辛○收\n    取。」等語（見原審卷第417、419、420 頁）。上訴人辛\n    ○復於該案證稱：「（凱旋大地No.2羽球場土地有無同意被\n    告使用？）地是我父親的，有同意被告通行，我收到二千四\n    百萬元。」等語（見原審卷第423 頁），王光祥另於原審\n    到庭證稱：「（提示和解書，是否有和李清江簽署系爭和解\n    書？）確實是我的簽名，…（9 紙支票之和解金和系爭臺北\n    縣汐止市○○段社后頂小段189、189-7地號土地使用權利是\n    否有對價關係？）因為我已經使用這兩筆土地，取得道路使\n    用的權利，他同意我繼續使用，但需要支付他賠償金，連同\n    使用權及賠償金是有對價關係。…（取得臺北縣汐止市○○\n    段社后頂小段189、189-7地號土地使用，沒有誤刻李清江印\n    章蓋在同意書上，需要賠償24,000,000元嗎？）其實也不是\n    誤刻，雙方認知有差距，要使用該地號土地，需要補24,0\n    00,000元給他。（提示辛○證詞，辛○所述是否實在？）依\n    照和解書，當時確實是因為要取得土地使用權利才簽立和解\n    書，但有無接到律師函已經不記得了。…（依照和解書第三\n    條，內容沒有說要取得臺北縣汐止市○○段社后頂小段189\n    、189-7地號土地使用權利，而是就你誤刻李清江印章蓋在\n    土地使用同意書上，李清江同意不追究刑事責任，何以你剛\n    才說系爭24,000,000元是作為取得土地使用的對價？）根本\n    不用提到，因為他不再追究，表示同意我使用。…（當時李\n    清江和你談和解時，是否賠償24,000,000元給李清江後，李\n    清江就不再追究刑事責任，李清江免費給你使用土地？）支\n    付24,000,000元是為了取得土地使用權。」等語（見原審卷\n    第4-8頁），堪認李清江所收取之2,400萬元係上圓公司使\n    用系爭道路之通行費用。且僅盜刻印章，即獲取高達2,400\n    萬元之賠償款，亦與常情不符。觀諸前揭和解書內容，李清\n    江既同意上圓公司使用自行刻用之印章以申請執照，業已補\n    正上開瑕疵，是上訴人辯稱2,400萬元純係上圓公司盜刻李\n    清江印章之賠償款云云，顯不足採。李清江以前開土地供上\n    圓公司做為道路通行使用而取得之補償費2,400萬元，乃受\n    任人受託登記上開土地所收取之金錢，應按被上訴人應有部\n    分比例交付被上訴人，被上訴人本於前開規定請求上訴人等\n    連帶給付各1/6即400萬元，洵屬有據。\n  (五)復按，因不可歸責於債務人之事由，致給付不能者，債務人\n    免給付義務。債務人因前項給付不能之事由，對第三人有損\n    害賠償請求權者，債權人得向債務人請求讓與其損害賠償請\n    求權，或交付其所受領之賠償物，民法第225條第1項、第2\n    項定有明文。又政府基於公權力徵收土地而給予債務人之補\n    償費，雖非侵權行為之賠償，惟係債務人於其所負債務陷於\n    給付不能發生之一種代替利益，此項補償費，債權人非不得\n    類推適用民法第225條第2項之規定，請求讓與或交付其所受\n    領之補償費。上訴人為李清江之共同繼承人，於李清江死亡\n    後負有返還借名登記物之責任，惟依前所述，系爭臺北縣汐\n    止市○○段社后頂小段189-8、189-16 地號土地於88年間被\n    政府徵收，補償費1億2,790萬7,640元；同段189-18 地號土\n    地於92年間被政府徵收，補償費1,365萬3,644元，分別由上\n    訴人於88年9 月29日、93年12月14日領訖，此部分上訴人之\n    返還義務因不可歸責於上訴人之事由致給付不能，被上訴人\n    主張，依前開規定，請求上訴人連帶給付該代替利益各1/6\n    ，即2,359萬3,547元（〈127,907,640＋13,653,644〉×1/6\n    ），自屬正當。\n  (六)再按，因可歸責於債務人之事由，致給付不能者，債權人得\n    請求賠償損害，民法第226條第1項定有明文。上訴人於借名\n    登記關係消滅後，因繼承李清江遺產而被課徵遺產稅，將系\n    爭臺北縣汐止市○○段社后頂小段189-5、189-6、189-8、\n    195-3、196-2地號土地用以抵繳部分遺產稅共9,941萬4,400\n    元，已如前述，則上訴人應連帶返還借名登記物之義務即因\n    可歸責上訴人之事由致給付不能，上訴人自應負連帶賠償義\n    務。查前開土地經國稅局評估而同意上訴人等抵繳其應納之\n    部分遺產稅額9,941萬4,400元，堪認前開土地客觀上有該交\n    易價值，上訴人辯稱，前開土地價值僅抵稅時公告現值之1/\n    10云云，未舉證以明之，尚不可採，是此部分被上訴人各得\n    請求之金額為1,656萬9,067元（99,414,400×1/6，元以下\n    四捨五入），即非無據。\n六、綜上所述，被上訴人主張，其與李清江間之借名登記關係已\n    因李清江死亡而消滅，上訴人負有返還借名登記物及連帶給\n    付補償費、權利金並賠償抵稅款等情，應為可採。從而，被\n    上訴人依借名登記之法律關係、民法第541條、第225第2 項\n    、第226條第1項規定，請求上訴人乙○○將系爭坐落臺北縣\n    汐止市○○段社后頂小段195-4及195-6地號土地之所有權應\n    有部分各1/6 移轉登記予被上訴人，並請求上訴人連帶給付\n    被上訴人各4,416萬2,614元（400萬＋2,359萬3,547＋1,656\n    萬9,067元），及自起訴狀繕本送達翌日即97年4月15日起至\n    清償日止，按年息5%計算之利息，洵屬有據，應予准許。是\n    則原審判命上訴人給付，並為假執行之宣告，經核於法並無\n    不合。上訴論旨，聲明廢棄改判，為無理由，應予駁回。\n七、兩造其餘攻擊防禦方法及未經援用之證據，經本院審酌後認\n    與本判決之論斷不生影響，爰不一一論駁。另前開和解書內\n    容業據辛○、王光祥證述明確，上訴人聲請訊問林清江律師\n    ，核無必要，附此敘明。\n八、據上論結，本件上訴為無理由。依民事訴訟法第449條第1項\n    、第78條、第85條第1項但書、第2項，判決如主文。"
  },
  "characters": {
    "judges": [
      "鄭雅萍",
      "徐福晉",
      "詹文馨"
    ],
    "prosecutors": [

    ],
    "lawyers": [
      "吳宜財",
      "游朝義",
      "林佳穎",
      "李璧合",
      "陳志雄",
      "有",
      "人或其他法定代理人具有"
    ],
    "clerks": [
      "洪秋帆"
    ],
    "plaintiffs": [

    ],
    "defendants": [

    ],
    "prosecutor_office": [

    ],
    "creditors": [

    ],
    "debtors": [

    ],
    "judicial_associate_officer": [

    ]
  },
  "adjudged_at": "2010-01-05",
  "created_at": "2016-01-05 15:05:23",
  "updated_at": "2016-01-05 15:05:23"
}