{
  "identify": "TPH-98-聲-3896-20100104-1",
  "court": {
    "name": "臺灣高等法院",
    "code": "TPH"
  },
  "division": {
    "name": "刑事",
    "code": "M"
  },
  "year": 98,
  "word": "聲",
  "number": "3896",
  "jcheck": "1",
  "reason": "聲請定其應執行刑",
  "content": "臺灣高等法院刑事裁定                  98年度聲字第3896號\n聲  請  人    臺灣高等法院檢察署檢察官\n受  刑  人    甲○○\n上列聲請人因受刑人數罪併罰有二裁判以上，聲請定其應執行之\n刑，本院裁定如下：\n    主  文\n甲○○所犯如附表所示各罪所處之刑，應執行有期徒刑柒年陸月\n，併科罰金新臺幣拾壹萬元，罰金如易服勞役，以新臺幣壹仟元\n折算壹日。\n    理  由\n一、受刑人甲○○因違反槍砲彈藥刀械管制條例等罪，經臺灣板\n    橋地方法院及本院先後判處如附表所示之刑，並均經分別確\n    定在案。茲檢察官聲請就各罪之有期徒刑及併科罰金部分定\n    其應執行之刑，本院審核認聲請為正當，應定其應執行之刑\n    ，並諭知罰金如易服勞役之折算標準\n二、爰依刑事訴訟法第四百七十七條第一項、刑法第五十三條、\n    第五十一條第五款、第七款、第四十二條第三項前段，裁定\n    如主文。\n中    華    民    國   九十九   年   一   月    四    日\n                  刑事第四庭審判長法  官  陳筱珮\n                                  法  官  孫惠琳\n                                  法  官  陳玉雲\n以上正本證明與原本無異。\n如不服本裁定，應於收受送達後五日內向本院提出抗告狀。\n                                  書記官  陳思云\n中    華    民    國    99    年    1     月    4     日\n",
  "structure": {
    "main": "甲○○所犯如附表所示各罪所處之刑，應執行有期徒刑柒年陸月\n，併科罰金新臺幣拾壹萬元，罰金如易服勞役，以新臺幣壹仟元\n折算壹日。",
    "reason": "一、受刑人甲○○因違反槍砲彈藥刀械管制條例等罪，經臺灣板\n    橋地方法院及本院先後判處如附表所示之刑，並均經分別確\n    定在案。茲檢察官聲請就各罪之有期徒刑及併科罰金部分定\n    其應執行之刑，本院審核認聲請為正當，應定其應執行之刑\n    ，並諭知罰金如易服勞役之折算標準\n二、爰依刑事訴訟法第四百七十七條第一項、刑法第五十三條、\n    第五十一條第五款、第七款、第四十二條第三項前段，裁定\n    如主文。"
  },
  "characters": {
    "judges": [
      "陳筱珮",
      "孫惠琳",
      "陳玉雲"
    ],
    "prosecutors": [

    ],
    "lawyers": [

    ],
    "clerks": [
      "陳思云"
    ],
    "plaintiffs": [

    ],
    "defendants": [

    ],
    "prosecutor_office": [
      "臺灣高等法院檢察署檢察官"
    ],
    "creditors": [

    ],
    "debtors": [

    ],
    "judicial_associate_officer": [

    ]
  },
  "adjudged_at": "2010-01-04",
  "created_at": "2016-01-05 14:35:01",
  "updated_at": "2016-01-05 14:35:01"
}