{
  "identify": "TPH-99-上訴-1176-20100512-1",
  "court": {
    "name": "臺灣高等法院",
    "code": "TPH"
  },
  "division": {
    "name": "刑事",
    "code": "M"
  },
  "year": 99,
  "word": "上訴",
  "number": "1176",
  "jcheck": "1",
  "reason": "誣告",
  "content": "臺灣高等法院刑事判決                99年度上訴字第1176號\n上  訴  人\n即  被  告  乙○○\n上列上訴人因誣告案件，不服臺灣桃園地方法院98年度訴字第74\n4號，中華民國99年1月26日第一審判決（起訴案號：臺灣桃園地\n方法院檢察署98年度偵字第10855號），提起上訴，本院判決如\n下：\n    主  文\n上訴駁回。\n    事  實\n一、乙○○於民國94年間向甲○○之妻子呂珠娟借貸新臺幣（下\n    同）232萬元，原約定於同年5月間清償，惟屆期乙○○未償\n    還，甲○○遂於同年9月19日代理呂珠娟委託一統徵信股份\n    有限公司（以下稱一統公司）派員為其催討債務，甲○○、\n    呂珠娟、一統公司職員徐文燿及乙○○等人嗣於同年10月3\n    日在桃園縣桃園市○○路、大興西路口之「大樹咖啡」店進\n    行商談，約定變賣乙○○擔任負責人之衛主星數位科技股份\n    有限公司設備，抵償債務共30萬元後，乙○○即避不見面，\n    迄至翌年（即95年）7月6日，始應某一姓名年籍不詳之梁姓\n    成年男子之邀約，由其友人嚴智傑及姓名年籍不詳綽號「小\n    君」之成年男子陪同，再次前往「大樹咖啡」店，並出於自\n    由意志，在該處簽具其向甲○○借款20萬元之借據，同時簽\n    發票號651876號、發票日95年7月6日、到期日95年7月20日\n    、發票人乙○○、面額20萬元之本票（以下簡稱本件本票）\n    ，於本件本票背面以其母周豔月之名義背書後，將該借據及\n    本票交予該梁姓男子（乙○○涉嫌偽造私文書部分未經起訴\n    ），該梁姓男子再於95年10月間透過一統公司副理劉順昌轉\n    交予甲○○。嗣甲○○持本件本票，以受讓呂美珠所轉讓債\n    權之地位，於96年1月30日向臺灣桃園地方院聲請取得95年\n    度票字第17050號裁定，再向同院民事執行處聲請強制執行\n    ，經同院以96年度執字第40614號查封乙○○所有之動產，\n    並定97年2月4日進行第一次拍賣。詎乙○○明知甲○○並未\n    指使他人對其出言恐嚇，惟避免其所有之動產遭法院拍賣，\n    竟萌生使甲○○受刑事訴追之意圖，於97年1月21日某時許\n    ，基於誣告犯意，在某不詳處，書寫虛捏：「告訴人乙○○\n    、被告甲○○。…告訴人從未自被告處收取20萬元或其他對\n    價關係，詎料被告卻據本人於95年7月6日遭脅迫所簽之本票\n    採取諸般行為，更甚者其據此藉公權力執行強制處分，其玩\n    法濫行，詳述如後：95年7月6日告訴人接獲一自稱姓梁之男\n    士（電話0000000000）謂：你找死阿！我現在在你家樓下，\n    你媽一個人在家裡，並言明係甲○○叫他來的，你不出來我\n    就…等語，致使告訴人心生畏懼遂答應其要求前往桃園市○\n    ○路大樹咖啡館後強迫簽下本件本票，並強迫告訴人於背書\n    人處簽下告訴人母親周豔月之姓名，該本票為非法取得，告\n    訴人自無給付之義務，惟被告已據此向臺灣桃園地方法院民\n    事執行處96年執字第40614號給付票款強制執行事件查封動\n    產，並於97.2.4第一次拍賣…」之刑事告訴狀，旋於同年1\n    月23日向該管公務員即臺灣桃園地方法院檢察署檢察官誣指\n    甲○○指使該梁姓男子共同涉嫌犯恐嚇及強制等罪，嗣經檢\n    察官偵查結果，認甲○○並無乙○○所指犯行，於97年10月\n    9日以97年度偵字第15793號不起訴處分書對甲○○予以不起\n    訴處分確定。\n二、案經甲○○訴由臺灣桃園地方法院檢察署檢察官偵查起訴。\n    理  由\n壹、證據能力部分\n一、按被告以外之人於審判外之言詞或書面陳述，除法律有規定\n    者外，不得作為證據。又被告以外之人於審判外之陳述，雖\n    不符前4 條之規定，而經當事人於審判程序同意作為證據，\n    法院審酌該言詞陳述或書面陳述作成時之情況，認為適當者\n    ，亦得為證據；當事人、代理人或辯護人於法院調查證據時\n    ，知有第159條第1項不得為證據之情形，而未於言詞辯論終\n    結前聲明異議者，視為有前項同意。刑事訴訟法第159條第1\n    項、第159條之5分別定有明文。\n二、有關本件判決所引用之被告以外之人於審判外陳述之證據能\n    力，上訴人即被告乙○○於本院審理時已表示無意見，迄於\n    言詞辯論終結前亦未爭執，本院審酌該等陳述作成時之情況\n    ，並無違法取證及證明力過低之瑕疵，亦認以之作為證據為\n    適當，依前揭規定說明，自有證據能力。\n貳、實體部分：\n一、訊據被告於矢口否認有使甲○○受刑事處分而誣告之犯行，\n    辯稱：95年7月6日前幾日，確有自稱姓梁的男子打電話給被\n    告，表示：「你欠甲○○的錢，你給我出來，你不要躲，我\n    現在在你家樓下，你媽媽一個人在裡面，你不回來你就試試\n    看」等恐嚇之語，並於7月6日當日在大樹咖啡要求被告還甲\n    ○○20萬元並簽發本票，嚇稱：「不簽的話，就不要想走出\n    這個門」，被告因心生恐懼，遂簽發本件本票，並以其母周\n    豔月之名義在本票背面背書，甲○○雖自始至終均未曾出面\n    ，然因梁姓男子於95年7月6日曾出示甲○○簽發委託其公司\n    處理債務之委託書，嗣後甲○○又以被告遭恐嚇後簽發之本\n    件本票至法院聲請95年度促字第48490號支付命令，是其主\n    觀上認知梁姓男子係經甲○○指示向其恐嚇云云。上訴理由\n    狀並謂：\n（一）原判決於事實欄既認定被告係向甲○○之妻呂珠娟借貸23\n      2萬元，於理由欄又稱「被告明知其尚有積欠甲○○之妻\n      子呂珠娟借貸金額，該筆債務已委甲○○出面催討之情事\n      ，竟於刑事告狀上記載甲○○與其之間並無任何債權債務\n      關係而擅持本件本票向本院聲請強制執行等語，顯屬虛枉\n      （妄），已有可議」。原判決既認本件借貸係存於被告與\n      呂珠娟之間，卻又認被告所稱其與甲○○間無任何債權債\n      務關係，其事實與理由顯屬矛盾。\n（二）原判決理由另稱「前開刑事告訴狀該狀紙之被告欄位已明\n      確記載告訴人「甲○○』及其地址，而告訴事實中亦明確\n      記載該名男子陳稱其係受甲○○指使而為恐嚇行為等文字\n      」云云。惟觀被告告訴狀之內容，並無任指訴甲○○親自\n      或指使梁姓男子對被告為恐嚇行為之記載，僅稱遭梁姓男\n      子電話恐嚇云云，並未稱係甲○○所指使，原判決上揭理\n      由與卷內告訴狀內容所載，尚有未符。\n二、然查：\n（一）被告於97年1月21日不詳地點，書寫其上記載甲○○涉嫌\n      恐嚇等如事實欄第一項所載內容犯行之刑事告訴狀，並於\n      同年月23日，向臺灣桃園地方法院檢察署遞狀，對甲○○\n      提出刑事告訴等情，為被告所不爭執，復有該刑事告訴狀\n      附卷可稽（見臺灣桃園地方法院檢察署97年度他字第516\n      號卷第1頁第至3頁），此部分事實自堪認定。\n（二）被告於94年間向甲○○之妻子呂珠娟借貸232萬元，原約\n      定於同年5月間清償，被告屆期未為償還，甲○○遂於同\n      年9月19日代理呂珠娟委託一統公司為其催討債務，甲○\n      ○、呂珠娟、一統公司職員徐文燿及被告等人，嗣於同年\n      10月3日在桃園縣桃園市○○路、大興西路口之「大樹咖\n      啡」商談，約定變賣被告擔任負責人之衛主星數位科技股\n      份有限公司設備，抵償債務共30萬元後，被告即避不見面\n      ，至95年7月前，均拒未清償其他款項等情，業據告訴人\n      即證人甲○○、徐文燿於原審證述明確（見原審98年度訴\n      字第744號卷第61頁至第72頁），並有被告所簽發本票、\n      支票及借據在卷可稽（見原審卷第14頁至第16頁）。細譯\n      前開借據上貸款人記載「甲○○」，而甲○○先前亦曾與\n      妻子共同前往大樹咖啡店協談債務處理等情，應認被告於\n      95年7月6日簽發本件本票前，已知其尚積欠甲○○之妻子\n      呂珠娟借款未償，而該筆債權既經呂珠娟委由甲○○出面\n      催討，被告在簽立上開以甲○○為債權人之借據前，亦可\n      推知呂珠娟係將借款債權轉讓予甲○○行使，其竟於刑事\n      告訴狀指稱甲○○與被告之間並無任何債權債務關係而擅\n      持本件本票向法院聲請強制執行云云，核其此部分指訴內\n      容，已明顯偏離事實。\n（三）被告所簽發本件本票，係於95年10月間由一統公司副理劉\n      順昌轉交予甲○○，並由甲○○持之向臺灣桃園地方法院\n      聲請取得95年度票字第17050號裁定，再向同法院民事執\n      行處聲請強制執行，經同法院以96年度執字第40614號查\n      封被告所有之動產等情，經告訴人即證人甲○○於原審證\n      述明確（見原審98年度訴字第744號卷第61頁至第72頁）\n      ，並有本件本票影本（見原審95年度票字第17050號卷第5\n      頁）、臺灣桃園地方法院95年度票字第17050號裁定、96\n      年度抗字第18號裁定、同法院96年9月17日桃院木執96年\n      執宇字第40614號、96年12月19日桃院木執96年執宇字第4\n      0614號民事執行處通知在卷可稽（見臺灣桃園地方法院檢\n      察署97年度他字第516號偵查卷第6頁至第9頁）。證人甲\n      ○○於原審堅稱：「委任一統公司時，我並沒有指示他們\n      用什麼方法催討被告欠我的債務，委託之後我也沒有過問\n      催討過程。」等語（見同前原審卷第62頁背面），故本件\n      應釐清者，即為：１、被告於95年7月6日前或當日在大樹\n      咖啡，有否遭受梁姓男子恐嚇、脅迫，因心生畏懼而簽發\n      本件本票？２、若有前開情事，該名梁姓男子之行為是否\n      為甲○○授權而為之？被告是否可合理認定甲○○係指示\n      梁姓男子向其恐嚇之人，而對其提起恐嚇告訴？\n（四）據證人嚴智傑於原審證稱：「（95年7月6日）當天，被告\n      打電話給我要我去他公司找他，沒有刻意要我找其他人一\n      起去，只是當時我剛好跟另一個朋友在一起，才共同前往\n      被告公司，到了以後，被告邀我跟他一起去喝咖啡，當時\n      沒有提到要跟別人談判事情，後來被告開車載我們去大樹\n      咖啡，當時還是公開營業的時間，我們走進去以後，有一\n      桌大概4、5個人一起站起來，被告就自己主動走到那一桌\n      去，我們跟著被告也要在同桌坐下時，那一群人就叫我們\n      坐在別桌。後來我聽到對方有人對被告說：『如果今天沒\n      有給他們交代，就不可能讓被告走』的意思，對方講話態\n      度蠻兇的，但沒有聽到他們說很明顯恐嚇、威脅的語句，\n      後來被告有簽了一張本票，對方有表示本件本票先當作償\n      還的部分，其他再約時間談，後來他們拿了本票就離開，\n      只說：『若你不處理，我會找你媽媽處理。』，我問被告\n      是何事，他說是跟合夥人債務的問題，然後我們就走了。\n      」等語（見同前原審卷第64頁至第72頁）。因此，在95年\n      7月6日當天，證人嚴智傑並未在大樹咖啡店內聽到對方表\n      示明顯恐嚇、脅迫之語句。再衡諸常情，若被告於95年7\n      月6日前曾遭不明人士於電話中為恐嚇：「你找死阿！我\n      現在在你家樓下，你媽一個人在家裡，係甲○○叫我來的\n      ，你不出來我就…」云云，則其邀請友人嚴智傑同行前往\n      大樹咖啡時，理當應向嚴智傑透露其前曾遭恐嚇乙節，並\n      要求嚴智傑尋覓其他能協助保護其人身安全之人手共同前\n      往談判處所，以被告所指稱之案發處所即大樹咖啡店，為\n      公眾得出入之場所，參酌被告明知其前往大樹咖啡店係為\n      商談債務解決，又刻意找友人嚴俊傑陪同前往，若有他人\n      恐嚇被告並迫使被告簽發本票等情，被告應可向近在咫尺\n      之嚴智傑表達求助之意，至遲在對方離去後，亦可立刻告\n      知嚴智傑其遭恐嚇之詳細情節，並商討因應對策，惟被告\n      捨此不為，僅向嚴智傑表示係處理合夥人間債務問題，其\n      反應顯與遭受恐嚇、脅迫而甫簽發本票之人有異。被告空\n      言指稱其於案發前及當日係遭他人恐嚇、脅迫而簽發本件\n      本票云云，顯屬無據。\n（五）又被告辯稱其遭恐嚇之時間為95年7月6日及其前數日，然\n      其於該日前後均未曾向司法警察或偵查機關報案以爭取時\n      效保全證據，此為被告所自承。甲○○持本件本票向臺灣\n      桃園地方法院聲請95年度票字第17050號裁定准予執行後\n      ，被告於95年12月間提出抗告，其自行書寫之抗告狀亦僅\n      聲明：「（一）本件本票裁定事件並未有任何交付之事實\n      。（二）原債權早經裁定並清償中。」等語（見原審96年\n      度抗字第18號卷第7頁至第9頁），並未指述本件本票係遭\n      人恐嚇而簽發之隻字片語。再甲○○亦曾於95年11月1日\n      以本件本票背書人即被告之母周艷月為相對人，向臺灣桃\n      園地方法院聲請取得95年度促字第48490號支付命令，經\n      周艷月聲明異議後，同法院以95年度壢簡字第1508號給付\n      票款案件審理，被告坦承該案審理期間，其聯絡地址即為\n      其母周艷月桃園縣中壢市○○○街13號8樓住所地（見同\n      前原審卷第11頁背面），當知悉甲○○已以周艷月為本件\n      本票背書人為由，請求給付票款一事，惟原審法院民事庭\n      於96年3月2日傳訊被告以證人身分出庭說明時，被告未到\n      庭說明該票係遭人恐嚇而簽發，致其以其母名義背書之事\n      （見原審95年度壢簡字第1508號卷第21頁至第24頁），被\n      告於涉及本件本票之民事案件期間，均未曾於審理過程以\n      言詞或書面方式向法院陳述其遭恐嚇情事，卻遲至本件本\n      票裁定確定，經臺灣桃園地方法院以96年12月19日桃院木\n      執96年執宇字第40614號民事執行處通知業已執行查封其\n      動產，將定於97年2月4日進行拍賣之際，乃於97年1月23\n      日，具狀指控甲○○提出刑事告訴，此顯與一般人遭暴力\n      殘害後隨即向司法警察或偵查機關報告，並於法院審理期\n      間，把握所有可能之機會提出答辯說明等反應相違。被告\n      指稱其於95年7月6日前及當日在大樹咖啡，因遭恐嚇、脅\n      迫而簽發本件本票，顯屬虛妄不實。而被告所提前開告訴\n      案，經臺灣桃園地方法院檢察署檢察官偵查終結後，亦認\n      定甲○○並無被告所指訴之恐嚇及強制等犯行，以甲○○\n      犯罪嫌疑不足為由，予以處分不起訴，有臺灣桃園地方法\n      院檢察署97年度偵字第15793號不起訴處分書在案可稽。\n（六）被告以證人嚴智傑曾於原審證稱：「（95年7月6日）當天\n      ，對方有4、5個人，指著被告說如果不給他們一個交代，\n      不給他離開…」等語，辯稱認被告於簽發本票當日之意識\n      自由確遭壓制，被告無誣告犯行云云。然行為人確否有恐\n      嚇行為，應由整體客觀情狀（包含行為之場所、氣氛、後\n      續之發展）判斷，不得單以行為人曾為某單一言語即斷章\n      取義認定其所言屬恐嚇之舉，證人嚴智傑於原審明確證稱\n      其與被告等進入大樹咖啡店時，仍屬營業時間，而該咖啡\n      店為公開營業之場所，對方雖有4、5人於現場等候，然被\n      告方面亦由嚴智傑及另一名友人共計3人陪同到場，被告\n      方面人數上並未居於絕對劣勢，證人嚴智傑並未見對造手\n      上持有其他武器，而除前開言語外，與被告商議債務處理\n      之對方亦無其他暴力舉動或為其他恐嚇之語，縱有不詳姓\n      名之男子曾為前語，依當時整體客觀環境，亦難認被告僅\n      因前語即有心生畏懼而意識自由遭壓制之情形。再觀被告\n      簽發本件本票之面額為20萬元，與其原先積欠債務金額尚\n      有落差，若被告所稱之梁姓男子真有恐嚇脅迫被告簽發本\n      票，否則不允其離開之真意及行為，何以未直接要求被告\n      於本票上填載得滿足全部債權之金額？又何以於被告簽發\n      交本件本票後即行離去並僅表示會再約時間詳談其他尚未\n      清償之債務？另參諸前述被告事後之反應與一般遭恐嚇之\n      人顯有落差等情，被告所執辯詞，亦無從為其有利之認定\n      。至被告辯稱其提出之刑事告訴狀明確記載係梁姓男子為\n      恐嚇行為，並無誣告甲○○恐嚇乙節，細觀被告所提刑事\n      告訴狀，其被告欄位明確記載「甲○○」及其地址，而告\n      訴事實亦明確記載梁姓男子陳稱其係受甲○○指使而為恐\n      嚇行為等文字，被告辯稱其無對甲○○提出告訴之意及相\n      關行為云云，亦無可採。\n三、綜上所述，被告明知其簽發本票並非因遭受他人恐嚇而為之\n    ，竟虛捏甲○○指使某梁姓男子對其恐嚇而使之簽發本票等\n    情，向檢察官誣告甲○○等涉犯恐嚇及強制等罪，其誣告犯\n    行，事證明確，洵堪認定，應依法論科。\n四、原審以被告犯罪事證明確，認定被告所為，係犯刑法第169\n    條第1 項之誣告罪。並敘明誣告罪為妨害國家審判權之罪，\n    直接受害者係國家，即國家之審判事務，每因誣告而為不當\n    之進行，至個人受害，乃國家進行不當審判事務所發生之結\n    果，與誣告行為不生直接之關係，故以一訴狀誣告數人，僅\n    能成立一誣告罪。被告以一訴狀誣告甲○○包含某梁姓男子\n    ，僅成立一誣告罪，檢察官起訴書犯罪事實雖僅列誣指告訴\n    人甲○○一人，惟被告誣告行既屬無從分割之一行為，則起\n    訴效力自及於未列載之梁姓男子部分，原審得併予認定，經\n    核原審認事用法，並無違誤。被告於劉銘龍所涉案件之偵查\n    程序及本案偵審期間，對於本件誣告犯罪，均未為認罪之自\n    白陳述，無依刑法第172條規定予以減輕其刑或免刑之餘地\n    。原審已詳斟刑法第57條事由，以被告明知其簽發本票並非\n    因遭受他人恐嚇而為之，惟避免其所有之動產遭法院拍賣，\n    竟向檢察官誣指甲○○涉犯恐嚇等罪嫌，致影響偵查機關偵\n    查犯罪之進行，使司法機關開啟不必要之偵查程序，耗費司\n    法資源，又使甲○○疲於應訴，受有司法機關偵辦之精神與\n    名譽損失，所為顯不足取，兼衡被告其犯罪動機、目的、手\n    段等一切情狀，量處被告有期徒刑5月，同時說明被告所犯\n    並非最重本刑為5年以下有期徒刑之罪，無從依刑法第41條\n    第1項規定併予諭知易科罰金之折算標準。末以被告行為後\n    ，刑法第41條增列第2項、第3項（原第2項改列為同條第8項\n    ），經總統於98年1月21日公布，自98年9月1日起施行，修\n    正後刑法第41條規定為：「犯最重本刑為5年以下有期徒刑\n    以下之刑之罪，而受6個月以下有期徒刑或拘役之宣告者，\n    得以新臺幣1千元、2千元或3千元折算1日，易科罰金。但確\n    因不執行所宣告之刑，難收矯正之效或難以維持法秩序者，\n    不在此限。依前項規定得易科罰金而未聲請易科罰金者，得\n    以提供社會勞動6小時折算1日，易服社會勞動。受六個月以\n    下有期徒刑或拘役之宣告，不符第一項易科罰金之規定者，\n    得依前項折算規定，易服社會勞動。」刑法施行法第3條之2\n    規定：「刑法第41條及第42條之1之規定，於中華民國98年9\n    月1日刑法修正施行前已裁判確定之處罰，未執行或執行未\n    完畢者，亦適用之。」其立法理由謂：「依刑法第41條規定\n    聲請易服社會勞動者，因條文已明定以社會勞動6小時折算\n    徒刑或拘役1日，與易科罰金應於裁判主文諭知折算標準之\n    情形不同，無須於裁判主文諭知…至於可否易服社會勞動，\n    與可否易科罰金相同，皆屬於執行事項，非裁判量刑事項，\n    故98 年9月1日刑法修正施行前已裁判確定之處罰，未執行\n    或執行未完畢者，無庸再向法院聲請裁定諭知折算標準。」\n    故而，本件有修正後刑法第41條之適用，被告依法得向執行\n    檢察官聲請以提供社會勞動6小時折算1日，易服社會勞動，\n    惟無庸於本判決主文諭知。原審對於被告之量刑，亦無違法\n    或濫權裁量之瑕疵。綜上，被告否認犯罪，其提起上訴，請\n    求改判無罪，為無理由，應予駁回。\n據上論斷，應依刑事訴訟法第368條，判決如主文。\n本案經檢察官繆卓然到庭執行職務。\n中    華    民    國    99    年    5     月    12    日\n                 刑事第十三庭  審判長法  官  曾德水\n                                     法  官  遲中慧\n                                     法  官  陳恆寬\n以上正本證明與原本無異。\n如不服本判決，應於收受送達後10日內向本院提出上訴書狀，其\n未敘述上訴之理由者並得於提起上訴後10日內向本院補提理由書\n（均須按他造當事人之人數附繕本）「切勿逕送上級法院」。\n                                     書記官  黃家麟\n中    華    民    國    99    年    5     月    14    日\n附錄本案論罪科刑法條全文\n中華民國刑法第169條\n意圖他人受刑事或懲戒處分，向該管公務員誣告者，處7 年以下\n有期徒刑。\n意圖他人受刑事或懲戒處分，而偽造、變造證據，或使用偽造、\n變造之證據者，亦同。",
  "structure": {
    "main": "上訴駁回。",
    "fact": "一、乙○○於民國94年間向甲○○之妻子呂珠娟借貸新臺幣（下\n    同）232萬元，原約定於同年5月間清償，惟屆期乙○○未償\n    還，甲○○遂於同年9月19日代理呂珠娟委託一統徵信股份\n    有限公司（以下稱一統公司）派員為其催討債務，甲○○、\n    呂珠娟、一統公司職員徐文燿及乙○○等人嗣於同年10月3\n    日在桃園縣桃園市○○路、大興西路口之「大樹咖啡」店進\n    行商談，約定變賣乙○○擔任負責人之衛主星數位科技股份\n    有限公司設備，抵償債務共30萬元後，乙○○即避不見面，\n    迄至翌年（即95年）7月6日，始應某一姓名年籍不詳之梁姓\n    成年男子之邀約，由其友人嚴智傑及姓名年籍不詳綽號「小\n    君」之成年男子陪同，再次前往「大樹咖啡」店，並出於自\n    由意志，在該處簽具其向甲○○借款20萬元之借據，同時簽\n    發票號651876號、發票日95年7月6日、到期日95年7月20日\n    、發票人乙○○、面額20萬元之本票（以下簡稱本件本票）\n    ，於本件本票背面以其母周豔月之名義背書後，將該借據及\n    本票交予該梁姓男子（乙○○涉嫌偽造私文書部分未經起訴\n    ），該梁姓男子再於95年10月間透過一統公司副理劉順昌轉\n    交予甲○○。嗣甲○○持本件本票，以受讓呂美珠所轉讓債\n    權之地位，於96年1月30日向臺灣桃園地方院聲請取得95年\n    度票字第17050號裁定，再向同院民事執行處聲請強制執行\n    ，經同院以96年度執字第40614號查封乙○○所有之動產，\n    並定97年2月4日進行第一次拍賣。詎乙○○明知甲○○並未\n    指使他人對其出言恐嚇，惟避免其所有之動產遭法院拍賣，\n    竟萌生使甲○○受刑事訴追之意圖，於97年1月21日某時許\n    ，基於誣告犯意，在某不詳處，書寫虛捏：「告訴人乙○○\n    、被告甲○○。…告訴人從未自被告處收取20萬元或其他對\n    價關係，詎料被告卻據本人於95年7月6日遭脅迫所簽之本票\n    採取諸般行為，更甚者其據此藉公權力執行強制處分，其玩\n    法濫行，詳述如後：95年7月6日告訴人接獲一自稱姓梁之男\n    士（電話0000000000）謂：你找死阿！我現在在你家樓下，\n    你媽一個人在家裡，並言明係甲○○叫他來的，你不出來我\n    就…等語，致使告訴人心生畏懼遂答應其要求前往桃園市○\n    ○路大樹咖啡館後強迫簽下本件本票，並強迫告訴人於背書\n    人處簽下告訴人母親周豔月之姓名，該本票為非法取得，告\n    訴人自無給付之義務，惟被告已據此向臺灣桃園地方法院民\n    事執行處96年執字第40614號給付票款強制執行事件查封動\n    產，並於97.2.4第一次拍賣…」之刑事告訴狀，旋於同年1\n    月23日向該管公務員即臺灣桃園地方法院檢察署檢察官誣指\n    甲○○指使該梁姓男子共同涉嫌犯恐嚇及強制等罪，嗣經檢\n    察官偵查結果，認甲○○並無乙○○所指犯行，於97年10月\n    9日以97年度偵字第15793號不起訴處分書對甲○○予以不起\n    訴處分確定。\n二、案經甲○○訴由臺灣桃園地方法院檢察署檢察官偵查起訴。",
    "reason": "壹、證據能力部分\n一、按被告以外之人於審判外之言詞或書面陳述，除法律有規定\n    者外，不得作為證據。又被告以外之人於審判外之陳述，雖\n    不符前4 條之規定，而經當事人於審判程序同意作為證據，\n    法院審酌該言詞陳述或書面陳述作成時之情況，認為適當者\n    ，亦得為證據；當事人、代理人或辯護人於法院調查證據時\n    ，知有第159條第1項不得為證據之情形，而未於言詞辯論終\n    結前聲明異議者，視為有前項同意。刑事訴訟法第159條第1\n    項、第159條之5分別定有明文。\n二、有關本件判決所引用之被告以外之人於審判外陳述之證據能\n    力，上訴人即被告乙○○於本院審理時已表示無意見，迄於\n    言詞辯論終結前亦未爭執，本院審酌該等陳述作成時之情況\n    ，並無違法取證及證明力過低之瑕疵，亦認以之作為證據為\n    適當，依前揭規定說明，自有證據能力。\n貳、實體部分：\n一、訊據被告於矢口否認有使甲○○受刑事處分而誣告之犯行，\n    辯稱：95年7月6日前幾日，確有自稱姓梁的男子打電話給被\n    告，表示：「你欠甲○○的錢，你給我出來，你不要躲，我\n    現在在你家樓下，你媽媽一個人在裡面，你不回來你就試試\n    看」等恐嚇之語，並於7月6日當日在大樹咖啡要求被告還甲\n    ○○20萬元並簽發本票，嚇稱：「不簽的話，就不要想走出\n    這個門」，被告因心生恐懼，遂簽發本件本票，並以其母周\n    豔月之名義在本票背面背書，甲○○雖自始至終均未曾出面\n    ，然因梁姓男子於95年7月6日曾出示甲○○簽發委託其公司\n    處理債務之委託書，嗣後甲○○又以被告遭恐嚇後簽發之本\n    件本票至法院聲請95年度促字第48490號支付命令，是其主\n    觀上認知梁姓男子係經甲○○指示向其恐嚇云云。上訴理由\n    狀並謂：\n（一）原判決於事實欄既認定被告係向甲○○之妻呂珠娟借貸23\n      2萬元，於理由欄又稱「被告明知其尚有積欠甲○○之妻\n      子呂珠娟借貸金額，該筆債務已委甲○○出面催討之情事\n      ，竟於刑事告狀上記載甲○○與其之間並無任何債權債務\n      關係而擅持本件本票向本院聲請強制執行等語，顯屬虛枉\n      （妄），已有可議」。原判決既認本件借貸係存於被告與\n      呂珠娟之間，卻又認被告所稱其與甲○○間無任何債權債\n      務關係，其事實與理由顯屬矛盾。\n（二）原判決理由另稱「前開刑事告訴狀該狀紙之被告欄位已明\n      確記載告訴人「甲○○』及其地址，而告訴事實中亦明確\n      記載該名男子陳稱其係受甲○○指使而為恐嚇行為等文字\n      」云云。惟觀被告告訴狀之內容，並無任指訴甲○○親自\n      或指使梁姓男子對被告為恐嚇行為之記載，僅稱遭梁姓男\n      子電話恐嚇云云，並未稱係甲○○所指使，原判決上揭理\n      由與卷內告訴狀內容所載，尚有未符。\n二、然查：\n（一）被告於97年1月21日不詳地點，書寫其上記載甲○○涉嫌\n      恐嚇等如事實欄第一項所載內容犯行之刑事告訴狀，並於\n      同年月23日，向臺灣桃園地方法院檢察署遞狀，對甲○○\n      提出刑事告訴等情，為被告所不爭執，復有該刑事告訴狀\n      附卷可稽（見臺灣桃園地方法院檢察署97年度他字第516\n      號卷第1頁第至3頁），此部分事實自堪認定。\n（二）被告於94年間向甲○○之妻子呂珠娟借貸232萬元，原約\n      定於同年5月間清償，被告屆期未為償還，甲○○遂於同\n      年9月19日代理呂珠娟委託一統公司為其催討債務，甲○\n      ○、呂珠娟、一統公司職員徐文燿及被告等人，嗣於同年\n      10月3日在桃園縣桃園市○○路、大興西路口之「大樹咖\n      啡」商談，約定變賣被告擔任負責人之衛主星數位科技股\n      份有限公司設備，抵償債務共30萬元後，被告即避不見面\n      ，至95年7月前，均拒未清償其他款項等情，業據告訴人\n      即證人甲○○、徐文燿於原審證述明確（見原審98年度訴\n      字第744號卷第61頁至第72頁），並有被告所簽發本票、\n      支票及借據在卷可稽（見原審卷第14頁至第16頁）。細譯\n      前開借據上貸款人記載「甲○○」，而甲○○先前亦曾與\n      妻子共同前往大樹咖啡店協談債務處理等情，應認被告於\n      95年7月6日簽發本件本票前，已知其尚積欠甲○○之妻子\n      呂珠娟借款未償，而該筆債權既經呂珠娟委由甲○○出面\n      催討，被告在簽立上開以甲○○為債權人之借據前，亦可\n      推知呂珠娟係將借款債權轉讓予甲○○行使，其竟於刑事\n      告訴狀指稱甲○○與被告之間並無任何債權債務關係而擅\n      持本件本票向法院聲請強制執行云云，核其此部分指訴內\n      容，已明顯偏離事實。\n（三）被告所簽發本件本票，係於95年10月間由一統公司副理劉\n      順昌轉交予甲○○，並由甲○○持之向臺灣桃園地方法院\n      聲請取得95年度票字第17050號裁定，再向同法院民事執\n      行處聲請強制執行，經同法院以96年度執字第40614號查\n      封被告所有之動產等情，經告訴人即證人甲○○於原審證\n      述明確（見原審98年度訴字第744號卷第61頁至第72頁）\n      ，並有本件本票影本（見原審95年度票字第17050號卷第5\n      頁）、臺灣桃園地方法院95年度票字第17050號裁定、96\n      年度抗字第18號裁定、同法院96年9月17日桃院木執96年\n      執宇字第40614號、96年12月19日桃院木執96年執宇字第4\n      0614號民事執行處通知在卷可稽（見臺灣桃園地方法院檢\n      察署97年度他字第516號偵查卷第6頁至第9頁）。證人甲\n      ○○於原審堅稱：「委任一統公司時，我並沒有指示他們\n      用什麼方法催討被告欠我的債務，委託之後我也沒有過問\n      催討過程。」等語（見同前原審卷第62頁背面），故本件\n      應釐清者，即為：１、被告於95年7月6日前或當日在大樹\n      咖啡，有否遭受梁姓男子恐嚇、脅迫，因心生畏懼而簽發\n      本件本票？２、若有前開情事，該名梁姓男子之行為是否\n      為甲○○授權而為之？被告是否可合理認定甲○○係指示\n      梁姓男子向其恐嚇之人，而對其提起恐嚇告訴？\n（四）據證人嚴智傑於原審證稱：「（95年7月6日）當天，被告\n      打電話給我要我去他公司找他，沒有刻意要我找其他人一\n      起去，只是當時我剛好跟另一個朋友在一起，才共同前往\n      被告公司，到了以後，被告邀我跟他一起去喝咖啡，當時\n      沒有提到要跟別人談判事情，後來被告開車載我們去大樹\n      咖啡，當時還是公開營業的時間，我們走進去以後，有一\n      桌大概4、5個人一起站起來，被告就自己主動走到那一桌\n      去，我們跟著被告也要在同桌坐下時，那一群人就叫我們\n      坐在別桌。後來我聽到對方有人對被告說：『如果今天沒\n      有給他們交代，就不可能讓被告走』的意思，對方講話態\n      度蠻兇的，但沒有聽到他們說很明顯恐嚇、威脅的語句，\n      後來被告有簽了一張本票，對方有表示本件本票先當作償\n      還的部分，其他再約時間談，後來他們拿了本票就離開，\n      只說：『若你不處理，我會找你媽媽處理。』，我問被告\n      是何事，他說是跟合夥人債務的問題，然後我們就走了。\n      」等語（見同前原審卷第64頁至第72頁）。因此，在95年\n      7月6日當天，證人嚴智傑並未在大樹咖啡店內聽到對方表\n      示明顯恐嚇、脅迫之語句。再衡諸常情，若被告於95年7\n      月6日前曾遭不明人士於電話中為恐嚇：「你找死阿！我\n      現在在你家樓下，你媽一個人在家裡，係甲○○叫我來的\n      ，你不出來我就…」云云，則其邀請友人嚴智傑同行前往\n      大樹咖啡時，理當應向嚴智傑透露其前曾遭恐嚇乙節，並\n      要求嚴智傑尋覓其他能協助保護其人身安全之人手共同前\n      往談判處所，以被告所指稱之案發處所即大樹咖啡店，為\n      公眾得出入之場所，參酌被告明知其前往大樹咖啡店係為\n      商談債務解決，又刻意找友人嚴俊傑陪同前往，若有他人\n      恐嚇被告並迫使被告簽發本票等情，被告應可向近在咫尺\n      之嚴智傑表達求助之意，至遲在對方離去後，亦可立刻告\n      知嚴智傑其遭恐嚇之詳細情節，並商討因應對策，惟被告\n      捨此不為，僅向嚴智傑表示係處理合夥人間債務問題，其\n      反應顯與遭受恐嚇、脅迫而甫簽發本票之人有異。被告空\n      言指稱其於案發前及當日係遭他人恐嚇、脅迫而簽發本件\n      本票云云，顯屬無據。\n（五）又被告辯稱其遭恐嚇之時間為95年7月6日及其前數日，然\n      其於該日前後均未曾向司法警察或偵查機關報案以爭取時\n      效保全證據，此為被告所自承。甲○○持本件本票向臺灣\n      桃園地方法院聲請95年度票字第17050號裁定准予執行後\n      ，被告於95年12月間提出抗告，其自行書寫之抗告狀亦僅\n      聲明：「（一）本件本票裁定事件並未有任何交付之事實\n      。（二）原債權早經裁定並清償中。」等語（見原審96年\n      度抗字第18號卷第7頁至第9頁），並未指述本件本票係遭\n      人恐嚇而簽發之隻字片語。再甲○○亦曾於95年11月1日\n      以本件本票背書人即被告之母周艷月為相對人，向臺灣桃\n      園地方法院聲請取得95年度促字第48490號支付命令，經\n      周艷月聲明異議後，同法院以95年度壢簡字第1508號給付\n      票款案件審理，被告坦承該案審理期間，其聯絡地址即為\n      其母周艷月桃園縣中壢市○○○街13號8樓住所地（見同\n      前原審卷第11頁背面），當知悉甲○○已以周艷月為本件\n      本票背書人為由，請求給付票款一事，惟原審法院民事庭\n      於96年3月2日傳訊被告以證人身分出庭說明時，被告未到\n      庭說明該票係遭人恐嚇而簽發，致其以其母名義背書之事\n      （見原審95年度壢簡字第1508號卷第21頁至第24頁），被\n      告於涉及本件本票之民事案件期間，均未曾於審理過程以\n      言詞或書面方式向法院陳述其遭恐嚇情事，卻遲至本件本\n      票裁定確定，經臺灣桃園地方法院以96年12月19日桃院木\n      執96年執宇字第40614號民事執行處通知業已執行查封其\n      動產，將定於97年2月4日進行拍賣之際，乃於97年1月23\n      日，具狀指控甲○○提出刑事告訴，此顯與一般人遭暴力\n      殘害後隨即向司法警察或偵查機關報告，並於法院審理期\n      間，把握所有可能之機會提出答辯說明等反應相違。被告\n      指稱其於95年7月6日前及當日在大樹咖啡，因遭恐嚇、脅\n      迫而簽發本件本票，顯屬虛妄不實。而被告所提前開告訴\n      案，經臺灣桃園地方法院檢察署檢察官偵查終結後，亦認\n      定甲○○並無被告所指訴之恐嚇及強制等犯行，以甲○○\n      犯罪嫌疑不足為由，予以處分不起訴，有臺灣桃園地方法\n      院檢察署97年度偵字第15793號不起訴處分書在案可稽。\n（六）被告以證人嚴智傑曾於原審證稱：「（95年7月6日）當天\n      ，對方有4、5個人，指著被告說如果不給他們一個交代，\n      不給他離開…」等語，辯稱認被告於簽發本票當日之意識\n      自由確遭壓制，被告無誣告犯行云云。然行為人確否有恐\n      嚇行為，應由整體客觀情狀（包含行為之場所、氣氛、後\n      續之發展）判斷，不得單以行為人曾為某單一言語即斷章\n      取義認定其所言屬恐嚇之舉，證人嚴智傑於原審明確證稱\n      其與被告等進入大樹咖啡店時，仍屬營業時間，而該咖啡\n      店為公開營業之場所，對方雖有4、5人於現場等候，然被\n      告方面亦由嚴智傑及另一名友人共計3人陪同到場，被告\n      方面人數上並未居於絕對劣勢，證人嚴智傑並未見對造手\n      上持有其他武器，而除前開言語外，與被告商議債務處理\n      之對方亦無其他暴力舉動或為其他恐嚇之語，縱有不詳姓\n      名之男子曾為前語，依當時整體客觀環境，亦難認被告僅\n      因前語即有心生畏懼而意識自由遭壓制之情形。再觀被告\n      簽發本件本票之面額為20萬元，與其原先積欠債務金額尚\n      有落差，若被告所稱之梁姓男子真有恐嚇脅迫被告簽發本\n      票，否則不允其離開之真意及行為，何以未直接要求被告\n      於本票上填載得滿足全部債權之金額？又何以於被告簽發\n      交本件本票後即行離去並僅表示會再約時間詳談其他尚未\n      清償之債務？另參諸前述被告事後之反應與一般遭恐嚇之\n      人顯有落差等情，被告所執辯詞，亦無從為其有利之認定\n      。至被告辯稱其提出之刑事告訴狀明確記載係梁姓男子為\n      恐嚇行為，並無誣告甲○○恐嚇乙節，細觀被告所提刑事\n      告訴狀，其被告欄位明確記載「甲○○」及其地址，而告\n      訴事實亦明確記載梁姓男子陳稱其係受甲○○指使而為恐\n      嚇行為等文字，被告辯稱其無對甲○○提出告訴之意及相\n      關行為云云，亦無可採。\n三、綜上所述，被告明知其簽發本票並非因遭受他人恐嚇而為之\n    ，竟虛捏甲○○指使某梁姓男子對其恐嚇而使之簽發本票等\n    情，向檢察官誣告甲○○等涉犯恐嚇及強制等罪，其誣告犯\n    行，事證明確，洵堪認定，應依法論科。\n四、原審以被告犯罪事證明確，認定被告所為，係犯刑法第169\n    條第1 項之誣告罪。並敘明誣告罪為妨害國家審判權之罪，\n    直接受害者係國家，即國家之審判事務，每因誣告而為不當\n    之進行，至個人受害，乃國家進行不當審判事務所發生之結\n    果，與誣告行為不生直接之關係，故以一訴狀誣告數人，僅\n    能成立一誣告罪。被告以一訴狀誣告甲○○包含某梁姓男子\n    ，僅成立一誣告罪，檢察官起訴書犯罪事實雖僅列誣指告訴\n    人甲○○一人，惟被告誣告行既屬無從分割之一行為，則起\n    訴效力自及於未列載之梁姓男子部分，原審得併予認定，經\n    核原審認事用法，並無違誤。被告於劉銘龍所涉案件之偵查\n    程序及本案偵審期間，對於本件誣告犯罪，均未為認罪之自\n    白陳述，無依刑法第172條規定予以減輕其刑或免刑之餘地\n    。原審已詳斟刑法第57條事由，以被告明知其簽發本票並非\n    因遭受他人恐嚇而為之，惟避免其所有之動產遭法院拍賣，\n    竟向檢察官誣指甲○○涉犯恐嚇等罪嫌，致影響偵查機關偵\n    查犯罪之進行，使司法機關開啟不必要之偵查程序，耗費司\n    法資源，又使甲○○疲於應訴，受有司法機關偵辦之精神與\n    名譽損失，所為顯不足取，兼衡被告其犯罪動機、目的、手\n    段等一切情狀，量處被告有期徒刑5月，同時說明被告所犯\n    並非最重本刑為5年以下有期徒刑之罪，無從依刑法第41條\n    第1項規定併予諭知易科罰金之折算標準。末以被告行為後\n    ，刑法第41條增列第2項、第3項（原第2項改列為同條第8項\n    ），經總統於98年1月21日公布，自98年9月1日起施行，修\n    正後刑法第41條規定為：「犯最重本刑為5年以下有期徒刑\n    以下之刑之罪，而受6個月以下有期徒刑或拘役之宣告者，\n    得以新臺幣1千元、2千元或3千元折算1日，易科罰金。但確\n    因不執行所宣告之刑，難收矯正之效或難以維持法秩序者，\n    不在此限。依前項規定得易科罰金而未聲請易科罰金者，得\n    以提供社會勞動6小時折算1日，易服社會勞動。受六個月以\n    下有期徒刑或拘役之宣告，不符第一項易科罰金之規定者，\n    得依前項折算規定，易服社會勞動。」刑法施行法第3條之2\n    規定：「刑法第41條及第42條之1之規定，於中華民國98年9\n    月1日刑法修正施行前已裁判確定之處罰，未執行或執行未\n    完畢者，亦適用之。」其立法理由謂：「依刑法第41條規定\n    聲請易服社會勞動者，因條文已明定以社會勞動6小時折算\n    徒刑或拘役1日，與易科罰金應於裁判主文諭知折算標準之\n    情形不同，無須於裁判主文諭知…至於可否易服社會勞動，\n    與可否易科罰金相同，皆屬於執行事項，非裁判量刑事項，\n    故98 年9月1日刑法修正施行前已裁判確定之處罰，未執行\n    或執行未完畢者，無庸再向法院聲請裁定諭知折算標準。」\n    故而，本件有修正後刑法第41條之適用，被告依法得向執行\n    檢察官聲請以提供社會勞動6小時折算1日，易服社會勞動，\n    惟無庸於本判決主文諭知。原審對於被告之量刑，亦無違法\n    或濫權裁量之瑕疵。綜上，被告否認犯罪，其提起上訴，請\n    求改判無罪，為無理由，應予駁回。\n據上論斷，應依刑事訴訟法第368條，判決如主文。\n本案經檢察官繆卓然到庭執行職務。\n中    華    民    國    99    年    5     月    12    日\n                 刑事第十三庭  審判長法  官  曾德水\n                                     法  官  遲中慧\n                                     法  官  陳恆寬\n以上正本證明與原本無異。\n如不服本判決，應於收受送達後10日內向本院提出上訴書狀，其\n未敘述上訴之理由者並得於提起上訴後10日內向本院補提理由書\n（均須按他造當事人之人數附繕本）「切勿逕送上級法院」。\n                                     書記官  黃家麟"
  },
  "characters": {
    "judges": [
      "曾德水",
      "遲中慧",
      "陳恆寬"
    ],
    "prosecutors": [
      "繆卓然"
    ],
    "lawyers": [

    ],
    "clerks": [
      "黃家麟"
    ],
    "plaintiffs": [

    ],
    "defendants": [
      "乙"
    ],
    "prosecutor_office": [

    ],
    "creditors": [

    ],
    "debtors": [

    ],
    "judicial_associate_officer": [

    ]
  },
  "adjudged_at": "2010-05-12",
  "created_at": "2016-01-05 11:53:44",
  "updated_at": "2016-01-05 11:53:44"
}