{
  "identify": "TPH-99-聲-1264-20100512-1",
  "court": {
    "name": "臺灣高等法院",
    "code": "TPH"
  },
  "division": {
    "name": "刑事",
    "code": "M"
  },
  "year": 99,
  "word": "聲",
  "number": "1264",
  "jcheck": "1",
  "reason": "保護管束",
  "content": "臺灣高等法院刑事裁定                  99年度聲字第1264號\n聲  請  人  臺灣高等法院檢察署檢察官\n受  刑  人  甲○○\n上列受刑人因違反毒品條例等案件，經核准假釋，聲請人聲請付\n保護管束（99年執聲付字第337號），本院裁定如下：\n    主  文\n甲○○假釋中付保護管束。\n    理  由\n一、聲請意旨略以：受刑人甲○○前因犯詐欺罪，最後事實審法\n    院為鈞院，經判刑確定並已移付執行。茲聲請人以受刑人業\n    經法務部核准假釋，爰依刑事訴訟法第481 條第1 項規定，\n    聲請於其假釋中付保護管束等語。\n二、經查：受刑人甲○○前因犯詐欺罪，經臺灣新竹地方法院91\n    年度訴字第205 號判決判處有期徒刑1 年6 月，上訴後經本\n    院以92年度上訴字第3857號判決上訴駁回確定，於民國98年\n    4 月27日送監執行。茲受刑人上開徒刑之執行，業經法務部\n    於99年5 月3 日以法矯司字第0990905867號函核准假釋，而\n    其刑期終結日為99年10月26日，行刑累進處遇條例縮刑日數\n    12日，縮短刑期後終結日為99年10月14日，亦有臺灣新竹監\n    獄新竹分監假釋出獄人交付保護管束名冊在卷可按。本院審\n    核上開文件後，認被告經假釋在案，應在假釋中付保護管束\n    ，聲請人之聲請為正當。\n三、據上論斷，應依刑事訴訟法第481 條第1 項、刑法第96條但\n    書、第93條第2 項，裁定如主文。\n中    華    民    國    99    年    5     月    12    日\n                  刑事第二十庭審判長法  官  楊貴雄\n                                    法  官  林銓正\n                                    法  官  許必奇\n以上正本證明與原本無異。\n如不服本裁定，應於收受送達後5日內向本院提出抗告狀。\n                                    書記官 高郁婷\n中    華    民    國    99    年    5     月    14    日",
  "structure": {
    "main": "甲○○假釋中付保護管束。",
    "reason": "一、聲請意旨略以：受刑人甲○○前因犯詐欺罪，最後事實審法\n    院為鈞院，經判刑確定並已移付執行。茲聲請人以受刑人業\n    經法務部核准假釋，爰依刑事訴訟法第481 條第1 項規定，\n    聲請於其假釋中付保護管束等語。\n二、經查：受刑人甲○○前因犯詐欺罪，經臺灣新竹地方法院91\n    年度訴字第205 號判決判處有期徒刑1 年6 月，上訴後經本\n    院以92年度上訴字第3857號判決上訴駁回確定，於民國98年\n    4 月27日送監執行。茲受刑人上開徒刑之執行，業經法務部\n    於99年5 月3 日以法矯司字第0990905867號函核准假釋，而\n    其刑期終結日為99年10月26日，行刑累進處遇條例縮刑日數\n    12日，縮短刑期後終結日為99年10月14日，亦有臺灣新竹監\n    獄新竹分監假釋出獄人交付保護管束名冊在卷可按。本院審\n    核上開文件後，認被告經假釋在案，應在假釋中付保護管束\n    ，聲請人之聲請為正當。\n三、據上論斷，應依刑事訴訟法第481 條第1 項、刑法第96條但\n    書、第93條第2 項，裁定如主文。"
  },
  "characters": {
    "judges": [
      "楊貴雄",
      "林銓正",
      "許必奇"
    ],
    "prosecutors": [

    ],
    "lawyers": [

    ],
    "clerks": [
      "高郁婷"
    ],
    "plaintiffs": [

    ],
    "defendants": [

    ],
    "prosecutor_office": [
      "臺灣高等法院檢察署檢察官"
    ],
    "creditors": [

    ],
    "debtors": [

    ],
    "judicial_associate_officer": [

    ]
  },
  "adjudged_at": "2010-05-12",
  "created_at": "2016-01-05 11:54:42",
  "updated_at": "2016-01-05 11:54:42"
}