{
  "identify": "TPH-99-上訴-932-20100512-1",
  "court": {
    "name": "臺灣高等法院",
    "code": "TPH"
  },
  "division": {
    "name": "刑事",
    "code": "M"
  },
  "year": 99,
  "word": "上訴",
  "number": "932",
  "jcheck": "1",
  "reason": "毒品危害防制條例",
  "content": "臺灣高等法院刑事判決                 99年度上訴字第932號\n上  訴  人     甲○○\n即  被  告\n上列上訴人即被告因違反毒品危害防制條例案件，不服臺灣基隆\n地方法院九十八年度訴字第一０二三號，中華民國九十九年一月\n廿一日第一審判決（起訴案號：臺灣基隆地方法院檢察署九十八\n年度偵字第二七二四號），提起上訴，本院判決如下：\n    主  文\n原判決撤銷。\n甲○○販賣第二級毒品，累犯，處有期徒刑肆年，扣案門號Ｚ0\n00000000號行動電話壹具（含SIM卡壹張）沒收，販賣\n第二級毒品所得財物新臺幣壹萬元均沒收，如全部或一部不能沒\n收時，以其財產抵償之。又販賣第二級毒品，累犯，處有期徒刑\n肆年，扣案門號Ｚ000000000號行動電話壹具（含SIM\n卡壹張）沒收，販賣第二級毒品所得財物新臺幣壹萬伍仟元均沒\n收，如全部或一部不能沒收時，以其財產抵償之。又轉讓第一級\n毒品，累犯，處有期徒刑壹年，扣案門號Ｚ000000000\n號行動電話壹具（含SIM卡壹張）沒收。應執行有期徒刑陸年，\n扣案門號Ｚ000000000號行動電話壹具（含SIM卡壹張\n）沒收，販賣第二級毒品所得財物新臺幣貳萬伍仟元均沒收，如\n全部或一部不能沒收時，以其財產抵償之。\n    事  實\n一、甲○○前因詐欺案件，經臺灣基隆地方法院以九十六年度易\n    字第一八九號判決，判處減為有期徒刑五月，並於民國九十\n    七年三月十六日入監起算刑期，至九十七年八月十五日期滿\n    執行完畢。詎其猶不知悔改，明知海洛因、安非他命分屬毒\n    品危害防制條例第二條第二項第一款、第二款所定之第一、\n    二級毒品，不得販賣、轉讓及持有，竟分別基於販賣第二級\n    毒品以營利，及轉讓第一級毒品之犯意，以其所有門號0000\n    000000號行動電話作為販賣、轉讓毒品聯繫之用，先於九十\n    七年十月十九日十三時四十二分許，莊金龍以其所有門號00\n    00000000號行動電話，與甲○○前開行動電話聯繫，二人約\n    至基隆市○○區○○街十二號八斗子派出所附近之海產店前\n    ，由甲○○販賣二包安非他命（一包毛重約二點五公克、另\n    一包淨重約零點五公克）予莊金龍，並當場收取一萬元之價\n    款營利。後於同年月廿日零時四十二分許，莊金龍又以同行\n    動電話與甲○○聯繫，二人約至基隆市○○區○○路基隆海\n    洋大學附近之全家便利商店處，由甲○○販賣交付安非他命\n    一包（毛重約四點六八七五公克）予莊金龍，並收取一萬五\n    千元之價款營利。嗣於同年月廿二日零時五分許，莊金龍向\n    甲○○索取試用第一級毒品海洛因，甲○○即約至基隆市○\n    ○區○○路、調和街口處見面，並無償提供不詳數量之海洛\n    因一包（無證據證明已逾淨重五公克）予莊金龍試用，惟莊\n    金龍施用後認為品質不佳，而無下文。\n二、案經警對莊金龍持用之0000000000號行動電話門號實施通訊\n    監察，因而循線查獲上情，乃由臺北縣政府警察局瑞芳分局\n    報請臺灣基隆地方法院檢察署檢察官偵查起訴。\n    理  由\n一、証據能力部分：\n    (一)按被告之自白，非出於強暴、脅迫、利誘、詐欺、疲勞訊\n      問、違法羈押或其他不正之方法，且與事實相符者，得為\n      證據；被告陳述其自白係出於不正之方法者，應先於其他\n      事證而為調查，該自白如係經檢察官提出者，法院應命檢\n      察官就自白之出於自由意志，指出證明之方法，刑事訴訟\n      法第一百五十六條第一項、第三項定有明文。準此，被告\n      及辯護人對檢察官所提被告於警詢、偵查中不利於己之供\n      述，證據能力並無意見，且本院亦查無有何顯然不正之方\n      法取得情事，而悖於其自由意志，是被告前開不利於己供\n      述得為證據。\n    (二)按被告以外之人於審判外之言詞或書面陳述，除法律有規\n      定者外，不得作為證據，刑事訴訟法第一百五十九條第一\n      項固有明文。惟被告以外之人於審判外之陳述，雖不符刑\n      事訴訟法第一百五十九條之一至第一百五十九條之四之規\n      定，而經當事人於審判程序同意作為證據，法院審酌該言\n      詞陳述或書面陳述作成時之情況，認為適當者，亦得為證\n      據；當事人、代理人或辯護人於法院調查證據時，知有第\n      一百五十九條第一項不得為證據之情形，而未於言詞辯論\n      終結前聲明異議者，視為有前項之同意，同法第一百五十\n      九條之五定有明文。經查，本案証人莊金龍前於警詢及偵\n      查中之陳述（偵卷第五～二０頁警詢筆錄、偵卷第一０六\n      頁～一一三頁偵查筆錄），固為被告以外之人於審判外之\n      言詞陳述，惟經原審及本院於審判程序中提示予被告並告\n      以要旨，被告及其辯護人對該證據之證據能力均表示無意\n      見，且均同意作為證據（本院九十九年三月二十三日準備\n      程序筆錄第二頁），且迄至言詞辯論終結前均未再聲明異\n      議，本院審酌上開陳述作成時之情況，尚無違法取證及證\n      明力明顯過低之瑕疵，為證明犯罪事實所必要，亦認以之\n      作為證據應屬適當，揆諸上開規定，前揭證據皆有證據能\n      力。\n    (三)再按有事實足認被告或犯罪嫌疑人有最輕本刑為三年以上\n      有期徒刑之罪嫌，並危害國家安全或社會秩序情節重大，\n      而有相當理由可信其通訊內容與本案有關，且不能或難以\n      其他方法蒐集或調查證據者，得發通訊監察書，通訊保障\n      及監察法第五條第一項第一款定有明文。經查，本案對證\n      人莊金龍使用之門號0000000000號行動電話實施通訊監察\n      ，乃以其涉犯毒品危害防制條例第四條罪嫌，為最輕本刑\n      為三年以上有期徒刑，並危害國家安全或社會秩序情節重\n      大，而不能或難以其他方法蒐集或調查證據，爰經法院准\n      予實施通訊監察，所得監聽譯文內容（見偵查卷第三二頁\n      至四四頁），合於通訊保障及監察法所定要件而取得之證\n      據，而被告於監聽過程透露犯罪行為之陳述，並非因員警\n      監聽所致，而係出於被告之自由意思，自可採信，因之監\n      聽錄音所取得之證據，有證據能力。又監聽錄得之錄音，\n      係憑機械力照錄，未經人為操作，復未伴有個人主觀意見\n      在內，而將監聽之內容製作成譯文，乃將上開具有證據能\n      力之監聽錄得之錄音具體為文字紀錄，此部分雖屬傳聞，\n      然此係由承辦員警本於偵查案件職務所製作，復無證據顯\n      示存有詐偽或虛飾之情事，況經原審及本院依職權於審理\n      期日提示上揭通訊監聽譯文令被告等辨識，被告及其選任\n      辯護人均未爭執證據能力，且不否認監聽譯文之內容為真\n      正，則該監聽譯文依據刑事訴訟法第一百五十九條之五規\n      定，自有證據能力。\n二、上開犯罪事實，業據上訴人即被告甲○○於本院審理中坦承\n    不諱，核與其使用之0000000000行動電話與証人莊金龍使用\n    之0000000000號行動電話，經監聽錄得二人對談內容：\n    97年10月19日13時42分\n      甲○○：喂。\n      莊金龍：老低，這次我是沒賺喔，他們說1萬啦，1萬你要\n              算多少給他？\n      甲○○：1萬喔。\n      莊金龍：實的1萬。\n      甲○○：我跟你說1克4 千，1萬剛好2.5啦。\n      莊金龍：哼，另外commission踩一點給我們啦。\n      甲○○：哥哥，阿厚阿，我2.5給他實重，我再0.2給你，\n              我沒賺啦。\n      莊金龍：不然你也拉一點過來。\n      甲○○：也可以從他那拉一點過去給你就對啦？\n      莊金龍：沒關係啦。\n      甲○○：這樣講我含袋的2.5給他。\n      莊金龍：含袋2.5就對啦。\n      甲○○：他減個0.2而已，那0.2補給你那邊。我給你實重\n              0.5。\n      莊金龍：好阿。\n      甲○○：你人在哪？\n      莊金龍：含袋2.5，另外一個實重0.5給我們。你打電話給\n              我，因為我這一支是易付卡。\n    97年10月19日13時55分\n      甲○○：喂。\n      莊金龍：他差不多要40分鐘就到了。\n      甲○○：到哪？\n      莊金龍：到我們瑞芳阿。\n      甲○○：多少你跟我說好了？\n      莊金龍：1萬，他們要1萬。你要分多少給他們？\n      甲○○：沒有啦，你跟我說他們要多少，要給你多少？\n      莊金龍：你說什麼？\n      甲○○：你想要給他們多少，我要給你多少，你直接講啦\n              。\n      莊金龍：一樣2.5就好了。\n      甲○○：實重還是含袋子重？\n      莊金龍：實重啦，實重給他。\n      甲○○：那你呢？\n      莊金龍：我有或沒有都沒關係啦。\n    97年10月19日15時24分\n      莊金龍：到了。\n      甲○○：你們等我3分鐘。\n      莊金龍：3分鐘。\n      甲○○：你們前面一點有一家五金行，不要好了到港邊，\n              你到八斗子派出所下去有一家海產店，約在那。\n      莊金龍：好。\n    97年10月19日15時31分\n      莊金龍：喂。\n      甲○○：到了，我到了。你在海產店對面嗎？\n      莊金龍：對阿。\n      甲○○：好。\n    97年10月19日22時53分\n      莊金龍：明天男孩子有比較好的？\n      甲○○：這就是好的，不然什麼叫好呢。\n      莊金龍：幾個都有辦法喔？\n      甲○○：何時？\n      莊金龍：明天阿。\n      甲○○：明天跟今天不一樣了喔，明天就沒辦法那樣了喔\n              ，我意思是說量不能給那麼多了喔。\n    97年10月20日0 時42分。\n      莊金龍：我這收訊不好，41。\n      甲○○：沒那麼多？\n      莊金龍：你那剩多少？\n      甲○○：81。\n      莊金龍：剩81而已喔。81要算多少？\n      甲○○：16。之前都這樣。每個都這樣。\n      莊金龍：81都切15。\n      甲○○：好，15。我早上這樣都沒賺錢呢。我剩81本來留\n              給臺北的朋友，但還沒上來，不然在催。你多久\n              會到？\n      莊金龍：我現在馬上聯絡。他馬上到。\n      甲○○：看多久會到打電話來說一下。\n      莊金龍：好。\n    97年10月20日2時23分許\n      甲○○：我在路上，你們到海洋大學翻頭過來有一間全家\n              。\n      莊金龍：全家在哪裡？\n      甲○○：全家便利商店啦。\n      莊金龍：喔。\n    97年10月20日2時43分\n      莊金龍：含袋子總共才4.2。\n      甲○○：那的袋子0.6啦。這樣... （模糊）\n      莊金龍：喂，你打給我。\n    97年10月22日0時5分\n      莊金龍：我叫你拿版子給我，人家電話一直打啦。對阿，\n              你版子拿給我，我拿給他，他說好你再出現。\n      甲○○：沒有，我現在。\n      莊金龍：你很像不信任我的樣子。\n      甲○○：不是，說這樣，那些都被動過了。\n      莊金龍：無啦，男孩子啦。\n      甲○○：男孩子我也沒有，2個都沒有啦。\n      莊金龍：你被動過，動到哪裡？\n      甲○○：我不知道。\n      莊金龍：我等一下過去你拿版子給我。\n      甲○○：阿被動過還版子，剛拿給別人就被別人退了。\n      莊金龍：阿。\n      甲○○：你說什麼？\n      莊金龍：我說那個是半個、一個而已。\n      甲○○：你說什麼東西？\n      莊金龍：男孩子阿，他那個是半錢和一錢而已。最高是這\n              樣。\n      甲○○：我聽不懂你意思？\n      莊金龍：意思說人家要半個、一個，我們拿給他。我主要\n              是要你的版子，不是要用你的版子。\n      甲○○：恩。\n      莊金龍：你版子給我，我拿給他，他說可以，我電話馬上\n              聯絡，你馬上送過來？\n      甲○○：你說查某的嗎？\n      莊金龍：恩啦。\n      甲○○：好啦，我等一下拿給你。\n      莊金龍：好啦。\n    97年10月22日0 時25分。\n      甲○○：你現在來調和街這？\n      莊金龍：這麼遠喔？\n      甲○○：不然不要好了？我現在人在這。\n      莊金龍：喔，這樣。\n      甲○○：你多久會到？\n      莊金龍：10分鐘。\n      甲○○：哪裡你知道嗎？不然我要走了。\n      莊金龍：靠近哪？\n      甲○○：你深澳坑路往八斗子這，現在，平交道過來轉彎\n              ，冷凍廠那，轉過來有一間廟。\n      莊金龍：好。\n      甲○○：快點喔。\n    97年10月22日0 時33分\n      莊金龍：我到八斗子冷凍廠了。\n      甲○○：哪有，我沒看到你，你沒從調和街這條彎上來？\n      莊金龍：有阿，我現在要彎過去了。\n      甲○○：有阿。\n      莊金龍：我看到了。\n    97年10月22日14時14分\n      簡訊內容：老弟昨晚你送來的點心我朋友說不新鮮所以回\n                個簡信告知看有新鮮一點，不要讓我漏氣…（\n                以下略）\n    甚為明確。其中，通聯對話內容～係聯繫九十七年十月\n    十九日販賣一萬元安非他命交易；～係聯繫九十七年十\n    月廿日販賣一萬五千元安非他命交易；～則係聯繫九十\n    七年十月廿二日轉讓第一級毒品海洛之試用；且對販賣或轉\n    讓之毒品種類、數量、金額、及交付時、地等內容，均至為\n    明確。且証人莊金龍亦對前揭通聯對話內容証稱：至係\n    請被告幫忙拿毒品，再將錢交給被告；與被告對話中所講的\n    「男孩子」是指安非他命；其要被告將安非他命分成一包含\n    袋秤重為二點五公克要給台北的朋友，另外一包為實重零點\n    五公克安非他命則是其酬傭（偵卷第五、六、八頁筆錄）。\n    而通聯對話內容至係其與被告議價八分之一兩，經被告\n    同意為一萬五千元（原審卷第一一０頁筆錄）。至通聯對話\n    內容至，「查某的」係指海洛因，「版子」係指海洛因\n    之樣品，該次與被告約見拿海洛因試用品，是由被告免費提\n    供（偵卷第一八頁筆錄）等情均相一致。是被告於九十七年\n    十月十九日、廿日各販賣一次安非他命予莊金龍，得款一萬\n    及一萬五千元；另於同年月廿二日無償轉讓一包海洛因予莊\n    金龍試用等情，事證至臻明確，被告犯行洵堪認定，自應依\n    法論科。\n三、毒品危害防制條例第四條第二項條文業於九十八年五月二十\n    日修正公布，且已施行，就該條例第四條第二項販賣第二級\n    毒品法定罰金刑部分，已由修正前得併科七百萬元以下罰金\n    ，修正為得併科一千萬元以下罰金，是此部份修正後，並未\n    較有利於被告。依刑法第二條第一項但書規定，本案被告販\n    賣第二級毒品部分犯行，自應適用修正前之第四條第二項規\n    定為最有利行為人。另同條例第十七條有關減輕其刑之規定\n    ，修正前毒品危害防制條例第十七條規定「犯第四條第一項\n    至第四項、第五條第一項至第四項前段、第六條第一項至第\n    四項、第七條第一項至第四項、第八條第一項至第四項、第\n    十條或第十一條第一項、第二項之罪，供出毒品來源，因而\n    破獲者，得減輕其刑」之規定；修正後第一項規定：「犯第\n    四條至第八條、第十條或第十一條之罪，供出毒品來源，因\n    而查獲其他正犯或共犯者，減輕或免除其刑。」擴張供出破\n    獲毒品來源至其他正犯或共犯；並增列第二項：「犯第四條\n    至第八條之罪於偵查及審判中均自白者，減輕其刑。」之規\n    定，是有關被告供出其他正犯（含來源）、共犯，或於偵審\n    中自白犯行，則均有減刑之適用，均先此敘明。\n四、核被告所為，於九十七年十月十九日及廿日二次與莊金龍之\n    交易毒品安非他命，均係犯毒品危害防制條例第四條第二項\n    之販賣第二級毒品罪；而於同年月廿二日交付毒品海洛因，\n    則係犯同條例第八條第一項之轉讓第一級毒品罪。至公訴人\n    就被告前揭轉讓第一級毒品部分之犯行，原起訴係犯同條例\n    第四條第一項、第六項之販賣第一級毒品未遂罪，然依卷附\n    通聯譯文，莊金龍僅向被告表示要索取海洛因試用，二人均\n    未提及交易價格、數量（參見前開通聯對話內容至），\n    且証人莊金龍亦証陳被告係免費提供試用品等語一致（偵卷\n    第一八頁筆錄），則此部份自無從証明被告有販賣營利之犯\n    行，惟此部分轉讓第一級毒品既遂與起訴販賣第一級毒品未\n    遂，就交付第一級毒品部分之基本社會事實同一，本院因得\n    變更起訴法條。又被告販賣第二級毒品安非他命、轉讓第一\n    級毒品海洛因，其前後持有安非他命及海洛因之低度行為，\n    均分別為販賣、轉讓之高度行為所吸收，均不另論罪。再被\n    告所犯上揭各罪，犯意各別，行為互異，時間亦殊，為數行\n    為，自應予分論併罰。另被告前因詐欺案件，經臺灣基隆地\n    方法院以九十六年度易字第一八九號判決，判處減為有期徒\n    刑五月，並於民國九十七年三月十六日入監起算刑期，至九\n    十七年八月十五日期滿執行完畢，此有本院被告前案紀錄表\n    一份在卷可按，其受有期徒刑執行完畢，五年以內故意再犯\n    有期徒刑以上之本案，均為累犯，惟除販賣第二級毒品法定\n    之無期徒刑，依法不得加重外，餘均應依刑法第四十七條第\n    一項規定加重其刑。又被告於調查初始，即曾以匿名方式供\n    出毒品安非他命之上手劉文斌之資料，並經海巡署查緝員廖\n    韋傑到庭結証：劉文斌雖經通訊監察時間較早，惟其出入地\n    點、處所太多，無法確切掌握，後確因被告提供之資訊始得\n    緝獲並移送安非他命案件（原審卷第九一、九二頁審判筆錄\n    ）等語；暨証人劉文斌雖於原審對確切之時、地（海洋大學\n    或八斗子漁會附近），因時隔久遠印象模糊，然對確曾交付\n    一萬五千元之安非他命予被告一節，則前後一致（原審卷第\n    一四一～一四二頁審判筆錄），是足認被告確有供出其第二\n    級毒品安非他命之來源並經查獲其他正犯劉文斌，是其所犯\n    販賣第二級毒品罪部分，自應依毒品危害防制條例第十七條\n    第一項規定及先加後減之例，減輕其刑。至轉讓之第一級毒\n    品海洛因，被告並未供出其來源（偵卷第七０頁倒數第七行\n    訊問筆錄），劉文斌亦否認有海洛因（原審卷第一四二頁第\n    十三行審判筆錄），且亦未經查獲販賣海洛因犯行。此部分\n    即不符同條項供出來源減刑之規定，附此敘明。又被告於偵\n    查中，就其監聽通聯有關交易第二級毒品安非他命之內容均\n    坦承，並逐一解釋其與莊金龍交易安非他命之時、地、交付\n    毒品數量、收取之價金（偵卷第二五～三０頁調查筆錄、第\n    六四～六九頁、第七三～七四頁訊問筆錄）等情，於警訊亦\n    坦認販賣安非他命（偵卷第三一頁第十八行調查筆錄）\n    ；另轉讓第一級毒品海洛因部分，被告於偵查中亦坦認不諱\n    （偵卷第三一頁調查筆錄、第七二、七三頁訊問筆錄）；暨\n    嗣於本院審理中，亦就前開販賣第二級毒品及轉讓第一級毒\n    品之犯罪事實均為自白犯罪（本院九十九年三月廿三日準備\n    筆錄第二頁、同年四月廿一日審判筆錄第三頁），亦均符同\n    條例第十七條第二項減刑規定，是各應依該條項規定及先加\n    後減之例減輕或遞減其刑。\n五、原審對被告論罪科刑，固非無見，惟(一)有關被告累犯之前科\n    ，其中經減刑、定執行刑各六月所犯之施用毒品、贓物案件\n    及減刑為二月之偽造文書案件，均係分別接續執行之前案，\n    原判決未注意及接續執行之先後，均論以累犯，容有未洽；\n    (二)如前所述，被告既有供出安非他命毒品來源並因而由警查\n    獲，然原判決猶以被告嗣畏懼報復之改稱及遭查獲之上手劉\n    文斌未供承係被告毒品供應上手或嗣為迴護等情，就販賣第\n    二級毒品安非他命部分，認被告不符毒品危害防制條例第十\n    七條第一項供出來源而查獲其他正犯之減刑規定，即有未合\n    ；(三)至被告於偵、審階段均有自白販賣第二級毒品安非他命\n    及轉讓第一級毒品海洛因犯行，依法均應為減輕其刑，原審\n    未查，認被告否認第二級毒品交易之營利及利得，難認其有\n    自白販賣第二級毒品犯行；復均未論及偵審中均自白轉讓第\n    一級毒品犯行，符合減刑規定，均有未洽。被告上訴指摘本\n    案販賣第二級毒品及轉讓第一級毒品，原審均未適用供出來\n    源查獲上手及於偵審中均自白二項減刑規定，雖非均有理由\n    ，然如前述，既有前揭可議，自應由本院撤銷改判。爰審酌\n    被告之品性、素行，明知毒品對人體有莫大之戕害仍予販賣\n    、轉讓，危害國民身體健康及社會風氣甚鉅，且現值壯年猶\n    不思以正當途徑賺取報酬，竟以此非法途徑為之，惡性非輕\n    ，惟於本院審理供承販賣第二級毒品、轉讓第一級毒品犯行\n    不諱，尚知悔悟，並兼衡本案所販賣、轉讓毒品之數量非多\n    ，所得利益亦非詎等一切情狀，乃分別量處如主文所示之刑\n    ，並定其應執行之刑，以資懲儆。\n六、被告經查獲時，另查扣於臺灣基隆地方法院檢察署九十八年\n    度偵字第七二四號案件之門號0000000000號行動電話一具（\n    含SIM卡一張），乃被告所有，且係供本案聯繫販賣第二級\n    毒品、轉讓第一級毒品使用之物，業據其供承在卷，自應依\n    毒品危害防制條例第十九條第一項規定宣告沒收。至被告就\n    二次販賣第二級毒品安非他命所得財物計二萬五千元，雖未\n    扣案，則係屬其因本案販賣毒品犯罪所得之財物，亦應依同\n    項規定宣告沒收，如全部或一部不能沒收時，以其財產抵償\n    之。\n七、據上論斷，應依刑事訴訟法第三百六十九條第一項前段、第\n    三百六十四條、第二百九十九條第一項前段、第三百條，修\n    正前毒品危害防制條例第四條第二項，毒品危害防制條例第\n    八條第一項、第十七條第一項、第二項、第十九條第一項，\n    刑法第二條第一項後段、第十一條前段、第四十七條第一項\n    、第五十一條第五款，判決如主文。\n本案經檢察官李叔芬到庭執行職務。\n中    華    民    國  九十九  年    五    月   十二   日\n                  刑事第四庭  審判長法  官  陳筱珮\n                                    法  官  孫惠琳\n                                    法  官  陳玉雲\n以上正本證明與原本無異。\n如不服本判決，應於收受送達後10日內向本院提出上訴書狀，其\n未敘述上訴之理由者並得於提起上訴後10日內向本院補提理由書\n（均須按他造當事人之人數附繕本）「切勿逕送上級法院」。\n                                    書記官  陳思云\n中    華    民    國    99    年    5     月    18    日\n附錄：本案論罪科刑法條全文\n毒品危害防制條例第4條（修正前）\n製造、運輸、販賣第一級毒品者，處死刑或無期徒刑；處無期徒\n刑者，得併科新臺幣一千萬元以下罰金。\n製造、運輸、販賣第二級毒品者，處無期徒刑或七年以上有期徒\n刑，得併科新臺幣七百萬元以下罰金。\n毒品危害防制條例第8條\n轉讓第一級毒品者，處 1 年以上 7 年以下有期徒刑，得併科新\n臺幣 1 百萬元以下罰金。\n毒品危害防制條例第17條\n犯第 4 條至第 8 條、第 10 條或第 11 條之罪，供出毒品來源\n，因而查獲其他正犯或共犯者，減輕或免除其刑。\n犯第 4 條至第 8 條之罪於偵查及審判中均自白者，減輕其刑。\n毒品危害防制條例第19條\n犯第 4 條至第 9 條、第 12 條、第 13 條或第 14 條第 1 項\n、第 2 項之罪者，其供犯罪所用或因犯罪所得之財物，均沒收\n之，如全部或一部不能沒收時，追徵其價額或以其財產抵償之。",
  "structure": {
    "main": "原判決撤銷。\n甲○○販賣第二級毒品，累犯，處有期徒刑肆年，扣案門號Ｚ0\n00000000號行動電話壹具（含SIM卡壹張）沒收，販賣\n第二級毒品所得財物新臺幣壹萬元均沒收，如全部或一部不能沒\n收時，以其財產抵償之。又販賣第二級毒品，累犯，處有期徒刑\n肆年，扣案門號Ｚ000000000號行動電話壹具（含SIM\n卡壹張）沒收，販賣第二級毒品所得財物新臺幣壹萬伍仟元均沒\n收，如全部或一部不能沒收時，以其財產抵償之。又轉讓第一級\n毒品，累犯，處有期徒刑壹年，扣案門號Ｚ000000000\n號行動電話壹具（含SIM卡壹張）沒收。應執行有期徒刑陸年，\n扣案門號Ｚ000000000號行動電話壹具（含SIM卡壹張\n）沒收，販賣第二級毒品所得財物新臺幣貳萬伍仟元均沒收，如\n全部或一部不能沒收時，以其財產抵償之。",
    "fact": "一、甲○○前因詐欺案件，經臺灣基隆地方法院以九十六年度易\n    字第一八九號判決，判處減為有期徒刑五月，並於民國九十\n    七年三月十六日入監起算刑期，至九十七年八月十五日期滿\n    執行完畢。詎其猶不知悔改，明知海洛因、安非他命分屬毒\n    品危害防制條例第二條第二項第一款、第二款所定之第一、\n    二級毒品，不得販賣、轉讓及持有，竟分別基於販賣第二級\n    毒品以營利，及轉讓第一級毒品之犯意，以其所有門號0000\n    000000號行動電話作為販賣、轉讓毒品聯繫之用，先於九十\n    七年十月十九日十三時四十二分許，莊金龍以其所有門號00\n    00000000號行動電話，與甲○○前開行動電話聯繫，二人約\n    至基隆市○○區○○街十二號八斗子派出所附近之海產店前\n    ，由甲○○販賣二包安非他命（一包毛重約二點五公克、另\n    一包淨重約零點五公克）予莊金龍，並當場收取一萬元之價\n    款營利。後於同年月廿日零時四十二分許，莊金龍又以同行\n    動電話與甲○○聯繫，二人約至基隆市○○區○○路基隆海\n    洋大學附近之全家便利商店處，由甲○○販賣交付安非他命\n    一包（毛重約四點六八七五公克）予莊金龍，並收取一萬五\n    千元之價款營利。嗣於同年月廿二日零時五分許，莊金龍向\n    甲○○索取試用第一級毒品海洛因，甲○○即約至基隆市○\n    ○區○○路、調和街口處見面，並無償提供不詳數量之海洛\n    因一包（無證據證明已逾淨重五公克）予莊金龍試用，惟莊\n    金龍施用後認為品質不佳，而無下文。\n二、案經警對莊金龍持用之0000000000號行動電話門號實施通訊\n    監察，因而循線查獲上情，乃由臺北縣政府警察局瑞芳分局\n    報請臺灣基隆地方法院檢察署檢察官偵查起訴。",
    "reason": "一、証據能力部分：\n    (一)按被告之自白，非出於強暴、脅迫、利誘、詐欺、疲勞訊\n      問、違法羈押或其他不正之方法，且與事實相符者，得為\n      證據；被告陳述其自白係出於不正之方法者，應先於其他\n      事證而為調查，該自白如係經檢察官提出者，法院應命檢\n      察官就自白之出於自由意志，指出證明之方法，刑事訴訟\n      法第一百五十六條第一項、第三項定有明文。準此，被告\n      及辯護人對檢察官所提被告於警詢、偵查中不利於己之供\n      述，證據能力並無意見，且本院亦查無有何顯然不正之方\n      法取得情事，而悖於其自由意志，是被告前開不利於己供\n      述得為證據。\n    (二)按被告以外之人於審判外之言詞或書面陳述，除法律有規\n      定者外，不得作為證據，刑事訴訟法第一百五十九條第一\n      項固有明文。惟被告以外之人於審判外之陳述，雖不符刑\n      事訴訟法第一百五十九條之一至第一百五十九條之四之規\n      定，而經當事人於審判程序同意作為證據，法院審酌該言\n      詞陳述或書面陳述作成時之情況，認為適當者，亦得為證\n      據；當事人、代理人或辯護人於法院調查證據時，知有第\n      一百五十九條第一項不得為證據之情形，而未於言詞辯論\n      終結前聲明異議者，視為有前項之同意，同法第一百五十\n      九條之五定有明文。經查，本案証人莊金龍前於警詢及偵\n      查中之陳述（偵卷第五～二０頁警詢筆錄、偵卷第一０六\n      頁～一一三頁偵查筆錄），固為被告以外之人於審判外之\n      言詞陳述，惟經原審及本院於審判程序中提示予被告並告\n      以要旨，被告及其辯護人對該證據之證據能力均表示無意\n      見，且均同意作為證據（本院九十九年三月二十三日準備\n      程序筆錄第二頁），且迄至言詞辯論終結前均未再聲明異\n      議，本院審酌上開陳述作成時之情況，尚無違法取證及證\n      明力明顯過低之瑕疵，為證明犯罪事實所必要，亦認以之\n      作為證據應屬適當，揆諸上開規定，前揭證據皆有證據能\n      力。\n    (三)再按有事實足認被告或犯罪嫌疑人有最輕本刑為三年以上\n      有期徒刑之罪嫌，並危害國家安全或社會秩序情節重大，\n      而有相當理由可信其通訊內容與本案有關，且不能或難以\n      其他方法蒐集或調查證據者，得發通訊監察書，通訊保障\n      及監察法第五條第一項第一款定有明文。經查，本案對證\n      人莊金龍使用之門號0000000000號行動電話實施通訊監察\n      ，乃以其涉犯毒品危害防制條例第四條罪嫌，為最輕本刑\n      為三年以上有期徒刑，並危害國家安全或社會秩序情節重\n      大，而不能或難以其他方法蒐集或調查證據，爰經法院准\n      予實施通訊監察，所得監聽譯文內容（見偵查卷第三二頁\n      至四四頁），合於通訊保障及監察法所定要件而取得之證\n      據，而被告於監聽過程透露犯罪行為之陳述，並非因員警\n      監聽所致，而係出於被告之自由意思，自可採信，因之監\n      聽錄音所取得之證據，有證據能力。又監聽錄得之錄音，\n      係憑機械力照錄，未經人為操作，復未伴有個人主觀意見\n      在內，而將監聽之內容製作成譯文，乃將上開具有證據能\n      力之監聽錄得之錄音具體為文字紀錄，此部分雖屬傳聞，\n      然此係由承辦員警本於偵查案件職務所製作，復無證據顯\n      示存有詐偽或虛飾之情事，況經原審及本院依職權於審理\n      期日提示上揭通訊監聽譯文令被告等辨識，被告及其選任\n      辯護人均未爭執證據能力，且不否認監聽譯文之內容為真\n      正，則該監聽譯文依據刑事訴訟法第一百五十九條之五規\n      定，自有證據能力。\n二、上開犯罪事實，業據上訴人即被告甲○○於本院審理中坦承\n    不諱，核與其使用之0000000000行動電話與証人莊金龍使用\n    之0000000000號行動電話，經監聽錄得二人對談內容：\n    97年10月19日13時42分\n      甲○○：喂。\n      莊金龍：老低，這次我是沒賺喔，他們說1萬啦，1萬你要\n              算多少給他？\n      甲○○：1萬喔。\n      莊金龍：實的1萬。\n      甲○○：我跟你說1克4 千，1萬剛好2.5啦。\n      莊金龍：哼，另外commission踩一點給我們啦。\n      甲○○：哥哥，阿厚阿，我2.5給他實重，我再0.2給你，\n              我沒賺啦。\n      莊金龍：不然你也拉一點過來。\n      甲○○：也可以從他那拉一點過去給你就對啦？\n      莊金龍：沒關係啦。\n      甲○○：這樣講我含袋的2.5給他。\n      莊金龍：含袋2.5就對啦。\n      甲○○：他減個0.2而已，那0.2補給你那邊。我給你實重\n              0.5。\n      莊金龍：好阿。\n      甲○○：你人在哪？\n      莊金龍：含袋2.5，另外一個實重0.5給我們。你打電話給\n              我，因為我這一支是易付卡。\n    97年10月19日13時55分\n      甲○○：喂。\n      莊金龍：他差不多要40分鐘就到了。\n      甲○○：到哪？\n      莊金龍：到我們瑞芳阿。\n      甲○○：多少你跟我說好了？\n      莊金龍：1萬，他們要1萬。你要分多少給他們？\n      甲○○：沒有啦，你跟我說他們要多少，要給你多少？\n      莊金龍：你說什麼？\n      甲○○：你想要給他們多少，我要給你多少，你直接講啦\n              。\n      莊金龍：一樣2.5就好了。\n      甲○○：實重還是含袋子重？\n      莊金龍：實重啦，實重給他。\n      甲○○：那你呢？\n      莊金龍：我有或沒有都沒關係啦。\n    97年10月19日15時24分\n      莊金龍：到了。\n      甲○○：你們等我3分鐘。\n      莊金龍：3分鐘。\n      甲○○：你們前面一點有一家五金行，不要好了到港邊，\n              你到八斗子派出所下去有一家海產店，約在那。\n      莊金龍：好。\n    97年10月19日15時31分\n      莊金龍：喂。\n      甲○○：到了，我到了。你在海產店對面嗎？\n      莊金龍：對阿。\n      甲○○：好。\n    97年10月19日22時53分\n      莊金龍：明天男孩子有比較好的？\n      甲○○：這就是好的，不然什麼叫好呢。\n      莊金龍：幾個都有辦法喔？\n      甲○○：何時？\n      莊金龍：明天阿。\n      甲○○：明天跟今天不一樣了喔，明天就沒辦法那樣了喔\n              ，我意思是說量不能給那麼多了喔。\n    97年10月20日0 時42分。\n      莊金龍：我這收訊不好，41。\n      甲○○：沒那麼多？\n      莊金龍：你那剩多少？\n      甲○○：81。\n      莊金龍：剩81而已喔。81要算多少？\n      甲○○：16。之前都這樣。每個都這樣。\n      莊金龍：81都切15。\n      甲○○：好，15。我早上這樣都沒賺錢呢。我剩81本來留\n              給臺北的朋友，但還沒上來，不然在催。你多久\n              會到？\n      莊金龍：我現在馬上聯絡。他馬上到。\n      甲○○：看多久會到打電話來說一下。\n      莊金龍：好。\n    97年10月20日2時23分許\n      甲○○：我在路上，你們到海洋大學翻頭過來有一間全家\n              。\n      莊金龍：全家在哪裡？\n      甲○○：全家便利商店啦。\n      莊金龍：喔。\n    97年10月20日2時43分\n      莊金龍：含袋子總共才4.2。\n      甲○○：那的袋子0.6啦。這樣... （模糊）\n      莊金龍：喂，你打給我。\n    97年10月22日0時5分\n      莊金龍：我叫你拿版子給我，人家電話一直打啦。對阿，\n              你版子拿給我，我拿給他，他說好你再出現。\n      甲○○：沒有，我現在。\n      莊金龍：你很像不信任我的樣子。\n      甲○○：不是，說這樣，那些都被動過了。\n      莊金龍：無啦，男孩子啦。\n      甲○○：男孩子我也沒有，2個都沒有啦。\n      莊金龍：你被動過，動到哪裡？\n      甲○○：我不知道。\n      莊金龍：我等一下過去你拿版子給我。\n      甲○○：阿被動過還版子，剛拿給別人就被別人退了。\n      莊金龍：阿。\n      甲○○：你說什麼？\n      莊金龍：我說那個是半個、一個而已。\n      甲○○：你說什麼東西？\n      莊金龍：男孩子阿，他那個是半錢和一錢而已。最高是這\n              樣。\n      甲○○：我聽不懂你意思？\n      莊金龍：意思說人家要半個、一個，我們拿給他。我主要\n              是要你的版子，不是要用你的版子。\n      甲○○：恩。\n      莊金龍：你版子給我，我拿給他，他說可以，我電話馬上\n              聯絡，你馬上送過來？\n      甲○○：你說查某的嗎？\n      莊金龍：恩啦。\n      甲○○：好啦，我等一下拿給你。\n      莊金龍：好啦。\n    97年10月22日0 時25分。\n      甲○○：你現在來調和街這？\n      莊金龍：這麼遠喔？\n      甲○○：不然不要好了？我現在人在這。\n      莊金龍：喔，這樣。\n      甲○○：你多久會到？\n      莊金龍：10分鐘。\n      甲○○：哪裡你知道嗎？不然我要走了。\n      莊金龍：靠近哪？\n      甲○○：你深澳坑路往八斗子這，現在，平交道過來轉彎\n              ，冷凍廠那，轉過來有一間廟。\n      莊金龍：好。\n      甲○○：快點喔。\n    97年10月22日0 時33分\n      莊金龍：我到八斗子冷凍廠了。\n      甲○○：哪有，我沒看到你，你沒從調和街這條彎上來？\n      莊金龍：有阿，我現在要彎過去了。\n      甲○○：有阿。\n      莊金龍：我看到了。\n    97年10月22日14時14分\n      簡訊內容：老弟昨晚你送來的點心我朋友說不新鮮所以回\n                個簡信告知看有新鮮一點，不要讓我漏氣…（\n                以下略）\n    甚為明確。其中，通聯對話內容～係聯繫九十七年十月\n    十九日販賣一萬元安非他命交易；～係聯繫九十七年十\n    月廿日販賣一萬五千元安非他命交易；～則係聯繫九十\n    七年十月廿二日轉讓第一級毒品海洛之試用；且對販賣或轉\n    讓之毒品種類、數量、金額、及交付時、地等內容，均至為\n    明確。且証人莊金龍亦對前揭通聯對話內容証稱：至係\n    請被告幫忙拿毒品，再將錢交給被告；與被告對話中所講的\n    「男孩子」是指安非他命；其要被告將安非他命分成一包含\n    袋秤重為二點五公克要給台北的朋友，另外一包為實重零點\n    五公克安非他命則是其酬傭（偵卷第五、六、八頁筆錄）。\n    而通聯對話內容至係其與被告議價八分之一兩，經被告\n    同意為一萬五千元（原審卷第一一０頁筆錄）。至通聯對話\n    內容至，「查某的」係指海洛因，「版子」係指海洛因\n    之樣品，該次與被告約見拿海洛因試用品，是由被告免費提\n    供（偵卷第一八頁筆錄）等情均相一致。是被告於九十七年\n    十月十九日、廿日各販賣一次安非他命予莊金龍，得款一萬\n    及一萬五千元；另於同年月廿二日無償轉讓一包海洛因予莊\n    金龍試用等情，事證至臻明確，被告犯行洵堪認定，自應依\n    法論科。\n三、毒品危害防制條例第四條第二項條文業於九十八年五月二十\n    日修正公布，且已施行，就該條例第四條第二項販賣第二級\n    毒品法定罰金刑部分，已由修正前得併科七百萬元以下罰金\n    ，修正為得併科一千萬元以下罰金，是此部份修正後，並未\n    較有利於被告。依刑法第二條第一項但書規定，本案被告販\n    賣第二級毒品部分犯行，自應適用修正前之第四條第二項規\n    定為最有利行為人。另同條例第十七條有關減輕其刑之規定\n    ，修正前毒品危害防制條例第十七條規定「犯第四條第一項\n    至第四項、第五條第一項至第四項前段、第六條第一項至第\n    四項、第七條第一項至第四項、第八條第一項至第四項、第\n    十條或第十一條第一項、第二項之罪，供出毒品來源，因而\n    破獲者，得減輕其刑」之規定；修正後第一項規定：「犯第\n    四條至第八條、第十條或第十一條之罪，供出毒品來源，因\n    而查獲其他正犯或共犯者，減輕或免除其刑。」擴張供出破\n    獲毒品來源至其他正犯或共犯；並增列第二項：「犯第四條\n    至第八條之罪於偵查及審判中均自白者，減輕其刑。」之規\n    定，是有關被告供出其他正犯（含來源）、共犯，或於偵審\n    中自白犯行，則均有減刑之適用，均先此敘明。\n四、核被告所為，於九十七年十月十九日及廿日二次與莊金龍之\n    交易毒品安非他命，均係犯毒品危害防制條例第四條第二項\n    之販賣第二級毒品罪；而於同年月廿二日交付毒品海洛因，\n    則係犯同條例第八條第一項之轉讓第一級毒品罪。至公訴人\n    就被告前揭轉讓第一級毒品部分之犯行，原起訴係犯同條例\n    第四條第一項、第六項之販賣第一級毒品未遂罪，然依卷附\n    通聯譯文，莊金龍僅向被告表示要索取海洛因試用，二人均\n    未提及交易價格、數量（參見前開通聯對話內容至），\n    且証人莊金龍亦証陳被告係免費提供試用品等語一致（偵卷\n    第一八頁筆錄），則此部份自無從証明被告有販賣營利之犯\n    行，惟此部分轉讓第一級毒品既遂與起訴販賣第一級毒品未\n    遂，就交付第一級毒品部分之基本社會事實同一，本院因得\n    變更起訴法條。又被告販賣第二級毒品安非他命、轉讓第一\n    級毒品海洛因，其前後持有安非他命及海洛因之低度行為，\n    均分別為販賣、轉讓之高度行為所吸收，均不另論罪。再被\n    告所犯上揭各罪，犯意各別，行為互異，時間亦殊，為數行\n    為，自應予分論併罰。另被告前因詐欺案件，經臺灣基隆地\n    方法院以九十六年度易字第一八九號判決，判處減為有期徒\n    刑五月，並於民國九十七年三月十六日入監起算刑期，至九\n    十七年八月十五日期滿執行完畢，此有本院被告前案紀錄表\n    一份在卷可按，其受有期徒刑執行完畢，五年以內故意再犯\n    有期徒刑以上之本案，均為累犯，惟除販賣第二級毒品法定\n    之無期徒刑，依法不得加重外，餘均應依刑法第四十七條第\n    一項規定加重其刑。又被告於調查初始，即曾以匿名方式供\n    出毒品安非他命之上手劉文斌之資料，並經海巡署查緝員廖\n    韋傑到庭結証：劉文斌雖經通訊監察時間較早，惟其出入地\n    點、處所太多，無法確切掌握，後確因被告提供之資訊始得\n    緝獲並移送安非他命案件（原審卷第九一、九二頁審判筆錄\n    ）等語；暨証人劉文斌雖於原審對確切之時、地（海洋大學\n    或八斗子漁會附近），因時隔久遠印象模糊，然對確曾交付\n    一萬五千元之安非他命予被告一節，則前後一致（原審卷第\n    一四一～一四二頁審判筆錄），是足認被告確有供出其第二\n    級毒品安非他命之來源並經查獲其他正犯劉文斌，是其所犯\n    販賣第二級毒品罪部分，自應依毒品危害防制條例第十七條\n    第一項規定及先加後減之例，減輕其刑。至轉讓之第一級毒\n    品海洛因，被告並未供出其來源（偵卷第七０頁倒數第七行\n    訊問筆錄），劉文斌亦否認有海洛因（原審卷第一四二頁第\n    十三行審判筆錄），且亦未經查獲販賣海洛因犯行。此部分\n    即不符同條項供出來源減刑之規定，附此敘明。又被告於偵\n    查中，就其監聽通聯有關交易第二級毒品安非他命之內容均\n    坦承，並逐一解釋其與莊金龍交易安非他命之時、地、交付\n    毒品數量、收取之價金（偵卷第二五～三０頁調查筆錄、第\n    六四～六九頁、第七三～七四頁訊問筆錄）等情，於警訊亦\n    坦認販賣安非他命（偵卷第三一頁第十八行調查筆錄）\n    ；另轉讓第一級毒品海洛因部分，被告於偵查中亦坦認不諱\n    （偵卷第三一頁調查筆錄、第七二、七三頁訊問筆錄）；暨\n    嗣於本院審理中，亦就前開販賣第二級毒品及轉讓第一級毒\n    品之犯罪事實均為自白犯罪（本院九十九年三月廿三日準備\n    筆錄第二頁、同年四月廿一日審判筆錄第三頁），亦均符同\n    條例第十七條第二項減刑規定，是各應依該條項規定及先加\n    後減之例減輕或遞減其刑。\n五、原審對被告論罪科刑，固非無見，惟(一)有關被告累犯之前科\n    ，其中經減刑、定執行刑各六月所犯之施用毒品、贓物案件\n    及減刑為二月之偽造文書案件，均係分別接續執行之前案，\n    原判決未注意及接續執行之先後，均論以累犯，容有未洽；\n    (二)如前所述，被告既有供出安非他命毒品來源並因而由警查\n    獲，然原判決猶以被告嗣畏懼報復之改稱及遭查獲之上手劉\n    文斌未供承係被告毒品供應上手或嗣為迴護等情，就販賣第\n    二級毒品安非他命部分，認被告不符毒品危害防制條例第十\n    七條第一項供出來源而查獲其他正犯之減刑規定，即有未合\n    ；(三)至被告於偵、審階段均有自白販賣第二級毒品安非他命\n    及轉讓第一級毒品海洛因犯行，依法均應為減輕其刑，原審\n    未查，認被告否認第二級毒品交易之營利及利得，難認其有\n    自白販賣第二級毒品犯行；復均未論及偵審中均自白轉讓第\n    一級毒品犯行，符合減刑規定，均有未洽。被告上訴指摘本\n    案販賣第二級毒品及轉讓第一級毒品，原審均未適用供出來\n    源查獲上手及於偵審中均自白二項減刑規定，雖非均有理由\n    ，然如前述，既有前揭可議，自應由本院撤銷改判。爰審酌\n    被告之品性、素行，明知毒品對人體有莫大之戕害仍予販賣\n    、轉讓，危害國民身體健康及社會風氣甚鉅，且現值壯年猶\n    不思以正當途徑賺取報酬，竟以此非法途徑為之，惡性非輕\n    ，惟於本院審理供承販賣第二級毒品、轉讓第一級毒品犯行\n    不諱，尚知悔悟，並兼衡本案所販賣、轉讓毒品之數量非多\n    ，所得利益亦非詎等一切情狀，乃分別量處如主文所示之刑\n    ，並定其應執行之刑，以資懲儆。\n六、被告經查獲時，另查扣於臺灣基隆地方法院檢察署九十八年\n    度偵字第七二四號案件之門號0000000000號行動電話一具（\n    含SIM卡一張），乃被告所有，且係供本案聯繫販賣第二級\n    毒品、轉讓第一級毒品使用之物，業據其供承在卷，自應依\n    毒品危害防制條例第十九條第一項規定宣告沒收。至被告就\n    二次販賣第二級毒品安非他命所得財物計二萬五千元，雖未\n    扣案，則係屬其因本案販賣毒品犯罪所得之財物，亦應依同\n    項規定宣告沒收，如全部或一部不能沒收時，以其財產抵償\n    之。\n七、據上論斷，應依刑事訴訟法第三百六十九條第一項前段、第\n    三百六十四條、第二百九十九條第一項前段、第三百條，修\n    正前毒品危害防制條例第四條第二項，毒品危害防制條例第\n    八條第一項、第十七條第一項、第二項、第十九條第一項，\n    刑法第二條第一項後段、第十一條前段、第四十七條第一項\n    、第五十一條第五款，判決如主文。\n本案經檢察官李叔芬到庭執行職務。\n中    華    民    國  九十九  年    五    月   十二   日\n                  刑事第四庭  審判長法  官  陳筱珮\n                                    法  官  孫惠琳\n                                    法  官  陳玉雲\n以上正本證明與原本無異。\n如不服本判決，應於收受送達後10日內向本院提出上訴書狀，其\n未敘述上訴之理由者並得於提起上訴後10日內向本院補提理由書\n（均須按他造當事人之人數附繕本）「切勿逕送上級法院」。\n                                    書記官  陳思云"
  },
  "characters": {
    "judges": [
      "陳筱珮",
      "孫惠琳",
      "陳玉雲"
    ],
    "prosecutors": [
      "李叔芬"
    ],
    "lawyers": [

    ],
    "clerks": [
      "陳思云"
    ],
    "plaintiffs": [

    ],
    "defendants": [
      "上列上訴人即被告因違反毒品危害防制條例案件"
    ],
    "prosecutor_office": [

    ],
    "creditors": [

    ],
    "debtors": [

    ],
    "judicial_associate_officer": [

    ]
  },
  "adjudged_at": "2010-05-12",
  "created_at": "2016-01-05 11:54:22",
  "updated_at": "2016-01-05 11:54:22"
}