{
  "identify": "TPH-98-重上-212-20100105-1",
  "court": {
    "name": "臺灣高等法院",
    "code": "TPH"
  },
  "division": {
    "name": "民事",
    "code": "V"
  },
  "year": 98,
  "word": "重上",
  "number": "212",
  "jcheck": "1",
  "reason": "侵權行為損害賠償",
  "content": "臺灣高等法院民事判決                 98年度重上字第212號\n    上  訴  人  國泰世華商業銀行股份有限公司\n    法定代理人  甲○○\n    訴訟代理人  謝協昌律師\n    上  訴  人  戊○○\n    被上訴人    丙○○\n                丁○○\n                乙○○\n    共      同\n    訴訟代理人  林永頌律師\n                黃韋齊律師\n                張譽尹律師\n    複代理人    洪任遠律師\n上列當事人間請求侵權行為損害賠償事件，國泰世華商業銀行股\n份有限公司對中華民國98年3 月25日臺灣臺北地方法院96年度重\n訴字第1598號第一審判決提起上訴，本院於98年12月15日言詞辯\n論終結，判決如下：\n    主      文\n原判決關於命上訴人應連帶給付被上訴人丁○○、乙○○本息部\n分，及該部分假執行之宣告，暨訴訟費用之裁判均廢棄。\n上開廢棄部分，被上訴人丁○○、乙○○在第一審之訴及假執行\n之聲請均駁回。\n國泰世華商業銀行股份有限公司其餘上訴駁回。\n第一、二審訴訟費用，由國泰世華商業銀行股份有限公司負擔三\n分之一，餘由被上訴人丁○○、乙○○負擔。\n    事實及理由\n一、程序方面：\n  (一)按訴訟標的對於共同訴訟之各人必須合一確定者，共同訴訟\n    中一人之行為有利益於共同訴訟人者，其效力及於全體；不\n    利益者，對於全體不生效力，民事訴訟法第56條第1 款定有\n    明文。而債權人以各連帶債務人為共同被告提起給付之訴，\n    以被告一人提出非基於其個人關係之抗辯，而經法院認為有\n    理由者為限，始得適用民事訴訟法第56條第1 項之規定（最\n    高法院41年台抗字第10號判例）。\n  (二)經查本件上訴人國泰世華商業銀行股份有限公司（下稱國泰\n    世華銀行）主張：原審共同被告戊○○憑藉其理財專員職務\n    之便，利用國泰世華銀行敦化分行之場所，長期對被上訴人\n    施以詐術，盜取被上訴人丙○○之取款密碼，詐騙鉅額存款\n    ，故戊○○應與國泰世華銀行依民法第184 條第1 項、第2\n    項、第188 條第1 項規定連帶負損害賠償責任等語。原審為\n    國泰世華銀行及戊○○敗訴之判決，國泰世華銀行聲明不服\n    提起上訴，經核其上訴理由屬非基於其個人關係之抗辯，且\n    對乙○○、丁○○上訴部分有利於共同訴訟人，此部分上訴\n    人為有理由（詳如後述），依民事訴訟法第56條第1 款之規\n    定，其上訴有理由部分之效力自及於戊○○，仍應併列為\n    本件之上訴人。至於對丙○○部分之上訴為無理由（亦詳如\n    後述），此部分上訴效力不及於戊○○，合先敘明。\n二、本件被上訴人起訴主張：\n  (一)被上訴人三人於國泰世華銀行敦化分行有基金、債券及儲蓄\n    之投資理財行為，但均係被上訴人丙○○借用其子女被上訴\n    人乙○○、丁○○之名義投資，實際上是丙○○在處理。戊\n    ○○時任國泰世華銀行敦化分行之員工，並擔任丙○○之理\n    財專員，而因丙○○不熟悉理財投資，故長期信賴戊○○，\n    由其負責協助丙○○辦理銀行相關業務事宜，雙方已建立特\n    殊之信任關係。嗣於民國93至95年間，戊○○利用職務之便\n    ，偽稱國泰世華銀行有年利率8 ％之優惠存款方案，建議丙\n    ○○將基金與債券贖回後並存入銀行。而丙○○年逾七旬，\n    學歷為高工畢業，自公路局土木建築設計監工退休，從未開\n    立支票，不瞭解銀行流程，且因小洞性中風造成智能障礙，\n    因此雖有從事基金、債券等理財行為，但非專精，不清楚銀\n    行之優惠利率及相關辦理流程，遂信任戊○○之專業建議，\n    而交付存摺、印章及提款密碼予戊○○，經其協助贖回多筆\n    基金及債券，以辦理優惠存款。丙○○復相信戊○○所給付\n    九張印有國泰世華銀行字樣、年利率約8%、發票日為1 年後\n    之支票，係國泰世華銀行敦化分行為定期返還本息所開立，\n    遂委由戊○○將贖回之金錢存入銀行。\n  (二)惟丙○○於95年8 月24日、95年11月1 日提示其中3 張支票\n    ，卻均遭退票，始知該支票為戊○○個人所簽發，經追查結\n    果，方知戊○○將當初應存入國泰世華銀行之款項，共計新\n    臺幣（下同）2,030 萬元，在丙○○不知情下，均由戊○○\n    自國泰世華銀行敦化分行、南門分行、西門分行轉匯入戊○\n    ○、訴外人鄭芫懿、鄭曾豔鳳之帳戶，丙○○至此始知遭戊\n    ○○詐騙鉅額存款。另國泰世華銀行未依銀行法、財政部相\n    關函釋及銀行內規，嚴禁行員代客戶辦理存提款、保管存摺\n    ，及禁止行員與客戶有異常資金往來，顯然未盡善良管理人\n    之注意義務，並違反銀行法第45條之1 第1 項規定。則被上\n    訴人自得依民法第184 條第1 項、第2 項、第188 條第1 項\n    規定，請求戊○○與國泰世華銀行連帶負損害賠償責任。爰\n    求為判命上訴人及戊○○應連帶給付被上訴人2,030 萬元，\n    及國泰世華銀行自96年12月7 日起、戊○○自96年12月11日\n    起至清償日止，按年息5%計算之利息等語（原審為被上訴人\n    勝訴之判決，國泰世華銀行聲明不服提起上訴）。並答辯聲\n    明：上訴駁回。\n三、國泰世華銀行則以：\n  (一)丙○○既於國泰世華銀行敦化分行有儲蓄及購買基金、債券\n    之投資行為，顯見丙○○就投資行為具有基本之經驗及知識\n    。戊○○所聲稱之8 ％優惠利息投資項目，明顯欠缺定期存\n    單之投資憑證，且其固定獲利比率、定期退還本息亦與一般\n    正常投資行為不符，獲利率之約定亦屬過高，故認丙○○僅\n    係因圖高額利息而與戊○○私人間之消費借貸關係。又借款\n    他人取得票據，於借款實務所常見，並未違反經驗法則。反\n    而若係投資行為，何以丙○○並未提出投資建議書、廣告、\n    文宣等任何有關投資之證明。戊○○因投資虧損而向丙○○\n    借款，非不可能。丙○○取得戊○○所簽發之本息支票後，\n    即依二人協議交付款項予戊○○，亦與民間借貸模式相符。\n    且戊○○在國泰世華銀行敦化分行亦設有私人帳戶，其以該\n    私人帳戶所簽發支票，當然印有國泰世華銀行敦化分行字樣\n    ，則縱遭退票，國泰世華銀行亦無庸負責。\n  (二)又戊○○為理財專員，其職務為分析客戶之投資理財方向，\n    則縱係利用上班時間、場所與客戶間為任何私人約定，亦與\n    執行職務無關，欠缺職務本質之內在關聯性。且一般民眾向\n    國泰世華銀行申請開戶時，必同時簽訂綜合約定書，其中共\n    通約定條款第10點規範之主要目的，即在杜絕存戶與行員間\n    私下之金錢往來行為，防止發生不必要之金錢糾紛。是被上\n    訴人於戊○○任職敦化分行期間，與丙○○成立消費借貸關\n    係，顯已違反上揭條款，故被上訴人因此所受之損失，係因\n    自身違背銀行開戶規範之過失所致。又戊○○縱令係以詐欺\n    之方式為之，亦屬其個人之犯罪行為，與其執行職務顯然無\n    關，自無民法第188 條第1 項規定之適用。\n  (三)被上訴人丁○○、乙○○均為被上訴人丙○○之成年子女，\n    渠等之帳戶均係交由丙○○辦理理財投資，丙○○尚且懂得\n    運用其成年子女之帳戶進行投資，而其投資金額更高達數千\n    萬元，其認知能力顯較一般人為高，並無投資、判斷能力較\n    一般人低之情事。又丙○○有多次辦理定期存款之經驗，必\n    定知悉定期存單與支票之差異，亦必然知悉除了借款，沒有\n    任何投資工具係於投資之初即將投資款項連同投資收益一次\n    以支票給付。至於財政部台財融字第88737515號函釋意旨，\n    係為防杜不法集團利用不實資金或調頭寸方式充作驗資證明\n    之弊端，因而要求避免行員與客戶間之不實資金往來，並非\n    當然禁止客戶與行員間之真實資金往來。又戊○○並未受丙\n    ○○之委託而保管存摺，而係於每次與丙○○達成借貸協議\n    後，由戊○○交付支票後，丙○○始交付存摺予戊○○等語\n    ，資為抗辯。惟原判決命國泰世華銀行及戊○○應連帶給付\n    被上訴人2,030 萬元本息，國泰世華銀行為此提起上訴並聲\n    明：(一)原判決廢棄。(二)被上訴人在第一審之訴駁回。\n四、兩造不爭執之事實：\n  (一)原審共同被告戊○○係被上訴人丙○○於國泰世華銀行之理\n    財專員。\n  (二)被上訴人三人於國泰世華銀行之投資、理財事宜，均係丙○\n    ○借用子女乙○○、丁○○之名義投資，均由丙○○處理。\n    原審共同被告戊○○於93年至95年間多次建議丙○○贖回基\n    金與債券。\n  (三)被上訴人三人於國泰世華銀行共2,030萬元之款項，均由原\n    審共同被告戊○○於國泰世華銀行敦化分行、南門分行、西\n    門分行轉入戊○○、戊○○之妻即訴外人鄭芫懿及岳母鄭曾\n    豔鳳之帳戶如下：\n  1.93年10月19日戊○○自丙○○帳戶領取150萬元，戊○○開\n    立發票日為95年10月18日，面額61萬元，票號AE0000000 號\n    ，付款人為國泰世華銀行之支票予丙○○，有國泰世華銀行\n    存款取款憑條、存款存入憑條、支票等件影本附卷可稽（見\n    原法院卷第33、50頁）。\n  2.94年1月19日戊○○自丙○○帳戶領取150萬元後開立發票日\n    為96年1月19日，面額174萬9,600元，票號AE0000000號，付\n    款人為國泰世華銀行支票予丙○○，有國泰世華銀行存款取\n    款憑條、支票影本附卷可稽（見原法院卷第38、53頁）。\n  3.94年10月3日戊○○自丙○○帳戶領取400萬元，戊○○開立\n    發票日為95年10月3日，面額432萬元，票號AE0000000號，\n    付款人為國泰世華銀行之支票予丙○○，有國泰世華銀行存\n    款取款憑條、存款存入憑條、支票影本附卷可稽（見原法院\n    卷第34、49頁）。\n  4.94年12月19日戊○○自被上訴人丁○○帳戶領取430萬元，\n    戊○○開立發票日為95年12月19日，面額464萬4,000元，票\n    號AE0000000號，付款人為國泰世華銀行之支票予被上訴人\n    丙○○，有國泰世華銀行存款取款憑條、存款存入憑條、支\n    票影本附卷可稽（見原法院卷第36、51頁）。\n  5.94年12月19日戊○○自被上訴人乙○○帳戶領取430萬元，\n    戊○○開立發票日為95年12月19日，面額464萬4,000元，票\n    號AE0000000號，付款人為國泰世華銀行之支票予被上訴人\n    丙○○，有國泰世華銀行存款取款憑條、存款存入憑條、支\n    票影本附卷可稽（見原法院卷第37、52頁）。\n  6.95年2月14日戊○○自被上訴人丙○○戶頭領取130萬元，戊\n    ○○開立發票日為96年2月14日，面額151萬6,320元，票號\n    AE0000000號，付款人為國泰世華銀行之支票予丙○○，有\n    國泰世華銀行存款取款憑條、存款存入憑條、支票影本附卷\n    可稽（見原法院卷第39、56頁）。\n  7.95年5月12日戊○○自被上訴人丁○○帳戶領取140萬元，戊\n    ○○開立發票日為96年5月12日，面額151萬2,000元，票號\n    AE0000000號，付款人為國泰世華銀行之支票予被上訴人丙\n    ○○，有國泰世華銀行存款取款憑條、存款存入憑條、支票\n    影本附卷可稽（見原法院卷第40、57頁）。\n  8.95年5月12日戊○○自被上訴人乙○○帳戶領取140萬元，戊\n    ○○開立發票日為96年5月12日，面額151萬2,000元，票號\n    AE0000000號，付款人為國泰世華銀行之支票予被上訴人丙\n    ○○，有國泰世華銀行存款取款憑條、存款存入憑條、支票\n    影本附卷可稽（見原法院卷第41、58頁）。\n  9.95年6月8日戊○○自被上訴人丙○○帳戶領取60萬元，戊○\n    ○開立發票日為95年8月8日，面額61萬元，票號AE0000000\n    號，付款人為國泰世華銀行之支票予丙○○，有國泰世華銀\n    行存款取款憑條、匯出匯款用紙、支票影本附卷可稽（見原\n    法院卷第33、48頁）。\n  (四)根據元富期貨股份有限公司提供原審共同被告戊○○「期貨\n    交易買賣告報書」，戊○○92年7月至95年6月間各月份投資\n    損益數額統計如附表一。\n  (五)被上訴人丙○○於95年8月24日及95年11月1日提示其中三張\n    支票，均遭退票，有退票理由單影本可證（見原法院卷第42\n    至47-1頁）。\n五、兩造爭執要點為：戊○○是否詐騙被上訴人2,030 萬元？國\n    泰世華銀行是否應依民法第188 條第1 項規定，與戊○○連\n    帶負損害賠償責任？茲就兩造爭點及本院得心證理由分述如\n    下：\n  (一)原審共同被告戊○○是否利用理財專員職務之便，向被上訴\n    人丙○○偽稱國泰世華銀行有年利率8％優惠存款，藉此詐\n    騙被上訴人2,030萬元？\n  1.按故意或過失不法侵害他人之權利者，負損害賠償責任，故\n    意以背於善良風俗之方法，加損害於他人者亦同，民法第\n    184 條第1 項定有明文。\n  2.經查被上訴人三人均於國泰世華銀行敦化分行設有活期儲蓄\n    存款帳戶及外幣存款帳戶，有存摺影本可稽（見原審卷第\n    249 至262 頁）。且被上訴人三人除儲蓄外，亦因原審共同\n    被告戊○○之建議而進行基金、債券等金融商品之投資，亦\n    有商品申購或贖回申請書影本可證（見原審卷第23頁）。又\n    被上訴人三人於國泰世華銀行之基金、債券及儲蓄等投資、\n    理財事宜，均係丙○○借用子女乙○○、丁○○之名義投資\n    ，均由丙○○處理。另丙○○自93年2 月間起至95年4 月28\n    日止，陸續購買泰國基金、連動債券等多項投資商品，有「\n    有價證券結構型商品申請書」影本可按（見原審卷第23至32\n    頁），復為兩造所不爭執。則據此足證丙○○確實基於信賴\n    戊○○之理財專業建議，而陸續購買該等商品。\n  3.又一般民眾向國泰世華銀行申請開戶時，必同時簽訂綜合約\n    定書，而依該約定書「壹、共通約定條款」第10點第2 項約\n    定：「存戶領用之存摺不宜交付他人……」有該約定書影本\n    可證（見原審卷第87頁）。而該規範之目的，在於杜絕存戶\n    與行員間私下之金錢來行為，防止發生不必要之金錢糾紛，\n    為兩造所不爭執。因此依照上開規範意旨，若存戶將存摺交\n    付予理財專員，則依一般常情，應認為係存戶委任理財專員\n    從事與銀行間之交易行為，而非存戶與理財專員私下之交易\n    行為。從而戊○○利用擔任丙○○之理財專員機會，建議丙\n    ○○贖回基金，復使丙○○告知提款密碼，並使丙○○先後\n    將自己與乙○○、丁○○之存摺及印鑑交給戊○○領取\n    2,030 萬元等行為，則衡諸常情，客觀上應以丙○○與國泰\n    世華銀行間進行交易行為為常態情形，而以丙○○與戊○○\n    間為消費借貸為變態情形。\n  4.然國泰世華銀行並無固定年利率8%之優惠存款方案，為兩造\n    所不爭執，且戊○○亦於原審到庭證稱：「我一開始跟丙○\n    ○聊現在的定存利率比較低，是否願意寄放在我這裡，我拿\n    去投資，約定給丙○○一年8%的利率……我會開本金加利息\n    8%的個人支票給丙○○，我會跟他說這是我私底下的交易行\n    為。」有言詞辯論筆錄可稽（見原審卷第212 頁）。而丙○\n    ○年逾七旬，其學歷為高工畢業，為公路局土木建築設計監\n    工退休，從未開立支票，不瞭解銀行流程，且因小洞性中風\n    造成智能障礙等情，有退休金證書及畢業證書、長庚紀念醫\n    院精神科診斷證明書影本在卷可憑（本院卷第130 至132 頁\n    ）。則據此足證戊○○明知國泰世華銀行並無上開優惠存款\n    方案，卻利用丙○○之認知、判斷能力較一般人略差之情形\n    ，向丙○○聲稱投資可獲得一年8%的利率，施用詐術使丙○\n    ○陷於錯誤，而交付存摺及印鑑給戊○○領取2,030 萬元。\n    因此丙○○主張：戊○○向丙○○宣稱國泰世華銀行有固定\n    年利率8%之優惠存款，並建議丙○○贖回基金，將款項存入\n    該項優惠存款方案，致丙○○信以為真，而將自己與乙○○\n    、丁○○之存摺及印鑑交給戊○○領取2,030 萬元，受有\n    2,030 萬元之損害等語，即屬有據。\n  5.國泰世華銀行雖否認戊○○詐騙丙○○，辯稱丙○○與戊○\n    ○間之交付印章、存摺與領款行為，係消費借貸關係云云。\n    經查：\n  (1)戊○○僅係為丙○○提供理財服務之人，二人之間並無任何\n    親誼關係，故丙○○若確實以自己之資金出借予戊○○，則\n    依一般交易習慣，即應令戊○○簽立借據或提供擔保。但戊\n    ○○並未簽立借據亦未提供擔保，或約定清償期、利息，復\n    未於原審提出任何反證證明二人之間確實有消費借貸關係，\n    亦未就原審所為敗訴判決聲明不服，故國泰世華銀行主張戊\n    ○○並未詐欺丙○○，而係向丙○○借款之變態事實，自應\n    提出反證以資證明。\n  (2)然國泰世華銀行雖聲請訊問戊○○，惟戊○○經本院傳喚無\n    著，並未到庭，有送達證書可稽（見本院卷第154 、155 頁\n    ）。至於國泰世華銀行雖提出關於戊○○與丙○○間之談話\n    錄音，有譯文在卷可證（見本院卷第77至78頁）。但丙○○\n    否認其真正，國泰世華銀行復未能證明為真；且縱使該錄音\n    譯文所示內容為真，惟綜觀其全文，亦無任何關於借貸還款\n    之對話。此外戊○○雖以個人名義簽發支票予丙○○，但據\n    此尚不足以證明戊○○向丙○○借款。另戊○○於95年7 月\n    11日離職，其所簽發之支票於95年8 月24日第一次跳票，丙\n    ○○遂於96年8 月3 日委請律師寄發存證信函予戊○○要求\n    其賠償，戊○○則於96年9 月6 日匯款5,000 元予丙○○，\n    有退票理由單、存證信函、丙○○之國泰世華銀行帳戶交易\n    明細影本可證（見原審卷第43、59頁、本院卷第80頁）。則\n    據此僅足以證明戊○○給付丙○○5,000 元，但並不足以證\n    明係戊○○與丙○○間締有消費借貸關係。故國泰世華銀行\n    此部分所辯，應屬無據。\n  (二)國泰世華銀行是否應依民法第188 條第1 項規定，與戊○○\n    連帶負損害賠償責任？\n  1.按受僱人因執行職務，不法侵害他人之權利者，由僱用人與\n    行為人連帶負損害賠償責任，民法第188 條第1 項定有明文\n    。而該條規定之目的，在於防免僱用人利用受僱人擴大自己\n    活動範疇之同時，增加侵害他人權益的危險性，因此始課予\n    僱用人選任監督受僱人之注意義務。從而民法第188 條第1\n    項所謂受僱人因執行職務不法侵害他人之權利，不僅指受僱\n    人因執行其所受命令，或委託之職務自體，或執行該職務所\n    必要之行為，而不法侵害他人之權利者而言，即受僱人之行\n    為，在客觀上足認為與其執行職務有關，而不法侵害他人之\n    權利者，就令其為自己利益所為亦應包括在內（最高法院42\n    年度台上字第1224號判例意旨參照）。此外發生損害的事由\n    ，必須與職務之執行，有內在關連性；而內在關連性之存在\n    與否，則視執行職務之目的與性質而定，亦即一切與僱用人\n    所命執行之職務通常合理相關聯之事項，均屬於職務範圍（\n    參見王澤鑑教授著，「僱用人無過失侵權責任的建立」，民\n    法學說與判例研究第一冊，第17頁（1983年7 版）；陳聰富\n    教授著，侵權歸責原則與損害賠償，「受僱人執行職務的行\n    為－評最高法院86年台上字第1497號判決」，第135 頁以下\n    ，93年初版）。\n  2.經查戊○○受僱於國泰世華銀行擔任理財專員，其職務性質\n    為代客戶分析投資理財，其目的為吸引客戶至國泰世華銀行\n    公司從事金融交易行為，而戊○○因此大部分利用上班時間\n    、在上班分行內為丙○○理財之機會，取得丙○○之信任，\n    進而為自己之利益詐取丙○○之金錢，應認為其詐欺行為屬\n    於職務範圍內之行為，與職務之執行有內在關聯性。此種事\n    項，與國泰世華銀行所委辦事務，既具有內在之關聯，國泰\n    世華銀行可得預見，事先可加防範，並得計算其損失於整個\n    企業之內而設法分散。因此課予國泰世華銀行損害賠償責任\n    ，並無不當。從而丙○○主張國泰世華銀行應依民法第188\n    條第1 項規定，與戊○○連帶賠償2,030 萬元本息，即屬有\n    據。至於戊○○之歷次詐欺行為，縱使部分行為非於營業場\n    所即國泰世華銀行國泰世華銀行敦化分行內為之，仍不妨害\n    其與職務執行之內在關聯性。是國泰世華銀行此部分所辯，\n    並不足採。\n  (三)至於被上訴人乙○○、丁○○雖亦於國泰世華銀行開設帳戶\n    並從事投資，但實為丙○○借名投資，並均為丙○○所處理\n    ，為丙○○所自陳，並為國泰世華銀行所不爭執。則乙○○\n    、丁○○既未受戊○○詐欺，且亦未受有經濟上利益之損失\n    ，則渠等請求國泰世華銀行與戊○○連帶賠償2,030 萬元本\n    息，即屬無據。至於戊○○雖未聲明不服提起上訴，惟國泰\n    世華銀行提出非基於其個人關係之抗辯，且部分有利於戊○\n    ○，則依民事訴訟法第56條第1 款之規定，其上訴有理由部\n    分之效力自及於戊○○。\n六、綜上所述，被上訴人丙○○請求國泰世華銀行與戊○○連帶\n    給付2,030 萬元本息，為有理由，應予准許。被上訴人乙○\n    ○、丁○○部分之請求，尚非正當。原審失察遽就超過上開\n    應准許部分，為國泰世華銀行敗訴之判決，並為假執行之宣\n    告，自有未洽。上訴意旨就此部分求予廢棄改判，應予准許\n    。至於上開應准許部分，原審判命國泰世華銀行與戊○○連\n    帶給付，核無違誤。國泰世華銀行就此部分指摘原判決不當\n    ，求予廢棄，為無理由，應駁回其上訴。\n七、本件事證已臻明確，兩造其餘之攻擊、防禦方法，核與判決\n    結果不生影響，毋庸逐一論列，併此敘明。\n八、據上論結，本件上訴為一部有理由，一部無理由。依民事訴\n    訟法第450 條、第449 條第1 項、第78條，判決如主文。\n中    華    民    國    99    年    1     月    5     日\n                    民事第七庭\n                        審判長法  官 鄭三源\n                              法  官 魏麗娟\n                              法  官 邱  琦\n正本係照原本作成。\n如不服本判決，應於收受送達後20日內向本院提出上訴書狀，其\n未表明上訴理由者，應於提出上訴後20日內向本院補提理由書狀\n（均須按他造當事人之人數附繕本）上訴時應提出委任律師或具\n有律師資格之人之委任狀；委任有律師資格者，另應附具律師資\n格證書及釋明委任人與受任人有民事訴訟法第466條之1第1項但\n書或第2項（詳附註）所定關係之釋明文書影本。\n中    華    民    國    99    年    1     月    7     日\n                              書記官 廖豔莉\n附註：\n民事訴訟法第466條之1（第1項、第2項）：\n對於第二審判決上訴，上訴人應委任律師為訴訟代理人。但上訴\n人或其他法定代理人具有律師資格者，不在此限。\n上訴人之配偶、三親等內之血親、二親等內之姻親，或上訴人為\n法人、中央或地方機關時，其所屬專任人員具有律師資格並經法\n院認為適當者，亦得為第三審訴訟代理人。\n附表一：\n┌────┬───────┬──────┬────────────────────┐\n│ 時  間 │當月損益      │累積損益    │備        註                            │\n├────┼───────┼──────┼────────────────────┤\n│92年7月 │      472,900 │     472,900│                                        │\n├────┼───────┼──────┼────────────────────┤\n│92年9月 │   -1,577,500 │  -1,104,600│                                        │\n├────┼───────┼──────┼────────────────────┤\n│92年10月│   -1,328,580 │  -2,433,180│                                        │\n├────┼───────┼──────┼────────────────────┤\n│92年11月│      77,9175 │  -1,654,005│                                        │\n├────┼───────┼──────┼────────────────────┤\n│92年12月│      398,420 │  -1,255,585│                                        │\n├────┼───────┼──────┼────────────────────┤\n│93年1月 │     -890,000 │  -2,145,585│                                        │\n├────┼───────┼──────┼────────────────────┤\n│93年2月 │     -132,890 │  -2,278,475│                                        │\n├────┼───────┼──────┼────────────────────┤\n│93年3月 │     -480,550 │  -2,759,025│                                        │\n├────┼───────┼──────┼────────────────────┤\n│93年4月 │     -240,730 │  -2,999,755│                                        │\n├────┼───────┼──────┼────────────────────┤\n│93年5月 │      -11,850 │  -3,011,605│                                        │\n├────┼───────┼──────┼────────────────────┤\n│93年6月 │     -106,700 │  -3,118,305│                                        │\n├────┼───────┼──────┼────────────────────┤\n│93年7月 │      -70,885 │  -3,189,190│                                        │\n├────┼───────┼──────┼────────────────────┤\n│93年8月 │        2,065 │  -3,187,125│                                        │\n├────┼───────┼──────┼────────────────────┤\n│93年9月 │       -2,075 │  -3,189,200│                                        │\n├────┼───────┼──────┼────────────────────┤\n│93年10月│        2,125 │  -3,187,075│93年10月19日自原告丙○○戶頭領取150 萬元│\n├────┼───────┼──────┼────────────────────┤\n│93年11月│            0 │  -3,187,075│                                        │\n├────┼───────┼──────┼────────────────────┤\n│93年12月│       60,325 │  -3,126,750│                                        │\n├────┼───────┼──────┼────────────────────┤\n│94年1月 │     -216,370 │  -3,343,120│94年1 月19日自原告丙○○戶頭領取150 萬元│\n├────┼───────┼──────┼────────────────────┤\n│94年2月 │      253,575 │  -3,089,545│                                        │\n├────┼───────┼──────┼────────────────────┤\n│94年3月 │     -436,145 │  -3,525,690│                                        │\n├────┼───────┼──────┼────────────────────┤\n│94年4月 │      118,065 │  -3,407,625│                                        │\n├────┼───────┼──────┼────────────────────┤\n│94年5月 │   -1,716,685 │  -5,124,310│                                        │\n├────┼───────┼──────┼────────────────────┤\n│94年6月 │    4,938,150 │    -186,160│                                        │\n├────┼───────┼──────┼────────────────────┤\n│94年7月 │   -1,233,400 │  -1,419,560│                                        │\n├────┼───────┼──────┼────────────────────┤\n│94年8月 │   -2,588,620 │  -4,008,180│                                        │\n├────┼───────┼──────┼────────────────────┤\n│94年9月 │   -2,164,310 │  -6,172,490│                                        │\n├────┼───────┼──────┼────────────────────┤\n│94年10月│   -2,642,050 │  -8,814,540│94年10月3 日被告戊○○自原告丙○○戶頭領│\n│        │              │            │取400 萬元                              │\n├────┼───────┼──────┼────────────────────┤\n│94年11月│     -918,115 │  -9,732,665│                                        │\n├────┼───────┼──────┼────────────────────┤\n│94年12月│     -102,435 │  -9,835,090│94年12月19日自原告丁○○、乙○○戶頭各領│\n│        │              │            │取430 萬元，共計860 萬元                │\n├────┼───────┼──────┼────────────────────┤\n│95年1月 │      462,695 │  -9,372,395│                                        │\n├────┼───────┼──────┼────────────────────┤\n│95年2月 │    1,029,300 │  -8,343,095│95年2 月14日自原告丙○○戶頭領取130 萬元│\n├────┼───────┼──────┼────────────────────┤\n│95年3月 │      27,0450 │  -8,072,645│                                        │\n├────┼───────┼──────┼────────────────────┤\n│95年4月 │      59,7425 │  -7,475,220│                                        │\n├────┼───────┼──────┼────────────────────┤\n│95年5月 │   -3,201,255 │ -10,676,475│95年5 月12日自原告丁○○、乙○○戶頭各領│\n│        │              │            │取140 萬元共計280 萬元                  │\n├────┼───────┼──────┼────────────────────┤\n│95年6月 │   -1,522,975 │ -12,199,450│95年6 月8 日自原告丙○○戶頭領取60 萬元 │\n└────┴───────┴──────┴────────────────────┘",
  "structure": {
    "main": "原判決關於命上訴人應連帶給付被上訴人丁○○、乙○○本息部\n分，及該部分假執行之宣告，暨訴訟費用之裁判均廢棄。\n上開廢棄部分，被上訴人丁○○、乙○○在第一審之訴及假執行\n之聲請均駁回。\n國泰世華商業銀行股份有限公司其餘上訴駁回。\n第一、二審訴訟費用，由國泰世華商業銀行股份有限公司負擔三\n分之一，餘由被上訴人丁○○、乙○○負擔。",
    "fact": "一、程序方面：\n  (一)按訴訟標的對於共同訴訟之各人必須合一確定者，共同訴訟\n    中一人之行為有利益於共同訴訟人者，其效力及於全體；不\n    利益者，對於全體不生效力，民事訴訟法第56條第1 款定有\n    明文。而債權人以各連帶債務人為共同被告提起給付之訴，\n    以被告一人提出非基於其個人關係之抗辯，而經法院認為有\n    理由者為限，始得適用民事訴訟法第56條第1 項之規定（最\n    高法院41年台抗字第10號判例）。\n  (二)經查本件上訴人國泰世華商業銀行股份有限公司（下稱國泰\n    世華銀行）主張：原審共同被告戊○○憑藉其理財專員職務\n    之便，利用國泰世華銀行敦化分行之場所，長期對被上訴人\n    施以詐術，盜取被上訴人丙○○之取款密碼，詐騙鉅額存款\n    ，故戊○○應與國泰世華銀行依民法第184 條第1 項、第2\n    項、第188 條第1 項規定連帶負損害賠償責任等語。原審為\n    國泰世華銀行及戊○○敗訴之判決，國泰世華銀行聲明不服\n    提起上訴，經核其上訴理由屬非基於其個人關係之抗辯，且\n    對乙○○、丁○○上訴部分有利於共同訴訟人，此部分上訴\n    人為有理由（詳如後述），依民事訴訟法第56條第1 款之規\n    定，其上訴有理由部分之效力自及於戊○○，仍應併列為\n    本件之上訴人。至於對丙○○部分之上訴為無理由（亦詳如\n    後述），此部分上訴效力不及於戊○○，合先敘明。\n二、本件被上訴人起訴主張：\n  (一)被上訴人三人於國泰世華銀行敦化分行有基金、債券及儲蓄\n    之投資理財行為，但均係被上訴人丙○○借用其子女被上訴\n    人乙○○、丁○○之名義投資，實際上是丙○○在處理。戊\n    ○○時任國泰世華銀行敦化分行之員工，並擔任丙○○之理\n    財專員，而因丙○○不熟悉理財投資，故長期信賴戊○○，\n    由其負責協助丙○○辦理銀行相關業務事宜，雙方已建立特\n    殊之信任關係。嗣於民國93至95年間，戊○○利用職務之便\n    ，偽稱國泰世華銀行有年利率8 ％之優惠存款方案，建議丙\n    ○○將基金與債券贖回後並存入銀行。而丙○○年逾七旬，\n    學歷為高工畢業，自公路局土木建築設計監工退休，從未開\n    立支票，不瞭解銀行流程，且因小洞性中風造成智能障礙，\n    因此雖有從事基金、債券等理財行為，但非專精，不清楚銀\n    行之優惠利率及相關辦理流程，遂信任戊○○之專業建議，\n    而交付存摺、印章及提款密碼予戊○○，經其協助贖回多筆\n    基金及債券，以辦理優惠存款。丙○○復相信戊○○所給付\n    九張印有國泰世華銀行字樣、年利率約8%、發票日為1 年後\n    之支票，係國泰世華銀行敦化分行為定期返還本息所開立，\n    遂委由戊○○將贖回之金錢存入銀行。\n  (二)惟丙○○於95年8 月24日、95年11月1 日提示其中3 張支票\n    ，卻均遭退票，始知該支票為戊○○個人所簽發，經追查結\n    果，方知戊○○將當初應存入國泰世華銀行之款項，共計新\n    臺幣（下同）2,030 萬元，在丙○○不知情下，均由戊○○\n    自國泰世華銀行敦化分行、南門分行、西門分行轉匯入戊○\n    ○、訴外人鄭芫懿、鄭曾豔鳳之帳戶，丙○○至此始知遭戊\n    ○○詐騙鉅額存款。另國泰世華銀行未依銀行法、財政部相\n    關函釋及銀行內規，嚴禁行員代客戶辦理存提款、保管存摺\n    ，及禁止行員與客戶有異常資金往來，顯然未盡善良管理人\n    之注意義務，並違反銀行法第45條之1 第1 項規定。則被上\n    訴人自得依民法第184 條第1 項、第2 項、第188 條第1 項\n    規定，請求戊○○與國泰世華銀行連帶負損害賠償責任。爰\n    求為判命上訴人及戊○○應連帶給付被上訴人2,030 萬元，\n    及國泰世華銀行自96年12月7 日起、戊○○自96年12月11日\n    起至清償日止，按年息5%計算之利息等語（原審為被上訴人\n    勝訴之判決，國泰世華銀行聲明不服提起上訴）。並答辯聲\n    明：上訴駁回。\n三、國泰世華銀行則以：\n  (一)丙○○既於國泰世華銀行敦化分行有儲蓄及購買基金、債券\n    之投資行為，顯見丙○○就投資行為具有基本之經驗及知識\n    。戊○○所聲稱之8 ％優惠利息投資項目，明顯欠缺定期存\n    單之投資憑證，且其固定獲利比率、定期退還本息亦與一般\n    正常投資行為不符，獲利率之約定亦屬過高，故認丙○○僅\n    係因圖高額利息而與戊○○私人間之消費借貸關係。又借款\n    他人取得票據，於借款實務所常見，並未違反經驗法則。反\n    而若係投資行為，何以丙○○並未提出投資建議書、廣告、\n    文宣等任何有關投資之證明。戊○○因投資虧損而向丙○○\n    借款，非不可能。丙○○取得戊○○所簽發之本息支票後，\n    即依二人協議交付款項予戊○○，亦與民間借貸模式相符。\n    且戊○○在國泰世華銀行敦化分行亦設有私人帳戶，其以該\n    私人帳戶所簽發支票，當然印有國泰世華銀行敦化分行字樣\n    ，則縱遭退票，國泰世華銀行亦無庸負責。\n  (二)又戊○○為理財專員，其職務為分析客戶之投資理財方向，\n    則縱係利用上班時間、場所與客戶間為任何私人約定，亦與\n    執行職務無關，欠缺職務本質之內在關聯性。且一般民眾向\n    國泰世華銀行申請開戶時，必同時簽訂綜合約定書，其中共\n    通約定條款第10點規範之主要目的，即在杜絕存戶與行員間\n    私下之金錢往來行為，防止發生不必要之金錢糾紛。是被上\n    訴人於戊○○任職敦化分行期間，與丙○○成立消費借貸關\n    係，顯已違反上揭條款，故被上訴人因此所受之損失，係因\n    自身違背銀行開戶規範之過失所致。又戊○○縱令係以詐欺\n    之方式為之，亦屬其個人之犯罪行為，與其執行職務顯然無\n    關，自無民法第188 條第1 項規定之適用。\n  (三)被上訴人丁○○、乙○○均為被上訴人丙○○之成年子女，\n    渠等之帳戶均係交由丙○○辦理理財投資，丙○○尚且懂得\n    運用其成年子女之帳戶進行投資，而其投資金額更高達數千\n    萬元，其認知能力顯較一般人為高，並無投資、判斷能力較\n    一般人低之情事。又丙○○有多次辦理定期存款之經驗，必\n    定知悉定期存單與支票之差異，亦必然知悉除了借款，沒有\n    任何投資工具係於投資之初即將投資款項連同投資收益一次\n    以支票給付。至於財政部台財融字第88737515號函釋意旨，\n    係為防杜不法集團利用不實資金或調頭寸方式充作驗資證明\n    之弊端，因而要求避免行員與客戶間之不實資金往來，並非\n    當然禁止客戶與行員間之真實資金往來。又戊○○並未受丙\n    ○○之委託而保管存摺，而係於每次與丙○○達成借貸協議\n    後，由戊○○交付支票後，丙○○始交付存摺予戊○○等語\n    ，資為抗辯。惟原判決命國泰世華銀行及戊○○應連帶給付\n    被上訴人2,030 萬元本息，國泰世華銀行為此提起上訴並聲\n    明：(一)原判決廢棄。(二)被上訴人在第一審之訴駁回。\n四、兩造不爭執之事實：\n  (一)原審共同被告戊○○係被上訴人丙○○於國泰世華銀行之理\n    財專員。\n  (二)被上訴人三人於國泰世華銀行之投資、理財事宜，均係丙○\n    ○借用子女乙○○、丁○○之名義投資，均由丙○○處理。\n    原審共同被告戊○○於93年至95年間多次建議丙○○贖回基\n    金與債券。\n  (三)被上訴人三人於國泰世華銀行共2,030萬元之款項，均由原\n    審共同被告戊○○於國泰世華銀行敦化分行、南門分行、西\n    門分行轉入戊○○、戊○○之妻即訴外人鄭芫懿及岳母鄭曾\n    豔鳳之帳戶如下：\n  1.93年10月19日戊○○自丙○○帳戶領取150萬元，戊○○開\n    立發票日為95年10月18日，面額61萬元，票號AE0000000 號\n    ，付款人為國泰世華銀行之支票予丙○○，有國泰世華銀行\n    存款取款憑條、存款存入憑條、支票等件影本附卷可稽（見\n    原法院卷第33、50頁）。\n  2.94年1月19日戊○○自丙○○帳戶領取150萬元後開立發票日\n    為96年1月19日，面額174萬9,600元，票號AE0000000號，付\n    款人為國泰世華銀行支票予丙○○，有國泰世華銀行存款取\n    款憑條、支票影本附卷可稽（見原法院卷第38、53頁）。\n  3.94年10月3日戊○○自丙○○帳戶領取400萬元，戊○○開立\n    發票日為95年10月3日，面額432萬元，票號AE0000000號，\n    付款人為國泰世華銀行之支票予丙○○，有國泰世華銀行存\n    款取款憑條、存款存入憑條、支票影本附卷可稽（見原法院\n    卷第34、49頁）。\n  4.94年12月19日戊○○自被上訴人丁○○帳戶領取430萬元，\n    戊○○開立發票日為95年12月19日，面額464萬4,000元，票\n    號AE0000000號，付款人為國泰世華銀行之支票予被上訴人\n    丙○○，有國泰世華銀行存款取款憑條、存款存入憑條、支\n    票影本附卷可稽（見原法院卷第36、51頁）。\n  5.94年12月19日戊○○自被上訴人乙○○帳戶領取430萬元，\n    戊○○開立發票日為95年12月19日，面額464萬4,000元，票\n    號AE0000000號，付款人為國泰世華銀行之支票予被上訴人\n    丙○○，有國泰世華銀行存款取款憑條、存款存入憑條、支\n    票影本附卷可稽（見原法院卷第37、52頁）。\n  6.95年2月14日戊○○自被上訴人丙○○戶頭領取130萬元，戊\n    ○○開立發票日為96年2月14日，面額151萬6,320元，票號\n    AE0000000號，付款人為國泰世華銀行之支票予丙○○，有\n    國泰世華銀行存款取款憑條、存款存入憑條、支票影本附卷\n    可稽（見原法院卷第39、56頁）。\n  7.95年5月12日戊○○自被上訴人丁○○帳戶領取140萬元，戊\n    ○○開立發票日為96年5月12日，面額151萬2,000元，票號\n    AE0000000號，付款人為國泰世華銀行之支票予被上訴人丙\n    ○○，有國泰世華銀行存款取款憑條、存款存入憑條、支票\n    影本附卷可稽（見原法院卷第40、57頁）。\n  8.95年5月12日戊○○自被上訴人乙○○帳戶領取140萬元，戊\n    ○○開立發票日為96年5月12日，面額151萬2,000元，票號\n    AE0000000號，付款人為國泰世華銀行之支票予被上訴人丙\n    ○○，有國泰世華銀行存款取款憑條、存款存入憑條、支票\n    影本附卷可稽（見原法院卷第41、58頁）。\n  9.95年6月8日戊○○自被上訴人丙○○帳戶領取60萬元，戊○\n    ○開立發票日為95年8月8日，面額61萬元，票號AE0000000\n    號，付款人為國泰世華銀行之支票予丙○○，有國泰世華銀\n    行存款取款憑條、匯出匯款用紙、支票影本附卷可稽（見原\n    法院卷第33、48頁）。\n  (四)根據元富期貨股份有限公司提供原審共同被告戊○○「期貨\n    交易買賣告報書」，戊○○92年7月至95年6月間各月份投資\n    損益數額統計如附表一。\n  (五)被上訴人丙○○於95年8月24日及95年11月1日提示其中三張\n    支票，均遭退票，有退票理由單影本可證（見原法院卷第42\n    至47-1頁）。\n五、兩造爭執要點為：戊○○是否詐騙被上訴人2,030 萬元？國\n    泰世華銀行是否應依民法第188 條第1 項規定，與戊○○連\n    帶負損害賠償責任？茲就兩造爭點及本院得心證理由分述如\n    下：\n  (一)原審共同被告戊○○是否利用理財專員職務之便，向被上訴\n    人丙○○偽稱國泰世華銀行有年利率8％優惠存款，藉此詐\n    騙被上訴人2,030萬元？\n  1.按故意或過失不法侵害他人之權利者，負損害賠償責任，故\n    意以背於善良風俗之方法，加損害於他人者亦同，民法第\n    184 條第1 項定有明文。\n  2.經查被上訴人三人均於國泰世華銀行敦化分行設有活期儲蓄\n    存款帳戶及外幣存款帳戶，有存摺影本可稽（見原審卷第\n    249 至262 頁）。且被上訴人三人除儲蓄外，亦因原審共同\n    被告戊○○之建議而進行基金、債券等金融商品之投資，亦\n    有商品申購或贖回申請書影本可證（見原審卷第23頁）。又\n    被上訴人三人於國泰世華銀行之基金、債券及儲蓄等投資、\n    理財事宜，均係丙○○借用子女乙○○、丁○○之名義投資\n    ，均由丙○○處理。另丙○○自93年2 月間起至95年4 月28\n    日止，陸續購買泰國基金、連動債券等多項投資商品，有「\n    有價證券結構型商品申請書」影本可按（見原審卷第23至32\n    頁），復為兩造所不爭執。則據此足證丙○○確實基於信賴\n    戊○○之理財專業建議，而陸續購買該等商品。\n  3.又一般民眾向國泰世華銀行申請開戶時，必同時簽訂綜合約\n    定書，而依該約定書「壹、共通約定條款」第10點第2 項約\n    定：「存戶領用之存摺不宜交付他人……」有該約定書影本\n    可證（見原審卷第87頁）。而該規範之目的，在於杜絕存戶\n    與行員間私下之金錢來行為，防止發生不必要之金錢糾紛，\n    為兩造所不爭執。因此依照上開規範意旨，若存戶將存摺交\n    付予理財專員，則依一般常情，應認為係存戶委任理財專員\n    從事與銀行間之交易行為，而非存戶與理財專員私下之交易\n    行為。從而戊○○利用擔任丙○○之理財專員機會，建議丙\n    ○○贖回基金，復使丙○○告知提款密碼，並使丙○○先後\n    將自己與乙○○、丁○○之存摺及印鑑交給戊○○領取\n    2,030 萬元等行為，則衡諸常情，客觀上應以丙○○與國泰\n    世華銀行間進行交易行為為常態情形，而以丙○○與戊○○\n    間為消費借貸為變態情形。\n  4.然國泰世華銀行並無固定年利率8%之優惠存款方案，為兩造\n    所不爭執，且戊○○亦於原審到庭證稱：「我一開始跟丙○\n    ○聊現在的定存利率比較低，是否願意寄放在我這裡，我拿\n    去投資，約定給丙○○一年8%的利率……我會開本金加利息\n    8%的個人支票給丙○○，我會跟他說這是我私底下的交易行\n    為。」有言詞辯論筆錄可稽（見原審卷第212 頁）。而丙○\n    ○年逾七旬，其學歷為高工畢業，為公路局土木建築設計監\n    工退休，從未開立支票，不瞭解銀行流程，且因小洞性中風\n    造成智能障礙等情，有退休金證書及畢業證書、長庚紀念醫\n    院精神科診斷證明書影本在卷可憑（本院卷第130 至132 頁\n    ）。則據此足證戊○○明知國泰世華銀行並無上開優惠存款\n    方案，卻利用丙○○之認知、判斷能力較一般人略差之情形\n    ，向丙○○聲稱投資可獲得一年8%的利率，施用詐術使丙○\n    ○陷於錯誤，而交付存摺及印鑑給戊○○領取2,030 萬元。\n    因此丙○○主張：戊○○向丙○○宣稱國泰世華銀行有固定\n    年利率8%之優惠存款，並建議丙○○贖回基金，將款項存入\n    該項優惠存款方案，致丙○○信以為真，而將自己與乙○○\n    、丁○○之存摺及印鑑交給戊○○領取2,030 萬元，受有\n    2,030 萬元之損害等語，即屬有據。\n  5.國泰世華銀行雖否認戊○○詐騙丙○○，辯稱丙○○與戊○\n    ○間之交付印章、存摺與領款行為，係消費借貸關係云云。\n    經查：\n  (1)戊○○僅係為丙○○提供理財服務之人，二人之間並無任何\n    親誼關係，故丙○○若確實以自己之資金出借予戊○○，則\n    依一般交易習慣，即應令戊○○簽立借據或提供擔保。但戊\n    ○○並未簽立借據亦未提供擔保，或約定清償期、利息，復\n    未於原審提出任何反證證明二人之間確實有消費借貸關係，\n    亦未就原審所為敗訴判決聲明不服，故國泰世華銀行主張戊\n    ○○並未詐欺丙○○，而係向丙○○借款之變態事實，自應\n    提出反證以資證明。\n  (2)然國泰世華銀行雖聲請訊問戊○○，惟戊○○經本院傳喚無\n    著，並未到庭，有送達證書可稽（見本院卷第154 、155 頁\n    ）。至於國泰世華銀行雖提出關於戊○○與丙○○間之談話\n    錄音，有譯文在卷可證（見本院卷第77至78頁）。但丙○○\n    否認其真正，國泰世華銀行復未能證明為真；且縱使該錄音\n    譯文所示內容為真，惟綜觀其全文，亦無任何關於借貸還款\n    之對話。此外戊○○雖以個人名義簽發支票予丙○○，但據\n    此尚不足以證明戊○○向丙○○借款。另戊○○於95年7 月\n    11日離職，其所簽發之支票於95年8 月24日第一次跳票，丙\n    ○○遂於96年8 月3 日委請律師寄發存證信函予戊○○要求\n    其賠償，戊○○則於96年9 月6 日匯款5,000 元予丙○○，\n    有退票理由單、存證信函、丙○○之國泰世華銀行帳戶交易\n    明細影本可證（見原審卷第43、59頁、本院卷第80頁）。則\n    據此僅足以證明戊○○給付丙○○5,000 元，但並不足以證\n    明係戊○○與丙○○間締有消費借貸關係。故國泰世華銀行\n    此部分所辯，應屬無據。\n  (二)國泰世華銀行是否應依民法第188 條第1 項規定，與戊○○\n    連帶負損害賠償責任？\n  1.按受僱人因執行職務，不法侵害他人之權利者，由僱用人與\n    行為人連帶負損害賠償責任，民法第188 條第1 項定有明文\n    。而該條規定之目的，在於防免僱用人利用受僱人擴大自己\n    活動範疇之同時，增加侵害他人權益的危險性，因此始課予\n    僱用人選任監督受僱人之注意義務。從而民法第188 條第1\n    項所謂受僱人因執行職務不法侵害他人之權利，不僅指受僱\n    人因執行其所受命令，或委託之職務自體，或執行該職務所\n    必要之行為，而不法侵害他人之權利者而言，即受僱人之行\n    為，在客觀上足認為與其執行職務有關，而不法侵害他人之\n    權利者，就令其為自己利益所為亦應包括在內（最高法院42\n    年度台上字第1224號判例意旨參照）。此外發生損害的事由\n    ，必須與職務之執行，有內在關連性；而內在關連性之存在\n    與否，則視執行職務之目的與性質而定，亦即一切與僱用人\n    所命執行之職務通常合理相關聯之事項，均屬於職務範圍（\n    參見王澤鑑教授著，「僱用人無過失侵權責任的建立」，民\n    法學說與判例研究第一冊，第17頁（1983年7 版）；陳聰富\n    教授著，侵權歸責原則與損害賠償，「受僱人執行職務的行\n    為－評最高法院86年台上字第1497號判決」，第135 頁以下\n    ，93年初版）。\n  2.經查戊○○受僱於國泰世華銀行擔任理財專員，其職務性質\n    為代客戶分析投資理財，其目的為吸引客戶至國泰世華銀行\n    公司從事金融交易行為，而戊○○因此大部分利用上班時間\n    、在上班分行內為丙○○理財之機會，取得丙○○之信任，\n    進而為自己之利益詐取丙○○之金錢，應認為其詐欺行為屬\n    於職務範圍內之行為，與職務之執行有內在關聯性。此種事\n    項，與國泰世華銀行所委辦事務，既具有內在之關聯，國泰\n    世華銀行可得預見，事先可加防範，並得計算其損失於整個\n    企業之內而設法分散。因此課予國泰世華銀行損害賠償責任\n    ，並無不當。從而丙○○主張國泰世華銀行應依民法第188\n    條第1 項規定，與戊○○連帶賠償2,030 萬元本息，即屬有\n    據。至於戊○○之歷次詐欺行為，縱使部分行為非於營業場\n    所即國泰世華銀行國泰世華銀行敦化分行內為之，仍不妨害\n    其與職務執行之內在關聯性。是國泰世華銀行此部分所辯，\n    並不足採。\n  (三)至於被上訴人乙○○、丁○○雖亦於國泰世華銀行開設帳戶\n    並從事投資，但實為丙○○借名投資，並均為丙○○所處理\n    ，為丙○○所自陳，並為國泰世華銀行所不爭執。則乙○○\n    、丁○○既未受戊○○詐欺，且亦未受有經濟上利益之損失\n    ，則渠等請求國泰世華銀行與戊○○連帶賠償2,030 萬元本\n    息，即屬無據。至於戊○○雖未聲明不服提起上訴，惟國泰\n    世華銀行提出非基於其個人關係之抗辯，且部分有利於戊○\n    ○，則依民事訴訟法第56條第1 款之規定，其上訴有理由部\n    分之效力自及於戊○○。\n六、綜上所述，被上訴人丙○○請求國泰世華銀行與戊○○連帶\n    給付2,030 萬元本息，為有理由，應予准許。被上訴人乙○\n    ○、丁○○部分之請求，尚非正當。原審失察遽就超過上開\n    應准許部分，為國泰世華銀行敗訴之判決，並為假執行之宣\n    告，自有未洽。上訴意旨就此部分求予廢棄改判，應予准許\n    。至於上開應准許部分，原審判命國泰世華銀行與戊○○連\n    帶給付，核無違誤。國泰世華銀行就此部分指摘原判決不當\n    ，求予廢棄，為無理由，應駁回其上訴。\n七、本件事證已臻明確，兩造其餘之攻擊、防禦方法，核與判決\n    結果不生影響，毋庸逐一論列，併此敘明。\n八、據上論結，本件上訴為一部有理由，一部無理由。依民事訴\n    訟法第450 條、第449 條第1 項、第78條，判決如主文。",
    "reason": "一、程序方面：\n  (一)按訴訟標的對於共同訴訟之各人必須合一確定者，共同訴訟\n    中一人之行為有利益於共同訴訟人者，其效力及於全體；不\n    利益者，對於全體不生效力，民事訴訟法第56條第1 款定有\n    明文。而債權人以各連帶債務人為共同被告提起給付之訴，\n    以被告一人提出非基於其個人關係之抗辯，而經法院認為有\n    理由者為限，始得適用民事訴訟法第56條第1 項之規定（最\n    高法院41年台抗字第10號判例）。\n  (二)經查本件上訴人國泰世華商業銀行股份有限公司（下稱國泰\n    世華銀行）主張：原審共同被告戊○○憑藉其理財專員職務\n    之便，利用國泰世華銀行敦化分行之場所，長期對被上訴人\n    施以詐術，盜取被上訴人丙○○之取款密碼，詐騙鉅額存款\n    ，故戊○○應與國泰世華銀行依民法第184 條第1 項、第2\n    項、第188 條第1 項規定連帶負損害賠償責任等語。原審為\n    國泰世華銀行及戊○○敗訴之判決，國泰世華銀行聲明不服\n    提起上訴，經核其上訴理由屬非基於其個人關係之抗辯，且\n    對乙○○、丁○○上訴部分有利於共同訴訟人，此部分上訴\n    人為有理由（詳如後述），依民事訴訟法第56條第1 款之規\n    定，其上訴有理由部分之效力自及於戊○○，仍應併列為\n    本件之上訴人。至於對丙○○部分之上訴為無理由（亦詳如\n    後述），此部分上訴效力不及於戊○○，合先敘明。\n二、本件被上訴人起訴主張：\n  (一)被上訴人三人於國泰世華銀行敦化分行有基金、債券及儲蓄\n    之投資理財行為，但均係被上訴人丙○○借用其子女被上訴\n    人乙○○、丁○○之名義投資，實際上是丙○○在處理。戊\n    ○○時任國泰世華銀行敦化分行之員工，並擔任丙○○之理\n    財專員，而因丙○○不熟悉理財投資，故長期信賴戊○○，\n    由其負責協助丙○○辦理銀行相關業務事宜，雙方已建立特\n    殊之信任關係。嗣於民國93至95年間，戊○○利用職務之便\n    ，偽稱國泰世華銀行有年利率8 ％之優惠存款方案，建議丙\n    ○○將基金與債券贖回後並存入銀行。而丙○○年逾七旬，\n    學歷為高工畢業，自公路局土木建築設計監工退休，從未開\n    立支票，不瞭解銀行流程，且因小洞性中風造成智能障礙，\n    因此雖有從事基金、債券等理財行為，但非專精，不清楚銀\n    行之優惠利率及相關辦理流程，遂信任戊○○之專業建議，\n    而交付存摺、印章及提款密碼予戊○○，經其協助贖回多筆\n    基金及債券，以辦理優惠存款。丙○○復相信戊○○所給付\n    九張印有國泰世華銀行字樣、年利率約8%、發票日為1 年後\n    之支票，係國泰世華銀行敦化分行為定期返還本息所開立，\n    遂委由戊○○將贖回之金錢存入銀行。\n  (二)惟丙○○於95年8 月24日、95年11月1 日提示其中3 張支票\n    ，卻均遭退票，始知該支票為戊○○個人所簽發，經追查結\n    果，方知戊○○將當初應存入國泰世華銀行之款項，共計新\n    臺幣（下同）2,030 萬元，在丙○○不知情下，均由戊○○\n    自國泰世華銀行敦化分行、南門分行、西門分行轉匯入戊○\n    ○、訴外人鄭芫懿、鄭曾豔鳳之帳戶，丙○○至此始知遭戊\n    ○○詐騙鉅額存款。另國泰世華銀行未依銀行法、財政部相\n    關函釋及銀行內規，嚴禁行員代客戶辦理存提款、保管存摺\n    ，及禁止行員與客戶有異常資金往來，顯然未盡善良管理人\n    之注意義務，並違反銀行法第45條之1 第1 項規定。則被上\n    訴人自得依民法第184 條第1 項、第2 項、第188 條第1 項\n    規定，請求戊○○與國泰世華銀行連帶負損害賠償責任。爰\n    求為判命上訴人及戊○○應連帶給付被上訴人2,030 萬元，\n    及國泰世華銀行自96年12月7 日起、戊○○自96年12月11日\n    起至清償日止，按年息5%計算之利息等語（原審為被上訴人\n    勝訴之判決，國泰世華銀行聲明不服提起上訴）。並答辯聲\n    明：上訴駁回。\n三、國泰世華銀行則以：\n  (一)丙○○既於國泰世華銀行敦化分行有儲蓄及購買基金、債券\n    之投資行為，顯見丙○○就投資行為具有基本之經驗及知識\n    。戊○○所聲稱之8 ％優惠利息投資項目，明顯欠缺定期存\n    單之投資憑證，且其固定獲利比率、定期退還本息亦與一般\n    正常投資行為不符，獲利率之約定亦屬過高，故認丙○○僅\n    係因圖高額利息而與戊○○私人間之消費借貸關係。又借款\n    他人取得票據，於借款實務所常見，並未違反經驗法則。反\n    而若係投資行為，何以丙○○並未提出投資建議書、廣告、\n    文宣等任何有關投資之證明。戊○○因投資虧損而向丙○○\n    借款，非不可能。丙○○取得戊○○所簽發之本息支票後，\n    即依二人協議交付款項予戊○○，亦與民間借貸模式相符。\n    且戊○○在國泰世華銀行敦化分行亦設有私人帳戶，其以該\n    私人帳戶所簽發支票，當然印有國泰世華銀行敦化分行字樣\n    ，則縱遭退票，國泰世華銀行亦無庸負責。\n  (二)又戊○○為理財專員，其職務為分析客戶之投資理財方向，\n    則縱係利用上班時間、場所與客戶間為任何私人約定，亦與\n    執行職務無關，欠缺職務本質之內在關聯性。且一般民眾向\n    國泰世華銀行申請開戶時，必同時簽訂綜合約定書，其中共\n    通約定條款第10點規範之主要目的，即在杜絕存戶與行員間\n    私下之金錢往來行為，防止發生不必要之金錢糾紛。是被上\n    訴人於戊○○任職敦化分行期間，與丙○○成立消費借貸關\n    係，顯已違反上揭條款，故被上訴人因此所受之損失，係因\n    自身違背銀行開戶規範之過失所致。又戊○○縱令係以詐欺\n    之方式為之，亦屬其個人之犯罪行為，與其執行職務顯然無\n    關，自無民法第188 條第1 項規定之適用。\n  (三)被上訴人丁○○、乙○○均為被上訴人丙○○之成年子女，\n    渠等之帳戶均係交由丙○○辦理理財投資，丙○○尚且懂得\n    運用其成年子女之帳戶進行投資，而其投資金額更高達數千\n    萬元，其認知能力顯較一般人為高，並無投資、判斷能力較\n    一般人低之情事。又丙○○有多次辦理定期存款之經驗，必\n    定知悉定期存單與支票之差異，亦必然知悉除了借款，沒有\n    任何投資工具係於投資之初即將投資款項連同投資收益一次\n    以支票給付。至於財政部台財融字第88737515號函釋意旨，\n    係為防杜不法集團利用不實資金或調頭寸方式充作驗資證明\n    之弊端，因而要求避免行員與客戶間之不實資金往來，並非\n    當然禁止客戶與行員間之真實資金往來。又戊○○並未受丙\n    ○○之委託而保管存摺，而係於每次與丙○○達成借貸協議\n    後，由戊○○交付支票後，丙○○始交付存摺予戊○○等語\n    ，資為抗辯。惟原判決命國泰世華銀行及戊○○應連帶給付\n    被上訴人2,030 萬元本息，國泰世華銀行為此提起上訴並聲\n    明：(一)原判決廢棄。(二)被上訴人在第一審之訴駁回。\n四、兩造不爭執之事實：\n  (一)原審共同被告戊○○係被上訴人丙○○於國泰世華銀行之理\n    財專員。\n  (二)被上訴人三人於國泰世華銀行之投資、理財事宜，均係丙○\n    ○借用子女乙○○、丁○○之名義投資，均由丙○○處理。\n    原審共同被告戊○○於93年至95年間多次建議丙○○贖回基\n    金與債券。\n  (三)被上訴人三人於國泰世華銀行共2,030萬元之款項，均由原\n    審共同被告戊○○於國泰世華銀行敦化分行、南門分行、西\n    門分行轉入戊○○、戊○○之妻即訴外人鄭芫懿及岳母鄭曾\n    豔鳳之帳戶如下：\n  1.93年10月19日戊○○自丙○○帳戶領取150萬元，戊○○開\n    立發票日為95年10月18日，面額61萬元，票號AE0000000 號\n    ，付款人為國泰世華銀行之支票予丙○○，有國泰世華銀行\n    存款取款憑條、存款存入憑條、支票等件影本附卷可稽（見\n    原法院卷第33、50頁）。\n  2.94年1月19日戊○○自丙○○帳戶領取150萬元後開立發票日\n    為96年1月19日，面額174萬9,600元，票號AE0000000號，付\n    款人為國泰世華銀行支票予丙○○，有國泰世華銀行存款取\n    款憑條、支票影本附卷可稽（見原法院卷第38、53頁）。\n  3.94年10月3日戊○○自丙○○帳戶領取400萬元，戊○○開立\n    發票日為95年10月3日，面額432萬元，票號AE0000000號，\n    付款人為國泰世華銀行之支票予丙○○，有國泰世華銀行存\n    款取款憑條、存款存入憑條、支票影本附卷可稽（見原法院\n    卷第34、49頁）。\n  4.94年12月19日戊○○自被上訴人丁○○帳戶領取430萬元，\n    戊○○開立發票日為95年12月19日，面額464萬4,000元，票\n    號AE0000000號，付款人為國泰世華銀行之支票予被上訴人\n    丙○○，有國泰世華銀行存款取款憑條、存款存入憑條、支\n    票影本附卷可稽（見原法院卷第36、51頁）。\n  5.94年12月19日戊○○自被上訴人乙○○帳戶領取430萬元，\n    戊○○開立發票日為95年12月19日，面額464萬4,000元，票\n    號AE0000000號，付款人為國泰世華銀行之支票予被上訴人\n    丙○○，有國泰世華銀行存款取款憑條、存款存入憑條、支\n    票影本附卷可稽（見原法院卷第37、52頁）。\n  6.95年2月14日戊○○自被上訴人丙○○戶頭領取130萬元，戊\n    ○○開立發票日為96年2月14日，面額151萬6,320元，票號\n    AE0000000號，付款人為國泰世華銀行之支票予丙○○，有\n    國泰世華銀行存款取款憑條、存款存入憑條、支票影本附卷\n    可稽（見原法院卷第39、56頁）。\n  7.95年5月12日戊○○自被上訴人丁○○帳戶領取140萬元，戊\n    ○○開立發票日為96年5月12日，面額151萬2,000元，票號\n    AE0000000號，付款人為國泰世華銀行之支票予被上訴人丙\n    ○○，有國泰世華銀行存款取款憑條、存款存入憑條、支票\n    影本附卷可稽（見原法院卷第40、57頁）。\n  8.95年5月12日戊○○自被上訴人乙○○帳戶領取140萬元，戊\n    ○○開立發票日為96年5月12日，面額151萬2,000元，票號\n    AE0000000號，付款人為國泰世華銀行之支票予被上訴人丙\n    ○○，有國泰世華銀行存款取款憑條、存款存入憑條、支票\n    影本附卷可稽（見原法院卷第41、58頁）。\n  9.95年6月8日戊○○自被上訴人丙○○帳戶領取60萬元，戊○\n    ○開立發票日為95年8月8日，面額61萬元，票號AE0000000\n    號，付款人為國泰世華銀行之支票予丙○○，有國泰世華銀\n    行存款取款憑條、匯出匯款用紙、支票影本附卷可稽（見原\n    法院卷第33、48頁）。\n  (四)根據元富期貨股份有限公司提供原審共同被告戊○○「期貨\n    交易買賣告報書」，戊○○92年7月至95年6月間各月份投資\n    損益數額統計如附表一。\n  (五)被上訴人丙○○於95年8月24日及95年11月1日提示其中三張\n    支票，均遭退票，有退票理由單影本可證（見原法院卷第42\n    至47-1頁）。\n五、兩造爭執要點為：戊○○是否詐騙被上訴人2,030 萬元？國\n    泰世華銀行是否應依民法第188 條第1 項規定，與戊○○連\n    帶負損害賠償責任？茲就兩造爭點及本院得心證理由分述如\n    下：\n  (一)原審共同被告戊○○是否利用理財專員職務之便，向被上訴\n    人丙○○偽稱國泰世華銀行有年利率8％優惠存款，藉此詐\n    騙被上訴人2,030萬元？\n  1.按故意或過失不法侵害他人之權利者，負損害賠償責任，故\n    意以背於善良風俗之方法，加損害於他人者亦同，民法第\n    184 條第1 項定有明文。\n  2.經查被上訴人三人均於國泰世華銀行敦化分行設有活期儲蓄\n    存款帳戶及外幣存款帳戶，有存摺影本可稽（見原審卷第\n    249 至262 頁）。且被上訴人三人除儲蓄外，亦因原審共同\n    被告戊○○之建議而進行基金、債券等金融商品之投資，亦\n    有商品申購或贖回申請書影本可證（見原審卷第23頁）。又\n    被上訴人三人於國泰世華銀行之基金、債券及儲蓄等投資、\n    理財事宜，均係丙○○借用子女乙○○、丁○○之名義投資\n    ，均由丙○○處理。另丙○○自93年2 月間起至95年4 月28\n    日止，陸續購買泰國基金、連動債券等多項投資商品，有「\n    有價證券結構型商品申請書」影本可按（見原審卷第23至32\n    頁），復為兩造所不爭執。則據此足證丙○○確實基於信賴\n    戊○○之理財專業建議，而陸續購買該等商品。\n  3.又一般民眾向國泰世華銀行申請開戶時，必同時簽訂綜合約\n    定書，而依該約定書「壹、共通約定條款」第10點第2 項約\n    定：「存戶領用之存摺不宜交付他人……」有該約定書影本\n    可證（見原審卷第87頁）。而該規範之目的，在於杜絕存戶\n    與行員間私下之金錢來行為，防止發生不必要之金錢糾紛，\n    為兩造所不爭執。因此依照上開規範意旨，若存戶將存摺交\n    付予理財專員，則依一般常情，應認為係存戶委任理財專員\n    從事與銀行間之交易行為，而非存戶與理財專員私下之交易\n    行為。從而戊○○利用擔任丙○○之理財專員機會，建議丙\n    ○○贖回基金，復使丙○○告知提款密碼，並使丙○○先後\n    將自己與乙○○、丁○○之存摺及印鑑交給戊○○領取\n    2,030 萬元等行為，則衡諸常情，客觀上應以丙○○與國泰\n    世華銀行間進行交易行為為常態情形，而以丙○○與戊○○\n    間為消費借貸為變態情形。\n  4.然國泰世華銀行並無固定年利率8%之優惠存款方案，為兩造\n    所不爭執，且戊○○亦於原審到庭證稱：「我一開始跟丙○\n    ○聊現在的定存利率比較低，是否願意寄放在我這裡，我拿\n    去投資，約定給丙○○一年8%的利率……我會開本金加利息\n    8%的個人支票給丙○○，我會跟他說這是我私底下的交易行\n    為。」有言詞辯論筆錄可稽（見原審卷第212 頁）。而丙○\n    ○年逾七旬，其學歷為高工畢業，為公路局土木建築設計監\n    工退休，從未開立支票，不瞭解銀行流程，且因小洞性中風\n    造成智能障礙等情，有退休金證書及畢業證書、長庚紀念醫\n    院精神科診斷證明書影本在卷可憑（本院卷第130 至132 頁\n    ）。則據此足證戊○○明知國泰世華銀行並無上開優惠存款\n    方案，卻利用丙○○之認知、判斷能力較一般人略差之情形\n    ，向丙○○聲稱投資可獲得一年8%的利率，施用詐術使丙○\n    ○陷於錯誤，而交付存摺及印鑑給戊○○領取2,030 萬元。\n    因此丙○○主張：戊○○向丙○○宣稱國泰世華銀行有固定\n    年利率8%之優惠存款，並建議丙○○贖回基金，將款項存入\n    該項優惠存款方案，致丙○○信以為真，而將自己與乙○○\n    、丁○○之存摺及印鑑交給戊○○領取2,030 萬元，受有\n    2,030 萬元之損害等語，即屬有據。\n  5.國泰世華銀行雖否認戊○○詐騙丙○○，辯稱丙○○與戊○\n    ○間之交付印章、存摺與領款行為，係消費借貸關係云云。\n    經查：\n  (1)戊○○僅係為丙○○提供理財服務之人，二人之間並無任何\n    親誼關係，故丙○○若確實以自己之資金出借予戊○○，則\n    依一般交易習慣，即應令戊○○簽立借據或提供擔保。但戊\n    ○○並未簽立借據亦未提供擔保，或約定清償期、利息，復\n    未於原審提出任何反證證明二人之間確實有消費借貸關係，\n    亦未就原審所為敗訴判決聲明不服，故國泰世華銀行主張戊\n    ○○並未詐欺丙○○，而係向丙○○借款之變態事實，自應\n    提出反證以資證明。\n  (2)然國泰世華銀行雖聲請訊問戊○○，惟戊○○經本院傳喚無\n    著，並未到庭，有送達證書可稽（見本院卷第154 、155 頁\n    ）。至於國泰世華銀行雖提出關於戊○○與丙○○間之談話\n    錄音，有譯文在卷可證（見本院卷第77至78頁）。但丙○○\n    否認其真正，國泰世華銀行復未能證明為真；且縱使該錄音\n    譯文所示內容為真，惟綜觀其全文，亦無任何關於借貸還款\n    之對話。此外戊○○雖以個人名義簽發支票予丙○○，但據\n    此尚不足以證明戊○○向丙○○借款。另戊○○於95年7 月\n    11日離職，其所簽發之支票於95年8 月24日第一次跳票，丙\n    ○○遂於96年8 月3 日委請律師寄發存證信函予戊○○要求\n    其賠償，戊○○則於96年9 月6 日匯款5,000 元予丙○○，\n    有退票理由單、存證信函、丙○○之國泰世華銀行帳戶交易\n    明細影本可證（見原審卷第43、59頁、本院卷第80頁）。則\n    據此僅足以證明戊○○給付丙○○5,000 元，但並不足以證\n    明係戊○○與丙○○間締有消費借貸關係。故國泰世華銀行\n    此部分所辯，應屬無據。\n  (二)國泰世華銀行是否應依民法第188 條第1 項規定，與戊○○\n    連帶負損害賠償責任？\n  1.按受僱人因執行職務，不法侵害他人之權利者，由僱用人與\n    行為人連帶負損害賠償責任，民法第188 條第1 項定有明文\n    。而該條規定之目的，在於防免僱用人利用受僱人擴大自己\n    活動範疇之同時，增加侵害他人權益的危險性，因此始課予\n    僱用人選任監督受僱人之注意義務。從而民法第188 條第1\n    項所謂受僱人因執行職務不法侵害他人之權利，不僅指受僱\n    人因執行其所受命令，或委託之職務自體，或執行該職務所\n    必要之行為，而不法侵害他人之權利者而言，即受僱人之行\n    為，在客觀上足認為與其執行職務有關，而不法侵害他人之\n    權利者，就令其為自己利益所為亦應包括在內（最高法院42\n    年度台上字第1224號判例意旨參照）。此外發生損害的事由\n    ，必須與職務之執行，有內在關連性；而內在關連性之存在\n    與否，則視執行職務之目的與性質而定，亦即一切與僱用人\n    所命執行之職務通常合理相關聯之事項，均屬於職務範圍（\n    參見王澤鑑教授著，「僱用人無過失侵權責任的建立」，民\n    法學說與判例研究第一冊，第17頁（1983年7 版）；陳聰富\n    教授著，侵權歸責原則與損害賠償，「受僱人執行職務的行\n    為－評最高法院86年台上字第1497號判決」，第135 頁以下\n    ，93年初版）。\n  2.經查戊○○受僱於國泰世華銀行擔任理財專員，其職務性質\n    為代客戶分析投資理財，其目的為吸引客戶至國泰世華銀行\n    公司從事金融交易行為，而戊○○因此大部分利用上班時間\n    、在上班分行內為丙○○理財之機會，取得丙○○之信任，\n    進而為自己之利益詐取丙○○之金錢，應認為其詐欺行為屬\n    於職務範圍內之行為，與職務之執行有內在關聯性。此種事\n    項，與國泰世華銀行所委辦事務，既具有內在之關聯，國泰\n    世華銀行可得預見，事先可加防範，並得計算其損失於整個\n    企業之內而設法分散。因此課予國泰世華銀行損害賠償責任\n    ，並無不當。從而丙○○主張國泰世華銀行應依民法第188\n    條第1 項規定，與戊○○連帶賠償2,030 萬元本息，即屬有\n    據。至於戊○○之歷次詐欺行為，縱使部分行為非於營業場\n    所即國泰世華銀行國泰世華銀行敦化分行內為之，仍不妨害\n    其與職務執行之內在關聯性。是國泰世華銀行此部分所辯，\n    並不足採。\n  (三)至於被上訴人乙○○、丁○○雖亦於國泰世華銀行開設帳戶\n    並從事投資，但實為丙○○借名投資，並均為丙○○所處理\n    ，為丙○○所自陳，並為國泰世華銀行所不爭執。則乙○○\n    、丁○○既未受戊○○詐欺，且亦未受有經濟上利益之損失\n    ，則渠等請求國泰世華銀行與戊○○連帶賠償2,030 萬元本\n    息，即屬無據。至於戊○○雖未聲明不服提起上訴，惟國泰\n    世華銀行提出非基於其個人關係之抗辯，且部分有利於戊○\n    ○，則依民事訴訟法第56條第1 款之規定，其上訴有理由部\n    分之效力自及於戊○○。\n六、綜上所述，被上訴人丙○○請求國泰世華銀行與戊○○連帶\n    給付2,030 萬元本息，為有理由，應予准許。被上訴人乙○\n    ○、丁○○部分之請求，尚非正當。原審失察遽就超過上開\n    應准許部分，為國泰世華銀行敗訴之判決，並為假執行之宣\n    告，自有未洽。上訴意旨就此部分求予廢棄改判，應予准許\n    。至於上開應准許部分，原審判命國泰世華銀行與戊○○連\n    帶給付，核無違誤。國泰世華銀行就此部分指摘原判決不當\n    ，求予廢棄，為無理由，應駁回其上訴。\n七、本件事證已臻明確，兩造其餘之攻擊、防禦方法，核與判決\n    結果不生影響，毋庸逐一論列，併此敘明。\n八、據上論結，本件上訴為一部有理由，一部無理由。依民事訴\n    訟法第450 條、第449 條第1 項、第78條，判決如主文。"
  },
  "characters": {
    "judges": [
      "鄭三源",
      "魏麗娟",
      "邱琦"
    ],
    "prosecutors": [

    ],
    "lawyers": [
      "謝協昌",
      "林永頌",
      "黃韋齊",
      "張譽尹",
      "洪任遠",
      "日委請",
      "有",
      "人或其他法定代理人具有"
    ],
    "clerks": [
      "廖豔莉"
    ],
    "plaintiffs": [

    ],
    "defendants": [

    ],
    "prosecutor_office": [

    ],
    "creditors": [

    ],
    "debtors": [

    ],
    "judicial_associate_officer": [

    ]
  },
  "adjudged_at": "2010-01-05",
  "created_at": "2016-01-05 15:05:08",
  "updated_at": "2016-01-05 15:05:08"
}