{
  "identify": "TPH-99-聲-1226-20100512-1",
  "court": {
    "name": "臺灣高等法院",
    "code": "TPH"
  },
  "division": {
    "name": "刑事",
    "code": "M"
  },
  "year": 99,
  "word": "聲",
  "number": "1226",
  "jcheck": "1",
  "reason": "聲請定其應執行刑",
  "content": "臺灣高等法院刑事裁定                  99年度聲字第1226號\n聲  請  人  臺灣高等法院檢察署檢察官\n受  刑  人  甲○○\n上列聲請人因受刑人數罪併罰有二裁判以上，聲請定其應執行之\n刑，本院裁定如下：\n    主  文\n甲○○因犯如附表所示各罪所處之刑，應執行有期徒刑陸年參月\n。\n    理  由\n一、聲請意旨略以：受刑人甲○○因殺人未遂等數罪，先後經判\n    決確定並判處如附表所示之刑，應依刑法第53條、第51條第\n    5 款規定，定其應執行之刑，爰依刑事訴訟法第477條第1項\n    聲請裁定等語。\n二、按裁判確定前犯數罪者，併合處罰之；數罪併罰有二裁判以\n    上者，應依刑法第51條之規定定其應執行之刑；宣告多數有\n    期徒刑者，於各刑中之最長期以上，各刑合併之刑期以下，\n    定其刑期，刑法第50條、第53 條、第51條第5款分別定有明\n    文。次按法律上屬於自由裁量之事項，有其外部性界限及內\n    部性界限，並非概無拘束。依據法律之具體規定，法院應在\n    其範圍選擇為適當之裁判者，為外部性界限；而法院為裁判\n    時，應考量法律之目的，及法律秩序之理念所在者，為內部\n    性界限。法院為裁判時，二者均不得有所踰越。在數罪併罰\n    ，有二裁判以上，定其應執行之刑時，固屬於法院自由裁量\n    之事項，然仍應受前揭外部性界限及內部性界限之拘束（參\n    照最高法院94年度台非字第233 號判決意旨）。\n三、查受刑人甲○○因殺人未遂等罪，經臺灣士林地方法院及本\n    院先後判處如附表編號1 至4 所示之刑，均經確定在案，且\n    受刑人所犯如附表編號1、2之罪所示之刑，經本院以98年度\n    上訴字第2928號刑事判決定其應執行之刑為有期徒刑6年1月\n    ，有上開判決在卷可考，則本件再次定其應執行之刑，自應\n    受此內部性界限之拘束。\n四、茲檢察官聲請就受刑人附表所示各罪定其應執行之刑，本院\n    審核認聲請為正當，應定其應執行刑。\n五、依刑事訴訟法第220條、第477條第1項，刑法第53條、第51\n    條第5款，裁定如主文。\n中    華    民    國    99    年    5    月     12    日\n                  刑事第十五庭審判長法  官  吳昭瑩\n                                    法  官  蘇隆惠\n                                    法  官  吳炳桂\n以上正本證明與原本無異。\n如不服本裁定，應於收受送達後五日內向本院提出抗告狀。\n                                    書記官  洪雅蔓\n中    華    民    國    99    年    5     月    13    日",
  "structure": {
    "main": "甲○○因犯如附表所示各罪所處之刑，應執行有期徒刑陸年參月\n。",
    "reason": "一、聲請意旨略以：受刑人甲○○因殺人未遂等數罪，先後經判\n    決確定並判處如附表所示之刑，應依刑法第53條、第51條第\n    5 款規定，定其應執行之刑，爰依刑事訴訟法第477條第1項\n    聲請裁定等語。\n二、按裁判確定前犯數罪者，併合處罰之；數罪併罰有二裁判以\n    上者，應依刑法第51條之規定定其應執行之刑；宣告多數有\n    期徒刑者，於各刑中之最長期以上，各刑合併之刑期以下，\n    定其刑期，刑法第50條、第53 條、第51條第5款分別定有明\n    文。次按法律上屬於自由裁量之事項，有其外部性界限及內\n    部性界限，並非概無拘束。依據法律之具體規定，法院應在\n    其範圍選擇為適當之裁判者，為外部性界限；而法院為裁判\n    時，應考量法律之目的，及法律秩序之理念所在者，為內部\n    性界限。法院為裁判時，二者均不得有所踰越。在數罪併罰\n    ，有二裁判以上，定其應執行之刑時，固屬於法院自由裁量\n    之事項，然仍應受前揭外部性界限及內部性界限之拘束（參\n    照最高法院94年度台非字第233 號判決意旨）。\n三、查受刑人甲○○因殺人未遂等罪，經臺灣士林地方法院及本\n    院先後判處如附表編號1 至4 所示之刑，均經確定在案，且\n    受刑人所犯如附表編號1、2之罪所示之刑，經本院以98年度\n    上訴字第2928號刑事判決定其應執行之刑為有期徒刑6年1月\n    ，有上開判決在卷可考，則本件再次定其應執行之刑，自應\n    受此內部性界限之拘束。\n四、茲檢察官聲請就受刑人附表所示各罪定其應執行之刑，本院\n    審核認聲請為正當，應定其應執行刑。\n五、依刑事訴訟法第220條、第477條第1項，刑法第53條、第51\n    條第5款，裁定如主文。"
  },
  "characters": {
    "judges": [
      "吳昭瑩",
      "蘇隆惠",
      "吳炳桂"
    ],
    "prosecutors": [

    ],
    "lawyers": [

    ],
    "clerks": [
      "洪雅蔓"
    ],
    "plaintiffs": [

    ],
    "defendants": [

    ],
    "prosecutor_office": [
      "臺灣高等法院檢察署檢察官"
    ],
    "creditors": [

    ],
    "debtors": [

    ],
    "judicial_associate_officer": [

    ]
  },
  "adjudged_at": "2010-05-12",
  "created_at": "2016-01-05 11:54:40",
  "updated_at": "2016-01-05 11:54:40"
}