{
  "identify": "TPH-97-重上更(一)-137-20100105-1",
  "court": {
    "name": "臺灣高等法院",
    "code": "TPH"
  },
  "division": {
    "name": "民事",
    "code": "V"
  },
  "year": 97,
  "word": "重上更(一)",
  "number": "137",
  "jcheck": "1",
  "reason": "給付工程款",
  "content": "臺灣高等法院民事判決             97年度重上更(一)字第137號\n上  訴  人  大棟營造股份有限公司\n法定代理人  甲○○\n訴訟代理人  唐月妙律師\n被 上訴 人  台灣電力股份有限公司\n法定代理人  乙○○\n訴訟代理人  簡維能律師\n            陳美華律師\n上列當事人間請求給付工程款事件，上訴人對於中華民國93年9\n月29日臺灣臺北地方法院92年度重訴字第1089號第一審判決提起\n上訴，經最高法院發回更審，本院於98年12月15日言詞辯論終結\n，玆判決如下：\n    主      文\n原判決關於駁回上訴人後開第2項之訴部分，及除確定部分外訴\n訟費用之裁判，均廢棄。\n被上訴人應再給付上訴人新台幣壹佰參拾陸萬伍仟玖佰玖拾玖元\n及自民國92年1月28日起至清償之日止，按周年利率5%計算之利\n息。\n其餘上訴駁回。\n第一、二審及發回前第三審訴訟費用除確定部分外，由被上訴人\n負擔二十分之一，餘由上訴人負擔。\n    事實及理由\n一、本件上訴人主張：兩造於民國87年3月26日簽立工程承攬契\n    約（下稱系爭契約），約定由伊承攬被上訴人「核能四廠第\n    一、二號機發電計畫循環水進水口防波堤及重件碼頭工程」\n    （下稱系爭工程）。被上訴人於系爭工程進行中為配合行政\n    院宣布停止興建核能四廠之政策，而於89年10月27日片面通\n    知伊按現狀暫時停工，伊嗣雖屢次請被上訴人召開協調會，\n    惟無具體結果，致伊因停工所受之損失不斷擴大，且被上訴\n    人就系爭工程是否繼續進行之態度猶疑不決，政府政策亦不\n    明確，伊無法預期系爭工程是否得以復工，遂於90年1月31\n    日依系爭契約第23條之約定，通知被上訴人終止系爭契約，\n    然被上訴人尚有：(一)臨時碼頭之設備款324萬4329元。(二)北\n    堤便道石料費99萬2283元。(三)浚挖超拋費之損害1790萬0432\n    元，合計2360萬7470元，及(四)水電費、工地安全衛生費、環\n    境保護費、施工品質管制費、施工測量費（下稱水電費等5\n    項）147萬0426元，合計2360萬7470元未予給付等情，爰依\n    系爭契約第23條第4項及第1項之約定、民法第227條之2、第\n    148條、第231條、第227條，及政府採購法第6條等規定，求\n    為判決命被上訴人給付伊新台幣（下同）2360萬7470元，及\n    自92年1月28日起至清償之日止，按年利率百分之五計算之\n    利息之判決。（原審判決駁回其訴）並對於原判決提起上訴\n    （上訴人逾上開金額之請求，業經判決確定，不予贅列），\n    聲明：(一)原判決除確定部分外廢棄。(二)被上訴人應再給付上\n    訴人2360萬7470元，及自92年1月28日起至清償日止按年息\n    百分之五計算之利息。\n二、被上訴人則以：(一)上訴人雖有施作臨時碼頭，惟臨時碼頭並\n    非專用於系爭工程之設備，上訴人不得請求伊給付臨時碼頭\n    設備款，且上訴人設計維護不當，早於89年11月1日上訴人\n    終止系爭契約前即因象神颱風來襲而毀損，而上訴人於臨時\n    碼頭設備款中所列計算表中第3項石塊拋放費及第4項石塊材\n    料費，為系爭工程施工項目之費用，伊於系爭工程南堤部分\n    驗收時均已計價予上訴人，上訴人不得重複請求，其餘部分\n    上訴人則未就其施作數量確實舉證。(二)系爭契約原約定採用\n    之全斷面施工法改為半半施工法（即先作堤防之一邊以供通\n    行），遂於88年7月24日出具承諾書表示願自行吸收較原設\n    計所增加之工期及費用，不再向伊請求給付，並於同年9月1\n    0日施工協調會議中再次提出，兩造已合意就系爭工程中「\n    北堤便道石料」部分費用不在伊收購範圍內，上訴人自不得\n    再請求伊給付該部分費用。再者上訴人所支出此部分費用，\n    已經系爭工程北防波堤部分工程之經驗收、計價而回收其成\n    本，不得再重複請求，何況上訴人並未舉證證明施作數量，\n    所為請求自不可採。(三)依系爭契約施工說明書第5.5.2條1.\n    之約定，系爭工程超過設計線深度之浚挖及拋石費用，應\n    由上訴人自行負擔，則系爭工程關於浚挖部分之計價，應以\n    符合系爭工程設計圖說之斷面為計價基礎，而非以上訴人實\n    際挖除之數量為計價基礎，至如何施工可達系爭契約約定之\n    效果者，則屬上訴人得自行選擇施工方法以定之，故系爭工\n    程如有為避免浚挖面迴淤而預先擴大開挖面之情事發生，縱\n    其預先浚挖部分屬系爭工程範圍，依系爭契約之約定，仍不\n    予計價，伊已就上訴人實際完成驗收部分給付完畢，已超出\n    上訴人所主張之金額，上訴人不得再請求。縱認上訴人因迴\n    淤而於浚挖部分有超挖數量之必要，亦係其履行輔助人無法\n    有效執行工作，及其使用機具不當所致，系爭工程坡度設計\n    並無不當，自屬可歸責於上訴人之事由，不得請求伊賠償。\n    (四)水電費等5項係以「一式」為其計價方式，伊已就上訴人\n    已施作且經驗收之工作項目按其比例給付之，依系爭契約第\n    23 條第4項第2款及第1項之約定，上訴人於系爭契約終止後\n    僅得請求伊給付在場未用材料及設備，與專用於系爭工程之\n    設備款等工程報酬，其餘報酬均不得請求，再依系爭契約附\n    件之投標須知第23條約定，以一式計價之項目除設計變更外\n    ，概不增減計價，從而上訴人請求水電費等費用，既係以一\n    式計價之方式計算，其自不得另行請求增加給付。(五)上訴人\n    請求伊給付之各項費用性質上均屬損害賠償，而非系爭工程\n    之承攬報酬，則不論其請求權消滅時效期間自系爭契約90年\n    1 月31日終止之日或自系爭工程90年8月28日完成結算驗收\n    之日起算，或自系爭工程89年10月間停工發生時起算，上訴\n    人於92年1月27日始發函請求伊賠償損害，而於同年6月間提\n    起本件訴訟，均已逾民法第514條第2項規定之1年消滅時效\n    期間等語，資為抗辯。並對於上訴人之上訴，答辯聲明：上\n    訴駁回。\n三、兩造不爭執之事項：\n  (一)兩造於87年3月26日簽立工程承攬契約（即系爭契約），約\n    定由上訴人承攬被上訴人「核能四廠第一、二號機發電計畫\n    循環水進水口防波堤及重件碼頭工程」（即系爭工程），其\n    中第3條約定系爭工程概要為：「本工程位於石碇溪南側及\n    鹽寮公園東北側之海域，包括北堤（含沉箱）、南堤（含沉\n    箱）、碼頭、海堤、港池浚挖、引道及貨櫃場、管理站、…\n    。」。\n  (二)被上訴人龍門施工處於89年10月27日以龍施工務字第8910-1\n    111號函通知上訴人自即日起，將所承攬該處之工程（即系\n    爭工程）就現狀暫停施工，靜候該處作進一步指示辦理後續\n    作業。\n  (三)上訴人嗣分別於89年10月30日、11月6日分別發函予被上訴\n    人請求召開協調會，被上訴人龍門施工處遂於89年11月14日\n    以龍施水字第8911-1153號函表示系爭工程就現況停止施工\n    後，可按承攬契約（即系爭契約）第23條（契約終止‧解除\n    ）辦理。兩造並於同年12月11日召開協商有關核四暫停施工\n    期間相關事宜會議。上訴人嗣於90年1月31日以90大棟總字\n    第0001號函，以系爭工程經被上訴人通知暫停施工已屆滿3\n    個月為由，通知被上訴人依系爭契約第23條規定終止合約。\n  (四)上訴人分別於90年5月14日及6月8日發函予被上訴人並檢附\n    系爭工程進場未用材料明細及收購計價單，請求辦理計價作\n    業。\n  (五)兩造於90年8月17日及21日就系爭工程剩餘在場未用材料收\n    購部分進行驗收，其中水中土石浚挖部分結算數量為2萬931\n    立方公尺。\n  (六)上訴人於92年1月27日以92大棟核字第0002號函請求被上訴\n    人給付停工及終止合約衍生相關損失。\n四、玆就兩造爭執之事項，分別判斷如下：\n  (一)關於上訴人本件請求已否罹於消滅時效部分：就此，被上訴\n    人雖抗辯稱上訴人之各項請求性質上均屬損害賠償，而非系\n    爭工程之承攬報酬，其遲於92年1月27日始發函請求伊賠償\n    損害，已逾民法第514條第2項規定之1年消滅時效期間等語\n    ，提出工程驗收紀錄（見原審卷(一)，113頁）、終止契約後\n    在場未用材料收購明細表及核定金額（見原審卷(一)，114至\n    115頁）、系爭工程結算驗收證明書（見原審卷(一)，116頁）\n    為證。然本件上訴人請求被上訴人給付臨時碼頭費、北堤便\n    道石料收購費、水電費等5項，均依系爭契約第23條第4項第\n    2款約定，以被上訴人連續停工3個月以上為由終止系爭契約\n    後，上訴人就已完成及未完成工作部分請求之報酬，至於請\n    求被上訴人給付超挖及浚挖費，則為基於民法第231條給付\n    遲延之損害償，均非民法第514條第2項之損害賠償，無民法\n    第514條第2項消滅時效規定之適用，是被上訴人抗辯本件已\n    罹於民法第514條第2項之消滅時效期間，並非可採。\n  (二)關於「臨時碼頭」設備款部分：就此，上訴人主張：施作系\n    爭工程時設置臨時碼頭係為供各種工作船舶機械停靠之用，\n    為系爭工程所必須支出之專用設備，縱因上訴人所委託運送\n    之船舶公司航次遭取消，系爭臨時碼頭仍有存在之必要，系\n    爭契約既係因可歸責於被上訴人之事由而終止，而前已支出\n    臨時碼頭設備款因而無法回收，被上訴人自應賠償此部分費\n    用之損害共計324萬4329元等語。被上訴人則辯稱：所謂臨\n    時碼頭僅係利用南防波堤之堤頭上下貨，並無碼頭存在，非\n    專用於系爭工程之設備，上訴人依約不得請求被上訴人給付\n    臨時碼頭設備款，且臨時碼頭為階段性設備，因上訴人設計\n    維護不當，早於其終止系爭契約前毀損，至於上訴人於臨時\n    碼頭設備款中所列計算表中第3項石塊拋放費及第4項石塊材\n    料費，為系爭工程施工項目之費用，被上訴人於系爭工程南\n    堤部分驗收時均已計價予上訴人，上訴人不得重複請求，且\n    上訴人亦未就其施作數量確實舉證等語。分述如下：\n  1.依系爭契約第23條第4項第2款適用第1項規定：「乙方（即\n    上訴人）已做工程由甲方（即被上訴人）按實做合格數量依\n    契約單價計價，乙方專用於本工程之設備，由甲方核實計價\n    ，剩餘在場未用材料，甲方得按約定合理價格收購或補償，\n    並退還履約保證金及押金等，乙方不得提出額外要求。」則\n    上訴人請求被上訴人給付臨時碼頭設備款，自應符合前開約\n    定係專用於本工程之設備之條件。查上訴人所稱臨時碼頭係\n    指於南堤前端拋放石塊以為船隻停靠之臨時性設備（照片如\n    本院更字卷，65頁、66頁、112頁至114頁），係上訴人為便\n    於船隻載運石料進港並卸石料所建，有上訴人制作之備忘錄\n    （見原審卷(一)，122頁，被證七）可據。證人即被上訴人主\n    辦人員丙○○於本院審理時亦證稱：「（問：臨時碼頭設置\n    的位置？）設在南堤的堤頭，在這工程並沒有設在海側的臨\n    時碼頭。」「（問：臨時碼頭有無提供海堤拋石船停靠之用\n    ？）有的。」「（問：海堤拋石船的石頭是拋在哪裡？）不\n    是拋在海底，是船靠在碼頭，然後石料用貨車送到岸上後再\n    運到其他地方去拋石。」「（問：你於原審證稱；比較深的\n    海域有使用拋石船？）是的。」「（問：石頭是否拋在海裡\n    ？）是的。」「（問：前後所稱是否矛盾？）沒有，原審所\n    稱在臨時碼頭所停靠的是載石頭的大型船，石頭運上岸上後\n    分類檢驗合格後，再分由小型的拋石船運到海中拋石，拋石\n    船的船底可以直接打開將石頭拋入海中，與運載石頭的不一\n    樣。」等語（見本院更字卷，98頁、99頁），證人即上訴人\n    之督導呂學禮於原審證稱：「我們在南堤有重新作一個臨時\n    碼頭，做拋石、施工械具的運送、進料用的，並由此接駁，\n    運石料去拋石。」等語（見原審卷(三)，98頁），證人即被上\n    訴人之職員陳昭仁於原審證稱：「臨時碼頭是已經原告終止\n    契約前因象神颱風而毀損，且因為當時就已經沒有在使用，\n    但這是原告臨時進料的工作，我們就沒有去拍照存證，且因\n    為違反禁止直航之相關規定，主管機關也禁止原告利用該臨\n    時碼頭作下貨的動作。原告進石料除船運外，尚有自臺灣東\n    部花蓮用貨車載運過來，原告用貨車運送的機會較多，因為\n    原告才進沒幾船，就遭人檢舉，無法使用該碼頭。就先前原\n    告利用臨時碼頭運載之石料，其來源都是大陸地區。原告是\n    否有從國內以海運的方式運送石料，我並不清楚。原告於施\n    作海堤要作拋石之船舶是否有停靠在該臨時碼頭，我也不清\n    楚。因為象神颱風來襲前原告有收到被告公司停工命令，所\n    以損壞現場當時是我去看的，當時拋石堤的路已經毀損，無\n    法靠近，但距離沒有十分遠，仍然可以看到臨時碼頭的狀況\n    ，象神颱風之後該臨時碼頭是已經無法使用的狀況。」等語\n    （見原審卷(三)，29頁），由上訴人所制作之前開備忘錄及證\n    人丙○○、呂禮學及陳昭仁之證言，可知該臨時碼頭係供載\n    運石料之船隻停靠之用。又依證人丙○○證言，載運石料與\n    拋放石料之船隻並不相同，拋放石料之船隻可直接將船底打\n    開使石料直接拋入海中，故拋石船不可能為拋石而停靠於利\n    用堤頭前端臨時設置之碼頭（否則其石料僅能拋放於該船下\n    方即堤防旁邊），是被上訴人抗辯上訴人建臨時碼頭之目的\n    ，乃在供船隻停靠卸放石料，而非專用於船隻為拋石築堤而\n    停靠之用，應屬可信。又上訴人拋石用之石料，並非均由船\n    運，業據證人陳昭仁證述如上，故被上訴人抗辯該臨時碼頭\n    並非專為拋石而興建之設備，應屬可信。\n  2.又該臨時碼頭係利用南堤前端作為停靠載運石料船隻之用，\n    已如前述，而上訴人就南堤部分之施工，最後為89年6月3日\n    ，全部施工長度為290公尺，兩造已結算至290公尺，被上訴\n    人已給付此部分之工程款等情，已據證人丙○○於本院審理\n    時證述明確（見本院更字卷，98頁），並有被上訴人所提出\n    第23期（第二分項）工程估驗表、工程估驗明細表第1頁、\n    工程估驗數量計算表、統一發票（見本院更字卷，67頁至71\n    頁），及由上訴人之職員參與驗收之現場照片（見本院更字\n    卷，109頁）附卷可稽，是被上訴人抗辯有關南堤工程款已\n    全部給付，上訴人不得再重複請求，亦屬可採。\n  3.再者，該臨時碼頭於系爭契約終止前已因象神颱風來襲而毀\n    損，為兩造所不爭，是臨時碼頭亦非剩餘在場未用材料，無\n    由被上訴人依前開約定為收購或補償之問題。\n  4.綜上，該臨時碼頭既非供系爭工程所專用之設備，且臨時碼\n    頭所在之南堤工程款亦經被上訴人給付完畢，臨時碼頭於系\n    爭契約終止前，復已不存在，則上訴人依系爭契約，請求被\n    上訴人給付此部分之設備款，自非所許。\n  (三)關於「北堤便道石料」費用部分：就此，上訴人主張：其並\n    無拋棄請求此部分費用之意思，其前出具承諾書之真意係於\n    系爭工程如期完工之前提下，得如期獲得報酬，故同意因改\n    變施工方法而分攤施工成本，惟系爭工程並未如期完工，其\n    所支出之成本自應由被上訴人賠償之。其已依被上訴人之要\n    求於堤心石面上多填1公尺砂石作為施工便道以利施工，並\n    提報施工計畫，被上訴人自應賠償所已支付之石料費用110\n    萬2783元（共1901.35立方公尺，以每立方公尺580元計算，\n    $580/立方公尺×1901.35立方公尺＝$1,102,783），扣除發\n    回前經本院判命被上訴人給付之11萬500元後，被上訴人應\n    再賠償99萬2283元等語。被上訴人則辯稱：上訴人為讓被上\n    訴人同意將系爭契約原約定採用之全斷面施工法改為半半施\n    工法，遂於88年7月24日出具承諾書表示願自行吸收較原設\n    計所增加之工期及費用，不再向被上訴人請求給付費用，是\n    兩造已合意就系爭工程中「北堤便道石料」部分費用不在收\n    購範圍內。何況上訴人支出該部分費用，已經系爭工程北防\n    波堤部分工程之經驗收、計價而回收其成本，不得再為重複\n    請求，且上訴人就此部分施作數量亦未舉證以實其說，其主\n    張自不足採等語。查上訴人就其前開主張，固提出系爭工程\n    88年9月10日施工協調會會議紀錄（見原審卷(一)，201至204\n    頁）為證，並於原審聲請訊問證人項光祥（見原審卷(三)，52\n    至54頁），然依前開施工協調會紀錄，上訴人所以提議施作\n    此便道，乃為便利施工而來，上訴人並主動提及以砂石充填\n    ，於使用完畢後回收，因被上訴人恐砂土會被海浪沖入堤心\n    而污染海域，遂改以碎石充填，可見此一施工法乃為便利上\n    訴人而採，非應被上訴人之要求。證人即上訴人之工地主任\n    項光祥於原審亦證稱：於該地施工時，因為漲退潮關係，車\n    輛、施工械具及人員行走相當不便，故於協調會時提及多填\n    的砂土由上訴人自行吸收等語，並有證人項光祥出具之書面\n    ，內載：「．．其中南北防波堤壓頂混凝土，為施工順利，\n    請（被上訴人）同意採用半半施工法，並保證維持原設計品\n    質，如就此較原設計增加之工期及費用等，均由本公司（上\n    訴人）自行吸收，與甲方無關。」等語（見原審卷(三)，12頁\n    ），證人項光群同時證稱：其係本於工地主任身分簽立該書\n    面，且已經回報上訴人等語（見原審卷(三)，52頁、53頁），\n    參之證人即被上訴人職員陳建洲、丙○○於原審證稱上訴人\n    承諾此費用由上訴人自行吸收等語（見原審卷(三)，26至28頁\n    、30至32頁）相符，可知此費用之支出，純因上訴人為圖施\n    工方便而為，所以必須經被上訴人同意，則為被上訴人恐污\n    染海域故為此要求，並非被上訴人同意此費用由被上訴人支\n    付。又系爭契約既有終止契約後應如何善後之約定，則上訴\n    人自應考慮系爭契約終止之風險，是上訴人主張費用係預估\n    系爭契約順利執行時，可由其利潤中吸收，但因系爭契約終\n    止無法取得原有利潤，故無法吸收前開費用，亦難贊同。是\n    上訴人既承諾自行吸收前開費用，自不能請求被上訴人給付\n    。\n  (四)關於系爭工程浚挖超支數量之費用部分：就此，上訴人主張\n    ：系爭工程浚挖部分施工範圍包括堤防及港池，而為避免浚\n    挖面迴淤導致二次施工，均須預先擴大開挖面，從而因此所\n    浚挖之砂石均屬系爭工程之施工範圍，與系爭契約施工說明\n    書第5.5.2條規定之情形不同，倘系爭契約未提前終止，其\n    所預先施作之系爭工程浚挖部分終會獲得計價而回收成本，\n    系爭契約既已終止，其所預先施作之系爭工程浚挖部分因無\n    法測量計價致受有損害，被上訴人即應依系爭契約第23條第\n    4項及第1項之約定，與民法第231條、第227條之規定賠償其\n    此部分所超支費用之損害。其已施作之系爭工程浚挖部分數\n    量至少為8萬2153.46立方公尺，扣除已計價之2萬930.81立\n    方公尺，其餘部分並未計價，共計為1790萬432元等語。被\n    上訴人則否認上訴人主張其於系爭契約存續期間已挖除水中\n    土石之數量，並稱：系爭契約訂價單中就水中土石浚挖部分\n    所載數量僅係87年4月2日系爭工程開工前之概估數量，其上\n    亦有附註表示該項目係按實作數量計價，而系爭工程實因施\n    工範圍海域廣闊而採分區施工之方式進行水中浚挖及拋石工\n    作，兩造於各分區施工前均進行會測，從而系爭工程有關浚\n    挖及拋石數量之計算，自應以兩造共同會測後之原地面會測\n    設計圖面所示海中土石高度與設計線間所顯示之數量為其計\n    算基礎。又依系爭契約施工說明書第5.5.2條1.之約定，系\n    爭工程超過設計線深度之浚挖及拋石費用，應由上訴人自行\n    負擔，從而此部分之計價，應以符合系爭工程設計圖說之斷\n    面為計價基礎，而非以上訴人實際挖除之數量為計價基礎，\n    至如何施工可達系爭契約約定之效果者，則屬上訴人得自行\n    選擇施工方法以定之，故系爭工程如有為避免浚挖面迴淤而\n    預先擴大開挖面之情事發生，為上訴人自行選擇之結果，縱\n    屬系爭工程之範圍，依約仍不予計價。縱認上訴人因迴淤而\n    於浚挖部分有超挖數量之必要，亦係其履行輔助人無法有效\n    執行工作，及其使用機具不當所致，系爭工程坡度設計並無\n    不當，自屬可歸責於上訴人之事由，上訴人不得再請求賠償\n    等語。分述如下：\n  1.查上訴人主張其因迴淤而須二次施工或為避免浚挖面迴淤而\n    預先擴大開挖面所為施工，與系爭合約施工說明書第五章第\n    5.5.2「水中浚挖」4.規定：「在港池或堤身浚挖過程中，\n    如遇風浪或停工以致有迴淤情形時，均由乙方（上訴人）自\n    行負責，乙方應預估在有關項目之工程費內，甲方（被上訴\n    人）不另列項計價。」（見原審卷(一)，119頁），有所不同\n    ，固難據此即認應由上訴人就本項費用自行負責（發回意旨\n    參照）。然依該章第5.5.2「水中浚挖」1.規定：「水中土\n    石及岩盤浚挖均應達設計線，未達設計線時應繼續浚挖至設\n    計線，超過設計線深度之土石方不予計價，超挖部分甲方（\n    被上訴人）得視設計圖說決定拋石與否，如需拋石則其費用\n    亦由乙方（上訴人）負擔，且不得異議。」（見原審卷(一)，\n    119頁），依此兩造就上訴人應浚挖之寬度已明定以設計線\n    為基準，若有不足，應由上訴人繼續浚挖，若已超過，不但\n    不得請求被上訴人給付超過之費用，且被上訴人得以拋石填\n    充並由上訴人支付拋石之費用，如何恰到好處，乃上訴人施\n    工技術問題，非得請求被上訴人給付額外費用。從而不論上\n    訴人主張二次施工或擴大挖浚之數量是否屬實，均不得因迴\n    淤而須二次施工或為避免浚挖面迴淤而預先擴大開挖面所為\n    施工，請求被上訴人給付費用。\n  2.又系爭契約第23條第4項及第1項係約定：「如甲方（即被上\n    訴人）因特殊情形需中止工作時，得通知乙方（即上訴人）\n    應即停工並終止契約，乙方應即照辦。乙方已做工程由甲方\n    按實做合格數量依契約單價計價，乙方專用於本工程之設備\n    ，由甲方核實計價，剩餘在場未用材料，甲方得按約定合理\n    價格收購或補償，並退還履約保證金及押金等，乙方不得提\n    出額外要求。」上開為免迴淤所為之二次施工或擴大浚挖，\n    既非合約所定工程項目，亦非專用於系爭工程之設備或剩餘\n    在場未用材料，自無系爭契約第23條第4項及第1項之適用。\n    再者，依民法第507條規定，工作需定作人之行為始能完成\n    者，而定作人不為其行為時，承攬人得定相當期限，催告定\n    作人為之。定作人不於前項期限內為其行為者，承攬人得解\n    除契約，並得請求賠償因契約解除而生之損害。依此，定作\n    人縱未為協力驗收，亦僅承攬人得解除契約，並得請求賠償\n    因契約解除而生之損害而已，非謂定作人有給付遲延或不完\n    全給付之問題，是上訴人以被上訴人是否停工之政策猶疑不\n    決致其無法計價而受損害，依民法第231條、第227條請求被\n    上訴人賠償損害，亦非可採。\n  (五)關於水電費、工地安全衛生費、環境保護費、施工品質管制\n    費及施工測量費等部分：就此，上訴人主張：此5項費用依\n    系爭工程訂價單所載均係以「一式」計價，並無單價，而訂\n    價單中所載依實作數量計價者，係指他項工作而言，非指此\n    5項工作之費用，而此5項工作於計價時係以系爭工程款給付\n    之金額按比例付款，從而被上訴人應給付此5項費用共計147\n    萬426元等語。被上訴人則辯稱：此5項費用係以「一式」為\n    其計價方式，其已就上訴人已施作且經驗收之工作項目按其\n    比例給付之，再依系爭契約附件之投標須知第23條約定，以\n    一式計價之項目除設計變更外，概不增減計價，從而上訴人\n    不得另行請求增加給付。縱認上訴人得請求給付上開費用，\n    其中水電費中之接水設施費（含申請費用、人工及材料等）\n    及接電及發電設施費部分被上訴人均已給付，另照明器材中\n    之耗損及水電工中之維護部分費用，因上訴人業已終止系爭\n    契約，亦無耗損及維護之問題，均應將該部分費用扣除。再\n    者，上訴人仍重新承攬系爭工程續建部分，該水電費工程部\n    分仍係由上訴人使用，且於續建工程中亦計價予上訴人，上\n    訴人再次就該部分費用為計價，即受有不當得利，被上訴人\n    亦以上訴人不當得利之數額主張預備抵銷抗辯（見本院卷，\n    74 及164頁）等語。分述如下：\n  1.關於水電費、工地安全衛生費、環境保護費、施工品質管制\n    費、施工測量費部分，依據系爭契約訂價單所載均是以一「\n    式」計，並無單價（見原審卷(一)，第232頁）；該訂價單備\n    註欄所載採用實作數量計算者係指該表其他第84項至第104\n    項及第111、112項目，並非指此5項工作，是被上訴人抗辯\n    此5項工作為實作實算，尚非可採。\n  2.又上訴人請求之水電費，係包含接水設施費（含申請費用、\n    人工及材料等）、接電及發電設施費、照明器材及零星工料\n    ，性質上為各項工程施工之前置工程，是上訴人主張系爭工\n    程既已實際開工，前開費用自已支出，應可採信。又上訴人\n    主張扣除被上訴人已依合約給付單價169萬2270元之23.37%\n    ，尚有76.63%即129萬6787元未付（見原審卷(一)，180頁，卷\n    (二)，20頁），被上訴人亦稱其已依驗收項目之比例給付（見\n    本院上字卷(四)，100頁，更字卷，17頁）可見上訴人主張被\n    上訴人未全部給付，亦屬可信。該水電事項既為開工前必須\n    完工之工程，則於被上訴人終止系爭契約當時，上訴人當已\n    全部完工，被上訴人僅依合約驗收比例付款，顯有不足，是\n    上訴人請求被上訴人應再給付其餘之129萬6787元，應屬可\n    採。至於系爭工程之續建工程是否仍由上訴人承攬，該水電\n    設施是否仍由上訴人使用，乃續建工程應如何計算問題，與\n    上訴人得於本件請求該費用，要屬二事。被上訴人雖以上訴\n    人重新於續建工程繼續使用該水電設備，受有不當得利，然\n    未具體主張其據以抵銷之金額為何，其抵銷之抗辯，與民事\n    訴訟法第400條第2項規定不符，抵銷抗辯為不合法。\n  3.至於工地安全衛生費（3萬7446元）、環境保護費（1萬0407\n    元）、施工品質管制費（78056元）、施工測量費（4萬7730\n    元）部分，為依工程報酬比例計價，已如前述。而被上訴人\n    就上訴人主張此部分所佔工程款之比例為1.00000000%，亦\n    無爭執，本院應以之為裁判基礎。又被上訴人應給付上訴人\n    388萬0958元之工程報酬（中高桅桿投光燈基礎螺栓22萬500\n    0元、北堤便道石料11萬500元、施工便道350萬8308元、管\n    路架3萬7150元）業經判決確定，則上訴人依前開比率，自\n    得請求被上訴人給付此4項之費用6萬9212元（388萬0958元\n    *1.00000000%＝6萬9212元，元以下四捨五入）。\n  (六)總計上訴人得另請求被上訴人給付之金額為136萬5999元（\n    129萬6787元+6萬9212元＝136萬5999元）\n五、綜上所述，上訴人請求被上訴人除已判決確定部分外，應另\n    給付136萬5999元及自92年1月28日（催告函送達翌日）起至\n    清償之日止，按周年利率5%計算之利息，為有理由，應予准\n    許。逾此金額之請求，為無理由，不應准許。上開應予准許\n    部分，原判決駁回上訴人之訴，尚有未洽，上訴意旨指摘原\n    判決此部分不當，求予廢棄改判，為有理由，應由本院將原\n    判決此部分廢棄，改判如主文第2項所示。前開不應准許部\n    分，原判決駁回上訴人之訴及其假執行之聲請，並無不合。\n    上訴意旨指摘原判決此部分不當，聲明廢棄改判，為無理由\n    ，應予駁回上訴。\n六、據上論結，本件上訴一部為有理由，一部為無理由。依民事\n    訴訟法第450條、第449條第1項、第79條，判決如主文。\n中    華    民    國    99    年     1     月    5    日\n                    民事第七庭\n                        審判長法  官    鄭三源\n                              法  官    魏麗娟\n                              法  官    呂太郎\n正本係照原本作成。\n上訴人如不服本判決，應於收受送達後20日內向本院提出上訴書\n狀，其未表明上訴理由者，應於提出上訴後20日內向本院補提理\n由書狀（均須按他造當事人之人數附繕本）上訴時應提出委任律\n師或具有律師資格之人之委任狀；委任有律師資格者，另應附具\n律師資格證書及釋明委任人與受任人有民事訴訟法第466條之1第\n1項但書或第2項（詳附註）所定關係之釋明文書影本。\n中    華    民    國    99    年    1     月    7     日\n                              書記官   黃千鶴\n附註：\n民事訴訟法第466條之1（第1項、第2項）：\n對於第二審判決上訴，上訴人應委任律師為訴訟代理人。但上訴\n人或其他法定代理人具有律師資格者，不在此限。\n上訴人之配偶、三親等內之血親、二親等內之姻親，或上訴人為\n法人、中央或地方機關時，其所屬專任人員具有律師資格並經法\n院認為適當者，亦得為第三審訴訟代理人。",
  "structure": {
    "main": "原判決關於駁回上訴人後開第2項之訴部分，及除確定部分外訴\n訟費用之裁判，均廢棄。\n被上訴人應再給付上訴人新台幣壹佰參拾陸萬伍仟玖佰玖拾玖元\n及自民國92年1月28日起至清償之日止，按周年利率5%計算之利\n息。\n其餘上訴駁回。\n第一、二審及發回前第三審訴訟費用除確定部分外，由被上訴人\n負擔二十分之一，餘由上訴人負擔。",
    "fact": "一、本件上訴人主張：兩造於民國87年3月26日簽立工程承攬契\n    約（下稱系爭契約），約定由伊承攬被上訴人「核能四廠第\n    一、二號機發電計畫循環水進水口防波堤及重件碼頭工程」\n    （下稱系爭工程）。被上訴人於系爭工程進行中為配合行政\n    院宣布停止興建核能四廠之政策，而於89年10月27日片面通\n    知伊按現狀暫時停工，伊嗣雖屢次請被上訴人召開協調會，\n    惟無具體結果，致伊因停工所受之損失不斷擴大，且被上訴\n    人就系爭工程是否繼續進行之態度猶疑不決，政府政策亦不\n    明確，伊無法預期系爭工程是否得以復工，遂於90年1月31\n    日依系爭契約第23條之約定，通知被上訴人終止系爭契約，\n    然被上訴人尚有：(一)臨時碼頭之設備款324萬4329元。(二)北\n    堤便道石料費99萬2283元。(三)浚挖超拋費之損害1790萬0432\n    元，合計2360萬7470元，及(四)水電費、工地安全衛生費、環\n    境保護費、施工品質管制費、施工測量費（下稱水電費等5\n    項）147萬0426元，合計2360萬7470元未予給付等情，爰依\n    系爭契約第23條第4項及第1項之約定、民法第227條之2、第\n    148條、第231條、第227條，及政府採購法第6條等規定，求\n    為判決命被上訴人給付伊新台幣（下同）2360萬7470元，及\n    自92年1月28日起至清償之日止，按年利率百分之五計算之\n    利息之判決。（原審判決駁回其訴）並對於原判決提起上訴\n    （上訴人逾上開金額之請求，業經判決確定，不予贅列），\n    聲明：(一)原判決除確定部分外廢棄。(二)被上訴人應再給付上\n    訴人2360萬7470元，及自92年1月28日起至清償日止按年息\n    百分之五計算之利息。\n二、被上訴人則以：(一)上訴人雖有施作臨時碼頭，惟臨時碼頭並\n    非專用於系爭工程之設備，上訴人不得請求伊給付臨時碼頭\n    設備款，且上訴人設計維護不當，早於89年11月1日上訴人\n    終止系爭契約前即因象神颱風來襲而毀損，而上訴人於臨時\n    碼頭設備款中所列計算表中第3項石塊拋放費及第4項石塊材\n    料費，為系爭工程施工項目之費用，伊於系爭工程南堤部分\n    驗收時均已計價予上訴人，上訴人不得重複請求，其餘部分\n    上訴人則未就其施作數量確實舉證。(二)系爭契約原約定採用\n    之全斷面施工法改為半半施工法（即先作堤防之一邊以供通\n    行），遂於88年7月24日出具承諾書表示願自行吸收較原設\n    計所增加之工期及費用，不再向伊請求給付，並於同年9月1\n    0日施工協調會議中再次提出，兩造已合意就系爭工程中「\n    北堤便道石料」部分費用不在伊收購範圍內，上訴人自不得\n    再請求伊給付該部分費用。再者上訴人所支出此部分費用，\n    已經系爭工程北防波堤部分工程之經驗收、計價而回收其成\n    本，不得再重複請求，何況上訴人並未舉證證明施作數量，\n    所為請求自不可採。(三)依系爭契約施工說明書第5.5.2條1.\n    之約定，系爭工程超過設計線深度之浚挖及拋石費用，應\n    由上訴人自行負擔，則系爭工程關於浚挖部分之計價，應以\n    符合系爭工程設計圖說之斷面為計價基礎，而非以上訴人實\n    際挖除之數量為計價基礎，至如何施工可達系爭契約約定之\n    效果者，則屬上訴人得自行選擇施工方法以定之，故系爭工\n    程如有為避免浚挖面迴淤而預先擴大開挖面之情事發生，縱\n    其預先浚挖部分屬系爭工程範圍，依系爭契約之約定，仍不\n    予計價，伊已就上訴人實際完成驗收部分給付完畢，已超出\n    上訴人所主張之金額，上訴人不得再請求。縱認上訴人因迴\n    淤而於浚挖部分有超挖數量之必要，亦係其履行輔助人無法\n    有效執行工作，及其使用機具不當所致，系爭工程坡度設計\n    並無不當，自屬可歸責於上訴人之事由，不得請求伊賠償。\n    (四)水電費等5項係以「一式」為其計價方式，伊已就上訴人\n    已施作且經驗收之工作項目按其比例給付之，依系爭契約第\n    23 條第4項第2款及第1項之約定，上訴人於系爭契約終止後\n    僅得請求伊給付在場未用材料及設備，與專用於系爭工程之\n    設備款等工程報酬，其餘報酬均不得請求，再依系爭契約附\n    件之投標須知第23條約定，以一式計價之項目除設計變更外\n    ，概不增減計價，從而上訴人請求水電費等費用，既係以一\n    式計價之方式計算，其自不得另行請求增加給付。(五)上訴人\n    請求伊給付之各項費用性質上均屬損害賠償，而非系爭工程\n    之承攬報酬，則不論其請求權消滅時效期間自系爭契約90年\n    1 月31日終止之日或自系爭工程90年8月28日完成結算驗收\n    之日起算，或自系爭工程89年10月間停工發生時起算，上訴\n    人於92年1月27日始發函請求伊賠償損害，而於同年6月間提\n    起本件訴訟，均已逾民法第514條第2項規定之1年消滅時效\n    期間等語，資為抗辯。並對於上訴人之上訴，答辯聲明：上\n    訴駁回。\n三、兩造不爭執之事項：\n  (一)兩造於87年3月26日簽立工程承攬契約（即系爭契約），約\n    定由上訴人承攬被上訴人「核能四廠第一、二號機發電計畫\n    循環水進水口防波堤及重件碼頭工程」（即系爭工程），其\n    中第3條約定系爭工程概要為：「本工程位於石碇溪南側及\n    鹽寮公園東北側之海域，包括北堤（含沉箱）、南堤（含沉\n    箱）、碼頭、海堤、港池浚挖、引道及貨櫃場、管理站、…\n    。」。\n  (二)被上訴人龍門施工處於89年10月27日以龍施工務字第8910-1\n    111號函通知上訴人自即日起，將所承攬該處之工程（即系\n    爭工程）就現狀暫停施工，靜候該處作進一步指示辦理後續\n    作業。\n  (三)上訴人嗣分別於89年10月30日、11月6日分別發函予被上訴\n    人請求召開協調會，被上訴人龍門施工處遂於89年11月14日\n    以龍施水字第8911-1153號函表示系爭工程就現況停止施工\n    後，可按承攬契約（即系爭契約）第23條（契約終止‧解除\n    ）辦理。兩造並於同年12月11日召開協商有關核四暫停施工\n    期間相關事宜會議。上訴人嗣於90年1月31日以90大棟總字\n    第0001號函，以系爭工程經被上訴人通知暫停施工已屆滿3\n    個月為由，通知被上訴人依系爭契約第23條規定終止合約。\n  (四)上訴人分別於90年5月14日及6月8日發函予被上訴人並檢附\n    系爭工程進場未用材料明細及收購計價單，請求辦理計價作\n    業。\n  (五)兩造於90年8月17日及21日就系爭工程剩餘在場未用材料收\n    購部分進行驗收，其中水中土石浚挖部分結算數量為2萬931\n    立方公尺。\n  (六)上訴人於92年1月27日以92大棟核字第0002號函請求被上訴\n    人給付停工及終止合約衍生相關損失。\n四、玆就兩造爭執之事項，分別判斷如下：\n  (一)關於上訴人本件請求已否罹於消滅時效部分：就此，被上訴\n    人雖抗辯稱上訴人之各項請求性質上均屬損害賠償，而非系\n    爭工程之承攬報酬，其遲於92年1月27日始發函請求伊賠償\n    損害，已逾民法第514條第2項規定之1年消滅時效期間等語\n    ，提出工程驗收紀錄（見原審卷(一)，113頁）、終止契約後\n    在場未用材料收購明細表及核定金額（見原審卷(一)，114至\n    115頁）、系爭工程結算驗收證明書（見原審卷(一)，116頁）\n    為證。然本件上訴人請求被上訴人給付臨時碼頭費、北堤便\n    道石料收購費、水電費等5項，均依系爭契約第23條第4項第\n    2款約定，以被上訴人連續停工3個月以上為由終止系爭契約\n    後，上訴人就已完成及未完成工作部分請求之報酬，至於請\n    求被上訴人給付超挖及浚挖費，則為基於民法第231條給付\n    遲延之損害償，均非民法第514條第2項之損害賠償，無民法\n    第514條第2項消滅時效規定之適用，是被上訴人抗辯本件已\n    罹於民法第514條第2項之消滅時效期間，並非可採。\n  (二)關於「臨時碼頭」設備款部分：就此，上訴人主張：施作系\n    爭工程時設置臨時碼頭係為供各種工作船舶機械停靠之用，\n    為系爭工程所必須支出之專用設備，縱因上訴人所委託運送\n    之船舶公司航次遭取消，系爭臨時碼頭仍有存在之必要，系\n    爭契約既係因可歸責於被上訴人之事由而終止，而前已支出\n    臨時碼頭設備款因而無法回收，被上訴人自應賠償此部分費\n    用之損害共計324萬4329元等語。被上訴人則辯稱：所謂臨\n    時碼頭僅係利用南防波堤之堤頭上下貨，並無碼頭存在，非\n    專用於系爭工程之設備，上訴人依約不得請求被上訴人給付\n    臨時碼頭設備款，且臨時碼頭為階段性設備，因上訴人設計\n    維護不當，早於其終止系爭契約前毀損，至於上訴人於臨時\n    碼頭設備款中所列計算表中第3項石塊拋放費及第4項石塊材\n    料費，為系爭工程施工項目之費用，被上訴人於系爭工程南\n    堤部分驗收時均已計價予上訴人，上訴人不得重複請求，且\n    上訴人亦未就其施作數量確實舉證等語。分述如下：\n  1.依系爭契約第23條第4項第2款適用第1項規定：「乙方（即\n    上訴人）已做工程由甲方（即被上訴人）按實做合格數量依\n    契約單價計價，乙方專用於本工程之設備，由甲方核實計價\n    ，剩餘在場未用材料，甲方得按約定合理價格收購或補償，\n    並退還履約保證金及押金等，乙方不得提出額外要求。」則\n    上訴人請求被上訴人給付臨時碼頭設備款，自應符合前開約\n    定係專用於本工程之設備之條件。查上訴人所稱臨時碼頭係\n    指於南堤前端拋放石塊以為船隻停靠之臨時性設備（照片如\n    本院更字卷，65頁、66頁、112頁至114頁），係上訴人為便\n    於船隻載運石料進港並卸石料所建，有上訴人制作之備忘錄\n    （見原審卷(一)，122頁，被證七）可據。證人即被上訴人主\n    辦人員丙○○於本院審理時亦證稱：「（問：臨時碼頭設置\n    的位置？）設在南堤的堤頭，在這工程並沒有設在海側的臨\n    時碼頭。」「（問：臨時碼頭有無提供海堤拋石船停靠之用\n    ？）有的。」「（問：海堤拋石船的石頭是拋在哪裡？）不\n    是拋在海底，是船靠在碼頭，然後石料用貨車送到岸上後再\n    運到其他地方去拋石。」「（問：你於原審證稱；比較深的\n    海域有使用拋石船？）是的。」「（問：石頭是否拋在海裡\n    ？）是的。」「（問：前後所稱是否矛盾？）沒有，原審所\n    稱在臨時碼頭所停靠的是載石頭的大型船，石頭運上岸上後\n    分類檢驗合格後，再分由小型的拋石船運到海中拋石，拋石\n    船的船底可以直接打開將石頭拋入海中，與運載石頭的不一\n    樣。」等語（見本院更字卷，98頁、99頁），證人即上訴人\n    之督導呂學禮於原審證稱：「我們在南堤有重新作一個臨時\n    碼頭，做拋石、施工械具的運送、進料用的，並由此接駁，\n    運石料去拋石。」等語（見原審卷(三)，98頁），證人即被上\n    訴人之職員陳昭仁於原審證稱：「臨時碼頭是已經原告終止\n    契約前因象神颱風而毀損，且因為當時就已經沒有在使用，\n    但這是原告臨時進料的工作，我們就沒有去拍照存證，且因\n    為違反禁止直航之相關規定，主管機關也禁止原告利用該臨\n    時碼頭作下貨的動作。原告進石料除船運外，尚有自臺灣東\n    部花蓮用貨車載運過來，原告用貨車運送的機會較多，因為\n    原告才進沒幾船，就遭人檢舉，無法使用該碼頭。就先前原\n    告利用臨時碼頭運載之石料，其來源都是大陸地區。原告是\n    否有從國內以海運的方式運送石料，我並不清楚。原告於施\n    作海堤要作拋石之船舶是否有停靠在該臨時碼頭，我也不清\n    楚。因為象神颱風來襲前原告有收到被告公司停工命令，所\n    以損壞現場當時是我去看的，當時拋石堤的路已經毀損，無\n    法靠近，但距離沒有十分遠，仍然可以看到臨時碼頭的狀況\n    ，象神颱風之後該臨時碼頭是已經無法使用的狀況。」等語\n    （見原審卷(三)，29頁），由上訴人所制作之前開備忘錄及證\n    人丙○○、呂禮學及陳昭仁之證言，可知該臨時碼頭係供載\n    運石料之船隻停靠之用。又依證人丙○○證言，載運石料與\n    拋放石料之船隻並不相同，拋放石料之船隻可直接將船底打\n    開使石料直接拋入海中，故拋石船不可能為拋石而停靠於利\n    用堤頭前端臨時設置之碼頭（否則其石料僅能拋放於該船下\n    方即堤防旁邊），是被上訴人抗辯上訴人建臨時碼頭之目的\n    ，乃在供船隻停靠卸放石料，而非專用於船隻為拋石築堤而\n    停靠之用，應屬可信。又上訴人拋石用之石料，並非均由船\n    運，業據證人陳昭仁證述如上，故被上訴人抗辯該臨時碼頭\n    並非專為拋石而興建之設備，應屬可信。\n  2.又該臨時碼頭係利用南堤前端作為停靠載運石料船隻之用，\n    已如前述，而上訴人就南堤部分之施工，最後為89年6月3日\n    ，全部施工長度為290公尺，兩造已結算至290公尺，被上訴\n    人已給付此部分之工程款等情，已據證人丙○○於本院審理\n    時證述明確（見本院更字卷，98頁），並有被上訴人所提出\n    第23期（第二分項）工程估驗表、工程估驗明細表第1頁、\n    工程估驗數量計算表、統一發票（見本院更字卷，67頁至71\n    頁），及由上訴人之職員參與驗收之現場照片（見本院更字\n    卷，109頁）附卷可稽，是被上訴人抗辯有關南堤工程款已\n    全部給付，上訴人不得再重複請求，亦屬可採。\n  3.再者，該臨時碼頭於系爭契約終止前已因象神颱風來襲而毀\n    損，為兩造所不爭，是臨時碼頭亦非剩餘在場未用材料，無\n    由被上訴人依前開約定為收購或補償之問題。\n  4.綜上，該臨時碼頭既非供系爭工程所專用之設備，且臨時碼\n    頭所在之南堤工程款亦經被上訴人給付完畢，臨時碼頭於系\n    爭契約終止前，復已不存在，則上訴人依系爭契約，請求被\n    上訴人給付此部分之設備款，自非所許。\n  (三)關於「北堤便道石料」費用部分：就此，上訴人主張：其並\n    無拋棄請求此部分費用之意思，其前出具承諾書之真意係於\n    系爭工程如期完工之前提下，得如期獲得報酬，故同意因改\n    變施工方法而分攤施工成本，惟系爭工程並未如期完工，其\n    所支出之成本自應由被上訴人賠償之。其已依被上訴人之要\n    求於堤心石面上多填1公尺砂石作為施工便道以利施工，並\n    提報施工計畫，被上訴人自應賠償所已支付之石料費用110\n    萬2783元（共1901.35立方公尺，以每立方公尺580元計算，\n    $580/立方公尺×1901.35立方公尺＝$1,102,783），扣除發\n    回前經本院判命被上訴人給付之11萬500元後，被上訴人應\n    再賠償99萬2283元等語。被上訴人則辯稱：上訴人為讓被上\n    訴人同意將系爭契約原約定採用之全斷面施工法改為半半施\n    工法，遂於88年7月24日出具承諾書表示願自行吸收較原設\n    計所增加之工期及費用，不再向被上訴人請求給付費用，是\n    兩造已合意就系爭工程中「北堤便道石料」部分費用不在收\n    購範圍內。何況上訴人支出該部分費用，已經系爭工程北防\n    波堤部分工程之經驗收、計價而回收其成本，不得再為重複\n    請求，且上訴人就此部分施作數量亦未舉證以實其說，其主\n    張自不足採等語。查上訴人就其前開主張，固提出系爭工程\n    88年9月10日施工協調會會議紀錄（見原審卷(一)，201至204\n    頁）為證，並於原審聲請訊問證人項光祥（見原審卷(三)，52\n    至54頁），然依前開施工協調會紀錄，上訴人所以提議施作\n    此便道，乃為便利施工而來，上訴人並主動提及以砂石充填\n    ，於使用完畢後回收，因被上訴人恐砂土會被海浪沖入堤心\n    而污染海域，遂改以碎石充填，可見此一施工法乃為便利上\n    訴人而採，非應被上訴人之要求。證人即上訴人之工地主任\n    項光祥於原審亦證稱：於該地施工時，因為漲退潮關係，車\n    輛、施工械具及人員行走相當不便，故於協調會時提及多填\n    的砂土由上訴人自行吸收等語，並有證人項光祥出具之書面\n    ，內載：「．．其中南北防波堤壓頂混凝土，為施工順利，\n    請（被上訴人）同意採用半半施工法，並保證維持原設計品\n    質，如就此較原設計增加之工期及費用等，均由本公司（上\n    訴人）自行吸收，與甲方無關。」等語（見原審卷(三)，12頁\n    ），證人項光群同時證稱：其係本於工地主任身分簽立該書\n    面，且已經回報上訴人等語（見原審卷(三)，52頁、53頁），\n    參之證人即被上訴人職員陳建洲、丙○○於原審證稱上訴人\n    承諾此費用由上訴人自行吸收等語（見原審卷(三)，26至28頁\n    、30至32頁）相符，可知此費用之支出，純因上訴人為圖施\n    工方便而為，所以必須經被上訴人同意，則為被上訴人恐污\n    染海域故為此要求，並非被上訴人同意此費用由被上訴人支\n    付。又系爭契約既有終止契約後應如何善後之約定，則上訴\n    人自應考慮系爭契約終止之風險，是上訴人主張費用係預估\n    系爭契約順利執行時，可由其利潤中吸收，但因系爭契約終\n    止無法取得原有利潤，故無法吸收前開費用，亦難贊同。是\n    上訴人既承諾自行吸收前開費用，自不能請求被上訴人給付\n    。\n  (四)關於系爭工程浚挖超支數量之費用部分：就此，上訴人主張\n    ：系爭工程浚挖部分施工範圍包括堤防及港池，而為避免浚\n    挖面迴淤導致二次施工，均須預先擴大開挖面，從而因此所\n    浚挖之砂石均屬系爭工程之施工範圍，與系爭契約施工說明\n    書第5.5.2條規定之情形不同，倘系爭契約未提前終止，其\n    所預先施作之系爭工程浚挖部分終會獲得計價而回收成本，\n    系爭契約既已終止，其所預先施作之系爭工程浚挖部分因無\n    法測量計價致受有損害，被上訴人即應依系爭契約第23條第\n    4項及第1項之約定，與民法第231條、第227條之規定賠償其\n    此部分所超支費用之損害。其已施作之系爭工程浚挖部分數\n    量至少為8萬2153.46立方公尺，扣除已計價之2萬930.81立\n    方公尺，其餘部分並未計價，共計為1790萬432元等語。被\n    上訴人則否認上訴人主張其於系爭契約存續期間已挖除水中\n    土石之數量，並稱：系爭契約訂價單中就水中土石浚挖部分\n    所載數量僅係87年4月2日系爭工程開工前之概估數量，其上\n    亦有附註表示該項目係按實作數量計價，而系爭工程實因施\n    工範圍海域廣闊而採分區施工之方式進行水中浚挖及拋石工\n    作，兩造於各分區施工前均進行會測，從而系爭工程有關浚\n    挖及拋石數量之計算，自應以兩造共同會測後之原地面會測\n    設計圖面所示海中土石高度與設計線間所顯示之數量為其計\n    算基礎。又依系爭契約施工說明書第5.5.2條1.之約定，系\n    爭工程超過設計線深度之浚挖及拋石費用，應由上訴人自行\n    負擔，從而此部分之計價，應以符合系爭工程設計圖說之斷\n    面為計價基礎，而非以上訴人實際挖除之數量為計價基礎，\n    至如何施工可達系爭契約約定之效果者，則屬上訴人得自行\n    選擇施工方法以定之，故系爭工程如有為避免浚挖面迴淤而\n    預先擴大開挖面之情事發生，為上訴人自行選擇之結果，縱\n    屬系爭工程之範圍，依約仍不予計價。縱認上訴人因迴淤而\n    於浚挖部分有超挖數量之必要，亦係其履行輔助人無法有效\n    執行工作，及其使用機具不當所致，系爭工程坡度設計並無\n    不當，自屬可歸責於上訴人之事由，上訴人不得再請求賠償\n    等語。分述如下：\n  1.查上訴人主張其因迴淤而須二次施工或為避免浚挖面迴淤而\n    預先擴大開挖面所為施工，與系爭合約施工說明書第五章第\n    5.5.2「水中浚挖」4.規定：「在港池或堤身浚挖過程中，\n    如遇風浪或停工以致有迴淤情形時，均由乙方（上訴人）自\n    行負責，乙方應預估在有關項目之工程費內，甲方（被上訴\n    人）不另列項計價。」（見原審卷(一)，119頁），有所不同\n    ，固難據此即認應由上訴人就本項費用自行負責（發回意旨\n    參照）。然依該章第5.5.2「水中浚挖」1.規定：「水中土\n    石及岩盤浚挖均應達設計線，未達設計線時應繼續浚挖至設\n    計線，超過設計線深度之土石方不予計價，超挖部分甲方（\n    被上訴人）得視設計圖說決定拋石與否，如需拋石則其費用\n    亦由乙方（上訴人）負擔，且不得異議。」（見原審卷(一)，\n    119頁），依此兩造就上訴人應浚挖之寬度已明定以設計線\n    為基準，若有不足，應由上訴人繼續浚挖，若已超過，不但\n    不得請求被上訴人給付超過之費用，且被上訴人得以拋石填\n    充並由上訴人支付拋石之費用，如何恰到好處，乃上訴人施\n    工技術問題，非得請求被上訴人給付額外費用。從而不論上\n    訴人主張二次施工或擴大挖浚之數量是否屬實，均不得因迴\n    淤而須二次施工或為避免浚挖面迴淤而預先擴大開挖面所為\n    施工，請求被上訴人給付費用。\n  2.又系爭契約第23條第4項及第1項係約定：「如甲方（即被上\n    訴人）因特殊情形需中止工作時，得通知乙方（即上訴人）\n    應即停工並終止契約，乙方應即照辦。乙方已做工程由甲方\n    按實做合格數量依契約單價計價，乙方專用於本工程之設備\n    ，由甲方核實計價，剩餘在場未用材料，甲方得按約定合理\n    價格收購或補償，並退還履約保證金及押金等，乙方不得提\n    出額外要求。」上開為免迴淤所為之二次施工或擴大浚挖，\n    既非合約所定工程項目，亦非專用於系爭工程之設備或剩餘\n    在場未用材料，自無系爭契約第23條第4項及第1項之適用。\n    再者，依民法第507條規定，工作需定作人之行為始能完成\n    者，而定作人不為其行為時，承攬人得定相當期限，催告定\n    作人為之。定作人不於前項期限內為其行為者，承攬人得解\n    除契約，並得請求賠償因契約解除而生之損害。依此，定作\n    人縱未為協力驗收，亦僅承攬人得解除契約，並得請求賠償\n    因契約解除而生之損害而已，非謂定作人有給付遲延或不完\n    全給付之問題，是上訴人以被上訴人是否停工之政策猶疑不\n    決致其無法計價而受損害，依民法第231條、第227條請求被\n    上訴人賠償損害，亦非可採。\n  (五)關於水電費、工地安全衛生費、環境保護費、施工品質管制\n    費及施工測量費等部分：就此，上訴人主張：此5項費用依\n    系爭工程訂價單所載均係以「一式」計價，並無單價，而訂\n    價單中所載依實作數量計價者，係指他項工作而言，非指此\n    5項工作之費用，而此5項工作於計價時係以系爭工程款給付\n    之金額按比例付款，從而被上訴人應給付此5項費用共計147\n    萬426元等語。被上訴人則辯稱：此5項費用係以「一式」為\n    其計價方式，其已就上訴人已施作且經驗收之工作項目按其\n    比例給付之，再依系爭契約附件之投標須知第23條約定，以\n    一式計價之項目除設計變更外，概不增減計價，從而上訴人\n    不得另行請求增加給付。縱認上訴人得請求給付上開費用，\n    其中水電費中之接水設施費（含申請費用、人工及材料等）\n    及接電及發電設施費部分被上訴人均已給付，另照明器材中\n    之耗損及水電工中之維護部分費用，因上訴人業已終止系爭\n    契約，亦無耗損及維護之問題，均應將該部分費用扣除。再\n    者，上訴人仍重新承攬系爭工程續建部分，該水電費工程部\n    分仍係由上訴人使用，且於續建工程中亦計價予上訴人，上\n    訴人再次就該部分費用為計價，即受有不當得利，被上訴人\n    亦以上訴人不當得利之數額主張預備抵銷抗辯（見本院卷，\n    74 及164頁）等語。分述如下：\n  1.關於水電費、工地安全衛生費、環境保護費、施工品質管制\n    費、施工測量費部分，依據系爭契約訂價單所載均是以一「\n    式」計，並無單價（見原審卷(一)，第232頁）；該訂價單備\n    註欄所載採用實作數量計算者係指該表其他第84項至第104\n    項及第111、112項目，並非指此5項工作，是被上訴人抗辯\n    此5項工作為實作實算，尚非可採。\n  2.又上訴人請求之水電費，係包含接水設施費（含申請費用、\n    人工及材料等）、接電及發電設施費、照明器材及零星工料\n    ，性質上為各項工程施工之前置工程，是上訴人主張系爭工\n    程既已實際開工，前開費用自已支出，應可採信。又上訴人\n    主張扣除被上訴人已依合約給付單價169萬2270元之23.37%\n    ，尚有76.63%即129萬6787元未付（見原審卷(一)，180頁，卷\n    (二)，20頁），被上訴人亦稱其已依驗收項目之比例給付（見\n    本院上字卷(四)，100頁，更字卷，17頁）可見上訴人主張被\n    上訴人未全部給付，亦屬可信。該水電事項既為開工前必須\n    完工之工程，則於被上訴人終止系爭契約當時，上訴人當已\n    全部完工，被上訴人僅依合約驗收比例付款，顯有不足，是\n    上訴人請求被上訴人應再給付其餘之129萬6787元，應屬可\n    採。至於系爭工程之續建工程是否仍由上訴人承攬，該水電\n    設施是否仍由上訴人使用，乃續建工程應如何計算問題，與\n    上訴人得於本件請求該費用，要屬二事。被上訴人雖以上訴\n    人重新於續建工程繼續使用該水電設備，受有不當得利，然\n    未具體主張其據以抵銷之金額為何，其抵銷之抗辯，與民事\n    訴訟法第400條第2項規定不符，抵銷抗辯為不合法。\n  3.至於工地安全衛生費（3萬7446元）、環境保護費（1萬0407\n    元）、施工品質管制費（78056元）、施工測量費（4萬7730\n    元）部分，為依工程報酬比例計價，已如前述。而被上訴人\n    就上訴人主張此部分所佔工程款之比例為1.00000000%，亦\n    無爭執，本院應以之為裁判基礎。又被上訴人應給付上訴人\n    388萬0958元之工程報酬（中高桅桿投光燈基礎螺栓22萬500\n    0元、北堤便道石料11萬500元、施工便道350萬8308元、管\n    路架3萬7150元）業經判決確定，則上訴人依前開比率，自\n    得請求被上訴人給付此4項之費用6萬9212元（388萬0958元\n    *1.00000000%＝6萬9212元，元以下四捨五入）。\n  (六)總計上訴人得另請求被上訴人給付之金額為136萬5999元（\n    129萬6787元+6萬9212元＝136萬5999元）\n五、綜上所述，上訴人請求被上訴人除已判決確定部分外，應另\n    給付136萬5999元及自92年1月28日（催告函送達翌日）起至\n    清償之日止，按周年利率5%計算之利息，為有理由，應予准\n    許。逾此金額之請求，為無理由，不應准許。上開應予准許\n    部分，原判決駁回上訴人之訴，尚有未洽，上訴意旨指摘原\n    判決此部分不當，求予廢棄改判，為有理由，應由本院將原\n    判決此部分廢棄，改判如主文第2項所示。前開不應准許部\n    分，原判決駁回上訴人之訴及其假執行之聲請，並無不合。\n    上訴意旨指摘原判決此部分不當，聲明廢棄改判，為無理由\n    ，應予駁回上訴。\n六、據上論結，本件上訴一部為有理由，一部為無理由。依民事\n    訴訟法第450條、第449條第1項、第79條，判決如主文。",
    "reason": "一、本件上訴人主張：兩造於民國87年3月26日簽立工程承攬契\n    約（下稱系爭契約），約定由伊承攬被上訴人「核能四廠第\n    一、二號機發電計畫循環水進水口防波堤及重件碼頭工程」\n    （下稱系爭工程）。被上訴人於系爭工程進行中為配合行政\n    院宣布停止興建核能四廠之政策，而於89年10月27日片面通\n    知伊按現狀暫時停工，伊嗣雖屢次請被上訴人召開協調會，\n    惟無具體結果，致伊因停工所受之損失不斷擴大，且被上訴\n    人就系爭工程是否繼續進行之態度猶疑不決，政府政策亦不\n    明確，伊無法預期系爭工程是否得以復工，遂於90年1月31\n    日依系爭契約第23條之約定，通知被上訴人終止系爭契約，\n    然被上訴人尚有：(一)臨時碼頭之設備款324萬4329元。(二)北\n    堤便道石料費99萬2283元。(三)浚挖超拋費之損害1790萬0432\n    元，合計2360萬7470元，及(四)水電費、工地安全衛生費、環\n    境保護費、施工品質管制費、施工測量費（下稱水電費等5\n    項）147萬0426元，合計2360萬7470元未予給付等情，爰依\n    系爭契約第23條第4項及第1項之約定、民法第227條之2、第\n    148條、第231條、第227條，及政府採購法第6條等規定，求\n    為判決命被上訴人給付伊新台幣（下同）2360萬7470元，及\n    自92年1月28日起至清償之日止，按年利率百分之五計算之\n    利息之判決。（原審判決駁回其訴）並對於原判決提起上訴\n    （上訴人逾上開金額之請求，業經判決確定，不予贅列），\n    聲明：(一)原判決除確定部分外廢棄。(二)被上訴人應再給付上\n    訴人2360萬7470元，及自92年1月28日起至清償日止按年息\n    百分之五計算之利息。\n二、被上訴人則以：(一)上訴人雖有施作臨時碼頭，惟臨時碼頭並\n    非專用於系爭工程之設備，上訴人不得請求伊給付臨時碼頭\n    設備款，且上訴人設計維護不當，早於89年11月1日上訴人\n    終止系爭契約前即因象神颱風來襲而毀損，而上訴人於臨時\n    碼頭設備款中所列計算表中第3項石塊拋放費及第4項石塊材\n    料費，為系爭工程施工項目之費用，伊於系爭工程南堤部分\n    驗收時均已計價予上訴人，上訴人不得重複請求，其餘部分\n    上訴人則未就其施作數量確實舉證。(二)系爭契約原約定採用\n    之全斷面施工法改為半半施工法（即先作堤防之一邊以供通\n    行），遂於88年7月24日出具承諾書表示願自行吸收較原設\n    計所增加之工期及費用，不再向伊請求給付，並於同年9月1\n    0日施工協調會議中再次提出，兩造已合意就系爭工程中「\n    北堤便道石料」部分費用不在伊收購範圍內，上訴人自不得\n    再請求伊給付該部分費用。再者上訴人所支出此部分費用，\n    已經系爭工程北防波堤部分工程之經驗收、計價而回收其成\n    本，不得再重複請求，何況上訴人並未舉證證明施作數量，\n    所為請求自不可採。(三)依系爭契約施工說明書第5.5.2條1.\n    之約定，系爭工程超過設計線深度之浚挖及拋石費用，應\n    由上訴人自行負擔，則系爭工程關於浚挖部分之計價，應以\n    符合系爭工程設計圖說之斷面為計價基礎，而非以上訴人實\n    際挖除之數量為計價基礎，至如何施工可達系爭契約約定之\n    效果者，則屬上訴人得自行選擇施工方法以定之，故系爭工\n    程如有為避免浚挖面迴淤而預先擴大開挖面之情事發生，縱\n    其預先浚挖部分屬系爭工程範圍，依系爭契約之約定，仍不\n    予計價，伊已就上訴人實際完成驗收部分給付完畢，已超出\n    上訴人所主張之金額，上訴人不得再請求。縱認上訴人因迴\n    淤而於浚挖部分有超挖數量之必要，亦係其履行輔助人無法\n    有效執行工作，及其使用機具不當所致，系爭工程坡度設計\n    並無不當，自屬可歸責於上訴人之事由，不得請求伊賠償。\n    (四)水電費等5項係以「一式」為其計價方式，伊已就上訴人\n    已施作且經驗收之工作項目按其比例給付之，依系爭契約第\n    23 條第4項第2款及第1項之約定，上訴人於系爭契約終止後\n    僅得請求伊給付在場未用材料及設備，與專用於系爭工程之\n    設備款等工程報酬，其餘報酬均不得請求，再依系爭契約附\n    件之投標須知第23條約定，以一式計價之項目除設計變更外\n    ，概不增減計價，從而上訴人請求水電費等費用，既係以一\n    式計價之方式計算，其自不得另行請求增加給付。(五)上訴人\n    請求伊給付之各項費用性質上均屬損害賠償，而非系爭工程\n    之承攬報酬，則不論其請求權消滅時效期間自系爭契約90年\n    1 月31日終止之日或自系爭工程90年8月28日完成結算驗收\n    之日起算，或自系爭工程89年10月間停工發生時起算，上訴\n    人於92年1月27日始發函請求伊賠償損害，而於同年6月間提\n    起本件訴訟，均已逾民法第514條第2項規定之1年消滅時效\n    期間等語，資為抗辯。並對於上訴人之上訴，答辯聲明：上\n    訴駁回。\n三、兩造不爭執之事項：\n  (一)兩造於87年3月26日簽立工程承攬契約（即系爭契約），約\n    定由上訴人承攬被上訴人「核能四廠第一、二號機發電計畫\n    循環水進水口防波堤及重件碼頭工程」（即系爭工程），其\n    中第3條約定系爭工程概要為：「本工程位於石碇溪南側及\n    鹽寮公園東北側之海域，包括北堤（含沉箱）、南堤（含沉\n    箱）、碼頭、海堤、港池浚挖、引道及貨櫃場、管理站、…\n    。」。\n  (二)被上訴人龍門施工處於89年10月27日以龍施工務字第8910-1\n    111號函通知上訴人自即日起，將所承攬該處之工程（即系\n    爭工程）就現狀暫停施工，靜候該處作進一步指示辦理後續\n    作業。\n  (三)上訴人嗣分別於89年10月30日、11月6日分別發函予被上訴\n    人請求召開協調會，被上訴人龍門施工處遂於89年11月14日\n    以龍施水字第8911-1153號函表示系爭工程就現況停止施工\n    後，可按承攬契約（即系爭契約）第23條（契約終止‧解除\n    ）辦理。兩造並於同年12月11日召開協商有關核四暫停施工\n    期間相關事宜會議。上訴人嗣於90年1月31日以90大棟總字\n    第0001號函，以系爭工程經被上訴人通知暫停施工已屆滿3\n    個月為由，通知被上訴人依系爭契約第23條規定終止合約。\n  (四)上訴人分別於90年5月14日及6月8日發函予被上訴人並檢附\n    系爭工程進場未用材料明細及收購計價單，請求辦理計價作\n    業。\n  (五)兩造於90年8月17日及21日就系爭工程剩餘在場未用材料收\n    購部分進行驗收，其中水中土石浚挖部分結算數量為2萬931\n    立方公尺。\n  (六)上訴人於92年1月27日以92大棟核字第0002號函請求被上訴\n    人給付停工及終止合約衍生相關損失。\n四、玆就兩造爭執之事項，分別判斷如下：\n  (一)關於上訴人本件請求已否罹於消滅時效部分：就此，被上訴\n    人雖抗辯稱上訴人之各項請求性質上均屬損害賠償，而非系\n    爭工程之承攬報酬，其遲於92年1月27日始發函請求伊賠償\n    損害，已逾民法第514條第2項規定之1年消滅時效期間等語\n    ，提出工程驗收紀錄（見原審卷(一)，113頁）、終止契約後\n    在場未用材料收購明細表及核定金額（見原審卷(一)，114至\n    115頁）、系爭工程結算驗收證明書（見原審卷(一)，116頁）\n    為證。然本件上訴人請求被上訴人給付臨時碼頭費、北堤便\n    道石料收購費、水電費等5項，均依系爭契約第23條第4項第\n    2款約定，以被上訴人連續停工3個月以上為由終止系爭契約\n    後，上訴人就已完成及未完成工作部分請求之報酬，至於請\n    求被上訴人給付超挖及浚挖費，則為基於民法第231條給付\n    遲延之損害償，均非民法第514條第2項之損害賠償，無民法\n    第514條第2項消滅時效規定之適用，是被上訴人抗辯本件已\n    罹於民法第514條第2項之消滅時效期間，並非可採。\n  (二)關於「臨時碼頭」設備款部分：就此，上訴人主張：施作系\n    爭工程時設置臨時碼頭係為供各種工作船舶機械停靠之用，\n    為系爭工程所必須支出之專用設備，縱因上訴人所委託運送\n    之船舶公司航次遭取消，系爭臨時碼頭仍有存在之必要，系\n    爭契約既係因可歸責於被上訴人之事由而終止，而前已支出\n    臨時碼頭設備款因而無法回收，被上訴人自應賠償此部分費\n    用之損害共計324萬4329元等語。被上訴人則辯稱：所謂臨\n    時碼頭僅係利用南防波堤之堤頭上下貨，並無碼頭存在，非\n    專用於系爭工程之設備，上訴人依約不得請求被上訴人給付\n    臨時碼頭設備款，且臨時碼頭為階段性設備，因上訴人設計\n    維護不當，早於其終止系爭契約前毀損，至於上訴人於臨時\n    碼頭設備款中所列計算表中第3項石塊拋放費及第4項石塊材\n    料費，為系爭工程施工項目之費用，被上訴人於系爭工程南\n    堤部分驗收時均已計價予上訴人，上訴人不得重複請求，且\n    上訴人亦未就其施作數量確實舉證等語。分述如下：\n  1.依系爭契約第23條第4項第2款適用第1項規定：「乙方（即\n    上訴人）已做工程由甲方（即被上訴人）按實做合格數量依\n    契約單價計價，乙方專用於本工程之設備，由甲方核實計價\n    ，剩餘在場未用材料，甲方得按約定合理價格收購或補償，\n    並退還履約保證金及押金等，乙方不得提出額外要求。」則\n    上訴人請求被上訴人給付臨時碼頭設備款，自應符合前開約\n    定係專用於本工程之設備之條件。查上訴人所稱臨時碼頭係\n    指於南堤前端拋放石塊以為船隻停靠之臨時性設備（照片如\n    本院更字卷，65頁、66頁、112頁至114頁），係上訴人為便\n    於船隻載運石料進港並卸石料所建，有上訴人制作之備忘錄\n    （見原審卷(一)，122頁，被證七）可據。證人即被上訴人主\n    辦人員丙○○於本院審理時亦證稱：「（問：臨時碼頭設置\n    的位置？）設在南堤的堤頭，在這工程並沒有設在海側的臨\n    時碼頭。」「（問：臨時碼頭有無提供海堤拋石船停靠之用\n    ？）有的。」「（問：海堤拋石船的石頭是拋在哪裡？）不\n    是拋在海底，是船靠在碼頭，然後石料用貨車送到岸上後再\n    運到其他地方去拋石。」「（問：你於原審證稱；比較深的\n    海域有使用拋石船？）是的。」「（問：石頭是否拋在海裡\n    ？）是的。」「（問：前後所稱是否矛盾？）沒有，原審所\n    稱在臨時碼頭所停靠的是載石頭的大型船，石頭運上岸上後\n    分類檢驗合格後，再分由小型的拋石船運到海中拋石，拋石\n    船的船底可以直接打開將石頭拋入海中，與運載石頭的不一\n    樣。」等語（見本院更字卷，98頁、99頁），證人即上訴人\n    之督導呂學禮於原審證稱：「我們在南堤有重新作一個臨時\n    碼頭，做拋石、施工械具的運送、進料用的，並由此接駁，\n    運石料去拋石。」等語（見原審卷(三)，98頁），證人即被上\n    訴人之職員陳昭仁於原審證稱：「臨時碼頭是已經原告終止\n    契約前因象神颱風而毀損，且因為當時就已經沒有在使用，\n    但這是原告臨時進料的工作，我們就沒有去拍照存證，且因\n    為違反禁止直航之相關規定，主管機關也禁止原告利用該臨\n    時碼頭作下貨的動作。原告進石料除船運外，尚有自臺灣東\n    部花蓮用貨車載運過來，原告用貨車運送的機會較多，因為\n    原告才進沒幾船，就遭人檢舉，無法使用該碼頭。就先前原\n    告利用臨時碼頭運載之石料，其來源都是大陸地區。原告是\n    否有從國內以海運的方式運送石料，我並不清楚。原告於施\n    作海堤要作拋石之船舶是否有停靠在該臨時碼頭，我也不清\n    楚。因為象神颱風來襲前原告有收到被告公司停工命令，所\n    以損壞現場當時是我去看的，當時拋石堤的路已經毀損，無\n    法靠近，但距離沒有十分遠，仍然可以看到臨時碼頭的狀況\n    ，象神颱風之後該臨時碼頭是已經無法使用的狀況。」等語\n    （見原審卷(三)，29頁），由上訴人所制作之前開備忘錄及證\n    人丙○○、呂禮學及陳昭仁之證言，可知該臨時碼頭係供載\n    運石料之船隻停靠之用。又依證人丙○○證言，載運石料與\n    拋放石料之船隻並不相同，拋放石料之船隻可直接將船底打\n    開使石料直接拋入海中，故拋石船不可能為拋石而停靠於利\n    用堤頭前端臨時設置之碼頭（否則其石料僅能拋放於該船下\n    方即堤防旁邊），是被上訴人抗辯上訴人建臨時碼頭之目的\n    ，乃在供船隻停靠卸放石料，而非專用於船隻為拋石築堤而\n    停靠之用，應屬可信。又上訴人拋石用之石料，並非均由船\n    運，業據證人陳昭仁證述如上，故被上訴人抗辯該臨時碼頭\n    並非專為拋石而興建之設備，應屬可信。\n  2.又該臨時碼頭係利用南堤前端作為停靠載運石料船隻之用，\n    已如前述，而上訴人就南堤部分之施工，最後為89年6月3日\n    ，全部施工長度為290公尺，兩造已結算至290公尺，被上訴\n    人已給付此部分之工程款等情，已據證人丙○○於本院審理\n    時證述明確（見本院更字卷，98頁），並有被上訴人所提出\n    第23期（第二分項）工程估驗表、工程估驗明細表第1頁、\n    工程估驗數量計算表、統一發票（見本院更字卷，67頁至71\n    頁），及由上訴人之職員參與驗收之現場照片（見本院更字\n    卷，109頁）附卷可稽，是被上訴人抗辯有關南堤工程款已\n    全部給付，上訴人不得再重複請求，亦屬可採。\n  3.再者，該臨時碼頭於系爭契約終止前已因象神颱風來襲而毀\n    損，為兩造所不爭，是臨時碼頭亦非剩餘在場未用材料，無\n    由被上訴人依前開約定為收購或補償之問題。\n  4.綜上，該臨時碼頭既非供系爭工程所專用之設備，且臨時碼\n    頭所在之南堤工程款亦經被上訴人給付完畢，臨時碼頭於系\n    爭契約終止前，復已不存在，則上訴人依系爭契約，請求被\n    上訴人給付此部分之設備款，自非所許。\n  (三)關於「北堤便道石料」費用部分：就此，上訴人主張：其並\n    無拋棄請求此部分費用之意思，其前出具承諾書之真意係於\n    系爭工程如期完工之前提下，得如期獲得報酬，故同意因改\n    變施工方法而分攤施工成本，惟系爭工程並未如期完工，其\n    所支出之成本自應由被上訴人賠償之。其已依被上訴人之要\n    求於堤心石面上多填1公尺砂石作為施工便道以利施工，並\n    提報施工計畫，被上訴人自應賠償所已支付之石料費用110\n    萬2783元（共1901.35立方公尺，以每立方公尺580元計算，\n    $580/立方公尺×1901.35立方公尺＝$1,102,783），扣除發\n    回前經本院判命被上訴人給付之11萬500元後，被上訴人應\n    再賠償99萬2283元等語。被上訴人則辯稱：上訴人為讓被上\n    訴人同意將系爭契約原約定採用之全斷面施工法改為半半施\n    工法，遂於88年7月24日出具承諾書表示願自行吸收較原設\n    計所增加之工期及費用，不再向被上訴人請求給付費用，是\n    兩造已合意就系爭工程中「北堤便道石料」部分費用不在收\n    購範圍內。何況上訴人支出該部分費用，已經系爭工程北防\n    波堤部分工程之經驗收、計價而回收其成本，不得再為重複\n    請求，且上訴人就此部分施作數量亦未舉證以實其說，其主\n    張自不足採等語。查上訴人就其前開主張，固提出系爭工程\n    88年9月10日施工協調會會議紀錄（見原審卷(一)，201至204\n    頁）為證，並於原審聲請訊問證人項光祥（見原審卷(三)，52\n    至54頁），然依前開施工協調會紀錄，上訴人所以提議施作\n    此便道，乃為便利施工而來，上訴人並主動提及以砂石充填\n    ，於使用完畢後回收，因被上訴人恐砂土會被海浪沖入堤心\n    而污染海域，遂改以碎石充填，可見此一施工法乃為便利上\n    訴人而採，非應被上訴人之要求。證人即上訴人之工地主任\n    項光祥於原審亦證稱：於該地施工時，因為漲退潮關係，車\n    輛、施工械具及人員行走相當不便，故於協調會時提及多填\n    的砂土由上訴人自行吸收等語，並有證人項光祥出具之書面\n    ，內載：「．．其中南北防波堤壓頂混凝土，為施工順利，\n    請（被上訴人）同意採用半半施工法，並保證維持原設計品\n    質，如就此較原設計增加之工期及費用等，均由本公司（上\n    訴人）自行吸收，與甲方無關。」等語（見原審卷(三)，12頁\n    ），證人項光群同時證稱：其係本於工地主任身分簽立該書\n    面，且已經回報上訴人等語（見原審卷(三)，52頁、53頁），\n    參之證人即被上訴人職員陳建洲、丙○○於原審證稱上訴人\n    承諾此費用由上訴人自行吸收等語（見原審卷(三)，26至28頁\n    、30至32頁）相符，可知此費用之支出，純因上訴人為圖施\n    工方便而為，所以必須經被上訴人同意，則為被上訴人恐污\n    染海域故為此要求，並非被上訴人同意此費用由被上訴人支\n    付。又系爭契約既有終止契約後應如何善後之約定，則上訴\n    人自應考慮系爭契約終止之風險，是上訴人主張費用係預估\n    系爭契約順利執行時，可由其利潤中吸收，但因系爭契約終\n    止無法取得原有利潤，故無法吸收前開費用，亦難贊同。是\n    上訴人既承諾自行吸收前開費用，自不能請求被上訴人給付\n    。\n  (四)關於系爭工程浚挖超支數量之費用部分：就此，上訴人主張\n    ：系爭工程浚挖部分施工範圍包括堤防及港池，而為避免浚\n    挖面迴淤導致二次施工，均須預先擴大開挖面，從而因此所\n    浚挖之砂石均屬系爭工程之施工範圍，與系爭契約施工說明\n    書第5.5.2條規定之情形不同，倘系爭契約未提前終止，其\n    所預先施作之系爭工程浚挖部分終會獲得計價而回收成本，\n    系爭契約既已終止，其所預先施作之系爭工程浚挖部分因無\n    法測量計價致受有損害，被上訴人即應依系爭契約第23條第\n    4項及第1項之約定，與民法第231條、第227條之規定賠償其\n    此部分所超支費用之損害。其已施作之系爭工程浚挖部分數\n    量至少為8萬2153.46立方公尺，扣除已計價之2萬930.81立\n    方公尺，其餘部分並未計價，共計為1790萬432元等語。被\n    上訴人則否認上訴人主張其於系爭契約存續期間已挖除水中\n    土石之數量，並稱：系爭契約訂價單中就水中土石浚挖部分\n    所載數量僅係87年4月2日系爭工程開工前之概估數量，其上\n    亦有附註表示該項目係按實作數量計價，而系爭工程實因施\n    工範圍海域廣闊而採分區施工之方式進行水中浚挖及拋石工\n    作，兩造於各分區施工前均進行會測，從而系爭工程有關浚\n    挖及拋石數量之計算，自應以兩造共同會測後之原地面會測\n    設計圖面所示海中土石高度與設計線間所顯示之數量為其計\n    算基礎。又依系爭契約施工說明書第5.5.2條1.之約定，系\n    爭工程超過設計線深度之浚挖及拋石費用，應由上訴人自行\n    負擔，從而此部分之計價，應以符合系爭工程設計圖說之斷\n    面為計價基礎，而非以上訴人實際挖除之數量為計價基礎，\n    至如何施工可達系爭契約約定之效果者，則屬上訴人得自行\n    選擇施工方法以定之，故系爭工程如有為避免浚挖面迴淤而\n    預先擴大開挖面之情事發生，為上訴人自行選擇之結果，縱\n    屬系爭工程之範圍，依約仍不予計價。縱認上訴人因迴淤而\n    於浚挖部分有超挖數量之必要，亦係其履行輔助人無法有效\n    執行工作，及其使用機具不當所致，系爭工程坡度設計並無\n    不當，自屬可歸責於上訴人之事由，上訴人不得再請求賠償\n    等語。分述如下：\n  1.查上訴人主張其因迴淤而須二次施工或為避免浚挖面迴淤而\n    預先擴大開挖面所為施工，與系爭合約施工說明書第五章第\n    5.5.2「水中浚挖」4.規定：「在港池或堤身浚挖過程中，\n    如遇風浪或停工以致有迴淤情形時，均由乙方（上訴人）自\n    行負責，乙方應預估在有關項目之工程費內，甲方（被上訴\n    人）不另列項計價。」（見原審卷(一)，119頁），有所不同\n    ，固難據此即認應由上訴人就本項費用自行負責（發回意旨\n    參照）。然依該章第5.5.2「水中浚挖」1.規定：「水中土\n    石及岩盤浚挖均應達設計線，未達設計線時應繼續浚挖至設\n    計線，超過設計線深度之土石方不予計價，超挖部分甲方（\n    被上訴人）得視設計圖說決定拋石與否，如需拋石則其費用\n    亦由乙方（上訴人）負擔，且不得異議。」（見原審卷(一)，\n    119頁），依此兩造就上訴人應浚挖之寬度已明定以設計線\n    為基準，若有不足，應由上訴人繼續浚挖，若已超過，不但\n    不得請求被上訴人給付超過之費用，且被上訴人得以拋石填\n    充並由上訴人支付拋石之費用，如何恰到好處，乃上訴人施\n    工技術問題，非得請求被上訴人給付額外費用。從而不論上\n    訴人主張二次施工或擴大挖浚之數量是否屬實，均不得因迴\n    淤而須二次施工或為避免浚挖面迴淤而預先擴大開挖面所為\n    施工，請求被上訴人給付費用。\n  2.又系爭契約第23條第4項及第1項係約定：「如甲方（即被上\n    訴人）因特殊情形需中止工作時，得通知乙方（即上訴人）\n    應即停工並終止契約，乙方應即照辦。乙方已做工程由甲方\n    按實做合格數量依契約單價計價，乙方專用於本工程之設備\n    ，由甲方核實計價，剩餘在場未用材料，甲方得按約定合理\n    價格收購或補償，並退還履約保證金及押金等，乙方不得提\n    出額外要求。」上開為免迴淤所為之二次施工或擴大浚挖，\n    既非合約所定工程項目，亦非專用於系爭工程之設備或剩餘\n    在場未用材料，自無系爭契約第23條第4項及第1項之適用。\n    再者，依民法第507條規定，工作需定作人之行為始能完成\n    者，而定作人不為其行為時，承攬人得定相當期限，催告定\n    作人為之。定作人不於前項期限內為其行為者，承攬人得解\n    除契約，並得請求賠償因契約解除而生之損害。依此，定作\n    人縱未為協力驗收，亦僅承攬人得解除契約，並得請求賠償\n    因契約解除而生之損害而已，非謂定作人有給付遲延或不完\n    全給付之問題，是上訴人以被上訴人是否停工之政策猶疑不\n    決致其無法計價而受損害，依民法第231條、第227條請求被\n    上訴人賠償損害，亦非可採。\n  (五)關於水電費、工地安全衛生費、環境保護費、施工品質管制\n    費及施工測量費等部分：就此，上訴人主張：此5項費用依\n    系爭工程訂價單所載均係以「一式」計價，並無單價，而訂\n    價單中所載依實作數量計價者，係指他項工作而言，非指此\n    5項工作之費用，而此5項工作於計價時係以系爭工程款給付\n    之金額按比例付款，從而被上訴人應給付此5項費用共計147\n    萬426元等語。被上訴人則辯稱：此5項費用係以「一式」為\n    其計價方式，其已就上訴人已施作且經驗收之工作項目按其\n    比例給付之，再依系爭契約附件之投標須知第23條約定，以\n    一式計價之項目除設計變更外，概不增減計價，從而上訴人\n    不得另行請求增加給付。縱認上訴人得請求給付上開費用，\n    其中水電費中之接水設施費（含申請費用、人工及材料等）\n    及接電及發電設施費部分被上訴人均已給付，另照明器材中\n    之耗損及水電工中之維護部分費用，因上訴人業已終止系爭\n    契約，亦無耗損及維護之問題，均應將該部分費用扣除。再\n    者，上訴人仍重新承攬系爭工程續建部分，該水電費工程部\n    分仍係由上訴人使用，且於續建工程中亦計價予上訴人，上\n    訴人再次就該部分費用為計價，即受有不當得利，被上訴人\n    亦以上訴人不當得利之數額主張預備抵銷抗辯（見本院卷，\n    74 及164頁）等語。分述如下：\n  1.關於水電費、工地安全衛生費、環境保護費、施工品質管制\n    費、施工測量費部分，依據系爭契約訂價單所載均是以一「\n    式」計，並無單價（見原審卷(一)，第232頁）；該訂價單備\n    註欄所載採用實作數量計算者係指該表其他第84項至第104\n    項及第111、112項目，並非指此5項工作，是被上訴人抗辯\n    此5項工作為實作實算，尚非可採。\n  2.又上訴人請求之水電費，係包含接水設施費（含申請費用、\n    人工及材料等）、接電及發電設施費、照明器材及零星工料\n    ，性質上為各項工程施工之前置工程，是上訴人主張系爭工\n    程既已實際開工，前開費用自已支出，應可採信。又上訴人\n    主張扣除被上訴人已依合約給付單價169萬2270元之23.37%\n    ，尚有76.63%即129萬6787元未付（見原審卷(一)，180頁，卷\n    (二)，20頁），被上訴人亦稱其已依驗收項目之比例給付（見\n    本院上字卷(四)，100頁，更字卷，17頁）可見上訴人主張被\n    上訴人未全部給付，亦屬可信。該水電事項既為開工前必須\n    完工之工程，則於被上訴人終止系爭契約當時，上訴人當已\n    全部完工，被上訴人僅依合約驗收比例付款，顯有不足，是\n    上訴人請求被上訴人應再給付其餘之129萬6787元，應屬可\n    採。至於系爭工程之續建工程是否仍由上訴人承攬，該水電\n    設施是否仍由上訴人使用，乃續建工程應如何計算問題，與\n    上訴人得於本件請求該費用，要屬二事。被上訴人雖以上訴\n    人重新於續建工程繼續使用該水電設備，受有不當得利，然\n    未具體主張其據以抵銷之金額為何，其抵銷之抗辯，與民事\n    訴訟法第400條第2項規定不符，抵銷抗辯為不合法。\n  3.至於工地安全衛生費（3萬7446元）、環境保護費（1萬0407\n    元）、施工品質管制費（78056元）、施工測量費（4萬7730\n    元）部分，為依工程報酬比例計價，已如前述。而被上訴人\n    就上訴人主張此部分所佔工程款之比例為1.00000000%，亦\n    無爭執，本院應以之為裁判基礎。又被上訴人應給付上訴人\n    388萬0958元之工程報酬（中高桅桿投光燈基礎螺栓22萬500\n    0元、北堤便道石料11萬500元、施工便道350萬8308元、管\n    路架3萬7150元）業經判決確定，則上訴人依前開比率，自\n    得請求被上訴人給付此4項之費用6萬9212元（388萬0958元\n    *1.00000000%＝6萬9212元，元以下四捨五入）。\n  (六)總計上訴人得另請求被上訴人給付之金額為136萬5999元（\n    129萬6787元+6萬9212元＝136萬5999元）\n五、綜上所述，上訴人請求被上訴人除已判決確定部分外，應另\n    給付136萬5999元及自92年1月28日（催告函送達翌日）起至\n    清償之日止，按周年利率5%計算之利息，為有理由，應予准\n    許。逾此金額之請求，為無理由，不應准許。上開應予准許\n    部分，原判決駁回上訴人之訴，尚有未洽，上訴意旨指摘原\n    判決此部分不當，求予廢棄改判，為有理由，應由本院將原\n    判決此部分廢棄，改判如主文第2項所示。前開不應准許部\n    分，原判決駁回上訴人之訴及其假執行之聲請，並無不合。\n    上訴意旨指摘原判決此部分不當，聲明廢棄改判，為無理由\n    ，應予駁回上訴。\n六、據上論結，本件上訴一部為有理由，一部為無理由。依民事\n    訴訟法第450條、第449條第1項、第79條，判決如主文。"
  },
  "characters": {
    "judges": [
      "鄭三源",
      "魏麗娟",
      "呂太郎"
    ],
    "prosecutors": [

    ],
    "lawyers": [
      "唐月妙",
      "簡維能",
      "陳美華",
      "師或具有",
      "人或其他法定代理人具有"
    ],
    "clerks": [
      "黃千鶴"
    ],
    "plaintiffs": [

    ],
    "defendants": [

    ],
    "prosecutor_office": [

    ],
    "creditors": [

    ],
    "debtors": [

    ],
    "judicial_associate_officer": [

    ]
  },
  "adjudged_at": "2010-01-05",
  "created_at": "2016-01-05 15:04:36",
  "updated_at": "2016-01-05 15:04:36"
}