{
  "identify": "TPH-99-上-93-20100512-1",
  "court": {
    "name": "臺灣高等法院",
    "code": "TPH"
  },
  "division": {
    "name": "民事",
    "code": "V"
  },
  "year": 99,
  "word": "上",
  "number": "93",
  "jcheck": "1",
  "reason": "債務人異議之訴",
  "content": "臺灣高等法院民事判決                    99年度上字第93號\n上  訴  人  甲○○\n上  訴  人  丁○○\n前列二人共同\n訴訟代理人  錢裕國律師\n被上訴人    永豐商業銀行股份有限公司\n法定代理人  邱正雄\n訴訟代理人  戊○○\n            乙○○\n上列當事人間請求債務人異議之訴事件，上訴人對於中華民國98\n年11月27日臺灣臺北地方法院98年度審訴字第5310號第一審判決\n提起上訴，本院於99年4月28日言詞辯論終結，判決如下：\n    主      文\n上訴駁回。\n第二審訴訟費用由上訴人負擔。\n    事實及理由\n一、本件被上訴人法定代理人原為丙○○，業經變更為邱正雄，\n    有行政院金融監督管理委員會函、銀行營業執照附卷可參（\n    見本院卷第26至27頁），並經聲明承受訴訟（見本院卷第21\n    頁），核無不合，應予准許。又本件上訴人係主張系爭支付\n    命令送達不合法，依強制執行法第14條第2項起訴請求系爭\n    執行程序應予撤銷，嗣於本院復主張並依強制執行法第14條\n    第1項請求撤銷系爭執行程序，核屬補充法律上之陳述，於\n    法尚無不合，亦應予准許，合先敘明。\n二、本件上訴人起訴主張略以：伊等於民國97年5月30日收受原\n    法院民事執行處97年5月23日北院隆97執酉字第43275號函，\n    嗣於同年6月2日聲請閱卷後，始發現原法院97年度執字第\n    43275號強制執行事件（下稱系爭執行事件）之執行名義係\n    原法院97年度促字第7131號確定支付命令（下稱系爭支付命\n    令），而系爭支付命令所載送達地址雖為伊等之戶籍地址即\n    台北市○○路○段437巷10弄12號3樓（下稱八德路址），然\n    八德路址係因伊等於93年3月10日向訴外人陳明慶承租而設\n    籍於該址，伊等已於95年10月20日另行購買坐落台北市○○\n    路之房屋為住所（下稱安和路址），故自95年12月起伊等雖\n    設籍於八德路址，實際上伊等並未居住於該處，系爭支付命\n    令於97年3月21日對八德路址為寄存送達，並不合法。且伊\n    等至八德路址，並未見門首有何黏貼之送達文書，自難認已\n    合法送達。伊等係於97年6月6日領取系爭支付命令，應自該\n    日始生送達效力，伊等復已另行聲明異議，系爭支付命令自\n    無從確定，故系爭強制執行事件執行程序應予撤銷。縱認系\n    爭支付命令已確定，依民法第126條規定，被上訴人所請求\n    有關利息部分，得請求者應以5年為限，被上訴人請求自84\n    年11月26日起算之利息，亦有未合。另上訴人劉淑敏固為連\n    帶保證人，然劉淑敏不知有何債務不履行之情事，乃被上訴\n    人請求20%之高額違約金，顯失公平，自有依民法第252條規\n    定予以酌減之必要。為此爰依強制執行法第14條第2項規定\n    提起本件訴訟，求為判決：臺灣臺北地方法院97年度執字第\n    43275號清償債務強制執行事件之執行程序（下稱系爭執行\n    程序）應予撤銷。原審為上訴人敗訴之判決，上訴人不服提\n    起本件上訴，並聲明為：(一)原判決廢棄。(二)系爭執行程序應\n    予撤銷。\n三、被上訴人則以：系爭支付命令送達時上訴人戶籍地址確為八\n    德路址，迄至97年5月14日止，上訴人所有轎車亦登記以八\n    德路址為所有權人地址。上訴人雖謂自95年12月起即未居住\n    於八德路址，然其等未為遷入及住址變更登記，足見上訴人\n    並無廢棄該址為其住所之意思。伊已盡一切努力調查上訴人\n    之住居所地，基於對戶政機關戶籍登記公文之信賴，客觀上\n    亦無法得知上訴人已變更意思而改以其他住址為住所，故難\n    謂原戶籍登記之住所非屬其住所，系爭支付命令之寄存送達\n    自屬合法。上訴人對系爭支付命令所為之聲明異議，並經原\n    法院於97年6月12日以97年度促字第7131號裁定、本院以97\n    年度抗字第1317號裁定駁回抗告確定。本件借款之違約金係\n    約定於逾期6個月以內者按約定利率一成計算，逾期超過6個\n    月者，按約定利率二成計算，本件債務係伊聲請拍賣上訴人\n    甲○○提供之抵押物後不足受償部分，前段違約金以年利率\n    0.96%計算，後段違約金以年利率1.92%計算（計算式：前段\n    違約金依約定利率9.6%×10%＝0.96%，後段違約金為9.6%×\n    20%＝1.92%），是利息及違約金合計均未超過法定利率20%\n    ，該違約金亦經原法院於審理系爭支付命令時核准在案，上\n    訴人抗辯無理由等語，資為抗辯。並於本院答辯聲明為：駁\n    回上訴。\n四、查上訴人甲○○前邀上訴人丁○○為連帶保證人，於民國81\n    年11月28日向被上訴人（前身為台北區中小企業銀行股份有\n    限公司，於87年2月11日更名為台北國際商業銀行股份有限\n    公司，再於95年11月13日經行政院金融監督管理委員會核准\n    與建華商業銀行股份有限公司合併，並經行政院金融管理委\n    員會以金管銀(六)字第09500476730號函同意，合併後之存續\n    公司並更名為被上訴人永豐商業銀行股份有限公司）借款新\n    台幣（下同）950萬元。嗣因未按期清償，被上訴人向原法\n    院聲請核發系爭支付命令，命上訴人連帶清償被上訴人本金\n    3,132,588元及自84年11月28日起至清償日止，按年息9.6%\n    計算之利息暨於逾期6個月以內者按約定利率一成計算，逾\n    期超過6個月者，按約定利率二成計算違約金。系爭支付命\n    令於97年3月21日送達至上訴人自93年3月10日起至97年8月\n    31日止設籍之八德路址，因不獲會晤應受送達人且無法交付\n    與有辨別事理能力之同居人或受僱人，故於97年3月21日寄\n    存送達於臺北市政府警察局松山分局中崙派出所，並經原法\n    院於97年4月25日核發系爭支付命令確定證明書，載明系爭\n    支付命令於97年4月21日確定。被上訴人以系爭支付命令為\n    執行名義，經以系爭執行事件執行中等情，為兩造所不爭執\n    ，及經本院調取系爭支付命令卷、系爭執行事件卷閱明屬實\n    ，並有系爭支付命令確定證明書、送達證書、借據附卷可參\n    （見原審卷第7、34至37、41頁），堪認為真正。\n五、上訴人主張系爭支付命令之寄存送達不合法，故系爭執行程\n    序應予撤銷；縱認系爭支付命令已確定，被上訴人所請求之\n    利息亦有部分已罹於時效，被上訴人請求20%違約金亦顯失\n    公平，應予酌減等語，則為被上訴人所否認，並以前詞置辯\n    。是本院所應審究者核為：上訴人主張系爭支付命令未合法\n    送達，被上訴人之部分利息請求權已罹於時效及本件約定之\n    違約金過高為由而依強制執行法第14條第2項規定提起債務\n    人異議之訴有無理由？其依強制執行法第14條第1項規定更\n    為主張，是否有據？\n六、經查：\n  (一)上訴人不得依強制執行法第14條第2項規定提起債務人異議\n    之訴：\n    1.按執行名義無確定判決同一之效力者，於執行名義成立前\n      ，如有債權不成立或消滅或妨礙債權人請求之事由發生，\n      債務人得於強制執行程序終結前提起異議之訴，強制執行\n      法第14條第2項定有明文，若執行名義並未成立，債權人\n      竟聲請對債務人強制執行，而侵害債務人之權利，僅係債\n      務人得否依強制執行法第12條第1項規定聲明異議而已，\n      尚非得提起債務人異議之訴（參照最高法院87年度台上字\n      第1438號判決意旨）；次按債務人對於支付命令未於法定\n      期間合法提出異議者，支付命令與確定判決有同一之效力\n      ，此為民事訴訟法第521條第1項所明定。故債務人對於以\n      具有確定判決同一效力之支付命令為執行名義所為之強制\n      執行程序，僅得依據強制執行法第14條第1項提起債務人\n      異議之訴以為救濟，而不得依同條第2項規定，以執行名\n      義成立前有債權不成立或消滅或妨礙債權人請求之事由發\n      生，而提起債務人異議之訴。\n    2.上訴人主張系爭支付命令送達不合法，故並未確定云云，\n      惟查上訴人就系爭支付命令固曾聲明異議，惟業經原法院\n      於97年6月12日以97年度促字第7131號裁定駁回異議，乃\n      上訴人不服提起抗告，亦經本院以系爭支付命令送達至上\n      訴人之戶籍地址，並踐行寄存送達之法定程序，屬合法寄\n      存送達，上訴人提出異議已逾越20日之不變期間為由，而\n      於97年8月20日以97年度抗字第1317號民事裁定駁回抗告\n      在案，有前開民事裁定在卷可參（見原審卷第38至40頁）\n      ，及經本院調取上開卷宗查明屬實，堪認系爭支付命令於\n      97年4月21日即已告確定，其猶執前詞，主張送達不合法\n      云云，洵無足取。是系爭執行程序所憑之執行名義即系爭\n      支付命令，核與確定判決有同一效力，揆諸上開說明，上\n      訴人依強制執行法第14條第2項提起債務人異議之訴，即\n      屬無據。\n  (二)上訴人依強制執行法第14條第1項規定提起債務人異議之訴\n    ，為無理由：\n    1.按執行名義成立後，如有消滅或妨礙債權人請求之事由發\n      生，債務人得於強制執行程序終結前，向執行法院對債權\n      人提起異議之訴，固為強制執行法第14條第1項所明定。\n      惟此須以其主張消滅或妨礙債權人請求之事由，係發生於\n      執行名義成立後者，始得為之，若其主張此項事由在執行\n      名義成立之前即已存在，則為執行名義之裁判縱有不當，\n      亦非異議之訴所能救濟（最高法院44年台上字第1472號判\n      例要旨參照）。\n    2.查本件上訴人所主張送達不合法、部分利息已罹於時效、\n      約定違約金計算比例過高等消滅或妨礙被上訴人請求之事\n      由，核均係在系爭支付命令確定前即執行名義成立前即已\n      存在。依照前開說明，亦不能謂上訴人得依強制執行法第\n      14條第1項之規定，提起債務人異議之訴，其聲請訊問證\n      人陳明慶證明於95年12月間即已搬離云云，即無必要。\n    3.上訴人固主張違約金部分於執行名義確定後亦有消滅或妨\n      礙被上訴人之事由發生（即違約金過高）云云，惟查兩造\n      就如何計算違約金之約定於借款當時即已成立，並經系爭\n      支付命令核准確定，上訴人此部分之主張尚不足採。又被\n      上訴人所請求之系爭利息債權，自84年11月28日至92年3\n      月5日止請求權已罹於民法第12 6條所規定之5年時效乙節\n      ，為被上訴人所不爭，其並就該部分已具狀向執行法院聲\n      請減縮金額，有聲請狀乙紙在卷可憑（見本院卷第28頁）\n      ，併此敘明。\n七、綜上所述，被上訴人主張為可採，上訴人所辯均無可取。從\n    而，上訴人依據強制執行法第14條第1、2項之規定，請求撤\n    銷系爭執行程序，為無理由，應予駁回。原審為上訴人敗訴\n    之判決，於法並無不合，上訴意旨指摘原判決不當，求予廢\n    棄改判，為無理由，應予駁回。\n八、本件事證已臻明確，兩造其餘攻擊或防禦方法，經審酌後認\n    與本件之結論無涉，爰不一一論述，併予敘明。\n九、據上論結，本件上訴為無理由，依民事訴訟法第449條第1項\n    、第78條、第85條第1項前段，判決如主文。\n中    華    民    國    99    年    5    月    12     日\n                    民事第二庭\n                        審判長法  官  吳謙仁\n                              法  官  李瓊蔭\n                              法  官  黃莉雲\n正本係照原本作成。\n如不服本判決，應於收受送達後20日內向本院提出上訴書狀，其\n未表明上訴理由者，應於提出上訴後20日內向本院補提理由書狀\n（均須按他造當事人之人數附繕本）上訴時應提出委任律師或具\n有律師資格之人之委任狀；委任有律師資格者，另應附具律師資\n格證書及釋明委任人與受任人有民事訴訟法第466條之1第1項但\n書或第2項（詳附註）所定關係之釋明文書影本。\n中    華    民    國    99    年    5     月    14    日\n                              書記官  魏汝萍\n附註：\n民事訴訟法第466條之1（第1項、第2項）：\n對於第二審判決上訴，上訴人應委任律師為訴訟代理人。但上訴\n人或其他法定代理人具有律師資格者，不在此限。\n上訴人之配偶、三親等內之血親、二親等內之姻親，或上訴人為\n法人、中央或地方機關時，其所屬專任人員具有律師資格並經法\n院認為適當者，亦得為第三審訴訟代理人。",
  "structure": {
    "main": "上訴駁回。\n第二審訴訟費用由上訴人負擔。",
    "fact": "一、本件被上訴人法定代理人原為丙○○，業經變更為邱正雄，\n    有行政院金融監督管理委員會函、銀行營業執照附卷可參（\n    見本院卷第26至27頁），並經聲明承受訴訟（見本院卷第21\n    頁），核無不合，應予准許。又本件上訴人係主張系爭支付\n    命令送達不合法，依強制執行法第14條第2項起訴請求系爭\n    執行程序應予撤銷，嗣於本院復主張並依強制執行法第14條\n    第1項請求撤銷系爭執行程序，核屬補充法律上之陳述，於\n    法尚無不合，亦應予准許，合先敘明。\n二、本件上訴人起訴主張略以：伊等於民國97年5月30日收受原\n    法院民事執行處97年5月23日北院隆97執酉字第43275號函，\n    嗣於同年6月2日聲請閱卷後，始發現原法院97年度執字第\n    43275號強制執行事件（下稱系爭執行事件）之執行名義係\n    原法院97年度促字第7131號確定支付命令（下稱系爭支付命\n    令），而系爭支付命令所載送達地址雖為伊等之戶籍地址即\n    台北市○○路○段437巷10弄12號3樓（下稱八德路址），然\n    八德路址係因伊等於93年3月10日向訴外人陳明慶承租而設\n    籍於該址，伊等已於95年10月20日另行購買坐落台北市○○\n    路之房屋為住所（下稱安和路址），故自95年12月起伊等雖\n    設籍於八德路址，實際上伊等並未居住於該處，系爭支付命\n    令於97年3月21日對八德路址為寄存送達，並不合法。且伊\n    等至八德路址，並未見門首有何黏貼之送達文書，自難認已\n    合法送達。伊等係於97年6月6日領取系爭支付命令，應自該\n    日始生送達效力，伊等復已另行聲明異議，系爭支付命令自\n    無從確定，故系爭強制執行事件執行程序應予撤銷。縱認系\n    爭支付命令已確定，依民法第126條規定，被上訴人所請求\n    有關利息部分，得請求者應以5年為限，被上訴人請求自84\n    年11月26日起算之利息，亦有未合。另上訴人劉淑敏固為連\n    帶保證人，然劉淑敏不知有何債務不履行之情事，乃被上訴\n    人請求20%之高額違約金，顯失公平，自有依民法第252條規\n    定予以酌減之必要。為此爰依強制執行法第14條第2項規定\n    提起本件訴訟，求為判決：臺灣臺北地方法院97年度執字第\n    43275號清償債務強制執行事件之執行程序（下稱系爭執行\n    程序）應予撤銷。原審為上訴人敗訴之判決，上訴人不服提\n    起本件上訴，並聲明為：(一)原判決廢棄。(二)系爭執行程序應\n    予撤銷。\n三、被上訴人則以：系爭支付命令送達時上訴人戶籍地址確為八\n    德路址，迄至97年5月14日止，上訴人所有轎車亦登記以八\n    德路址為所有權人地址。上訴人雖謂自95年12月起即未居住\n    於八德路址，然其等未為遷入及住址變更登記，足見上訴人\n    並無廢棄該址為其住所之意思。伊已盡一切努力調查上訴人\n    之住居所地，基於對戶政機關戶籍登記公文之信賴，客觀上\n    亦無法得知上訴人已變更意思而改以其他住址為住所，故難\n    謂原戶籍登記之住所非屬其住所，系爭支付命令之寄存送達\n    自屬合法。上訴人對系爭支付命令所為之聲明異議，並經原\n    法院於97年6月12日以97年度促字第7131號裁定、本院以97\n    年度抗字第1317號裁定駁回抗告確定。本件借款之違約金係\n    約定於逾期6個月以內者按約定利率一成計算，逾期超過6個\n    月者，按約定利率二成計算，本件債務係伊聲請拍賣上訴人\n    甲○○提供之抵押物後不足受償部分，前段違約金以年利率\n    0.96%計算，後段違約金以年利率1.92%計算（計算式：前段\n    違約金依約定利率9.6%×10%＝0.96%，後段違約金為9.6%×\n    20%＝1.92%），是利息及違約金合計均未超過法定利率20%\n    ，該違約金亦經原法院於審理系爭支付命令時核准在案，上\n    訴人抗辯無理由等語，資為抗辯。並於本院答辯聲明為：駁\n    回上訴。\n四、查上訴人甲○○前邀上訴人丁○○為連帶保證人，於民國81\n    年11月28日向被上訴人（前身為台北區中小企業銀行股份有\n    限公司，於87年2月11日更名為台北國際商業銀行股份有限\n    公司，再於95年11月13日經行政院金融監督管理委員會核准\n    與建華商業銀行股份有限公司合併，並經行政院金融管理委\n    員會以金管銀(六)字第09500476730號函同意，合併後之存續\n    公司並更名為被上訴人永豐商業銀行股份有限公司）借款新\n    台幣（下同）950萬元。嗣因未按期清償，被上訴人向原法\n    院聲請核發系爭支付命令，命上訴人連帶清償被上訴人本金\n    3,132,588元及自84年11月28日起至清償日止，按年息9.6%\n    計算之利息暨於逾期6個月以內者按約定利率一成計算，逾\n    期超過6個月者，按約定利率二成計算違約金。系爭支付命\n    令於97年3月21日送達至上訴人自93年3月10日起至97年8月\n    31日止設籍之八德路址，因不獲會晤應受送達人且無法交付\n    與有辨別事理能力之同居人或受僱人，故於97年3月21日寄\n    存送達於臺北市政府警察局松山分局中崙派出所，並經原法\n    院於97年4月25日核發系爭支付命令確定證明書，載明系爭\n    支付命令於97年4月21日確定。被上訴人以系爭支付命令為\n    執行名義，經以系爭執行事件執行中等情，為兩造所不爭執\n    ，及經本院調取系爭支付命令卷、系爭執行事件卷閱明屬實\n    ，並有系爭支付命令確定證明書、送達證書、借據附卷可參\n    （見原審卷第7、34至37、41頁），堪認為真正。\n五、上訴人主張系爭支付命令之寄存送達不合法，故系爭執行程\n    序應予撤銷；縱認系爭支付命令已確定，被上訴人所請求之\n    利息亦有部分已罹於時效，被上訴人請求20%違約金亦顯失\n    公平，應予酌減等語，則為被上訴人所否認，並以前詞置辯\n    。是本院所應審究者核為：上訴人主張系爭支付命令未合法\n    送達，被上訴人之部分利息請求權已罹於時效及本件約定之\n    違約金過高為由而依強制執行法第14條第2項規定提起債務\n    人異議之訴有無理由？其依強制執行法第14條第1項規定更\n    為主張，是否有據？\n六、經查：\n  (一)上訴人不得依強制執行法第14條第2項規定提起債務人異議\n    之訴：\n    1.按執行名義無確定判決同一之效力者，於執行名義成立前\n      ，如有債權不成立或消滅或妨礙債權人請求之事由發生，\n      債務人得於強制執行程序終結前提起異議之訴，強制執行\n      法第14條第2項定有明文，若執行名義並未成立，債權人\n      竟聲請對債務人強制執行，而侵害債務人之權利，僅係債\n      務人得否依強制執行法第12條第1項規定聲明異議而已，\n      尚非得提起債務人異議之訴（參照最高法院87年度台上字\n      第1438號判決意旨）；次按債務人對於支付命令未於法定\n      期間合法提出異議者，支付命令與確定判決有同一之效力\n      ，此為民事訴訟法第521條第1項所明定。故債務人對於以\n      具有確定判決同一效力之支付命令為執行名義所為之強制\n      執行程序，僅得依據強制執行法第14條第1項提起債務人\n      異議之訴以為救濟，而不得依同條第2項規定，以執行名\n      義成立前有債權不成立或消滅或妨礙債權人請求之事由發\n      生，而提起債務人異議之訴。\n    2.上訴人主張系爭支付命令送達不合法，故並未確定云云，\n      惟查上訴人就系爭支付命令固曾聲明異議，惟業經原法院\n      於97年6月12日以97年度促字第7131號裁定駁回異議，乃\n      上訴人不服提起抗告，亦經本院以系爭支付命令送達至上\n      訴人之戶籍地址，並踐行寄存送達之法定程序，屬合法寄\n      存送達，上訴人提出異議已逾越20日之不變期間為由，而\n      於97年8月20日以97年度抗字第1317號民事裁定駁回抗告\n      在案，有前開民事裁定在卷可參（見原審卷第38至40頁）\n      ，及經本院調取上開卷宗查明屬實，堪認系爭支付命令於\n      97年4月21日即已告確定，其猶執前詞，主張送達不合法\n      云云，洵無足取。是系爭執行程序所憑之執行名義即系爭\n      支付命令，核與確定判決有同一效力，揆諸上開說明，上\n      訴人依強制執行法第14條第2項提起債務人異議之訴，即\n      屬無據。\n  (二)上訴人依強制執行法第14條第1項規定提起債務人異議之訴\n    ，為無理由：\n    1.按執行名義成立後，如有消滅或妨礙債權人請求之事由發\n      生，債務人得於強制執行程序終結前，向執行法院對債權\n      人提起異議之訴，固為強制執行法第14條第1項所明定。\n      惟此須以其主張消滅或妨礙債權人請求之事由，係發生於\n      執行名義成立後者，始得為之，若其主張此項事由在執行\n      名義成立之前即已存在，則為執行名義之裁判縱有不當，\n      亦非異議之訴所能救濟（最高法院44年台上字第1472號判\n      例要旨參照）。\n    2.查本件上訴人所主張送達不合法、部分利息已罹於時效、\n      約定違約金計算比例過高等消滅或妨礙被上訴人請求之事\n      由，核均係在系爭支付命令確定前即執行名義成立前即已\n      存在。依照前開說明，亦不能謂上訴人得依強制執行法第\n      14條第1項之規定，提起債務人異議之訴，其聲請訊問證\n      人陳明慶證明於95年12月間即已搬離云云，即無必要。\n    3.上訴人固主張違約金部分於執行名義確定後亦有消滅或妨\n      礙被上訴人之事由發生（即違約金過高）云云，惟查兩造\n      就如何計算違約金之約定於借款當時即已成立，並經系爭\n      支付命令核准確定，上訴人此部分之主張尚不足採。又被\n      上訴人所請求之系爭利息債權，自84年11月28日至92年3\n      月5日止請求權已罹於民法第12 6條所規定之5年時效乙節\n      ，為被上訴人所不爭，其並就該部分已具狀向執行法院聲\n      請減縮金額，有聲請狀乙紙在卷可憑（見本院卷第28頁）\n      ，併此敘明。\n七、綜上所述，被上訴人主張為可採，上訴人所辯均無可取。從\n    而，上訴人依據強制執行法第14條第1、2項之規定，請求撤\n    銷系爭執行程序，為無理由，應予駁回。原審為上訴人敗訴\n    之判決，於法並無不合，上訴意旨指摘原判決不當，求予廢\n    棄改判，為無理由，應予駁回。\n八、本件事證已臻明確，兩造其餘攻擊或防禦方法，經審酌後認\n    與本件之結論無涉，爰不一一論述，併予敘明。\n九、據上論結，本件上訴為無理由，依民事訴訟法第449條第1項\n    、第78條、第85條第1項前段，判決如主文。",
    "reason": "一、本件被上訴人法定代理人原為丙○○，業經變更為邱正雄，\n    有行政院金融監督管理委員會函、銀行營業執照附卷可參（\n    見本院卷第26至27頁），並經聲明承受訴訟（見本院卷第21\n    頁），核無不合，應予准許。又本件上訴人係主張系爭支付\n    命令送達不合法，依強制執行法第14條第2項起訴請求系爭\n    執行程序應予撤銷，嗣於本院復主張並依強制執行法第14條\n    第1項請求撤銷系爭執行程序，核屬補充法律上之陳述，於\n    法尚無不合，亦應予准許，合先敘明。\n二、本件上訴人起訴主張略以：伊等於民國97年5月30日收受原\n    法院民事執行處97年5月23日北院隆97執酉字第43275號函，\n    嗣於同年6月2日聲請閱卷後，始發現原法院97年度執字第\n    43275號強制執行事件（下稱系爭執行事件）之執行名義係\n    原法院97年度促字第7131號確定支付命令（下稱系爭支付命\n    令），而系爭支付命令所載送達地址雖為伊等之戶籍地址即\n    台北市○○路○段437巷10弄12號3樓（下稱八德路址），然\n    八德路址係因伊等於93年3月10日向訴外人陳明慶承租而設\n    籍於該址，伊等已於95年10月20日另行購買坐落台北市○○\n    路之房屋為住所（下稱安和路址），故自95年12月起伊等雖\n    設籍於八德路址，實際上伊等並未居住於該處，系爭支付命\n    令於97年3月21日對八德路址為寄存送達，並不合法。且伊\n    等至八德路址，並未見門首有何黏貼之送達文書，自難認已\n    合法送達。伊等係於97年6月6日領取系爭支付命令，應自該\n    日始生送達效力，伊等復已另行聲明異議，系爭支付命令自\n    無從確定，故系爭強制執行事件執行程序應予撤銷。縱認系\n    爭支付命令已確定，依民法第126條規定，被上訴人所請求\n    有關利息部分，得請求者應以5年為限，被上訴人請求自84\n    年11月26日起算之利息，亦有未合。另上訴人劉淑敏固為連\n    帶保證人，然劉淑敏不知有何債務不履行之情事，乃被上訴\n    人請求20%之高額違約金，顯失公平，自有依民法第252條規\n    定予以酌減之必要。為此爰依強制執行法第14條第2項規定\n    提起本件訴訟，求為判決：臺灣臺北地方法院97年度執字第\n    43275號清償債務強制執行事件之執行程序（下稱系爭執行\n    程序）應予撤銷。原審為上訴人敗訴之判決，上訴人不服提\n    起本件上訴，並聲明為：(一)原判決廢棄。(二)系爭執行程序應\n    予撤銷。\n三、被上訴人則以：系爭支付命令送達時上訴人戶籍地址確為八\n    德路址，迄至97年5月14日止，上訴人所有轎車亦登記以八\n    德路址為所有權人地址。上訴人雖謂自95年12月起即未居住\n    於八德路址，然其等未為遷入及住址變更登記，足見上訴人\n    並無廢棄該址為其住所之意思。伊已盡一切努力調查上訴人\n    之住居所地，基於對戶政機關戶籍登記公文之信賴，客觀上\n    亦無法得知上訴人已變更意思而改以其他住址為住所，故難\n    謂原戶籍登記之住所非屬其住所，系爭支付命令之寄存送達\n    自屬合法。上訴人對系爭支付命令所為之聲明異議，並經原\n    法院於97年6月12日以97年度促字第7131號裁定、本院以97\n    年度抗字第1317號裁定駁回抗告確定。本件借款之違約金係\n    約定於逾期6個月以內者按約定利率一成計算，逾期超過6個\n    月者，按約定利率二成計算，本件債務係伊聲請拍賣上訴人\n    甲○○提供之抵押物後不足受償部分，前段違約金以年利率\n    0.96%計算，後段違約金以年利率1.92%計算（計算式：前段\n    違約金依約定利率9.6%×10%＝0.96%，後段違約金為9.6%×\n    20%＝1.92%），是利息及違約金合計均未超過法定利率20%\n    ，該違約金亦經原法院於審理系爭支付命令時核准在案，上\n    訴人抗辯無理由等語，資為抗辯。並於本院答辯聲明為：駁\n    回上訴。\n四、查上訴人甲○○前邀上訴人丁○○為連帶保證人，於民國81\n    年11月28日向被上訴人（前身為台北區中小企業銀行股份有\n    限公司，於87年2月11日更名為台北國際商業銀行股份有限\n    公司，再於95年11月13日經行政院金融監督管理委員會核准\n    與建華商業銀行股份有限公司合併，並經行政院金融管理委\n    員會以金管銀(六)字第09500476730號函同意，合併後之存續\n    公司並更名為被上訴人永豐商業銀行股份有限公司）借款新\n    台幣（下同）950萬元。嗣因未按期清償，被上訴人向原法\n    院聲請核發系爭支付命令，命上訴人連帶清償被上訴人本金\n    3,132,588元及自84年11月28日起至清償日止，按年息9.6%\n    計算之利息暨於逾期6個月以內者按約定利率一成計算，逾\n    期超過6個月者，按約定利率二成計算違約金。系爭支付命\n    令於97年3月21日送達至上訴人自93年3月10日起至97年8月\n    31日止設籍之八德路址，因不獲會晤應受送達人且無法交付\n    與有辨別事理能力之同居人或受僱人，故於97年3月21日寄\n    存送達於臺北市政府警察局松山分局中崙派出所，並經原法\n    院於97年4月25日核發系爭支付命令確定證明書，載明系爭\n    支付命令於97年4月21日確定。被上訴人以系爭支付命令為\n    執行名義，經以系爭執行事件執行中等情，為兩造所不爭執\n    ，及經本院調取系爭支付命令卷、系爭執行事件卷閱明屬實\n    ，並有系爭支付命令確定證明書、送達證書、借據附卷可參\n    （見原審卷第7、34至37、41頁），堪認為真正。\n五、上訴人主張系爭支付命令之寄存送達不合法，故系爭執行程\n    序應予撤銷；縱認系爭支付命令已確定，被上訴人所請求之\n    利息亦有部分已罹於時效，被上訴人請求20%違約金亦顯失\n    公平，應予酌減等語，則為被上訴人所否認，並以前詞置辯\n    。是本院所應審究者核為：上訴人主張系爭支付命令未合法\n    送達，被上訴人之部分利息請求權已罹於時效及本件約定之\n    違約金過高為由而依強制執行法第14條第2項規定提起債務\n    人異議之訴有無理由？其依強制執行法第14條第1項規定更\n    為主張，是否有據？\n六、經查：\n  (一)上訴人不得依強制執行法第14條第2項規定提起債務人異議\n    之訴：\n    1.按執行名義無確定判決同一之效力者，於執行名義成立前\n      ，如有債權不成立或消滅或妨礙債權人請求之事由發生，\n      債務人得於強制執行程序終結前提起異議之訴，強制執行\n      法第14條第2項定有明文，若執行名義並未成立，債權人\n      竟聲請對債務人強制執行，而侵害債務人之權利，僅係債\n      務人得否依強制執行法第12條第1項規定聲明異議而已，\n      尚非得提起債務人異議之訴（參照最高法院87年度台上字\n      第1438號判決意旨）；次按債務人對於支付命令未於法定\n      期間合法提出異議者，支付命令與確定判決有同一之效力\n      ，此為民事訴訟法第521條第1項所明定。故債務人對於以\n      具有確定判決同一效力之支付命令為執行名義所為之強制\n      執行程序，僅得依據強制執行法第14條第1項提起債務人\n      異議之訴以為救濟，而不得依同條第2項規定，以執行名\n      義成立前有債權不成立或消滅或妨礙債權人請求之事由發\n      生，而提起債務人異議之訴。\n    2.上訴人主張系爭支付命令送達不合法，故並未確定云云，\n      惟查上訴人就系爭支付命令固曾聲明異議，惟業經原法院\n      於97年6月12日以97年度促字第7131號裁定駁回異議，乃\n      上訴人不服提起抗告，亦經本院以系爭支付命令送達至上\n      訴人之戶籍地址，並踐行寄存送達之法定程序，屬合法寄\n      存送達，上訴人提出異議已逾越20日之不變期間為由，而\n      於97年8月20日以97年度抗字第1317號民事裁定駁回抗告\n      在案，有前開民事裁定在卷可參（見原審卷第38至40頁）\n      ，及經本院調取上開卷宗查明屬實，堪認系爭支付命令於\n      97年4月21日即已告確定，其猶執前詞，主張送達不合法\n      云云，洵無足取。是系爭執行程序所憑之執行名義即系爭\n      支付命令，核與確定判決有同一效力，揆諸上開說明，上\n      訴人依強制執行法第14條第2項提起債務人異議之訴，即\n      屬無據。\n  (二)上訴人依強制執行法第14條第1項規定提起債務人異議之訴\n    ，為無理由：\n    1.按執行名義成立後，如有消滅或妨礙債權人請求之事由發\n      生，債務人得於強制執行程序終結前，向執行法院對債權\n      人提起異議之訴，固為強制執行法第14條第1項所明定。\n      惟此須以其主張消滅或妨礙債權人請求之事由，係發生於\n      執行名義成立後者，始得為之，若其主張此項事由在執行\n      名義成立之前即已存在，則為執行名義之裁判縱有不當，\n      亦非異議之訴所能救濟（最高法院44年台上字第1472號判\n      例要旨參照）。\n    2.查本件上訴人所主張送達不合法、部分利息已罹於時效、\n      約定違約金計算比例過高等消滅或妨礙被上訴人請求之事\n      由，核均係在系爭支付命令確定前即執行名義成立前即已\n      存在。依照前開說明，亦不能謂上訴人得依強制執行法第\n      14條第1項之規定，提起債務人異議之訴，其聲請訊問證\n      人陳明慶證明於95年12月間即已搬離云云，即無必要。\n    3.上訴人固主張違約金部分於執行名義確定後亦有消滅或妨\n      礙被上訴人之事由發生（即違約金過高）云云，惟查兩造\n      就如何計算違約金之約定於借款當時即已成立，並經系爭\n      支付命令核准確定，上訴人此部分之主張尚不足採。又被\n      上訴人所請求之系爭利息債權，自84年11月28日至92年3\n      月5日止請求權已罹於民法第12 6條所規定之5年時效乙節\n      ，為被上訴人所不爭，其並就該部分已具狀向執行法院聲\n      請減縮金額，有聲請狀乙紙在卷可憑（見本院卷第28頁）\n      ，併此敘明。\n七、綜上所述，被上訴人主張為可採，上訴人所辯均無可取。從\n    而，上訴人依據強制執行法第14條第1、2項之規定，請求撤\n    銷系爭執行程序，為無理由，應予駁回。原審為上訴人敗訴\n    之判決，於法並無不合，上訴意旨指摘原判決不當，求予廢\n    棄改判，為無理由，應予駁回。\n八、本件事證已臻明確，兩造其餘攻擊或防禦方法，經審酌後認\n    與本件之結論無涉，爰不一一論述，併予敘明。\n九、據上論結，本件上訴為無理由，依民事訴訟法第449條第1項\n    、第78條、第85條第1項前段，判決如主文。"
  },
  "characters": {
    "judges": [
      "吳謙仁",
      "李瓊蔭",
      "黃莉雲"
    ],
    "prosecutors": [

    ],
    "lawyers": [
      "錢裕國",
      "有",
      "人或其他法定代理人具有"
    ],
    "clerks": [
      "魏汝萍"
    ],
    "plaintiffs": [

    ],
    "defendants": [

    ],
    "prosecutor_office": [

    ],
    "creditors": [

    ],
    "debtors": [

    ],
    "judicial_associate_officer": [

    ]
  },
  "adjudged_at": "2010-05-12",
  "created_at": "2016-01-05 11:56:19",
  "updated_at": "2016-01-05 11:56:19"
}