{
  "identify": "TPH-99-抗-7-20100105-1",
  "court": {
    "name": "臺灣高等法院",
    "code": "TPH"
  },
  "division": {
    "name": "刑事",
    "code": "M"
  },
  "year": 99,
  "word": "抗",
  "number": "7",
  "jcheck": "1",
  "reason": "聲請法官迴避",
  "content": "臺灣高等法院刑事裁定                     99年度抗字第7號\n抗  告  人\n即  被  告  甲○○\n選任辯護人  李明諭律師\n上列抗告人因聲請法官迴避案件，不服臺灣士林地方法院中華民\n國98年12月10日裁定（98年度聲字第2239號），提起抗告，本院\n裁定如下：\n    主  文\n抗告駁回。\n    理  由\n一、原裁定略以：抗告人即被告甲○○告訴案外人李志雄涉嫌侵\n    占案件（96年度易字第311 號，下稱甲案）與本案抗告人涉\n    犯之妨害自由、誣告、重利等罪案件（97年度訴字第803 號\n    ，下稱乙案），均由審判長蔡明宏審理，顯有偏頗之虞為由\n    ，聲請法官迴避。然上開二案件，係分屬不同案件，甲案李\n    志雄雖經原審判決無罪，惟乙案抗告人所涉妨害自由等罪，\n    仍須獨立踐行調查審理程序，以釐清事實真象，是審判長蔡\n    明宏固參與甲案之審理，然並不影響乙案抗告人訴訟上之權\n    益，且被告亦未提出審判長蔡明宏因參與甲案之審理，致使\n    其於乙案執行職務有偏頗之虞之客觀具體事證，其空言主張\n    ，自無可採。是本件聲請法官迴避，核無理由，應予駁回等\n    語。\n二、抗告意旨略以：依甲案原審於民國97年2 月27日審判筆錄第\n    12頁以下記載，審判長蔡明宏問甲○○「之前有無前科？」\n    ，甲○○稱「之前有重利罪前科，被判4個月」，顯見承辦\n    甲案審判長蔡明宏在甲案審理中，已對甲○○留有偏頗、負\n    面之印象；再者，甲案與乙案即使分屬不同案件，仍不失為\n    相牽連案件，審理結果亦互有影響之可能，且甲案李志雄獲\n    判無罪之理由，是否肇因於乙案審判長蔡明宏對甲○○之偏\n    頗印象，客觀上已足起疑，是其有刑事訴訟法第18條第2 款\n    「足認其執行職務有偏頗之虞者」之情形，審判長蔡明宏法\n    官應予迴避，爰依法提起抗告，以維抗告人訴訟上之權益云\n    云。\n三、本院認為：\n(一)按當事人聲請法官迴避，以有刑事訴訟法第18條第1、2款所\n    列情形之一者為限，亦即需法官有刑事訴訟法第17條各款所\n    列應自行迴避，不得執行職務之情形而不自行迴避，或除該\n    等情形以外，足認其執行職務有偏頗之虞者，當事人始得聲\n    請法官迴避。而刑事訴訟法第18條第2 款所謂足認其執行職\n    務有偏頗之虞者，係指以一般通常之人所具有之合理觀點，\n    對於該承辦法官是否為公平之裁判，均足產生懷疑；且此種\n    懷疑之發生，存有其客觀之原因，而非僅出諸當事人自己主\n    觀之判斷者，始足當之。若僅以空言攻訐，私意揣測，或對\n    法官之指揮訴訟或訊問方式不滿，均不得據為聲請之理由。\n    再當事人依刑事訴訟法第18條第2款規定聲請法官迴避，以\n    有具體事實足認其執行職務有偏頗之情形為限，所謂有偏頗\n    之虞，係指法官與訴訟關係具有故舊、恩怨等關係，其審判\n    恐有不公平者而言（最高法院19年抗字第285 號判例）。至\n    於訴訟上之指揮，乃專屬於法院之職權，當事人之主張、聲\n    請，在無礙於事實之確認以及法的解釋適用之範圍下，法院\n    固得斟酌其請求以為訴訟之進行，但仍不得以此對當事人之\n    有利與否，作為其將有不公平裁判之依據，更不得以此訴訟\n    之進行與否，乃謂有偏頗之虞，而聲請法官迴避（最高法院\n    79年臺抗字第318號著有判例）。\n(二)觀諸抗告人以甲案、乙案，二案件之審判長相同，然上開二\n    案件，犯罪事實不同，受命法官不同（建股、陸股），且甲\n    案，業經原審法院判決無罪確定而脫離原審繫屬，而乙案尚\n    於原審法院繫屬中，有甲案判決書、抗告人及李志雄本院前\n    案紀錄表各1 紙在卷可參，則乙案抗告人所涉妨害自由等罪\n    ，仍須依法踐行調查、審理程序，以求無枉無縱。是乙案之\n    審理，並不因同一審判長蔡明宏而影響抗告人訴訟上之權益\n    甚明。又抗告人在甲案以證人身分接受詰問，審判長蔡明宏\n    縱曾對之詢問有無前科，乃屬甲案法院指揮訴訟、調查證據\n    之職權內容之一，與乙案毫無干係。且一般法院承辦刑事案\n    件，為了解涉案被告是否該當累犯而須加重其刑，均依職權\n    調閱被告之本院前案紀錄表，故審判長蔡明宏在審理乙案時\n    ，容已知悉抗告人之前案紀錄，自不因在甲案審理時，詢問\n    抗告人之前科，而認審判長蔡明宏有偏頗之虞。再甲案件之\n    判斷與乙案之審理有何因審判長蔡明宏相同而相互影響之虞\n    ，亦未見抗告人釋明。是抗告人所舉前述抗告理由，純屬主\n    觀上對於法院訴訟指揮之臆斷。本件以一般通常之人所具有\n    之合理觀點，對於原審審判長蔡明宏能否為公平之裁判，並\n    無產生懷疑之可能，原裁定認抗告人所提迴避原因，與刑事\n    訴訟法第18條第2 款規定要件不符，而駁回其聲請，於法尚\n    無不合。抗告人猶執持前詞指摘原裁定不當，為無理由，應\n    予駁回。\n據上論斷，應依刑事訴訟法第412條，裁定如主文。\n中    華    民    國    99    年     1     月    5    日\n                  刑事第二庭審判長法  官  洪光燦\n                                  法  官  楊照男\n                                  法  官  李麗玲\n以上正本證明與原本無異。\n不得再抗告。\n                                  書記官  廖婷璇\n中    華    民    國    99    年     1    月    6    日\n",
  "structure": {
    "main": "抗告駁回。",
    "reason": "一、原裁定略以：抗告人即被告甲○○告訴案外人李志雄涉嫌侵\n    占案件（96年度易字第311 號，下稱甲案）與本案抗告人涉\n    犯之妨害自由、誣告、重利等罪案件（97年度訴字第803 號\n    ，下稱乙案），均由審判長蔡明宏審理，顯有偏頗之虞為由\n    ，聲請法官迴避。然上開二案件，係分屬不同案件，甲案李\n    志雄雖經原審判決無罪，惟乙案抗告人所涉妨害自由等罪，\n    仍須獨立踐行調查審理程序，以釐清事實真象，是審判長蔡\n    明宏固參與甲案之審理，然並不影響乙案抗告人訴訟上之權\n    益，且被告亦未提出審判長蔡明宏因參與甲案之審理，致使\n    其於乙案執行職務有偏頗之虞之客觀具體事證，其空言主張\n    ，自無可採。是本件聲請法官迴避，核無理由，應予駁回等\n    語。\n二、抗告意旨略以：依甲案原審於民國97年2 月27日審判筆錄第\n    12頁以下記載，審判長蔡明宏問甲○○「之前有無前科？」\n    ，甲○○稱「之前有重利罪前科，被判4個月」，顯見承辦\n    甲案審判長蔡明宏在甲案審理中，已對甲○○留有偏頗、負\n    面之印象；再者，甲案與乙案即使分屬不同案件，仍不失為\n    相牽連案件，審理結果亦互有影響之可能，且甲案李志雄獲\n    判無罪之理由，是否肇因於乙案審判長蔡明宏對甲○○之偏\n    頗印象，客觀上已足起疑，是其有刑事訴訟法第18條第2 款\n    「足認其執行職務有偏頗之虞者」之情形，審判長蔡明宏法\n    官應予迴避，爰依法提起抗告，以維抗告人訴訟上之權益云\n    云。\n三、本院認為：\n(一)按當事人聲請法官迴避，以有刑事訴訟法第18條第1、2款所\n    列情形之一者為限，亦即需法官有刑事訴訟法第17條各款所\n    列應自行迴避，不得執行職務之情形而不自行迴避，或除該\n    等情形以外，足認其執行職務有偏頗之虞者，當事人始得聲\n    請法官迴避。而刑事訴訟法第18條第2 款所謂足認其執行職\n    務有偏頗之虞者，係指以一般通常之人所具有之合理觀點，\n    對於該承辦法官是否為公平之裁判，均足產生懷疑；且此種\n    懷疑之發生，存有其客觀之原因，而非僅出諸當事人自己主\n    觀之判斷者，始足當之。若僅以空言攻訐，私意揣測，或對\n    法官之指揮訴訟或訊問方式不滿，均不得據為聲請之理由。\n    再當事人依刑事訴訟法第18條第2款規定聲請法官迴避，以\n    有具體事實足認其執行職務有偏頗之情形為限，所謂有偏頗\n    之虞，係指法官與訴訟關係具有故舊、恩怨等關係，其審判\n    恐有不公平者而言（最高法院19年抗字第285 號判例）。至\n    於訴訟上之指揮，乃專屬於法院之職權，當事人之主張、聲\n    請，在無礙於事實之確認以及法的解釋適用之範圍下，法院\n    固得斟酌其請求以為訴訟之進行，但仍不得以此對當事人之\n    有利與否，作為其將有不公平裁判之依據，更不得以此訴訟\n    之進行與否，乃謂有偏頗之虞，而聲請法官迴避（最高法院\n    79年臺抗字第318號著有判例）。\n(二)觀諸抗告人以甲案、乙案，二案件之審判長相同，然上開二\n    案件，犯罪事實不同，受命法官不同（建股、陸股），且甲\n    案，業經原審法院判決無罪確定而脫離原審繫屬，而乙案尚\n    於原審法院繫屬中，有甲案判決書、抗告人及李志雄本院前\n    案紀錄表各1 紙在卷可參，則乙案抗告人所涉妨害自由等罪\n    ，仍須依法踐行調查、審理程序，以求無枉無縱。是乙案之\n    審理，並不因同一審判長蔡明宏而影響抗告人訴訟上之權益\n    甚明。又抗告人在甲案以證人身分接受詰問，審判長蔡明宏\n    縱曾對之詢問有無前科，乃屬甲案法院指揮訴訟、調查證據\n    之職權內容之一，與乙案毫無干係。且一般法院承辦刑事案\n    件，為了解涉案被告是否該當累犯而須加重其刑，均依職權\n    調閱被告之本院前案紀錄表，故審判長蔡明宏在審理乙案時\n    ，容已知悉抗告人之前案紀錄，自不因在甲案審理時，詢問\n    抗告人之前科，而認審判長蔡明宏有偏頗之虞。再甲案件之\n    判斷與乙案之審理有何因審判長蔡明宏相同而相互影響之虞\n    ，亦未見抗告人釋明。是抗告人所舉前述抗告理由，純屬主\n    觀上對於法院訴訟指揮之臆斷。本件以一般通常之人所具有\n    之合理觀點，對於原審審判長蔡明宏能否為公平之裁判，並\n    無產生懷疑之可能，原裁定認抗告人所提迴避原因，與刑事\n    訴訟法第18條第2 款規定要件不符，而駁回其聲請，於法尚\n    無不合。抗告人猶執持前詞指摘原裁定不當，為無理由，應\n    予駁回。\n據上論斷，應依刑事訴訟法第412條，裁定如主文。"
  },
  "characters": {
    "judges": [
      "洪光燦",
      "楊照男",
      "李麗玲"
    ],
    "prosecutors": [

    ],
    "lawyers": [
      "李明諭"
    ],
    "clerks": [
      "廖婷璇"
    ],
    "plaintiffs": [

    ],
    "defendants": [
      "甲"
    ],
    "prosecutor_office": [

    ],
    "creditors": [

    ],
    "debtors": [

    ],
    "judicial_associate_officer": [

    ]
  },
  "adjudged_at": "2010-01-05",
  "created_at": "2016-01-05 15:00:55",
  "updated_at": "2016-01-05 15:00:55"
}