{
  "identify": "TPH-99-聲-1269-20100512-1",
  "court": {
    "name": "臺灣高等法院",
    "code": "TPH"
  },
  "division": {
    "name": "刑事",
    "code": "M"
  },
  "year": 99,
  "word": "聲",
  "number": "1269",
  "jcheck": "1",
  "reason": "保護管束",
  "content": "臺灣高等法院刑事裁定                  99年度聲字第1269號\n聲  請  人  臺灣高等法院檢察署檢察官\n受  刑  人  甲○○\n上列受刑人因營利姦淫猥褻罪案件，聲請人聲請付保護管束（99\n年度執聲付字第322號），本院裁定如下：\n    主  文\n甲○○假釋中付保護管束。\n    理  由\n一、聲請意旨略以：受刑人甲○○因營利姦淫猥褻罪案件，經本\n    院以96年度上更(二)字第339號判處有期徒刑1年6月，另犯貪\n    污治罪條例罪經本院97年度重上更(三)字第146號判處有期徒\n    刑1年，禠奪公權1年確定。二案並經本院98年度聲字第1199\n    號定其應執行之刑為有期徒刑2年2月。受刑人於民國97年9\n    月30日送監執行，茲聲請人以受刑人業經法務部於99年5月3\n    日核准假釋，爰依刑法第93條第2項規定，聲請於其假釋中\n    付保護管束等語。\n二、按刑法第96條有關保護管束之規定，於94年2月2日修正公布\n    ，95年7月1日施行，修正前、後之文字用語雖略有不同，修\n    正前規定：「保安處分於裁判時併宣告之。但因假釋或於刑\n    之赦免後，付保安處分者，不在此限。」修正後則規定：「\n    保安處分於裁判時併宣告之。但本法或其他法律另有規定者\n    ，不在此限。」然依其修正理由，上開文字之修訂並非排除\n    假釋期間付保護管束之宣告。復參以刑法第93條第2項「假\n    釋出獄者，在假釋中付保護管束」之規定，無論於修正前、\n    後，其文字俱未變動。是以上開條文用語之修正不生刑罰法\n    律效果之差異，即非刑罰科刑規範之變更，自不生新舊法律\n    比較適用之問題，依法律一般適用原則，本件自應適用現行\n    有效之法律規定以為裁定。\n三、經查：受刑人甲○○前因營利姦淫猥褻罪及貪污治罪條例罪\n    等案件，分別判處有期徒刑1年6月、1年，並定其應執行刑\n    為2年2月。其於97年9月30日送監執行，刑期終結日期為99\n    年11月29日，縮短刑期後刑期終結日為99年10月14日。茲受\n    刑人上開徒刑之執行，業經法務部於99年5月3日以法矯司字\n    第0990905867號函核准假釋。本院審核上開文件後，認受刑\n    人經假釋在案，應在假釋中付保護管束，聲請人之聲請為正\n    當，應予准許。\n四、據上論斷，應依刑事訴訟法第481條第1項、刑法第93條第2\n    項，裁定如主文。\n中    華    民    國    99    年    5     月    12    日\n                  刑事第二十二庭審判長法  官  郭雅美\n                                      法  官  李麗珠\n                                      法  官  洪于智\n以上正本證明與原本無異。\n如不服本裁定，應於收受送達後五日內向本院提出抗告狀。\n                                      書記官  強梅芳\n中    華    民    國    99    年    5     月    12    日",
  "structure": {
    "main": "甲○○假釋中付保護管束。",
    "reason": "一、聲請意旨略以：受刑人甲○○因營利姦淫猥褻罪案件，經本\n    院以96年度上更(二)字第339號判處有期徒刑1年6月，另犯貪\n    污治罪條例罪經本院97年度重上更(三)字第146號判處有期徒\n    刑1年，禠奪公權1年確定。二案並經本院98年度聲字第1199\n    號定其應執行之刑為有期徒刑2年2月。受刑人於民國97年9\n    月30日送監執行，茲聲請人以受刑人業經法務部於99年5月3\n    日核准假釋，爰依刑法第93條第2項規定，聲請於其假釋中\n    付保護管束等語。\n二、按刑法第96條有關保護管束之規定，於94年2月2日修正公布\n    ，95年7月1日施行，修正前、後之文字用語雖略有不同，修\n    正前規定：「保安處分於裁判時併宣告之。但因假釋或於刑\n    之赦免後，付保安處分者，不在此限。」修正後則規定：「\n    保安處分於裁判時併宣告之。但本法或其他法律另有規定者\n    ，不在此限。」然依其修正理由，上開文字之修訂並非排除\n    假釋期間付保護管束之宣告。復參以刑法第93條第2項「假\n    釋出獄者，在假釋中付保護管束」之規定，無論於修正前、\n    後，其文字俱未變動。是以上開條文用語之修正不生刑罰法\n    律效果之差異，即非刑罰科刑規範之變更，自不生新舊法律\n    比較適用之問題，依法律一般適用原則，本件自應適用現行\n    有效之法律規定以為裁定。\n三、經查：受刑人甲○○前因營利姦淫猥褻罪及貪污治罪條例罪\n    等案件，分別判處有期徒刑1年6月、1年，並定其應執行刑\n    為2年2月。其於97年9月30日送監執行，刑期終結日期為99\n    年11月29日，縮短刑期後刑期終結日為99年10月14日。茲受\n    刑人上開徒刑之執行，業經法務部於99年5月3日以法矯司字\n    第0990905867號函核准假釋。本院審核上開文件後，認受刑\n    人經假釋在案，應在假釋中付保護管束，聲請人之聲請為正\n    當，應予准許。\n四、據上論斷，應依刑事訴訟法第481條第1項、刑法第93條第2\n    項，裁定如主文。"
  },
  "characters": {
    "judges": [
      "郭雅美",
      "李麗珠",
      "洪于智"
    ],
    "prosecutors": [

    ],
    "lawyers": [

    ],
    "clerks": [
      "強梅芳"
    ],
    "plaintiffs": [

    ],
    "defendants": [

    ],
    "prosecutor_office": [
      "臺灣高等法院檢察署檢察官"
    ],
    "creditors": [

    ],
    "debtors": [

    ],
    "judicial_associate_officer": [

    ]
  },
  "adjudged_at": "2010-05-12",
  "created_at": "2016-01-05 11:52:21",
  "updated_at": "2016-01-05 11:52:21"
}