{
  "identify": "TPH-98-重上-39-20100105-1",
  "court": {
    "name": "臺灣高等法院",
    "code": "TPH"
  },
  "division": {
    "name": "民事",
    "code": "V"
  },
  "year": 98,
  "word": "重上",
  "number": "39",
  "jcheck": "1",
  "reason": "損害賠償等",
  "content": "臺灣高等法院民事判決                  98年度重上字第39號\n上  訴  人  澳商聯盛國際企業股份有限公司台灣分公司\n法定代理人  乙○○\n訴訟代理人  陳彥希律師\n            林哲誠律師\n上  訴  人  國立故宮博物院\n法定代理人  甲○○\n訴訟代理人  陳井星律師\n            謝進益律師\n上列當事人間請求損害賠償等事件，兩造對於中華民國97年11月\n28日臺灣士林地方法院96年度重訴字第16號第一審判決各自提起\n上訴，經本院於98年12月15日言詞辯論終結，玆判決如下：\n    主      文\n原判決關於命國立故宮博物院給付及假執行宣告，並訴訟費用之\n裁判，均廢棄。\n上開廢棄部分，澳商聯盛國際企業股份有限公司台灣分公司於第\n一審之訴及假執行之聲請，均駁回。\n澳商聯盛國際企業股份有限公司台灣分公司之上訴駁回。\n第一、二審訴訟費用，由澳商聯盛國際企業股份有限公司台灣分\n公司負擔。\n    事實及理由\n一、澳商聯盛國際企業股份有限公司台灣分公司（下稱聯盛公司\n    ）法定代理人原為牧漢龍，於民國98年2月19日變更為乙○\n    ○，有聯盛公司變更登記表在卷可稽（見本院卷，71頁），\n    經其以書狀聲明承受訴訟（見本院卷，70頁），核無不合，\n    應予准許。\n二、聯盛公司主張：伊於94年3月間參加國立故宮博物院（下稱\n    故宮博物院）「國立故宮博物院南部院區新建工程委託專案\n    管理服務案」（下稱系爭專案）之招標，並於同年4月7日經\n    故宮博物院召開評選委員會議通過資格審查，且經故宮博物\n    院公開評審為系爭專案最優廠商。兩造於同年9月27日完成\n    議價，同年10月7日簽訂「國立故宮博物院南部院區新建工\n    程委託專案管理服務案契約書」（下稱系爭契約），約定契\n    約總價為新台幣（下同）1億7950萬元（含稅），故宮博物\n    院並於94年10月18日刊登決標公告。惟另一投標廠商即訴外\n    人美商誠國際股份有限公司於94年10月間向行政院公共工\n    程委員會提起採購申訴案，請求撤銷故宮博物院就系爭專案\n    所為之採購決定，經行政院公共工程委員會採購申訴審議委\n    員會於95年5月5日第178次委員會議決議撤銷系爭專案之決\n    標採購決定（下稱系爭審議判斷），伊因未獲通知而無從參\n    與上開採購申訴程序，亦無從對之提起行政救濟。詎故宮博\n    物院竟於95年5月22日以伊違反政府採購法（下稱採購法）\n    第50條規定為由，發函通知伊依系爭契約第14條第(一)項第2\n    款規定解除系爭契約，並要求伊停止系爭契約工作及於同年\n    月31日前移交工作成果，兩造嗣於同年月30日就解約相關問\n    題進行第一次協商時，故宮博物院就應賠償伊損害部分並無\n    異議，僅要求伊結算至同年5月31日之服務費及相關費用並\n    提出詳細計算資料，甚且於兩造同年9月22日進行第二次協\n    商時，故宮博物院仍表示伊事實上已提供服務並移交服務成\n    果，其均會給付合理費用等語，並要求伊補充薪資結構、開\n    銷憑證等資料。伊遂於同年10月1日將系爭專案之工作成果\n    全數移交予故宮博物院，其中包含系爭專案時程綱要進度表\n    、品質管理計畫、設計審查制度、相關作業標準程序及專案\n    資訊管理與檔案管理系統，及設計審查成果等。又伊已依系\n    爭契約第2條第(二)項第2款之約定於系爭契約生效後2週內將\n    執行服務計畫書交付予故宮博物院，故宮博物院自應依系爭\n    契約第5條第(二)項之約定給付價金，惟經伊催告，故宮博物\n    院始終拖延拒絕給付，應負遲延責任，伊自得終止系爭契約\n    ，並請求損害賠償，爰以起訴狀繕本之送達為終止系爭契約\n    之意思表示等情，先位依民法第263條、第260條、第511條\n    、第507條規定，備位依系爭契約第5條第(一)項2.及損害賠償\n    之約定，求為判決命故宮博物院給付伊5333萬9450元暨如原\n    判決附表二所示各期應付款日起至清償日止，按週年利率百\n    分之五計算之利息。（原審准予聯盛公司備位部分4008萬\n    8333元之請求，另准予故宮博物院以受行政院環境保護署罰\n    鍰之30萬元為抵銷之主張，判命故宮博物院應給付聯盛公司\n    3978萬元8333元及如原判決附表一所示之利息，駁回聯盛公\n    司其餘請求）並對於原判決不利部分提起上訴，聲明：(一)原\n    判決不利於聯盛公司部分廢棄。(二)上廢棄部分，故宮博物院\n    應再給付聯盛公司1355萬1117元暨自95年5月31日起至清償\n    之日止，按年息百分之五計算之利息。另對於故宮博物院之\n    上訴，答辯聲明：上訴駁回。\n三、故宮博物院則以：系爭契約因違反「機關委託技術服務廠商\n    評選及計費辦法」（下稱技術服務辦法）第3條及工程技術\n    顧問管理條例第8條第3項等規定，當然無效，縱非無效，伊\n    依採購法第50條之規定，亦直接取得系爭契約之終止權及解\n    除權，且系爭審議判斷係依據採購法第50條第1項、第2項規\n    定，撤銷伊就系爭專案所做成之原採購決定，並認應撤銷決\n    標，聯盛公司雖未參加該申訴審議程序，惟其於得知上開判\n    斷結果後，未依行政訴訟法第106條第1項之規定提起撤銷訴\n    訟，該申訴審議判斷即告確定，應受系爭審議判斷之拘束，\n    伊自應遵循該確定申訴審議判斷之意旨解除系爭契約，伊已\n    於95年5月22日以台博祕字第0950003533號函為行使系爭契\n    約解除權之意思表示，系爭契約自已解除而失其效力。縱認\n    伊不得解除系爭契約，因聯盛公司所為終止系爭契約之意思\n    表示亦不合法，爰再依系爭契約第14條第(一)項第2款之約定\n    ，以98年3月25日所提爭點整理狀為終止系爭契約之意思表\n    示。系爭專案相關承辦人員因涉違反貪污治罪條例等案件，\n    經臺灣士林地方法院檢察署檢察官提起公訴在案，則依系爭\n    契約第14條第(一)項約定及採購法第50條第1項、第2項規定，\n    伊以聯盛公司之行為有影響採購公正之情形而解除系爭契約\n    ，自不需負損害賠償責任。再依系爭契約第2條第(二)項第2款\n    之約定，聯盛公司執行系爭專案之各項工作，須待伊審定執\n    行服務計畫書後始得辦理其他後續工作，聯盛公司於執行服\n    務計畫書未經伊審定前即自行作業，其所生費用自不得要求\n    伊賠償，且聯盛公司未就其請求之金額舉證以實其說，其請\n    求伊賠償損害，並不合理。系爭契約因違反前揭效力規定而\n    無效，縱非無效，系爭契約已經伊解除，上訴人聯盛公司亦\n    不得依系爭契約之約定請求伊給付報酬。而上訴人聯盛公司\n    亦有違反機關委託技術服務廠商評選及計費辦法第3條及工\n    程技術顧問管理條例第8條第3項、系爭專案投標須知第13條\n    及第40條等規定之情形，依系爭契約第5條第(一)項第3款第(5)\n    點之約定，亦不得請求給付報酬。又依系爭契約第5條第(一)\n    項第2款第(1)點約定，聯盛公司於伊審定執行服務計畫書及\n    各期報告前，不得請求伊給付契約價金，而其所提出之專案\n    作業程序執行手冊與專案整體進度表等文件尚未經伊審定，\n    其逕自進行後階段工作，而伊於解除系爭契約後，另行透過\n    招標程序與訴外人中興工程顧問股份有限公司（下稱中興工\n    程公司）就系爭專案締結管理服務契約，聯盛公司逕自進行\n    之後階段工作，對伊並無實益，其依民法第512條第2項之規\n    定請求伊給付報酬，不足憑採。縱認聯盛公司得請求伊給付\n    報酬，應先扣除系爭契約第5條第(一)項第2款第(1)點約定中之\n    首期預付款額度，始為合理，否則即為無法律上之原因而受\n    有利益。另聯盛公司於系爭契約有效期間內實際履約期間至\n    多為7個月，應提出該期間內實際履約之人力支出時數表以\n    為證明。若認聯盛公司之請求有理由，聯盛公司未盡善良管\n    理人之責任，致伊未能及時辦理環境監測之採購案，違反環\n    保法規而遭行政院環境保護署處以30萬元之罰鍰，依系爭契\n    約第12條第(八)項之約定及民法第227條、第544條及第495條\n    等規定，應由聯盛公司負賠償責任，伊得以上開額外支出之\n    罰鍰30萬元主張抵銷等語，資為抗辯。並對於原判決不利部\n    分提起上訴，聲明：(一)原判決不利於故宮博物院部分廢棄。\n    (二)上廢棄部分，聯盛公司在第一審之訴及假執行之聲請均駁\n    回。另對於聯盛公司之上訴，答辯聲明：上訴駁回。\n四、兩造不爭執之事項：\n  (一)故宮博物院就系爭專案，於94年4月7日召開評選委員會，通\n    過聯盛公司資格審查，且公開評審聯盛公司為系爭專案最優\n    廠商。兩造於94年9月27日完成議價，並於同年10月27日締\n    結「國立故宮博物院南部院區新建工程委託專案管理服務案\n    契約書」（即系爭契約），約定契約總價為1億7950萬元（\n    含稅）。\n  (二)聯盛公司於94年10月31日送交系爭專案「執行服務計畫書」\n    予故宮博物院，並請求故宮博物院給付系爭契約總額之10%\n    服務費用共計1795萬元（見原審卷(一)，309至311頁）。\n  (三)聯盛公司分別於95年3月17日、同年4月18日，將第1季、第2\n    季報告交付予故宮博物院，並請求故宮博物院支付價款各80\n    7萬7500元。聯盛公司並已交付第3季報告予故宮博物院（見\n    本院卷，164頁反面）。\n  (四)故宮博物院就系爭專案之採購決定嗣遭行政院公共工程委員\n    會於95年5月5日以訴字第940418號採購申訴審議判斷書予以\n    撤銷。\n  (五)故宮博物院於95年5月22日以台博祕字第0950003533號函通\n    知聯盛公司表示依系爭契約第14條第(一)款第2點之約定解除\n    系爭契約，並請聯盛公司依系爭契約第14條第(三)款第1點規\n    定，將工作成果於同年月31日前移交予之。\n  (六)聯盛公司於95年6月1日將系爭專案工作成果（含系爭專案結\n    案報告書及移交清單各3份、工作成果移交檔案資料計7箱，\n    內容共計46冊）移交予故宮博物院，並經上訴人故宮博物院\n    簽收。\n  (七)故宮博物院因未持續執行系爭專案環境監測計畫而於95年10\n    月24日遭行政院環境保護署以違反環境影響評估法第17條規\n    定為由，依同法第23條第1項第1款規定裁處30萬元之罰鍰。\n  (八)聯盛公司於95年12月12日催告故宮博物院給付契約總價10%\n    之款項，否則將終止系爭契約，嗣依系爭契約第14條第8款\n    之約定，以本件起訴狀繕本之送達（96年1月12日）為終止\n    系爭契約之意思表示（見原審卷(一)，11頁，本院卷，209頁\n    ）。\n  (九)故宮博物院迄今未曾因兩造間系爭契約之法律關係支付聯盛\n    公司任何款項。\n  (十)兩造就系爭契約性質為承攬契約，且未因兩造合意而解除或\n    終止（見本院卷，99頁反面及164頁反面）。\n五、玆就兩造爭執之事項，分別判斷如下：\n  (一)關於系爭契約是否自始無效：就此，故宮博物院主張系爭契\n    約違反技術服務辦法第3條規定及工程技術顧問管理條例第8\n    條第3項規定而無效，聯盛公司則主張前開規定均僅取締規\n    定而非強制規定，系爭契約縱有違反，亦非無效。查技術服\n    務辦法係依據採購法第22條所頒布，依該條第1項第9款規定\n    ：「機關辦理公告金額以上之採購，符合下列情形之一者，\n    得採限制性招標：．．九、委託專業服務、技術服務或資訊\n    服務，經公開客觀評選為優勝者。」第2項規定：「前項第9\n    款之廠商評選辦法與服務費用計算方式，由主管機關定之。\n    」可知依該條第1項第9款委託專業服務、技術服務或資訊服\n    務，為公開客觀評選，僅為得採限制性招標之一要件，並非\n    強制所有限制性採購案均應依此方式辦理。又主管機關依該\n    條第2項所頒訂之技術服務辦法第3條規定：「本辦法所稱技\n    術服務，指建築師事務所、技師事務所、技術顧問機構及其\n    他依法令得提供技術性服務之自然人或法人所提供之規劃、\n    設計、監造或管理等服務。」亦未強制所有限制性採購契約\n    ，均應委託該條所之自然人或法人為規劃、設計、監造或管\n    理等服務，是技術服務辦法第3條規定，顯非民法第71條所\n    稱之強制或禁止規定。至於工程技術顧問公司管理條例第3\n    條規定：「本條例所稱工程技術顧問公司，指從事在地面上\n    下新建、增建、改建、修建、拆除構造物與其所屬設備、改\n    變自然環境之行為及其他經主管機關認定工程之技術服務事\n    項，包括規劃與可行性研究、基本設計、細部設計、協辦招\n    標與決標、施工監造、專案管理及其相關技術性服務之公司\n    。」第8條第3項規定：「外國公司於我國從事第三條所定業\n    務者，應經主管機關許可，及經公司登記主管機關認許及辦\n    理分公司登記，並於領得主管機關核發之工程技術顧問公司\n    登記證及加入全國商業同業公會或地方同業公會後，始得營\n    業。」參照同法第32條規定，違反者僅主管機關得限期改善\n    、罰鍰、警告，可知為行政管理之取締規定，非強制規定，\n    難認違反該條規定所訂立之契約為無效。\n  (二)關於系爭契約是否因撤銷決標、終止或解除而不存在部分：\n    就此，聯盛公司主張：系爭契約不因行政院公共工程委員會\n    決議撤銷決標而自始無效，故宮博物院於95年5月22日所為\n    解除系爭契約之意思表示，並不合法。其因故宮博物院給付\n    遲延而發函催告故宮博物院於5日內給付，故宮博物院仍未\n    給付，爰以本件起訴狀繕本之送達為伊終止系爭契約之意思\n    表示等語。故宮博物院則辯稱：系爭契約因違反技術服務辦\n    法第3條及工程顧問管理條例第8條第3項等效力規定，當然\n    無效。縱認系爭契約有效，因系爭專案之採購決定已經系爭\n    審議判斷撤銷，故宮博物院自得依該判斷結果解除系爭契約\n    或依系爭契約第14條第(一)項第2款之約定終止系爭契約等語\n    。分述如下：\n  1.聯盛公司得標後，另一投標廠商即訴外人美商誠國際股份\n    有限公司於94年10月間向行政院公共工程委員會提起採購申\n    訴案，請求撤銷故宮博物院就系爭專案所為之採購決定，經\n    系爭審議判斷認定：依技術服務辦法第3條規定：「本辦法\n    所稱技術服務，指建築師事務所、技師事務所、技術顧問機\n    構及其他依法令得提供技術性服務之自然人或法人所提供之\n    規劃、設計、監造或管理等服務。」而故宮博物院於94年3\n    月1日更正招標公告時，放寬增加「其他具有本採購專業技\n    術及人力資格需求之單位組成團隊。」亦得參與投標，而聯\n    盛公司雖已為公司登記，但依其登記營業項目，並無工程技\n    術顧問項目，不符合技術服務辦法所規定之投標資格。又系\n    爭專案所採之限制性招標公告中，其採協商措施之欄位規定\n    為「否」，然而故宮博物院於94年8月19日議約會前會議事\n    項紀錄，其中決議事項1、3、4、9等項均提及故宮博物院要\n    求聯盛公司更改或修正原投標文件內容，顯已違反採購法第\n    57條規定：「機關依前二條之規定採行協商措施者，應依下\n    列原則辦理︰．．二、協商時應平等對待所有合於招標文件\n    規定之投標廠商，必要時並錄影或錄音存證。三、原招標文\n    件已標示得更改項目之內容，始得納入協商。．．」之協商\n    應遵循之原則等事實，因而為撤銷系爭專案之決標採購決定\n    ，有系爭審議判斷附卷可稽，且為兩造所不爭（見原審卷(一)\n    ，165頁以下），堪信為真實。\n  2.按關於招標、審標、決標爭議之審議判斷視同訴願決定，政\n    府採購法第83條定有明文，據此，政府機關之招標、審標、\n    決標行為均係行政處分。如行政處分確係有效存在，雖內容\n    有不當或違法，而其爭訟在行政法院未依行政訴訟程序撤銷\n    以前，民事法院亦不能否認其效力。聯盛公司固非系爭審議\n    判斷之當事人，仍為利害關係人，倘對系爭審議判斷不服，\n    依司法院院字第1430號解釋之意旨，得於知悉後在法定期間\n    內提起行政爭訟，然被上訴人未提起之，要非不應受系爭審\n    議判斷之拘束（最高法院95年度台上字第1468號判決參照）\n    。系爭專案之決標既經系爭審議判斷認定明顯違反法令，且\n    屬違法情節重大而撤銷決標，而聯盛公司於接獲通知後並未\n    提起行政訴訟救濟，依前開說明，自應受系爭審議判斷之拘\n    束。\n  3.按採購法就行政機關依同法規定撤銷決標者，對於已簽立之\n    採購契約，有何影響，固未直接明文。然同法第50條第2項\n    既規定，投標廠商有該條第1項所列情形之一，經機關於開\n    標前發現者，其所投之標應不予開標；於開標後發現者，應\n    不決標予該廠商，決標或簽約後發現得標廠商於決標前有前\n    項情形者，應撤銷決標、終止契約或解除契約，並得追償損\n    失。但撤銷決標、終止契約或解除契約反不符公共利益，並\n    經上級機關核准者，不在此限，可知撤銷決標與終止契約、\n    解除契約，均為使契約關係消滅之獨立原因，一旦為撤銷決\n    標、終止契約或解除契約中任一行為，契約關係即消滅無再\n    為其他二行為之必要。又採購程序通常流程為招標、投標、\n    開標、審標、決標、簽約、履約，故一旦撤銷決標，應視同\n    自始未決標，若撤銷決標時尚未簽約者，即不能進入簽約程\n    序，若已簽約，亦應認為欠缺簽約前提之決標程序，而有終\n    止或解除之原因。此非唯由採購法第50條第2項文字將撤銷\n    決標與終止、解除對照於決標後與簽約後之不同效果，應為\n    如此解釋，即觀諸同法第74條之立法理由謂：「政府採購行\n    為一向被認定係私經濟行為，廠商與機關之間如有爭議，本\n    應循民事程序途徑解決，惟因廠商於招標、審標、決標階段\n    ，與機關並無契約關係，難有可供訴訟提起之訴因，故為增\n    加廠商之救濟及保護，並兼顧政府採購之時效性需求，爰參\n    酌政府採購協定第二十條之規定，訂定異議及申訴程序。」\n    等語，亦見立法意旨係以決標為契約成立之前置行政程序。\n    再由同法第85條第1項規定：「審議判斷指明原採購行為違\n    反法令者，招標機關應另為適法之處置。」第3項規定：「\n    第一項情形，廠商得向招標機關請求償付其準備投標、異議\n    及申訴所支出之必要費用。」益知決標經審議判斷應予撤銷\n    時，廠商僅得向招標機關請求償付其準備投標、異議及申訴\n    所支出之必要費用，非得基於契約而有所請求（請求履行契\n    約或債務不履行之損害賠償）。如已簽立採購契約後，決標\n    經撤銷者，採購單位即依採購法第50條第2項規定，取得終\n    止或解除契約權利。\n  4.系爭契約既經系爭審議判斷撤銷決標確定，依前開說明，應\n    認故宮博物院已取得終止或解除系爭契約權利，故其於95年\n    5月22日據系爭審議判斷，依系爭契約第14條第(一)款2.所約\n    定：「有採購法第50條第2項前段規定之情形。」對聯盛公\n    司所為解除契約之意思表示，即非無據。又系爭契約關係既\n    因解除而消滅，則聯盛公司即無再以起訴狀為終止系爭契約\n    之餘地。\n  (三)關於聯盛公司請求有無理由部分：按系爭契約經上級行政機\n    關撤銷決標後，故宮博物院進而據以解除致系爭契約關係消\n    滅，已如前述，且依系爭契約第14條第(一)款規定，故宮博物\n    院不必補償聯盛公司因此所生之損失，則聯盛公司先位依民\n    法第263條、第260條、第511條、第507條規定，備位依系爭\n    契約第5條第(一)項2.及損害賠償之約定，求為判決命故宮博\n    物院給付伊5333萬9450元暨如原判決附表二所示各期應付款\n    日起至清償日止，按週年利率百分之五計算之利息，均非可\n    採。至於聯盛公司因準備投標所支出之費用，僅得依採購法\n    第85條第3項規定，循行政訴訟程序以資解決，併予敘明（\n    最高法院94年度台上字第1792號判決參照）。\n  (四)關於故宮博物院抵銷抗辯部分：聯盛公司之請求既無理由，\n    本院自不必就此予以判斷。\n六、據上論結，聯盛公司先位依民法第263條、第260條、第511\n    條、第507條規定，備位依系爭契約第5條第(一)項2.及損害賠\n    償之約定，求為判決命故宮博物院給付伊5333萬9450元暨如\n    原判決附表二所示各期應付款日起至清償日止，按週年利率\n    百分之五計算之利息，均無理由，不應准許。原審判命故宮\n    博物院給付3978萬8333元及如原判決附表一所示利息，並為\n    假執行宣告，尚有未洽，故宮博物院上訴意旨指摘原判決此\n    部分不當，求予廢棄改判，為有理由，應由本院將原判決此\n    部分廢棄，並駁回聯盛公司於第一審之訴及假執行之聲請。\n    至於原審駁回聯盛公司其餘之訴及假執行聲請，則無不合，\n    聯盛公司上訴指摘原判決此部分不當，聲明廢棄，為無理由\n    ，應駁回其上訴。\n七、據上論結，故宮博物院上訴為有理由，聯盛公司上訴為無理\n    由。依民事訴訟法第450條、第449條第1項、第78條，判決\n    如主文。\n中    華    民    國     99    年    1    月     5    日\n                     民事第七庭\n                         審判長法  官  鄭三源\n                               法  官  魏麗娟\n                               法  官  呂太郎\n正本係照原本作成。\n聯盛公司如不服本判決，應於收受送達後20日內向本院提出上訴\n書狀，其未表明上訴理由者，應於提出上訴後20日內向本院補提\n理由書狀（均須按他造當事人之人數附繕本）上訴時應提出委任\n律師或具有律師資格之人之委任狀；委任有律師資格者，另應附\n具律師資格證書及釋明委任人與受任人有民事訴訟法第466條之1\n第1項但書或第2項（詳附註）所定關係之釋明文書影本。\n中    華    民    國    99    年    1     月    6     日\n                              書記官  黃千鶴\n附註：\n民事訴訟法第466條之1（第1項、第2項）：\n對於第二審判決上訴，上訴人應委任律師為訴訟代理人。但上訴\n人或其他法定代理人具有律師資格者，不在此限。\n上訴人之配偶、三親等內之血親、二親等內之姻親，或上訴人為\n法人、中央或地方機關時，其所屬專任人員具有律師資格並經法\n院認為適當者，亦得為第三審訴訟代理人。",
  "structure": {
    "main": "原判決關於命國立故宮博物院給付及假執行宣告，並訴訟費用之\n裁判，均廢棄。\n上開廢棄部分，澳商聯盛國際企業股份有限公司台灣分公司於第\n一審之訴及假執行之聲請，均駁回。\n澳商聯盛國際企業股份有限公司台灣分公司之上訴駁回。\n第一、二審訴訟費用，由澳商聯盛國際企業股份有限公司台灣分\n公司負擔。",
    "fact": "一、澳商聯盛國際企業股份有限公司台灣分公司（下稱聯盛公司\n    ）法定代理人原為牧漢龍，於民國98年2月19日變更為乙○\n    ○，有聯盛公司變更登記表在卷可稽（見本院卷，71頁），\n    經其以書狀聲明承受訴訟（見本院卷，70頁），核無不合，\n    應予准許。\n二、聯盛公司主張：伊於94年3月間參加國立故宮博物院（下稱\n    故宮博物院）「國立故宮博物院南部院區新建工程委託專案\n    管理服務案」（下稱系爭專案）之招標，並於同年4月7日經\n    故宮博物院召開評選委員會議通過資格審查，且經故宮博物\n    院公開評審為系爭專案最優廠商。兩造於同年9月27日完成\n    議價，同年10月7日簽訂「國立故宮博物院南部院區新建工\n    程委託專案管理服務案契約書」（下稱系爭契約），約定契\n    約總價為新台幣（下同）1億7950萬元（含稅），故宮博物\n    院並於94年10月18日刊登決標公告。惟另一投標廠商即訴外\n    人美商誠國際股份有限公司於94年10月間向行政院公共工\n    程委員會提起採購申訴案，請求撤銷故宮博物院就系爭專案\n    所為之採購決定，經行政院公共工程委員會採購申訴審議委\n    員會於95年5月5日第178次委員會議決議撤銷系爭專案之決\n    標採購決定（下稱系爭審議判斷），伊因未獲通知而無從參\n    與上開採購申訴程序，亦無從對之提起行政救濟。詎故宮博\n    物院竟於95年5月22日以伊違反政府採購法（下稱採購法）\n    第50條規定為由，發函通知伊依系爭契約第14條第(一)項第2\n    款規定解除系爭契約，並要求伊停止系爭契約工作及於同年\n    月31日前移交工作成果，兩造嗣於同年月30日就解約相關問\n    題進行第一次協商時，故宮博物院就應賠償伊損害部分並無\n    異議，僅要求伊結算至同年5月31日之服務費及相關費用並\n    提出詳細計算資料，甚且於兩造同年9月22日進行第二次協\n    商時，故宮博物院仍表示伊事實上已提供服務並移交服務成\n    果，其均會給付合理費用等語，並要求伊補充薪資結構、開\n    銷憑證等資料。伊遂於同年10月1日將系爭專案之工作成果\n    全數移交予故宮博物院，其中包含系爭專案時程綱要進度表\n    、品質管理計畫、設計審查制度、相關作業標準程序及專案\n    資訊管理與檔案管理系統，及設計審查成果等。又伊已依系\n    爭契約第2條第(二)項第2款之約定於系爭契約生效後2週內將\n    執行服務計畫書交付予故宮博物院，故宮博物院自應依系爭\n    契約第5條第(二)項之約定給付價金，惟經伊催告，故宮博物\n    院始終拖延拒絕給付，應負遲延責任，伊自得終止系爭契約\n    ，並請求損害賠償，爰以起訴狀繕本之送達為終止系爭契約\n    之意思表示等情，先位依民法第263條、第260條、第511條\n    、第507條規定，備位依系爭契約第5條第(一)項2.及損害賠償\n    之約定，求為判決命故宮博物院給付伊5333萬9450元暨如原\n    判決附表二所示各期應付款日起至清償日止，按週年利率百\n    分之五計算之利息。（原審准予聯盛公司備位部分4008萬\n    8333元之請求，另准予故宮博物院以受行政院環境保護署罰\n    鍰之30萬元為抵銷之主張，判命故宮博物院應給付聯盛公司\n    3978萬元8333元及如原判決附表一所示之利息，駁回聯盛公\n    司其餘請求）並對於原判決不利部分提起上訴，聲明：(一)原\n    判決不利於聯盛公司部分廢棄。(二)上廢棄部分，故宮博物院\n    應再給付聯盛公司1355萬1117元暨自95年5月31日起至清償\n    之日止，按年息百分之五計算之利息。另對於故宮博物院之\n    上訴，答辯聲明：上訴駁回。\n三、故宮博物院則以：系爭契約因違反「機關委託技術服務廠商\n    評選及計費辦法」（下稱技術服務辦法）第3條及工程技術\n    顧問管理條例第8條第3項等規定，當然無效，縱非無效，伊\n    依採購法第50條之規定，亦直接取得系爭契約之終止權及解\n    除權，且系爭審議判斷係依據採購法第50條第1項、第2項規\n    定，撤銷伊就系爭專案所做成之原採購決定，並認應撤銷決\n    標，聯盛公司雖未參加該申訴審議程序，惟其於得知上開判\n    斷結果後，未依行政訴訟法第106條第1項之規定提起撤銷訴\n    訟，該申訴審議判斷即告確定，應受系爭審議判斷之拘束，\n    伊自應遵循該確定申訴審議判斷之意旨解除系爭契約，伊已\n    於95年5月22日以台博祕字第0950003533號函為行使系爭契\n    約解除權之意思表示，系爭契約自已解除而失其效力。縱認\n    伊不得解除系爭契約，因聯盛公司所為終止系爭契約之意思\n    表示亦不合法，爰再依系爭契約第14條第(一)項第2款之約定\n    ，以98年3月25日所提爭點整理狀為終止系爭契約之意思表\n    示。系爭專案相關承辦人員因涉違反貪污治罪條例等案件，\n    經臺灣士林地方法院檢察署檢察官提起公訴在案，則依系爭\n    契約第14條第(一)項約定及採購法第50條第1項、第2項規定，\n    伊以聯盛公司之行為有影響採購公正之情形而解除系爭契約\n    ，自不需負損害賠償責任。再依系爭契約第2條第(二)項第2款\n    之約定，聯盛公司執行系爭專案之各項工作，須待伊審定執\n    行服務計畫書後始得辦理其他後續工作，聯盛公司於執行服\n    務計畫書未經伊審定前即自行作業，其所生費用自不得要求\n    伊賠償，且聯盛公司未就其請求之金額舉證以實其說，其請\n    求伊賠償損害，並不合理。系爭契約因違反前揭效力規定而\n    無效，縱非無效，系爭契約已經伊解除，上訴人聯盛公司亦\n    不得依系爭契約之約定請求伊給付報酬。而上訴人聯盛公司\n    亦有違反機關委託技術服務廠商評選及計費辦法第3條及工\n    程技術顧問管理條例第8條第3項、系爭專案投標須知第13條\n    及第40條等規定之情形，依系爭契約第5條第(一)項第3款第(5)\n    點之約定，亦不得請求給付報酬。又依系爭契約第5條第(一)\n    項第2款第(1)點約定，聯盛公司於伊審定執行服務計畫書及\n    各期報告前，不得請求伊給付契約價金，而其所提出之專案\n    作業程序執行手冊與專案整體進度表等文件尚未經伊審定，\n    其逕自進行後階段工作，而伊於解除系爭契約後，另行透過\n    招標程序與訴外人中興工程顧問股份有限公司（下稱中興工\n    程公司）就系爭專案締結管理服務契約，聯盛公司逕自進行\n    之後階段工作，對伊並無實益，其依民法第512條第2項之規\n    定請求伊給付報酬，不足憑採。縱認聯盛公司得請求伊給付\n    報酬，應先扣除系爭契約第5條第(一)項第2款第(1)點約定中之\n    首期預付款額度，始為合理，否則即為無法律上之原因而受\n    有利益。另聯盛公司於系爭契約有效期間內實際履約期間至\n    多為7個月，應提出該期間內實際履約之人力支出時數表以\n    為證明。若認聯盛公司之請求有理由，聯盛公司未盡善良管\n    理人之責任，致伊未能及時辦理環境監測之採購案，違反環\n    保法規而遭行政院環境保護署處以30萬元之罰鍰，依系爭契\n    約第12條第(八)項之約定及民法第227條、第544條及第495條\n    等規定，應由聯盛公司負賠償責任，伊得以上開額外支出之\n    罰鍰30萬元主張抵銷等語，資為抗辯。並對於原判決不利部\n    分提起上訴，聲明：(一)原判決不利於故宮博物院部分廢棄。\n    (二)上廢棄部分，聯盛公司在第一審之訴及假執行之聲請均駁\n    回。另對於聯盛公司之上訴，答辯聲明：上訴駁回。\n四、兩造不爭執之事項：\n  (一)故宮博物院就系爭專案，於94年4月7日召開評選委員會，通\n    過聯盛公司資格審查，且公開評審聯盛公司為系爭專案最優\n    廠商。兩造於94年9月27日完成議價，並於同年10月27日締\n    結「國立故宮博物院南部院區新建工程委託專案管理服務案\n    契約書」（即系爭契約），約定契約總價為1億7950萬元（\n    含稅）。\n  (二)聯盛公司於94年10月31日送交系爭專案「執行服務計畫書」\n    予故宮博物院，並請求故宮博物院給付系爭契約總額之10%\n    服務費用共計1795萬元（見原審卷(一)，309至311頁）。\n  (三)聯盛公司分別於95年3月17日、同年4月18日，將第1季、第2\n    季報告交付予故宮博物院，並請求故宮博物院支付價款各80\n    7萬7500元。聯盛公司並已交付第3季報告予故宮博物院（見\n    本院卷，164頁反面）。\n  (四)故宮博物院就系爭專案之採購決定嗣遭行政院公共工程委員\n    會於95年5月5日以訴字第940418號採購申訴審議判斷書予以\n    撤銷。\n  (五)故宮博物院於95年5月22日以台博祕字第0950003533號函通\n    知聯盛公司表示依系爭契約第14條第(一)款第2點之約定解除\n    系爭契約，並請聯盛公司依系爭契約第14條第(三)款第1點規\n    定，將工作成果於同年月31日前移交予之。\n  (六)聯盛公司於95年6月1日將系爭專案工作成果（含系爭專案結\n    案報告書及移交清單各3份、工作成果移交檔案資料計7箱，\n    內容共計46冊）移交予故宮博物院，並經上訴人故宮博物院\n    簽收。\n  (七)故宮博物院因未持續執行系爭專案環境監測計畫而於95年10\n    月24日遭行政院環境保護署以違反環境影響評估法第17條規\n    定為由，依同法第23條第1項第1款規定裁處30萬元之罰鍰。\n  (八)聯盛公司於95年12月12日催告故宮博物院給付契約總價10%\n    之款項，否則將終止系爭契約，嗣依系爭契約第14條第8款\n    之約定，以本件起訴狀繕本之送達（96年1月12日）為終止\n    系爭契約之意思表示（見原審卷(一)，11頁，本院卷，209頁\n    ）。\n  (九)故宮博物院迄今未曾因兩造間系爭契約之法律關係支付聯盛\n    公司任何款項。\n  (十)兩造就系爭契約性質為承攬契約，且未因兩造合意而解除或\n    終止（見本院卷，99頁反面及164頁反面）。\n五、玆就兩造爭執之事項，分別判斷如下：\n  (一)關於系爭契約是否自始無效：就此，故宮博物院主張系爭契\n    約違反技術服務辦法第3條規定及工程技術顧問管理條例第8\n    條第3項規定而無效，聯盛公司則主張前開規定均僅取締規\n    定而非強制規定，系爭契約縱有違反，亦非無效。查技術服\n    務辦法係依據採購法第22條所頒布，依該條第1項第9款規定\n    ：「機關辦理公告金額以上之採購，符合下列情形之一者，\n    得採限制性招標：．．九、委託專業服務、技術服務或資訊\n    服務，經公開客觀評選為優勝者。」第2項規定：「前項第9\n    款之廠商評選辦法與服務費用計算方式，由主管機關定之。\n    」可知依該條第1項第9款委託專業服務、技術服務或資訊服\n    務，為公開客觀評選，僅為得採限制性招標之一要件，並非\n    強制所有限制性採購案均應依此方式辦理。又主管機關依該\n    條第2項所頒訂之技術服務辦法第3條規定：「本辦法所稱技\n    術服務，指建築師事務所、技師事務所、技術顧問機構及其\n    他依法令得提供技術性服務之自然人或法人所提供之規劃、\n    設計、監造或管理等服務。」亦未強制所有限制性採購契約\n    ，均應委託該條所之自然人或法人為規劃、設計、監造或管\n    理等服務，是技術服務辦法第3條規定，顯非民法第71條所\n    稱之強制或禁止規定。至於工程技術顧問公司管理條例第3\n    條規定：「本條例所稱工程技術顧問公司，指從事在地面上\n    下新建、增建、改建、修建、拆除構造物與其所屬設備、改\n    變自然環境之行為及其他經主管機關認定工程之技術服務事\n    項，包括規劃與可行性研究、基本設計、細部設計、協辦招\n    標與決標、施工監造、專案管理及其相關技術性服務之公司\n    。」第8條第3項規定：「外國公司於我國從事第三條所定業\n    務者，應經主管機關許可，及經公司登記主管機關認許及辦\n    理分公司登記，並於領得主管機關核發之工程技術顧問公司\n    登記證及加入全國商業同業公會或地方同業公會後，始得營\n    業。」參照同法第32條規定，違反者僅主管機關得限期改善\n    、罰鍰、警告，可知為行政管理之取締規定，非強制規定，\n    難認違反該條規定所訂立之契約為無效。\n  (二)關於系爭契約是否因撤銷決標、終止或解除而不存在部分：\n    就此，聯盛公司主張：系爭契約不因行政院公共工程委員會\n    決議撤銷決標而自始無效，故宮博物院於95年5月22日所為\n    解除系爭契約之意思表示，並不合法。其因故宮博物院給付\n    遲延而發函催告故宮博物院於5日內給付，故宮博物院仍未\n    給付，爰以本件起訴狀繕本之送達為伊終止系爭契約之意思\n    表示等語。故宮博物院則辯稱：系爭契約因違反技術服務辦\n    法第3條及工程顧問管理條例第8條第3項等效力規定，當然\n    無效。縱認系爭契約有效，因系爭專案之採購決定已經系爭\n    審議判斷撤銷，故宮博物院自得依該判斷結果解除系爭契約\n    或依系爭契約第14條第(一)項第2款之約定終止系爭契約等語\n    。分述如下：\n  1.聯盛公司得標後，另一投標廠商即訴外人美商誠國際股份\n    有限公司於94年10月間向行政院公共工程委員會提起採購申\n    訴案，請求撤銷故宮博物院就系爭專案所為之採購決定，經\n    系爭審議判斷認定：依技術服務辦法第3條規定：「本辦法\n    所稱技術服務，指建築師事務所、技師事務所、技術顧問機\n    構及其他依法令得提供技術性服務之自然人或法人所提供之\n    規劃、設計、監造或管理等服務。」而故宮博物院於94年3\n    月1日更正招標公告時，放寬增加「其他具有本採購專業技\n    術及人力資格需求之單位組成團隊。」亦得參與投標，而聯\n    盛公司雖已為公司登記，但依其登記營業項目，並無工程技\n    術顧問項目，不符合技術服務辦法所規定之投標資格。又系\n    爭專案所採之限制性招標公告中，其採協商措施之欄位規定\n    為「否」，然而故宮博物院於94年8月19日議約會前會議事\n    項紀錄，其中決議事項1、3、4、9等項均提及故宮博物院要\n    求聯盛公司更改或修正原投標文件內容，顯已違反採購法第\n    57條規定：「機關依前二條之規定採行協商措施者，應依下\n    列原則辦理︰．．二、協商時應平等對待所有合於招標文件\n    規定之投標廠商，必要時並錄影或錄音存證。三、原招標文\n    件已標示得更改項目之內容，始得納入協商。．．」之協商\n    應遵循之原則等事實，因而為撤銷系爭專案之決標採購決定\n    ，有系爭審議判斷附卷可稽，且為兩造所不爭（見原審卷(一)\n    ，165頁以下），堪信為真實。\n  2.按關於招標、審標、決標爭議之審議判斷視同訴願決定，政\n    府採購法第83條定有明文，據此，政府機關之招標、審標、\n    決標行為均係行政處分。如行政處分確係有效存在，雖內容\n    有不當或違法，而其爭訟在行政法院未依行政訴訟程序撤銷\n    以前，民事法院亦不能否認其效力。聯盛公司固非系爭審議\n    判斷之當事人，仍為利害關係人，倘對系爭審議判斷不服，\n    依司法院院字第1430號解釋之意旨，得於知悉後在法定期間\n    內提起行政爭訟，然被上訴人未提起之，要非不應受系爭審\n    議判斷之拘束（最高法院95年度台上字第1468號判決參照）\n    。系爭專案之決標既經系爭審議判斷認定明顯違反法令，且\n    屬違法情節重大而撤銷決標，而聯盛公司於接獲通知後並未\n    提起行政訴訟救濟，依前開說明，自應受系爭審議判斷之拘\n    束。\n  3.按採購法就行政機關依同法規定撤銷決標者，對於已簽立之\n    採購契約，有何影響，固未直接明文。然同法第50條第2項\n    既規定，投標廠商有該條第1項所列情形之一，經機關於開\n    標前發現者，其所投之標應不予開標；於開標後發現者，應\n    不決標予該廠商，決標或簽約後發現得標廠商於決標前有前\n    項情形者，應撤銷決標、終止契約或解除契約，並得追償損\n    失。但撤銷決標、終止契約或解除契約反不符公共利益，並\n    經上級機關核准者，不在此限，可知撤銷決標與終止契約、\n    解除契約，均為使契約關係消滅之獨立原因，一旦為撤銷決\n    標、終止契約或解除契約中任一行為，契約關係即消滅無再\n    為其他二行為之必要。又採購程序通常流程為招標、投標、\n    開標、審標、決標、簽約、履約，故一旦撤銷決標，應視同\n    自始未決標，若撤銷決標時尚未簽約者，即不能進入簽約程\n    序，若已簽約，亦應認為欠缺簽約前提之決標程序，而有終\n    止或解除之原因。此非唯由採購法第50條第2項文字將撤銷\n    決標與終止、解除對照於決標後與簽約後之不同效果，應為\n    如此解釋，即觀諸同法第74條之立法理由謂：「政府採購行\n    為一向被認定係私經濟行為，廠商與機關之間如有爭議，本\n    應循民事程序途徑解決，惟因廠商於招標、審標、決標階段\n    ，與機關並無契約關係，難有可供訴訟提起之訴因，故為增\n    加廠商之救濟及保護，並兼顧政府採購之時效性需求，爰參\n    酌政府採購協定第二十條之規定，訂定異議及申訴程序。」\n    等語，亦見立法意旨係以決標為契約成立之前置行政程序。\n    再由同法第85條第1項規定：「審議判斷指明原採購行為違\n    反法令者，招標機關應另為適法之處置。」第3項規定：「\n    第一項情形，廠商得向招標機關請求償付其準備投標、異議\n    及申訴所支出之必要費用。」益知決標經審議判斷應予撤銷\n    時，廠商僅得向招標機關請求償付其準備投標、異議及申訴\n    所支出之必要費用，非得基於契約而有所請求（請求履行契\n    約或債務不履行之損害賠償）。如已簽立採購契約後，決標\n    經撤銷者，採購單位即依採購法第50條第2項規定，取得終\n    止或解除契約權利。\n  4.系爭契約既經系爭審議判斷撤銷決標確定，依前開說明，應\n    認故宮博物院已取得終止或解除系爭契約權利，故其於95年\n    5月22日據系爭審議判斷，依系爭契約第14條第(一)款2.所約\n    定：「有採購法第50條第2項前段規定之情形。」對聯盛公\n    司所為解除契約之意思表示，即非無據。又系爭契約關係既\n    因解除而消滅，則聯盛公司即無再以起訴狀為終止系爭契約\n    之餘地。\n  (三)關於聯盛公司請求有無理由部分：按系爭契約經上級行政機\n    關撤銷決標後，故宮博物院進而據以解除致系爭契約關係消\n    滅，已如前述，且依系爭契約第14條第(一)款規定，故宮博物\n    院不必補償聯盛公司因此所生之損失，則聯盛公司先位依民\n    法第263條、第260條、第511條、第507條規定，備位依系爭\n    契約第5條第(一)項2.及損害賠償之約定，求為判決命故宮博\n    物院給付伊5333萬9450元暨如原判決附表二所示各期應付款\n    日起至清償日止，按週年利率百分之五計算之利息，均非可\n    採。至於聯盛公司因準備投標所支出之費用，僅得依採購法\n    第85條第3項規定，循行政訴訟程序以資解決，併予敘明（\n    最高法院94年度台上字第1792號判決參照）。\n  (四)關於故宮博物院抵銷抗辯部分：聯盛公司之請求既無理由，\n    本院自不必就此予以判斷。\n六、據上論結，聯盛公司先位依民法第263條、第260條、第511\n    條、第507條規定，備位依系爭契約第5條第(一)項2.及損害賠\n    償之約定，求為判決命故宮博物院給付伊5333萬9450元暨如\n    原判決附表二所示各期應付款日起至清償日止，按週年利率\n    百分之五計算之利息，均無理由，不應准許。原審判命故宮\n    博物院給付3978萬8333元及如原判決附表一所示利息，並為\n    假執行宣告，尚有未洽，故宮博物院上訴意旨指摘原判決此\n    部分不當，求予廢棄改判，為有理由，應由本院將原判決此\n    部分廢棄，並駁回聯盛公司於第一審之訴及假執行之聲請。\n    至於原審駁回聯盛公司其餘之訴及假執行聲請，則無不合，\n    聯盛公司上訴指摘原判決此部分不當，聲明廢棄，為無理由\n    ，應駁回其上訴。\n七、據上論結，故宮博物院上訴為有理由，聯盛公司上訴為無理\n    由。依民事訴訟法第450條、第449條第1項、第78條，判決\n    如主文。",
    "reason": "一、澳商聯盛國際企業股份有限公司台灣分公司（下稱聯盛公司\n    ）法定代理人原為牧漢龍，於民國98年2月19日變更為乙○\n    ○，有聯盛公司變更登記表在卷可稽（見本院卷，71頁），\n    經其以書狀聲明承受訴訟（見本院卷，70頁），核無不合，\n    應予准許。\n二、聯盛公司主張：伊於94年3月間參加國立故宮博物院（下稱\n    故宮博物院）「國立故宮博物院南部院區新建工程委託專案\n    管理服務案」（下稱系爭專案）之招標，並於同年4月7日經\n    故宮博物院召開評選委員會議通過資格審查，且經故宮博物\n    院公開評審為系爭專案最優廠商。兩造於同年9月27日完成\n    議價，同年10月7日簽訂「國立故宮博物院南部院區新建工\n    程委託專案管理服務案契約書」（下稱系爭契約），約定契\n    約總價為新台幣（下同）1億7950萬元（含稅），故宮博物\n    院並於94年10月18日刊登決標公告。惟另一投標廠商即訴外\n    人美商誠國際股份有限公司於94年10月間向行政院公共工\n    程委員會提起採購申訴案，請求撤銷故宮博物院就系爭專案\n    所為之採購決定，經行政院公共工程委員會採購申訴審議委\n    員會於95年5月5日第178次委員會議決議撤銷系爭專案之決\n    標採購決定（下稱系爭審議判斷），伊因未獲通知而無從參\n    與上開採購申訴程序，亦無從對之提起行政救濟。詎故宮博\n    物院竟於95年5月22日以伊違反政府採購法（下稱採購法）\n    第50條規定為由，發函通知伊依系爭契約第14條第(一)項第2\n    款規定解除系爭契約，並要求伊停止系爭契約工作及於同年\n    月31日前移交工作成果，兩造嗣於同年月30日就解約相關問\n    題進行第一次協商時，故宮博物院就應賠償伊損害部分並無\n    異議，僅要求伊結算至同年5月31日之服務費及相關費用並\n    提出詳細計算資料，甚且於兩造同年9月22日進行第二次協\n    商時，故宮博物院仍表示伊事實上已提供服務並移交服務成\n    果，其均會給付合理費用等語，並要求伊補充薪資結構、開\n    銷憑證等資料。伊遂於同年10月1日將系爭專案之工作成果\n    全數移交予故宮博物院，其中包含系爭專案時程綱要進度表\n    、品質管理計畫、設計審查制度、相關作業標準程序及專案\n    資訊管理與檔案管理系統，及設計審查成果等。又伊已依系\n    爭契約第2條第(二)項第2款之約定於系爭契約生效後2週內將\n    執行服務計畫書交付予故宮博物院，故宮博物院自應依系爭\n    契約第5條第(二)項之約定給付價金，惟經伊催告，故宮博物\n    院始終拖延拒絕給付，應負遲延責任，伊自得終止系爭契約\n    ，並請求損害賠償，爰以起訴狀繕本之送達為終止系爭契約\n    之意思表示等情，先位依民法第263條、第260條、第511條\n    、第507條規定，備位依系爭契約第5條第(一)項2.及損害賠償\n    之約定，求為判決命故宮博物院給付伊5333萬9450元暨如原\n    判決附表二所示各期應付款日起至清償日止，按週年利率百\n    分之五計算之利息。（原審准予聯盛公司備位部分4008萬\n    8333元之請求，另准予故宮博物院以受行政院環境保護署罰\n    鍰之30萬元為抵銷之主張，判命故宮博物院應給付聯盛公司\n    3978萬元8333元及如原判決附表一所示之利息，駁回聯盛公\n    司其餘請求）並對於原判決不利部分提起上訴，聲明：(一)原\n    判決不利於聯盛公司部分廢棄。(二)上廢棄部分，故宮博物院\n    應再給付聯盛公司1355萬1117元暨自95年5月31日起至清償\n    之日止，按年息百分之五計算之利息。另對於故宮博物院之\n    上訴，答辯聲明：上訴駁回。\n三、故宮博物院則以：系爭契約因違反「機關委託技術服務廠商\n    評選及計費辦法」（下稱技術服務辦法）第3條及工程技術\n    顧問管理條例第8條第3項等規定，當然無效，縱非無效，伊\n    依採購法第50條之規定，亦直接取得系爭契約之終止權及解\n    除權，且系爭審議判斷係依據採購法第50條第1項、第2項規\n    定，撤銷伊就系爭專案所做成之原採購決定，並認應撤銷決\n    標，聯盛公司雖未參加該申訴審議程序，惟其於得知上開判\n    斷結果後，未依行政訴訟法第106條第1項之規定提起撤銷訴\n    訟，該申訴審議判斷即告確定，應受系爭審議判斷之拘束，\n    伊自應遵循該確定申訴審議判斷之意旨解除系爭契約，伊已\n    於95年5月22日以台博祕字第0950003533號函為行使系爭契\n    約解除權之意思表示，系爭契約自已解除而失其效力。縱認\n    伊不得解除系爭契約，因聯盛公司所為終止系爭契約之意思\n    表示亦不合法，爰再依系爭契約第14條第(一)項第2款之約定\n    ，以98年3月25日所提爭點整理狀為終止系爭契約之意思表\n    示。系爭專案相關承辦人員因涉違反貪污治罪條例等案件，\n    經臺灣士林地方法院檢察署檢察官提起公訴在案，則依系爭\n    契約第14條第(一)項約定及採購法第50條第1項、第2項規定，\n    伊以聯盛公司之行為有影響採購公正之情形而解除系爭契約\n    ，自不需負損害賠償責任。再依系爭契約第2條第(二)項第2款\n    之約定，聯盛公司執行系爭專案之各項工作，須待伊審定執\n    行服務計畫書後始得辦理其他後續工作，聯盛公司於執行服\n    務計畫書未經伊審定前即自行作業，其所生費用自不得要求\n    伊賠償，且聯盛公司未就其請求之金額舉證以實其說，其請\n    求伊賠償損害，並不合理。系爭契約因違反前揭效力規定而\n    無效，縱非無效，系爭契約已經伊解除，上訴人聯盛公司亦\n    不得依系爭契約之約定請求伊給付報酬。而上訴人聯盛公司\n    亦有違反機關委託技術服務廠商評選及計費辦法第3條及工\n    程技術顧問管理條例第8條第3項、系爭專案投標須知第13條\n    及第40條等規定之情形，依系爭契約第5條第(一)項第3款第(5)\n    點之約定，亦不得請求給付報酬。又依系爭契約第5條第(一)\n    項第2款第(1)點約定，聯盛公司於伊審定執行服務計畫書及\n    各期報告前，不得請求伊給付契約價金，而其所提出之專案\n    作業程序執行手冊與專案整體進度表等文件尚未經伊審定，\n    其逕自進行後階段工作，而伊於解除系爭契約後，另行透過\n    招標程序與訴外人中興工程顧問股份有限公司（下稱中興工\n    程公司）就系爭專案締結管理服務契約，聯盛公司逕自進行\n    之後階段工作，對伊並無實益，其依民法第512條第2項之規\n    定請求伊給付報酬，不足憑採。縱認聯盛公司得請求伊給付\n    報酬，應先扣除系爭契約第5條第(一)項第2款第(1)點約定中之\n    首期預付款額度，始為合理，否則即為無法律上之原因而受\n    有利益。另聯盛公司於系爭契約有效期間內實際履約期間至\n    多為7個月，應提出該期間內實際履約之人力支出時數表以\n    為證明。若認聯盛公司之請求有理由，聯盛公司未盡善良管\n    理人之責任，致伊未能及時辦理環境監測之採購案，違反環\n    保法規而遭行政院環境保護署處以30萬元之罰鍰，依系爭契\n    約第12條第(八)項之約定及民法第227條、第544條及第495條\n    等規定，應由聯盛公司負賠償責任，伊得以上開額外支出之\n    罰鍰30萬元主張抵銷等語，資為抗辯。並對於原判決不利部\n    分提起上訴，聲明：(一)原判決不利於故宮博物院部分廢棄。\n    (二)上廢棄部分，聯盛公司在第一審之訴及假執行之聲請均駁\n    回。另對於聯盛公司之上訴，答辯聲明：上訴駁回。\n四、兩造不爭執之事項：\n  (一)故宮博物院就系爭專案，於94年4月7日召開評選委員會，通\n    過聯盛公司資格審查，且公開評審聯盛公司為系爭專案最優\n    廠商。兩造於94年9月27日完成議價，並於同年10月27日締\n    結「國立故宮博物院南部院區新建工程委託專案管理服務案\n    契約書」（即系爭契約），約定契約總價為1億7950萬元（\n    含稅）。\n  (二)聯盛公司於94年10月31日送交系爭專案「執行服務計畫書」\n    予故宮博物院，並請求故宮博物院給付系爭契約總額之10%\n    服務費用共計1795萬元（見原審卷(一)，309至311頁）。\n  (三)聯盛公司分別於95年3月17日、同年4月18日，將第1季、第2\n    季報告交付予故宮博物院，並請求故宮博物院支付價款各80\n    7萬7500元。聯盛公司並已交付第3季報告予故宮博物院（見\n    本院卷，164頁反面）。\n  (四)故宮博物院就系爭專案之採購決定嗣遭行政院公共工程委員\n    會於95年5月5日以訴字第940418號採購申訴審議判斷書予以\n    撤銷。\n  (五)故宮博物院於95年5月22日以台博祕字第0950003533號函通\n    知聯盛公司表示依系爭契約第14條第(一)款第2點之約定解除\n    系爭契約，並請聯盛公司依系爭契約第14條第(三)款第1點規\n    定，將工作成果於同年月31日前移交予之。\n  (六)聯盛公司於95年6月1日將系爭專案工作成果（含系爭專案結\n    案報告書及移交清單各3份、工作成果移交檔案資料計7箱，\n    內容共計46冊）移交予故宮博物院，並經上訴人故宮博物院\n    簽收。\n  (七)故宮博物院因未持續執行系爭專案環境監測計畫而於95年10\n    月24日遭行政院環境保護署以違反環境影響評估法第17條規\n    定為由，依同法第23條第1項第1款規定裁處30萬元之罰鍰。\n  (八)聯盛公司於95年12月12日催告故宮博物院給付契約總價10%\n    之款項，否則將終止系爭契約，嗣依系爭契約第14條第8款\n    之約定，以本件起訴狀繕本之送達（96年1月12日）為終止\n    系爭契約之意思表示（見原審卷(一)，11頁，本院卷，209頁\n    ）。\n  (九)故宮博物院迄今未曾因兩造間系爭契約之法律關係支付聯盛\n    公司任何款項。\n  (十)兩造就系爭契約性質為承攬契約，且未因兩造合意而解除或\n    終止（見本院卷，99頁反面及164頁反面）。\n五、玆就兩造爭執之事項，分別判斷如下：\n  (一)關於系爭契約是否自始無效：就此，故宮博物院主張系爭契\n    約違反技術服務辦法第3條規定及工程技術顧問管理條例第8\n    條第3項規定而無效，聯盛公司則主張前開規定均僅取締規\n    定而非強制規定，系爭契約縱有違反，亦非無效。查技術服\n    務辦法係依據採購法第22條所頒布，依該條第1項第9款規定\n    ：「機關辦理公告金額以上之採購，符合下列情形之一者，\n    得採限制性招標：．．九、委託專業服務、技術服務或資訊\n    服務，經公開客觀評選為優勝者。」第2項規定：「前項第9\n    款之廠商評選辦法與服務費用計算方式，由主管機關定之。\n    」可知依該條第1項第9款委託專業服務、技術服務或資訊服\n    務，為公開客觀評選，僅為得採限制性招標之一要件，並非\n    強制所有限制性採購案均應依此方式辦理。又主管機關依該\n    條第2項所頒訂之技術服務辦法第3條規定：「本辦法所稱技\n    術服務，指建築師事務所、技師事務所、技術顧問機構及其\n    他依法令得提供技術性服務之自然人或法人所提供之規劃、\n    設計、監造或管理等服務。」亦未強制所有限制性採購契約\n    ，均應委託該條所之自然人或法人為規劃、設計、監造或管\n    理等服務，是技術服務辦法第3條規定，顯非民法第71條所\n    稱之強制或禁止規定。至於工程技術顧問公司管理條例第3\n    條規定：「本條例所稱工程技術顧問公司，指從事在地面上\n    下新建、增建、改建、修建、拆除構造物與其所屬設備、改\n    變自然環境之行為及其他經主管機關認定工程之技術服務事\n    項，包括規劃與可行性研究、基本設計、細部設計、協辦招\n    標與決標、施工監造、專案管理及其相關技術性服務之公司\n    。」第8條第3項規定：「外國公司於我國從事第三條所定業\n    務者，應經主管機關許可，及經公司登記主管機關認許及辦\n    理分公司登記，並於領得主管機關核發之工程技術顧問公司\n    登記證及加入全國商業同業公會或地方同業公會後，始得營\n    業。」參照同法第32條規定，違反者僅主管機關得限期改善\n    、罰鍰、警告，可知為行政管理之取締規定，非強制規定，\n    難認違反該條規定所訂立之契約為無效。\n  (二)關於系爭契約是否因撤銷決標、終止或解除而不存在部分：\n    就此，聯盛公司主張：系爭契約不因行政院公共工程委員會\n    決議撤銷決標而自始無效，故宮博物院於95年5月22日所為\n    解除系爭契約之意思表示，並不合法。其因故宮博物院給付\n    遲延而發函催告故宮博物院於5日內給付，故宮博物院仍未\n    給付，爰以本件起訴狀繕本之送達為伊終止系爭契約之意思\n    表示等語。故宮博物院則辯稱：系爭契約因違反技術服務辦\n    法第3條及工程顧問管理條例第8條第3項等效力規定，當然\n    無效。縱認系爭契約有效，因系爭專案之採購決定已經系爭\n    審議判斷撤銷，故宮博物院自得依該判斷結果解除系爭契約\n    或依系爭契約第14條第(一)項第2款之約定終止系爭契約等語\n    。分述如下：\n  1.聯盛公司得標後，另一投標廠商即訴外人美商誠國際股份\n    有限公司於94年10月間向行政院公共工程委員會提起採購申\n    訴案，請求撤銷故宮博物院就系爭專案所為之採購決定，經\n    系爭審議判斷認定：依技術服務辦法第3條規定：「本辦法\n    所稱技術服務，指建築師事務所、技師事務所、技術顧問機\n    構及其他依法令得提供技術性服務之自然人或法人所提供之\n    規劃、設計、監造或管理等服務。」而故宮博物院於94年3\n    月1日更正招標公告時，放寬增加「其他具有本採購專業技\n    術及人力資格需求之單位組成團隊。」亦得參與投標，而聯\n    盛公司雖已為公司登記，但依其登記營業項目，並無工程技\n    術顧問項目，不符合技術服務辦法所規定之投標資格。又系\n    爭專案所採之限制性招標公告中，其採協商措施之欄位規定\n    為「否」，然而故宮博物院於94年8月19日議約會前會議事\n    項紀錄，其中決議事項1、3、4、9等項均提及故宮博物院要\n    求聯盛公司更改或修正原投標文件內容，顯已違反採購法第\n    57條規定：「機關依前二條之規定採行協商措施者，應依下\n    列原則辦理︰．．二、協商時應平等對待所有合於招標文件\n    規定之投標廠商，必要時並錄影或錄音存證。三、原招標文\n    件已標示得更改項目之內容，始得納入協商。．．」之協商\n    應遵循之原則等事實，因而為撤銷系爭專案之決標採購決定\n    ，有系爭審議判斷附卷可稽，且為兩造所不爭（見原審卷(一)\n    ，165頁以下），堪信為真實。\n  2.按關於招標、審標、決標爭議之審議判斷視同訴願決定，政\n    府採購法第83條定有明文，據此，政府機關之招標、審標、\n    決標行為均係行政處分。如行政處分確係有效存在，雖內容\n    有不當或違法，而其爭訟在行政法院未依行政訴訟程序撤銷\n    以前，民事法院亦不能否認其效力。聯盛公司固非系爭審議\n    判斷之當事人，仍為利害關係人，倘對系爭審議判斷不服，\n    依司法院院字第1430號解釋之意旨，得於知悉後在法定期間\n    內提起行政爭訟，然被上訴人未提起之，要非不應受系爭審\n    議判斷之拘束（最高法院95年度台上字第1468號判決參照）\n    。系爭專案之決標既經系爭審議判斷認定明顯違反法令，且\n    屬違法情節重大而撤銷決標，而聯盛公司於接獲通知後並未\n    提起行政訴訟救濟，依前開說明，自應受系爭審議判斷之拘\n    束。\n  3.按採購法就行政機關依同法規定撤銷決標者，對於已簽立之\n    採購契約，有何影響，固未直接明文。然同法第50條第2項\n    既規定，投標廠商有該條第1項所列情形之一，經機關於開\n    標前發現者，其所投之標應不予開標；於開標後發現者，應\n    不決標予該廠商，決標或簽約後發現得標廠商於決標前有前\n    項情形者，應撤銷決標、終止契約或解除契約，並得追償損\n    失。但撤銷決標、終止契約或解除契約反不符公共利益，並\n    經上級機關核准者，不在此限，可知撤銷決標與終止契約、\n    解除契約，均為使契約關係消滅之獨立原因，一旦為撤銷決\n    標、終止契約或解除契約中任一行為，契約關係即消滅無再\n    為其他二行為之必要。又採購程序通常流程為招標、投標、\n    開標、審標、決標、簽約、履約，故一旦撤銷決標，應視同\n    自始未決標，若撤銷決標時尚未簽約者，即不能進入簽約程\n    序，若已簽約，亦應認為欠缺簽約前提之決標程序，而有終\n    止或解除之原因。此非唯由採購法第50條第2項文字將撤銷\n    決標與終止、解除對照於決標後與簽約後之不同效果，應為\n    如此解釋，即觀諸同法第74條之立法理由謂：「政府採購行\n    為一向被認定係私經濟行為，廠商與機關之間如有爭議，本\n    應循民事程序途徑解決，惟因廠商於招標、審標、決標階段\n    ，與機關並無契約關係，難有可供訴訟提起之訴因，故為增\n    加廠商之救濟及保護，並兼顧政府採購之時效性需求，爰參\n    酌政府採購協定第二十條之規定，訂定異議及申訴程序。」\n    等語，亦見立法意旨係以決標為契約成立之前置行政程序。\n    再由同法第85條第1項規定：「審議判斷指明原採購行為違\n    反法令者，招標機關應另為適法之處置。」第3項規定：「\n    第一項情形，廠商得向招標機關請求償付其準備投標、異議\n    及申訴所支出之必要費用。」益知決標經審議判斷應予撤銷\n    時，廠商僅得向招標機關請求償付其準備投標、異議及申訴\n    所支出之必要費用，非得基於契約而有所請求（請求履行契\n    約或債務不履行之損害賠償）。如已簽立採購契約後，決標\n    經撤銷者，採購單位即依採購法第50條第2項規定，取得終\n    止或解除契約權利。\n  4.系爭契約既經系爭審議判斷撤銷決標確定，依前開說明，應\n    認故宮博物院已取得終止或解除系爭契約權利，故其於95年\n    5月22日據系爭審議判斷，依系爭契約第14條第(一)款2.所約\n    定：「有採購法第50條第2項前段規定之情形。」對聯盛公\n    司所為解除契約之意思表示，即非無據。又系爭契約關係既\n    因解除而消滅，則聯盛公司即無再以起訴狀為終止系爭契約\n    之餘地。\n  (三)關於聯盛公司請求有無理由部分：按系爭契約經上級行政機\n    關撤銷決標後，故宮博物院進而據以解除致系爭契約關係消\n    滅，已如前述，且依系爭契約第14條第(一)款規定，故宮博物\n    院不必補償聯盛公司因此所生之損失，則聯盛公司先位依民\n    法第263條、第260條、第511條、第507條規定，備位依系爭\n    契約第5條第(一)項2.及損害賠償之約定，求為判決命故宮博\n    物院給付伊5333萬9450元暨如原判決附表二所示各期應付款\n    日起至清償日止，按週年利率百分之五計算之利息，均非可\n    採。至於聯盛公司因準備投標所支出之費用，僅得依採購法\n    第85條第3項規定，循行政訴訟程序以資解決，併予敘明（\n    最高法院94年度台上字第1792號判決參照）。\n  (四)關於故宮博物院抵銷抗辯部分：聯盛公司之請求既無理由，\n    本院自不必就此予以判斷。\n六、據上論結，聯盛公司先位依民法第263條、第260條、第511\n    條、第507條規定，備位依系爭契約第5條第(一)項2.及損害賠\n    償之約定，求為判決命故宮博物院給付伊5333萬9450元暨如\n    原判決附表二所示各期應付款日起至清償日止，按週年利率\n    百分之五計算之利息，均無理由，不應准許。原審判命故宮\n    博物院給付3978萬8333元及如原判決附表一所示利息，並為\n    假執行宣告，尚有未洽，故宮博物院上訴意旨指摘原判決此\n    部分不當，求予廢棄改判，為有理由，應由本院將原判決此\n    部分廢棄，並駁回聯盛公司於第一審之訴及假執行之聲請。\n    至於原審駁回聯盛公司其餘之訴及假執行聲請，則無不合，\n    聯盛公司上訴指摘原判決此部分不當，聲明廢棄，為無理由\n    ，應駁回其上訴。\n七、據上論結，故宮博物院上訴為有理由，聯盛公司上訴為無理\n    由。依民事訴訟法第450條、第449條第1項、第78條，判決\n    如主文。"
  },
  "characters": {
    "judges": [
      "鄭三源",
      "魏麗娟",
      "呂太郎"
    ],
    "prosecutors": [

    ],
    "lawyers": [
      "陳彥希",
      "林哲誠",
      "陳井星",
      "謝進益",
      "律師或具有",
      "具",
      "人或其他法定代理人具有"
    ],
    "clerks": [
      "黃千鶴"
    ],
    "plaintiffs": [

    ],
    "defendants": [

    ],
    "prosecutor_office": [

    ],
    "creditors": [

    ],
    "debtors": [

    ],
    "judicial_associate_officer": [

    ]
  },
  "adjudged_at": "2010-01-05",
  "created_at": "2016-01-05 15:05:25",
  "updated_at": "2016-01-05 15:05:25"
}