{
  "identify": "TPH-99-聲-1289-20100512-1",
  "court": {
    "name": "臺灣高等法院",
    "code": "TPH"
  },
  "division": {
    "name": "刑事",
    "code": "M"
  },
  "year": 99,
  "word": "聲",
  "number": "1289",
  "jcheck": "1",
  "reason": "保護管束",
  "content": "臺灣高等法院刑事裁定                  99年度聲字第1289號\n聲  請  人  臺灣高等法院檢察署檢察官\n受  刑  人  甲○○\n上列受刑人因強盜罪案件，聲請人聲請付保護管束（99年度執聲\n付字第351號），本院裁定如下：\n    主  文\n甲○○假釋中付保護管束。\n    理  由\n一、查受刑人甲○○因強盜罪案件，前經臺灣板橋地方法院以95\n    年度訴字第585號判處有期徒刑5 年4月，嗣經本院以95年度\n    上訴字第2099號上訴駁回確定。茲受刑人於民國95年11月22\n    日入監執行，嗣經法務部於99年5月3日核准假釋，聲請人因\n    依刑事訴訟法第481條第1 項、刑法第93條第2項、第96條但\n    書規定，聲請受刑人於假釋中付保護管束，並檢具法務部矯\n    正司99年5月3日法矯司字第0990905877號函附臺灣雲林監獄\n    假釋出獄人交付保護管束名冊及臺灣高等法院檢察署刑案紀\n    錄簡覆表前來。經本院審核結果，認為並無不合。\n二、據上論斷，應依刑事訴訟法第481條第1項，刑法第96條但書\n    、第93條第2項，裁定如主文。\n中    華    民    國    99    年    5     月    12    日\n                  刑事第五庭  審判長 法  官  高明哲\n                                     法  官  高玉舜\n                                     法  官  劉秉鑫\n以上正本證明與原本無異。\n如不服本裁定，應於收受送達後五日內向本院提出抗告狀。\n                                     書記官  蔡宜蓁\n中    華    民    國    99    年    5     月    13    日",
  "structure": {
    "main": "甲○○假釋中付保護管束。",
    "reason": "一、查受刑人甲○○因強盜罪案件，前經臺灣板橋地方法院以95\n    年度訴字第585號判處有期徒刑5 年4月，嗣經本院以95年度\n    上訴字第2099號上訴駁回確定。茲受刑人於民國95年11月22\n    日入監執行，嗣經法務部於99年5月3日核准假釋，聲請人因\n    依刑事訴訟法第481條第1 項、刑法第93條第2項、第96條但\n    書規定，聲請受刑人於假釋中付保護管束，並檢具法務部矯\n    正司99年5月3日法矯司字第0990905877號函附臺灣雲林監獄\n    假釋出獄人交付保護管束名冊及臺灣高等法院檢察署刑案紀\n    錄簡覆表前來。經本院審核結果，認為並無不合。\n二、據上論斷，應依刑事訴訟法第481條第1項，刑法第96條但書\n    、第93條第2項，裁定如主文。"
  },
  "characters": {
    "judges": [
      "高明哲",
      "高玉舜",
      "劉秉鑫"
    ],
    "prosecutors": [

    ],
    "lawyers": [

    ],
    "clerks": [
      "蔡宜蓁"
    ],
    "plaintiffs": [

    ],
    "defendants": [

    ],
    "prosecutor_office": [
      "臺灣高等法院檢察署檢察官"
    ],
    "creditors": [

    ],
    "debtors": [

    ],
    "judicial_associate_officer": [

    ]
  },
  "adjudged_at": "2010-05-12",
  "created_at": "2016-01-05 11:53:35",
  "updated_at": "2016-01-05 11:53:35"
}