{
  "identify": "TPH-98-聲-3910-20100104-1",
  "court": {
    "name": "臺灣高等法院",
    "code": "TPH"
  },
  "division": {
    "name": "刑事",
    "code": "M"
  },
  "year": 98,
  "word": "聲",
  "number": "3910",
  "jcheck": "1",
  "reason": "聲請定其應執行刑",
  "content": "臺灣高等法院刑事裁定                  98年度聲字第3910號\n    聲  請  人  臺灣高等法院檢察署檢察官\n    受  刑  人  甲○○\n上列聲請人因受刑人數罪併罰有二裁判以上，聲請定其應執行之\n刑（98年度執聲字第1754號），本院裁定如下：\n    主    文\n甲○○因犯如附表所示各罪所處之刑，有期徒刑部分應執行有期\n徒刑參年伍月。\n    理    由\n一、按行為後法律有變更者，適用行為時之法律。但行為後之法\n    律有利於行為人者，適用最有利於行為人之法律，刑法第2\n    條第1項定有明文。依刑法第51條定應執行刑時，裁判確定\n    前犯數罪，其中一罪在新法施行前者，亦應為新舊法比較（\n    參照最高法院民國95年5月23日第8次刑事庭會議決議）。刑\n    法第51條前於94年2月2日修正公布，並於95年7月1日公布施\n    行，修正前刑法第51條第5款規定：數罪併罰，宣告多數有\n    期徒刑者，定其應執行者．於各刑中之最長期以上，各刑合\n    併之刑期以下，定其刑期。但不得逾20年。修正後刑法第51\n    條第5款規定：宣告多數有期徒刑者，於各刑中之最長期以\n    上，各刑合併之刑期以下，定其刑期。但不得逾30年。本院\n    比較新舊法結果，認以修正前刑法之規定較有利於行為人，\n    依刑法第2條第1項前段規定，自應依修正前刑法第51條第5\n    款，定其應執行之刑。\n二、受刑人甲○○因犯如附表所示各罪，經臺灣基隆地方法院及\n    本院先後判處如附表所示之刑，均分別確定在案。而甲○○\n    於裁判確定前所犯如附表所示之罪，均係95年7月1日前犯之\n    ，經比較新舊法結果，修正前之刑法較有利於甲○○，依刑\n    法第2條第1項前段之規定，應適用修正前刑法第51條第5款\n    ，為定其應執行刑之根據。\n三、茲檢察官聲請定其應執行之刑，本院審核認聲請為正當，應\n    就如附表所示定其應執行之刑。至如附表編號2所示併科罰\n    金部分，因無數罪併罰，有二裁判以上，須定其應執行刑之\n    情形，自仍依其原宣告之行執行之，附此敘明。爰依刑事訴\n    訟法第477條第1項、刑法第53條、第51條第5款，裁定如主\n    文。\n中    華    民    國    99    年    1     月    4    日\n                  刑事第五庭審判長法  官  高明哲\n                                  法  官  劉秉鑫\n                                  法  官  林洲富\n以上正本證明與原本無異。\n如不服本裁定，應於收受送達後五日內向本院提出抗告狀。\n                                  書記官  楊秋鈴\n中    華    民    國    99    年    1     月    5     日\n",
  "structure": {
    "main": "甲○○因犯如附表所示各罪所處之刑，有期徒刑部分應執行有期\n徒刑參年伍月。",
    "reason": "一、按行為後法律有變更者，適用行為時之法律。但行為後之法\n    律有利於行為人者，適用最有利於行為人之法律，刑法第2\n    條第1項定有明文。依刑法第51條定應執行刑時，裁判確定\n    前犯數罪，其中一罪在新法施行前者，亦應為新舊法比較（\n    參照最高法院民國95年5月23日第8次刑事庭會議決議）。刑\n    法第51條前於94年2月2日修正公布，並於95年7月1日公布施\n    行，修正前刑法第51條第5款規定：數罪併罰，宣告多數有\n    期徒刑者，定其應執行者．於各刑中之最長期以上，各刑合\n    併之刑期以下，定其刑期。但不得逾20年。修正後刑法第51\n    條第5款規定：宣告多數有期徒刑者，於各刑中之最長期以\n    上，各刑合併之刑期以下，定其刑期。但不得逾30年。本院\n    比較新舊法結果，認以修正前刑法之規定較有利於行為人，\n    依刑法第2條第1項前段規定，自應依修正前刑法第51條第5\n    款，定其應執行之刑。\n二、受刑人甲○○因犯如附表所示各罪，經臺灣基隆地方法院及\n    本院先後判處如附表所示之刑，均分別確定在案。而甲○○\n    於裁判確定前所犯如附表所示之罪，均係95年7月1日前犯之\n    ，經比較新舊法結果，修正前之刑法較有利於甲○○，依刑\n    法第2條第1項前段之規定，應適用修正前刑法第51條第5款\n    ，為定其應執行刑之根據。\n三、茲檢察官聲請定其應執行之刑，本院審核認聲請為正當，應\n    就如附表所示定其應執行之刑。至如附表編號2所示併科罰\n    金部分，因無數罪併罰，有二裁判以上，須定其應執行刑之\n    情形，自仍依其原宣告之行執行之，附此敘明。爰依刑事訴\n    訟法第477條第1項、刑法第53條、第51條第5款，裁定如主\n    文。"
  },
  "characters": {
    "judges": [
      "高明哲",
      "劉秉鑫",
      "林洲富"
    ],
    "prosecutors": [

    ],
    "lawyers": [

    ],
    "clerks": [
      "楊秋鈴"
    ],
    "plaintiffs": [

    ],
    "defendants": [

    ],
    "prosecutor_office": [
      "臺灣高等法院檢察署檢察官"
    ],
    "creditors": [

    ],
    "debtors": [

    ],
    "judicial_associate_officer": [

    ]
  },
  "adjudged_at": "2010-01-04",
  "created_at": "2016-01-05 14:34:49",
  "updated_at": "2016-01-05 14:34:49"
}