{
  "identify": "TPH-99-聲-1307-20100512-1",
  "court": {
    "name": "臺灣高等法院",
    "code": "TPH"
  },
  "division": {
    "name": "刑事",
    "code": "M"
  },
  "year": 99,
  "word": "聲",
  "number": "1307",
  "jcheck": "1",
  "reason": "聲請具保停止羈押",
  "content": "臺灣高等法院刑事裁定                  99年度聲字第1307號\n聲  請  人\n即  被  告  甲○○\n義務辯護人  許華雄律師\n上列被告因犯強盜等案件（99年度上訴字第208號），聲請具保\n停止羈押，本院裁定如下：\n    主  文\n聲請駁回。\n    理  由\n一、本件被告甲○○因涉犯加重強盜、加重竊盜、搶奪等案件，\n    前經本院認為犯罪嫌疑重大，所犯加重強盜罪係最經本刑五\n    年以上有期徒刑之罪，亦經原審判處重刑在案，有刑事訴訟\n    法第101條第1項第1款、第3款之情形，非予羈押，顯難進行\n    審判，於民國99年3月10日起執行羈押。\n二、聲請意旨略以：被告甲○○自始即坦承犯罪，且部分也符合\n    自首要件，無勾串證人或湮滅證據之可能，被告家境貧寒，\n    又有老母之累，其經濟能力遠較一般人為低，因此被告欠缺\n    逃亡能力，亦無離開台灣躲避司法審判之資力，準此，如未\n    羈押被告，是否顯然難以繼續進行審判，顯有疑問。又因被\n    告甲○○坦承犯罪，致同案被告楊政憲、劉志忠嚴重不滿，\n    乃致俟機拳頭相向，被告甲○○在開庭之途中，隨時有暴力\n    事件發生之可能，因而為使審判順利進行，羈押已無必要性\n    。況國家在干涉人民權利或自由時，須符合比例原則，本案\n    被告既已無上開羈押之必要性，若為保全日後審判程序順利\n    進行之目的，則請准予改以其他侵害較小的方式限制被告。\n    又被告為糖尿病、高血壓及甲狀線亢進症之長期病患，於看\n    守所內病情日益嚴重，非保外治療顯難有妥適治療，請准予\n    具保云云。\n三、經查：聲請人即被告甲○○因另犯偽造文書等罪，經臺灣桃\n    園地方法院以98年度審訴字第2345號判決並定執行刑有期徒\n    刑1年，聲請人不服提起上訴，經本院以98年度上訴第4923\n    號、最高法院以99年度台上字第1269號上訴駁回，而於99年\n    3月4日確定在案，並經檢察官借提執行，刑期起算日為99年\n    5 月7日，有臺灣板橋地方法院檢察署檢察官執行指揮書乙\n    紙在卷可稽。被告業因另案在監執行，執行期間即非本院之\n    在押人犯，所請無從准許，應予駁回。\n中    華    民    國    99    年     5    月    12    日\n                  刑事第十七庭  審判長法  官  王聰明\n                                      法  官  陳憲裕\n                                      法  官  黃雅芬\n以上正本證明與原本無異。\n如不服本裁定，應於裁定送達後5日內向本院提出抗告狀。\n                                      書記官  鄭雅云\n中    華    民    國    99    年    5     月    14    日",
  "structure": {
    "main": "聲請駁回。",
    "reason": "一、本件被告甲○○因涉犯加重強盜、加重竊盜、搶奪等案件，\n    前經本院認為犯罪嫌疑重大，所犯加重強盜罪係最經本刑五\n    年以上有期徒刑之罪，亦經原審判處重刑在案，有刑事訴訟\n    法第101條第1項第1款、第3款之情形，非予羈押，顯難進行\n    審判，於民國99年3月10日起執行羈押。\n二、聲請意旨略以：被告甲○○自始即坦承犯罪，且部分也符合\n    自首要件，無勾串證人或湮滅證據之可能，被告家境貧寒，\n    又有老母之累，其經濟能力遠較一般人為低，因此被告欠缺\n    逃亡能力，亦無離開台灣躲避司法審判之資力，準此，如未\n    羈押被告，是否顯然難以繼續進行審判，顯有疑問。又因被\n    告甲○○坦承犯罪，致同案被告楊政憲、劉志忠嚴重不滿，\n    乃致俟機拳頭相向，被告甲○○在開庭之途中，隨時有暴力\n    事件發生之可能，因而為使審判順利進行，羈押已無必要性\n    。況國家在干涉人民權利或自由時，須符合比例原則，本案\n    被告既已無上開羈押之必要性，若為保全日後審判程序順利\n    進行之目的，則請准予改以其他侵害較小的方式限制被告。\n    又被告為糖尿病、高血壓及甲狀線亢進症之長期病患，於看\n    守所內病情日益嚴重，非保外治療顯難有妥適治療，請准予\n    具保云云。\n三、經查：聲請人即被告甲○○因另犯偽造文書等罪，經臺灣桃\n    園地方法院以98年度審訴字第2345號判決並定執行刑有期徒\n    刑1年，聲請人不服提起上訴，經本院以98年度上訴第4923\n    號、最高法院以99年度台上字第1269號上訴駁回，而於99年\n    3月4日確定在案，並經檢察官借提執行，刑期起算日為99年\n    5 月7日，有臺灣板橋地方法院檢察署檢察官執行指揮書乙\n    紙在卷可稽。被告業因另案在監執行，執行期間即非本院之\n    在押人犯，所請無從准許，應予駁回。"
  },
  "characters": {
    "judges": [
      "王聰明",
      "陳憲裕",
      "黃雅芬"
    ],
    "prosecutors": [

    ],
    "lawyers": [
      "許華雄"
    ],
    "clerks": [
      "鄭雅云"
    ],
    "plaintiffs": [

    ],
    "defendants": [
      "甲"
    ],
    "prosecutor_office": [

    ],
    "creditors": [

    ],
    "debtors": [

    ],
    "judicial_associate_officer": [

    ]
  },
  "adjudged_at": "2010-05-12",
  "created_at": "2016-01-05 11:54:48",
  "updated_at": "2016-01-05 11:54:48"
}