{
  "identify": "TPH-99-重上-69-20100512-1",
  "court": {
    "name": "臺灣高等法院",
    "code": "TPH"
  },
  "division": {
    "name": "民事",
    "code": "V"
  },
  "year": 99,
  "word": "重上",
  "number": "69",
  "jcheck": "1",
  "reason": "返還不當得利等",
  "content": "臺灣高等法院民事判決                  99年度重上字第69號\n上  訴  人  丁○○\n訴訟代理人  張瑞釗律師\n被  上訴人  丙○○\n訴訟代理人  陳建勳律師\n            張弘明律師\n上列當事人間請求返還不當得利等事件，上訴人對於中華民國98\n年12月8日臺灣板橋地方法院98年度重訴字第310號第一審判決提\n起上訴，本院於99年4月28日言詞辯論終結，判決如下：\n    主      文\n上訴駁回。\n第二審訴訟費用由上訴人負擔。\n    事實及理由\n一、上訴人起訴主張：\n  (一)上訴人於民國（下同）83年6月初，委任三女即被上訴人出\n    售其所有坐落臺北市○○區○○段86-1地號土地及其上門牌\n    號碼為臺北市○○區○○路2段420號9樓之3之建物（下稱系\n    爭房地），83年6月底，上訴人詢問被上訴人已否賣出、價\n    金多少，被上訴人竟謂已先辦理贈與登記在被上訴人名下再\n    賣，此後一直沒消息。直至97年下半年，上訴人申請系爭房\n    地之土地及建築改良物登記簿謄本，發現被上訴人早已在92\n    年9 月18日將系爭房地辦理所有權移轉登記為訴外人梁愛蘋\n    所有，經向被上訴人查詢，被上訴人謂以新台幣（下同）80\n    0 萬元將系爭房地出售，上訴人向被上訴人索取價款，竟置\n    之不理。\n  (二)系爭房地為國宅，由上訴人承購，購屋價款亦由上訴人支付\n    ，另銀行貸款、火災保險、水電費亦由上訴人給付。權狀原\n    由上訴人保管，被上訴人潛行取走，因被上訴人係上訴人之\n    女兒，隨時均可利用上訴人不在家時拿取。系爭房地係由上\n    訴人承購，上訴人亦無將其贈與被上訴人。爰依民法第528\n    條、第541條之委任關係，及民法184條之侵權行為、同法第\n    179條之不當得利等法律關係提起本訴。\n  (三)求為判決：\n    1.被上訴人應給付上訴人800 萬元及自起訴狀繕本送達之翌\n      日起至清償日止按年息5%計算之利息。\n    2.願供擔保請宣告准為假執行。\n二、被上訴人則以：\n  (一)上訴人與被上訴人係父女，80年1 月間由於上訴人原本居住\n    之房屋基地屬國有財產，因而列為地上拆遷戶，上訴人享有\n    國宅配售之優先承購權及領取一筆約700 萬元之補償金。惟\n    上訴人當時已年屆69歲，且已領取一筆約700 萬元之補償金\n    ，早有退休之計劃，故無意願再額外給付一筆費用承購國宅\n    ，遂直接詢問被上訴人有無意願享有此國宅配售之優先承購\n    權，但購屋費用必須自行負擔，被上訴人遂向上訴人表示願\n    意承購。因此，兩造當時合意由被上訴人負擔2,298,457 元\n    之購屋價款，以上訴人名義向臺北市政府承購系爭房地及向\n    臺北市銀行貸款195 萬元，相關之購屋款項、銀行貸款、火\n    災保險費、辦理抵押權設定之費用、及地價稅、房屋稅等費\n    用，均係由被上訴人支出並持有相關契約書及收據正本，且\n    系爭房地之土地及建物所有權狀正本亦由被上訴人持有保管\n    ，系爭房地點交後，由被上訴人為實際管理使用收益，被上\n    訴人將系爭房地出租予第三人。\n  (二)被上訴人承購系爭房地後，依據承購國民住宅暨貸款契約書\n    第16條約定，被上訴人於80年2 月間就系爭房地以上訴人之\n    名義委由臺北市銀行向第一產物保險股份有限公司投保火災\n    保險，總保險費7,970 元由被上訴人以上訴人之名義支付。\n    系爭房地辦理抵押權設定所需之相關費用，亦均由被上訴人\n    支出。而系爭房地於83年8 月25日贈與移轉登記予被上訴人\n    前，地價稅及房屋稅亦均係由被上訴人以上訴人之名義負擔\n    。兩造合意以贈與方式移轉登記，係因兩造為直系血親三親\n    等內之關係，當時若以買賣為移轉登記之原因，國稅局會要\n    求兩造提出買賣資金流向證明，然由於系爭房地於80年1 月\n    間係由被上訴人出資購買，所有費用均由被上訴人負擔，故\n    於83年6、7月間辦理移轉登記時，兩造根本不存在任何買賣\n    資金流向，而被上訴人亦不想為此而假造與上訴人間之買賣\n    資金流向，故以贈與為原因辦理移轉登記。\n  (三)被上訴人於符合71年7月30日修正之國民住宅條例第19條第1\n    項關於限制移轉規定之2 年年限後，上訴人與被上訴人合意\n    將系爭房地過戶予被上訴人，雙方並共同委託代書於83年6\n    、7 月間，以贈與為原因將系爭房地所有權辦理移轉登記予\n    被上訴人。為辦理移轉登記時所需贈與人即上訴人之證件，\n    含印鑑證明、身分證正本等證件，及持印鑑章用印等手續，\n    均係上訴人親自出面委託代書辦理。另為辦理系爭房地所有\n    權移轉登記所須繳納之土地增值稅、契稅、贈與稅及規費等\n    費用均係由被上訴人負擔。系爭房地所有權於83年8 月25日\n    移轉登記予被上訴人後，被上訴人業於83年12月23日如數清\n    償系爭房地之貸款。\n  (四)被上訴人於92年間將系爭房地出售予第三人並取得售屋款項\n    ，並非受上訴人委任而為，未侵害上訴人任何權利，且被上\n    訴人亦非無法律上之原因而受有利益，致上訴人受有損害，\n    上訴人訴請被上訴人給付800 萬元，於法無據等語，資為抗\n    辯。\n三、原審為上訴人敗訴之判決，上訴人提起上訴，上訴聲明為：\n    (一)原判決廢棄。(二)被上訴人應給付上訴人800 萬元及自起訴\n    狀繕本送達翌日起至清償日止，按年息5%計算之利息。(三)請\n    求准供擔保宣告假執行。被上訴人答辯聲明：(一)上訴駁回。\n    (二)如受不利判決，被上訴人願供擔保，請准宣告免為假執行\n    。\n四、本件不爭執事項：坐落臺北市○○區○○段1 小段86-1地號\n    土地及其上門牌號碼為臺北市○○區○○路2段420號9樓之3\n    之建物為國民住宅，80年間以上訴人名義向臺北市政府承購\n    ，被上訴人係上訴人女兒，83年間系爭房地經贈與登記於被\n    上訴人名下，92年9 月18日被上訴人將系爭房地，以買賣為\n    原因移轉登記為訴外人梁愛蘋所有，被上訴人得款800 萬元\n    。\n五、本件爭點：\n  (一)系爭房地何人出資承購，是否被上訴人借用上訴人名義購得\n    ？\n  (二)上訴人有無委任被上訴人出售系爭房地？\n  (三)83年間兩造有無共同委任代書以贈與為原因，辦理系爭房地\n    所有權移轉登記為被上訴人所有？\n  (四)上訴人依民法第528條、第541條之委任關係，及民法184條\n    之侵權行為、同法第179條之不當得利法律關係請求給付，\n    有無理由？\n六、按文書，依其程式及意旨得認作公文書者，推定為真正，民\n    事訴訟法第355條第1項定有明文。次按事實之真偽，應由事\n    實審法院斟酌辯論意旨及調查證據之結果，依自由心證判斷\n    之，苟其判斷並不違背法令，即不許當事人以空言指摘。法\n    院依自由心證判斷事實之真偽，不得違背論理及經驗法則，\n    民事訴訟法第222條第3項亦有明示。所謂論理法則，係指依\n    立法意旨或法規之社會機能就法律事實所為價值判斷之法則\n    而言。所謂經驗法則，係指由社會生活累積的經驗歸納所得\n    之法則而言；凡日常生活所得之通常經驗及基於專門知識所\n    得之特別經驗均屬之（最高法院21年上字第1406號判例、91\n    年台上字第741號判決意旨參照）。\n  (一)關於出資購買系爭房地部分：\n    1.查系爭房地係於80年間以上訴人名義向臺北市政府承購，\n      有臺北市政府出售國民住宅繳款通知書在卷可稽（原審卷\n      (一)第26頁），兩造不爭執。\n    2.次查，80年1月24日承購國民住宅暨貸款契約書，立契約\n      書人為承購人即上訴人與出賣人臺北市政府，契約第3、5\n      條約定，上訴人以2,298,457 元購買系爭房地，臺北市政\n      府依規定貸予上訴人195 萬元，貸款期間20年，契約第16\n      條約定承購人應投保火災保險至貸款清償為止，有契約書\n      在卷可稽（原審卷(二)第13頁）；系爭房地於80年2 月間投\n      保火災保險，保險期間自80年1月24日起至100年1月24 日\n      ，有火災保險單在卷可稽（原審卷(二)第14頁）。上開買賣\n      暨貸款契約書係承購系爭房地時，承購人所應持有之權利\n      文件，且為系爭房地投保火災保險為承購人承購系爭房地\n      應履行之義務。上開文件之持有者為被上訴人，被上訴人\n      另提出火災保險費收據、臺北市地政規費收據、房地產登\n      記費用明細表、82年地價稅及房屋稅繳款書，及國民住宅\n      貸款清償證明書（原審卷(二)第15、19、46頁）。\n    3.上訴人固提出臺北市政府出售國民住宅繳款通知書、臺北\n      市國民住宅處購國宅進住通知單、水、電費通知、臺北市\n      銀行營業部代辦國民住宅基金貸款還款簿（原審卷(一)第26\n      至27頁、第30至110頁）。然上開通知單及繳款單係有關\n      系爭房地應納之貸款及費用，自當以系爭房地之承購人為\n      通知對象，惟上訴人身為承購人，卻未持有原始承購系爭\n      房地之契約書及須投保火災保險之保險單及繳費收據及國\n      民住宅貸款清償證明書。上訴人主張相關文件係由被上訴\n      人自行取走云云，未據上訴人立證證明，不能採信。\n    4.再查，承購系爭房地之後即80年3月1日，被上訴人將系爭\n      房屋出租予第三人，有房屋租賃契約書在卷可稽（原審卷\n      (二)第20至24頁）。依社會一般常情，所有權人或對不動產\n      有權利之人，方會以自己之名義出租房屋而為收益。\n    5.末查，系爭房地於81年2月26日設定本件最高限額500萬元\n      抵押權予被上訴人，債務人為上訴人，有臺北市土地建物\n      登記簿在卷可稽（原審卷(二)第82至83頁）。若上訴人確為\n      出資承購系爭房地之人，當無必要設定抵押權予被上訴人\n      。\n    6.由上事證，被上訴人稱系爭房地係由其出資以上訴人名義\n      登記購買，伊對系爭房屋有實際管理使用收益之權，可以\n      採信。\n  (二)關於83年間系爭房地所有權以贈與為原因移轉登記為被上訴\n    人所有部分：\n    1.上訴人之戶籍僅於80年3月21日至84年5月10日設於系爭房\n      屋之地址，於80年3月21日之前，及84年5月10日之後，上\n      訴人均設籍於臺北市○○區○○街164巷62弄16號地址（\n      即現址忠孝東路5段236巷37弄33號），有戶口名簿、戶籍\n      謄本在卷可稽（本院卷第92、72、82頁）。依承購國民住\n      宅暨貸款契約書第12條約定，承購之住宅及基地居住滿2\n      年後，得依國民住宅條例第19條暨施行細則第27條規定，\n      經臺北市政府同意後，將該住宅及基地出售、出典、贈與\n      或交換予具有承購國民住宅之資格者。由上事證足認，上\n      訴人設籍於系爭房屋，即於80年1月間承購後至83年間以\n      贈與為原因移轉登記時，係為符合系爭房地應居住滿2年\n      之移轉限制。\n    2.查上訴人於83年5 月28日書立理由書予臺北市政府國民住\n      宅處，申請將系爭房地贈與予被上訴人，經臺北市政府國\n      民住宅處函覆略以：「台端等所有臺北市○○路○段420號\n      9 樓之3國輝國宅及基地（持分120/50000）申請贈與給丙\n      ○○君乙節，本處同意」，有83年7月2日（83）北市宅三\n      字第16522 號函及申請書相關文件在卷可稽（本院卷第76\n      至96頁）。次查，兩造於83年7月1日於臺灣臺北地方法院\n      公證處，請求公證上訴人將系爭房屋贈與予被上訴人，有\n      83年義公字第30513 號公證書在卷可稽（本院卷第66至67\n      頁），並經本院調閱該公證卷宗查核屬實。嗣於83年6 月\n      22日、7月1日，系爭房地以贈與為原因申請所有權移轉登\n      記，贈與人為上訴人，受贈人為被上訴人，有土地登記申\n      請書、土地及建築改良物贈與所有權移轉契約書在卷可稽\n      （原審卷(二)第25至30頁）。由上事證足認，系爭房地以贈\n      與為原因移轉所有權登記予被上訴人。\n    3.上訴人之戶籍僅於80年3月21日至84年5月10日設於系爭房\n      屋之地址，於80年3月21日之前，及84年5月10日之後，上\n      訴人均設籍於臺北市○○區○○街164 巷62弄16號地址（\n      即現址忠孝東路5段236巷37弄33號），有戶口名簿、戶籍\n      謄本在卷可稽（本院卷第92、72、82頁）。依承購國民住\n      宅暨貸款契約書第12條約定，承購之住宅及基地居住滿2\n      年後，得依國民住宅條例第19條暨施行細則第27條規定，\n      經臺北市政府同意後，將該住宅及基地出售、出典、贈與\n      或交換予具有承購國民住宅之資格者。由上事證足認，上\n      訴人設籍於系爭房屋，即於80年1 月間承購後至83年間以\n      贈與為原因移轉登記時，係為符合系爭房地應居住滿2 年\n      之移轉限制期間。參以被上訴人以上訴人名義出資購買系\n      爭房地（詳前理由(一)所述），被上訴人與上訴人間就系爭\n      房地並無買賣之事實，被上訴人與上訴人以贈與為原因移\n      轉系爭房地之所有權登記，係符常情。\n    4.末查，系爭房地之贈與所有權契約書約定：受贈人（即被\n      上訴人）應承擔贈與人（即上訴人）就本不動產向銀行之\n      貸款，有土地及建築改良物贈與所有權移轉契約書在卷可\n      稽（原審卷(二)第28、30頁）。嗣於83年12月23日系爭房地\n      之貸款全部清償，被上訴人持有國民住宅貸款清償證明書\n      （原審卷(二)第46頁）。\n    5.綜上，被上訴人抗辯上訴人同意於系爭房地符合限制移轉\n      登記年限後，將系爭房地移轉登記予被上訴人等語，可以\n      採信。\n七、關於上訴人有無委任被上訴人出售系爭房地部分：\n    按當事人主張有利於己之事實者，就其事實有舉證之責任，\n    民事訴訟法第277 條前段定有明文。次按請求履行債務之訴\n    ，除被告自認原告所主張債權發生原因之事實外，應先由原\n    告就其主張此項事實，負舉證之責任，必須證明其為真實後\n    ，被告於其抗辯事實，始應負證明之責任，此為舉證責任分\n    擔之原則（最高法院43年台上字第377號判例意旨參照）。\n  (一)上訴人主張其於83年間委任被上訴人出售系爭房地，為被上\n    訴人否認。證人乙○○於原審證稱略以：因為被上訴人是做\n    房地產的，上訴人買系爭房地的時候，有很多人告訴上訴人\n    可以賣不錯的價錢，但因為剛買，所以不想賣，後來83年左\n    右上訴人想要賣房子，就叫被上訴人幫忙賣等語。在83年5\n    、6 月的時候決定要賣，這些事是上訴人告訴伊，上訴人說\n    只有委託被上訴人去賣，沒有要贈與的意思等語（原審卷(二)\n    第71頁反面、第73頁反面）。證人乙○○於本院先證稱：「\n    83年間上訴人有委任被上訴人出售系爭國宅。有將印章、國\n    民身份證、印鑑證明等交予被上訴人」，嗣又稱：「1991年\n    間，我問被上訴人系爭國宅，上訴人有無請被上訴人賣，被\n    上訴人表示上訴人把上開文件交給被上訴人，叫她賣系爭國\n    宅」（本院卷第106頁反面、第107頁）。證人乙○○就上訴\n    人委託被上訴人出賣系爭房地之時間，前後陳述不一致，且\n    證人乙○○係上訴人之女兒，難期證言為真正，不能逕信。\n  (二)證人甲○○證稱略以：系爭房地係由上訴人承購，上訴人並\n    未將系爭房地贈與予被上訴人，亦無與被上訴人共同委任代\n    書以贈與為原因將系爭房地過戶予被上訴人，亦無與被上訴\n    人共同委任代書將系爭房地為被上訴人辦理抵押權設定登記\n    ，上訴人有委任被上訴人出售系爭房地，將印章、國民身份\n    證、印鑑證明等交予被上訴人，上開事項係伊與上訴人談話\n    中知悉等語（本院卷第107頁至反面）。證人甲○○為上訴\n    人之女，作證事項係聽聞自上訴人，其證言不能採信。\n  (三)再查，上訴人主張被上訴人於98年3月25日電話中承認將系\n    爭房地偷偷賣掉之事實，另於98年2月至6月間之電話談話中\n    ，上訴人並無贈與系爭房地予被上訴人等語，提出電話譯文\n    4件（原審卷(一)第112至186頁）。經查，上開電話譯文係被\n    上訴人與證人乙○○及兩造就系爭房地出售及贈與等節互為\n    爭執之對話，尚難為有利於上訴人之認定。\n  (四)上訴人主張被上訴人自79年11月間就計畫奪產，提出79年11\n    月間上訴人寄予證人乙○○之信件（本院卷第57至59頁）。\n    惟查，上開信件之時間為79年11月間，斯時系爭房地尚未承\n    購，尚難以該信件為有利於上訴人之認定。\n  (五)末查，上訴人起訴主張於83年6月委任被上訴人出售系爭房\n    地，迄於97年下半年申請系爭房地之登記謄本時，始發現被\n    上訴人出售系爭房地予第三人之情事（原法院司重調字卷第\n    3頁）。依上訴人所述，自83年6月間至97年下半年，長達14\n    年，上訴人始發現系爭房地出售之情事。衡諸社會常情，委\n    託他人出售不動產此等高價資產，應會密切注意委託事務進\n    行之進度，上訴人長達14年間就委託出售系爭房地之事未為\n    聞問，與一般經驗法則不符。\n  (六)上訴人未舉其他證據證明其委託被上訴人間出售系爭房地，\n    上訴人主張其與被上訴人間有委任之法律關係存在，請求被\n    上訴人給付出售系爭房地之款項800萬元，為無理由。\n八、按因故意或過失，不法侵害他人之權利者，負損害賠償責任\n    。故意以背於善良風俗之方法，加損害於他人者，亦同，民\n    法第184條第1項定有明文。查系爭房地由被上訴人借用上訴\n    人之名義出資購買，嗣以贈與為原因，移轉登記所有權予被\n    上訴人，業經認定詳前述。被上訴人將自己名下之系爭房地\n    出售予第三人，並無侵害上訴人之權利，或以背於善良風俗\n    之方法加損害於上訴人。上訴人依據民法第184 條規定，請\n    求被上訴人給付系爭房地出售之價款800萬元，為無理由。\n九、按無法律上之原因而受利益，致他人受損害者，應返還其利\n    益；雖有法律上之原因，而其後已不存在者，亦同，民法第\n    179 條定有明文。系爭房地於83年間以贈與為原因移轉登記\n    予被上訴人，被上訴人將系爭房地出售得款800 萬元，係為\n    有權處分，並無受利益致上訴人受損害。上訴人依據民法第\n    179條規定，請求被上訴人給付系爭房地出售之價款800萬元\n    ，為無理由。\n十、綜上所述，上訴人主張本於民法第528條、第541條、第184\n    條、第179條法律關係，請求被上訴人給付800萬元，及自起\n    訴狀繕本送達翌日起至清償日止，按年息5%計算之利息，為\n    無理由，不應准許。原審為上訴人敗訴之判決，及駁回其假\n    執行之聲請，並無不合。上訴意旨指摘原判決不當，求予廢\n    棄改判，為無理由，應予駁回。\n十一、上訴人聲請鑑定臺北市政府國民住宅處所附贈與之理由書\n      其上之簽名，核無必要，附此說明。\n十二、本件事證已臻明確，兩造其餘攻擊防禦方法及未經援用之\n      舉證，經審酌核與本件判決結果不生影響，不再逐一論述\n      ，附此敘明。\n十三、據上論結，本件上訴為無理由，依民事訴訟法第449條第1\n      項、第78條，判決如主文。\n中    華    民    國    99    年    5     月    12    日\n                    民事第二庭\n                        審判長法  官  吳謙仁\n                              法  官  蘇瑞華\n                              法  官  李瓊蔭\n正本係照原本作成。\n如不服本判決，應於收受送達後20日內向本院提出上訴書狀，其\n未表明上訴理由者，應於提出上訴後20日內向本院補提理由書狀\n（均須按他造當事人之人數附繕本）上訴時應提出委任律師或具\n有律師資格之人之委任狀；委任有律師資格者，另應附具律師資\n格證書及釋明委任人與受任人有民事訴訟法第466條之1第1項但\n書或第2項（詳附註）所定關係之釋明文書影本。\n中    華    民    國    99    年    5     月    13    日\n                              書記官  王才生\n附註：\n民事訴訟法第466條之1（第1項、第2項）：\n對於第二審判決上訴，上訴人應委任律師為訴訟代理人。但上訴\n人或其他法定代理人具有律師資格者，不在此限。\n上訴人之配偶、三親等內之血親、二親等內之姻親，或上訴人為\n法人、中央或地方機關時，其所屬專任人員具有律師資格並經法\n院認為適當者，亦得為第三審訴訟代理人。",
  "structure": {
    "main": "上訴駁回。\n第二審訴訟費用由上訴人負擔。",
    "fact": "一、上訴人起訴主張：\n  (一)上訴人於民國（下同）83年6月初，委任三女即被上訴人出\n    售其所有坐落臺北市○○區○○段86-1地號土地及其上門牌\n    號碼為臺北市○○區○○路2段420號9樓之3之建物（下稱系\n    爭房地），83年6月底，上訴人詢問被上訴人已否賣出、價\n    金多少，被上訴人竟謂已先辦理贈與登記在被上訴人名下再\n    賣，此後一直沒消息。直至97年下半年，上訴人申請系爭房\n    地之土地及建築改良物登記簿謄本，發現被上訴人早已在92\n    年9 月18日將系爭房地辦理所有權移轉登記為訴外人梁愛蘋\n    所有，經向被上訴人查詢，被上訴人謂以新台幣（下同）80\n    0 萬元將系爭房地出售，上訴人向被上訴人索取價款，竟置\n    之不理。\n  (二)系爭房地為國宅，由上訴人承購，購屋價款亦由上訴人支付\n    ，另銀行貸款、火災保險、水電費亦由上訴人給付。權狀原\n    由上訴人保管，被上訴人潛行取走，因被上訴人係上訴人之\n    女兒，隨時均可利用上訴人不在家時拿取。系爭房地係由上\n    訴人承購，上訴人亦無將其贈與被上訴人。爰依民法第528\n    條、第541條之委任關係，及民法184條之侵權行為、同法第\n    179條之不當得利等法律關係提起本訴。\n  (三)求為判決：\n    1.被上訴人應給付上訴人800 萬元及自起訴狀繕本送達之翌\n      日起至清償日止按年息5%計算之利息。\n    2.願供擔保請宣告准為假執行。\n二、被上訴人則以：\n  (一)上訴人與被上訴人係父女，80年1 月間由於上訴人原本居住\n    之房屋基地屬國有財產，因而列為地上拆遷戶，上訴人享有\n    國宅配售之優先承購權及領取一筆約700 萬元之補償金。惟\n    上訴人當時已年屆69歲，且已領取一筆約700 萬元之補償金\n    ，早有退休之計劃，故無意願再額外給付一筆費用承購國宅\n    ，遂直接詢問被上訴人有無意願享有此國宅配售之優先承購\n    權，但購屋費用必須自行負擔，被上訴人遂向上訴人表示願\n    意承購。因此，兩造當時合意由被上訴人負擔2,298,457 元\n    之購屋價款，以上訴人名義向臺北市政府承購系爭房地及向\n    臺北市銀行貸款195 萬元，相關之購屋款項、銀行貸款、火\n    災保險費、辦理抵押權設定之費用、及地價稅、房屋稅等費\n    用，均係由被上訴人支出並持有相關契約書及收據正本，且\n    系爭房地之土地及建物所有權狀正本亦由被上訴人持有保管\n    ，系爭房地點交後，由被上訴人為實際管理使用收益，被上\n    訴人將系爭房地出租予第三人。\n  (二)被上訴人承購系爭房地後，依據承購國民住宅暨貸款契約書\n    第16條約定，被上訴人於80年2 月間就系爭房地以上訴人之\n    名義委由臺北市銀行向第一產物保險股份有限公司投保火災\n    保險，總保險費7,970 元由被上訴人以上訴人之名義支付。\n    系爭房地辦理抵押權設定所需之相關費用，亦均由被上訴人\n    支出。而系爭房地於83年8 月25日贈與移轉登記予被上訴人\n    前，地價稅及房屋稅亦均係由被上訴人以上訴人之名義負擔\n    。兩造合意以贈與方式移轉登記，係因兩造為直系血親三親\n    等內之關係，當時若以買賣為移轉登記之原因，國稅局會要\n    求兩造提出買賣資金流向證明，然由於系爭房地於80年1 月\n    間係由被上訴人出資購買，所有費用均由被上訴人負擔，故\n    於83年6、7月間辦理移轉登記時，兩造根本不存在任何買賣\n    資金流向，而被上訴人亦不想為此而假造與上訴人間之買賣\n    資金流向，故以贈與為原因辦理移轉登記。\n  (三)被上訴人於符合71年7月30日修正之國民住宅條例第19條第1\n    項關於限制移轉規定之2 年年限後，上訴人與被上訴人合意\n    將系爭房地過戶予被上訴人，雙方並共同委託代書於83年6\n    、7 月間，以贈與為原因將系爭房地所有權辦理移轉登記予\n    被上訴人。為辦理移轉登記時所需贈與人即上訴人之證件，\n    含印鑑證明、身分證正本等證件，及持印鑑章用印等手續，\n    均係上訴人親自出面委託代書辦理。另為辦理系爭房地所有\n    權移轉登記所須繳納之土地增值稅、契稅、贈與稅及規費等\n    費用均係由被上訴人負擔。系爭房地所有權於83年8 月25日\n    移轉登記予被上訴人後，被上訴人業於83年12月23日如數清\n    償系爭房地之貸款。\n  (四)被上訴人於92年間將系爭房地出售予第三人並取得售屋款項\n    ，並非受上訴人委任而為，未侵害上訴人任何權利，且被上\n    訴人亦非無法律上之原因而受有利益，致上訴人受有損害，\n    上訴人訴請被上訴人給付800 萬元，於法無據等語，資為抗\n    辯。\n三、原審為上訴人敗訴之判決，上訴人提起上訴，上訴聲明為：\n    (一)原判決廢棄。(二)被上訴人應給付上訴人800 萬元及自起訴\n    狀繕本送達翌日起至清償日止，按年息5%計算之利息。(三)請\n    求准供擔保宣告假執行。被上訴人答辯聲明：(一)上訴駁回。\n    (二)如受不利判決，被上訴人願供擔保，請准宣告免為假執行\n    。\n四、本件不爭執事項：坐落臺北市○○區○○段1 小段86-1地號\n    土地及其上門牌號碼為臺北市○○區○○路2段420號9樓之3\n    之建物為國民住宅，80年間以上訴人名義向臺北市政府承購\n    ，被上訴人係上訴人女兒，83年間系爭房地經贈與登記於被\n    上訴人名下，92年9 月18日被上訴人將系爭房地，以買賣為\n    原因移轉登記為訴外人梁愛蘋所有，被上訴人得款800 萬元\n    。\n五、本件爭點：\n  (一)系爭房地何人出資承購，是否被上訴人借用上訴人名義購得\n    ？\n  (二)上訴人有無委任被上訴人出售系爭房地？\n  (三)83年間兩造有無共同委任代書以贈與為原因，辦理系爭房地\n    所有權移轉登記為被上訴人所有？\n  (四)上訴人依民法第528條、第541條之委任關係，及民法184條\n    之侵權行為、同法第179條之不當得利法律關係請求給付，\n    有無理由？\n六、按文書，依其程式及意旨得認作公文書者，推定為真正，民\n    事訴訟法第355條第1項定有明文。次按事實之真偽，應由事\n    實審法院斟酌辯論意旨及調查證據之結果，依自由心證判斷\n    之，苟其判斷並不違背法令，即不許當事人以空言指摘。法\n    院依自由心證判斷事實之真偽，不得違背論理及經驗法則，\n    民事訴訟法第222條第3項亦有明示。所謂論理法則，係指依\n    立法意旨或法規之社會機能就法律事實所為價值判斷之法則\n    而言。所謂經驗法則，係指由社會生活累積的經驗歸納所得\n    之法則而言；凡日常生活所得之通常經驗及基於專門知識所\n    得之特別經驗均屬之（最高法院21年上字第1406號判例、91\n    年台上字第741號判決意旨參照）。\n  (一)關於出資購買系爭房地部分：\n    1.查系爭房地係於80年間以上訴人名義向臺北市政府承購，\n      有臺北市政府出售國民住宅繳款通知書在卷可稽（原審卷\n      (一)第26頁），兩造不爭執。\n    2.次查，80年1月24日承購國民住宅暨貸款契約書，立契約\n      書人為承購人即上訴人與出賣人臺北市政府，契約第3、5\n      條約定，上訴人以2,298,457 元購買系爭房地，臺北市政\n      府依規定貸予上訴人195 萬元，貸款期間20年，契約第16\n      條約定承購人應投保火災保險至貸款清償為止，有契約書\n      在卷可稽（原審卷(二)第13頁）；系爭房地於80年2 月間投\n      保火災保險，保險期間自80年1月24日起至100年1月24 日\n      ，有火災保險單在卷可稽（原審卷(二)第14頁）。上開買賣\n      暨貸款契約書係承購系爭房地時，承購人所應持有之權利\n      文件，且為系爭房地投保火災保險為承購人承購系爭房地\n      應履行之義務。上開文件之持有者為被上訴人，被上訴人\n      另提出火災保險費收據、臺北市地政規費收據、房地產登\n      記費用明細表、82年地價稅及房屋稅繳款書，及國民住宅\n      貸款清償證明書（原審卷(二)第15、19、46頁）。\n    3.上訴人固提出臺北市政府出售國民住宅繳款通知書、臺北\n      市國民住宅處購國宅進住通知單、水、電費通知、臺北市\n      銀行營業部代辦國民住宅基金貸款還款簿（原審卷(一)第26\n      至27頁、第30至110頁）。然上開通知單及繳款單係有關\n      系爭房地應納之貸款及費用，自當以系爭房地之承購人為\n      通知對象，惟上訴人身為承購人，卻未持有原始承購系爭\n      房地之契約書及須投保火災保險之保險單及繳費收據及國\n      民住宅貸款清償證明書。上訴人主張相關文件係由被上訴\n      人自行取走云云，未據上訴人立證證明，不能採信。\n    4.再查，承購系爭房地之後即80年3月1日，被上訴人將系爭\n      房屋出租予第三人，有房屋租賃契約書在卷可稽（原審卷\n      (二)第20至24頁）。依社會一般常情，所有權人或對不動產\n      有權利之人，方會以自己之名義出租房屋而為收益。\n    5.末查，系爭房地於81年2月26日設定本件最高限額500萬元\n      抵押權予被上訴人，債務人為上訴人，有臺北市土地建物\n      登記簿在卷可稽（原審卷(二)第82至83頁）。若上訴人確為\n      出資承購系爭房地之人，當無必要設定抵押權予被上訴人\n      。\n    6.由上事證，被上訴人稱系爭房地係由其出資以上訴人名義\n      登記購買，伊對系爭房屋有實際管理使用收益之權，可以\n      採信。\n  (二)關於83年間系爭房地所有權以贈與為原因移轉登記為被上訴\n    人所有部分：\n    1.上訴人之戶籍僅於80年3月21日至84年5月10日設於系爭房\n      屋之地址，於80年3月21日之前，及84年5月10日之後，上\n      訴人均設籍於臺北市○○區○○街164巷62弄16號地址（\n      即現址忠孝東路5段236巷37弄33號），有戶口名簿、戶籍\n      謄本在卷可稽（本院卷第92、72、82頁）。依承購國民住\n      宅暨貸款契約書第12條約定，承購之住宅及基地居住滿2\n      年後，得依國民住宅條例第19條暨施行細則第27條規定，\n      經臺北市政府同意後，將該住宅及基地出售、出典、贈與\n      或交換予具有承購國民住宅之資格者。由上事證足認，上\n      訴人設籍於系爭房屋，即於80年1月間承購後至83年間以\n      贈與為原因移轉登記時，係為符合系爭房地應居住滿2年\n      之移轉限制。\n    2.查上訴人於83年5 月28日書立理由書予臺北市政府國民住\n      宅處，申請將系爭房地贈與予被上訴人，經臺北市政府國\n      民住宅處函覆略以：「台端等所有臺北市○○路○段420號\n      9 樓之3國輝國宅及基地（持分120/50000）申請贈與給丙\n      ○○君乙節，本處同意」，有83年7月2日（83）北市宅三\n      字第16522 號函及申請書相關文件在卷可稽（本院卷第76\n      至96頁）。次查，兩造於83年7月1日於臺灣臺北地方法院\n      公證處，請求公證上訴人將系爭房屋贈與予被上訴人，有\n      83年義公字第30513 號公證書在卷可稽（本院卷第66至67\n      頁），並經本院調閱該公證卷宗查核屬實。嗣於83年6 月\n      22日、7月1日，系爭房地以贈與為原因申請所有權移轉登\n      記，贈與人為上訴人，受贈人為被上訴人，有土地登記申\n      請書、土地及建築改良物贈與所有權移轉契約書在卷可稽\n      （原審卷(二)第25至30頁）。由上事證足認，系爭房地以贈\n      與為原因移轉所有權登記予被上訴人。\n    3.上訴人之戶籍僅於80年3月21日至84年5月10日設於系爭房\n      屋之地址，於80年3月21日之前，及84年5月10日之後，上\n      訴人均設籍於臺北市○○區○○街164 巷62弄16號地址（\n      即現址忠孝東路5段236巷37弄33號），有戶口名簿、戶籍\n      謄本在卷可稽（本院卷第92、72、82頁）。依承購國民住\n      宅暨貸款契約書第12條約定，承購之住宅及基地居住滿2\n      年後，得依國民住宅條例第19條暨施行細則第27條規定，\n      經臺北市政府同意後，將該住宅及基地出售、出典、贈與\n      或交換予具有承購國民住宅之資格者。由上事證足認，上\n      訴人設籍於系爭房屋，即於80年1 月間承購後至83年間以\n      贈與為原因移轉登記時，係為符合系爭房地應居住滿2 年\n      之移轉限制期間。參以被上訴人以上訴人名義出資購買系\n      爭房地（詳前理由(一)所述），被上訴人與上訴人間就系爭\n      房地並無買賣之事實，被上訴人與上訴人以贈與為原因移\n      轉系爭房地之所有權登記，係符常情。\n    4.末查，系爭房地之贈與所有權契約書約定：受贈人（即被\n      上訴人）應承擔贈與人（即上訴人）就本不動產向銀行之\n      貸款，有土地及建築改良物贈與所有權移轉契約書在卷可\n      稽（原審卷(二)第28、30頁）。嗣於83年12月23日系爭房地\n      之貸款全部清償，被上訴人持有國民住宅貸款清償證明書\n      （原審卷(二)第46頁）。\n    5.綜上，被上訴人抗辯上訴人同意於系爭房地符合限制移轉\n      登記年限後，將系爭房地移轉登記予被上訴人等語，可以\n      採信。\n七、關於上訴人有無委任被上訴人出售系爭房地部分：\n    按當事人主張有利於己之事實者，就其事實有舉證之責任，\n    民事訴訟法第277 條前段定有明文。次按請求履行債務之訴\n    ，除被告自認原告所主張債權發生原因之事實外，應先由原\n    告就其主張此項事實，負舉證之責任，必須證明其為真實後\n    ，被告於其抗辯事實，始應負證明之責任，此為舉證責任分\n    擔之原則（最高法院43年台上字第377號判例意旨參照）。\n  (一)上訴人主張其於83年間委任被上訴人出售系爭房地，為被上\n    訴人否認。證人乙○○於原審證稱略以：因為被上訴人是做\n    房地產的，上訴人買系爭房地的時候，有很多人告訴上訴人\n    可以賣不錯的價錢，但因為剛買，所以不想賣，後來83年左\n    右上訴人想要賣房子，就叫被上訴人幫忙賣等語。在83年5\n    、6 月的時候決定要賣，這些事是上訴人告訴伊，上訴人說\n    只有委託被上訴人去賣，沒有要贈與的意思等語（原審卷(二)\n    第71頁反面、第73頁反面）。證人乙○○於本院先證稱：「\n    83年間上訴人有委任被上訴人出售系爭國宅。有將印章、國\n    民身份證、印鑑證明等交予被上訴人」，嗣又稱：「1991年\n    間，我問被上訴人系爭國宅，上訴人有無請被上訴人賣，被\n    上訴人表示上訴人把上開文件交給被上訴人，叫她賣系爭國\n    宅」（本院卷第106頁反面、第107頁）。證人乙○○就上訴\n    人委託被上訴人出賣系爭房地之時間，前後陳述不一致，且\n    證人乙○○係上訴人之女兒，難期證言為真正，不能逕信。\n  (二)證人甲○○證稱略以：系爭房地係由上訴人承購，上訴人並\n    未將系爭房地贈與予被上訴人，亦無與被上訴人共同委任代\n    書以贈與為原因將系爭房地過戶予被上訴人，亦無與被上訴\n    人共同委任代書將系爭房地為被上訴人辦理抵押權設定登記\n    ，上訴人有委任被上訴人出售系爭房地，將印章、國民身份\n    證、印鑑證明等交予被上訴人，上開事項係伊與上訴人談話\n    中知悉等語（本院卷第107頁至反面）。證人甲○○為上訴\n    人之女，作證事項係聽聞自上訴人，其證言不能採信。\n  (三)再查，上訴人主張被上訴人於98年3月25日電話中承認將系\n    爭房地偷偷賣掉之事實，另於98年2月至6月間之電話談話中\n    ，上訴人並無贈與系爭房地予被上訴人等語，提出電話譯文\n    4件（原審卷(一)第112至186頁）。經查，上開電話譯文係被\n    上訴人與證人乙○○及兩造就系爭房地出售及贈與等節互為\n    爭執之對話，尚難為有利於上訴人之認定。\n  (四)上訴人主張被上訴人自79年11月間就計畫奪產，提出79年11\n    月間上訴人寄予證人乙○○之信件（本院卷第57至59頁）。\n    惟查，上開信件之時間為79年11月間，斯時系爭房地尚未承\n    購，尚難以該信件為有利於上訴人之認定。\n  (五)末查，上訴人起訴主張於83年6月委任被上訴人出售系爭房\n    地，迄於97年下半年申請系爭房地之登記謄本時，始發現被\n    上訴人出售系爭房地予第三人之情事（原法院司重調字卷第\n    3頁）。依上訴人所述，自83年6月間至97年下半年，長達14\n    年，上訴人始發現系爭房地出售之情事。衡諸社會常情，委\n    託他人出售不動產此等高價資產，應會密切注意委託事務進\n    行之進度，上訴人長達14年間就委託出售系爭房地之事未為\n    聞問，與一般經驗法則不符。\n  (六)上訴人未舉其他證據證明其委託被上訴人間出售系爭房地，\n    上訴人主張其與被上訴人間有委任之法律關係存在，請求被\n    上訴人給付出售系爭房地之款項800萬元，為無理由。\n八、按因故意或過失，不法侵害他人之權利者，負損害賠償責任\n    。故意以背於善良風俗之方法，加損害於他人者，亦同，民\n    法第184條第1項定有明文。查系爭房地由被上訴人借用上訴\n    人之名義出資購買，嗣以贈與為原因，移轉登記所有權予被\n    上訴人，業經認定詳前述。被上訴人將自己名下之系爭房地\n    出售予第三人，並無侵害上訴人之權利，或以背於善良風俗\n    之方法加損害於上訴人。上訴人依據民法第184 條規定，請\n    求被上訴人給付系爭房地出售之價款800萬元，為無理由。\n九、按無法律上之原因而受利益，致他人受損害者，應返還其利\n    益；雖有法律上之原因，而其後已不存在者，亦同，民法第\n    179 條定有明文。系爭房地於83年間以贈與為原因移轉登記\n    予被上訴人，被上訴人將系爭房地出售得款800 萬元，係為\n    有權處分，並無受利益致上訴人受損害。上訴人依據民法第\n    179條規定，請求被上訴人給付系爭房地出售之價款800萬元\n    ，為無理由。\n十、綜上所述，上訴人主張本於民法第528條、第541條、第184\n    條、第179條法律關係，請求被上訴人給付800萬元，及自起\n    訴狀繕本送達翌日起至清償日止，按年息5%計算之利息，為\n    無理由，不應准許。原審為上訴人敗訴之判決，及駁回其假\n    執行之聲請，並無不合。上訴意旨指摘原判決不當，求予廢\n    棄改判，為無理由，應予駁回。\n十一、上訴人聲請鑑定臺北市政府國民住宅處所附贈與之理由書\n      其上之簽名，核無必要，附此說明。\n十二、本件事證已臻明確，兩造其餘攻擊防禦方法及未經援用之\n      舉證，經審酌核與本件判決結果不生影響，不再逐一論述\n      ，附此敘明。\n十三、據上論結，本件上訴為無理由，依民事訴訟法第449條第1\n      項、第78條，判決如主文。",
    "reason": "一、上訴人起訴主張：\n  (一)上訴人於民國（下同）83年6月初，委任三女即被上訴人出\n    售其所有坐落臺北市○○區○○段86-1地號土地及其上門牌\n    號碼為臺北市○○區○○路2段420號9樓之3之建物（下稱系\n    爭房地），83年6月底，上訴人詢問被上訴人已否賣出、價\n    金多少，被上訴人竟謂已先辦理贈與登記在被上訴人名下再\n    賣，此後一直沒消息。直至97年下半年，上訴人申請系爭房\n    地之土地及建築改良物登記簿謄本，發現被上訴人早已在92\n    年9 月18日將系爭房地辦理所有權移轉登記為訴外人梁愛蘋\n    所有，經向被上訴人查詢，被上訴人謂以新台幣（下同）80\n    0 萬元將系爭房地出售，上訴人向被上訴人索取價款，竟置\n    之不理。\n  (二)系爭房地為國宅，由上訴人承購，購屋價款亦由上訴人支付\n    ，另銀行貸款、火災保險、水電費亦由上訴人給付。權狀原\n    由上訴人保管，被上訴人潛行取走，因被上訴人係上訴人之\n    女兒，隨時均可利用上訴人不在家時拿取。系爭房地係由上\n    訴人承購，上訴人亦無將其贈與被上訴人。爰依民法第528\n    條、第541條之委任關係，及民法184條之侵權行為、同法第\n    179條之不當得利等法律關係提起本訴。\n  (三)求為判決：\n    1.被上訴人應給付上訴人800 萬元及自起訴狀繕本送達之翌\n      日起至清償日止按年息5%計算之利息。\n    2.願供擔保請宣告准為假執行。\n二、被上訴人則以：\n  (一)上訴人與被上訴人係父女，80年1 月間由於上訴人原本居住\n    之房屋基地屬國有財產，因而列為地上拆遷戶，上訴人享有\n    國宅配售之優先承購權及領取一筆約700 萬元之補償金。惟\n    上訴人當時已年屆69歲，且已領取一筆約700 萬元之補償金\n    ，早有退休之計劃，故無意願再額外給付一筆費用承購國宅\n    ，遂直接詢問被上訴人有無意願享有此國宅配售之優先承購\n    權，但購屋費用必須自行負擔，被上訴人遂向上訴人表示願\n    意承購。因此，兩造當時合意由被上訴人負擔2,298,457 元\n    之購屋價款，以上訴人名義向臺北市政府承購系爭房地及向\n    臺北市銀行貸款195 萬元，相關之購屋款項、銀行貸款、火\n    災保險費、辦理抵押權設定之費用、及地價稅、房屋稅等費\n    用，均係由被上訴人支出並持有相關契約書及收據正本，且\n    系爭房地之土地及建物所有權狀正本亦由被上訴人持有保管\n    ，系爭房地點交後，由被上訴人為實際管理使用收益，被上\n    訴人將系爭房地出租予第三人。\n  (二)被上訴人承購系爭房地後，依據承購國民住宅暨貸款契約書\n    第16條約定，被上訴人於80年2 月間就系爭房地以上訴人之\n    名義委由臺北市銀行向第一產物保險股份有限公司投保火災\n    保險，總保險費7,970 元由被上訴人以上訴人之名義支付。\n    系爭房地辦理抵押權設定所需之相關費用，亦均由被上訴人\n    支出。而系爭房地於83年8 月25日贈與移轉登記予被上訴人\n    前，地價稅及房屋稅亦均係由被上訴人以上訴人之名義負擔\n    。兩造合意以贈與方式移轉登記，係因兩造為直系血親三親\n    等內之關係，當時若以買賣為移轉登記之原因，國稅局會要\n    求兩造提出買賣資金流向證明，然由於系爭房地於80年1 月\n    間係由被上訴人出資購買，所有費用均由被上訴人負擔，故\n    於83年6、7月間辦理移轉登記時，兩造根本不存在任何買賣\n    資金流向，而被上訴人亦不想為此而假造與上訴人間之買賣\n    資金流向，故以贈與為原因辦理移轉登記。\n  (三)被上訴人於符合71年7月30日修正之國民住宅條例第19條第1\n    項關於限制移轉規定之2 年年限後，上訴人與被上訴人合意\n    將系爭房地過戶予被上訴人，雙方並共同委託代書於83年6\n    、7 月間，以贈與為原因將系爭房地所有權辦理移轉登記予\n    被上訴人。為辦理移轉登記時所需贈與人即上訴人之證件，\n    含印鑑證明、身分證正本等證件，及持印鑑章用印等手續，\n    均係上訴人親自出面委託代書辦理。另為辦理系爭房地所有\n    權移轉登記所須繳納之土地增值稅、契稅、贈與稅及規費等\n    費用均係由被上訴人負擔。系爭房地所有權於83年8 月25日\n    移轉登記予被上訴人後，被上訴人業於83年12月23日如數清\n    償系爭房地之貸款。\n  (四)被上訴人於92年間將系爭房地出售予第三人並取得售屋款項\n    ，並非受上訴人委任而為，未侵害上訴人任何權利，且被上\n    訴人亦非無法律上之原因而受有利益，致上訴人受有損害，\n    上訴人訴請被上訴人給付800 萬元，於法無據等語，資為抗\n    辯。\n三、原審為上訴人敗訴之判決，上訴人提起上訴，上訴聲明為：\n    (一)原判決廢棄。(二)被上訴人應給付上訴人800 萬元及自起訴\n    狀繕本送達翌日起至清償日止，按年息5%計算之利息。(三)請\n    求准供擔保宣告假執行。被上訴人答辯聲明：(一)上訴駁回。\n    (二)如受不利判決，被上訴人願供擔保，請准宣告免為假執行\n    。\n四、本件不爭執事項：坐落臺北市○○區○○段1 小段86-1地號\n    土地及其上門牌號碼為臺北市○○區○○路2段420號9樓之3\n    之建物為國民住宅，80年間以上訴人名義向臺北市政府承購\n    ，被上訴人係上訴人女兒，83年間系爭房地經贈與登記於被\n    上訴人名下，92年9 月18日被上訴人將系爭房地，以買賣為\n    原因移轉登記為訴外人梁愛蘋所有，被上訴人得款800 萬元\n    。\n五、本件爭點：\n  (一)系爭房地何人出資承購，是否被上訴人借用上訴人名義購得\n    ？\n  (二)上訴人有無委任被上訴人出售系爭房地？\n  (三)83年間兩造有無共同委任代書以贈與為原因，辦理系爭房地\n    所有權移轉登記為被上訴人所有？\n  (四)上訴人依民法第528條、第541條之委任關係，及民法184條\n    之侵權行為、同法第179條之不當得利法律關係請求給付，\n    有無理由？\n六、按文書，依其程式及意旨得認作公文書者，推定為真正，民\n    事訴訟法第355條第1項定有明文。次按事實之真偽，應由事\n    實審法院斟酌辯論意旨及調查證據之結果，依自由心證判斷\n    之，苟其判斷並不違背法令，即不許當事人以空言指摘。法\n    院依自由心證判斷事實之真偽，不得違背論理及經驗法則，\n    民事訴訟法第222條第3項亦有明示。所謂論理法則，係指依\n    立法意旨或法規之社會機能就法律事實所為價值判斷之法則\n    而言。所謂經驗法則，係指由社會生活累積的經驗歸納所得\n    之法則而言；凡日常生活所得之通常經驗及基於專門知識所\n    得之特別經驗均屬之（最高法院21年上字第1406號判例、91\n    年台上字第741號判決意旨參照）。\n  (一)關於出資購買系爭房地部分：\n    1.查系爭房地係於80年間以上訴人名義向臺北市政府承購，\n      有臺北市政府出售國民住宅繳款通知書在卷可稽（原審卷\n      (一)第26頁），兩造不爭執。\n    2.次查，80年1月24日承購國民住宅暨貸款契約書，立契約\n      書人為承購人即上訴人與出賣人臺北市政府，契約第3、5\n      條約定，上訴人以2,298,457 元購買系爭房地，臺北市政\n      府依規定貸予上訴人195 萬元，貸款期間20年，契約第16\n      條約定承購人應投保火災保險至貸款清償為止，有契約書\n      在卷可稽（原審卷(二)第13頁）；系爭房地於80年2 月間投\n      保火災保險，保險期間自80年1月24日起至100年1月24 日\n      ，有火災保險單在卷可稽（原審卷(二)第14頁）。上開買賣\n      暨貸款契約書係承購系爭房地時，承購人所應持有之權利\n      文件，且為系爭房地投保火災保險為承購人承購系爭房地\n      應履行之義務。上開文件之持有者為被上訴人，被上訴人\n      另提出火災保險費收據、臺北市地政規費收據、房地產登\n      記費用明細表、82年地價稅及房屋稅繳款書，及國民住宅\n      貸款清償證明書（原審卷(二)第15、19、46頁）。\n    3.上訴人固提出臺北市政府出售國民住宅繳款通知書、臺北\n      市國民住宅處購國宅進住通知單、水、電費通知、臺北市\n      銀行營業部代辦國民住宅基金貸款還款簿（原審卷(一)第26\n      至27頁、第30至110頁）。然上開通知單及繳款單係有關\n      系爭房地應納之貸款及費用，自當以系爭房地之承購人為\n      通知對象，惟上訴人身為承購人，卻未持有原始承購系爭\n      房地之契約書及須投保火災保險之保險單及繳費收據及國\n      民住宅貸款清償證明書。上訴人主張相關文件係由被上訴\n      人自行取走云云，未據上訴人立證證明，不能採信。\n    4.再查，承購系爭房地之後即80年3月1日，被上訴人將系爭\n      房屋出租予第三人，有房屋租賃契約書在卷可稽（原審卷\n      (二)第20至24頁）。依社會一般常情，所有權人或對不動產\n      有權利之人，方會以自己之名義出租房屋而為收益。\n    5.末查，系爭房地於81年2月26日設定本件最高限額500萬元\n      抵押權予被上訴人，債務人為上訴人，有臺北市土地建物\n      登記簿在卷可稽（原審卷(二)第82至83頁）。若上訴人確為\n      出資承購系爭房地之人，當無必要設定抵押權予被上訴人\n      。\n    6.由上事證，被上訴人稱系爭房地係由其出資以上訴人名義\n      登記購買，伊對系爭房屋有實際管理使用收益之權，可以\n      採信。\n  (二)關於83年間系爭房地所有權以贈與為原因移轉登記為被上訴\n    人所有部分：\n    1.上訴人之戶籍僅於80年3月21日至84年5月10日設於系爭房\n      屋之地址，於80年3月21日之前，及84年5月10日之後，上\n      訴人均設籍於臺北市○○區○○街164巷62弄16號地址（\n      即現址忠孝東路5段236巷37弄33號），有戶口名簿、戶籍\n      謄本在卷可稽（本院卷第92、72、82頁）。依承購國民住\n      宅暨貸款契約書第12條約定，承購之住宅及基地居住滿2\n      年後，得依國民住宅條例第19條暨施行細則第27條規定，\n      經臺北市政府同意後，將該住宅及基地出售、出典、贈與\n      或交換予具有承購國民住宅之資格者。由上事證足認，上\n      訴人設籍於系爭房屋，即於80年1月間承購後至83年間以\n      贈與為原因移轉登記時，係為符合系爭房地應居住滿2年\n      之移轉限制。\n    2.查上訴人於83年5 月28日書立理由書予臺北市政府國民住\n      宅處，申請將系爭房地贈與予被上訴人，經臺北市政府國\n      民住宅處函覆略以：「台端等所有臺北市○○路○段420號\n      9 樓之3國輝國宅及基地（持分120/50000）申請贈與給丙\n      ○○君乙節，本處同意」，有83年7月2日（83）北市宅三\n      字第16522 號函及申請書相關文件在卷可稽（本院卷第76\n      至96頁）。次查，兩造於83年7月1日於臺灣臺北地方法院\n      公證處，請求公證上訴人將系爭房屋贈與予被上訴人，有\n      83年義公字第30513 號公證書在卷可稽（本院卷第66至67\n      頁），並經本院調閱該公證卷宗查核屬實。嗣於83年6 月\n      22日、7月1日，系爭房地以贈與為原因申請所有權移轉登\n      記，贈與人為上訴人，受贈人為被上訴人，有土地登記申\n      請書、土地及建築改良物贈與所有權移轉契約書在卷可稽\n      （原審卷(二)第25至30頁）。由上事證足認，系爭房地以贈\n      與為原因移轉所有權登記予被上訴人。\n    3.上訴人之戶籍僅於80年3月21日至84年5月10日設於系爭房\n      屋之地址，於80年3月21日之前，及84年5月10日之後，上\n      訴人均設籍於臺北市○○區○○街164 巷62弄16號地址（\n      即現址忠孝東路5段236巷37弄33號），有戶口名簿、戶籍\n      謄本在卷可稽（本院卷第92、72、82頁）。依承購國民住\n      宅暨貸款契約書第12條約定，承購之住宅及基地居住滿2\n      年後，得依國民住宅條例第19條暨施行細則第27條規定，\n      經臺北市政府同意後，將該住宅及基地出售、出典、贈與\n      或交換予具有承購國民住宅之資格者。由上事證足認，上\n      訴人設籍於系爭房屋，即於80年1 月間承購後至83年間以\n      贈與為原因移轉登記時，係為符合系爭房地應居住滿2 年\n      之移轉限制期間。參以被上訴人以上訴人名義出資購買系\n      爭房地（詳前理由(一)所述），被上訴人與上訴人間就系爭\n      房地並無買賣之事實，被上訴人與上訴人以贈與為原因移\n      轉系爭房地之所有權登記，係符常情。\n    4.末查，系爭房地之贈與所有權契約書約定：受贈人（即被\n      上訴人）應承擔贈與人（即上訴人）就本不動產向銀行之\n      貸款，有土地及建築改良物贈與所有權移轉契約書在卷可\n      稽（原審卷(二)第28、30頁）。嗣於83年12月23日系爭房地\n      之貸款全部清償，被上訴人持有國民住宅貸款清償證明書\n      （原審卷(二)第46頁）。\n    5.綜上，被上訴人抗辯上訴人同意於系爭房地符合限制移轉\n      登記年限後，將系爭房地移轉登記予被上訴人等語，可以\n      採信。\n七、關於上訴人有無委任被上訴人出售系爭房地部分：\n    按當事人主張有利於己之事實者，就其事實有舉證之責任，\n    民事訴訟法第277 條前段定有明文。次按請求履行債務之訴\n    ，除被告自認原告所主張債權發生原因之事實外，應先由原\n    告就其主張此項事實，負舉證之責任，必須證明其為真實後\n    ，被告於其抗辯事實，始應負證明之責任，此為舉證責任分\n    擔之原則（最高法院43年台上字第377號判例意旨參照）。\n  (一)上訴人主張其於83年間委任被上訴人出售系爭房地，為被上\n    訴人否認。證人乙○○於原審證稱略以：因為被上訴人是做\n    房地產的，上訴人買系爭房地的時候，有很多人告訴上訴人\n    可以賣不錯的價錢，但因為剛買，所以不想賣，後來83年左\n    右上訴人想要賣房子，就叫被上訴人幫忙賣等語。在83年5\n    、6 月的時候決定要賣，這些事是上訴人告訴伊，上訴人說\n    只有委託被上訴人去賣，沒有要贈與的意思等語（原審卷(二)\n    第71頁反面、第73頁反面）。證人乙○○於本院先證稱：「\n    83年間上訴人有委任被上訴人出售系爭國宅。有將印章、國\n    民身份證、印鑑證明等交予被上訴人」，嗣又稱：「1991年\n    間，我問被上訴人系爭國宅，上訴人有無請被上訴人賣，被\n    上訴人表示上訴人把上開文件交給被上訴人，叫她賣系爭國\n    宅」（本院卷第106頁反面、第107頁）。證人乙○○就上訴\n    人委託被上訴人出賣系爭房地之時間，前後陳述不一致，且\n    證人乙○○係上訴人之女兒，難期證言為真正，不能逕信。\n  (二)證人甲○○證稱略以：系爭房地係由上訴人承購，上訴人並\n    未將系爭房地贈與予被上訴人，亦無與被上訴人共同委任代\n    書以贈與為原因將系爭房地過戶予被上訴人，亦無與被上訴\n    人共同委任代書將系爭房地為被上訴人辦理抵押權設定登記\n    ，上訴人有委任被上訴人出售系爭房地，將印章、國民身份\n    證、印鑑證明等交予被上訴人，上開事項係伊與上訴人談話\n    中知悉等語（本院卷第107頁至反面）。證人甲○○為上訴\n    人之女，作證事項係聽聞自上訴人，其證言不能採信。\n  (三)再查，上訴人主張被上訴人於98年3月25日電話中承認將系\n    爭房地偷偷賣掉之事實，另於98年2月至6月間之電話談話中\n    ，上訴人並無贈與系爭房地予被上訴人等語，提出電話譯文\n    4件（原審卷(一)第112至186頁）。經查，上開電話譯文係被\n    上訴人與證人乙○○及兩造就系爭房地出售及贈與等節互為\n    爭執之對話，尚難為有利於上訴人之認定。\n  (四)上訴人主張被上訴人自79年11月間就計畫奪產，提出79年11\n    月間上訴人寄予證人乙○○之信件（本院卷第57至59頁）。\n    惟查，上開信件之時間為79年11月間，斯時系爭房地尚未承\n    購，尚難以該信件為有利於上訴人之認定。\n  (五)末查，上訴人起訴主張於83年6月委任被上訴人出售系爭房\n    地，迄於97年下半年申請系爭房地之登記謄本時，始發現被\n    上訴人出售系爭房地予第三人之情事（原法院司重調字卷第\n    3頁）。依上訴人所述，自83年6月間至97年下半年，長達14\n    年，上訴人始發現系爭房地出售之情事。衡諸社會常情，委\n    託他人出售不動產此等高價資產，應會密切注意委託事務進\n    行之進度，上訴人長達14年間就委託出售系爭房地之事未為\n    聞問，與一般經驗法則不符。\n  (六)上訴人未舉其他證據證明其委託被上訴人間出售系爭房地，\n    上訴人主張其與被上訴人間有委任之法律關係存在，請求被\n    上訴人給付出售系爭房地之款項800萬元，為無理由。\n八、按因故意或過失，不法侵害他人之權利者，負損害賠償責任\n    。故意以背於善良風俗之方法，加損害於他人者，亦同，民\n    法第184條第1項定有明文。查系爭房地由被上訴人借用上訴\n    人之名義出資購買，嗣以贈與為原因，移轉登記所有權予被\n    上訴人，業經認定詳前述。被上訴人將自己名下之系爭房地\n    出售予第三人，並無侵害上訴人之權利，或以背於善良風俗\n    之方法加損害於上訴人。上訴人依據民法第184 條規定，請\n    求被上訴人給付系爭房地出售之價款800萬元，為無理由。\n九、按無法律上之原因而受利益，致他人受損害者，應返還其利\n    益；雖有法律上之原因，而其後已不存在者，亦同，民法第\n    179 條定有明文。系爭房地於83年間以贈與為原因移轉登記\n    予被上訴人，被上訴人將系爭房地出售得款800 萬元，係為\n    有權處分，並無受利益致上訴人受損害。上訴人依據民法第\n    179條規定，請求被上訴人給付系爭房地出售之價款800萬元\n    ，為無理由。\n十、綜上所述，上訴人主張本於民法第528條、第541條、第184\n    條、第179條法律關係，請求被上訴人給付800萬元，及自起\n    訴狀繕本送達翌日起至清償日止，按年息5%計算之利息，為\n    無理由，不應准許。原審為上訴人敗訴之判決，及駁回其假\n    執行之聲請，並無不合。上訴意旨指摘原判決不當，求予廢\n    棄改判，為無理由，應予駁回。\n十一、上訴人聲請鑑定臺北市政府國民住宅處所附贈與之理由書\n      其上之簽名，核無必要，附此說明。\n十二、本件事證已臻明確，兩造其餘攻擊防禦方法及未經援用之\n      舉證，經審酌核與本件判決結果不生影響，不再逐一論述\n      ，附此敘明。\n十三、據上論結，本件上訴為無理由，依民事訴訟法第449條第1\n      項、第78條，判決如主文。"
  },
  "characters": {
    "judges": [
      "吳謙仁",
      "蘇瑞華",
      "李瓊蔭"
    ],
    "prosecutors": [

    ],
    "lawyers": [
      "張瑞釗",
      "陳建勳",
      "張弘明",
      "有",
      "人或其他法定代理人具有"
    ],
    "clerks": [
      "王才生"
    ],
    "plaintiffs": [

    ],
    "defendants": [

    ],
    "prosecutor_office": [

    ],
    "creditors": [

    ],
    "debtors": [

    ],
    "judicial_associate_officer": [

    ]
  },
  "adjudged_at": "2010-05-12",
  "created_at": "2016-01-05 11:56:08",
  "updated_at": "2016-01-05 11:56:08"
}