{
  "identify": "TPH-99-聲-2-20100104-1",
  "court": {
    "name": "臺灣高等法院",
    "code": "TPH"
  },
  "division": {
    "name": "刑事",
    "code": "M"
  },
  "year": 99,
  "word": "聲",
  "number": "2",
  "jcheck": "1",
  "reason": "聲請定其應執行刑",
  "content": "臺灣高等法院刑事裁定                     99年度聲字第2號\n聲  請  人  臺灣高等法院檢察署檢察官\n受  刑  人  甲○○\n                    現於臺灣臺北監獄執行中\n上列聲請人因受刑人數罪併罰有二裁判以上，聲請定其應執行之\n刑，本院裁定如下：\n    主  文\n甲○○因犯如附表所示各罪所處之刑，應執行有期徒刑貳年。\n    理  由\n一、本件受刑人甲○○因犯如附表所示各罪，經本院、臺灣士林\n    地方法院先後判處如附表所示之宣告刑，均經分別確定在案\n    。茲檢察官向最後事實審之本院聲請就受刑人所犯各罪所處\n    之有期徒刑定其應執行之刑，本院審核認聲請為正當，爰依\n    刑法第51條第5款規定，定其應執行之刑。\n二、據上論結，應依刑事訴訟法第477條第1項、刑法第53條、第\n    51條第5款，裁定如主文。\n中    華    民    國    99    年    1     月    4     日\n                  刑事第八庭審判長法  官  張傳栗\n                                  法  官  郭豫珍\n                                  法  官  劉嶽承\n以上正本證明與原本無異。\n如不服本裁定，應於收受送達後五日內向本院提出抗告狀。\n                                  書記官  何仁崴\n中    華    民    國    99    年    1     月    4     日\n",
  "structure": {
    "main": "甲○○因犯如附表所示各罪所處之刑，應執行有期徒刑貳年。",
    "reason": "一、本件受刑人甲○○因犯如附表所示各罪，經本院、臺灣士林\n    地方法院先後判處如附表所示之宣告刑，均經分別確定在案\n    。茲檢察官向最後事實審之本院聲請就受刑人所犯各罪所處\n    之有期徒刑定其應執行之刑，本院審核認聲請為正當，爰依\n    刑法第51條第5款規定，定其應執行之刑。\n二、據上論結，應依刑事訴訟法第477條第1項、刑法第53條、第\n    51條第5款，裁定如主文。"
  },
  "characters": {
    "judges": [
      "張傳栗",
      "郭豫珍",
      "劉嶽承"
    ],
    "prosecutors": [

    ],
    "lawyers": [

    ],
    "clerks": [
      "何仁崴"
    ],
    "plaintiffs": [

    ],
    "defendants": [

    ],
    "prosecutor_office": [
      "臺灣高等法院檢察署檢察官"
    ],
    "creditors": [

    ],
    "debtors": [

    ],
    "judicial_associate_officer": [

    ]
  },
  "adjudged_at": "2010-01-04",
  "created_at": "2016-01-05 14:34:38",
  "updated_at": "2016-01-05 14:34:38"
}