{
  "identify": "TPH-98-上訴-4209-20100105-2",
  "court": {
    "name": "臺灣高等法院",
    "code": "TPH"
  },
  "division": {
    "name": "刑事",
    "code": "M"
  },
  "year": 98,
  "word": "上訴",
  "number": "4209",
  "jcheck": "2",
  "reason": "毒品危害防制條例",
  "content": "臺灣高等法院刑事裁定                98年度上訴字第4209號\n上  訴  人  臺灣板橋地方法院檢察署檢察官\n上  訴  人\n即  被  告  甲○○\n                    （現於臺灣臺北看守所羈押中）\n指定辯護人  義務辯護人  劉宏邈律師\n指定辯護人  本院公設辯護人  郭書益\n上列被告因違反毒品危害防制條例上訴案件，本院裁定如下：\n    主  文\n甲○○羈押期間，自民國九十九年一月十九日起，延長貳月。\n    理  由\n一、上列上訴人即被告甲○○因違反違反毒品危害防制條例案件\n    ，前經本院訊問後，認依原審及本院判決引用各項證據，其\n    涉犯毒品危害防制條例第四條第一項之販賣第一級毒品罪，\n    犯罪嫌疑重大，有相當理由足認被告甲○○有刑事訴訟法第\n    一百零一條第一項第三款所定之情形，非予羈押顯難進行審\n    判或執行，而有羈押之必要，於九十八年十月十九日執行羈\n    押。茲查其羈押期間至九十九年一月十八日即將屆滿，而經\n    本院於九十九年一月四日訊問被告甲○○後，認前項原因仍\n    然存在，尚有繼續羈押之必要，自九十九年一月十九日起延\n    長羈押二月。\n二、按刑事訴訟法第一百零一條第一項所定：「被告經法官訊問\n    後，認為犯罪嫌疑重大，而有左列情形之一，非予羈押，顯\n    難進行追訴、審判或執行者，得羈押之︰一、逃亡或有事實\n    足認為有逃亡之虞者。二、有事實足認為有湮滅、偽造、變\n    造證據或勾串共犯或證人之虞者。三、所犯為死刑、無期徒\n    刑或最輕本刑為五年以上有期徒刑之罪者。」，首段文字即\n    表明羈押之目的，唯在於保全之必要，且受比例原則限制。\n    次按「基於憲法保障人民身體自由之意旨，被告犯上開重罪\n    條款且嫌疑重大者，仍應有相當理由認為其有逃亡、湮滅、\n    偽造、變造證據或勾串共犯或證人等之虞，法院斟酌命該被\n    告具保、責付或限制住居等侵害較小之手段，均不足以確保\n    追訴、審判或執行程序之順利進行，此際予以羈押，方堪稱\n    係屬維持刑事司法權有效行使之最後必要手段。是被告縱然\n    符合上揭第三款之羈押事由，法官仍須就犯罪嫌疑是否重大\n    、有無羈押必要、有無不得羈押之情形予以審酌，非謂一符\n    合該款規定之羈押事由，即得予以羈押。」，業經司法院釋\n    字第六六五號解釋釋明在案。\n三、旨揭大法官會議之解釋文已經指明刑事訴訟法第一百零一條\n    第一項第三款之羈押事由，必須具備有「相當理由」之要件\n    ，始符合憲法規範之要求。大法官理由既謂「相當理由」，\n    即與同條項第一款、第二款法律條文所規定之「有事實足認\n    有．．．之虞」之要件有所不同。兩者之區別，可以顯現在\n    所要求證明度高低的差異上，亦即刑事訴訟法第一百零一條\n    第一款、第二款之羈押事由，必須國家機關所提出被告有逃\n    亡、滅證之虞的具體事實，經綜合評估個案有利及不利被告\n    的一切事證後，能達到明白有力（clear and convincing）\n    之證明度，但在第三款情形相關事證不用證明至明白有力的\n    證明度，而只要綜合個案具體情況，可堪認定被告逃亡滅證\n    的可能性高於不逃亡滅證的可能性即可，或稱為優勢之證明\n    。亦即「重罪常伴有逃亡、滅證之高度可能，係趨吉避凶、\n    脫免刑責、不甘受罰之基本人性，倘一般正常之人，依其合\n    理判斷，可認為該犯重罪嫌疑具有逃亡或滅證之相當或然率\n    存在，即已該當『相當理由』之認定標準，不以達到充分可\n    信或確定程度為必要。以量化為諭，若依客觀、正常之社會\n    通念，認為其人已有超過百分之五十之逃亡、滅證可能性者\n    ，當可認為具有相當理由認為其有逃亡、滅證之虞」（詳最\n    高法院九十八年度台抗字第六六八號裁定意旨參照）。另外\n    一項區別也可以顯現在重罪羈押的立法目的之達成上，此一\n    如大法官會議解釋理由書所言，必須綜合判斷重罪羈押有無\n    牴觸無罪推定原則、武器平等原則或過度限制刑事被告之充\n    分防禦權而違反比例原則之虞。因此偵查中事證未臻明確，\n    被告尚受無罪推定之嚴格保護時，不應以被告可能犯有重罪\n    ，作為羈押被告唯一之理由；而在審判中，雖然已經有相當\n    事證證明被告可能犯有重罪，但如果為了保障被告之防禦權\n    ，讓被告可以使用合法但比較熟悉、可資信賴以及便利的方\n    式行使防禦權，也不應以被告被起訴的罪名為重罪，作為羈\n    押被告的唯一理由，但如果綜合卷內事證，可認為已經具有\n    「相當理由」，足以認定被告犯重罪之嫌疑十分重大，甚至\n    已經達到足以認定犯罪成立所需要的證明度，而且事證調查\n    也已經充分，不會妨害被告防禦權之行使，且以被告犯罪之\n    型態，諸如販售毒品，持有槍械、連續殺人等等，可能造成\n    追訴審判上的極度困擾，或者讓被告停押後「回籠」執行，\n    可能讓被告中斷重新建立之正常生活網路，無法達成執行刑\n    罰之目的等等，均應認為已符合刑事訴訟法第一百零一條第\n    一項第三款之羈押事由。\n四、經查本件被告甲○○所犯販賣第一級毒品罪，為死刑、無期\n    徒刑之重罪，佐以本件被告甲○○於偵查中自白犯行，核與\n    證人乙○○於偵查中多次證述之情節相符，參酌卷附證人乙\n    ○○之通聯紀錄，及被告甲○○於本院之供述內容，被告甲\n    ○○犯罪嫌疑確屬重大。本院考量被告甲○○之供述與各項\n    證據所呈現之事實差距甚大，且證人乙○○於本案起訴後有\n    部分翻異前詞等情節，不能排除被告甲○○具保停止羈押後\n    ，勾串證人而致使調查真相之工作增加困難之虞。又被告甲\n    ○○原有吸毒之惡習，嗣又販賣毒品，顯見其與毒品之供貨\n    者及需求者交往密切，以該生活網路觀之，不無難以排除被\n    告重回毒品圈復實施犯罪之機率，甚而加深本案確保證據之\n    調查及追訴困難之疑慮，並難以達成執行刑罰之目的，本案\n    被告所犯重罪條款之嫌疑重大，而有相當理由肯認其有逃亡\n    、勾串證人之虞，已符合上揭司法院解釋意旨之要件。是以\n    被告羈押原因尚未消滅，僅以命被告具保、責付或限制住居\n    等侵害較小之手段，均不足以確保追訴、審判或執行程序之\n    順利進行，應予延長羈押。\n五、爰依刑事訴訟法第一百零八條第一項、第五項，裁定如主文\n    。\n中    華    民    國    99    年    1     月    5     日\n                  刑事第十八庭審判長法  官  吳鴻章\n                                    法  官  周政達\n                                    法  官  曾淑華\n以上正本證明與原本無異。\n如不服本裁定，應於裁定送達後5日內向本院提出抗告狀。抗告\n書狀，並應敘述抗告之理由。\n                                    書記官  王增華\n中    華    民    國    99    年    1     月    5     日\n",
  "structure": {
    "main": "甲○○羈押期間，自民國九十九年一月十九日起，延長貳月。",
    "reason": "一、上列上訴人即被告甲○○因違反違反毒品危害防制條例案件\n    ，前經本院訊問後，認依原審及本院判決引用各項證據，其\n    涉犯毒品危害防制條例第四條第一項之販賣第一級毒品罪，\n    犯罪嫌疑重大，有相當理由足認被告甲○○有刑事訴訟法第\n    一百零一條第一項第三款所定之情形，非予羈押顯難進行審\n    判或執行，而有羈押之必要，於九十八年十月十九日執行羈\n    押。茲查其羈押期間至九十九年一月十八日即將屆滿，而經\n    本院於九十九年一月四日訊問被告甲○○後，認前項原因仍\n    然存在，尚有繼續羈押之必要，自九十九年一月十九日起延\n    長羈押二月。\n二、按刑事訴訟法第一百零一條第一項所定：「被告經法官訊問\n    後，認為犯罪嫌疑重大，而有左列情形之一，非予羈押，顯\n    難進行追訴、審判或執行者，得羈押之︰一、逃亡或有事實\n    足認為有逃亡之虞者。二、有事實足認為有湮滅、偽造、變\n    造證據或勾串共犯或證人之虞者。三、所犯為死刑、無期徒\n    刑或最輕本刑為五年以上有期徒刑之罪者。」，首段文字即\n    表明羈押之目的，唯在於保全之必要，且受比例原則限制。\n    次按「基於憲法保障人民身體自由之意旨，被告犯上開重罪\n    條款且嫌疑重大者，仍應有相當理由認為其有逃亡、湮滅、\n    偽造、變造證據或勾串共犯或證人等之虞，法院斟酌命該被\n    告具保、責付或限制住居等侵害較小之手段，均不足以確保\n    追訴、審判或執行程序之順利進行，此際予以羈押，方堪稱\n    係屬維持刑事司法權有效行使之最後必要手段。是被告縱然\n    符合上揭第三款之羈押事由，法官仍須就犯罪嫌疑是否重大\n    、有無羈押必要、有無不得羈押之情形予以審酌，非謂一符\n    合該款規定之羈押事由，即得予以羈押。」，業經司法院釋\n    字第六六五號解釋釋明在案。\n三、旨揭大法官會議之解釋文已經指明刑事訴訟法第一百零一條\n    第一項第三款之羈押事由，必須具備有「相當理由」之要件\n    ，始符合憲法規範之要求。大法官理由既謂「相當理由」，\n    即與同條項第一款、第二款法律條文所規定之「有事實足認\n    有．．．之虞」之要件有所不同。兩者之區別，可以顯現在\n    所要求證明度高低的差異上，亦即刑事訴訟法第一百零一條\n    第一款、第二款之羈押事由，必須國家機關所提出被告有逃\n    亡、滅證之虞的具體事實，經綜合評估個案有利及不利被告\n    的一切事證後，能達到明白有力（clear and convincing）\n    之證明度，但在第三款情形相關事證不用證明至明白有力的\n    證明度，而只要綜合個案具體情況，可堪認定被告逃亡滅證\n    的可能性高於不逃亡滅證的可能性即可，或稱為優勢之證明\n    。亦即「重罪常伴有逃亡、滅證之高度可能，係趨吉避凶、\n    脫免刑責、不甘受罰之基本人性，倘一般正常之人，依其合\n    理判斷，可認為該犯重罪嫌疑具有逃亡或滅證之相當或然率\n    存在，即已該當『相當理由』之認定標準，不以達到充分可\n    信或確定程度為必要。以量化為諭，若依客觀、正常之社會\n    通念，認為其人已有超過百分之五十之逃亡、滅證可能性者\n    ，當可認為具有相當理由認為其有逃亡、滅證之虞」（詳最\n    高法院九十八年度台抗字第六六八號裁定意旨參照）。另外\n    一項區別也可以顯現在重罪羈押的立法目的之達成上，此一\n    如大法官會議解釋理由書所言，必須綜合判斷重罪羈押有無\n    牴觸無罪推定原則、武器平等原則或過度限制刑事被告之充\n    分防禦權而違反比例原則之虞。因此偵查中事證未臻明確，\n    被告尚受無罪推定之嚴格保護時，不應以被告可能犯有重罪\n    ，作為羈押被告唯一之理由；而在審判中，雖然已經有相當\n    事證證明被告可能犯有重罪，但如果為了保障被告之防禦權\n    ，讓被告可以使用合法但比較熟悉、可資信賴以及便利的方\n    式行使防禦權，也不應以被告被起訴的罪名為重罪，作為羈\n    押被告的唯一理由，但如果綜合卷內事證，可認為已經具有\n    「相當理由」，足以認定被告犯重罪之嫌疑十分重大，甚至\n    已經達到足以認定犯罪成立所需要的證明度，而且事證調查\n    也已經充分，不會妨害被告防禦權之行使，且以被告犯罪之\n    型態，諸如販售毒品，持有槍械、連續殺人等等，可能造成\n    追訴審判上的極度困擾，或者讓被告停押後「回籠」執行，\n    可能讓被告中斷重新建立之正常生活網路，無法達成執行刑\n    罰之目的等等，均應認為已符合刑事訴訟法第一百零一條第\n    一項第三款之羈押事由。\n四、經查本件被告甲○○所犯販賣第一級毒品罪，為死刑、無期\n    徒刑之重罪，佐以本件被告甲○○於偵查中自白犯行，核與\n    證人乙○○於偵查中多次證述之情節相符，參酌卷附證人乙\n    ○○之通聯紀錄，及被告甲○○於本院之供述內容，被告甲\n    ○○犯罪嫌疑確屬重大。本院考量被告甲○○之供述與各項\n    證據所呈現之事實差距甚大，且證人乙○○於本案起訴後有\n    部分翻異前詞等情節，不能排除被告甲○○具保停止羈押後\n    ，勾串證人而致使調查真相之工作增加困難之虞。又被告甲\n    ○○原有吸毒之惡習，嗣又販賣毒品，顯見其與毒品之供貨\n    者及需求者交往密切，以該生活網路觀之，不無難以排除被\n    告重回毒品圈復實施犯罪之機率，甚而加深本案確保證據之\n    調查及追訴困難之疑慮，並難以達成執行刑罰之目的，本案\n    被告所犯重罪條款之嫌疑重大，而有相當理由肯認其有逃亡\n    、勾串證人之虞，已符合上揭司法院解釋意旨之要件。是以\n    被告羈押原因尚未消滅，僅以命被告具保、責付或限制住居\n    等侵害較小之手段，均不足以確保追訴、審判或執行程序之\n    順利進行，應予延長羈押。\n五、爰依刑事訴訟法第一百零八條第一項、第五項，裁定如主文\n    。"
  },
  "characters": {
    "judges": [
      "吳鴻章",
      "周政達",
      "曾淑華"
    ],
    "prosecutors": [

    ],
    "lawyers": [
      "劉宏邈"
    ],
    "clerks": [
      "王增華"
    ],
    "plaintiffs": [

    ],
    "defendants": [
      "甲"
    ],
    "prosecutor_office": [

    ],
    "creditors": [

    ],
    "debtors": [

    ],
    "judicial_associate_officer": [

    ]
  },
  "adjudged_at": "2010-01-05",
  "created_at": "2016-01-05 15:00:34",
  "updated_at": "2016-01-05 15:00:34"
}