{
  "identify": "TPH-99-聲-10-20100104-1",
  "court": {
    "name": "臺灣高等法院",
    "code": "TPH"
  },
  "division": {
    "name": "刑事",
    "code": "M"
  },
  "year": 99,
  "word": "聲",
  "number": "10",
  "jcheck": "1",
  "reason": "聲請具保停止羈押",
  "content": "臺灣高等法院刑事裁定                    99年度聲字第10號\n聲  請  人\n即  被  告  甲○○\n                    現於臺灣台北看守所（\n選任辯護人 蔡宏修律師\n上列被告因98年度上訴字第4054號違反毒品危害防制條例案件，\n聲請人聲請具保停止羈押，本院裁定如下：\n    主  文\n聲請駁回。\n    理  由\n一、本件被告因違反毒品危害防制條例案件，前經本院認為有刑\n    事訴訟法第一百零一條第一項第三款之情形，非予羈押，顯\n    難進行審判，執行羈押。\n二、聲請意旨略以：依大法官會議釋字第六六五號解釋，不得單\n    依刑事訴訟法第一百零一條第一項第三款予以羈押，尚應審\n    酌有無逃亡等情狀。且法院為羈押時，依學者見解應審酌有\n    無必要性，及有無符合比例原則。本件依共同被告李毓興供\n    述，而為被告有罪判決，顯違無罪推定原則，蓋其供述有瑕\n    疵可指，並違反論理、經驗法則，且無其他證據可佐，自不\n    得採為被告有罪之依據。是被告並未涉案，且素行良好，有\n    正當職業，並無逃亡之虞，依上開大法官會議解釋，自無羈\n    押必要。且被告家有病父幼子，若遭羈押，家中生計，即生\n    困頓。請准具保停止羈押等語。\n三、經查：被告所犯毒品危害防制條例等罪，最輕本刑為五年\n    以上之罪，且有人證物證可參，足認其犯嫌重大，並經原審\n    判處有期徒刑八年四月之重刑，是有相當理由足認有逃亡之\n    虞，復無不得羈押之情形，自有羈押必要。再審酌被告所涉\n    犯運輸毒品案件，對社會危害甚鉅，予以羈押，適足以防衛\n    社會安全，並不違比例原則。抗告意旨以：依大法官會議\n    解釋，本件並無羈押必要乙節，按大法官會議釋字第六六五\n    號解釋主文載：「二、刑事訴訟法第一百零一條第一項第三\n    款規定，於被告犯該款規定之罪，犯罪嫌疑重大，且有相當\n    理由認為有逃亡、湮滅、偽造、變造證據或勾串共犯或證人\n    之虞，非予羈押，顯難進行追訴、審判或執行者，得羈押之\n    。於此範圍內，該條款規定符合憲法第二十三條之比例原則\n    ，與憲法第八條保障人民身體自由及第十六條保障人民訴訟\n    權之意旨，尚無牴觸」等語。足認刑事訴訟法第一百零一條\n    第一項第三款規定，並未違憲。而法院於審理羈押案件時，\n    除審認是否符合上開法條規定外，尚需依同法第一百零一條\n    之二意旨，審酌有無羈押必要。而此所謂有無羈押必要，參\n    酌上開大法官會議解釋，當係：有相當理由認為有逃亡、湮\n    滅、偽造、變造證據或勾串共犯或證人之虞等情。本件，被\n    告經原審判處重刑，自有相當理由足認有逃亡之虞，而有羈\n    押必要，本院因而予以羈押，自與上開大法官會議解釋意旨\n    相符。是此部份聲請意旨，尚有誤會。至於聲請意旨認被\n    告並未犯罪乙節，無非實體事項，尚非羈押案件，所應審酌\n    ，此部份聲請意旨，亦有誤會。另有關被告家況，固值同\n    情，惟並非合法停止羈押事由。綜上，本件羈押原因尚未消\n    滅，所請具保停止羈押，自難准許，應予駁回。\n中    華    民    國    99    年    1     月    4     日\n                  刑事第十八庭  審判長法  官  吳鴻章\n                                      法  官  汪梅芬\n                                      法  官  周政達\n以上正本證明與原本無異。\n如不服本裁定，應於收受送達後五日內向本院提出抗告狀。\n                                      書記官  廖純瑜\n中    華    民    國    99    年    1     月    4     日\n",
  "structure": {
    "main": "聲請駁回。",
    "reason": "一、本件被告因違反毒品危害防制條例案件，前經本院認為有刑\n    事訴訟法第一百零一條第一項第三款之情形，非予羈押，顯\n    難進行審判，執行羈押。\n二、聲請意旨略以：依大法官會議釋字第六六五號解釋，不得單\n    依刑事訴訟法第一百零一條第一項第三款予以羈押，尚應審\n    酌有無逃亡等情狀。且法院為羈押時，依學者見解應審酌有\n    無必要性，及有無符合比例原則。本件依共同被告李毓興供\n    述，而為被告有罪判決，顯違無罪推定原則，蓋其供述有瑕\n    疵可指，並違反論理、經驗法則，且無其他證據可佐，自不\n    得採為被告有罪之依據。是被告並未涉案，且素行良好，有\n    正當職業，並無逃亡之虞，依上開大法官會議解釋，自無羈\n    押必要。且被告家有病父幼子，若遭羈押，家中生計，即生\n    困頓。請准具保停止羈押等語。\n三、經查：被告所犯毒品危害防制條例等罪，最輕本刑為五年\n    以上之罪，且有人證物證可參，足認其犯嫌重大，並經原審\n    判處有期徒刑八年四月之重刑，是有相當理由足認有逃亡之\n    虞，復無不得羈押之情形，自有羈押必要。再審酌被告所涉\n    犯運輸毒品案件，對社會危害甚鉅，予以羈押，適足以防衛\n    社會安全，並不違比例原則。抗告意旨以：依大法官會議\n    解釋，本件並無羈押必要乙節，按大法官會議釋字第六六五\n    號解釋主文載：「二、刑事訴訟法第一百零一條第一項第三\n    款規定，於被告犯該款規定之罪，犯罪嫌疑重大，且有相當\n    理由認為有逃亡、湮滅、偽造、變造證據或勾串共犯或證人\n    之虞，非予羈押，顯難進行追訴、審判或執行者，得羈押之\n    。於此範圍內，該條款規定符合憲法第二十三條之比例原則\n    ，與憲法第八條保障人民身體自由及第十六條保障人民訴訟\n    權之意旨，尚無牴觸」等語。足認刑事訴訟法第一百零一條\n    第一項第三款規定，並未違憲。而法院於審理羈押案件時，\n    除審認是否符合上開法條規定外，尚需依同法第一百零一條\n    之二意旨，審酌有無羈押必要。而此所謂有無羈押必要，參\n    酌上開大法官會議解釋，當係：有相當理由認為有逃亡、湮\n    滅、偽造、變造證據或勾串共犯或證人之虞等情。本件，被\n    告經原審判處重刑，自有相當理由足認有逃亡之虞，而有羈\n    押必要，本院因而予以羈押，自與上開大法官會議解釋意旨\n    相符。是此部份聲請意旨，尚有誤會。至於聲請意旨認被\n    告並未犯罪乙節，無非實體事項，尚非羈押案件，所應審酌\n    ，此部份聲請意旨，亦有誤會。另有關被告家況，固值同\n    情，惟並非合法停止羈押事由。綜上，本件羈押原因尚未消\n    滅，所請具保停止羈押，自難准許，應予駁回。"
  },
  "characters": {
    "judges": [
      "吳鴻章",
      "汪梅芬",
      "周政達"
    ],
    "prosecutors": [

    ],
    "lawyers": [
      "蔡宏修"
    ],
    "clerks": [
      "廖純瑜"
    ],
    "plaintiffs": [

    ],
    "defendants": [
      "甲"
    ],
    "prosecutor_office": [

    ],
    "creditors": [

    ],
    "debtors": [

    ],
    "judicial_associate_officer": [

    ]
  },
  "adjudged_at": "2010-01-04",
  "created_at": "2016-01-05 14:34:55",
  "updated_at": "2016-01-05 14:34:55"
}