{
  "identify": "TPH-99-聲-28-20100105-1",
  "court": {
    "name": "臺灣高等法院",
    "code": "TPH"
  },
  "division": {
    "name": "刑事",
    "code": "M"
  },
  "year": 99,
  "word": "聲",
  "number": "28",
  "jcheck": "1",
  "reason": "保護管束",
  "content": "臺灣高等法院刑事裁定                    99年度聲字第28號\n聲  請  人  臺灣高等法院檢察署檢察官\n受  刑  人  甲○○\n上列受刑人因違反毒品危害防制條例罪案件，聲請人聲請付保護\n管束（聲請案號：臺灣高等法院檢察署99年度執聲付字第1 號）\n，本院裁定如下：\n    主  文\n甲○○假釋中付保護管束。\n    理  由\n一、聲請意旨略以：受刑人甲○○因違反毒品危害防制條例罪案\n    件，經臺灣臺北地方法院以96年度聲減字第3211號裁定減刑\n    及定其應執行有期徒刑4年2月確定，移付執行在案，茲經法\n    務部矯正司於民國98年12月25日核准假釋在案，依刑法第93\n    條第2項規定，在假釋中付保護管束，爰依刑事訴訟法第481\n    第1項規定聲請裁定等語。\n二、本院審核法務部矯正司98年12月25日法矯司字第0980907649\n    號函及所附交付保護管束名冊（核准假釋日期及文號：98年\n    12月25日法矯字第0980052465號），認聲請人之聲請為正當\n    ，應予准許。\n三、依刑事訴訟法第481條第1項、刑法第96條但書、第93條第 2\n    項，裁定如主文。\n中    華    民    國    99    年    1     月    5     日\n                  刑事第十三庭  審判長法  官  曾德水\n                                      法  官  崔玲琦\n                                      法  官  遲中慧\n以上正本證明與原本無異。\n如不服本裁定，應於收受送達後五日內向本院提出抗告狀。\n                                      書記官  陳韋杉\n中    華    民    國    99    年    1     月    5     日\n",
  "structure": {
    "main": "甲○○假釋中付保護管束。",
    "reason": "一、聲請意旨略以：受刑人甲○○因違反毒品危害防制條例罪案\n    件，經臺灣臺北地方法院以96年度聲減字第3211號裁定減刑\n    及定其應執行有期徒刑4年2月確定，移付執行在案，茲經法\n    務部矯正司於民國98年12月25日核准假釋在案，依刑法第93\n    條第2項規定，在假釋中付保護管束，爰依刑事訴訟法第481\n    第1項規定聲請裁定等語。\n二、本院審核法務部矯正司98年12月25日法矯司字第0980907649\n    號函及所附交付保護管束名冊（核准假釋日期及文號：98年\n    12月25日法矯字第0980052465號），認聲請人之聲請為正當\n    ，應予准許。\n三、依刑事訴訟法第481條第1項、刑法第96條但書、第93條第 2\n    項，裁定如主文。"
  },
  "characters": {
    "judges": [
      "曾德水",
      "崔玲琦",
      "遲中慧"
    ],
    "prosecutors": [

    ],
    "lawyers": [

    ],
    "clerks": [
      "陳韋杉"
    ],
    "plaintiffs": [

    ],
    "defendants": [

    ],
    "prosecutor_office": [
      "臺灣高等法院檢察署檢察官"
    ],
    "creditors": [

    ],
    "debtors": [

    ],
    "judicial_associate_officer": [

    ]
  },
  "adjudged_at": "2010-01-05",
  "created_at": "2016-01-05 15:00:59",
  "updated_at": "2016-01-05 15:00:59"
}