{
  "identify": "TPH-98-上重訴-63-20100105-2",
  "court": {
    "name": "臺灣高等法院",
    "code": "TPH"
  },
  "division": {
    "name": "刑事",
    "code": "M"
  },
  "year": 98,
  "word": "上重訴",
  "number": "63",
  "jcheck": "2",
  "reason": "銀行法等",
  "content": "臺灣高等法院刑事裁定                98年度上重訴字第63號\n上  訴  人\n即  被  告  甲○○\n                    （現於臺灣臺北看守所羈押中）\n選任辯護人  陳麗玢律師\n上列被告因違反銀行法等案件，經檢察官提起公訴（起訴案號：\n臺灣臺北地方法院檢察署年度偵字第22711 號），嗣原審判決後\n提起上訴，本院裁定如下：\n    主  文\n甲○○羈押期間，自民國九十九年一月十二日起，延長貳月。\n    理  由\n一、上訴人即被告甲○○前經本院訊問後，認為犯銀行法等罪嫌\n    疑重大，有刑事訴訟法第101 條第1 項第1 款之情形，非予\n    羈押顯難進行審判，於民國98年10月12日執行羈押，至民國\n    99年1 月11日止，三個月羈押期間即將屆滿。\n二、查：(一)被告甲○○因違反銀行法等案件，前經臺灣臺北地\n    方法院檢察署以95年度偵字第22711 號案件偵查，並於96年\n    8 月24日以北檢盛緝字第3289號發布通緝，被告於通緝到案\n    後，經檢察官限制出境，且聲請人遭檢察官起訴其涉犯違反\n    銀行法等罪嫌後，經臺灣臺北地方法以96年度重訴字第64號\n    判決，判處被告甲○○共同意圖為自己不法之所有，以詐術\n    使人將本人之物交付，處有期徒刑四年十一月在案，檢察官\n    不服提起上訴，認被告所為應係犯銀行法第29條、第29條之\n    1 及刑法第339 條第1 項之罪，兩罪有修正前刑法上牽連犯\n    關係，應從一重之銀行法第125 條第1 項處斷，原審關於被\n    告犯行之法律適用有待商榷，故尚未判決確定。且檢察官認\n    定被告吸收存款金額高達三億六千萬元，則依檢察官起訴犯\n    罪事實，被告所為該當於銀行法第125 條第1 項後段犯罪所\n    得達新臺幣一億元以上，法定本刑為七年以上有期徒刑，得\n    併科罰金新臺幣五千五百萬元以上五億元以下，是被告所犯\n    罪名是否該當於刑事訴訟法第101 條第1 項第3 款之重罪，\n    仍待調查審理。(二)被告因上揭案件遭通緝，嗣於98年4 月\n    15日經大陸公安遣送回臺灣而緝獲到案，再者，被告已受重\n    刑之諭知，又所詐得資金流向不明，尚待調查釐清，依合理\n    判斷，被告逃匿以規避審判程序之進行及刑罰之執行之可能\n    性甚高，有事實足認被告有逃亡之虞。(三)本案於本院準備\n    程序中，其他共犯被告之辯護人尚聲請傳喚證人詰問，則無\n    法完全排除被告可能有煙滅、偽造、變造或勾串共犯或證人\n    之虞。本院參諸被告被訴涉犯刑法第339 條第1 項、銀行法\n    第29條、第29條之1 而犯同法第125 條第1 項之罪嫌，曾經\n    原審法院合法傳拘無著並發布通緝，業如前述，另審酌案內\n    相關事證以及其他一切情事，其羈押之原因仍然存在，認有\n    繼續羈押之必要，應自民國99年1 月12日起延長羈押二月，\n    爰依刑事訴訟法第108 條第1 項、第5 項，裁定如主文。\n中    華    民    國    99    年    1     月    5     日\n                  刑事第四庭  審判長法  官  陳筱珮\n                                    法  官  陳玉雲\n                                    法  官  邱滋杉\n以上正本證明與原本無異。\n如不服本裁定，應於收受送達後五日內向本院提出抗告狀。\n                                    書記官  劉貞達\n中    華    民    國    99    年    1     月    5     日\n",
  "structure": {
    "main": "甲○○羈押期間，自民國九十九年一月十二日起，延長貳月。",
    "reason": "一、上訴人即被告甲○○前經本院訊問後，認為犯銀行法等罪嫌\n    疑重大，有刑事訴訟法第101 條第1 項第1 款之情形，非予\n    羈押顯難進行審判，於民國98年10月12日執行羈押，至民國\n    99年1 月11日止，三個月羈押期間即將屆滿。\n二、查：(一)被告甲○○因違反銀行法等案件，前經臺灣臺北地\n    方法院檢察署以95年度偵字第22711 號案件偵查，並於96年\n    8 月24日以北檢盛緝字第3289號發布通緝，被告於通緝到案\n    後，經檢察官限制出境，且聲請人遭檢察官起訴其涉犯違反\n    銀行法等罪嫌後，經臺灣臺北地方法以96年度重訴字第64號\n    判決，判處被告甲○○共同意圖為自己不法之所有，以詐術\n    使人將本人之物交付，處有期徒刑四年十一月在案，檢察官\n    不服提起上訴，認被告所為應係犯銀行法第29條、第29條之\n    1 及刑法第339 條第1 項之罪，兩罪有修正前刑法上牽連犯\n    關係，應從一重之銀行法第125 條第1 項處斷，原審關於被\n    告犯行之法律適用有待商榷，故尚未判決確定。且檢察官認\n    定被告吸收存款金額高達三億六千萬元，則依檢察官起訴犯\n    罪事實，被告所為該當於銀行法第125 條第1 項後段犯罪所\n    得達新臺幣一億元以上，法定本刑為七年以上有期徒刑，得\n    併科罰金新臺幣五千五百萬元以上五億元以下，是被告所犯\n    罪名是否該當於刑事訴訟法第101 條第1 項第3 款之重罪，\n    仍待調查審理。(二)被告因上揭案件遭通緝，嗣於98年4 月\n    15日經大陸公安遣送回臺灣而緝獲到案，再者，被告已受重\n    刑之諭知，又所詐得資金流向不明，尚待調查釐清，依合理\n    判斷，被告逃匿以規避審判程序之進行及刑罰之執行之可能\n    性甚高，有事實足認被告有逃亡之虞。(三)本案於本院準備\n    程序中，其他共犯被告之辯護人尚聲請傳喚證人詰問，則無\n    法完全排除被告可能有煙滅、偽造、變造或勾串共犯或證人\n    之虞。本院參諸被告被訴涉犯刑法第339 條第1 項、銀行法\n    第29條、第29條之1 而犯同法第125 條第1 項之罪嫌，曾經\n    原審法院合法傳拘無著並發布通緝，業如前述，另審酌案內\n    相關事證以及其他一切情事，其羈押之原因仍然存在，認有\n    繼續羈押之必要，應自民國99年1 月12日起延長羈押二月，\n    爰依刑事訴訟法第108 條第1 項、第5 項，裁定如主文。"
  },
  "characters": {
    "judges": [
      "陳筱珮",
      "陳玉雲",
      "邱滋杉"
    ],
    "prosecutors": [

    ],
    "lawyers": [
      "陳麗玢"
    ],
    "clerks": [
      "劉貞達"
    ],
    "plaintiffs": [

    ],
    "defendants": [
      "甲"
    ],
    "prosecutor_office": [

    ],
    "creditors": [

    ],
    "debtors": [

    ],
    "judicial_associate_officer": [

    ]
  },
  "adjudged_at": "2010-01-05",
  "created_at": "2016-01-05 15:00:29",
  "updated_at": "2016-01-05 15:00:29"
}