{
  "identify": "TPH-99-聲-1261-20100512-1",
  "court": {
    "name": "臺灣高等法院",
    "code": "TPH"
  },
  "division": {
    "name": "刑事",
    "code": "M"
  },
  "year": 99,
  "word": "聲",
  "number": "1261",
  "jcheck": "1",
  "reason": "保護管束",
  "content": "臺灣高等法院刑事裁定                  99年度聲字第1261號\n聲  請  人  臺灣高等法院檢察署檢察官\n受  刑  人  甲○○\n上列受刑人因妨害性自主案件，聲請人聲請付保護管束（99年度\n執聲付字第334號），本院裁定如下：\n    主  文\n甲○○假釋中付保護管束。\n    理  由\n一、聲請意旨略以：受刑人甲○○因妨害性自主案件，經台灣板\n    橋地方法院判處應執行有期徒刑3年2月，上訴台灣高等法院\n    以95年度上訴字第3851號判處應執行有期徒刑3年10月，並\n    經最高法院96年度台上字第4468號上訴駁回確定，並經台灣\n    高等法院96年聲減字第4681號減刑，並定其應執行之刑為有\n    期徒刑3年5月，於民國（下同）96年10月1日送監執行，嗣\n    經法務部於99年5月5日核准假釋在案，爰依刑事訴訟法第\n    481 條第1項規定，聲請於其假釋中付保護管束等語。\n二、本院審核法務部矯正司99年5月5日法矯司字第0990905905號\n    函所附假釋出獄人交付保護管束名冊，認聲請人之聲請為正\n    當。\n三、依刑事訴訟法第481條第1項，刑法第93條第2項，裁定如主\n    文。\n中    華    民    國    99    年    5    月    12    日\n                  刑事第六庭審判長法  官 林明俊\n                                  法  官 何信慶\n                                  法  官 吳淑惠\n以上正本證明與原本無異。\n如不服本裁定，應於收受送達後五日內向本院提出抗告狀。\n                                  書記官 陳雅加\n中    華    民    國    99    年    5     月    12    日",
  "structure": {
    "main": "甲○○假釋中付保護管束。",
    "reason": "一、聲請意旨略以：受刑人甲○○因妨害性自主案件，經台灣板\n    橋地方法院判處應執行有期徒刑3年2月，上訴台灣高等法院\n    以95年度上訴字第3851號判處應執行有期徒刑3年10月，並\n    經最高法院96年度台上字第4468號上訴駁回確定，並經台灣\n    高等法院96年聲減字第4681號減刑，並定其應執行之刑為有\n    期徒刑3年5月，於民國（下同）96年10月1日送監執行，嗣\n    經法務部於99年5月5日核准假釋在案，爰依刑事訴訟法第\n    481 條第1項規定，聲請於其假釋中付保護管束等語。\n二、本院審核法務部矯正司99年5月5日法矯司字第0990905905號\n    函所附假釋出獄人交付保護管束名冊，認聲請人之聲請為正\n    當。\n三、依刑事訴訟法第481條第1項，刑法第93條第2項，裁定如主\n    文。"
  },
  "characters": {
    "judges": [
      "林明俊",
      "何信慶",
      "吳淑惠"
    ],
    "prosecutors": [

    ],
    "lawyers": [

    ],
    "clerks": [
      "陳雅加"
    ],
    "plaintiffs": [

    ],
    "defendants": [

    ],
    "prosecutor_office": [
      "臺灣高等法院檢察署檢察官"
    ],
    "creditors": [

    ],
    "debtors": [

    ],
    "judicial_associate_officer": [

    ]
  },
  "adjudged_at": "2010-05-12",
  "created_at": "2016-01-05 11:52:19",
  "updated_at": "2016-01-05 11:52:19"
}