{
  "identify": "TPH-97-重訴更(一)-5-20100105-2",
  "court": {
    "name": "臺灣高等法院",
    "code": "TPH"
  },
  "division": {
    "name": "民事",
    "code": "V"
  },
  "year": 97,
  "word": "重訴更(一)",
  "number": "5",
  "jcheck": "2",
  "reason": "侵權行為損害賠償",
  "content": "臺灣高等法院民事裁定               97年度重訴更(一)字第5號\n原      告  庚○○\n訴訟代理人  丁○○\n追 加被 告  澳大利亞商安盛國衛人壽保險股份有限公司臺灣分\n            公司\n法定代理人  辛○○\n訴訟代理人  程守真律師\n            林哲誠律師\n追 加被 告  丙○○\n            癸○○\n            己○○\n兼上三人共同\n訴訟代理人  朱昭勳律師\n複 代理 人  甲○\n追 加被 告  壬○○\n上列原告因與被告乙○○等間侵權行為損害賠償事件，上訴人追\n加澳大利亞商安盛國衛人壽保險股份有限公司臺灣分公司等為被\n告，本院裁定如下：\n    主  文\n追加之訴駁回。\n追加之訴訴訟費用由原告負擔。\n    理  由\n一、按「訴狀送達後，原告不得將原訴變更或追加他訴。但有下\n    列各款情形之一者，不在此限：二請求之基礎事實同一者。\n    被告於訴之變更或追加無異議，而為本案之言詞辯論者，視\n    為同意變更或追加。」，民事訴訟法第255條第1項但書第2\n    款、第2項定有明文。又按民事訴訟法第255條第1項第2款所\n    謂請求之基礎事實同一，係指變更或追加之訴與原訴之原因\n    事實有其共同性，先後所為請求之主張在社會生活上可認為\n    有共通性或關連性，而就原請求之訴訟及證據資料於相當程\n    度範圍內具有同一性或一體性，在審理時得加以利用，俾先\n    後兩請求可在同一程序得加以解決，以避免重複審理，庶能\n    統一解決紛爭，用符訴訟經濟者即屬之（最高法院96年台上\n    字第471號、95年台上字第1573號判決意旨參照）。\n二、本件原告於本院以追加被告丙○○、癸○○、己○○、壬○\n    ○為被告乙○○、戊○○（下稱乙○○等2人，另以判決駁\n    回）之人頭，追加被告澳大利亞安盛國衛人壽保險股份有限\n    公司臺灣分公司（下稱國衛人壽公司）及丙○○、癸○○、\n    己○○、壬○○均同意乙○○等2人經由臺灣之聲電台介紹\n    而投保之保險業績掛在丙○○、癸○○、己○○、壬○○名\n    下，向國衛人壽公司領取保險佣金，追加被告朱昭勳明知乙\n    ○○等2人至少以壬○○等16位人頭領取保險佣金侵占原告\n    權益，仍一再違反律師法欺誘、矇騙法院等相關規定，爰依\n    民法第184條第1項前段、第185條之規定，求為命：(一)朱昭\n    勳應與被告乙○○等2人連帶給付原告新臺幣（下同）10萬\n    元。(二)國衛人壽公司應與乙○○等2人連帶給付原告10萬元\n    。(三)丙○○、癸○○、己○○、壬○○應與乙○○等2人連\n    帶給付原告10萬元。(四)附帶請求國衛人壽公司應與乙○○等\n    2人連帶賠償原告2億元。(五)第(一)項至第(三)項追加聲明與原起\n    訴聲明中如有一追加被告給付10萬元，其餘聲明之追加被告\n    即免除連帶給付10萬元責任之判決。\n三、經查，原告原起訴主張原告與乙○○口頭約定，經由臺灣之\n    聲電台介紹而投保國衛人壽公司保險之客戶，其佣金由原告\n    收取，乙○○竟違反與原告間之約定，與戊○○共同侵占原\n    告應得之保險佣金，乙○○復在臺北藝術大學向他人宣稱原\n    告已領得國衛人壽公司之保險佣金，侵害原告名譽權，請求\n    乙○○等2人侵權行為損害賠償等語。而原告追加之訴既係\n    主張追加被告丙○○、癸○○、己○○、壬○○為乙○○等\n    2人之人頭，國衛人壽公司明知上情而同意乙○○等2人領取\n    保險佣金，暨朱昭勳違反律師法之規定等情，與原告原訴主\n    張乙○○與原告間口頭約定保險佣金及乙○○等2人侵占保\n    險佣金及侵害原告名譽權之原因事實並無共同性，就原請求\n    之訴訟及證據資料亦無法於審理原告追加之訴時加以利用，\n    堪認本件原告請求之原訴及追加之訴間之基礎事實並非同一\n    ，其追加國衛人壽公司、丙○○、癸○○、己○○、壬○○\n    、朱昭勳為被告，顯未具備訴之追加要件，不應准許。\n四、據上論結，本件追加之訴為不合法，爰裁定如主文。\n中    華    民    國    99    年    1     月    5     日\n                    民事第十三庭\n                          審判長法  官  蕭艿菁\n                                法  官  楊絮雲\n                                法  官  周舒雁\n正本係照原本作成。\n如不服本裁定，應於收受送達後10日內向本院提出抗告狀，並應\n繳納抗告費新台幣1000。\n中    華    民    國    99    年    1     月    5     日\n                              書記官  秦仲芳",
  "structure": {
    "main": "追加之訴駁回。\n追加之訴訴訟費用由原告負擔。",
    "reason": "一、按「訴狀送達後，原告不得將原訴變更或追加他訴。但有下\n    列各款情形之一者，不在此限：二請求之基礎事實同一者。\n    被告於訴之變更或追加無異議，而為本案之言詞辯論者，視\n    為同意變更或追加。」，民事訴訟法第255條第1項但書第2\n    款、第2項定有明文。又按民事訴訟法第255條第1項第2款所\n    謂請求之基礎事實同一，係指變更或追加之訴與原訴之原因\n    事實有其共同性，先後所為請求之主張在社會生活上可認為\n    有共通性或關連性，而就原請求之訴訟及證據資料於相當程\n    度範圍內具有同一性或一體性，在審理時得加以利用，俾先\n    後兩請求可在同一程序得加以解決，以避免重複審理，庶能\n    統一解決紛爭，用符訴訟經濟者即屬之（最高法院96年台上\n    字第471號、95年台上字第1573號判決意旨參照）。\n二、本件原告於本院以追加被告丙○○、癸○○、己○○、壬○\n    ○為被告乙○○、戊○○（下稱乙○○等2人，另以判決駁\n    回）之人頭，追加被告澳大利亞安盛國衛人壽保險股份有限\n    公司臺灣分公司（下稱國衛人壽公司）及丙○○、癸○○、\n    己○○、壬○○均同意乙○○等2人經由臺灣之聲電台介紹\n    而投保之保險業績掛在丙○○、癸○○、己○○、壬○○名\n    下，向國衛人壽公司領取保險佣金，追加被告朱昭勳明知乙\n    ○○等2人至少以壬○○等16位人頭領取保險佣金侵占原告\n    權益，仍一再違反律師法欺誘、矇騙法院等相關規定，爰依\n    民法第184條第1項前段、第185條之規定，求為命：(一)朱昭\n    勳應與被告乙○○等2人連帶給付原告新臺幣（下同）10萬\n    元。(二)國衛人壽公司應與乙○○等2人連帶給付原告10萬元\n    。(三)丙○○、癸○○、己○○、壬○○應與乙○○等2人連\n    帶給付原告10萬元。(四)附帶請求國衛人壽公司應與乙○○等\n    2人連帶賠償原告2億元。(五)第(一)項至第(三)項追加聲明與原起\n    訴聲明中如有一追加被告給付10萬元，其餘聲明之追加被告\n    即免除連帶給付10萬元責任之判決。\n三、經查，原告原起訴主張原告與乙○○口頭約定，經由臺灣之\n    聲電台介紹而投保國衛人壽公司保險之客戶，其佣金由原告\n    收取，乙○○竟違反與原告間之約定，與戊○○共同侵占原\n    告應得之保險佣金，乙○○復在臺北藝術大學向他人宣稱原\n    告已領得國衛人壽公司之保險佣金，侵害原告名譽權，請求\n    乙○○等2人侵權行為損害賠償等語。而原告追加之訴既係\n    主張追加被告丙○○、癸○○、己○○、壬○○為乙○○等\n    2人之人頭，國衛人壽公司明知上情而同意乙○○等2人領取\n    保險佣金，暨朱昭勳違反律師法之規定等情，與原告原訴主\n    張乙○○與原告間口頭約定保險佣金及乙○○等2人侵占保\n    險佣金及侵害原告名譽權之原因事實並無共同性，就原請求\n    之訴訟及證據資料亦無法於審理原告追加之訴時加以利用，\n    堪認本件原告請求之原訴及追加之訴間之基礎事實並非同一\n    ，其追加國衛人壽公司、丙○○、癸○○、己○○、壬○○\n    、朱昭勳為被告，顯未具備訴之追加要件，不應准許。\n四、據上論結，本件追加之訴為不合法，爰裁定如主文。"
  },
  "characters": {
    "judges": [
      "蕭艿菁",
      "楊絮雲",
      "周舒雁"
    ],
    "prosecutors": [

    ],
    "lawyers": [
      "程守真",
      "林哲誠",
      "朱昭勳"
    ],
    "clerks": [

    ],
    "plaintiffs": [
      "庚"
    ],
    "defendants": [
      "澳大利亞商安盛國衛人壽保險股份有限公司臺灣分",
      "丙",
      "壬"
    ],
    "prosecutor_office": [

    ],
    "creditors": [

    ],
    "debtors": [

    ],
    "judicial_associate_officer": [

    ]
  },
  "adjudged_at": "2010-01-05",
  "created_at": "2016-01-05 15:02:01",
  "updated_at": "2016-01-05 15:02:01"
}