{
  "identify": "TPH-98-重選上更(六)-39-20100512-1",
  "court": {
    "name": "臺灣高等法院",
    "code": "TPH"
  },
  "division": {
    "name": "刑事",
    "code": "M"
  },
  "year": 98,
  "word": "重選上更(六)",
  "number": "39",
  "jcheck": "1",
  "reason": "選罷法",
  "content": "臺灣高等法院刑事判決          98年度重選上更(六)字第39號\n上  訴  人    臺灣新竹地方法院檢察署檢察官\n上  訴  人    甲○○○○\n即  被  告\n上列上訴人因被告違反公職人員選舉罷免法等案件，不服臺灣新\n竹地方法院九十一年度訴字第四八號，中華民國九十二年二月廿\n一日第一審判決（起訴案號：臺灣新竹地方法院檢察署九十年度\n選偵字第三、九、一二號），提起上訴，經判決後，由最高法院\n第五次發回更審，本院判決如下：\n    主  文\n原判決關於甲○○○○部份撤銷。\n甲○○○○共同對於有投票權之人，交付賄賂，而約其投票權為\n一定之行使，處有期徒刑壹年陸月，褫奪公權肆年。減為有期徒\n刑玖月，褫奪公權貳年。扣案新臺幣拾伍萬伍仟元、信封袋伍個\n、行賄名單貳張均沒收。\n    事  實\n一、甲○○○○為中華民國第五屆立法委員自由地區山地原住民\n    之候選人；露妮．萊撒（未經起訴）為甲○○○○之妻，負\n    責甲○○○○競選期間之財務；丁○○（業經本院以九十五\n    年度選上更(四)字第一號判處有期徒刑十月，褫奪公權三年\n    確定）為甲○○○○之表弟，擔任甲○○○○競選總部辦公\n    室主任；戊○○（業經原審法院判處有期徒刑十月，褫奪公\n    權三年，緩刑三年確定）係甲○○○○妻子露妮．萊撒之同\n    學，與丁○○同為新竹縣五峰鄉公所之同事，擔任甲○○○\n    ○競選總部拜票組組長兼會計組組長。\n二、甲○○○○與其妻露妮．萊撒、表弟丁○○及戊○○等人為\n    使甲○○○○當選連任，乃共同基於對有投票權之選民交付\n    賄賂，約定其將選票投予甲○○○○之犯意聯絡，由露妮．\n    萊撒負責將張羅提供行賄之款項，交予其競選主任丁○○，\n    丁○○即偕同會計組長戊○○依渠等共同行賄買票之謀議，\n    於前往新竹縣尖石鄉為競選活動時：\n    (一)先於九十年十一月一日下午六時許，在尖石鄉錦屏村三鄰\n      天然谷六之一號「天然谷鱒魚養殖休閒農場餐廳」（以下\n      簡稱「天然谷餐廳」），於邀請義工及選民餐敘席間，由\n      丁○○指示亦基於賄選犯意聯絡之另一不詳姓名之成年男\n      子，在「天然谷餐廳」門前甲○○○○所有DE─6198號休\n      旅車右後方，等候經指引至該休旅車右後方之選民前去時\n      ，即以一張選票一千元代價，交付賄款之方式，旋由該成\n      年男子分別以內置一千元賄款之白色信封分別交付予均設\n      籍於新竹縣尖石鄉且於戶政註記為山地原住民，具有原住\n      民選票之張家旺、溫桂英、羅金錄三人（該三人投票受賄\n      罪部分，均經檢察官依職權不起訴處分確定），並囑付張\n      家旺等三人須投票支持甲○○○○，而張家旺等三人亦知\n      該金錢利益係選舉買票之目的，猶均基於受賄意思而收受\n      。嗣丁○○並向戊○○領取五千元，於餐會中與有投票權\n      之葉維明共同基於賄選之犯意聯絡，由丁○○將五千元以\n      三千元、二千元分裝於二信封袋內，並各置入一文宣之牛\n      皮紙袋，交付葉維明（投票行賄罪業經原審法院判處有期\n      徒刑四月，投票受賄罪處有期徒刑二月，定執行刑為有期\n      徒刑五月，褫奪公權二年，緩刑二年確定），囑其交付予\n      亦均設籍於新竹縣尖石鄉且於戶政註記為山地原住民，具\n      有原住民選票之丙○○及劉錦來。葉維明即將前開賄款及\n      文宣均轉交予丙○○（投票行賄罪業經原審法院判處有期\n      徒刑三月，投票受賄罪處有期徒刑二月，並定執行刑為有\n      期徒刑四月，褫奪公權二年，緩刑二年確定），同時告知\n      其中一份係其家中三張選票之賄款，要其投選甲○○○○\n      ；另一份則請其轉交家中具有二張原住民選票之劉錦來。\n      丙○○收受後，明知係選舉買票，仍將裝有三千元之信封\n      袋收下，並與葉維明基於共同賄選之犯意聯絡，於搭載劉\n      錦來（投票受賄罪業經檢察官依職權不起訴處分確定）返\n      回新竹縣尖石鄉嘉樂村四鄰麥樹仁九十四之一號劉錦來住\n      處後，即將內有二千元之信封交予劉錦來（起訴書誤載為\n      三千元），並以此金錢利益約定行使投票權給甲○○○○\n      ，劉錦來亦明知該金錢利益之目的，仍基於受賄意思而收\n      受。\n    (二)繼甲○○○○預訂於同年月三日下午六、七時許，在尖石\n      鄉秀巒村下田埔集會舉辦政見發表會，其妻露妮．萊撒乃\n      於同年月二日在其竹東競選總部，再交付丁○○十一萬餘\n      元，供買票賄選之用，丁○○抽取其中一萬餘元後，將十\n      萬轉交戊○○預作翌日行賄發放之用。嗣於三日晚間七時\n      四十六分許，甲○○○○、露妮．萊撒、丁○○、戊○○\n      仍承前同一犯意，由丁○○覓得熟知該選區選票且亦基於\n      共同賄選犯意聯絡之劉榮和（未經檢察官起訴），提供選\n      民名單，丁○○即與戊○○、劉榮和先於集會所旁商討發\n      放賄款事宜，旋由丁○○指示劉榮和交付二紙欲行賄之選\n      民名單予戊○○，戊○○並依劉榮和指引，前往該集會所\n      旁之新竹縣尖石鄉秀巒村二鄰田埔三０號民宅內等候，旋\n      於同日晚上七時五十二分、七時五十四分及七時五十五分\n      ，於核對名單後，分別交付各一千元賄賂予經劉榮和指引\n      前來均設籍於新竹縣尖石鄉且於戶政註記為山地原住民，\n      具有原住民選票之高勝宏、溫春雨、田勝賢（以上三人投\n      票受賄罪另由檢察官為職權不起訴處分確定）三人，並請\n      渠等投票支持甲○○○○。高勝宏、溫春雨、田勝賢等人\n      均明知戊○○交付金錢之目的，仍基於受賄意思而收受。\n      嗣經法務部調查局新竹市調查站調查員見時機成熟，於田\n      勝賢尚未離開時即入內當場查獲，並在戊○○皮包內起出\n      尚未發出之賄款十萬元（另有二萬四千一百五十元認係戊\n      ○○私人款項，與行賄無關）；在田勝賢身上起出方收受\n      之賄款一千元；繼在戊○○所有3H─1883號之自小客車上\n      （起訴書誤載為DE─6198號休旅車），起出丁○○所持有\n      尚未發出之賄款五萬五千元（分別裝在丁○○所有之五個\n      信封袋內，再裝入丁○○所有之黑色肩包內）。嗣溫春雨\n      嗣經通知到案後，提出所收受之一千元賄款扣案；張家旺\n      則稱所收受之賄款，已花用殆盡。\n三、案經臺灣新竹地方法院檢察署檢察官指揮法務部調查局新竹\n    市調查站（下稱調查站）、新竹市警察局、新竹縣警察局調\n    查移送臺灣新竹地方法院檢察署檢察官偵查起訴。\n    理  由\n壹、程序部份：\n一、按新修正刑事訴訟法係於九十二年二月六日經總統公布施行\n    ，而同日公布施行之修正刑事訴訟法施行法增訂第七條之三\n    復規定：「中華民國九十二年一月十四日修正通過之刑事訴\n    訟法施行前，已繫屬於各級法院之案件，其以後之訴訟程序\n    ，應依修正刑事訴訟法終結之。但修正刑事訴訟法施行前已\n    依法定程序進行之訴訟程序，其效力不受影響。」故九十二\n    年一月十四日修正刑事訴訟法施行前，已繫屬於法院之案件\n    ，證人及共同被告於警詢或檢察官偵查中之證言，其效力不\n    受影響（最高法院九十三年度台非字第九三號判決、九十三\n    年度台上字第二０三號判決意旨參照）。本件係於九十一年\n    一月十一日繫屬於臺灣新竹地方法院（原審卷第一頁），因\n    此本件有關證人田聖賢、林金榮、高勝宏、羅金祿、葉維明\n    、丙○○及共同被告於警詢、偵查中證言，效力均不受影響\n    ，辯護人主張證人於警詢之陳述無證據能力，洵屬無據。\n二、共同被告戊○○、葉維明、丙○○及共犯露妮．萊撒、劉榮\n    和均於本院前審以證人身分到庭陳述，另戊○○、丙○○、\n    丁○○再經本院以證人身分傳証，並均經被告及辯護人詰問\n    ，有本院選上訴字第八號卷第九０～一０四頁、重選上更(四)\n    第一０一～一０二頁、原審卷第二九五～二九八頁、及本院\n    重選上更(六)卷審判筆錄可考，渠等所為證言，均非傳聞，自\n    具證據能力。\n三、至本案認定事實所引用之書面証據，如天然谷名片、巴燕\n    . 達魯名片、宣傳單、宣傳資料、手繪地圖、山地原住民候\n    選人登記冊、賄選案件事實表、搜索筆錄、扣押物品收據證\n    明書、扣押筆錄、新竹縣警局化驗結果函、皮包及現金照片\n    、立委候選人甲○○○○各鄉輔選人員組織及責任分工執掌\n    表、總部會議紀錄、總部及其後援會之主要幹部名單、輔選\n    會議簽到表、總部及後援會主要幹部聯絡電話、美國運通銀\n    行對帳單、信用卡月結單、荷蘭銀行、遠東國際商業銀行信\n    用卡繳款通知單、五峰郵局檢送之丁○○存款往來明細表、\n    、甲○○○○競選總部人員分工表、筆記資料、白色便條紙\n    、藍色便條紙、黑色筆記本、法務部調查局蒐證錄影帶、翻\n    拍照片、測謊報告等文書証據，均係於訴訟繫屬前即已存於\n    卷內，且非係公務員違背法定程序所取得，又無刑事訴訟法\n    第一百五十九條之四之顯有不可信之情況與不得作為證據之\n    情形，且被告及其辯護人亦均不爭執証據能力（本院卷第三\n    一頁背面～三二頁背面），應認均有證據能力。\n貳、實體有罪部份：\n一、本案訊據被告甲○○○○固坦承上開時日因競選活動而在「\n    天然谷餐廳」開席，及在下田埔集會所為政見發表時均在場\n    ，惟矢口否認有賄選犯行，並辯稱：天然谷餐廳，其僅是依\n    行程安排，是同行有人說天晚了要吃飯，而山上只有那家餐\n    廳，且當天隨行的其只認得自己幹部。錄影帶調閱後也證明\n    其不是畫面中的人。另其妻交付丁○○之金錢是選舉開支，\n    不是要賄選。在下田埔集會所為政見發表時，其一直在集會\n    所內，並未進入民宅，他人如何發放賄款，均未參與，亦不\n    知情。其是改革者不可能去買票，且本案證人大都不認識，\n    其未賄選，亦未指使他們，是他們自行談好去做的，與其無\n    涉云云。\n二、經查：\n    (一)同案丁○○於偵、審均供証其係被告競選總部辦公室主\n        任一節，核與証人戊○○証稱：丁○○是總指揮，競選\n        總部活動均係其安排，所有拜票活動都是其主持（原審\n        卷第一七、二一、一六六頁筆錄）；証人葉維明證稱：\n        其於某日路過甲○○○○競選總部，經丁○○邀請為甲\n        ○○○○助選（選上訴卷第九九頁筆錄）。證人劉榮和\n        證稱：其係丁○○出面找去為甲○○○○助選（選上訴\n        卷第九三頁筆錄）等情，均相一致，且有被告競選總部\n        幹部名單一件扣案可稽（選他卷第一０六頁）。參以，\n        證人露妮．萊撒亦証稱：有交付十一萬餘元予丁○○，\n        作為競選後援會開銷使用（原審卷第六三頁、重上更(四)\n        卷第一一頁筆錄）。是丁○○確係競選總指揮，其支配\n        活動行程及為被告邀集助選者等事宜，就被告整個競選\n        活動積極參與介入極深，居於主控地位，則丁○○嗣於\n        本案証稱其僅是擔任志工；或證人陳道明證稱：不知甲\n        ○○○○之競選總部有安排職務（選上更(一)字卷第八九\n        、九０頁筆錄），指稱競選幹部名冊不實，顯與前開事\n        證有違，而為飾卸、迴護之詞，要無足採，丁○○係被\n        告競選辦公室主任之事實，可堪認定。\n    (二)另本件扣案印有民主進步黨字樣之紙張共六張，其中五\n        張上寫有徵召提名立法委員候選人甲○○○○，下方則\n        分別有各鄉輔選人員組織及責任分工職掌表三張、各鄉\n        、鎮、市、區輔選組  織責任分工職掌表二張（選他卷\n        第九六、九七、一０二～一０四頁）。而各鄉輔選人員\n        組織及責任分工職掌表三張分別為：竹林村（列有村召\n        集人一名、副召集人二名及各鄰連絡人共五名，並均列\n        有各該負責人之連絡電話）、桃山村（列有村召集人一\n        名、副召集人一名及各鄰連絡人共廿一名，並列有召集\n        人之連絡電話）、及一張未列村名（但列有總召集人一\n        名、副總召集人一名、村召集人一名、副召集人二名及\n        各鄰連絡人共廿五名之姓名，並列有各該總召集人、召\n        集人、副召集人之連絡電話）。各鄉、鎮、市、區輔選\n        組織責任分工職掌表其中一張列有大隘村、桃山村、花\n        園村及竹林村共四村之召集人、副召集人姓名。核與竹\n        林村及桃山村之各鄉輔選人員組織及責任分工職掌表上\n        之召集人、副召集人姓名相同。另一張印有民主進步黨\n        字樣之紙張，其上寫有十月廿二日下午三時總部會議，\n        下方則列有七項議事進行順序（選他卷第九八頁）等情\n        。被告當時係民主進步黨之立法委員，該印有民主進步\n        黨徵召提名立法委員候選人甲○○○○字樣紙張之內容\n        自係為被告所擬。且單就扣案部分資料，已可看出競選\n        組織架構形成。再觀扣案輔選會議簽到表（同上卷第一\n        ０七～一一０頁），不僅係以立法委員用箋之紙張簽到\n        ，且簽到出席之三十人均列有各該出席人之電話及住址\n        ，雖無法看出會議召開時間，然可確定有召開過輔選會\n        議，且其上三十名出席人員，多與上述召集人、副召集\n        人或各鄰連絡人重覆（出席人員而列為上開組織及責任\n        分工職掌表之名單有：萬福壽、朱禮沐、羅新輝、朱禮\n        元、陳錦富、夏有年、丁○○、張國獻、秋賢良、錢大\n        維、彭興福、戴文乾、呂源吉、林坤金、王正雄、田光\n        男、陳雲鵬）。又依扣案總部及後援會之主要幹部名單\n        、總部及後援會之主要幹部聯絡電話（同上卷第一０六\n        、一一一頁）二紙，亦係以立法委員用箋之紙張列名，\n        再與競選總部幹部名單、及組織架構圖（同上卷第一０\n        ０、一０五頁）相互對照結果，該競選組織顯然經過研\n        商後定案，架構完整而仔細，且以當時仍係立法委員之\n        被告立法委員用箋紙張為之，被告一切活動並按照排定\n        行程進行，被告自均有參與商議無疑。是被告辯稱：組\n        織架構尚未成立，辦公室進出沒有管制，任何人都可以\n        進來，其未積極參與，殊與常情不符，不足憑信。證人\n        蕭世暉於本院前審證稱：「僅係處理地方要找委員（即\n        被告甲○○○○）及人民陳情之事情，不清楚甲○○○\n        ○行程，後援會之事是丁○○在處理」等語（選上訴卷\n        第一四九～一五０頁筆錄），顯與前開事証不符，而為\n        迴護被告之詞，無從採為被告有利之證明。\n    (三)又巴燕、達魯之妻露妮．萊撒先於原審証稱：在竹東競\n        選總部，有交十一萬多元給丁○○，為後援會成立費用\n        （原審卷第六三頁筆錄）；於本院前審則證稱：九十年\n        間甲○○○○選舉立委之財務，係其一人處理。其記得\n        在九十年十一四日成立尖石鄉後援會，需要一筆錢，故\n        於成立前一星期交付不只十一萬元給丁○○，作為成立\n        後援會的花費，如鷹架、舞台等開銷，甲○○○○募款\n        及財務都是其在管理（重選上更(四)卷第一○一頁反面～\n        一０二頁反面筆錄）等語。是本案被告巴燕、達魯競選\n        財務既均由其妻露妮．萊撒一人統籌辦理，而同案丁○\n        ○係競選總部主任，且是被告之表弟；同案戊○○為競\n        選總部之拜票組、會計組組長，並係露妮．萊撒之同學\n        ，與甲○○○○及露妮．萊撒夫妻關係密切，露妮．萊\n        撒並稱因信任表弟丁○○而交付款項（原審卷第六三頁\n        ），且丁○○、戊○○均非參選之人，亦未曾自行出資\n        ，則渠等行賄款項自係來自被告之妻露妮．萊撒，當可\n        認定。亦無可能丁○○及戊○○在未經允許情況下，即\n        將被告之妻交付之十萬餘元逕行用來向選民行賄，另被\n        告對其親密之配偶及高達十餘萬元之競選支出，事關其\n        當選與否，亦難諉稱毫不知情。參以一般選舉，均以成\n        立總部方式從事競選活動，倘非候選人親信，無法參與\n        重要競選策略。若有行賄，亦係由親信、親屬或重要幹\n        部等人事先謀議分工，各司其職。則被告於以下之餐廳\n        或集會所忙於演說或舉辦政見說明會，而推由與同車上\n        山且係渠夫妻最信任之丁○○、戊○○在餐廳或集會所\n        外打點行賄及負責賄款發放等事實，均屬選舉責任分工\n        常態，自不得以被告未實際交付賄款，即認與被告無關\n        。被告辯稱不知其妻交付鉅款及同案丁○○、戊○○有\n        交付賄款之事云云，核與常情不符，不足採信。被告聲\n        請傳喚證人即選民游國當，欲證明下田埔說明會時其均\n        在會場，不可能事事插手。惟證人游國當證稱：「當日\n        下田埔說明會其未在場，其妻亦是去聽幾分鐘即回家」\n        等語（選上訴卷第八八頁筆錄）。證人鳳秋喜、芭翁‧\n        都宓雖均證稱：「甲○○○○都在說明會場，沒有離開\n        」等語。本件既由被告之妻交付金錢予同案丁○○，再\n        由同案丁○○轉交其他競選工作夥伴或同案戊○○行賄\n        ，則於行賄交付賄款時，被告縱人在說明會場，仍無礙\n        於其與妻露妮．萊撒、同案丁○○、戊○○等人成立共\n        同行賄之事實。況同案戊○○於原審業已坦承為被告行\n        賄買票之事，嗣於本院前審亦以證人身分結證無誤（選\n        上訴字第九七頁筆錄）。故被告與其妻露妮．萊撒、同\n        案丁○○、戊○○等人間，就買票賄選犯行，應早有謀\n        議，致丁○○、戊○○至以下之活動地點，即得分工進\n        行。\n三、再查，有關於天然谷餐廳停車場旁行賄部分：\n    (一)本案被告於「天然谷餐廳」餐敘時，有一不詳姓名成年\n        男子，在天然谷餐廳前DE─6198號休旅車旁，交付賄款\n        予張家旺、溫桂英、羅金錄部分，業據證人張家旺證稱\n        ：九十年十一月一日晚間，其與老闆李金水一同前往『\n        天然谷餐廳』吃飯，看到立委參選人甲○○○○亦在場\n        ，其用餐完等候要離去時，碰到一位不詳姓名之男子，\n        叫其至室外休旅車旁，在車旁即有另一位不詳姓名之男\n        子，交予其一個白色信封，其拿取後就直接放進口袋，\n        回去打開才知道信封內是裝著一千元（選他卷第一三七\n        頁背面調查筆錄）；證人溫桂英證稱：其於九十年十一\n        月一日晚間確實有至『天然谷餐廳』，當時立法委員候\n        選人甲○○○○有在現場演講，餐會中有不明之女子要\n        其至屋外空地車旁，其即依言，至屋外休旅車旁，即有\n        一位不詳姓名之男子，交予其以空信封裝著一千元（選\n        他卷第一四０、一四一頁調查筆錄）；證人羅金錄證稱\n        ：九十年十一月一日晚間伊前往『天然谷餐廳』，替立\n        委參選人甲○○○○助選造勢，餐會中其因肚子不舒服\n        ，到屋外找衛生紙，碰到一位不詳姓名男子，叫其至休\n        旅車旁，即有另一位不詳姓名之男子，交付其一白色信\n        封內裝著一千元，當時該男子還問其是否只有一個人，\n        其告知家裡僅其一人前來，其知道該不詳姓名男子應該\n        是替甲○○○○買票（選他卷第一四三、一四四頁調查\n        筆錄）各等情，大多相符。乃證人張家旺、溫桂英、羅\n        金錄與被告均無怨隙，自無誣指被告之必要，且渠等均\n        非被告競選幹部，並係應邀前往，則被告辯稱僅是「同\n        行有人說天晚了要吃飯，而山上只有那家餐廳」之臨時\n        前往用餐一節，顯與事實不符，要無足採。況前開證人\n        張家旺、溫桂英、羅金錄均証稱於「天然谷餐廳」，係\n        經人指引至休旅車旁，由不詳男子交付一千元一節，核\n        與經原審及本院前審當庭勘驗調查局採証九十年十一月\n        一日在天然谷餐廳前之錄影帶結果，畫面顯示：自六時\n        卅分至七時四十分間，餐廳外陸續有多人（或男或女或\n        抱小孩者），一一走向DE─6198號休旅車右側，雖畫面\n        因遭該休旅車遮擋，無法得見於休旅車右側該戴白色帽\n        男子與走近之人之互動，然走近之人，既非同時趨前，\n        且均於短暫停留即走離該休旅車折返（原審卷第一五九\n        頁、重選上更(三)卷第五五～五六頁）等情相符，衡以該\n        時既係競選餐會，則多人分別逐一轉至停車場角落隱蔽\n        之該休旅車旁，均於卅秒至一分鐘不到即又走出，所為\n        何事？則除如前開証人所証，係經人指引前去領取一千\n        元賄款外，已無其他合理說明，乃証人前揭証述，自屬\n        可信。\n    (二)雖證人羅金錄嗣於原審改稱：「一千元是有去幫忙掛旗\n        子的油費」（原審卷第一九五頁筆錄）、證人張家旺及\n        溫桂英亦改稱：「不知道所收受之一千元是什麼錢，也\n        都已經用完」（原審卷第一九七～一九九頁筆錄）各云\n        云，不僅與渠等先前所述不符，且當時該名男子亦未交\n        付任何旗子供羅金錄懸掛；及惟該名不詳姓名男子既與\n        証人張家旺、溫桂英二人均不相識，豈會無端各交付一\n        千元，渠二人亦無在不知目的之情況下任意收受他人金\n        錢之理，是渠等前揭更異之詞，當係事後迴護被告及同\n        案丁○○之詞，均委無足採。\n    (三)又車號DE─6198號休旅車係被告所有，有車號查詢汽車\n        車籍一紙在卷可憑（選他卷第四頁），被告並自承當日\n        乘坐該休旅車至「天然谷餐廳」用餐，而依錄影帶內容\n        及翻拍照片亦可看出休旅車內載有他人，並有人打開車\n        門與車內之人聊天，被告曾陪同民眾進入該休旅車右側\n        ，後即有一不詳姓名之男子即於休旅車旁發放賄款，此\n        經同案丁○○、張家旺、羅金錄證述無訛。雖取得賄款\n        之証人張家旺、溫桂英、羅金錄均稱不識該於休旅車右\n        後方交付賄款之男子，而自錄影帶或刑警局翻拍照片亦\n        均無法確認其身分，然均可明顯見其頭戴白色帽子（卷\n        附錄影磁片及翻拍照片附件二、三）。佐以於錄影及翻\n        拍照片有多人均戴同款白色鴨舌帽及白色汗衫（背後印\n        字），及被告及証人丁○○亦均供証有提供白色帽子及\n        汗衫予工作人員穿戴（本院九十八年六月十日審判筆錄\n        第三頁），則該立於休旅車右後發放賄款之男子，為被\n        告競選之工作人員，亦堪確認。而於該為被告競選之不\n        詳姓名男子發放賄款期間，証人丁○○、戊○○及被告\n        均曾靠近該休旅車（如本院前審（更(三)）勘驗結果被告\n        於四、五、十九均在車旁；二十則是戊○○開該車門放\n        置一包物品入車內；証物袋內翻拍照片及刑警局翻拍照\n        片附件二三均見著白色紅短袖上衣之丁○○同立於該車\n        右後等），故被告實無法諉為與其無關或不知此事之理\n        。\n    (四)另丁○○於「天然谷餐廳」內，將裝有賄款之信封袋及\n        裝有文宣之牛皮紙袋交付葉維明，囑付其轉交丙○○及\n        劉錦來之事實，業據同案葉維明於調查站供稱：「裝有\n        三千元及二千元之信封係丁○○交付，請其拿給丙○○\n        及同車來的劉錦來。袋子裡面確實有信封袋，信封袋裡\n        面有三千元，其即將信封裡的三千元連同信封袋直接拿\n        給丙○○轉交劉錦來」（偵卷第一六九頁筆錄）。其於\n        偵訊時亦供陳：「新竹市調查站所言實在，一定有錢，\n        是丁○○要其交給劉錦來等人」各等語（偵卷第一六五\n        頁反面）。核與同案丙○○於調查站、偵查中供稱：「\n        當時丁○○拿了二個大型牛皮紙袋內裝很多現金的小信\n        封，以及甲○○○○的競選文宣交給葉維明，葉維明當\n        場就從其中一個大信封袋中抽出二個內裝現金的小信封\n        交給他，並要他將其中一個轉交給其叔叔劉錦來。其推\n        測是錢而馬上拒絕，但葉維明向其表示你看到了拿去沒\n        關係，隨後其載劉錦來回家，到他家時，即將葉維明要\n        其轉交的信封袋和甲○○○○的文宣拿給劉錦來，並當\n        場打開，裡面裝有二千元，其自己的那個信封袋回家後\n        打開看，裡面裝有現金一千元三張，共三千元，已被其\n        花掉」（偵卷第一七０頁反面、第一七七、一七八頁筆\n        錄；原審卷第一一四頁筆錄）；及至本院前審仍具結證\n        稱：確有自葉維明處取得丁○○交付之二信封，內各有\n        三千元、二千元，二千元信封其依葉維明指示交付劉錦\n        來無誤，且確實未告知用途無誤（選上訴卷第一０三頁\n        ；選上更(一)卷第一０一～一０二頁筆錄）等語一致，且\n        同案丁○○於原審亦坦認：「錢是其另外給葉維明的，\n        是用二個信封裝錢，但未指明要給誰，是要找人幫忙插\n        旗子用的，但其並沒有給旗子」（原審卷第一一三頁筆\n        錄），確有交付內裝錢之二信封一情均相符合，況葉維\n        明既為被告助選，當無自陷入罪誣指被告及丁○○二人\n        之可能。乃葉維明、高明光所証前揭交錢、取錢一情，\n        既與事實相符，自可堪信為真實。\n    (五)至葉維明嗣於原審、本院前審改稱：「錢是要給丙○○\n        及劉錦來兩人一組插旗子的費用」云云，然其就親身經\n        歷之單純事實，前後所稱不一，已難採信。況所稱「插\n        旗子」之事，於九十一年二月廿七日原審訊問之前，均\n        未有任何人提出，及至丁○○推稱提出「插旗子」之說\n        詞，葉維明始附合其詞。況渠所找插旗之人，依同案丙\n        ○○於原審陳稱：當天七點多回到劉錦來門口，拿其中\n        一個信封給他，告訴他說這是葉維明給的，他說他知道\n        。根本沒有要插旗子，且劉錦來年紀很大，得癌症，行\n        動不方便（原審卷第二三九頁筆錄）之八十餘歲罹患癌\n        症且行動不便之劉錦來，復未交給任何旗子，自與常情\n        有違。於本院更結証：葉維明於翌日告知其將會被調查\n        站約談，及錢是要給其插旗用，然其並未幫被告插旗子\n        （本院九十八年十一月四日審判筆錄第五頁）等語明確\n        在卷。又證人劉錦來早在調查站詢問時即坦承交錢未有\n        說明要用來插旗子（選他卷第一七五頁筆錄），並於原\n        審第一次作證時猶承認收受賄款（原審卷第一一七、一\n        一八頁），迨至第二次作證時始改稱：是丙○○交給，\n        說其很辛苦插旗子、發文宣云云（原審卷第一五六頁筆\n        錄），經原審訊以是否確有幫忙插旗子及發文宣時，又\n        答以是「之後」幫忙（原審卷第一六一、一六二頁）等\n        語。顯見葉維明、劉錦來嗣所稱「插旗子、發文宣」，\n        均屬事後串証、迴護被告之詞，均不足採。\n    (六)另於「天然谷餐廳」，同案丁○○係持印有立法院之牛\n        皮紙袋內裝有現金用以行賄之事實，已如前述，而被告\n        當時為立法委員，該牛皮紙袋當係出自被告無誤。被告\n        既以成立競選組織方式，從事競選活動，同案丁○○及\n        同案戊○○均屬被告之親信，丁○○並於本院前審陳稱\n        ：交予葉維明信封內的錢，是服務處負責管帳的人交付\n        的（選上訴字第四六頁筆錄），而依其競選組織架構，\n        同案戊○○係會計組組長，負責金錢支付、記帳等會計\n        事項，參以「天然谷餐廳」聚餐時，同案丁○○自承曾\n        問同案戊○○有無帶錢，及當天餐費亦係由同案戊○○\n        支付，亦堪認前揭丁○○所指賄款應係向戊○○領取無\n        訛。是本案被告既與競選辦公室主任丁○○同時到達「\n        天然谷餐廳」，嗣復係於被告之休旅車旁，或由一男性\n        或由一女性（張家旺、羅金錄指係經由男子；溫桂英則\n        指係經由女子）指引至被告休旅車後向一男子取得賄款\n        ；嗣丁○○並隆以被告提供之立法院牛皮紙袋裝錢行賄\n        ，要求支持被告，則前揭賄款既非丁○○自行出資，且\n        行賄當選之利益全歸參與競選之被告，則顯係被告推由\n        同案丁○○、戊○○負責並指示其他工作人員行賄選民\n        ，既與當今社會選舉賄選型態相符，益足証係與被告共\n        同基於犯意聯絡無疑。\n四、另查，有關下田埔集會所旁民宅行賄部分：\n    (一)據同案戊○○於原審及本院更(四)審時供稱：「當天在集\n        會所時，其到外面與人聊天，看到丁○○與其不認識的\n        劉榮和在廣場談話，丁○○叫其過去幫忙一下，說其身\n        上有錢，他已交代劉榮和，丁○○並對劉榮和說交代給\n        其即可，他就先進去集會所，劉榮和就拿二張上面載有\n        姓名的便條紙（即欲行賄之選民名單），並要其去集會\n        所旁邊田埔三０號民宅，說他會叫人去民宅，且只要有\n        人找，就給他一千元。其即用前一天丁○○交付之十萬\n        元給名單上的人，其計交錢給溫春雨、高勝宏、田勝賢\n        時，雖未講要他們支持甲○○○○，但事實上確實希望\n        他們能支持甲○○○○，他們應該也都明白。扣案二張\n        名單就是劉榮和交其持有」等情不諱（原審卷第一二八\n        、二四五、二四六頁、選上訴卷第九七頁、更(四)審卷審\n        判筆錄第8頁、第10頁）。核與當日新竹市調查站之搜\n        證，並經原審勘驗，製有勘驗筆錄（原審卷第一六七～\n        一六九頁、第三００～三０一頁）之錄影帶螢幕顯示：\n        (1)七時四十六分，戊○○與同案丁○○、劉榮和三人交\n        談（戊○○指稱當時討論發放賄款事宜；同案丁○○指\n        稱是要劉榮和找人發文宣，劉榮和身上沒錢，故請戊○\n        ○先付錢，並交待劉榮和如果情況緊急，請他找幾個人\n        ，一人發一千元工錢、便當錢給他們；證人劉榮和則證\n        稱在聊天）。(2)七時四十九分，劉榮和右手指向右邊（\n        戊○○稱此時是指向旁邊下田埔三０號民宅，欲其入內\n        發放賄款；證人劉榮和則證稱是戊○○說要借房間，其\n        以為戊○○要借廁所，就隨便借給她）。(3)四十九分十\n        二秒，戊○○與劉榮和二人有擦身，劉榮和交某物品到\n        戊○○右手，戊○○右手多出白白的東西（戊○○稱劉\n        榮和當時即交付名單至其右手；證人劉榮和否認交付物\n        品，稱未見過該便條紙）。(4)七時五十二分，有一名男\n        子進入該房間與戊○○交談，戊○○低頭看東西，五十\n        二分五十四秒，戊○○抬起頭來，右手伸到右邊口袋再\n        掏出來，該名男子離去；五十三分卅八秒，又有一名男\n        子進入，戊○○又低頭看東西，五十四分零五秒，戊○\n        ○再從右邊口袋掏出東西，該名男子離去；五十四分五\n        十六秒，一名戴帽子男子進入，先在房內走晃一圈，接\n        近戊○○，楊又低頭看東西，不時抬頭往窗外看，五十\n        五分五十四秒戊○○抬起頭來後幾秒，該名男子離去（\n        戊○○指稱低頭動作是在看名單，手伸入口袋是掏錢動\n        作，並發放賄款給該三名男子）。(5)七時五十八分，一\n        名女子進入，與戊○○交談，五十九分，調查站人員衝\n        入等情，均相符合。且證人劉榮和嗣於本院前審亦證稱\n        ：「是應丁○○邀請，出面為甲○○○○助選，當天與\n        丁○○等人一起到下田埔，當晚係與丁○○商量，並依\n        丁○○指示交付名單給戊○○」等情一致（選上訴卷第\n        九二、九三頁筆錄），此外，復有記載羅雲志、羅雪花\n        等十六人之行賄名單二紙扣案可資佐證，乃丁○○、劉\n        榮和、戊○○三人於下田埔集會所旁民宅發放賄款之事\n        証，至臻明確。\n    (二)雖同案戊○○稱其不認識錄影帶翻拍照片中之三名男子\n        ，及田勝賢、溫春雨亦稱此翻拍照片太模糊或太暗，看\n        不清楚照片中男子是何人（更(四)卷第審96年5月8日審判\n        筆錄），惟田勝賢、高勝宏及溫春雨均證稱：確有收\n        到同案戊○○交付之一千元，並知悉係為支持甲○○○\n        ○而收取，或戊○○有要求彼等支持甲○○○○（選他\n        卷第四四～四八頁、第一一八～一二０頁、第一二二～\n        一二九頁筆錄；原審卷第一二一～一二四頁筆錄），足\n        認戊○○確於該址交付賄款予溫春雨等三人，況田勝賢\n        、高勝宏及溫春雨均與被告素無怨隙，若非同案戊○○\n        確有交付一千元賄款，並要求支持被告，自無一致誣指\n        被告之必要，是渠三人上揭證詞應屬實情，而可採信。\n    (三)有關露妮．萊撒前稱有交付丁○○十一萬餘元一節，丁\n        ○○亦先否認有交付戊○○十餘萬元（選他卷第七二頁\n        反面筆錄）；後供証：九十年十一月三日中午左右，其\n        有將甲○○○○太太交付之約十一萬元轉交給戊○○，\n        親手轉交前，有從中拿出約一萬元，剩下約十萬元在戊\n        ○○手上，主要是用作支付第二天競選總部後援會成立\n        大會時之開銷（選他卷第一八九頁反面筆錄）；露妮．\n        萊撒交給我十一多萬元，說要訂一些桌椅、架子等費用\n        ，我抽其中一萬多元支付，十萬元交給戊○○（原審卷\n        第五三頁筆錄）；露妮．萊撒有交付十一萬元，作後援\n        會成立大會相關開支費用，其付雜項開支，剩下的錢因\n        甲○○○○希望我陪他去下田埔，其位於偏遠山區，怕\n        錢放身上弄怕，就請戊○○幫忙保管（重選上更(四)卷第\n        一○三頁正、反面）等語。另戊○○先後供証：扣案十\n        萬元是今日下午二、三點在竹東競選總部，由丁○○本\n        人交付，是次日幹部會議用來支付花籃的（選他卷第六\n        三、六四頁筆錄）；遭查扣的錢是因丁○○要去山上，\n        怕掉了，並說是明天總部開銷的錢，交其保管，交錢是\n        在下午二點多，在竹東總部（原審卷第七一頁筆錄）。\n        身上十萬元是十一月三日早上丁○○在競選總部拿給我\n        的，是總部辦活動的費用，下午七點多在下田埔，丁○\n        ○叫我過去，並交代劉榮和說交代我就可以了，他就進\n        去集會所，劉榮和問我身上有無錢，他說丁○○交代這\n        個與妳談，錢在我這邊，即交給我二張便條紙，要我去\n        集會所旁邊民宅，他會去集會所裡面叫人出來找我，只\n        要有人找我就給他一千元，劉榮和沒有給我任何錢，我\n        不認識劉榮和，是因為丁○○告訴我他已交代劉榮和，\n        及我身上有之前丁○○交給我的十萬元，我即從皮夾拿\n        出二萬多元放在口袋裡，再一張張抽出來給來的人，來\n        的人自己報名字，我即核對劉榮和給的名單並打勾（原\n        審卷第二四五～二四六頁管筆錄）等情。是關於露妮．\n        萊撒交付十一餘萬元予張國之用途，已先見渠等先否認\n        ，諉飾避重之情，且對該筆款項用途，究係總幹部會議\n        、或總部後援會、亦或五峰鄉尖石後援會使用？渠等供\n        辯亦有歧異，對交付或取得該筆十一萬餘元之時間，究\n        係於成立大會前一周（即十月底）？亦或查獲前一日（\n        即十一月二日）或查獲當日（即三日）？丁○○交予戊\n        ○○係上午或下午？均互核不一，已有可議。況經本院\n        追問後援會事宜，被告先稱係一名為邱志明為其籌組五\n        峰鄉尖石之後援會，然又稱其已撤走，無法提供地址供\n        傳証（本院九十八年四月廿一日準備筆錄第七頁），被\n        告旋又另具狀提供三後援會主要成員供查。惟該三証人\n        乙○○○○、烏杜大勒巴克及己○○○於本院結証：係\n        屬三不同區域之後援會成員，且渠等後援會均宗教或社\n        會團體自發性或機動性組成，並無一固定領導人，被告\n        亦未曾支付任何款項，甚且証人翡束寶於競選期間未曾\n        見過被告，僅因被告係部落產生之立委而為支持（本院\n        九十九年四月十四日審判筆錄第三～八頁）等情。乃三\n        証人所証渠後援會之自發且機動之性質，即不可能係接\n        受被告任何補助款項籌組，是証人所証不僅無從為被告\n        有利之認定，反足証被告所辯其妻露妮．萊撒交付丁○\n        ○之十一餘萬元係供後援會使用一節，非屬實在。又衡\n        以丁○○方交給戊○○十萬元，然於下田埔現場即僅指\n        示劉榮和交行賄名單予戊○○，並告知劉榮和戊○○身\n        上有錢，劉榮和即要戊○○依名單所載對其指示前來之\n        人各行賄一千元，戊○○旋並依指示交付賄款，既未質\n        疑丁○○所指其身上有錢何所指？且依錄影帶顯示，行\n        賄名單係由劉榮和交付，而同案戊○○與劉榮和互不相\n        識，劉榮和亦不認識被告（原審卷第二四八頁、選上訴\n        卷第九三頁筆錄），則戊○○竟未經詢問丁○○或劉榮\n        和，即依言對經指引前來民宅之選民交付賄款。顯見渠\n        三人對戊○○持有自被告配偶處取得之十萬元現金，即\n        係做為賄款發放一節，早已明知並有犯意聯絡，故無待\n        徵詢，即可分工進行。參以，戊○○經法務部調查局為\n        測謊鑑定時，就「(一)渠沒有幫巴燕達魯買票賄選；(二)扣\n        案十萬元現金不是巴燕達魯的買票款項。二問題經測試\n        均呈情緒波動反應，研判有說謊。」亦有該局測謊報\n        告書一件在卷可參（選他卷第二二八頁），益足認定。\n    (四)至如前所述，証人露妮．萊撒稱係於十一月三日前一星\n        期即已交付十一萬餘元予丁○○，而丁○○亦供証甲○\n        ○○○夫人交給其亦係十一萬多元一致，惟其後稱轉交\n        予戊○○或係十萬餘元或僅係十萬元整，而同案戊○○\n        則供稱：其係於到下田埔當日自丁○○處收到該十萬元\n        ，其因想那十萬元是一疊錢，就先用自己的錢交付行賄\n        ，事後再從那十萬元扣除（原審卷第第二四五頁筆錄）\n        一情，則本案在戊○○皮包及其身上起出之十二萬四千\n        一百五十元，既均稱其中十萬元是一疊，則該十萬元確\n        係露妮．萊撒原交付予同案丁○○十一萬餘元之一部，\n        且係由丁○○轉交戊○○預備供發放之「賄款」無訛，\n        另戊○○於遭查獲前在現場交付高勝宏、溫春雨、田勝\n        賢各一千元之賄款，戊○○稱係先自行墊付，核與丁○\n        ○既已交賄款供其交付，且原訂行賄對象亦不止高勝宏\n        、溫春雨、田勝賢三人，衡情自是逕取賄款交付，何須\n        費事自行墊付再行扣抵？惟因戊○○亦為本案共犯，縱\n        所言墊付屬實，亦係其與被告夫妻另行結算事宜，要無\n        礙扣案十萬元原即係供預備交付之賄款性質。至另扣得\n        二萬四千一百五十元，因無証據認係露妮．萊撒或丁○\n        ○之前所交供發放之「賄款」，則應認係戊○○私人所\n        有款項。另丁○○經於黑色肩包裡查扣五萬五千元於原\n        審供稱：係其所有，其中一個白色信封一萬四千元是要\n        交給其子為大學生活費，其餘則是預備於下週一繳信用\n        卡費，其用信封袋分裝是避免混淆云云。惟查扣案五個\n        信封袋，均係裝千元紙鈔，分別為二萬三千元一封、一\n        萬四千元一封、及六千元有三封，而九十年十一月三日\n        係星期六，被告於星期六晚上將前開現金分裝於信封袋\n        帶至深山，既不可能繳錢，也不可能係為交付其於台北\n        生活之兒子，帶如此多現金上山為了「星期一繳錢」令\n        人不解，且只為了「避免混淆」而分裝在五個信封袋內\n        卻無法說出所以然來，更令人難以置信。況被告丁○○\n        自承其薪資均入五峰郵局帳戶（原審卷第二五０頁審理\n        筆錄），以當今全省自動提款機林立之情形，若真有信\n        用卡款待繳，其幾乎可隨時隨地提款繳納，當無提前多\n        天並攜現金至偏遠山區之理。且經原審調閱其五峰郵局\n        帳戶，自九十年一月二日起至九十年十一月卅日止，均\n        無提領超過一萬五千元之記錄，此有五峰郵局客戶歷史\n        交易清單在卷可參，已難証明扣案五萬五千元係自有提\n        領。另其於本院提出美國運通銀行（下稱運通銀行）綜\n        合對帳單一紙、信用卡月結單二紙、荷蘭銀行繳款通知\n        單二紙、遠東國際商業銀行（下稱遠東商銀）信用卡繳\n        款通知單二紙，共係三張信用卡，與其所辯之四張不符\n        外，觀之各該單據內容，無一與其所分裝現金之金額相\n        符。且其中就荷蘭銀行繳款通知單，經丁○○塗以黃顏\n        色，分別係十月份五千零十八元及十一月份六千零十八\n        元，且均註記為「已繳金額」，既已繳款，自亦無須再\n        行繳交；況上二筆帳單均係以自動轉帳扣繳，更無取款\n        繳交之必要。另運通銀行信用卡月結單之六千元消費金\n        額，亦已註明「已收到您由提款機支付之賬款，謝謝」\n        ，則被告空言分裝現金為避免所繳款項混淆，惟所提證\n        據無一係待繳之款項，亦無一與其分裝之金額相符，上\n        開證據均無法為有利於丁○○之認定。參以，露妮．萊\n        撒前已証稱被告甲○○○○競選之財務均由其一人負責\n        ，及如前所述，丁○○前於十一月一日在天然谷餐廳已\n        然行賄付款，復非其亦未自行出資，故露妮．萊撒當非\n        僅交付此次賄款予丁○○發放，足証前開金額亦係露妮\n        ．萊撒交予丁○○供行賄之用所餘，致其須飾詞狡卸。\n        是本案經查獲時，仍有未交付之十五萬五千元賄款扣案\n        足資佐証，則被告甲○○○○賄選犯行，事証已臻明確\n        。\n五、按公職人員選舉罷免法第九十條之一第一項之賄選罪，以對\n    於有投票權之人行求、期約或交付賄賂或其他不正利益，而\n    約其不行使投票權或為一定之行使者為構成要件，其行求、\n    期約、交付行為，係屬階段行為。交付賄款階段，以行賄者\n    已實施交付賄賂之行為，一經交付，罪即成立，雖不以收受\n    者確已承諾，或進而為一定投票權之行使為必要，但仍以收\n    受者已收受，而有受賄意思者為限。本案前揭收取賄款之証\n    人即張家旺、溫桂英、羅金錄、丙○○、劉錦來、高勝宏、\n    溫春雨、田勝賢等人，均設籍新竹縣尖石鄉，除丙○○外，\n    渠等戶政資料並均註記為山地原住民，此有法務部戶政連結\n    作業系統電腦資料在卷（原審卷第二五八、二六一～二六五\n    頁；重選上更(六)卷第四０頁）可稽，是渠等均為本次山地原\n    住民立法委員選舉之有投票權之人，自堪認定。又本件據證\n    人羅金錄證稱：其知道前述不詳姓名男子應該是替甲○○○\n    ○買票（選他卷第一四三、第一四四頁筆錄）；同案丙○○\n    於原審、證人劉錦來於原審第一次作證、證人田勝賢、高勝\n    宏於調查站亦均為相同之證言（選他卷第四五、一一九頁筆\n    錄；原審卷第一一四、一一七、一一八頁筆錄）。另證人溫\n    春雨於調查站則證稱：同案戊○○確實有拿一千元給我，並\n    要求其支持甲○○○○（選他卷第一二四頁筆錄）。是六人\n    均已證稱得知交付賄款之人意在期約投票支持被告。雖證人\n    張家旺、溫桂英均稱：不知交付該一千元用意為何云云，惟\n    於「天然谷餐廳」時，被告在現場造勢，該不詳姓名男子並\n    在被告休旅車旁交付賄款，同時一併伴隨交付被告之競選文\n    宣（選他卷第一七四、一七五頁），且該不詳姓名之人與張\n    家旺、溫桂英素不相識，亦不可能無端交付二人各一千元現\n    金，縱該不詳姓名男子交付張家旺、溫桂英現款一千元時，\n    未言明以此金錢利益約定行使投票權給甲○○○○，張家旺\n    、溫桂英亦能得知意在要求支持被告。足證張家旺、溫桂英\n    、羅金錄、丙○○、劉錦來、高勝宏、溫春雨、田勝賢等人\n    對該不詳姓名男子、同案丁○○或同案戊○○分別交付現金\n    之目的有所認識，並係基於受賄之意思而收受無訛。\n六、按被告行為後，九十四年二月二日修正公布之刑法部分修正\n    條文，業於九十五年七月一日施行。修正後刑法第二條第一\n    項規定：「行為後法律有變更者，適用行為時之法律。但行\n    為後之法律有利於行為人者，適用最有利於行為人之法律」\n    ，上揭條文係規範行為後法律變更所生新舊法律比較適用之\n    準據法，於刑法修正施行後，應適用上揭條文之規定，為「\n    從舊從輕」之比較。又法律變更之比較適用，比較時應就罪\n    刑有關之共犯、未遂犯、想像競合犯、牽連犯、連續犯、結\n    合犯，以及累犯加重、自首減輕暨其他法定加減（如身分加\n    減）與加減例等一切情形，綜其全部罪刑之結果而為比較；\n    且就比較之結果，須為整體之適用，不能割裂分別適用各該\n    有利於行為人之法律，此即法律變更之比較適用所應遵守之\n    「罪刑綜合比較原則」及「擇用整體性原則」（最高法院二\n    十四年上字第四六三四號判例、二十七年上字第二六一五號\n    判例、九十五年第八次刑事庭會議決議意旨參照）。\n    (一)被告行為後，公職人員選舉罷免法業於九十四年十一月卅\n      日修正公布，並於同年十二月二日施行，修正前第九十條\n      之一第一項法定刑原規定為五年以下，得併科新台幣四十\n      萬元以上四百萬元以下罰金，修正後該項投票行賄罪之法\n      定刑則提高為三年以上十年以下有期徒刑，得併科新台幣\n      一百萬元以上一千萬元以下罰金。另於九十六年十一月七\n      日再修正並於同日施行，則內容並未修正，僅係將前開九\n      十條之一第一項移列為九十九條第一項。則比較被告行為\n      時、行為中及裁判時之新舊法結果，以被告行為時之公職\n      人員選舉罷免法，較有利於被告。\n    (二)又被告行為後，刑法亦經修正，並自九十五年七月一日生\n      效施行，修正後刑法第二十八條將「實施」修正為「實行\n      」，其中「實施」一語，涵蓋陰謀、預備、著手及實行之\n      概念在內，其範圍較廣；而「實行」則著重於直接從事構\n      成犯罪事實之行為，其範圍較狹，是修正後刑法共同正犯\n      之範圍已有限縮，共同正犯之範圍既因此而有變動，自屬\n      犯罪後法律有變更，而非僅屬純文字修正，惟經比較結果\n      ，對本案被告為學說上所稱之共謀共同正犯，依司法院釋\n      字第一０九號解釋，仍成立共同正犯。是以修正後刑法共\n      犯之規定，未較有利於被告。\n    (三)至刑法第三十七條第二項於有關褫奪公權之規定，修正前\n      規定「宣告六個月以上有期徒刑，依犯罪之性質認為有褫\n      奪公權之必要者，宣告一年以上十年以下褫奪公權」，修\n      正為「宣告一年以上有期徒刑，依犯罪之性質認為有褫奪\n      公權之必要者，宣告一年以上十年以下褫奪公權」，經比\n      較修正前、後之規定，對宣告褫奪公權期間，新舊法之規\n      定相同；至對修正「宣告之徒刑」，按公職人員選舉罷免\n      法第九十八條第三項（九十六年修正時移列第一百十三條\n      第三項）規定：「犯本章之罪或刑法分則第六章之妨害投\n      票罪，宣告有期徒刑以上之刑者，並宣告褫奪公權。」，\n      此項褫奪公權之規定，寓有強制性，為刑法第三十七條第\n      二項之特別規定，自應優先適用公職人員選舉罷免法第九\n      十八條第三項之規定諭知褫奪公權（參照最高法院八十一\n      年度台非字第二四六號判決），是對違反選罷法之被告，\n      於經宣告有期徒刑以上之刑，即應併宣告褫奪公權，而無\n      期間長短之分別，併附此敘明。\n七、核被告所為，係犯修正前公職人員選舉罷免法第九十條之一\n    第一項之對有投票權人行賄罪。本案於「天然谷餐廳」或下\n    田埔會場，以現金行賄選民部分，雖均非被告親自交付賄款\n    而實行犯罪，然如前述，其既就以買票賄選方式求取連任，\n    而行賄之財務款項均由其妻露妮．萊撒張羅及交付予競選總\n    部主要成員丁○○及戊○○發放，則渠四人就賄選犯行當有\n    犯意聯絡，另於「天然谷餐廳」前休旅車旁行賄張家旺、溫\n    桂英、羅金錄選民部分，更與該發放款項之不詳姓名之成年\n    男子間，亦有犯意聯絡，而係推由丁○○、戊○○及該不詳\n    姓名之成年男子為行為分擔；而就「天然谷餐廳」以現金行\n    賄丙○○及丙○○轉交劉錦來現金部分，則與葉維明、丙○\n    ○分別有犯意聯絡，亦推由丁○○、戊○○、葉維明、丙○\n    ○為行為分擔；就下田埔以現金行賄選民部分，則與劉榮和\n    間亦有犯意聯絡，及推由丁○○、戊○○、劉榮和為行為分\n    擔，是被告雖未親為交付賄款犯行，然仍無從脫免其為本案\n    共謀共同正犯。至公職人員選舉罷免法第九十條之一第一項\n    所定之對有投票權人交付賄賂或不正利益罪之賄選行為，乃\n    行為人基於足以讓候選人當選票數之賄選目的，反覆向多數\n    人交付賄賂或其他不正利益，約定不行使投票權或為一定行\n    使。是對有投票權人交付賄賂或其他不正利益之犯行，於構\n    成要件類型上，本質上已具備反覆、延續之行為特徵，其持\n    續多次對有投票權人交付賄賂或其他不正利益即為此類犯罪\n    之典型或常態，於刑法評價上自應僅成立集合犯一罪（最高\n    法院九十六年台上字第一一三三號判決意旨參照）。本件被\n    告與同案丁○○、戊○○、葉維明、丙○○、劉榮和等人對\n    於有投票權之多人，交付賄賂，而約其投票權為一定之行使\n    ，其交付賄款人數共有八人，已如上述，但公職人員選舉罷\n    免法第九十一條之一第一項所定之構成要件，本質上已具備\n    反覆、延續之行為特徵，其持續多次對有投票權人交付賄賂\n    即為此類犯罪之典型或常態，於刑法評價上自應僅成立集合\n    犯一罪，故起訴書認被告上揭數次行賄犯行係連續犯，容有\n    誤會，先此敘明。\n八、原審對被告論罪科刑，固非無見。惟(一)本案尚無證據證明被\n    告於「天然谷餐廳」以餐飲不正利益行賄之犯行（如下述不\n    另為無罪部分），原審對此部分，亦認構成犯罪，尚有未洽\n    。(二)被告對有投票權之人，交付賄賂，而約其投票權為一定\n    之行使，其人數共有八人，於刑法評價上應僅成立集合犯一\n    罪，原判決認被告應成立連續犯，容有違誤。(三)漏未論列被\n    告之妻露妮．萊撒為共犯不當。(四)調查人員在同案同案戊○\n    ○皮包內起出尚未發出之賄款係十萬元（另有二萬四千一百\n    五十元則係同案同案戊○○私人款項），原審誤均為賄款，\n    亦有未當。(五)原判決對受賄之張家旺、溫桂英、羅金錄、丙\n    ○○，劉錦來、高勝宏、溫春雨、田勝賢等人，如何之確為\n    該次山地原住民立法委員選舉有投票權之人，並未於事實明\n    白認定，復未於理由說明其所憑之依據，亦有未洽。(六)原判\n    決於事實係認被告僅參與共謀，而未參與實行交付賄款，然\n    於理由論列被告有犯意聯絡及行為分擔，皆為共同正犯，乃\n    將共謀共同正犯與實行共同正犯之觀念混淆而有未洽。(七)被\n    告合於中華民國九十六年罪犯減刑條例之規定，原審未及適\n    用，亦有未洽。公訴人上訴意旨，指稱原判決對被告部分量\n    刑過輕，如下所述，非無理由；而被告上訴空言否認全部行\n    賄犯行，則無足採，另被告否認「天然谷餐廳」以餐飲不正\n    利益行賄部分，不構成犯罪，如下所述，為有理由，是原判\n    決因有上揭可議之處，自應由本院將原判決關於被告部分撤\n    銷改判。\n九、爰審酌被告行為當時仍擔任立法委員，未能明法守法，為民\n    表率，竟以行賄方式選舉，破壞選舉之公平性，敗壞社會良\n    善選風，妨礙民主政治之實現，所生危害非輕，其雖無不良\n    素行，然本案犯罪情節、手段、智識程度、及犯罪後猶飾詞\n    狡飾，否認犯行，態度非佳等一切情狀，乃量處如主文所示\n    之刑，並依公職人員選舉罷免法之規定諭知褫奪公權四年。\n    又被告犯罪時間，係在九十六年四月廿四日以前，要符中華\n    民國九十六年罪犯減刑條例所定之減刑規定，爰依法減其宣\n    告之主、從刑二分之一，以資懲儆。復按公職人員選舉罷免\n    法第九十一條第三項固規定「預備或用以行求期約或交付之\n    賄賂，不問屬於犯人與否沒收之」，但如其賄賂已交付予有\n    投票權人收受，收受者係犯刑法第一百四十三條第一項之罪\n    ，其收受之賄賂應同法條二項之規定，於其對向共犯所犯投\n    票受賄罪之從刑宣告沒收之，如全部或一部不能沒收時，追\n    徵其價額，此時即不得再依上開規定對交付賄賂者為沒收之\n    宣告（最高法院九十五年度台上字第一四七號判決意旨參照\n    ）。本案在同案丁○○之黑色肩包內扣得五萬五千元及在同\n    案戊○○皮包內扣得十萬元，如前所述，均係被告等預備交\n    付之賄款（至同案戊○○雖稱其先以自有三千元私人款項代\n    墊發予高勝宏、溫春雨、田勝賢三人，然係其與被告夫妻間\n    之私誼或民事糾葛，要與本案刑事部分對該扣案十萬元為供\n    預備交付之「賄款」性質無礙）依修正前公職人員選舉罷免\n    法第九十條之一第三項規定，不論何人所有，均予沒收。另\n    扣案之信封袋五個，係預備供本件犯罪所用之物，並屬共犯\n    丁○○所有，已據共犯丁○○自承在卷；而扣案之行賄名單\n    二張則係共犯劉榮和交予同案戊○○行賄選民，為共犯劉榮\n    和所有供共同犯罪之用，業經劉榮和於本院前審證述屬實（\n    選上訴字第九二頁筆錄），均應依刑法第三十八條第一項第\n    二款之規定，宣告沒收。又同案戊○○身上扣得二萬四千一\n    百五十元應無証據足認係供本案行賄之賄款，另於田勝賢、\n    溫春雨身上扣得之各一千元，既係已交付予其二人之賄款，\n    如前所述，均不得於本案宣告沒收，併此敘明。至黑色肩包\n    一只及扣案其他物品，均與本件犯罪無關，且非違禁物，乃\n    均不為沒收之諭知，併附此敘明。\n參、不另為無罪諭知部分：\n一、公訴意旨另以：被告與同案丁○○、戊○○三人另基於對有\n    投票權之人交付賄賂，而約其投票權為一定行使之概括犯意\n    聯絡，於九十年十一月一日十八時許在「天然谷餐廳」一樓\n    ，以餐飲之不正利益，邀請有投票權之張家旺、溫桂英、羅\n    金錄、何秋琴、李秀玉、高義茂、劉春妹、甘松枝、劉錦來\n    、林新宏（以上十人業經檢察官為不起訴處分）、李興泉、\n    李志松、葉維明、丙○○等人參加，席間被告並對在場參加\n    飲宴之人演講要求彼等支持。又在下田埔集會所以炒米粉之\n    不正利益招待選民。因認被告、丁○○涉有連續犯公職人員\n    選舉罷免法第九十條之一第一項對於有投票權人行賄罪嫌云\n    云。訊之被告、丁○○均堅決否認有此部分犯行，辯稱：「\n    天然谷餐廳」部分，當天是去村落拜訪後，與義工一起吃飯\n    ，席間並有小孩及一些無投票權之人，又無任何競選活動，\n    原住民有呼朋引友一起用餐之習慣，少許餐費之支出又符合\n    原住民的社會禮儀，並無對價關係及賄賂行為，另關於下田\n    埔集會所並無任何炒米粉招待之事等語。\n二、經查：公職人員選舉罷免法第九十條之一第一項之賄選罪，\n    係以對於有投票權之人，行求期約或交付賄賂或其他不正利\n    益，而約其不行使投票權或為一定之行使為構成要件。亦即\n    須視行為人主觀上是否具有行賄之犯意，而約使有投票權人\n    為投票權一定之行使或不行使；客觀上行為人所行求期約或\n    交付之賄賂或不正利益是否可認係約使投票權人為投票權之\n    一定行使或不行使之對價。以及所行求、期約、交付之對象\n    是否為有投票權人而定。所謂對價關係，在於行賄者之一方\n    ，係認知其所行求、期約或交付之意思表示，乃為約使有投\n    票權人為投票權一定之行使或不行使；在受賄者之一方，亦\n    應認知行賄者對其所行求、期約或交付之意思表示，乃為約\n    使其為投票權一定之行使或不行使。且對有投票權人交付之\n    財物或不正利益，並不以金錢之多寡為絕對標準，而應綜合\n    社會價值觀念、授受雙方之認知及其他客觀情事而為判斷（\n    最高法院九十三年台上字第二００七號判決意旨參照）。\n二、據證人何秋琴於新竹市調查站證稱：「因前村長李金水請渠\n    等協助蓋房子，才請渠等到『天然谷餐廳』用餐等語（選他\n    卷第一四五頁背面筆錄）。證人李秀玉證稱：「因大哥李金\n    水請替他蓋廚房之工人至『天然谷餐廳』吃飯，順便跟隨前\n    往」等語（同上卷第一七四頁背面筆錄）。證人張家旺證稱\n    ：「與老闆李金水一同前往吃飯，到達時已開始吃飯」等語\n    （同上卷第一三七頁背面筆錄）。證人即李金水之妻劉春妹\n    證稱：「請李興泉、李志松父子、張家旺、高義茂等人幫忙\n    蓋房子，工作完畢，他們要求請吃飯，乃到『天然谷餐廳』\n    用餐，到時被告及其助選員及其他村民已在用餐，被告及其\n    助選員邀請一起用餐」等語（同上卷第一五三頁背面筆錄）\n    。證人溫桂英證稱：「當晚原要至『天然谷餐廳』找該餐廳\n    老闆廖炎輝，是伊以前男友，正好被告在那邊宴客，因客人\n    大部分是伊認識之錦屏村村民，乃過去與他們用餐」等語（\n    同上卷第一四０頁筆錄）。證人丙○○供稱：「當晚是送叔\n    叔前往『天然谷餐廳』，到達後本想要離去，因邱致明叫伊\n    留下來，才留下」等語（同上卷第一七六頁背面筆錄）。證\n    人林新宏證稱：「當天原要開車載伊子及女友前去認識路，\n    經過『天然谷餐廳』見很多車輛，好奇進入，不好意思推拒\n    乃留下來用餐」等語（同上卷第一八六頁背面筆錄）。證人\n    劉錦來證稱：「原不知道要去參加被告之說明會，是伊朋友\n    邱老師打電話通知伊前往，才要丙○○開車載我前往，伊吃\n    飽才去，並未在『天然谷餐廳』用餐」（同上卷第一七四頁\n    背面筆錄）。證人劉春妹証稱：「伊蓋了一棟房子，請工人\n    去『天然谷餐廳』用餐，事先被告沒有請伊去用餐，用餐時\n    ，被告沒有表示要投票給他」等語（選上更(一)卷第六二、六\n    三頁筆錄）。證人何秋琴証稱：「伊等蓋劉春妹的房子，她\n    要請伊等去吃飯，到那裡遇到很多人，伊等就一起吃飯，現\n    場有很多小孩子，伊也有帶伊外甥女，被告等沒有要伊等投\n    票給他」等語（同上卷第六五、六六頁筆錄）。證人林新宏\n    結証稱：「當天小孩從台北回來看青蛙石，經過天然谷餐廳\n    ，看很多人，他們差不多已用餐完畢，伊等坐了幾分鐘就離\n    開了，伊小孩19歲，媳婦17歲，被告等沒有拉票動作」等語\n    （選上更(一)卷第六六、六七頁筆錄）。是在「天然谷餐廳」\n    用餐，席間有小孩、無投票權人、或有未接受吃飯之人，被\n    告等亦未以餐飲為對價要求投票權為一定之行使，自與公職\n    人員選舉罷免法第九十條之一第一項之犯罪構成要件不合。\n三、又公訴人所指九十年十一月三日下田埔炒米粉部分，遍查全\n    卷，並無任何證據足證被告有炒米粉之行為，證人即新竹市\n    調查站搜證人員黃孝賢亦證稱並未搜到有關炒米粉之事證（\n    原審卷第一二五頁筆錄）。且依社會常情，被告與同案丁○\n    ○縱有以炒米粉提供選民食用，客觀上尚不致達到行賄之代\n    價，至多只是利於邀集選民而已，亦不構成公職人員選舉罷\n    免法第九十條之一第一項之罪。\n四、綜上所述，公訴人所舉證據顯不足以證明被告有以餐飲或炒\n    米粉之不正利益賄賂選民，此外復查無其他積極證據足認被\n    告有此犯行，應認不能證明被告此部分犯罪，惟公訴人認與\n    前開論罪科刑部分有連續犯裁判上一罪關係，爰不另為無罪\n    之諭知。\n肆、據上論斷，應依刑事訴訟法第三百六十九條第一項前段、第\n    三百六十四條、第二百九十九條第一項前段，九十四年十一\n    月卅日修正前公職人員選舉罷免法第九十條之一第一項、第\n    三項、第九十八條第三項，刑法第二條第一項、第十一條前\n    段、第二十八條、第三十八條第一項第二款，中華民國九十\n    六年罪犯減刑條例第二條第一項第三款、第七條、第九條、\n    第十四條，判決如主文。\n本案經檢察官陳明光到庭執行職務\n中    華    民    國  九十九  年    五    月   十二   日\n                  刑事第四庭  審判長法  官  陳筱珮\n                                    法  官  孫惠琳\n                                    法  官  陳玉雲\n以上正本證明與原本無異。\n如不服本判決，應於收受送達後10日內向本院提出上訴書狀，其\n未敘述上訴之理由者並得於提起上訴後10日內向本院補提理由書\n（均須按他造當事人之人數附繕本）「切勿逕送上級法院」。\n                                    書記官  陳思云\n中    華    民    國    99    年    5     月    18    日\n附錄：本案論罪科刑法條全文\n公職人員選舉罷免法第90-1條（修正前）\n對於有投票權之人，行求期約或交付賄賂或其他不正利益，而約\n其不行使投票權或為一定之行使者，處五年以下有期徒刑，得併\n科新台幣四十萬元以上四百萬元以下罰金。\n預備犯前項之罪者，處一年以下有期徒刑。\n預備或用以行求期約或交付之賄賂，不問屬於犯人與否，沒收之\n。\n公職人員選舉罷免法第98條第3項（修正前）\n犯本章之罪，其他法律有較重處罰之規定者，從其規定。\n辦理選舉、罷免事務人員，假借職務上之權力、機會、或方法，\n以故意犯本章之罪者，加重其刑至二分之一。\n犯本章之罪或刑法分則第六章之妨害投票罪，宣告有期徒刑以上\n之刑者，並宣告褫奪公權。",
  "structure": {
    "main": "原判決關於甲○○○○部份撤銷。\n甲○○○○共同對於有投票權之人，交付賄賂，而約其投票權為\n一定之行使，處有期徒刑壹年陸月，褫奪公權肆年。減為有期徒\n刑玖月，褫奪公權貳年。扣案新臺幣拾伍萬伍仟元、信封袋伍個\n、行賄名單貳張均沒收。",
    "fact": "一、甲○○○○為中華民國第五屆立法委員自由地區山地原住民\n    之候選人；露妮．萊撒（未經起訴）為甲○○○○之妻，負\n    責甲○○○○競選期間之財務；丁○○（業經本院以九十五\n    年度選上更(四)字第一號判處有期徒刑十月，褫奪公權三年\n    確定）為甲○○○○之表弟，擔任甲○○○○競選總部辦公\n    室主任；戊○○（業經原審法院判處有期徒刑十月，褫奪公\n    權三年，緩刑三年確定）係甲○○○○妻子露妮．萊撒之同\n    學，與丁○○同為新竹縣五峰鄉公所之同事，擔任甲○○○\n    ○競選總部拜票組組長兼會計組組長。\n二、甲○○○○與其妻露妮．萊撒、表弟丁○○及戊○○等人為\n    使甲○○○○當選連任，乃共同基於對有投票權之選民交付\n    賄賂，約定其將選票投予甲○○○○之犯意聯絡，由露妮．\n    萊撒負責將張羅提供行賄之款項，交予其競選主任丁○○，\n    丁○○即偕同會計組長戊○○依渠等共同行賄買票之謀議，\n    於前往新竹縣尖石鄉為競選活動時：\n    (一)先於九十年十一月一日下午六時許，在尖石鄉錦屏村三鄰\n      天然谷六之一號「天然谷鱒魚養殖休閒農場餐廳」（以下\n      簡稱「天然谷餐廳」），於邀請義工及選民餐敘席間，由\n      丁○○指示亦基於賄選犯意聯絡之另一不詳姓名之成年男\n      子，在「天然谷餐廳」門前甲○○○○所有DE─6198號休\n      旅車右後方，等候經指引至該休旅車右後方之選民前去時\n      ，即以一張選票一千元代價，交付賄款之方式，旋由該成\n      年男子分別以內置一千元賄款之白色信封分別交付予均設\n      籍於新竹縣尖石鄉且於戶政註記為山地原住民，具有原住\n      民選票之張家旺、溫桂英、羅金錄三人（該三人投票受賄\n      罪部分，均經檢察官依職權不起訴處分確定），並囑付張\n      家旺等三人須投票支持甲○○○○，而張家旺等三人亦知\n      該金錢利益係選舉買票之目的，猶均基於受賄意思而收受\n      。嗣丁○○並向戊○○領取五千元，於餐會中與有投票權\n      之葉維明共同基於賄選之犯意聯絡，由丁○○將五千元以\n      三千元、二千元分裝於二信封袋內，並各置入一文宣之牛\n      皮紙袋，交付葉維明（投票行賄罪業經原審法院判處有期\n      徒刑四月，投票受賄罪處有期徒刑二月，定執行刑為有期\n      徒刑五月，褫奪公權二年，緩刑二年確定），囑其交付予\n      亦均設籍於新竹縣尖石鄉且於戶政註記為山地原住民，具\n      有原住民選票之丙○○及劉錦來。葉維明即將前開賄款及\n      文宣均轉交予丙○○（投票行賄罪業經原審法院判處有期\n      徒刑三月，投票受賄罪處有期徒刑二月，並定執行刑為有\n      期徒刑四月，褫奪公權二年，緩刑二年確定），同時告知\n      其中一份係其家中三張選票之賄款，要其投選甲○○○○\n      ；另一份則請其轉交家中具有二張原住民選票之劉錦來。\n      丙○○收受後，明知係選舉買票，仍將裝有三千元之信封\n      袋收下，並與葉維明基於共同賄選之犯意聯絡，於搭載劉\n      錦來（投票受賄罪業經檢察官依職權不起訴處分確定）返\n      回新竹縣尖石鄉嘉樂村四鄰麥樹仁九十四之一號劉錦來住\n      處後，即將內有二千元之信封交予劉錦來（起訴書誤載為\n      三千元），並以此金錢利益約定行使投票權給甲○○○○\n      ，劉錦來亦明知該金錢利益之目的，仍基於受賄意思而收\n      受。\n    (二)繼甲○○○○預訂於同年月三日下午六、七時許，在尖石\n      鄉秀巒村下田埔集會舉辦政見發表會，其妻露妮．萊撒乃\n      於同年月二日在其竹東競選總部，再交付丁○○十一萬餘\n      元，供買票賄選之用，丁○○抽取其中一萬餘元後，將十\n      萬轉交戊○○預作翌日行賄發放之用。嗣於三日晚間七時\n      四十六分許，甲○○○○、露妮．萊撒、丁○○、戊○○\n      仍承前同一犯意，由丁○○覓得熟知該選區選票且亦基於\n      共同賄選犯意聯絡之劉榮和（未經檢察官起訴），提供選\n      民名單，丁○○即與戊○○、劉榮和先於集會所旁商討發\n      放賄款事宜，旋由丁○○指示劉榮和交付二紙欲行賄之選\n      民名單予戊○○，戊○○並依劉榮和指引，前往該集會所\n      旁之新竹縣尖石鄉秀巒村二鄰田埔三０號民宅內等候，旋\n      於同日晚上七時五十二分、七時五十四分及七時五十五分\n      ，於核對名單後，分別交付各一千元賄賂予經劉榮和指引\n      前來均設籍於新竹縣尖石鄉且於戶政註記為山地原住民，\n      具有原住民選票之高勝宏、溫春雨、田勝賢（以上三人投\n      票受賄罪另由檢察官為職權不起訴處分確定）三人，並請\n      渠等投票支持甲○○○○。高勝宏、溫春雨、田勝賢等人\n      均明知戊○○交付金錢之目的，仍基於受賄意思而收受。\n      嗣經法務部調查局新竹市調查站調查員見時機成熟，於田\n      勝賢尚未離開時即入內當場查獲，並在戊○○皮包內起出\n      尚未發出之賄款十萬元（另有二萬四千一百五十元認係戊\n      ○○私人款項，與行賄無關）；在田勝賢身上起出方收受\n      之賄款一千元；繼在戊○○所有3H─1883號之自小客車上\n      （起訴書誤載為DE─6198號休旅車），起出丁○○所持有\n      尚未發出之賄款五萬五千元（分別裝在丁○○所有之五個\n      信封袋內，再裝入丁○○所有之黑色肩包內）。嗣溫春雨\n      嗣經通知到案後，提出所收受之一千元賄款扣案；張家旺\n      則稱所收受之賄款，已花用殆盡。\n三、案經臺灣新竹地方法院檢察署檢察官指揮法務部調查局新竹\n    市調查站（下稱調查站）、新竹市警察局、新竹縣警察局調\n    查移送臺灣新竹地方法院檢察署檢察官偵查起訴。",
    "reason": "壹、程序部份：\n一、按新修正刑事訴訟法係於九十二年二月六日經總統公布施行\n    ，而同日公布施行之修正刑事訴訟法施行法增訂第七條之三\n    復規定：「中華民國九十二年一月十四日修正通過之刑事訴\n    訟法施行前，已繫屬於各級法院之案件，其以後之訴訟程序\n    ，應依修正刑事訴訟法終結之。但修正刑事訴訟法施行前已\n    依法定程序進行之訴訟程序，其效力不受影響。」故九十二\n    年一月十四日修正刑事訴訟法施行前，已繫屬於法院之案件\n    ，證人及共同被告於警詢或檢察官偵查中之證言，其效力不\n    受影響（最高法院九十三年度台非字第九三號判決、九十三\n    年度台上字第二０三號判決意旨參照）。本件係於九十一年\n    一月十一日繫屬於臺灣新竹地方法院（原審卷第一頁），因\n    此本件有關證人田聖賢、林金榮、高勝宏、羅金祿、葉維明\n    、丙○○及共同被告於警詢、偵查中證言，效力均不受影響\n    ，辯護人主張證人於警詢之陳述無證據能力，洵屬無據。\n二、共同被告戊○○、葉維明、丙○○及共犯露妮．萊撒、劉榮\n    和均於本院前審以證人身分到庭陳述，另戊○○、丙○○、\n    丁○○再經本院以證人身分傳証，並均經被告及辯護人詰問\n    ，有本院選上訴字第八號卷第九０～一０四頁、重選上更(四)\n    第一０一～一０二頁、原審卷第二九五～二九八頁、及本院\n    重選上更(六)卷審判筆錄可考，渠等所為證言，均非傳聞，自\n    具證據能力。\n三、至本案認定事實所引用之書面証據，如天然谷名片、巴燕\n    . 達魯名片、宣傳單、宣傳資料、手繪地圖、山地原住民候\n    選人登記冊、賄選案件事實表、搜索筆錄、扣押物品收據證\n    明書、扣押筆錄、新竹縣警局化驗結果函、皮包及現金照片\n    、立委候選人甲○○○○各鄉輔選人員組織及責任分工執掌\n    表、總部會議紀錄、總部及其後援會之主要幹部名單、輔選\n    會議簽到表、總部及後援會主要幹部聯絡電話、美國運通銀\n    行對帳單、信用卡月結單、荷蘭銀行、遠東國際商業銀行信\n    用卡繳款通知單、五峰郵局檢送之丁○○存款往來明細表、\n    、甲○○○○競選總部人員分工表、筆記資料、白色便條紙\n    、藍色便條紙、黑色筆記本、法務部調查局蒐證錄影帶、翻\n    拍照片、測謊報告等文書証據，均係於訴訟繫屬前即已存於\n    卷內，且非係公務員違背法定程序所取得，又無刑事訴訟法\n    第一百五十九條之四之顯有不可信之情況與不得作為證據之\n    情形，且被告及其辯護人亦均不爭執証據能力（本院卷第三\n    一頁背面～三二頁背面），應認均有證據能力。\n貳、實體有罪部份：\n一、本案訊據被告甲○○○○固坦承上開時日因競選活動而在「\n    天然谷餐廳」開席，及在下田埔集會所為政見發表時均在場\n    ，惟矢口否認有賄選犯行，並辯稱：天然谷餐廳，其僅是依\n    行程安排，是同行有人說天晚了要吃飯，而山上只有那家餐\n    廳，且當天隨行的其只認得自己幹部。錄影帶調閱後也證明\n    其不是畫面中的人。另其妻交付丁○○之金錢是選舉開支，\n    不是要賄選。在下田埔集會所為政見發表時，其一直在集會\n    所內，並未進入民宅，他人如何發放賄款，均未參與，亦不\n    知情。其是改革者不可能去買票，且本案證人大都不認識，\n    其未賄選，亦未指使他們，是他們自行談好去做的，與其無\n    涉云云。\n二、經查：\n    (一)同案丁○○於偵、審均供証其係被告競選總部辦公室主\n        任一節，核與証人戊○○証稱：丁○○是總指揮，競選\n        總部活動均係其安排，所有拜票活動都是其主持（原審\n        卷第一七、二一、一六六頁筆錄）；証人葉維明證稱：\n        其於某日路過甲○○○○競選總部，經丁○○邀請為甲\n        ○○○○助選（選上訴卷第九九頁筆錄）。證人劉榮和\n        證稱：其係丁○○出面找去為甲○○○○助選（選上訴\n        卷第九三頁筆錄）等情，均相一致，且有被告競選總部\n        幹部名單一件扣案可稽（選他卷第一０六頁）。參以，\n        證人露妮．萊撒亦証稱：有交付十一萬餘元予丁○○，\n        作為競選後援會開銷使用（原審卷第六三頁、重上更(四)\n        卷第一一頁筆錄）。是丁○○確係競選總指揮，其支配\n        活動行程及為被告邀集助選者等事宜，就被告整個競選\n        活動積極參與介入極深，居於主控地位，則丁○○嗣於\n        本案証稱其僅是擔任志工；或證人陳道明證稱：不知甲\n        ○○○○之競選總部有安排職務（選上更(一)字卷第八九\n        、九０頁筆錄），指稱競選幹部名冊不實，顯與前開事\n        證有違，而為飾卸、迴護之詞，要無足採，丁○○係被\n        告競選辦公室主任之事實，可堪認定。\n    (二)另本件扣案印有民主進步黨字樣之紙張共六張，其中五\n        張上寫有徵召提名立法委員候選人甲○○○○，下方則\n        分別有各鄉輔選人員組織及責任分工職掌表三張、各鄉\n        、鎮、市、區輔選組  織責任分工職掌表二張（選他卷\n        第九六、九七、一０二～一０四頁）。而各鄉輔選人員\n        組織及責任分工職掌表三張分別為：竹林村（列有村召\n        集人一名、副召集人二名及各鄰連絡人共五名，並均列\n        有各該負責人之連絡電話）、桃山村（列有村召集人一\n        名、副召集人一名及各鄰連絡人共廿一名，並列有召集\n        人之連絡電話）、及一張未列村名（但列有總召集人一\n        名、副總召集人一名、村召集人一名、副召集人二名及\n        各鄰連絡人共廿五名之姓名，並列有各該總召集人、召\n        集人、副召集人之連絡電話）。各鄉、鎮、市、區輔選\n        組織責任分工職掌表其中一張列有大隘村、桃山村、花\n        園村及竹林村共四村之召集人、副召集人姓名。核與竹\n        林村及桃山村之各鄉輔選人員組織及責任分工職掌表上\n        之召集人、副召集人姓名相同。另一張印有民主進步黨\n        字樣之紙張，其上寫有十月廿二日下午三時總部會議，\n        下方則列有七項議事進行順序（選他卷第九八頁）等情\n        。被告當時係民主進步黨之立法委員，該印有民主進步\n        黨徵召提名立法委員候選人甲○○○○字樣紙張之內容\n        自係為被告所擬。且單就扣案部分資料，已可看出競選\n        組織架構形成。再觀扣案輔選會議簽到表（同上卷第一\n        ０七～一一０頁），不僅係以立法委員用箋之紙張簽到\n        ，且簽到出席之三十人均列有各該出席人之電話及住址\n        ，雖無法看出會議召開時間，然可確定有召開過輔選會\n        議，且其上三十名出席人員，多與上述召集人、副召集\n        人或各鄰連絡人重覆（出席人員而列為上開組織及責任\n        分工職掌表之名單有：萬福壽、朱禮沐、羅新輝、朱禮\n        元、陳錦富、夏有年、丁○○、張國獻、秋賢良、錢大\n        維、彭興福、戴文乾、呂源吉、林坤金、王正雄、田光\n        男、陳雲鵬）。又依扣案總部及後援會之主要幹部名單\n        、總部及後援會之主要幹部聯絡電話（同上卷第一０六\n        、一一一頁）二紙，亦係以立法委員用箋之紙張列名，\n        再與競選總部幹部名單、及組織架構圖（同上卷第一０\n        ０、一０五頁）相互對照結果，該競選組織顯然經過研\n        商後定案，架構完整而仔細，且以當時仍係立法委員之\n        被告立法委員用箋紙張為之，被告一切活動並按照排定\n        行程進行，被告自均有參與商議無疑。是被告辯稱：組\n        織架構尚未成立，辦公室進出沒有管制，任何人都可以\n        進來，其未積極參與，殊與常情不符，不足憑信。證人\n        蕭世暉於本院前審證稱：「僅係處理地方要找委員（即\n        被告甲○○○○）及人民陳情之事情，不清楚甲○○○\n        ○行程，後援會之事是丁○○在處理」等語（選上訴卷\n        第一四九～一五０頁筆錄），顯與前開事証不符，而為\n        迴護被告之詞，無從採為被告有利之證明。\n    (三)又巴燕、達魯之妻露妮．萊撒先於原審証稱：在竹東競\n        選總部，有交十一萬多元給丁○○，為後援會成立費用\n        （原審卷第六三頁筆錄）；於本院前審則證稱：九十年\n        間甲○○○○選舉立委之財務，係其一人處理。其記得\n        在九十年十一四日成立尖石鄉後援會，需要一筆錢，故\n        於成立前一星期交付不只十一萬元給丁○○，作為成立\n        後援會的花費，如鷹架、舞台等開銷，甲○○○○募款\n        及財務都是其在管理（重選上更(四)卷第一○一頁反面～\n        一０二頁反面筆錄）等語。是本案被告巴燕、達魯競選\n        財務既均由其妻露妮．萊撒一人統籌辦理，而同案丁○\n        ○係競選總部主任，且是被告之表弟；同案戊○○為競\n        選總部之拜票組、會計組組長，並係露妮．萊撒之同學\n        ，與甲○○○○及露妮．萊撒夫妻關係密切，露妮．萊\n        撒並稱因信任表弟丁○○而交付款項（原審卷第六三頁\n        ），且丁○○、戊○○均非參選之人，亦未曾自行出資\n        ，則渠等行賄款項自係來自被告之妻露妮．萊撒，當可\n        認定。亦無可能丁○○及戊○○在未經允許情況下，即\n        將被告之妻交付之十萬餘元逕行用來向選民行賄，另被\n        告對其親密之配偶及高達十餘萬元之競選支出，事關其\n        當選與否，亦難諉稱毫不知情。參以一般選舉，均以成\n        立總部方式從事競選活動，倘非候選人親信，無法參與\n        重要競選策略。若有行賄，亦係由親信、親屬或重要幹\n        部等人事先謀議分工，各司其職。則被告於以下之餐廳\n        或集會所忙於演說或舉辦政見說明會，而推由與同車上\n        山且係渠夫妻最信任之丁○○、戊○○在餐廳或集會所\n        外打點行賄及負責賄款發放等事實，均屬選舉責任分工\n        常態，自不得以被告未實際交付賄款，即認與被告無關\n        。被告辯稱不知其妻交付鉅款及同案丁○○、戊○○有\n        交付賄款之事云云，核與常情不符，不足採信。被告聲\n        請傳喚證人即選民游國當，欲證明下田埔說明會時其均\n        在會場，不可能事事插手。惟證人游國當證稱：「當日\n        下田埔說明會其未在場，其妻亦是去聽幾分鐘即回家」\n        等語（選上訴卷第八八頁筆錄）。證人鳳秋喜、芭翁‧\n        都宓雖均證稱：「甲○○○○都在說明會場，沒有離開\n        」等語。本件既由被告之妻交付金錢予同案丁○○，再\n        由同案丁○○轉交其他競選工作夥伴或同案戊○○行賄\n        ，則於行賄交付賄款時，被告縱人在說明會場，仍無礙\n        於其與妻露妮．萊撒、同案丁○○、戊○○等人成立共\n        同行賄之事實。況同案戊○○於原審業已坦承為被告行\n        賄買票之事，嗣於本院前審亦以證人身分結證無誤（選\n        上訴字第九七頁筆錄）。故被告與其妻露妮．萊撒、同\n        案丁○○、戊○○等人間，就買票賄選犯行，應早有謀\n        議，致丁○○、戊○○至以下之活動地點，即得分工進\n        行。\n三、再查，有關於天然谷餐廳停車場旁行賄部分：\n    (一)本案被告於「天然谷餐廳」餐敘時，有一不詳姓名成年\n        男子，在天然谷餐廳前DE─6198號休旅車旁，交付賄款\n        予張家旺、溫桂英、羅金錄部分，業據證人張家旺證稱\n        ：九十年十一月一日晚間，其與老闆李金水一同前往『\n        天然谷餐廳』吃飯，看到立委參選人甲○○○○亦在場\n        ，其用餐完等候要離去時，碰到一位不詳姓名之男子，\n        叫其至室外休旅車旁，在車旁即有另一位不詳姓名之男\n        子，交予其一個白色信封，其拿取後就直接放進口袋，\n        回去打開才知道信封內是裝著一千元（選他卷第一三七\n        頁背面調查筆錄）；證人溫桂英證稱：其於九十年十一\n        月一日晚間確實有至『天然谷餐廳』，當時立法委員候\n        選人甲○○○○有在現場演講，餐會中有不明之女子要\n        其至屋外空地車旁，其即依言，至屋外休旅車旁，即有\n        一位不詳姓名之男子，交予其以空信封裝著一千元（選\n        他卷第一四０、一四一頁調查筆錄）；證人羅金錄證稱\n        ：九十年十一月一日晚間伊前往『天然谷餐廳』，替立\n        委參選人甲○○○○助選造勢，餐會中其因肚子不舒服\n        ，到屋外找衛生紙，碰到一位不詳姓名男子，叫其至休\n        旅車旁，即有另一位不詳姓名之男子，交付其一白色信\n        封內裝著一千元，當時該男子還問其是否只有一個人，\n        其告知家裡僅其一人前來，其知道該不詳姓名男子應該\n        是替甲○○○○買票（選他卷第一四三、一四四頁調查\n        筆錄）各等情，大多相符。乃證人張家旺、溫桂英、羅\n        金錄與被告均無怨隙，自無誣指被告之必要，且渠等均\n        非被告競選幹部，並係應邀前往，則被告辯稱僅是「同\n        行有人說天晚了要吃飯，而山上只有那家餐廳」之臨時\n        前往用餐一節，顯與事實不符，要無足採。況前開證人\n        張家旺、溫桂英、羅金錄均証稱於「天然谷餐廳」，係\n        經人指引至休旅車旁，由不詳男子交付一千元一節，核\n        與經原審及本院前審當庭勘驗調查局採証九十年十一月\n        一日在天然谷餐廳前之錄影帶結果，畫面顯示：自六時\n        卅分至七時四十分間，餐廳外陸續有多人（或男或女或\n        抱小孩者），一一走向DE─6198號休旅車右側，雖畫面\n        因遭該休旅車遮擋，無法得見於休旅車右側該戴白色帽\n        男子與走近之人之互動，然走近之人，既非同時趨前，\n        且均於短暫停留即走離該休旅車折返（原審卷第一五九\n        頁、重選上更(三)卷第五五～五六頁）等情相符，衡以該\n        時既係競選餐會，則多人分別逐一轉至停車場角落隱蔽\n        之該休旅車旁，均於卅秒至一分鐘不到即又走出，所為\n        何事？則除如前開証人所証，係經人指引前去領取一千\n        元賄款外，已無其他合理說明，乃証人前揭証述，自屬\n        可信。\n    (二)雖證人羅金錄嗣於原審改稱：「一千元是有去幫忙掛旗\n        子的油費」（原審卷第一九五頁筆錄）、證人張家旺及\n        溫桂英亦改稱：「不知道所收受之一千元是什麼錢，也\n        都已經用完」（原審卷第一九七～一九九頁筆錄）各云\n        云，不僅與渠等先前所述不符，且當時該名男子亦未交\n        付任何旗子供羅金錄懸掛；及惟該名不詳姓名男子既與\n        証人張家旺、溫桂英二人均不相識，豈會無端各交付一\n        千元，渠二人亦無在不知目的之情況下任意收受他人金\n        錢之理，是渠等前揭更異之詞，當係事後迴護被告及同\n        案丁○○之詞，均委無足採。\n    (三)又車號DE─6198號休旅車係被告所有，有車號查詢汽車\n        車籍一紙在卷可憑（選他卷第四頁），被告並自承當日\n        乘坐該休旅車至「天然谷餐廳」用餐，而依錄影帶內容\n        及翻拍照片亦可看出休旅車內載有他人，並有人打開車\n        門與車內之人聊天，被告曾陪同民眾進入該休旅車右側\n        ，後即有一不詳姓名之男子即於休旅車旁發放賄款，此\n        經同案丁○○、張家旺、羅金錄證述無訛。雖取得賄款\n        之証人張家旺、溫桂英、羅金錄均稱不識該於休旅車右\n        後方交付賄款之男子，而自錄影帶或刑警局翻拍照片亦\n        均無法確認其身分，然均可明顯見其頭戴白色帽子（卷\n        附錄影磁片及翻拍照片附件二、三）。佐以於錄影及翻\n        拍照片有多人均戴同款白色鴨舌帽及白色汗衫（背後印\n        字），及被告及証人丁○○亦均供証有提供白色帽子及\n        汗衫予工作人員穿戴（本院九十八年六月十日審判筆錄\n        第三頁），則該立於休旅車右後發放賄款之男子，為被\n        告競選之工作人員，亦堪確認。而於該為被告競選之不\n        詳姓名男子發放賄款期間，証人丁○○、戊○○及被告\n        均曾靠近該休旅車（如本院前審（更(三)）勘驗結果被告\n        於四、五、十九均在車旁；二十則是戊○○開該車門放\n        置一包物品入車內；証物袋內翻拍照片及刑警局翻拍照\n        片附件二三均見著白色紅短袖上衣之丁○○同立於該車\n        右後等），故被告實無法諉為與其無關或不知此事之理\n        。\n    (四)另丁○○於「天然谷餐廳」內，將裝有賄款之信封袋及\n        裝有文宣之牛皮紙袋交付葉維明，囑付其轉交丙○○及\n        劉錦來之事實，業據同案葉維明於調查站供稱：「裝有\n        三千元及二千元之信封係丁○○交付，請其拿給丙○○\n        及同車來的劉錦來。袋子裡面確實有信封袋，信封袋裡\n        面有三千元，其即將信封裡的三千元連同信封袋直接拿\n        給丙○○轉交劉錦來」（偵卷第一六九頁筆錄）。其於\n        偵訊時亦供陳：「新竹市調查站所言實在，一定有錢，\n        是丁○○要其交給劉錦來等人」各等語（偵卷第一六五\n        頁反面）。核與同案丙○○於調查站、偵查中供稱：「\n        當時丁○○拿了二個大型牛皮紙袋內裝很多現金的小信\n        封，以及甲○○○○的競選文宣交給葉維明，葉維明當\n        場就從其中一個大信封袋中抽出二個內裝現金的小信封\n        交給他，並要他將其中一個轉交給其叔叔劉錦來。其推\n        測是錢而馬上拒絕，但葉維明向其表示你看到了拿去沒\n        關係，隨後其載劉錦來回家，到他家時，即將葉維明要\n        其轉交的信封袋和甲○○○○的文宣拿給劉錦來，並當\n        場打開，裡面裝有二千元，其自己的那個信封袋回家後\n        打開看，裡面裝有現金一千元三張，共三千元，已被其\n        花掉」（偵卷第一七０頁反面、第一七七、一七八頁筆\n        錄；原審卷第一一四頁筆錄）；及至本院前審仍具結證\n        稱：確有自葉維明處取得丁○○交付之二信封，內各有\n        三千元、二千元，二千元信封其依葉維明指示交付劉錦\n        來無誤，且確實未告知用途無誤（選上訴卷第一０三頁\n        ；選上更(一)卷第一０一～一０二頁筆錄）等語一致，且\n        同案丁○○於原審亦坦認：「錢是其另外給葉維明的，\n        是用二個信封裝錢，但未指明要給誰，是要找人幫忙插\n        旗子用的，但其並沒有給旗子」（原審卷第一一三頁筆\n        錄），確有交付內裝錢之二信封一情均相符合，況葉維\n        明既為被告助選，當無自陷入罪誣指被告及丁○○二人\n        之可能。乃葉維明、高明光所証前揭交錢、取錢一情，\n        既與事實相符，自可堪信為真實。\n    (五)至葉維明嗣於原審、本院前審改稱：「錢是要給丙○○\n        及劉錦來兩人一組插旗子的費用」云云，然其就親身經\n        歷之單純事實，前後所稱不一，已難採信。況所稱「插\n        旗子」之事，於九十一年二月廿七日原審訊問之前，均\n        未有任何人提出，及至丁○○推稱提出「插旗子」之說\n        詞，葉維明始附合其詞。況渠所找插旗之人，依同案丙\n        ○○於原審陳稱：當天七點多回到劉錦來門口，拿其中\n        一個信封給他，告訴他說這是葉維明給的，他說他知道\n        。根本沒有要插旗子，且劉錦來年紀很大，得癌症，行\n        動不方便（原審卷第二三九頁筆錄）之八十餘歲罹患癌\n        症且行動不便之劉錦來，復未交給任何旗子，自與常情\n        有違。於本院更結証：葉維明於翌日告知其將會被調查\n        站約談，及錢是要給其插旗用，然其並未幫被告插旗子\n        （本院九十八年十一月四日審判筆錄第五頁）等語明確\n        在卷。又證人劉錦來早在調查站詢問時即坦承交錢未有\n        說明要用來插旗子（選他卷第一七五頁筆錄），並於原\n        審第一次作證時猶承認收受賄款（原審卷第一一七、一\n        一八頁），迨至第二次作證時始改稱：是丙○○交給，\n        說其很辛苦插旗子、發文宣云云（原審卷第一五六頁筆\n        錄），經原審訊以是否確有幫忙插旗子及發文宣時，又\n        答以是「之後」幫忙（原審卷第一六一、一六二頁）等\n        語。顯見葉維明、劉錦來嗣所稱「插旗子、發文宣」，\n        均屬事後串証、迴護被告之詞，均不足採。\n    (六)另於「天然谷餐廳」，同案丁○○係持印有立法院之牛\n        皮紙袋內裝有現金用以行賄之事實，已如前述，而被告\n        當時為立法委員，該牛皮紙袋當係出自被告無誤。被告\n        既以成立競選組織方式，從事競選活動，同案丁○○及\n        同案戊○○均屬被告之親信，丁○○並於本院前審陳稱\n        ：交予葉維明信封內的錢，是服務處負責管帳的人交付\n        的（選上訴字第四六頁筆錄），而依其競選組織架構，\n        同案戊○○係會計組組長，負責金錢支付、記帳等會計\n        事項，參以「天然谷餐廳」聚餐時，同案丁○○自承曾\n        問同案戊○○有無帶錢，及當天餐費亦係由同案戊○○\n        支付，亦堪認前揭丁○○所指賄款應係向戊○○領取無\n        訛。是本案被告既與競選辦公室主任丁○○同時到達「\n        天然谷餐廳」，嗣復係於被告之休旅車旁，或由一男性\n        或由一女性（張家旺、羅金錄指係經由男子；溫桂英則\n        指係經由女子）指引至被告休旅車後向一男子取得賄款\n        ；嗣丁○○並隆以被告提供之立法院牛皮紙袋裝錢行賄\n        ，要求支持被告，則前揭賄款既非丁○○自行出資，且\n        行賄當選之利益全歸參與競選之被告，則顯係被告推由\n        同案丁○○、戊○○負責並指示其他工作人員行賄選民\n        ，既與當今社會選舉賄選型態相符，益足証係與被告共\n        同基於犯意聯絡無疑。\n四、另查，有關下田埔集會所旁民宅行賄部分：\n    (一)據同案戊○○於原審及本院更(四)審時供稱：「當天在集\n        會所時，其到外面與人聊天，看到丁○○與其不認識的\n        劉榮和在廣場談話，丁○○叫其過去幫忙一下，說其身\n        上有錢，他已交代劉榮和，丁○○並對劉榮和說交代給\n        其即可，他就先進去集會所，劉榮和就拿二張上面載有\n        姓名的便條紙（即欲行賄之選民名單），並要其去集會\n        所旁邊田埔三０號民宅，說他會叫人去民宅，且只要有\n        人找，就給他一千元。其即用前一天丁○○交付之十萬\n        元給名單上的人，其計交錢給溫春雨、高勝宏、田勝賢\n        時，雖未講要他們支持甲○○○○，但事實上確實希望\n        他們能支持甲○○○○，他們應該也都明白。扣案二張\n        名單就是劉榮和交其持有」等情不諱（原審卷第一二八\n        、二四五、二四六頁、選上訴卷第九七頁、更(四)審卷審\n        判筆錄第8頁、第10頁）。核與當日新竹市調查站之搜\n        證，並經原審勘驗，製有勘驗筆錄（原審卷第一六七～\n        一六九頁、第三００～三０一頁）之錄影帶螢幕顯示：\n        (1)七時四十六分，戊○○與同案丁○○、劉榮和三人交\n        談（戊○○指稱當時討論發放賄款事宜；同案丁○○指\n        稱是要劉榮和找人發文宣，劉榮和身上沒錢，故請戊○\n        ○先付錢，並交待劉榮和如果情況緊急，請他找幾個人\n        ，一人發一千元工錢、便當錢給他們；證人劉榮和則證\n        稱在聊天）。(2)七時四十九分，劉榮和右手指向右邊（\n        戊○○稱此時是指向旁邊下田埔三０號民宅，欲其入內\n        發放賄款；證人劉榮和則證稱是戊○○說要借房間，其\n        以為戊○○要借廁所，就隨便借給她）。(3)四十九分十\n        二秒，戊○○與劉榮和二人有擦身，劉榮和交某物品到\n        戊○○右手，戊○○右手多出白白的東西（戊○○稱劉\n        榮和當時即交付名單至其右手；證人劉榮和否認交付物\n        品，稱未見過該便條紙）。(4)七時五十二分，有一名男\n        子進入該房間與戊○○交談，戊○○低頭看東西，五十\n        二分五十四秒，戊○○抬起頭來，右手伸到右邊口袋再\n        掏出來，該名男子離去；五十三分卅八秒，又有一名男\n        子進入，戊○○又低頭看東西，五十四分零五秒，戊○\n        ○再從右邊口袋掏出東西，該名男子離去；五十四分五\n        十六秒，一名戴帽子男子進入，先在房內走晃一圈，接\n        近戊○○，楊又低頭看東西，不時抬頭往窗外看，五十\n        五分五十四秒戊○○抬起頭來後幾秒，該名男子離去（\n        戊○○指稱低頭動作是在看名單，手伸入口袋是掏錢動\n        作，並發放賄款給該三名男子）。(5)七時五十八分，一\n        名女子進入，與戊○○交談，五十九分，調查站人員衝\n        入等情，均相符合。且證人劉榮和嗣於本院前審亦證稱\n        ：「是應丁○○邀請，出面為甲○○○○助選，當天與\n        丁○○等人一起到下田埔，當晚係與丁○○商量，並依\n        丁○○指示交付名單給戊○○」等情一致（選上訴卷第\n        九二、九三頁筆錄），此外，復有記載羅雲志、羅雪花\n        等十六人之行賄名單二紙扣案可資佐證，乃丁○○、劉\n        榮和、戊○○三人於下田埔集會所旁民宅發放賄款之事\n        証，至臻明確。\n    (二)雖同案戊○○稱其不認識錄影帶翻拍照片中之三名男子\n        ，及田勝賢、溫春雨亦稱此翻拍照片太模糊或太暗，看\n        不清楚照片中男子是何人（更(四)卷第審96年5月8日審判\n        筆錄），惟田勝賢、高勝宏及溫春雨均證稱：確有收\n        到同案戊○○交付之一千元，並知悉係為支持甲○○○\n        ○而收取，或戊○○有要求彼等支持甲○○○○（選他\n        卷第四四～四八頁、第一一八～一二０頁、第一二二～\n        一二九頁筆錄；原審卷第一二一～一二四頁筆錄），足\n        認戊○○確於該址交付賄款予溫春雨等三人，況田勝賢\n        、高勝宏及溫春雨均與被告素無怨隙，若非同案戊○○\n        確有交付一千元賄款，並要求支持被告，自無一致誣指\n        被告之必要，是渠三人上揭證詞應屬實情，而可採信。\n    (三)有關露妮．萊撒前稱有交付丁○○十一萬餘元一節，丁\n        ○○亦先否認有交付戊○○十餘萬元（選他卷第七二頁\n        反面筆錄）；後供証：九十年十一月三日中午左右，其\n        有將甲○○○○太太交付之約十一萬元轉交給戊○○，\n        親手轉交前，有從中拿出約一萬元，剩下約十萬元在戊\n        ○○手上，主要是用作支付第二天競選總部後援會成立\n        大會時之開銷（選他卷第一八九頁反面筆錄）；露妮．\n        萊撒交給我十一多萬元，說要訂一些桌椅、架子等費用\n        ，我抽其中一萬多元支付，十萬元交給戊○○（原審卷\n        第五三頁筆錄）；露妮．萊撒有交付十一萬元，作後援\n        會成立大會相關開支費用，其付雜項開支，剩下的錢因\n        甲○○○○希望我陪他去下田埔，其位於偏遠山區，怕\n        錢放身上弄怕，就請戊○○幫忙保管（重選上更(四)卷第\n        一○三頁正、反面）等語。另戊○○先後供証：扣案十\n        萬元是今日下午二、三點在竹東競選總部，由丁○○本\n        人交付，是次日幹部會議用來支付花籃的（選他卷第六\n        三、六四頁筆錄）；遭查扣的錢是因丁○○要去山上，\n        怕掉了，並說是明天總部開銷的錢，交其保管，交錢是\n        在下午二點多，在竹東總部（原審卷第七一頁筆錄）。\n        身上十萬元是十一月三日早上丁○○在競選總部拿給我\n        的，是總部辦活動的費用，下午七點多在下田埔，丁○\n        ○叫我過去，並交代劉榮和說交代我就可以了，他就進\n        去集會所，劉榮和問我身上有無錢，他說丁○○交代這\n        個與妳談，錢在我這邊，即交給我二張便條紙，要我去\n        集會所旁邊民宅，他會去集會所裡面叫人出來找我，只\n        要有人找我就給他一千元，劉榮和沒有給我任何錢，我\n        不認識劉榮和，是因為丁○○告訴我他已交代劉榮和，\n        及我身上有之前丁○○交給我的十萬元，我即從皮夾拿\n        出二萬多元放在口袋裡，再一張張抽出來給來的人，來\n        的人自己報名字，我即核對劉榮和給的名單並打勾（原\n        審卷第二四五～二四六頁管筆錄）等情。是關於露妮．\n        萊撒交付十一餘萬元予張國之用途，已先見渠等先否認\n        ，諉飾避重之情，且對該筆款項用途，究係總幹部會議\n        、或總部後援會、亦或五峰鄉尖石後援會使用？渠等供\n        辯亦有歧異，對交付或取得該筆十一萬餘元之時間，究\n        係於成立大會前一周（即十月底）？亦或查獲前一日（\n        即十一月二日）或查獲當日（即三日）？丁○○交予戊\n        ○○係上午或下午？均互核不一，已有可議。況經本院\n        追問後援會事宜，被告先稱係一名為邱志明為其籌組五\n        峰鄉尖石之後援會，然又稱其已撤走，無法提供地址供\n        傳証（本院九十八年四月廿一日準備筆錄第七頁），被\n        告旋又另具狀提供三後援會主要成員供查。惟該三証人\n        乙○○○○、烏杜大勒巴克及己○○○於本院結証：係\n        屬三不同區域之後援會成員，且渠等後援會均宗教或社\n        會團體自發性或機動性組成，並無一固定領導人，被告\n        亦未曾支付任何款項，甚且証人翡束寶於競選期間未曾\n        見過被告，僅因被告係部落產生之立委而為支持（本院\n        九十九年四月十四日審判筆錄第三～八頁）等情。乃三\n        証人所証渠後援會之自發且機動之性質，即不可能係接\n        受被告任何補助款項籌組，是証人所証不僅無從為被告\n        有利之認定，反足証被告所辯其妻露妮．萊撒交付丁○\n        ○之十一餘萬元係供後援會使用一節，非屬實在。又衡\n        以丁○○方交給戊○○十萬元，然於下田埔現場即僅指\n        示劉榮和交行賄名單予戊○○，並告知劉榮和戊○○身\n        上有錢，劉榮和即要戊○○依名單所載對其指示前來之\n        人各行賄一千元，戊○○旋並依指示交付賄款，既未質\n        疑丁○○所指其身上有錢何所指？且依錄影帶顯示，行\n        賄名單係由劉榮和交付，而同案戊○○與劉榮和互不相\n        識，劉榮和亦不認識被告（原審卷第二四八頁、選上訴\n        卷第九三頁筆錄），則戊○○竟未經詢問丁○○或劉榮\n        和，即依言對經指引前來民宅之選民交付賄款。顯見渠\n        三人對戊○○持有自被告配偶處取得之十萬元現金，即\n        係做為賄款發放一節，早已明知並有犯意聯絡，故無待\n        徵詢，即可分工進行。參以，戊○○經法務部調查局為\n        測謊鑑定時，就「(一)渠沒有幫巴燕達魯買票賄選；(二)扣\n        案十萬元現金不是巴燕達魯的買票款項。二問題經測試\n        均呈情緒波動反應，研判有說謊。」亦有該局測謊報\n        告書一件在卷可參（選他卷第二二八頁），益足認定。\n    (四)至如前所述，証人露妮．萊撒稱係於十一月三日前一星\n        期即已交付十一萬餘元予丁○○，而丁○○亦供証甲○\n        ○○○夫人交給其亦係十一萬多元一致，惟其後稱轉交\n        予戊○○或係十萬餘元或僅係十萬元整，而同案戊○○\n        則供稱：其係於到下田埔當日自丁○○處收到該十萬元\n        ，其因想那十萬元是一疊錢，就先用自己的錢交付行賄\n        ，事後再從那十萬元扣除（原審卷第第二四五頁筆錄）\n        一情，則本案在戊○○皮包及其身上起出之十二萬四千\n        一百五十元，既均稱其中十萬元是一疊，則該十萬元確\n        係露妮．萊撒原交付予同案丁○○十一萬餘元之一部，\n        且係由丁○○轉交戊○○預備供發放之「賄款」無訛，\n        另戊○○於遭查獲前在現場交付高勝宏、溫春雨、田勝\n        賢各一千元之賄款，戊○○稱係先自行墊付，核與丁○\n        ○既已交賄款供其交付，且原訂行賄對象亦不止高勝宏\n        、溫春雨、田勝賢三人，衡情自是逕取賄款交付，何須\n        費事自行墊付再行扣抵？惟因戊○○亦為本案共犯，縱\n        所言墊付屬實，亦係其與被告夫妻另行結算事宜，要無\n        礙扣案十萬元原即係供預備交付之賄款性質。至另扣得\n        二萬四千一百五十元，因無証據認係露妮．萊撒或丁○\n        ○之前所交供發放之「賄款」，則應認係戊○○私人所\n        有款項。另丁○○經於黑色肩包裡查扣五萬五千元於原\n        審供稱：係其所有，其中一個白色信封一萬四千元是要\n        交給其子為大學生活費，其餘則是預備於下週一繳信用\n        卡費，其用信封袋分裝是避免混淆云云。惟查扣案五個\n        信封袋，均係裝千元紙鈔，分別為二萬三千元一封、一\n        萬四千元一封、及六千元有三封，而九十年十一月三日\n        係星期六，被告於星期六晚上將前開現金分裝於信封袋\n        帶至深山，既不可能繳錢，也不可能係為交付其於台北\n        生活之兒子，帶如此多現金上山為了「星期一繳錢」令\n        人不解，且只為了「避免混淆」而分裝在五個信封袋內\n        卻無法說出所以然來，更令人難以置信。況被告丁○○\n        自承其薪資均入五峰郵局帳戶（原審卷第二五０頁審理\n        筆錄），以當今全省自動提款機林立之情形，若真有信\n        用卡款待繳，其幾乎可隨時隨地提款繳納，當無提前多\n        天並攜現金至偏遠山區之理。且經原審調閱其五峰郵局\n        帳戶，自九十年一月二日起至九十年十一月卅日止，均\n        無提領超過一萬五千元之記錄，此有五峰郵局客戶歷史\n        交易清單在卷可參，已難証明扣案五萬五千元係自有提\n        領。另其於本院提出美國運通銀行（下稱運通銀行）綜\n        合對帳單一紙、信用卡月結單二紙、荷蘭銀行繳款通知\n        單二紙、遠東國際商業銀行（下稱遠東商銀）信用卡繳\n        款通知單二紙，共係三張信用卡，與其所辯之四張不符\n        外，觀之各該單據內容，無一與其所分裝現金之金額相\n        符。且其中就荷蘭銀行繳款通知單，經丁○○塗以黃顏\n        色，分別係十月份五千零十八元及十一月份六千零十八\n        元，且均註記為「已繳金額」，既已繳款，自亦無須再\n        行繳交；況上二筆帳單均係以自動轉帳扣繳，更無取款\n        繳交之必要。另運通銀行信用卡月結單之六千元消費金\n        額，亦已註明「已收到您由提款機支付之賬款，謝謝」\n        ，則被告空言分裝現金為避免所繳款項混淆，惟所提證\n        據無一係待繳之款項，亦無一與其分裝之金額相符，上\n        開證據均無法為有利於丁○○之認定。參以，露妮．萊\n        撒前已証稱被告甲○○○○競選之財務均由其一人負責\n        ，及如前所述，丁○○前於十一月一日在天然谷餐廳已\n        然行賄付款，復非其亦未自行出資，故露妮．萊撒當非\n        僅交付此次賄款予丁○○發放，足証前開金額亦係露妮\n        ．萊撒交予丁○○供行賄之用所餘，致其須飾詞狡卸。\n        是本案經查獲時，仍有未交付之十五萬五千元賄款扣案\n        足資佐証，則被告甲○○○○賄選犯行，事証已臻明確\n        。\n五、按公職人員選舉罷免法第九十條之一第一項之賄選罪，以對\n    於有投票權之人行求、期約或交付賄賂或其他不正利益，而\n    約其不行使投票權或為一定之行使者為構成要件，其行求、\n    期約、交付行為，係屬階段行為。交付賄款階段，以行賄者\n    已實施交付賄賂之行為，一經交付，罪即成立，雖不以收受\n    者確已承諾，或進而為一定投票權之行使為必要，但仍以收\n    受者已收受，而有受賄意思者為限。本案前揭收取賄款之証\n    人即張家旺、溫桂英、羅金錄、丙○○、劉錦來、高勝宏、\n    溫春雨、田勝賢等人，均設籍新竹縣尖石鄉，除丙○○外，\n    渠等戶政資料並均註記為山地原住民，此有法務部戶政連結\n    作業系統電腦資料在卷（原審卷第二五八、二六一～二六五\n    頁；重選上更(六)卷第四０頁）可稽，是渠等均為本次山地原\n    住民立法委員選舉之有投票權之人，自堪認定。又本件據證\n    人羅金錄證稱：其知道前述不詳姓名男子應該是替甲○○○\n    ○買票（選他卷第一四三、第一四四頁筆錄）；同案丙○○\n    於原審、證人劉錦來於原審第一次作證、證人田勝賢、高勝\n    宏於調查站亦均為相同之證言（選他卷第四五、一一九頁筆\n    錄；原審卷第一一四、一一七、一一八頁筆錄）。另證人溫\n    春雨於調查站則證稱：同案戊○○確實有拿一千元給我，並\n    要求其支持甲○○○○（選他卷第一二四頁筆錄）。是六人\n    均已證稱得知交付賄款之人意在期約投票支持被告。雖證人\n    張家旺、溫桂英均稱：不知交付該一千元用意為何云云，惟\n    於「天然谷餐廳」時，被告在現場造勢，該不詳姓名男子並\n    在被告休旅車旁交付賄款，同時一併伴隨交付被告之競選文\n    宣（選他卷第一七四、一七五頁），且該不詳姓名之人與張\n    家旺、溫桂英素不相識，亦不可能無端交付二人各一千元現\n    金，縱該不詳姓名男子交付張家旺、溫桂英現款一千元時，\n    未言明以此金錢利益約定行使投票權給甲○○○○，張家旺\n    、溫桂英亦能得知意在要求支持被告。足證張家旺、溫桂英\n    、羅金錄、丙○○、劉錦來、高勝宏、溫春雨、田勝賢等人\n    對該不詳姓名男子、同案丁○○或同案戊○○分別交付現金\n    之目的有所認識，並係基於受賄之意思而收受無訛。\n六、按被告行為後，九十四年二月二日修正公布之刑法部分修正\n    條文，業於九十五年七月一日施行。修正後刑法第二條第一\n    項規定：「行為後法律有變更者，適用行為時之法律。但行\n    為後之法律有利於行為人者，適用最有利於行為人之法律」\n    ，上揭條文係規範行為後法律變更所生新舊法律比較適用之\n    準據法，於刑法修正施行後，應適用上揭條文之規定，為「\n    從舊從輕」之比較。又法律變更之比較適用，比較時應就罪\n    刑有關之共犯、未遂犯、想像競合犯、牽連犯、連續犯、結\n    合犯，以及累犯加重、自首減輕暨其他法定加減（如身分加\n    減）與加減例等一切情形，綜其全部罪刑之結果而為比較；\n    且就比較之結果，須為整體之適用，不能割裂分別適用各該\n    有利於行為人之法律，此即法律變更之比較適用所應遵守之\n    「罪刑綜合比較原則」及「擇用整體性原則」（最高法院二\n    十四年上字第四六三四號判例、二十七年上字第二六一五號\n    判例、九十五年第八次刑事庭會議決議意旨參照）。\n    (一)被告行為後，公職人員選舉罷免法業於九十四年十一月卅\n      日修正公布，並於同年十二月二日施行，修正前第九十條\n      之一第一項法定刑原規定為五年以下，得併科新台幣四十\n      萬元以上四百萬元以下罰金，修正後該項投票行賄罪之法\n      定刑則提高為三年以上十年以下有期徒刑，得併科新台幣\n      一百萬元以上一千萬元以下罰金。另於九十六年十一月七\n      日再修正並於同日施行，則內容並未修正，僅係將前開九\n      十條之一第一項移列為九十九條第一項。則比較被告行為\n      時、行為中及裁判時之新舊法結果，以被告行為時之公職\n      人員選舉罷免法，較有利於被告。\n    (二)又被告行為後，刑法亦經修正，並自九十五年七月一日生\n      效施行，修正後刑法第二十八條將「實施」修正為「實行\n      」，其中「實施」一語，涵蓋陰謀、預備、著手及實行之\n      概念在內，其範圍較廣；而「實行」則著重於直接從事構\n      成犯罪事實之行為，其範圍較狹，是修正後刑法共同正犯\n      之範圍已有限縮，共同正犯之範圍既因此而有變動，自屬\n      犯罪後法律有變更，而非僅屬純文字修正，惟經比較結果\n      ，對本案被告為學說上所稱之共謀共同正犯，依司法院釋\n      字第一０九號解釋，仍成立共同正犯。是以修正後刑法共\n      犯之規定，未較有利於被告。\n    (三)至刑法第三十七條第二項於有關褫奪公權之規定，修正前\n      規定「宣告六個月以上有期徒刑，依犯罪之性質認為有褫\n      奪公權之必要者，宣告一年以上十年以下褫奪公權」，修\n      正為「宣告一年以上有期徒刑，依犯罪之性質認為有褫奪\n      公權之必要者，宣告一年以上十年以下褫奪公權」，經比\n      較修正前、後之規定，對宣告褫奪公權期間，新舊法之規\n      定相同；至對修正「宣告之徒刑」，按公職人員選舉罷免\n      法第九十八條第三項（九十六年修正時移列第一百十三條\n      第三項）規定：「犯本章之罪或刑法分則第六章之妨害投\n      票罪，宣告有期徒刑以上之刑者，並宣告褫奪公權。」，\n      此項褫奪公權之規定，寓有強制性，為刑法第三十七條第\n      二項之特別規定，自應優先適用公職人員選舉罷免法第九\n      十八條第三項之規定諭知褫奪公權（參照最高法院八十一\n      年度台非字第二四六號判決），是對違反選罷法之被告，\n      於經宣告有期徒刑以上之刑，即應併宣告褫奪公權，而無\n      期間長短之分別，併附此敘明。\n七、核被告所為，係犯修正前公職人員選舉罷免法第九十條之一\n    第一項之對有投票權人行賄罪。本案於「天然谷餐廳」或下\n    田埔會場，以現金行賄選民部分，雖均非被告親自交付賄款\n    而實行犯罪，然如前述，其既就以買票賄選方式求取連任，\n    而行賄之財務款項均由其妻露妮．萊撒張羅及交付予競選總\n    部主要成員丁○○及戊○○發放，則渠四人就賄選犯行當有\n    犯意聯絡，另於「天然谷餐廳」前休旅車旁行賄張家旺、溫\n    桂英、羅金錄選民部分，更與該發放款項之不詳姓名之成年\n    男子間，亦有犯意聯絡，而係推由丁○○、戊○○及該不詳\n    姓名之成年男子為行為分擔；而就「天然谷餐廳」以現金行\n    賄丙○○及丙○○轉交劉錦來現金部分，則與葉維明、丙○\n    ○分別有犯意聯絡，亦推由丁○○、戊○○、葉維明、丙○\n    ○為行為分擔；就下田埔以現金行賄選民部分，則與劉榮和\n    間亦有犯意聯絡，及推由丁○○、戊○○、劉榮和為行為分\n    擔，是被告雖未親為交付賄款犯行，然仍無從脫免其為本案\n    共謀共同正犯。至公職人員選舉罷免法第九十條之一第一項\n    所定之對有投票權人交付賄賂或不正利益罪之賄選行為，乃\n    行為人基於足以讓候選人當選票數之賄選目的，反覆向多數\n    人交付賄賂或其他不正利益，約定不行使投票權或為一定行\n    使。是對有投票權人交付賄賂或其他不正利益之犯行，於構\n    成要件類型上，本質上已具備反覆、延續之行為特徵，其持\n    續多次對有投票權人交付賄賂或其他不正利益即為此類犯罪\n    之典型或常態，於刑法評價上自應僅成立集合犯一罪（最高\n    法院九十六年台上字第一一三三號判決意旨參照）。本件被\n    告與同案丁○○、戊○○、葉維明、丙○○、劉榮和等人對\n    於有投票權之多人，交付賄賂，而約其投票權為一定之行使\n    ，其交付賄款人數共有八人，已如上述，但公職人員選舉罷\n    免法第九十一條之一第一項所定之構成要件，本質上已具備\n    反覆、延續之行為特徵，其持續多次對有投票權人交付賄賂\n    即為此類犯罪之典型或常態，於刑法評價上自應僅成立集合\n    犯一罪，故起訴書認被告上揭數次行賄犯行係連續犯，容有\n    誤會，先此敘明。\n八、原審對被告論罪科刑，固非無見。惟(一)本案尚無證據證明被\n    告於「天然谷餐廳」以餐飲不正利益行賄之犯行（如下述不\n    另為無罪部分），原審對此部分，亦認構成犯罪，尚有未洽\n    。(二)被告對有投票權之人，交付賄賂，而約其投票權為一定\n    之行使，其人數共有八人，於刑法評價上應僅成立集合犯一\n    罪，原判決認被告應成立連續犯，容有違誤。(三)漏未論列被\n    告之妻露妮．萊撒為共犯不當。(四)調查人員在同案同案戊○\n    ○皮包內起出尚未發出之賄款係十萬元（另有二萬四千一百\n    五十元則係同案同案戊○○私人款項），原審誤均為賄款，\n    亦有未當。(五)原判決對受賄之張家旺、溫桂英、羅金錄、丙\n    ○○，劉錦來、高勝宏、溫春雨、田勝賢等人，如何之確為\n    該次山地原住民立法委員選舉有投票權之人，並未於事實明\n    白認定，復未於理由說明其所憑之依據，亦有未洽。(六)原判\n    決於事實係認被告僅參與共謀，而未參與實行交付賄款，然\n    於理由論列被告有犯意聯絡及行為分擔，皆為共同正犯，乃\n    將共謀共同正犯與實行共同正犯之觀念混淆而有未洽。(七)被\n    告合於中華民國九十六年罪犯減刑條例之規定，原審未及適\n    用，亦有未洽。公訴人上訴意旨，指稱原判決對被告部分量\n    刑過輕，如下所述，非無理由；而被告上訴空言否認全部行\n    賄犯行，則無足採，另被告否認「天然谷餐廳」以餐飲不正\n    利益行賄部分，不構成犯罪，如下所述，為有理由，是原判\n    決因有上揭可議之處，自應由本院將原判決關於被告部分撤\n    銷改判。\n九、爰審酌被告行為當時仍擔任立法委員，未能明法守法，為民\n    表率，竟以行賄方式選舉，破壞選舉之公平性，敗壞社會良\n    善選風，妨礙民主政治之實現，所生危害非輕，其雖無不良\n    素行，然本案犯罪情節、手段、智識程度、及犯罪後猶飾詞\n    狡飾，否認犯行，態度非佳等一切情狀，乃量處如主文所示\n    之刑，並依公職人員選舉罷免法之規定諭知褫奪公權四年。\n    又被告犯罪時間，係在九十六年四月廿四日以前，要符中華\n    民國九十六年罪犯減刑條例所定之減刑規定，爰依法減其宣\n    告之主、從刑二分之一，以資懲儆。復按公職人員選舉罷免\n    法第九十一條第三項固規定「預備或用以行求期約或交付之\n    賄賂，不問屬於犯人與否沒收之」，但如其賄賂已交付予有\n    投票權人收受，收受者係犯刑法第一百四十三條第一項之罪\n    ，其收受之賄賂應同法條二項之規定，於其對向共犯所犯投\n    票受賄罪之從刑宣告沒收之，如全部或一部不能沒收時，追\n    徵其價額，此時即不得再依上開規定對交付賄賂者為沒收之\n    宣告（最高法院九十五年度台上字第一四七號判決意旨參照\n    ）。本案在同案丁○○之黑色肩包內扣得五萬五千元及在同\n    案戊○○皮包內扣得十萬元，如前所述，均係被告等預備交\n    付之賄款（至同案戊○○雖稱其先以自有三千元私人款項代\n    墊發予高勝宏、溫春雨、田勝賢三人，然係其與被告夫妻間\n    之私誼或民事糾葛，要與本案刑事部分對該扣案十萬元為供\n    預備交付之「賄款」性質無礙）依修正前公職人員選舉罷免\n    法第九十條之一第三項規定，不論何人所有，均予沒收。另\n    扣案之信封袋五個，係預備供本件犯罪所用之物，並屬共犯\n    丁○○所有，已據共犯丁○○自承在卷；而扣案之行賄名單\n    二張則係共犯劉榮和交予同案戊○○行賄選民，為共犯劉榮\n    和所有供共同犯罪之用，業經劉榮和於本院前審證述屬實（\n    選上訴字第九二頁筆錄），均應依刑法第三十八條第一項第\n    二款之規定，宣告沒收。又同案戊○○身上扣得二萬四千一\n    百五十元應無証據足認係供本案行賄之賄款，另於田勝賢、\n    溫春雨身上扣得之各一千元，既係已交付予其二人之賄款，\n    如前所述，均不得於本案宣告沒收，併此敘明。至黑色肩包\n    一只及扣案其他物品，均與本件犯罪無關，且非違禁物，乃\n    均不為沒收之諭知，併附此敘明。\n參、不另為無罪諭知部分：\n一、公訴意旨另以：被告與同案丁○○、戊○○三人另基於對有\n    投票權之人交付賄賂，而約其投票權為一定行使之概括犯意\n    聯絡，於九十年十一月一日十八時許在「天然谷餐廳」一樓\n    ，以餐飲之不正利益，邀請有投票權之張家旺、溫桂英、羅\n    金錄、何秋琴、李秀玉、高義茂、劉春妹、甘松枝、劉錦來\n    、林新宏（以上十人業經檢察官為不起訴處分）、李興泉、\n    李志松、葉維明、丙○○等人參加，席間被告並對在場參加\n    飲宴之人演講要求彼等支持。又在下田埔集會所以炒米粉之\n    不正利益招待選民。因認被告、丁○○涉有連續犯公職人員\n    選舉罷免法第九十條之一第一項對於有投票權人行賄罪嫌云\n    云。訊之被告、丁○○均堅決否認有此部分犯行，辯稱：「\n    天然谷餐廳」部分，當天是去村落拜訪後，與義工一起吃飯\n    ，席間並有小孩及一些無投票權之人，又無任何競選活動，\n    原住民有呼朋引友一起用餐之習慣，少許餐費之支出又符合\n    原住民的社會禮儀，並無對價關係及賄賂行為，另關於下田\n    埔集會所並無任何炒米粉招待之事等語。\n二、經查：公職人員選舉罷免法第九十條之一第一項之賄選罪，\n    係以對於有投票權之人，行求期約或交付賄賂或其他不正利\n    益，而約其不行使投票權或為一定之行使為構成要件。亦即\n    須視行為人主觀上是否具有行賄之犯意，而約使有投票權人\n    為投票權一定之行使或不行使；客觀上行為人所行求期約或\n    交付之賄賂或不正利益是否可認係約使投票權人為投票權之\n    一定行使或不行使之對價。以及所行求、期約、交付之對象\n    是否為有投票權人而定。所謂對價關係，在於行賄者之一方\n    ，係認知其所行求、期約或交付之意思表示，乃為約使有投\n    票權人為投票權一定之行使或不行使；在受賄者之一方，亦\n    應認知行賄者對其所行求、期約或交付之意思表示，乃為約\n    使其為投票權一定之行使或不行使。且對有投票權人交付之\n    財物或不正利益，並不以金錢之多寡為絕對標準，而應綜合\n    社會價值觀念、授受雙方之認知及其他客觀情事而為判斷（\n    最高法院九十三年台上字第二００七號判決意旨參照）。\n二、據證人何秋琴於新竹市調查站證稱：「因前村長李金水請渠\n    等協助蓋房子，才請渠等到『天然谷餐廳』用餐等語（選他\n    卷第一四五頁背面筆錄）。證人李秀玉證稱：「因大哥李金\n    水請替他蓋廚房之工人至『天然谷餐廳』吃飯，順便跟隨前\n    往」等語（同上卷第一七四頁背面筆錄）。證人張家旺證稱\n    ：「與老闆李金水一同前往吃飯，到達時已開始吃飯」等語\n    （同上卷第一三七頁背面筆錄）。證人即李金水之妻劉春妹\n    證稱：「請李興泉、李志松父子、張家旺、高義茂等人幫忙\n    蓋房子，工作完畢，他們要求請吃飯，乃到『天然谷餐廳』\n    用餐，到時被告及其助選員及其他村民已在用餐，被告及其\n    助選員邀請一起用餐」等語（同上卷第一五三頁背面筆錄）\n    。證人溫桂英證稱：「當晚原要至『天然谷餐廳』找該餐廳\n    老闆廖炎輝，是伊以前男友，正好被告在那邊宴客，因客人\n    大部分是伊認識之錦屏村村民，乃過去與他們用餐」等語（\n    同上卷第一四０頁筆錄）。證人丙○○供稱：「當晚是送叔\n    叔前往『天然谷餐廳』，到達後本想要離去，因邱致明叫伊\n    留下來，才留下」等語（同上卷第一七六頁背面筆錄）。證\n    人林新宏證稱：「當天原要開車載伊子及女友前去認識路，\n    經過『天然谷餐廳』見很多車輛，好奇進入，不好意思推拒\n    乃留下來用餐」等語（同上卷第一八六頁背面筆錄）。證人\n    劉錦來證稱：「原不知道要去參加被告之說明會，是伊朋友\n    邱老師打電話通知伊前往，才要丙○○開車載我前往，伊吃\n    飽才去，並未在『天然谷餐廳』用餐」（同上卷第一七四頁\n    背面筆錄）。證人劉春妹証稱：「伊蓋了一棟房子，請工人\n    去『天然谷餐廳』用餐，事先被告沒有請伊去用餐，用餐時\n    ，被告沒有表示要投票給他」等語（選上更(一)卷第六二、六\n    三頁筆錄）。證人何秋琴証稱：「伊等蓋劉春妹的房子，她\n    要請伊等去吃飯，到那裡遇到很多人，伊等就一起吃飯，現\n    場有很多小孩子，伊也有帶伊外甥女，被告等沒有要伊等投\n    票給他」等語（同上卷第六五、六六頁筆錄）。證人林新宏\n    結証稱：「當天小孩從台北回來看青蛙石，經過天然谷餐廳\n    ，看很多人，他們差不多已用餐完畢，伊等坐了幾分鐘就離\n    開了，伊小孩19歲，媳婦17歲，被告等沒有拉票動作」等語\n    （選上更(一)卷第六六、六七頁筆錄）。是在「天然谷餐廳」\n    用餐，席間有小孩、無投票權人、或有未接受吃飯之人，被\n    告等亦未以餐飲為對價要求投票權為一定之行使，自與公職\n    人員選舉罷免法第九十條之一第一項之犯罪構成要件不合。\n三、又公訴人所指九十年十一月三日下田埔炒米粉部分，遍查全\n    卷，並無任何證據足證被告有炒米粉之行為，證人即新竹市\n    調查站搜證人員黃孝賢亦證稱並未搜到有關炒米粉之事證（\n    原審卷第一二五頁筆錄）。且依社會常情，被告與同案丁○\n    ○縱有以炒米粉提供選民食用，客觀上尚不致達到行賄之代\n    價，至多只是利於邀集選民而已，亦不構成公職人員選舉罷\n    免法第九十條之一第一項之罪。\n四、綜上所述，公訴人所舉證據顯不足以證明被告有以餐飲或炒\n    米粉之不正利益賄賂選民，此外復查無其他積極證據足認被\n    告有此犯行，應認不能證明被告此部分犯罪，惟公訴人認與\n    前開論罪科刑部分有連續犯裁判上一罪關係，爰不另為無罪\n    之諭知。\n肆、據上論斷，應依刑事訴訟法第三百六十九條第一項前段、第\n    三百六十四條、第二百九十九條第一項前段，九十四年十一\n    月卅日修正前公職人員選舉罷免法第九十條之一第一項、第\n    三項、第九十八條第三項，刑法第二條第一項、第十一條前\n    段、第二十八條、第三十八條第一項第二款，中華民國九十\n    六年罪犯減刑條例第二條第一項第三款、第七條、第九條、\n    第十四條，判決如主文。\n本案經檢察官陳明光到庭執行職務\n中    華    民    國  九十九  年    五    月   十二   日\n                  刑事第四庭  審判長法  官  陳筱珮\n                                    法  官  孫惠琳\n                                    法  官  陳玉雲\n以上正本證明與原本無異。\n如不服本判決，應於收受送達後10日內向本院提出上訴書狀，其\n未敘述上訴之理由者並得於提起上訴後10日內向本院補提理由書\n（均須按他造當事人之人數附繕本）「切勿逕送上級法院」。\n                                    書記官  陳思云"
  },
  "characters": {
    "judges": [
      "陳筱珮",
      "孫惠琳",
      "陳玉雲"
    ],
    "prosecutors": [
      "陳明光"
    ],
    "lawyers": [

    ],
    "clerks": [
      "陳思云"
    ],
    "plaintiffs": [

    ],
    "defendants": [
      "上列上訴人因被告違反公職人員選舉罷免法等案件"
    ],
    "prosecutor_office": [

    ],
    "creditors": [

    ],
    "debtors": [

    ],
    "judicial_associate_officer": [

    ]
  },
  "adjudged_at": "2010-05-12",
  "created_at": "2016-01-05 11:54:11",
  "updated_at": "2016-01-05 11:54:11"
}