{
  "identify": "TPH-99-聲-1316-20100512-1",
  "court": {
    "name": "臺灣高等法院",
    "code": "TPH"
  },
  "division": {
    "name": "刑事",
    "code": "M"
  },
  "year": 99,
  "word": "聲",
  "number": "1316",
  "jcheck": "1",
  "reason": "保護管束",
  "content": "臺灣高等法院刑事裁定                  99年度聲字第1316號\n聲  請  人  臺灣高等法院檢察署檢察官\n受  刑  人  甲○○\n上列被告因保護管束案件，本院裁定如下：\n    主  文\n甲○○假釋中付保護管束。\n    理  由\n一、聲請意旨略以：受刑人甲○○前因竊盜案件，經臺灣板橋地\n    方法院判處有期徒刑3年確定，另犯竊盜罪，經本院判處有\n    期徒刑3年6月，並應於刑之執行前令入勞動處所強制工作3\n    年確定，另犯毒品危害防制條例案件，經判處有期徒刑7月\n    確定，後二案經聲請減刑及定執行之刑為應執行有期徒刑3\n    年8月確定，於民國95年3月24日送監執行。嗣經法務部於99\n    年5月3日核准假釋在案，爰聲請裁定等語。\n二、經核卷附法務部矯正司函及附件保護管束名冊，並無不合。\n三、據上論斷，依刑事訴訟法第481條第1項，刑法第93條第2項\n    規定，裁定如主文。\n中    華    民    國    99    年    5     月    12    日\n                  刑事第十七庭  審判長法  官  王聰明\n                                      法  官  黃雅芬\n                                      法  官  陳世宗\n以上正本證明與原本無異。\n不得抗告。\n                                      書記官  李佳穎\n中    華    民    國    99    年    5     月    13    日",
  "structure": {
    "main": "甲○○假釋中付保護管束。",
    "reason": "一、聲請意旨略以：受刑人甲○○前因竊盜案件，經臺灣板橋地\n    方法院判處有期徒刑3年確定，另犯竊盜罪，經本院判處有\n    期徒刑3年6月，並應於刑之執行前令入勞動處所強制工作3\n    年確定，另犯毒品危害防制條例案件，經判處有期徒刑7月\n    確定，後二案經聲請減刑及定執行之刑為應執行有期徒刑3\n    年8月確定，於民國95年3月24日送監執行。嗣經法務部於99\n    年5月3日核准假釋在案，爰聲請裁定等語。\n二、經核卷附法務部矯正司函及附件保護管束名冊，並無不合。\n三、據上論斷，依刑事訴訟法第481條第1項，刑法第93條第2項\n    規定，裁定如主文。"
  },
  "characters": {
    "judges": [
      "王聰明",
      "黃雅芬",
      "陳世宗"
    ],
    "prosecutors": [

    ],
    "lawyers": [

    ],
    "clerks": [
      "李佳穎"
    ],
    "plaintiffs": [

    ],
    "defendants": [

    ],
    "prosecutor_office": [
      "臺灣高等法院檢察署檢察官"
    ],
    "creditors": [

    ],
    "debtors": [

    ],
    "judicial_associate_officer": [

    ]
  },
  "adjudged_at": "2010-05-12",
  "created_at": "2016-01-05 11:53:07",
  "updated_at": "2016-01-05 11:53:07"
}