{
  "identify": "TPH-98-聲-3924-20100105-1",
  "court": {
    "name": "臺灣高等法院",
    "code": "TPH"
  },
  "division": {
    "name": "刑事",
    "code": "M"
  },
  "year": 98,
  "word": "聲",
  "number": "3924",
  "jcheck": "1",
  "reason": "聲請定其應執行刑",
  "content": "臺灣高等法院刑事裁定                  98年度聲字第3924號\n聲  請  人  臺灣高等法院檢察署檢察官\n受  刑  人  甲○○\n上列聲請人因受刑人數罪併罰有二裁判以上，聲請定其應執行之\n刑（聲請案號：臺灣高等法院檢察署98年度執聲字第1771號），\n本院裁定如下：\n    主  文\n甲○○因犯如附表所示各罪所處之刑，應執行有期徒刑壹年捌月\n，如易科罰金，以新臺幣壹仟元折算壹日。\n    理  由\n一、按依司法院釋字第662號解釋：「中華民國（下同）94年2月\n    2日修正公布之現行刑法第41條第2項，關於數罪併罰，數宣\n    告刑均得易科罰金，而定應執行刑之刑逾6個月者，排除適\n    用同條第1項得易科罰金之規定部分，與憲法第23條規定有\n    違，並與本院釋字第366號解釋意旨不符，應自本解釋公布\n    之日起失其效力。」故對於數罪併罰，數宣告刑均得易科罰\n    金，而定應執行之刑超過6個月之案件，依司法院釋字第366\n    號、662號解釋意旨，仍得易科罰金。\n二、受刑人甲○○所犯重利等罪，分別經臺灣花蓮地方法院、臺\n    灣宜蘭地方法院、臺灣高等法院花蓮分院及本院先後各判處\n    如附表所示之刑。其中附表編號三至五、十七所示之罪，已\n    依中華民國96年罪犯減刑條例之規定，減為如附表編號三至\n    五、十七所示之刑確定在案。茲聲請人聲請定其應執行之刑\n    ，本院審核認聲請為正當，應定其應執行之刑，而附表所示\n    十七罪，原確定判決宣告之刑期均未逾有期徒刑6月，揆諸\n    上揭說明，附表所示十七罪所定之應執行刑，仍得易科罰金\n    。\n四、爰依刑事訴訟法第477條第1項、刑法第2條第1項、第53條、\n    第51條第5款、第41條第1項前段，裁定如主文。\n中    華    民    國    99    年    1     月    5     日\n                    刑事第一庭審判長法  官  葉騰瑞\n                                    法  官  王炳梁\n                                    法  官  莊明彰\n以上正本證明與原本無異。\n不得抗告。\n                                    書記官  王韻雅\n中    華    民    國    99    年    1     月    5     日\n",
  "structure": {
    "main": "甲○○因犯如附表所示各罪所處之刑，應執行有期徒刑壹年捌月\n，如易科罰金，以新臺幣壹仟元折算壹日。",
    "reason": "一、按依司法院釋字第662號解釋：「中華民國（下同）94年2月\n    2日修正公布之現行刑法第41條第2項，關於數罪併罰，數宣\n    告刑均得易科罰金，而定應執行刑之刑逾6個月者，排除適\n    用同條第1項得易科罰金之規定部分，與憲法第23條規定有\n    違，並與本院釋字第366號解釋意旨不符，應自本解釋公布\n    之日起失其效力。」故對於數罪併罰，數宣告刑均得易科罰\n    金，而定應執行之刑超過6個月之案件，依司法院釋字第366\n    號、662號解釋意旨，仍得易科罰金。\n二、受刑人甲○○所犯重利等罪，分別經臺灣花蓮地方法院、臺\n    灣宜蘭地方法院、臺灣高等法院花蓮分院及本院先後各判處\n    如附表所示之刑。其中附表編號三至五、十七所示之罪，已\n    依中華民國96年罪犯減刑條例之規定，減為如附表編號三至\n    五、十七所示之刑確定在案。茲聲請人聲請定其應執行之刑\n    ，本院審核認聲請為正當，應定其應執行之刑，而附表所示\n    十七罪，原確定判決宣告之刑期均未逾有期徒刑6月，揆諸\n    上揭說明，附表所示十七罪所定之應執行刑，仍得易科罰金\n    。\n四、爰依刑事訴訟法第477條第1項、刑法第2條第1項、第53條、\n    第51條第5款、第41條第1項前段，裁定如主文。"
  },
  "characters": {
    "judges": [
      "葉騰瑞",
      "王炳梁",
      "莊明彰"
    ],
    "prosecutors": [

    ],
    "lawyers": [

    ],
    "clerks": [
      "王韻雅"
    ],
    "plaintiffs": [

    ],
    "defendants": [

    ],
    "prosecutor_office": [
      "臺灣高等法院檢察署檢察官"
    ],
    "creditors": [

    ],
    "debtors": [

    ],
    "judicial_associate_officer": [

    ]
  },
  "adjudged_at": "2010-01-05",
  "created_at": "2016-01-05 15:00:51",
  "updated_at": "2016-01-05 15:00:51"
}