{
  "identify": "TPH-99-聲-1296-20100512-1",
  "court": {
    "name": "臺灣高等法院",
    "code": "TPH"
  },
  "division": {
    "name": "刑事",
    "code": "M"
  },
  "year": 99,
  "word": "聲",
  "number": "1296",
  "jcheck": "1",
  "reason": "保護管束",
  "content": "臺灣高等法院刑事裁定                  99年度聲字第1296號\n聲  請  人  臺灣高等法院檢察署檢察官\n受  刑  人  甲○○\n上列受刑人因廢棄物清理法罪案件，聲請人聲請在假釋中付保護\n管束（聲請案號：99年度執聲付字第341號），本院裁定如下：\n    主  文\n甲○○假釋中付保護管束。\n    理  由\n一、聲請意旨略以：上列受刑人因廢棄物清理法罪案件，經臺灣\n    桃園地方法院91年訴字第131號判決判處應執行有期徒刑1年\n    4月，上訴臺灣高等法院以96年上更二字第578號判處應執行\n    有期徒刑2年2月，並經最高法院97年台上字第2875號上訴駁\n    回確定。於97年9月30日送監執行，嗣經法務部於99年5月3\n    日核准假釋在案，依刑法第93條第2項規定，假釋出獄者，\n    在假釋中付保護管束，爰依刑事訴訟法第481條第1項規定聲\n    請裁定等語。\n二、本院審核法務部矯正司99年5月3日法矯司字第0990905867號\n    函及「臺灣新竹監獄假釋出獄人交付保護管束名冊」，認聲\n    請人之聲請為正當，應予准許。\n三、94年2 月2 日修正公布、95年7 月1 日施行之刑法第96條有\n    關保護管束之規定，其於修正前、後之文字用語，雖已略有\n    不同（即修正前係規定：「保安處分於裁判時併宣告之。但\n    因假釋或於刑之赦免後，付保安處分者，不在此限。」，修\n    正後則規定：「保安處分於裁判時併宣告之。但本法或其他\n    法律另有規定者，不在此限。」），然考其修正理由，上開\n    文字之更動並非意在排除假釋期間付保護管束之宣告；參以\n    刑法第93條第2 項「假釋出獄者，在假釋中付保護管束。」\n    之規定，無論於修正前、後，文字俱未變動，足見對於「假\n    釋期間宣告保護管束」而言，新、舊法律並無不同。修法前\n    、後就此部分之規範既無不同，上開文字用語更動，即非刑\n    罰科刑規範變更，不生新舊法律比較適用之問題，自應適用\n    現行有效之法律規定以為裁定。\n四、據上論結，應依刑事訴訟法第481 條第1 項，刑法第96條但\n    書、第93條第2 項，裁定如主文。\n中    華    民    國    99    年    5    月    12    日\n                  刑事第九庭    審判長法  官  陳貽男\n                                      法  官  詹駿鴻\n                                      法  官  楊炳禎\n以上正本證明與原本無異。\n如不服本裁定，應於收受送達後五日內向本院提出抗告狀。\n                                      書記官  林月蓉\n中    華    民    國    99    年    5    月    13    日",
  "structure": {
    "main": "甲○○假釋中付保護管束。",
    "reason": "一、聲請意旨略以：上列受刑人因廢棄物清理法罪案件，經臺灣\n    桃園地方法院91年訴字第131號判決判處應執行有期徒刑1年\n    4月，上訴臺灣高等法院以96年上更二字第578號判處應執行\n    有期徒刑2年2月，並經最高法院97年台上字第2875號上訴駁\n    回確定。於97年9月30日送監執行，嗣經法務部於99年5月3\n    日核准假釋在案，依刑法第93條第2項規定，假釋出獄者，\n    在假釋中付保護管束，爰依刑事訴訟法第481條第1項規定聲\n    請裁定等語。\n二、本院審核法務部矯正司99年5月3日法矯司字第0990905867號\n    函及「臺灣新竹監獄假釋出獄人交付保護管束名冊」，認聲\n    請人之聲請為正當，應予准許。\n三、94年2 月2 日修正公布、95年7 月1 日施行之刑法第96條有\n    關保護管束之規定，其於修正前、後之文字用語，雖已略有\n    不同（即修正前係規定：「保安處分於裁判時併宣告之。但\n    因假釋或於刑之赦免後，付保安處分者，不在此限。」，修\n    正後則規定：「保安處分於裁判時併宣告之。但本法或其他\n    法律另有規定者，不在此限。」），然考其修正理由，上開\n    文字之更動並非意在排除假釋期間付保護管束之宣告；參以\n    刑法第93條第2 項「假釋出獄者，在假釋中付保護管束。」\n    之規定，無論於修正前、後，文字俱未變動，足見對於「假\n    釋期間宣告保護管束」而言，新、舊法律並無不同。修法前\n    、後就此部分之規範既無不同，上開文字用語更動，即非刑\n    罰科刑規範變更，不生新舊法律比較適用之問題，自應適用\n    現行有效之法律規定以為裁定。\n四、據上論結，應依刑事訴訟法第481 條第1 項，刑法第96條但\n    書、第93條第2 項，裁定如主文。"
  },
  "characters": {
    "judges": [
      "陳貽男",
      "詹駿鴻",
      "楊炳禎"
    ],
    "prosecutors": [

    ],
    "lawyers": [

    ],
    "clerks": [
      "林月蓉"
    ],
    "plaintiffs": [

    ],
    "defendants": [

    ],
    "prosecutor_office": [
      "臺灣高等法院檢察署檢察官"
    ],
    "creditors": [

    ],
    "debtors": [

    ],
    "judicial_associate_officer": [

    ]
  },
  "adjudged_at": "2010-05-12",
  "created_at": "2016-01-05 11:53:57",
  "updated_at": "2016-01-05 11:53:57"
}