{
  "identify": "TPH-98-矚上重更(十一)-7-20100512-6",
  "court": {
    "name": "臺灣高等法院",
    "code": "TPH"
  },
  "division": {
    "name": "刑事",
    "code": "M"
  },
  "year": 98,
  "word": "矚上重更(十一)",
  "number": "7",
  "jcheck": "6",
  "reason": "強盜等",
  "content": "臺灣高等法院刑事裁定         98年度矚上重更(十一)字第7號\n抗  告  人\n即  被  告  甲○○\n選任辯護人  尤伯祥律師\n上列抗告人因強盜等案件，不服本院中華民國九十九年五月四日\n延長羈押裁定（九十八年度矚上重更(十一)字第七號），提起抗\n告，本院裁定如下：\n    主  文\n抗告駁回。\n    理  由\n一、按抗告期間，除有特別規定外，為五日，自送達裁定後起算\n    ，刑事訴訟法第四百零六條前段定有明文。又原審法院認為\n    抗告不合法律上之程式或法律上不應准許，或其抗告權已喪\n    失者，應以裁定駁回之，同法第四百零八條第一項本文亦定\n    有明文。另按刑事判決應受送達之人除有特別規定外，僅以\n    當事人及其他受裁判之人為限，為刑事訴訟法第二百零六條\n    第一項（現行法第二百二十七條）所規定，而辯護人在刑事\n    訴訟法上並無對之應行送達判決之明文，因之法院對於辯護\n    人為判決送達時，僅為一種便利行為，不生法律上起算上訴\n    期間之效力，辯護人如依刑事訴訟法第三百三十八條（現行\n    法第三百四十六條）規定提起上訴，其上訴期間之計算，仍\n    應自被告收受判決之日為標準，此有最高法院三十年上字第\n    二七０二號判例可資參照。上述判例於當事人不服法院裁定\n    提起抗告時，亦應有所適用，合先敘明。\n二、本件抗告人即被告甲○○因強盜等案件，經本院於民國九十\n    九年五月四日以原羈押原因尚未消滅，依一般人之經驗法則\n    ，被告犯嫌重大且有逃亡之虞，現階段無以羈押以外之其他\n    方法以確保審判程之進行為由，裁定延長羈押，上開裁定業\n    於同年月五日合法送達抗告人，此有送達證書在卷可資佐證\n    ，計至九十九年五月十日，其抗告期間即已屆滿。乃抗告人\n    延至同年月十一日始行提起抗告，業已逾越法定抗告期間，\n    其抗告顯非合法，應予駁回。\n三、據上論斷，應依刑事訴訟法第四百零八條第一項本文，裁定\n    如主文。\n中    華    民    國    99    年    5     月    12    日\n                  刑事第九庭  審判長法  官  陳貽男\n                                    法  官  周盈文\n                                    法  官  詹駿鴻\n以上正本證明與原本無異。\n如不服本裁定，應於收受送達後五日內向本院提出抗告狀。\n                                    書記官  郭家慧\n中    華    民    國    99    年    5     月    13    日",
  "structure": {
    "main": "抗告駁回。",
    "reason": "一、按抗告期間，除有特別規定外，為五日，自送達裁定後起算\n    ，刑事訴訟法第四百零六條前段定有明文。又原審法院認為\n    抗告不合法律上之程式或法律上不應准許，或其抗告權已喪\n    失者，應以裁定駁回之，同法第四百零八條第一項本文亦定\n    有明文。另按刑事判決應受送達之人除有特別規定外，僅以\n    當事人及其他受裁判之人為限，為刑事訴訟法第二百零六條\n    第一項（現行法第二百二十七條）所規定，而辯護人在刑事\n    訴訟法上並無對之應行送達判決之明文，因之法院對於辯護\n    人為判決送達時，僅為一種便利行為，不生法律上起算上訴\n    期間之效力，辯護人如依刑事訴訟法第三百三十八條（現行\n    法第三百四十六條）規定提起上訴，其上訴期間之計算，仍\n    應自被告收受判決之日為標準，此有最高法院三十年上字第\n    二七０二號判例可資參照。上述判例於當事人不服法院裁定\n    提起抗告時，亦應有所適用，合先敘明。\n二、本件抗告人即被告甲○○因強盜等案件，經本院於民國九十\n    九年五月四日以原羈押原因尚未消滅，依一般人之經驗法則\n    ，被告犯嫌重大且有逃亡之虞，現階段無以羈押以外之其他\n    方法以確保審判程之進行為由，裁定延長羈押，上開裁定業\n    於同年月五日合法送達抗告人，此有送達證書在卷可資佐證\n    ，計至九十九年五月十日，其抗告期間即已屆滿。乃抗告人\n    延至同年月十一日始行提起抗告，業已逾越法定抗告期間，\n    其抗告顯非合法，應予駁回。\n三、據上論斷，應依刑事訴訟法第四百零八條第一項本文，裁定\n    如主文。"
  },
  "characters": {
    "judges": [
      "陳貽男",
      "周盈文",
      "詹駿鴻"
    ],
    "prosecutors": [

    ],
    "lawyers": [
      "尤伯祥"
    ],
    "clerks": [
      "郭家慧"
    ],
    "plaintiffs": [

    ],
    "defendants": [
      "甲"
    ],
    "prosecutor_office": [

    ],
    "creditors": [

    ],
    "debtors": [

    ],
    "judicial_associate_officer": [

    ]
  },
  "adjudged_at": "2010-05-12",
  "created_at": "2016-01-05 11:52:37",
  "updated_at": "2016-01-05 11:52:37"
}