{
  "identify": "TPH-98-上訴-4266-20100105-1",
  "court": {
    "name": "臺灣高等法院",
    "code": "TPH"
  },
  "division": {
    "name": "刑事",
    "code": "M"
  },
  "year": 98,
  "word": "上訴",
  "number": "4266",
  "jcheck": "1",
  "reason": "毒品危害防制條例",
  "content": "臺灣高等法院刑事判決                98年度上訴字第4266號\n上  訴  人\n即  被  告  乙○○\n選任辯護人  柴健華律師\n上列上訴人因毒品危害防制條例案件，不服臺灣板橋地方法院\n98年度訴字第1379號，中華民國98年7月17日第一審判決（起訴\n案號：臺灣板橋地方法院檢察署98年度偵字第8790號），提起上\n訴，本院判決如下：\n    主  文\n原判決撤銷。\n乙○○所犯如附表一所示之各罪，各處如附表一所示之宣告刑。\n應執行有期徒刑柒年貳月。扣案甲基安非他命（合計淨重零點貳\n陸陸零公克，驗餘淨重零點貳陸伍玖公克），沒收銷燬之；扣案\n門號0000000000號手機壹支（含SIM卡壹枚）沒收；販賣第二級\n毒品所得新臺幣仟佰元沒收之，如全一部不能沒收時，以其\n財產抵償之。\n    事  實\n一、乙○○前因施用第二級毒品甲基安非他命遭警查獲而經執行\n    觀察勒戒後，已明知甲基安非他命為毒品危害防制條例第2\n    條第2項第2款所定之第二級毒品，不得販賣，竟因友人甲○\n    ○主動詢問有無販賣甲基安非他命，且有獲得毒品之管道，\n    認為有利可圖，而基於意圖營利販賣甲基安非他命之犯意，\n    以其所有門號0000000000號手機（含SIM卡1枚）作為販賣甲\n    基安非他命之聯絡工具，而分別為下列販賣第二級毒品甲基\n    安非他命之行為：\n  (一)於民國98年1月底某日，由甲○○撥打乙○○使用之上開行\n    動電話門號向其表示欲購買新台幣（下同）1500元之甲基安\n    非他命，並約定在臺北縣中和市○○路695號三樓住處附近\n    某全家便利超商交易，乙○○遂前往上開約定之地點，以\n    1500元之價格販賣並交付第二級毒品甲基安非他命1包（重\n    量不詳）予甲○○。\n  (二)又於98年3月17日下午2時許，經甲○○撥打乙○○使用之上\n    開行動電話聯絡表示欲購買1800元之甲基安非他命，並約定\n    在台北縣土城市○○路○段清水國中門口交易，乙○○遂於\n    同日下午2時30分許騎乘機車前往上開約定地點，以1800元\n    之價格販賣並交付第二級毒品甲基安非他命1包（重量不詳\n    ）予甲○○。\n  (三)甲○○再於98年3月17日晚間7時許，撥打乙○○使用之上開\n    行動電話聯絡表示欲購買2000元之甲基安非他命，並約定在\n    臺北縣中和市○○路637巷40號之便利商店前旁交易，乙○\n    ○隨即於同日晚間7時50分許騎乘機車前往上開約定地點交\n    易，交付甲基安非他命1包（經警初步檢測毛重0.44公克，\n    淨重0.24公克）予甲○○，並留在現場等候甲○○前往巷內\n    向友人「阿寶」借款以為付款。甲○○尚未借得款項支付，\n    2 人即因形跡可疑經警盤檢查獲，並當場在甲○○身上查獲\n    乙○○甫販賣予甲○○之上開甲基安非他命1包。\n二、嗣經乙○○、甲○○2人同意，由甲○○帶同員警前往位在\n    臺北縣土城市○○街291巷15號三樓住處搜索，查扣乙○○\n    於同日下午2時許販賣予甲○○之甲基安非他命1包（經警初\n    步檢測毛重0.38公克、淨重0.18公克）；另由乙○○帶同員\n    警前往其位在臺北縣中和市○○路695號三樓住處搜索，查\n    獲其所有之行動電話1支、吸食器1組、電子磅秤1台、分裝\n    袋21個、第二級毒品甲基安非他命1包（經警初步檢測毛重\n    0.32公克、淨重0.12公克），始循線查知上情。\n三、案經臺北縣政府警察局海山分局移送臺灣板橋地方法院檢察\n    署檢察官偵查起訴。\n    理  由\n一、查本案下列所引用之供述及非供述證據，經本院依法踐行調\n    查證據程式，檢察官、被告及其選任辯護人均不爭執各該證\n    據之證據能力（見本院卷第40至41頁、第76至78頁），且亦\n    查無依法應排除其證據能力之情形，依刑事訴訟法第15 9\n    條之4、第159條之5規定意旨，後述所引用證據之證據能力\n    均無疑義，先予敘明。\n二、上訴人即被告乙○○就其於事實欄一(一)至(三)所示之時、地，\n    交付如各該欄所示之第二級毒品甲基安非他命予甲○○，並\n    向甲○○收取如各該欄所示之現金等情，固於警詢、偵訊、\n    原審及本院審理中均坦承不諱（見偵卷第8至15頁、原審卷\n    第9頁反面、本院卷第39頁反面、第74頁反面、第79頁反面\n    ），惟矢口否認其販賣第二級毒品之犯行，辯稱事實欄所載\n    之三次行為均係其與甲○○合資後，由其出面向其友人「阿\n    猴」購買毒品甲基安非他命，伊並未牟利云云。辯護人則為\n    被告辯護稱：被告並未販售甲基安非他命予甲○○，係為以\n    較便宜價格取得毒品，而與甲○○共同合資向綽號「猴子」\n    之購買毒品，並無將應分配甲○○之毒品偷斤減兩侵吞私用\n    等語。\n三、本院查：\n  (一)被告於前揭時地販賣甲基安非他命三次給甲○○之犯罪事實\n    ，業據證人甲○○於警詢、偵查時證述：警方在現場查獲之\n    甲基安非他命1包是所跟綽號「阿振」購買的，警方在現場\n    一同查獲之男子乙○○即是「阿振」，因為我向他購買毒品\n    ，並相約在中和市○○路與連城路口交易，他到現場把甲基\n    安非他命毒品交給我，我要向朋友借錢給他，所以一同遭警\n    方查獲，向乙○○購買過三次毒品甲基安非他命，第一次是\n    98 年1月底，在中和市○○路他家附近的全家便利商店購買\n    ，買1小包金額為新台幣1500元，第二次是在98年3月17日14\n    時30分左右，在台北縣土城市○○路○段清水國中門口購買\n    ，買一小包金額1800元，第三次是在98年3月17日19時50 分\n    許在中和市○○路637巷40號前購買，購買1小包金額新台幣\n    2000元，他到場就將甲基安非他命交給我，交完貨就被查獲\n    ，是用家中電話、公共電話打乙○○持用之0000000000號告\n    訴他購買毒品金額，然後約定地方交易，警方在我住處查扣\n    之甲基安非他命1包是向乙○○購買的等情綦詳（見98年度\n    偵字第8790號卷第16至22頁、第81至82頁），衡以證人甲○\n    ○與被告間為朋友關係，並無任何怨隙，其應無不良動機故\n    為不利於被告之陳述，且其與被告同時為警查獲後，旋於警\n    詢、偵查時分別為上開證述，而其所述關於被告販賣第二級\n    毒品甲基安非他命之時間、地點、數量、金額、方法等情，\n    內容互核相符，並無明顯矛盾或不合常情之處。再者，證人\n    甲○○確實有於事實欄所載時、地、金額向被告取得第二級\n    毒品甲基安非他命等情，亦為被告所不爭執，被告並於警詢\n    、原審法院羈押庭中自承：「查扣之毒品是我賣給甲○○的\n    」、「共販賣三次毒品給甲○○」、「因為我向猴子購買毒\n    品後會將少量安非他命取出自用，再將剩餘之安非他命以同\n    樣價格賣給甲○○」、「我朋友會拿一些毒品給我施用」等\n    情（見8790號偵查卷第9至14頁、原審98年度聲羈字第166號\n    卷第3頁反面），足徵證人甲○○上開證述應具憑信性。此\n    外，並有被告持用之門號0000000000行動電話1支、證人甲\n    ○○2次自被告處購得之甲基安非他命2包（合計毛重0.7960\n    公克，淨重0.2660公克，取樣0.0001公克，餘重0.2659公克\n    ）扣案足資佐證，而上開甲基安非他命2包經送鑑定結果，\n    確實均含有第二級毒品甲基安非他命成分，復有交通部民用\n    航空局航空醫務中心98年3月20日航藥鑑字第0981619號毒品\n    鑑定書1份附卷可查（見98年度毒偵字第2310號卷第54頁）\n    ，益證證人甲○○上開證言與事實相符，應堪採信。\n  (二)被告雖辯稱：只有與證人甲○○合資購買毒品3次並無賺取\n    利潤云云。但其前開辯解，悉與其於警詢時坦承販賣毒品行\n    為及偵查時供陳：是3次無償轉讓毒品給甲○○，都沒有收\n    錢云云（見同上第8790號偵查卷第9至14頁、第79頁）不符\n    ，且與證人甲○○上開證述情節相左，已難憑信。況依證人\n    甲○○所述購買毒品之過程，係伊先告知被告所欲購買毒品\n    之金額，由被告出錢購買，待被告交付毒品時，伊才交付被\n    告金錢，被告向何人購買毒品，證人並不知悉等語（見本院\n    卷第75頁反面），已明顯可見證人甲○○確係向被告購買毒\n    品之意，而非邀集被告共同出資向他人購買。至於被告或可\n    能因無存貨，而再轉向其他上游之藥頭調貨，但此亦係被告\n    與該上游藥頭之買賣關係，要與被告與證人甲○○二人間之\n    買賣關係無涉。是被告此節所辯，亦無足取。\n  (三)雖證人甲○○於原審及本院審理時翻異前詞，改稱並非向被\n    告購買毒品甲基安非他命，是與被告合資購買毒品云云。惟\n    查證人甲○○、於警詢偵查之陳述，是其甫與被告完成交易\n    後所供，與事實較相近，且製作筆錄時被告未在場，直接面\n    對警員、檢察官之訊問坦然供述，亦較無受外力干擾或事後\n    串謀之情形。況依證人甲○○於原審證述之內容以觀（見原\n    審卷第108至114頁），除與其先前於警偵訊證述直接向被告\n    購買毒品之情節迥異外，復與被告於原審準備程序時供述是\n    與證人甲○○約在賣方附近一起跟賣方拿，第一次是我們一\n    起到全家便利商店，甲○○交錢給我，我帶甲○○從全家便\n    利商店出發一起去找買主，買主再當場把貨給我們，第二次\n    跟第一次情形一樣，第三次是賣方還沒來，警察就來了，查\n    獲的毒品是我之前第二次所拿剩下的乙節不同（見原審卷第\n    9 頁反面），足證證人甲○○前開所述，應係事後迴護偏袒\n    被告所為之虛偽證述，實難採信。\n  (四)按毒品危害防制條例所規定之販賣毒品罪，雖未明示「營利\n    之意圖」為其犯罪構成要件，然「販賣」一語，在文義解釋\n    上當然已寓含有買賤賣貴，而從中取利之意思存在。且從商\n    業交易原理與一般社會觀念而言，販賣行為在通常情形下，\n    仍係以謀取利益為其活動之主要誘因與目的。然被告自始即\n    否認有販賣甲基安非他命之情事，致無從得知其購入甲基安\n    非他命之確實價格及是否確有買低賣高營利情事，惟販賣海\n    洛因係屬違法行為，非可公然為之，販賣者販入後可任意分\n    裝增減其份量再行出售，而每次交易之價格、數量，亦隨時\n    依交易對象、當時行情而變動，縱或出售之價格較低，亦非\n    當然無營利意圖，即便為相同價格，因份量較少亦能從中獲\n    利，除經坦承犯行並能供明販入、賣出確實價量外，委難查\n    得實情，如被告自始否認到底，既無法追得上手，更難查悉\n    有無從中獲利，是除非別有事證，足認係按同一價量委買或\n    轉售，確未牟利外，尚難據此即認販賣之證據有所未足，否\n    則將造成知過坦承者難辭重典，飾詞否認者反得僥倖，而失\n    情理之平。且按一般民眾均知政府一向對毒品之查禁森嚴，\n    且重罰不予寬貸，衡情倘非有利可圖，絕無平白甘冒被嚴查\n    重罰高度風險之理，從而，舉凡其有償交易，除足反證其確\n    係另基於某種非營利本意之關係外，通常尚難因無法查悉其\n    販入價格，作為是否高價賣出之比較，諉無營利之意思阻卻\n    販賣犯行之追訴（最高法院84年度第3次刑事庭會議決議意\n    旨參照），又販賣毒品罪之所謂「意圖」，即犯罪之目的，\n    原則上不以發生特定結果為必要，只需有營利之意圖為已足\n    ，不以買賤賣貴而從中得利為必要（參見最高法院97年度台\n    上字第2109號判決意旨）。參酌第二級毒品甲基安非他命，\n    物稀價昂，取得不易，且此等交易為政府懸為嚴予取締之犯\n    罪，苟無利可圖，應無甘冒被查緝法辦重刑之危險，平白無\n    端義務為該買賣之工作，況被告與證人甲○○並非至親，倘\n    無從中賺取差價或投機貪圖小利，豈有屢屢甘冒重典依購入\n    價格轉售或代購之理？是被告主觀上當有營利之意圖，亦臻\n    明確。\n  (五)綜上調查結果，被告所辯不足採信。本件事證明確，被告販\n    賣第二級毒品甲基安非他命之犯行，已堪認定。\n三、法律修正之比較適用：\n  (一)行為後法律有變更，致發生新舊法比較適用時，除與罪刑無\n    關者，例如易刑處分、拘束人身自由之保安處分等事項，不\n    必列入綜合比較，得分別適用有利於行為人之法律，另從刑\n    原則上附隨於主刑一併比較外，於比較新舊法時應就罪刑有\n    關之一切情形，含本刑及有關之共犯、未遂犯、想像競合犯\n    、牽連犯、連續犯、結合犯，以及累犯加重、自首減輕暨其\n    他法定加減原因（如身分加減）與加減例等，綜其全部罪刑\n    之結果為比較後，擇較有利者為整體之適用，不能予以割裂\n    而分別適用個別有利之條文。\n  (二)按法規之制定與法規之修正，如有特定生效日之必要者，依\n    中央法規標準法第14條或第20條第2項準用第14條之規定，\n    應分別特定其施行日期。法規制定或前次修正基於特殊因素\n    所特定之施行日期，並不適用於日後修正或再次修正之條文\n    。又法律之制定或修正，若未明定施行日期者，中央法規標\n    準法雖未規定應自何時生效，然法律既經制定或修正並經總\n    統公布，自應依一般原則，自公布日起算至第3日發生效力\n    。92年7月9日修正公布之毒品危害防制條例第36條規定：「\n    本條例自公布後6個月施行」，其立法理由謂：「(一)依修正\n    草案第2條第3項規定，法務部需會同衛生署成立審議委員會\n    每3個月定期檢討調整毒品之分級及品項，而本次新增第4級\n    毒品，有需要在新法施行前先經該審議會檢討後再調整公布\n    ，爰預留6個月緩衝期，以利處理。(二)依本條例新修正之規\n    定，有必要再訂定相關子法及修正相關法規，以配合本條例\n    之施行，故亦有需要預留適當緩衝期，以利訂頒相關子法及\n    相關法規之配合修正」，故該條規定，顯係因應該次修正之\n    需，始預留適當之緩衝期，故其後修正條文之施行日期尚難\n    援引此一規定而為標準，若未明定施行日期者，自應依一般\n    原則，自公布日起算至第3日發生效力。查總統於98年5月20\n    日以華總一義字第09800125141號令修正公布毒品危害防制\n    條例第4、11、11之1、17、20、25條條文，依上開說明，修\n    正條文應自公布日起第3日即98年5月22日發生效力。\n  (三)又毒品危害防制條例第4條第2項原規定「製造、運輸、販賣\n    第二級毒品者，處無期徒刑或7年以上有期徒刑，得併科新\n    臺幣7百萬元以下罰金」，本案被告行為後，上開規定業經\n    立法院於98年5月5日三讀修正為「製造、運輸、販賣第二級\n    毒品者，處無期徒刑或7年以上有期徒刑，得併科新臺幣1千\n    萬元以下罰金」，並經總統於98年5月20日公布，同年月22\n    日生效，經比較上開新舊法之規定，犯罪構成要件並未變動\n    ，僅新法之罰金數額提高，因販賣第二級毒品之新法並未較\n    有利於被告，且被告並未於偵審中自白犯行，並無修正後毒\n    品危害防制條例第17條第2項之適用，故此部分自應適用舊\n    法即修正前毒品危害防制條例第4條第2項之規定，附此敘明\n    。\n四、查甲基安非他命屬毒品危害防制條例第2條第2項第2款所列\n    之第二級毒品，是核被告上開3次所為，均係犯修正前毒品\n    危害防制條例第4條第2項之販賣第二級毒品罪。被告持有第\n    二級毒品，復進而販賣，其持有毒品之低度行為，為販賣之\n    高度行為所吸收，均不另論罪。被告於所為上開三次販賣第\n    二級毒品之犯行，犯意各別，且係分別所為，應予分論併罰\n    。又查販賣第二級毒品罪之法定刑為「處無期徒刑或七年以\n    上有期徒刑，得併科新臺幣七百萬元以下罰金」，然同為販\n    賣毒品之人，其原因動機不一，犯罪情節亦未必盡同，或有\n    大、中、小盤毒梟之分、或僅止於吸毒者間為求互通有無之\n    有償轉讓者，是其等各自販賣行為所造成危害社會之程度自\n    屬有異，法律科處此類犯罪，所設之法定最低本刑卻屬相同\n    ，不可謂不重，查被告販賣第2級毒品甲基安非他命之對象\n    僅甲○○一人，販賣之甲基安非他命數量甚微，總所得僅區\n    區現金三千三百元，獲利有限，又無證據足以證明其等為大\n    量走私進口或長期販賣毒品之所謂「大盤」、「中盤」之販\n    毒者，惡性與犯罪情節核與大毒梟有重大差異，如不論其情\n    節輕重，遽處以販賣毒品罪之法定本刑死刑或無期徒刑，誠\n    屬情輕法重，過於嚴苛，有傷人民對法律之情感，其等犯罪\n    情狀，顯有可憫恕之情況，本院認科以最低度刑，仍嫌過重\n    ，爰均依刑法第59條規定，酌量減輕其刑。\n五、原判決對被告予以論罪科刑，固非無見。惟查：(一)被告行為\n    後，毒品危害防制條例業經修正，原審未及比較適用，尚有\n    未洽。(二)扣案之門號0000000000手機1支（含SIM卡1枚），\n    係被告所有供聯絡販賣毒品使用之工具，業據被告及證人甲\n    ○○供述明確（見偵卷第10、17、18、82頁、原審卷第115\n    頁），自應依法宣告沒收，原審未諭知沒收，自有違誤。(三)\n    又被告為事實欄一、(三)之販賣行為後，未及向甲○○收取價\n    金2000元即為警查獲，已如前述，足見該次販賣毒品之對價\n    並未取得，原審遽認新台幣2000元係被告犯罪所得，而依毒\n    品危害防制條例第19條第1項規定宣告沒收，亦有未合。被\n    告上訴，仍執陳詞，否認犯罪，雖無理由，惟判決既有上開\n    可議，仍屬無可維持，應由本院將原判決撤銷改判。爰審酌\n    被告素行欠佳，有多次毒品前案紀錄，有本院被告前案紀錄\n    表在卷可參，被告不思依循正軌賺取金錢，竟無視政府反毒\n    政策及宣導，仍意圖營利而販賣第二級毒品予友人施用，影\n    響所及，非僅他人之生命、身體將可能受其侵害，社會、國\n    家之法益亦不能免，為害之鉅，當非個人一己之生命、身體\n    法益所可比擬，自應嚴厲規範，且犯後否認犯罪，惡性非輕\n    ，兼衡其犯罪所得有限、犯罪動機、目的、手法、智識程度\n    非高、家庭經濟狀況僅為勉持等一切情狀，酌情分別量處如\n    附表一編號一至三所示之刑，並定其應執行之刑為有期徒刑\n    七年二月，以資懲儆。\n六、沒收部分之說明：\n  (一)按毒品危害防制條例第18條第1項前段規定，查獲之第1、2\n    級毒品，不問屬於犯人與否，均沒收銷燬之，此所稱「查獲\n    之毒品」，係指被查獲而與本案有關之全部毒品而言；至同\n    條例第19條第1項所規定，犯第4條至第9條、第12條、第13\n    條或第14條第1項、第2項之罪者，其供犯罪所用或因犯罪所\n    得之財物均沒收之，所稱「供犯罪所用或因犯罪所得之財物\n    」，則係指查獲毒品以外之其他供犯罪所用或因犯罪所得之\n    財物而言，並不包括前揭查獲之毒品，縱該查獲之毒品係供\n    被告犯罪所用或屬被告犯罪所得之物，仍應依毒品危害防制\n    條例第18條第1項前段規定，諭知沒收並銷燬之（最高法院\n    95年台上字第5304號判決意旨參照）。查本案證人甲○○為\n    警查獲後，員警自其身上及住處分別扣得之甲基安非他命2\n    包（詳附表二編號2），係被告販賣予證人甲○○之第二級\n    毒品，自屬查獲且與本案被告犯行有關之毒品，揆諸上開說\n    明，均應依毒品危害防制條例第18條第1項前段規定，不問\n    屬於犯人與否，於各該次罪名之主文項內宣告沒收銷燬之。\n    至包裝上開毒品之外包裝夾鏈袋2個，因已於販賣時交付證\n    人甲○○，故已非屬被告所有，爰不予宣告沒收。\n  (二)又查被告持用之門號0000000000號手機（含SIM卡1枚）1支\n    ，乃係供被告於事實欄所示之各次販賣第二級毒品聯絡所用\n    ，且係被告所有之物，此經被告於原審供明在卷（參見原審\n    卷第115頁），應依毒品危害防制條例第19條第1項規定，於\n    各該次罪名之主文項內分別諭知沒收。又本件被告販賣毒品\n    甲基安非他命予甲○○所得之價金，除因事實欄一、(三)部分\n    尚未取得，不屬販賣毒品「所得」之金錢，爰不予宣告沒收\n    或以其財產抵償外，其餘已取得之價金部分（分別詳如附表\n    一編號一、二所示），爰依毒品危害防制條例第19條第1項\n    規定，自應於各該犯行之主文項內分別諭知沒收，且如全部\n    或一部不能沒收時，則以被告之財產抵償之。\n  (三)至自被告住處查扣如附表二編號3至5所示之物，雖係被告所\n    有，然均乏證據證明與本件販賣毒品之犯罪事實有所關聯，\n    自不予宣告沒收。另扣案如附表二編號1所示之第二級毒品\n    甲基安非他命1包，雖屬違禁物，但係供被告施用之毒品，\n    並據被告另案施用毒品案件中宣告沒收銷燬在案，此經被告\n    供明在卷（見原審卷第115頁），並有本院被告犯罪前科紀\n    錄表、臺灣板橋地方法院98年度易字第1180號刑事判決各1\n    份可參，自難遽認扣案之甲基安非他命即係供本件販賣甲基\n    安非他命所用或預備，亦難認與本件販賣該等毒品之犯行有\n    所關聯，自不予宣告沒收銷燬，併此敘明。\n據上論斷，應依刑事訴訟法第369條第1項前段、第364條、第299\n條第1項前段，修正前毒品危害防制條例第4條第2項、第18條第1\n項、第19條第1項，刑法第2條第1項前段、第11條前段、第59條\n、第51條第5款，判決如主文。\n本案經檢察官侯千姬到庭執行職務。\n中    華    民    國    99    年    1     月     5    日\n                  刑事第十八庭審判長法  官  吳鴻章\n                                    法  官  曾淑華\n                                    法  官  汪梅芬\n以上正本證明與原本無異。\n如不服本判決，應於收受送達後10日內向本院提出上訴書狀，其\n未敘述上訴之理由者並得於提起上訴後10日內向本院補提理由書\n（均須按他造當事人之人數附繕本）「切勿逕送上級法院」。\n                                    書記官  劉寶鈴\n中    華    民    國    99    年    1     月    5     日\n附錄本案論罪科刑法條全文：\n修正前毒品危害防制條例第4 條第2項\n製造、運輸、販賣第二級毒品者，處無期徒刑或七年以上有期徒\n刑，得併科新臺幣七百萬元以下罰金。\n┌──────────────────────────────────────────────┐\n│附表一：                                                                                    │\n├──┬────────────┬─────────┬────────────────────┤\n│編號│犯罪事實                │所犯罪名          │宣告刑                                  │\n├──┼────────────┼─────────┼────────────────────┤\n│ 一 │事實欄一(一)之犯罪事實    │販賣第二級毒品。  │處有期徒刑年陸月。扣案門號0000000000手│\n│    │                        │                  │機壹支（含SIM卡壹枚）沒收；販賣第二級毒 │\n│    │                        │                  │品所得之新臺幣壹仟伍佰元沒收之，如全部或│\n│    │                        │                  │一部不能沒收時，以其財產抵償之。        │\n├──┼────────────┼─────────┼────────────────────┤\n│ 二 │事實欄一(二)之犯罪事實    │販賣第二級毒品。  │處有期徒刑年陸月。扣案甲基安非他命（淨│\n│    │                        │                  │重約0.18公克）沒收銷燬之；扣案門號091529│\n│    │                        │                  │2022手機壹支（含SIM卡壹枚）沒收；販賣第 │\n│    │                        │                  │二級毒品所得之新臺幣壹仟捌佰元沒收之，如│\n│    │                        │                  │全部或一部不能沒收時，以其財產抵償之。  │\n├──┼────────────┼─────────┼────────────────────┤\n│ 三 │事實欄一(三)之犯罪事實    │販賣第二級毒品。  │處有期徒刑年陸月。扣案甲基安非他命（淨│\n│    │                        │                  │重約0.24公克）沒收銷燬之；扣案門號091529│\n│    │                        │                  │2022手機壹支（含SIM卡壹枚）沒收。       │\n│    │                        │                  │                                        │\n└──┴────────────┴─────────┴────────────────────┘\n附表二【扣案物品】\n┌─┬────┬─────────────┬──────────┬────────┐\n│編│物品名稱│    檢   驗   結   果     │   鑑    定    書   │   備    註     │\n│號│及數量  │                          │ （卷  面  位  置） │                │\n├─┼────┼─────────────┼──────────┼────────┤\n│1 │白色結晶│毛重0.3220公克，淨重0.0820│交通部民用航空局航空│左列甲基安非他命│\n│  │塊1袋   │公克，取樣0.0002公克，餘重│醫務中心98年3月27日 │係被告購入供已施│\n│  │        │0.0818公克，檢出第二級毒品│航藥鑑字第0981620號 │用，顯與本案犯罪│\n│  │        │甲基安非他命成分。        │鑑定書（見98年度偵字│無關，爰不併予宣│\n│  │        │                          │第8790號卷第87頁）  │告沒收銷燬。    │\n│  │        │                          │                    │                │\n│  │        │                          │                    │                │\n├─┼────┼─────────────┼──────────┼────────┤\n│2 │白色結晶│毛重0.7960公克（含2袋2標籤│交通部民用航空局航空│左列甲基安非他命│\n│  │塊2袋   │），淨重0.2660公克，取樣0.│醫務中心98年3 月20日│2包係甲○○於前 │\n│  │        │0001公克，餘重0.2659公克，│航藥鑑字第0981619 號│揭事實欄一(二)(三)向│\n│  │        │檢出甲基安非他命成分。    │毒品鑑定書（見98年度│被告所購入，且屬│\n│  │        │                          │毒偵字第2310號卷，第│違禁物，應依法宣│\n│  │        │                          │54頁）。            │告沒收銷燬。    │\n│  │        │                          │                    │                │\n│  │        │                          │                    │                │\n├─┼────┼─────────────┼──────────┼────────┤\n│3 │電子磅秤│                          │                    │雖為被告所有，惟│\n│  │1台     │                          │                    │與本案犯罪無關，│\n│  │        │                          │                    │爰不併予宣告沒收│\n│  │        │                          │                    │。              │\n│  │        │                          │                    │                │\n├─┼────┼─────────────┼──────────┼────────┤\n│4 │分裝袋21│                          │                    │雖為被告所有，惟│\n│  │個      │                          │                    │與本案犯罪無關，│\n│  │        │                          │                    │爰不併予宣告沒收│\n│  │        │                          │                    │。              │\n│  │        │                          │                    │                │\n├─┼────┼─────────────┼──────────┼────────┤\n│5 │吸食器1 │                          │                    │雖為被告所有，惟│\n│  │組      │                          │                    │與本案犯罪無關，│\n│  │        │                          │                    │爰不併予宣告沒收│\n│  │        │                          │                    │。              │\n├─┼────┼─────────────┼──────────┼────────┤\n│6 │手機1支 │                          │                    │為被告所有，且供│\n│  │（含0915│                          │                    │被告於前開事實欄│\n│  │292022門│                          │                    │所示各次販賣毒品│\n│  │號SIM卡1│                          │                    │聯絡使用，應予宣│\n│  │張）    │                          │                    │告沒收。        │\n└─┴────┴─────────────┴──────────┴────────┘\n",
  "structure": {
    "main": "原判決撤銷。\n乙○○所犯如附表一所示之各罪，各處如附表一所示之宣告刑。\n應執行有期徒刑柒年貳月。扣案甲基安非他命（合計淨重零點貳\n陸陸零公克，驗餘淨重零點貳陸伍玖公克），沒收銷燬之；扣案\n門號0000000000號手機壹支（含SIM卡壹枚）沒收；販賣第二級\n毒品所得新臺幣仟佰元沒收之，如全一部不能沒收時，以其\n財產抵償之。",
    "fact": "一、乙○○前因施用第二級毒品甲基安非他命遭警查獲而經執行\n    觀察勒戒後，已明知甲基安非他命為毒品危害防制條例第2\n    條第2項第2款所定之第二級毒品，不得販賣，竟因友人甲○\n    ○主動詢問有無販賣甲基安非他命，且有獲得毒品之管道，\n    認為有利可圖，而基於意圖營利販賣甲基安非他命之犯意，\n    以其所有門號0000000000號手機（含SIM卡1枚）作為販賣甲\n    基安非他命之聯絡工具，而分別為下列販賣第二級毒品甲基\n    安非他命之行為：\n  (一)於民國98年1月底某日，由甲○○撥打乙○○使用之上開行\n    動電話門號向其表示欲購買新台幣（下同）1500元之甲基安\n    非他命，並約定在臺北縣中和市○○路695號三樓住處附近\n    某全家便利超商交易，乙○○遂前往上開約定之地點，以\n    1500元之價格販賣並交付第二級毒品甲基安非他命1包（重\n    量不詳）予甲○○。\n  (二)又於98年3月17日下午2時許，經甲○○撥打乙○○使用之上\n    開行動電話聯絡表示欲購買1800元之甲基安非他命，並約定\n    在台北縣土城市○○路○段清水國中門口交易，乙○○遂於\n    同日下午2時30分許騎乘機車前往上開約定地點，以1800元\n    之價格販賣並交付第二級毒品甲基安非他命1包（重量不詳\n    ）予甲○○。\n  (三)甲○○再於98年3月17日晚間7時許，撥打乙○○使用之上開\n    行動電話聯絡表示欲購買2000元之甲基安非他命，並約定在\n    臺北縣中和市○○路637巷40號之便利商店前旁交易，乙○\n    ○隨即於同日晚間7時50分許騎乘機車前往上開約定地點交\n    易，交付甲基安非他命1包（經警初步檢測毛重0.44公克，\n    淨重0.24公克）予甲○○，並留在現場等候甲○○前往巷內\n    向友人「阿寶」借款以為付款。甲○○尚未借得款項支付，\n    2 人即因形跡可疑經警盤檢查獲，並當場在甲○○身上查獲\n    乙○○甫販賣予甲○○之上開甲基安非他命1包。\n二、嗣經乙○○、甲○○2人同意，由甲○○帶同員警前往位在\n    臺北縣土城市○○街291巷15號三樓住處搜索，查扣乙○○\n    於同日下午2時許販賣予甲○○之甲基安非他命1包（經警初\n    步檢測毛重0.38公克、淨重0.18公克）；另由乙○○帶同員\n    警前往其位在臺北縣中和市○○路695號三樓住處搜索，查\n    獲其所有之行動電話1支、吸食器1組、電子磅秤1台、分裝\n    袋21個、第二級毒品甲基安非他命1包（經警初步檢測毛重\n    0.32公克、淨重0.12公克），始循線查知上情。\n三、案經臺北縣政府警察局海山分局移送臺灣板橋地方法院檢察\n    署檢察官偵查起訴。",
    "reason": "一、查本案下列所引用之供述及非供述證據，經本院依法踐行調\n    查證據程式，檢察官、被告及其選任辯護人均不爭執各該證\n    據之證據能力（見本院卷第40至41頁、第76至78頁），且亦\n    查無依法應排除其證據能力之情形，依刑事訴訟法第15 9\n    條之4、第159條之5規定意旨，後述所引用證據之證據能力\n    均無疑義，先予敘明。\n二、上訴人即被告乙○○就其於事實欄一(一)至(三)所示之時、地，\n    交付如各該欄所示之第二級毒品甲基安非他命予甲○○，並\n    向甲○○收取如各該欄所示之現金等情，固於警詢、偵訊、\n    原審及本院審理中均坦承不諱（見偵卷第8至15頁、原審卷\n    第9頁反面、本院卷第39頁反面、第74頁反面、第79頁反面\n    ），惟矢口否認其販賣第二級毒品之犯行，辯稱事實欄所載\n    之三次行為均係其與甲○○合資後，由其出面向其友人「阿\n    猴」購買毒品甲基安非他命，伊並未牟利云云。辯護人則為\n    被告辯護稱：被告並未販售甲基安非他命予甲○○，係為以\n    較便宜價格取得毒品，而與甲○○共同合資向綽號「猴子」\n    之購買毒品，並無將應分配甲○○之毒品偷斤減兩侵吞私用\n    等語。\n三、本院查：\n  (一)被告於前揭時地販賣甲基安非他命三次給甲○○之犯罪事實\n    ，業據證人甲○○於警詢、偵查時證述：警方在現場查獲之\n    甲基安非他命1包是所跟綽號「阿振」購買的，警方在現場\n    一同查獲之男子乙○○即是「阿振」，因為我向他購買毒品\n    ，並相約在中和市○○路與連城路口交易，他到現場把甲基\n    安非他命毒品交給我，我要向朋友借錢給他，所以一同遭警\n    方查獲，向乙○○購買過三次毒品甲基安非他命，第一次是\n    98 年1月底，在中和市○○路他家附近的全家便利商店購買\n    ，買1小包金額為新台幣1500元，第二次是在98年3月17日14\n    時30分左右，在台北縣土城市○○路○段清水國中門口購買\n    ，買一小包金額1800元，第三次是在98年3月17日19時50 分\n    許在中和市○○路637巷40號前購買，購買1小包金額新台幣\n    2000元，他到場就將甲基安非他命交給我，交完貨就被查獲\n    ，是用家中電話、公共電話打乙○○持用之0000000000號告\n    訴他購買毒品金額，然後約定地方交易，警方在我住處查扣\n    之甲基安非他命1包是向乙○○購買的等情綦詳（見98年度\n    偵字第8790號卷第16至22頁、第81至82頁），衡以證人甲○\n    ○與被告間為朋友關係，並無任何怨隙，其應無不良動機故\n    為不利於被告之陳述，且其與被告同時為警查獲後，旋於警\n    詢、偵查時分別為上開證述，而其所述關於被告販賣第二級\n    毒品甲基安非他命之時間、地點、數量、金額、方法等情，\n    內容互核相符，並無明顯矛盾或不合常情之處。再者，證人\n    甲○○確實有於事實欄所載時、地、金額向被告取得第二級\n    毒品甲基安非他命等情，亦為被告所不爭執，被告並於警詢\n    、原審法院羈押庭中自承：「查扣之毒品是我賣給甲○○的\n    」、「共販賣三次毒品給甲○○」、「因為我向猴子購買毒\n    品後會將少量安非他命取出自用，再將剩餘之安非他命以同\n    樣價格賣給甲○○」、「我朋友會拿一些毒品給我施用」等\n    情（見8790號偵查卷第9至14頁、原審98年度聲羈字第166號\n    卷第3頁反面），足徵證人甲○○上開證述應具憑信性。此\n    外，並有被告持用之門號0000000000行動電話1支、證人甲\n    ○○2次自被告處購得之甲基安非他命2包（合計毛重0.7960\n    公克，淨重0.2660公克，取樣0.0001公克，餘重0.2659公克\n    ）扣案足資佐證，而上開甲基安非他命2包經送鑑定結果，\n    確實均含有第二級毒品甲基安非他命成分，復有交通部民用\n    航空局航空醫務中心98年3月20日航藥鑑字第0981619號毒品\n    鑑定書1份附卷可查（見98年度毒偵字第2310號卷第54頁）\n    ，益證證人甲○○上開證言與事實相符，應堪採信。\n  (二)被告雖辯稱：只有與證人甲○○合資購買毒品3次並無賺取\n    利潤云云。但其前開辯解，悉與其於警詢時坦承販賣毒品行\n    為及偵查時供陳：是3次無償轉讓毒品給甲○○，都沒有收\n    錢云云（見同上第8790號偵查卷第9至14頁、第79頁）不符\n    ，且與證人甲○○上開證述情節相左，已難憑信。況依證人\n    甲○○所述購買毒品之過程，係伊先告知被告所欲購買毒品\n    之金額，由被告出錢購買，待被告交付毒品時，伊才交付被\n    告金錢，被告向何人購買毒品，證人並不知悉等語（見本院\n    卷第75頁反面），已明顯可見證人甲○○確係向被告購買毒\n    品之意，而非邀集被告共同出資向他人購買。至於被告或可\n    能因無存貨，而再轉向其他上游之藥頭調貨，但此亦係被告\n    與該上游藥頭之買賣關係，要與被告與證人甲○○二人間之\n    買賣關係無涉。是被告此節所辯，亦無足取。\n  (三)雖證人甲○○於原審及本院審理時翻異前詞，改稱並非向被\n    告購買毒品甲基安非他命，是與被告合資購買毒品云云。惟\n    查證人甲○○、於警詢偵查之陳述，是其甫與被告完成交易\n    後所供，與事實較相近，且製作筆錄時被告未在場，直接面\n    對警員、檢察官之訊問坦然供述，亦較無受外力干擾或事後\n    串謀之情形。況依證人甲○○於原審證述之內容以觀（見原\n    審卷第108至114頁），除與其先前於警偵訊證述直接向被告\n    購買毒品之情節迥異外，復與被告於原審準備程序時供述是\n    與證人甲○○約在賣方附近一起跟賣方拿，第一次是我們一\n    起到全家便利商店，甲○○交錢給我，我帶甲○○從全家便\n    利商店出發一起去找買主，買主再當場把貨給我們，第二次\n    跟第一次情形一樣，第三次是賣方還沒來，警察就來了，查\n    獲的毒品是我之前第二次所拿剩下的乙節不同（見原審卷第\n    9 頁反面），足證證人甲○○前開所述，應係事後迴護偏袒\n    被告所為之虛偽證述，實難採信。\n  (四)按毒品危害防制條例所規定之販賣毒品罪，雖未明示「營利\n    之意圖」為其犯罪構成要件，然「販賣」一語，在文義解釋\n    上當然已寓含有買賤賣貴，而從中取利之意思存在。且從商\n    業交易原理與一般社會觀念而言，販賣行為在通常情形下，\n    仍係以謀取利益為其活動之主要誘因與目的。然被告自始即\n    否認有販賣甲基安非他命之情事，致無從得知其購入甲基安\n    非他命之確實價格及是否確有買低賣高營利情事，惟販賣海\n    洛因係屬違法行為，非可公然為之，販賣者販入後可任意分\n    裝增減其份量再行出售，而每次交易之價格、數量，亦隨時\n    依交易對象、當時行情而變動，縱或出售之價格較低，亦非\n    當然無營利意圖，即便為相同價格，因份量較少亦能從中獲\n    利，除經坦承犯行並能供明販入、賣出確實價量外，委難查\n    得實情，如被告自始否認到底，既無法追得上手，更難查悉\n    有無從中獲利，是除非別有事證，足認係按同一價量委買或\n    轉售，確未牟利外，尚難據此即認販賣之證據有所未足，否\n    則將造成知過坦承者難辭重典，飾詞否認者反得僥倖，而失\n    情理之平。且按一般民眾均知政府一向對毒品之查禁森嚴，\n    且重罰不予寬貸，衡情倘非有利可圖，絕無平白甘冒被嚴查\n    重罰高度風險之理，從而，舉凡其有償交易，除足反證其確\n    係另基於某種非營利本意之關係外，通常尚難因無法查悉其\n    販入價格，作為是否高價賣出之比較，諉無營利之意思阻卻\n    販賣犯行之追訴（最高法院84年度第3次刑事庭會議決議意\n    旨參照），又販賣毒品罪之所謂「意圖」，即犯罪之目的，\n    原則上不以發生特定結果為必要，只需有營利之意圖為已足\n    ，不以買賤賣貴而從中得利為必要（參見最高法院97年度台\n    上字第2109號判決意旨）。參酌第二級毒品甲基安非他命，\n    物稀價昂，取得不易，且此等交易為政府懸為嚴予取締之犯\n    罪，苟無利可圖，應無甘冒被查緝法辦重刑之危險，平白無\n    端義務為該買賣之工作，況被告與證人甲○○並非至親，倘\n    無從中賺取差價或投機貪圖小利，豈有屢屢甘冒重典依購入\n    價格轉售或代購之理？是被告主觀上當有營利之意圖，亦臻\n    明確。\n  (五)綜上調查結果，被告所辯不足採信。本件事證明確，被告販\n    賣第二級毒品甲基安非他命之犯行，已堪認定。\n三、法律修正之比較適用：\n  (一)行為後法律有變更，致發生新舊法比較適用時，除與罪刑無\n    關者，例如易刑處分、拘束人身自由之保安處分等事項，不\n    必列入綜合比較，得分別適用有利於行為人之法律，另從刑\n    原則上附隨於主刑一併比較外，於比較新舊法時應就罪刑有\n    關之一切情形，含本刑及有關之共犯、未遂犯、想像競合犯\n    、牽連犯、連續犯、結合犯，以及累犯加重、自首減輕暨其\n    他法定加減原因（如身分加減）與加減例等，綜其全部罪刑\n    之結果為比較後，擇較有利者為整體之適用，不能予以割裂\n    而分別適用個別有利之條文。\n  (二)按法規之制定與法規之修正，如有特定生效日之必要者，依\n    中央法規標準法第14條或第20條第2項準用第14條之規定，\n    應分別特定其施行日期。法規制定或前次修正基於特殊因素\n    所特定之施行日期，並不適用於日後修正或再次修正之條文\n    。又法律之制定或修正，若未明定施行日期者，中央法規標\n    準法雖未規定應自何時生效，然法律既經制定或修正並經總\n    統公布，自應依一般原則，自公布日起算至第3日發生效力\n    。92年7月9日修正公布之毒品危害防制條例第36條規定：「\n    本條例自公布後6個月施行」，其立法理由謂：「(一)依修正\n    草案第2條第3項規定，法務部需會同衛生署成立審議委員會\n    每3個月定期檢討調整毒品之分級及品項，而本次新增第4級\n    毒品，有需要在新法施行前先經該審議會檢討後再調整公布\n    ，爰預留6個月緩衝期，以利處理。(二)依本條例新修正之規\n    定，有必要再訂定相關子法及修正相關法規，以配合本條例\n    之施行，故亦有需要預留適當緩衝期，以利訂頒相關子法及\n    相關法規之配合修正」，故該條規定，顯係因應該次修正之\n    需，始預留適當之緩衝期，故其後修正條文之施行日期尚難\n    援引此一規定而為標準，若未明定施行日期者，自應依一般\n    原則，自公布日起算至第3日發生效力。查總統於98年5月20\n    日以華總一義字第09800125141號令修正公布毒品危害防制\n    條例第4、11、11之1、17、20、25條條文，依上開說明，修\n    正條文應自公布日起第3日即98年5月22日發生效力。\n  (三)又毒品危害防制條例第4條第2項原規定「製造、運輸、販賣\n    第二級毒品者，處無期徒刑或7年以上有期徒刑，得併科新\n    臺幣7百萬元以下罰金」，本案被告行為後，上開規定業經\n    立法院於98年5月5日三讀修正為「製造、運輸、販賣第二級\n    毒品者，處無期徒刑或7年以上有期徒刑，得併科新臺幣1千\n    萬元以下罰金」，並經總統於98年5月20日公布，同年月22\n    日生效，經比較上開新舊法之規定，犯罪構成要件並未變動\n    ，僅新法之罰金數額提高，因販賣第二級毒品之新法並未較\n    有利於被告，且被告並未於偵審中自白犯行，並無修正後毒\n    品危害防制條例第17條第2項之適用，故此部分自應適用舊\n    法即修正前毒品危害防制條例第4條第2項之規定，附此敘明\n    。\n四、查甲基安非他命屬毒品危害防制條例第2條第2項第2款所列\n    之第二級毒品，是核被告上開3次所為，均係犯修正前毒品\n    危害防制條例第4條第2項之販賣第二級毒品罪。被告持有第\n    二級毒品，復進而販賣，其持有毒品之低度行為，為販賣之\n    高度行為所吸收，均不另論罪。被告於所為上開三次販賣第\n    二級毒品之犯行，犯意各別，且係分別所為，應予分論併罰\n    。又查販賣第二級毒品罪之法定刑為「處無期徒刑或七年以\n    上有期徒刑，得併科新臺幣七百萬元以下罰金」，然同為販\n    賣毒品之人，其原因動機不一，犯罪情節亦未必盡同，或有\n    大、中、小盤毒梟之分、或僅止於吸毒者間為求互通有無之\n    有償轉讓者，是其等各自販賣行為所造成危害社會之程度自\n    屬有異，法律科處此類犯罪，所設之法定最低本刑卻屬相同\n    ，不可謂不重，查被告販賣第2級毒品甲基安非他命之對象\n    僅甲○○一人，販賣之甲基安非他命數量甚微，總所得僅區\n    區現金三千三百元，獲利有限，又無證據足以證明其等為大\n    量走私進口或長期販賣毒品之所謂「大盤」、「中盤」之販\n    毒者，惡性與犯罪情節核與大毒梟有重大差異，如不論其情\n    節輕重，遽處以販賣毒品罪之法定本刑死刑或無期徒刑，誠\n    屬情輕法重，過於嚴苛，有傷人民對法律之情感，其等犯罪\n    情狀，顯有可憫恕之情況，本院認科以最低度刑，仍嫌過重\n    ，爰均依刑法第59條規定，酌量減輕其刑。\n五、原判決對被告予以論罪科刑，固非無見。惟查：(一)被告行為\n    後，毒品危害防制條例業經修正，原審未及比較適用，尚有\n    未洽。(二)扣案之門號0000000000手機1支（含SIM卡1枚），\n    係被告所有供聯絡販賣毒品使用之工具，業據被告及證人甲\n    ○○供述明確（見偵卷第10、17、18、82頁、原審卷第115\n    頁），自應依法宣告沒收，原審未諭知沒收，自有違誤。(三)\n    又被告為事實欄一、(三)之販賣行為後，未及向甲○○收取價\n    金2000元即為警查獲，已如前述，足見該次販賣毒品之對價\n    並未取得，原審遽認新台幣2000元係被告犯罪所得，而依毒\n    品危害防制條例第19條第1項規定宣告沒收，亦有未合。被\n    告上訴，仍執陳詞，否認犯罪，雖無理由，惟判決既有上開\n    可議，仍屬無可維持，應由本院將原判決撤銷改判。爰審酌\n    被告素行欠佳，有多次毒品前案紀錄，有本院被告前案紀錄\n    表在卷可參，被告不思依循正軌賺取金錢，竟無視政府反毒\n    政策及宣導，仍意圖營利而販賣第二級毒品予友人施用，影\n    響所及，非僅他人之生命、身體將可能受其侵害，社會、國\n    家之法益亦不能免，為害之鉅，當非個人一己之生命、身體\n    法益所可比擬，自應嚴厲規範，且犯後否認犯罪，惡性非輕\n    ，兼衡其犯罪所得有限、犯罪動機、目的、手法、智識程度\n    非高、家庭經濟狀況僅為勉持等一切情狀，酌情分別量處如\n    附表一編號一至三所示之刑，並定其應執行之刑為有期徒刑\n    七年二月，以資懲儆。\n六、沒收部分之說明：\n  (一)按毒品危害防制條例第18條第1項前段規定，查獲之第1、2\n    級毒品，不問屬於犯人與否，均沒收銷燬之，此所稱「查獲\n    之毒品」，係指被查獲而與本案有關之全部毒品而言；至同\n    條例第19條第1項所規定，犯第4條至第9條、第12條、第13\n    條或第14條第1項、第2項之罪者，其供犯罪所用或因犯罪所\n    得之財物均沒收之，所稱「供犯罪所用或因犯罪所得之財物\n    」，則係指查獲毒品以外之其他供犯罪所用或因犯罪所得之\n    財物而言，並不包括前揭查獲之毒品，縱該查獲之毒品係供\n    被告犯罪所用或屬被告犯罪所得之物，仍應依毒品危害防制\n    條例第18條第1項前段規定，諭知沒收並銷燬之（最高法院\n    95年台上字第5304號判決意旨參照）。查本案證人甲○○為\n    警查獲後，員警自其身上及住處分別扣得之甲基安非他命2\n    包（詳附表二編號2），係被告販賣予證人甲○○之第二級\n    毒品，自屬查獲且與本案被告犯行有關之毒品，揆諸上開說\n    明，均應依毒品危害防制條例第18條第1項前段規定，不問\n    屬於犯人與否，於各該次罪名之主文項內宣告沒收銷燬之。\n    至包裝上開毒品之外包裝夾鏈袋2個，因已於販賣時交付證\n    人甲○○，故已非屬被告所有，爰不予宣告沒收。\n  (二)又查被告持用之門號0000000000號手機（含SIM卡1枚）1支\n    ，乃係供被告於事實欄所示之各次販賣第二級毒品聯絡所用\n    ，且係被告所有之物，此經被告於原審供明在卷（參見原審\n    卷第115頁），應依毒品危害防制條例第19條第1項規定，於\n    各該次罪名之主文項內分別諭知沒收。又本件被告販賣毒品\n    甲基安非他命予甲○○所得之價金，除因事實欄一、(三)部分\n    尚未取得，不屬販賣毒品「所得」之金錢，爰不予宣告沒收\n    或以其財產抵償外，其餘已取得之價金部分（分別詳如附表\n    一編號一、二所示），爰依毒品危害防制條例第19條第1項\n    規定，自應於各該犯行之主文項內分別諭知沒收，且如全部\n    或一部不能沒收時，則以被告之財產抵償之。\n  (三)至自被告住處查扣如附表二編號3至5所示之物，雖係被告所\n    有，然均乏證據證明與本件販賣毒品之犯罪事實有所關聯，\n    自不予宣告沒收。另扣案如附表二編號1所示之第二級毒品\n    甲基安非他命1包，雖屬違禁物，但係供被告施用之毒品，\n    並據被告另案施用毒品案件中宣告沒收銷燬在案，此經被告\n    供明在卷（見原審卷第115頁），並有本院被告犯罪前科紀\n    錄表、臺灣板橋地方法院98年度易字第1180號刑事判決各1\n    份可參，自難遽認扣案之甲基安非他命即係供本件販賣甲基\n    安非他命所用或預備，亦難認與本件販賣該等毒品之犯行有\n    所關聯，自不予宣告沒收銷燬，併此敘明。\n據上論斷，應依刑事訴訟法第369條第1項前段、第364條、第299\n條第1項前段，修正前毒品危害防制條例第4條第2項、第18條第1\n項、第19條第1項，刑法第2條第1項前段、第11條前段、第59條\n、第51條第5款，判決如主文。\n本案經檢察官侯千姬到庭執行職務。\n中    華    民    國    99    年    1     月     5    日\n                  刑事第十八庭審判長法  官  吳鴻章\n                                    法  官  曾淑華\n                                    法  官  汪梅芬\n以上正本證明與原本無異。\n如不服本判決，應於收受送達後10日內向本院提出上訴書狀，其\n未敘述上訴之理由者並得於提起上訴後10日內向本院補提理由書\n（均須按他造當事人之人數附繕本）「切勿逕送上級法院」。\n                                    書記官  劉寶鈴"
  },
  "characters": {
    "judges": [
      "吳鴻章",
      "曾淑華",
      "汪梅芬"
    ],
    "prosecutors": [
      "侯千姬"
    ],
    "lawyers": [
      "柴健華"
    ],
    "clerks": [
      "劉寶鈴"
    ],
    "plaintiffs": [

    ],
    "defendants": [
      "乙"
    ],
    "prosecutor_office": [

    ],
    "creditors": [

    ],
    "debtors": [

    ],
    "judicial_associate_officer": [

    ]
  },
  "adjudged_at": "2010-01-05",
  "created_at": "2016-01-05 15:01:39",
  "updated_at": "2016-01-05 15:01:39"
}