{
  "identify": "TPH-99-聲-1200-20100512-1",
  "court": {
    "name": "臺灣高等法院",
    "code": "TPH"
  },
  "division": {
    "name": "刑事",
    "code": "M"
  },
  "year": 99,
  "word": "聲",
  "number": "1200",
  "jcheck": "1",
  "reason": "聲請定其應執行刑",
  "content": "臺灣高等法院刑事裁定                  99年度聲字第1200號\n聲  請  人  臺灣高等法院檢察署檢察官\n受  刑  人  甲○○\n上列聲請人因受刑人數罪併罰有二裁判以上，聲請定其應執行之\n刑，本院裁定如下：\n    主  文\n甲○○因犯如附表所示各罪所處之刑，應執行有期徒刑拾陸年陸\n月。\n    理  由\n一、受刑人因違反毒品危害防制條例等罪，經臺灣宜蘭地方法院\n    及本院先後判處如附表所示之刑，均經分別確定在案。\n二、茲檢察官聲請定其應執行之刑，本院審核認聲請為正當，應\n    定其應執行之刑。\n爰依刑事訴訟法第477條第1項、刑法第53條、第51條第5款，裁\n定如主文。\n中    華    民    國    99    年    5     月    12    日\n                  刑事第六庭審判長法  官 林明俊\n                                  法  官 何信慶\n                                  法  官 吳淑惠\n以上正本證明與原本無異。\n如不服本裁定，應於收受送達後五日內向本院提出抗告狀。\n                                  書記官 陳雅加\n中    華    民    國    99    年    5     月    12    日",
  "structure": {
    "main": "甲○○因犯如附表所示各罪所處之刑，應執行有期徒刑拾陸年陸\n月。",
    "reason": "一、受刑人因違反毒品危害防制條例等罪，經臺灣宜蘭地方法院\n    及本院先後判處如附表所示之刑，均經分別確定在案。\n二、茲檢察官聲請定其應執行之刑，本院審核認聲請為正當，應\n    定其應執行之刑。\n爰依刑事訴訟法第477條第1項、刑法第53條、第51條第5款，裁\n定如主文。"
  },
  "characters": {
    "judges": [
      "林明俊",
      "何信慶",
      "吳淑惠"
    ],
    "prosecutors": [

    ],
    "lawyers": [

    ],
    "clerks": [
      "陳雅加"
    ],
    "plaintiffs": [

    ],
    "defendants": [

    ],
    "prosecutor_office": [
      "臺灣高等法院檢察署檢察官"
    ],
    "creditors": [

    ],
    "debtors": [

    ],
    "judicial_associate_officer": [

    ]
  },
  "adjudged_at": "2010-05-12",
  "created_at": "2016-01-05 11:53:03",
  "updated_at": "2016-01-05 11:53:03"
}