{
  "identify": "TPH-99-聲-1317-20100512-1",
  "court": {
    "name": "臺灣高等法院",
    "code": "TPH"
  },
  "division": {
    "name": "刑事",
    "code": "M"
  },
  "year": 99,
  "word": "聲",
  "number": "1317",
  "jcheck": "1",
  "reason": "保護管束",
  "content": "臺灣高等法院刑事裁定                  99年度聲字第1317號\n聲  請  人  臺灣高等法院檢察署檢察官\n受  刑  人  甲○○\n聲請人因上列受刑人強盜等案件，聲請付保護管束（臺灣高等法\n院檢察署99年執聲付字第349 號），本院裁定如下：\n    主  文\n甲○○假釋中付保護管束。\n    理  由\n一、聲請意旨略以：受刑人甲○○因強盜罪，經本院以94年度上\n    訴字第4209號判處有期徒刑5 年6 月確定，另犯竊盜罪經臺\n    灣桃園地方法院以94年度壢簡字第666 號判處有期徒刑6 月\n    確定，二案並經臺灣桃園地方法院以96年度聲減字第8750號\n    減刑並定其應執行有期徒刑5 年7 月。另犯毒品案件，經台\n    灣桃園地方法院以93年度訴字第178 號判處有期徒刑9 月，\n    上訴本院以93年度上訴字第2330號判處有期徒刑9 月；另犯\n    毒品案件，經台灣桃園地方法院以93年度壢簡字第687 號判\n    處有期徒刑5 月，二案並經本院以94年度聲字第641 號定其\n    應執行有期徒刑1 年確定，於94年5 月6 日送監執行，嗣經\n    法務部於99年5 月3 日核准假釋在案。依刑法第93條第2 項\n    規定假釋出獄者，在假釋中付保護管束，爰依刑事訴訟法第\n    481 條第1 項規定聲請裁定等語。\n二、本院審核法務部矯正司99年5 月3 日法矯司字第0990905877\n    號函及所附交付保護管束名冊，認檢察官之聲請為正當，爰\n    裁定如主文所示。\n據上論斷，應依刑事訴訟法第481 條第1 項、刑法第96條但書、\n第93條第2 項，裁定如主文。\n中    華    民    國    99    年    5     月    12    日\n                  刑事第十庭審判長法  官  陳榮和\n                                  法  官  李春地\n                                  法  官  彭政章\n以上正本證明與原本無異。\n如不服本裁定，應於收受送達後五日內向本院提出抗告狀。\n                                  書記官  杜宜寧\n中    華    民    國    99    年    5     月    12    日",
  "structure": {
    "main": "甲○○假釋中付保護管束。",
    "reason": "一、聲請意旨略以：受刑人甲○○因強盜罪，經本院以94年度上\n    訴字第4209號判處有期徒刑5 年6 月確定，另犯竊盜罪經臺\n    灣桃園地方法院以94年度壢簡字第666 號判處有期徒刑6 月\n    確定，二案並經臺灣桃園地方法院以96年度聲減字第8750號\n    減刑並定其應執行有期徒刑5 年7 月。另犯毒品案件，經台\n    灣桃園地方法院以93年度訴字第178 號判處有期徒刑9 月，\n    上訴本院以93年度上訴字第2330號判處有期徒刑9 月；另犯\n    毒品案件，經台灣桃園地方法院以93年度壢簡字第687 號判\n    處有期徒刑5 月，二案並經本院以94年度聲字第641 號定其\n    應執行有期徒刑1 年確定，於94年5 月6 日送監執行，嗣經\n    法務部於99年5 月3 日核准假釋在案。依刑法第93條第2 項\n    規定假釋出獄者，在假釋中付保護管束，爰依刑事訴訟法第\n    481 條第1 項規定聲請裁定等語。\n二、本院審核法務部矯正司99年5 月3 日法矯司字第0990905877\n    號函及所附交付保護管束名冊，認檢察官之聲請為正當，爰\n    裁定如主文所示。\n據上論斷，應依刑事訴訟法第481 條第1 項、刑法第96條但書、\n第93條第2 項，裁定如主文。"
  },
  "characters": {
    "judges": [
      "陳榮和",
      "李春地",
      "彭政章"
    ],
    "prosecutors": [

    ],
    "lawyers": [

    ],
    "clerks": [
      "杜宜寧"
    ],
    "plaintiffs": [

    ],
    "defendants": [

    ],
    "prosecutor_office": [
      "臺灣高等法院檢察署檢察官"
    ],
    "creditors": [

    ],
    "debtors": [

    ],
    "judicial_associate_officer": [

    ]
  },
  "adjudged_at": "2010-05-12",
  "created_at": "2016-01-05 11:53:39",
  "updated_at": "2016-01-05 11:53:39"
}