{
  "identify": "TPH-99-聲-1312-20100512-1",
  "court": {
    "name": "臺灣高等法院",
    "code": "TPH"
  },
  "division": {
    "name": "刑事",
    "code": "M"
  },
  "year": 99,
  "word": "聲",
  "number": "1312",
  "jcheck": "1",
  "reason": "保護管束",
  "content": "臺灣高等法院刑事裁定                  99年度聲字第1312號\n聲  請  人  臺灣高等法院檢察署檢察官\n受  刑  人  甲○○\n聲請人因上列受刑人詐欺等案件，聲請付保護管束（臺灣高等法\n院檢察署98年執聲付字第326號），本院裁定如下：\n    主  文\n甲○○假釋中付保護管束。\n    理  由\n一、聲請意旨略以：受刑人甲○○因犯詐欺等罪，經本院以91年\n    度上訴字第3826號、90年度上更一字第3 號、86年度上易字\n    第2426號、台灣板橋地方法院91年度訴字第2362號、臺灣新\n    竹地方法院90年度易緝字第32號、92年度易緝字第17號等判\n    決確定，部分並經減刑及定應執行刑。於民國92年11月28日\n    送監執行，嗣經法務部於99年5月3日核准假釋在案。依刑法\n    第93條第2 項規定假釋出獄者，在假釋中付保護管束，爰依\n    刑事訴訟法第481條第1項規定聲請裁定等語。\n二、本院審核法務部矯正司99年5月3日法矯司字第0990905882號\n    函及所附交付保護管束名冊，認檢察官之聲請為正當，爰裁\n    定如主文所示。\n三、據上論斷，應依刑事訴訟法第481條第1項、刑法第96條但書\n    、第93條第2項，裁定如主文。\n中    華    民    國    99    年    5     月    12    日\n                  刑事第二十一庭審判長法  官  蔡聰明\n                                      法  官  許永煌\n                                      法  官  趙文\n以上正本證明與原本無異。\n如不服本裁定，應於收受送達後五日內向本院提出抗告狀。\n                                      書記官  葉金發\n中    華    民    國    99    年    5     月    12    日",
  "structure": {
    "main": "甲○○假釋中付保護管束。",
    "reason": "一、聲請意旨略以：受刑人甲○○因犯詐欺等罪，經本院以91年\n    度上訴字第3826號、90年度上更一字第3 號、86年度上易字\n    第2426號、台灣板橋地方法院91年度訴字第2362號、臺灣新\n    竹地方法院90年度易緝字第32號、92年度易緝字第17號等判\n    決確定，部分並經減刑及定應執行刑。於民國92年11月28日\n    送監執行，嗣經法務部於99年5月3日核准假釋在案。依刑法\n    第93條第2 項規定假釋出獄者，在假釋中付保護管束，爰依\n    刑事訴訟法第481條第1項規定聲請裁定等語。\n二、本院審核法務部矯正司99年5月3日法矯司字第0990905882號\n    函及所附交付保護管束名冊，認檢察官之聲請為正當，爰裁\n    定如主文所示。\n三、據上論斷，應依刑事訴訟法第481條第1項、刑法第96條但書\n    、第93條第2項，裁定如主文。"
  },
  "characters": {
    "judges": [
      "蔡聰明",
      "許永煌",
      "趙文"
    ],
    "prosecutors": [

    ],
    "lawyers": [

    ],
    "clerks": [
      "葉金發"
    ],
    "plaintiffs": [

    ],
    "defendants": [

    ],
    "prosecutor_office": [
      "臺灣高等法院檢察署檢察官"
    ],
    "creditors": [

    ],
    "debtors": [

    ],
    "judicial_associate_officer": [

    ]
  },
  "adjudged_at": "2010-05-12",
  "created_at": "2016-01-05 11:53:05",
  "updated_at": "2016-01-05 11:53:05"
}