{
  "identify": "TPH-99-上易-784-20100512-1",
  "court": {
    "name": "臺灣高等法院",
    "code": "TPH"
  },
  "division": {
    "name": "刑事",
    "code": "M"
  },
  "year": 99,
  "word": "上易",
  "number": "784",
  "jcheck": "1",
  "reason": "農業管理法",
  "content": "臺灣高等法院刑事判決                 99年度上易字第784號\n上  訴  人  臺灣臺北地方法院檢察署檢察官\n被      告  東和化學企業股份有限公司\n兼代表人    甲○○\n共      同\n選任辯護人  湯明亮  律師\n上列上訴人因被告違反農藥管理法案件，不服臺灣臺北地方法院\n中華民國99年3月9日98年度易字第2629號第一審判決（起訴案號\n：臺灣臺北地方法院檢察署98年度偵字第13777號），提起上訴\n，本院判決如下：\n    主    文\n上訴駁回。\n    理    由\n壹、程序方面：\n一、按被告以外之人於審判外之言詞或書面陳述，除法律有規定\n    者外，不得作為證據，刑事訴訟法第159條第1項固有明文。\n    被告以外之人於審判外之陳述，經當事人於審判程序同意作\n    為證據，法院審酌該言詞陳述或書面陳述作成時之情況，認\n    為適當者，亦得為證據；當事人、代理人或辯護人於法院調\n    查證據時，知有上開刑事訴訟法第159條第1項不得為證據之\n    情形，而未於言詞辯論終結前聲明異議者，視為有前項之同\n    意，刑事訴訟法第159條之5定有明文。查證人賴君章、劉天\n    成及胡文芎於偵查之證述，雖屬被告以外之人於審判外之陳\n    述。惟渠等業經具結在案，有結文在卷為憑（臺灣臺北地方\n    法院98年度他字第3號偵查卷第18、38、43頁；臺灣臺北地\n    方法院98年度偵字第13777號偵查卷第31頁；臺灣澎湖地方\n    法院97年度他字第134號偵查卷第88頁）。本院審酌被告、\n    辯護人及檢察官均同意該等證述作為證據，且該等陳述作成\n    時之情況，核無違法取證及證明力明顯過低之瑕疵，為證明\n    犯罪事實所必要，以之作為證據亦為正當，況上開證人亦經\n    原審傳喚到庭，行交互詰問，已足保障被告詰問權，依刑事\n    訴訟法第159條之5第1項規定，自得作為證據。\n二、本院以下援引之其餘證據資料，其中關於刑事訴訟法第164\n    條第2項規定，證物如為文書部分，係屬證物範圍。該等可\n    為證據之文書，已經依法踐行調查證據之程序，即提示或告\n    以要旨，自具有證據能力。而有關被告以外之人於審判外之\n    書面陳述，被告與檢察官均不爭執其證據能力，本院審酌該\n    等書面作成時之狀況，認並無不宜作為證據之情事，依刑事\n    訴訟法第159條之5第2項規定，自得作為證據。\n貳、實體方面：\n一、公訴意旨略以：被告甲○○係被告東和化學企業股份有限公\n    司（下稱東和公司）負責人，明知未經核准擅自製造、加工\n    或輸入之農藥係偽農藥，詎基於加工偽農藥之犯意，竟於民\n    國94年7月間，代表被告東和公司，自維丰國際股份有限公\n    司（址設臺北縣永和市○○路111巷2弄1號4樓，下稱維丰公\n    司）購入5,000公升經行政院農業委員會以農藥進字第02293\n     號核准之「益達胺」農藥，並於不詳時地，添加甲醇及二\n    甲基甲醯胺為溶劑成分後，分裝成為250毫升小瓶裝之偽農\n    藥，計200瓶（下稱系爭農藥）。並於97年5月間，販賣系爭\n    農藥與不知情之胡文芎。嗣於97年6月1日，在澎湖縣馬公商\n    港安檢所經警查獲該批系爭農藥，始查悉上情，因認被告甲\n    ○○所為涉犯違反修正前農藥管理法第43條第1項之罪嫌，\n    被告東和公司則應依同法第47條規定科以罰金等語。\n二、按犯罪事實應依證據認定之，無證據不得認定其犯罪事實。\n    檢察官就被告犯罪事實，應負舉證責任，並指出證明之方法\n    。不能證明被告犯罪者，應諭知無罪之判決。刑事訴訟法第\n    154條第2項、第161條第1項及第301條第1項分別定有明文。\n    職是，檢察官對於其所訴之被告犯罪事實，應負提出證據及\n    說服之實質舉證責任，倘所提出之證據，不足為被告有罪之\n    積極證明，或其闡明之證明方法，無從說服法官以形成被告\n    有罪之心證，基於無罪推定之原則，自應為被告無罪判決之\n    諭知。所謂認定犯罪事實之證據，係指足以認定被告確有犯\n    罪行為之積極證據而言，倘未發現相當證據，或證據不足以\n    證明，自不能以推測或擬制之方法，以為裁判基礎，最高法\n    院40年臺上字第86號著有判例。再者，認定犯罪事實所憑之\n    證據，包含直接證據與間接證據。無論直接或間接證據，其\n    為訴訟上之證明，須於通常一般之人均不致有所懷疑，而得\n    確信其為真實之程度者，始得據為有罪之認定，倘其證明未\n    達到此程度，而有合理之懷疑存在時，事實審法院復已就其\n    心證上理由予以闡述，敘明其無從為有罪之確信，因而為無\n    罪之判決，自不得任意指為違法，最高法院76年臺上字第49\n    86號著有判例。\n三、公訴人認被告東和公司、甲○○涉有違反農藥管理法罪嫌，\n    無非以被告甲○○之供述、證人即維丰公司經理賴君章之證\n    述、行政院農業委員會動植物防疫檢疫局科長劉天成之證述\n    、胡文芎之證述、扣案之系爭農藥200瓶、行政院農業委員\n    會農業藥物毒物試驗所農藥檢驗報告、行政院農業委員會農\n    業藥物毒物試驗所函、扣案農藥標籤、東和公司溶劑成品化\n    驗報告及儀器資料及統一發票多紙證據，作為其主要論據。\n    訊據被告甲○○固坦承其為東和公司之負責人，並有向維丰\n    公司購入「益達胺」農藥等事實，惟否認有違反農藥管理法\n    之犯行，並辯稱：伊並無加工、添加之行為，伊向維丰公司\n    購買農藥時，其包裝係200公升之桶裝，買進後就分裝成250\n    毫升、500毫升及1,000毫升之小瓶裝，所有之農藥於95 年\n    10月之前，均已分裝完畢。扣案之農藥，是胡文芎向伊公司\n    所購買，當時購買5箱，1箱40瓶、每瓶250毫升，計50公升\n    ，伊事後詢問公司業務，始知悉係胡文芎自行準備英文標示\n    交予伊公司，委請伊公司貼在包裝瓶上出貨。伊不知道「益\n    達胺」為何有甲醇及二甲基甲醯胺之成分，伊工廠之設備無\n    法化驗該等成分，僅能化驗出主成分「益達胺」之成分等語\n    。職是，本院自應審究被告是否涉犯修正前農藥管理法第43\n    條第1項之犯行。經查：\n（一）扣案「益達胺」農藥，係被告東和公司向維丰公司進貨購\n      買，再分裝出售予胡文芎，嗣於97年6月1日，在澎湖縣馬\n      公商港安檢所為警查獲，並經採樣化驗，得知內含有甲醇\n      及二甲基甲醯胺化學成分等情。業據被告坦承在案，並經\n      證人賴君章證述明確，復有東和公司提出之進口報單、經\n      銷合約書、統一發票、行政院農業委員會農業藥物毒物試\n      驗所農藥檢驗報告1份（臺灣澎湖地方法院檢察署97年度\n      他字第134號偵查卷第35至37頁；臺灣臺北地方法院檢察\n      署98年度偵字第13777號偵查卷第3至10頁）、現場照片4\n      張（臺灣澎湖地方法院檢察署97年度他字第134號偵查卷\n      第9至10頁）附卷可稽，暨標示為「Assistant LinNung Co\n      ,Ltd」之系爭偽農藥200瓶扣案可證，是此部分事實足堪\n      認定。\n（二）按製造、加工或輸入偽農藥者，處3年以下有期徒刑，得\n      併科5萬元以下罰金，96年7月18日修正前農藥管理法第43\n      條第1項定有明文。96年7月18日修正後農藥管理法第5條\n      第8款規定，所謂加工者，係指將農藥原體生產為成品農\n      藥之過程。其立法理由中說明，新增有關加工之名詞定義\n      ，以資明確。而農藥管理法第5條第8款之增訂，係因農藥\n      管理法對於法律文義不明確之立法解釋，對於修正前農藥\n      管理法第43條第1項之加工偽農藥罪，故應採相同之解釋\n      。經查：\n    1.證人胡文芎雖於98年5月21日偵查中證稱：被告甲○○向\n      伊表示農藥有進字登記證與製字登記證，這批農業進口貨\n      ，故標示書寫英文云云（臺灣臺北地方法院檢察署98年度\n      他字第3號卷偵查卷第41至42頁）。惟嗣於98年7月6日偵\n      查中及99年2月9日原審審理時均證稱：因為澎湖之農友表\n      示要購買「益達胺」農藥，所以伊就打電話向東和公司訂\n      購，伊是直接向業務訂購，整個過程伊均與業務接洽，裝\n      罐之部分，伊僅表示需要瓶裝250毫升，因農友表示貼上\n      英文標籤，進口貨比較好，比較好賣，所以農友拿1張標\n      籤交予伊，伊按照標籤印製後，再交予東和公司，請東和\n      公司貼上英文標籤，並附中文說明書。伊不知東和公司如\n      何裝罐或分裝「益達胺」農藥，亦未要求東和公司就農藥\n      之成分另作處理等語（臺灣臺北地方法院檢察署98年度偵\n      字第13777號偵查卷第9至10頁；原審卷第141至143頁）。\n      證人胡文芎之前後證述固有歧異之處，惟被告東和公司、\n      甲○○與證人胡文芎間，並無其他利害關係，衡情應無袒\n      護被告之可能，且證人胡文芎於98年7月6日偵查中及原審\n      審理時證述之情節亦大致相符，應以於98年7月6日偵查中\n      及99年2月9日原審審理之證述較為可採。\n    2.證人賴君章於原審審理時證稱：本件扣案之農藥是維丰公\n      司向新加坡公司進口，維丰公司於94年間再賣予東和公司\n      ，向新加坡進口200公升之大桶包裝，轉賣予東和公司後\n      ，再由東和公司分成小包裝販售，在販售予東和公司之前\n      ，不會進行換桶或進行其他程序，因伊公司相信國外廠商\n      ，而伊公司亦無檢測儀器等語（原審卷第95至97頁）。自\n      證人賴君章之上開證言，可知被告東和公司向維丰公司購\n      買「益達胺」農藥，該批系爭偽農業由維丰公司自國外原\n      裝進口後，直接以200公升大桶包裝販售予東和公司，再\n      由東和公司分裝成250毫升之小包裝後，再轉賣給證人胡\n      文芎，並應證人胡文芎之要求，而於系爭農藥上貼上英文\n      標籤無疑。\n    3.公訴人雖以被告東和公司販售予胡文芎之扣案農藥，經農\n      委會農業藥物毒物試驗所檢驗結果，除有效成分益達胺9.\n      67%外，尚包含甲醇6.43%及二甲基甲醯胺20.1%之其他成\n      分，認與維丰公司經許可進口之「益達胺」農藥化學組成\n      之成分不同，而指稱被告有「加工」偽農藥之行為云云。\n      惟證人賴君章於原審審理時證稱：本件扣案之農藥是維丰\n      公司向新加坡公司進口，維丰公司再賣予東和公司。國外\n      供應廠商，有自己之配方，伊公司訂購時，並未指定其他\n      成分，僅針對主要成分9.6%之益達胺，必須達到國際標準\n      ，國外廠商有自己之配方，伊有向國外廠商求證，國外廠\n      商之說明，係廠商會因應當時之狀況，提供不同原料，故\n      配方並非是確定不變，因原料會因價格上漲或缺料而進行\n      調整，所以不會針對其他成分作限定。本件扣案農藥含有\n      甲醇及二甲基甲醯胺，應是新加坡公司加入等語（原審卷\n      第95至96頁背面）。自證人賴君章之上開證言可知，系爭\n      偽農藥中之甲醇及二甲基甲醯胺成分，係原出口之新加坡\n      公司所添加。況被告亦否認有添加行為，是系爭農藥究為\n      被告自行加工，或是自新加坡進口時，即已添加甲醇及二\n      甲基甲醯胺之其他成分，抑是如公訴人所指係進口後，始\n      由被告添加，即有疑義。\n    4.依據96年7月18日修正前、後之農藥管理法規定，所謂加\n      工行為者，均係指將農藥原體生產為成品農藥之過程。本\n      件扣案之「益達胺」農藥，係維丰公司自國外新加坡進口\n      200公升之大桶裝後，直接販售予被告東和公司，再由被\n      告東和公司分裝成小包裝對外販售等情，已認定如前。職\n      是，縱認被告甲○○、東和公司確有公訴人所指於「益達\n      胺」農藥中添加甲醇及二甲基甲醯胺溶劑成分，並分裝成\n      250毫升小瓶包裝，並張貼英文標籤後出售予證人胡文芎\n      之行為，因系爭農藥進口時已為成品農藥，並非農藥原體\n      ，其非農藥管理法所謂將農藥原體生產為成品農藥之加工\n      行為甚明，即難該當公訴人所指修正前農藥管理法第43條\n      加工偽農藥之罪行。\n（三）按偽農藥者，係指農藥有下列各款情形之一者：1.未經核\n      准擅自製造、加工或輸入；2.摻雜其他有效成分之含量超\n      過中央主管機關所定之限量基準；3.抽換或仿冒國內外產\n      品；4.塗改或變更有效期間之標示；5.所含有效成分之名\n      稱與核准不符。所稱劣農藥，指經核准登記之農藥有下列\n      各款情形之一者：1.有效成分之含量與標準規格不符；2.\n      超過有效期間；3.第1款所定有效成分含量以外之品質與\n      標準規格不符。農藥管理法第7條、第8條分別定有明文。\n      再者，修正前農藥管理法第43條「製造、加工、輸入」或\n      修正後第47條「製造、加工、分裝、輸入」，其應受刑事\n      處罰之行為，均以該農藥屬於偽農藥者為要件。職是，本\n      院茲審究扣案農藥是否屬偽農藥，詳述如下：\n    1.本件扣案之系爭農藥，經農委會農業藥物毒物試驗所檢驗\n      結果，呈有效成分為益達胺9.67%，其他成分為甲醇6.43%\n      及二甲基甲醯胺20.1%等情。有該試驗所97年7月23日藥試\n      化字第09725064419號函在卷可稽（臺灣臺北地方法院檢\n      察署98年度偵字第13777號偵查卷第3至10頁）。而維丰公\n      司取得之農藥許可證，農藥許可證號為農藥進字第02293\n      號，其許可進口之有效成分為益達胺9.6%之農藥原體，亦\n      有該公司之農藥許可證在卷可參（臺灣澎湖地方法院檢察\n      署97年度他字第134號偵查卷第53頁）。依農藥標準規格\n      準則第3條第1項第1款第1目規定，成品農藥以化學方法分\n      析者，其測定值與標稱有效成分之容許差如下：標稱有效\n      成分在1.0%至10%，容許差為正負15%。準此，維丰公司許\n      可進口益達胺有效成分9.6%之農藥，其容許差為8.16%至\n      11.5%之間，故扣案之系爭農藥，其檢測值為9.67%，其與\n      經核准之益達胺9.6%相較，未逾法定之容許誤差，且其所\n      含有效成分名稱亦與核准許可進口證內容相符，自非屬偽\n      農藥。\n    2.扣案之系爭農藥其有效成分為益達胺9.67%，其他成分為\n      甲醇6.43%及二甲基甲醯胺20.1%，屬有效成分含量以外之\n      品質與標準規格不符者，係農藥管理法第8條第3款所稱之\n      劣農藥。是系爭農業並非偽農藥，公訴人指稱被告係加工\n      偽農藥，亦有未合。揆諸前開說明，製造、加工、分裝或\n      輸入劣農藥，並非應受刑事處罰之行為，僅屬科以行政罰\n      鍰之行為。\n    3.按農藥標示之使用或變更，應先經中央主管機關核准。標\n      示變更後，原標示應於6個月內更換之。前項農藥標示所\n      用文字、應記載事項、警告與注意標誌樣式及應遵行事項\n      之辦法，由中央主管機關定之。違反同法第14條之規定，\n      處新臺幣2萬元以上20萬元以下罰鍰。農藥管理法第14條\n      與第52條第2款分別定有明文。扣案之系爭農藥經持有農\n      藥許可證之維丰公司合法自新加坡進口後，賣予被告東和\n      公司，並非未經核准之成品農業。且東和公司領有農藥販\n      賣業執照，有臺北市政府農藥販賣業執照在卷可稽（臺灣\n      澎湖地方法院檢察署97年度他字第134號偵查卷第42頁）\n      。職是，被告東和公司雖應胡文芎之要求，而於農藥外貼\n      上英文標籤，惟此僅係違反農藥標示之規定，尚難以修正\n      前農藥管理法第43條加工偽農藥罪行相繩。至於證人劉天\n      成固於原審審理時證稱：認定扣案之產品為偽農藥之原因\n      ，是自外面標示沒有許可字號，亦無核准的公司，即可直\n      接認定屬於偽農藥等語云云（原審卷第102頁背面）。然\n      該證言與農藥管理法之規定不符，其見解自屬有誤，即不\n      足採。\n    4.被告東和公司雖有將自維丰公司進貨購買之「益達胺」農\n      藥，分裝成小瓶零星販售之行為，然該農藥所含之有效成\n      分與原核准者相同，其成分比例亦在容許差內，並非農藥\n      管理法所稱之偽農藥。況修正前農藥管理法第43條僅處罰\n      製造、加工或輸入偽農藥之行為，分裝行為不在處罰之列\n      ，依據罪刑法定主義，自無從對被告以該罪相繩，併予敘\n      明。\n四、綜上所述，公訴人所舉之證據與指出之證明方法，未足使本\n    院形成被告有罪之確信，故被告東和公司、甲○○是否涉有\n    加工偽農藥犯行，猶有合理之懷疑。此外，復查無其他積極\n    證據足資證明被告確有上開犯行。揆諸前揭說明，本案無法\n    證明被告甲○○有加工偽農藥之犯罪，是被告東和公司亦無\n    從依修正農藥管理法第47條規定科以罰金，故應併為無罪之\n    諭知。\n五、原審同此認定，因予諭知被告無罪之判決，經核尚無違誤。\n    公訴人不服提起上訴，指謫原審認定事實與適用法律均有違\n    誤，被告有加工偽農藥犯行。其上訴意旨略以：證人即行政\n    院農業委員會動植物防疫檢疫局科長劉天成於98年5月7日偵\n    查時證稱：益達胺雖為核准登記之農藥成分，然扣案物標示\n    不合規定，且內容物與當初登記內容物不一致，認定為偽農\n    藥等語。復於同年12月1日原審審理時證稱：針對本案扣案\n    產品，自其外觀、標籤顯示，並無中央主管機關之核准字號\n    ，同時扣案產品上顯示之公司名稱，經查未在經核准公司之\n    資料內，且產品標示亦沒有經過中央主管機關核可。內容物\n    經檢驗結果，確認含有農藥有效成分，故認定屬偽農藥等語\n    。參諸本院臺中分院94年度上易字第1020號判決謂：製造、\n    加工或輸入之農藥，應與中央主管機關核發之農藥許可證記\n    載事項完全相符，始得為之，且非經主管機關核准，不得任\n    意變更許可證記載事項。查本件農藥許可證國外原製造工廠\n    欄記載為「AGSIN PTE LTD」，其與被告所販售扣案之農藥\n    標籤上之標示為LIN NUNG Co.Ltd明顯即有不符，足認扣案\n    之系爭農藥確屬農藥管理法所規範之偽農藥，而非劣農藥，\n    ，是原判決將系爭農藥認定為劣農藥，顯有違誤云云。\n六、因被告於本院審理中，否認有公訴人起訴與上訴所稱之犯行\n    。職是，本院自應審究公訴人之上訴有無理由，以認定被告\n    是否涉有上開罪嫌。本院茲探究如後：\n（一）證人即行政院農業委員會動植物防疫檢疫局科長劉天成於\n      98年5月7日偵查時雖證稱：益達胺為核准登記的農藥成分\n      ，因扣案物標示不合規定，而內容物與當初登記內容物不\n      一致，故認定為偽農藥云云。嗣於98年12月1日原審審理\n      時證稱：就系爭農業之外觀而言、標籤未顯示中央主管機\n      關之核准字號，且顯示之公司名稱，亦非經核准之公司，\n      故認定屬偽農藥云云。惟系爭農藥之標籤為被告東和公司\n      分裝成250毫升之小包裝後，再轉賣予胡文芎，並應胡文\n      芎之要求，在系爭農藥張貼英文標籤。且系爭農藥究為被\n      告自行加工，或是自新加坡進口時，即已添加甲醇及二甲\n      基甲醯胺之其他成分，抑是如公訴人所指係進口後，始由\n      東和公司添加，非無疑義。再者，維丰公司許可進口益達\n      胺有效成分9.6%之農藥，其容許差為8.16%至11.5%之間。\n      系爭農藥之檢測值為9.67%，其與經核准之益達胺9.6%相\n      較，未逾法定之容許誤差，有如前述。是系爭農藥是否有\n      經被告自行加工，仍有疑義。況其外標示係應購買人之要\n      求所張貼，非原本之標籤，而其有效成分亦未逾法定之容\n      許誤差。準此，證人劉天成逕以標籤所示與內容物成分不\n      同，即逕認為系爭農藥屬偽農藥，實嫌率斷，即難以證人\n      證詞作為不利於被告之認定。\n（二）96年7月18日修正前、後之農藥管理法，其所規定之「加\n      工」行為，均係指將農藥原體生產為成品農藥之過程。系\n      爭農藥為維丰公司自國外新加坡進口200公升之大桶裝後\n      ，直接販售予被告東和公司，再由被告東和公司分裝成小\n      包裝對外販售，有如前述。足認被告購買系爭農藥時，其\n      為農藥管理法第5條第2款之成品農藥，並非同條第3款之\n      農藥原體。退步言，縱使被告事後確有添加甲醇及二甲基\n      甲醯胺等溶劑成分之行為，亦不該當於修正前、後之農藥\n      管理法所謂之「加工」行為，自亦難構成修正前農藥管理\n      法第43條第1項之罪。\n（三）本院臺中分院94年度上易字第1020號判決事實雖謂：被告\n      在億昌農藥行，除接收其父親所遺留之來源不明之偽農藥\n      外，並自不詳中年男子處取得數量不詳之偽農藥，且未經\n      核准擅自將合法之農藥更改外包裝而予以加工成偽農藥，\n      再連續販賣偽農藥予不特定之人嫌等情。有判決書在卷為\n      憑。惟扣案系爭農藥經持有農藥許可證之維丰公司合法自\n      新加坡進口後，賣予被告東和公司，並非係未經核准之產\n      品，且東和公司亦領有農藥販賣業執照，可合法販賣農業\n      ，是本案事實與該判決事實不相同，自難比附援引，而為\n      不利被告之佐證。公訴人上訴意旨，仍執陳詞，指摘原判\n      決不當，為無理由，應予駁回。\n據上論斷，應依刑事訴訟法第368條，判決如主文。\n本案經檢察官吳茂松到庭執行職務。\n中    華    民    國    99    年    5     月    12    日\n                  刑事第五庭審判長法  官  高明哲\n                                  法  官  劉秉鑫\n                                  法  官  林洲富\n以上正本證明與原本無異。\n不得上訴。\n                                  書記官  楊秋鈴\n中    華    民    國    99    年    5     月    12    日",
  "structure": {
    "main": "上訴駁回。\n    理    由\n壹、程序方面：\n一、按被告以外之人於審判外之言詞或書面陳述，除法律有規定\n    者外，不得作為證據，刑事訴訟法第159條第1項固有明文。\n    被告以外之人於審判外之陳述，經當事人於審判程序同意作\n    為證據，法院審酌該言詞陳述或書面陳述作成時之情況，認\n    為適當者，亦得為證據；當事人、代理人或辯護人於法院調\n    查證據時，知有上開刑事訴訟法第159條第1項不得為證據之\n    情形，而未於言詞辯論終結前聲明異議者，視為有前項之同\n    意，刑事訴訟法第159條之5定有明文。查證人賴君章、劉天\n    成及胡文芎於偵查之證述，雖屬被告以外之人於審判外之陳\n    述。惟渠等業經具結在案，有結文在卷為憑（臺灣臺北地方\n    法院98年度他字第3號偵查卷第18、38、43頁；臺灣臺北地\n    方法院98年度偵字第13777號偵查卷第31頁；臺灣澎湖地方\n    法院97年度他字第134號偵查卷第88頁）。本院審酌被告、\n    辯護人及檢察官均同意該等證述作為證據，且該等陳述作成\n    時之情況，核無違法取證及證明力明顯過低之瑕疵，為證明",
    "fact": "原審傳喚到庭，行交互詰問，已足保障被告詰問權，依刑事\n    訴訟法第159條之5第1項規定，自得作為證據。\n二、本院以下援引之其餘證據資料，其中關於刑事訴訟法第164\n    條第2項規定，證物如為文書部分，係屬證物範圍。該等可\n    為證據之文書，已經依法踐行調查證據之程序，即提示或告\n    以要旨，自具有證據能力。而有關被告以外之人於審判外之\n    書面陳述，被告與檢察官均不爭執其證據能力，本院審酌該\n    等書面作成時之狀況，認並無不宜作為證據之情事，依刑事\n    訴訟法第159條之5第2項規定，自得作為證據。\n貳、實體方面：\n一、公訴意旨略以：被告甲○○係被告東和化學企業股份有限公\n    司（下稱東和公司）負責人，明知未經核准擅自製造、加工\n    或輸入之農藥係偽農藥，詎基於加工偽農藥之犯意，竟於民\n    國94年7月間，代表被告東和公司，自維丰國際股份有限公\n    司（址設臺北縣永和市○○路111巷2弄1號4樓，下稱維丰公\n    司）購入5,000公升經行政院農業委員會以農藥進字第02293\n     號核准之「益達胺」農藥，並於不詳時地，添加甲醇及二\n    甲基甲醯胺為溶劑成分後，分裝成為250毫升小瓶裝之偽農\n    藥，計200瓶（下稱系爭農藥）。並於97年5月間，販賣系爭\n    農藥與不知情之胡文芎。嗣於97年6月1日，在澎湖縣馬公商\n    港安檢所經警查獲該批系爭農藥，始查悉上情，因認被告甲\n    ○○所為涉犯違反修正前農藥管理法第43條第1項之罪嫌，\n    被告東和公司則應依同法第47條規定科以罰金等語。\n二、按犯罪事實應依證據認定之，無證據不得認定其犯罪事實。\n    檢察官就被告犯罪事實，應負舉證責任，並指出證明之方法\n    。不能證明被告犯罪者，應諭知無罪之判決。刑事訴訟法第\n    154條第2項、第161條第1項及第301條第1項分別定有明文。\n    職是，檢察官對於其所訴之被告犯罪事實，應負提出證據及\n    說服之實質舉證責任，倘所提出之證據，不足為被告有罪之\n    積極證明，或其闡明之證明方法，無從說服法官以形成被告\n    有罪之心證，基於無罪推定之原則，自應為被告無罪判決之\n    諭知。所謂認定犯罪事實之證據，係指足以認定被告確有犯\n    罪行為之積極證據而言，倘未發現相當證據，或證據不足以\n    證明，自不能以推測或擬制之方法，以為裁判基礎，最高法\n    院40年臺上字第86號著有判例。再者，認定犯罪事實所憑之\n    證據，包含直接證據與間接證據。無論直接或間接證據，其\n    為訴訟上之證明，須於通常一般之人均不致有所懷疑，而得\n    確信其為真實之程度者，始得據為有罪之認定，倘其證明未\n    達到此程度，而有合理之懷疑存在時，事實審法院復已就其\n    心證上理由予以闡述，敘明其無從為有罪之確信，因而為無\n    罪之判決，自不得任意指為違法，最高法院76年臺上字第49\n    86號著有判例。\n三、公訴人認被告東和公司、甲○○涉有違反農藥管理法罪嫌，\n    無非以被告甲○○之供述、證人即維丰公司經理賴君章之證\n    述、行政院農業委員會動植物防疫檢疫局科長劉天成之證述\n    、胡文芎之證述、扣案之系爭農藥200瓶、行政院農業委員\n    會農業藥物毒物試驗所農藥檢驗報告、行政院農業委員會農\n    業藥物毒物試驗所函、扣案農藥標籤、東和公司溶劑成品化\n    驗報告及儀器資料及統一發票多紙證據，作為其主要論據。\n    訊據被告甲○○固坦承其為東和公司之負責人，並有向維丰\n    公司購入「益達胺」農藥等事實，惟否認有違反農藥管理法\n    之犯行，並辯稱：伊並無加工、添加之行為，伊向維丰公司\n    購買農藥時，其包裝係200公升之桶裝，買進後就分裝成250\n    毫升、500毫升及1,000毫升之小瓶裝，所有之農藥於95 年\n    10月之前，均已分裝完畢。扣案之農藥，是胡文芎向伊公司\n    所購買，當時購買5箱，1箱40瓶、每瓶250毫升，計50公升\n    ，伊事後詢問公司業務，始知悉係胡文芎自行準備英文標示\n    交予伊公司，委請伊公司貼在包裝瓶上出貨。伊不知道「益\n    達胺」為何有甲醇及二甲基甲醯胺之成分，伊工廠之設備無\n    法化驗該等成分，僅能化驗出主成分「益達胺」之成分等語\n    。職是，本院自應審究被告是否涉犯修正前農藥管理法第43\n    條第1項之犯行。經查：\n（一）扣案「益達胺」農藥，係被告東和公司向維丰公司進貨購\n      買，再分裝出售予胡文芎，嗣於97年6月1日，在澎湖縣馬\n      公商港安檢所為警查獲，並經採樣化驗，得知內含有甲醇\n      及二甲基甲醯胺化學成分等情。業據被告坦承在案，並經\n      證人賴君章證述明確，復有東和公司提出之進口報單、經\n      銷合約書、統一發票、行政院農業委員會農業藥物毒物試\n      驗所農藥檢驗報告1份（臺灣澎湖地方法院檢察署97年度\n      他字第134號偵查卷第35至37頁；臺灣臺北地方法院檢察\n      署98年度偵字第13777號偵查卷第3至10頁）、現場照片4\n      張（臺灣澎湖地方法院檢察署97年度他字第134號偵查卷\n      第9至10頁）附卷可稽，暨標示為「Assistant LinNung Co\n      ,Ltd」之系爭偽農藥200瓶扣案可證，是此部分事實足堪\n      認定。\n（二）按製造、加工或輸入偽農藥者，處3年以下有期徒刑，得\n      併科5萬元以下罰金，96年7月18日修正前農藥管理法第43\n      條第1項定有明文。96年7月18日修正後農藥管理法第5條\n      第8款規定，所謂加工者，係指將農藥原體生產為成品農\n      藥之過程。其立法理由中說明，新增有關加工之名詞定義\n      ，以資明確。而農藥管理法第5條第8款之增訂，係因農藥\n      管理法對於法律文義不明確之立法解釋，對於修正前農藥\n      管理法第43條第1項之加工偽農藥罪，故應採相同之解釋\n      。經查：\n    1.證人胡文芎雖於98年5月21日偵查中證稱：被告甲○○向\n      伊表示農藥有進字登記證與製字登記證，這批農業進口貨\n      ，故標示書寫英文云云（臺灣臺北地方法院檢察署98年度\n      他字第3號卷偵查卷第41至42頁）。惟嗣於98年7月6日偵\n      查中及99年2月9日原審審理時均證稱：因為澎湖之農友表\n      示要購買「益達胺」農藥，所以伊就打電話向東和公司訂\n      購，伊是直接向業務訂購，整個過程伊均與業務接洽，裝\n      罐之部分，伊僅表示需要瓶裝250毫升，因農友表示貼上\n      英文標籤，進口貨比較好，比較好賣，所以農友拿1張標\n      籤交予伊，伊按照標籤印製後，再交予東和公司，請東和\n      公司貼上英文標籤，並附中文說明書。伊不知東和公司如\n      何裝罐或分裝「益達胺」農藥，亦未要求東和公司就農藥\n      之成分另作處理等語（臺灣臺北地方法院檢察署98年度偵\n      字第13777號偵查卷第9至10頁；原審卷第141至143頁）。\n      證人胡文芎之前後證述固有歧異之處，惟被告東和公司、\n      甲○○與證人胡文芎間，並無其他利害關係，衡情應無袒\n      護被告之可能，且證人胡文芎於98年7月6日偵查中及原審\n      審理時證述之情節亦大致相符，應以於98年7月6日偵查中\n      及99年2月9日原審審理之證述較為可採。\n    2.證人賴君章於原審審理時證稱：本件扣案之農藥是維丰公\n      司向新加坡公司進口，維丰公司於94年間再賣予東和公司\n      ，向新加坡進口200公升之大桶包裝，轉賣予東和公司後\n      ，再由東和公司分成小包裝販售，在販售予東和公司之前\n      ，不會進行換桶或進行其他程序，因伊公司相信國外廠商\n      ，而伊公司亦無檢測儀器等語（原審卷第95至97頁）。自\n      證人賴君章之上開證言，可知被告東和公司向維丰公司購\n      買「益達胺」農藥，該批系爭偽農業由維丰公司自國外原\n      裝進口後，直接以200公升大桶包裝販售予東和公司，再\n      由東和公司分裝成250毫升之小包裝後，再轉賣給證人胡\n      文芎，並應證人胡文芎之要求，而於系爭農藥上貼上英文\n      標籤無疑。\n    3.公訴人雖以被告東和公司販售予胡文芎之扣案農藥，經農\n      委會農業藥物毒物試驗所檢驗結果，除有效成分益達胺9.\n      67%外，尚包含甲醇6.43%及二甲基甲醯胺20.1%之其他成\n      分，認與維丰公司經許可進口之「益達胺」農藥化學組成\n      之成分不同，而指稱被告有「加工」偽農藥之行為云云。\n      惟證人賴君章於原審審理時證稱：本件扣案之農藥是維丰\n      公司向新加坡公司進口，維丰公司再賣予東和公司。國外\n      供應廠商，有自己之配方，伊公司訂購時，並未指定其他\n      成分，僅針對主要成分9.6%之益達胺，必須達到國際標準\n      ，國外廠商有自己之配方，伊有向國外廠商求證，國外廠\n      商之說明，係廠商會因應當時之狀況，提供不同原料，故\n      配方並非是確定不變，因原料會因價格上漲或缺料而進行\n      調整，所以不會針對其他成分作限定。本件扣案農藥含有\n      甲醇及二甲基甲醯胺，應是新加坡公司加入等語（原審卷\n      第95至96頁背面）。自證人賴君章之上開證言可知，系爭\n      偽農藥中之甲醇及二甲基甲醯胺成分，係原出口之新加坡\n      公司所添加。況被告亦否認有添加行為，是系爭農藥究為\n      被告自行加工，或是自新加坡進口時，即已添加甲醇及二\n      甲基甲醯胺之其他成分，抑是如公訴人所指係進口後，始\n      由被告添加，即有疑義。\n    4.依據96年7月18日修正前、後之農藥管理法規定，所謂加\n      工行為者，均係指將農藥原體生產為成品農藥之過程。本\n      件扣案之「益達胺」農藥，係維丰公司自國外新加坡進口\n      200公升之大桶裝後，直接販售予被告東和公司，再由被\n      告東和公司分裝成小包裝對外販售等情，已認定如前。職\n      是，縱認被告甲○○、東和公司確有公訴人所指於「益達\n      胺」農藥中添加甲醇及二甲基甲醯胺溶劑成分，並分裝成\n      250毫升小瓶包裝，並張貼英文標籤後出售予證人胡文芎\n      之行為，因系爭農藥進口時已為成品農藥，並非農藥原體\n      ，其非農藥管理法所謂將農藥原體生產為成品農藥之加工\n      行為甚明，即難該當公訴人所指修正前農藥管理法第43條\n      加工偽農藥之罪行。\n（三）按偽農藥者，係指農藥有下列各款情形之一者：1.未經核\n      准擅自製造、加工或輸入；2.摻雜其他有效成分之含量超\n      過中央主管機關所定之限量基準；3.抽換或仿冒國內外產\n      品；4.塗改或變更有效期間之標示；5.所含有效成分之名\n      稱與核准不符。所稱劣農藥，指經核准登記之農藥有下列\n      各款情形之一者：1.有效成分之含量與標準規格不符；2.\n      超過有效期間；3.第1款所定有效成分含量以外之品質與\n      標準規格不符。農藥管理法第7條、第8條分別定有明文。\n      再者，修正前農藥管理法第43條「製造、加工、輸入」或\n      修正後第47條「製造、加工、分裝、輸入」，其應受刑事\n      處罰之行為，均以該農藥屬於偽農藥者為要件。職是，本\n      院茲審究扣案農藥是否屬偽農藥，詳述如下：\n    1.本件扣案之系爭農藥，經農委會農業藥物毒物試驗所檢驗\n      結果，呈有效成分為益達胺9.67%，其他成分為甲醇6.43%\n      及二甲基甲醯胺20.1%等情。有該試驗所97年7月23日藥試\n      化字第09725064419號函在卷可稽（臺灣臺北地方法院檢\n      察署98年度偵字第13777號偵查卷第3至10頁）。而維丰公\n      司取得之農藥許可證，農藥許可證號為農藥進字第02293\n      號，其許可進口之有效成分為益達胺9.6%之農藥原體，亦\n      有該公司之農藥許可證在卷可參（臺灣澎湖地方法院檢察\n      署97年度他字第134號偵查卷第53頁）。依農藥標準規格\n      準則第3條第1項第1款第1目規定，成品農藥以化學方法分\n      析者，其測定值與標稱有效成分之容許差如下：標稱有效\n      成分在1.0%至10%，容許差為正負15%。準此，維丰公司許\n      可進口益達胺有效成分9.6%之農藥，其容許差為8.16%至\n      11.5%之間，故扣案之系爭農藥，其檢測值為9.67%，其與\n      經核准之益達胺9.6%相較，未逾法定之容許誤差，且其所\n      含有效成分名稱亦與核准許可進口證內容相符，自非屬偽\n      農藥。\n    2.扣案之系爭農藥其有效成分為益達胺9.67%，其他成分為\n      甲醇6.43%及二甲基甲醯胺20.1%，屬有效成分含量以外之\n      品質與標準規格不符者，係農藥管理法第8條第3款所稱之\n      劣農藥。是系爭農業並非偽農藥，公訴人指稱被告係加工\n      偽農藥，亦有未合。揆諸前開說明，製造、加工、分裝或\n      輸入劣農藥，並非應受刑事處罰之行為，僅屬科以行政罰\n      鍰之行為。\n    3.按農藥標示之使用或變更，應先經中央主管機關核准。標\n      示變更後，原標示應於6個月內更換之。前項農藥標示所\n      用文字、應記載事項、警告與注意標誌樣式及應遵行事項\n      之辦法，由中央主管機關定之。違反同法第14條之規定，\n      處新臺幣2萬元以上20萬元以下罰鍰。農藥管理法第14條\n      與第52條第2款分別定有明文。扣案之系爭農藥經持有農\n      藥許可證之維丰公司合法自新加坡進口後，賣予被告東和\n      公司，並非未經核准之成品農業。且東和公司領有農藥販\n      賣業執照，有臺北市政府農藥販賣業執照在卷可稽（臺灣\n      澎湖地方法院檢察署97年度他字第134號偵查卷第42頁）\n      。職是，被告東和公司雖應胡文芎之要求，而於農藥外貼\n      上英文標籤，惟此僅係違反農藥標示之規定，尚難以修正\n      前農藥管理法第43條加工偽農藥罪行相繩。至於證人劉天\n      成固於原審審理時證稱：認定扣案之產品為偽農藥之原因\n      ，是自外面標示沒有許可字號，亦無核准的公司，即可直\n      接認定屬於偽農藥等語云云（原審卷第102頁背面）。然\n      該證言與農藥管理法之規定不符，其見解自屬有誤，即不\n      足採。\n    4.被告東和公司雖有將自維丰公司進貨購買之「益達胺」農\n      藥，分裝成小瓶零星販售之行為，然該農藥所含之有效成\n      分與原核准者相同，其成分比例亦在容許差內，並非農藥\n      管理法所稱之偽農藥。況修正前農藥管理法第43條僅處罰\n      製造、加工或輸入偽農藥之行為，分裝行為不在處罰之列\n      ，依據罪刑法定主義，自無從對被告以該罪相繩，併予敘\n      明。\n四、綜上所述，公訴人所舉之證據與指出之證明方法，未足使本\n    院形成被告有罪之確信，故被告東和公司、甲○○是否涉有\n    加工偽農藥犯行，猶有合理之懷疑。此外，復查無其他積極\n    證據足資證明被告確有上開犯行。揆諸前揭說明，本案無法\n    證明被告甲○○有加工偽農藥之犯罪，是被告東和公司亦無\n    從依修正農藥管理法第47條規定科以罰金，故應併為無罪之\n    諭知。\n五、原審同此認定，因予諭知被告無罪之判決，經核尚無違誤。\n    公訴人不服提起上訴，指謫原審認定事實與適用法律均有違\n    誤，被告有加工偽農藥犯行。其上訴意旨略以：證人即行政\n    院農業委員會動植物防疫檢疫局科長劉天成於98年5月7日偵\n    查時證稱：益達胺雖為核准登記之農藥成分，然扣案物標示\n    不合規定，且內容物與當初登記內容物不一致，認定為偽農\n    藥等語。復於同年12月1日原審審理時證稱：針對本案扣案\n    產品，自其外觀、標籤顯示，並無中央主管機關之核准字號\n    ，同時扣案產品上顯示之公司名稱，經查未在經核准公司之\n    資料內，且產品標示亦沒有經過中央主管機關核可。內容物\n    經檢驗結果，確認含有農藥有效成分，故認定屬偽農藥等語\n    。參諸本院臺中分院94年度上易字第1020號判決謂：製造、\n    加工或輸入之農藥，應與中央主管機關核發之農藥許可證記\n    載事項完全相符，始得為之，且非經主管機關核准，不得任\n    意變更許可證記載事項。查本件農藥許可證國外原製造工廠\n    欄記載為「AGSIN PTE LTD」，其與被告所販售扣案之農藥\n    標籤上之標示為LIN NUNG Co.Ltd明顯即有不符，足認扣案\n    之系爭農藥確屬農藥管理法所規範之偽農藥，而非劣農藥，\n    ，是原判決將系爭農藥認定為劣農藥，顯有違誤云云。\n六、因被告於本院審理中，否認有公訴人起訴與上訴所稱之犯行\n    。職是，本院自應審究公訴人之上訴有無理由，以認定被告\n    是否涉有上開罪嫌。本院茲探究如後：\n（一）證人即行政院農業委員會動植物防疫檢疫局科長劉天成於\n      98年5月7日偵查時雖證稱：益達胺為核准登記的農藥成分\n      ，因扣案物標示不合規定，而內容物與當初登記內容物不\n      一致，故認定為偽農藥云云。嗣於98年12月1日原審審理\n      時證稱：就系爭農業之外觀而言、標籤未顯示中央主管機\n      關之核准字號，且顯示之公司名稱，亦非經核准之公司，\n      故認定屬偽農藥云云。惟系爭農藥之標籤為被告東和公司\n      分裝成250毫升之小包裝後，再轉賣予胡文芎，並應胡文\n      芎之要求，在系爭農藥張貼英文標籤。且系爭農藥究為被\n      告自行加工，或是自新加坡進口時，即已添加甲醇及二甲\n      基甲醯胺之其他成分，抑是如公訴人所指係進口後，始由\n      東和公司添加，非無疑義。再者，維丰公司許可進口益達\n      胺有效成分9.6%之農藥，其容許差為8.16%至11.5%之間。\n      系爭農藥之檢測值為9.67%，其與經核准之益達胺9.6%相\n      較，未逾法定之容許誤差，有如前述。是系爭農藥是否有\n      經被告自行加工，仍有疑義。況其外標示係應購買人之要\n      求所張貼，非原本之標籤，而其有效成分亦未逾法定之容\n      許誤差。準此，證人劉天成逕以標籤所示與內容物成分不\n      同，即逕認為系爭農藥屬偽農藥，實嫌率斷，即難以證人\n      證詞作為不利於被告之認定。\n（二）96年7月18日修正前、後之農藥管理法，其所規定之「加\n      工」行為，均係指將農藥原體生產為成品農藥之過程。系\n      爭農藥為維丰公司自國外新加坡進口200公升之大桶裝後\n      ，直接販售予被告東和公司，再由被告東和公司分裝成小\n      包裝對外販售，有如前述。足認被告購買系爭農藥時，其\n      為農藥管理法第5條第2款之成品農藥，並非同條第3款之\n      農藥原體。退步言，縱使被告事後確有添加甲醇及二甲基\n      甲醯胺等溶劑成分之行為，亦不該當於修正前、後之農藥\n      管理法所謂之「加工」行為，自亦難構成修正前農藥管理\n      法第43條第1項之罪。\n（三）本院臺中分院94年度上易字第1020號判決事實雖謂：被告\n      在億昌農藥行，除接收其父親所遺留之來源不明之偽農藥\n      外，並自不詳中年男子處取得數量不詳之偽農藥，且未經\n      核准擅自將合法之農藥更改外包裝而予以加工成偽農藥，\n      再連續販賣偽農藥予不特定之人嫌等情。有判決書在卷為\n      憑。惟扣案系爭農藥經持有農藥許可證之維丰公司合法自\n      新加坡進口後，賣予被告東和公司，並非係未經核准之產\n      品，且東和公司亦領有農藥販賣業執照，可合法販賣農業\n      ，是本案事實與該判決事實不相同，自難比附援引，而為\n      不利被告之佐證。公訴人上訴意旨，仍執陳詞，指摘原判\n      決不當，為無理由，應予駁回。\n據上論斷，應依刑事訴訟法第368條，判決如主文。\n本案經檢察官吳茂松到庭執行職務。"
  },
  "characters": {
    "judges": [
      "高明哲",
      "劉秉鑫",
      "林洲富"
    ],
    "prosecutors": [
      "吳茂松"
    ],
    "lawyers": [

    ],
    "clerks": [
      "楊秋鈴"
    ],
    "plaintiffs": [

    ],
    "defendants": [
      "東和化學企業股份有限公司",
      "兼代表人    甲○○",
      "共      同"
    ],
    "prosecutor_office": [

    ],
    "creditors": [

    ],
    "debtors": [

    ],
    "judicial_associate_officer": [

    ]
  },
  "adjudged_at": "2010-05-12",
  "created_at": "2016-01-05 11:52:48",
  "updated_at": "2016-01-05 11:52:48"
}