{
  "identify": "TPH-99-聲-1265-20100512-1",
  "court": {
    "name": "臺灣高等法院",
    "code": "TPH"
  },
  "division": {
    "name": "刑事",
    "code": "M"
  },
  "year": 99,
  "word": "聲",
  "number": "1265",
  "jcheck": "1",
  "reason": "保護管束",
  "content": "臺灣高等法院刑事裁定                  99年度聲字第1265號\n聲  請  人  臺灣高等法院檢察署檢察官\n受  刑  人  甲○○\n上列受刑人因竊盜案件假釋出獄，聲請人聲請付保護管束（99年\n度執聲付字第338 號），本院裁定如下\n    主  文\n甲○○假釋中付保護管束。\n    理  由\n一、聲請意旨略以：受刑人甲○○因竊盜案件，經本院97年度上\n    易字第38號判決有期徒刑3 年6 月。受刑人於97年8 月28日\n    送監執行，嗣經法務部於99年5 月3 日核准假釋。依刑法第\n    93 條 第2 項規定，假釋出獄者，於假釋中應付保護管束。\n    爰依刑事訴訟法第481 條第1 項規定聲請裁定等語。\n二、本院審核法務部矯正司99年5 月3 日法矯司字第0990905867\n    號函及所附「假釋出獄人交付保護管束名冊」，認聲請人之\n    聲請為正當，應予准許。\n據上論斷，應依刑事訴訟法第481條第1項，刑法第96條但書、第\n93條第2項，裁定如主文。\n中    華    民    國    99    年    5     月    12    日\n                  刑事第九庭審判長法  官  陳貽男\n                                  法  官  楊炳禎\n                                  法  官  周盈文\n以上正本證明與原本無異。\n不得抗告。\n                                  書記官  張郁琳\n中    華    民    國    99    年    5     月    12    日",
  "structure": {
    "main": "甲○○假釋中付保護管束。",
    "reason": "一、聲請意旨略以：受刑人甲○○因竊盜案件，經本院97年度上\n    易字第38號判決有期徒刑3 年6 月。受刑人於97年8 月28日\n    送監執行，嗣經法務部於99年5 月3 日核准假釋。依刑法第\n    93 條 第2 項規定，假釋出獄者，於假釋中應付保護管束。\n    爰依刑事訴訟法第481 條第1 項規定聲請裁定等語。\n二、本院審核法務部矯正司99年5 月3 日法矯司字第0990905867\n    號函及所附「假釋出獄人交付保護管束名冊」，認聲請人之\n    聲請為正當，應予准許。\n據上論斷，應依刑事訴訟法第481條第1項，刑法第96條但書、第\n93條第2項，裁定如主文。"
  },
  "characters": {
    "judges": [
      "陳貽男",
      "楊炳禎",
      "周盈文"
    ],
    "prosecutors": [

    ],
    "lawyers": [

    ],
    "clerks": [
      "張郁琳"
    ],
    "plaintiffs": [

    ],
    "defendants": [

    ],
    "prosecutor_office": [
      "臺灣高等法院檢察署檢察官"
    ],
    "creditors": [

    ],
    "debtors": [

    ],
    "judicial_associate_officer": [

    ]
  },
  "adjudged_at": "2010-05-12",
  "created_at": "2016-01-05 11:53:31",
  "updated_at": "2016-01-05 11:53:31"
}