{
  "identify": "TPH-99-聲-29-20100105-1",
  "court": {
    "name": "臺灣高等法院",
    "code": "TPH"
  },
  "division": {
    "name": "刑事",
    "code": "M"
  },
  "year": 99,
  "word": "聲",
  "number": "29",
  "jcheck": "1",
  "reason": "保護管束",
  "content": "臺灣高等法院刑事裁定                    99年度聲字第29號\n聲  請  人  臺灣高等法院檢察署檢察官\n受  刑  人  甲○○\n上列受刑人因肅清煙毒條例案件，經核准假釋，聲請人聲請付保\n護管束（99年度執聲付字第4號），本院裁定如下：\n    主  文\n甲○○假釋中付保護管束。\n    理  由\n一、聲請意旨略以：受刑人甲○○因肅清煙毒條例案件，經臺灣\n    士林地方法院83年重訴字第19號判處無期徒刑，禠奪公權終\n    身，施用毒品3年4月，持有槍枝1年6月，應執行無期徒刑，\n    禠奪公權終身。上訴經本院84年上重更(一)字第28號上訴駁回\n    ，販賣毒品部分並經最高法院84年台覆字第240 號確定。於\n    民國84年10月13日送監執行，嗣經法務部矯正司於98年12月\n    28日核准假釋在案，依刑法第93條第2 項規定，假釋出獄者\n    ，在假釋中付保護管束，爰依刑事訴訟法第481條第1項規定\n    聲請裁定等語。\n二、經審核法務部矯正司98年12月28日法矯司字第0980907663號\n    函所附假釋出獄人交付保護管束名冊，認聲請人之聲請為正\n    當，應予准許。\n三、依刑事訴訟法第481條第1 項，刑法第96條但書、第93條第2\n    項，裁定如主文。\n中    華    民    國    99    年    1     月    5     日\n                  刑事第二十庭審判長法  官  楊貴雄\n                                    法  官  許必奇\n                                    法  官  周明鴻\n以上正本證明與原本無異。\n如不服本裁定，應於收受送達後五日內向本院提出抗告狀。\n                                    書記官  郭彥琪\n中    華    民    國    99    年    1     月    6     日\n",
  "structure": {
    "main": "甲○○假釋中付保護管束。",
    "reason": "一、聲請意旨略以：受刑人甲○○因肅清煙毒條例案件，經臺灣\n    士林地方法院83年重訴字第19號判處無期徒刑，禠奪公權終\n    身，施用毒品3年4月，持有槍枝1年6月，應執行無期徒刑，\n    禠奪公權終身。上訴經本院84年上重更(一)字第28號上訴駁回\n    ，販賣毒品部分並經最高法院84年台覆字第240 號確定。於\n    民國84年10月13日送監執行，嗣經法務部矯正司於98年12月\n    28日核准假釋在案，依刑法第93條第2 項規定，假釋出獄者\n    ，在假釋中付保護管束，爰依刑事訴訟法第481條第1項規定\n    聲請裁定等語。\n二、經審核法務部矯正司98年12月28日法矯司字第0980907663號\n    函所附假釋出獄人交付保護管束名冊，認聲請人之聲請為正\n    當，應予准許。\n三、依刑事訴訟法第481條第1 項，刑法第96條但書、第93條第2\n    項，裁定如主文。"
  },
  "characters": {
    "judges": [
      "楊貴雄",
      "許必奇",
      "周明鴻"
    ],
    "prosecutors": [

    ],
    "lawyers": [

    ],
    "clerks": [
      "郭彥琪"
    ],
    "plaintiffs": [

    ],
    "defendants": [

    ],
    "prosecutor_office": [
      "臺灣高等法院檢察署檢察官"
    ],
    "creditors": [

    ],
    "debtors": [

    ],
    "judicial_associate_officer": [

    ]
  },
  "adjudged_at": "2010-01-05",
  "created_at": "2016-01-05 15:01:00",
  "updated_at": "2016-01-05 15:01:00"
}