{
  "identify": "TTD-98-司執消債更-37-20100101",
  "court": {
    "name": "臺灣臺東地方法院",
    "code": "TTD"
  },
  "division": {
    "name": "民事",
    "code": "V"
  },
  "year": 98,
  "word": "司執消債更",
  "number": "37",
  "jcheck": "",
  "reason": "更生事件",
  "content": "臺灣臺東地方法院民事裁定        98年度司執消債更字第37號\n債  務  人  陳斐韡\n即  聲請人\n代  理  人  廖頌熙律師\n債  權  人  國泰世華商業銀行股份有限公司\n法定代理人  汪國華\n訴訟代理人  馮佳慧\n債  權  人  玉山商業銀行股份有限公司\n法定代理人  黃永仁\n訴訟代理人  林玉惠\n債  權  人  大眾商業銀行股份有限公司\n法定代理人  陳建平\n訴訟代理人  陳眉秀\n上列當事人聲請消費者債務清理事件，本院裁定如下：\n    主  文\n債務人所提如附表一所示之更生方案應予認可。\n債務人未依更生條件全部履行完畢前，其生活程度應受如附表二\n內容之限制。\n    理  由\n一、按債務人有薪資、執行業務所得或其他固定收入，法院認更\n    生方案之條件公允者，得不經債權人會議可決，逕依債務人\n    之聲請或依職權以裁定認可更生方案；法院為認可之裁定時\n    ，因更生方案履行之必要，對於債務人在未依更生條件全部\n    履行完畢前之生活程度，得為相當之限制，消費者債務清理\n    條例第64條第1項、第62條第2項分別定有明文。次按內政部\n    民國98年所公佈台灣省每人每月最低生活支出為新臺幣（下\n    同）9,829元（其中包含食、衣、住、行之支出）。\n二、經查：\n  （一）本件債務人聲請更生，前經本院於98年6月19日以98年\n        消債更字第13號裁定開始更生程序在案，有上開裁定在\n        卷可參；又債務人每月確有薪資、各項補助之收入10,0\n        00元等情，亦有第三人京富商店員工職務證明書（詳卷\n        51頁，每月約10,000元）在卷可堪認定。\n  （二）債務人於98年8月21日陳報更生方案，內容略為：每月\n        償還新台幣3,000元整，分6年清償，清償總額216,000\n        元，清償成數約為百分之40.9。另於每月15日電匯予各\n        債權人。\n  （三）又債務人陳報與其配偶共同扶養3名未成年子女（即陳\n        貞聿、陳品佑、陳彥亨）有戶籍謄本在卷（詳消債卷\n        52頁）可認屬實，惟債務人自陳（詳卷50頁），因其每\n        月於京富商店打零工，收入不甚豐稔，為展現還款誠意\n        ，故未將子女扶養費列入更生方案中，未成年子女交由\n        其配偶扶養，僅列計個人每月生活費約7,000元。\n  （四）依內政部98年所公佈之臺灣省每人每月最低生活標準，\n        債務人每月可支出之生活費應以9,829元限度內為宜。\n        而以債務人更生方案每月收入10,000元，扣除每月償還\n        3,000元後，僅保留7,000元觀之，債務人每月必要支出\n        顯已低於上述之標準，所提更生方案應屬合理。\n三、綜上所述，債務人所提如附表一所示之更生方案，其條件核\n    屬公允、適當、可行，每月生活必要支出（詳卷50頁）亦無\n    浮報、浪費之情事，且無同條例第63條所定不應認可之消極\n    事由存在，故不經債權人會議可決，予以認可該更生方案，\n    另並依上開規定，就債務人在未依更生條件全部履行完畢前\n    之生活程度，裁定如附表二相當之限制，爰裁定如主文所示\n    。\n中    華    民    國    99    年    1     月    1     日\n              民事執行處    司法事務官   李忠憲\n上為正本係照原本作成。\n如不服本裁定，應於裁定送達後10日內，以書狀向本院司法事務\n官提出異議。\n中    華    民    國    99    年    1     月    1     日\n附表一：更生方案\n┌───────────────────────────────────┐\n│一、更生方案內容                                                      │\n├───────────────────────────────────┤\n│1.每期清償總金額：新台幣3,000元，由各債權人按債權比例分配清償，其明細 │\n│  如下述之分配表。                                                    │\n│2.清償期間及方法：分6年共72期，自認可更生方案裁定確定之翌月起，以每月 │\n│  為一期，於每月15日前（遇假日則順延至下個工作日），將每期應繳金額以臨│\n│  櫃繳款或匯款方式分別匯入各債權人指定匯款帳號，匯款手續費由債務人負擔│\n│  。債務人應自行向各債權人索取指定之匯款帳號，並按月匯入。            │\n│3.無擔保債務總金額：新台幣526,928元                                   │\n│4.無擔保債務滿期清償總金額：新台幣216,000元                           │\n│5.無擔保債務清償比例：約40.9%                                         │\n│6.備註：無                                                            │\n│                                                                      │\n├───────────────────────────────────┤\n│二、更生清償分配表                                                    │\n├──┬─────────┬──────┬─────┬─────────┤\n│編號│   債  權  人     │ 債權金額   │ 債權比例 │ 每期可分配之金額 │\n│    │                  │            │（百分比）│（單位：新台幣元）│\n├──┼─────────┼──────┼─────┼─────────┤\n│ 1  │玉山商業銀行股份有│119,408     │22.66     │680               │\n│    │限公司            │            │          │                  │\n├──┼─────────┼──────┼─────┼─────────┤\n│ 2  │國泰世華商業銀行股│325,166     │61.71     │1,851             │\n│    │份有限公司        │            │          │                  │\n├──┼─────────┼──────┼─────┼─────────┤\n│ 3  │大眾商業銀行股份有│82,354      │15.63     │469               │\n│    │限公司            │            │          │                  │\n├──┼─────────┼──────┼─────┼─────────┤\n│   合            計     │526,928     │  100%    │3,000             │\n├────────────┴──────┴─────┴─────────┤\n│                                                                      │\n└───────────────────────────────────┘\n附表二：更生債務人之生活程度限制\n┌───────────────────────────────────┐\n│准許更生之債務人，未依更生條件完全履行完畢前，應受下列之生活程度限制：│\n├───────────────────────────────────┤\n│01、不得購買精品服裝、飾品、及非生活所必須之電子產品 (例如電玩遊樂主機│\n│    ) 。                                                              │\n├───────────────────────────────────┤\n│02、不得購置不動產、高價動產及非生活所必須之動產。                    │\n├───────────────────────────────────┤\n│03、不得搭乘計程車、遊輪、高鐵及航空器，但因公務所需且由公費支付者，不│\n│    在此限。                                                          │\n├───────────────────────────────────┤\n│04、不得出入特種營業場所、電子遊藝場所、酒吧、夜店、舞廳、卡拉OK、KTV │\n│    等其他娛樂場所。                                                  │\n├───────────────────────────────────┤\n│05、不得投資金融商品(例如股票、基金、期貨等)。                        │\n│                                                                      │\n├───────────────────────────────────┤\n│06、不得從事逾越通常生活程度之贈與、餽贈禮金不得超過新台幣1,000元。   │\n│                                                                      │\n│                                                                      │\n├───────────────────────────────────┤\n│07、不得從事美容醫療之消費行為。                                      │\n│                                                                      │\n├───────────────────────────────────┤\n│08、不得從事國外遊學或出國旅遊等消費行為、國內旅遊每趟行程不得超過新台│\n│    幣3,000元。                                                       │\n├───────────────────────────────────┤\n│09、每月應遵守支出限制 (每月薪資扣除勞健保及履行更生方案之金額後，不得│\n│    逾越新台幣7,000元。                                               │\n│                                                                      │\n├───────────────────────────────────┤\n│10、不得參與賭博、六合彩等投機行為；且不得有金錢借貸之行為。          │\n│                                                                      │\n└───────────────────────────────────┘",
  "structure": {
    "main": "債務人所提如附表一所示之更生方案應予認可。\n債務人未依更生條件全部履行完畢前，其生活程度應受如附表二\n內容之限制。",
    "reason": "一、按債務人有薪資、執行業務所得或其他固定收入，法院認更\n    生方案之條件公允者，得不經債權人會議可決，逕依債務人\n    之聲請或依職權以裁定認可更生方案；法院為認可之裁定時\n    ，因更生方案履行之必要，對於債務人在未依更生條件全部\n    履行完畢前之生活程度，得為相當之限制，消費者債務清理\n    條例第64條第1項、第62條第2項分別定有明文。次按內政部\n    民國98年所公佈台灣省每人每月最低生活支出為新臺幣（下\n    同）9,829元（其中包含食、衣、住、行之支出）。\n二、經查：\n  （一）本件債務人聲請更生，前經本院於98年6月19日以98年\n        消債更字第13號裁定開始更生程序在案，有上開裁定在\n        卷可參；又債務人每月確有薪資、各項補助之收入10,0\n        00元等情，亦有第三人京富商店員工職務證明書（詳卷\n        51頁，每月約10,000元）在卷可堪認定。\n  （二）債務人於98年8月21日陳報更生方案，內容略為：每月\n        償還新台幣3,000元整，分6年清償，清償總額216,000\n        元，清償成數約為百分之40.9。另於每月15日電匯予各\n        債權人。\n  （三）又債務人陳報與其配偶共同扶養3名未成年子女（即陳\n        貞聿、陳品佑、陳彥亨）有戶籍謄本在卷（詳消債卷\n        52頁）可認屬實，惟債務人自陳（詳卷50頁），因其每\n        月於京富商店打零工，收入不甚豐稔，為展現還款誠意\n        ，故未將子女扶養費列入更生方案中，未成年子女交由\n        其配偶扶養，僅列計個人每月生活費約7,000元。\n  （四）依內政部98年所公佈之臺灣省每人每月最低生活標準，\n        債務人每月可支出之生活費應以9,829元限度內為宜。\n        而以債務人更生方案每月收入10,000元，扣除每月償還\n        3,000元後，僅保留7,000元觀之，債務人每月必要支出\n        顯已低於上述之標準，所提更生方案應屬合理。\n三、綜上所述，債務人所提如附表一所示之更生方案，其條件核\n    屬公允、適當、可行，每月生活必要支出（詳卷50頁）亦無\n    浮報、浪費之情事，且無同條例第63條所定不應認可之消極\n    事由存在，故不經債權人會議可決，予以認可該更生方案，\n    另並依上開規定，就債務人在未依更生條件全部履行完畢前\n    之生活程度，裁定如附表二相當之限制，爰裁定如主文所示\n    。"
  },
  "characters": {
    "judges": [

    ],
    "prosecutors": [

    ],
    "lawyers": [
      "廖頌熙"
    ],
    "clerks": [

    ],
    "plaintiffs": [

    ],
    "defendants": [

    ],
    "prosecutor_office": [

    ],
    "creditors": [
      "國泰世華商業銀行股份有限公司",
      "玉山商業銀行股份有限公司",
      "大眾商業銀行股份有限公司"
    ],
    "debtors": [
      "陳斐韡"
    ],
    "judicial_associate_officer": [
      "李忠憲"
    ]
  },
  "adjudged_at": "2010-01-01",
  "created_at": "2016-01-05 14:26:27",
  "updated_at": "2016-01-05 14:26:27"
}