{
  "identify": "TYD-99-交易-121-20100512-1",
  "court": {
    "name": "臺灣桃園地方法院",
    "code": "TYD"
  },
  "division": {
    "name": "刑事",
    "code": "M"
  },
  "year": 99,
  "word": "交易",
  "number": "121",
  "jcheck": "1",
  "reason": "過失傷害",
  "content": "臺灣桃園地方法院刑事判決             99年度交易字第121號\n公  訴  人  臺灣桃園地方法院檢察署檢察官\n被      告  甲○○\n上列被告因過失傷害等案件，經檢察官聲請以簡易判決處刑（99\n年度偵字第285 號），就被訴過失傷害部分，本院認不得以簡易\n判決處刑，改依通常程序審理，判決如下：\n    主  文\n本件公訴不受理。\n    理  由\n一、按告訴乃論之罪，告訴人於第一審辯論終結前得撤回其告訴\n    ，又告訴經撤回者，法院應諭知不受理之判決，刑事訴訟法\n    第238 條第1 項、第303 條第3 款定有明文。\n二、公訴意旨如聲請簡易判決處刑書所載（簡易判決處刑之聲請\n    與提起公訴有同一之效力，聲請簡易判決處刑書詳如附件）\n    。\n三、查本件告訴人乙○○告訴被告甲○○過失傷害案件，公訴意\n    旨認係觸犯刑法第284 條第1 項前段之罪，依同法第287 條\n    前段之規定，須告訴乃論。茲據告訴人具狀撤回告訴，因公\n    訴意旨認被告此部分之犯行，與其被訴刑法第185 條之3 公\n    共危險罪部分，犯意各別，行為互殊，應予分論併罰，爰依\n    照首開說明，不經言詞辯論，逕就被告被訴過失傷害部分為\n    不受理之諭知。\n四、至本件被告被訴公共危險犯嫌部分，由本院另依簡易程序審\n    結，附此敘明。\n據上論斷，應依刑事訴訟法第452 條、第303 條第3 款、第307\n條，判決如主文。\n中    華    民    國    99    年    5     月    12    日\n                  刑事第二庭  審判長  法  官  徐培元\n                                      法  官  柯姿佐\n                                      法  官  陳德池\n以上正本證明與原本無異。\n如不服本判決應於收受判決後10日內向本院提出上訴書狀，並應\n敘述具體理由。其未敘述上訴理由者，應於上訴期間屆滿後20日\n內向本院補提理由書( 均須按他造當事人之人數附繕本) 「切勿\n逕送上級法院」。\n                                      書記官  謝雅茹\n中    華    民    國    99    年    5     月    14    日\n附件：臺灣桃園地方法院檢察署檢察官99年度偵字第285 號聲請\n      簡易判決處刑書1 份。",
  "structure": {
    "main": "本件公訴不受理。",
    "reason": "一、按告訴乃論之罪，告訴人於第一審辯論終結前得撤回其告訴\n    ，又告訴經撤回者，法院應諭知不受理之判決，刑事訴訟法\n    第238 條第1 項、第303 條第3 款定有明文。\n二、公訴意旨如聲請簡易判決處刑書所載（簡易判決處刑之聲請\n    與提起公訴有同一之效力，聲請簡易判決處刑書詳如附件）\n    。\n三、查本件告訴人乙○○告訴被告甲○○過失傷害案件，公訴意\n    旨認係觸犯刑法第284 條第1 項前段之罪，依同法第287 條\n    前段之規定，須告訴乃論。茲據告訴人具狀撤回告訴，因公\n    訴意旨認被告此部分之犯行，與其被訴刑法第185 條之3 公\n    共危險罪部分，犯意各別，行為互殊，應予分論併罰，爰依\n    照首開說明，不經言詞辯論，逕就被告被訴過失傷害部分為\n    不受理之諭知。\n四、至本件被告被訴公共危險犯嫌部分，由本院另依簡易程序審\n    結，附此敘明。\n據上論斷，應依刑事訴訟法第452 條、第303 條第3 款、第307\n條，判決如主文。"
  },
  "characters": {
    "judges": [
      "徐培元",
      "柯姿佐",
      "陳德池"
    ],
    "prosecutors": [

    ],
    "lawyers": [

    ],
    "clerks": [
      "謝雅茹"
    ],
    "plaintiffs": [

    ],
    "defendants": [
      "甲○○"
    ],
    "prosecutor_office": [
      "臺灣桃園地方法院檢察署檢察官"
    ],
    "creditors": [

    ],
    "debtors": [

    ],
    "judicial_associate_officer": [

    ]
  },
  "adjudged_at": "2010-05-12",
  "created_at": "2016-01-05 12:36:25",
  "updated_at": "2016-01-05 12:36:25"
}