{
  "identify": "TYD-99-壢交簡-1016-20100512-1",
  "court": {
    "name": "臺灣桃園地方法院",
    "code": "TYD"
  },
  "division": {
    "name": "刑事",
    "code": "M"
  },
  "year": 99,
  "word": "壢交簡",
  "number": "1016",
  "jcheck": "1",
  "reason": "過失傷害",
  "content": "臺灣桃園地方法院刑事簡易判決      99年度壢交簡字第1016號\n聲  請  人  臺灣桃園地方法院檢察署檢察官\n被      告  甲○○\n上列被告因過失傷害案件，經檢察官聲請以簡易判決處刑（99年\n度偵字第2488號），本院判決如下：\n    主      文\n甲○○因過失傷害人，處拘役肆拾日，如易科罰金，以新臺幣壹\n仟元折算壹日。\n    事實及理由\n一、本件犯罪事實及證據，併所犯法條，均引用臺灣桃園地方法\n    院檢察署檢察官聲請簡易判決處刑書之記載（如附件），並\n    補充：核被告甲○○所為，係犯刑法第284 條第1 項前段之\n    過失傷害罪。又被告於車禍發生後，其過失傷害犯行未為有\n    追訴權限機關公務員發覺前，即親自報警，並向到場處理車\n    禍事故之警員表示其為肇事之駕駛人，自首而受裁判之事實\n    ，有桃園縣政府警察局道路交通事故肇事人自首情形紀錄表\n    附卷（見偵查卷第13頁）可稽，乃依刑法第62條前段規定減\n    輕其刑。爰審酌被告之過失程度非輕、告訴人因此所受之骨\n    折傷勢、被告迄今尚未與告訴人達成和解、智識程度、素行\n    、犯罪後態度等一切情狀，量處如主文所示之刑，並諭知易\n    科罰金之折算標準，以資懲儆。\n二、依刑事訴訟法第449 條第1 項前段、第3 項、第454 條第2\n    項，刑法第284 條第1 項前段、第62條前段、第41條第1 項\n    前段，刑法施行法第1 條之1 第1 項、第2 項前段，逕以簡\n    易判決處如主文所示之刑。\n三、如不服本判決，應於判決送達後10日內，向本院提出上訴狀\n    （應附繕本），上訴於本院合議庭。\n中    華    民    國    99    年    5     月    12    日\n                  交通法庭    法  官  陳德池\n以上正本證明與原本無異。\n如不服本判決，應於判決送達後10日內向本院提出上訴狀（應附\n繕本）。\n                              書記官  謝雅茹\n中    華    民    國    99    年    5     月    14    日\n附錄本件論罪科刑法條全文：\n中華民國刑法第284 條第1 項\n因過失傷害人者，處6 月以下有期徒刑、拘役或5 百元以下罰金\n，致重傷者，處1 年以下有期徒刑、拘役或5 百元以下罰金。\n附件：臺灣桃園地方法院檢察署檢察官99年度偵字第2488號聲請\n      簡易判決處刑書1 份。",
  "structure": {
    "main": "甲○○因過失傷害人，處拘役肆拾日，如易科罰金，以新臺幣壹\n仟元折算壹日。",
    "fact": "一、本件犯罪事實及證據，併所犯法條，均引用臺灣桃園地方法\n    院檢察署檢察官聲請簡易判決處刑書之記載（如附件），並\n    補充：核被告甲○○所為，係犯刑法第284 條第1 項前段之\n    過失傷害罪。又被告於車禍發生後，其過失傷害犯行未為有\n    追訴權限機關公務員發覺前，即親自報警，並向到場處理車\n    禍事故之警員表示其為肇事之駕駛人，自首而受裁判之事實\n    ，有桃園縣政府警察局道路交通事故肇事人自首情形紀錄表\n    附卷（見偵查卷第13頁）可稽，乃依刑法第62條前段規定減\n    輕其刑。爰審酌被告之過失程度非輕、告訴人因此所受之骨\n    折傷勢、被告迄今尚未與告訴人達成和解、智識程度、素行\n    、犯罪後態度等一切情狀，量處如主文所示之刑，並諭知易\n    科罰金之折算標準，以資懲儆。\n二、依刑事訴訟法第449 條第1 項前段、第3 項、第454 條第2\n    項，刑法第284 條第1 項前段、第62條前段、第41條第1 項\n    前段，刑法施行法第1 條之1 第1 項、第2 項前段，逕以簡\n    易判決處如主文所示之刑。\n三、如不服本判決，應於判決送達後10日內，向本院提出上訴狀\n    （應附繕本），上訴於本院合議庭。",
    "reason": "一、本件犯罪事實及證據，併所犯法條，均引用臺灣桃園地方法\n    院檢察署檢察官聲請簡易判決處刑書之記載（如附件），並\n    補充：核被告甲○○所為，係犯刑法第284 條第1 項前段之\n    過失傷害罪。又被告於車禍發生後，其過失傷害犯行未為有\n    追訴權限機關公務員發覺前，即親自報警，並向到場處理車\n    禍事故之警員表示其為肇事之駕駛人，自首而受裁判之事實\n    ，有桃園縣政府警察局道路交通事故肇事人自首情形紀錄表\n    附卷（見偵查卷第13頁）可稽，乃依刑法第62條前段規定減\n    輕其刑。爰審酌被告之過失程度非輕、告訴人因此所受之骨\n    折傷勢、被告迄今尚未與告訴人達成和解、智識程度、素行\n    、犯罪後態度等一切情狀，量處如主文所示之刑，並諭知易\n    科罰金之折算標準，以資懲儆。\n二、依刑事訴訟法第449 條第1 項前段、第3 項、第454 條第2\n    項，刑法第284 條第1 項前段、第62條前段、第41條第1 項\n    前段，刑法施行法第1 條之1 第1 項、第2 項前段，逕以簡\n    易判決處如主文所示之刑。\n三、如不服本判決，應於判決送達後10日內，向本院提出上訴狀\n    （應附繕本），上訴於本院合議庭。"
  },
  "characters": {
    "judges": [
      "陳德池"
    ],
    "prosecutors": [

    ],
    "lawyers": [

    ],
    "clerks": [
      "謝雅茹"
    ],
    "plaintiffs": [

    ],
    "defendants": [
      "甲○○"
    ],
    "prosecutor_office": [
      "臺灣桃園地方法院檢察署檢察官"
    ],
    "creditors": [

    ],
    "debtors": [

    ],
    "judicial_associate_officer": [

    ]
  },
  "adjudged_at": "2010-05-12",
  "created_at": "2016-01-05 12:36:59",
  "updated_at": "2016-01-05 12:36:59"
}