{
  "identify": "TYD-99-壢簡-879-20100512-1",
  "court": {
    "name": "臺灣桃園地方法院",
    "code": "TYD"
  },
  "division": {
    "name": "刑事",
    "code": "M"
  },
  "year": 99,
  "word": "壢簡",
  "number": "879",
  "jcheck": "1",
  "reason": "傷害",
  "content": "臺灣桃園地方法院刑事簡易判決         99年度壢簡字第879號\n聲  請  人  臺灣桃園地方法院檢察署檢察官\n被      告  甲○○\n上列被告因傷害案件，經檢察官聲請以簡易判決處刑（99年度偵\n字第705 號），本院判決如下：\n    主      文\n甲○○傷害人之身體，處罰金新臺幣捌仟元，如易服勞役，以新\n臺幣壹仟元折算壹日。\n    事實及理由\n一、本件犯罪事實及證據，併所犯法條，均引用臺灣桃園地方法\n    院檢察署檢察官聲請簡易判決處刑書之記載（如附件），並\n    補充：核被告甲○○所為，係犯刑法第277 條第1 項普通傷\n    害罪。爰審酌被告因細故發生爭執即傷害告訴人，實屬不該\n    ，且迄未與告訴人達成和解，並考量告訴人受傷程度非重、\n    被告犯後態度，並其智識程度、品行等一切情狀，量處如主\n    文之刑，並諭知易科罰金之折算標準。\n二、依刑事訴訟法第449 條第1 項前段、第3 項、第454 條第2\n    項，刑法第277 條第1 項、第42條第3 項前段，刑法施行法\n    第1 條之1 第1 項、第2 項前段，逕以簡易判決處刑如主文\n    。\n三、如不服本判決，應於判決送達後10日內，向本院提出上訴狀\n    （應附繕本），上訴於本院合議庭。\n中    華    民    國    99    年    5     月    12    日\n                  刑事第二庭  法  官  陳德池\n以上正本證明與原本無異。\n如不服本判決，應於判決送達後10日內向本院提出上訴狀（應附\n繕本）。\n                              書記官  謝雅茹\n中    華    民    國    99    年    5     月    19    日\n附錄論罪科刑法條全文：\n中華民國刑法第277條\n（普通傷害罪）\n傷害人之身體或健康者，處3 年以下有期徒刑、拘役或1 千元以\n下罰金。\n犯前項之罪因而致人於死者，處無期徒刑或7 年以上有期徒刑；\n致重傷者，處3 年以上10年以下有期徒刑。\n附件：臺灣桃園地方法院檢察署檢察官99年度偵字第705 號聲請\n      簡易判決處刑書1 份。",
  "structure": {
    "main": "甲○○傷害人之身體，處罰金新臺幣捌仟元，如易服勞役，以新\n臺幣壹仟元折算壹日。",
    "fact": "一、本件犯罪事實及證據，併所犯法條，均引用臺灣桃園地方法\n    院檢察署檢察官聲請簡易判決處刑書之記載（如附件），並\n    補充：核被告甲○○所為，係犯刑法第277 條第1 項普通傷\n    害罪。爰審酌被告因細故發生爭執即傷害告訴人，實屬不該\n    ，且迄未與告訴人達成和解，並考量告訴人受傷程度非重、\n    被告犯後態度，並其智識程度、品行等一切情狀，量處如主\n    文之刑，並諭知易科罰金之折算標準。\n二、依刑事訴訟法第449 條第1 項前段、第3 項、第454 條第2\n    項，刑法第277 條第1 項、第42條第3 項前段，刑法施行法\n    第1 條之1 第1 項、第2 項前段，逕以簡易判決處刑如主文\n    。\n三、如不服本判決，應於判決送達後10日內，向本院提出上訴狀\n    （應附繕本），上訴於本院合議庭。",
    "reason": "一、本件犯罪事實及證據，併所犯法條，均引用臺灣桃園地方法\n    院檢察署檢察官聲請簡易判決處刑書之記載（如附件），並\n    補充：核被告甲○○所為，係犯刑法第277 條第1 項普通傷\n    害罪。爰審酌被告因細故發生爭執即傷害告訴人，實屬不該\n    ，且迄未與告訴人達成和解，並考量告訴人受傷程度非重、\n    被告犯後態度，並其智識程度、品行等一切情狀，量處如主\n    文之刑，並諭知易科罰金之折算標準。\n二、依刑事訴訟法第449 條第1 項前段、第3 項、第454 條第2\n    項，刑法第277 條第1 項、第42條第3 項前段，刑法施行法\n    第1 條之1 第1 項、第2 項前段，逕以簡易判決處刑如主文\n    。\n三、如不服本判決，應於判決送達後10日內，向本院提出上訴狀\n    （應附繕本），上訴於本院合議庭。"
  },
  "characters": {
    "judges": [
      "陳德池"
    ],
    "prosecutors": [

    ],
    "lawyers": [

    ],
    "clerks": [
      "謝雅茹"
    ],
    "plaintiffs": [

    ],
    "defendants": [
      "甲○○"
    ],
    "prosecutor_office": [
      "臺灣桃園地方法院檢察署檢察官"
    ],
    "creditors": [

    ],
    "debtors": [

    ],
    "judicial_associate_officer": [

    ]
  },
  "adjudged_at": "2010-05-12",
  "created_at": "2016-01-05 12:38:18",
  "updated_at": "2016-01-05 12:38:18"
}