{
  "identify": "TYD-99-壢簡-964-20100512-1",
  "court": {
    "name": "臺灣桃園地方法院",
    "code": "TYD"
  },
  "division": {
    "name": "刑事",
    "code": "M"
  },
  "year": 99,
  "word": "壢簡",
  "number": "964",
  "jcheck": "1",
  "reason": "竊盜",
  "content": "臺灣桃園地方法院刑事簡易判決         99年度壢簡字第964號\n聲  請  人  臺灣桃園地方法院檢察署檢察官\n被      告  甲○○\n上列被告因竊盜案件，經檢察官聲請以簡易判決處刑（99年度偵\n字第2785號），本院判決如下：\n    主      文\n甲○○竊盜，累犯，處有期徒刑參月，如易科罰金，以新臺幣壹\n仟元折算壹日。\n    事實及理由\n一、本件犯罪事實及證據併所犯法條，均引用臺灣桃園地方法院\n    檢察署檢察官聲請簡易判決處刑書之記載（如附件），並補\n    充及更正：\n  (一)犯罪事實欄前科部分應更正為：甲○○曾於民國92年間，因\n    偽造文書案件，經本院以93年度訴字第124 號判決判處有期\n    徒刑6 月確定；又於94年間，因施用毒品及竊盜案件，分別\n    經本院以94年度壢簡字第1259號判決判處有期徒刑3 月確定\n    、94年度壢簡字第966 號判決判處有期徒刑5 月確定，上開\n    二罪嗣經本院以95年度聲字第524 號裁定應執行有期徒刑7\n    月確定，並與上開所犯之偽造文書罪接續執行，於95年9 月\n    29日縮刑期滿執行完畢。\n  (二)核被告甲○○所為，係犯刑法第320 條第1 項竊盜既遂罪。\n    又被告有如上所示之犯罪前科與執行情形，此有臺灣高等法\n    院被告前案紀錄表存卷可按，其於5 年以內故意再犯本件有\n    期徒刑以上之罪，為累犯，應依刑法第47條第1 項之規定加\n    重其刑。爰審酌被告正值盛年，不思正途營生，竟冀望不勞\n    而獲竊取他人財物，其犯罪之動機實屬可議，暨其生活狀況\n    、犯罪手段、所竊得財物價值等一切情狀，量處如主文所示\n    之刑，並諭知易科罰金之折算標準。\n二、依刑事訴訟法第449 條第1 項前段、第3 項、第454 條第2\n    項，刑法第320 條第1 項、第47條第1 項、第41條第1 項前\n    段，刑法施行法第1 條之1 第1 項、第2 項前段，判決如主\n    文。\n三、如不服本判決，應於判決送達後10日內，向本院提出上訴狀\n    （應附繕本），上訴於本院合議庭。\n中    華    民    國    99    年    5     月    12    日\n                  刑事第二庭    法  官  陳德池\n以上正本證明與原本無異。\n如不服本判決，應於判決送達後10日內向本院提出上訴狀（應附\n繕本）。\n                                書記官  謝雅茹\n中    華    民    國    99    年    5     月    14    日\n附錄論罪科刑法條全文：\n刑法第320 條第1 項\n意圖為自己或第三人不法之所有，而竊取他人之動產者，為竊盜\n罪，處5 年以下有期徒刑、拘役或500 元以下罰金。\n附件：臺灣桃園地方法院檢察署檢察官99年度偵字第2785號聲請\n      簡易判決處刑書1 份。",
  "structure": {
    "main": "甲○○竊盜，累犯，處有期徒刑參月，如易科罰金，以新臺幣壹\n仟元折算壹日。",
    "fact": "一、本件犯罪事實及證據併所犯法條，均引用臺灣桃園地方法院\n    檢察署檢察官聲請簡易判決處刑書之記載（如附件），並補\n    充及更正：\n  (一)犯罪事實欄前科部分應更正為：甲○○曾於民國92年間，因\n    偽造文書案件，經本院以93年度訴字第124 號判決判處有期\n    徒刑6 月確定；又於94年間，因施用毒品及竊盜案件，分別\n    經本院以94年度壢簡字第1259號判決判處有期徒刑3 月確定\n    、94年度壢簡字第966 號判決判處有期徒刑5 月確定，上開\n    二罪嗣經本院以95年度聲字第524 號裁定應執行有期徒刑7\n    月確定，並與上開所犯之偽造文書罪接續執行，於95年9 月\n    29日縮刑期滿執行完畢。\n  (二)核被告甲○○所為，係犯刑法第320 條第1 項竊盜既遂罪。\n    又被告有如上所示之犯罪前科與執行情形，此有臺灣高等法\n    院被告前案紀錄表存卷可按，其於5 年以內故意再犯本件有\n    期徒刑以上之罪，為累犯，應依刑法第47條第1 項之規定加\n    重其刑。爰審酌被告正值盛年，不思正途營生，竟冀望不勞\n    而獲竊取他人財物，其犯罪之動機實屬可議，暨其生活狀況\n    、犯罪手段、所竊得財物價值等一切情狀，量處如主文所示\n    之刑，並諭知易科罰金之折算標準。\n二、依刑事訴訟法第449 條第1 項前段、第3 項、第454 條第2\n    項，刑法第320 條第1 項、第47條第1 項、第41條第1 項前\n    段，刑法施行法第1 條之1 第1 項、第2 項前段，判決如主\n    文。\n三、如不服本判決，應於判決送達後10日內，向本院提出上訴狀\n    （應附繕本），上訴於本院合議庭。",
    "reason": "一、本件犯罪事實及證據併所犯法條，均引用臺灣桃園地方法院\n    檢察署檢察官聲請簡易判決處刑書之記載（如附件），並補\n    充及更正：\n  (一)犯罪事實欄前科部分應更正為：甲○○曾於民國92年間，因\n    偽造文書案件，經本院以93年度訴字第124 號判決判處有期\n    徒刑6 月確定；又於94年間，因施用毒品及竊盜案件，分別\n    經本院以94年度壢簡字第1259號判決判處有期徒刑3 月確定\n    、94年度壢簡字第966 號判決判處有期徒刑5 月確定，上開\n    二罪嗣經本院以95年度聲字第524 號裁定應執行有期徒刑7\n    月確定，並與上開所犯之偽造文書罪接續執行，於95年9 月\n    29日縮刑期滿執行完畢。\n  (二)核被告甲○○所為，係犯刑法第320 條第1 項竊盜既遂罪。\n    又被告有如上所示之犯罪前科與執行情形，此有臺灣高等法\n    院被告前案紀錄表存卷可按，其於5 年以內故意再犯本件有\n    期徒刑以上之罪，為累犯，應依刑法第47條第1 項之規定加\n    重其刑。爰審酌被告正值盛年，不思正途營生，竟冀望不勞\n    而獲竊取他人財物，其犯罪之動機實屬可議，暨其生活狀況\n    、犯罪手段、所竊得財物價值等一切情狀，量處如主文所示\n    之刑，並諭知易科罰金之折算標準。\n二、依刑事訴訟法第449 條第1 項前段、第3 項、第454 條第2\n    項，刑法第320 條第1 項、第47條第1 項、第41條第1 項前\n    段，刑法施行法第1 條之1 第1 項、第2 項前段，判決如主\n    文。\n三、如不服本判決，應於判決送達後10日內，向本院提出上訴狀\n    （應附繕本），上訴於本院合議庭。"
  },
  "characters": {
    "judges": [
      "陳德池"
    ],
    "prosecutors": [

    ],
    "lawyers": [

    ],
    "clerks": [
      "謝雅茹"
    ],
    "plaintiffs": [

    ],
    "defendants": [
      "甲○○"
    ],
    "prosecutor_office": [
      "臺灣桃園地方法院檢察署檢察官"
    ],
    "creditors": [

    ],
    "debtors": [

    ],
    "judicial_associate_officer": [

    ]
  },
  "adjudged_at": "2010-05-12",
  "created_at": "2016-01-05 12:37:38",
  "updated_at": "2016-01-05 12:37:38"
}