{
  "identify": "TYD-99-易-173-20100512-2",
  "court": {
    "name": "臺灣桃園地方法院",
    "code": "TYD"
  },
  "division": {
    "name": "刑事",
    "code": "M"
  },
  "year": 99,
  "word": "易",
  "number": "173",
  "jcheck": "2",
  "reason": "竊盜",
  "content": "臺灣桃園地方法院刑事裁定               99年度易字第173號\n公  訴  人  臺灣桃園地方法院檢察署檢察官\n被      告  乙○○\n具  保  人  甲○○\n上列被告因竊盜案件，本院裁定如下：\n    主  文\n甲○○繳納之保證金新臺幣伍仟元，沒入之。\n    理  由\n一、聲請意旨略以：上列具保人甲○○因被告乙○○涉犯竊盜案\n    件，經依檢察官指定之保證金額新臺幣5,000 元，出具現金\n    保證後，即將被告釋放，茲因該被告逃匿，依刑事訴訟法第\n    118 條之規定，應命具保人繳納指定之保證金並沒入，爰依\n    刑事訴訟法第121 條第1 項規定，聲請沒入具保人繳納之保\n    證金等語。\n二、按具保之被告逃匿者，應命具保人繳納指定之保證金額，並\n    沒入之，不繳納者，強制執行。保證金已繳納者，沒入之，\n    刑事訴訟法第118條第1項定有明文。\n三、經查，被告經本院依其住、居所傳喚、拘提均未到庭，此有\n    本院送達證書、拘票及準備程序筆錄等在卷可稽，嗣經本院\n    依具保人之住所傳喚具保人攜同被告遵期到庭，惟具保人仍\n    未攜同被告到庭，亦有本送達證書及準備程序筆錄等在卷足\n    憑，足見被告業已逃匿，揆諸首揭規定，堪認本件聲請人之\n    聲請，於法要無不合，應予准許。\n四、依刑事訴訟法第118 條、第121條第1項，裁定如主文。\n中    華    民    國    99    年    5     月    12    日\n                刑事第十庭    審判長  法  官  江德民\n                                      法  官  蘇昌澤\n                                      法  官  華奕超\n以上正本證明與原本無異。\n如不服本裁定，應於送達後5 日內，向本院提出抗告狀。\n                                      書記官  常毓生\n中    華    民    國    99    年    5     月    12    日",
  "structure": {
    "main": "甲○○繳納之保證金新臺幣伍仟元，沒入之。",
    "reason": "一、聲請意旨略以：上列具保人甲○○因被告乙○○涉犯竊盜案\n    件，經依檢察官指定之保證金額新臺幣5,000 元，出具現金\n    保證後，即將被告釋放，茲因該被告逃匿，依刑事訴訟法第\n    118 條之規定，應命具保人繳納指定之保證金並沒入，爰依\n    刑事訴訟法第121 條第1 項規定，聲請沒入具保人繳納之保\n    證金等語。\n二、按具保之被告逃匿者，應命具保人繳納指定之保證金額，並\n    沒入之，不繳納者，強制執行。保證金已繳納者，沒入之，\n    刑事訴訟法第118條第1項定有明文。\n三、經查，被告經本院依其住、居所傳喚、拘提均未到庭，此有\n    本院送達證書、拘票及準備程序筆錄等在卷可稽，嗣經本院\n    依具保人之住所傳喚具保人攜同被告遵期到庭，惟具保人仍\n    未攜同被告到庭，亦有本送達證書及準備程序筆錄等在卷足\n    憑，足見被告業已逃匿，揆諸首揭規定，堪認本件聲請人之\n    聲請，於法要無不合，應予准許。\n四、依刑事訴訟法第118 條、第121條第1項，裁定如主文。"
  },
  "characters": {
    "judges": [
      "江德民",
      "蘇昌澤",
      "華奕超"
    ],
    "prosecutors": [

    ],
    "lawyers": [

    ],
    "clerks": [
      "常毓生"
    ],
    "plaintiffs": [

    ],
    "defendants": [
      "乙○○",
      "具  保  人  甲○○"
    ],
    "prosecutor_office": [
      "臺灣桃園地方法院檢察署檢察官"
    ],
    "creditors": [

    ],
    "debtors": [

    ],
    "judicial_associate_officer": [

    ]
  },
  "adjudged_at": "2010-05-12",
  "created_at": "2016-01-05 12:38:41",
  "updated_at": "2016-01-05 12:38:41"
}