{
  "identify": "TYD-99-桃交簡-1237-20100512-2",
  "court": {
    "name": "臺灣桃園地方法院",
    "code": "TYD"
  },
  "division": {
    "name": "刑事",
    "code": "M"
  },
  "year": 99,
  "word": "桃交簡",
  "number": "1237",
  "jcheck": "2",
  "reason": "公共危險",
  "content": "臺灣桃園地方法院刑事裁定          99年度桃交簡字第1237號\n聲  請  人  臺灣桃園地方法院檢察署檢察官\n被      告  甲○○\n上列被告因公共危險案件，本院於中華民國99年4 月23 日所為\n刑事簡易判決之原本及於99年4 月27 日所為刑事簡易判決之正\n本有誤寫，應裁定更正如下：\n    主  文\n原判決之原本及其正本事實及理由欄內關於被告駕駛之重型機車\n車牌號碼：「PJQ-753 」號之記載，均應更正為「PJQ-763 」號\n。\n    理  由\n一、按刑事判決文字，顯係誤寫，而不影響於全案情節與判決之\n    本旨者，參照民事訴訟法第232 條規定，原審法院得以裁定\n    更正之，業經司法院大法官會議釋字第43號解釋在案。又更\n    正裁定，並非法院就事件之爭執重新為裁判，不過將裁判中\n    誤寫、誤算或其他類此顯然之錯誤，加以更正，使裁判中所\n    表示者，與法院本來之意思相符，亦有最高法院79年臺聲字\n    第349 號判例可參。\n二、本件原刑事簡易判決之原本及其正本事實及理由欄內關於被\n    告駕駛之重型機車車牌號碼：「PJQ-753 」號之記載，均應\n    更正為「PJQ-763 」號。\n三、依刑事訴訟法第220 條，裁定如主文。\n中    華    民    國    99    年    5     月    12    日\n                    交通法庭  法  官  黃裕民\n以上正本證明與原本無異。\n如不服本裁定，應於裁定送達後5 日內向本院提出抗告狀。\n                              書記官  劉家蕙\n中    華    民    國    99    年    5     月    19    日",
  "structure": {
    "main": "原判決之原本及其正本事實及理由欄內關於被告駕駛之重型機車\n車牌號碼：「PJQ-753 」號之記載，均應更正為「PJQ-763 」號\n。",
    "reason": "一、按刑事判決文字，顯係誤寫，而不影響於全案情節與判決之\n    本旨者，參照民事訴訟法第232 條規定，原審法院得以裁定\n    更正之，業經司法院大法官會議釋字第43號解釋在案。又更\n    正裁定，並非法院就事件之爭執重新為裁判，不過將裁判中\n    誤寫、誤算或其他類此顯然之錯誤，加以更正，使裁判中所\n    表示者，與法院本來之意思相符，亦有最高法院79年臺聲字\n    第349 號判例可參。\n二、本件原刑事簡易判決之原本及其正本事實及理由欄內關於被\n    告駕駛之重型機車車牌號碼：「PJQ-753 」號之記載，均應\n    更正為「PJQ-763 」號。\n三、依刑事訴訟法第220 條，裁定如主文。"
  },
  "characters": {
    "judges": [
      "黃裕民"
    ],
    "prosecutors": [

    ],
    "lawyers": [

    ],
    "clerks": [
      "劉家蕙"
    ],
    "plaintiffs": [

    ],
    "defendants": [
      "甲○○"
    ],
    "prosecutor_office": [
      "臺灣桃園地方法院檢察署檢察官"
    ],
    "creditors": [

    ],
    "debtors": [

    ],
    "judicial_associate_officer": [

    ]
  },
  "adjudged_at": "2010-05-12",
  "created_at": "2016-01-05 12:37:12",
  "updated_at": "2016-01-05 12:37:12"
}