{
  "identify": "TYD-99-桃簡-999-20100512-1",
  "court": {
    "name": "臺灣桃園地方法院",
    "code": "TYD"
  },
  "division": {
    "name": "刑事",
    "code": "M"
  },
  "year": 99,
  "word": "桃簡",
  "number": "999",
  "jcheck": "1",
  "reason": "詐欺",
  "content": "臺灣桃園地方法院刑事簡易判決         99年度桃簡字第999號\n聲  請  人  臺灣桃園地方法院檢察署檢察官\n被      告  乙○○\n上列被告因詐欺案件，經檢察官聲請以簡易判決處刑（98年度偵\n字第11104 號），本院判決如下：\n    主      文\n乙○○幫助意圖為自己不法之所有，以詐術使人將本人之物交付\n，處拘役肆拾日，如易科罰金，以新臺幣壹仟元折算壹日。\n    事實及理由\n一、本件犯罪事實及證據併所犯法條，均引用臺灣桃園地方法院\n    檢察署檢察官聲請簡易判決處刑書之記載（如附件），並補\n    充及更正：\n  (一)按幫助犯係從屬於正犯而成立，以正犯已經犯罪為要件，故\n    幫助犯並非其幫助行為一經完成，即成立犯罪，必其幫助行\n    為或其影響力持續至正犯實施犯罪始行成立，是本件被告乙\n    ○○之犯罪時間當以正犯之犯罪行為時間（即民國97年12月\n    24日被害人甲○○上網瀏覽拍賣訊息之時間）為準，至為明\n    確。\n  (二)核被告乙○○所為，係犯刑法第339 條第1 項之詐欺取財罪\n    。被告對詐欺正犯提供帳戶資以助力，但並未參與詐欺犯罪\n    行為之實行，應屬幫助他人實行犯罪行為，為幫助犯，乃依\n    刑法第30條第2 項之規定減輕其刑。爰審酌被告輕易提供行\n    動電話門號SIM 卡供他人從事詐欺犯罪使用，非但增加被害\n    人尋求救濟之困難，造成社會人心不安，亦助長詐騙犯罪者\n    之氣焰，使詐欺犯罪者得以順利詐得財物，並逃避追緝，危\n    害財產交易安全，犯罪情節非輕，暨其行為手段、素行、犯\n    罪後態度等一切情狀，量處如主文所示之刑，並諭知易科罰\n    金之折算標準。\n二、據上論斷，應依刑事訴訟法第449 條第1 項前段、第3 項、\n    第454 條第2 項，刑法第339 條第1 項、第30條第1 項前段\n    、第2 項、第41條第1 項前段，刑法施行法第1 條之1 第1\n    項、第2 項前段，逕以簡易判決處刑如主文。\n三、如不服本判決，應於判決送達後10日內，向本院提出上訴狀\n    （應附繕本），上訴於本院合議庭。\n中    華    民    國    99    年    5     月    12    日\n                  刑事第二庭  法  官  陳德池\n以上正本證明與原本無異。\n如不服本判決，應於判決送達後10日內向本院提出上訴狀（應附\n繕本）。\n                              書記官  謝雅茹\n中    華    民    國    99    年    5     月    14    日\n附錄論罪科刑法條全文：\n刑法第339條第1 項(普通詐欺罪)：\n意圖為自己或第三人不法之所有，以詐術使人將本人或第三人之\n物交付者，處五年以下有期徒刑、拘役或科或併科一千元以下罰\n金。\n附件：臺灣桃園地方法院檢察署檢察官98年度偵字第11104 號聲\n      請簡易判決處刑書1 份。",
  "structure": {
    "main": "乙○○幫助意圖為自己不法之所有，以詐術使人將本人之物交付\n，處拘役肆拾日，如易科罰金，以新臺幣壹仟元折算壹日。",
    "fact": "一、本件犯罪事實及證據併所犯法條，均引用臺灣桃園地方法院\n    檢察署檢察官聲請簡易判決處刑書之記載（如附件），並補\n    充及更正：\n  (一)按幫助犯係從屬於正犯而成立，以正犯已經犯罪為要件，故\n    幫助犯並非其幫助行為一經完成，即成立犯罪，必其幫助行\n    為或其影響力持續至正犯實施犯罪始行成立，是本件被告乙\n    ○○之犯罪時間當以正犯之犯罪行為時間（即民國97年12月\n    24日被害人甲○○上網瀏覽拍賣訊息之時間）為準，至為明\n    確。\n  (二)核被告乙○○所為，係犯刑法第339 條第1 項之詐欺取財罪\n    。被告對詐欺正犯提供帳戶資以助力，但並未參與詐欺犯罪\n    行為之實行，應屬幫助他人實行犯罪行為，為幫助犯，乃依\n    刑法第30條第2 項之規定減輕其刑。爰審酌被告輕易提供行\n    動電話門號SIM 卡供他人從事詐欺犯罪使用，非但增加被害\n    人尋求救濟之困難，造成社會人心不安，亦助長詐騙犯罪者\n    之氣焰，使詐欺犯罪者得以順利詐得財物，並逃避追緝，危\n    害財產交易安全，犯罪情節非輕，暨其行為手段、素行、犯\n    罪後態度等一切情狀，量處如主文所示之刑，並諭知易科罰\n    金之折算標準。\n二、據上論斷，應依刑事訴訟法第449 條第1 項前段、第3 項、\n    第454 條第2 項，刑法第339 條第1 項、第30條第1 項前段\n    、第2 項、第41條第1 項前段，刑法施行法第1 條之1 第1\n    項、第2 項前段，逕以簡易判決處刑如主文。\n三、如不服本判決，應於判決送達後10日內，向本院提出上訴狀\n    （應附繕本），上訴於本院合議庭。",
    "reason": "一、本件犯罪事實及證據併所犯法條，均引用臺灣桃園地方法院\n    檢察署檢察官聲請簡易判決處刑書之記載（如附件），並補\n    充及更正：\n  (一)按幫助犯係從屬於正犯而成立，以正犯已經犯罪為要件，故\n    幫助犯並非其幫助行為一經完成，即成立犯罪，必其幫助行\n    為或其影響力持續至正犯實施犯罪始行成立，是本件被告乙\n    ○○之犯罪時間當以正犯之犯罪行為時間（即民國97年12月\n    24日被害人甲○○上網瀏覽拍賣訊息之時間）為準，至為明\n    確。\n  (二)核被告乙○○所為，係犯刑法第339 條第1 項之詐欺取財罪\n    。被告對詐欺正犯提供帳戶資以助力，但並未參與詐欺犯罪\n    行為之實行，應屬幫助他人實行犯罪行為，為幫助犯，乃依\n    刑法第30條第2 項之規定減輕其刑。爰審酌被告輕易提供行\n    動電話門號SIM 卡供他人從事詐欺犯罪使用，非但增加被害\n    人尋求救濟之困難，造成社會人心不安，亦助長詐騙犯罪者\n    之氣焰，使詐欺犯罪者得以順利詐得財物，並逃避追緝，危\n    害財產交易安全，犯罪情節非輕，暨其行為手段、素行、犯\n    罪後態度等一切情狀，量處如主文所示之刑，並諭知易科罰\n    金之折算標準。\n二、據上論斷，應依刑事訴訟法第449 條第1 項前段、第3 項、\n    第454 條第2 項，刑法第339 條第1 項、第30條第1 項前段\n    、第2 項、第41條第1 項前段，刑法施行法第1 條之1 第1\n    項、第2 項前段，逕以簡易判決處刑如主文。\n三、如不服本判決，應於判決送達後10日內，向本院提出上訴狀\n    （應附繕本），上訴於本院合議庭。"
  },
  "characters": {
    "judges": [
      "陳德池"
    ],
    "prosecutors": [

    ],
    "lawyers": [

    ],
    "clerks": [
      "謝雅茹"
    ],
    "plaintiffs": [

    ],
    "defendants": [
      "乙○○"
    ],
    "prosecutor_office": [
      "臺灣桃園地方法院檢察署檢察官"
    ],
    "creditors": [

    ],
    "debtors": [

    ],
    "judicial_associate_officer": [

    ]
  },
  "adjudged_at": "2010-05-12",
  "created_at": "2016-01-05 12:37:20",
  "updated_at": "2016-01-05 12:37:20"
}