{
  "identify": "TYD-99-桃簡-1068-20100512-1",
  "court": {
    "name": "臺灣桃園地方法院",
    "code": "TYD"
  },
  "division": {
    "name": "刑事",
    "code": "M"
  },
  "year": 99,
  "word": "桃簡",
  "number": "1068",
  "jcheck": "1",
  "reason": "毒品危害防制條例",
  "content": "臺灣桃園地方法院刑事簡易判決        99年度桃簡字第1068號\n聲  請  人  臺灣桃園地方法院檢察署檢察官\n被      告  甲○○原名鄧雅心.\n上列被告因違反毒品危害防制條例案件，經檢察官聲請以簡易判\n決處刑（99年度毒偵字第1018號），本院判決如下：\n    主      文\n甲○○施用第二級毒品，處有期徒刑貳月，如易科罰金，以新臺\n幣壹仟元折算壹日。\n    事實及理由\n一、本件犯罪事實及證據，併所犯法條，均引用臺灣桃園地方法\n    院檢察署檢察官聲請簡易判決處刑書之記載（如附件），並\n    補充：\n  (一)證據另補充：桃園縣政府警察局桃園分局被採尿人尿液暨毒\n    品真實姓名與編號對照表。\n  (二)核被告甲○○所為，係犯毒品危害防制條例第10條第2 項之\n    施用第二級毒品罪。被告於施用第二級毒品甲基安非他命前\n    持有之低度行為為施用之高度行為所吸收，不另論罪。爰審\n    酌被告曾經觀察勒戒程序，仍無法戒除，復又觸犯本件犯行\n    ，顯示其尚無法完全戒絕吸毒惡習，惟施用毒品係傷害其自\n    身健康，所生危害非鉅，犯後坦承犯行等一切情狀，量處如\n    主文所示之刑，並諭知易科罰金之折算標準，以資儆懲。\n二、依刑事訴訟法第449 條第1 項前段、第3 項、第454 條第2\n    項，毒品危害防制條例第10條第2 項，刑法第11條前段、第\n    41條第1 項前段，逕以簡易判決處如主文所示之刑。\n三、如不服本判決，應於判決送達後10日內，向本院提出上訴狀\n    （應附繕本），上訴於本院合議庭。\n中    華    民    國    99    年    5     月    12    日\n                  刑事第二庭  法  官  陳德池\n以上正本證明與原本無異。\n如不服本判決，應於判決送達後10日內向本院提出上訴狀（應附\n繕本）。\n                              書記官  謝雅茹\n中    華    民    國    99    年    5     月    19    日\n附錄論罪科刑法條全文：\n毒品危害防制條例第10條\n施用第一級毒品者，處6 月以上5 年以下有期徒刑。\n施用第二級毒品者，處3 年以下有期徒刑。\n附件：臺灣桃園地方法院檢察署檢察官99年度毒偵字第1018號聲\n      請簡易判決處刑書1 份。",
  "structure": {
    "main": "甲○○施用第二級毒品，處有期徒刑貳月，如易科罰金，以新臺\n幣壹仟元折算壹日。",
    "fact": "一、本件犯罪事實及證據，併所犯法條，均引用臺灣桃園地方法\n    院檢察署檢察官聲請簡易判決處刑書之記載（如附件），並\n    補充：\n  (一)證據另補充：桃園縣政府警察局桃園分局被採尿人尿液暨毒\n    品真實姓名與編號對照表。\n  (二)核被告甲○○所為，係犯毒品危害防制條例第10條第2 項之\n    施用第二級毒品罪。被告於施用第二級毒品甲基安非他命前\n    持有之低度行為為施用之高度行為所吸收，不另論罪。爰審\n    酌被告曾經觀察勒戒程序，仍無法戒除，復又觸犯本件犯行\n    ，顯示其尚無法完全戒絕吸毒惡習，惟施用毒品係傷害其自\n    身健康，所生危害非鉅，犯後坦承犯行等一切情狀，量處如\n    主文所示之刑，並諭知易科罰金之折算標準，以資儆懲。\n二、依刑事訴訟法第449 條第1 項前段、第3 項、第454 條第2\n    項，毒品危害防制條例第10條第2 項，刑法第11條前段、第\n    41條第1 項前段，逕以簡易判決處如主文所示之刑。\n三、如不服本判決，應於判決送達後10日內，向本院提出上訴狀\n    （應附繕本），上訴於本院合議庭。",
    "reason": "一、本件犯罪事實及證據，併所犯法條，均引用臺灣桃園地方法\n    院檢察署檢察官聲請簡易判決處刑書之記載（如附件），並\n    補充：\n  (一)證據另補充：桃園縣政府警察局桃園分局被採尿人尿液暨毒\n    品真實姓名與編號對照表。\n  (二)核被告甲○○所為，係犯毒品危害防制條例第10條第2 項之\n    施用第二級毒品罪。被告於施用第二級毒品甲基安非他命前\n    持有之低度行為為施用之高度行為所吸收，不另論罪。爰審\n    酌被告曾經觀察勒戒程序，仍無法戒除，復又觸犯本件犯行\n    ，顯示其尚無法完全戒絕吸毒惡習，惟施用毒品係傷害其自\n    身健康，所生危害非鉅，犯後坦承犯行等一切情狀，量處如\n    主文所示之刑，並諭知易科罰金之折算標準，以資儆懲。\n二、依刑事訴訟法第449 條第1 項前段、第3 項、第454 條第2\n    項，毒品危害防制條例第10條第2 項，刑法第11條前段、第\n    41條第1 項前段，逕以簡易判決處如主文所示之刑。\n三、如不服本判決，應於判決送達後10日內，向本院提出上訴狀\n    （應附繕本），上訴於本院合議庭。"
  },
  "characters": {
    "judges": [
      "陳德池"
    ],
    "prosecutors": [

    ],
    "lawyers": [

    ],
    "clerks": [
      "謝雅茹"
    ],
    "plaintiffs": [

    ],
    "defendants": [
      "甲○○原名鄧雅心."
    ],
    "prosecutor_office": [
      "臺灣桃園地方法院檢察署檢察官"
    ],
    "creditors": [

    ],
    "debtors": [

    ],
    "judicial_associate_officer": [

    ]
  },
  "adjudged_at": "2010-05-12",
  "created_at": "2016-01-05 12:38:04",
  "updated_at": "2016-01-05 12:38:04"
}