{
  "identify": "TYD-99-壢簡-963-20100512-1",
  "court": {
    "name": "臺灣桃園地方法院",
    "code": "TYD"
  },
  "division": {
    "name": "刑事",
    "code": "M"
  },
  "year": 99,
  "word": "壢簡",
  "number": "963",
  "jcheck": "1",
  "reason": "電子遊戲場業管理條例等",
  "content": "臺灣桃園地方法院刑事簡易判決         99年度壢簡字第963號\n聲  請  人  臺灣桃園地方法院檢察署檢察官\n被      告  甲○○○\n上列被告因違反電子遊戲場業管理條例等案件，經檢察官聲請以\n簡易判決處刑（99年度偵字第10476 號），本院判決如下：\n    主      文\n甲○○○違反未依電子遊戲場業管理條例規定領有電子遊戲場業\n營業級別證者，不得經營電子遊戲場業之規定，處拘役參拾日，\n如易科罰金，以新臺幣壹 仟元折算壹日。扣案之電子遊戲機「小\n瑪莉」貳台（含IC板貳塊）、賭資現金新臺幣貳仟柒拾元，均沒\n收。\n    事實及理由\n一、本件犯罪事實及證據，併所犯法條，均引用臺灣桃園地方法\n    院檢察署檢察官聲請簡易判決處刑書之記載（如附件），並\n    補充：\n  (一)犯罪事實欄之「營利事業登記」，均更正為：「電子遊戲場\n    業營業級別證」；擺設及扣案之電子遊戲機「小瑪莉」均更\n    正為2 台（含IC板2 塊）。\n  (二)按未依電子遊戲場業管理條例規定領有電子遊戲場業營業級\n    別證者，不得經營電子遊戲場業，違反者應予處罰，電子遊\n    戲場業管理條例第15條、第22條分別定有明文。而電子遊戲\n    場業管理條例所謂「電子遊戲場業」之「業」，係指「業務\n    」而言；刑法上所謂業務，係以事實上執行業務者為標準，\n    指以反覆同種類之行為為目的之社會活動而言；執行此項業\n    務，縱令欠缺形式上之條件，仍無礙於業務之性質。因此，\n    不論該事業是否「專營」電子遊戲場業，亦不問經營是否需\n    達一定之規模，即使於原本所營事業外，兼營電子遊戲場業\n    ，或所經營之電子遊戲場業不具相當之規模，亦無礙於電子\n    遊戲場業管理條例相關規定之適用。經查，被告甲○○○在\n    公眾得出入之場所擺設賭博性電子遊戲機供不特定人把玩，\n    揆諸前揭說明，自有電子遊戲場業管理條例相關規定之適用\n    ，是核其所為，係違反電子遊戲場業管理條例第22條之違法\n    經營電子遊戲場業罪及刑法第266 條第1 項前段之在公眾得\n    出入之場所賭博罪。又被告自民國99年3 月30日起至同年4\n    月1 日下午4 時30分遭警查獲時止，在公眾得出入之場所內\n    擺設電子遊戲機與不特定人對賭之行為，係於密切接近之時\n    、地實施，侵害同一法益，各行為之獨立性極為薄弱，依一\n    般社會健全觀念，在時間差距上，難以強行分開，刑法評價\n    上，以視為數個舉動之接續行為，合為包括之一行為予以評\n    價，較為合理，均應成立接續犯而為包括一罪。再被告係基\n    於一賭博犯意以前開賭博性電子遊戲機具持續與人對賭，係\n    以一行為觸犯上開二罪名，應依刑法第55條想像競合犯之規\n    定，從較重之電子遊戲場業管理條例第22條之違法經營電子\n    遊戲場業罪處斷。\n  (三)爰審酌被告經營之時間、違法經營之遊戲機數量、規模、犯\n    後態度、智識程度、素行、行為手段等一切情狀，量處如主\n    文所示之刑，並諭知易科罰金之折算標準，以示懲儆。\n  (四)至扣案之電子遊戲機「小瑪莉」2 台（均含IC板2 塊），為\n    當場賭博之器具；賭資現金新臺幣2,070 元則係賭檯之財物\n    ，不問屬於犯人與否，均應依刑法第266 條第2 項規定沒收\n    之。\n二、依刑事訴訟法第449 條第1 項前段、第3 項、第450 條第1\n    項、第454 條第2 項，電子遊戲場業管理條例第22條、第15\n    條，刑法第11條前段、第266 條第1 項前段、第2 項、第55\n    條、第41條第1 項前段，刑法施行法第1 條之1 第1 項、第\n    2 項前段，逕以簡易判決處刑如主文。\n三、如不服本判決，應於判決送達後10日內，敘述上訴理由（須\n    附繕本），向本院合議庭提起上訴。\n中    華    民    國    99    年    5     月    12    日\n                  刑事第二庭  法  官  陳德池\n以上正本證明與原本無異。\n如不服本判決，應於判決送達後10日內向本院提出上訴狀（應附\n繕本）。\n                              書記官  謝雅茹\n中    華    民    國    99    年    5     月    14    日\n附錄論罪之法條：\n電子遊戲場業管理條例第15條\n未依本條例規定領有電子遊戲場業營業級別證者，不得經營電子\n遊戲場業。\n電子遊戲場業管理條例第22條\n違反第十五條規定者，處行為人一年以下有期徒刑、拘役或科或\n併科新台幣五十萬元以上二百五十萬元以下罰金。\n刑法第266 條\n在公共場所或公眾得出入之場所賭博財物者，處一千元以下罰金\n。但以供人暫時娛樂之物為賭者，不在此限。\n當場賭博之器具與在賭檯或兌換籌碼處之財物，不問屬於犯人與\n否，沒收之。\n附件：臺灣桃園地方法院檢察署檢察官99年度偵字第10476 號聲\n      請簡易判決處刑書1 份。",
  "structure": {
    "main": "甲○○○違反未依電子遊戲場業管理條例規定領有電子遊戲場業\n營業級別證者，不得經營電子遊戲場業之規定，處拘役參拾日，\n如易科罰金，以新臺幣壹 仟元折算壹日。扣案之電子遊戲機「小\n瑪莉」貳台（含IC板貳塊）、賭資現金新臺幣貳仟柒拾元，均沒\n收。",
    "fact": "一、本件犯罪事實及證據，併所犯法條，均引用臺灣桃園地方法\n    院檢察署檢察官聲請簡易判決處刑書之記載（如附件），並\n    補充：\n  (一)犯罪事實欄之「營利事業登記」，均更正為：「電子遊戲場\n    業營業級別證」；擺設及扣案之電子遊戲機「小瑪莉」均更\n    正為2 台（含IC板2 塊）。\n  (二)按未依電子遊戲場業管理條例規定領有電子遊戲場業營業級\n    別證者，不得經營電子遊戲場業，違反者應予處罰，電子遊\n    戲場業管理條例第15條、第22條分別定有明文。而電子遊戲\n    場業管理條例所謂「電子遊戲場業」之「業」，係指「業務\n    」而言；刑法上所謂業務，係以事實上執行業務者為標準，\n    指以反覆同種類之行為為目的之社會活動而言；執行此項業\n    務，縱令欠缺形式上之條件，仍無礙於業務之性質。因此，\n    不論該事業是否「專營」電子遊戲場業，亦不問經營是否需\n    達一定之規模，即使於原本所營事業外，兼營電子遊戲場業\n    ，或所經營之電子遊戲場業不具相當之規模，亦無礙於電子\n    遊戲場業管理條例相關規定之適用。經查，被告甲○○○在\n    公眾得出入之場所擺設賭博性電子遊戲機供不特定人把玩，\n    揆諸前揭說明，自有電子遊戲場業管理條例相關規定之適用\n    ，是核其所為，係違反電子遊戲場業管理條例第22條之違法\n    經營電子遊戲場業罪及刑法第266 條第1 項前段之在公眾得\n    出入之場所賭博罪。又被告自民國99年3 月30日起至同年4\n    月1 日下午4 時30分遭警查獲時止，在公眾得出入之場所內\n    擺設電子遊戲機與不特定人對賭之行為，係於密切接近之時\n    、地實施，侵害同一法益，各行為之獨立性極為薄弱，依一\n    般社會健全觀念，在時間差距上，難以強行分開，刑法評價\n    上，以視為數個舉動之接續行為，合為包括之一行為予以評\n    價，較為合理，均應成立接續犯而為包括一罪。再被告係基\n    於一賭博犯意以前開賭博性電子遊戲機具持續與人對賭，係\n    以一行為觸犯上開二罪名，應依刑法第55條想像競合犯之規\n    定，從較重之電子遊戲場業管理條例第22條之違法經營電子\n    遊戲場業罪處斷。\n  (三)爰審酌被告經營之時間、違法經營之遊戲機數量、規模、犯\n    後態度、智識程度、素行、行為手段等一切情狀，量處如主\n    文所示之刑，並諭知易科罰金之折算標準，以示懲儆。\n  (四)至扣案之電子遊戲機「小瑪莉」2 台（均含IC板2 塊），為\n    當場賭博之器具；賭資現金新臺幣2,070 元則係賭檯之財物\n    ，不問屬於犯人與否，均應依刑法第266 條第2 項規定沒收\n    之。\n二、依刑事訴訟法第449 條第1 項前段、第3 項、第450 條第1\n    項、第454 條第2 項，電子遊戲場業管理條例第22條、第15\n    條，刑法第11條前段、第266 條第1 項前段、第2 項、第55\n    條、第41條第1 項前段，刑法施行法第1 條之1 第1 項、第\n    2 項前段，逕以簡易判決處刑如主文。\n三、如不服本判決，應於判決送達後10日內，敘述上訴理由（須\n    附繕本），向本院合議庭提起上訴。",
    "reason": "一、本件犯罪事實及證據，併所犯法條，均引用臺灣桃園地方法\n    院檢察署檢察官聲請簡易判決處刑書之記載（如附件），並\n    補充：\n  (一)犯罪事實欄之「營利事業登記」，均更正為：「電子遊戲場\n    業營業級別證」；擺設及扣案之電子遊戲機「小瑪莉」均更\n    正為2 台（含IC板2 塊）。\n  (二)按未依電子遊戲場業管理條例規定領有電子遊戲場業營業級\n    別證者，不得經營電子遊戲場業，違反者應予處罰，電子遊\n    戲場業管理條例第15條、第22條分別定有明文。而電子遊戲\n    場業管理條例所謂「電子遊戲場業」之「業」，係指「業務\n    」而言；刑法上所謂業務，係以事實上執行業務者為標準，\n    指以反覆同種類之行為為目的之社會活動而言；執行此項業\n    務，縱令欠缺形式上之條件，仍無礙於業務之性質。因此，\n    不論該事業是否「專營」電子遊戲場業，亦不問經營是否需\n    達一定之規模，即使於原本所營事業外，兼營電子遊戲場業\n    ，或所經營之電子遊戲場業不具相當之規模，亦無礙於電子\n    遊戲場業管理條例相關規定之適用。經查，被告甲○○○在\n    公眾得出入之場所擺設賭博性電子遊戲機供不特定人把玩，\n    揆諸前揭說明，自有電子遊戲場業管理條例相關規定之適用\n    ，是核其所為，係違反電子遊戲場業管理條例第22條之違法\n    經營電子遊戲場業罪及刑法第266 條第1 項前段之在公眾得\n    出入之場所賭博罪。又被告自民國99年3 月30日起至同年4\n    月1 日下午4 時30分遭警查獲時止，在公眾得出入之場所內\n    擺設電子遊戲機與不特定人對賭之行為，係於密切接近之時\n    、地實施，侵害同一法益，各行為之獨立性極為薄弱，依一\n    般社會健全觀念，在時間差距上，難以強行分開，刑法評價\n    上，以視為數個舉動之接續行為，合為包括之一行為予以評\n    價，較為合理，均應成立接續犯而為包括一罪。再被告係基\n    於一賭博犯意以前開賭博性電子遊戲機具持續與人對賭，係\n    以一行為觸犯上開二罪名，應依刑法第55條想像競合犯之規\n    定，從較重之電子遊戲場業管理條例第22條之違法經營電子\n    遊戲場業罪處斷。\n  (三)爰審酌被告經營之時間、違法經營之遊戲機數量、規模、犯\n    後態度、智識程度、素行、行為手段等一切情狀，量處如主\n    文所示之刑，並諭知易科罰金之折算標準，以示懲儆。\n  (四)至扣案之電子遊戲機「小瑪莉」2 台（均含IC板2 塊），為\n    當場賭博之器具；賭資現金新臺幣2,070 元則係賭檯之財物\n    ，不問屬於犯人與否，均應依刑法第266 條第2 項規定沒收\n    之。\n二、依刑事訴訟法第449 條第1 項前段、第3 項、第450 條第1\n    項、第454 條第2 項，電子遊戲場業管理條例第22條、第15\n    條，刑法第11條前段、第266 條第1 項前段、第2 項、第55\n    條、第41條第1 項前段，刑法施行法第1 條之1 第1 項、第\n    2 項前段，逕以簡易判決處刑如主文。\n三、如不服本判決，應於判決送達後10日內，敘述上訴理由（須\n    附繕本），向本院合議庭提起上訴。"
  },
  "characters": {
    "judges": [
      "陳德池"
    ],
    "prosecutors": [

    ],
    "lawyers": [

    ],
    "clerks": [
      "謝雅茹"
    ],
    "plaintiffs": [

    ],
    "defendants": [
      "甲○○○"
    ],
    "prosecutor_office": [
      "臺灣桃園地方法院檢察署檢察官"
    ],
    "creditors": [

    ],
    "debtors": [

    ],
    "judicial_associate_officer": [

    ]
  },
  "adjudged_at": "2010-05-12",
  "created_at": "2016-01-05 12:37:35",
  "updated_at": "2016-01-05 12:37:35"
}