{
  "identify": "TYD-99-壢簡-679-20100512-1",
  "court": {
    "name": "臺灣桃園地方法院",
    "code": "TYD"
  },
  "division": {
    "name": "刑事",
    "code": "M"
  },
  "year": 99,
  "word": "壢簡",
  "number": "679",
  "jcheck": "1",
  "reason": "贓物",
  "content": "臺灣桃園地方法院刑事簡易判決         99年度壢簡字第679號\n聲  請  人  臺灣桃園地方法院檢察署檢察官\n被      告  甲○○\n上列被告因贓物案件，經檢察官聲請以簡易判決處刑（98年度偵\n緝字第1919號、99年度偵字第1849號），本院判決如下：\n    主  文\n甲○○收受贓物，累犯，處拘役肆拾日，如易科罰金，以新臺幣\n壹仟元折算壹日。\n    事實及理由\n一、本件犯罪事實及理由均引用檢察官聲請簡易判決處刑書之記\n    載（如附件）。\n二、核被告所為，係犯刑法第349 條之收受贓物罪。被告前於民\n    國93年間，因違反職役職責案件，經國防部北部地方軍事法\n    院桃園分院於93年5 月27日以93年桃審字第78號判處有期徒\n    刑8 月，於93年12月4 日執行完畢等情，有臺灣高等法院被\n    告前案紀錄表1 份在卷足憑，是被告於有期徒刑執行完畢後\n    ，5 年內故意犯本件有期徒刑以上之罪，為累犯，應依刑法\n    第47條第1 項規定加重其刑。爰審酌被告之犯罪動機、目的\n    、手段、對被害人所生之危害及犯後猶飾詞狡辯，未見有悔\n    改之意等一切情狀，量處如主文所示之刑，並諭知易科罰金\n    之折算標準，以示警懲。\n三、依刑事訴訟法第449 條第1 項前段、第454 條第2 項，刑法\n    第349 條第1 項、第47條第1 項、第41條第1 項前段，刑法\n    施行法第1 之1 條第1 項、第2 項前段，逕以簡易判決處刑\n    如主文。\n四、如不服本判決，得於判決書送達之翌日起10日內，以書狀敘\n    述理由，向本庭提出上訴。\n中    華    民    國    99    年    5     月    12    日\n                        臺灣桃園地方法院刑事第二庭\n                              法  官  柯姿佐\n以上正本證明與原本無異\n如不服本判決應於判決書送達之翌日起10日內，向本院提出上訴\n狀（應附繕本）。\n                              書記官  林舒涵\n中    華    民    國    99    年    5     月    13    日\n附錄論罪科刑依據之法條：\n中華民國刑法第349條\n（普通贓物罪）\n收受贓物者，處 3 年以下有期徒刑、拘役或 5 百元以下罰金。\n搬運、寄藏、故買贓物或為牙保者，處 5 年以下有期徒刑、拘\n役或科或併科 1 千元以下罰金。\n因贓物變得之財物，以贓物論。",
  "structure": {
    "main": "甲○○收受贓物，累犯，處拘役肆拾日，如易科罰金，以新臺幣\n壹仟元折算壹日。",
    "fact": "一、本件犯罪事實及理由均引用檢察官聲請簡易判決處刑書之記\n    載（如附件）。\n二、核被告所為，係犯刑法第349 條之收受贓物罪。被告前於民\n    國93年間，因違反職役職責案件，經國防部北部地方軍事法\n    院桃園分院於93年5 月27日以93年桃審字第78號判處有期徒\n    刑8 月，於93年12月4 日執行完畢等情，有臺灣高等法院被\n    告前案紀錄表1 份在卷足憑，是被告於有期徒刑執行完畢後\n    ，5 年內故意犯本件有期徒刑以上之罪，為累犯，應依刑法\n    第47條第1 項規定加重其刑。爰審酌被告之犯罪動機、目的\n    、手段、對被害人所生之危害及犯後猶飾詞狡辯，未見有悔\n    改之意等一切情狀，量處如主文所示之刑，並諭知易科罰金\n    之折算標準，以示警懲。\n三、依刑事訴訟法第449 條第1 項前段、第454 條第2 項，刑法\n    第349 條第1 項、第47條第1 項、第41條第1 項前段，刑法\n    施行法第1 之1 條第1 項、第2 項前段，逕以簡易判決處刑\n    如主文。\n四、如不服本判決，得於判決書送達之翌日起10日內，以書狀敘\n    述理由，向本庭提出上訴。",
    "reason": "一、本件犯罪事實及理由均引用檢察官聲請簡易判決處刑書之記\n    載（如附件）。\n二、核被告所為，係犯刑法第349 條之收受贓物罪。被告前於民\n    國93年間，因違反職役職責案件，經國防部北部地方軍事法\n    院桃園分院於93年5 月27日以93年桃審字第78號判處有期徒\n    刑8 月，於93年12月4 日執行完畢等情，有臺灣高等法院被\n    告前案紀錄表1 份在卷足憑，是被告於有期徒刑執行完畢後\n    ，5 年內故意犯本件有期徒刑以上之罪，為累犯，應依刑法\n    第47條第1 項規定加重其刑。爰審酌被告之犯罪動機、目的\n    、手段、對被害人所生之危害及犯後猶飾詞狡辯，未見有悔\n    改之意等一切情狀，量處如主文所示之刑，並諭知易科罰金\n    之折算標準，以示警懲。\n三、依刑事訴訟法第449 條第1 項前段、第454 條第2 項，刑法\n    第349 條第1 項、第47條第1 項、第41條第1 項前段，刑法\n    施行法第1 之1 條第1 項、第2 項前段，逕以簡易判決處刑\n    如主文。\n四、如不服本判決，得於判決書送達之翌日起10日內，以書狀敘\n    述理由，向本庭提出上訴。"
  },
  "characters": {
    "judges": [
      "柯姿佐"
    ],
    "prosecutors": [

    ],
    "lawyers": [

    ],
    "clerks": [
      "林舒涵"
    ],
    "plaintiffs": [

    ],
    "defendants": [
      "甲○○"
    ],
    "prosecutor_office": [
      "臺灣桃園地方法院檢察署檢察官"
    ],
    "creditors": [

    ],
    "debtors": [

    ],
    "judicial_associate_officer": [

    ]
  },
  "adjudged_at": "2010-05-12",
  "created_at": "2016-01-05 12:37:04",
  "updated_at": "2016-01-05 12:37:04"
}