{
  "identify": "TYD-99-聲-1016-20100512-1",
  "court": {
    "name": "臺灣桃園地方法院",
    "code": "TYD"
  },
  "division": {
    "name": "刑事",
    "code": "M"
  },
  "year": 99,
  "word": "聲",
  "number": "1016",
  "jcheck": "1",
  "reason": "聲請撤銷羈押",
  "content": "臺灣桃園地方法院刑事裁定              99年度聲字第1016號\n被      告  甲○○\n選任辯護人  廖威淵律師\n上列聲請人即被告因詐欺案件，聲請具保停止羈押，本院裁定如\n下：\n    主  文\n聲請駁回。\n    理  由\n一、查本件聲請人即被告甲○○因詐欺案件，經本院訊問後，認\n    其犯罪嫌疑重大，且有刑事訴訟法第10 1條之1 第1 項第7\n    款之情形，並有羈押之必要，於民國99年3 月12日執行羈押\n    迄今，合先敘明。\n二、聲請人聲請意旨略以：被告於臺灣臺南地方法院雖前遭通緝\n    ，然係因被告未接到通知所致，且被告現已歸案，並經以新\n    台幣3 萬元具保候在案，且前開遭通緝之案件，被告與被害\n    人業已達成和解，並已付清和解款，被告與證人間或其他被\n    告間實無串證、湮滅證據之可能，且被告羈押前原居住於台\n    南縣新化鎮○○路33巷12號，本有固定住居所，更無逃亡之\n    虞，為此狀請准予具保停止羈押云云。\n三、按羈押之目的在於確保刑事偵查、審判程式之完成，及刑事\n    執行之保全，或預防反覆實施特定犯罪。被告有無羈押之必\n    要，應許由法院斟酌訴訟進行程度及其他一切情事而為認定\n    （參照最高法院46年台抗字第6 號判例），而關於羈押與否\n    之審查，其目的僅在判斷有無實施羈押強制處分之必要，並\n    非認定被告有無犯罪之實體審判程式，故關於羈押之要件，\n    無須經嚴格之證明，而以經釋明得以自由證明為已足，至於\n    被告是否成立犯罪，乃本案實體上應予判斷之問題，先予敘\n    明。\n四、次按被告經法官訊問後，認為犯罪嫌疑重大，而有刑事訴訟\n    法101 條之1 第1 項第7 款所列情形之一，非予羈押，顯難\n    進行追訴、審判或執行者，得羈押之。查聲請人即被告甲○\n    ○所涉詐欺罪嫌，有起訴書所載之證據可證，足認犯罪嫌疑\n    重大，且被告於95年、96年及97年間，均曾因與本案同類型\n    之詐欺案件分別經檢察官為緩起訴處分、起訴，及經法院判\n    刑，復於本案再犯詐欺罪嫌，足認被告所犯詐欺罪嫌部分，\n    有反覆實施之虞，非予羈押，顯難擔保日後審判之進行及刑\n    罰之執行，因認有羈押之必要，是聲請人聲請具保停止羈押\n    ，自難准許，應予駁回。\n五、據上論斷，應依刑事訴訟法第220條，裁定如主文。\n中    華    民    國    99    年    5     月    12    日\n                  刑事第七庭審判長法  官  蕭世昌\n                                  法  官  蔡羽玄\n                                  法  官  蔡世芳\n以上正本證明與原本無異。\n如不服本裁定，應於裁定送達後5 日內向本院提出抗告狀。\n                                  書記官  張尹嫚\n中    華    民    國    99    年    5     月    13    日",
  "structure": {
    "main": "聲請駁回。",
    "reason": "一、查本件聲請人即被告甲○○因詐欺案件，經本院訊問後，認\n    其犯罪嫌疑重大，且有刑事訴訟法第10 1條之1 第1 項第7\n    款之情形，並有羈押之必要，於民國99年3 月12日執行羈押\n    迄今，合先敘明。\n二、聲請人聲請意旨略以：被告於臺灣臺南地方法院雖前遭通緝\n    ，然係因被告未接到通知所致，且被告現已歸案，並經以新\n    台幣3 萬元具保候在案，且前開遭通緝之案件，被告與被害\n    人業已達成和解，並已付清和解款，被告與證人間或其他被\n    告間實無串證、湮滅證據之可能，且被告羈押前原居住於台\n    南縣新化鎮○○路33巷12號，本有固定住居所，更無逃亡之\n    虞，為此狀請准予具保停止羈押云云。\n三、按羈押之目的在於確保刑事偵查、審判程式之完成，及刑事\n    執行之保全，或預防反覆實施特定犯罪。被告有無羈押之必\n    要，應許由法院斟酌訴訟進行程度及其他一切情事而為認定\n    （參照最高法院46年台抗字第6 號判例），而關於羈押與否\n    之審查，其目的僅在判斷有無實施羈押強制處分之必要，並\n    非認定被告有無犯罪之實體審判程式，故關於羈押之要件，\n    無須經嚴格之證明，而以經釋明得以自由證明為已足，至於\n    被告是否成立犯罪，乃本案實體上應予判斷之問題，先予敘\n    明。\n四、次按被告經法官訊問後，認為犯罪嫌疑重大，而有刑事訴訟\n    法101 條之1 第1 項第7 款所列情形之一，非予羈押，顯難\n    進行追訴、審判或執行者，得羈押之。查聲請人即被告甲○\n    ○所涉詐欺罪嫌，有起訴書所載之證據可證，足認犯罪嫌疑\n    重大，且被告於95年、96年及97年間，均曾因與本案同類型\n    之詐欺案件分別經檢察官為緩起訴處分、起訴，及經法院判\n    刑，復於本案再犯詐欺罪嫌，足認被告所犯詐欺罪嫌部分，\n    有反覆實施之虞，非予羈押，顯難擔保日後審判之進行及刑\n    罰之執行，因認有羈押之必要，是聲請人聲請具保停止羈押\n    ，自難准許，應予駁回。\n五、據上論斷，應依刑事訴訟法第220條，裁定如主文。"
  },
  "characters": {
    "judges": [
      "蕭世昌",
      "蔡羽玄",
      "蔡世芳"
    ],
    "prosecutors": [

    ],
    "lawyers": [
      "廖威淵"
    ],
    "clerks": [
      "張尹嫚"
    ],
    "plaintiffs": [

    ],
    "defendants": [
      "甲○○"
    ],
    "prosecutor_office": [

    ],
    "creditors": [

    ],
    "debtors": [

    ],
    "judicial_associate_officer": [

    ]
  },
  "adjudged_at": "2010-05-12",
  "created_at": "2016-01-05 12:35:55",
  "updated_at": "2016-01-05 12:35:55"
}