{
  "identify": "TYD-99-聲-1533-20100512-1",
  "court": {
    "name": "臺灣桃園地方法院",
    "code": "TYD"
  },
  "division": {
    "name": "刑事",
    "code": "M"
  },
  "year": 99,
  "word": "聲",
  "number": "1533",
  "jcheck": "1",
  "reason": "沒入保證金",
  "content": "臺灣桃園地方法院刑事裁定              99年度聲字第1533號\n聲  請  人  臺灣桃園地方法院檢察署檢察官\n被      告  甲○○\n具  保  人  丙○○\n上列受刑人因違反臺灣地區與大陸地區人民關係條例案件，經檢\n察官聲請沒入保證金（99年度執聲沒字第144 號），本院裁定如\n下：\n    主  文\n丙○○繳納之保證金新臺幣伍萬元，沒入之。\n    理  由\n一、聲請意旨略以：具保人丙○○因被告甲○○犯臺灣地區與大\n    陸地區人民關係條例案件，經檢察官指定保證金額新臺幣（\n    下同）5萬元，出具現金保證後，將被告釋放。茲因被告逃\n    匿，應沒入具保人繳納之保證金等語。\n二、按具保之被告逃匿者，應命具保人繳納指定之保證金額，並\n    沒入之；保證金已繳納者，沒入之；前項規定，於檢察官依\n    第93條第3項但書及第228條第3項命具保者準用之，刑事訴\n    訟法第118條定有明文。次按被告、自訴人、告訴人、附帶\n    民事訴訟當事人、代理人、辯護人、輔佐人或被害人為接受\n    文書之送達，應將其住所、居所或事務所向法院或檢察官陳\n    明；前項之陳明，其效力及於同地之各級法院，刑事訴訟法\n    第55條第1項、第2項分別定有明文，是依當事人陳報之居住\n    處所送達文書，自屬於法有據。又送達文書，除本章有特別\n    規定外，準用民事訴訟法之規定；送達於應受送達人之住居\n    所、事務所或營業所行之；送達於住、居所、事務所或營業\n    所不獲會晤應受送達人者，得將文書付與有辨別事理能力之\n    同居人或受僱人；送達不能依前2條規定為之者，得將文書\n    寄存送達地之自治或警察機關，並作送達通知書2份，1份黏\n    貼於應受送達人住居所、事務所、營業所或其就業處所門首\n    ，另1份置於該送達處所信箱或其他適當位置，以為送達；\n    寄存送達自寄存之日起，經10日發生效力，刑事訴訟法第62\n    條、民事訴訟法第136 條第1項、第137條、第138條第1項、\n    第2項亦分別定有明文。\n三、經查：\n(一)被告因違反臺灣地區與大陸地區人民關係條例案件，經臺灣\n    桃園地方法院檢察署檢察官指定保證金5萬元，並由具保人\n    於民國96年9月3日出具現金保證後，將被告釋放，該案經本\n    院於97年10月6日以96年度易字第1284號判決判處有期徒刑1\n    年2月確定之情，有臺灣桃園地方法院檢察署刑保字第96103\n    659號刑事保證金收據影本1份附卷可考，並有臺灣高等法院\n    被告前案紀錄表1份在卷可查。\n(二)被告於上開案件執行時，經臺灣桃園地方法院檢察署檢察官\n    於98年11月6日將執行傳票送達其先前於該案偵審程式中所\n    陳報之「臺北市○○○路180巷13號7樓」地址，因未獲會晤\n    本人，亦無受領文書之同居人或受僱人，寄存送達於臺北市\n    政府警察局敦化南路派出所，且於98年11月9日將具保人遵\n    期帶同被告到案執行之通知送達於具保人，亦因未獲會晤本\n    人，亦無受領文書之同居人或受僱人，寄存送達於臺北市政\n    府警察局武敦化南路派出所，惟被告於97年12月1日已將其\n    住所自「臺北市大安區○○○路180巷13號7樓」，遷至「臺\n    北縣汐止市○○路213巷9號3樓」乙節，有被告之個人基本\n    資料查詢結果可憑。臺灣桃園地方法院檢察署檢察官再於99\n    年2月9日將執行傳票送達至被告位在臺北縣汐止市○○路21\n    3巷9號3樓之住所，因不獲會晤其本人，亦不無受領文書之\n    同居人或受僱人，故寄存於臺北縣政府警察局汐止分局八連\n    派出所，嗣經該署檢察官囑託臺灣士林地方法院檢察署執行\n    拘提被告未獲，迄今仍未依法到案執行，經臺灣桃園地方法\n    院檢察署於99年4月30日以99年度乙○堂執丑緝字第1839號\n    對被告發布通緝在案，現仍未緝獲等情，有送達證書、拘票\n    、拘提報告書、臺灣高等法院被告前案紀錄表及臺灣高等法\n    院在監在押全國紀錄表等件在卷可稽，足證被告確已逃匿，\n    揆諸前揭說明，自應將具保人繳納之上開保證金沒入。\n四、依刑事訴訟法第118 條、第121條第1 項，裁定如主文。\n中    華    民    國    99    年    5     月    12    日\n                  刑事第十一庭  法  官  汪曉君\n以上正本證明與原本無異。\n如不服本裁定，應於裁定送達後5 日內向本院提出抗告狀。\n                                書記官  楊晴文\n中    華    民    國    99    年    5     月    13    日",
  "structure": {
    "main": "丙○○繳納之保證金新臺幣伍萬元，沒入之。",
    "reason": "一、聲請意旨略以：具保人丙○○因被告甲○○犯臺灣地區與大\n    陸地區人民關係條例案件，經檢察官指定保證金額新臺幣（\n    下同）5萬元，出具現金保證後，將被告釋放。茲因被告逃\n    匿，應沒入具保人繳納之保證金等語。\n二、按具保之被告逃匿者，應命具保人繳納指定之保證金額，並\n    沒入之；保證金已繳納者，沒入之；前項規定，於檢察官依\n    第93條第3項但書及第228條第3項命具保者準用之，刑事訴\n    訟法第118條定有明文。次按被告、自訴人、告訴人、附帶\n    民事訴訟當事人、代理人、辯護人、輔佐人或被害人為接受\n    文書之送達，應將其住所、居所或事務所向法院或檢察官陳\n    明；前項之陳明，其效力及於同地之各級法院，刑事訴訟法\n    第55條第1項、第2項分別定有明文，是依當事人陳報之居住\n    處所送達文書，自屬於法有據。又送達文書，除本章有特別\n    規定外，準用民事訴訟法之規定；送達於應受送達人之住居\n    所、事務所或營業所行之；送達於住、居所、事務所或營業\n    所不獲會晤應受送達人者，得將文書付與有辨別事理能力之\n    同居人或受僱人；送達不能依前2條規定為之者，得將文書\n    寄存送達地之自治或警察機關，並作送達通知書2份，1份黏\n    貼於應受送達人住居所、事務所、營業所或其就業處所門首\n    ，另1份置於該送達處所信箱或其他適當位置，以為送達；\n    寄存送達自寄存之日起，經10日發生效力，刑事訴訟法第62\n    條、民事訴訟法第136 條第1項、第137條、第138條第1項、\n    第2項亦分別定有明文。\n三、經查：\n(一)被告因違反臺灣地區與大陸地區人民關係條例案件，經臺灣\n    桃園地方法院檢察署檢察官指定保證金5萬元，並由具保人\n    於民國96年9月3日出具現金保證後，將被告釋放，該案經本\n    院於97年10月6日以96年度易字第1284號判決判處有期徒刑1\n    年2月確定之情，有臺灣桃園地方法院檢察署刑保字第96103\n    659號刑事保證金收據影本1份附卷可考，並有臺灣高等法院\n    被告前案紀錄表1份在卷可查。\n(二)被告於上開案件執行時，經臺灣桃園地方法院檢察署檢察官\n    於98年11月6日將執行傳票送達其先前於該案偵審程式中所\n    陳報之「臺北市○○○路180巷13號7樓」地址，因未獲會晤\n    本人，亦無受領文書之同居人或受僱人，寄存送達於臺北市\n    政府警察局敦化南路派出所，且於98年11月9日將具保人遵\n    期帶同被告到案執行之通知送達於具保人，亦因未獲會晤本\n    人，亦無受領文書之同居人或受僱人，寄存送達於臺北市政\n    府警察局武敦化南路派出所，惟被告於97年12月1日已將其\n    住所自「臺北市大安區○○○路180巷13號7樓」，遷至「臺\n    北縣汐止市○○路213巷9號3樓」乙節，有被告之個人基本\n    資料查詢結果可憑。臺灣桃園地方法院檢察署檢察官再於99\n    年2月9日將執行傳票送達至被告位在臺北縣汐止市○○路21\n    3巷9號3樓之住所，因不獲會晤其本人，亦不無受領文書之\n    同居人或受僱人，故寄存於臺北縣政府警察局汐止分局八連\n    派出所，嗣經該署檢察官囑託臺灣士林地方法院檢察署執行\n    拘提被告未獲，迄今仍未依法到案執行，經臺灣桃園地方法\n    院檢察署於99年4月30日以99年度乙○堂執丑緝字第1839號\n    對被告發布通緝在案，現仍未緝獲等情，有送達證書、拘票\n    、拘提報告書、臺灣高等法院被告前案紀錄表及臺灣高等法\n    院在監在押全國紀錄表等件在卷可稽，足證被告確已逃匿，\n    揆諸前揭說明，自應將具保人繳納之上開保證金沒入。\n四、依刑事訴訟法第118 條、第121條第1 項，裁定如主文。"
  },
  "characters": {
    "judges": [
      "汪曉君"
    ],
    "prosecutors": [

    ],
    "lawyers": [

    ],
    "clerks": [
      "楊晴文"
    ],
    "plaintiffs": [

    ],
    "defendants": [
      "甲○○",
      "具  保  人  丙○○"
    ],
    "prosecutor_office": [
      "臺灣桃園地方法院檢察署檢察官"
    ],
    "creditors": [

    ],
    "debtors": [

    ],
    "judicial_associate_officer": [

    ]
  },
  "adjudged_at": "2010-05-12",
  "created_at": "2016-01-05 12:36:03",
  "updated_at": "2016-01-05 12:36:03"
}