{
  "identify": "TYD-99-桃簡-1070-20100512-1",
  "court": {
    "name": "臺灣桃園地方法院",
    "code": "TYD"
  },
  "division": {
    "name": "刑事",
    "code": "M"
  },
  "year": 99,
  "word": "桃簡",
  "number": "1070",
  "jcheck": "1",
  "reason": "詐欺",
  "content": "臺灣桃園地方法院刑事簡易判決        99年度桃簡字第1070號\n聲  請  人  臺灣桃園地方法院檢察署檢察官\n被      告  甲○○\n上列被告因詐欺案件，經檢察官聲請以簡易判決處刑（99年度偵\n緝字第25號），本院判決如下：\n    主      文\n甲○○幫助意圖為自己不法之所有，以詐術使人將本人之物交付\n，累犯，處有期徒刑參月，如易科罰金，以新臺幣壹仟元折算壹\n日。\n    事實及理由\n一、本件犯罪事實及證據併所犯法條，均引用臺灣桃園地方法院\n    檢察署檢察官聲請簡易判決處刑書之記載（如附件），並補\n    充及更正：\n  (一)犯罪事實欄應補充：「甲○○前曾因施用毒品案件，經本院\n    及臺灣雲林地方法院分別判處有期徒刑8 月、1 年2 月確定\n    ，二罪接續執行，於民國95年8 月22日縮短刑期假釋出監併\n    付保護管束，迄於96年1 月6 日縮刑期滿，假釋未經撤銷，\n    其未執行之刑以已執行完畢論。」\n  (二)按幫助犯係從屬於正犯而成立，以正犯已經犯罪為要件，故\n    幫助犯並非其幫助行為一經完成，即成立犯罪，必其幫助行\n    為或其影響力持續至正犯實施犯罪始行成立，是本件被告甲\n    ○○之犯罪時間當以正犯之犯罪行為時間（即民國98年7 月\n    3 日詐欺集團正犯向被害人乙○○施用詐術之時間）為準，\n    至為明確。\n  (三)核被告甲○○所為，係犯刑法第339 條第1 項之詐欺取財罪\n    。被告對詐欺正犯提供帳戶資以助力，但並未參與詐欺犯罪\n    行為之實行，應屬幫助他人實行犯罪行為，為幫助犯，乃依\n    刑法第30條第2 項之規定減輕其刑。又被告有如上所示之犯\n    罪前科與執行情形，此有臺灣高等法院被告前案紀錄表存卷\n    可按，其於5 年以內故意再犯本件有期徒刑以上之罪，為累\n    犯，應依刑法第47條第1 項之規定加重其刑，併先加後減之\n    。爰審酌被告輕易提供金融帳戶資料供他人掩飾犯罪所得使\n    用，非但增加被害人尋求救濟之困難，造成社會人心不安，\n    亦助長詐騙犯罪者之氣焰，使詐欺犯罪者得以順利取得詐欺\n    所得之財物，危害財產交易安全，犯罪情節非輕，暨其行為\n    手段、素行、犯罪後態度等一切情狀，量處如主文所示之刑\n    ，並諭知易科罰金之折算標準。\n二、據上論斷，應依刑事訴訟法第449 條第1 項前段、第3 項、\n    第454 條第2 項，刑法第339 條第1 項、第30條第1 項前段\n    、第2 項、第47條第1 項、第41條第1 項前段，刑法施行法\n    第1 條之1 第1 項、第2 項前段，逕以簡易判決處刑如主文\n    。\n三、如不服本判決，應於判決送達後10日內，向本院提出上訴狀\n    （應附繕本），上訴於本院合議庭。\n中    華    民    國    99    年    5     月    12    日\n                  刑事第二庭  法  官  陳德池\n以上正本證明與原本無異。\n如不服本判決，應於判決送達後10日內向本院提出上訴狀（應附\n繕本）。\n                              書記官  謝雅茹\n中    華    民    國    99    年    5     月    14    日\n附錄論罪科刑法條全文：\n刑法第339條第1 項(普通詐欺罪)：\n意圖為自己或第三人不法之所有，以詐術使人將本人或第三人之\n物交付者，處五年以下有期徒刑、拘役或科或併科一千元以下罰\n金。\n附件：臺灣桃園地方法院檢察署檢察官99年度偵緝字第25號聲請\n      簡易判決處刑書1 份。",
  "structure": {
    "main": "甲○○幫助意圖為自己不法之所有，以詐術使人將本人之物交付\n，累犯，處有期徒刑參月，如易科罰金，以新臺幣壹仟元折算壹\n日。",
    "fact": "一、本件犯罪事實及證據併所犯法條，均引用臺灣桃園地方法院\n    檢察署檢察官聲請簡易判決處刑書之記載（如附件），並補\n    充及更正：\n  (一)犯罪事實欄應補充：「甲○○前曾因施用毒品案件，經本院\n    及臺灣雲林地方法院分別判處有期徒刑8 月、1 年2 月確定\n    ，二罪接續執行，於民國95年8 月22日縮短刑期假釋出監併\n    付保護管束，迄於96年1 月6 日縮刑期滿，假釋未經撤銷，\n    其未執行之刑以已執行完畢論。」\n  (二)按幫助犯係從屬於正犯而成立，以正犯已經犯罪為要件，故\n    幫助犯並非其幫助行為一經完成，即成立犯罪，必其幫助行\n    為或其影響力持續至正犯實施犯罪始行成立，是本件被告甲\n    ○○之犯罪時間當以正犯之犯罪行為時間（即民國98年7 月\n    3 日詐欺集團正犯向被害人乙○○施用詐術之時間）為準，\n    至為明確。\n  (三)核被告甲○○所為，係犯刑法第339 條第1 項之詐欺取財罪\n    。被告對詐欺正犯提供帳戶資以助力，但並未參與詐欺犯罪\n    行為之實行，應屬幫助他人實行犯罪行為，為幫助犯，乃依\n    刑法第30條第2 項之規定減輕其刑。又被告有如上所示之犯\n    罪前科與執行情形，此有臺灣高等法院被告前案紀錄表存卷\n    可按，其於5 年以內故意再犯本件有期徒刑以上之罪，為累\n    犯，應依刑法第47條第1 項之規定加重其刑，併先加後減之\n    。爰審酌被告輕易提供金融帳戶資料供他人掩飾犯罪所得使\n    用，非但增加被害人尋求救濟之困難，造成社會人心不安，\n    亦助長詐騙犯罪者之氣焰，使詐欺犯罪者得以順利取得詐欺\n    所得之財物，危害財產交易安全，犯罪情節非輕，暨其行為\n    手段、素行、犯罪後態度等一切情狀，量處如主文所示之刑\n    ，並諭知易科罰金之折算標準。\n二、據上論斷，應依刑事訴訟法第449 條第1 項前段、第3 項、\n    第454 條第2 項，刑法第339 條第1 項、第30條第1 項前段\n    、第2 項、第47條第1 項、第41條第1 項前段，刑法施行法\n    第1 條之1 第1 項、第2 項前段，逕以簡易判決處刑如主文\n    。\n三、如不服本判決，應於判決送達後10日內，向本院提出上訴狀\n    （應附繕本），上訴於本院合議庭。",
    "reason": "一、本件犯罪事實及證據併所犯法條，均引用臺灣桃園地方法院\n    檢察署檢察官聲請簡易判決處刑書之記載（如附件），並補\n    充及更正：\n  (一)犯罪事實欄應補充：「甲○○前曾因施用毒品案件，經本院\n    及臺灣雲林地方法院分別判處有期徒刑8 月、1 年2 月確定\n    ，二罪接續執行，於民國95年8 月22日縮短刑期假釋出監併\n    付保護管束，迄於96年1 月6 日縮刑期滿，假釋未經撤銷，\n    其未執行之刑以已執行完畢論。」\n  (二)按幫助犯係從屬於正犯而成立，以正犯已經犯罪為要件，故\n    幫助犯並非其幫助行為一經完成，即成立犯罪，必其幫助行\n    為或其影響力持續至正犯實施犯罪始行成立，是本件被告甲\n    ○○之犯罪時間當以正犯之犯罪行為時間（即民國98年7 月\n    3 日詐欺集團正犯向被害人乙○○施用詐術之時間）為準，\n    至為明確。\n  (三)核被告甲○○所為，係犯刑法第339 條第1 項之詐欺取財罪\n    。被告對詐欺正犯提供帳戶資以助力，但並未參與詐欺犯罪\n    行為之實行，應屬幫助他人實行犯罪行為，為幫助犯，乃依\n    刑法第30條第2 項之規定減輕其刑。又被告有如上所示之犯\n    罪前科與執行情形，此有臺灣高等法院被告前案紀錄表存卷\n    可按，其於5 年以內故意再犯本件有期徒刑以上之罪，為累\n    犯，應依刑法第47條第1 項之規定加重其刑，併先加後減之\n    。爰審酌被告輕易提供金融帳戶資料供他人掩飾犯罪所得使\n    用，非但增加被害人尋求救濟之困難，造成社會人心不安，\n    亦助長詐騙犯罪者之氣焰，使詐欺犯罪者得以順利取得詐欺\n    所得之財物，危害財產交易安全，犯罪情節非輕，暨其行為\n    手段、素行、犯罪後態度等一切情狀，量處如主文所示之刑\n    ，並諭知易科罰金之折算標準。\n二、據上論斷，應依刑事訴訟法第449 條第1 項前段、第3 項、\n    第454 條第2 項，刑法第339 條第1 項、第30條第1 項前段\n    、第2 項、第47條第1 項、第41條第1 項前段，刑法施行法\n    第1 條之1 第1 項、第2 項前段，逕以簡易判決處刑如主文\n    。\n三、如不服本判決，應於判決送達後10日內，向本院提出上訴狀\n    （應附繕本），上訴於本院合議庭。"
  },
  "characters": {
    "judges": [
      "陳德池"
    ],
    "prosecutors": [

    ],
    "lawyers": [

    ],
    "clerks": [
      "謝雅茹"
    ],
    "plaintiffs": [

    ],
    "defendants": [
      "甲○○"
    ],
    "prosecutor_office": [
      "臺灣桃園地方法院檢察署檢察官"
    ],
    "creditors": [

    ],
    "debtors": [

    ],
    "judicial_associate_officer": [

    ]
  },
  "adjudged_at": "2010-05-12",
  "created_at": "2016-01-05 12:36:42",
  "updated_at": "2016-01-05 12:36:42"
}