{
  "identify": "TYD-99-桃交簡-1442-20100512-1",
  "court": {
    "name": "臺灣桃園地方法院",
    "code": "TYD"
  },
  "division": {
    "name": "刑事",
    "code": "M"
  },
  "year": 99,
  "word": "桃交簡",
  "number": "1442",
  "jcheck": "1",
  "reason": "公共危險",
  "content": "臺灣桃園地方法院刑事簡易判決      99年度桃交簡字第1442號\n聲  請  人  臺灣桃園地方法院檢察署檢察官\n被      告  甲○○\n上列被告因公共危險案件，經檢察官聲請以簡易判決處刑（99年\n度偵字第8222號），本院判決如下：\n    主      文\n甲○○服用酒類，不能安全駕駛動力交通工具而駕駛，處拘役伍\n拾日，如易科罰金，以新臺幣壹仟元折算壹日。\n    事實及理由\n一、本件犯罪事實及證據，併所犯法條，均引用臺灣桃園地方法\n    院檢察署檢察官聲請簡易判決處刑書之記載（如附件），並\n    補充：核被告甲○○所為，係犯刑法第185 條之3 之公共危\n    險罪。爰審酌被告前無酒駕前科，本次酒後駕車行為確實有\n    害於交通安全，對他人生命、身體、財產造成莫大危險，暨\n    其犯後態度、智識程度、生活狀況等一切情狀，量處如主文\n    所示之刑，並諭知易科罰金之折算標準。\n二、依刑事訴訟法第449 條第1 項前段、第3 項、第454 條第2\n    項，刑法第185 條之3 、第41條第1 項前段，刑法施行法第\n    1 條之1 第1 項，逕以簡易判決處刑如主文。\n三、如不服本判決，應於判決送達後10日內，向本院提出上訴狀\n    （應附繕本），上訴於本院合議庭。\n中    華    民    國    99    年    5     月    12    日\n                  交通法庭    法  官  陳德池\n以上正本證明與原本無異。\n如不服本判決，應於判決送達後10日內向本院提出上訴狀（應附\n繕本）。\n                              書記官  謝雅茹\n中    華    民    國    99    年    5     月    19    日\n附錄論罪科刑法條全文：\n刑法第185條之3：\n服用毒品、麻醉藥品酒類或其他相類之物，不能安全駕駛動力交\n通工具而駕駛者，處一年以下有期徒刑、拘役或十五萬元以下罰\n金。\n附件：臺灣桃園地方法院檢察署檢察官99年度偵字第8222號聲請\n      簡易判決處刑書1 份。",
  "structure": {
    "main": "甲○○服用酒類，不能安全駕駛動力交通工具而駕駛，處拘役伍\n拾日，如易科罰金，以新臺幣壹仟元折算壹日。",
    "fact": "一、本件犯罪事實及證據，併所犯法條，均引用臺灣桃園地方法\n    院檢察署檢察官聲請簡易判決處刑書之記載（如附件），並\n    補充：核被告甲○○所為，係犯刑法第185 條之3 之公共危\n    險罪。爰審酌被告前無酒駕前科，本次酒後駕車行為確實有\n    害於交通安全，對他人生命、身體、財產造成莫大危險，暨\n    其犯後態度、智識程度、生活狀況等一切情狀，量處如主文\n    所示之刑，並諭知易科罰金之折算標準。\n二、依刑事訴訟法第449 條第1 項前段、第3 項、第454 條第2\n    項，刑法第185 條之3 、第41條第1 項前段，刑法施行法第\n    1 條之1 第1 項，逕以簡易判決處刑如主文。\n三、如不服本判決，應於判決送達後10日內，向本院提出上訴狀\n    （應附繕本），上訴於本院合議庭。",
    "reason": "一、本件犯罪事實及證據，併所犯法條，均引用臺灣桃園地方法\n    院檢察署檢察官聲請簡易判決處刑書之記載（如附件），並\n    補充：核被告甲○○所為，係犯刑法第185 條之3 之公共危\n    險罪。爰審酌被告前無酒駕前科，本次酒後駕車行為確實有\n    害於交通安全，對他人生命、身體、財產造成莫大危險，暨\n    其犯後態度、智識程度、生活狀況等一切情狀，量處如主文\n    所示之刑，並諭知易科罰金之折算標準。\n二、依刑事訴訟法第449 條第1 項前段、第3 項、第454 條第2\n    項，刑法第185 條之3 、第41條第1 項前段，刑法施行法第\n    1 條之1 第1 項，逕以簡易判決處刑如主文。\n三、如不服本判決，應於判決送達後10日內，向本院提出上訴狀\n    （應附繕本），上訴於本院合議庭。"
  },
  "characters": {
    "judges": [
      "陳德池"
    ],
    "prosecutors": [

    ],
    "lawyers": [

    ],
    "clerks": [
      "謝雅茹"
    ],
    "plaintiffs": [

    ],
    "defendants": [
      "甲○○"
    ],
    "prosecutor_office": [
      "臺灣桃園地方法院檢察署檢察官"
    ],
    "creditors": [

    ],
    "debtors": [

    ],
    "judicial_associate_officer": [

    ]
  },
  "adjudged_at": "2010-05-12",
  "created_at": "2016-01-05 12:37:55",
  "updated_at": "2016-01-05 12:37:55"
}