{
  "identify": "TYD-99-交易-117-20100512-1",
  "court": {
    "name": "臺灣桃園地方法院",
    "code": "TYD"
  },
  "division": {
    "name": "刑事",
    "code": "M"
  },
  "year": 99,
  "word": "交易",
  "number": "117",
  "jcheck": "1",
  "reason": "公共危險",
  "content": "臺灣桃園地方法院刑事判決             99年度交易字第117號\n公  訴  人  臺灣桃園地方法院檢察署檢察官\n被      告  乙○○\n上列被告因公共危險案件，經檢察官聲請以簡易判決處刑（99年\n度撤緩偵字第104 號），本院認不得以簡易判決處刑（99年度壢\n交簡字第722 號），改依通常程序審理，判決如下：\n    主  文\n本件公訴不受理。\n    理  由\n一、聲請簡易判決處刑意旨略以：被告乙○○自民國98年4 月5\n    日中午12時許起至同日下午1 時許止，在桃園縣平鎮市某檳\n    榔攤，飲用約2 瓶米酒後，已達不能安全駕駛動力交通工具\n    之程度，仍於飲酒結束後某時，自該處騎乘車牌號碼BWZ －\n    125 號輕型機車上路，嗣於同日下午2時21 分許，在桃園縣\n    平鎮市○○路○○段1 巷42弄口，為警查獲，測得其呼氣所\n    含酒精濃度為每公升1.08毫克，因認被告涉犯刑法第185 條\n    之3 之公共危險罪嫌。\n二、按起訴之程序違背規定者，應諭知不受理之判決，並得不經\n    言詞辯論為之。再檢察官為緩起訴處分者，得命被告於一定\n    期間內遵守或履行刑事訴訟法第253 條之2 第1 項各款所定\n    事項。被告於緩起訴期間內如有違背上開應遵守或履行事項\n    之情形，檢察官固得依職權或依告訴人之聲請，撤銷原緩起\n    訴處分，繼續偵查或起訴；惟檢察官撤銷前所為之緩起訴處\n    分者，應製作處分書敘述其處分之理由，並將正本送達於被\n    告；被告接受撤銷緩起訴處分書後，得於七日內以書狀敘述\n    不服之理由，經原檢察官向直接上級法院檢察署檢察長或檢\n    察總長聲請再議。是以在撤銷原緩起訴處分未確定前，檢察\n    官尚不得對同一事實再行起訴，否則將使撤銷緩起訴處分程\n    序及被告得聲請再議之規定形同具文，如檢察官未於緩起訴\n    期間內踐行上揭法定之撤銷緩起訴處分程序而逕行起訴或聲\n    請以簡易判決處刑，其起訴程序應屬違背規定，依刑事訴訟\n    法第303 條第1 款規定，應諭知公訴不受理之判決，此觀刑\n    事訴訟法第253 條之3 第1 項第3 款、第255 條第1 項、第\n    2 項、第256 條之1 規定甚明。\n三、經查：\n  (一)被告乙○○涉犯上開公共危險案件，經臺灣桃園地方法院檢\n    察署檢察官於98年4 月13日，以98年度速偵字第2416號為緩\n    起訴處分，期間為二年。嗣該緩起訴處分經職權再議，並經\n    臺灣高等法院檢察署檢察長處分駁回，而於98年5 月6 日確\n    定；被告因未於緩起訴履行期間內，向財團法人犯罪被害人\n    保護協會臺灣桃園分會支付新臺幣1 萬元之應履行事項，經\n    檢察官於98年11月24日撤銷前開緩起訴處分。上開撤銷緩起\n    訴處分書於98年12月16日，分別向被告當時所陳報之戶籍地\n    及居住地為寄存送達，且迄至99年4 月16日止，被告均未前\n    往寄存之平鎮、北勢派出所領取撤銷緩起訴處分書等節，有\n    上開緩起訴處分書、臺灣高等法院檢察署98年5 月12日檢紀\n    信字第0980001543號函及所附處分書、撤銷緩起訴處分書、\n    臺灣高等法院被告前案紀錄表、送達證書、桃園縣政府警察\n    局平鎮分局99年4 月16日平警分刑字第0996013502號函所檢\n    附之司法文書郵件登記簿在卷（見臺灣桃園地方法院檢察署\n    98年度速偵字第2416號卷第27頁、第29頁至第30頁，同上地\n    檢署98年度撤緩字第676 號卷第2 頁至第4 頁、本院99年度\n    壢交簡字第722 號卷第8 頁至第10頁）可查，應甚明確，而\n    堪認定。則檢察官將前開撤銷緩起訴處分書向上址為寄存送\n    達，固無不合，然：\n  (二)按送達於在監獄或看守所之人，應囑託該監所長官為之，刑\n    事訴訟法第56條第2 項定有明文，依此規定，被告如在監獄\n    執行刑罰，檢察官應囑託監獄長官將撤銷緩起訴處分書正本\n    送達於被告，不得將之送達於被告住所，或寄存送達於警察\n    機關，其理至明。本院查：被告自乙○○98年11月5 日起至\n    同年12月29日止，係在臺灣桃園監獄執行刑罰，此有臺灣高\n    等法院被告前案紀錄表、臺灣桃園監獄98年11月20日桃監總\n    字第0980401929號函及所附執行指揮書在卷（見同上檢察署\n    98年度撤緩字第676 號卷第5 頁至第6 頁）可憑，而本件撤\n    銷緩起訴處分書以寄存方式送達時（即98年12月16日），被\n    告恰於監所執行刑罰，揆之前揭說明，本件撤銷緩起訴處分\n    書自應囑託監獄長官送達於被告，不得寄存送達於警察機關\n    ，然本件撤銷緩起訴處分書除以前述方式為寄存送達外，確\n    未囑託監獄長官送達於被告，亦有臺灣桃園地方法院檢察署\n    99年4 月29日甲○堂陽98撤緩676 字第34519 號函可佐（見\n    本院99年度壢交簡字第722 號卷第15頁），且本院亦查無卷\n    內有何證據證明檢察官嗣後有再次合法送達之情形，足認本\n    件檢察官並未合法送達撤銷緩起訴處分書正本於被告，至為\n    明確。\n  (三)再本件撤銷緩起訴處分書雖曾於緩起訴處分期間內之98年11\n    月27日對外公告（見本院99年度壢交簡字第722 號卷第6 頁\n    之電話紀錄查詢表），然緩起訴處分確定後，有拘束檢察官\n    之效力，檢察官於緩起訴期間內對於同一被告之同一案件，\n    除有合於刑事訴訟法第253 條之3 之情形，並撤銷原處分外\n    ，不得繼續偵查或起訴；緩起訴期間屆滿而緩起訴處分未經\n    撤銷者，非有刑事訴訟法第260 條所定事由，不得再行起訴\n    。又刑事訴訟法第255 條第1 項、第2 項規定撤銷緩起訴處\n    分，應製作處分書，敘述理由，處分書正本應送達於被告，\n    其規範目的，除使被告知悉此一攸關權益之處分理由外，亦\n    寓有落實刑事訴訟法第256 條之1 賦予被告得就撤銷緩起訴\n    處分聲請再議之旨，以保障被告之救濟機會，並使上級檢察\n    署檢察官得以審查處分之當否。是以聲請再議之期間，自收\n    受處分書正本之翌日起算，若未為合法之送達，自無從起算\n    再議之期間，撤銷緩起訴處分即尚未生效。實務上以檢察官\n    之偵查處分無如判決宣示之規定，為恐不肖之徒在處分書送\n    達前招搖撞騙，故均將處分結果先行公告，以昭公信。該公\n    告固有將檢察官之決定公示於外之形式，然而究非法定送達\n    方法，亦不能資為聲請再議期間起算之依據，其法律效果無\n    從與送達同視。檢察官尚不得於緩起訴期間內，在撤銷原緩\n    起訴處分未確定前，即對同一案件再行起訴，而使撤銷緩起\n    訴處分程序及被告得聲請再議之規定形同具文。是本件檢察\n    官既未於緩起訴期間內踐行上揭法定之撤銷緩起訴處分程序\n    而逕行聲請以簡易判決處刑，其聲請即起訴程序自屬違背規\n    定。\n四、綜上所述，本件檢察官未合法送達撤銷緩起訴處分書正本於\n    被告乙○○，撤銷緩起訴處分之再議期間即無從起算，被告\n    亦無對該撤銷緩起訴處分聲請再議之機會，該撤銷緩起訴處\n    分自不發生確定之效力。從而，公訴人於撤銷緩起訴處分未\n    確定前，對被告上開犯行聲請簡易判決處刑，揆諸前揭說明\n    ，其起訴程序不合規定，且其瑕疵無從補正治癒，依刑事訴\n    訟法第303 條第1 款之規定，爰不經言詞辯論，逕為不受理\n    判決之諭知。\n五、本件係檢察官聲請以簡易判決處刑案件，因有刑事訴訟法第\n    451 條之1 第4 項但書第3 款情形，依同法第452 條規定適\n    用通常程序審判。\n據上論斷，應依刑事訴訟法第452 條、第303 條第1 款、第307\n條，判決如主文。\n中    華    民    國    99    年    5     月    12    日\n                  刑事第二庭  審判長  法  官  徐培元\n                                      法  官  柯姿佐\n                                      法  官  陳德池\n以上正本證明與原本無異。\n如不服本判決應於收受判決後10日內向本院提出上訴書狀，並應\n敘述具體理由。其未敘述上訴理由者，應於上訴期間屆滿後20日\n內向本院補提理由書( 均須按他造當事人之人數附繕本) 「切勿\n逕送上級法院」。\n                                      書記官  謝雅茹\n中    華    民    國    99    年    5     月    14    日",
  "structure": {
    "main": "本件公訴不受理。",
    "reason": "一、聲請簡易判決處刑意旨略以：被告乙○○自民國98年4 月5\n    日中午12時許起至同日下午1 時許止，在桃園縣平鎮市某檳\n    榔攤，飲用約2 瓶米酒後，已達不能安全駕駛動力交通工具\n    之程度，仍於飲酒結束後某時，自該處騎乘車牌號碼BWZ －\n    125 號輕型機車上路，嗣於同日下午2時21 分許，在桃園縣\n    平鎮市○○路○○段1 巷42弄口，為警查獲，測得其呼氣所\n    含酒精濃度為每公升1.08毫克，因認被告涉犯刑法第185 條\n    之3 之公共危險罪嫌。\n二、按起訴之程序違背規定者，應諭知不受理之判決，並得不經\n    言詞辯論為之。再檢察官為緩起訴處分者，得命被告於一定\n    期間內遵守或履行刑事訴訟法第253 條之2 第1 項各款所定\n    事項。被告於緩起訴期間內如有違背上開應遵守或履行事項\n    之情形，檢察官固得依職權或依告訴人之聲請，撤銷原緩起\n    訴處分，繼續偵查或起訴；惟檢察官撤銷前所為之緩起訴處\n    分者，應製作處分書敘述其處分之理由，並將正本送達於被\n    告；被告接受撤銷緩起訴處分書後，得於七日內以書狀敘述\n    不服之理由，經原檢察官向直接上級法院檢察署檢察長或檢\n    察總長聲請再議。是以在撤銷原緩起訴處分未確定前，檢察\n    官尚不得對同一事實再行起訴，否則將使撤銷緩起訴處分程\n    序及被告得聲請再議之規定形同具文，如檢察官未於緩起訴\n    期間內踐行上揭法定之撤銷緩起訴處分程序而逕行起訴或聲\n    請以簡易判決處刑，其起訴程序應屬違背規定，依刑事訴訟\n    法第303 條第1 款規定，應諭知公訴不受理之判決，此觀刑\n    事訴訟法第253 條之3 第1 項第3 款、第255 條第1 項、第\n    2 項、第256 條之1 規定甚明。\n三、經查：\n  (一)被告乙○○涉犯上開公共危險案件，經臺灣桃園地方法院檢\n    察署檢察官於98年4 月13日，以98年度速偵字第2416號為緩\n    起訴處分，期間為二年。嗣該緩起訴處分經職權再議，並經\n    臺灣高等法院檢察署檢察長處分駁回，而於98年5 月6 日確\n    定；被告因未於緩起訴履行期間內，向財團法人犯罪被害人\n    保護協會臺灣桃園分會支付新臺幣1 萬元之應履行事項，經\n    檢察官於98年11月24日撤銷前開緩起訴處分。上開撤銷緩起\n    訴處分書於98年12月16日，分別向被告當時所陳報之戶籍地\n    及居住地為寄存送達，且迄至99年4 月16日止，被告均未前\n    往寄存之平鎮、北勢派出所領取撤銷緩起訴處分書等節，有\n    上開緩起訴處分書、臺灣高等法院檢察署98年5 月12日檢紀\n    信字第0980001543號函及所附處分書、撤銷緩起訴處分書、\n    臺灣高等法院被告前案紀錄表、送達證書、桃園縣政府警察\n    局平鎮分局99年4 月16日平警分刑字第0996013502號函所檢\n    附之司法文書郵件登記簿在卷（見臺灣桃園地方法院檢察署\n    98年度速偵字第2416號卷第27頁、第29頁至第30頁，同上地\n    檢署98年度撤緩字第676 號卷第2 頁至第4 頁、本院99年度\n    壢交簡字第722 號卷第8 頁至第10頁）可查，應甚明確，而\n    堪認定。則檢察官將前開撤銷緩起訴處分書向上址為寄存送\n    達，固無不合，然：\n  (二)按送達於在監獄或看守所之人，應囑託該監所長官為之，刑\n    事訴訟法第56條第2 項定有明文，依此規定，被告如在監獄\n    執行刑罰，檢察官應囑託監獄長官將撤銷緩起訴處分書正本\n    送達於被告，不得將之送達於被告住所，或寄存送達於警察\n    機關，其理至明。本院查：被告自乙○○98年11月5 日起至\n    同年12月29日止，係在臺灣桃園監獄執行刑罰，此有臺灣高\n    等法院被告前案紀錄表、臺灣桃園監獄98年11月20日桃監總\n    字第0980401929號函及所附執行指揮書在卷（見同上檢察署\n    98年度撤緩字第676 號卷第5 頁至第6 頁）可憑，而本件撤\n    銷緩起訴處分書以寄存方式送達時（即98年12月16日），被\n    告恰於監所執行刑罰，揆之前揭說明，本件撤銷緩起訴處分\n    書自應囑託監獄長官送達於被告，不得寄存送達於警察機關\n    ，然本件撤銷緩起訴處分書除以前述方式為寄存送達外，確\n    未囑託監獄長官送達於被告，亦有臺灣桃園地方法院檢察署\n    99年4 月29日甲○堂陽98撤緩676 字第34519 號函可佐（見\n    本院99年度壢交簡字第722 號卷第15頁），且本院亦查無卷\n    內有何證據證明檢察官嗣後有再次合法送達之情形，足認本\n    件檢察官並未合法送達撤銷緩起訴處分書正本於被告，至為\n    明確。\n  (三)再本件撤銷緩起訴處分書雖曾於緩起訴處分期間內之98年11\n    月27日對外公告（見本院99年度壢交簡字第722 號卷第6 頁\n    之電話紀錄查詢表），然緩起訴處分確定後，有拘束檢察官\n    之效力，檢察官於緩起訴期間內對於同一被告之同一案件，\n    除有合於刑事訴訟法第253 條之3 之情形，並撤銷原處分外\n    ，不得繼續偵查或起訴；緩起訴期間屆滿而緩起訴處分未經\n    撤銷者，非有刑事訴訟法第260 條所定事由，不得再行起訴\n    。又刑事訴訟法第255 條第1 項、第2 項規定撤銷緩起訴處\n    分，應製作處分書，敘述理由，處分書正本應送達於被告，\n    其規範目的，除使被告知悉此一攸關權益之處分理由外，亦\n    寓有落實刑事訴訟法第256 條之1 賦予被告得就撤銷緩起訴\n    處分聲請再議之旨，以保障被告之救濟機會，並使上級檢察\n    署檢察官得以審查處分之當否。是以聲請再議之期間，自收\n    受處分書正本之翌日起算，若未為合法之送達，自無從起算\n    再議之期間，撤銷緩起訴處分即尚未生效。實務上以檢察官\n    之偵查處分無如判決宣示之規定，為恐不肖之徒在處分書送\n    達前招搖撞騙，故均將處分結果先行公告，以昭公信。該公\n    告固有將檢察官之決定公示於外之形式，然而究非法定送達\n    方法，亦不能資為聲請再議期間起算之依據，其法律效果無\n    從與送達同視。檢察官尚不得於緩起訴期間內，在撤銷原緩\n    起訴處分未確定前，即對同一案件再行起訴，而使撤銷緩起\n    訴處分程序及被告得聲請再議之規定形同具文。是本件檢察\n    官既未於緩起訴期間內踐行上揭法定之撤銷緩起訴處分程序\n    而逕行聲請以簡易判決處刑，其聲請即起訴程序自屬違背規\n    定。\n四、綜上所述，本件檢察官未合法送達撤銷緩起訴處分書正本於\n    被告乙○○，撤銷緩起訴處分之再議期間即無從起算，被告\n    亦無對該撤銷緩起訴處分聲請再議之機會，該撤銷緩起訴處\n    分自不發生確定之效力。從而，公訴人於撤銷緩起訴處分未\n    確定前，對被告上開犯行聲請簡易判決處刑，揆諸前揭說明\n    ，其起訴程序不合規定，且其瑕疵無從補正治癒，依刑事訴\n    訟法第303 條第1 款之規定，爰不經言詞辯論，逕為不受理\n    判決之諭知。\n五、本件係檢察官聲請以簡易判決處刑案件，因有刑事訴訟法第\n    451 條之1 第4 項但書第3 款情形，依同法第452 條規定適\n    用通常程序審判。\n據上論斷，應依刑事訴訟法第452 條、第303 條第1 款、第307\n條，判決如主文。"
  },
  "characters": {
    "judges": [
      "徐培元",
      "柯姿佐",
      "陳德池"
    ],
    "prosecutors": [

    ],
    "lawyers": [

    ],
    "clerks": [
      "謝雅茹"
    ],
    "plaintiffs": [

    ],
    "defendants": [
      "乙○○"
    ],
    "prosecutor_office": [
      "臺灣桃園地方法院檢察署檢察官"
    ],
    "creditors": [

    ],
    "debtors": [

    ],
    "judicial_associate_officer": [

    ]
  },
  "adjudged_at": "2010-05-12",
  "created_at": "2016-01-05 12:36:21",
  "updated_at": "2016-01-05 12:36:21"
}