{
  "identify": "TYD-99-桃簡-942-20100512-1",
  "court": {
    "name": "臺灣桃園地方法院",
    "code": "TYD"
  },
  "division": {
    "name": "刑事",
    "code": "M"
  },
  "year": 99,
  "word": "桃簡",
  "number": "942",
  "jcheck": "1",
  "reason": "業務過失致死",
  "content": "臺灣桃園地方法院刑事簡易判決         99年度桃簡字第942號\n聲  請  人  臺灣桃園地方法院檢察署檢察官\n被      告  甲○○\n上列被告因業務過失致死案件，經檢察官聲請以簡易判決處刑（\n99年度撤緩偵字第134 號），本院判決如下：\n    主      文\n甲○○從事業務之人，因業務上之過失致人於死，處有期徒刑伍\n月，如易科罰金，以新臺幣壹仟元折算壹日。緩刑貳年。\n    事實及理由\n一、本件犯罪事實及證據，併所犯法條，均引用臺灣桃園地方法\n    院檢察署檢察官聲請簡易判決處刑書之記載（如附件），並\n    補充：\n  (一)犯罪事實欄第2 行「為從事營建業務之人」後，另補充：「\n    屬勞工安全衛生法所稱之雇主」；犯罪事實欄第3 行「對於\n    屋頂、施工架、工作台應依規定設置護欄、護蓋，以防墜落\n    之危險」，更正為：「於工作場所邊緣及開口部份，勞工有\n    遭受墜落危險之虞者，應設有適當強度之圍欄、握把、覆蓋\n    等防護措施；若前項措施顯有困難，亦應採取使勞工使用安\n    全帶等防止因墜落而致勞工遭受危險之措施」。\n  (二)按雇主為防止有墜落之虞作業場所所引起之危害，應有符合\n    標準之必要安全設備，勞工安全衛生法第5 條第1 項第5 款\n    定有明文；又雇主對於高度在二公尺以上之工作場所邊緣及\n    開口部份，勞工有遭受墜落危險之虞者，應設有適當強度之\n    圍欄、握把、覆蓋等防護措施。雇主為前項措施顯有困難，\n    或作業之需要臨時將圍欄等拆除，應採取使勞工使用安全帶\n    等防止因墜落而致勞工遭受危險之措施；雇主對於在高度二\n    公尺以上之高處作業，勞工有墜落之虞者，應使勞工確實使\n    用安全帶、安全帽及其他必要之防護具，亦為勞工安全衛生\n    設施規則第224 條、第281 條第1 項所明定；被告甲○○既\n    係勞工安全衛生法第2 條第2 項稱之雇主，自應注意上揭規\n    定內容，設置相關防護措施，且依其情形並無不能注意之情\n    事，竟疏未注意設置，以致受僱員工乙○不慎墜落死亡，其\n    違反前揭規定而有過失甚明，致生死亡之職業災害，至為明\n    確，是核其為從事業務之人，因業務上之過失致人於死之行\n    為，係犯刑法第276 條第2 項之業務過失致死罪；又其為僱\n    主，違反勞工安全衛生法第5 條第1 項第5 款之規定，致發\n    生同法第28條第2 項第1 款勞工死亡之職業災害之行為，係\n    犯勞工安全衛生法第31條第1 項之罪。被告以一行為而犯上\n    開二罪名，應依刑法第55條想像競合犯之規定，從一重依業\n    務過失致死罪處斷。聲請人雖未引用勞工安全衛生法，惟於\n    事實欄已明確記載該部分之事實，且與業務過失致死罪為想\n    像競合犯之裁判上一罪關係，本院自應加以裁判。\n  (三)爰審酌被告過失情節非輕，致被害人傷重不治死亡、犯後坦\n    承犯行、已與被害人家屬和解、素行、智識程度等一切情狀\n    ，量處如主文所示之刑，並諭知易科罰金之折算標準，以示\n    懲儆。末查，本件被告前未曾因故意犯罪受有期徒刑以上刑\n    之宣告，此有臺灣高等法院被告前案紀錄表1 份在卷可稽，\n    其因一時失慮，致罹刑章，犯罪後已坦承犯行，且已達成和\n    解，經此偵審教訓，自當知所警惕，信無再犯之虞，因認前\n    開宣告之刑以暫不執行為適當，併宣告緩刑2 年，以啟自新\n    。\n二、依刑事訴訟法第449 條第1 項前段、第3 項、第454 條第2\n    項，勞工安全衛生法第31條第1 項，刑法第11條前段、第27\n    6 條第2 項、第55條、第41條第1 項前段、第74條第1 項第\n    1 款，刑法施行法第1 條之1 第1 項、第2 項前段，判決如\n    主文。\n三、如不服本判決，應於判決送達後10日內，向本院提出上訴狀\n    （應附繕本），上訴於本院合議庭。\n中    華    民    國    99    年    5     月    12    日\n                  刑事第二庭  法  官  陳德池\n以上正本證明與原本無異。\n如不服本判決，應於判決送達後10日內向本院提出上訴狀（應附\n繕本）。\n                              書記官  謝雅茹\n中    華    民    國    99    年    5     月    14    日\n附錄論罪科刑法條全文：\n勞工安全衛生法第31條\n違反第5 條第1 項或第8 條第1 項之規定，致發生第28條第2 項\n第1 款之職業災害者，處3 年以下有期徒刑、拘役或科或併科新\n臺幣15萬元以下罰金。\n法人犯前項之罪者，除處罰其負責人外，對該法人亦科以前項之\n罰金。\n刑法第276 條第2 項\n從事業務之人，因業務上之過失犯前項之罪者，處5 年以下有期\n徒刑或拘役，得併科3 千元以下罰金。\n附件：臺灣桃園地方法院檢察署檢察官99年度撤緩偵字第134 號\n      聲請簡易判決處刑書1 份。",
  "structure": {
    "main": "甲○○從事業務之人，因業務上之過失致人於死，處有期徒刑伍\n月，如易科罰金，以新臺幣壹仟元折算壹日。緩刑貳年。",
    "fact": "一、本件犯罪事實及證據，併所犯法條，均引用臺灣桃園地方法\n    院檢察署檢察官聲請簡易判決處刑書之記載（如附件），並\n    補充：\n  (一)犯罪事實欄第2 行「為從事營建業務之人」後，另補充：「\n    屬勞工安全衛生法所稱之雇主」；犯罪事實欄第3 行「對於\n    屋頂、施工架、工作台應依規定設置護欄、護蓋，以防墜落\n    之危險」，更正為：「於工作場所邊緣及開口部份，勞工有\n    遭受墜落危險之虞者，應設有適當強度之圍欄、握把、覆蓋\n    等防護措施；若前項措施顯有困難，亦應採取使勞工使用安\n    全帶等防止因墜落而致勞工遭受危險之措施」。\n  (二)按雇主為防止有墜落之虞作業場所所引起之危害，應有符合\n    標準之必要安全設備，勞工安全衛生法第5 條第1 項第5 款\n    定有明文；又雇主對於高度在二公尺以上之工作場所邊緣及\n    開口部份，勞工有遭受墜落危險之虞者，應設有適當強度之\n    圍欄、握把、覆蓋等防護措施。雇主為前項措施顯有困難，\n    或作業之需要臨時將圍欄等拆除，應採取使勞工使用安全帶\n    等防止因墜落而致勞工遭受危險之措施；雇主對於在高度二\n    公尺以上之高處作業，勞工有墜落之虞者，應使勞工確實使\n    用安全帶、安全帽及其他必要之防護具，亦為勞工安全衛生\n    設施規則第224 條、第281 條第1 項所明定；被告甲○○既\n    係勞工安全衛生法第2 條第2 項稱之雇主，自應注意上揭規\n    定內容，設置相關防護措施，且依其情形並無不能注意之情\n    事，竟疏未注意設置，以致受僱員工乙○不慎墜落死亡，其\n    違反前揭規定而有過失甚明，致生死亡之職業災害，至為明\n    確，是核其為從事業務之人，因業務上之過失致人於死之行\n    為，係犯刑法第276 條第2 項之業務過失致死罪；又其為僱\n    主，違反勞工安全衛生法第5 條第1 項第5 款之規定，致發\n    生同法第28條第2 項第1 款勞工死亡之職業災害之行為，係\n    犯勞工安全衛生法第31條第1 項之罪。被告以一行為而犯上\n    開二罪名，應依刑法第55條想像競合犯之規定，從一重依業\n    務過失致死罪處斷。聲請人雖未引用勞工安全衛生法，惟於\n    事實欄已明確記載該部分之事實，且與業務過失致死罪為想\n    像競合犯之裁判上一罪關係，本院自應加以裁判。\n  (三)爰審酌被告過失情節非輕，致被害人傷重不治死亡、犯後坦\n    承犯行、已與被害人家屬和解、素行、智識程度等一切情狀\n    ，量處如主文所示之刑，並諭知易科罰金之折算標準，以示\n    懲儆。末查，本件被告前未曾因故意犯罪受有期徒刑以上刑\n    之宣告，此有臺灣高等法院被告前案紀錄表1 份在卷可稽，\n    其因一時失慮，致罹刑章，犯罪後已坦承犯行，且已達成和\n    解，經此偵審教訓，自當知所警惕，信無再犯之虞，因認前\n    開宣告之刑以暫不執行為適當，併宣告緩刑2 年，以啟自新\n    。\n二、依刑事訴訟法第449 條第1 項前段、第3 項、第454 條第2\n    項，勞工安全衛生法第31條第1 項，刑法第11條前段、第27\n    6 條第2 項、第55條、第41條第1 項前段、第74條第1 項第\n    1 款，刑法施行法第1 條之1 第1 項、第2 項前段，判決如\n    主文。\n三、如不服本判決，應於判決送達後10日內，向本院提出上訴狀\n    （應附繕本），上訴於本院合議庭。",
    "reason": "一、本件犯罪事實及證據，併所犯法條，均引用臺灣桃園地方法\n    院檢察署檢察官聲請簡易判決處刑書之記載（如附件），並\n    補充：\n  (一)犯罪事實欄第2 行「為從事營建業務之人」後，另補充：「\n    屬勞工安全衛生法所稱之雇主」；犯罪事實欄第3 行「對於\n    屋頂、施工架、工作台應依規定設置護欄、護蓋，以防墜落\n    之危險」，更正為：「於工作場所邊緣及開口部份，勞工有\n    遭受墜落危險之虞者，應設有適當強度之圍欄、握把、覆蓋\n    等防護措施；若前項措施顯有困難，亦應採取使勞工使用安\n    全帶等防止因墜落而致勞工遭受危險之措施」。\n  (二)按雇主為防止有墜落之虞作業場所所引起之危害，應有符合\n    標準之必要安全設備，勞工安全衛生法第5 條第1 項第5 款\n    定有明文；又雇主對於高度在二公尺以上之工作場所邊緣及\n    開口部份，勞工有遭受墜落危險之虞者，應設有適當強度之\n    圍欄、握把、覆蓋等防護措施。雇主為前項措施顯有困難，\n    或作業之需要臨時將圍欄等拆除，應採取使勞工使用安全帶\n    等防止因墜落而致勞工遭受危險之措施；雇主對於在高度二\n    公尺以上之高處作業，勞工有墜落之虞者，應使勞工確實使\n    用安全帶、安全帽及其他必要之防護具，亦為勞工安全衛生\n    設施規則第224 條、第281 條第1 項所明定；被告甲○○既\n    係勞工安全衛生法第2 條第2 項稱之雇主，自應注意上揭規\n    定內容，設置相關防護措施，且依其情形並無不能注意之情\n    事，竟疏未注意設置，以致受僱員工乙○不慎墜落死亡，其\n    違反前揭規定而有過失甚明，致生死亡之職業災害，至為明\n    確，是核其為從事業務之人，因業務上之過失致人於死之行\n    為，係犯刑法第276 條第2 項之業務過失致死罪；又其為僱\n    主，違反勞工安全衛生法第5 條第1 項第5 款之規定，致發\n    生同法第28條第2 項第1 款勞工死亡之職業災害之行為，係\n    犯勞工安全衛生法第31條第1 項之罪。被告以一行為而犯上\n    開二罪名，應依刑法第55條想像競合犯之規定，從一重依業\n    務過失致死罪處斷。聲請人雖未引用勞工安全衛生法，惟於\n    事實欄已明確記載該部分之事實，且與業務過失致死罪為想\n    像競合犯之裁判上一罪關係，本院自應加以裁判。\n  (三)爰審酌被告過失情節非輕，致被害人傷重不治死亡、犯後坦\n    承犯行、已與被害人家屬和解、素行、智識程度等一切情狀\n    ，量處如主文所示之刑，並諭知易科罰金之折算標準，以示\n    懲儆。末查，本件被告前未曾因故意犯罪受有期徒刑以上刑\n    之宣告，此有臺灣高等法院被告前案紀錄表1 份在卷可稽，\n    其因一時失慮，致罹刑章，犯罪後已坦承犯行，且已達成和\n    解，經此偵審教訓，自當知所警惕，信無再犯之虞，因認前\n    開宣告之刑以暫不執行為適當，併宣告緩刑2 年，以啟自新\n    。\n二、依刑事訴訟法第449 條第1 項前段、第3 項、第454 條第2\n    項，勞工安全衛生法第31條第1 項，刑法第11條前段、第27\n    6 條第2 項、第55條、第41條第1 項前段、第74條第1 項第\n    1 款，刑法施行法第1 條之1 第1 項、第2 項前段，判決如\n    主文。\n三、如不服本判決，應於判決送達後10日內，向本院提出上訴狀\n    （應附繕本），上訴於本院合議庭。"
  },
  "characters": {
    "judges": [
      "陳德池"
    ],
    "prosecutors": [

    ],
    "lawyers": [

    ],
    "clerks": [
      "謝雅茹"
    ],
    "plaintiffs": [

    ],
    "defendants": [
      "甲○○"
    ],
    "prosecutor_office": [
      "臺灣桃園地方法院檢察署檢察官"
    ],
    "creditors": [

    ],
    "debtors": [

    ],
    "judicial_associate_officer": [

    ]
  },
  "adjudged_at": "2010-05-12",
  "created_at": "2016-01-05 12:37:15",
  "updated_at": "2016-01-05 12:37:15"
}