{
  "identify": "TYD-99-審訴-555-20100512-1",
  "court": {
    "name": "臺灣桃園地方法院",
    "code": "TYD"
  },
  "division": {
    "name": "刑事",
    "code": "M"
  },
  "year": 99,
  "word": "審訴",
  "number": "555",
  "jcheck": "1",
  "reason": "毒品危害防制條例",
  "content": "臺灣桃園地方法院刑事裁定             99年度審訴字第555號\n公  訴  人  臺灣桃園地方法院檢察署檢察官\n被      告  甲○○\n即具保人\n上列被告因違反毒品危害防制條例案件，經檢察官提起公訴（99\n年度毒偵字第291號），本院依職權沒入保證金，茲裁定如下：\n    主      文\n甲○○繳納之保證金新臺幣壹萬元沒入之。\n    理      由\n一、按具保之被告逃匿者，應命具保人繳納指定之保證金額，並\n    沒入之。不繳納者，強制執行。保證金已繳納者，沒入之。\n    刑事訴訟法第118條第1項定有明文。\n二、本案被告甲○○因違反毒品危害防制條例案件，前經臺灣桃\n    園地方法院檢察署檢察官指定保證金新台幣（下同）1 萬元\n    ，經被告自行繳納該保證金後，已將被告釋放。茲因該被告\n    經合法傳喚未到庭，復經本院派警前往拘提未果，此有送達\n    回證及原刑事保證金收據、拘票、報告書等資料附卷可稽，\n    顯見被告已逃匿，核諸上開規定，應依法沒入被告所繳納之\n    保證金1 萬元。\n三、爰依刑事訴訟法第118 條第1 項、第121 條第1 項，裁定如\n    主文。\n中    華    民    國    99    年    5     月    12    日\n               刑事庭  審判長  法  官  林孟宜\n                               法  官  鍾雅蘭\n                               法  官  林靜梅\n以上正本證明與原本無異。\n如不服本裁定，應於裁定送達後5 日內向本院提出抗告狀。\n                              書記官  郭怡君\n中    華    民    國    99    年    5     月    12    日",
  "structure": {
    "main": "甲○○繳納之保證金新臺幣壹萬元沒入之。",
    "reason": "一、按具保之被告逃匿者，應命具保人繳納指定之保證金額，並\n    沒入之。不繳納者，強制執行。保證金已繳納者，沒入之。\n    刑事訴訟法第118條第1項定有明文。\n二、本案被告甲○○因違反毒品危害防制條例案件，前經臺灣桃\n    園地方法院檢察署檢察官指定保證金新台幣（下同）1 萬元\n    ，經被告自行繳納該保證金後，已將被告釋放。茲因該被告\n    經合法傳喚未到庭，復經本院派警前往拘提未果，此有送達\n    回證及原刑事保證金收據、拘票、報告書等資料附卷可稽，\n    顯見被告已逃匿，核諸上開規定，應依法沒入被告所繳納之\n    保證金1 萬元。\n三、爰依刑事訴訟法第118 條第1 項、第121 條第1 項，裁定如\n    主文。"
  },
  "characters": {
    "judges": [
      "林孟宜",
      "鍾雅蘭",
      "林靜梅"
    ],
    "prosecutors": [

    ],
    "lawyers": [

    ],
    "clerks": [
      "郭怡君"
    ],
    "plaintiffs": [

    ],
    "defendants": [
      "甲○○",
      "即具保人"
    ],
    "prosecutor_office": [
      "臺灣桃園地方法院檢察署檢察官"
    ],
    "creditors": [

    ],
    "debtors": [

    ],
    "judicial_associate_officer": [

    ]
  },
  "adjudged_at": "2010-05-12",
  "created_at": "2016-01-05 12:38:43",
  "updated_at": "2016-01-05 12:38:43"
}