{
  "identify": "TYD-99-壢簡-957-20100512-1",
  "court": {
    "name": "臺灣桃園地方法院",
    "code": "TYD"
  },
  "division": {
    "name": "刑事",
    "code": "M"
  },
  "year": 99,
  "word": "壢簡",
  "number": "957",
  "jcheck": "1",
  "reason": "詐欺",
  "content": "臺灣桃園地方法院刑事簡易判決         99年度壢簡字第957號\n聲  請  人  臺灣桃園地方法院檢察署檢察官\n被      告  甲○○\n上列被告因詐欺案件，經檢察官聲請以簡易判決處刑（98年度偵\n字第23781 號、98年度偵字第26778 號），本院判決如下：\n    主      文\n甲○○幫助意圖為自己不法之所有，以詐術使人將本人之物交付\n，處拘役伍拾日，如易科罰金，以新臺幣壹仟元折算壹日。\n    事實及理由\n一、本件犯罪事實及證據併所犯法條，均引用臺灣桃園地方法院\n    檢察署檢察官聲請簡易判決處刑書之記載（如附件），並補\n    充及更正：核被告甲○○所為，係犯刑法第339 條第1 項之\n    詐欺取財罪。被告對詐欺正犯提供帳戶資以助力，但並未參\n    與詐欺犯罪行為之實行，應屬幫助他人實行犯罪行為，為幫\n    助犯，乃依刑法第30條第2 項之規定減輕其刑。又被告係以\n    一提供帳戶之幫助行為，同時幫助詐欺集團詐得如附件犯罪\n    事實欄所示三名被害人財物，係一行為而觸犯3 個幫助詐欺\n    取財既遂罪，為同種想像競合犯，應從一重之幫助詐欺取財\n    既遂罪處斷。爰審酌被告輕易提供金融帳戶資料供他人掩飾\n    犯罪所得使用，非但增加被害人尋求救濟之困難，造成社會\n    人心不安，亦助長詐騙犯罪者之氣焰，使詐欺犯罪者得以順\n    利取得詐欺所得之財物，危害財產交易安全，犯罪情節非輕\n    ，暨其行為手段、素行、犯罪後態度等一切情狀，量處如主\n    文所示之刑，並諭知易科罰金之折算標準。\n二、據上論斷，應依刑事訴訟法第449 條第1 項前段、第3 項、\n    第454 條第2 項，刑法第339 條第1 項、第30條第1 項前段\n    、第2 項、第55條、第41條第1 項前段，刑法施行法第1 條\n    之1 第1 項、第2 項前段，逕以簡易判決處刑如主文。\n三、如不服本判決，應於判決送達後10日內，向本院提出上訴狀\n    （應附繕本），上訴於本院合議庭。\n中    華    民    國    99    年    5     月    12    日\n                  刑事第二庭  法  官  陳德池\n以上正本證明與原本無異。\n如不服本判決，應於判決送達後10日內向本院提出上訴狀（應附\n繕本）。\n                              書記官  謝雅茹\n中    華    民    國    99    年    5     月    14    日\n附錄論罪科刑法條全文：\n刑法第339 條第1 項(普通詐欺罪)：\n意圖為自己或第三人不法之所有，以詐術使人將本人或第三人之\n物交付者，處五年以下有期徒刑、拘役或科或併科一千元以下罰\n金。\n附件：臺灣桃園地方法院檢察署檢察官98年度偵字第23781 號、\n      98年度偵字第26778 號聲請簡易判決處刑書1 份。",
  "structure": {
    "main": "甲○○幫助意圖為自己不法之所有，以詐術使人將本人之物交付\n，處拘役伍拾日，如易科罰金，以新臺幣壹仟元折算壹日。",
    "fact": "一、本件犯罪事實及證據併所犯法條，均引用臺灣桃園地方法院\n    檢察署檢察官聲請簡易判決處刑書之記載（如附件），並補\n    充及更正：核被告甲○○所為，係犯刑法第339 條第1 項之\n    詐欺取財罪。被告對詐欺正犯提供帳戶資以助力，但並未參\n    與詐欺犯罪行為之實行，應屬幫助他人實行犯罪行為，為幫\n    助犯，乃依刑法第30條第2 項之規定減輕其刑。又被告係以\n    一提供帳戶之幫助行為，同時幫助詐欺集團詐得如附件犯罪\n    事實欄所示三名被害人財物，係一行為而觸犯3 個幫助詐欺\n    取財既遂罪，為同種想像競合犯，應從一重之幫助詐欺取財\n    既遂罪處斷。爰審酌被告輕易提供金融帳戶資料供他人掩飾\n    犯罪所得使用，非但增加被害人尋求救濟之困難，造成社會\n    人心不安，亦助長詐騙犯罪者之氣焰，使詐欺犯罪者得以順\n    利取得詐欺所得之財物，危害財產交易安全，犯罪情節非輕\n    ，暨其行為手段、素行、犯罪後態度等一切情狀，量處如主\n    文所示之刑，並諭知易科罰金之折算標準。\n二、據上論斷，應依刑事訴訟法第449 條第1 項前段、第3 項、\n    第454 條第2 項，刑法第339 條第1 項、第30條第1 項前段\n    、第2 項、第55條、第41條第1 項前段，刑法施行法第1 條\n    之1 第1 項、第2 項前段，逕以簡易判決處刑如主文。\n三、如不服本判決，應於判決送達後10日內，向本院提出上訴狀\n    （應附繕本），上訴於本院合議庭。",
    "reason": "一、本件犯罪事實及證據併所犯法條，均引用臺灣桃園地方法院\n    檢察署檢察官聲請簡易判決處刑書之記載（如附件），並補\n    充及更正：核被告甲○○所為，係犯刑法第339 條第1 項之\n    詐欺取財罪。被告對詐欺正犯提供帳戶資以助力，但並未參\n    與詐欺犯罪行為之實行，應屬幫助他人實行犯罪行為，為幫\n    助犯，乃依刑法第30條第2 項之規定減輕其刑。又被告係以\n    一提供帳戶之幫助行為，同時幫助詐欺集團詐得如附件犯罪\n    事實欄所示三名被害人財物，係一行為而觸犯3 個幫助詐欺\n    取財既遂罪，為同種想像競合犯，應從一重之幫助詐欺取財\n    既遂罪處斷。爰審酌被告輕易提供金融帳戶資料供他人掩飾\n    犯罪所得使用，非但增加被害人尋求救濟之困難，造成社會\n    人心不安，亦助長詐騙犯罪者之氣焰，使詐欺犯罪者得以順\n    利取得詐欺所得之財物，危害財產交易安全，犯罪情節非輕\n    ，暨其行為手段、素行、犯罪後態度等一切情狀，量處如主\n    文所示之刑，並諭知易科罰金之折算標準。\n二、據上論斷，應依刑事訴訟法第449 條第1 項前段、第3 項、\n    第454 條第2 項，刑法第339 條第1 項、第30條第1 項前段\n    、第2 項、第55條、第41條第1 項前段，刑法施行法第1 條\n    之1 第1 項、第2 項前段，逕以簡易判決處刑如主文。\n三、如不服本判決，應於判決送達後10日內，向本院提出上訴狀\n    （應附繕本），上訴於本院合議庭。"
  },
  "characters": {
    "judges": [
      "陳德池"
    ],
    "prosecutors": [

    ],
    "lawyers": [

    ],
    "clerks": [
      "謝雅茹"
    ],
    "plaintiffs": [

    ],
    "defendants": [
      "甲○○"
    ],
    "prosecutor_office": [
      "臺灣桃園地方法院檢察署檢察官"
    ],
    "creditors": [

    ],
    "debtors": [

    ],
    "judicial_associate_officer": [

    ]
  },
  "adjudged_at": "2010-05-12",
  "created_at": "2016-01-05 12:37:30",
  "updated_at": "2016-01-05 12:37:30"
}