{
  "identify": "TYD-99-易-393-20100512-1",
  "court": {
    "name": "臺灣桃園地方法院",
    "code": "TYD"
  },
  "division": {
    "name": "刑事",
    "code": "M"
  },
  "year": 99,
  "word": "易",
  "number": "393",
  "jcheck": "1",
  "reason": "傷害等",
  "content": "臺灣桃園地方法院刑事判決               99年度易字第393號\n公  訴  人  臺灣桃園地方法院檢察署檢察官\n被      告  甲○○\n上列被告因過失傷害案件，經檢察官聲請以簡易判決處刑（98年\n度偵字第25280 號），本院認不得以簡易判決處刑，改依通常程\n序審理，判決如下：\n    主  文\n本件公訴不受理。\n    理  由\n一、公訴意旨如聲請簡易判決處刑書所載（簡易判決處刑之聲請\n    與提起公訴有同一之效力，聲請簡易判決處刑書詳如附件）\n    。\n二、按被告死亡者，應諭知不受理之判決，刑事訴訟法第303 條\n    第5 款定有明文。\n三、查本件被告甲○○業於民國98年12月25日死亡，此有桃園縣\n    八德市戶政事務所99年4 月21日桃德戶字第0990002421號函\n    所附死亡登記申請書、臺灣桃園地方法院檢察署相驗屍體證\n    明書及本院依戶政查詢系統查得被告個人基本資料查詢結果\n    1 紙附卷（參本院99年度桃簡字第880 號卷第10頁至第12頁\n    、第7 頁至第8 頁）可憑。依照上開說明，爰不經言詞辯論\n    ，逕為不受理之判決。\n四、本件係檢察官聲請以簡易判決處刑案件，因有刑事訴訟法第\n    451 條之1 第4 項但書第3 款情形，適用通常程序審判。\n據上論斷，應依刑事訴訟法第452 條、第303 條第5 款、第307\n條，判決如主文。\n中    華    民    國    99    年    5     月    12    日\n                  刑事第二庭審判長  法  官  徐培元\n                                    法  官  柯姿佐\n                                    法  官  陳德池\n以上正本證明與原本無異。\n如不服本判決應於收受判決後10日內向本院提出上訴書狀，並應\n敘述具體理由。其未敘述上訴理由者，應於上訴期間屆滿後20日\n內向本院補提理由書( 均須按他造當事人之人數附繕本) 「切勿\n逕送上級法院」。\n                                    書記官  謝雅茹\n中    華    民    國    99    年    5     月    14    日\n附件：臺灣桃園地方法院檢察署檢察官98年度偵字第25280 號聲\n      請簡易判決處刑書1 份。",
  "structure": {
    "main": "本件公訴不受理。",
    "reason": "一、公訴意旨如聲請簡易判決處刑書所載（簡易判決處刑之聲請\n    與提起公訴有同一之效力，聲請簡易判決處刑書詳如附件）\n    。\n二、按被告死亡者，應諭知不受理之判決，刑事訴訟法第303 條\n    第5 款定有明文。\n三、查本件被告甲○○業於民國98年12月25日死亡，此有桃園縣\n    八德市戶政事務所99年4 月21日桃德戶字第0990002421號函\n    所附死亡登記申請書、臺灣桃園地方法院檢察署相驗屍體證\n    明書及本院依戶政查詢系統查得被告個人基本資料查詢結果\n    1 紙附卷（參本院99年度桃簡字第880 號卷第10頁至第12頁\n    、第7 頁至第8 頁）可憑。依照上開說明，爰不經言詞辯論\n    ，逕為不受理之判決。\n四、本件係檢察官聲請以簡易判決處刑案件，因有刑事訴訟法第\n    451 條之1 第4 項但書第3 款情形，適用通常程序審判。\n據上論斷，應依刑事訴訟法第452 條、第303 條第5 款、第307\n條，判決如主文。"
  },
  "characters": {
    "judges": [
      "徐培元",
      "柯姿佐",
      "陳德池"
    ],
    "prosecutors": [

    ],
    "lawyers": [

    ],
    "clerks": [
      "謝雅茹"
    ],
    "plaintiffs": [

    ],
    "defendants": [
      "甲○○"
    ],
    "prosecutor_office": [
      "臺灣桃園地方法院檢察署檢察官"
    ],
    "creditors": [

    ],
    "debtors": [

    ],
    "judicial_associate_officer": [

    ]
  },
  "adjudged_at": "2010-05-12",
  "created_at": "2016-01-05 12:36:35",
  "updated_at": "2016-01-05 12:36:35"
}