{
  "identify": "TYD-99-簡-78-20100512-1",
  "court": {
    "name": "臺灣桃園地方法院",
    "code": "TYD"
  },
  "division": {
    "name": "刑事",
    "code": "M"
  },
  "year": 99,
  "word": "簡",
  "number": "78",
  "jcheck": "1",
  "reason": "竊盜",
  "content": "臺灣桃園地方法院刑事簡易判決           99年度簡字第78號\n聲  請  人  臺灣桃園地方法院檢察署檢察官\n被      告  甲○○\n上列被告因竊盜案件，經檢察官聲請以簡易判決處刑（98年度偵\n字第27129 號），本院改依通常程序審理，被告經本院訊問後，\n坦承犯行，本院認宜以簡易判決處刑，改依簡易判決處刑程序，\n判決如下：\n    主  文\n甲○○竊盜，累犯，處拘役伍拾日，如易科罰金，以新臺幣壹仟\n元折算壹日。\n     事實及理由\n一、本件犯罪事實及理由除引用檢察官聲請簡易判決處刑書所載\n    外（詳如附件），另更正「以自備鑰匙1 支」為「真實姓名\n    年籍均不詳綽號『阿清』之友人所交付之鑰匙1 支」及補充\n    如下：\n  (一)被告前於民國85年間，因竊盜案件，經臺灣高等法院以87年\n    度上易字第1233 號 判決判處有期徒刑1 年4 月確定；復於\n    86年間，因違反肅清煙毒條例案件，經臺灣高等法院以86年\n    度上訴字第5788號判決判處有期徒刑3 年4 月確定；又於86\n    年間，因違反麻醉藥品管理條例案件，經本院以86年度訴緝\n    字第153 號判決判處有期徒刑1 年1 月，上訴後，經臺灣高\n    等法院以86年度上訴字第6025號判決上訴駁回確定；再於86\n    年間，因竊盜案件，經臺灣高等法院以87年度上易字第7144\n    號判決判處有期徒刑1 年確定；上開數罪經接續執行，於89\n    年7 月18日縮短刑期假釋出監，嗣經撤銷假釋，應執行殘刑\n    3 年8 月6 日。又於90年間，因違反槍砲彈藥刀械管制條例\n    案件，經臺灣高等法院以90年度上訴字第2805號判決判處有\n    期徒刑1 年7 月，併科罰金新臺幣5 萬元，上訴後，嗣經最\n    高法院以91年度臺上字第475 號判決上訴駁回確定；另於92\n    年間，因贓物案件，經臺灣澎湖地方法院以92年度馬簡字第\n    127 號判決判處有期徒刑5 月確定；上述二罪與前開殘刑3\n    年8 月6 日、罰金新臺幣5 萬元易服勞役55日接續執行，於\n    95年9 月20日縮短刑期假釋出監併付保護管束，於96年3 月\n    10日縮刑期滿，假釋未經撤銷，其未執行之刑，以已執行論\n    而執行完畢」。\n  (二)被告於本院調查時坦承竊盜之犯行。\n二、核被告所為，係犯刑法第320 條第1 項之竊盜罪。被告有前\n    揭有期徒刑執行完畢之紀錄，有臺灣高等法院被告前案紀錄\n    表1 份在卷足憑，其於有期徒刑執行完畢後，5 年內故意再\n    犯本件有期徒刑以上之罪，為累犯，應依刑法第47條第1 項\n    之規定加重其刑。爰審酌被告之犯罪動機、目的、手段、犯\n    罪手法、行竊物品之價值及被害人業已取回遭竊之自用小貨\n    車，兼衡其素行、犯後態度等一切情狀，量處如主文所示之\n    刑，並諭知易科罰金之折算標準，以示警懲。至被告持以行\n    竊該車之鑰匙，被告於警詢、偵查中均陳稱係一名綽號阿清\n    之男子所交付，本院復查無證據足以證明該支鑰匙係被告所\n    有，是爰不另為沒收之諭知，併此敘明之。\n三、依刑事訴訟法第449 條第1 項、第454 條第2 項，刑法第32\n    0 條第1 項、第47條第1 項、第41條第1 項前段，刑法施行\n    法第1 之1 條第1 項、第2 項前段，逕以簡易判決處刑如主\n    文。\n四、如不服本判決，得於判決書送達之翌日起10日內，以書狀敘\n    述理由，向本庭提出上訴。\n中    華    民    國    99    年    5     月    12    日\n                        臺灣桃園地方法院刑事第二庭\n                              法  官   柯姿佐\n以上正本證明與原本無異\n如不服本判決應於判決書送達之翌日起10日內，向本院提出上訴\n狀（應附繕本）。\n                              書記官  林舒涵\n中    華    民    國    99    年    5     月    13    日\n附錄論罪科刑依據之法條：\n中華民國刑法第320條\n（普通竊盜罪、竊佔罪）\n意圖為自己或第三人不法之所有，而竊取他人之動產者，為竊盜\n罪，處5  年以下有期徒刑、拘役或 5 百元以下罰金。\n意圖為自己或第三人不法之利益，而竊佔他人之不動產者，依前\n項之規定處斷。\n前二項之未遂犯罰之。",
  "structure": {
    "main": "甲○○竊盜，累犯，處拘役伍拾日，如易科罰金，以新臺幣壹仟\n元折算壹日。",
    "fact": "一、本件犯罪事實及理由除引用檢察官聲請簡易判決處刑書所載\n    外（詳如附件），另更正「以自備鑰匙1 支」為「真實姓名\n    年籍均不詳綽號『阿清』之友人所交付之鑰匙1 支」及補充\n    如下：\n  (一)被告前於民國85年間，因竊盜案件，經臺灣高等法院以87年\n    度上易字第1233 號 判決判處有期徒刑1 年4 月確定；復於\n    86年間，因違反肅清煙毒條例案件，經臺灣高等法院以86年\n    度上訴字第5788號判決判處有期徒刑3 年4 月確定；又於86\n    年間，因違反麻醉藥品管理條例案件，經本院以86年度訴緝\n    字第153 號判決判處有期徒刑1 年1 月，上訴後，經臺灣高\n    等法院以86年度上訴字第6025號判決上訴駁回確定；再於86\n    年間，因竊盜案件，經臺灣高等法院以87年度上易字第7144\n    號判決判處有期徒刑1 年確定；上開數罪經接續執行，於89\n    年7 月18日縮短刑期假釋出監，嗣經撤銷假釋，應執行殘刑\n    3 年8 月6 日。又於90年間，因違反槍砲彈藥刀械管制條例\n    案件，經臺灣高等法院以90年度上訴字第2805號判決判處有\n    期徒刑1 年7 月，併科罰金新臺幣5 萬元，上訴後，嗣經最\n    高法院以91年度臺上字第475 號判決上訴駁回確定；另於92\n    年間，因贓物案件，經臺灣澎湖地方法院以92年度馬簡字第\n    127 號判決判處有期徒刑5 月確定；上述二罪與前開殘刑3\n    年8 月6 日、罰金新臺幣5 萬元易服勞役55日接續執行，於\n    95年9 月20日縮短刑期假釋出監併付保護管束，於96年3 月\n    10日縮刑期滿，假釋未經撤銷，其未執行之刑，以已執行論\n    而執行完畢」。\n  (二)被告於本院調查時坦承竊盜之犯行。\n二、核被告所為，係犯刑法第320 條第1 項之竊盜罪。被告有前\n    揭有期徒刑執行完畢之紀錄，有臺灣高等法院被告前案紀錄\n    表1 份在卷足憑，其於有期徒刑執行完畢後，5 年內故意再\n    犯本件有期徒刑以上之罪，為累犯，應依刑法第47條第1 項\n    之規定加重其刑。爰審酌被告之犯罪動機、目的、手段、犯\n    罪手法、行竊物品之價值及被害人業已取回遭竊之自用小貨\n    車，兼衡其素行、犯後態度等一切情狀，量處如主文所示之\n    刑，並諭知易科罰金之折算標準，以示警懲。至被告持以行\n    竊該車之鑰匙，被告於警詢、偵查中均陳稱係一名綽號阿清\n    之男子所交付，本院復查無證據足以證明該支鑰匙係被告所\n    有，是爰不另為沒收之諭知，併此敘明之。\n三、依刑事訴訟法第449 條第1 項、第454 條第2 項，刑法第32\n    0 條第1 項、第47條第1 項、第41條第1 項前段，刑法施行\n    法第1 之1 條第1 項、第2 項前段，逕以簡易判決處刑如主\n    文。\n四、如不服本判決，得於判決書送達之翌日起10日內，以書狀敘\n    述理由，向本庭提出上訴。",
    "reason": "一、本件犯罪事實及理由除引用檢察官聲請簡易判決處刑書所載\n    外（詳如附件），另更正「以自備鑰匙1 支」為「真實姓名\n    年籍均不詳綽號『阿清』之友人所交付之鑰匙1 支」及補充\n    如下：\n  (一)被告前於民國85年間，因竊盜案件，經臺灣高等法院以87年\n    度上易字第1233 號 判決判處有期徒刑1 年4 月確定；復於\n    86年間，因違反肅清煙毒條例案件，經臺灣高等法院以86年\n    度上訴字第5788號判決判處有期徒刑3 年4 月確定；又於86\n    年間，因違反麻醉藥品管理條例案件，經本院以86年度訴緝\n    字第153 號判決判處有期徒刑1 年1 月，上訴後，經臺灣高\n    等法院以86年度上訴字第6025號判決上訴駁回確定；再於86\n    年間，因竊盜案件，經臺灣高等法院以87年度上易字第7144\n    號判決判處有期徒刑1 年確定；上開數罪經接續執行，於89\n    年7 月18日縮短刑期假釋出監，嗣經撤銷假釋，應執行殘刑\n    3 年8 月6 日。又於90年間，因違反槍砲彈藥刀械管制條例\n    案件，經臺灣高等法院以90年度上訴字第2805號判決判處有\n    期徒刑1 年7 月，併科罰金新臺幣5 萬元，上訴後，嗣經最\n    高法院以91年度臺上字第475 號判決上訴駁回確定；另於92\n    年間，因贓物案件，經臺灣澎湖地方法院以92年度馬簡字第\n    127 號判決判處有期徒刑5 月確定；上述二罪與前開殘刑3\n    年8 月6 日、罰金新臺幣5 萬元易服勞役55日接續執行，於\n    95年9 月20日縮短刑期假釋出監併付保護管束，於96年3 月\n    10日縮刑期滿，假釋未經撤銷，其未執行之刑，以已執行論\n    而執行完畢」。\n  (二)被告於本院調查時坦承竊盜之犯行。\n二、核被告所為，係犯刑法第320 條第1 項之竊盜罪。被告有前\n    揭有期徒刑執行完畢之紀錄，有臺灣高等法院被告前案紀錄\n    表1 份在卷足憑，其於有期徒刑執行完畢後，5 年內故意再\n    犯本件有期徒刑以上之罪，為累犯，應依刑法第47條第1 項\n    之規定加重其刑。爰審酌被告之犯罪動機、目的、手段、犯\n    罪手法、行竊物品之價值及被害人業已取回遭竊之自用小貨\n    車，兼衡其素行、犯後態度等一切情狀，量處如主文所示之\n    刑，並諭知易科罰金之折算標準，以示警懲。至被告持以行\n    竊該車之鑰匙，被告於警詢、偵查中均陳稱係一名綽號阿清\n    之男子所交付，本院復查無證據足以證明該支鑰匙係被告所\n    有，是爰不另為沒收之諭知，併此敘明之。\n三、依刑事訴訟法第449 條第1 項、第454 條第2 項，刑法第32\n    0 條第1 項、第47條第1 項、第41條第1 項前段，刑法施行\n    法第1 之1 條第1 項、第2 項前段，逕以簡易判決處刑如主\n    文。\n四、如不服本判決，得於判決書送達之翌日起10日內，以書狀敘\n    述理由，向本庭提出上訴。"
  },
  "characters": {
    "judges": [
      "柯姿佐"
    ],
    "prosecutors": [

    ],
    "lawyers": [

    ],
    "clerks": [
      "林舒涵"
    ],
    "plaintiffs": [

    ],
    "defendants": [
      "甲○○"
    ],
    "prosecutor_office": [
      "臺灣桃園地方法院檢察署檢察官"
    ],
    "creditors": [

    ],
    "debtors": [

    ],
    "judicial_associate_officer": [

    ]
  },
  "adjudged_at": "2010-05-12",
  "created_at": "2016-01-05 12:36:56",
  "updated_at": "2016-01-05 12:36:56"
}