{
  "identify": "TYD-99-桃簡-1072-20100512-1",
  "court": {
    "name": "臺灣桃園地方法院",
    "code": "TYD"
  },
  "division": {
    "name": "刑事",
    "code": "M"
  },
  "year": 99,
  "word": "桃簡",
  "number": "1072",
  "jcheck": "1",
  "reason": "竊盜",
  "content": "臺灣桃園地方法院刑事簡易判決        99年度桃簡字第1072號\n聲  請  人  臺灣桃園地方法院檢察署檢察官\n被      告  甲○○\n上列被告因竊盜案件，經檢察官聲請以簡易判決處刑（99年度偵\n字第11002 號），本院判決如下：\n    主      文\n甲○○竊盜，處罰金新臺幣伍仟元，如易服勞役，以新臺幣壹仟\n元折算壹日。\n    事實及理由\n一、本件犯罪事實及證據併所犯法條，均引用臺灣桃園地方法院\n    檢察署檢察官聲請簡易判決處刑書之記載（如附件），並補\n    充及更正：核被告甲○○所為，係犯刑法第320 條第1 項竊\n    盜既遂罪。爰審酌被告正值盛年，不思正途營生，竟冀望不\n    勞而獲竊取他人財物，其犯罪之動機實屬可議，暨其犯罪後\n    態度、品行、行為手段、竊得財物價值非高、被害人已取回\n    失竊財物等一切情狀，量處如主文所示之刑，並諭知易服勞\n    役之折算標準。\n二、依刑事訴訟法第449 條第1 項前段、第3 項、第454 條第2\n    項，刑法第320 條第1 項、第42條第3 項前段，刑法施行法\n    第1 條之1 第1 項、第2 項前段，判決如主文。\n三、如不服本判決，應於判決書送達之翌日起10日內，向本院提\n    出上訴狀（應附繕本），上訴於本院合議庭。\n中    華    民    國    99    年    5     月    12    日\n                  刑事第二庭    法  官  陳德池\n以上正本證明與原本無異。\n如不服本判決，應於判決送達後10日內向本院提出上訴狀（應附\n繕本）。\n                                書記官  謝雅茹\n中    華    民    國    99    年    5     月    14    日\n附錄論罪科刑法條全文：\n刑法第320條第1項\n意圖為自己或第三人不法之所有，而竊取他人之動產者，為竊盜\n罪，處5年以下有期徒刑、拘役或500元以下罰金。\n附件：臺灣桃園地方法院檢察署檢察官99年度偵字第11002 號聲\n      請簡易判決處刑書1 份。",
  "structure": {
    "main": "甲○○竊盜，處罰金新臺幣伍仟元，如易服勞役，以新臺幣壹仟\n元折算壹日。",
    "fact": "一、本件犯罪事實及證據併所犯法條，均引用臺灣桃園地方法院\n    檢察署檢察官聲請簡易判決處刑書之記載（如附件），並補\n    充及更正：核被告甲○○所為，係犯刑法第320 條第1 項竊\n    盜既遂罪。爰審酌被告正值盛年，不思正途營生，竟冀望不\n    勞而獲竊取他人財物，其犯罪之動機實屬可議，暨其犯罪後\n    態度、品行、行為手段、竊得財物價值非高、被害人已取回\n    失竊財物等一切情狀，量處如主文所示之刑，並諭知易服勞\n    役之折算標準。\n二、依刑事訴訟法第449 條第1 項前段、第3 項、第454 條第2\n    項，刑法第320 條第1 項、第42條第3 項前段，刑法施行法\n    第1 條之1 第1 項、第2 項前段，判決如主文。\n三、如不服本判決，應於判決書送達之翌日起10日內，向本院提\n    出上訴狀（應附繕本），上訴於本院合議庭。",
    "reason": "一、本件犯罪事實及證據併所犯法條，均引用臺灣桃園地方法院\n    檢察署檢察官聲請簡易判決處刑書之記載（如附件），並補\n    充及更正：核被告甲○○所為，係犯刑法第320 條第1 項竊\n    盜既遂罪。爰審酌被告正值盛年，不思正途營生，竟冀望不\n    勞而獲竊取他人財物，其犯罪之動機實屬可議，暨其犯罪後\n    態度、品行、行為手段、竊得財物價值非高、被害人已取回\n    失竊財物等一切情狀，量處如主文所示之刑，並諭知易服勞\n    役之折算標準。\n二、依刑事訴訟法第449 條第1 項前段、第3 項、第454 條第2\n    項，刑法第320 條第1 項、第42條第3 項前段，刑法施行法\n    第1 條之1 第1 項、第2 項前段，判決如主文。\n三、如不服本判決，應於判決書送達之翌日起10日內，向本院提\n    出上訴狀（應附繕本），上訴於本院合議庭。"
  },
  "characters": {
    "judges": [
      "陳德池"
    ],
    "prosecutors": [

    ],
    "lawyers": [

    ],
    "clerks": [
      "謝雅茹"
    ],
    "plaintiffs": [

    ],
    "defendants": [
      "甲○○"
    ],
    "prosecutor_office": [
      "臺灣桃園地方法院檢察署檢察官"
    ],
    "creditors": [

    ],
    "debtors": [

    ],
    "judicial_associate_officer": [

    ]
  },
  "adjudged_at": "2010-05-12",
  "created_at": "2016-01-05 12:36:45",
  "updated_at": "2016-01-05 12:36:45"
}