{
  "identify": "TYD-99-壢簡-799-20100512-1",
  "court": {
    "name": "臺灣桃園地方法院",
    "code": "TYD"
  },
  "division": {
    "name": "刑事",
    "code": "M"
  },
  "year": 99,
  "word": "壢簡",
  "number": "799",
  "jcheck": "1",
  "reason": "傷害",
  "content": "臺灣桃園地方法院刑事簡易判決         99年度壢簡字第799號\n聲  請  人  臺灣桃園地方法院檢察署檢察官\n被      告  甲○○\n上列被告因傷害案件，經檢察官聲請以簡易判決處刑（99年度偵\n字第4332號），本院判決如下：\n    主      文\n甲○○傷害人之身體，處拘役肆拾日，如易科罰金，以新臺幣壹\n仟元折算壹日。扣案之鋁棒壹支沒收。\n    事實及理由\n一、本件犯罪事實及證據，併所犯法條，均引用臺灣桃園地方法\n    院檢察署檢察官聲請簡易判決處刑書之記載（如附件），並\n    補充：\n  (一)犯罪事實欄另補充：「並扣得甲○○所有之鋁棒一支」。\n  (二)核被告甲○○所為，係犯刑法第277 條第1 項普通傷害罪。\n    爰審酌被告因細故發生爭執即傷害告訴人，實屬不該，且迄\n    未與告訴人達成和解，並考量告訴人受傷程度、被告犯後坦\n    認犯行，並其智識程度、品行等一切情狀，量處如主文之刑\n    ，並諭知易科罰金之折算標準。\n  (三)扣案之鋁棒一支為被告所有，供本件犯罪所用之物，此據被\n    告於警詢陳述綦詳，應依刑法第38第1 項第2 款宣告沒收。\n二、依刑事訴訟法第449 條第1 項前段、第3 項、第450 條第1\n    項、第454 條第2 項，刑法第277 條第1 項、第41條第1 項\n    前段、第38條第1 項第2 款，刑法施行法第1 條之1 第1 項\n    、第2 項前段，逕以簡易判決處刑如主文。\n三、如不服本判決，應於判決送達後10日內，向本院提出上訴狀\n    （應附繕本），上訴於本院合議庭。\n中    華    民    國    99    年    5     月    12    日\n                  刑事第二庭  法  官  陳德池\n以上正本證明與原本無異。\n如不服本判決，應於判決送達後10日內向本院提出上訴狀（應附\n繕本）。\n                              書記官  謝雅茹\n中    華    民    國    99    年    5     月    19    日\n附錄論罪科刑法條全文：\n中華民國刑法第277 條\n（普通傷害罪）\n傷害人之身體或健康者，處3 年以下有期徒刑、拘役或1 千元以\n下罰金。\n犯前項之罪因而致人於死者，處無期徒刑或7 年以上有期徒刑；\n致重傷者，處3 年以上10年以下有期徒刑。\n附件：臺灣桃園地方法院檢察署檢察官99年度偵字第4332號聲請\n      簡易判決處刑書1 份。",
  "structure": {
    "main": "甲○○傷害人之身體，處拘役肆拾日，如易科罰金，以新臺幣壹\n仟元折算壹日。扣案之鋁棒壹支沒收。",
    "fact": "一、本件犯罪事實及證據，併所犯法條，均引用臺灣桃園地方法\n    院檢察署檢察官聲請簡易判決處刑書之記載（如附件），並\n    補充：\n  (一)犯罪事實欄另補充：「並扣得甲○○所有之鋁棒一支」。\n  (二)核被告甲○○所為，係犯刑法第277 條第1 項普通傷害罪。\n    爰審酌被告因細故發生爭執即傷害告訴人，實屬不該，且迄\n    未與告訴人達成和解，並考量告訴人受傷程度、被告犯後坦\n    認犯行，並其智識程度、品行等一切情狀，量處如主文之刑\n    ，並諭知易科罰金之折算標準。\n  (三)扣案之鋁棒一支為被告所有，供本件犯罪所用之物，此據被\n    告於警詢陳述綦詳，應依刑法第38第1 項第2 款宣告沒收。\n二、依刑事訴訟法第449 條第1 項前段、第3 項、第450 條第1\n    項、第454 條第2 項，刑法第277 條第1 項、第41條第1 項\n    前段、第38條第1 項第2 款，刑法施行法第1 條之1 第1 項\n    、第2 項前段，逕以簡易判決處刑如主文。\n三、如不服本判決，應於判決送達後10日內，向本院提出上訴狀\n    （應附繕本），上訴於本院合議庭。",
    "reason": "一、本件犯罪事實及證據，併所犯法條，均引用臺灣桃園地方法\n    院檢察署檢察官聲請簡易判決處刑書之記載（如附件），並\n    補充：\n  (一)犯罪事實欄另補充：「並扣得甲○○所有之鋁棒一支」。\n  (二)核被告甲○○所為，係犯刑法第277 條第1 項普通傷害罪。\n    爰審酌被告因細故發生爭執即傷害告訴人，實屬不該，且迄\n    未與告訴人達成和解，並考量告訴人受傷程度、被告犯後坦\n    認犯行，並其智識程度、品行等一切情狀，量處如主文之刑\n    ，並諭知易科罰金之折算標準。\n  (三)扣案之鋁棒一支為被告所有，供本件犯罪所用之物，此據被\n    告於警詢陳述綦詳，應依刑法第38第1 項第2 款宣告沒收。\n二、依刑事訴訟法第449 條第1 項前段、第3 項、第450 條第1\n    項、第454 條第2 項，刑法第277 條第1 項、第41條第1 項\n    前段、第38條第1 項第2 款，刑法施行法第1 條之1 第1 項\n    、第2 項前段，逕以簡易判決處刑如主文。\n三、如不服本判決，應於判決送達後10日內，向本院提出上訴狀\n    （應附繕本），上訴於本院合議庭。"
  },
  "characters": {
    "judges": [
      "陳德池"
    ],
    "prosecutors": [

    ],
    "lawyers": [

    ],
    "clerks": [
      "謝雅茹"
    ],
    "plaintiffs": [

    ],
    "defendants": [
      "甲○○"
    ],
    "prosecutor_office": [
      "臺灣桃園地方法院檢察署檢察官"
    ],
    "creditors": [

    ],
    "debtors": [

    ],
    "judicial_associate_officer": [

    ]
  },
  "adjudged_at": "2010-05-12",
  "created_at": "2016-01-05 12:38:14",
  "updated_at": "2016-01-05 12:38:14"
}