{
  "identify": "TYD-99-附民-10-20100512-1",
  "court": {
    "name": "臺灣桃園地方法院",
    "code": "TYD"
  },
  "division": {
    "name": "刑事",
    "code": "M"
  },
  "year": 99,
  "word": "附民",
  "number": "10",
  "jcheck": "1",
  "reason": "請求賠償損害",
  "content": "臺灣桃園地方法院刑事附帶民事判決      99年度附民字第10號\n原      告  甲○○○\n            丁○○\n            乙○○\n            丙○○○\n上4人共同\n訴訟代理人  陳鄭權律師\n            丁俊和律師\n被      告  戊○○\n選任辯護人  邱國旺律師\n上列被告因竊佔案件（本院99年度易字第19號），經原告提起附\n帶民事訴訟，請求損害賠償事件，本院判決如下：\n    主  文\n原告之訴及假執行之聲請均駁回。\n    事  實\n一、原告方面：原告之聲明及陳述均如附件刑事附帶民事起訴狀\n    所載。\n二、被告方面：被告未提出書狀亦未以言詞作任何聲明及陳述。\n    理  由\n一、按刑事訴訟諭知無罪、免訴或不受理之判決者，應以判決駁\n    回原告之訴，刑事訴訟法第503 條第1 項前段定有明文。\n二、經查，本件被告戊○○所涉竊佔案件，已於民國99年5 月12\n    日經本院以98年度易字第19號判決無罪，依首揭法條之規定\n    ，本件原告4 人所提附帶民事訴訟自應予以駁回。又原告之\n    訴既已駁回，其假執行之聲請因而失所憑，應併予駁回。\n三、應依刑事訴訟法第503 條第1 項前段，判決如主文。\n中    華    民    國    99    年    5     月    12    日\n                  刑事第十一法庭  審判長法  官 蔡榮澤\n                                        法  官 吳宗航\n                                        法  官 汪曉君\n以上正本證明與原本無異。\n非對於刑事訴訟之判決有上訴時，不得上訴。\n如不服本判決應於收受判決後10日內向本院提出上訴書狀。\n                                        書記官 楊晴文\n中    華    民    國    99    年    5     月    12    日",
  "structure": {
    "main": "原告之訴及假執行之聲請均駁回。",
    "fact": "一、原告方面：原告之聲明及陳述均如附件刑事附帶民事起訴狀\n    所載。\n二、被告方面：被告未提出書狀亦未以言詞作任何聲明及陳述。",
    "reason": "一、按刑事訴訟諭知無罪、免訴或不受理之判決者，應以判決駁\n    回原告之訴，刑事訴訟法第503 條第1 項前段定有明文。\n二、經查，本件被告戊○○所涉竊佔案件，已於民國99年5 月12\n    日經本院以98年度易字第19號判決無罪，依首揭法條之規定\n    ，本件原告4 人所提附帶民事訴訟自應予以駁回。又原告之\n    訴既已駁回，其假執行之聲請因而失所憑，應併予駁回。\n三、應依刑事訴訟法第503 條第1 項前段，判決如主文。\n中    華    民    國    99    年    5     月    12    日\n                  刑事第十一法庭  審判長法  官 蔡榮澤\n                                        法  官 吳宗航\n                                        法  官 汪曉君\n以上正本證明與原本無異。\n非對於刑事訴訟之判決有上訴時，不得上訴。\n如不服本判決應於收受判決後10日內向本院提出上訴書狀。\n                                        書記官 楊晴文"
  },
  "characters": {
    "judges": [
      "蔡榮澤",
      "吳宗航",
      "汪曉君"
    ],
    "prosecutors": [

    ],
    "lawyers": [
      "陳鄭權",
      "丁俊和",
      "邱國旺"
    ],
    "clerks": [
      "楊晴文"
    ],
    "plaintiffs": [
      "甲"
    ],
    "defendants": [
      "戊○○"
    ],
    "prosecutor_office": [

    ],
    "creditors": [

    ],
    "debtors": [

    ],
    "judicial_associate_officer": [

    ]
  },
  "adjudged_at": "2010-05-12",
  "created_at": "2016-01-05 12:38:35",
  "updated_at": "2016-01-05 12:38:35"
}