{
  "identify": "TYD-99-易緝-14-20100512-1",
  "court": {
    "name": "臺灣桃園地方法院",
    "code": "TYD"
  },
  "division": {
    "name": "刑事",
    "code": "M"
  },
  "year": 99,
  "word": "易緝",
  "number": "14",
  "jcheck": "1",
  "reason": "詐欺",
  "content": "臺灣桃園地方法院刑事裁定              99年度易緝字第14號\n公  訴  人  臺灣桃園地方法院檢察署檢察官\n被      告  甲○○\n選任辯護人  金鑫律師\n上列被告因詐欺案件，經檢察官提起公訴，本院裁定如下：\n    主  文\n甲○○自民國玖拾玖年伍月拾日起延長羈押貳月。\n    理  由\n一、本件被告甲○○因詐欺案件，前經本院訊問後，依刑事訴訟\n    法第101 條第1 項第1 款之規定，於民國99年2 月13日起執\n    行羈押。茲本院以羈押期間即將屆滿，經訊問被告後，認羈\n    押原因依然存在，仍有繼續羈押之必要，自99年5 月13日起\n    延長羈押2 月。\n二、依刑事訴訟法第108 條第1 項裁定如主文。\n中    華    民    國    99    年    5     月    12    日\n                  刑事第四庭    審判長法  官  袁雪華\n                                      法  官  張淑華\n                                      法  官  林宜靜\n以上正本證明與原本無異。\n如不服本裁定，應於裁定送達後5 日內向本院提出抗告狀。\n                                      書記官  王明玉\n中    華    民    國    99    年    5     月    12    日",
  "structure": {
    "main": "甲○○自民國玖拾玖年伍月拾日起延長羈押貳月。",
    "reason": "一、本件被告甲○○因詐欺案件，前經本院訊問後，依刑事訴訟\n    法第101 條第1 項第1 款之規定，於民國99年2 月13日起執\n    行羈押。茲本院以羈押期間即將屆滿，經訊問被告後，認羈\n    押原因依然存在，仍有繼續羈押之必要，自99年5 月13日起\n    延長羈押2 月。\n二、依刑事訴訟法第108 條第1 項裁定如主文。"
  },
  "characters": {
    "judges": [
      "袁雪華",
      "張淑華",
      "林宜靜"
    ],
    "prosecutors": [

    ],
    "lawyers": [
      "金鑫"
    ],
    "clerks": [
      "王明玉"
    ],
    "plaintiffs": [

    ],
    "defendants": [
      "甲○○"
    ],
    "prosecutor_office": [
      "臺灣桃園地方法院檢察署檢察官"
    ],
    "creditors": [

    ],
    "debtors": [

    ],
    "judicial_associate_officer": [

    ]
  },
  "adjudged_at": "2010-05-12",
  "created_at": "2016-01-05 12:35:43",
  "updated_at": "2016-01-05 12:35:43"
}