{
  "identify": "TYD-98-附民-34-20100512-1",
  "court": {
    "name": "臺灣桃園地方法院",
    "code": "TYD"
  },
  "division": {
    "name": "刑事",
    "code": "M"
  },
  "year": 98,
  "word": "附民",
  "number": "34",
  "jcheck": "1",
  "reason": "請求賠償損害",
  "content": "臺灣桃園地方法院刑事判決              98年度附民字第34號\n原      告  乙○○\n原  告  兼\n法定代理人  甲○○\n原      告  丙○○\n            丁○○\n被      告  戊○○\n上列被告因業務過失致重傷案件，經原告提起附帶民事訴訟請求\n損害賠償，本院判決如下：\n    主  文\n原告之訴及其假執行之聲請均駁回。\n    事  實\n一、原告之聲明及陳述均詳如附件所示。\n二、被告未為任何聲明或陳述，亦未提出任何書狀。\n    理  由\n一、按刑事訴訟諭知無罪、免訴或不受理之判決者，應以判決駁\n    回原告之訴。但經原告聲請時，應將附帶民事訴訟移送管轄\n    法院之民事庭。前項判決，非對於刑事訴訟之判決有上訴時\n    ，不得上訴。第一項但書移送案件，應繳納訴訟費用。自訴\n    案件經裁定駁回自訴者，應以裁定駁回原告之訴，並準用前\n    三項之規定。刑事訴訟法第503條定有明文。\n二、本院受理98年度易字第136 號案件，被告戊○○部分，經本\n    院諭知無罪判決，自應依首揭規定，以判決駁回原告之訴，\n    其假執行之聲請亦因本訴駁回而失所依附，應併予駁回。\n三、據上論結，應依刑事訴訟法第503 條第1項，判決如主文。\n中    華    民    國    99    年    5     月    12    日\n                  刑事第五庭審判長法  官 潘政宏\n                                  法  官 劉淑玲\n                                  法  官 江春瑩\n以上正本證明與原本無異。\n如不服本判決應於收受判決後10日內向本院提出上訴書狀，並應\n敘述具體理由。其未敘述上訴理由者，應於上訴期間屆滿後20日\n內向本院補提理由書( 均須按他造當事人之人數附繕本) 「切勿\n逕送上級法院」。\n                                  書記官 羅婉榕\n中    華    民    國    99    年    5     月    13    日",
  "structure": {
    "main": "原告之訴及其假執行之聲請均駁回。",
    "fact": "一、原告之聲明及陳述均詳如附件所示。\n二、被告未為任何聲明或陳述，亦未提出任何書狀。",
    "reason": "一、按刑事訴訟諭知無罪、免訴或不受理之判決者，應以判決駁\n    回原告之訴。但經原告聲請時，應將附帶民事訴訟移送管轄\n    法院之民事庭。前項判決，非對於刑事訴訟之判決有上訴時\n    ，不得上訴。第一項但書移送案件，應繳納訴訟費用。自訴\n    案件經裁定駁回自訴者，應以裁定駁回原告之訴，並準用前\n    三項之規定。刑事訴訟法第503條定有明文。\n二、本院受理98年度易字第136 號案件，被告戊○○部分，經本\n    院諭知無罪判決，自應依首揭規定，以判決駁回原告之訴，\n    其假執行之聲請亦因本訴駁回而失所依附，應併予駁回。\n三、據上論結，應依刑事訴訟法第503 條第1項，判決如主文。\n中    華    民    國    99    年    5     月    12    日\n                  刑事第五庭審判長法  官 潘政宏\n                                  法  官 劉淑玲\n                                  法  官 江春瑩\n以上正本證明與原本無異。\n如不服本判決應於收受判決後10日內向本院提出上訴書狀，並應\n敘述具體理由。其未敘述上訴理由者，應於上訴期間屆滿後20日\n內向本院補提理由書( 均須按他造當事人之人數附繕本) 「切勿\n逕送上級法院」。\n                                  書記官 羅婉榕"
  },
  "characters": {
    "judges": [
      "潘政宏",
      "劉淑玲",
      "江春瑩"
    ],
    "prosecutors": [

    ],
    "lawyers": [

    ],
    "clerks": [
      "羅婉榕"
    ],
    "plaintiffs": [
      "乙",
      "兼",
      "丙"
    ],
    "defendants": [
      "戊○○"
    ],
    "prosecutor_office": [

    ],
    "creditors": [

    ],
    "debtors": [

    ],
    "judicial_associate_officer": [

    ]
  },
  "adjudged_at": "2010-05-12",
  "created_at": "2016-01-05 12:36:15",
  "updated_at": "2016-01-05 12:36:15"
}